Workbook

Sheet RESUMO
A2: Resumo dos investimentos
A3: BENEFÍCIO FISCAL DE PD&I 2023
G4: 2023-026 - NETZSCH MOAGEM
A5: NETZSCH INDUSTRIA E COMERCIO DE EQUIPAMENTOS DE MOAGEM LTDA | E5: CNPJ 07.389.050/0001-51 | G5: =TODAY() -> 46168
A6: Rua Emilio Marquardt, 300, Ribeirão Souto - SC - SUL - POMERODE - CEP 89.107-000
A8: Natureza | B8: 1º Trimestre | C8: 2º Trimestre | D8: 3º Trimestre | E8: 4º Trimestre | G8: TOTAL
A9: Material | B9: - | C9: - | D9: - | E9: - | G9: =sum(B9:E9) -> 0
A10: Terceiros | B10: =IFERROR(__xludf.DUMMYFUNCTION("iferror(sum(filter('Resumo - TERCEIROS'!$G:$G,'Resumo - TERCEIROS'!$K:$K=TRUE,month('Resumo - TERCEIROS'!$H:$H)>=1,month('Resumo - TERCEIROS'!$H:$H)<=3)))"),249643.17000000004) -> 249643.17 | C10: =IFERROR(__xludf.DUMMYFUNCTION("iferror(sum(filter('Resumo - TERCEIROS'!$G:$G,'Resumo - TERCEIROS'!$K:$K=TRUE,month('Resumo - TERCEIROS'!$H:$H)>=4,month('Resumo - TERCEIROS'!$H:$H)<=6)))"),270565.37) -> 270565.37 | D10: =IFERROR(__xludf.DUMMYFUNCTION("iferror(sum(filter('Resumo - TERCEIROS'!$G:$G,'Resumo - TERCEIROS'!$K:$K=TRUE,month('Resumo - TERCEIROS'!$H:$H)>=7,month('Resumo - TERCEIROS'!$H:$H)<=9)))"),436998.42) -> 436998.42 | E10: =IFERROR(__xludf.DUMMYFUNCTION("iferror(sum(filter('Resumo - TERCEIROS'!$G:$G,'Resumo - TERCEIROS'!$K:$K=TRUE,month('Resumo - TERCEIROS'!$H:$H)>=10,month('Resumo - TERCEIROS'!$H:$H)<=12)))"),364921.97) -> 364921.97 | G10: =sum(B10:E10) -> 1322128.9
A11: RH (Parcial inovação) | B11: =IFERROR(__xludf.DUMMYFUNCTION("iferror(sum(filter('Resumo - TIMESHEETS'!$L$12:$L49,'Resumo - TIMESHEETS'!$O$12:$O49=""Parcial"",month('Resumo - TIMESHEETS'!$G$12:$G49)>=1,month('Resumo - TIMESHEETS'!$G$12:$G49)<=3)),0)"),27955.666660157865) -> 27955.667 | C11: =IFERROR(__xludf.DUMMYFUNCTION("iferror(sum(filter('Resumo - TIMESHEETS'!$L$12:$L49,'Resumo - TIMESHEETS'!$O$12:$O49=""Parcial"",month('Resumo - TIMESHEETS'!$G$12:$G49)>=4,month('Resumo - TIMESHEETS'!$G$12:$G49)<=6)),0)"),219121.24926862077) -> 219121.25 | D11: =IFERROR(__xludf.DUMMYFUNCTION("iferror(sum(filter('Resumo - TIMESHEETS'!$L$12:$L49,'Resumo - TIMESHEETS'!$O$12:$O49=""Parcial"",month('Resumo - TIMESHEETS'!$G$12:$G49)>=7,month('Resumo - TIMESHEETS'!$G$12:$G49)<=9)),0)"),185946.35230050277) -> 185946.35 | E11: =IFERROR(__xludf.DUMMYFUNCTION("iferror(sum(filter('Resumo - TIMESHEETS'!$L$12:$L49,'Resumo - TIMESHEETS'!$O$12:$O49=""Parcial"",month('Resumo - TIMESHEETS'!$G$12:$G49)>=10,month('Resumo - TIMESHEETS'!$G$12:$G49)<=12)),0)"),121276.19605978376) -> 121276.2 | G11: =sum(B11:E11) -> 554299.46
A12: RH (Exclusivo inovação) | B12: =IFERROR(__xludf.DUMMYFUNCTION("iferror(sum(filter('Resumo - TIMESHEETS'!$L$12:$L49,'Resumo - TIMESHEETS'!$O$12:$O49=""Exclusivo"",month('Resumo - TIMESHEETS'!$G$12:$G49)>=1,month('Resumo - TIMESHEETS'!$G$12:$G49)<=3)),0)"),205663.2395166963) -> 205663.24 | C12: =IFERROR(__xludf.DUMMYFUNCTION("iferror(sum(filter('Resumo - TIMESHEETS'!$L$12:$L49,'Resumo - TIMESHEETS'!$O$12:$O49=""Exclusivo"",month('Resumo - TIMESHEETS'!$G$12:$G49)>=4,month('Resumo - TIMESHEETS'!$G$12:$G49)<=6)),0)"),227193.7884235887) -> 227193.79 | D12: =IFERROR(__xludf.DUMMYFUNCTION("iferror(sum(filter('Resumo - TIMESHEETS'!$L$12:$L49,'Resumo - TIMESHEETS'!$O$12:$O49=""Exclusivo"",month('Resumo - TIMESHEETS'!$G$12:$G49)>=7,month('Resumo - TIMESHEETS'!$G$12:$G49)<=9)),0)"),221950.78725329504) -> 221950.79 | E12: =IFERROR(__xludf.DUMMYFUNCTION("iferror(sum(filter('Resumo - TIMESHEETS'!$L$12:$L49,'Resumo - TIMESHEETS'!$O$12:$O49=""Exclusivo"",month('Resumo - TIMESHEETS'!$G$12:$G49)>=10,month('Resumo - TIMESHEETS'!$G$12:$G49)<=12)),0)"),217421.32573212715) -> 217421.33 | G12: =sum(B12:E12) -> 872229.14
A13: Total 1 | B13: =sum(B10:B12) -> 483262.08 | C13: =sum(C10:C12) -> 716880.41 | D13: =sum(D10:D12) -> 844895.56 | E13: =sum(E10:E12) -> 703619.49 | G13: =sum(G9:G12) -> 2748657.5
A14: Percentual Exclusão | B14: 0.6 | C14: 0.6 | D14: 0.6 | E14: 0.6 | G14: 0.6
A15: Exclusão da Base de cálculo do IRPJ e CSLL | B15: =B13*B14 -> 289957.25 | C15: =C13*C14 -> 430128.24 | D15: =D13*D14 -> 506937.34 | E15: =E13*E14 -> 422171.7 | G15: =G13*G14 -> 1649194.5
A17: Economia Estimada [34%] | B17: =B15*34% -> 98585.464 | C17: =C15*34% -> 146243.6 | D17: =D15*34% -> 172358.69 | E17: =E15*34% -> 143538.38 | G17: =G15*34% -> 560726.14
A18: Comissão McBenner | B18: =B17*0.05 -> 4929.2732 | C18: =C17*0.05 -> 7312.1802 | D18: =D17*0.05 -> 8617.9347 | E18: =E17*0.05 -> 7176.9188 | G18: =G17*0.05 -> 28036.307
A20: Observações:
A21: 1. Os dispêndios devem ser registrados na contabilidade em conta específica
A22: 2. O benefício deve ser aproveitado na ECF do respectivo ano/competência
A23: 3. O formulário do MCTIC (governo) será enviado até fim de Julho/2024
A24: 4. Os projetos estão descritos em arquivo a parte a ser anexado no FORM PD&I
A25: 5. Alguns benefícios previstos na Lei do Bem não foram utilizados:
A26: - 5.1. Depreciação acelerada
A27: - 5.2. Redução de IPI na aquisição de equipamento para PD&I
A28: - 5.3. Acréscimo de até 20% na exclusão por incrementar o número de pesquisadores contratados (exclusivos) em percentual acima de 5% ou até 5% em comparação ao ano-calendário anterior
A29: --- 5.3. Até 70% de exclusão por incrementar o numero de pesquisadores contratados em percentual até 5%
A31: Equipe de PD&I
A32: Quadro de resumo | B32: Dedicação Parcial | E32: Dedicação Exclusiva
B33: Qtd | C33: Valor gasto | D33: Horas | E33: Qtd | F33: Valor gasto | G33: Horas
A34: Técnico | B34: =IFERROR(__xludf.DUMMYFUNCTION("COUNTA(IFERROR(FILTER(RH!$F$13:$F$34,RH!$F$13:$F$34 = $A34,RH!$V$13:$V$34 = ""Parcial""),))"),5.0) -> 5 | C34: =IFERROR(__xludf.DUMMYFUNCTION("SUM(IFERROR(FILTER(RH!$U$49:$U$69,RH!$F$49:$F$69 = $A34,RH!$E$49:$E$69 = ""Parcial""),0))"),83136.24831155327) -> 83136.248 | D34: =IFERROR(__xludf.DUMMYFUNCTION("SUM(IFERROR(FILTER(RH!$T$13:$T$27,RH!$F$13:$F$27 = $A34,RH!$V$13:$V$27 = ""Parcial""),0))*24"),1861.0100000000002) -> 1861.01 | E34: =IFERROR(__xludf.DUMMYFUNCTION("COUNTA(IFERROR(FILTER(RH!$F$13:$F$27,RH!$F$13:$F$27 = $A34,RH!$V$13:$V$27 = ""Exclusivo""),))"),0.0) -> 0 | F34: =IFERROR(__xludf.DUMMYFUNCTION("SUM(IFERROR(FILTER(RH!$U$49:$U$69,RH!$F$49:$F$69 = $A34,RH!$E$49:$E$69 = ""Exclusivo""),0))"),0.0) -> 0 | G34: =IFERROR(__xludf.DUMMYFUNCTION("SUM(IFERROR(FILTER(RH!$T$13:$T$27,RH!$F$13:$F$27 = $A34,RH!$V$13:$V$27 = ""Exclusivo""),0))*24"),0.0) -> 0
A35: Tecnologo | B35: =IFERROR(__xludf.DUMMYFUNCTION("COUNTA(IFERROR(FILTER(RH!$F$13:$F$34,RH!$F$13:$F$34 = $A35,RH!$V$13:$V$34 = ""Parcial""),))"),0.0) -> 0 | C35: =IFERROR(__xludf.DUMMYFUNCTION("SUM(IFERROR(FILTER(RH!$U$49:$U$69,RH!$F$49:$F$69 = $A35,RH!$E$49:$E$69 = ""Parcial""),0))"),0.0) -> 0 | D35: =IFERROR(__xludf.DUMMYFUNCTION("SUM(IFERROR(FILTER(RH!$T$13:$T$27,RH!$F$13:$F$27 = $A35,RH!$V$13:$V$27 = ""Parcial""),0))*24"),0.0) -> 0 | E35: =IFERROR(__xludf.DUMMYFUNCTION("COUNTA(IFERROR(FILTER(RH!$F$13:$F$27,RH!$F$13:$F$27 = $A35,RH!$V$13:$V$27 = ""Exclusivo""),))"),0.0) -> 0 | F35: =IFERROR(__xludf.DUMMYFUNCTION("SUM(IFERROR(FILTER(RH!$U$49:$U$69,RH!$F$49:$F$69 = $A35,RH!$E$49:$E$69 = ""Exclusivo""),0))"),0.0) -> 0 | G35: =IFERROR(__xludf.DUMMYFUNCTION("SUM(IFERROR(FILTER(RH!$T$13:$T$27,RH!$F$13:$F$27 = $A35,RH!$V$13:$V$27 = ""Exclusivo""),0))*24"),0.0) -> 0
A36: Superior Completo | B36: =IFERROR(__xludf.DUMMYFUNCTION("COUNTA(IFERROR(FILTER(RH!$F$13:$F$34,RH!$F$13:$F$34 = $A36,RH!$V$13:$V$34 = ""Parcial""),))"),10.0) -> 10 | C36: =IFERROR(__xludf.DUMMYFUNCTION("SUM(IFERROR(FILTER(RH!$U$49:$U$69,RH!$F$49:$F$69 = $A36,RH!$E$49:$E$69 = ""Parcial""),0))"),380378.4030854129) -> 380378.4 | D36: =IFERROR(__xludf.DUMMYFUNCTION("SUM(IFERROR(FILTER(RH!$T$13:$T$27,RH!$F$13:$F$27 = $A36,RH!$V$13:$V$27 = ""Parcial""),0))*24"),4634.15) -> 4634.15 | E36: =IFERROR(__xludf.DUMMYFUNCTION("COUNTA(IFERROR(FILTER(RH!$F$13:$F$27,RH!$F$13:$F$27 = $A36,RH!$V$13:$V$27 = ""Exclusivo""),))"),4.0) -> 4 | F36: =IFERROR(__xludf.DUMMYFUNCTION("SUM(IFERROR(FILTER(RH!$U$49:$U$69,RH!$F$49:$F$69 = $A36,RH!$E$49:$E$69 = ""Exclusivo""),0))"),872229.1409257072) -> 872229.14 | G36: =IFERROR(__xludf.DUMMYFUNCTION("SUM(IFERROR(FILTER(RH!$T$13:$T$27,RH!$F$13:$F$27 = $A36,RH!$V$13:$V$27 = ""Exclusivo""),0))*24"),8326.0) -> 8326
A37: Pós graduado | B37: =IFERROR(__xludf.DUMMYFUNCTION("COUNTA(IFERROR(FILTER(RH!$F$13:$F$34,RH!$F$13:$F$34 = $A37,RH!$V$13:$V$34 = ""Parcial""),))"),0.0) -> 0 | C37: =IFERROR(__xludf.DUMMYFUNCTION("SUM(IFERROR(FILTER(RH!$U$49:$U$69,RH!$F$49:$F$69 = $A37,RH!$E$49:$E$69 = ""Parcial""),0))"),0.0) -> 0 | D37: =IFERROR(__xludf.DUMMYFUNCTION("SUM(IFERROR(FILTER(RH!$T$13:$T$27,RH!$F$13:$F$27 = $A37,RH!$V$13:$V$27 = ""Parcial""),0))*24"),0.0) -> 0 | E37: =IFERROR(__xludf.DUMMYFUNCTION("COUNTA(IFERROR(FILTER(RH!$F$13:$F$27,RH!$F$13:$F$27 = $A37,RH!$V$13:$V$27 = ""Exclusivo""),))"),0.0) -> 0 | F37: =IFERROR(__xludf.DUMMYFUNCTION("SUM(IFERROR(FILTER(RH!$U$49:$U$69,RH!$F$49:$F$69 = $A37,RH!$E$49:$E$69 = ""Exclusivo""),0))"),0.0) -> 0 | G37: =IFERROR(__xludf.DUMMYFUNCTION("SUM(IFERROR(FILTER(RH!$T$13:$T$27,RH!$F$13:$F$27 = $A37,RH!$V$13:$V$27 = ""Exclusivo""),0))*24"),0.0) -> 0
A38: Mestrado | B38: =IFERROR(__xludf.DUMMYFUNCTION("COUNTA(IFERROR(FILTER(RH!$F$13:$F$34,RH!$F$13:$F$34 = $A38,RH!$V$13:$V$34 = ""Parcial""),))"),1.0) -> 1 | C38: =IFERROR(__xludf.DUMMYFUNCTION("SUM(IFERROR(FILTER(RH!$U$49:$U$69,RH!$F$49:$F$69 = $A38,RH!$E$49:$E$69 = ""Parcial""),0))"),0.0) -> 0 | D38: =IFERROR(__xludf.DUMMYFUNCTION("SUM(IFERROR(FILTER(RH!$T$13:$T$27,RH!$F$13:$F$27 = $A38,RH!$V$13:$V$27 = ""Parcial""),0))*24"),0.0) -> 0 | E38: =IFERROR(__xludf.DUMMYFUNCTION("COUNTA(IFERROR(FILTER(RH!$F$13:$F$27,RH!$F$13:$F$27 = $A38,RH!$V$13:$V$27 = ""Exclusivo""),))"),0.0) -> 0 | F38: =IFERROR(__xludf.DUMMYFUNCTION("SUM(IFERROR(FILTER(RH!$U$49:$U$69,RH!$F$49:$F$69 = $A38,RH!$E$49:$E$69 = ""Exclusivo""),0))"),0.0) -> 0 | G38: =IFERROR(__xludf.DUMMYFUNCTION("SUM(IFERROR(FILTER(RH!$T$13:$T$27,RH!$F$13:$F$27 = $A38,RH!$V$13:$V$27 = ""Exclusivo""),0))*24"),0.0) -> 0
A39: Doutorado | B39: =IFERROR(__xludf.DUMMYFUNCTION("COUNTA(IFERROR(FILTER(RH!$F$13:$F$34,RH!$F$13:$F$34 = $A39,RH!$V$13:$V$34 = ""Parcial""),))"),0.0) -> 0 | C39: =IFERROR(__xludf.DUMMYFUNCTION("SUM(IFERROR(FILTER(RH!$U$49:$U$69,RH!$F$49:$F$69 = $A39,RH!$E$49:$E$69 = ""Parcial""),0))"),0.0) -> 0 | D39: =IFERROR(__xludf.DUMMYFUNCTION("SUM(IFERROR(FILTER(RH!$T$13:$T$27,RH!$F$13:$F$27 = $A39,RH!$V$13:$V$27 = ""Parcial""),0))*24"),0.0) -> 0 | E39: =IFERROR(__xludf.DUMMYFUNCTION("COUNTA(IFERROR(FILTER(RH!$F$13:$F$27,RH!$F$13:$F$27 = $A39,RH!$V$13:$V$27 = ""Exclusivo""),))"),0.0) -> 0 | F39: =IFERROR(__xludf.DUMMYFUNCTION("SUM(IFERROR(FILTER(RH!$U$49:$U$69,RH!$F$49:$F$69 = $A39,RH!$E$49:$E$69 = ""Exclusivo""),0))"),0.0) -> 0 | G39: =IFERROR(__xludf.DUMMYFUNCTION("SUM(IFERROR(FILTER(RH!$T$13:$T$27,RH!$F$13:$F$27 = $A39,RH!$V$13:$V$27 = ""Exclusivo""),0))*24"),0.0) -> 0
B40: =SUM(B34:B39) -> 16 | C40: =SUM(C34:C39) -> 463514.65 | D40: =SUM(D34:D39) -> 6495.16 | E40: =SUM(E34:E39) -> 4 | F40: =SUM(F34:F39) -> 872229.14 | G40: =SUM(G34:G39) -> 8326
A42: Valores por projeto de PD&I
A43: Projetos | B43: TOTAL | D43: Vlr materiais | E43: Vlr terceiros | F43: Vlr Rh parcial | G43: Vlr exclusivos
A44: {='Resumo - PROJETOS'!B12:B49} -> IRIS | B44: =sum(D44:G44) -> 422175.06 | D44: - | E44: =IFERROR(__xludf.DUMMYFUNCTION("iferror(sum(filter('Resumo - TERCEIROS'!$G:$G,'Resumo - TERCEIROS'!$K:$K=TRUE,'Resumo - TERCEIROS'!$B:$B=$A44)),0)"),105672.13) -> 105672.13 | F44: =IFERROR(__xludf.DUMMYFUNCTION("iferror(sum(filter('Resumo - TIMESHEETS'!$L$12:$L49,'Resumo - TIMESHEETS'!$O$12:$O49=""Parcial"",'Resumo - TIMESHEETS'!$C$12:$C49=$A44)),0)"),316502.92701534065) -> 316502.93 | G44: =IFERROR(__xludf.DUMMYFUNCTION("iferror(sum(filter('Resumo - TIMESHEETS'!$L$12:$L49,'Resumo - TIMESHEETS'!$O$12:$O49=""Exclusivo"",'Resumo - TIMESHEETS'!$C$12:$C49=$A44)),0)"),0.0) -> 0
A45: NOTIFY | B45: =sum(D45:G45) -> 2006004.4 | D45: - | E45: =IFERROR(__xludf.DUMMYFUNCTION("iferror(sum(filter('Resumo - TERCEIROS'!$G:$G,'Resumo - TERCEIROS'!$K:$K=TRUE,'Resumo - TERCEIROS'!$B:$B=$A45)),0)"),1063146.31) -> 1063146.3 | F45: =IFERROR(__xludf.DUMMYFUNCTION("iferror(sum(filter('Resumo - TIMESHEETS'!$L$12:$L49,'Resumo - TIMESHEETS'!$O$12:$O49=""Parcial"",'Resumo - TIMESHEETS'!$C$12:$C49=$A45)),0)"),70628.94894818438) -> 70628.949 | G45: =IFERROR(__xludf.DUMMYFUNCTION("iferror(sum(filter('Resumo - TIMESHEETS'!$L$12:$L49,'Resumo - TIMESHEETS'!$O$12:$O49=""Exclusivo"",'Resumo - TIMESHEETS'!$C$12:$C49=$A45)),0)"),872229.1409257068) -> 872229.14
A46: P&D_1 | B46: =sum(D46:G46) -> 100730.61 | D46: - | E46: =IFERROR(__xludf.DUMMYFUNCTION("iferror(sum(filter('Resumo - TERCEIROS'!$G:$G,'Resumo - TERCEIROS'!$K:$K=TRUE,'Resumo - TERCEIROS'!$B:$B=$A46)),0)"),0.0) -> 0 | F46: =IFERROR(__xludf.DUMMYFUNCTION("iferror(sum(filter('Resumo - TIMESHEETS'!$L$12:$L49,'Resumo - TIMESHEETS'!$O$12:$O49=""Parcial"",'Resumo - TIMESHEETS'!$C$12:$C49=$A46)),0)"),100730.61356324713) -> 100730.61 | G46: =IFERROR(__xludf.DUMMYFUNCTION("iferror(sum(filter('Resumo - TIMESHEETS'!$L$12:$L49,'Resumo - TIMESHEETS'!$O$12:$O49=""Exclusivo"",'Resumo - TIMESHEETS'!$C$12:$C49=$A46)),0)"),0.0) -> 0
A47: P&D_2 | B47: =sum(D47:G47) -> 76802.561 | D47: - | E47: =IFERROR(__xludf.DUMMYFUNCTION("iferror(sum(filter('Resumo - TERCEIROS'!$G:$G,'Resumo - TERCEIROS'!$K:$K=TRUE,'Resumo - TERCEIROS'!$B:$B=$A47)),0)"),30957.949999999997) -> 30957.95 | F47: =IFERROR(__xludf.DUMMYFUNCTION("iferror(sum(filter('Resumo - TIMESHEETS'!$L$12:$L49,'Resumo - TIMESHEETS'!$O$12:$O49=""Parcial"",'Resumo - TIMESHEETS'!$C$12:$C49=$A47)),0)"),45844.610869300064) -> 45844.611 | G47: =IFERROR(__xludf.DUMMYFUNCTION("iferror(sum(filter('Resumo - TIMESHEETS'!$L$12:$L49,'Resumo - TIMESHEETS'!$O$12:$O49=""Exclusivo"",'Resumo - TIMESHEETS'!$C$12:$C49=$A47)),0)"),0.0) -> 0
A48: P&D_3 | B48: =sum(D48:G48) -> 142944.9 | D48: - | E48: =IFERROR(__xludf.DUMMYFUNCTION("iferror(sum(filter('Resumo - TERCEIROS'!$G:$G,'Resumo - TERCEIROS'!$K:$K=TRUE,'Resumo - TERCEIROS'!$B:$B=$A48)),0)"),122352.54000000001) -> 122352.54 | F48: =IFERROR(__xludf.DUMMYFUNCTION("iferror(sum(filter('Resumo - TIMESHEETS'!$L$12:$L49,'Resumo - TIMESHEETS'!$O$12:$O49=""Parcial"",'Resumo - TIMESHEETS'!$C$12:$C49=$A48)),0)"),20592.363892992773) -> 20592.364 | G48: =IFERROR(__xludf.DUMMYFUNCTION("iferror(sum(filter('Resumo - TIMESHEETS'!$L$12:$L49,'Resumo - TIMESHEETS'!$O$12:$O49=""Exclusivo"",'Resumo - TIMESHEETS'!$C$12:$C49=$A48)),0)"),0.0) -> 0
A49: Subtotais | B49: =SUM(B44:B48) -> 2748657.5 | D49: =Sum(D44:D48) -> 0 | E49: =SUM(E44:E48) -> 1322128.9 | F49: =SUM(F44:F48) -> 554299.46 | G49: =SUM(G44:G48) -> 872229.14

Sheet Resumo - TERCEIROS
B2: NETZSCH
B3: Pesquisa, Desenvolvimento & Inovação
B4: Formulário de PD&I - Ano 2023
B5: - preencher somente os campos sombreados (cinza)
B8: Dossiê do projeto
B9: Investimentos com terceiros
B11: Projeto | C11: Etapa | D11: Fornecedor | E11: CNPJ | F11: Nota fiscal | G11: Valor | H11: Data | I11: Descrição da Atividade | J11: Objetivo do gasto e eventual info de rateio | K11: Projeto incentiv. | M11: CNPJ
B12: {={'IRIS TERCEIROS'!B12:J579;'NOTIFY TERCEIROS'!B12:J579;'P&D_1 TERCEIROS'!B12:J579;'P&D_2 TERCEIROS'!B12:J579;'P&D_3 TERCEIROS'!B12:J579}} -> IRIS | C12: IRISV3 - Desenvolvimento de bilbioteca de objetos | D12: KMCC Equipamentos Elétricos Ltda | E12: 05.974.479/0001-80 | F12: NFS-e2128 | G12: 572 | H12: 45017 | I12: Desenvolvimento IHM | J12: Total nota fiscal: R$ 8931. Rateio: 6,4 % | K12: {=xlookup($B$12:$B579,'Resumo - PROJETOS'!$B:$B,'Resumo - PROJETOS'!$C:$C,,0)} -> TRUE
B13: IRIS | C13: Todas as etapas | D13: JAV AUTOMACAO INDUSTRIAL LTDA | E13: 82.731.779/0002-60 | F13: NFS-e1363 | G13: 9963.35 | H13: 45065 | I13: Serviço de manutenção de acesso remoto TALK2M | J13: Total nota fiscal: R$ 9963,35. Rateio: 100 % | K13: TRUE
B14: IRIS | C14: Todas as etapas | D14: JAV AUTOMACAO INDUSTRIAL LTDA | E14: 82.731.779/0002-60 | F14: NFS-e1373 | G14: 28380.48 | H14: 45082 | I14: Licenças de desenvolvimento ROCKWELL | J14: Total nota fiscal: R$ 28380,48. Rateio: 100 % | K14: TRUE
B15: IRIS | C15: Todas as etapas | D15: SIEMENS INFRAESTRUTURA E INDÚSTRIA LTDA. | E15: 34.776.007/0003-83 | F15: NFS-e7876 | G15: 19768.3 | H15: 45141 | I15: Licenças de desenvolvimento SIEMENS | J15: Total nota fiscal: R$ 19768,3. Rateio: 100 % | K15: TRUE
B16: IRIS | C16: IRISV3 - Desenvolvimento de bilbioteca de objetos | D16: KMCC Equipamentos Elétricos Ltda | E16: 05.974.479/0001-80 | F16: NFS-e2193 | G16: 15123 | H16: 45170 | I16: Desenvolvimento IHM | J16: Total nota fiscal: R$ 17375. Rateio: 87,04 % | K16: TRUE
B17: IRIS | C17: IRISV3 - Desenvolvimento de bilbioteca de objetos | D17: KMCC Equipamentos Elétricos Ltda | E17: 05.974.479/0001-80 | F17: NFS-e2218 | G17: 15045 | H17: 45200 | I17: Desenvolvimento IHM | J17: Total nota fiscal: R$ 20052,5. Rateio: 75,03 % | K17: TRUE
B18: IRIS | C18: IRISV3 - Desenvolvimento de bilbioteca de objetos | D18: KMCC Equipamentos Elétricos Ltda | E18: 05.974.479/0001-80 | F18: NFS-e2228 | G18: 16820 | H18: 45231 | I18: Desenvolvimento IHM | J18: Total nota fiscal: R$ 17962,5. Rateio: 93,64 % | K18: TRUE
B19: Notify | C19: Criação de ordens de serviço | D19: Materialize Serviços Digitais Ltda | E19: 34.269.716/0001-00 | F19: 338 | G19: 34850 | H19: 44929 | I19: Agênciamento de serviços de desenvovimento de software | J19: Total nota fiscal: R$ 69700. Rateio: 50 % | K19: TRUE
B20: Notify | C20: Planejamento de manutenções preventivas | D20: Materialize Serviços Digitais Ltda | E20: 34.269.716/0001-00 | F20: 338 | G20: 34850 | H20: 44929 | I20: Agênciamento de serviços de desenvovimento de software | J20: Total nota fiscal: R$ 69700. Rateio: 50 % | K20: TRUE
B21: Notify | C21: Criação de ordens de serviço | D21: Amazon AWS Serviços Brasil Ltda | E21: 23.412.247/0001-10 | F21: 1684279_TRARB7GL | G21: 4059.07 | H21: 44959 | I21: Custo da infraestrutura em nuvem | J21: Total nota fiscal: R$ 8118,14. Rateio: 50 % | K21: TRUE
B22: Notify | C22: Planejamento de manutenções preventivas | D22: Amazon AWS Serviços Brasil Ltda | E22: 23.412.247/0001-10 | F22: 1684279_TRARB7GL | G22: 4059.07 | H22: 44959 | I22: Custo da infraestrutura em nuvem | J22: Total nota fiscal: R$ 8118,14. Rateio: 50 % | K22: TRUE
B23: Notify | C23: Teste de penetração (cybersegurança) | D23: XLABS ON SECURITY SEGURANCA DA INFORMACAO LTDA | E23: 30.162.109/0001-96 | F23: 202324 | G23: 4850 | H23: 44960 | I23: Serviços prestados em segurança da informação | J23: Total nota fiscal: R$ 4850. Rateio: 100 % | K23: TRUE
B24: Notify | C24: Criação de ordens de serviço | D24: Materialize Serviços Digitais Ltda | E24: 34.269.716/0001-00 | F24: 377 | G24: 34850 | H24: 44960 | I24: Agênciamento de serviços de desenvovimento de software | J24: Total nota fiscal: R$ 69700. Rateio: 50 % | K24: TRUE
B25: Notify | C25: Planejamento de manutenções preventivas | D25: Materialize Serviços Digitais Ltda | E25: 34.269.716/0001-00 | F25: 377 | G25: 34850 | H25: 44960 | I25: Agênciamento de serviços de desenvovimento de software | J25: Total nota fiscal: R$ 69700. Rateio: 50 % | K25: TRUE
B26: Notify | C26: Criação de ordens de serviço | D26: Amazon AWS Serviços Brasil Ltda | E26: 23.412.247/0001-10 | F26: 1834979_ZLH5AEKP | G26: 1907.88 | H26: 44987 | I26: Custo da infraestrutura em nuvem | J26: Total nota fiscal: R$ 7631,54. Rateio: 25 % | K26: TRUE
B27: Notify | C27: Planejamento de manutenções preventivas | D27: Amazon AWS Serviços Brasil Ltda | E27: 23.412.247/0001-10 | F27: 1834979_ZLH5AEKP | G27: 1907.88 | H27: 44987 | I27: Custo da infraestrutura em nuvem | J27: Total nota fiscal: R$ 7631,54. Rateio: 25 % | K27: TRUE
B28: Notify | C28: Gerencimeno de licenças | D28: Amazon AWS Serviços Brasil Ltda | E28: 23.412.247/0001-10 | F28: 1834979_ZLH5AEKP | G28: 1907.88 | H28: 44987 | I28: Custo da infraestrutura em nuvem | J28: Total nota fiscal: R$ 7631,54. Rateio: 25 % | K28: TRUE
B29: Notify | C29: Duplicar máquinas existentes | D29: Amazon AWS Serviços Brasil Ltda | E29: 23.412.247/0001-10 | F29: 1834979_ZLH5AEKP | G29: 1907.88 | H29: 44987 | I29: Custo da infraestrutura em nuvem | J29: Total nota fiscal: R$ 7631,54. Rateio: 25 % | K29: TRUE
B30: Notify | C30: Criação de ordens de serviço | D30: Materialize Serviços Digitais Ltda | E30: 34.269.716/0001-00 | F30: 408 | G30: 17425 | H30: 44991 | I30: Agênciamento de serviços de desenvovimento de software | J30: Total nota fiscal: R$ 69700. Rateio: 25 % | K30: TRUE
B31: Notify | C31: Planejamento de manutenções preventivas | D31: Materialize Serviços Digitais Ltda | E31: 34.269.716/0001-00 | F31: 408 | G31: 17425 | H31: 44991 | I31: Agênciamento de serviços de desenvovimento de software | J31: Total nota fiscal: R$ 69700. Rateio: 25 % | K31: TRUE
B32: Notify | C32: Gerencimeno de licenças | D32: Materialize Serviços Digitais Ltda | E32: 34.269.716/0001-00 | F32: 408 | G32: 17425 | H32: 44991 | I32: Agênciamento de serviços de desenvovimento de software | J32: Total nota fiscal: R$ 69700. Rateio: 25 % | K32: TRUE
B33: Notify | C33: Duplicar máquinas existentes | D33: Materialize Serviços Digitais Ltda | E33: 34.269.716/0001-00 | F33: 408 | G33: 17425 | H33: 44991 | I33: Agênciamento de serviços de desenvovimento de software | J33: Total nota fiscal: R$ 69700. Rateio: 25 % | K33: TRUE
B34: Notify | C34: Teste de penetração (cybersegurança) | D34: XLABS ON SECURITY SEGURANCA DA INFORMACAO LTDA | E34: 30.162.109/0001-96 | F34: 202369 | G34: 4850 | H34: 44992 | I34: Serviços prestados em segurança da informação | J34: Total nota fiscal: R$ 4850. Rateio: 100 % | K34: TRUE
B35: Notify | C35: Criação de ordens de serviço | D35: Amazon AWS Serviços Brasil Ltda | E35: 23.412.247/0001-10 | F35: 1851758_THE47Z4R | G35: 2101.47 | H35: 45018 | I35: Custo da infraestrutura em nuvem | J35: Total nota fiscal: R$ 8405,9. Rateio: 25 % | K35: TRUE
B36: Notify | C36: Planejamento de manutenções preventivas | D36: Amazon AWS Serviços Brasil Ltda | E36: 23.412.247/0001-10 | F36: 1851758_THE47Z4R | G36: 2101.47 | H36: 45018 | I36: Custo da infraestrutura em nuvem | J36: Total nota fiscal: R$ 8405,9. Rateio: 25 % | K36: TRUE
B37: Notify | C37: Gerencimeno de licenças | D37: Amazon AWS Serviços Brasil Ltda | E37: 23.412.247/0001-10 | F37: 1851758_THE47Z4R | G37: 2101.47 | H37: 45018 | I37: Custo da infraestrutura em nuvem | J37: Total nota fiscal: R$ 8405,9. Rateio: 25 % | K37: TRUE
B38: Notify | C38: Duplicar máquinas existentes | D38: Amazon AWS Serviços Brasil Ltda | E38: 23.412.247/0001-10 | F38: 1851758_THE47Z4R | G38: 2101.47 | H38: 45018 | I38: Custo da infraestrutura em nuvem | J38: Total nota fiscal: R$ 8405,9. Rateio: 25 % | K38: TRUE
B39: Notify | C39: Criação de ordens de serviço | D39: Materialize Serviços Digitais Ltda | E39: 34.269.716/0001-00 | F39: 439 | G39: 17425 | H39: 45022 | I39: Agênciamento de serviços de desenvovimento de software | J39: Total nota fiscal: R$ 69700. Rateio: 25 % | K39: TRUE
B40: Notify | C40: Planejamento de manutenções preventivas | D40: Materialize Serviços Digitais Ltda | E40: 34.269.716/0001-00 | F40: 439 | G40: 17425 | H40: 45022 | I40: Agênciamento de serviços de desenvovimento de software | J40: Total nota fiscal: R$ 69700. Rateio: 25 % | K40: TRUE
B41: Notify | C41: Gerencimeno de licenças | D41: Materialize Serviços Digitais Ltda | E41: 34.269.716/0001-00 | F41: 439 | G41: 17425 | H41: 45022 | I41: Agênciamento de serviços de desenvovimento de software | J41: Total nota fiscal: R$ 69700. Rateio: 25 % | K41: TRUE
B42: Notify | C42: Duplicar máquinas existentes | D42: Materialize Serviços Digitais Ltda | E42: 34.269.716/0001-00 | F42: 439 | G42: 17425 | H42: 45022 | I42: Agênciamento de serviços de desenvovimento de software | J42: Total nota fiscal: R$ 69700. Rateio: 25 % | K42: TRUE
B43: Notify | C43: Gerencimeno de licenças | D43: Amazon AWS Serviços Brasil Ltda | E43: 23.412.247/0001-10 | F43: 1974603_J4XEGDTG | G43: 3917.99 | H43: 45048 | I43: Custo da infraestrutura em nuvem | J43: Total nota fiscal: R$ 7835,98. Rateio: 50 % | K43: TRUE
B44: Notify | C44: Duplicar máquinas existentes | D44: Amazon AWS Serviços Brasil Ltda | E44: 23.412.247/0001-10 | F44: 1974603_J4XEGDTG | G44: 3917.99 | H44: 45048 | I44: Custo da infraestrutura em nuvem | J44: Total nota fiscal: R$ 7835,98. Rateio: 50 % | K44: TRUE
B45: Notify | C45: Gerencimeno de licenças | D45: Materialize Serviços Digitais Ltda | E45: 34.269.716/0001-00 | F45: 475 | G45: 34000 | H45: 45055 | I45: Agênciamento de serviços de desenvovimento de software | J45: Total nota fiscal: R$ 68000. Rateio: 50 % | K45: TRUE
B46: Notify | C46: Duplicar máquinas existentes | D46: Materialize Serviços Digitais Ltda | E46: 34.269.716/0001-00 | F46: 475 | G46: 34000 | H46: 45055 | I46: Agênciamento de serviços de desenvovimento de software | J46: Total nota fiscal: R$ 68000. Rateio: 50 % | K46: TRUE
B47: Notify | C47: Gerencimeno de licenças | D47: Materialize Serviços Digitais Ltda | E47: 34.269.716/0001-00 | F47: 497 | G47: 23233.33 | H47: 45078 | I47: Agênciamento de serviços de desenvovimento de software | J47: Total nota fiscal: R$ 69700. Rateio: 33,33 % | K47: TRUE
B48: Notify | C48: Duplicar máquinas existentes | D48: Materialize Serviços Digitais Ltda | E48: 34.269.716/0001-00 | F48: 497 | G48: 23233.33 | H48: 45078 | I48: Agênciamento de serviços de desenvovimento de software | J48: Total nota fiscal: R$ 69700. Rateio: 33,33 % | K48: TRUE
B49: Notify | C49: Cadastro de tarefas de manutenção preventiva | D49: Materialize Serviços Digitais Ltda | E49: 34.269.716/0001-00 | F49: 497 | G49: 23233.33 | H49: 45078 | I49: Agênciamento de serviços de desenvovimento de software | J49: Total nota fiscal: R$ 69700. Rateio: 33,33 % | K49: TRUE
B50: Notify | C50: Gerencimeno de licenças | D50: Amazon AWS Serviços Brasil Ltda | E50: 23.412.247/0001-10 | F50: 2073356_N3RQWJJ4 | G50: 2669.23 | H50: 45079 | I50: Custo da infraestrutura em nuvem | J50: Total nota fiscal: R$ 8007,7. Rateio: 33,33 % | K50: TRUE
B51: Notify | C51: Duplicar máquinas existentes | D51: Amazon AWS Serviços Brasil Ltda | E51: 23.412.247/0001-10 | F51: 2073356_N3RQWJJ4 | G51: 2669.23 | H51: 45079 | I51: Custo da infraestrutura em nuvem | J51: Total nota fiscal: R$ 8007,7. Rateio: 33,33 % | K51: TRUE
B52: Notify | C52: Cadastro de tarefas de manutenção preventiva | D52: Amazon AWS Serviços Brasil Ltda | E52: 23.412.247/0001-10 | F52: 2073356_N3RQWJJ4 | G52: 2669.23 | H52: 45079 | I52: Custo da infraestrutura em nuvem | J52: Total nota fiscal: R$ 8007,7. Rateio: 33,33 % | K52: TRUE
B53: Notify | C53: Cadastro de tarefas de manutenção preventiva | D53: Amazon AWS Serviços Brasil Ltda | E53: 23.412.247/0001-10 | F53: 2135752_9VMHLMTL | G53: 8323.82 | H53: 45109 | I53: Custo da infraestrutura em nuvem | J53: Total nota fiscal: R$ 8323,82. Rateio: 100 % | K53: TRUE
B54: Notify | C54: Cadastro de tarefas de manutenção preventiva | D54: Materialize Serviços Digitais Ltda | E54: 34.269.716/0001-00 | F54: 524 | G54: 69700 | H54: 45110 | I54: Agênciamento de serviços de desenvovimento de software | J54: Total nota fiscal: R$ 69700. Rateio: 100 % | K54: TRUE
B55: Notify | C55: NETZSCH G&D Digital Products Home | D55: Materialize Serviços Digitais Ltda | E55: 34.269.716/0001-00 | F55: 539 | G55: 69700 | H55: 45139 | I55: Agênciamento de serviços de desenvovimento de software | J55: Total nota fiscal: R$ 69700. Rateio: 100 % | K55: TRUE
B56: Notify | C56: NETZSCH G&D Digital Products Home | D56: Amazon AWS Serviços Brasil Ltda | E56: 23.412.247/0001-10 | F56: 2227234_KD4PPGBK | G56: 10629.3 | H56: 45140 | I56: Custo da infraestrutura em nuvem | J56: Total nota fiscal: R$ 10629,3. Rateio: 100 % | K56: TRUE
B57: Notify | C57: Adequação do Gateway para o IRIS V3 | D57: MOUT S SOLUCOES EM TECNOLOGIA DA INFORMATICA LTDA | E57: 25.056.849/0001-08 | F57: 2889 | G57: 27000 | H57: 45148 | I57: ALOCAÇÃO PROFISSIONAL: Análise e desenvolvimento de sistemas | J57: Total nota fiscal: R$ 27000. Rateio: 100 % | K57: TRUE
B58: Notify | C58: NETZSCH G&D Digital Products Home | D58: Materialize Serviços Digitais Ltda | E58: 34.269.716/0001-00 | F58: 549 | G58: 34850 | H58: 45170 | I58: Agênciamento de serviços de desenvovimento de software | J58: Total nota fiscal: R$ 69700. Rateio: 50 % | K58: TRUE
B59: Notify | C59: Relatório de lotes | D59: Materialize Serviços Digitais Ltda | E59: 34.269.716/0001-00 | F59: 549 | G59: 34850 | H59: 45170 | I59: Agênciamento de serviços de desenvovimento de software | J59: Total nota fiscal: R$ 69700. Rateio: 50 % | K59: TRUE
B60: Notify | C60: NETZSCH G&D Digital Products Home | D60: Amazon AWS Serviços Brasil Ltda | E60: 23.412.247/0001-10 | F60: 2385112_EMIUSLCC | G60: 5436.5 | H60: 45172 | I60: Custo da infraestrutura em nuvem | J60: Total nota fiscal: R$ 10873,01. Rateio: 50 % | K60: TRUE
B61: Notify | C61: Relatório de lotes | D61: Amazon AWS Serviços Brasil Ltda | E61: 23.412.247/0001-10 | F61: 2385112_EMIUSLCC | G61: 5436.5 | H61: 45172 | I61: Custo da infraestrutura em nuvem | J61: Total nota fiscal: R$ 10873,01. Rateio: 50 % | K61: TRUE
B62: Notify | C62: NETZSCH G&D Digital Products Home | D62: Amazon AWS Serviços Brasil Ltda | E62: 23.412.247/0001-10 | F62: 2430376_4MVGWINA | G62: 3585.26 | H62: 45201 | I62: Custo da infraestrutura em nuvem | J62: Total nota fiscal: R$ 10755,78. Rateio: 33,33 % | K62: TRUE
B63: Notify | C63: Relatório de lotes | D63: Amazon AWS Serviços Brasil Ltda | E63: 23.412.247/0001-10 | F63: 2430376_4MVGWINA | G63: 3585.26 | H63: 45201 | I63: Custo da infraestrutura em nuvem | J63: Total nota fiscal: R$ 10755,78. Rateio: 33,33 % | K63: TRUE
B64: Notify | C64: Exportar dados para o Excel | D64: Amazon AWS Serviços Brasil Ltda | E64: 23.412.247/0001-10 | F64: 2430376_4MVGWINA | G64: 3585.26 | H64: 45201 | I64: Custo da infraestrutura em nuvem | J64: Total nota fiscal: R$ 10755,78. Rateio: 33,33 % | K64: TRUE
B65: Notify | C65: NETZSCH G&D Digital Products Home | D65: Materialize Serviços Digitais Ltda | E65: 34.269.716/0001-00 | F65: 570 | G65: 23233.33 | H65: 45202 | I65: Agênciamento de serviços de desenvovimento de software | J65: Total nota fiscal: R$ 69700. Rateio: 33,33 % | K65: TRUE
B66: Notify | C66: Relatório de lotes | D66: Materialize Serviços Digitais Ltda | E66: 34.269.716/0001-00 | F66: 570 | G66: 23233.33 | H66: 45202 | I66: Agênciamento de serviços de desenvovimento de software | J66: Total nota fiscal: R$ 69700. Rateio: 33,33 % | K66: TRUE
B67: Notify | C67: Exportar dados para o Excel | D67: Materialize Serviços Digitais Ltda | E67: 34.269.716/0001-00 | F67: 570 | G67: 23233.33 | H67: 45202 | I67: Agênciamento de serviços de desenvovimento de software | J67: Total nota fiscal: R$ 69700. Rateio: 33,33 % | K67: TRUE
B68: Notify | C68: Adequação do Gateway para o IRIS V3 | D68: MOUT S SOLUCOES EM TECNOLOGIA DA INFORMATICA LTDA | E68: 25.056.849/0001-08 | F68: 1991 | G68: 13920 | H68: 45148 | I68: ALOCAÇÃO PROFISSIONAL: Análise e desenvolvimento de sistemas | J68: Total nota fiscal: R$ 13920. Rateio: 100 % | K68: TRUE
B69: Notify | C69: Exportar dados para o Excel | D69: Amazon AWS Serviços Brasil Ltda | E69: 23.412.247/0001-10 | F69: 2548011_J7IJ9ZIE | G69: 5684.14 | H69: 45232 | I69: Custo da infraestrutura em nuvem | J69: Total nota fiscal: R$ 11368,28. Rateio: 50 % | K69: TRUE
B70: Notify | C70: Templates de gráficos | D70: Amazon AWS Serviços Brasil Ltda | E70: 23.412.247/0001-10 | F70: 2548011_J7IJ9ZIE | G70: 5684.14 | H70: 45232 | I70: Custo da infraestrutura em nuvem | J70: Total nota fiscal: R$ 11368,28. Rateio: 50 % | K70: TRUE
B71: Notify | C71: Exportar dados para o Excel | D71: Materialize Serviços Digitais Ltda | E71: 34.269.716/0001-00 | F71: 608 | G71: 69700 | H71: 45237 | I71: Agênciamento de serviços de desenvovimento de software | J71: Total nota fiscal: R$ 69700. Rateio: 100 % | K71: TRUE
B72: Notify | C72: Adequação do Gateway para o IRIS V3 | D72: MOUT S SOLUCOES EM TECNOLOGIA DA INFORMATICA LTDA | E72: 25.056.849/0001-08 | F72: 3054 | G72: 23400 | H72: 45244 | I72: ALOCAÇÃO PROFISSIONAL: Análise e desenvolvimento de sistemas | J72: Total nota fiscal: R$ 23400. Rateio: 100 % | K72: TRUE
B73: Notify | C73: Exportar dados para o Excel | D73: Amazon AWS Serviços Brasil Ltda | E73: 23.412.247/0001-10 | F73: 2610688_YNZZNXN6 | G73: 5305.71 | H73: 45262 | I73: Custo da infraestrutura em nuvem | J73: Total nota fiscal: R$ 10611,42. Rateio: 50 % | K73: TRUE
B74: Notify | C74: Templates de gráficos | D74: Amazon AWS Serviços Brasil Ltda | E74: 23.412.247/0001-10 | F74: 2610688_YNZZNXN6 | G74: 5305.71 | H74: 45262 | I74: Custo da infraestrutura em nuvem | J74: Total nota fiscal: R$ 10611,42. Rateio: 50 % | K74: TRUE
B75: Notify | C75: Adequação do Gateway para o IRIS V3 | D75: MOUT S SOLUCOES EM TECNOLOGIA DA INFORMATICA LTDA | E75: 25.056.849/0001-08 | F75: 3108 | G75: 41040 | H75: 45244 | I75: ALOCAÇÃO PROFISSIONAL: Análise e desenvolvimento de sistemas | J75: Total nota fiscal: R$ 41040. Rateio: 100 % | K75: TRUE
B76: Notify | C76: Exportar dados para o Excel | D76: Materialize Serviços Digitais Ltda | E76: 34.269.716/0001-00 | F76: 643 | G76: 34850 | H76: 45282 | I76: Agênciamento de serviços de desenvovimento de software | J76: Total nota fiscal: R$ 69700. Rateio: 50 % | K76: TRUE
B77: Notify | C77: Templates de gráficos | D77: Materialize Serviços Digitais Ltda | E77: 34.269.716/0001-00 | F77: 643 | G77: 34850 | H77: 45282 | I77: Agênciamento de serviços de desenvovimento de software | J77: Total nota fiscal: R$ 69700. Rateio: 50 % | K77: TRUE
B78: Notify | C78: Exportar dados para o Excel | D78: Amazon AWS Serviços Brasil Ltda | E78: 23.412.247/0001-10 | F78: 2709240_ECNZ6XB8 | G78: 5412.76 | H78: 44928 | I78: Custo da infraestrutura em nuvem | J78: Total nota fiscal: R$ 10825,52. Rateio: 50 % | K78: TRUE
B79: Notify | C79: Templates de gráficos | D79: Amazon AWS Serviços Brasil Ltda | E79: 23.412.247/0001-10 | F79: 2709240_ECNZ6XB8 | G79: 5412.76 | H79: 44928 | I79: Custo da infraestrutura em nuvem | J79: Total nota fiscal: R$ 10825,52. Rateio: 50 % | K79: TRUE
B80: P&D_1 | K80: TRUE
B81: P&D_2 | C81: Outros tamanhos e geometrias de dentes das ferramentas, outros materiais / Rotor liso para redução da viscosidade após a moagem | D81: STR FERRAMENTARIA EIRELI - ME | E81: 12715548000105 | F81: NF 9873-1 | G81: 18197.26 | H81: 45117 | I81: Compra das ferramentas de 5mm, facas de pré-corte e ferramentas lisas | J81: Testes | K81: TRUE
B82: P&D_2 | C82: Outros tamanhos e geometrias de dentes das ferramentas, outros materiais | D82: RIJEZA INDUSTRIA METALURGICA LTDA / STR FERRAMENTARIA EIRELI - ME | E82: 5034416000144 / 12715548000105 | F82: NF 19147 / NF 9135-1 | G82: 4267.99 | H82: 44964 | I82: Compra de ferramentas com revestimento resistente ao desgaste | J82: Testes | K82: TRUE
B83: P&D_2 | C83: Melhorias do MasterCream MINI | D83: STR FERRAMENTARIA EIRELI - ME | E83: 12715548000105 | F83: NF 10094-1 | G83: 5998.03 | H83: 45206 | I83: Compra das novas ferramentas de moagem | J83: Testes | K83: TRUE
B84: P&D_2 | C84: Melhorias do MasterCream MINI | D84: WEG EQUIPAMENTOS ELÉTRICOS S/A | E84: 7175725001050 | F84: NF 3411393-1 | G84: 2494.67 | H84: 45203 | I84: Compra de acionamento mais potente | J84: Testes | K84: TRUE
B85: P&D_3 | C85: MasterRefiner 30 Hygienic design | D85: Netzsch Moagem | E85: 7389050000151 | G85: 22629.05 | H85: 45141 | I85: Fabricação interna do eixo agitador para o moinho MasterRefiner 30 | J85: Moinho com design higienico para limpeza CIP | K85: TRUE
B86: P&D_3 | C86: MasterRefiner 30 Hygienic design | D86: Wachholz LTDA. EPP | E86: 10591960000127 | F86: NF 7419-2 | G86: 29979.16 | H86: 45188 | I86: Fabricação do recipiente de moagem do moinho MasterRefiner 30 | J86: Moinho com design higienico para limpeza CIP | K86: TRUE
B87: P&D_3 | C87: MasterRefiner 30 Hygienic design | D87: JGW MECANICA INDUSTRIAL LTDA. EPP | E87: 7564023000178 | F87: NF 8904-2 | G87: 6992.07 | H87: 45182 | I87: Fabricação de peineira separadora de esferas para MasterRefiner 30 | J87: Moinho com design higienico para limpeza CIP | K87: TRUE
B88: P&D_3 | C88: MasterRefiner 30 Hygienic design | D88: Netzsch Moagem | E88: 7389050000151 | G88: 12688.67 | H88: 45182 | I88: Fabricação de selo mecanico para moinho MasterRefiner 30 | J88: Moinho com design higienico para limpeza CIP | K88: TRUE
B89: P&D_3 | C89: Sistema de limpeza com água | D89: TREFFER INDUSTRY | E89: 11368303000188 | F89: NF 152-1 | G89: 28209.9 | H89: 45149 | I89: Compra de cabeçotes de limpeza Hydroclaw | J89: Teste de limpeza com cabeçotes estaticos | K89: TRUE
B90: P&D_3 | C90: Sistema de limpeza com água | D90: NETZSCH FEINMAHLTECHNIK GmbH | E90: 22311610035 | F90: NF 12689 | G90: 3564.89 | H90: 45169 | I90: Utilização dos cabeçotes que estavam em estoque | J90: Realização de teste de limpeza preliminar | K90: TRUE
B91: P&D_3 | C91: Sistema de limpeza com água | D91: Netzsch Moagem | E91: 7389050000151 | G91: 9544 | H91: 45223 | I91: Montagem do sistema de limpeza/áquecimento | J91: Realização de testes de limpeza com água quente | K91: TRUE
B92: P&D_3 | C92: Sistema de limpeza com água | D92: FRANKLIN ELECTRIC IND. MOTOBOMBAS | E92: 84685106000166 | F92: NF 480102-2 | G92: 8744.8 | H92: 45260 | I92: Montagem de bombas para sistema de limpeza | J92: Montagem de bombas com maior vazão/pressão para aumentar a capacidade de limpeza | K92: TRUE

Sheet Resumo - PROJETOS
B2: NETZSCH
B3: Pesquisa, Desenvolvimento & Inovação
B4: Formulário de PD&I - Ano 2023
B5: - preencher somente os campos sombreados (cinza)
B8: Dossiê do projeto
B9: Investimentos com terceiros
B11: Projeto | C11: Incentivado pela Lei do Bem | D11: Objetiva tornar-se um Ativo | E11: Objetiva gerar patente/registro
B12: IRIS | C12: {=transpose(IRIS!M4:M6)} -> TRUE | D12: FALSE | E12: FALSE
B13: NOTIFY | C13: {=transpose(NOTIFY!M4:M6)} -> TRUE | D13: FALSE | E13: FALSE
B14: P&D_1 | C14: {=TRANSPOSE('P&D_1'!M4:M6)} -> TRUE | D14: FALSE | E14: FALSE
B15: P&D_2 | C15: {=TRANSPOSE('P&D_2'!M4:M6)} -> TRUE | D15: FALSE | E15: FALSE
B16: P&D_3 | C16: {=transpose('P&D_3'!M4:M6)} -> TRUE | D16: FALSE | E16: FALSE

Sheet Resumo - TIMESHEETS
B2: NETZSCH
B3: Pesquisa, Desenvolvimento & Inovação
B4: Formulário de PD&I - Ano 2023
B5: - preencher somente os campos sombreados (cinza)
J6: Treinamento
J7: Pesquisa
B8: Dossiê do projeto | J8: Desenvolvimento
B9: Atividades de Pesquisa, Desenvolvimento e Inovação | J9: Gestão e outros
B11: RowID | C11: Projeto | D11: Etapa | E11: Colaborador | F11: CPF | G11: Data | H11: Tempo (h) | J11: Classificação | K11: Descrição da atividade e observações | L11: Custo | M11: Atividade incentiv. | N11: Projeto incentiv. | O11: Dedic.
C12: IRIS | D12: Revisão protocolos de comissionamento | E12: Alexandre Baseggio | G12: 44927 | H12: 19.77 | I12: =H12/24 -> 0.82375 | J12: Desenvolvimento | K12: Desenvolvimento PLC | L12: =iferror(if(and($M12=TRUE,$N12=TRUE),vlookup($E12,RH!$B$48:$S$70,month($G12)+6,false)*$H12,0),0) -> 1057.0824 | M12: =if(OR(J12="Treinamento",J12="Pesquisa",J12="Desenvolvimento"),TRUE,FALSE) -> TRUE | N12: {=xlookup($C$12:$C273,'Resumo - PROJETOS'!$B:$B,'Resumo - PROJETOS'!$C:$C,,0)} -> TRUE | O12: {=xlookup($E$12:$E273,RH!$B:$B,RH!$V:$V,,0)} -> Parcial
C13: IRIS | D13: Revisão protocolos de comissionamento | E13: Eduardo Flohr | F13: 064.303.159-67 | G13: 44927 | H13: 2.5 | I13: =H13/24 -> 0.10416667 | J13: Gestão e outros | K13: Gestão | L13: =iferror(if(and($M13=TRUE,$N13=TRUE),vlookup($E13,RH!$B$48:$S$70,month($G13)+6,false)*$H13,0),0) -> 0 | M13: =if(OR(J13="Treinamento",J13="Pesquisa",J13="Desenvolvimento"),TRUE,FALSE) -> FALSE | N13: TRUE | O13: Parcial
C14: IRIS | D14: Revisão protocolos de comissionamento | E14: Gabriel Alves Ferraz | F14: 132.105.086-07 | G14: 44927 | H14: 28 | I14: =H14/24 -> 1.1666667 | J14: Desenvolvimento | K14: Desenvolvimento IHM | L14: =iferror(if(and($M14=TRUE,$N14=TRUE),vlookup($E14,RH!$B$48:$S$70,month($G14)+6,false)*$H14,0),0) -> 598.90009 | M14: =if(OR(J14="Treinamento",J14="Pesquisa",J14="Desenvolvimento"),TRUE,FALSE) -> TRUE | N14: TRUE | O14: Parcial
C15: IRIS | D15: Revisão protocolos de comissionamento | E15: Filipe Harbs | G15: 44927 | H15: 22 | I15: =H15/24 -> 0.91666667 | J15: Desenvolvimento | K15: Desenvolvimento IHM | L15: =iferror(if(and($M15=TRUE,$N15=TRUE),vlookup($E15,RH!$B$48:$S$70,month($G15)+6,false)*$H15,0),0) -> 929.56786 | M15: =if(OR(J15="Treinamento",J15="Pesquisa",J15="Desenvolvimento"),TRUE,FALSE) -> TRUE | N15: TRUE | O15: Parcial
C16: IRIS | D16: Revisão protocolos de comissionamento | E16: Ivo Ersching | G16: 44927 | H16: 11 | I16: =H16/24 -> 0.45833333 | J16: Pesquisa | K16: Desenvolvimento PLC | L16: =iferror(if(and($M16=TRUE,$N16=TRUE),vlookup($E16,RH!$B$48:$S$70,month($G16)+6,false)*$H16,0),0) -> 689.28516 | M16: =if(OR(J16="Treinamento",J16="Pesquisa",J16="Desenvolvimento"),TRUE,FALSE) -> TRUE | N16: TRUE | O16: Parcial
C17: IRIS | D17: Aprimorar dados de processo | E17: Filipe Harbs | G17: 44958 | H17: 4 | I17: =H17/24 -> 0.16666667 | J17: Desenvolvimento | K17: Desenvolvimento IHM | L17: =iferror(if(and($M17=TRUE,$N17=TRUE),vlookup($E17,RH!$B$48:$S$70,month($G17)+6,false)*$H17,0),0) -> 175.05405 | M17: =if(OR(J17="Treinamento",J17="Pesquisa",J17="Desenvolvimento"),TRUE,FALSE) -> TRUE | N17: TRUE | O17: Parcial
C18: IRIS | D18: Aprimorar dados de processo | E18: Ivo Ersching | G18: 44958 | H18: 5.5 | I18: =H18/24 -> 0.22916667 | J18: Desenvolvimento | K18: Desenvolvimento PLC | L18: =iferror(if(and($M18=TRUE,$N18=TRUE),vlookup($E18,RH!$B$48:$S$70,month($G18)+6,false)*$H18,0),0) -> 356.96257 | M18: =if(OR(J18="Treinamento",J18="Pesquisa",J18="Desenvolvimento"),TRUE,FALSE) -> TRUE | N18: TRUE | O18: Parcial
C19: IRIS | D19: Aprimorar dados de processo | E19: Eduardo Flohr | F19: 064.303.159-67 | G19: 44958 | H19: 5.5 | I19: =H19/24 -> 0.22916667 | J19: Gestão e outros | K19: Gestão | L19: =iferror(if(and($M19=TRUE,$N19=TRUE),vlookup($E19,RH!$B$48:$S$70,month($G19)+6,false)*$H19,0),0) -> 0 | M19: =if(OR(J19="Treinamento",J19="Pesquisa",J19="Desenvolvimento"),TRUE,FALSE) -> FALSE | N19: TRUE | O19: Parcial
C20: IRIS | D20: Configuração de dispositivo de acesso remoto | E20: Gabriel Alves Ferraz | F20: 132.105.086-07 | G20: 44958 | H20: 33 | I20: =H20/24 -> 1.375 | J20: Desenvolvimento | K20: Desenvolvimento IHM | L20: =iferror(if(and($M20=TRUE,$N20=TRUE),vlookup($E20,RH!$B$48:$S$70,month($G20)+6,false)*$H20,0),0) -> 731.07855 | M20: =if(OR(J20="Treinamento",J20="Pesquisa",J20="Desenvolvimento"),TRUE,FALSE) -> TRUE | N20: TRUE | O20: Parcial
C21: IRIS | D21: Configuração de dispositivo de acesso remoto | E21: Lucca Sardá Tonim Matos | F21: 123.342.589-70 | G21: 44958 | H21: 4.33 | I21: =H21/24 -> 0.18041667 | J21: Desenvolvimento | K21: Documentação | L21: =iferror(if(and($M21=TRUE,$N21=TRUE),vlookup($E21,RH!$B$48:$S$70,month($G21)+6,false)*$H21,0),0) -> 54.034242 | M21: =if(OR(J21="Treinamento",J21="Pesquisa",J21="Desenvolvimento"),TRUE,FALSE) -> TRUE | N21: TRUE | O21: Parcial
C22: IRIS | D22: Configuração de dispositivo de acesso remoto | E22: Eduardo Flohr | F22: 064.303.159-67 | G22: 44958 | H22: 6 | I22: =H22/24 -> 0.25 | J22: Gestão e outros | K22: Gestão | L22: =iferror(if(and($M22=TRUE,$N22=TRUE),vlookup($E22,RH!$B$48:$S$70,month($G22)+6,false)*$H22,0),0) -> 0 | M22: =if(OR(J22="Treinamento",J22="Pesquisa",J22="Desenvolvimento"),TRUE,FALSE) -> FALSE | N22: TRUE | O22: Parcial
C23: IRIS | D23: IRISV3 - Projetar novo sistema de automação | E23: Eduardo Flohr | F23: 064.303.159-67 | G23: 44958 | H23: 5 | I23: =H23/24 -> 0.20833333 | J23: Gestão e outros | K23: Gestão | L23: =iferror(if(and($M23=TRUE,$N23=TRUE),vlookup($E23,RH!$B$48:$S$70,month($G23)+6,false)*$H23,0),0) -> 0 | M23: =if(OR(J23="Treinamento",J23="Pesquisa",J23="Desenvolvimento"),TRUE,FALSE) -> FALSE | N23: TRUE | O23: Parcial
C24: IRIS | D24: IRISV3 - Projetar novo sistema de automação | E24: Johann Ribeiro | F24: 100.110.019-09 | G24: 44958 | H24: 24 | I24: =H24/24 -> 1 | J24: Desenvolvimento | K24: Documentação | L24: =iferror(if(and($M24=TRUE,$N24=TRUE),vlookup($E24,RH!$B$48:$S$70,month($G24)+6,false)*$H24,0),0) -> 299.49695 | M24: =if(OR(J24="Treinamento",J24="Pesquisa",J24="Desenvolvimento"),TRUE,FALSE) -> TRUE | N24: TRUE | O24: Parcial
C25: IRIS | D25: IRISV3 - Projetar novo sistema de automação | E25: Paulo Fernando Odwazny | F25: 035.705.119-01 | G25: 44958 | H25: 3 | I25: =H25/24 -> 0.125 | J25: Pesquisa | K25: Especificação da funcionalidade | L25: =iferror(if(and($M25=TRUE,$N25=TRUE),vlookup($E25,RH!$B$48:$S$70,month($G25)+6,false)*$H25,0),0) -> 320.4183 | M25: =if(OR(J25="Treinamento",J25="Pesquisa",J25="Desenvolvimento"),TRUE,FALSE) -> TRUE | N25: TRUE | O25: Parcial
C26: IRIS | D26: Aprimorar dados de processo | E26: Filipe Harbs | G26: 44986 | H26: 3.2 | I26: =H26/24 -> 0.13333333 | J26: Desenvolvimento | K26: Desenvolvimento IHM | L26: =iferror(if(and($M26=TRUE,$N26=TRUE),vlookup($E26,RH!$B$48:$S$70,month($G26)+6,false)*$H26,0),0) -> 121.71268 | M26: =if(OR(J26="Treinamento",J26="Pesquisa",J26="Desenvolvimento"),TRUE,FALSE) -> TRUE | N26: TRUE | O26: Parcial
C27: IRIS | D27: Aprimorar dados de processo | E27: Ivo Ersching | G27: 44986 | H27: 17.33 | I27: =H27/24 -> 0.72208333 | J27: Desenvolvimento | K27: Desenvolvimento PLC | L27: =iferror(if(and($M27=TRUE,$N27=TRUE),vlookup($E27,RH!$B$48:$S$70,month($G27)+6,false)*$H27,0),0) -> 977.53477 | M27: =if(OR(J27="Treinamento",J27="Pesquisa",J27="Desenvolvimento"),TRUE,FALSE) -> TRUE | N27: TRUE | O27: Parcial
C28: IRIS | D28: Aprimorar dados de processo | E28: Eduardo Flohr | F28: 064.303.159-67 | G28: 44986 | H28: 15 | I28: =H28/24 -> 0.625 | J28: Gestão e outros | L28: =iferror(if(and($M28=TRUE,$N28=TRUE),vlookup($E28,RH!$B$48:$S$70,month($G28)+6,false)*$H28,0),0) -> 0 | M28: =if(OR(J28="Treinamento",J28="Pesquisa",J28="Desenvolvimento"),TRUE,FALSE) -> FALSE | N28: TRUE | O28: Parcial
C29: IRIS | D29: Configuração de dispositivo de acesso remoto | E29: Gabriel Alves Ferraz | F29: 132.105.086-07 | G29: 44986 | H29: 30 | I29: =H29/24 -> 1.25 | J29: Desenvolvimento | K29: Desenvolvimento IHM | L29: =iferror(if(and($M29=TRUE,$N29=TRUE),vlookup($E29,RH!$B$48:$S$70,month($G29)+6,false)*$H29,0),0) -> 577.62371 | M29: =if(OR(J29="Treinamento",J29="Pesquisa",J29="Desenvolvimento"),TRUE,FALSE) -> TRUE | N29: TRUE | O29: Parcial
C30: IRIS | D30: Configuração de dispositivo de acesso remoto | E30: Lucca Sardá Tonim Matos | F30: 123.342.589-70 | G30: 44986 | H30: 15.75 | I30: =H30/24 -> 0.65625 | J30: Desenvolvimento | K30: Documentação | L30: =iferror(if(and($M30=TRUE,$N30=TRUE),vlookup($E30,RH!$B$48:$S$70,month($G30)+6,false)*$H30,0),0) -> 170.81869 | M30: =if(OR(J30="Treinamento",J30="Pesquisa",J30="Desenvolvimento"),TRUE,FALSE) -> TRUE | N30: TRUE | O30: Parcial
C31: IRIS | D31: Configuração de dispositivo de acesso remoto | E31: Eduardo Flohr | F31: 064.303.159-67 | G31: 44986 | H31: 17.5 | I31: =H31/24 -> 0.72916667 | J31: Gestão e outros | K31: Gestão | L31: =iferror(if(and($M31=TRUE,$N31=TRUE),vlookup($E31,RH!$B$48:$S$70,month($G31)+6,false)*$H31,0),0) -> 0 | M31: =if(OR(J31="Treinamento",J31="Pesquisa",J31="Desenvolvimento"),TRUE,FALSE) -> FALSE | N31: TRUE | O31: Parcial
C32: IRIS | D32: Criação de processo de liberação de versão | E32: Gabriel Alves Ferraz | F32: 132.105.086-07 | G32: 44986 | H32: 32.5 | I32: =H32/24 -> 1.3541667 | J32: Desenvolvimento | K32: Desenvolvimento IHM | L32: =iferror(if(and($M32=TRUE,$N32=TRUE),vlookup($E32,RH!$B$48:$S$70,month($G32)+6,false)*$H32,0),0) -> 625.75902 | M32: =if(OR(J32="Treinamento",J32="Pesquisa",J32="Desenvolvimento"),TRUE,FALSE) -> TRUE | N32: TRUE | O32: Parcial
C33: IRIS | D33: Criação de processo de liberação de versão | E33: Alexandre Baseggio | G33: 44986 | H33: 16.85 | I33: =H33/24 -> 0.70208333 | J33: Desenvolvimento | K33: Desenvolvimento PLC | L33: =iferror(if(and($M33=TRUE,$N33=TRUE),vlookup($E33,RH!$B$48:$S$70,month($G33)+6,false)*$H33,0),0) -> 811.01612 | M33: =if(OR(J33="Treinamento",J33="Pesquisa",J33="Desenvolvimento"),TRUE,FALSE) -> TRUE | N33: TRUE | O33: Parcial
C34: IRIS | D34: Criação de processo de liberação de versão | E34: Paulo Fernando Odwazny | F34: 035.705.119-01 | G34: 44986 | H34: 5.5 | I34: =H34/24 -> 0.22916667 | J34: Pesquisa | K34: Especificação da funcionalidade | L34: =iferror(if(and($M34=TRUE,$N34=TRUE),vlookup($E34,RH!$B$48:$S$70,month($G34)+6,false)*$H34,0),0) -> 510.5431 | M34: =if(OR(J34="Treinamento",J34="Pesquisa",J34="Desenvolvimento"),TRUE,FALSE) -> TRUE | N34: TRUE | O34: Parcial
C35: IRIS | D35: IRISV3 - Projetar novo sistema de automação | E35: Alexandre Baseggio | G35: 44986 | H35: 1.92 | I35: =H35/24 -> 0.08 | J35: Desenvolvimento | K35: Desenvolvimento PLC | L35: =iferror(if(and($M35=TRUE,$N35=TRUE),vlookup($E35,RH!$B$48:$S$70,month($G35)+6,false)*$H35,0),0) -> 92.412519 | M35: =if(OR(J35="Treinamento",J35="Pesquisa",J35="Desenvolvimento"),TRUE,FALSE) -> TRUE | N35: TRUE | O35: Parcial
C36: IRIS | D36: IRISV3 - Projetar novo sistema de automação | E36: Eduardo Flohr | F36: 064.303.159-67 | G36: 44986 | H36: 26.75 | I36: =H36/24 -> 1.1145833 | J36: Gestão e outros | K36: Gestão | L36: =iferror(if(and($M36=TRUE,$N36=TRUE),vlookup($E36,RH!$B$48:$S$70,month($G36)+6,false)*$H36,0),0) -> 0 | M36: =if(OR(J36="Treinamento",J36="Pesquisa",J36="Desenvolvimento"),TRUE,FALSE) -> FALSE | N36: TRUE | O36: Parcial
C37: IRIS | D37: IRISV3 - Projetar novo sistema de automação | E37: Johann Ribeiro | F37: 100.110.019-09 | G37: 44986 | H37: 86.58 | I37: =H37/24 -> 3.6075 | J37: Desenvolvimento | K37: Documentação | L37: =iferror(if(and($M37=TRUE,$N37=TRUE),vlookup($E37,RH!$B$48:$S$70,month($G37)+6,false)*$H37,0),0) -> 939.01474 | M37: =if(OR(J37="Treinamento",J37="Pesquisa",J37="Desenvolvimento"),TRUE,FALSE) -> TRUE | N37: TRUE | O37: Parcial
C38: IRIS | D38: IRISV3 - Projetar novo sistema de automação | E38: Paulo Fernando Odwazny | F38: 035.705.119-01 | G38: 44986 | H38: 61.98 | I38: =H38/24 -> 2.5825 | J38: Pesquisa | K38: Especificação da funcionalidade | L38: =iferror(if(and($M38=TRUE,$N38=TRUE),vlookup($E38,RH!$B$48:$S$70,month($G38)+6,false)*$H38,0),0) -> 5753.3566 | M38: =if(OR(J38="Treinamento",J38="Pesquisa",J38="Desenvolvimento"),TRUE,FALSE) -> TRUE | N38: TRUE | O38: Parcial
C39: IRIS | D39: Tradução da Interface para o idioma Estoniano | E39: Gabriel Alves Ferraz | F39: 132.105.086-07 | G39: 45017 | H39: 80.25 | I39: =H39/24 -> 3.34375 | J39: Desenvolvimento | K39: Desenvolvimento IHM | L39: =iferror(if(and($M39=TRUE,$N39=TRUE),vlookup($E39,RH!$B$48:$S$70,month($G39)+6,false)*$H39,0),0) -> 2124.3809 | M39: =if(OR(J39="Treinamento",J39="Pesquisa",J39="Desenvolvimento"),TRUE,FALSE) -> TRUE | N39: TRUE | O39: Parcial
C40: IRIS | D40: Tradução da Interface para o idioma Estoniano | E40: Lucca Sardá Tonim Matos | F40: 123.342.589-70 | G40: 45017 | H40: 15.58 | I40: =H40/24 -> 0.64916667 | J40: Desenvolvimento | K40: Documentação | L40: =iferror(if(and($M40=TRUE,$N40=TRUE),vlookup($E40,RH!$B$48:$S$70,month($G40)+6,false)*$H40,0),0) -> 232.31961 | M40: =if(OR(J40="Treinamento",J40="Pesquisa",J40="Desenvolvimento"),TRUE,FALSE) -> TRUE | N40: TRUE | O40: Parcial
C41: IRIS | D41: Tradução da Interface para o idioma Estoniano | E41: Johann Ribeiro | F41: 100.110.019-09 | G41: 45017 | H41: 25 | I41: =H41/24 -> 1.0416667 | J41: Desenvolvimento | K41: Documentação | L41: =iferror(if(and($M41=TRUE,$N41=TRUE),vlookup($E41,RH!$B$48:$S$70,month($G41)+6,false)*$H41,0),0) -> 372.78499 | M41: =if(OR(J41="Treinamento",J41="Pesquisa",J41="Desenvolvimento"),TRUE,FALSE) -> TRUE | N41: TRUE | O41: Parcial
C42: IRIS | D42: Tradução da Interface para o idioma Estoniano | E42: Eduardo Flohr | F42: 064.303.159-67 | G42: 45017 | H42: 16.58 | I42: =H42/24 -> 0.69083333 | J42: Gestão e outros | K42: Gestão | L42: =iferror(if(and($M42=TRUE,$N42=TRUE),vlookup($E42,RH!$B$48:$S$70,month($G42)+6,false)*$H42,0),0) -> 0 | M42: =if(OR(J42="Treinamento",J42="Pesquisa",J42="Desenvolvimento"),TRUE,FALSE) -> FALSE | N42: TRUE | O42: Parcial
C43: IRIS | D43: Alteração de UPS | E43: Ivo Ersching | G43: 45017 | H43: 25 | I43: =H43/24 -> 1.0416667 | J43: Desenvolvimento | K43: Desenvolvimento PLC | L43: =iferror(if(and($M43=TRUE,$N43=TRUE),vlookup($E43,RH!$B$48:$S$70,month($G43)+6,false)*$H43,0),0) -> 1938.8189 | M43: =if(OR(J43="Treinamento",J43="Pesquisa",J43="Desenvolvimento"),TRUE,FALSE) -> TRUE | N43: TRUE | O43: Parcial
C44: IRIS | D44: Alteração de UPS | E44: Eduardo Flohr | F44: 064.303.159-67 | G44: 45017 | H44: 10 | I44: =H44/24 -> 0.41666667 | J44: Gestão e outros | K44: Gestão | L44: =iferror(if(and($M44=TRUE,$N44=TRUE),vlookup($E44,RH!$B$48:$S$70,month($G44)+6,false)*$H44,0),0) -> 0 | M44: =if(OR(J44="Treinamento",J44="Pesquisa",J44="Desenvolvimento"),TRUE,FALSE) -> FALSE | N44: TRUE | O44: Parcial
C45: IRIS | D45: Alteração de UPS | E45: Filipe Harbs | G45: 45017 | H45: 1 | I45: =H45/24 -> 0.041666667 | J45: Desenvolvimento | K45: Desenvolvimento IHM | L45: =iferror(if(and($M45=TRUE,$N45=TRUE),vlookup($E45,RH!$B$48:$S$70,month($G45)+6,false)*$H45,0),0) -> 52.293705 | M45: =if(OR(J45="Treinamento",J45="Pesquisa",J45="Desenvolvimento"),TRUE,FALSE) -> TRUE | N45: TRUE | O45: Parcial
C46: IRIS | D46: Alteração de UPS | E46: Alexandre Baseggio | G46: 45017 | H46: 1.75 | I46: =H46/24 -> 0.072916667 | J46: Desenvolvimento | K46: Desenvolvimento PLC | L46: =iferror(if(and($M46=TRUE,$N46=TRUE),vlookup($E46,RH!$B$48:$S$70,month($G46)+6,false)*$H46,0),0) -> 115.80604 | M46: =if(OR(J46="Treinamento",J46="Pesquisa",J46="Desenvolvimento"),TRUE,FALSE) -> TRUE | N46: TRUE | O46: Parcial
C47: IRIS | D47: Alteração de UPS | E47: Marcos Tribess | G47: 45017 | H47: 7.75 | I47: =H47/24 -> 0.32291667 | J47: Desenvolvimento | K47: Desenvolvimento PLC | L47: =iferror(if(and($M47=TRUE,$N47=TRUE),vlookup($E47,RH!$B$48:$S$70,month($G47)+6,false)*$H47,0),0) -> 482.8533 | M47: =if(OR(J47="Treinamento",J47="Pesquisa",J47="Desenvolvimento"),TRUE,FALSE) -> TRUE | N47: TRUE | O47: Parcial
C48: IRIS | D48: Alteração de UPS | E48: Guilherme Jacques | G48: 45017 | H48: 5.3 | I48: =H48/24 -> 0.22083333 | J48: Desenvolvimento | K48: Desenvolvimento PLC | L48: =iferror(if(and($M48=TRUE,$N48=TRUE),vlookup($E48,RH!$B$48:$S$70,month($G48)+6,false)*$H48,0),0) -> 265.28282 | M48: =if(OR(J48="Treinamento",J48="Pesquisa",J48="Desenvolvimento"),TRUE,FALSE) -> TRUE | N48: TRUE | O48: Parcial
C49: IRIS | D49: Alteração de UPS | E49: Ricardo Bordin | G49: 45017 | H49: 5.67 | I49: =H49/24 -> 0.23625 | J49: Desenvolvimento | K49: Desenvolvimento PLC | L49: =iferror(if(and($M49=TRUE,$N49=TRUE),vlookup($E49,RH!$B$48:$S$70,month($G49)+6,false)*$H49,0),0) -> 283.80257 | M49: =if(OR(J49="Treinamento",J49="Pesquisa",J49="Desenvolvimento"),TRUE,FALSE) -> TRUE | N49: TRUE | O49: Parcial
C50: IRIS | D50: IRISV3 - Desenvolvimento de bilbioteca de objetos | E50: Eduardo Flohr | F50: 064.303.159-67 | G50: 45017 | H50: 28.17 | I50: =H50/24 -> 1.17375 | J50: Gestão e outros | K50: Gestão | L50: =iferror(if(and($M50=TRUE,$N50=TRUE),vlookup($E50,RH!$B$48:$S$70,month($G50)+6,false)*$H50,0),0) -> 0 | M50: =if(OR(J50="Treinamento",J50="Pesquisa",J50="Desenvolvimento"),TRUE,FALSE) -> FALSE | N50: TRUE | O50: Parcial
C51: IRIS | D51: IRISV3 - Desenvolvimento de bilbioteca de objetos | E51: Gabriel Oliveira | F51: 085.943.039-12 | G51: 45017 | H51: 54.28 | I51: =H51/24 -> 2.2616667 | J51: Desenvolvimento | K51: Desgin UX/UI | L51: =iferror(if(and($M51=TRUE,$N51=TRUE),vlookup($E51,RH!$B$48:$S$70,month($G51)+6,false)*$H51,0),0) -> 5188.4024 | M51: =if(OR(J51="Treinamento",J51="Pesquisa",J51="Desenvolvimento"),TRUE,FALSE) -> TRUE | N51: TRUE | O51: Parcial
C52: IRIS | D52: IRISV3 - Desenvolvimento de bilbioteca de objetos | E52: Filipe Harbs | G52: 45017 | H52: 42.83 | I52: =H52/24 -> 1.7845833 | J52: Desenvolvimento | K52: Desenvolvimento IHM | L52: =iferror(if(and($M52=TRUE,$N52=TRUE),vlookup($E52,RH!$B$48:$S$70,month($G52)+6,false)*$H52,0),0) -> 2239.7394 | M52: =if(OR(J52="Treinamento",J52="Pesquisa",J52="Desenvolvimento"),TRUE,FALSE) -> TRUE | N52: TRUE | O52: Parcial
C53: IRIS | D53: IRISV3 - Desenvolvimento de bilbioteca de objetos | E53: Ivo Ersching | G53: 45017 | H53: 19.5 | I53: =H53/24 -> 0.8125 | J53: Desenvolvimento | K53: Desenvolvimento PLC | L53: =iferror(if(and($M53=TRUE,$N53=TRUE),vlookup($E53,RH!$B$48:$S$70,month($G53)+6,false)*$H53,0),0) -> 1512.2787 | M53: =if(OR(J53="Treinamento",J53="Pesquisa",J53="Desenvolvimento"),TRUE,FALSE) -> TRUE | N53: TRUE | O53: Parcial
C54: IRIS | D54: IRISV3 - Desenvolvimento de bilbioteca de objetos | E54: Johann Ribeiro | F54: 100.110.019-09 | G54: 45017 | H54: 40.5 | I54: =H54/24 -> 1.6875 | J54: Desenvolvimento | K54: Documentação | L54: =iferror(if(and($M54=TRUE,$N54=TRUE),vlookup($E54,RH!$B$48:$S$70,month($G54)+6,false)*$H54,0),0) -> 603.91169 | M54: =if(OR(J54="Treinamento",J54="Pesquisa",J54="Desenvolvimento"),TRUE,FALSE) -> TRUE | N54: TRUE | O54: Parcial
C55: IRIS | D55: IRISV3 - Desenvolvimento de bilbioteca de objetos | E55: Marcos Tribess | G55: 45017 | H55: 3.25 | I55: =H55/24 -> 0.13541667 | J55: Desenvolvimento | K55: Desenvolvimento PLC | L55: =iferror(if(and($M55=TRUE,$N55=TRUE),vlookup($E55,RH!$B$48:$S$70,month($G55)+6,false)*$H55,0),0) -> 202.48687 | M55: =if(OR(J55="Treinamento",J55="Pesquisa",J55="Desenvolvimento"),TRUE,FALSE) -> TRUE | N55: TRUE | O55: Parcial
C56: IRIS | D56: IRISV3 - Desenvolvimento de bilbioteca de objetos | E56: Paulo Fernando Odwazny | F56: 035.705.119-01 | G56: 45017 | H56: 83.25 | I56: =H56/24 -> 3.46875 | J56: Pesquisa | K56: Especificação da funcionalidade | L56: =iferror(if(and($M56=TRUE,$N56=TRUE),vlookup($E56,RH!$B$48:$S$70,month($G56)+6,false)*$H56,0),0) -> 10624.721 | M56: =if(OR(J56="Treinamento",J56="Pesquisa",J56="Desenvolvimento"),TRUE,FALSE) -> TRUE | N56: TRUE | O56: Parcial
C57: IRIS | D57: Alteração de UPS | E57: Eduardo Flohr | F57: 064.303.159-67 | G57: 45047 | H57: 10 | I57: =H57/24 -> 0.41666667 | J57: Gestão e outros | K57: Gestão | L57: =iferror(if(and($M57=TRUE,$N57=TRUE),vlookup($E57,RH!$B$48:$S$70,month($G57)+6,false)*$H57,0),0) -> 0 | M57: =if(OR(J57="Treinamento",J57="Pesquisa",J57="Desenvolvimento"),TRUE,FALSE) -> FALSE | N57: TRUE | O57: Parcial
C58: IRIS | D58: Alteração de UPS | E58: Gabriel Alves Ferraz | F58: 132.105.086-07 | G58: 45047 | H58: 34 | I58: =H58/24 -> 1.4166667 | J58: Desenvolvimento | K58: Desenvolvimento IHM | L58: =iferror(if(and($M58=TRUE,$N58=TRUE),vlookup($E58,RH!$B$48:$S$70,month($G58)+6,false)*$H58,0),0) -> 691.35627 | M58: =if(OR(J58="Treinamento",J58="Pesquisa",J58="Desenvolvimento"),TRUE,FALSE) -> TRUE | N58: TRUE | O58: Parcial
C59: IRIS | D59: Alteração de UPS | E59: Guilherme Jacques | G59: 45047 | H59: 21.6 | I59: =H59/24 -> 0.9 | J59: Desenvolvimento | K59: Desenvolvimento PLC | L59: =iferror(if(and($M59=TRUE,$N59=TRUE),vlookup($E59,RH!$B$48:$S$70,month($G59)+6,false)*$H59,0),0) -> 830.46754 | M59: =if(OR(J59="Treinamento",J59="Pesquisa",J59="Desenvolvimento"),TRUE,FALSE) -> TRUE | N59: TRUE | O59: Parcial
C60: IRIS | D60: Alteração de UPS | E60: Ivo Ersching | G60: 45047 | H60: 4 | I60: =H60/24 -> 0.16666667 | J60: Desenvolvimento | K60: Desenvolvimento PLC | L60: =iferror(if(and($M60=TRUE,$N60=TRUE),vlookup($E60,RH!$B$48:$S$70,month($G60)+6,false)*$H60,0),0) -> 238.2829 | M60: =if(OR(J60="Treinamento",J60="Pesquisa",J60="Desenvolvimento"),TRUE,FALSE) -> TRUE | N60: TRUE | O60: Parcial
C61: IRIS | D61: IRISV3 - Desenvolvimento de bilbioteca de objetos | E61: Eduardo Flohr | F61: 064.303.159-67 | G61: 45047 | H61: 24.5 | I61: =H61/24 -> 1.0208333 | J61: Gestão e outros | K61: Gestão | L61: =iferror(if(and($M61=TRUE,$N61=TRUE),vlookup($E61,RH!$B$48:$S$70,month($G61)+6,false)*$H61,0),0) -> 0 | M61: =if(OR(J61="Treinamento",J61="Pesquisa",J61="Desenvolvimento"),TRUE,FALSE) -> FALSE | N61: TRUE | O61: Parcial
C62: IRIS | D62: IRISV3 - Desenvolvimento de bilbioteca de objetos | E62: Gabriel Oliveira | F62: 085.943.039-12 | G62: 45047 | H62: 202.6 | I62: =H62/24 -> 8.4416667 | J62: Desenvolvimento | K62: Desgin UX/UI | L62: =iferror(if(and($M62=TRUE,$N62=TRUE),vlookup($E62,RH!$B$48:$S$70,month($G62)+6,false)*$H62,0),0) -> 14875.408 | M62: =if(OR(J62="Treinamento",J62="Pesquisa",J62="Desenvolvimento"),TRUE,FALSE) -> TRUE | N62: TRUE | O62: Parcial
C63: IRIS | D63: IRISV3 - Desenvolvimento de bilbioteca de objetos | E63: Filipe Harbs | G63: 45047 | H63: 200.93 | I63: =H63/24 -> 8.3720833 | J63: Desenvolvimento | K63: Desenvolvimento IHM | L63: =iferror(if(and($M63=TRUE,$N63=TRUE),vlookup($E63,RH!$B$48:$S$70,month($G63)+6,false)*$H63,0),0) -> 8071.0464 | M63: =if(OR(J63="Treinamento",J63="Pesquisa",J63="Desenvolvimento"),TRUE,FALSE) -> TRUE | N63: TRUE | O63: Parcial
C64: IRIS | D64: IRISV3 - Desenvolvimento de bilbioteca de objetos | E64: Ivo Ersching | G64: 45047 | H64: 89.5 | I64: =H64/24 -> 3.7291667 | J64: Desenvolvimento | K64: Desenvolvimento PLC | L64: =iferror(if(and($M64=TRUE,$N64=TRUE),vlookup($E64,RH!$B$48:$S$70,month($G64)+6,false)*$H64,0),0) -> 5331.5799 | M64: =if(OR(J64="Treinamento",J64="Pesquisa",J64="Desenvolvimento"),TRUE,FALSE) -> TRUE | N64: TRUE | O64: Parcial
C65: IRIS | D65: IRISV3 - Desenvolvimento de bilbioteca de objetos | E65: Johann Ribeiro | F65: 100.110.019-09 | G65: 45047 | H65: 40.5 | I65: =H65/24 -> 1.6875 | J65: Desenvolvimento | K65: Documentação | L65: =iferror(if(and($M65=TRUE,$N65=TRUE),vlookup($E65,RH!$B$48:$S$70,month($G65)+6,false)*$H65,0),0) -> 463.88367 | M65: =if(OR(J65="Treinamento",J65="Pesquisa",J65="Desenvolvimento"),TRUE,FALSE) -> TRUE | N65: TRUE | O65: Parcial
C66: IRIS | D66: IRISV3 - Desenvolvimento de bilbioteca de objetos | E66: Lucca Sardá Tonim Matos | F66: 123.342.589-70 | G66: 45047 | H66: 0.25 | I66: =H66/24 -> 0.010416667 | J66: Desenvolvimento | K66: Documentação | L66: =iferror(if(and($M66=TRUE,$N66=TRUE),vlookup($E66,RH!$B$48:$S$70,month($G66)+6,false)*$H66,0),0) -> 2.8634794 | M66: =if(OR(J66="Treinamento",J66="Pesquisa",J66="Desenvolvimento"),TRUE,FALSE) -> TRUE | N66: TRUE | O66: Parcial
C67: IRIS | D67: IRISV3 - Desenvolvimento de bilbioteca de objetos | E67: Marcos Tribess | G67: 45047 | H67: 2.25 | I67: =H67/24 -> 0.09375 | J67: Desenvolvimento | K67: Desenvolvimento PLC | L67: =iferror(if(and($M67=TRUE,$N67=TRUE),vlookup($E67,RH!$B$48:$S$70,month($G67)+6,false)*$H67,0),0) -> 107.67916 | M67: =if(OR(J67="Treinamento",J67="Pesquisa",J67="Desenvolvimento"),TRUE,FALSE) -> TRUE | N67: TRUE | O67: Parcial
C68: IRIS | D68: IRISV3 - Desenvolvimento de bilbioteca de objetos | E68: Paulo Fernando Odwazny | F68: 035.705.119-01 | G68: 45047 | H68: 84.4 | I68: =H68/24 -> 3.5166667 | J68: Desenvolvimento | K68: Especificação da funcionalidade | L68: =iferror(if(and($M68=TRUE,$N68=TRUE),vlookup($E68,RH!$B$48:$S$70,month($G68)+6,false)*$H68,0),0) -> 8273.9216 | M68: =if(OR(J68="Treinamento",J68="Pesquisa",J68="Desenvolvimento"),TRUE,FALSE) -> TRUE | N68: TRUE | O68: Parcial
C69: IRIS | D69: Tradução da Interface para o idioma Italiano | E69: Eduardo Flohr | F69: 064.303.159-67 | G69: 45047 | H69: 8.75 | I69: =H69/24 -> 0.36458333 | J69: Desenvolvimento | K69: Gestão | L69: =iferror(if(and($M69=TRUE,$N69=TRUE),vlookup($E69,RH!$B$48:$S$70,month($G69)+6,false)*$H69,0),0) -> 857.78215 | M69: =if(OR(J69="Treinamento",J69="Pesquisa",J69="Desenvolvimento"),TRUE,FALSE) -> TRUE | N69: TRUE | O69: Parcial
C70: IRIS | D70: Tradução da Interface para o idioma Italiano | E70: Gabriel Alves Ferraz | F70: 132.105.086-07 | G70: 45047 | H70: 50 | I70: =H70/24 -> 2.0833333 | J70: Desenvolvimento | K70: Desenvolvimento IHM | L70: =iferror(if(and($M70=TRUE,$N70=TRUE),vlookup($E70,RH!$B$48:$S$70,month($G70)+6,false)*$H70,0),0) -> 1016.7004 | M70: =if(OR(J70="Treinamento",J70="Pesquisa",J70="Desenvolvimento"),TRUE,FALSE) -> TRUE | N70: TRUE | O70: Parcial
C71: IRIS | D71: Tradução da Interface para o idioma Italiano | E71: Johann Ribeiro | F71: 100.110.019-09 | G71: 45047 | H71: 49.33 | I71: =H71/24 -> 2.0554167 | J71: Desenvolvimento | K71: Documentação | L71: =iferror(if(and($M71=TRUE,$N71=TRUE),vlookup($E71,RH!$B$48:$S$70,month($G71)+6,false)*$H71,0),0) -> 565.02176 | M71: =if(OR(J71="Treinamento",J71="Pesquisa",J71="Desenvolvimento"),TRUE,FALSE) -> TRUE | N71: TRUE | O71: Parcial
C72: IRIS | D72: Tradução da Interface para o idioma Italiano | E72: Lucca Sardá Tonim Matos | F72: 123.342.589-70 | G72: 45047 | H72: 6.92 | I72: =H72/24 -> 0.28833333 | J72: Desenvolvimento | K72: Documentação | L72: =iferror(if(and($M72=TRUE,$N72=TRUE),vlookup($E72,RH!$B$48:$S$70,month($G72)+6,false)*$H72,0),0) -> 79.26111 | M72: =if(OR(J72="Treinamento",J72="Pesquisa",J72="Desenvolvimento"),TRUE,FALSE) -> TRUE | N72: TRUE | O72: Parcial
C73: IRIS | D73: Tradução da Interface para o idioma Italiano | E73: Marcos Tribess | G73: 45047 | H73: 5.75 | I73: =H73/24 -> 0.23958333 | J73: Desenvolvimento | K73: Desenvolvimento PLC | L73: =iferror(if(and($M73=TRUE,$N73=TRUE),vlookup($E73,RH!$B$48:$S$70,month($G73)+6,false)*$H73,0),0) -> 275.18008 | M73: =if(OR(J73="Treinamento",J73="Pesquisa",J73="Desenvolvimento"),TRUE,FALSE) -> TRUE | N73: TRUE | O73: Parcial
C74: IRIS | D74: IRISV3 - Desenvolvimento de bilbioteca de objetos | E74: Eduardo Flohr | F74: 064.303.159-67 | G74: 45078 | H74: 47.67 | I74: =H74/24 -> 1.98625 | J74: Gestão e outros | K74: Gestão | L74: =iferror(if(and($M74=TRUE,$N74=TRUE),vlookup($E74,RH!$B$48:$S$70,month($G74)+6,false)*$H74,0),0) -> 0 | M74: =if(OR(J74="Treinamento",J74="Pesquisa",J74="Desenvolvimento"),TRUE,FALSE) -> FALSE | N74: TRUE | O74: Parcial
C75: IRIS | D75: IRISV3 - Desenvolvimento de bilbioteca de objetos | E75: Gabriel Oliveira | F75: 085.943.039-12 | G75: 45078 | H75: 200.17 | I75: =H75/24 -> 8.3404167 | J75: Desenvolvimento | K75: Desgin UX/UI | L75: =iferror(if(and($M75=TRUE,$N75=TRUE),vlookup($E75,RH!$B$48:$S$70,month($G75)+6,false)*$H75,0),0) -> 15363.21 | M75: =if(OR(J75="Treinamento",J75="Pesquisa",J75="Desenvolvimento"),TRUE,FALSE) -> TRUE | N75: TRUE | O75: Parcial
C76: IRIS | D76: IRISV3 - Desenvolvimento de bilbioteca de objetos | E76: Filipe Harbs | G76: 45078 | H76: 233 | I76: =H76/24 -> 9.7083333 | J76: Desenvolvimento | K76: Desenvolvimento IHM | L76: =iferror(if(and($M76=TRUE,$N76=TRUE),vlookup($E76,RH!$B$48:$S$70,month($G76)+6,false)*$H76,0),0) -> 9783.5056 | M76: =if(OR(J76="Treinamento",J76="Pesquisa",J76="Desenvolvimento"),TRUE,FALSE) -> TRUE | N76: TRUE | O76: Parcial
C77: IRIS | D77: IRISV3 - Desenvolvimento de bilbioteca de objetos | E77: Ivo Ersching | G77: 45078 | H77: 121.17 | I77: =H77/24 -> 5.04875 | J77: Desenvolvimento | K77: Desenvolvimento PLC | L77: =iferror(if(and($M77=TRUE,$N77=TRUE),vlookup($E77,RH!$B$48:$S$70,month($G77)+6,false)*$H77,0),0) -> 7545.3868 | M77: =if(OR(J77="Treinamento",J77="Pesquisa",J77="Desenvolvimento"),TRUE,FALSE) -> TRUE | N77: TRUE | O77: Parcial
C78: IRIS | D78: IRISV3 - Desenvolvimento de bilbioteca de objetos | E78: Johann Ribeiro | F78: 100.110.019-09 | G78: 45078 | H78: 123 | I78: =H78/24 -> 5.125 | J78: Desenvolvimento | K78: Documentação | L78: =iferror(if(and($M78=TRUE,$N78=TRUE),vlookup($E78,RH!$B$48:$S$70,month($G78)+6,false)*$H78,0),0) -> 1472.6946 | M78: =if(OR(J78="Treinamento",J78="Pesquisa",J78="Desenvolvimento"),TRUE,FALSE) -> TRUE | N78: TRUE | O78: Parcial
C79: IRIS | D79: IRISV3 - Desenvolvimento de bilbioteca de objetos | E79: Lucca Sardá Tonim Matos | F79: 123.342.589-70 | G79: 45078 | H79: 25.5 | I79: =H79/24 -> 1.0625 | J79: Desenvolvimento | K79: Documentação | L79: =iferror(if(and($M79=TRUE,$N79=TRUE),vlookup($E79,RH!$B$48:$S$70,month($G79)+6,false)*$H79,0),0) -> 305.31473 | M79: =if(OR(J79="Treinamento",J79="Pesquisa",J79="Desenvolvimento"),TRUE,FALSE) -> TRUE | N79: TRUE | O79: Parcial
C80: IRIS | D80: IRISV3 - Desenvolvimento de bilbioteca de objetos | E80: Rafael Augusto Barbieri Lobato | G80: 45078 | H80: 77.15 | I80: =H80/24 -> 3.2145833 | J80: Desenvolvimento | K80: Desenvolvimento IHM | L80: =iferror(if(and($M80=TRUE,$N80=TRUE),vlookup($E80,RH!$B$48:$S$70,month($G80)+6,false)*$H80,0),0) -> 1639.8814 | M80: =if(OR(J80="Treinamento",J80="Pesquisa",J80="Desenvolvimento"),TRUE,FALSE) -> TRUE | N80: TRUE | O80: Parcial
C81: IRIS | D81: Unificação de software p/ Rockwell | E81: Alexandre Baseggio | G81: 45078 | H81: 21.3 | I81: =H81/24 -> 0.8875 | J81: Desenvolvimento | K81: Desenvolvimento PLC | L81: =iferror(if(and($M81=TRUE,$N81=TRUE),vlookup($E81,RH!$B$48:$S$70,month($G81)+6,false)*$H81,0),0) -> 1131.7798 | M81: =if(OR(J81="Treinamento",J81="Pesquisa",J81="Desenvolvimento"),TRUE,FALSE) -> TRUE | N81: TRUE | O81: Parcial
C82: IRIS | D82: Unificação de software p/ Rockwell | E82: Eduardo Flohr | F82: 064.303.159-67 | G82: 45078 | H82: 7.25 | I82: =H82/24 -> 0.30208333 | J82: Gestão e outros | K82: Gestão | L82: =iferror(if(and($M82=TRUE,$N82=TRUE),vlookup($E82,RH!$B$48:$S$70,month($G82)+6,false)*$H82,0),0) -> 0 | M82: =if(OR(J82="Treinamento",J82="Pesquisa",J82="Desenvolvimento"),TRUE,FALSE) -> FALSE | N82: TRUE | O82: Parcial
C83: IRIS | D83: Unificação de software p/ Rockwell | E83: Gabriel Alves Ferraz | F83: 132.105.086-07 | G83: 45078 | H83: 32 | I83: =H83/24 -> 1.3333333 | J83: Desenvolvimento | K83: Desenvolvimento IHM | L83: =iferror(if(and($M83=TRUE,$N83=TRUE),vlookup($E83,RH!$B$48:$S$70,month($G83)+6,false)*$H83,0),0) -> 680.18411 | M83: =if(OR(J83="Treinamento",J83="Pesquisa",J83="Desenvolvimento"),TRUE,FALSE) -> TRUE | N83: TRUE | O83: Parcial
C84: IRIS | D84: Unificação de software p/ Rockwell | E84: Johann Ribeiro | F84: 100.110.019-09 | G84: 45078 | H84: 3 | I84: =H84/24 -> 0.125 | J84: Desenvolvimento | K84: Documentação | L84: =iferror(if(and($M84=TRUE,$N84=TRUE),vlookup($E84,RH!$B$48:$S$70,month($G84)+6,false)*$H84,0),0) -> 35.91938 | M84: =if(OR(J84="Treinamento",J84="Pesquisa",J84="Desenvolvimento"),TRUE,FALSE) -> TRUE | N84: TRUE | O84: Parcial
C85: IRIS | D85: Unificação de software p/ Rockwell | E85: Eduardo Flohr | F85: 064.303.159-67 | G85: 45108 | H85: 8 | I85: =H85/24 -> 0.33333333 | J85: Gestão e outros | K85: Gestão | L85: =iferror(if(and($M85=TRUE,$N85=TRUE),vlookup($E85,RH!$B$48:$S$70,month($G85)+6,false)*$H85,0),0) -> 0 | M85: =if(OR(J85="Treinamento",J85="Pesquisa",J85="Desenvolvimento"),TRUE,FALSE) -> FALSE | N85: TRUE | O85: Parcial
C86: IRIS | D86: Unificação de software p/ Rockwell | E86: Gabriel Alves Ferraz | F86: 132.105.086-07 | G86: 45108 | H86: 14 | I86: =H86/24 -> 0.58333333 | J86: Desenvolvimento | K86: Desenvolvimento IHM | L86: =iferror(if(and($M86=TRUE,$N86=TRUE),vlookup($E86,RH!$B$48:$S$70,month($G86)+6,false)*$H86,0),0) -> 332.17221 | M86: =if(OR(J86="Treinamento",J86="Pesquisa",J86="Desenvolvimento"),TRUE,FALSE) -> TRUE | N86: TRUE | O86: Parcial
C87: IRIS | D87: Unificação de software p/ Rockwell | E87: Ivo Ersching | G87: 45108 | H87: 2 | I87: =H87/24 -> 0.083333333 | J87: Desenvolvimento | K87: Desenvolvimento PLC | L87: =iferror(if(and($M87=TRUE,$N87=TRUE),vlookup($E87,RH!$B$48:$S$70,month($G87)+6,false)*$H87,0),0) -> 129.92466 | M87: =if(OR(J87="Treinamento",J87="Pesquisa",J87="Desenvolvimento"),TRUE,FALSE) -> TRUE | N87: TRUE | O87: Parcial
C88: IRIS | D88: Unificação de software p/ Rockwell | E88: Johann Ribeiro | F88: 100.110.019-09 | G88: 45108 | H88: 18 | I88: =H88/24 -> 0.75 | J88: Desenvolvimento | K88: Documentação | L88: =iferror(if(and($M88=TRUE,$N88=TRUE),vlookup($E88,RH!$B$48:$S$70,month($G88)+6,false)*$H88,0),0) -> 224.83053 | M88: =if(OR(J88="Treinamento",J88="Pesquisa",J88="Desenvolvimento"),TRUE,FALSE) -> TRUE | N88: TRUE | O88: Parcial
C89: IRIS | D89: Unificação de software p/ Rockwell | E89: Marcos Tribess | G89: 45108 | H89: 29.75 | I89: =H89/24 -> 1.2395833 | J89: Desenvolvimento | K89: Desenvolvimento PLC | L89: =iferror(if(and($M89=TRUE,$N89=TRUE),vlookup($E89,RH!$B$48:$S$70,month($G89)+6,false)*$H89,0),0) -> 1696.1139 | M89: =if(OR(J89="Treinamento",J89="Pesquisa",J89="Desenvolvimento"),TRUE,FALSE) -> TRUE | N89: TRUE | O89: Parcial
C90: IRIS | D90: IRIS V3 - Controle de receita avançado | E90: Eduardo Flohr | F90: 064.303.159-67 | G90: 45108 | H90: 31.5 | I90: =H90/24 -> 1.3125 | J90: Gestão e outros | K90: Gestão | L90: =iferror(if(and($M90=TRUE,$N90=TRUE),vlookup($E90,RH!$B$48:$S$70,month($G90)+6,false)*$H90,0),0) -> 0 | M90: =if(OR(J90="Treinamento",J90="Pesquisa",J90="Desenvolvimento"),TRUE,FALSE) -> FALSE | N90: TRUE | O90: Parcial
C91: IRIS | D91: IRIS V3 - Controle de receita avançado | E91: Gabriel Oliveira | F91: 085.943.039-12 | G91: 45108 | H91: 159.92 | I91: =H91/24 -> 6.6633333 | J91: Desenvolvimento | K91: Desgin UX/UI | L91: =iferror(if(and($M91=TRUE,$N91=TRUE),vlookup($E91,RH!$B$48:$S$70,month($G91)+6,false)*$H91,0),0) -> 12804.451 | M91: =if(OR(J91="Treinamento",J91="Pesquisa",J91="Desenvolvimento"),TRUE,FALSE) -> TRUE | N91: TRUE | O91: Parcial
C92: IRIS | D92: IRIS V3 - Controle de receita avançado | E92: Filipe Harbs | G92: 45108 | H92: 235.17 | I92: =H92/24 -> 9.79875 | J92: Desenvolvimento | K92: Desenvolvimento IHM | L92: =iferror(if(and($M92=TRUE,$N92=TRUE),vlookup($E92,RH!$B$48:$S$70,month($G92)+6,false)*$H92,0),0) -> 11127.552 | M92: =if(OR(J92="Treinamento",J92="Pesquisa",J92="Desenvolvimento"),TRUE,FALSE) -> TRUE | N92: TRUE | O92: Parcial
C93: IRIS | D93: IRIS V3 - Controle de receita avançado | E93: Ivo Ersching | G93: 45108 | H93: 170.3 | I93: =H93/24 -> 7.0958333 | J93: Desenvolvimento | K93: Desenvolvimento PLC | L93: =iferror(if(and($M93=TRUE,$N93=TRUE),vlookup($E93,RH!$B$48:$S$70,month($G93)+6,false)*$H93,0),0) -> 11063.085 | M93: =if(OR(J93="Treinamento",J93="Pesquisa",J93="Desenvolvimento"),TRUE,FALSE) -> TRUE | N93: TRUE | O93: Parcial
C94: IRIS | D94: IRIS V3 - Controle de receita avançado | E94: Johann Ribeiro | F94: 100.110.019-09 | G94: 45108 | H94: 39 | I94: =H94/24 -> 1.625 | J94: Desenvolvimento | K94: Documentação | L94: =iferror(if(and($M94=TRUE,$N94=TRUE),vlookup($E94,RH!$B$48:$S$70,month($G94)+6,false)*$H94,0),0) -> 487.13281 | M94: =if(OR(J94="Treinamento",J94="Pesquisa",J94="Desenvolvimento"),TRUE,FALSE) -> TRUE | N94: TRUE | O94: Parcial
C95: IRIS | D95: IRIS V3 - Controle de receita avançado | E95: Paulo Fernando Odwazny | F95: 035.705.119-01 | G95: 45108 | H95: 32.5 | I95: =H95/24 -> 1.3541667 | J95: Pesquisa | K95: Especificação da funcionalidade | L95: =iferror(if(and($M95=TRUE,$N95=TRUE),vlookup($E95,RH!$B$48:$S$70,month($G95)+6,false)*$H95,0),0) -> 3474.4097 | M95: =if(OR(J95="Treinamento",J95="Pesquisa",J95="Desenvolvimento"),TRUE,FALSE) -> TRUE | N95: TRUE | O95: Parcial
C96: IRIS | D96: IRIS V3 - Controle de receita avançado | E96: Rafael Augusto Barbieri Lobato | G96: 45108 | H96: 157 | I96: =H96/24 -> 6.5416667 | J96: Desenvolvimento | K96: Desenvolvimento IHM | L96: =iferror(if(and($M96=TRUE,$N96=TRUE),vlookup($E96,RH!$B$48:$S$70,month($G96)+6,false)*$H96,0),0) -> 3481.3794 | M96: =if(OR(J96="Treinamento",J96="Pesquisa",J96="Desenvolvimento"),TRUE,FALSE) -> TRUE | N96: TRUE | O96: Parcial
C97: IRIS | D97: Refatoração dos scripts p/ C# | E97: Eduardo Flohr | F97: 064.303.159-67 | G97: 45139 | H97: 31 | I97: =H97/24 -> 1.2916667 | J97: Gestão e outros | K97: Gestão | L97: =iferror(if(and($M97=TRUE,$N97=TRUE),vlookup($E97,RH!$B$48:$S$70,month($G97)+6,false)*$H97,0),0) -> 0 | M97: =if(OR(J97="Treinamento",J97="Pesquisa",J97="Desenvolvimento"),TRUE,FALSE) -> FALSE | N97: TRUE | O97: Parcial
C98: IRIS | D98: Refatoração dos scripts p/ C# | E98: Gabriel Alves Ferraz | F98: 132.105.086-07 | G98: 45139 | H98: 11.08 | I98: =H98/24 -> 0.46166667 | J98: Desenvolvimento | K98: Desenvolvimento IHM | L98: =iferror(if(and($M98=TRUE,$N98=TRUE),vlookup($E98,RH!$B$48:$S$70,month($G98)+6,false)*$H98,0),0) -> 230.40822 | M98: =if(OR(J98="Treinamento",J98="Pesquisa",J98="Desenvolvimento"),TRUE,FALSE) -> TRUE | N98: TRUE | O98: Parcial
C99: IRIS | D99: Refatoração dos scripts p/ C# | E99: Guilherme Jacques | G99: 45139 | H99: 30 | I99: =H99/24 -> 1.25 | J99: Desenvolvimento | K99: Desenvolvimento PLC | L99: =iferror(if(and($M99=TRUE,$N99=TRUE),vlookup($E99,RH!$B$48:$S$70,month($G99)+6,false)*$H99,0),0) -> 1102.4067 | M99: =if(OR(J99="Treinamento",J99="Pesquisa",J99="Desenvolvimento"),TRUE,FALSE) -> TRUE | N99: TRUE | O99: Parcial
C100: IRIS | D100: IRIS V3 - Operação por lotes com controle de receita avançado | E100: Eduardo Flohr | F100: 064.303.159-67 | G100: 45139 | H100: 48.25 | I100: =H100/24 -> 2.0104167 | J100: Gestão e outros | K100: Gestão | L100: =iferror(if(and($M100=TRUE,$N100=TRUE),vlookup($E100,RH!$B$48:$S$70,month($G100)+6,false)*$H100,0),0) -> 0 | M100: =if(OR(J100="Treinamento",J100="Pesquisa",J100="Desenvolvimento"),TRUE,FALSE) -> FALSE | N100: TRUE | O100: Parcial
C101: IRIS | D101: IRIS V3 - Operação por lotes com controle de receita avançado | E101: Gabriel Oliveira | F101: 085.943.039-12 | G101: 45139 | H101: 179.42 | I101: =H101/24 -> 7.4758333 | J101: Desenvolvimento | K101: Desgin UX/UI | L101: =iferror(if(and($M101=TRUE,$N101=TRUE),vlookup($E101,RH!$B$48:$S$70,month($G101)+6,false)*$H101,0),0) -> 12590.761 | M101: =if(OR(J101="Treinamento",J101="Pesquisa",J101="Desenvolvimento"),TRUE,FALSE) -> TRUE | N101: TRUE | O101: Parcial
C102: IRIS | D102: IRIS V3 - Operação por lotes com controle de receita avançado | E102: Filipe Harbs | G102: 45139 | H102: 240.8 | I102: =H102/24 -> 10.033333 | J102: Desenvolvimento | K102: Desenvolvimento IHM | L102: =iferror(if(and($M102=TRUE,$N102=TRUE),vlookup($E102,RH!$B$48:$S$70,month($G102)+6,false)*$H102,0),0) -> 9986.1289 | M102: =if(OR(J102="Treinamento",J102="Pesquisa",J102="Desenvolvimento"),TRUE,FALSE) -> TRUE | N102: TRUE | O102: Parcial
...

Sheet Tabela dinâmica 1

Sheet RH
B2: NETZSCH
B3: Pesquisa ,Desenvolvimento & Inovação
B4: Formulário de PD&I - Ano 2022
B5: -preencher somente os campos sombreados (cinza)
B8: Dossiê do projeto
B9: Cálculo de custo - Pessoal
B11: Salário bruto | T11: =(U11/12)*24 -> 183.33333 | U11: =(SUM(H47:S47)*8.8)/24 -> 91.666667
B12: Nome Completo | C12: CPF | D12: notas | E12: Cargo/função | F12: Formação | G12: Attachments | H12: Salário 01 | I12: Salário 02 | J12: Salário 03 | K12: Salário 04 | L12: Salário 05 | M12: Salário 06 | N12: Salário 07 | O12: Salário 08 | P12: Salário 09 | Q12: Salário 10 | R12: Salário 11 | S12: Salário 12 | T12: PD&I time | U12: PD&I (%) | V12: Classificação | W12: Pesquisador
B13: Alberto Reuters | C13: 041.176.229-00 | E13: Gerente Desenv. Soft/Automação | F13: Mestrado | H13: 14837.22 | I13: 14837.22 | J13: 14837.22 | K13: 14837.22 | L13: 14837.22 | M13: 14837.22 | N13: 14837.22 | O13: 14837.22 | P13: 14837.22 | Q13: 24932.42 | R13: 26213.95 | S13: 26213.95 | T13: =IFERROR(__xludf.DUMMYFUNCTION("IFERROR(if(W13=true, SUM(FILTER('Resumo - TIMESHEETS'!$H:$H,'Resumo - TIMESHEETS'!M:M = TRUE,'Resumo - TIMESHEETS'!N:N = TRUE,'Resumo - TIMESHEETS'!E:E = B13))/24,0),0)"),0.0) -> 0 | U13: =T13/$U$11 -> 0 | V13: =IF(U13<80%,"Parcial","Exclusivo") -> Parcial | W13: TRUE
B14: Alexandre Baseggio | C14: 020.066.430-10 | E14: Analista de Automação | F14: Superior Completo | H14: 6923.08 | I14: 6923.08 | J14: 6923.08 | K14: 6923.08 | L14: 6923.08 | M14: 6923.08 | N14: 6923.08 | O14: 6923.08 | P14: 6923.08 | Q14: 6923.08 | R14: 7278.93 | S14: 7278.93 | T14: =IFERROR(__xludf.DUMMYFUNCTION("IFERROR(if(W14=true, SUM(FILTER('Resumo - TIMESHEETS'!$H:$H,'Resumo - TIMESHEETS'!M:M = TRUE,'Resumo - TIMESHEETS'!N:N = TRUE,'Resumo - TIMESHEETS'!E:E = B14))/24,0),0)"),2.56625) -> 2.56625 | U14: =T14/$U$11 -> 0.027995455 | V14: =IF(U14<80%,"Parcial","Exclusivo") -> Parcial | W14: TRUE
B15: Arthur Muniz | C15: 037.196.611-64 | E15: Desenvolvedor de Software | F15: Superior Completo | H15: 11291.29 | I15: 11291.29 | J15: 11291.29 | K15: 11291.29 | L15: 11291.29 | M15: 11291.29 | N15: 11868.23 | O15: 11868.23 | P15: 11868.23 | Q15: 11868.23 | R15: 12478.26 | S15: 12478.26 | T15: =IFERROR(__xludf.DUMMYFUNCTION("IFERROR(if(W15=true, SUM(FILTER('Resumo - TIMESHEETS'!$H:$H,'Resumo - TIMESHEETS'!M:M = TRUE,'Resumo - TIMESHEETS'!N:N = TRUE,'Resumo - TIMESHEETS'!E:E = B15))/24,0),0)"),81.08333333333333) -> 81.083333 | U15: =T15/$U$11 -> 0.88454545 | V15: =IF(U15<80%,"Parcial","Exclusivo") -> Exclusivo | W15: TRUE
B16: Bruno katzjarowksi | C16: 080.850.859-84 | E16: Desenvolvedor de Software | F16: Superior Completo | H16: 14024.96 | I16: 14024.96 | J16: 14024.96 | K16: 14024.96 | L16: 14024.96 | M16: 14024.96 | N16: 14300 | O16: 14300 | P16: 14300 | Q16: 14300 | R16: 15035.02 | S16: 15035.02 | T16: =IFERROR(__xludf.DUMMYFUNCTION("IFERROR(if(W16=true, SUM(FILTER('Resumo - TIMESHEETS'!$H:$H,'Resumo - TIMESHEETS'!M:M = TRUE,'Resumo - TIMESHEETS'!N:N = TRUE,'Resumo - TIMESHEETS'!E:E = B16))/24,0),0)"),88.33333333333333) -> 88.333333 | U16: =T16/$U$11 -> 0.96363636 | V16: =IF(U16<80%,"Parcial","Exclusivo") -> Exclusivo | W16: TRUE
B17: Cleiton Capristano | C17: 068.504.079-88 | E17: Desenvolvedor de Software | F17: Superior Completo | H17: 12500 | I17: 12500 | J17: 12500 | K17: 12500 | L17: 12500 | M17: 12500 | N17: 12500 | O17: 12629.01 | P17: 12629.01 | Q17: 12629.01 | R17: 13278.15 | S17: 13278.15 | T17: =IFERROR(__xludf.DUMMYFUNCTION("IFERROR(if(W17=true, SUM(FILTER('Resumo - TIMESHEETS'!$H:$H,'Resumo - TIMESHEETS'!M:M = TRUE,'Resumo - TIMESHEETS'!N:N = TRUE,'Resumo - TIMESHEETS'!E:E = B17))/24,0),0)"),95.625) -> 95.625 | U17: =T17/$U$11 -> 1.0431818 | V17: =IF(U17<80%,"Parcial","Exclusivo") -> Exclusivo | W17: TRUE
B18: Eduardo Flohr | C18: 064.303.159-67 | E18: Supervisor Automação | F18: Superior Completo | H18: 13351.79 | I18: 13351.79 | J18: 13351.79 | K18: 13351.79 | L18: 13351.79 | M18: 13351.79 | N18: 13351.79 | O18: 13351.79 | P18: 13351.79 | Q18: 18013.96 | R18: 18939.88 | S18: 18939.88 | T18: =IFERROR(__xludf.DUMMYFUNCTION("IFERROR(if(W18=true, SUM(FILTER('Resumo - TIMESHEETS'!$H:$H,'Resumo - TIMESHEETS'!M:M = TRUE,'Resumo - TIMESHEETS'!N:N = TRUE,'Resumo - TIMESHEETS'!E:E = B18))/24,0),0)"),5.53125) -> 5.53125 | U18: =T18/$U$11 -> 0.060340909 | V18: =IF(U18<80%,"Parcial","Exclusivo") -> Parcial | W18: TRUE
B19: Fernando Leal | C19: Bolsista | T19: =IFERROR(__xludf.DUMMYFUNCTION("IFERROR(if(W19=true, SUM(FILTER('Resumo - TIMESHEETS'!$H:$H,'Resumo - TIMESHEETS'!M:M = TRUE,'Resumo - TIMESHEETS'!N:N = TRUE,'Resumo - TIMESHEETS'!E:E = B19))/24,0),0)"),0.0) -> 0 | U19: =T19/$U$11 -> 0 | V19: =IF(U19<80%,"Parcial","Exclusivo") -> Parcial | W19: FALSE
B20: Filipe Harbs | C20: 087.609.209-12 | E20: Analista de Automação | F20: Técnico | H20: 5470.86 | I20: 5470.86 | J20: 5470.86 | K20: 5470.86 | L20: 5470.86 | M20: 5470.86 | N20: 5909.62 | O20: 5909.62 | P20: 5909.62 | Q20: 5909.62 | R20: 6213.38 | S20: 6213.38 | T20: =IFERROR(__xludf.DUMMYFUNCTION("IFERROR(if(W20=true, SUM(FILTER('Resumo - TIMESHEETS'!$H:$H,'Resumo - TIMESHEETS'!M:M = TRUE,'Resumo - TIMESHEETS'!N:N = TRUE,'Resumo - TIMESHEETS'!E:E = B20))/24,0),0)"),63.09625) -> 63.09625 | U20: =T20/$U$11 -> 0.68832273 | V20: =IF(U20<80%,"Parcial","Exclusivo") -> Parcial | W20: TRUE
B21: Gabriel Alves Ferraz | C21: 132.105.086-07 | E21: Analista de Automação | F21: Superior Completo | H21: 2769.45 | I21: 2769.45 | J21: 2769.45 | K21: 2769.45 | L21: 2769.45 | M21: 2769.45 | N21: 2963.31 | O21: 2963.31 | P21: 2963.31 | Q21: 2963.31 | R21: 3115.63 | S21: 3115.63 | T21: =IFERROR(__xludf.DUMMYFUNCTION("IFERROR(if(W21=true, SUM(FILTER('Resumo - TIMESHEETS'!$H:$H,'Resumo - TIMESHEETS'!M:M = TRUE,'Resumo - TIMESHEETS'!N:N = TRUE,'Resumo - TIMESHEETS'!E:E = B21))/24,0),0)"),20.992916666666666) -> 20.992917 | U21: =T21/$U$11 -> 0.22901364 | V21: =IF(U21<80%,"Parcial","Exclusivo") -> Parcial | W21: TRUE
B22: Gabriel Oliveira | C22: 085.943.039-12 | E22: UX/UI Designer | F22: Superior Completo | H22: 0 | I22: 0 | J22: 0 | K22: 10000 | L22: 10000 | M22: 10000 | N22: 10000 | O22: 10000 | P22: 10000 | Q22: 10000 | R22: 10514 | S22: 10514 | T22: =IFERROR(__xludf.DUMMYFUNCTION("IFERROR(if(W22=true, SUM(FILTER('Resumo - TIMESHEETS'!$H:$H,'Resumo - TIMESHEETS'!M:M = TRUE,'Resumo - TIMESHEETS'!N:N = TRUE,'Resumo - TIMESHEETS'!E:E = B22))/24,0),0)"),63.04749999999999) -> 63.0475 | U22: =T22/$U$11 -> 0.68779091 | V22: =IF(U22<80%,"Parcial","Exclusivo") -> Parcial | W22: TRUE
B23: Gabriel Possamai | C23: 085.815.809-47 | E23: Desenvolvedor de Software | F23: Superior Completo | H23: 14856.95 | I23: 14856.95 | J23: 14856.95 | K23: 14856.95 | L23: 14856.95 | M23: 14856.95 | N23: 15216.66 | O23: 15216.66 | P23: 15216.66 | Q23: 15216.66 | R23: 15998.8 | S23: 15998.8 | T23: =IFERROR(__xludf.DUMMYFUNCTION("IFERROR(if(W23=true, SUM(FILTER('Resumo - TIMESHEETS'!$H:$H,'Resumo - TIMESHEETS'!M:M = TRUE,'Resumo - TIMESHEETS'!N:N = TRUE,'Resumo - TIMESHEETS'!E:E = B23))/24,0),0)"),81.875) -> 81.875 | U23: =T23/$U$11 -> 0.89318182 | V23: =IF(U23<80%,"Parcial","Exclusivo") -> Exclusivo | W23: TRUE
B24: Guilherme Jacques | C24: 085.705.039-70 | E24: Analista de Automação | F24: Técnico | H24: 0 | I24: 0 | J24: 0 | K24: 5236.48 | L24: 5236.48 | M24: 5236.48 | N24: 5236.48 | O24: 5236.48 | P24: 5236.48 | Q24: 5236.48 | R24: 5505.64 | S24: 5505.64 | T24: =IFERROR(__xludf.DUMMYFUNCTION("IFERROR(if(W24=true, SUM(FILTER('Resumo - TIMESHEETS'!$H:$H,'Resumo - TIMESHEETS'!M:M = TRUE,'Resumo - TIMESHEETS'!N:N = TRUE,'Resumo - TIMESHEETS'!E:E = B24))/24,0),0)"),2.966666666666667) -> 2.9666667 | U24: =T24/$U$11 -> 0.032363636 | V24: =IF(U24<80%,"Parcial","Exclusivo") -> Parcial | W24: TRUE
B25: Italo Ebel | C25: 534.546.398-08 | E25: Estagiário | F25: Técnico | H25: 0 | I25: 0 | J25: 0 | K25: 0 | L25: 0 | M25: 0 | N25: 0 | O25: 1560 | P25: 1560 | Q25: 1560 | R25: 1641 | S25: 1641 | T25: =IFERROR(__xludf.DUMMYFUNCTION("IFERROR(if(W25=true, SUM(FILTER('Resumo - TIMESHEETS'!$H:$H,'Resumo - TIMESHEETS'!M:M = TRUE,'Resumo - TIMESHEETS'!N:N = TRUE,'Resumo - TIMESHEETS'!E:E = B25))/24,0),0)"),11.479166666666666) -> 11.479167 | U25: =T25/$U$11 -> 0.12522727 | V25: =IF(U25<80%,"Parcial","Exclusivo") -> Parcial | W25: TRUE
B26: Ivo Ersching | C26: 052.208.059-67 | E26: Analista de Automação | F26: Superior Completo | H26: 8113.41 | I26: 8113.41 | J26: 8113.41 | K26: 8113.41 | L26: 8113.41 | M26: 8113.41 | N26: 8113.41 | O26: 8113.41 | P26: 8113.41 | Q26: 8113.41 | R26: 8530.44 | S26: 8530.44 | T26: =IFERROR(__xludf.DUMMYFUNCTION("IFERROR(if(W26=true, SUM(FILTER('Resumo - TIMESHEETS'!$H:$H,'Resumo - TIMESHEETS'!M:M = TRUE,'Resumo - TIMESHEETS'!N:N = TRUE,'Resumo - TIMESHEETS'!E:E = B26))/24,0),0)"),44.840833333333336) -> 44.840833 | U26: =T26/$U$11 -> 0.48917273 | V26: =IF(U26<80%,"Parcial","Exclusivo") -> Parcial | W26: TRUE
B27: Jivago Rusch | C27: 091.530.489-97 | E27: Projetista Industrial | F27: Superior Completo | H27: 5971.56 | I27: 6518.08 | J27: 6518.08 | K27: 6518.08 | L27: 6518.08 | M27: 6518.08 | N27: 7028.31 | O27: 7028.31 | P27: 7028.31 | Q27: 7028.31 | R27: 7389.57 | S27: 7389.57 | T27: =IFERROR(__xludf.DUMMYFUNCTION("IFERROR(if(W27=true, SUM(FILTER('Resumo - TIMESHEETS'!$H:$H,'Resumo - TIMESHEETS'!M:M = TRUE,'Resumo - TIMESHEETS'!N:N = TRUE,'Resumo - TIMESHEETS'!E:E = B27))/24,0),0)"),56.110833333333325) -> 56.110833 | U27: =T27/$U$11 -> 0.61211818 | V27: =IF(U27<80%,"Parcial","Exclusivo") -> Parcial | W27: TRUE
B28: Johann Ribeiro | C28: 100.110.019-09 | E28: Estagiário | F28: Técnico | H28: 0 | I28: 1560 | J28: 1560 | K28: 1560 | L28: 1560 | M28: 1560 | N28: 1560 | O28: 1560 | P28: 1560 | Q28: 1560 | R28: 1641 | S28: 1641 | T28: =IFERROR(__xludf.DUMMYFUNCTION("IFERROR(if(W28=true, SUM(FILTER('Resumo - TIMESHEETS'!$H:$H,'Resumo - TIMESHEETS'!M:M = TRUE,'Resumo - TIMESHEETS'!N:N = TRUE,'Resumo - TIMESHEETS'!E:E = B28))/24,0),0)"),23.579583333333332) -> 23.579583 | U28: =T28/$U$11 -> 0.25723182 | V28: =IF(U28<80%,"Parcial","Exclusivo") -> Parcial | W28: TRUE
B29: Lucca Sardá Tonim Matos | C29: 123.342.589-70 | E29: Estagiário | F29: Técnico | H29: 1560 | I29: 1560 | J29: 1560 | K29: 1560 | L29: 1560 | M29: 1560 | N29: 1560 | O29: 0 | P29: 0 | Q29: 0 | R29: 0 | S29: 0 | T29: =IFERROR(__xludf.DUMMYFUNCTION("IFERROR(if(W29=true, SUM(FILTER('Resumo - TIMESHEETS'!$H:$H,'Resumo - TIMESHEETS'!M:M = TRUE,'Resumo - TIMESHEETS'!N:N = TRUE,'Resumo - TIMESHEETS'!E:E = B29))/24,0),0)"),6.430416666666666) -> 6.4304167 | U29: =T29/$U$11 -> 0.07015 | V29: =IF(U29<80%,"Parcial","Exclusivo") -> Parcial | W29: TRUE
B30: Marcos Tribess | C30: 057.903.319-80 | E30: Analista de Automação | F30: Superior Completo | H30: 6518.08 | I30: 6518.08 | J30: 6518.08 | K30: 6518.08 | L30: 6518.08 | M30: 6518.08 | N30: 7120.49 | O30: 7120.49 | P30: 7120.49 | Q30: 7120.49 | R30: 7486.49 | S30: 7486.49 | T30: =IFERROR(__xludf.DUMMYFUNCTION("IFERROR(if(W30=true, SUM(FILTER('Resumo - TIMESHEETS'!$H:$H,'Resumo - TIMESHEETS'!M:M = TRUE,'Resumo - TIMESHEETS'!N:N = TRUE,'Resumo - TIMESHEETS'!E:E = B30))/24,0),0)"),2.03125) -> 2.03125 | U30: =T30/$U$11 -> 0.022159091 | V30: =IF(U30<80%,"Parcial","Exclusivo") -> Parcial | W30: TRUE
B31: Paulo Fernando Odwazny | C31: 035.705.119-01 | E31: Supervisor Desenv. Software | F31: Superior Completo | H31: 13351.79 | I31: 13351.79 | J31: 13351.79 | K31: 13351.79 | L31: 13351.79 | M31: 13351.79 | N31: 13351.79 | O31: 13351.79 | P31: 13351.79 | Q31: 17357.33 | R31: 18249.5 | S31: 18249.5 | T31: =IFERROR(__xludf.DUMMYFUNCTION("IFERROR(if(W31=true, SUM(FILTER('Resumo - TIMESHEETS'!$H:$H,'Resumo - TIMESHEETS'!M:M = TRUE,'Resumo - TIMESHEETS'!N:N = TRUE,'Resumo - TIMESHEETS'!E:E = B31))/24,0),0)"),27.30333333333333) -> 27.303333 | U31: =T31/$U$11 -> 0.29785455 | V31: =IF(U31<80%,"Parcial","Exclusivo") -> Parcial | W31: TRUE
B32: Rafael Augusto Barbieri Lobato | C32: 374.320.848-23 | E32: Analista de Automação | F32: Superior Completo | H32: 0 | I32: 0 | J32: 0 | K32: 2769.45 | L32: 2769.45 | M32: 2769.45 | N32: 2769.45 | O32: 2769.45 | P32: 2769.45 | Q32: 2769.45 | R32: 2911.8 | S32: 2911.8 | T32: =IFERROR(__xludf.DUMMYFUNCTION("IFERROR(if(W32=true, SUM(FILTER('Resumo - TIMESHEETS'!$H:$H,'Resumo - TIMESHEETS'!M:M = TRUE,'Resumo - TIMESHEETS'!N:N = TRUE,'Resumo - TIMESHEETS'!E:E = B32))/24,0),0)"),27.10833333333333) -> 27.108333 | U32: =T32/$U$11 -> 0.29572727 | V32: =IF(U32<80%,"Parcial","Exclusivo") -> Parcial | W32: TRUE
B33: Ricardo Bordin | C33: 029.623.950-07 | E33: Analista de Automação | F33: Superior Completo | H33: 0 | I33: 0 | J33: 0 | K33: 5236.48 | L33: 5236.48 | M33: 5236.48 | N33: 5236.48 | O33: 5236.48 | P33: 5236.48 | Q33: 5236.48 | R33: 5505.64 | S33: 5505.64 | T33: =IFERROR(__xludf.DUMMYFUNCTION("IFERROR(if(W33=true, SUM(FILTER('Resumo - TIMESHEETS'!$H:$H,'Resumo - TIMESHEETS'!M:M = TRUE,'Resumo - TIMESHEETS'!N:N = TRUE,'Resumo - TIMESHEETS'!E:E = B33))/24,0),0)"),0.7883333333333334) -> 0.78833333 | U33: =T33/$U$11 -> 0.0086 | V33: =IF(U33<80%,"Parcial","Exclusivo") -> Parcial | W33: TRUE
B34: Theron Wolfgang Harbs | C34: PJ | E34: Consultor | K34: 50000 | L34: 25000 | M34: 25000 | N34: 25000 | O34: 25000 | P34: 25000 | Q34: 25000 | R34: 25000 | S34: 25000 | T34: =IFERROR(__xludf.DUMMYFUNCTION("IFERROR(if(W34=true, SUM(FILTER('Resumo - TIMESHEETS'!$H:$H,'Resumo - TIMESHEETS'!M:M = TRUE,'Resumo - TIMESHEETS'!N:N = TRUE,'Resumo - TIMESHEETS'!E:E = B34))/24,0),0)"),12.777499999999998) -> 12.7775 | U34: =T34/$U$11 -> 0.13939091 | V34: =IF(U34<80%,"Parcial","Exclusivo") -> Parcial | W34: TRUE
F38: Cálculo do custo/hora | G38: Patronal | H38: 0.0286 | I38: 0.01238 | J38: 0.01176 | K38: 0.03086 | L38: 0.02374 | M38: 0.02114 | N38: 0.07246 | O38: 0.0228 | P38: 0.0446 | Q38: 0.02436 | R38: 0.02 | S38: 0.03624 | T38: // Informações recebidas por e-mail do RH
G39: Terceiros | H39: 0.058 | I39: 0.058 | J39: 0.058 | K39: 0.058 | L39: 0.058 | M39: 0.058 | N39: 0.058 | O39: 0.058 | P39: 0.058 | Q39: 0.058 | R39: 0.058 | S39: 0.058
G40: RAT | H40: 0.02832 | I40: 0.02832 | J40: 0.02832 | K40: 0.02832 | L40: 0.02832 | M40: 0.02832 | N40: 0.02832 | O40: 0.02832 | P40: 0.02832 | Q40: 0.02832 | R40: 0.02832 | S40: 0.02832
G41: INSS | H41: =SUM(H38:H40) -> 0.11492 | I41: =SUM(I38:I40) -> 0.0987 | J41: =SUM(J38:J40) -> 0.09808 | K41: =SUM(K38:K40) -> 0.11718 | L41: =SUM(L38:L40) -> 0.11006 | M41: =SUM(M38:M40) -> 0.10746 | N41: =SUM(N38:N40) -> 0.15878 | O41: =SUM(O38:O40) -> 0.10912 | ... S41: =SUM(S38:S40) -> 0.12256
G42: FGTS | H42: 0.08 | I42: 0.08 | J42: 0.08 | K42: 0.08 | L42: 0.08 | M42: 0.08 | N42: 0.08 | O42: 0.08 | P42: 0.08 | Q42: 0.08 | R42: 0.08 | S42: 0.08
G43: Férias | H43: =((1+(1/3))*(1+H41+H42)/12) -> 0.13276889 | I43: =((1+(1/3))*(1+I41+I42)/12) -> 0.13096667 | J43: =((1+(1/3))*(1+J41+J42)/12) -> 0.13089778 | K43: =((1+(1/3))*(1+K41+K42)/12) -> 0.13302 | L43: =((1+(1/3))*(1+L41+L42)/12) -> 0.13222889 | M43: =((1+(1/3))*(1+M41+M42)/12) -> 0.13194 | N43: =((1+(1/3))*(1+N41+N42)/12) -> 0.13764222 | O43: =((1+(1/3))*(1+O41+O42)/12) -> 0.13212444 | ... S43: =((1+(1/3))*(1+S41+S42)/12) -> 0.13361778
G44: 13º | H44: =(1/12)*(1+H41+H42) -> 0.099576667 | I44: =(1/12)*(1+I41+I42) -> 0.098225 | J44: =(1/12)*(1+J41+J42) -> 0.098173333 | K44: =(1/12)*(1+K41+K42) -> 0.099765 | L44: =(1/12)*(1+L41+L42) -> 0.099171667 | M44: =(1/12)*(1+M41+M42) -> 0.098955 | N44: =(1/12)*(1+N41+N42) -> 0.10323167 | O44: =(1/12)*(1+O41+O42) -> 0.099093333 | ... S44: =(1/12)*(1+S41+S42) -> 0.10021333
G45: TOTAL | H45: =SUM(H41:H44) -> 0.42726556 | I45: =SUM(I41:I44) -> 0.40789167 | J45: =SUM(J41:J44) -> 0.40715111 | K45: =SUM(K41:K44) -> 0.429965 | L45: =SUM(L41:L44) -> 0.42146056 | M45: =SUM(M41:M44) -> 0.418355 | N45: =SUM(N41:N44) -> 0.47965389 | O45: =SUM(O41:O44) -> 0.42033778 | ... S45: =SUM(S41:S44) -> 0.43639111
H47: 21 | I47: 20 | J47: 23 | K47: 17 | L47: 22 | M47: 21 | N47: 21 | O47: 23 | P47: 21 | Q47: 19 | R47: 20 | S47: 22 | T47: =sum(T49:T68) -> 1334869.8 | U47: =sum(U49:U68) -> 1334869.8 | V47: =U47-T47 -> 0
B48: Nome Completo | E48: Classificação | F48: Formação | H48: 44592 | I48: 44620 | J48: 44651 | K48: 44681 | L48: 44712 | M48: 44742 | N48: 44773 | O48: 44804 | P48: 44834 | Q48: 44865 | R48: 44895 | S48: 44926 | T48: PD&I R$ | U48: Aprovado R$ | V48: Pesquisador
B49: {=unique(B13:B34)} -> Alberto Reuters | E49: {=V13:V34} -> Parcial | F49: {=F13:F34} -> Mestrado | H49: =iferror((xlookup($B49,$B$13:$B$34,H$13:H$34)*(1+H$45))/(H$47*8.8),"") -> 114.59228 | I49: =iferror((xlookup($B49,$B$13:$B$34,I$13:I$34)*(1+I$45))/(I$47*8.8),"") -> 118.68863 | J49: =iferror((xlookup($B49,$B$13:$B$34,J$13:J$34)*(1+J$45))/(J$47*8.8),"") -> 103.15321 | K49: =iferror((xlookup($B49,$B$13:$B$34,K$13:K$34)*(1+K$45))/(K$47*8.8),"") -> 141.8229 | L49: =iferror((xlookup($B49,$B$13:$B$34,L$13:L$34)*(1+L$45))/(L$47*8.8),"") -> 108.93865 | M49: =iferror((xlookup($B49,$B$13:$B$34,M$13:M$34)*(1+M$45))/(M$47*8.8),"") -> 113.87687 | N49: =iferror((xlookup($B49,$B$13:$B$34,N$13:N$34)*(1+N$45))/(N$47*8.8),"") -> 118.79843 | O49: =iferror((xlookup($B49,$B$13:$B$34,O$13:O$34)*(1+O$45))/(O$47*8.8),"") -> 104.11988 | ... S49: =iferror((xlookup($B49,$B$13:$B$34,S$13:S$34)*(1+S$45))/(S$47*8.8),"") -> 194.49114 | T49: =SUMIF('Resumo - TIMESHEETS'!E:E,B49,'Resumo - TIMESHEETS'!L:L) -> 0 | U49: =SUMIF(V49,TRUE,T49) -> 0 | V49: TRUE
B50: Alexandre Baseggio | E50: Parcial | F50: Superior Completo | H50: =iferror((xlookup($B50,$B$13:$B$34,H$13:H$34)*(1+H$45))/(H$47*8.8),"") -> 53.469013 | I50: =iferror((xlookup($B50,$B$13:$B$34,I$13:I$34)*(1+I$45))/(I$47*8.8),"") -> 55.380379 | J50: =iferror((xlookup($B50,$B$13:$B$34,J$13:J$34)*(1+J$45))/(J$47*8.8),"") -> 48.13152 | K50: =iferror((xlookup($B50,$B$13:$B$34,K$13:K$34)*(1+K$45))/(K$47*8.8),"") -> 66.17488 | L50: =iferror((xlookup($B50,$B$13:$B$34,L$13:L$34)*(1+L$45))/(L$47*8.8),"") -> 50.831018 | M50: =iferror((xlookup($B50,$B$13:$B$34,M$13:M$34)*(1+M$45))/(M$47*8.8),"") -> 53.135201 | N50: =iferror((xlookup($B50,$B$13:$B$34,N$13:N$34)*(1+N$45))/(N$47*8.8),"") -> 55.431614 | O50: =iferror((xlookup($B50,$B$13:$B$34,O$13:O$34)*(1+O$45))/(O$47*8.8),"") -> 48.582569 | ... S50: =iferror((xlookup($B50,$B$13:$B$34,S$13:S$34)*(1+S$45))/(S$47*8.8),"") -> 54.005115 | T50: =SUMIF('Resumo - TIMESHEETS'!E:E,B50,'Resumo - TIMESHEETS'!L:L) -> 3208.0968 | U50: =SUMIF(V50,TRUE,T50) -> 3208.0968 | V50: TRUE
B51: Arthur Muniz | E51: Exclusivo | F51: Superior Completo | H51: =iferror((xlookup($B51,$B$13:$B$34,H$13:H$34)*(1+H$45))/(H$47*8.8),"") -> 87.206003 | I51: =iferror((xlookup($B51,$B$13:$B$34,I$13:I$34)*(1+I$45))/(I$47*8.8),"") -> 90.32337 | J51: =iferror((xlookup($B51,$B$13:$B$34,J$13:J$34)*(1+J$45))/(J$47*8.8),"") -> 78.500747 | K51: =iferror((xlookup($B51,$B$13:$B$34,K$13:K$34)*(1+K$45))/(K$47*8.8),"") -> 107.92881 | L51: =iferror((xlookup($B51,$B$13:$B$34,L$13:L$34)*(1+L$45))/(L$47*8.8),"") -> 82.90353 | M51: =iferror((xlookup($B51,$B$13:$B$34,M$13:M$34)*(1+M$45))/(M$47*8.8),"") -> 86.661567 | N51: =iferror((xlookup($B51,$B$13:$B$34,N$13:N$34)*(1+N$45))/(N$47*8.8),"") -> 95.026367 | O51: =iferror((xlookup($B51,$B$13:$B$34,O$13:O$34)*(1+O$45))/(O$47*8.8),"") -> 83.285056 | ... S51: =iferror((xlookup($B51,$B$13:$B$34,S$13:S$34)*(1+S$45))/(S$47*8.8),"") -> 92.580897 | T51: =SUMIF('Resumo - TIMESHEETS'!E:E,B51,'Resumo - TIMESHEETS'!L:L) -> 176592.26 | U51: =SUMIF(V51,TRUE,T51) -> 176592.26 | V51: TRUE
B52: Bruno katzjarowksi | E52: Exclusivo | F52: Superior Completo | H52: =iferror((xlookup($B52,$B$13:$B$34,H$13:H$34)*(1+H$45))/(H$47*8.8),"") -> 108.31895 | I52: =iferror((xlookup($B52,$B$13:$B$34,I$13:I$34)*(1+I$45))/(I$47*8.8),"") -> 112.19105 | J52: =iferror((xlookup($B52,$B$13:$B$34,J$13:J$34)*(1+J$45))/(J$47*8.8),"") -> 97.506117 | K52: =iferror((xlookup($B52,$B$13:$B$34,K$13:K$34)*(1+K$45))/(K$47*8.8),"") -> 134.05884 | L52: =iferror((xlookup($B52,$B$13:$B$34,L$13:L$34)*(1+L$45))/(L$47*8.8),"") -> 102.97483 | M52: =iferror((xlookup($B52,$B$13:$B$34,M$13:M$34)*(1+M$45))/(M$47*8.8),"") -> 107.64271 | N52: =iferror((xlookup($B52,$B$13:$B$34,N$13:N$34)*(1+N$45))/(N$47*8.8),"") -> 114.49703 | O52: =iferror((xlookup($B52,$B$13:$B$34,O$13:O$34)*(1+O$45))/(O$47*8.8),"") -> 100.34995 | ... S52: =iferror((xlookup($B52,$B$13:$B$34,S$13:S$34)*(1+S$45))/(S$47*8.8),"") -> 111.55046 | T52: =SUMIF('Resumo - TIMESHEETS'!E:E,B52,'Resumo - TIMESHEETS'!L:L) -> 236612.19 | U52: =SUMIF(V52,TRUE,T52) -> 236612.19 | V52: TRUE
B53: Cleiton Capristano | E53: Exclusivo | F53: Superior Completo | H53: =iferror((xlookup($B53,$B$13:$B$34,H$13:H$34)*(1+H$45))/(H$47*8.8),"") -> 96.541231 | I53: =iferror((xlookup($B53,$B$13:$B$34,I$13:I$34)*(1+I$45))/(I$47*8.8),"") -> 99.992306 | J53: =iferror((xlookup($B53,$B$13:$B$34,J$13:J$34)*(1+J$45))/(J$47*8.8),"") -> 86.904095 | K53: =iferror((xlookup($B53,$B$13:$B$34,K$13:K$34)*(1+K$45))/(K$47*8.8),"") -> 119.48237 | L53: =iferror((xlookup($B53,$B$13:$B$34,L$13:L$34)*(1+L$45))/(L$47*8.8),"") -> 91.778187 | M53: =iferror((xlookup($B53,$B$13:$B$34,M$13:M$34)*(1+M$45))/(M$47*8.8),"") -> 95.938515 | N53: =iferror((xlookup($B53,$B$13:$B$34,N$13:N$34)*(1+N$45))/(N$47*8.8),"") -> 100.08481 | O53: =iferror((xlookup($B53,$B$13:$B$34,O$13:O$34)*(1+O$45))/(O$47*8.8),"") -> 88.623814 | ... S53: =iferror((xlookup($B53,$B$13:$B$34,S$13:S$34)*(1+S$45))/(S$47*8.8),"") -> 98.515582 | T53: =SUMIF('Resumo - TIMESHEETS'!E:E,B53,'Resumo - TIMESHEETS'!L:L) -> 225788.73 | U53: =SUMIF(V53,TRUE,T53) -> 225788.73 | V53: TRUE
B54: Eduardo Flohr | E54: Parcial | F54: Superior Completo | H54: =iferror((xlookup($B54,$B$13:$B$34,H$13:H$34)*(1+H$45))/(H$47*8.8),"") -> 103.11986 | I54: =iferror((xlookup($B54,$B$13:$B$34,I$13:I$34)*(1+I$45))/(I$47*8.8),"") -> 106.8061 | J54: =iferror((xlookup($B54,$B$13:$B$34,J$13:J$34)*(1+J$45))/(J$47*8.8),"") -> 92.826018 | K54: =iferror((xlookup($B54,$B$13:$B$34,K$13:K$34)*(1+K$45))/(K$47*8.8),"") -> 127.62428 | L54: =iferror((xlookup($B54,$B$13:$B$34,L$13:L$34)*(1+L$45))/(L$47*8.8),"") -> 98.032246 | M54: =iferror((xlookup($B54,$B$13:$B$34,M$13:M$34)*(1+M$45))/(M$47*8.8),"") -> 102.47607 | N54: =iferror((xlookup($B54,$B$13:$B$34,N$13:N$34)*(1+N$45))/(N$47*8.8),"") -> 106.90491 | O54: =iferror((xlookup($B54,$B$13:$B$34,O$13:O$34)*(1+O$45))/(O$47*8.8),"") -> 93.695908 | ... S54: =iferror((xlookup($B54,$B$13:$B$34,S$13:S$34)*(1+S$45))/(S$47*8.8),"") -> 140.52208 | T54: =SUMIF('Resumo - TIMESHEETS'!E:E,B54,'Resumo - TIMESHEETS'!L:L) -> 15040.492 | U54: =SUMIF(V54,TRUE,T54) -> 15040.492 | V54: TRUE
B55: Fernando Leal | E55: Parcial | H55: =iferror((xlookup($B55,$B$13:$B$34,H$13:H$34)*(1+H$45))/(H$47*8.8),"") -> 0 | I55: =iferror((xlookup($B55,$B$13:$B$34,I$13:I$34)*(1+I$45))/(I$47*8.8),"") -> 0 | J55: =iferror((xlookup($B55,$B$13:$B$34,J$13:J$34)*(1+J$45))/(J$47*8.8),"") -> 0 | K55: =iferror((xlookup($B55,$B$13:$B$34,K$13:K$34)*(1+K$45))/(K$47*8.8),"") -> 0 | L55: =iferror((xlookup($B55,$B$13:$B$34,L$13:L$34)*(1+L$45))/(L$47*8.8),"") -> 0 | M55: =iferror((xlookup($B55,$B$13:$B$34,M$13:M$34)*(1+M$45))/(M$47*8.8),"") -> 0 | N55: =iferror((xlookup($B55,$B$13:$B$34,N$13:N$34)*(1+N$45))/(N$47*8.8),"") -> 0 | O55: =iferror((xlookup($B55,$B$13:$B$34,O$13:O$34)*(1+O$45))/(O$47*8.8),"") -> 0 | ... S55: =iferror((xlookup($B55,$B$13:$B$34,S$13:S$34)*(1+S$45))/(S$47*8.8),"") -> 0 | T55: =SUMIF('Resumo - TIMESHEETS'!E:E,B55,'Resumo - TIMESHEETS'!L:L) -> 0 | U55: =SUMIF(V55,TRUE,T55) -> 0 | V55: TRUE
B56: Filipe Harbs | E56: Parcial | F56: Técnico | H56: =iferror((xlookup($B56,$B$13:$B$34,H$13:H$34)*(1+H$45))/(H$47*8.8),"") -> 42.253085 | I56: =iferror((xlookup($B56,$B$13:$B$34,I$13:I$34)*(1+I$45))/(I$47*8.8),"") -> 43.763513 | J56: =iferror((xlookup($B56,$B$13:$B$34,J$13:J$34)*(1+J$45))/(J$47*8.8),"") -> 38.035211 | K56: =iferror((xlookup($B56,$B$13:$B$34,K$13:K$34)*(1+K$45))/(K$47*8.8),"") -> 52.293705 | L56: =iferror((xlookup($B56,$B$13:$B$34,L$13:L$34)*(1+L$45))/(L$47*8.8),"") -> 40.168449 | M56: =iferror((xlookup($B56,$B$13:$B$34,M$13:M$34)*(1+M$45))/(M$47*8.8),"") -> 41.989295 | N56: =iferror((xlookup($B56,$B$13:$B$34,N$13:N$34)*(1+N$45))/(N$47*8.8),"") -> 47.317057 | O56: =iferror((xlookup($B56,$B$13:$B$34,O$13:O$34)*(1+O$45))/(O$47*8.8),"") -> 41.470635 | ... S56: =iferror((xlookup($B56,$B$13:$B$34,S$13:S$34)*(1+S$45))/(S$47*8.8),"") -> 46.0994 | T56: =SUMIF('Resumo - TIMESHEETS'!E:E,B56,'Resumo - TIMESHEETS'!L:L) -> 68078.453 | U56: =SUMIF(V56,TRUE,T56) -> 68078.453 | V56: TRUE
B57: Gabriel Alves Ferraz | E57: Parcial | F57: Superior Completo | H57: =iferror((xlookup($B57,$B$13:$B$34,H$13:H$34)*(1+H$45))/(H$47*8.8),"") -> 21.389289 | I57: =iferror((xlookup($B57,$B$13:$B$34,I$13:I$34)*(1+I$45))/(I$47*8.8),"") -> 22.153895 | J57: =iferror((xlookup($B57,$B$13:$B$34,J$13:J$34)*(1+J$45))/(J$47*8.8),"") -> 19.254124 | K57: =iferror((xlookup($B57,$B$13:$B$34,K$13:K$34)*(1+K$45))/(K$47*8.8),"") -> 26.472036 | L57: =iferror((xlookup($B57,$B$13:$B$34,L$13:L$34)*(1+L$45))/(L$47*8.8),"") -> 20.334008 | M57: =iferror((xlookup($B57,$B$13:$B$34,M$13:M$34)*(1+M$45))/(M$47*8.8),"") -> 21.255754 | N57: =iferror((xlookup($B57,$B$13:$B$34,N$13:N$34)*(1+N$45))/(N$47*8.8),"") -> 23.726586 | O57: =iferror((xlookup($B57,$B$13:$B$34,O$13:O$34)*(1+O$45))/(O$47*8.8),"") -> 20.794966 | ... S57: =iferror((xlookup($B57,$B$13:$B$34,S$13:S$34)*(1+S$45))/(S$47*8.8),"") -> 23.116029 | T57: =SUMIF('Resumo - TIMESHEETS'!E:E,B57,'Resumo - TIMESHEETS'!L:L) -> 11465.849 | U57: =SUMIF(V57,TRUE,T57) -> 11465.849 | V57: TRUE
B58: Gabriel Oliveira | E58: Parcial | F58: Superior Completo | H58: =iferror((xlookup($B58,$B$13:$B$34,H$13:H$34)*(1+H$45))/(H$47*8.8),"") -> 0 | I58: =iferror((xlookup($B58,$B$13:$B$34,I$13:I$34)*(1+I$45))/(I$47*8.8),"") -> 0 | J58: =iferror((xlookup($B58,$B$13:$B$34,J$13:J$34)*(1+J$45))/(J$47*8.8),"") -> 0 | K58: =iferror((xlookup($B58,$B$13:$B$34,K$13:K$34)*(1+K$45))/(K$47*8.8),"") -> 95.585896 | L58: =iferror((xlookup($B58,$B$13:$B$34,L$13:L$34)*(1+L$45))/(L$47*8.8),"") -> 73.422549 | M58: =iferror((xlookup($B58,$B$13:$B$34,M$13:M$34)*(1+M$45))/(M$47*8.8),"") -> 76.750812 | N58: =iferror((xlookup($B58,$B$13:$B$34,N$13:N$34)*(1+N$45))/(N$47*8.8),"") -> 80.067851 | O58: =iferror((xlookup($B58,$B$13:$B$34,O$13:O$34)*(1+O$45))/(O$47*8.8),"") -> 70.174791 | ... S58: =iferror((xlookup($B58,$B$13:$B$34,S$13:S$34)*(1+S$45))/(S$47*8.8),"") -> 78.007315 | T58: =SUMIF('Resumo - TIMESHEETS'!E:E,B58,'Resumo - TIMESHEETS'!L:L) -> 119279.73 | U58: =SUMIF(V58,TRUE,T58) -> 119279.73 | V58: TRUE
B59: Gabriel Possamai | E59: Exclusivo | F59: Superior Completo | H59: =iferror((xlookup($B59,$B$13:$B$34,H$13:H$34)*(1+H$45))/(H$47*8.8),"") -> 114.74466 | I59: =iferror((xlookup($B59,$B$13:$B$34,I$13:I$34)*(1+I$45))/(I$47*8.8),"") -> 118.84646 | J59: =iferror((xlookup($B59,$B$13:$B$34,J$13:J$34)*(1+J$45))/(J$47*8.8),"") -> 103.29038 | K59: =iferror((xlookup($B59,$B$13:$B$34,K$13:K$34)*(1+K$45))/(K$47*8.8),"") -> 142.01149 | L59: =iferror((xlookup($B59,$B$13:$B$34,L$13:L$34)*(1+L$45))/(L$47*8.8),"") -> 109.08351 | M59: =iferror((xlookup($B59,$B$13:$B$34,M$13:M$34)*(1+M$45))/(M$47*8.8),"") -> 114.0283 | N59: =iferror((xlookup($B59,$B$13:$B$34,N$13:N$34)*(1+N$45))/(N$47*8.8),"") -> 121.83653 | O59: =iferror((xlookup($B59,$B$13:$B$34,O$13:O$34)*(1+O$45))/(O$47*8.8),"") -> 106.78259 | ... S59: =iferror((xlookup($B59,$B$13:$B$34,S$13:S$34)*(1+S$45))/(S$47*8.8),"") -> 118.70111 | T59: =SUMIF('Resumo - TIMESHEETS'!E:E,B59,'Resumo - TIMESHEETS'!L:L) -> 233235.96 | U59: =SUMIF(V59,TRUE,T59) -> 233235.96 | V59: TRUE
B60: Guilherme Jacques | E60: Parcial | F60: Técnico | H60: =iferror((xlookup($B60,$B$13:$B$34,H$13:H$34)*(1+H$45))/(H$47*8.8),"") -> 0 | I60: =iferror((xlookup($B60,$B$13:$B$34,I$13:I$34)*(1+I$45))/(I$47*8.8),"") -> 0 | J60: =iferror((xlookup($B60,$B$13:$B$34,J$13:J$34)*(1+J$45))/(J$47*8.8),"") -> 0 | K60: =iferror((xlookup($B60,$B$13:$B$34,K$13:K$34)*(1+K$45))/(K$47*8.8),"") -> 50.053363 | L60: =iferror((xlookup($B60,$B$13:$B$34,L$13:L$34)*(1+L$45))/(L$47*8.8),"") -> 38.447571 | M60: =iferror((xlookup($B60,$B$13:$B$34,M$13:M$34)*(1+M$45))/(M$47*8.8),"") -> 40.190409 | N60: =iferror((xlookup($B60,$B$13:$B$34,N$13:N$34)*(1+N$45))/(N$47*8.8),"") -> 41.92737 | O60: =iferror((xlookup($B60,$B$13:$B$34,O$13:O$34)*(1+O$45))/(O$47*8.8),"") -> 36.746889 | ... S60: =iferror((xlookup($B60,$B$13:$B$34,S$13:S$34)*(1+S$45))/(S$47*8.8),"") -> 40.848411 | T60: =SUMIF('Resumo - TIMESHEETS'!E:E,B60,'Resumo - TIMESHEETS'!L:L) -> 2831.5474 | U60: =SUMIF(V60,TRUE,T60) -> 2831.5474 | V60: TRUE
B61: Italo Ebel | E61: Parcial | F61: Técnico | H61: =iferror((xlookup($B61,$B$13:$B$34,H$13:H$34)*(1+H$45))/(H$47*8.8),"") -> 0 | I61: =iferror((xlookup($B61,$B$13:$B$34,I$13:I$34)*(1+I$45))/(I$47*8.8),"") -> 0 | J61: =iferror((xlookup($B61,$B$13:$B$34,J$13:J$34)*(1+J$45))/(J$47*8.8),"") -> 0 | K61: =iferror((xlookup($B61,$B$13:$B$34,K$13:K$34)*(1+K$45))/(K$47*8.8),"") -> 0 | L61: =iferror((xlookup($B61,$B$13:$B$34,L$13:L$34)*(1+L$45))/(L$47*8.8),"") -> 0 | M61: =iferror((xlookup($B61,$B$13:$B$34,M$13:M$34)*(1+M$45))/(M$47*8.8),"") -> 0 | N61: =iferror((xlookup($B61,$B$13:$B$34,N$13:N$34)*(1+N$45))/(N$47*8.8),"") -> 0 | O61: =iferror((xlookup($B61,$B$13:$B$34,O$13:O$34)*(1+O$45))/(O$47*8.8),"") -> 10.947267 | ... S61: =iferror((xlookup($B61,$B$13:$B$34,S$13:S$34)*(1+S$45))/(S$47*8.8),"") -> 12.175195 | T61: =SUMIF('Resumo - TIMESHEETS'!E:E,B61,'Resumo - TIMESHEETS'!L:L) -> 3476.3723 | U61: =SUMIF(V61,TRUE,T61) -> 3476.3723 | V61: TRUE
B62: Ivo Ersching | E62: Parcial | F62: Superior Completo | H62: =iferror((xlookup($B62,$B$13:$B$34,H$13:H$34)*(1+H$45))/(H$47*8.8),"") -> 62.662287 | I62: =iferror((xlookup($B62,$B$13:$B$34,I$13:I$34)*(1+I$45))/(I$47*8.8),"") -> 64.902286 | J62: =iferror((xlookup($B62,$B$13:$B$34,J$13:J$34)*(1+J$45))/(J$47*8.8),"") -> 56.407084 | K62: =iferror((xlookup($B62,$B$13:$B$34,K$13:K$34)*(1+K$45))/(K$47*8.8),"") -> 77.552756 | L62: =iferror((xlookup($B62,$B$13:$B$34,L$13:L$34)*(1+L$45))/(L$47*8.8),"") -> 59.570725 | M62: =iferror((xlookup($B62,$B$13:$B$34,M$13:M$34)*(1+M$45))/(M$47*8.8),"") -> 62.27108 | N62: =iferror((xlookup($B62,$B$13:$B$34,N$13:N$34)*(1+N$45))/(N$47*8.8),"") -> 64.96233 | O62: =iferror((xlookup($B62,$B$13:$B$34,O$13:O$34)*(1+O$45))/(O$47*8.8),"") -> 56.935685 | ... S62: =iferror((xlookup($B62,$B$13:$B$34,S$13:S$34)*(1+S$45))/(S$47*8.8),"") -> 63.290538 | T62: =SUMIF('Resumo - TIMESHEETS'!E:E,B62,'Resumo - TIMESHEETS'!L:L) -> 68856.65 | U62: =SUMIF(V62,TRUE,T62) -> 68856.65 | V62: TRUE
B63: Jivago Rusch | E63: Parcial | F63: Superior Completo | H63: =iferror((xlookup($B63,$B$13:$B$34,H$13:H$34)*(1+H$45))/(H$47*8.8),"") -> 46.12014 | I63: =iferror((xlookup($B63,$B$13:$B$34,I$13:I$34)*(1+I$45))/(I$47*8.8),"") -> 52.140628 | J63: =iferror((xlookup($B63,$B$13:$B$34,J$13:J$34)*(1+J$45))/(J$47*8.8),"") -> 45.315828 | K63: =iferror((xlookup($B63,$B$13:$B$34,K$13:K$34)*(1+K$45))/(K$47*8.8),"") -> 62.303652 | L63: =iferror((xlookup($B63,$B$13:$B$34,L$13:L$34)*(1+L$45))/(L$47*8.8),"") -> 47.857405 | M63: =iferror((xlookup($B63,$B$13:$B$34,M$13:M$34)*(1+M$45))/(M$47*8.8),"") -> 50.026793 | N63: =iferror((xlookup($B63,$B$13:$B$34,N$13:N$34)*(1+N$45))/(N$47*8.8),"") -> 56.274168 | O63: =iferror((xlookup($B63,$B$13:$B$34,O$13:O$34)*(1+O$45))/(O$47*8.8),"") -> 49.321019 | ... S63: =iferror((xlookup($B63,$B$13:$B$34,S$13:S$34)*(1+S$45))/(S$47*8.8),"") -> 54.825995 | T63: =SUMIF('Resumo - TIMESHEETS'!E:E,B63,'Resumo - TIMESHEETS'!L:L) -> 76382.775 | U63: =SUMIF(V63,TRUE,T63) -> 76382.775 | V63: TRUE
B64: Johann Ribeiro | E64: Parcial | F64: Técnico | H64: =iferror((xlookup($B64,$B$13:$B$34,H$13:H$34)*(1+H$45))/(H$47*8.8),"") -> 0 | I64: =iferror((xlookup($B64,$B$13:$B$34,I$13:I$34)*(1+I$45))/(I$47*8.8),"") -> 12.47904 | J64: =iferror((xlookup($B64,$B$13:$B$34,J$13:J$34)*(1+J$45))/(J$47*8.8),"") -> 10.845631 | K64: =iferror((xlookup($B64,$B$13:$B$34,K$13:K$34)*(1+K$45))/(K$47*8.8),"") -> 14.9114 | L64: =iferror((xlookup($B64,$B$13:$B$34,L$13:L$34)*(1+L$45))/(L$47*8.8),"") -> 11.453918 | M64: =iferror((xlookup($B64,$B$13:$B$34,M$13:M$34)*(1+M$45))/(M$47*8.8),"") -> 11.973127 | N64: =iferror((xlookup($B64,$B$13:$B$34,N$13:N$34)*(1+N$45))/(N$47*8.8),"") -> 12.490585 | O64: =iferror((xlookup($B64,$B$13:$B$34,O$13:O$34)*(1+O$45))/(O$47*8.8),"") -> 10.947267 | ... S64: =iferror((xlookup($B64,$B$13:$B$34,S$13:S$34)*(1+S$45))/(S$47*8.8),"") -> 12.175195 | T64: =SUMIF('Resumo - TIMESHEETS'!E:E,B64,'Resumo - TIMESHEETS'!L:L) -> 6838.116 | U64: =SUMIF(V64,TRUE,T64) -> 6838.116 | V64: TRUE
B65: Lucca Sardá Tonim Matos | E65: Parcial | F65: Técnico | H65: =iferror((xlookup($B65,$B$13:$B$34,H$13:H$34)*(1+H$45))/(H$47*8.8),"") -> 12.048346 | I65: =iferror((xlookup($B65,$B$13:$B$34,I$13:I$34)*(1+I$45))/(I$47*8.8),"") -> 12.47904 | J65: =iferror((xlookup($B65,$B$13:$B$34,J$13:J$34)*(1+J$45))/(J$47*8.8),"") -> 10.845631 | K65: =iferror((xlookup($B65,$B$13:$B$34,K$13:K$34)*(1+K$45))/(K$47*8.8),"") -> 14.9114 | L65: =iferror((xlookup($B65,$B$13:$B$34,L$13:L$34)*(1+L$45))/(L$47*8.8),"") -> 11.453918 | M65: =iferror((xlookup($B65,$B$13:$B$34,M$13:M$34)*(1+M$45))/(M$47*8.8),"") -> 11.973127 | N65: =iferror((xlookup($B65,$B$13:$B$34,N$13:N$34)*(1+N$45))/(N$47*8.8),"") -> 12.490585 | O65: =iferror((xlookup($B65,$B$13:$B$34,O$13:O$34)*(1+O$45))/(O$47*8.8),"") -> 0 | ... S65: =iferror((xlookup($B65,$B$13:$B$34,S$13:S$34)*(1+S$45))/(S$47*8.8),"") -> 0 | T65: =SUMIF('Resumo - TIMESHEETS'!E:E,B65,'Resumo - TIMESHEETS'!L:L) -> 1911.7595 | U65: =SUMIF(V65,TRUE,T65) -> 1911.7595 | V65: TRUE
B66: Marcos Tribess | E66: Parcial | F66: Superior Completo | H66: =iferror((xlookup($B66,$B$13:$B$34,H$13:H$34)*(1+H$45))/(H$47*8.8),"") -> 50.341077 | I66: =iferror((xlookup($B66,$B$13:$B$34,I$13:I$34)*(1+I$45))/(I$47*8.8),"") -> 52.140628 | J66: =iferror((xlookup($B66,$B$13:$B$34,J$13:J$34)*(1+J$45))/(J$47*8.8),"") -> 45.315828 | K66: =iferror((xlookup($B66,$B$13:$B$34,K$13:K$34)*(1+K$45))/(K$47*8.8),"") -> 62.303652 | L66: =iferror((xlookup($B66,$B$13:$B$34,L$13:L$34)*(1+L$45))/(L$47*8.8),"") -> 47.857405 | M66: =iferror((xlookup($B66,$B$13:$B$34,M$13:M$34)*(1+M$45))/(M$47*8.8),"") -> 50.026793 | N66: =iferror((xlookup($B66,$B$13:$B$34,N$13:N$34)*(1+N$45))/(N$47*8.8),"") -> 57.012233 | O66: =iferror((xlookup($B66,$B$13:$B$34,O$13:O$34)*(1+O$45))/(O$47*8.8),"") -> 49.96789 | ... S66: =iferror((xlookup($B66,$B$13:$B$34,S$13:S$34)*(1+S$45))/(S$47*8.8),"") -> 55.545081 | T66: =SUMIF('Resumo - TIMESHEETS'!E:E,B66,'Resumo - TIMESHEETS'!L:L) -> 2764.3133 | U66: =SUMIF(V66,TRUE,T66) -> 2764.3133 | V66: TRUE
B67: Paulo Fernando Odwazny | E67: Parcial | F67: Superior Completo | H67: =iferror((xlookup($B67,$B$13:$B$34,H$13:H$34)*(1+H$45))/(H$47*8.8),"") -> 103.11986 | I67: =iferror((xlookup($B67,$B$13:$B$34,I$13:I$34)*(1+I$45))/(I$47*8.8),"") -> 106.8061 | J67: =iferror((xlookup($B67,$B$13:$B$34,J$13:J$34)*(1+J$45))/(J$47*8.8),"") -> 92.826018 | K67: =iferror((xlookup($B67,$B$13:$B$34,K$13:K$34)*(1+K$45))/(K$47*8.8),"") -> 127.62428 | L67: =iferror((xlookup($B67,$B$13:$B$34,L$13:L$34)*(1+L$45))/(L$47*8.8),"") -> 98.032246 | M67: =iferror((xlookup($B67,$B$13:$B$34,M$13:M$34)*(1+M$45))/(M$47*8.8),"") -> 102.47607 | N67: =iferror((xlookup($B67,$B$13:$B$34,N$13:N$34)*(1+N$45))/(N$47*8.8),"") -> 106.90491 | O67: =iferror((xlookup($B67,$B$13:$B$34,O$13:O$34)*(1+O$45))/(O$47*8.8),"") -> 93.695908 | ... S67: =iferror((xlookup($B67,$B$13:$B$34,S$13:S$34)*(1+S$45))/(S$47*8.8),"") -> 135.39989 | T67: =SUMIF('Resumo - TIMESHEETS'!E:E,B67,'Resumo - TIMESHEETS'!L:L) -> 68515.474 | U67: =SUMIF(V67,TRUE,T67) -> 68515.474 | V67: TRUE
... B69: Ricardo Bordin | E69: Parcial | F69: Superior Completo | H69: =iferror((xlookup($B69,$B$13:$B$34,H$13:H$34)*(1+H$45))/(H$47*8.8),"") -> 0 | I69: =iferror((xlookup($B69,$B$13:$B$34,I$13:I$34)*(1+I$45))/(I$47*8.8),"") -> 0 | J69: =iferror((xlookup($B69,$B$13:$B$34,J$13:J$34)*(1+J$45))/(J$47*8.8),"") -> 0 | K69: =iferror((xlookup($B69,$B$13:$B$34,K$13:K$34)*(1+K$45))/(K$47*8.8),"") -> 50.053363 | L69: =iferror((xlookup($B69,$B$13:$B$34,L$13:L$34)*(1+L$45))/(L$47*8.8),"") -> 38.447571 | M69: =iferror((xlookup($B69,$B$13:$B$34,M$13:M$34)*(1+M$45))/(M$47*8.8),"") -> 40.190409 | N69: =iferror((xlookup($B69,$B$13:$B$34,N$13:N$34)*(1+N$45))/(N$47*8.8),"") -> 41.92737 | O69: =iferror((xlookup($B69,$B$13:$B$34,O$13:O$34)*(1+O$45))/(O$47*8.8),"") -> 36.746889 | ... S69: =iferror((xlookup($B69,$B$13:$B$34,S$13:S$34)*(1+S$45))/(S$47*8.8),"") -> 40.848411 | T69: =SUMIF('Resumo - TIMESHEETS'!E:E,B69,'Resumo - TIMESHEETS'!L:L) -> 873.97656 | U69: =SUMIF(V69,TRUE,T69) -> 873.97656 | V69: TRUE
B70: Theron Wolfgang Harbs | E70: Parcial | H70: =iferror((xlookup($B70,$B$13:$B$34,H$13:H$34)/(H$47*8.8)),"") -> 0 | I70: =iferror((xlookup($B70,$B$13:$B$34,I$13:I$34)/(I$47*8.8)),"") -> 0 | J70: =iferror((xlookup($B70,$B$13:$B$34,J$13:J$34)/(J$47*8.8)),"") -> 0 | K70: =iferror((xlookup($B70,$B$13:$B$34,K$13:K$34)/(K$47*8.8)),"") -> 334.2246 | L70: =iferror((xlookup($B70,$B$13:$B$34,L$13:L$34)/(L$47*8.8)),"") -> 129.13223 | M70: =iferror((xlookup($B70,$B$13:$B$34,M$13:M$34)/(M$47*8.8)),"") -> 135.28139 | N70: =iferror((xlookup($B70,$B$13:$B$34,N$13:N$34)/(N$47*8.8)),"") -> 135.28139 | O70: =iferror((xlookup($B70,$B$13:$B$34,O$13:O$34)/(O$47*8.8)),"") -> 123.51779 | ... S70: =iferror((xlookup($B70,$B$13:$B$34,S$13:S$34)/(S$47*8.8)),"") -> 129.13223 | T70: =SUMIF('Resumo - TIMESHEETS'!E:E,B70,'Resumo - TIMESHEETS'!L:L) -> 90784.813 | U70: =SUMIF(V70,TRUE,T70) -> 90784.813 | V70: TRUE
B72: Feriados
B73: 44927 | C73: Ano Novo
B74: 45023 | C74: Paixão de Cristo
B75: 45025 | C75: Páscoa
B76: 45026 | C76: Aniversário Município
B77: 45037 | C77: Tiradentes
B78: 45047 | C78: Dia do Trabalhador
B79: 45085 | C79: Corpus Christi
B80: 45176 | C80: independência
B81: 45211 | C81: Nossa Senhora Aparecida
B82: 45230 | C82: Dia de Reforma
B83: 45232 | C83: Finados
B84: 45245 | C84: Proclamação da República
B85: 45285 | C85: Natal

Sheet IRIS
B2: Netzsch Moagem
B3: Pesquisa, Desenvolvimento & Inovação
B4: Formulário de PD&I - Ano 2023 | J4: Incentivado pela Lei do Bem | M4: TRUE
B5: - preencher somente os campos sombreados (cinza) e - adicionar cronograma no formato de imagem ao fim do formulário - preencher um deste para cada projeto de PD&I | J5: Objetiva tornar-se um Ativo | M5: FALSE
J6: Objetiva gerar patente/registro | M6: FALSE
B8: Dossiê do projeto
B9: Dados gerais para identificação e validação do projeto de PD&I
B11: Nome do projeto | E11: IRIS -> IRIS V3
J12: Pesquisa básica | M12: 📑
B13: Classificação do projeto | E13: Pesquisa aplicada | J13: Pesquisa aplicada | M13: 📑
J14: Desenvolvimento experimental | M14: 📑
B15: Objetivos do projeto | E15: O projeto visa reformular o software de automação para equipamentos de moagem a úmido, introduzindo novas funcionalidades e melhorias. O objetivo é revisar e aprimorar os protocolos de comissionamento, configurar dispositivos de acesso remoto, e desenvolver o IRIS V3, um novo sistema de automação. Além disso, o projeto abrange a tradução da interface para o idioma Estoniano e Italiano, a unificação do software para a plataforma Rockwell, e a implementação de funcionalidades avançadas como controle de receita, gerenciamento de falhas, análise de gráficos avançada, e testes de estresse do software.
J16: Inovação tecnológica de produto | M16: 📑
B17: Tipo de inovação | E17: Inovação tecnológica de produto | J17: Inovação tecnológica de processo | M17: 📑
J18: Inovação tecnológica de serviços | M18: 📑
B19: Elemento inovador | E19: O elemento inovador deste projeto é a criação do IRIS V3, um sistema de automação avançado que traz o desenvolvimento de uma biblioteca de objetos, a refatoração de scripts para C#, e a implementação de operações por lotes com controle de receita avançado. A unificação do software para a plataforma Rockwell e a tradução da interface para diferentes idiomas representam um esforço para padronizar e globalizar o software, tornando-o mais acessível e eficiente para um público mais amplo. | J19: - Não podem ser consideradas as inovações organizacionais, comerciais e de marketing
J20: Empresa ou segmento regional | M20: 📑
B21: Nível de inovação | E21: Empresa ou segmento regional | J21: Inovador para o Brasil | M21: 📑
J22: Inovador para o Mundo | M22: 📑
B23: Risco tecnológico | E23: Os riscos tecnológicos incluem desafios na integração de novas funcionalidades com o sistema existente, garantindo a compatibilidade e a estabilidade operacional. A refatoração de scripts para C# e a unificação para a plataforma Rockwell podem apresentar desafios técnicos e riscos de compatibilidade. Além disso, o desenvolvimento de um sistema de automação avançado como o IRIS V3 exige um elevado nível de precisão e confiabilidade, implicando riscos em termos de gerenciamento de falhas e análise de gráficos. A tradução precisa para idiomas estrangeiros também é um desafio, dada a necessidade de manter a clareza técnica e a usabilidade.
B25: Metodologias | E25: A metodologia do projeto segue um processo estruturado e iterativo: Classificação de Feedbacks: Coleta e classificação de sugestões e requisitos dos clientes para entender as necessidades e expectativas. Criação e Validação de Protótipos: Desenvolvimento de protótipos com base nos feedbacks coletados e validação destes com usuários para garantir que as novas funcionalidades atendam às expectativas e requisitos. Desenvolvimento da Funcionalidade: Construção das funcionalidades conforme especificado, com foco na integração eficaz com o sistema existente e na aderência aos padrões de qualidade. Validação em Ambiente de Teste: Testes rigorosos em um ambiente controlado para garantir a estabilidade, segurança e desempenho do software antes da implantação. Liberação para Todos os Usuários: Após a validação bem-sucedida, o software atualizado é disponibilizado para todos os usuários, garantindo uma transição suave e eficaz para a nova versão.
B27: Equipe | E27: Nome Completo | F27: Cargo/Função | G27: Qualificação | H27: !
E28: Alexandre Baseggio | F28: Desenvolvedor | G28: Pós-graduação | H28: FALSE | L28: Técnico | M28: 📑
E29: Eduardo Flohr | F29: Supervisor de Automação | G29: Pós-graduação | H29: FALSE | L29: Graduação
E30: Gabriel Alves Ferraz | F30: Desenvolvedor | G30: Graduação | H30: FALSE | L30: Pós-graduação
E31: Filipe Harbs | F31: Desenvolvedor | G31: Técnico | H31: FALSE | L31: Mestrado
E32: Ivo Ersching | F32: Desenvolvedor | G32: Graduação | H32: FALSE | L32: Doutorado
E33: Lucca Sardá Tonim Matos | F33: Desenvolvedor | G33: Técnico | H33: FALSE
E34: Paulo Fernando Odwazny | F34: Supervisor de Desenvolvimento | G34: Graduação | H34: FALSE
E35: Johann Ribeiro | F35: Desenvolvedor | G35: Técnico | H35: FALSE
E36: Marcos Tribess | F36: Desenvolvedor | G36: Graduação | H36: FALSE
E37: Guilherme Jacques | F37: Desenvolvedor | G37: Graduação | H37: FALSE
E38: Ricardo Bordin | F38: Desenvolvedor | G38: Graduação | H38: FALSE
E39: Gabriel Oliveira | F39: Designer | G39: Graduação | H39: FALSE
E40: Rafael Augusto Barbieri Lobato | F40: Desenvolvedor | G40: Graduação | H40: FALSE
E41: Italo Ebel | F41: Desenvolvedor | G41: Graduação | H41: FALSE
B43: Cronograma
B44: [anexar imagem - preferencialmente Gantt]

Sheet IRIS  TIMESHEET
B2: NETZSCH
B3: Pesquisa, Desenvolvimento & Inovação
B4: Formulário de PD&I - Ano 2023
B5: - preencher somente os campos sombreados (cinza)
I6: Treinamento
I7: Pesquisa
B8: Dossiê do projeto | I8: Desenvolvimento
B9: Atividades de Pesquisa, Desenvolvimento e Inovação | I9: Gestão e outros
H10: =SUM(H12:H57) -> 980.12
B11: RowID | C11: Projeto | D11: Etapa | E11: Colaborador | F11: CPF | G11: Data | H11: Tempo (h) | I11: Classificação | J11: Descrição da atividade e observações
C12: IRIS | D12: Revisão protocolos de comissionamento | E12: Alexandre Baseggio | G12: 44927 | H12: 19.77 | I12: Desenvolvimento | J12: Desenvolvimento PLC
C13: IRIS | D13: Revisão protocolos de comissionamento | E13: Eduardo Flohr | F13: 064.303.159-67 | G13: 44927 | H13: 2.5 | I13: Gestão e outros | J13: Gestão
C14: IRIS | D14: Revisão protocolos de comissionamento | E14: Gabriel Alves Ferraz | F14: 132.105.086-07 | G14: 44927 | H14: 28 | I14: Desenvolvimento | J14: Desenvolvimento IHM
C15: IRIS | D15: Revisão protocolos de comissionamento | E15: Filipe Harbs | G15: 44927 | H15: 22 | I15: Desenvolvimento | J15: Desenvolvimento IHM
C16: IRIS | D16: Revisão protocolos de comissionamento | E16: Ivo Ersching | G16: 44927 | H16: 11 | I16: Pesquisa | J16: Desenvolvimento PLC
C17: IRIS | D17: Aprimorar dados de processo | E17: Filipe Harbs | G17: 44958 | H17: 4 | I17: Desenvolvimento | J17: Desenvolvimento IHM
C18: IRIS | D18: Aprimorar dados de processo | E18: Ivo Ersching | G18: 44958 | H18: 5.5 | I18: Desenvolvimento | J18: Desenvolvimento PLC
C19: IRIS | D19: Aprimorar dados de processo | E19: Eduardo Flohr | F19: 064.303.159-67 | G19: 44958 | H19: 5.5 | I19: Gestão e outros | J19: Gestão
C20: IRIS | D20: Configuração de dispositivo de acesso remoto | E20: Gabriel Alves Ferraz | F20: 132.105.086-07 | G20: 44958 | H20: 33 | I20: Desenvolvimento | J20: Desenvolvimento IHM
C21: IRIS | D21: Configuração de dispositivo de acesso remoto | E21: Lucca Sardá Tonim Matos | F21: 123.342.589-70 | G21: 44958 | H21: 4.33 | I21: Desenvolvimento | J21: Documentação
C22: IRIS | D22: Configuração de dispositivo de acesso remoto | E22: Eduardo Flohr | F22: 064.303.159-67 | G22: 44958 | H22: 6 | I22: Gestão e outros | J22: Gestão
C23: IRIS | D23: IRISV3 - Projetar novo sistema de automação | E23: Eduardo Flohr | F23: 064.303.159-67 | G23: 44958 | H23: 5 | I23: Gestão e outros | J23: Gestão
C24: IRIS | D24: IRISV3 - Projetar novo sistema de automação | E24: Johann Ribeiro | F24: 100.110.019-09 | G24: 44958 | H24: 24 | I24: Desenvolvimento | J24: Documentação
C25: IRIS | D25: IRISV3 - Projetar novo sistema de automação | E25: Paulo Fernando Odwazny | F25: 035.705.119-01 | G25: 44958 | H25: 3 | I25: Pesquisa | J25: Especificação da funcionalidade
C26: IRIS | D26: Aprimorar dados de processo | E26: Filipe Harbs | G26: 44986 | H26: 3.2 | I26: Desenvolvimento | J26: Desenvolvimento IHM
C27: IRIS | D27: Aprimorar dados de processo | E27: Ivo Ersching | G27: 44986 | H27: 17.33 | I27: Desenvolvimento | J27: Desenvolvimento PLC
C28: IRIS | D28: Aprimorar dados de processo | E28: Eduardo Flohr | F28: 064.303.159-67 | G28: 44986 | H28: 15 | I28: Gestão e outros
C29: IRIS | D29: Configuração de dispositivo de acesso remoto | E29: Gabriel Alves Ferraz | F29: 132.105.086-07 | G29: 44986 | H29: 30 | I29: Desenvolvimento | J29: Desenvolvimento IHM
C30: IRIS | D30: Configuração de dispositivo de acesso remoto | E30: Lucca Sardá Tonim Matos | F30: 123.342.589-70 | G30: 44986 | H30: 15.75 | I30: Desenvolvimento | J30: Documentação
C31: IRIS | D31: Configuração de dispositivo de acesso remoto | E31: Eduardo Flohr | F31: 064.303.159-67 | G31: 44986 | H31: 17.5 | I31: Gestão e outros | J31: Gestão
C32: IRIS | D32: Criação de processo de liberação de versão | E32: Gabriel Alves Ferraz | F32: 132.105.086-07 | G32: 44986 | H32: 32.5 | I32: Desenvolvimento | J32: Desenvolvimento IHM
C33: IRIS | D33: Criação de processo de liberação de versão | E33: Alexandre Baseggio | G33: 44986 | H33: 16.85 | I33: Desenvolvimento | J33: Desenvolvimento PLC
C34: IRIS | D34: Criação de processo de liberação de versão | E34: Paulo Fernando Odwazny | F34: 035.705.119-01 | G34: 44986 | H34: 5.5 | I34: Pesquisa | J34: Especificação da funcionalidade
C35: IRIS | D35: IRISV3 - Projetar novo sistema de automação | E35: Alexandre Baseggio | G35: 44986 | H35: 1.92 | I35: Desenvolvimento | J35: Desenvolvimento PLC
C36: IRIS | D36: IRISV3 - Projetar novo sistema de automação | E36: Eduardo Flohr | F36: 064.303.159-67 | G36: 44986 | H36: 26.75 | I36: Gestão e outros | J36: Gestão
C37: IRIS | D37: IRISV3 - Projetar novo sistema de automação | E37: Johann Ribeiro | F37: 100.110.019-09 | G37: 44986 | H37: 86.58 | I37: Desenvolvimento | J37: Documentação
C38: IRIS | D38: IRISV3 - Projetar novo sistema de automação | E38: Paulo Fernando Odwazny | F38: 035.705.119-01 | G38: 44986 | H38: 61.98 | I38: Pesquisa | J38: Especificação da funcionalidade
C39: IRIS | D39: Tradução da Interface para o idioma Estoniano | E39: Gabriel Alves Ferraz | F39: 132.105.086-07 | G39: 45017 | H39: 80.25 | I39: Desenvolvimento | J39: Desenvolvimento IHM
C40: IRIS | D40: Tradução da Interface para o idioma Estoniano | E40: Lucca Sardá Tonim Matos | F40: 123.342.589-70 | G40: 45017 | H40: 15.58 | I40: Desenvolvimento | J40: Documentação
C41: IRIS | D41: Tradução da Interface para o idioma Estoniano | E41: Johann Ribeiro | F41: 100.110.019-09 | G41: 45017 | H41: 25 | I41: Desenvolvimento | J41: Documentação
C42: IRIS | D42: Tradução da Interface para o idioma Estoniano | E42: Eduardo Flohr | F42: 064.303.159-67 | G42: 45017 | H42: 16.58 | I42: Gestão e outros | J42: Gestão
C43: IRIS | D43: Alteração de UPS | E43: Ivo Ersching | G43: 45017 | H43: 25 | I43: Desenvolvimento | J43: Desenvolvimento PLC
C44: IRIS | D44: Alteração de UPS | E44: Eduardo Flohr | F44: 064.303.159-67 | G44: 45017 | H44: 10 | I44: Gestão e outros | J44: Gestão
C45: IRIS | D45: Alteração de UPS | E45: Filipe Harbs | G45: 45017 | H45: 1 | I45: Desenvolvimento | J45: Desenvolvimento IHM
C46: IRIS | D46: Alteração de UPS | E46: Alexandre Baseggio | G46: 45017 | H46: 1.75 | I46: Desenvolvimento | J46: Desenvolvimento PLC
C47: IRIS | D47: Alteração de UPS | E47: Marcos Tribess | G47: 45017 | H47: 7.75 | I47: Desenvolvimento | J47: Desenvolvimento PLC
C48: IRIS | D48: Alteração de UPS | E48: Guilherme Jacques | G48: 45017 | H48: 5.3 | I48: Desenvolvimento | J48: Desenvolvimento PLC
C49: IRIS | D49: Alteração de UPS | E49: Ricardo Bordin | G49: 45017 | H49: 5.67 | I49: Desenvolvimento | J49: Desenvolvimento PLC
C50: IRIS | D50: IRISV3 - Desenvolvimento de bilbioteca de objetos | E50: Eduardo Flohr | F50: 064.303.159-67 | G50: 45017 | H50: 28.17 | I50: Gestão e outros | J50: Gestão
C51: IRIS | D51: IRISV3 - Desenvolvimento de bilbioteca de objetos | E51: Gabriel Oliveira | F51: 085.943.039-12 | G51: 45017 | H51: 54.28 | I51: Desenvolvimento | J51: Desgin UX/UI
C52: IRIS | D52: IRISV3 - Desenvolvimento de bilbioteca de objetos | E52: Filipe Harbs | G52: 45017 | H52: 42.83 | I52: Desenvolvimento | J52: Desenvolvimento IHM
C53: IRIS | D53: IRISV3 - Desenvolvimento de bilbioteca de objetos | E53: Ivo Ersching | G53: 45017 | H53: 19.5 | I53: Desenvolvimento | J53: Desenvolvimento PLC
C54: IRIS | D54: IRISV3 - Desenvolvimento de bilbioteca de objetos | E54: Johann Ribeiro | F54: 100.110.019-09 | G54: 45017 | H54: 40.5 | I54: Desenvolvimento | J54: Documentação
C55: IRIS | D55: IRISV3 - Desenvolvimento de bilbioteca de objetos | E55: Marcos Tribess | G55: 45017 | H55: 3.25 | I55: Desenvolvimento | J55: Desenvolvimento PLC
C56: IRIS | D56: IRISV3 - Desenvolvimento de bilbioteca de objetos | E56: Paulo Fernando Odwazny | F56: 035.705.119-01 | G56: 45017 | H56: 83.25 | I56: Pesquisa | J56: Especificação da funcionalidade
C57: IRIS | D57: Alteração de UPS | E57: Eduardo Flohr | F57: 064.303.159-67 | G57: 45047 | H57: 10 | I57: Gestão e outros | J57: Gestão
C58: IRIS | D58: Alteração de UPS | E58: Gabriel Alves Ferraz | F58: 132.105.086-07 | G58: 45047 | H58: 34 | I58: Desenvolvimento | J58: Desenvolvimento IHM
C59: IRIS | D59: Alteração de UPS | E59: Guilherme Jacques | G59: 45047 | H59: 21.6 | I59: Desenvolvimento | J59: Desenvolvimento PLC
C60: IRIS | D60: Alteração de UPS | E60: Ivo Ersching | G60: 45047 | H60: 4 | I60: Desenvolvimento | J60: Desenvolvimento PLC
C61: IRIS | D61: IRISV3 - Desenvolvimento de bilbioteca de objetos | E61: Eduardo Flohr | F61: 064.303.159-67 | G61: 45047 | H61: 24.5 | I61: Gestão e outros | J61: Gestão
C62: IRIS | D62: IRISV3 - Desenvolvimento de bilbioteca de objetos | E62: Gabriel Oliveira | F62: 085.943.039-12 | G62: 45047 | H62: 202.6 | I62: Desenvolvimento | J62: Desgin UX/UI
C63: IRIS | D63: IRISV3 - Desenvolvimento de bilbioteca de objetos | E63: Filipe Harbs | G63: 45047 | H63: 200.93 | I63: Desenvolvimento | J63: Desenvolvimento IHM
C64: IRIS | D64: IRISV3 - Desenvolvimento de bilbioteca de objetos | E64: Ivo Ersching | G64: 45047 | H64: 89.5 | I64: Desenvolvimento | J64: Desenvolvimento PLC
C65: IRIS | D65: IRISV3 - Desenvolvimento de bilbioteca de objetos | E65: Johann Ribeiro | F65: 100.110.019-09 | G65: 45047 | H65: 40.5 | I65: Desenvolvimento | J65: Documentação
C66: IRIS | D66: IRISV3 - Desenvolvimento de bilbioteca de objetos | E66: Lucca Sardá Tonim Matos | F66: 123.342.589-70 | G66: 45047 | H66: 0.25 | I66: Desenvolvimento | J66: Documentação
C67: IRIS | D67: IRISV3 - Desenvolvimento de bilbioteca de objetos | E67: Marcos Tribess | G67: 45047 | H67: 2.25 | I67: Desenvolvimento | J67: Desenvolvimento PLC
C68: IRIS | D68: IRISV3 - Desenvolvimento de bilbioteca de objetos | E68: Paulo Fernando Odwazny | F68: 035.705.119-01 | G68: 45047 | H68: 84.4 | I68: Desenvolvimento | J68: Especificação da funcionalidade
C69: IRIS | D69: Tradução da Interface para o idioma Italiano | E69: Eduardo Flohr | F69: 064.303.159-67 | G69: 45047 | H69: 8.75 | I69: Desenvolvimento | J69: Gestão
C70: IRIS | D70: Tradução da Interface para o idioma Italiano | E70: Gabriel Alves Ferraz | F70: 132.105.086-07 | G70: 45047 | H70: 50 | I70: Desenvolvimento | J70: Desenvolvimento IHM
C71: IRIS | D71: Tradução da Interface para o idioma Italiano | E71: Johann Ribeiro | F71: 100.110.019-09 | G71: 45047 | H71: 49.33 | I71: Desenvolvimento | J71: Documentação
C72: IRIS | D72: Tradução da Interface para o idioma Italiano | E72: Lucca Sardá Tonim Matos | F72: 123.342.589-70 | G72: 45047 | H72: 6.92 | I72: Desenvolvimento | J72: Documentação
C73: IRIS | D73: Tradução da Interface para o idioma Italiano | E73: Marcos Tribess | G73: 45047 | H73: 5.75 | I73: Desenvolvimento | J73: Desenvolvimento PLC
C74: IRIS | D74: IRISV3 - Desenvolvimento de bilbioteca de objetos | E74: Eduardo Flohr | F74: 064.303.159-67 | G74: 45078 | H74: 47.67 | I74: Gestão e outros | J74: Gestão
C75: IRIS | D75: IRISV3 - Desenvolvimento de bilbioteca de objetos | E75: Gabriel Oliveira | F75: 085.943.039-12 | G75: 45078 | H75: 200.17 | I75: Desenvolvimento | J75: Desgin UX/UI
C76: IRIS | D76: IRISV3 - Desenvolvimento de bilbioteca de objetos | E76: Filipe Harbs | G76: 45078 | H76: 233 | I76: Desenvolvimento | J76: Desenvolvimento IHM
C77: IRIS | D77: IRISV3 - Desenvolvimento de bilbioteca de objetos | E77: Ivo Ersching | G77: 45078 | H77: 121.17 | I77: Desenvolvimento | J77: Desenvolvimento PLC
C78: IRIS | D78: IRISV3 - Desenvolvimento de bilbioteca de objetos | E78: Johann Ribeiro | F78: 100.110.019-09 | G78: 45078 | H78: 123 | I78: Desenvolvimento | J78: Documentação
C79: IRIS | D79: IRISV3 - Desenvolvimento de bilbioteca de objetos | E79: Lucca Sardá Tonim Matos | F79: 123.342.589-70 | G79: 45078 | H79: 25.5 | I79: Desenvolvimento | J79: Documentação
C80: IRIS | D80: IRISV3 - Desenvolvimento de bilbioteca de objetos | E80: Rafael Augusto Barbieri Lobato | G80: 45078 | H80: 77.15 | I80: Desenvolvimento | J80: Desenvolvimento IHM
C81: IRIS | D81: Unificação de software p/ Rockwell | E81: Alexandre Baseggio | G81: 45078 | H81: 21.3 | I81: Desenvolvimento | J81: Desenvolvimento PLC
C82: IRIS | D82: Unificação de software p/ Rockwell | E82: Eduardo Flohr | F82: 064.303.159-67 | G82: 45078 | H82: 7.25 | I82: Gestão e outros | J82: Gestão
C83: IRIS | D83: Unificação de software p/ Rockwell | E83: Gabriel Alves Ferraz | F83: 132.105.086-07 | G83: 45078 | H83: 32 | I83: Desenvolvimento | J83: Desenvolvimento IHM
C84: IRIS | D84: Unificação de software p/ Rockwell | E84: Johann Ribeiro | F84: 100.110.019-09 | G84: 45078 | H84: 3 | I84: Desenvolvimento | J84: Documentação
C85: IRIS | D85: Unificação de software p/ Rockwell | E85: Eduardo Flohr | F85: 064.303.159-67 | G85: 45108 | H85: 8 | I85: Gestão e outros | J85: Gestão
C86: IRIS | D86: Unificação de software p/ Rockwell | E86: Gabriel Alves Ferraz | F86: 132.105.086-07 | G86: 45108 | H86: 14 | I86: Desenvolvimento | J86: Desenvolvimento IHM
C87: IRIS | D87: Unificação de software p/ Rockwell | E87: Ivo Ersching | G87: 45108 | H87: 2 | I87: Desenvolvimento | J87: Desenvolvimento PLC
C88: IRIS | D88: Unificação de software p/ Rockwell | E88: Johann Ribeiro | F88: 100.110.019-09 | G88: 45108 | H88: 18 | I88: Desenvolvimento | J88: Documentação
C89: IRIS | D89: Unificação de software p/ Rockwell | E89: Marcos Tribess | G89: 45108 | H89: 29.75 | I89: Desenvolvimento | J89: Desenvolvimento PLC
C90: IRIS | D90: IRIS V3 - Controle de receita avançado | E90: Eduardo Flohr | F90: 064.303.159-67 | G90: 45108 | H90: 31.5 | I90: Gestão e outros | J90: Gestão
C91: IRIS | D91: IRIS V3 - Controle de receita avançado | E91: Gabriel Oliveira | F91: 085.943.039-12 | G91: 45108 | H91: 159.92 | I91: Desenvolvimento | J91: Desgin UX/UI
C92: IRIS | D92: IRIS V3 - Controle de receita avançado | E92: Filipe Harbs | G92: 45108 | H92: 235.17 | I92: Desenvolvimento | J92: Desenvolvimento IHM
C93: IRIS | D93: IRIS V3 - Controle de receita avançado | E93: Ivo Ersching | G93: 45108 | H93: 170.3 | I93: Desenvolvimento | J93: Desenvolvimento PLC
C94: IRIS | D94: IRIS V3 - Controle de receita avançado | E94: Johann Ribeiro | F94: 100.110.019-09 | G94: 45108 | H94: 39 | I94: Desenvolvimento | J94: Documentação
C95: IRIS | D95: IRIS V3 - Controle de receita avançado | E95: Paulo Fernando Odwazny | F95: 035.705.119-01 | G95: 45108 | H95: 32.5 | I95: Pesquisa | J95: Especificação da funcionalidade
C96: IRIS | D96: IRIS V3 - Controle de receita avançado | E96: Rafael Augusto Barbieri Lobato | G96: 45108 | H96: 157 | I96: Desenvolvimento | J96: Desenvolvimento IHM
C97: IRIS | D97: Refatoração dos scripts p/ C# | E97: Eduardo Flohr | F97: 064.303.159-67 | G97: 45139 | H97: 31 | I97: Gestão e outros | J97: Gestão
C98: IRIS | D98: Refatoração dos scripts p/ C# | E98: Gabriel Alves Ferraz | F98: 132.105.086-07 | G98: 45139 | H98: 11.08 | I98: Desenvolvimento | J98: Desenvolvimento IHM
C99: IRIS | D99: Refatoração dos scripts p/ C# | E99: Guilherme Jacques | G99: 45139 | H99: 30 | I99: Desenvolvimento | J99: Desenvolvimento PLC
C100: IRIS | D100: IRIS V3 - Operação por lotes com controle de receita avançado | E100: Eduardo Flohr | F100: 064.303.159-67 | G100: 45139 | H100: 48.25 | I100: Gestão e outros | J100: Gestão
C101: IRIS | D101: IRIS V3 - Operação por lotes com controle de receita avançado | E101: Gabriel Oliveira | F101: 085.943.039-12 | G101: 45139 | H101: 179.42 | I101: Desenvolvimento | J101: Desgin UX/UI
...

Sheet IRIS MILESTONES
B2: NETZSCH
B3: Pesquisa, Desenvolvimento & Inovação
B4: Formulário de PD&I - Ano 2023
B5: - preencher somente os campos sombreados (cinza)
B8: Dossiê do projeto | E8: Um objetivo a ser concluído durante esta etapa. Podemos ter vários em cada etapa. | G8: Uma data estimada que atualizará após etapa concluída
B9: Etapas e Milestones
B11: Projeto | C11: Etapa | D11: Principais atividades | E11: Milestones | F11: Data inicial | G11: Data conclusão | H11: Observações do gestor
B12: IRIS | C12: Revisão protocolos de comissionamento | D12: Criação de documento de protocolo de configuração para registro de qualidade do equipamento finalizado | E12: Finalização da documentação revisada | F12: 44927 | G12: 44957
B13: IRIS | C13: Aprimorar dados de processo | D13: Desenvolvimento da vsualização da viscodidade, densidade e potência líquida do equipamento para análise de processo na interface de operação | E13: Conclusão e validação com o cliente | F13: 410200 | G13: 45016
B14: IRIS | C14: Configuração de dispositivo de acesso remoto | D14: Desenvolvimento de acesso direto da configuração doi sipositivo de VPM pela interface de operação | E14: Finalização da etapa | F14: 44958 | G14: 45016
B15: IRIS | C15: IRISV3 - Projetar novo sistema de automação | D15: Pesquisa, documentação, requisitos e Mockups da nova versão | E15: Finalização da etapa | F15: 44958 | G15: 45016
B16: IRIS | C16: Criação de processo de liberação de versão | D16: Documentação do protocolo de liberação de versão com checklist de QA | E16: Finalização da etapa | F16: 44986 | G16: 45016
B17: IRIS | C17: Tradução da Interface para o idioma Estoniano | D17: Exportação dos textos, tradução , importação e revisão da interface para o idioma Estoniano | E17: Finalização da etapa | F17: 45017 | G17: 45046
B18: IRIS | C18: Alteração de UPS | D18: Alteração de UPS com bateria para capacitor | E18: Finalização da etapa | F18: 45017 | G18: 45077
B19: IRIS | C19: IRIS V3 - Desenvolvimento de bilbioteca de objetos | D19: Criação de biblioteca de objetos para agilziar o processo de desenvolvimento. Blocos para o PLC e SmarObjects para o SCADA | E19: Finalização da etapa | F19: 45748 | G19: 45107
B20: IRIS | C20: Tradução da Interface para o idioma Italiano | D20: Exportação dos textos, tradução , importação e revisão da interface para o idioma Italiano | E20: Finalização da etapa | F20: 45047 | G20: 45077
B21: IRIS | C21: Unificação de software p/ Rockwell | D21: Criação de um úncio código fonte para p/ controladores Rockwell. | E21: Finalização da etapa | F21: 45078 | G21: 45138
B22: IRIS | C22: IRIS V3 - Controle de receita avançado | D22: Implementaçaõ de processo de moagem por passadas com cálculo de energia específica. | E22: Finalização da etapa | F22: 45108 | G22: 45138
B23: IRIS | C23: Refatoração dos scripts p/ C# | D23: Reafatoração de todas as lógicas dos scrips para a linguagem C# com intuito de melhora de performance ecompatibildiade futura. | E23: Finalização da etapa | F23: 45139 | G23: 45230
... B28: IRIS | C28: IRIS V3 - Testes de estresse do software | D28: Procedimento de testes de estresse no software em equipamentos internos e no cliente | E28: Finalização da etapa | F28: 45231 | G28: 45282

Sheet IRIS TERCEIROS
B2: NETZSCH
B3: Pesquisa, Desenvolvimento & Inovação
B4: Formulário de PD&I - Ano 2023
B5: - preencher somente os campos sombreados (cinza)
B8: Dossiê do projeto
B9: Investimentos com terceiros
B11: Projeto | C11: Etapa | D11: Fornecedor | E11: CNPJ | F11: Nota fiscal | G11: Valor | H11: Data | I11: Descrição da Atividade | J11: Objetivo do gasto e eventual info de rateio
B12: IRIS | C12: IRISV3 - Desenvolvimento de bilbioteca de objetos | D12: KMCC Equipamentos Elétricos Ltda | E12: 05.974.479/0001-80 | F12: NFS-e2128 | G12: 572 | H12: 45017 | I12: Desenvolvimento IHM | J12: Total nota fiscal: R$ 8931. Rateio: 6,4 %
B13: IRIS | C13: Todas as etapas | D13: JAV AUTOMACAO INDUSTRIAL LTDA | E13: 82.731.779/0002-60 | F13: NFS-e1363 | G13: 9963.35 | H13: 45065 | I13: Serviço de manutenção de acesso remoto TALK2M | J13: Total nota fiscal: R$ 9963,35. Rateio: 100 %
B14: IRIS | C14: Todas as etapas | D14: JAV AUTOMACAO INDUSTRIAL LTDA | E14: 82.731.779/0002-60 | F14: NFS-e1373 | G14: 28380.48 | H14: 45082 | I14: Licenças de desenvolvimento ROCKWELL | J14: Total nota fiscal: R$ 28380,48. Rateio: 100 %
B15: IRIS | C15: Todas as etapas | D15: SIEMENS INFRAESTRUTURA E INDÚSTRIA LTDA. | E15: 34.776.007/0003-83 | F15: NFS-e7876 | G15: 19768.3 | H15: 45141 | I15: Licenças de desenvolvimento SIEMENS | J15: Total nota fiscal: R$ 19768,3. Rateio: 100 %
B16: IRIS | C16: IRISV3 - Desenvolvimento de bilbioteca de objetos | D16: KMCC Equipamentos Elétricos Ltda | E16: 05.974.479/0001-80 | F16: NFS-e2193 | G16: 15123 | H16: 45170 | I16: Desenvolvimento IHM | J16: Total nota fiscal: R$ 17375. Rateio: 87,04 %
B17: IRIS | C17: IRISV3 - Desenvolvimento de bilbioteca de objetos | D17: KMCC Equipamentos Elétricos Ltda | E17: 05.974.479/0001-80 | F17: NFS-e2218 | G17: 15045 | H17: 45200 | I17: Desenvolvimento IHM | J17: Total nota fiscal: R$ 20052,5. Rateio: 75,03 %
B18: IRIS | C18: IRISV3 - Desenvolvimento de bilbioteca de objetos | D18: KMCC Equipamentos Elétricos Ltda | E18: 05.974.479/0001-80 | F18: NFS-e2228 | G18: 16820 | H18: 45231 | I18: Desenvolvimento IHM | J18: Total nota fiscal: R$ 17962,5. Rateio: 93,64 %

Sheet NOTIFY
B2: Netzsch Moagem
B3: Pesquisa, Desenvolvimento & Inovação
B4: Formulário de PD&I - Ano 2023 | J4: Incentivado pela Lei do Bem | M4: TRUE
B5: - preencher somente os campos sombreados (cinza) e - adicionar cronograma no formato de imagem ao fim do formulário - preencher um deste para cada projeto de PD&I | J5: Objetiva tornar-se um Ativo | M5: FALSE
J6: Objetiva gerar patente/registro | M6: FALSE
B8: Dossiê do projeto
B9: Dados gerais para identificação e validação do projeto de PD&I
B11: Nome do projeto | E11: Notify - Novas funcionalidades
J12: Pesquisa básica | M12: 📑
B13: Classificação do projeto | E13: Desenvolvimento experimental | J13: Pesquisa aplicada | M13: 📑
J14: Desenvolvimento experimental | M14: 📑
B15: Objetivos do projeto | E15: O objetivo deste projeto é desenvolver novas funcionalidades para aprimorar a análise de dados em máquinas e enriquecer a experiência do usuário. As funcionalidades propostas incluem a criação de ordens de serviço, o planejamento de manutenções preventivas, a realização de testes de penetração para reforçar a cibersegurança, o gerenciamento de licenças, a duplicação de configurações de máquinas existentes, o cadastro de tarefas de manutenção preventiva, e a implementação de novas capacidades digitais na plataforma NETZSCH G&D Digital Products Home. Além disso, o projeto engloba a criação de relatórios de lotes, a exportação de dados para o Excel, a adequação do Gateway para o IRIS V3 e o desenvolvimento de templates de gráficos.
J16: Inovação tecnológica de produto | M16: 📑
B17: Tipo de inovação | E17: Inovação tecnológica de serviços | J17: Inovação tecnológica de processo | M17: 📑
J18: Inovação tecnológica de serviços | M18: 📑
B19: Elemento inovador | E19: As inovações do projeto residem na integração de funcionalidades avançadas que não só aprimoram a gestão e manutenção de máquinas, mas também elevam a segurança e a eficiência dos processos. A inclusão de testes de penetração (cybersegurança) é particularmente inovadora, pois aborda a crescente preocupação com a segurança digital em sistemas automatizados. A adequação do Gateway para o IRIS V3 representa uma inovação tecnológica que alinha o software às necessidades atuais de automação e controle de processos. | J19: - Não podem ser consideradas as inovações organizacionais, comerciais e de marketing
J20: Empresa ou segmento regional | M20: 📑
B21: Nível de inovação | E21: Empresa ou segmento regional | J21: Inovador para o Brasil | M21: 📑
J22: Inovador para o Mundo | M22: 📑
B23: Risco tecnológico | E23: Os riscos tecnológicos incluem a integração eficaz de novas funcionalidades no sistema existente, garantindo que todas as adições funcionem harmoniosamente sem causar interrupções ou falhas. Os testes de penetração exigem um alto grau de especialização e precisão para identificar e mitigar vulnerabilidades de segurança sem comprometer a funcionalidade do sistema. A implementação de funcionalidades para exportação de dados e a criação de relatórios precisam garantir a precisão e a integridade dos dados. Além disso, a adaptação do software existente para se integrar ao IRIS V3 pode apresentar desafios de compatibilidade e estabilidade.
B25: Metodologias | E25: Metodologia A metodologia do projeto consiste em várias etapas estruturadas: Classificação de Feedbacks: Inicialmente, haverá uma coleta e análise de sugestões e requisitos dos clientes para entender as necessidades do usuário e do mercado. Criação e Validação de Protótipos: Desenvolvimento de protótipos baseados nos feedbacks coletados, seguido pela validação destes com usuários finais, garantindo que as funcionalidades propostas sejam práticas e atendam às expectativas dos usuários. Desenvolvimento da Funcionalidade: Construção e integração das novas funcionalidades ao sistema, focando na eficiência, usabilidade e segurança. Validação em Ambiente de Teste: Antes da implementação final, as funcionalidades serão rigorosamente testadas em um ambiente controlado para garantir que operem conforme o esperado. Liberação para Todos os Usuários: Após a validação e refinamento bem-sucedidos, as funcionalidades serão liberadas para todos os usuários, com suporte contínuo para garantir uma transição suave e eficaz.
B27: Equipe | E27: Nome Completo | F27: Cargo/Função | G27: Qualificação | H27: !
E28: Bruno katzjarowksi | F28: Desenvolvedor | H28: FALSE | L28: Técnico | M28: 📑
E29: Gabriel Possamai | F29: Desenvolvedor | H29: FALSE | L29: Graduação
E30: Lucca Sardá Tonim Matos | F30: Desenvolvedor | H30: FALSE | L30: Pós-graduação
E31: Arthur Muniz | F31: Desenvolvedor | H31: FALSE | L31: Mestrado
E32: Cleiton Capristano | F32: Desenvolvedor | G32: Graduação | H32: FALSE | L32: Doutorado
E33: Gabriel Alves Ferraz | F33: Desenvolvedor | G33: Graduação | H33: FALSE
E34: Alberto Reuters | F34: Gerente de Desenvolvimento e Automação | G34: Mestrado | H34: FALSE
E35: Eduardo Flohr | F35: Supervisor de Automação | G35: Pós-graduação | H35: FALSE
E36: Paulo Fernando Odwazny | F36: Supervisor de Desenvolvimento | G36: Graduação | H36: FALSE
E37: Johann Ribeiro | F37: Desenvolvedor | H37: FALSE
E38: Gabriel Oliveira | F38: Designer | G38: Graduação | H38: FALSE
E39: Italo Ebel | F39: Desenvolvedor | H39: FALSE
B41: Cronograma
B42: [anexar imagem - preferencialmente Gantt]

Sheet NOTIFY TIMESHEET
B2: NETZSCH
B3: Pesquisa, Desenvolvimento & Inovação
B4: Formulário de PD&I - Ano 2023
B5: - preencher somente os campos sombreados (cinza)
I6: Treinamento
I7: Pesquisa
B8: Dossiê do projeto | I8: Desenvolvimento
B9: Atividades de Pesquisa, Desenvolvimento e Inovação | I9: Gestão e outros
H10: =SUM(H12:H106) -> 9341
B11: RowID | C11: Projeto | D11: Etapa | E11: Colaborador | F11: CPF | G11: Data | H11: Tempo (h) | I11: Classificação | J11: Descrição da atividade e observações
C12: Notify | D12: Criação de ordens de serviço | E12: Bruno katzjarowksi | F12: 080.850.859-84 | G12: 44927 | H12: 166 | I12: Desenvolvimento | J12: Desenvolvimento Backend
C13: Notify | D13: Criação de ordens de serviço | E13: Gabriel Possamai | F13: 085.815.809-47 | G13: 44927 | H13: 125 | I13: Desenvolvimento | J13: Desenvolvimento Frontend
C14: Notify | D14: Criação de ordens de serviço | E14: Lucca Sardá Tonim Matos | F14: 123.342.589-70 | G14: 44927 | H14: 3 | I14: Gestão e outros | J14: Testes
C15: Notify | D15: Planejamento de manutenções preventivas | E15: Arthur Muniz | F15: 037.196.611-64 | G15: 44927 | H15: 163 | I15: Desenvolvimento | J15: Desenvolvimento Backend
C16: Notify | D16: Planejamento de manutenções preventivas | E16: Cleiton Capristano | F16: 068.504.079-88 | G16: 44927 | H16: 175 | I16: Desenvolvimento | J16: Desenvolvimento Frontend
C17: Notify | D17: Planejamento de manutenções preventivas | E17: Gabriel Alves Ferraz | F17: 132.105.086-07 | G17: 44927 | H17: 18 | I17: Gestão e outros | J17: Testes
C18: Notify | D18: Teste de penetração (cybersegurança) | E18: Alberto Reuters | F18: 041.176.229-00 | G18: 44927 | H18: 2 | I18: Gestão e outros | J18: Gestão
C19: Notify | D19: Teste de penetração (cybersegurança) | E19: Eduardo Flohr | F19: 064.303.159-67 | G19: 44927 | H19: 13 | I19: Pesquisa | J19: Especificação dos principais testes
C20: Notify | D20: Criação de ordens de serviço | E20: Bruno katzjarowksi | F20: 080.850.859-84 | G20: 44958 | H20: 171 | I20: Desenvolvimento | J20: Desenvolvimento Backend
C21: Notify | D21: Criação de ordens de serviço | E21: Lucca Sardá Tonim Matos | F21: 123.342.589-70 | G21: 44958 | H21: 17 | I21: Gestão e outros | J21: Testes
C22: Notify | D22: Planejamento de manutenções preventivas | E22: Arthur Muniz | F22: 037.196.611-64 | G22: 44958 | H22: 179 | I22: Desenvolvimento | J22: Desenvolvimento Backend
C23: Notify | D23: Planejamento de manutenções preventivas | E23: Cleiton Capristano | F23: 068.504.079-88 | G23: 44958 | H23: 182 | I23: Desenvolvimento | J23: Desenvolvimento Frontend
... C106: Notify | D106: Adequação do Gateway para o IRIS V3 | E106: Eduardo Flohr | F106: 064.303.159-67 | G106: 45261 | H106: 40 | I106: Pesquisa | J106: Especificação da funcionalidade

Sheet NOTIFY MILESTONES
B2: NETZSCH
B3: Pesquisa, Desenvolvimento & Inovação
B4: Formulário de PD&I - Ano 2023
B5: - preencher somente os campos sombreados (cinza)
B8: Dossiê do projeto | E8: Um objetivo a ser concluído durante esta etapa. Podemos ter vários em cada etapa. | G8: Uma data estimada que atualizará após etapa concluída
B9: Etapas e Milestones
B11: Projeto | C11: Etapa | D11: Principais atividades | E11: Milestones | F11: Data inicial | G11: Data conclusão | H11: Observações do gestor
B12: Notify | C12: Criação de ordens de serviço | D12: Criação de cadastro e visualização de ordens de serviço das manutenções preventivas | E12: Lançamento da funcionalidade | F12: 44866 | G12: 44986
B13: Notify | C13: Planejamento de manutenções preventivas | D13: Planejamento a acompanhamento da realização das manutenções preventivas | E13: Lançamento da funcionalidade | F13: 44866 | G13: 44986
B14: Notify | C14: Teste de penetração (cybersegurança) | D14: Realização de testes de penetração de cybersegurança e correção de eventuais vulnerabilidades | E14: Teste de penetração realizado e vulnerabilidades corrigidas | F14: 44927 | G14: 45107
B15: Notify | C15: Gerencimeno de licenças | D15: Gerenciar as licenças compradas pelos cliente | E15: Lançamento da funcionalidade | F15: 44958 | G15: 45077
B16: Notify | C16: Duplicar máquinas existentes | D16: Duplicar a configuração de máquinas existentes | E16: Lançamento da funcionalidade | F16: 44958 | G16: 45077
B17: Notify | C17: Cadastro de tarefas de manutenção preventiva | D17: Cadastro das tarefas de manutenção preventiva | E17: Lançamento da funcionalidade | F17: 45047 | G17: 45107
B18: Notify | C18: NETZSCH G&D Digital Products Home | D18: Portal para acesso de todos os produtos digitais da NETZSCH G&D | E18: Lançamento da funcionalidade | F18: 45108 | G18: 45199
B19: Notify | C19: Relatório de lotes | D19: Relatório dos lotes produzidos pelas máquinas NETZSCH | E19: Documentação para apresentação ao Board | F19: 45108 | G19: 45350
B20: Notify | C20: Exportar dados para o Excel | D20: Exportar dados do Notify para aquivo de format Microsoft Excel | E20: Lançamento da funcionalidade | F20: 45170 | G20: 45291
B21: Notify | C21: Adequação do Gateway para o IRIS V3 | D21: Gateway para envio dos dados de máquina para os servidores do Notify | E21: Lançamento da funcionalidade | F21: 45170 | G21: 45382
B22: Notify | C22: Templates de gráficos | D22: Modelo de gráfico para comparação de sensores | E22: Lançamento da funcionalidade | F22: 45200 | G22: 45382

Sheet NOTIFY TERCEIROS
B2: NETZSCH
B3: Pesquisa, Desenvolvimento & Inovação
B4: Formulário de PD&I - Ano 2023
B5: - preencher somente os campos sombreados (cinza)
B8: Dossiê do projeto
B9: Investimentos com terceiros
B11: Projeto | C11: Etapa | D11: Fornecedor | E11: CNPJ | F11: Nota fiscal | G11: Valor | H11: Data | I11: Descrição da Atividade | J11: Objetivo do gasto e eventual info de rateio
B12: Notify | C12: Criação de ordens de serviço | D12: Materialize Serviços Digitais Ltda | E12: 34.269.716/0001-00 | F12: 338 | G12: 34850 | H12: 44929 | I12: Agênciamento de serviços de desenvovimento de software | J12: Total nota fiscal: R$ 69700. Rateio: 50 %
B13: Notify | C13: Planejamento de manutenções preventivas | D13: Materialize Serviços Digitais Ltda | E13: 34.269.716/0001-00 | F13: 338 | G13: 34850 | H13: 44929 | I13: Agênciamento de serviços de desenvovimento de software | J13: Total nota fiscal: R$ 69700. Rateio: 50 %
B14: Notify | C14: Criação de ordens de serviço | D14: Amazon AWS Serviços Brasil Ltda | E14: 23.412.247/0001-10 | F14: 1684279_TRARB7GL | G14: 4059.07 | H14: 44959 | I14: Custo da infraestrutura em nuvem | J14: Total nota fiscal: R$ 8118,14. Rateio: 50 %
B15: Notify | C15: Planejamento de manutenções preventivas | D15: Amazon AWS Serviços Brasil Ltda | E15: 23.412.247/0001-10 | F15: 1684279_TRARB7GL | G15: 4059.07 | H15: 44959 | I15: Custo da infraestrutura em nuvem | J15: Total nota fiscal: R$ 8118,14. Rateio: 50 %
B16: Notify | C16: Teste de penetração (cybersegurança) | D16: XLABS ON SECURITY SEGURANCA DA INFORMACAO LTDA | E16: 30.162.109/0001-96 | F16: 202324 | G16: 4850 | H16: 44960 | I16: Serviços prestados em segurança da informação | J16: Total nota fiscal: R$ 4850. Rateio: 100 %
B17: Notify | C17: Criação de ordens de serviço | D17: Materialize Serviços Digitais Ltda | E17: 34.269.716/0001-00 | F17: 377 | G17: 34850 | H17: 44960 | I17: Agênciamento de serviços de desenvovimento de software | J17: Total nota fiscal: R$ 69700. Rateio: 50 %
B18: Notify | C18: Planejamento de manutenções preventivas | D18: Materialize Serviços Digitais Ltda | E18: 34.269.716/0001-00 | F18: 377 | G18: 34850 | H18: 44960 | I18: Agênciamento de serviços de desenvovimento de software | J18: Total nota fiscal: R$ 69700. Rateio: 50 %
B19: Notify | C19: Criação de ordens de serviço | D19: Amazon AWS Serviços Brasil Ltda | E19: 23.412.247/0001-10 | F19: 1834979_ZLH5AEKP | G19: 1907.88 | H19: 44987 | I19: Custo da infraestrutura em nuvem | J19: Total nota fiscal: R$ 7631,54. Rateio: 25 %
B20: Notify | C20: Planejamento de manutenções preventivas | D20: Amazon AWS Serviços Brasil Ltda | E20: 23.412.247/0001-10 | F20: 1834979_ZLH5AEKP | G20: 1907.88 | H20: 44987 | I20: Custo da infraestrutura em nuvem | J20: Total nota fiscal: R$ 7631,54. Rateio: 25 %
B21: Notify | C21: Gerencimeno de licenças | D21: Amazon AWS Serviços Brasil Ltda | E21: 23.412.247/0001-10 | F21: 1834979_ZLH5AEKP | G21: 1907.88 | H21: 44987 | I21: Custo da infraestrutura em nuvem | J21: Total nota fiscal: R$ 7631,54. Rateio: 25 %
B22: Notify | C22: Duplicar máquinas existentes | D22: Amazon AWS Serviços Brasil Ltda | E22: 23.412.247/0001-10 | F22: 1834979_ZLH5AEKP | G22: 1907.88 | H22: 44987 | I22: Custo da infraestrutura em nuvem | J22: Total nota fiscal: R$ 7631,54. Rateio: 25 %
B23: Notify | C23: Criação de ordens de serviço | D23: Materialize Serviços Digitais Ltda | E23: 34.269.716/0001-00 | F23: 408 | G23: 17425 | H23: 44991 | I23: Agênciamento de serviços de desenvovimento de software | J23: Total nota fiscal: R$ 69700. Rateio: 25 %
B24: Notify | C24: Planejamento de manutenções preventivas | D24: Materialize Serviços Digitais Ltda | E24: 34.269.716/0001-00 | F24: 408 | G24: 17425 | H24: 44991 | I24: Agênciamento de serviços de desenvovimento de software | J24: Total nota fiscal: R$ 69700. Rateio: 25 %
B25: Notify | C25: Gerencimeno de licenças | D25: Materialize Serviços Digitais Ltda | E25: 34.269.716/0001-00 | F25: 408 | G25: 17425 | H25: 44991 | I25: Agênciamento de serviços de desenvovimento de software | J25: Total nota fiscal: R$ 69700. Rateio: 25 %
B26: Notify | C26: Duplicar máquinas existentes | D26: Materialize Serviços Digitais Ltda | E26: 34.269.716/0001-00 | F26: 408 | G26: 17425 | H26: 44991 | I26: Agênciamento de serviços de desenvovimento de software | J26: Total nota fiscal: R$ 69700. Rateio: 25 %
B27: Notify | C27: Teste de penetração (cybersegurança) | D27: XLABS ON SECURITY SEGURANCA DA INFORMACAO LTDA | E27: 30.162.109/0001-96 | F27: 202369 | G27: 4850 | H27: 44992 | I27: Serviços prestados em segurança da informação | J27: Total nota fiscal: R$ 4850. Rateio: 100 %
B28: Notify | C28: Criação de ordens de serviço | D28: Amazon AWS Serviços Brasil Ltda | E28: 23.412.247/0001-10 | F28: 1851758_THE47Z4R | G28: 2101.47 | H28: 45018 | I28: Custo da infraestrutura em nuvem | J28: Total nota fiscal: R$ 8405,9. Rateio: 25 %
B29: Notify | C29: Planejamento de manutenções preventivas | D29: Amazon AWS Serviços Brasil Ltda | E29: 23.412.247/0001-10 | F29: 1851758_THE47Z4R | G29: 2101.47 | H29: 45018 | I29: Custo da infraestrutura em nuvem | J29: Total nota fiscal: R$ 8405,9. Rateio: 25 %
B30: Notify | C30: Gerencimeno de licenças | D30: Amazon AWS Serviços Brasil Ltda | E30: 23.412.247/0001-10 | F30: 1851758_THE47Z4R | G30: 2101.47 | H30: 45018 | I30: Custo da infraestrutura em nuvem | J30: Total nota fiscal: R$ 8405,9. Rateio: 25 %
B31: Notify | C31: Duplicar máquinas existentes | D31: Amazon AWS Serviços Brasil Ltda | E31: 23.412.247/0001-10 | F31: 1851758_THE47Z4R | G31: 2101.47 | H31: 45018 | I31: Custo da infraestrutura em nuvem | J31: Total nota fiscal: R$ 8405,9. Rateio: 25 %
B32: Notify | C32: Criação de ordens de serviço | D32: Materialize Serviços Digitais Ltda | E32: 34.269.716/0001-00 | F32: 439 | G32: 17425 | H32: 45022 | I32: Agênciamento de serviços de desenvovimento de software | J32: Total nota fiscal: R$ 69700. Rateio: 25 %
B33: Notify | C33: Planejamento de manutenções preventivas | D33: Materialize Serviços Digitais Ltda | E33: 34.269.716/0001-00 | F33: 439 | G33: 17425 | H33: 45022 | I33: Agênciamento de serviços de desenvovimento de software | J33: Total nota fiscal: R$ 69700. Rateio: 25 %
B34: Notify | C34: Gerencimeno de licenças | D34: Materialize Serviços Digitais Ltda | E34: 34.269.716/0001-00 | F34: 439 | G34: 17425 | H34: 45022 | I34: Agênciamento de serviços de desenvovimento de software | J34: Total nota fiscal: R$ 69700. Rateio: 25 %
B35: Notify | C35: Duplicar máquinas existentes | D35: Materialize Serviços Digitais Ltda | E35: 34.269.716/0001-00 | F35: 439 | G35: 17425 | H35: 45022 | I35: Agênciamento de serviços de desenvovimento de software | J35: Total nota fiscal: R$ 69700. Rateio: 25 %
B36: Notify | C36: Gerencimeno de licenças | D36: Amazon AWS Serviços Brasil Ltda | E36: 23.412.247/0001-10 | F36: 1974603_J4XEGDTG | G36: 3917.99 | H36: 45048 | I36: Custo da infraestrutura em nuvem | J36: Total nota fiscal: R$ 7835,98. Rateio: 50 %
B37: Notify | C37: Duplicar máquinas existentes | D37: Amazon AWS Serviços Brasil Ltda | E37: 23.412.247/0001-10 | F37: 1974603_J4XEGDTG | G37: 3917.99 | H37: 45048 | I37: Custo da infraestrutura em nuvem | J37: Total nota fiscal: R$ 7835,98. Rateio: 50 %
B38: Notify | C38: Gerencimeno de licenças | D38: Materialize Serviços Digitais Ltda | E38: 34.269.716/0001-00 | F38: 475 | G38: 34000 | H38: 45055 | I38: Agênciamento de serviços de desenvovimento de software | J38: Total nota fiscal: R$ 68000. Rateio: 50 %
B39: Notify | C39: Duplicar máquinas existentes | D39: Materialize Serviços Digitais Ltda | E39: 34.269.716/0001-00 | F39: 475 | G39: 34000 | H39: 45055 | I39: Agênciamento de serviços de desenvovimento de software | J39: Total nota fiscal: R$ 68000. Rateio: 50 %
B40: Notify | C40: Gerencimeno de licenças | D40: Materialize Serviços Digitais Ltda | E40: 34.269.716/0001-00 | F40: 497 | G40: 23233.33 | H40: 45078 | I40: Agênciamento de serviços de desenvovimento de software | J40: Total nota fiscal: R$ 69700. Rateio: 33,33 %
B41: Notify | C41: Duplicar máquinas existentes | D41: Materialize Serviços Digitais Ltda | E41: 34.269.716/0001-00 | F41: 497 | G41: 23233.33 | H41: 45078 | I41: Agênciamento de serviços de desenvovimento de software | J41: Total nota fiscal: R$ 69700. Rateio: 33,33 %
B42: Notify | C42: Cadastro de tarefas de manutenção preventiva | D42: Materialize Serviços Digitais Ltda | E42: 34.269.716/0001-00 | F42: 497 | G42: 23233.33 | H42: 45078 | I42: Agênciamento de serviços de desenvovimento de software | J42: Total nota fiscal: R$ 69700. Rateio: 33,33 %
B43: Notify | C43: Gerencimeno de licenças | D43: Amazon AWS Serviços Brasil Ltda | E43: 23.412.247/0001-10 | F43: 2073356_N3RQWJJ4 | G43: 2669.23 | H43: 45079 | I43: Custo da infraestrutura em nuvem | J43: Total nota fiscal: R$ 8007,7. Rateio: 33,33 %
B44: Notify | C44: Duplicar máquinas existentes | D44: Amazon AWS Serviços Brasil Ltda | E44: 23.412.247/0001-10 | F44: 2073356_N3RQWJJ4 | G44: 2669.23 | H44: 45079 | I44: Custo da infraestrutura em nuvem | J44: Total nota fiscal: R$ 8007,7. Rateio: 33,33 %
B45: Notify | C45: Cadastro de tarefas de manutenção preventiva | D45: Amazon AWS Serviços Brasil Ltda | E45: 23.412.247/0001-10 | F45: 2073356_N3RQWJJ4 | G45: 2669.23 | H45: 45079 | I45: Custo da infraestrutura em nuvem | J45: Total nota fiscal: R$ 8007,7. Rateio: 33,33 %
B46: Notify | C46: Cadastro de tarefas de manutenção preventiva | D46: Amazon AWS Serviços Brasil Ltda | E46: 23.412.247/0001-10 | F46: 2135752_9VMHLMTL | G46: 8323.82 | H46: 45109 | I46: Custo da infraestrutura em nuvem | J46: Total nota fiscal: R$ 8323,82. Rateio: 100 %
B47: Notify | C47: Cadastro de tarefas de manutenção preventiva | D47: Materialize Serviços Digitais Ltda | E47: 34.269.716/0001-00 | F47: 524 | G47: 69700 | H47: 45110 | I47: Agênciamento de serviços de desenvovimento de software | J47: Total nota fiscal: R$ 69700. Rateio: 100 %
B48: Notify | C48: NETZSCH G&D Digital Products Home | D48: Materialize Serviços Digitais Ltda | E48: 34.269.716/0001-00 | F48: 539 | G48: 69700 | H48: 45139 | I48: Agênciamento de serviços de desenvovimento de software | J48: Total nota fiscal: R$ 69700. Rateio: 100 %
B49: Notify | C49: NETZSCH G&D Digital Products Home | D49: Amazon AWS Serviços Brasil Ltda | E49: 23.412.247/0001-10 | F49: 2227234_KD4PPGBK | G49: 10629.3 | H49: 45140 | I49: Custo da infraestrutura em nuvem | J49: Total nota fiscal: R$ 10629,3. Rateio: 100 %
B50: Notify | C50: Adequação do Gateway para o IRIS V3 | D50: MOUT S SOLUCOES EM TECNOLOGIA DA INFORMATICA LTDA | E50: 25.056.849/0001-08 | F50: 2889 | G50: 27000 | H50: 45148 | I50: ALOCAÇÃO PROFISSIONAL: Análise e desenvolvimento de sistemas | J50: Total nota fiscal: R$ 27000. Rateio: 100 %
B51: Notify | C51: NETZSCH G&D Digital Products Home | D51: Materialize Serviços Digitais Ltda | E51: 34.269.716/0001-00 | F51: 549 | G51: 34850 | H51: 45170 | I51: Agênciamento de serviços de desenvovimento de software | J51: Total nota fiscal: R$ 69700. Rateio: 50 %
B52: Notify | C52: Relatório de lotes | D52: Materialize Serviços Digitais Ltda | E52: 34.269.716/0001-00 | F52: 549 | G52: 34850 | H52: 45170 | I52: Agênciamento de serviços de desenvovimento de software | J52: Total nota fiscal: R$ 69700. Rateio: 50 %
B53: Notify | C53: NETZSCH G&D Digital Products Home | D53: Amazon AWS Serviços Brasil Ltda | E53: 23.412.247/0001-10 | F53: 2385112_EMIUSLCC | G53: 5436.5 | H53: 45172 | I53: Custo da infraestrutura em nuvem | J53: Total nota fiscal: R$ 10873,01. Rateio: 50 %
B54: Notify | C54: Relatório de lotes | D54: Amazon AWS Serviços Brasil Ltda | E54: 23.412.247/0001-10 | F54: 2385112_EMIUSLCC | G54: 5436.5 | H54: 45172 | I54: Custo da infraestrutura em nuvem | J54: Total nota fiscal: R$ 10873,01. Rateio: 50 %
B55: Notify | C55: NETZSCH G&D Digital Products Home | D55: Amazon AWS Serviços Brasil Ltda | E55: 23.412.247/0001-10 | F55: 2430376_4MVGWINA | G55: 3585.26 | H55: 45201 | I55: Custo da infraestrutura em nuvem | J55: Total nota fiscal: R$ 10755,78. Rateio: 33,33 %
B56: Notify | C56: Relatório de lotes | D56: Amazon AWS Serviços Brasil Ltda | E56: 23.412.247/0001-10 | F56: 2430376_4MVGWINA | G56: 3585.26 | H56: 45201 | I56: Custo da infraestrutura em nuvem | J56: Total nota fiscal: R$ 10755,78. Rateio: 33,33 %
B57: Notify | C57: Exportar dados para o Excel | D57: Amazon AWS Serviços Brasil Ltda | E57: 23.412.247/0001-10 | F57: 2430376_4MVGWINA | G57: 3585.26 | H57: 45201 | I57: Custo da infraestrutura em nuvem | J57: Total nota fiscal: R$ 10755,78. Rateio: 33,33 %
B58: Notify | C58: NETZSCH G&D Digital Products Home | D58: Materialize Serviços Digitais Ltda | E58: 34.269.716/0001-00 | F58: 570 | G58: 23233.33 | H58: 45202 | I58: Agênciamento de serviços de desenvovimento de software | J58: Total nota fiscal: R$ 69700. Rateio: 33,33 %
B59: Notify | C59: Relatório de lotes | D59: Materialize Serviços Digitais Ltda | E59: 34.269.716/0001-00 | F59: 570 | G59: 23233.33 | H59: 45202 | I59: Agênciamento de serviços de desenvovimento de software | J59: Total nota fiscal: R$ 69700. Rateio: 33,33 %
B60: Notify | C60: Exportar dados para o Excel | D60: Materialize Serviços Digitais Ltda | E60: 34.269.716/0001-00 | F60: 570 | G60: 23233.33 | H60: 45202 | I60: Agênciamento de serviços de desenvovimento de software | J60: Total nota fiscal: R$ 69700. Rateio: 33,33 %
B61: Notify | C61: Adequação do Gateway para o IRIS V3 | D61: MOUT S SOLUCOES EM TECNOLOGIA DA INFORMATICA LTDA | E61: 25.056.849/0001-08 | F61: 1991 | G61: 13920 | H61: 45148 | I61: ALOCAÇÃO PROFISSIONAL: Análise e desenvolvimento de sistemas | J61: Total nota fiscal: R$ 13920. Rateio: 100 %
B62: Notify | C62: Exportar dados para o Excel | D62: Amazon AWS Serviços Brasil Ltda | E62: 23.412.247/0001-10 | F62: 2548011_J7IJ9ZIE | G62: 5684.14 | H62: 45232 | I62: Custo da infraestrutura em nuvem | J62: Total nota fiscal: R$ 11368,28. Rateio: 50 %
B63: Notify | C63: Templates de gráficos | D63: Amazon AWS Serviços Brasil Ltda | E63: 23.412.247/0001-10 | F63: 2548011_J7IJ9ZIE | G63: 5684.14 | H63: 45232 | I63: Custo da infraestrutura em nuvem | J63: Total nota fiscal: R$ 11368,28. Rateio: 50 %
B64: Notify | C64: Exportar dados para o Excel | D64: Materialize Serviços Digitais Ltda | E64: 34.269.716/0001-00 | F64: 608 | G64: 69700 | H64: 45237 | I64: Agênciamento de serviços de desenvovimento de software | J64: Total nota fiscal: R$ 69700. Rateio: 100 %
B65: Notify | C65: Adequação do Gateway para o IRIS V3 | D65: MOUT S SOLUCOES EM TECNOLOGIA DA INFORMATICA LTDA | E65: 25.056.849/0001-08 | F65: 3054 | G65: 23400 | H65: 45244 | I65: ALOCAÇÃO PROFISSIONAL: Análise e desenvolvimento de sistemas | J65: Total nota fiscal: R$ 23400. Rateio: 100 %
B66: Notify | C66: Exportar dados para o Excel | D66: Amazon AWS Serviços Brasil Ltda | E66: 23.412.247/0001-10 | F66: 2610688_YNZZNXN6 | G66: 5305.71 | H66: 45262 | I66: Custo da infraestrutura em nuvem | J66: Total nota fiscal: R$ 10611,42. Rateio: 50 %
B67: Notify | C67: Templates de gráficos | D67: Amazon AWS Serviços Brasil Ltda | E67: 23.412.247/0001-10 | F67: 2610688_YNZZNXN6 | G67: 5305.71 | H67: 45262 | I67: Custo da infraestrutura em nuvem | J67: Total nota fiscal: R$ 10611,42. Rateio: 50 %
B68: Notify | C68: Adequação do Gateway para o IRIS V3 | D68: MOUT S SOLUCOES EM TECNOLOGIA DA INFORMATICA LTDA | E68: 25.056.849/0001-08 | F68: 3108 | G68: 41040 | H68: 45244 | I68: ALOCAÇÃO PROFISSIONAL: Análise e desenvolvimento de sistemas | J68: Total nota fiscal: R$ 41040. Rateio: 100 %
B69: Notify | C69: Exportar dados para o Excel | D69: Materialize Serviços Digitais Ltda | E69: 34.269.716/0001-00 | F69: 643 | G69: 34850 | H69: 45282 | I69: Agênciamento de serviços de desenvovimento de software | J69: Total nota fiscal: R$ 69700. Rateio: 50 %
B70: Notify | C70: Templates de gráficos | D70: Materialize Serviços Digitais Ltda | E70: 34.269.716/0001-00 | F70: 643 | G70: 34850 | H70: 45282 | I70: Agênciamento de serviços de desenvovimento de software | J70: Total nota fiscal: R$ 69700. Rateio: 50 %
B71: Notify | C71: Exportar dados para o Excel | D71: Amazon AWS Serviços Brasil Ltda | E71: 23.412.247/0001-10 | F71: 2709240_ECNZ6XB8 | G71: 5412.76 | H71: 44928 | I71: Custo da infraestrutura em nuvem | J71: Total nota fiscal: R$ 10825,52. Rateio: 50 %
B72: Notify | C72: Templates de gráficos | D72: Amazon AWS Serviços Brasil Ltda | E72: 23.412.247/0001-10 | F72: 2709240_ECNZ6XB8 | G72: 5412.76 | H72: 44928 | I72: Custo da infraestrutura em nuvem | J72: Total nota fiscal: R$ 10825,52. Rateio: 50 %

Sheet P&D_1
B2: Netzsch Moagem
B3: Pesquisa, Desenvolvimento & Inovação
B4: Formulário de PD&I - Ano 2023 | J4: Incentivado pela Lei do Bem | M4: TRUE
B5: - preencher somente os campos sombreados (cinza) e - adicionar cronograma no formato de imagem ao fim do formulário - preencher um deste para cada projeto de PD&I | J5: Objetiva tornar-se um Ativo | M5: FALSE
J6: Objetiva gerar patente/registro | M6: FALSE
B8: Dossiê do projeto
B9: Dados gerais para identificação e validação do projeto de PD&I
E10: ChocoFlow
B11: Nome do projeto | E11: Projeto 1 - Otimização da viscosidade do chocolate ao leite
J12: Pesquisa básica | M12: 📑
B13: Classificação do projeto | E13: Desenvolvimento experimental | J13: Pesquisa aplicada | M13: 📑
J14: Desenvolvimento experimental | M14: 📑
B15: Objetivos do projeto | E15: O objetivo deste projeto é otimizar o processo de fabricação de chocolate ao leite europeu, desenvolvido pela Netzsch, com foco na redução da viscosidade e do ponto de fluidez do chocolate, sem a necessidade de adicionar PGPR (um emulsificante comum na indústria de chocolates). O projeto visa atingir especificações técnicas precisas: uma viscosidade máxima de 2,3 Pas, um ponto de fluidez entre 10 a 20 Pa e uma granulometria de 18 a 22 µm. Isso será alcançado através da implementação de um processo inovador de cristalização da lactose antes da etapa de conchagem a seco, o que permite a liberação da gordura do leite e a redução da quantidade de manteiga de cacau utilizada, um ingrediente de alto custo.
J16: Inovação tecnológica de produto | M16: 📑
B17: Tipo de inovação | E17: Inovação tecnológica de processo | J17: Inovação tecnológica de processo | M17: 📑
J18: Inovação tecnológica de serviços | M18: 📑
B19: Elemento inovador | E19: O elemento inovador deste projeto é a aplicação de um processo único de cristalização da lactose antes da conchagem a seco. Este processo libera a gordura do leite, permitindo a redução do uso de manteiga de cacau sem comprometer a qualidade do produto. Adicionalmente, a inclusão da máquina Netzsch MasterCream Inline com ferramentas lisas após a moagem é uma abordagem inovadora para diminuir a viscosidade do chocolate, mantendo um ponto de fluidez adequado. A retenção e adição subsequente de manteiga do processo após a moagem é outra inovação técnica que visa melhorar a reologia do chocolate ao leite. | J19: - Não podem ser consideradas as inovações organizacionais, comerciais e de marketing
J20: Empresa ou segmento regional | M20: 📑
B21: Nível de inovação | E21: Inovador para o Mundo | J21: Inovador para o Brasil | M21: 📑
J22: Inovador para o Mundo | M22: 📑
B23: Risco tecnológico | E23: Os riscos tecnológicos envolvem a incerteza na obtenção dos resultados desejados de viscosidade, ponto de fluidez e granulometria, dadas as variáveis controladas no processo de fabricação. A cristalização da lactose, um processo delicado, deve ser otimizada para garantir a liberação eficaz da gordura do leite sem afetar negativamente o sabor característico do chocolate europeu. Além disso, a eficácia da máquina Netzsch MasterCream Inline em reduzir a viscosidade sem aumentar significativamente o ponto de fluidez representa um desafio técnico. Há também o risco de variações na retenção e adição de manteiga impactarem adversamente a textura e a qualidade final do chocolate.
B25: Metodologias | E25: Inicialmente, serão realizados testes de fabricação de massa de chocolate ao leite para coletar dados de reologia, umidade, granulometria e capacidade do processo. Com base nesses dados, parâmetros como potência, tamanho e quantidade de esferas, emulsificantes, tamanho do dente da ferramenta de pré-moagem, temperatura, tempo de conchagem/cristalização da lactose, quantidade de água e quantidade de manteiga retida serão ajustados. Após cada teste, os parâmetros serão refinados para o teste subsequente, e os dados coletados novamente. Uma vez obtido um resultado efetivo, o teste será repetido para garantir a consistência, e os parâmetros finais serão transferidos para a NFT (Netzsch Feinmahltechnik) na Alemanha para implementação em escala maior.
B27: Equipe | E27: Nome Completo | F27: Cargo/Função | G27: Qualificação | H27: !
E28: Theron Wolfgang Harbs | F28: Consultor | G28: Graduação | H28: TRUE | L28: Técnico | M28: 📑
E29: Jivago Rusch | F29: Projetista Industrial | G29: Pós-graduação | H29: TRUE | L29: Graduação
H30: FALSE | L30: Pós-graduação
H31: FALSE | L31: Mestrado
H32: FALSE | L32: Doutorado
H33: FALSE
H34: FALSE
B36: Cronograma
B37: [anexar imagem - preferencialmente Gantt em pdf]

Sheet P&D_1 MILESTONES
B2: NETZSCH
B3: Pesquisa, Desenvolvimento & Inovação
B4: Formulário de PD&I - Ano 2023
B5: - preencher somente os campos sombreados (cinza)
B8: Dossiê do projeto | E8: Um objetivo a ser concluído durante esta etapa. Podemos ter vários em cada etapa. | G8: Uma data estimada que atualizará após etapa concluída
B9: Etapas e Milestones
B11: Projeto | C11: Etapa | D11: Principais atividades | E11: Milestones | F11: Data inicial | G11: Data conclusão | H11: Observações do gestor
B12: P&D_1 | C12: Definição parametros e metricas | D12: Especificação da viscosidade e ponto de fluidez esperado com base no cliente da NFT, definição da receita do chocolate ao leite | E12: Viscosidade de 2 a 3,5Pas e ponto de fluidez de 10 a 20 Pa esperado | F12: 45021 | G12: 45072
B13: P&D_1 | C13: Definição dos equipamentos e metodos de medição | D13: Preparação do laboratorio de food para realizar as etapas de processamento de chocolate, medição de granulometria, reologia e umidade | E13: Realizar cristalização da lactose antes da conchagem a seco | F13: 45021 | G13: 45072
B14: P&D_1 | C14: Realização de testes | D14: Realizar a fabricação do chocolate ao leite no laboratorio de food da NEM | E14: Coletar dados do processo, verificar os resultados e ajustar os parametros para teste seguinte | F14: 45041 | G14: 45195
B15: P&D_1 | C15: Divulgação dos resultados para NFT | D15: Definir entre testes 1 a 12 qual a NFT deve repetir na Alemanha | E15: Teste 9 selecionado | F15: 45195 | G15: 45225
C16: Adaptação para produto do mercado da NEM | D16: Replicar teste 9, receita similar mas sem lactose, utilizar PGPR, granulometria mais alta | E16: Produzir um produto que atenda o mercado do Brasil e America latina | F16: 45323 | G16: 45474

Sheet P&D_1 TIMESHEET
B2: NETZSCH
B3: Pesquisa, Desenvolvimento & Inovação
B4: Formulário de PD&I - Ano 2023
B5: - preencher somente os campos sombreados (cinza)
I6: Treinamento
I7: Pesquisa
B8: Dossiê do projeto | I8: Desenvolvimento
B9: Atividades de Pesquisa, Desenvolvimento e Inovação | I9: Gestão e outros
H10: =SUM(H12:H15) -> 488
B11: RowID | C11: Projeto | D11: Etapa | E11: Colaborador | F11: CPF | G11: Data | H11: Tempo (h) | I11: Classificação | J11: Descrição da atividade e observações
C12: P&D_1 | D12: Definição parametros e metricas | E12: Theron Wolfgang Harbs | G12: 45021 | H12: 96 | I12: Pesquisa | J12: Especificação da viscosidade e ponto de fluidez esperado com base no cliente da NFT, definição da receita do chocolate ao leite
C13: P&D_1 | D13: Definição dos equipamentos e metodos de medição | E13: Theron Wolfgang Harbs / Jivago Rusch | G13: 45021 | H13: 88 | I13: Gestão e outros | J13: Preparação do laboratorio de food para realizar as etapas de processamento de chocolate, medição de granulometria, reologia e umidade
C14: P&D_1 | D14: Realização de testes | E14: Theron Wolfgang Harbs / Jivago Rusch | G14: 45021 | H14: 216 | I14: Pesquisa | J14: Realizar a fabricação do chocolate ao leite no laboratorio de food da NEM, Coletar dados do processo, verificar os resultados e ajustar os parametros
C15: P&D_1 | D15: Divulgação dos resultados para NFT | E15: Theron Wolfgang Harbs / Jivago Rusch | G15: 45195 | H15: 88 | I15: Desenvolvimento | J15: Definir entre testes 1 a 12 qual a NFT deve repetir na Alemanha

Sheet P&D_1 TERCEIROS
B2: NETZSCH
B3: Pesquisa, Desenvolvimento & Inovação
B4: Formulário de PD&I - Ano 2023
B5: - preencher somente os campos sombreados (cinza)
B8: Dossiê do projeto
B9: Investimentos com terceiros
B11: Projeto | C11: Etapa | D11: Fornecedor | E11: CNPJ | F11: Nota fiscal | G11: Valor | H11: Data | I11: Descrição da Atividade | J11: Objetivo do gasto e eventual info de rateio
B12: P&D_1

Sheet P&D_2
A1: FALSE
B2: Netzsch Moagem
B3: Pesquisa, Desenvolvimento & Inovação
B4: Formulário de PD&I - Ano 2023 | J4: Incentivado pela Lei do Bem | M4: TRUE
B5: - preencher somente os campos sombreados (cinza) e - adicionar cronograma no formato de imagem ao fim do formulário - preencher um deste para cada projeto de PD&I | J5: Objetiva tornar-se um Ativo | M5: FALSE
J6: Objetiva gerar patente/registro | M6: FALSE
B8: Dossiê do projeto
B9: Dados gerais para identificação e validação do projeto de PD&I
E10: MasterCream Maximizer
B11: Nome do projeto | E11: Projeto 2 - Expansão das Aplicações do Equipamento MasterCream
J12: Pesquisa básica | M12: 📑
B13: Classificação do projeto | E13: Desenvolvimento experimental | J13: Pesquisa aplicada | M13: 📑
J14: Desenvolvimento experimental | M14: 📑
B15: Objetivos do projeto | E15: O projeto visa desenvolver novos tamanhos e geometrias de dentes/estator para moagem eficaz de suspensões e granulados, com foco em produtos finais de diversas consistências. As melhorias incluem a otimização do funil/tubo de alimentação e do eixo helicoidal, inspiradas no modelo Mini MasterCream para produtos de difícil alimentação. O desenvolvimento de facas de pré-corte, como aplicado na Lübecker para o MasterCream 20, é projetado especificamente para produtos como amêndoas com umidade de até 4%. Além disso, o projeto contempla o desenvolvimento de um estator cônico de altura ajustável para produtos em pedaços grandes e a melhoria da construção do equipamento para facilitar a limpeza e a higienização, possivelmente com um sistema CIP integrado. Em conjunto, será desenvolvida uma ferramenta com rotor/estator liso para reduzir a viscosidade após a moagem. Este projeto também inclui a limpeza do sistema de moagem e seus periféricos, visando alcançar um grau de limpeza que permita a troca de produtos entre lotes, como a mudança de chocolate meio amargo para branco ou de produtos não veganos para veganos.
J16: Inovação tecnológica de produto | M16: 📑
B17: Tipo de inovação | E17: Inovação tecnológica de produto | J17: Inovação tecnológica de processo | M17: 📑
J18: Inovação tecnológica de serviços | M18: 📑
B19: Elemento inovador | E19: A inovação do projeto reside na combinação de várias melhorias técnicas que visam aumentar a eficiência e a versatilidade do processo de moagem. A introdução de dentes maiores e a possibilidade de ajustar a distância entre o rotor cônico e o estator, sem alterar a posição relativa dos anéis estáticos, são avanços significativos que permitem o processamento de uma gama mais ampla de produtos. O desenvolvimento de um design higiênico com materiais resistentes à corrosão e vedações melhora a limpeza e a manutenção do equipamento. A inclusão de uma ferramenta de pré-corte para produtos mais duros e a implementação de um rotor/estator liso para melhorar a viscosidade pós-moagem são outras inovações que otimizam o processo. | J19: - Não podem ser consideradas as inovações organizacionais, comerciais e de marketing
J20: Empresa ou segmento regional | M20: 📑
B21: Nível de inovação | E21: Inovador para o Mundo | J21: Inovador para o Brasil | M21: 📑
J22: Inovador para o Mundo | M22: 📑
B23: Risco tecnológico | E23: Integração de Componentes Mecânicos: A introdução de novos tamanhos e geometrias de dentes/estatores e a adaptação de um estator cônico ajustável apresentam desafios mecânicos significativos. Há o risco de incompatibilidade estrutural com os sistemas existentes, o que pode levar a problemas de alinhamento, desgaste irregular, e ineficiência na moagem. A precisão na fabricação destes componentes é crucial para assegurar a integridade estrutural e o funcionamento adequado do equipamento. Eficiência do Pré-corte e Moagem: O desenvolvimento de facas de pré-corte para produtos duros como amêndoas com umidade de até 4% requer um design que maximize a eficácia do corte sem causar obstruções ou danificar o material. O desafio reside na criação de um mecanismo de corte que possa lidar eficientemente com a variação na dureza e tamanho dos grãos, mantendo uma operação consistente e minimizando o desgaste excessivo. Manutenção da Higiene e Limpeza: A melhoria do design para facilitar a limpeza e permitir a implementação de um sistema CIP (Clean-In-Place) implica riscos relacionados à manutenção da higiene. É necessário garantir que todas as superfícies sejam acessíveis e fáceis de limpar, evitando áreas onde resíduos de produtos possam se acumular. O material usado no equipamento deve resistir a procedimentos de limpeza frequentes e rigorosos sem corroer ou deteriorar. Desenvolvimento do Rotor/Estator Liso: A inovação de um rotor/estator liso para reduzir a viscosidade após a moagem exige um design que equilibre eficácia na redução da viscosidade com o mínimo impacto no tamanho e na forma das partículas. O desafio técnico aqui é criar um sistema que possa processar uma variedade de produtos mantendo a qualidade e a consistência desejadas. Adaptação para Diversos Produtos e Lotes: O sistema precisa ser versátil o suficiente para se adaptar a diferentes tipos de produtos e permitir mudanças rápidas entre lotes, como na transição de chocolate meio amargo para chocolate branco. Isso exige um design que possa acomodar variações na textura, viscosidade e outros atributos físicos dos produtos sem comprometer a eficiência da moagem ou a qualidade do produto final. Validação de Materiais e Revestimentos Resistentes ao Desgaste: A escolha de materiais e revestimentos que sejam duráveis e resistentes ao desgaste é crucial, especialmente considerando a diversidade dos produtos processados e as condições operacionais. A seleção inadequada pode resultar em falhas prematuras do equipamento, aumentando os custos de manutenção e tempo de inatividade.
B25: Metodologias | E25: A metodologia do projeto é estruturada em várias etapas: Desenvolvimento de Novos Componentes: Desenho e fabricação de novos tamanhos de dentes e estatores, assim como a implementação de facas de pré-corte e ajustes no estator cônico. Testes e Avaliações: Realização de testes para avaliar a eficácia do esvaziamento do produto moído, a melhoria na alimentação do funil e a eficiência do novo design resistente ao desgaste. Análise de Resultados: Coleta e análise dos dados de desempenho, incluindo vazão, potência, rotação e tamanho de partícula, para otimizar os componentes e o processo. Desenvolvimento de um Banco de Dados: Criação de um banco de dados MasterCream com informações detalhadas sobre os diferentes aspectos do processo de moagem. Aprimoramento do Design Higiênico: Verificação e melhoria do design higiênico do equipamento, incluindo materiais e vedações, para facilitar a limpeza e manutenção. Implementação e Teste de Rotor/Estator Liso: Desenvolvimento e teste de um rotor/estator liso para verificar a melhoria na viscosidade após o moinho. Validação em Ambiente Real: Aplicação e teste das melhorias em um ambiente de produção real para garantir a eficácia e a aplicabilidade prática das inovações.
B27: Equipe | E27: Nome Completo | F27: Cargo/Função | G27: Qualificação | H27: !
E28: Theron Wolfgang Harbs | F28: Consultor | G28: Graduação | H28: TRUE | L28: Técnico | M28: 📑
E29: Jivago Rusch | F29: Projetista Industrial | G29: Pós-graduação | H29: TRUE | L29: Graduação
H30: FALSE | L30: Pós-graduação
H31: FALSE | L31: Mestrado
H32: FALSE | L32: Doutorado
H33: FALSE
H34: FALSE
B41: Cronograma
B42: [anexar imagem - preferencialmente Gantt em pdf]

Sheet P&D_2 MILESTONES
B2: NETZSCH
B3: Pesquisa, Desenvolvimento & Inovação
B4: Formulário de PD&I - Ano 2023
B5: - preencher somente os campos sombreados (cinza)
B8: Dossiê do projeto | E8: Um objetivo a ser concluído durante esta etapa. Podemos ter vários em cada etapa. | G8: Uma data estimada que atualizará após etapa concluída
B9: Etapas e Milestones
B11: Projeto | C11: Etapa | D11: Principais atividades | E11: Milestones | F11: Data inicial | G11: Data conclusão | H11: Observações do gestor
B12: P&D_2 | C12: Outros tamanhos e geometrias de dentes das ferramentas, outros materiais | D12: Desenvolver ferramentas com dentes de 5mm para pastas com granulados; desenvolver ferramentas com materiais resistentes ao desgaste; redução da area de moagem do MCIL40, redução da capacidade de bombeamento do MCIL40 | E12: Produzir pastas com granulados de amendoim, alho, pimenta etc. Testar ferramentas de WC ZrO2 com açai e mostarda | F12: 45203 | G12: 45566
B13: P&D_2 | C13: Melhorias do MasterCream MINI | D13: Desenvolver novo rotor de moagem, acionamento com mais potencia, dispositivo para diferentes tamanhos de entrada de produto, tubo de imersão, valvula para limitação da area de descarga | E13: Possibilitar a operação continua com o funil afogado | F13: 45139 | G13: 45505
B14: P&D_2 | C14: Facas de pré-corte | D14: Desenvolver facas de pré-corte na entrada do MasterCream | E14: Cortar o produto com alto teor de umidade e possibilitar que o rotor superior faça a pré quebra | F14: 45198 | G14: 45564
B15: P&D_2 | C15: Altura ajustavel do estator conico | D15: Desenvolver dispositivo para ajuste da altura do estator conico | E15: Testar dispositivo com produtos dificies de moer | F15: 45444 | G15: 45627
B16: P&D_2 | C16: Eixo helicoidal para alimentação | D16: Desenvolver eixo helicoidal similar ao do MC-MINI para MC10, 20, 40 | E16: Otimizar alimentação vertical | F16: 45444 | G16: 45627
B17: P&D_2 | C17: Adequação conforme design higienico | D17: Desenvolver carcaça, conexão de entrada, conexão de saída, funil, vedações e ferramentas conforme design higienico | E17: Diminuir a quantidade de acumolo residual | F17: 45444 | G17: 45627
B18: P&D_2 | C18: Criar banco de dados de processo com informações de vazão, potencia, rotação e tamanho de particula para MasterCream | D18: Desenvolver planilha de scale up para os diferentes tamanhos de maquina para comparar os dados de processo | E18: Coletar os dados de processo do MCIL40 que está operando em cliene | F18: 45198 | G18: 45564
B19: P&D_2 | C19: Rotor liso para redução da viscosidade após a moagem | D19: Desenvolver ferramentas para MasterCream lisas | E19: Montar após o moinho e testar para verificar possivel redução da viscosidade | F19: 45167 | G19: 45533

Sheet P&D_2 TIMESHEET
B2: NETZSCH
B3: Pesquisa, Desenvolvimento & Inovação
B4: Formulário de PD&I - Ano 2023
B5: - preencher somente os campos sombreados (cinza)
I6: Treinamento
I7: Pesquisa
B8: Dossiê do projeto | I8: Desenvolvimento
B9: Atividades de Pesquisa, Desenvolvimento e Inovação | I9: Gestão e outros
H10: =SUM(H12:H19) -> 828
B11: RowID | C11: Projeto | D11: Etapa | E11: Colaborador | F11: CPF | G11: Data | H11: Tempo (h) | I11: Classificação | J11: Descrição da atividade e observações
C12: P&D_2 | D12: Outros tamanhos e geometrias de dentes das ferramentas, outros materiais | E12: Jivago Rusch | G12: 45203 | H12: 88 | I12: Desenvolvimento | J12: Modelamento, detalhamento e lista de peças das ferramentas de moagem com dentes de 5mm
C13: P&D_2 | D13: Outros tamanhos e geometrias de dentes das ferramentas, outros materiais | E13: Jivago Rusch | G13: 45260 | H13: 16 | I13: Pesquisa | J13: Testes com ferramentas de 5mm com alho e amendoas
C14: P&D_2 | D14: Outros tamanhos e geometrias de dentes das ferramentas, outros materiais | E14: Jivago Rusch | G14: 44951 | H14: 88 | I14: Desenvolvimento | J14: Desenvolvimento de fornecedor, modelamento, detalhamento e lista de peças para ferramentas de moagem em AISI304 revestidas com CR3CR2
C15: P&D_2 | D15: Outros tamanhos e geometrias de dentes das ferramentas, outros materiais | E15: Jivago Rusch | G15: 45125 | H15: 88 | I15: Pesquisa | J15: Teste com ferramentas revestidas com CR3CR2 em cliente com moagem de nibs de cacau
C16: P&D_2 | D16: Facas de pré-corte Ativar | E16: Jivago Rusch | G16: 45111 | H16: 108 | I16: Desenvolvimento | J16: Modelamento, detalhamento, lista de peças e testes de facas de pré corte com amendoas com alto teor de umidade
C17: P&D_2 | D17: Criar banco de dados de processo com informações de vazão, potencia, rotação e tamanho de particula para MasterCream | E17: Jivago Rusch | G17: 45198 | H17: 176 | I17: Pesquisa | J17: Coleta de dados do MCIL40 em cliente durante Startup, criação de planiilha de calculo com dados tecnicos para comparação do dos tamanhos diferentes de maquinas para scale up, manual de boas praticas de operação, alteração do projeto das ferramentas do MCIL40 para area de moagem 30% menor
C18: P&D_2 | D18: Melhorias do MasterCream MINI | E18: Jivago Rusch | G18: 45217 | H18: 176 | I18: Desenvolvimento | J18: Desenvolvimento de novo rotor de moagem, acionamento com mais potencia, dispositivo para diferentes tamanhos de entrada de produto, tubo de imersão, valvula para limitação da area de descarga, realização de testes com amendoim
C19: P&D_2 | D19: Rotor liso para redução da viscosidade após a moagem | E19: Jivago Rusch | G19: 45167 | H19: 88 | I19: Desenvolvimento | J19: Desenvolvimento de ferramentas lisas com diferentes fendas, realização de testes com chocolate ao leite após a moagem, verificação da redução da viscosidade

Sheet P&D_2 TERCEIROS
B2: NETZSCH
B3: Pesquisa, Desenvolvimento & Inovação
B4: Formulário de PD&I - Ano 2023
B5: - preencher somente os campos sombreados (cinza)
B8: Dossiê do projeto | G8: Valores lançados no FORMS como Material de Uso e consumo
B9: Investimentos com terceiros
G10: =SUM(G12:G15) -> 30957.95
B11: Projeto | C11: Etapa | D11: Fornecedor | E11: CNPJ | F11: Nota fiscal | G11: Valor | H11: Data | I11: Descrição da Atividade | J11: Objetivo do gasto e eventual info de rateio
B12: P&D_2 | C12: Outros tamanhos e geometrias de dentes das ferramentas, outros materiais / Rotor liso para redução da viscosidade após a moagem | D12: STR FERRAMENTARIA EIRELI - ME | E12: 12715548000105 | F12: NF 9873-1 | G12: 18197.26 | H12: 45117 | I12: Compra das ferramentas de 5mm, facas de pré-corte e ferramentas lisas | J12: Testes
B13: P&D_2 | C13: Outros tamanhos e geometrias de dentes das ferramentas, outros materiais | D13: RIJEZA INDUSTRIA METALURGICA LTDA / STR FERRAMENTARIA EIRELI - ME | E13: 5034416000144 / 12715548000105 | F13: NF 19147 / NF 9135-1 | G13: 4267.99 | H13: 44964 | I13: Compra de ferramentas com revestimento resistente ao desgaste | J13: Testes
B14: P&D_2 | C14: Melhorias do MasterCream MINI | D14: STR FERRAMENTARIA EIRELI - ME | E14: 12715548000105 | F14: NF 10094-1 | G14: 5998.03 | H14: 45206 | I14: Compra das novas ferramentas de moagem | J14: Testes
B15: P&D_2 | C15: Melhorias do MasterCream MINI | D15: WEG EQUIPAMENTOS ELÉTRICOS S/A | E15: 7175725001050 | F15: NF 3411393-1 | G15: 2494.67 | H15: 45203 | I15: Compra de acionamento mais potente | J15: Testes

Sheet P&D_3
B2: Netzsch Moagem
B3: Pesquisa, Desenvolvimento & Inovação
B4: Formulário de PD&I - Ano 2023 | J4: Incentivado pela Lei do Bem | M4: TRUE
B5: - preencher somente os campos sombreados (cinza) e - adicionar cronograma no formato de imagem ao fim do formulário - preencher um deste para cada projeto de PD&I | J5: Objetiva tornar-se um Ativo | M5: FALSE
J6: Objetiva gerar patente/registro | M6: FALSE
B8: Dossiê do projeto
B9: Dados gerais para identificação e validação do projeto de PD&I
E10: CleanTech
B11: Nome do projeto | E11: Projeto 3 - Desenvolvimento de Processo de Limpeza CIP e SIP para linhas Food
J12: Pesquisa básica | M12: 📑
B13: Classificação do projeto | E13: Desenvolvimento experimental | J13: Pesquisa aplicada | M13: 📑
J14: Desenvolvimento experimental | M14: 📑
B15: Objetivos do projeto | E15: O projeto tem como objetivo aprimorar a limpeza e a higiene nos sistemas de moagem e conchagem da NETZSCH, utilizados na produção de confeitaria, incluindo Conch, Mixer e Bead Mill. O foco está em desenvolver um sistema de limpeza CIP (Clean-In-Place) à base de óleo, eficiente e rápido, que minimize o consumo de meios de limpeza e atenda às diretrizes de projeto higiênico (HD). O projeto visa também validar e implementar o conceito de HD em toda a linha de produção, otimizando componentes como cabeçotes de limpeza e garantindo a conformidade com as diretrizes da EHEDG, HACCP e GMP. O objetivo é alcançar um grau de limpeza que permita a troca de produtos entre lotes, facilitando a transição entre diferentes tipos de chocolates ou entre produtos veganos e não veganos.
J16: Inovação tecnológica de produto | M16: 📑
B17: Tipo de inovação | E17: Inovação tecnológica de processo | J17: Inovação tecnológica de processo | M17: 📑
J18: Inovação tecnológica de serviços | M18: 📑
B19: Elemento inovador | E19: A inovação deste projeto reside na aplicação e otimização de um sistema CIP à base de óleo em máquinas de produção de confeitaria. O desafio inovador é integrar um design higiênico que permita uma limpeza eficiente e rápida, reduzindo o tempo de inatividade e o consumo de recursos. A otimização dos cabeçotes de limpeza para evitar a acumulação de resíduos e a validação do conceito de HD para equipamentos como o Bead Mill MasterRefiner representam avanços significativos na manutenção da higiene e na eficiência operacional. | J19: - Não podem ser consideradas as inovações organizacionais, comerciais e de marketing
J20: Empresa ou segmento regional | M20: 📑
B21: Nível de inovação | E21: Inovador para o Mundo | J21: Inovador para o Brasil | M21: 📑
J22: Inovador para o Mundo | M22: 📑
B23: Risco tecnológico | E23: Desenvolvimento do Sistema CIP: A integração de um sistema CIP eficiente em máquinas existentes, apresenta desafios de engenharia, exigindo ajustes precisos para garantir uma limpeza eficaz sem danificar os componentes da máquina. Otimização de Cabeçotes de Limpeza: O redesign dos cabeçotes de limpeza para evitar a acumulação de resíduos e garantir uma limpeza completa é complexo, pois requer um equilíbrio entre eficácia de limpeza, facilidade de manutenção e impacto mínimo no processo de produção. Validação do Conceito de HD: A adaptação e validação do conceito de HD em diferentes equipamentos, respeitando as diretrizes da EHEDG, HACCP e GMP, envolve riscos associados à compatibilidade de materiais, eficácia de limpeza e conformidade com as normas. Análises Microbiológicas: Realizar análises microbiológicas para determinar o grau de limpeza alcançado implica em desafios técnicos para assegurar que os métodos de teste sejam confiáveis e representativos das condições reais de operação. Desenvolvimento de Especificações de Limpeza: Definir especificações precisas de limpeza para diferentes aplicações e produtos, como a troca de chocolate ao leite por chocolate branco ou de produtos não veganos para veganos, requer um entendimento profundo dos requisitos de limpeza para cada tipo de produto.
B25: Metodologias | E25: Especificação do Sistema CIP: Definição preliminar das etapas do sistema CIP, incluindo a configuração de um sistema CIP preliminar no MAC300 para testes. Testes e Coleta de Dados: Realização de testes nos cabeçotes de limpeza e coleta de dados como vazão, temperatura, pressão e tempo para avaliar a eficiência e identificar áreas críticas de resíduos na concha. Melhoria do Design de Equipamentos: Revisão e aprimoramento da construção de equipamentos, tubulações, válvulas e conexões, seguindo as diretrizes de projeto higiênico. Análises Microbiológicas: Trabalho conjunto com engenheiros de alimentos para realizar análises microbiológicas e determinar o grau de limpeza alcançado. Especificação do Grau de Limpeza: Definição de critérios de limpeza aceitáveis conforme normas para cada tipo de aplicação. Desenvolvimento do Sistema Definitivo: Criação do projeto final do sistema CIP, descrevendo as etapas para cada aplicação e o projeto de automação associado.
B27: Equipe | E27: Nome Completo | F27: Cargo/Função | G27: Qualificação | H27: !
E28: Theron Wolfgang Harbs | F28: Consultor | G28: Graduação | H28: TRUE | L28: Técnico | M28: 📑
E29: Jivago Rusch | F29: Projetista Industrial | G29: Pós-graduação | H29: TRUE | L29: Graduação
E30: Fernando Leal | F30: Bolsista | G30: Doutorado | H30: TRUE | L30: Pós-graduação
H31: FALSE | L31: Mestrado
H32: FALSE | L32: Doutorado
H33: FALSE
H34: FALSE
B37: Cronograma
B38: [anexar imagem - preferencialmente Gantt em pdf]

Sheet P&D_3 MILESTONES
B2: NETZSCH
B3: Pesquisa, Desenvolvimento & Inovação
B4: Formulário de PD&I - Ano 2023
B5: - preencher somente os campos sombreados (cinza)
B8: Dossiê do projeto | E8: Um objetivo a ser concluído durante esta etapa. Podemos ter vários em cada etapa. | G8: Uma data estimada que atualizará após etapa concluída
B9: Etapas e Milestones
B11: Projeto | C11: Etapa | D11: Principais atividades | E11: Milestones | F11: Data inicial | G11: Data conclusão | H11: Observações do gestor
B12: P&D_3 | C12: MasterRefiner 30 Hygienic design | D12: Desenvolver peças para adequar o MR30 do laboratorio conforme design higienico | E12: Realizar teste de limpeza | F12: 45024 | G12: 45351
B13: P&D_3 | C13: Sistema de limpeza com água | D13: Desenvolver fluxo de limpeza para Rumba/Salsa 300 | E13: Testar cabeçotes Hydroclaw | F13: 45148 | G13: 45383
B14: P&D_3 | C14: Sistema de esvaziamento com ar comprimido | D14: Desenvolver sistema de pressurização para Moinho, tubulação e sistema de pre moagem | E14: Testar esvaziamento no moinho | F14: 45383 | G14: 45444
B15: P&D_3 | C15: Sistema de secagem com ar quente | D15: Adequar sistema de ar quente existente na concha para secagem do sistema completo | E15: Testar secagem do sistema | F15: 45383 | G15: 45444
B16: P&D_3 | C16: Sistema de secagem com vácuo | D16: Adequar sistema de vacuo existente no lab para secagem do sistema completo | E16: Testar secagem com vacuo no sistema | F16: 45383 | G16: 45444
B17: P&D_3 | C17: Adequação do laboratorio Rumba 300 para CIP/Design higienico | D17: Projetar tanques de processo, tubulação, bombas e valvulas conforme design higienico | E17: Realizar teste de CIP completo | F17: 45170 | G17: 45536
B18: P&D_3 | C18: Caracterização de nivel de residuos remanescentes | D18: Pesquisar normas/legislação brasileira, europeia e americana. Desenvolver metodo de analise de residuos | E18: Classificar grau de limpeza requerido para troca de produto | F18: 45268 | G18: 45536

Sheet P&D_3 TIMESHEET
B2: NETZSCH
B3: Pesquisa, Desenvolvimento & Inovação
B4: Formulário de PD&I - Ano 2023
B5: - preencher somente os campos sombreados (cinza)
I6: Treinamento
I7: Pesquisa
B8: Dossiê do projeto | I8: Desenvolvimento
B9: Atividades de Pesquisa, Desenvolvimento e Inovação | I9: Gestão e outros
H10: =SUM(H12:H18) -> 392
B11: RowID | C11: Projeto | D11: Etapa | E11: Colaborador | F11: CPF | G11: Data | H11: Tempo (h) | I11: Classificação | J11: Descrição da atividade e observações
C12: P&D_3 | D12: MasterRefiner 30 Hygienic design | E12: Jivago Rusch | G12: 45024 | H12: 132 | I12: Desenvolvimento | J12: Modelamento, detalhamento e lista de peças
C13: P&D_3 | D13: Sistema de limpeza com água | E13: Jivago Rusch | G13: 45148 | H13: 88 | I13: Desenvolvimento | J13: Desenvolvimento do fluxograma de limpeza
C14: P&D_3 | D14: Sistema de limpeza com água | E14: Jivago Rusch | G14: 45201 | H14: 88 | I14: Desenvolvimento | J14: Projeto para o sistema de limpeza preliminar
C15: P&D_3 | D15: Sistema de limpeza com água | E15: Jivago Rusch / Theron Wolfgang Harbs | G15: 45244 | H15: 8 | I15: Pesquisa | J15: Teste preliminar de limpeza na Concha
