Workbook

Sheet RESUMO
A2: Resumo dos investimentos
A3: BENEFÍCIO FISCAL DE PD&I 2024
A5: NETZSCH INDUSTRIA E COMERCIO DE EQUIPAMENTOS DE MOAGEM LTDA | E5: CNPJ 07.389.050/0001-51 | G5: 2023-026 - NETZSCH MOAGEM
A6: Rua Emilio Marquardt, 300, Ribeirão Souto - SC - SUL - POMERODE - CEP 89.107-000 | G6: =TODAY() -> 46168
A8: Natureza | B8: 1º Trimestre | C8: 2º Trimestre | D8: 3º Trimestre | E8: 4º Trimestre | G8: TOTAL
A9: Material | B9: - | C9: - | D9: - | E9: - | G9: =sum(B9:E9) -> 0
A10: Terceiros | B10: 306712.34 | C10: 337695.39 | D10: 230052.05 | E10: 247145.2 | G10: =sum(B10:E10) -> 1121605
A11: RH (Parcial inovação) | B11: 340510.15 | C11: 322717.47 | D11: 318597.36 | E11: 302109.18 | G11: =sum(B11:E11) -> 1283934.2
A12: RH (Exclusivo inovação) | B12: 0 | C12: 0 | D12: 0 | E12: 0 | G12: =sum(B12:E12) -> 0
A13: Total 1 | B13: =sum(B10:B12) -> 647222.49 | C13: =sum(C10:C12) -> 660412.86 | D13: =sum(D10:D12) -> 548649.41 | E13: =sum(E10:E12) -> 549254.38 | G13: =sum(G9:G12) -> 2405539.1
A14: Percentual Exclusão | B14: 0.6 | C14: 0.6 | D14: 0.6 | E14: 0.6 | G14: 0.6
A15: Exclusão da Base de cálculo do IRPJ e CSLL | B15: =B13*B14 -> 388333.49 | C15: =C13*C14 -> 396247.72 | D15: =D13*D14 -> 329189.65 | E15: =E13*E14 -> 329552.63 | G15: =G13*G14 -> 1443323.5
A17: Economia Estimada [34%] | B17: =B15*34% -> 132033.39 | C17: =C15*34% -> 134724.22 | D17: =D15*34% -> 111924.48 | E17: =E15*34% -> 112047.89 | G17: =G15*34% -> 490729.98
A18: Comissão McBenner | B18: =B17*0.05 -> 6601.6694 | C18: =C17*0.05 -> 6736.2112 | D18: =D17*0.05 -> 5596.224 | E18: =E17*0.05 -> 5602.3947 | G18: =G17*0.05 -> 24536.499
A20: Observações:
A21: 1. Os dispêndios devem ser registrados na contabilidade em conta específica
A22: 2. O benefício deve ser aproveitado na ECF do respectivo ano/competência
A23: 3. O formulário do MCTIC (governo) será enviado até fim de Julho/2025
A24: 4. Os projetos estão descritos em arquivo a parte a ser anexado no FORM PD&I
A25: 5. Alguns benefícios previstos na Lei do Bem não foram utilizados:
A26: - 5.1. Depreciação acelerada
A27: - 5.2. Redução de IPI na aquisição de equipamento para PD&I
A28: - 5.3. Acréscimo de até 20% na exclusão por incrementar o número de pesquisadores contratados (exclusivos) em percentual acima de 5% ou até 5% em comparação ao ano-calendário anterior
A29: --- 5.3. Até 70% de exclusão por incrementar o numero de pesquisadores contratados em percentual até 5%
A31: Equipe de PD&I
A32: Quadro de resumo | B32: Dedicação Parcial | E32: Dedicação Exclusiva
B33: Qtd | C33: Valor gasto | D33: Horas | E33: Qtd | F33: Valor gasto | G33: Horas
A34: Técnico | B34: =IFERROR(__xludf.DUMMYFUNCTION("COUNTA(IFERROR(FILTER(RH!$F$13:$F$33,RH!$F$13:$F$33 = $A34,RH!$V$13:$V$33 = ""Parcial""),))"),3.0) -> 3 | C34: =IFERROR(__xludf.DUMMYFUNCTION("SUM(IFERROR(FILTER(RH!$U$47:$U$66,RH!$F$47:$F$66 = $A34,RH!$E$47:$E$66 = ""Parcial""),0))"),37828.2767842249) -> 37828.277 | D34: =IFERROR(__xludf.DUMMYFUNCTION("SUM(IFERROR(FILTER(RH!$T$13:$T$33,RH!$F$13:$F$33 = $A34,RH!$V$13:$V$33 = ""Parcial""),0))*24"),1252.13) -> 1252.13 | E34: =IFERROR(__xludf.DUMMYFUNCTION("COUNTA(IFERROR(FILTER(RH!$F$13:$F$26,RH!$F$13:$F$26 = $A34,RH!$V$13:$V$26 = ""Exclusivo""),))"),0.0) -> 0 | F34: =IFERROR(__xludf.DUMMYFUNCTION("SUM(IFERROR(FILTER(RH!$U$47:$U$66,RH!$F$47:$F$66 = $A34,RH!$E$47:$E$66 = ""Exclusivo""),0))"),0.0) -> 0 | G34: =IFERROR(__xludf.DUMMYFUNCTION("SUM(IFERROR(FILTER(RH!$T$13:$T$33,RH!$F$13:$F$33 = $A34,RH!$V$13:$V$33 = ""Exclusivo""),0))*24"),0.0) -> 0
A35: Tecnologo | B35: =IFERROR(__xludf.DUMMYFUNCTION("COUNTA(IFERROR(FILTER(RH!$F$13:$F$30,RH!$F$13:$F$30 = $A35,RH!$V$13:$V$30 = ""Parcial""),))"),0.0) -> 0 | C35: =IFERROR(__xludf.DUMMYFUNCTION("SUM(IFERROR(FILTER(RH!$U$47:$U$66,RH!$F$47:$F$66 = $A35,RH!$E$47:$E$66 = ""Parcial""),0))"),0.0) -> 0 | D35: =IFERROR(__xludf.DUMMYFUNCTION("SUM(IFERROR(FILTER(RH!$T$13:$T$26,RH!$F$13:$F$26 = $A35,RH!$V$13:$V$26 = ""Parcial""),0))*24"),0.0) -> 0 | E35: =IFERROR(__xludf.DUMMYFUNCTION("COUNTA(IFERROR(FILTER(RH!$F$13:$F$26,RH!$F$13:$F$26 = $A35,RH!$V$13:$V$26 = ""Exclusivo""),))"),0.0) -> 0 | F35: =IFERROR(__xludf.DUMMYFUNCTION("SUM(IFERROR(FILTER(RH!$U$47:$U$66,RH!$F$47:$F$66 = $A35,RH!$E$47:$E$66 = ""Exclusivo""),0))"),0.0) -> 0 | G35: =IFERROR(__xludf.DUMMYFUNCTION("SUM(IFERROR(FILTER(RH!$T$13:$T$26,RH!$F$13:$F$26 = $A35,RH!$V$13:$V$26 = ""Exclusivo""),0))*24"),0.0) -> 0
A36: Superior Completo | B36: =IFERROR(__xludf.DUMMYFUNCTION("COUNTA(IFERROR(FILTER(RH!$F$13:$F$33,RH!$F$13:$F$33 = $A36,RH!$V$13:$V$33 = ""Parcial""),))"),10.0) -> 10 | C36: 1229924.4 | D36: 15203.96 | E36: 0 | F36: 0 | G36: 0
A37: Pós graduado | B37: =IFERROR(__xludf.DUMMYFUNCTION("COUNTA(IFERROR(FILTER(RH!$F$13:$F$33,RH!$F$13:$F$33 = $A37,RH!$V$13:$V$33 = ""Parcial""),))"),3.0) -> 3 | C37: =IFERROR(__xludf.DUMMYFUNCTION("SUM(IFERROR(FILTER(RH!$U$47:$U$66,RH!$F$47:$F$66 = $A37,RH!$E$47:$E$66 = ""Parcial""),0))"),18521.516312461263) -> 18521.516 | D37: =IFERROR(__xludf.DUMMYFUNCTION("SUM(IFERROR(FILTER(RH!$T$13:$T$33,RH!$F$13:$F$33 = $A37,RH!$V$13:$V$33 = ""Parcial""),0))*24"),362.2) -> 362.2 | E37: =IFERROR(__xludf.DUMMYFUNCTION("COUNTA(IFERROR(FILTER(RH!$F$13:$F$26,RH!$F$13:$F$26 = $A37,RH!$V$13:$V$26 = ""Exclusivo""),))"),0.0) -> 0 | F37: =IFERROR(__xludf.DUMMYFUNCTION("SUM(IFERROR(FILTER(RH!$U$47:$U$66,RH!$F$47:$F$66 = $A37,RH!$E$47:$E$66 = ""Exclusivo""),0))"),0.0) -> 0 | G37: =IFERROR(__xludf.DUMMYFUNCTION("SUM(IFERROR(FILTER(RH!$T$13:$T$33,RH!$F$13:$F$33 = $A37,RH!$V$13:$V$33 = ""Exclusivo""),0))*24"),0.0) -> 0
A38: Mestrado | B38: =IFERROR(__xludf.DUMMYFUNCTION("COUNTA(IFERROR(FILTER(RH!$F$13:$F$33,RH!$F$13:$F$33 = $A38,RH!$V$13:$V$33 = ""Parcial""),))"),1.0) -> 1 | C38: =IFERROR(__xludf.DUMMYFUNCTION("SUM(IFERROR(FILTER(RH!$U$47:$U$66,RH!$F$47:$F$66 = $A38,RH!$E$47:$E$66 = ""Parcial""),0))"),0.0) -> 0 | D38: =IFERROR(__xludf.DUMMYFUNCTION("SUM(IFERROR(FILTER(RH!$T$13:$T$33,RH!$F$13:$F$33 = $A38,RH!$V$13:$V$33 = ""Parcial""),0))*24"),0.0) -> 0 | E38: =IFERROR(__xludf.DUMMYFUNCTION("COUNTA(IFERROR(FILTER(RH!$F$13:$F$26,RH!$F$13:$F$26 = $A38,RH!$V$13:$V$26 = ""Exclusivo""),))"),0.0) -> 0 | F38: =IFERROR(__xludf.DUMMYFUNCTION("SUM(IFERROR(FILTER(RH!$U$47:$U$66,RH!$F$47:$F$66 = $A38,RH!$E$47:$E$66 = ""Exclusivo""),0))"),0.0) -> 0 | G38: =IFERROR(__xludf.DUMMYFUNCTION("SUM(IFERROR(FILTER(RH!$T$13:$T$33,RH!$F$13:$F$33 = $A38,RH!$V$13:$V$33 = ""Exclusivo""),0))*24"),0.0) -> 0
A39: Doutorado | B39: =IFERROR(__xludf.DUMMYFUNCTION("COUNTA(IFERROR(FILTER(RH!$F$13:$F$30,RH!$F$13:$F$30 = $A39,RH!$V$13:$V$30 = ""Parcial""),))"),0.0) -> 0 | C39: =IFERROR(__xludf.DUMMYFUNCTION("SUM(IFERROR(FILTER(RH!$U$47:$U$66,RH!$F$47:$F$66 = $A39,RH!$E$47:$E$66 = ""Parcial""),0))"),0.0) -> 0 | D39: =IFERROR(__xludf.DUMMYFUNCTION("SUM(IFERROR(FILTER(RH!$T$13:$T$26,RH!$F$13:$F$26 = $A39,RH!$V$13:$V$26 = ""Parcial""),0))*24"),0.0) -> 0 | E39: =IFERROR(__xludf.DUMMYFUNCTION("COUNTA(IFERROR(FILTER(RH!$F$13:$F$26,RH!$F$13:$F$26 = $A39,RH!$V$13:$V$26 = ""Exclusivo""),))"),0.0) -> 0 | F39: =IFERROR(__xludf.DUMMYFUNCTION("SUM(IFERROR(FILTER(RH!$U$47:$U$66,RH!$F$47:$F$66 = $A39,RH!$E$47:$E$66 = ""Exclusivo""),0))"),0.0) -> 0 | G39: =IFERROR(__xludf.DUMMYFUNCTION("SUM(IFERROR(FILTER(RH!$T$13:$T$26,RH!$F$13:$F$26 = $A39,RH!$V$13:$V$26 = ""Exclusivo""),0))*24"),0.0) -> 0
B40: =SUM(B34:B39) -> 17 | C40: =SUM(C34:C39) -> 1286274.2 | D40: =SUM(D34:D39) -> 16818.29 | E40: =SUM(E34:E39) -> 0 | F40: =SUM(F34:F39) -> 0 | G40: =SUM(G34:G39) -> 0
A42: Valores por projeto de PD&I
A43: Projetos | B43: TOTAL | D43: Vlr materiais | E43: Vlr terceiros | F43: Vlr Rh parcial | G43: Vlr exclusivos
A44: {='Resumo - PROJETOS'!B12:B49} -> IRIS | B44: =sum(D44:G44) -> 381031.46 | D44: - | E44: =IFERROR(__xludf.DUMMYFUNCTION("iferror(sum(filter('Resumo - TERCEIROS'!$G:$G,'Resumo - TERCEIROS'!$K:$K=TRUE,'Resumo - TERCEIROS'!$L:$L=TRUE,'Resumo - TERCEIROS'!$B:$B=$A44)),0)"),98396.55) -> 98396.55 | F44: =IFERROR(__xludf.DUMMYFUNCTION("iferror(sum(filter('Resumo - TIMESHEETS'!$L$12:$L49,'Resumo - TIMESHEETS'!$O$12:$O49=""Parcial"",'Resumo - TIMESHEETS'!$C$12:$C49=$A44)),0)"),282634.90880039515) -> 282634.91 | G44: =IFERROR(__xludf.DUMMYFUNCTION("iferror(sum(filter('Resumo - TIMESHEETS'!$L$12:$L49,'Resumo - TIMESHEETS'!$O$12:$O49=""Exclusivo"",'Resumo - TIMESHEETS'!$C$12:$C49=$A44)),0)"),0.0) -> 0
A45: NOTIFY | B45: =sum(D45:G45) -> 1989512.5 | D45: - | E45: =IFERROR(__xludf.DUMMYFUNCTION("iferror(sum(filter('Resumo - TERCEIROS'!$G:$G,'Resumo - TERCEIROS'!$K:$K=TRUE,'Resumo - TERCEIROS'!$L:$L=TRUE,'Resumo - TERCEIROS'!$B:$B=$A45)),0)"),990309.0100000002) -> 990309.01 | F45: 999203.49 | G45: 0
A46: P&D_1 | B46: =sum(D46:G46) -> 0 | D46: - | E46: =IFERROR(__xludf.DUMMYFUNCTION("iferror(sum(filter('Resumo - TERCEIROS'!$G:$G,'Resumo - TERCEIROS'!$L:$L=TRUE,'Resumo - TERCEIROS'!$B:$B=$A46)),0)"),0.0) -> 0 | F46: =IFERROR(__xludf.DUMMYFUNCTION("iferror(sum(filter('Resumo - TIMESHEETS'!$L$12:$L49,'Resumo - TIMESHEETS'!$O$12:$O49=""Parcial"",'Resumo - TIMESHEETS'!$C$12:$C49=$A46)),0)"),0.0) -> 0 | G46: =IFERROR(__xludf.DUMMYFUNCTION("iferror(sum(filter('Resumo - TIMESHEETS'!$L$12:$L49,'Resumo - TIMESHEETS'!$O$12:$O49=""Exclusivo"",'Resumo - TIMESHEETS'!$C$12:$C49=$A46)),0)"),0.0) -> 0
A47: P&D_2 | B47: =sum(D47:G47) -> 0 | D47: - | E47: =IFERROR(__xludf.DUMMYFUNCTION("iferror(sum(filter('Resumo - TERCEIROS'!$G:$G,'Resumo - TERCEIROS'!$L:$L=TRUE,'Resumo - TERCEIROS'!$B:$B=$A47)),0)"),0.0) -> 0 | F47: =IFERROR(__xludf.DUMMYFUNCTION("iferror(sum(filter('Resumo - TIMESHEETS'!$L$12:$L49,'Resumo - TIMESHEETS'!$O$12:$O49=""Parcial"",'Resumo - TIMESHEETS'!$C$12:$C49=$A47)),0)"),0.0) -> 0 | G47: =IFERROR(__xludf.DUMMYFUNCTION("iferror(sum(filter('Resumo - TIMESHEETS'!$L$12:$L49,'Resumo - TIMESHEETS'!$O$12:$O49=""Exclusivo"",'Resumo - TIMESHEETS'!$C$12:$C49=$A47)),0)"),0.0) -> 0
A48: P&D_3 | B48: =sum(D48:G48) -> 40325.091 | D48: - | E48: =IFERROR(__xludf.DUMMYFUNCTION("iferror(sum(filter('Resumo - TERCEIROS'!$G:$G,'Resumo - TERCEIROS'!$K:$K=TRUE,'Resumo - TERCEIROS'!$L:$L=TRUE,'Resumo - TERCEIROS'!$B:$B=$A48)),0)"),35089.02) -> 35089.02 | F48: =IFERROR(__xludf.DUMMYFUNCTION("iferror(sum(filter('Resumo - TIMESHEETS'!$L$12:$L49,'Resumo - TIMESHEETS'!$O$12:$O49=""Parcial"",'Resumo - TIMESHEETS'!$C$12:$C49=$A48)),0)"),5236.071215351803) -> 5236.0712 | G48: =IFERROR(__xludf.DUMMYFUNCTION("iferror(sum(filter('Resumo - TIMESHEETS'!$L$12:$L49,'Resumo - TIMESHEETS'!$O$12:$O49=""Exclusivo"",'Resumo - TIMESHEETS'!$C$12:$C49=$A48)),0)"),0.0) -> 0
A49: Subtotais | B49: =SUM(B44:B48) -> 2410869 | D49: =Sum(D44:D48) -> 0 | E49: =SUM(E44:E48) -> 1123794.6 | F49: =SUM(F44:F48) -> 1287074.5 | G49: =SUM(G44:G48) -> 0

Sheet Resumo - PROJETOS
B2: NETZSCH
B3: Pesquisa, Desenvolvimento & Inovação
B4: Formulário de PD&I - Ano 2024
B5: - preencher somente os campos sombreados (cinza)
B8: Dossiê do projeto
B9: Investimentos com terceiros
B11: Projeto | C11: Incentivado pela Lei do Bem | D11: Objetiva tornar-se um Ativo | E11: Objetiva gerar patente/registro
B12: IRIS | C12: {=TRANSPOSE(IRIS!M4:M6)} -> TRUE | D12: FALSE | E12: FALSE
B13: NOTIFY | C13: {=TRANSPOSE(NOTIFY!M4:M6)} -> TRUE | D13: FALSE | E13: FALSE
B14: P&D_1 | C14: FALSE
B15: P&D_2 | C15: FALSE
B16: P&D_3 | C16: TRUE

Sheet Resumo - TIMESHEETS
B2: NETZSCH
B3: Pesquisa, Desenvolvimento & Inovação
B4: Formulário de PD&I - Ano 2024
B5: - preencher somente os campos sombreados (cinza)
I6: Treinamento
I7: Pesquisa
B8: Dossiê do projeto | I8: Desenvolvimento
B9: Atividades de Pesquisa, Desenvolvimento e Inovação | I9: Gestão e outros
B11: RowID | C11: Projeto | D11: Etapa | E11: Colaborador | F11: CPF | G11: Data | H11: Tempo (h) | I11: Classificação | J11: Descrição da atividade e observações | K11: Custo/hora | L11: Custo total | M11: Atividade incentiv. | N11: Projeto incentiv. | O11: Dedic.
B12: {={'IRIS TIMESHEET'!B12:J1778;'NOTIFY TIMESHEET'!B12:J1778;'P&D_1 TIMESHEET'!B12:J1778;'P&D_2 TIMESHEET'!B12:J1778;'P&D_3 TIMESHEET'!B12:J1778}} | C12: IRIS | D12: Processo aprimorado de moagem no modo passada | E12: Gabriel Alves Ferraz | G12: 45313 | H12: 76.9 | I12: Desenvolvimento | J12: Desenvolvimento IHM | K12: =IF(AND($M12=TRUE,$N12=TRUE),VLOOKUP($E12,RH!$B$47:$S$67,MONTH($G12)+6,FALSE)) -> 22.246026 | L12: =IFERROR(IF(AND($M12=TRUE,$N12=TRUE),VLOOKUP($E12,RH!$B$47:$S$67,MONTH($G12)+6,FALSE)*$H12,0),0) -> 1710.7194 | M12: =IF(OR(I12="Treinamento",I12="Pesquisa",I12="Desenvolvimento"),TRUE,FALSE) -> TRUE | N12: {=XLOOKUP($C$12:$C1778,'Resumo - PROJETOS'!$B:$B,'Resumo - PROJETOS'!$C:$C,,0)} -> TRUE | O12: {=XLOOKUP($E$12:$E1778,RH!$B:$B,RH!$V:$V,,0)} -> Parcial
C13: IRIS | D13: Processo aprimorado de moagem no modo passada | E13: Gabriel Oliveira | G13: 45294 | H13: 166.5 | I13: Desenvolvimento | J13: Design UX/UI | K13: =IF(AND($M13=TRUE,$N13=TRUE),VLOOKUP($E13,RH!$B$47:$S$67,MONTH($G13)+6,FALSE)) -> 75.071402 | L13: =IFERROR(IF(AND($M13=TRUE,$N13=TRUE),VLOOKUP($E13,RH!$B$47:$S$67,MONTH($G13)+6,FALSE)*$H13,0),0) -> 12499.388 | M13: =IF(OR(I13="Treinamento",I13="Pesquisa",I13="Desenvolvimento"),TRUE,FALSE) -> TRUE | N13: TRUE | O13: Parcial
C14: IRIS | D14: Processo aprimorado de moagem no modo passada | E14: Guilherme Jacques | G14: 45320 | H14: 4.5 | I14: Desenvolvimento | J14: Desenvolvimento PLC | K14: =IF(AND($M14=TRUE,$N14=TRUE),VLOOKUP($E14,RH!$B$47:$S$67,MONTH($G14)+6,FALSE)) -> 39.311025 | L14: =IFERROR(IF(AND($M14=TRUE,$N14=TRUE),VLOOKUP($E14,RH!$B$47:$S$67,MONTH($G14)+6,FALSE)*$H14,0),0) -> 176.89961 | M14: =IF(OR(I14="Treinamento",I14="Pesquisa",I14="Desenvolvimento"),TRUE,FALSE) -> TRUE | N14: TRUE | O14: Parcial
C15: IRIS | D15: Processo aprimorado de moagem no modo passada | E15: Filipe Harbs | G15: 45299 | H15: 186.75 | I15: Desenvolvimento | J15: Desenvolvimento IHM | K15: =IF(AND($M15=TRUE,$N15=TRUE),VLOOKUP($E15,RH!$B$47:$S$67,MONTH($G15)+6,FALSE)) -> 44.364385 | L15: =IFERROR(IF(AND($M15=TRUE,$N15=TRUE),VLOOKUP($E15,RH!$B$47:$S$67,MONTH($G15)+6,FALSE)*$H15,0),0) -> 8285.049 | M15: =IF(OR(I15="Treinamento",I15="Pesquisa",I15="Desenvolvimento"),TRUE,FALSE) -> TRUE | N15: TRUE | O15: Parcial
C16: IRIS | D16: Processo aprimorado de moagem no modo passada | E16: Italo Ebel | G16: 45295 | H16: 43 | I16: Desenvolvimento | J16: Documentação | K16: =IF(AND($M16=TRUE,$N16=TRUE),VLOOKUP($E16,RH!$B$47:$S$67,MONTH($G16)+6,FALSE)) -> 11.716965 | L16: =IFERROR(IF(AND($M16=TRUE,$N16=TRUE),VLOOKUP($E16,RH!$B$47:$S$67,MONTH($G16)+6,FALSE)*$H16,0),0) -> 503.8295 | M16: =IF(OR(I16="Treinamento",I16="Pesquisa",I16="Desenvolvimento"),TRUE,FALSE) -> TRUE | N16: TRUE | O16: Parcial
C17: IRIS | D17: Processo aprimorado de moagem no modo passada | E17: Ivo Ersching | G17: 45299 | H17: 140 | I17: Desenvolvimento | J17: Desenvolvimento PLC | K17: =IF(AND($M17=TRUE,$N17=TRUE),VLOOKUP($E17,RH!$B$47:$S$67,MONTH($G17)+6,FALSE)) -> 60.908512 | L17: =IFERROR(IF(AND($M17=TRUE,$N17=TRUE),VLOOKUP($E17,RH!$B$47:$S$67,MONTH($G17)+6,FALSE)*$H17,0),0) -> 8527.1916 | M17: =IF(OR(I17="Treinamento",I17="Pesquisa",I17="Desenvolvimento"),TRUE,FALSE) -> TRUE | N17: TRUE | O17: Parcial
C18: IRIS | D18: Processo aprimorado de moagem no modo passada | E18: Johann Ribeiro | G18: 45299 | H18: 43.5 | I18: Desenvolvimento | J18: Documentação | K18: =IF(AND($M18=TRUE,$N18=TRUE),VLOOKUP($E18,RH!$B$47:$S$67,MONTH($G18)+6,FALSE)) -> 12.916508 | L18: =IFERROR(IF(AND($M18=TRUE,$N18=TRUE),VLOOKUP($E18,RH!$B$47:$S$67,MONTH($G18)+6,FALSE)*$H18,0),0) -> 561.8681 | M18: =IF(OR(I18="Treinamento",I18="Pesquisa",I18="Desenvolvimento"),TRUE,FALSE) -> TRUE | N18: TRUE | O18: Parcial
C19: IRIS | D19: Processo aprimorado de moagem no modo passada | E19: Rafael Augusto Barbieri Lobato | G19: 45313 | H19: 2.8 | I19: Desenvolvimento | J19: Desenvolvimento PLC | K19: =IF(AND($M19=TRUE,$N19=TRUE),VLOOKUP($E19,RH!$B$47:$S$67,MONTH($G19)+6,FALSE)) -> 20.790651 | L19: =IFERROR(IF(AND($M19=TRUE,$N19=TRUE),VLOOKUP($E19,RH!$B$47:$S$67,MONTH($G19)+6,FALSE)*$H19,0),0) -> 58.213824 | M19: =IF(OR(I19="Treinamento",I19="Pesquisa",I19="Desenvolvimento"),TRUE,FALSE) -> TRUE | N19: TRUE | O19: Parcial
C20: IRIS | D20: Processo aprimorado de moagem no modo circulação | E20: Alexandre Baseggio | G20: 45344 | H20: 6.75 | I20: Desenvolvimento | J20: Desenvolvimento PLC | K20: =IF(AND($M20=TRUE,$N20=TRUE),VLOOKUP($E20,RH!$B$47:$S$67,MONTH($G20)+6,FALSE)) -> 54.32512 | L20: =IFERROR(IF(AND($M20=TRUE,$N20=TRUE),VLOOKUP($E20,RH!$B$47:$S$67,MONTH($G20)+6,FALSE)*$H20,0),0) -> 366.69456 | M20: =IF(OR(I20="Treinamento",I20="Pesquisa",I20="Desenvolvimento"),TRUE,FALSE) -> TRUE | N20: TRUE | O20: Parcial
C21: IRIS | D21: Processo aprimorado de moagem no modo circulação | E21: Gabriel Alves Ferraz | G21: 45323 | H21: 71.8 | I21: Desenvolvimento | J21: Desenvolvimento IHM | K21: =IF(AND($M21=TRUE,$N21=TRUE),VLOOKUP($E21,RH!$B$47:$S$67,MONTH($G21)+6,FALSE)) -> 23.253002 | L21: =IFERROR(IF(AND($M21=TRUE,$N21=TRUE),VLOOKUP($E21,RH!$B$47:$S$67,MONTH($G21)+6,FALSE)*$H21,0),0) -> 1669.5656 | M21: =IF(OR(I21="Treinamento",I21="Pesquisa",I21="Desenvolvimento"),TRUE,FALSE) -> TRUE | N21: TRUE | O21: Parcial
C22: IRIS | D22: Processo aprimorado de moagem no modo circulação | E22: Gabriel Oliveira | G22: 45323 | H22: 189.92 | I22: Desenvolvimento | J22: Design UX/UI | K22: =IF(AND($M22=TRUE,$N22=TRUE),VLOOKUP($E22,RH!$B$47:$S$67,MONTH($G22)+6,FALSE)) -> 78.469544 | L22: =IFERROR(IF(AND($M22=TRUE,$N22=TRUE),VLOOKUP($E22,RH!$B$47:$S$67,MONTH($G22)+6,FALSE)*$H22,0),0) -> 14902.936 | M22: =IF(OR(I22="Treinamento",I22="Pesquisa",I22="Desenvolvimento"),TRUE,FALSE) -> TRUE | N22: TRUE | O22: Parcial
C23: IRIS | D23: Processo aprimorado de moagem no modo circulação | E23: Guilherme Jacques | G23: 45327 | H23: 115.65 | I23: Desenvolvimento | J23: Desenvolvimento PLC | K23: =IF(AND($M23=TRUE,$N23=TRUE),VLOOKUP($E23,RH!$B$47:$S$67,MONTH($G23)+6,FALSE)) -> 41.090456 | L23: =IFERROR(IF(AND($M23=TRUE,$N23=TRUE),VLOOKUP($E23,RH!$B$47:$S$67,MONTH($G23)+6,FALSE)*$H23,0),0) -> 4752.1113 | M23: =IF(OR(I23="Treinamento",I23="Pesquisa",I23="Desenvolvimento"),TRUE,FALSE) -> TRUE | N23: TRUE | O23: Parcial
C24: IRIS | D24: Processo aprimorado de moagem no modo circulação | E24: Italo Ebel | G24: 45324 | H24: 33 | I24: Desenvolvimento | J24: Documentação | K24: =IF(AND($M24=TRUE,$N24=TRUE),VLOOKUP($E24,RH!$B$47:$S$67,MONTH($G24)+6,FALSE)) -> 12.247339 | L24: =IFERROR(IF(AND($M24=TRUE,$N24=TRUE),VLOOKUP($E24,RH!$B$47:$S$67,MONTH($G24)+6,FALSE)*$H24,0),0) -> 404.16218 | M24: =IF(OR(I24="Treinamento",I24="Pesquisa",I24="Desenvolvimento"),TRUE,FALSE) -> TRUE | N24: TRUE | O24: Parcial
... C149: IRIS | D149: IRIS V3 BeadMill Inview - Advance Training video | E149: Johann Ribeiro | G149: 45628 | H149: 30 | I149: Desenvolvimento | J149: Gravação de videos | K149: =IF(AND($M149=TRUE,$N149=TRUE),VLOOKUP($E149,RH!$B$47:$S$67,MONTH($G149)+6,FALSE)) -> 14.249843 | L149: =IFERROR(IF(AND($M149=TRUE,$N149=TRUE),VLOOKUP($E149,RH!$B$47:$S$67,MONTH($G149)+6,FALSE)*$H149,0),0) -> 427.49529 | M149: =IF(OR(I149="Treinamento",I149="Pesquisa",I149="Desenvolvimento"),TRUE,FALSE) -> TRUE | N149: TRUE | O149: Parcial
C150: Notify | D150: Relatório de lotes | E150: Gabriel Oliveira | F150: 085.943.039-12 | G150: 45292 | H150: 20 | I150: Desenvolvimento | J150: Desenvolvimento dos designs (UI/UX) | K150: =IF(AND($M150=TRUE,$N150=TRUE),VLOOKUP($E150,RH!$B$47:$S$67,MONTH($G150)+6,FALSE)) -> 75.071402 | L150: =IFERROR(IF(AND($M150=TRUE,$N150=TRUE),VLOOKUP($E150,RH!$B$47:$S$67,MONTH($G150)+6,FALSE)*$H150,0),0) -> 1501.428 | M150: =IF(OR(I150="Treinamento",I150="Pesquisa",I150="Desenvolvimento"),TRUE,FALSE) -> TRUE | N150: TRUE | O150: Parcial
C151: Notify | D151: Configuração Gateway para o IRIS V3 | E151: Arthur Muniz | F151: 037.196.611-64 | G151: 45292 | H151: 191 | I151: Desenvolvimento | J151: Desenvolvimento Beckend | K151: =IF(AND($M151=TRUE,$N151=TRUE),VLOOKUP($E151,RH!$B$47:$S$67,MONTH($G151)+6,FALSE)) -> 89.096488 | L151: =IFERROR(IF(AND($M151=TRUE,$N151=TRUE),VLOOKUP($E151,RH!$B$47:$S$67,MONTH($G151)+6,FALSE)*$H151,0),0) -> 17017.429 | M151: =IF(OR(I151="Treinamento",I151="Pesquisa",I151="Desenvolvimento"),TRUE,FALSE) -> TRUE | N151: TRUE | O151: Exclusivo
C152: Notify | D152: Exportar dados para o Excel | E152: Italo Ebel | F152: 534.546.398-08 | G152: 45292 | H152: 4 | I152: Desenvolvimento | J152: Testes | K152: =IF(AND($M152=TRUE,$N152=TRUE),VLOOKUP($E152,RH!$B$47:$S$67,MONTH($G152)+6,FALSE)) -> 11.716965 | L152: =IFERROR(IF(AND($M152=TRUE,$N152=TRUE),VLOOKUP($E152,RH!$B$47:$S$67,MONTH($G152)+6,FALSE)*$H152,0),0) -> 46.86786 | M152: =IF(OR(I152="Treinamento",I152="Pesquisa",I152="Desenvolvimento"),TRUE,FALSE) -> TRUE | N152: TRUE | O152: Parcial
C153: Notify | D153: Adequação do Gateway para o IRIS V3 | E153: Bruno katzjarowksi | F153: 080.850.859-84 | G153: 45292 | H153: 198 | I153: Desenvolvimento | J153: Desenvolvimento Beckend | K153: =IF(AND($M153=TRUE,$N153=TRUE),VLOOKUP($E153,RH!$B$47:$S$67,MONTH($G153)+6,FALSE)) -> 107.35211 | L153: =IFERROR(IF(AND($M153=TRUE,$N153=TRUE),VLOOKUP($E153,RH!$B$47:$S$67,MONTH($G153)+6,FALSE)*$H153,0),0) -> 21255.717 | M153: =IF(OR(I153="Treinamento",I153="Pesquisa",I153="Desenvolvimento"),TRUE,FALSE) -> TRUE | N153: TRUE | O153: Exclusivo
C154: Notify | D154: Templates de gráficos | E154: Cleiton Capristano | F154: 068.504.079-88 | G154: 45292 | H154: 122 | I154: Desenvolvimento | J154: Desenvolvimento Fronend | K154: =IF(AND($M154=TRUE,$N154=TRUE),VLOOKUP($E154,RH!$B$47:$S$67,MONTH($G154)+6,FALSE)) -> 94.807812 | L154: =IFERROR(IF(AND($M154=TRUE,$N154=TRUE),VLOOKUP($E154,RH!$B$47:$S$67,MONTH($G154)+6,FALSE)*$H154,0),0) -> 11566.553 | M154: =IF(OR(I154="Treinamento",I154="Pesquisa",I154="Desenvolvimento"),TRUE,FALSE) -> TRUE | N154: TRUE | O154: Exclusivo
C155: Notify | D155: Configuração Gateway para o IRIS V3 | E155: Gabriel Possamai | F155: 085.815.809-47 | G155: 45292 | H155: 120 | I155: Pesquisa | J155: Especificação da funcionalidade | K155: =IF(AND($M155=TRUE,$N155=TRUE),VLOOKUP($E155,RH!$B$47:$S$67,MONTH($G155)+6,FALSE)) -> 114.23363 | L155: =IFERROR(IF(AND($M155=TRUE,$N155=TRUE),VLOOKUP($E155,RH!$B$47:$S$67,MONTH($G155)+6,FALSE)*$H155,0),0) -> 13708.035 | M155: =IF(OR(I155="Treinamento",I155="Pesquisa",I155="Desenvolvimento"),TRUE,FALSE) -> TRUE | N155: TRUE | O155: Exclusivo
C156: Notify | D156: Configuração Gateway para o IRIS V3 | E156: Paulo Odwazny | F156: 035.705.119-01 | G156: 45292 | H156: 5 | I156: Pesquisa | J156: Especificação da funcionalidade | K156: =IF(AND($M156=TRUE,$N156=TRUE),VLOOKUP($E156,RH!$B$47:$S$67,MONTH($G156)+6,FALSE)) -> 130.30393 | L156: =IFERROR(IF(AND($M156=TRUE,$N156=TRUE),VLOOKUP($E156,RH!$B$47:$S$67,MONTH($G156)+6,FALSE)*$H156,0),0) -> 651.51967 | M156: =IF(OR(I156="Treinamento",I156="Pesquisa",I156="Desenvolvimento"),TRUE,FALSE) -> TRUE | N156: TRUE | O156: Parcial
C157: Notify | D157: Templates de gráficos | E157: Cristiano Schroeder | F157: 080.335.889-00 | G157: 45292 | H157: 168 | I157: Desenvolvimento | J157: Testes | K157: =IF(AND($M157=TRUE,$N157=TRUE),VLOOKUP($E157,RH!$B$47:$S$67,MONTH($G157)+6,FALSE)) -> 55.69307 | L157: =IFERROR(IF(AND($M157=TRUE,$N157=TRUE),VLOOKUP($E157,RH!$B$47:$S$67,MONTH($G157)+6,FALSE)*$H157,0),0) -> 9356.4357 | M157: =IF(OR(I157="Treinamento",I157="Pesquisa",I157="Desenvolvimento"),TRUE,FALSE) -> TRUE | N157: TRUE | O157: Parcial
C158: Notify | D158: Relatório de lotes | E158: Gabriel Oliveira | F158: 085.943.039-12 | G158: 45323 | H158: 17 | I158: Desenvolvimento | J158: Desenvolvimento dos designs (UI/UX) | K158: =IF(AND($M158=TRUE,$N158=TRUE),VLOOKUP($E158,RH!$B$47:$S$67,MONTH($G158)+6,FALSE)) -> 78.469544 | L158: =IFERROR(IF(AND($M158=TRUE,$N158=TRUE),VLOOKUP($E158,RH!$B$47:$S$67,MONTH($G158)+6,FALSE)*$H158,0),0) -> 1333.9822 | M158: =IF(OR(I158="Treinamento",I158="Pesquisa",I158="Desenvolvimento"),TRUE,FALSE) -> TRUE | N158: TRUE | O158: Parcial
C159: Notify | D159: Configuração Gateway para o IRIS V3 | E159: Arthur Muniz | F159: 037.196.611-64 | G159: 45323 | H159: 89 | I159: Desenvolvimento | J159: Desenvolvimento Beckend | K159: =IF(AND($M159=TRUE,$N159=TRUE),VLOOKUP($E159,RH!$B$47:$S$67,MONTH($G159)+6,FALSE)) -> 93.129481 | L159: =IFERROR(IF(AND($M159=TRUE,$N159=TRUE),VLOOKUP($E159,RH!$B$47:$S$67,MONTH($G159)+6,FALSE)*$H159,0),0) -> 8288.5238 | M159: =IF(OR(I159="Treinamento",I159="Pesquisa",I159="Desenvolvimento"),TRUE,FALSE) -> TRUE | N159: TRUE | O159: Exclusivo
C160: Notify | D160: Templates de gráficos | E160: Italo Ebel | F160: 534.546.398-08 | G160: 45323 | H160: 36 | I160: Desenvolvimento | J160: Testes | K160: =IF(AND($M160=TRUE,$N160=TRUE),VLOOKUP($E160,RH!$B$47:$S$67,MONTH($G160)+6,FALSE)) -> 12.247339 | L160: =IFERROR(IF(AND($M160=TRUE,$N160=TRUE),VLOOKUP($E160,RH!$B$47:$S$67,MONTH($G160)+6,FALSE)*$H160,0),0) -> 440.9042 | M160: =IF(OR(I160="Treinamento",I160="Pesquisa",I160="Desenvolvimento"),TRUE,FALSE) -> TRUE | N160: TRUE | O160: Parcial
C161: Notify | D161: Adequação do Gateway para o IRIS V3 | E161: Bruno katzjarowksi | F161: 080.850.859-84 | G161: 45323 | H161: 193 | I161: Desenvolvimento | J161: Desenvolvimento Beckend | K161: =IF(AND($M161=TRUE,$N161=TRUE),VLOOKUP($E161,RH!$B$47:$S$67,MONTH($G161)+6,FALSE)) -> 112.21145 | L161: =IFERROR(IF(AND($M161=TRUE,$N161=TRUE),VLOOKUP($E161,RH!$B$47:$S$67,MONTH($G161)+6,FALSE)*$H161,0),0) -> 21656.809 | M161: =IF(OR(I161="Treinamento",I161="Pesquisa",I161="Desenvolvimento"),TRUE,FALSE) -> TRUE | N161: TRUE | O161: Exclusivo
... C241: Notify | D241: Adequação do Gateway para o IRIS V3 | E241: Italo Ebel | F241: 534.546.398-08 | G241: 45627 | H241: 154 | I241: Desenvolvimento | J241: Testes | K241: =IF(AND($M241=TRUE,$N241=TRUE),VLOOKUP($E241,RH!$B$47:$S$67,MONTH($G241)+6,FALSE)) -> 14.249843 | L241: =IFERROR(IF(AND($M241=TRUE,$N241=TRUE),VLOOKUP($E241,RH!$B$47:$S$67,MONTH($G241)+6,FALSE)*$H241,0),0) -> 2194.4758 | M241: =IF(OR(I241="Treinamento",I241="Pesquisa",I241="Desenvolvimento"),TRUE,FALSE) -> TRUE | N241: TRUE | O241: Parcial
K242: =IF(AND($M242=TRUE,$N242=TRUE),VLOOKUP($E242,RH!$B$47:$S$67,MONTH($G242)+6,FALSE)) -> FALSE | L242: =IFERROR(IF(AND($M242=TRUE,$N242=TRUE),VLOOKUP($E242,RH!$B$47:$S$67,MONTH($G242)+6,FALSE)*$H242,0),0) -> 0 | M242: =IF(OR(I242="Treinamento",I242="Pesquisa",I242="Desenvolvimento"),TRUE,FALSE) -> FALSE
C243: P&D_2 | D243: Outros tamanhos e geometrias de dentes das ferramentas, outros materiais | E243: Jivago Rusch | G243: 45314 | H243: 16 | I243: Desenvolvimento | J243: Teste com ferramentas de 5mm com amendoim | K243: =IF(AND($M243=TRUE,$N243=TRUE),VLOOKUP($E243,RH!$B$47:$S$67,MONTH($G243)+6,FALSE)) -> FALSE | L243: =IFERROR(IF(AND($M243=TRUE,$N243=TRUE),VLOOKUP($E243,RH!$B$47:$S$67,MONTH($G243)+6,FALSE)*$H243,0),0) -> 0 | M243: =IF(OR(I243="Treinamento",I243="Pesquisa",I243="Desenvolvimento"),TRUE,FALSE) -> TRUE | N243: FALSE | O243: Parcial
C244: P&D_2 | D244: Ferramentas resistente ao desgaste | E244: Jivago Rusch | G244: 45338 | H244: 8 | I244: Desenvolvimento | J244: Modelamento de ferramenta com novo design progressivo para maior resistencia ao desgaste | K244: =IF(AND($M244=TRUE,$N244=TRUE),VLOOKUP($E244,RH!$B$47:$S$67,MONTH($G244)+6,FALSE)) -> FALSE | L244: =IFERROR(IF(AND($M244=TRUE,$N244=TRUE),VLOOKUP($E244,RH!$B$47:$S$67,MONTH($G244)+6,FALSE)*$H244,0),0) -> 0 | M244: =IF(OR(I244="Treinamento",I244="Pesquisa",I244="Desenvolvimento"),TRUE,FALSE) -> TRUE | N244: FALSE | O244: Parcial
C245: P&D_2 | D245: Melhorias do MasterCream MINI | E245: Jivago Rusch | G245: 45343 | H245: 40 | I245: Desenvolvimento | J245: Testes com novas ferramentas | K245: =IF(AND($M245=TRUE,$N245=TRUE),VLOOKUP($E245,RH!$B$47:$S$67,MONTH($G245)+6,FALSE)) -> FALSE | L245: =IFERROR(IF(AND($M245=TRUE,$N245=TRUE),VLOOKUP($E245,RH!$B$47:$S$67,MONTH($G245)+6,FALSE)*$H245,0),0) -> 0 | M245: =IF(OR(I245="Treinamento",I245="Pesquisa",I245="Desenvolvimento"),TRUE,FALSE) -> TRUE | N245: FALSE | O245: Parcial
C246: P&D_2 | D246: Rotor liso para redução da viscosidade após a moagem | E246: Jivago Rusch | G246: 45436 | H246: 40 | I246: Desenvolvimento | J246: Testes com rotor liso para redução da viscosidade do chocolate | K246: =IF(AND($M246=TRUE,$N246=TRUE),VLOOKUP($E246,RH!$B$47:$S$67,MONTH($G246)+6,FALSE)) -> FALSE | L246: =IFERROR(IF(AND($M246=TRUE,$N246=TRUE),VLOOKUP($E246,RH!$B$47:$S$67,MONTH($G246)+6,FALSE)*$H246,0),0) -> 0 | M246: =IF(OR(I246="Treinamento",I246="Pesquisa",I246="Desenvolvimento"),TRUE,FALSE) -> TRUE | N246: FALSE | O246: Parcial
C247: P&D_2 | D247: Adequação conforme design higienico | E247: Jivago Rusch | G247: 45468 | H247: 40 | I247: Desenvolvimento | J247: Desenho em corte do MC10 e MCIL10 com melhorias proposta conforme design higienico | K247: =IF(AND($M247=TRUE,$N247=TRUE),VLOOKUP($E247,RH!$B$47:$S$67,MONTH($G247)+6,FALSE)) -> FALSE | L247: =IFERROR(IF(AND($M247=TRUE,$N247=TRUE),VLOOKUP($E247,RH!$B$47:$S$67,MONTH($G247)+6,FALSE)*$H247,0),0) -> 0 | M247: =IF(OR(I247="Treinamento",I247="Pesquisa",I247="Desenvolvimento"),TRUE,FALSE) -> TRUE | N247: FALSE | O247: Parcial
C248: P&D_2 | D248: Adequações do MC10 conforme norma americana NFS ANSI 8 | E248: Jivago Rusch | G248: 45558 | H248: 40 | I248: Desenvolvimento | J248: Desenvolvimento do projeto do equipamento MC10 atendendo requisitos da norma do mercado de alimentos americana NFS ANSI 8 para certificar o equipamento e facilitar processos de limpeza CIP e garantir a segurança alimentar | K248: =IF(AND($M248=TRUE,$N248=TRUE),VLOOKUP($E248,RH!$B$47:$S$67,MONTH($G248)+6,FALSE)) -> FALSE | L248: =IFERROR(IF(AND($M248=TRUE,$N248=TRUE),VLOOKUP($E248,RH!$B$47:$S$67,MONTH($G248)+6,FALSE)*$H248,0),0) -> 0 | M248: =IF(OR(I248="Treinamento",I248="Pesquisa",I248="Desenvolvimento"),TRUE,FALSE) -> TRUE | N248: FALSE | O248: Parcial
C249: P&D_3 | D249: Testes de limpeza e e secagem com linha Rumba sem tanques | E249: Jivago Rusch | G249: 45321 | H249: 8 | I249: Desenvolvimento | J249: Teste 3.5 - Chocolate ao leite | K249: =IF(AND($M249=TRUE,$N249=TRUE),VLOOKUP($E249,RH!$B$47:$S$67,MONTH($G249)+6,FALSE)) -> 52.762543 | L249: =IFERROR(IF(AND($M249=TRUE,$N249=TRUE),VLOOKUP($E249,RH!$B$47:$S$67,MONTH($G249)+6,FALSE)*$H249,0),0) -> 422.10035 | M249: =IF(OR(I249="Treinamento",I249="Pesquisa",I249="Desenvolvimento"),TRUE,FALSE) -> TRUE | N249: TRUE | O249: Parcial
D250: Testes de limpeza e e secagem com linha Rumba sem tanques | E250: Fernando Leal | G250: 45321 | H250: 8 | I250: Desenvolvimento | J250: Teste 3.5 - Chocolate ao leite | K250: =IF(AND($M250=TRUE,$N250=TRUE),VLOOKUP($E250,RH!$B$47:$S$67,MONTH($G250)+6,FALSE)) -> FALSE | L250: =IFERROR(IF(AND($M250=TRUE,$N250=TRUE),VLOOKUP($E250,RH!$B$47:$S$67,MONTH($G250)+6,FALSE)*$H250,0),0) -> 0 | M250: =IF(OR(I250="Treinamento",I250="Pesquisa",I250="Desenvolvimento"),TRUE,FALSE) -> TRUE | O250: Parcial
C251: P&D_3 | D251: Testes de limpeza e e secagem com linha Rumba sem tanques | E251: Jivago Rusch | G251: 45334 | H251: 8 | I251: Desenvolvimento | J251: Teste 3.6 - Chocolate ao leite | K251: =IF(AND($M251=TRUE,$N251=TRUE),VLOOKUP($E251,RH!$B$47:$S$67,MONTH($G251)+6,FALSE)) -> 55.150864 | L251: =IFERROR(IF(AND($M251=TRUE,$N251=TRUE),VLOOKUP($E251,RH!$B$47:$S$67,MONTH($G251)+6,FALSE)*$H251,0),0) -> 441.20691 | M251: =IF(OR(I251="Treinamento",I251="Pesquisa",I251="Desenvolvimento"),TRUE,FALSE) -> TRUE | N251: TRUE | O251: Parcial
D252: Testes de limpeza e e secagem com linha Rumba sem tanques | E252: Fernando Leal | G252: 45334 | H252: 8 | I252: Desenvolvimento | J252: Teste 3.6 - Chocolate ao leite | K252: =IF(AND($M252=TRUE,$N252=TRUE),VLOOKUP($E252,RH!$B$47:$S$67,MONTH($G252)+6,FALSE)) -> FALSE | L252: =IFERROR(IF(AND($M252=TRUE,$N252=TRUE),VLOOKUP($E252,RH!$B$47:$S$67,MONTH($G252)+6,FALSE)*$H252,0),0) -> 0 | M252: =IF(OR(I252="Treinamento",I252="Pesquisa",I252="Desenvolvimento"),TRUE,FALSE) -> TRUE | O252: Parcial
C253: P&D_3 | D253: Testes de limpeza e e secagem com linha Rumba sem tanques | E253: Jivago Rusch | G253: 45379 | H253: 8 | I253: Desenvolvimento | J253: Teste 3.7 - Compound | K253: =IF(AND($M253=TRUE,$N253=TRUE),VLOOKUP($E253,RH!$B$47:$S$67,MONTH($G253)+6,FALSE)) -> 57.858257 | L253: =IFERROR(IF(AND($M253=TRUE,$N253=TRUE),VLOOKUP($E253,RH!$B$47:$S$67,MONTH($G253)+6,FALSE)*$H253,0),0) -> 462.86606 | M253: =IF(OR(I253="Treinamento",I253="Pesquisa",I253="Desenvolvimento"),TRUE,FALSE) -> TRUE | N253: TRUE | O253: Parcial
D254: Testes de limpeza e e secagem com linha Rumba sem tanques | E254: Fernando Leal | G254: 45379 | H254: 8 | I254: Desenvolvimento | J254: Teste 3.7 - Compound | K254: =IF(AND($M254=TRUE,$N254=TRUE),VLOOKUP($E254,RH!$B$47:$S$67,MONTH($G254)+6,FALSE)) -> FALSE | L254: =IFERROR(IF(AND($M254=TRUE,$N254=TRUE),VLOOKUP($E254,RH!$B$47:$S$67,MONTH($G254)+6,FALSE)*$H254,0),0) -> 0 | M254: =IF(OR(I254="Treinamento",I254="Pesquisa",I254="Desenvolvimento"),TRUE,FALSE) -> TRUE | O254: Parcial
C255: P&D_3 | D255: Testes de limpeza e e secagem com linha Rumba sem tanques | E255: Jivago Rusch | G255: 45391 | H255: 8 | I255: Desenvolvimento | J255: Teste 3.8 - Chocolate amargo | K255: =IF(AND($M255=TRUE,$N255=TRUE),VLOOKUP($E255,RH!$B$47:$S$67,MONTH($G255)+6,FALSE)) -> 55.466094 | L255: =IFERROR(IF(AND($M255=TRUE,$N255=TRUE),VLOOKUP($E255,RH!$B$47:$S$67,MONTH($G255)+6,FALSE)*$H255,0),0) -> 443.72875 | M255: =IF(OR(I255="Treinamento",I255="Pesquisa",I255="Desenvolvimento"),TRUE,FALSE) -> TRUE | N255: TRUE | O255: Parcial
D256: Testes de limpeza e e secagem com linha Rumba sem tanques | E256: Fernando Leal | G256: 45391 | H256: 8 | I256: Desenvolvimento | J256: Teste 3.8 - Chocolate amargo | K256: =IF(AND($M256=TRUE,$N256=TRUE),VLOOKUP($E256,RH!$B$47:$S$67,MONTH($G256)+6,FALSE)) -> FALSE | L256: =IFERROR(IF(AND($M256=TRUE,$N256=TRUE),VLOOKUP($E256,RH!$B$47:$S$67,MONTH($G256)+6,FALSE)*$H256,0),0) -> 0 | M256: =IF(OR(I256="Treinamento",I256="Pesquisa",I256="Desenvolvimento"),TRUE,FALSE) -> TRUE | O256: Parcial
C257: P&D_3 | D257: Testes de limpeza e e secagem com linha Rumba sem tanques | E257: Jivago Rusch | G257: 45394 | H257: 8 | I257: Desenvolvimento | J257: Teste 3.9 - Chocolate ao leite - Cristalização da lactose | K257: =IF(AND($M257=TRUE,$N257=TRUE),VLOOKUP($E257,RH!$B$47:$S$67,MONTH($G257)+6,FALSE)) -> 55.466094 | L257: =IFERROR(IF(AND($M257=TRUE,$N257=TRUE),VLOOKUP($E257,RH!$B$47:$S$67,MONTH($G257)+6,FALSE)*$H257,0),0) -> 443.72875 | M257: =IF(OR(I257="Treinamento",I257="Pesquisa",I257="Desenvolvimento"),TRUE,FALSE) -> TRUE | N257: TRUE | O257: Parcial
D258: Testes de limpeza e e secagem com linha Rumba sem tanques | E258: Fernando Leal | G258: 45394 | H258: 8 | I258: Desenvolvimento | J258: Teste 3.9 - Chocolate ao leite - Cristalização da lactose | K258: =IF(AND($M258=TRUE,$N258=TRUE),VLOOKUP($E258,RH!$B$47:$S$67,MONTH($G258)+6,FALSE)) -> FALSE | L258: =IFERROR(IF(AND($M258=TRUE,$N258=TRUE),VLOOKUP($E258,RH!$B$47:$S$67,MONTH($G258)+6,FALSE)*$H258,0),0) -> 0 | M258: =IF(OR(I258="Treinamento",I258="Pesquisa",I258="Desenvolvimento"),TRUE,FALSE) -> TRUE | O258: Parcial
C259: P&D_3 | D259: Testes de limpeza e e secagem com linha Rumba sem tanques | E259: Jivago Rusch | G259: 45411 | H259: 8 | I259: Desenvolvimento | J259: Teste 3.10 - Chocolate ao leite - Cristalização da lactose | K259: =IF(AND($M259=TRUE,$N259=TRUE),VLOOKUP($E259,RH!$B$47:$S$67,MONTH($G259)+6,FALSE)) -> 55.466094 | L259: =IFERROR(IF(AND($M259=TRUE,$N259=TRUE),VLOOKUP($E259,RH!$B$47:$S$67,MONTH($G259)+6,FALSE)*$H259,0),0) -> 443.72875 | M259: =IF(OR(I259="Treinamento",I259="Pesquisa",I259="Desenvolvimento"),TRUE,FALSE) -> TRUE | N259: TRUE | O259: Parcial
D260: Testes de limpeza e e secagem com linha Rumba sem tanques | E260: Fernando Leal | G260: 45411 | H260: 8 | I260: Desenvolvimento | J260: Teste 3.10 - Chocolate ao leite - Cristalização da lactose | K260: =IF(AND($M260=TRUE,$N260=TRUE),VLOOKUP($E260,RH!$B$47:$S$67,MONTH($G260)+6,FALSE)) -> FALSE | L260: =IFERROR(IF(AND($M260=TRUE,$N260=TRUE),VLOOKUP($E260,RH!$B$47:$S$67,MONTH($G260)+6,FALSE)*$H260,0),0) -> 0 | M260: =IF(OR(I260="Treinamento",I260="Pesquisa",I260="Desenvolvimento"),TRUE,FALSE) -> TRUE | O260: Parcial
C261: P&D_3 | D261: Testes de limpeza e e secagem com linha Rumba sem tanques | E261: Jivago Rusch | G261: 45447 | H261: 8 | I261: Desenvolvimento | J261: Teste 3.11 - Chocolate branco | K261: =IF(AND($M261=TRUE,$N261=TRUE),VLOOKUP($E261,RH!$B$47:$S$67,MONTH($G261)+6,FALSE)) -> 58.038798 | L261: =IFERROR(IF(AND($M261=TRUE,$N261=TRUE),VLOOKUP($E261,RH!$B$47:$S$67,MONTH($G261)+6,FALSE)*$H261,0),0) -> 464.31038 | M261: =IF(OR(I261="Treinamento",I261="Pesquisa",I261="Desenvolvimento"),TRUE,FALSE) -> TRUE | N261: TRUE | O261: Parcial
C262: P&D_3 | D262: Testes de limpeza e e secagem com linha Rumba sem tanques | E262: Jivago Rusch | G262: 45447 | H262: 8 | I262: Pesquisa | J262: Teste 3.11 - Chocolate branco | K262: =IF(AND($M262=TRUE,$N262=TRUE),VLOOKUP($E262,RH!$B$47:$S$67,MONTH($G262)+6,FALSE)) -> 58.038798 | L262: =IFERROR(IF(AND($M262=TRUE,$N262=TRUE),VLOOKUP($E262,RH!$B$47:$S$67,MONTH($G262)+6,FALSE)*$H262,0),0) -> 464.31038 | M262: =IF(OR(I262="Treinamento",I262="Pesquisa",I262="Desenvolvimento"),TRUE,FALSE) -> TRUE | N262: TRUE | O262: Parcial
C263: P&D_3 | D263: Testes de limpeza e e secagem com linha Rumba sem tanques | E263: Fernando Leal | G263: 45447 | H263: 8 | I263: Pesquisa | J263: Teste 3.11 - Chocolate branco | K263: =IF(AND($M263=TRUE,$N263=TRUE),VLOOKUP($E263,RH!$B$47:$S$67,MONTH($G263)+6,FALSE)) -> 35.343679 | L263: =IFERROR(IF(AND($M263=TRUE,$N263=TRUE),VLOOKUP($E263,RH!$B$47:$S$67,MONTH($G263)+6,FALSE)*$H263,0),0) -> 282.74943 | M263: =IF(OR(I263="Treinamento",I263="Pesquisa",I263="Desenvolvimento"),TRUE,FALSE) -> TRUE | N263: TRUE | O263: Parcial
C264: P&D_3 | D264: Testes de limpeza e e secagem com linha Rumba sem tanques | E264: Jivago Rusch | G264: 45489 | H264: 8 | I264: Pesquisa | J264: Teste 3.12 - Recheio com amendoim. Realizada analise de alergenicos para amendoim. Foi identificada a presença de alergenicos na tubulação, porem a analise não quantifica. Necessario desenvolver uma analise que quantifique em ppm. | K264: =IF(AND($M264=TRUE,$N264=TRUE),VLOOKUP($E264,RH!$B$47:$S$67,MONTH($G264)+6,FALSE)) -> 50.795586 | L264: =IFERROR(IF(AND($M264=TRUE,$N264=TRUE),VLOOKUP($E264,RH!$B$47:$S$67,MONTH($G264)+6,FALSE)*$H264,0),0) -> 406.36469 | M264: =IF(OR(I264="Treinamento",I264="Pesquisa",I264="Desenvolvimento"),TRUE,FALSE) -> TRUE | N264: TRUE | O264: Parcial
C265: P&D_3 | D265: Testes de limpeza e e secagem com linha Rumba sem tanques | E265: Fernando Leal | G265: 45489 | H265: 8 | I265: Pesquisa | J265: Teste 3.12 - Recheio com amendoim. Realizada analise de alergenicos para amendoim. Foi identificada a presença de alergenicos na tubulação, porem a analise não quantifica. Necessario desenvolver uma analise que quantifique em ppm. | K265: =IF(AND($M265=TRUE,$N265=TRUE),VLOOKUP($E265,RH!$B$47:$S$67,MONTH($G265)+6,FALSE)) -> 30.932806 | L265: =IFERROR(IF(AND($M265=TRUE,$N265=TRUE),VLOOKUP($E265,RH!$B$47:$S$67,MONTH($G265)+6,FALSE)*$H265,0),0) -> 247.46245 | M265: =IF(OR(I265="Treinamento",I265="Pesquisa",I265="Desenvolvimento"),TRUE,FALSE) -> TRUE | N265: TRUE | O265: Parcial
K266: =IF(AND($M266=TRUE,$N266=TRUE),VLOOKUP($E266,RH!$B$47:$S$67,MONTH($G266)+6,FALSE)) -> FALSE | L266: =IFERROR(IF(AND($M266=TRUE,$N266=TRUE),VLOOKUP($E266,RH!$B$47:$S$67,MONTH($G266)+6,FALSE)*$H266,0),0) -> 0 | M266: =IF(OR(I266="Treinamento",I266="Pesquisa",I266="Desenvolvimento"),TRUE,FALSE) -> FALSE
C267: P&D_3 | D267: Testes de limpeza e e secagem com linha Rumba sem tanques | E267: Jivago Rusch | G267: 45558 | H267: 8 | I267: Pesquisa | J267: Teste 3.14 - Recheio com amendoim 2%, realizada a limpeza e analise de alergenicos de amendoim, resultados abaixo de 2ppm. | K267: =IF(AND($M267=TRUE,$N267=TRUE),VLOOKUP($E267,RH!$B$47:$S$67,MONTH($G267)+6,FALSE)) -> 55.43266 | L267: =IFERROR(IF(AND($M267=TRUE,$N267=TRUE),VLOOKUP($E267,RH!$B$47:$S$67,MONTH($G267)+6,FALSE)*$H267,0),0) -> 443.46128 | M267: =IF(OR(I267="Treinamento",I267="Pesquisa",I267="Desenvolvimento"),TRUE,FALSE) -> TRUE | N267: TRUE | O267: Parcial
C268: P&D_3 | D268: Testes de limpeza e e secagem com linha Rumba sem tanques | E268: Fernando Leal | G268: 45558 | H268: 8 | I268: Pesquisa | J268: Teste 3.14 - Recheio com amendoim 2%, realizada a limpeza e analise de alergenicos de amendoim, resultados abaixo de 2ppm. | K268: =IF(AND($M268=TRUE,$N268=TRUE),VLOOKUP($E268,RH!$B$47:$S$67,MONTH($G268)+6,FALSE)) -> 33.756629 | L268: =IFERROR(IF(AND($M268=TRUE,$N268=TRUE),VLOOKUP($E268,RH!$B$47:$S$67,MONTH($G268)+6,FALSE)*$H268,0),0) -> 270.05303 | M268: =IF(OR(I268="Treinamento",I268="Pesquisa",I268="Desenvolvimento"),TRUE,FALSE) -> TRUE | N268: TRUE | O268: Parcial
K269: =IF(AND($M269=TRUE,$N269=TRUE),VLOOKUP($E269,RH!$B$47:$S$67,MONTH($G269)+6,FALSE)) -> FALSE | L269: =IFERROR(IF(AND($M269=TRUE,$N269=TRUE),VLOOKUP($E269,RH!$B$47:$S$67,MONTH($G269)+6,FALSE)*$H269,0),0) -> 0 | M269: =IF(OR(I269="Treinamento",I269="Pesquisa",I269="Desenvolvimento"),TRUE,FALSE) -> FALSE
K270: =IF(AND($M270=TRUE,$N270=TRUE),VLOOKUP($E270,RH!$B$47:$S$67,MONTH($G270)+6,FALSE)) -> FALSE | L270: =IFERROR(IF(AND($M270=TRUE,$N270=TRUE),VLOOKUP($E270,RH!$B$47:$S$67,MONTH($G270)+6,FALSE)*$H270,0),0) -> 0 | M270: =IF(OR(I270="Treinamento",I270="Pesquisa",I270="Desenvolvimento"),TRUE,FALSE) -> FALSE
K271: =IF(AND($M271=TRUE,$N271=TRUE),VLOOKUP($E271,RH!$B$47:$S$67,MONTH($G271)+6,FALSE)) -> FALSE | L271: =IFERROR(IF(AND($M271=TRUE,$N271=TRUE),VLOOKUP($E271,RH!$B$47:$S$67,MONTH($G271)+6,FALSE)*$H271,0),0) -> 0 | M271: =IF(OR(I271="Treinamento",I271="Pesquisa",I271="Desenvolvimento"),TRUE,FALSE) -> FALSE
K272: =IF(AND($M272=TRUE,$N272=TRUE),VLOOKUP($E272,RH!$B$47:$S$67,MONTH($G272)+6,FALSE)) -> FALSE | L272: =IFERROR(IF(AND($M272=TRUE,$N272=TRUE),VLOOKUP($E272,RH!$B$47:$S$67,MONTH($G272)+6,FALSE)*$H272,0),0) -> 0 | M272: =IF(OR(I272="Treinamento",I272="Pesquisa",I272="Desenvolvimento"),TRUE,FALSE) -> FALSE
K273: =IF(AND($M273=TRUE,$N273=TRUE),VLOOKUP($E273,RH!$B$47:$S$67,MONTH($G273)+6,FALSE)) -> FALSE | L273: =IFERROR(IF(AND($M273=TRUE,$N273=TRUE),VLOOKUP($E273,RH!$B$47:$S$67,MONTH($G273)+6,FALSE)*$H273,0),0) -> 0 | M273: =IF(OR(I273="Treinamento",I273="Pesquisa",I273="Desenvolvimento"),TRUE,FALSE) -> FALSE
K274: =IF(AND($M274=TRUE,$N274=TRUE),VLOOKUP($E274,RH!$B$47:$S$67,MONTH($G274)+6,FALSE)) -> FALSE | L274: =IFERROR(IF(AND($M274=TRUE,$N274=TRUE),VLOOKUP($E274,RH!$B$47:$S$67,MONTH($G274)+6,FALSE)*$H274,0),0) -> 0 | M274: =IF(OR(I274="Treinamento",I274="Pesquisa",I274="Desenvolvimento"),TRUE,FALSE) -> FALSE
K275: =IF(AND($M275=TRUE,$N275=TRUE),VLOOKUP($E275,RH!$B$47:$S$67,MONTH($G275)+6,FALSE)) -> FALSE | L275: =IFERROR(IF(AND($M275=TRUE,$N275=TRUE),VLOOKUP($E275,RH!$B$47:$S$67,MONTH($G275)+6,FALSE)*$H275,0),0) -> 0 | M275: =IF(OR(I275="Treinamento",I275="Pesquisa",I275="Desenvolvimento"),TRUE,FALSE) -> FALSE
K276: =IF(AND($M276=TRUE,$N276=TRUE),VLOOKUP($E276,RH!$B$47:$S$67,MONTH($G276)+6,FALSE)) -> FALSE | L276: =IFERROR(IF(AND($M276=TRUE,$N276=TRUE),VLOOKUP($E276,RH!$B$47:$S$67,MONTH($G276)+6,FALSE)*$H276,0),0) -> 0 | M276: =IF(OR(I276="Treinamento",I276="Pesquisa",I276="Desenvolvimento"),TRUE,FALSE) -> FALSE
K277: =IF(AND($M277=TRUE,$N277=TRUE),VLOOKUP($E277,RH!$B$47:$S$67,MONTH($G277)+6,FALSE)) -> FALSE | L277: =IFERROR(IF(AND($M277=TRUE,$N277=TRUE),VLOOKUP($E277,RH!$B$47:$S$67,MONTH($G277)+6,FALSE)*$H277,0),0) -> 0 | M277: =IF(OR(I277="Treinamento",I277="Pesquisa",I277="Desenvolvimento"),TRUE,FALSE) -> FALSE
K278: =IF(AND($M278=TRUE,$N278=TRUE),VLOOKUP($E278,RH!$B$47:$S$67,MONTH($G278)+6,FALSE)) -> FALSE | L278: =IFERROR(IF(AND($M278=TRUE,$N278=TRUE),VLOOKUP($E278,RH!$B$47:$S$67,MONTH($G278)+6,FALSE)*$H278,0),0) -> 0 | M278: =IF(OR(I278="Treinamento",I278="Pesquisa",I278="Desenvolvimento"),TRUE,FALSE) -> FALSE
K279: =IF(AND($M279=TRUE,$N279=TRUE),VLOOKUP($E279,RH!$B$47:$S$67,MONTH($G279)+6,FALSE)) -> FALSE | L279: =IFERROR(IF(AND($M279=TRUE,$N279=TRUE),VLOOKUP($E279,RH!$B$47:$S$67,MONTH($G279)+6,FALSE)*$H279,0),0) -> 0 | M279: =IF(OR(I279="Treinamento",I279="Pesquisa",I279="Desenvolvimento"),TRUE,FALSE) -> FALSE
K280: =IF(AND($M280=TRUE,$N280=TRUE),VLOOKUP($E280,RH!$B$47:$S$67,MONTH($G280)+6,FALSE)) -> FALSE | L280: =IFERROR(IF(AND($M280=TRUE,$N280=TRUE),VLOOKUP($E280,RH!$B$47:$S$67,MONTH($G280)+6,FALSE)*$H280,0),0) -> 0 | M280: =IF(OR(I280="Treinamento",I280="Pesquisa",I280="Desenvolvimento"),TRUE,FALSE) -> FALSE
... K1012: =IF(AND($M1012=TRUE,$N1012=TRUE),VLOOKUP($E1012,RH!$B$47:$S$67,MONTH($G1012)+6,FALSE)) -> FALSE | L1012: =IFERROR(IF(AND($M1012=TRUE,$N1012=TRUE),VLOOKUP($E1012,RH!$B$47:$S$67,MONTH($G1012)+6,FALSE)*$H1012,0),0) -> 0 | M1012: =IF(OR(I1012="Treinamento",I1012="Pesquisa",I1012="Desenvolvimento"),TRUE,FALSE) -> FALSE
M1013: FALSE
M1014: FALSE
M1015: FALSE
M1016: FALSE
M1017: FALSE
M1018: FALSE
M1019: FALSE
M1020: FALSE
M1021: FALSE
M1022: FALSE
M1023: FALSE
M1024: FALSE
... M1778: FALSE

Sheet Tabela dinâmica 1
E2: Ok
E3: 185 | F3: =E3-D3 -> -1.75
E4: Ok
E5: Ok
E6: 408 | F6: =E6-D6 -> -0.95
E7: 422 | F7: =E7-D7 -> -48.25
E8: 1027 | F8: =E8-D8 -> -1.08
E9: 373 | F9: =E9-D9 -> -30
E10: Ok
E11: 613 | F11: =E11-D11 -> -0.7
E12: 381 | F12: =E12-D12 -> -2.38
E14: Ok
E15: Ok
E16: Ok
E17: 1176 | F17: =E17-D17 -> -600
E18: 100 | F18: =E18-D18 -> -2
E19: Ok
E20: Ok
E21: 236 | F21: =E21-D21 -> -43
E22: 17 | F22: =E22-D22 -> -4
E24: 8 | F24: =E24-D24 -> -16
E25: 8 | F25: =E25-D25 -> -72

Sheet RH
B2: NETZSCH
B3: Pesquisa ,Desenvolvimento & Inovação
B4: Formulário de PD&I - Ano 2024
B5: -preencher somente os campos sombreados (cinza)
B8: Dossiê do projeto
B9: Cálculo de custo - Pessoal
B11: Salário bruto | T11: =(U11/12)*24 -> 185.53333 | U11: =(SUM(H45:S45)*8.8)/24 -> 92.766667
B12: Nome Completo | C12: CPF | D12: notas | E12: Cargo/função | F12: Formação | G12: Attachments | H12: Salário 01 | I12: Salário 02 | J12: Salário 03 | K12: Salário 04 | L12: Salário 05 | M12: Salário 06 | N12: Salário 07 | O12: Salário 08 | P12: Salário 09 | Q12: Salário 10 | R12: Salário 11 | S12: Salário 12 | T12: PD&I time | U12: PD&I (%) | V12: Classificação | W12: Pesquisador
B13: Alberto Reuters | C13: 041.176.229-00 | E13: Gerente de Desenvolvimento e Automação | F13: Mestrado | H13: 26213.95 | I13: 26213.95 | J13: 26213.95 | K13: 26213.95 | L13: 26213.95 | M13: 26213.95 | N13: 26213.95 | O13: 26213.95 | P13: 26213.95 | Q13: 26213.95 | R13: 27629.51 | S13: 27629.51 | T13: =IFERROR(__xludf.DUMMYFUNCTION("IFERROR(IF(W13=TRUE, SUM(FILTER('Resumo - TIMESHEETS'!$H:$H,'Resumo - TIMESHEETS'!M:M = TRUE,'Resumo - TIMESHEETS'!N:N = TRUE,'Resumo - TIMESHEETS'!E:E = B13))/24,0),0)"),0.0) -> 0 | U13: =T13/$U$11 -> 0 | V13: =IF(U13<80%,"Parcial","Exclusivo") -> Parcial | W13: TRUE
B14: Alexandre Baseggio | C14: 020.066.430-10 | E14: Desenvolvedor | F14: Pós graduado | H14: 7278.93 | I14: 7278.93 | J14: 7278.93 | K14: 7278.93 | L14: 7278.93 | M14: 7278.93 | N14: 7278.93 | O14: 7278.93 | P14: 7278.93 | Q14: 7278.93 | R14: 7672 | S14: 7672 | T14: =IFERROR(__xludf.DUMMYFUNCTION("IFERROR(IF(W14=TRUE, SUM(FILTER('Resumo - TIMESHEETS'!$H:$H,'Resumo - TIMESHEETS'!M:M = TRUE,'Resumo - TIMESHEETS'!N:N = TRUE,'Resumo - TIMESHEETS'!E:E = B14))/24,0),0)"),14.091666666666667) -> 14.091667 | U14: =T14/$U$11 -> 0.15190442 | V14: =IF(U14<80%,"Parcial","Exclusivo") -> Parcial | W14: TRUE
B15: Arthur Muniz | C15: 037.196.611-64 | E15: Desenvolvedor | F15: Superior Completo | H15: 12478.26 | I15: 12478.26 | J15: 12478.26 | K15: 12478.26 | L15: 12478.26 | M15: 12478.26 | N15: 13278.14 | O15: 13278.14 | P15: 13278.14 | Q15: 13278.14 | R15: 13995.16 | S15: 13995.16 | T15: =IFERROR(__xludf.DUMMYFUNCTION("IFERROR(IF(W15=TRUE, SUM(FILTER('Resumo - TIMESHEETS'!$H:$H,'Resumo - TIMESHEETS'!M:M = TRUE,'Resumo - TIMESHEETS'!N:N = TRUE,'Resumo - TIMESHEETS'!E:E = B15))/24,0),0)"),94.375) -> 94.375 | U15: =T15/$U$11 -> 1.0173374 | V15: =IF(U15<80%,"Parcial","Exclusivo") -> Exclusivo | W15: TRUE
B16: Bruno katzjarowksi | C16: 080.850.859-84 | E16: Desenvolvedor | F16: Superior Completo | H16: 15035.02 | I16: 15035.02 | J16: 15035.02 | K16: 15035.02 | L16: 15035.02 | M16: 15035.02 | N16: 15035.02 | O16: 15035.02 | P16: 15035.02 | Q16: 15035.02 | R16: 15846.92 | S16: 15846.92 | T16: =IFERROR(__xludf.DUMMYFUNCTION("IFERROR(IF(W16=TRUE, SUM(FILTER('Resumo - TIMESHEETS'!$H:$H,'Resumo - TIMESHEETS'!M:M = TRUE,'Resumo - TIMESHEETS'!N:N = TRUE,'Resumo - TIMESHEETS'!E:E = B16))/24,0),0)"),83.75) -> 83.75 | U16: =T16/$U$11 -> 0.90280273 | V16: =IF(U16<80%,"Parcial","Exclusivo") -> Exclusivo | W16: TRUE
B17: Cleiton Capristano | C17: 068.504.079-88 | E17: Desenvolvedor | F17: Superior Completo | H17: 13278.15 | I17: 14129.3 | J17: 14129.3 | K17: 14129.3 | L17: 14129.3 | M17: 14129.3 | N17: 14129.3 | O17: 14129.3 | P17: 14129.3 | Q17: 14129.3 | R17: 14892.29 | S17: 14892.29 | T17: =IFERROR(__xludf.DUMMYFUNCTION("IFERROR(IF(W17=TRUE, SUM(FILTER('Resumo - TIMESHEETS'!$H:$H,'Resumo - TIMESHEETS'!M:M = TRUE,'Resumo - TIMESHEETS'!N:N = TRUE,'Resumo - TIMESHEETS'!E:E = B17))/24,0),0)"),79.66666666666667) -> 79.666667 | U17: =T17/$U$11 -> 0.85878548 | V17: =IF(U17<80%,"Parcial","Exclusivo") -> Exclusivo | W17: TRUE
B18: Cristiano Schroeder | C18: 080.335.889-00 | E18: Desenvolvedor | F18: Superior Completo | H18: 7800 | I18: 7800 | J18: 7800 | K18: 7800 | L18: 7800 | M18: 7800 | N18: 7800 | O18: 7800 | P18: 7800 | Q18: 7800 | R18: 8221.2 | S18: 8221.2 | T18: =IFERROR(__xludf.DUMMYFUNCTION("IFERROR(IF(W18=TRUE, SUM(FILTER('Resumo - TIMESHEETS'!$H:$H,'Resumo - TIMESHEETS'!M:M = TRUE,'Resumo - TIMESHEETS'!N:N = TRUE,'Resumo - TIMESHEETS'!E:E = B18))/24,0),0)"),74.0) -> 74 | U18: =T18/$U$11 -> 0.79770032 | V18: =IF(U18<80%,"Parcial","Exclusivo") -> Parcial | W18: TRUE
B19: Eduardo Flohr | C19: 064.303.159-67 | E19: Supervisor de Automação | F19: Pós graduado | H19: 18939.88 | I19: 18939.88 | J19: 18939.88 | K19: 18939.88 | L19: 18939.88 | M19: 18939.88 | N19: 18939.88 | O19: 18939.88 | P19: 18939.88 | Q19: 18939.88 | R19: 19962.64 | S19: 19962.64 | T19: =IFERROR(__xludf.DUMMYFUNCTION("IFERROR(IF(W19=TRUE, SUM(FILTER('Resumo - TIMESHEETS'!$H:$H,'Resumo - TIMESHEETS'!M:M = TRUE,'Resumo - TIMESHEETS'!N:N = TRUE,'Resumo - TIMESHEETS'!E:E = B19))/24,0),0)"),0.0) -> 0 | U19: =T19/$U$11 -> 0 | V19: =IF(U19<80%,"Parcial","Exclusivo") -> Parcial | W19: TRUE
B20: Filipe Harbs | C20: 087.609.209-12 | E20: Desenvolvedor | F20: Técnico | H20: 6213.38 | T20: =IFERROR(__xludf.DUMMYFUNCTION("IFERROR(IF(W20=TRUE, SUM(FILTER('Resumo - TIMESHEETS'!$H:$H,'Resumo - TIMESHEETS'!M:M = TRUE,'Resumo - TIMESHEETS'!N:N = TRUE,'Resumo - TIMESHEETS'!E:E = B20))/24,0),0)"),7.78125) -> 7.78125 | U20: =T20/$U$11 -> 0.083879806 | V20: =IF(U20<80%,"Parcial","Exclusivo") -> Parcial | W20: TRUE
B21: Gabriel Alves Ferraz | C21: 132.105.086-07 | E21: Desenvolvedor | F21: Superior Completo | H21: 3115.63 | I21: 3115.63 | J21: 3115.63 | K21: 3115.63 | L21: 3115.63 | M21: 3115.63 | N21: 3338.07 | O21: 3338.07 | P21: 3338.07 | Q21: 3338.07 | R21: 3518.33 | S21: 3518.33 | T21: =IFERROR(__xludf.DUMMYFUNCTION("IFERROR(IF(W21=TRUE, SUM(FILTER('Resumo - TIMESHEETS'!$H:$H,'Resumo - TIMESHEETS'!M:M = TRUE,'Resumo - TIMESHEETS'!N:N = TRUE,'Resumo - TIMESHEETS'!E:E = B21))/24,0),0)"),29.767083333333332) -> 29.767083 | U21: =T21/$U$11 -> 0.32088124 | V21: =IF(U21<80%,"Parcial","Exclusivo") -> Parcial | W21: TRUE
B22: Gabriel Oliveira | C22: 085.943.039-12 | E22: Designer | F22: Superior Completo | H22: 10514 | I22: 10514 | J22: 10514 | K22: 10514 | L22: 10514 | M22: 10514 | N22: 10514 | O22: 10514 | P22: 10514 | Q22: 10514 | R22: 11081.76 | S22: 11081.76 | T22: =IFERROR(__xludf.DUMMYFUNCTION("IFERROR(IF(W22=TRUE, SUM(FILTER('Resumo - TIMESHEETS'!$H:$H,'Resumo - TIMESHEETS'!M:M = TRUE,'Resumo - TIMESHEETS'!N:N = TRUE,'Resumo - TIMESHEETS'!E:E = B22))/24,0),0)"),58.298750000000005) -> 58.29875 | U22: =T22/$U$11 -> 0.62844502 | V22: =IF(U22<80%,"Parcial","Exclusivo") -> Parcial | W22: TRUE
B23: Gabriel Possamai | C23: 085.815.809-47 | E23: Desenvolvedor | F23: Superior Completo | H23: 15998.8 | I23: 15998.8 | J23: 15998.8 | K23: 15998.8 | L23: 15998.8 | M23: 15998.8 | N23: 15998.8 | O23: 15998.8 | P23: 15998.8 | Q23: 15998.8 | R23: 16862.74 | S23: 16862.74 | T23: =IFERROR(__xludf.DUMMYFUNCTION("IFERROR(IF(W23=TRUE, SUM(FILTER('Resumo - TIMESHEETS'!$H:$H,'Resumo - TIMESHEETS'!M:M = TRUE,'Resumo - TIMESHEETS'!N:N = TRUE,'Resumo - TIMESHEETS'!E:E = B23))/24,0),0)"),78.54166666666667) -> 78.541667 | U23: =T23/$U$11 -> 0.84665828 | V23: =IF(U23<80%,"Parcial","Exclusivo") -> Exclusivo | W23: TRUE
B24: Guilherme Jacques | C24: 085.705.039-70 | E24: Desenvolvedor | F24: Superior Completo | H24: 5505.64 | I24: 5505.64 | J24: 5505.64 | K24: 5505.64 | L24: 5505.64 | M24: 5505.64 | N24: 6213.37 | O24: 6213.37 | P24: 6213.37 | Q24: 6213.37 | R24: 6548.9 | S24: 6548.9 | T24: =IFERROR(__xludf.DUMMYFUNCTION("IFERROR(IF(W24=TRUE, SUM(FILTER('Resumo - TIMESHEETS'!$H:$H,'Resumo - TIMESHEETS'!M:M = TRUE,'Resumo - TIMESHEETS'!N:N = TRUE,'Resumo - TIMESHEETS'!E:E = B24))/24,0),0)"),17.039583333333333) -> 17.039583 | U24: =T24/$U$11 -> 0.18368218 | V24: =IF(U24<80%,"Parcial","Exclusivo") -> Parcial | W24: TRUE
B25: Italo Ebel | C25: 534.546.398-08 | E25: Desenvolvedor | F25: Superior Completo | H25: 1641 | I25: 1641 | J25: 1641 | K25: 1641 | L25: 1641 | M25: 1641 | N25: 1641 | O25: 1809 | P25: 1809 | Q25: 1809 | R25: 1907 | S25: 1907 | T25: =IFERROR(__xludf.DUMMYFUNCTION("IFERROR(IF(W25=TRUE, SUM(FILTER('Resumo - TIMESHEETS'!$H:$H,'Resumo - TIMESHEETS'!M:M = TRUE,'Resumo - TIMESHEETS'!N:N = TRUE,'Resumo - TIMESHEETS'!E:E = B25))/24,0),0)"),43.510416666666664) -> 43.510417 | U25: =T25/$U$11 -> 0.46903072 | V25: =IF(U25<80%,"Parcial","Exclusivo") -> Parcial | W25: TRUE
B26: Ivo Ersching | C26: 052.208.059-67 | E26: Desenvolvedor | F26: Superior Completo | H26: 8530.44 | I26: 8530.44 | J26: 8530.44 | K26: 8530.44 | L26: 8530.44 | M26: 8530.44 | N26: 9020.43 | O26: 9020.43 | P26: 9020.43 | Q26: 9020.43 | R26: 9507.54 | S26: 9507.54 | T26: =IFERROR(__xludf.DUMMYFUNCTION("IFERROR(IF(W26=TRUE, SUM(FILTER('Resumo - TIMESHEETS'!$H:$H,'Resumo - TIMESHEETS'!M:M = TRUE,'Resumo - TIMESHEETS'!N:N = TRUE,'Resumo - TIMESHEETS'!E:E = B26))/24,0),0)"),42.836666666666666) -> 42.836667 | U26: =T26/$U$11 -> 0.46176788 | V26: =IF(U26<80%,"Parcial","Exclusivo") -> Parcial | W26: TRUE
B27: Johann Ribeiro | C27: 100.110.019-09 | E27: Desenvolvedor | F27: Técnico | H27: 1809 | I27: 1809 | J27: 1809 | K27: 1809 | L27: 1809 | M27: 1809 | N27: 1809 | O27: 1809 | P27: 1809 | Q27: 1809 | R27: 1907 | S27: 1907 | T27: =IFERROR(__xludf.DUMMYFUNCTION("IFERROR(IF(W27=TRUE, SUM(FILTER('Resumo - TIMESHEETS'!$H:$H,'Resumo - TIMESHEETS'!M:M = TRUE,'Resumo - TIMESHEETS'!N:N = TRUE,'Resumo - TIMESHEETS'!E:E = B27))/24,0),0)"),28.416666666666668) -> 28.416667 | U27: =T27/$U$11 -> 0.30632411 | V27: =IF(U27<80%,"Parcial","Exclusivo") -> Parcial | W27: TRUE
B28: Marcos Tribess | C28: 057.903.319-80 | E28: Desenvolvedor | F28: Superior Completo | H28: 7486.49 | I28: 7486.49 | J28: 7486.49 | K28: 7486.49 | L28: 7486.49 | M28: 7486.49 | N28: 7486.49 | O28: 7486.49 | P28: 7486.49 | Q28: 7486.79 | R28: 7890.76 | S28: 7890.76 | T28: =IFERROR(__xludf.DUMMYFUNCTION("IFERROR(IF(W28=TRUE, SUM(FILTER('Resumo - TIMESHEETS'!$H:$H,'Resumo - TIMESHEETS'!M:M = TRUE,'Resumo - TIMESHEETS'!N:N = TRUE,'Resumo - TIMESHEETS'!E:E = B28))/24,0),0)"),1.9333333333333333) -> 1.9333333 | U28: =T28/$U$11 -> 0.020840819 | V28: =IF(U28<80%,"Parcial","Exclusivo") -> Parcial | W28: TRUE
B29: Paulo Odwazny | C29: 035.705.119-01 | E29: Supervisor de Desenvolvimento | F29: Superior Completo | H29: 18249.5 | I29: 18249.5 | J29: 18249.5 | K29: 18249.5 | L29: 18249.5 | M29: 18249.5 | N29: 18249.5 | O29: 18249.5 | P29: 18249.5 | Q29: 18249.5 | R29: 19234.98 | S29: 19234.98 | T29: =IFERROR(__xludf.DUMMYFUNCTION("IFERROR(IF(W29=TRUE, SUM(FILTER('Resumo - TIMESHEETS'!$H:$H,'Resumo - TIMESHEETS'!M:M = TRUE,'Resumo - TIMESHEETS'!N:N = TRUE,'Resumo - TIMESHEETS'!E:E = B29))/24,0),0)"),0.875) -> 0.875 | U29: =T29/$U$11 -> 0.0094322673 | V29: =IF(U29<80%,"Parcial","Exclusivo") -> Parcial | W29: TRUE
B30: Rafael Augusto Barbieri Lobato | C30: 374.320.848-23 | E30: Desenvolvedor | F30: Superior Completo | H30: 2911.8 | I30: 2911.8 | J30: 2911.8 | K30: 2911.8 | L30: 2911.8 | M30: 2911.8 | N30: 3338.07 | O30: 3338.07 | P30: 3338.07 | Q30: 3338.07 | R30: 3518.33 | S30: 3518.33 | T30: =IFERROR(__xludf.DUMMYFUNCTION("IFERROR(IF(W30=TRUE, SUM(FILTER('Resumo - TIMESHEETS'!$H:$H,'Resumo - TIMESHEETS'!M:M = TRUE,'Resumo - TIMESHEETS'!N:N = TRUE,'Resumo - TIMESHEETS'!E:E = B30))/24,0),0)"),25.57083333333333) -> 25.570833 | U30: =T30/$U$11 -> 0.27564678 | V30: =IF(U30<80%,"Parcial","Exclusivo") -> Parcial | W30: TRUE
B31: Jivago Rusch | C31: 091.530.489-97 | E31: Projetista | F31: Superior Completo | H31: 7389.57 | I31: 7389.57 | J31: 7389.57 | K31: 7389.57 | L31: 7389.57 | M31: 7389.57 | N31: 7389.57 | O31: 7389.57 | P31: 7389.57 | Q31: 7389.57 | R31: 7788.61 | S31: 7788.61 | T31: =IFERROR(__xludf.DUMMYFUNCTION("IFERROR(IF(W31=TRUE, SUM(FILTER('Resumo - TIMESHEETS'!$H:$H,'Resumo - TIMESHEETS'!M:M = TRUE,'Resumo - TIMESHEETS'!N:N = TRUE,'Resumo - TIMESHEETS'!E:E = B31))/24,0),0)"),3.3333333333333335) -> 3.3333333 | U31: =T31/$U$11 -> 0.035932447 | V31: =IF(U31<80%,"Parcial","Exclusivo") -> Parcial | W31: TRUE
B32: William Buttenberg | C32: 091.530.489-97 | E32: Analista de Automação | F32: Técnico | Q32: 6611.67 | R32: 6968.7 | S32: 6968.7 | T32: =IFERROR(__xludf.DUMMYFUNCTION("IFERROR(IF(W32=TRUE, SUM(FILTER('Resumo - TIMESHEETS'!$H:$H,'Resumo - TIMESHEETS'!M:M = TRUE,'Resumo - TIMESHEETS'!N:N = TRUE,'Resumo - TIMESHEETS'!E:E = B32))/24,0),0)"),15.974166666666667) -> 15.974167 | U32: =T32/$U$11 -> 0.17219727 | V32: =IF(U32<80%,"Parcial","Exclusivo") -> Parcial | W32: TRUE
B33: Fernando Leal | C33: 416.012.648-01 | E33: Bolsista | F33: Pós graduado | H33: 4500 | I33: 4500 | J33: 4500 | K33: 4500 | L33: 4500 | M33: 4500 | N33: 4500 | O33: 4500 | P33: 4500 | Q33: 4500 | R33: 4500 | S33: 7000 | T33: =IFERROR(__xludf.DUMMYFUNCTION("IFERROR(IF(W33=TRUE, SUM(FILTER('Resumo - TIMESHEETS'!$H:$H,'Resumo - TIMESHEETS'!M:M = TRUE,'Resumo - TIMESHEETS'!N:N = TRUE,'Resumo - TIMESHEETS'!E:E = B33))/24,0),0)"),1.0) -> 1 | U33: =T33/$U$11 -> 0.010779734 | V33: =IF(U33<80%,"Parcial","Exclusivo") -> Parcial | W33: TRUE
F36: Cálculo do custo/hora | G36: Patronal | H36: 0.0043 | I36: 0.0017 | J36: 0.0007 | K36: 0.0083 | L36: 0.0076 | M36: 0.0043 | N36: 0.0118 | O36: 0.0125 | P36: 0.0076 | Q36: 0.0043 | R36: 0.0063 | S36: 0.0031 | T36: // Informações recebidas por e-mail do RH
G37: Terceiros | H37: 0.058 | I37: 0.058 | J37: 0.058 | K37: 0.058 | L37: 0.058 | M37: 0.058 | N37: 0.058 | O37: 0.058 | P37: 0.058 | Q37: 0.058 | R37: 0.058 | S37: 0.058
G38: RAT | H38: 0.015 | I38: 0.015 | J38: 0.015 | K38: 0.015 | L38: 0.015 | M38: 0.015 | N38: 0.015 | O38: 0.015 | P38: 0.015 | Q38: 0.015 | R38: 0.015 | S38: 0.015
G39: INSS | H39: =SUM(H36:H38) -> 0.0773 | I39: =SUM(I36:I38) -> 0.0747 | J39: =SUM(J36:J38) -> 0.0737 | K39: =SUM(K36:K38) -> 0.0813 | L39: =SUM(L36:L38) -> 0.0806 | M39: =SUM(M36:M38) -> 0.0773 | N39: =SUM(N36:N38) -> 0.0848 | O39: =SUM(O36:O38) -> 0.0855 | ... S39: =SUM(S36:S38) -> 0.0761
G40: FGTS | H40: 0.08 | I40: 0.08 | J40: 0.08 | K40: 0.08 | L40: 0.08 | M40: 0.08 | N40: 0.08 | O40: 0.08 | P40: 0.08 | Q40: 0.08 | R40: 0.08 | S40: 0.08
G41: Férias | H41: =((1+(1/3))*(1+H39+H40)/12) -> 0.12858889 | I41: =((1+(1/3))*(1+I39+I40)/12) -> 0.1283 | J41: =((1+(1/3))*(1+J39+J40)/12) -> 0.12818889 | K41: =((1+(1/3))*(1+K39+K40)/12) -> 0.12903333 | L41: =((1+(1/3))*(1+L39+L40)/12) -> 0.12895556 | M41: =((1+(1/3))*(1+M39+M40)/12) -> 0.12858889 | N41: =((1+(1/3))*(1+N39+N40)/12) -> 0.12942222 | O41: =((1+(1/3))*(1+O39+O40)/12) -> 0.1295 | ... S41: =((1+(1/3))*(1+S39+S40)/12) -> 0.12845556
G42: 13º | H42: =(1/12)*(1+H39+H40) -> 0.096441667 | I42: =(1/12)*(1+I39+I40) -> 0.096225 | J42: =(1/12)*(1+J39+J40) -> 0.096141667 | K42: =(1/12)*(1+K39+K40) -> 0.096775 | L42: =(1/12)*(1+L39+L40) -> 0.096716667 | M42: =(1/12)*(1+M39+M40) -> 0.096441667 | N42: =(1/12)*(1+N39+N40) -> 0.097066667 | O42: =(1/12)*(1+O39+O40) -> 0.097125 | ... S42: =(1/12)*(1+S39+S40) -> 0.096341667
G43: TOTAL | H43: =sum(H39:H42) -> 0.38233056 | I43: =sum(I39:I42) -> 0.379225 | J43: =sum(J39:J42) -> 0.37803056 | K43: =sum(K39:K42) -> 0.38710833 | L43: =sum(L39:L42) -> 0.38627222 | M43: =sum(M39:M42) -> 0.38233056 | N43: =sum(N39:N42) -> 0.39128889 | O43: =sum(O39:O42) -> 0.392125 | ... S43: =sum(S39:S42) -> 0.38089722
H45: =NETWORKDAYS(DATE(year(H46),month(H46),1),DATE(year(H46),month(H46)+1,0),$B$70:$B$82) -> 22 | I45: =NETWORKDAYS(DATE(year(I46),month(I46),1),DATE(year(I46),month(I46)+1,0),$B$70:$B$82) -> 21 | J45: =NETWORKDAYS(DATE(year(J46),month(J46),1),DATE(year(J46),month(J46)+1,0),$B$70:$B$82) -> 20 | K45: =NETWORKDAYS(DATE(year(K46),month(K46),1),DATE(year(K46),month(K46)+1,0),$B$70:$B$82) -> 21 | L45: =NETWORKDAYS(DATE(year(L46),month(L46),1),DATE(year(L46),month(L46)+1,0),$B$70:$B$82) -> 21 | M45: =NETWORKDAYS(DATE(year(M46),month(M46),1),DATE(year(M46),month(M46)+1,0),$B$70:$B$82) -> 20 | N45: =NETWORKDAYS(DATE(year(N46),month(N46),1),DATE(year(N46),month(N46)+1,0),$B$70:$B$82) -> 23 | O45: =NETWORKDAYS(DATE(year(O46),month(O46),1),DATE(year(O46),month(O46)+1,0),$B$70:$B$82) -> 22 | ... S45: =NETWORKDAYS(DATE(year(S46),month(S46),1),DATE(year(S46),month(S46)+1,0),$B$70:$B$82) -> 21 | T45: =sum(T47:T66) -> 1286274.2 | U45: =sum(U47:U66) -> 1286274.2 | V45: =U45-T45 -> 0
B46: Nome Completo | E46: Classificação | F46: Formação | H46: 45322 | I46: 45350 | J46: 45382 | K46: 45412 | L46: 45443 | M46: 45473 | N46: 45504 | O46: 45535 | P46: 45565 | Q46: 45596 | R46: 45626 | S46: 45657 | T46: PD&I R$ | U46: Aprovado R$ | V46: Pesquisador
B47: {=unique(B13:B33)} -> Alberto Reuters | E47: {=V13:V33} -> Parcial | F47: {=F13:F33} -> Mestrado | H47: =iferror((xlookup($B47,$B$13:$B$33,H$13:H$33)*(1+H$43))/(H$45*8.8),"") -> 187.1712 | I47: =iferror((xlookup($B47,$B$13:$B$33,I$13:I$33)*(1+I$43))/(I$45*8.8),"") -> 195.64359 | J47: =iferror((xlookup($B47,$B$13:$B$33,J$13:J$33)*(1+J$43))/(J$45*8.8),"") -> 205.24786 | K47: =iferror((xlookup($B47,$B$13:$B$33,K$13:K$33)*(1+K$43))/(K$45*8.8),"") -> 196.76184 | L47: =iferror((xlookup($B47,$B$13:$B$33,L$13:L$33)*(1+L$43))/(L$45*8.8),"") -> 196.64324 | M47: =iferror((xlookup($B47,$B$13:$B$33,M$13:M$33)*(1+M$43))/(M$45*8.8),"") -> 205.88832 | N47: =iferror((xlookup($B47,$B$13:$B$33,N$13:N$33)*(1+N$43))/(N$45*8.8),"") -> 180.19356 | O47: =iferror((xlookup($B47,$B$13:$B$33,O$13:O$33)*(1+O$43))/(O$45*8.8),"") -> 188.49739 | ... S47: =iferror((xlookup($B47,$B$13:$B$33,S$13:S$33)*(1+S$43))/(S$45*8.8),"") -> 206.45841 | T47: =SUMIF('Resumo - TIMESHEETS'!E:E,B47,'Resumo - TIMESHEETS'!L:L) -> 0 | U47: =SUMIF(V47,TRUE,T47) -> 0 | V47: TRUE
B48: Alexandre Baseggio | E48: Parcial | F48: Pós graduado | H48: =iferror((xlookup($B48,$B$13:$B$33,H$13:H$33)*(1+H$43))/(H$45*8.8),"") -> 51.972559 | I48: =iferror((xlookup($B48,$B$13:$B$33,I$13:I$33)*(1+I$43))/(I$45*8.8),"") -> 54.32512 | J48: =iferror((xlookup($B48,$B$13:$B$33,J$13:J$33)*(1+J$43))/(J$45*8.8),"") -> 56.991977 | K48: =iferror((xlookup($B48,$B$13:$B$33,K$13:K$33)*(1+K$43))/(K$45*8.8),"") -> 54.63563 | L48: =iferror((xlookup($B48,$B$13:$B$33,L$13:L$33)*(1+L$43))/(L$45*8.8),"") -> 54.602697 | M48: =iferror((xlookup($B48,$B$13:$B$33,M$13:M$33)*(1+M$43))/(M$45*8.8),"") -> 57.169814 | N48: =iferror((xlookup($B48,$B$13:$B$33,N$13:N$33)*(1+N$43))/(N$45*8.8),"") -> 50.035052 | O48: =iferror((xlookup($B48,$B$13:$B$33,O$13:O$33)*(1+O$43))/(O$45*8.8),"") -> 52.340808 | ... S48: =iferror((xlookup($B48,$B$13:$B$33,S$13:S$33)*(1+S$43))/(S$45*8.8),"") -> 57.328157 | T48: =SUMIF('Resumo - TIMESHEETS'!E:E,B48,'Resumo - TIMESHEETS'!L:L) -> 18521.516 | U48: =SUMIF(V48,TRUE,T48) -> 18521.516 | V48: TRUE
B49: Arthur Muniz | E49: Exclusivo | F49: Superior Completo | H49: =iferror((xlookup($B49,$B$13:$B$33,H$13:H$33)*(1+H$43))/(H$45*8.8),"") -> 89.096488 | I49: =iferror((xlookup($B49,$B$13:$B$33,I$13:I$33)*(1+I$43))/(I$45*8.8),"") -> 93.129481 | J49: =iferror((xlookup($B49,$B$13:$B$33,J$13:J$33)*(1+J$43))/(J$45*8.8),"") -> 97.70127 | K49: =iferror((xlookup($B49,$B$13:$B$33,K$13:K$33)*(1+K$43))/(K$45*8.8),"") -> 93.661788 | L49: =iferror((xlookup($B49,$B$13:$B$33,L$13:L$33)*(1+L$43))/(L$45*8.8),"") -> 93.605331 | M49: =iferror((xlookup($B49,$B$13:$B$33,M$13:M$33)*(1+M$43))/(M$45*8.8),"") -> 98.006137 | N49: =iferror((xlookup($B49,$B$13:$B$33,N$13:N$33)*(1+N$43))/(N$45*8.8),"") -> 91.273363 | O49: =iferror((xlookup($B49,$B$13:$B$33,O$13:O$33)*(1+O$43))/(O$45*8.8),"") -> 95.479497 | ... S49: =iferror((xlookup($B49,$B$13:$B$33,S$13:S$33)*(1+S$43))/(S$45*8.8),"") -> 104.57726 | T49: =SUMIF('Resumo - TIMESHEETS'!E:E,B49,'Resumo - TIMESHEETS'!L:L) -> 220682.4 | U49: =SUMIF(V49,TRUE,T49) -> 220682.4 | V49: TRUE
B50: Bruno katzjarowksi | E50: Exclusivo | F50: Superior Completo | H50: =iferror((xlookup($B50,$B$13:$B$33,H$13:H$33)*(1+H$43))/(H$45*8.8),"") -> 107.35211 | I50: =iferror((xlookup($B50,$B$13:$B$33,I$13:I$33)*(1+I$43))/(I$45*8.8),"") -> 112.21145 | J50: =iferror((xlookup($B50,$B$13:$B$33,J$13:J$33)*(1+J$43))/(J$45*8.8),"") -> 117.71998 | K50: =iferror((xlookup($B50,$B$13:$B$33,K$13:K$33)*(1+K$43))/(K$45*8.8),"") -> 112.85282 | L50: =iferror((xlookup($B50,$B$13:$B$33,L$13:L$33)*(1+L$43))/(L$45*8.8),"") -> 112.7848 | M50: =iferror((xlookup($B50,$B$13:$B$33,M$13:M$33)*(1+M$43))/(M$45*8.8),"") -> 118.08732 | N50: =iferror((xlookup($B50,$B$13:$B$33,N$13:N$33)*(1+N$43))/(N$45*8.8),"") -> 103.35008 | O50: =iferror((xlookup($B50,$B$13:$B$33,O$13:O$33)*(1+O$43))/(O$45*8.8),"") -> 108.11274 | ... S50: =iferror((xlookup($B50,$B$13:$B$33,S$13:S$33)*(1+S$43))/(S$45*8.8),"") -> 118.41433 | T50: =SUMIF('Resumo - TIMESHEETS'!E:E,B50,'Resumo - TIMESHEETS'!L:L) -> 228482.12 | U50: =SUMIF(V50,TRUE,T50) -> 228482.12 | V50: TRUE
B51: Cleiton Capristano | E51: Exclusivo | F51: Superior Completo | H51: =iferror((xlookup($B51,$B$13:$B$33,H$13:H$33)*(1+H$43))/(H$45*8.8),"") -> 94.807812 | I51: =iferror((xlookup($B51,$B$13:$B$33,I$13:I$33)*(1+I$43))/(I$45*8.8),"") -> 105.45175 | J51: =iferror((xlookup($B51,$B$13:$B$33,J$13:J$33)*(1+J$43))/(J$45*8.8),"") -> 110.62845 | K51: =iferror((xlookup($B51,$B$13:$B$33,K$13:K$33)*(1+K$43))/(K$45*8.8),"") -> 106.05449 | L51: =iferror((xlookup($B51,$B$13:$B$33,L$13:L$33)*(1+L$43))/(L$45*8.8),"") -> 105.99056 | M51: =iferror((xlookup($B51,$B$13:$B$33,M$13:M$33)*(1+M$43))/(M$45*8.8),"") -> 110.97365 | N51: =iferror((xlookup($B51,$B$13:$B$33,N$13:N$33)*(1+N$43))/(N$45*8.8),"") -> 97.1242 | O51: =iferror((xlookup($B51,$B$13:$B$33,O$13:O$33)*(1+O$43))/(O$45*8.8),"") -> 101.59996 | ... S51: =iferror((xlookup($B51,$B$13:$B$33,S$13:S$33)*(1+S$43))/(S$45*8.8),"") -> 111.28096 | T51: =SUMIF('Resumo - TIMESHEETS'!E:E,B51,'Resumo - TIMESHEETS'!L:L) -> 202256.2 | U51: =SUMIF(V51,TRUE,T51) -> 202256.2 | V51: TRUE
B52: Cristiano Schroeder | E52: Parcial | F52: Superior Completo | H52: =iferror((xlookup($B52,$B$13:$B$33,H$13:H$33)*(1+H$43))/(H$45*8.8),"") -> 55.69307 | I52: =iferror((xlookup($B52,$B$13:$B$33,I$13:I$33)*(1+I$43))/(I$45*8.8),"") -> 58.214042 | J52: =iferror((xlookup($B52,$B$13:$B$33,J$13:J$33)*(1+J$43))/(J$45*8.8),"") -> 61.071809 | K52: =iferror((xlookup($B52,$B$13:$B$33,K$13:K$33)*(1+K$43))/(K$45*8.8),"") -> 58.54678 | L52: =iferror((xlookup($B52,$B$13:$B$33,L$13:L$33)*(1+L$43))/(L$45*8.8),"") -> 58.51149 | M52: =iferror((xlookup($B52,$B$13:$B$33,M$13:M$33)*(1+M$43))/(M$45*8.8),"") -> 61.262377 | N52: =iferror((xlookup($B52,$B$13:$B$33,N$13:N$33)*(1+N$43))/(N$45*8.8),"") -> 53.616864 | O52: =iferror((xlookup($B52,$B$13:$B$33,O$13:O$33)*(1+O$43))/(O$45*8.8),"") -> 56.087681 | ... S52: =iferror((xlookup($B52,$B$13:$B$33,S$13:S$33)*(1+S$43))/(S$45*8.8),"") -> 61.431993 | T52: =SUMIF('Resumo - TIMESHEETS'!E:E,B52,'Resumo - TIMESHEETS'!L:L) -> 102458.99 | U52: =SUMIF(V52,TRUE,T52) -> 102458.99 | V52: TRUE
B53: Eduardo Flohr | E53: Parcial | F53: Pós graduado | H53: =iferror((xlookup($B53,$B$13:$B$33,H$13:H$33)*(1+H$43))/(H$45*8.8),"") -> 135.23334 | I53: =iferror((xlookup($B53,$B$13:$B$33,I$13:I$33)*(1+I$43))/(I$45*8.8),"") -> 141.35474 | J53: =iferror((xlookup($B53,$B$13:$B$33,J$13:J$33)*(1+J$43))/(J$45*8.8),"") -> 148.29394 | K53: =iferror((xlookup($B53,$B$13:$B$33,K$13:K$33)*(1+K$43))/(K$45*8.8),"") -> 142.16269 | L53: =iferror((xlookup($B53,$B$13:$B$33,L$13:L$33)*(1+L$43))/(L$45*8.8),"") -> 142.077 | M53: =iferror((xlookup($B53,$B$13:$B$33,M$13:M$33)*(1+M$43))/(M$45*8.8),"") -> 148.75668 | N53: =iferror((xlookup($B53,$B$13:$B$33,N$13:N$33)*(1+N$43))/(N$45*8.8),"") -> 130.19192 | O53: =iferror((xlookup($B53,$B$13:$B$33,O$13:O$33)*(1+O$43))/(O$45*8.8),"") -> 136.19153 | ... S53: =iferror((xlookup($B53,$B$13:$B$33,S$13:S$33)*(1+S$43))/(S$45*8.8),"") -> 149.16858 | T53: =SUMIF('Resumo - TIMESHEETS'!E:E,B53,'Resumo - TIMESHEETS'!L:L) -> 0 | U53: =SUMIF(V53,TRUE,T53) -> 0 | V53: TRUE
B54: Filipe Harbs | E54: Parcial | F54: Técnico | H54: =iferror((xlookup($B54,$B$13:$B$33,H$13:H$33)*(1+H$43))/(H$45*8.8),"") -> 44.364385 | I54: =iferror((xlookup($B54,$B$13:$B$33,I$13:I$33)*(1+I$43))/(I$45*8.8),"") -> 0 | J54: =iferror((xlookup($B54,$B$13:$B$33,J$13:J$33)*(1+J$43))/(J$45*8.8),"") -> 0 | K54: =iferror((xlookup($B54,$B$13:$B$33,K$13:K$33)*(1+K$43))/(K$45*8.8),"") -> 0 | L54: =iferror((xlookup($B54,$B$13:$B$33,L$13:L$33)*(1+L$43))/(L$45*8.8),"") -> 0 | M54: =iferror((xlookup($B54,$B$13:$B$33,M$13:M$33)*(1+M$43))/(M$45*8.8),"") -> 0 | N54: =iferror((xlookup($B54,$B$13:$B$33,N$13:N$33)*(1+N$43))/(N$45*8.8),"") -> 0 | O54: =iferror((xlookup($B54,$B$13:$B$33,O$13:O$33)*(1+O$43))/(O$45*8.8),"") -> 0 | ... S54: =iferror((xlookup($B54,$B$13:$B$33,S$13:S$33)*(1+S$43))/(S$45*8.8),"") -> 0 | T54: =SUMIF('Resumo - TIMESHEETS'!E:E,B54,'Resumo - TIMESHEETS'!L:L) -> 8285.049 | U54: =SUMIF(V54,TRUE,T54) -> 8285.049 | V54: TRUE
B55: Gabriel Alves Ferraz | E55: Parcial | F55: Superior Completo | H55: =iferror((xlookup($B55,$B$13:$B$33,H$13:H$33)*(1+H$43))/(H$45*8.8),"") -> 22.246026 | I55: =iferror((xlookup($B55,$B$13:$B$33,I$13:I$33)*(1+I$43))/(I$45*8.8),"") -> 23.253002 | J55: =iferror((xlookup($B55,$B$13:$B$33,J$13:J$33)*(1+J$43))/(J$45*8.8),"") -> 24.394508 | K55: =iferror((xlookup($B55,$B$13:$B$33,K$13:K$33)*(1+K$43))/(K$45*8.8),"") -> 23.385911 | L55: =iferror((xlookup($B55,$B$13:$B$33,L$13:L$33)*(1+L$43))/(L$45*8.8),"") -> 23.371815 | M55: =iferror((xlookup($B55,$B$13:$B$33,M$13:M$33)*(1+M$43))/(M$45*8.8),"") -> 24.470628 | N55: =iferror((xlookup($B55,$B$13:$B$33,N$13:N$33)*(1+N$43))/(N$45*8.8),"") -> 22.94575 | O55: =iferror((xlookup($B55,$B$13:$B$33,O$13:O$33)*(1+O$43))/(O$45*8.8),"") -> 24.003154 | ... S55: =iferror((xlookup($B55,$B$13:$B$33,S$13:S$33)*(1+S$43))/(S$45*8.8),"") -> 26.290325 | T55: =SUMIF('Resumo - TIMESHEETS'!E:E,B55,'Resumo - TIMESHEETS'!L:L) -> 17176.405 | U55: =SUMIF(V55,TRUE,T55) -> 17176.405 | V55: TRUE
B56: Gabriel Oliveira | E56: Parcial | F56: Superior Completo | H56: =iferror((xlookup($B56,$B$13:$B$33,H$13:H$33)*(1+H$43))/(H$45*8.8),"") -> 75.071402 | I56: =iferror((xlookup($B56,$B$13:$B$33,I$13:I$33)*(1+I$43))/(I$45*8.8),"") -> 78.469544 | J56: =iferror((xlookup($B56,$B$13:$B$33,J$13:J$33)*(1+J$43))/(J$45*8.8),"") -> 82.321666 | K56: =iferror((xlookup($B56,$B$13:$B$33,K$13:K$33)*(1+K$43))/(K$45*8.8),"") -> 78.918057 | L56: =iferror((xlookup($B56,$B$13:$B$33,L$13:L$33)*(1+L$43))/(L$45*8.8),"") -> 78.870488 | M56: =iferror((xlookup($B56,$B$13:$B$33,M$13:M$33)*(1+M$43))/(M$45*8.8),"") -> 82.578542 | N56: =iferror((xlookup($B56,$B$13:$B$33,N$13:N$33)*(1+N$43))/(N$45*8.8),"") -> 72.272783 | O56: =iferror((xlookup($B56,$B$13:$B$33,O$13:O$33)*(1+O$43))/(O$45*8.8),"") -> 75.603317 | ... S56: =iferror((xlookup($B56,$B$13:$B$33,S$13:S$33)*(1+S$43))/(S$45*8.8),"") -> 82.807206 | T56: =SUMIF('Resumo - TIMESHEETS'!E:E,B56,'Resumo - TIMESHEETS'!L:L) -> 111216.57 | U56: =SUMIF(V56,TRUE,T56) -> 111216.57 | V56: TRUE
B57: Gabriel Possamai | E57: Exclusivo | F57: Superior Completo | H57: =iferror((xlookup($B57,$B$13:$B$33,H$13:H$33)*(1+H$43))/(H$45*8.8),"") -> 114.23363 | I57: =iferror((xlookup($B57,$B$13:$B$33,I$13:I$33)*(1+I$43))/(I$45*8.8),"") -> 119.40446 | J57: =iferror((xlookup($B57,$B$13:$B$33,J$13:J$33)*(1+J$43))/(J$45*8.8),"") -> 125.26611 | K57: =iferror((xlookup($B57,$B$13:$B$33,K$13:K$33)*(1+K$43))/(K$45*8.8),"") -> 120.08695 | L57: =iferror((xlookup($B57,$B$13:$B$33,L$13:L$33)*(1+L$43))/(L$45*8.8),"") -> 120.01457 | M57: =iferror((xlookup($B57,$B$13:$B$33,M$13:M$33)*(1+M$43))/(M$45*8.8),"") -> 125.65699 | N57: =iferror((xlookup($B57,$B$13:$B$33,N$13:N$33)*(1+N$43))/(N$45*8.8),"") -> 109.97506 | O57: =iferror((xlookup($B57,$B$13:$B$33,O$13:O$33)*(1+O$43))/(O$45*8.8),"") -> 115.04302 | ... S57: =iferror((xlookup($B57,$B$13:$B$33,S$13:S$33)*(1+S$43))/(S$45*8.8),"") -> 126.00493 | T57: =SUMIF('Resumo - TIMESHEETS'!E:E,B57,'Resumo - TIMESHEETS'!L:L) -> 222738.49 | U57: =SUMIF(V57,TRUE,T57) -> 222738.49 | V57: TRUE
B58: Guilherme Jacques | E58: Parcial | F58: Superior Completo | H58: =iferror((xlookup($B58,$B$13:$B$33,H$13:H$33)*(1+H$43))/(H$45*8.8),"") -> 39.311025 | I58: =iferror((xlookup($B58,$B$13:$B$33,I$13:I$33)*(1+I$43))/(I$45*8.8),"") -> 41.090456 | J58: =iferror((xlookup($B58,$B$13:$B$33,J$13:J$33)*(1+J$43))/(J$45*8.8),"") -> 43.107614 | K58: =iferror((xlookup($B58,$B$13:$B$33,K$13:K$33)*(1+K$43))/(K$45*8.8),"") -> 41.32532 | L58: =iferror((xlookup($B58,$B$13:$B$33,L$13:L$33)*(1+L$43))/(L$45*8.8),"") -> 41.30041 | M58: =iferror((xlookup($B58,$B$13:$B$33,M$13:M$33)*(1+M$43))/(M$45*8.8),"") -> 43.242127 | N58: =iferror((xlookup($B58,$B$13:$B$33,N$13:N$33)*(1+N$43))/(N$45*8.8),"") -> 42.710438 | O58: =iferror((xlookup($B58,$B$13:$B$33,O$13:O$33)*(1+O$43))/(O$45*8.8),"") -> 44.678656 | ... S58: =iferror((xlookup($B58,$B$13:$B$33,S$13:S$33)*(1+S$43))/(S$45*8.8),"") -> 48.935919 | T58: =SUMIF('Resumo - TIMESHEETS'!E:E,B58,'Resumo - TIMESHEETS'!L:L) -> 18270.621 | U58: =SUMIF(V58,TRUE,T58) -> 18270.621 | V58: TRUE
B59: Italo Ebel | E59: Parcial | F59: Superior Completo | H59: =iferror((xlookup($B59,$B$13:$B$33,H$13:H$33)*(1+H$43))/(H$45*8.8),"") -> 11.716965 | I59: =iferror((xlookup($B59,$B$13:$B$33,I$13:I$33)*(1+I$43))/(I$45*8.8),"") -> 12.247339 | J59: =iferror((xlookup($B59,$B$13:$B$33,J$13:J$33)*(1+J$43))/(J$45*8.8),"") -> 12.848569 | K59: =iferror((xlookup($B59,$B$13:$B$33,K$13:K$33)*(1+K$43))/(K$45*8.8),"") -> 12.317342 | L59: =iferror((xlookup($B59,$B$13:$B$33,L$13:L$33)*(1+L$43))/(L$45*8.8),"") -> 12.309917 | M59: =iferror((xlookup($B59,$B$13:$B$33,M$13:M$33)*(1+M$43))/(M$45*8.8),"") -> 12.888662 | N59: =iferror((xlookup($B59,$B$13:$B$33,N$13:N$33)*(1+N$43))/(N$45*8.8),"") -> 11.280163 | O59: =iferror((xlookup($B59,$B$13:$B$33,O$13:O$33)*(1+O$43))/(O$45*8.8),"") -> 13.008028 | ... S59: =iferror((xlookup($B59,$B$13:$B$33,S$13:S$33)*(1+S$43))/(S$45*8.8),"") -> 14.249843 | T59: =SUMIF('Resumo - TIMESHEETS'!E:E,B59,'Resumo - TIMESHEETS'!L:L) -> 14205.742 | U59: =SUMIF(V59,TRUE,T59) -> 14205.742 | V59: TRUE
... B67: Fernando Leal | E67: Parcial | F67: Pós graduado | H67: =iferror((xlookup($B67,$B$13:$B$33,H$13:H$33)*(1+H$43))/(H$45*8.8),"") -> 32.130617 | I67: =iferror((xlookup($B67,$B$13:$B$33,I$13:I$33)*(1+I$43))/(I$45*8.8),"") -> 33.585024 | J67: =iferror((xlookup($B67,$B$13:$B$33,J$13:J$33)*(1+J$43))/(J$45*8.8),"") -> 35.233736 | K67: =iferror((xlookup($B67,$B$13:$B$33,K$13:K$33)*(1+K$43))/(K$45*8.8),"") -> 33.776989 | L67: =iferror((xlookup($B67,$B$13:$B$33,L$13:L$33)*(1+L$43))/(L$45*8.8),"") -> 33.756629 | M67: =iferror((xlookup($B67,$B$13:$B$33,M$13:M$33)*(1+M$43))/(M$45*8.8),"") -> 35.343679 | N67: =iferror((xlookup($B67,$B$13:$B$33,N$13:N$33)*(1+N$43))/(N$45*8.8),"") -> 30.932806 | O67: =iferror((xlookup($B67,$B$13:$B$33,O$13:O$33)*(1+O$43))/(O$45*8.8),"") -> 32.358277 | ... S67: =iferror((xlookup($B67,$B$13:$B$33,S$13:S$33)*(1+S$43))/(S$45*8.8),"") -> 52.306713 | T67: =SUMIF('Resumo - TIMESHEETS'!E:E,B67,'Resumo - TIMESHEETS'!L:L) -> 800.26491 | U67: =SUMIF(V67,TRUE,T67) -> 800.26491 | V67: TRUE
B69: Feriados
B70: 45292 | C70: Segunda-Feira | D70: Ano Novo
B71: 45380 | C71: Sexta-Feira | D71: Sexta-Feira Santa
B72: 45383 | C72: Segunda-Feira | D72: 2º dia de Páscoa
B73: 45413 | C73: Quarta-feira | D73: Dia do Trabalhado
B74: 45442 | C74: Quinta-feira | D74: Corpus Christi
B75: 45596 | C75: Quinta-feira | D75: Dia da Reforma
B76: 45611 | C76: Sexta-Feira | D76: Proclamação da República
B77: 45616 | C77: Quarta-feira | D77: Dia da Consciência Negra
B78: 45651 | C78: Quarta-feira | D78: Natal

Sheet Resumo - TERCEIROS
B2: NETZSCH
B3: Pesquisa, Desenvolvimento & Inovação
B4: Formulário de PD&I - Ano 2024
B5: - preencher somente os campos sombreados (cinza)
B8: Dossiê do projeto
B9: Investimentos com terceiros
B11: Projeto | C11: Etapa | D11: Fornecedor | E11: CNPJ | F11: Nota fiscal | G11: Valor | H11: Data | I11: Descrição da Atividade | J11: Objetivo do gasto e eventual info de rateio | K11: Gasto incentiv. | L11: Projeto incentiv.
B12: {={'IRIS TERCEIROS'!B12:K579;'NOTIFY TERCEIROS'!B12:K579;'P&D_1 TERCEIROS'!B12:K579;'P&D_2 TERCEIROS'!B12:K579;'P&D_3 TERCEIROS'!B12:K579}} -> IRIS | C12: Processo aprimorado de moagem no modo passada | D12: KMCC Equipamentos Elétricos Ltda | E12: 07.389.050/0001-51 | F12: 2288 | G12: 10353.48 | H12: 45307 | I12: Desenvolvimento IHM | J12: Pedido 2304662. Total do pedido: R$ 10.451,00. Percentual no projeto: 99% | K12: TRUE | L12: {=XLOOKUP($B$12:$B579,'Resumo - PROJETOS'!$B:$B,'Resumo - PROJETOS'!$C:$C,,0)} -> TRUE
B13: IRIS | C13: Processo aprimorado de moagem no modo circulação | D13: KMCC Equipamentos Elétricos Ltda | E13: 07.389.050/0001-51 | F13: 2268 | G13: 18491 | H13: 45323 | I13: Desenvolvimento IHM | J13: Pedido 2302666. Total do pedido: R$ 18.491,00. Percentual no projeto: 100 % | K13: TRUE | L13: TRUE
B14: IRIS | C14: Registro avançado de dados de processo | D14: KMCC Equipamentos Elétricos Ltda | E14: 07.389.050/0001-51 | F14: 2287 | G14: 16965.07 | H14: 45352 | I14: Desenvolvimento IHM | J14: Pedido 2304623. Total do pedido: R$ 17.467,00. Percentual no projeto: 97 % | K14: TRUE | L14: TRUE
B15: IRIS | C15: Portabilidade para funcionamento com CLP da Rockwell | D15: KMCC Equipamentos Elétricos Ltda | E15: 07.389.050/0001-51 | F15: NFS 2292 | G15: 275 | H15: 45383 | I15: Desenvolvimento IHM | K15: TRUE | L15: TRUE
B16: IRIS | C16: Gerenciamento de dados remanecentes | D16: KMCC Equipamentos Elétricos Ltda | E16: 07.389.050/0001-51 | F16: NFS 2292 | G16: 14235 | H16: 45383 | I16: Desenvolvimento IHM | K16: TRUE | L16: TRUE
B17: IRIS | C17: Portabilidade para funcionamento com CLP da Rockwell | D17: KMCC Equipamentos Elétricos Ltda | E17: 07.389.050/0001-51 | F17: NFS 2310 | G17: 4508 | H17: 45413 | I17: Desenvolvimento IHM | K17: TRUE | L17: TRUE
B18: IRIS | C18: Implementação de sistema automático de gerenciamento de garantia | D18: KMCC Equipamentos Elétricos Ltda | E18: 07.389.050/0001-51 | F18: NFS 2310 | G18: 6595 | H18: 45413 | I18: Desenvolvimento IHM | K18: TRUE | L18: TRUE
B19: IRIS | C19: Portabilidade para funcionamento com CLP da Rockwell | D19: KMCC Equipamentos Elétricos Ltda | E19: 07.389.050/0001-51 | F19: NFS 2311 | G19: 10940 | H19: 45444 | I19: Desenvolvimento IHM | K19: TRUE | L19: TRUE
B20: IRIS | C20: IRIS V3 Epsilon InView - Desenvolvimento | D20: KMCC Equipamentos Elétricos Ltda | E20: 07.389.050/0001-51 | F20: NFS 21013 | G20: 1180 | H20: 45474 | I20: Desenvolvimento IHM | J20: Percentual no projeto: 7,6 % | K20: TRUE | L20: TRUE
B21: IRIS | C21: IRIS V3 for Confectionary - Prototipação | D21: KMCC Equipamentos Elétricos Ltda | E21: 07.389.050/0001-51 | F21: NFS 21013 | G21: 1607 | H21: 45474 | I21: Documentação | J21: Percentual no projeto: 10,4 % | K21: TRUE | L21: TRUE
B22: IRIS | C22: IRIS V3 Epsilon InView - Desenvolvimento | D22: KMCC Equipamentos Elétricos Ltda | E22: 07.389.050/0001-51 | F22: Requisição de pedido: 4401020 | G22: 2623 | H22: 45505 | I22: Desenvolvimento IHM | J22: Percentual no projeto: 16,8 % | K22: TRUE | L22: TRUE
B23: IRIS | C23: IRIS V3 for Confectionary - Prototipação | D23: KMCC Equipamentos Elétricos Ltda | E23: 07.389.050/0001-51 | F23: Requisição de pedido: 4401020 | G23: 2357 | H23: 45505 | I23: Documentação | J23: Percentual no projeto: 15,1 % | K23: TRUE | L23: TRUE
B24: IRIS | C24: IRIS V3 Epsilon InView - Recontrole | D24: KMCC Equipamentos Elétricos Ltda | E24: 07.389.050/0001-51 | F24: Pedido: 2316035 | G24: 2332 | H24: 45536 | I24: Desenvolvimento IHM | J24: Percentual no projeto: 13,4 % | K24: TRUE | L24: TRUE
B25: IRIS | C25: IRIS V3 for Confectionary - Prototipação | D25: KMCC Equipamentos Elétricos Ltda | E25: 07.389.050/0001-51 | F25: Pedido: 2316035 | G25: 5935 | H25: 45536 | I25: Documentação | J25: Percentual no projeto: 34 % | K25: TRUE | L25: TRUE
B26: Notify | C26: Relatório de lotes | D26: Materialize Serviços Digitais Ltda | E26: 34.269.716/0001-00 | F26: 650 | G26: 32040 | H26: 45293 | I26: Agenciamento de serviços de desenvovimento de software | J26: Total nota fiscal: R$ 32040. Rateio: 100 % | K26: TRUE | L26: TRUE
B27: Notify | C27: Templates de gráficos | D27: Mout´s Soluçõesem Tecnologia da Informação Ltda. | E27: 5.056.849/0001-08 | F27: 3169 | G27: 19849.28 | H27: 45308 | I27: Agenciamento de serviços de desenvovimento de software | J27: Total nota fiscal: R$ 39698,55. Rateio: 50 % | K27: TRUE | L27: TRUE
B28: Notify | C28: Relatório de lotes | D28: Mout´s Soluçõesem Tecnologia da Informação Ltda. | E28: 5.056.849/0001-08 | F28: 3169 | G28: 19849.28 | H28: 45308 | I28: Agenciamento de serviços de desenvovimento de software | J28: Total nota fiscal: R$ 39698,55. Rateio: 50 % | K28: TRUE | L28: TRUE
B29: Notify | C29: Templates de gráficos | D29: Amazon AWS Serviços Brasil Ltda | E29: 23.412.247/0001-10 | F29: 2709240_ECNZ6XB8 | G29: 5412.76 | H29: 45293 | I29: Custo da infraestrutura em nuvem | J29: Total nota fiscal: R$ 10825,52. Rateio: 50 % | K29: TRUE | L29: TRUE
B30: Notify | C30: Relatório de lotes | D30: Amazon AWS Serviços Brasil Ltda | E30: 23.412.247/0001-10 | F30: 2709240_ECNZ6XB8 | G30: 5412.76 | H30: 45293 | I30: Custo da infraestrutura em nuvem | J30: Total nota fiscal: R$ 10825,52. Rateio: 50 % | K30: TRUE | L30: TRUE
B31: Notify | C31: Templates de gráficos | D31: Materialize Serviços Digitais Ltda | E31: 34.269.716/0001-00 | F31: 684 | G31: 32040 | H31: 45323 | I31: Agenciamento de serviços de desenvovimento de software | J31: Total nota fiscal: R$ 32040. Rateio: 100 % | K31: TRUE | L31: TRUE
B32: Notify | C32: Templates de gráficos | D32: Mout´s Soluçõesem Tecnologia da Informação Ltda. | E32: 5.056.849/0001-08 | F32: 3188 | G32: 22059.44 | H32: 45328 | I32: Agenciamento de serviços de desenvovimento de software | J32: Total nota fiscal: R$ 44118,88. Rateio: 50 % | K32: TRUE | L32: TRUE
B33: Notify | C33: Relatório de lotes | D33: Mout´s Soluçõesem Tecnologia da Informação Ltda. | E33: 5.056.849/0001-08 | F33: 3188 | G33: 22059.44 | H33: 45328 | I33: Agenciamento de serviços de desenvovimento de software | J33: Total nota fiscal: R$ 44118,88. Rateio: 50 % | K33: TRUE | L33: TRUE
B34: Notify | C34: Templates de gráficos | D34: Amazon AWS Serviços Brasil Ltda | E34: 23.412.247/0001-10 | F34: 2845975_9ZHR17CA | G34: 5496.54 | H34: 45324 | I34: Custo da infraestrutura em nuvem | J34: Total nota fiscal: R$ 10993,07. Rateio: 50 % | K34: TRUE | L34: TRUE
B35: Notify | C35: Relatório de lotes | D35: Amazon AWS Serviços Brasil Ltda | E35: 23.412.247/0001-10 | F35: 2845975_9ZHR17CA | G35: 5496.54 | H35: 45324 | I35: Custo da infraestrutura em nuvem | J35: Total nota fiscal: R$ 10993,07. Rateio: 50 % | K35: TRUE | L35: TRUE
B36: Notify | C36: Templates de gráficos | D36: Materialize Serviços Digitais Ltda | E36: 34.269.716/0001-00 | F36: 710 | G36: 32040 | H36: 45355 | I36: Agenciamento de serviços de desenvovimento de software | J36: Total nota fiscal: R$ 32040. Rateio: 100 % | K36: TRUE | L36: TRUE
B37: Notify | C37: Templates de gráficos | D37: Mout´s Soluçõesem Tecnologia da Informação Ltda. | E37: 5.056.849/0001-08 | F37: 3225 | G37: 16057.73 | H37: 45359 | I37: Agenciamento de serviços de desenvovimento de software | J37: Total nota fiscal: R$ 48173,2. Rateio: 33,33 % | K37: TRUE | L37: TRUE
B38: Notify | C38: Configuração Gateway para o IRIS V3 | D38: Mout´s Soluçõesem Tecnologia da Informação Ltda. | E38: 5.056.849/0001-08 | F38: 3228 | G38: 16057.73 | H38: 45359 | I38: Agenciamento de serviços de desenvovimento de software | J38: Total nota fiscal: R$ 48173,2. Rateio: 33,33 % | K38: TRUE | L38: TRUE
B39: Notify | C39: Design System | D39: Mout´s Soluçõesem Tecnologia da Informação Ltda. | E39: 5.056.849/0001-08 | F39: 3228 | G39: 16057.73 | H39: 45359 | I39: Agenciamento de serviços de desenvovimento de software | J39: Total nota fiscal: R$ 48173,2. Rateio: 33,33 % | K39: TRUE | L39: TRUE
B40: Notify | C40: Templates de gráficos | D40: Amazon AWS Serviços Brasil Ltda | E40: 23.412.247/0001-10 | F40: 2901379_BRL69BTP | G40: 5486.78 | H40: 45353 | I40: Custo da infraestrutura em nuvem | J40: Total nota fiscal: R$ 10973,56. Rateio: 50 % | K40: TRUE | L40: TRUE
B41: Notify | C41: Configuração Gateway para o IRIS V3 | D41: Amazon AWS Serviços Brasil Ltda | E41: 23.412.247/0001-10 | F41: 2901379_BRL69BTP | G41: 5486.78 | H41: 45353 | I41: Custo da infraestrutura em nuvem | J41: Total nota fiscal: R$ 10973,56. Rateio: 50 % | K41: TRUE | L41: TRUE
B42: Notify | C42: Templates de gráficos | D42: Materialize Serviços Digitais Ltda | E42: 34.269.716/0001-00 | F42: 729 | G42: 32040 | H42: 45383 | I42: Agênciamento de serviços de desenvovimento de software | J42: Total nota fiscal: R$ 32040. Rateio: 100 % | K42: TRUE | L42: TRUE
B43: Notify | C43: Templates de gráficos | D43: Mout´s Soluçõesem Tecnologia da Informação Ltda. | E43: 5.056.849/0001-08 | F43: 3266 | G43: 14884.61 | H43: 45386 | I43: Agênciamento de serviços de desenvovimento de software | J43: Total nota fiscal: R$ 44653,83. Rateio: 33,33 % | K43: TRUE | L43: TRUE
B44: Notify | C44: Configuração Gateway para o IRIS V3 | D44: Mout´s Soluçõesem Tecnologia da Informação Ltda. | E44: 5.056.849/0001-08 | F44: 3266 | G44: 14884.61 | H44: 45386 | I44: Agênciamento de serviços de desenvovimento de software | J44: Total nota fiscal: R$ 44653,83. Rateio: 33,33 % | K44: TRUE | L44: TRUE
B45: Notify | C45: Design System | D45: Mout´s Soluçõesem Tecnologia da Informação Ltda. | E45: 5.056.849/0001-08 | F45: 3266 | G45: 14884.61 | H45: 45386 | I45: Agênciamento de serviços de desenvovimento de software | J45: Total nota fiscal: R$ 44653,83. Rateio: 33,33 % | K45: TRUE | L45: TRUE
B46: Notify | C46: Templates de gráficos | D46: Amazon AWS Serviços Brasil Ltda | E46: 23.412.247/0001-10 | F46: 2992055_YIQTWU6S | G46: 6465.15 | H46: 45384 | I46: Custo da infraestrutura em nuvem | J46: Total nota fiscal: R$ 12930,29. Rateio: 50 % | K46: TRUE | L46: TRUE
B47: Notify | C47: Configuração Gateway para o IRIS V3 | D47: Amazon AWS Serviços Brasil Ltda | E47: 23.412.247/0001-10 | F47: 2992055_YIQTWU6S | G47: 6465.15 | H47: 45384 | I47: Custo da infraestrutura em nuvem | J47: Total nota fiscal: R$ 12930,29. Rateio: 50 % | K47: TRUE | L47: TRUE
B48: Notify | C48: Templates de gráficos | D48: Materialize Serviços Digitais Ltda | E48: 34.269.716/0001-00 | F48: 757 | G48: 32040 | H48: 45414 | I48: Agênciamento de serviços de desenvovimento de software | J48: Total nota fiscal: R$ 32040. Rateio: 100 % | K48: TRUE | L48: TRUE
B49: Notify | C49: Templates de gráficos | D49: Mout´s Soluçõesem Tecnologia da Informação Ltda. | E49: 5.056.849/0001-08 | F49: 3317 | G49: 14668.75 | H49: 45422 | I49: Agênciamento de serviços de desenvovimento de software | J49: Total nota fiscal: R$ 44006,26. Rateio: 33,33 % | K49: TRUE | L49: TRUE
B50: Notify | C50: Configuração Gateway para o IRIS V3 | D50: Mout´s Soluçõesem Tecnologia da Informação Ltda. | E50: 5.056.849/0001-08 | F50: 3317 | G50: 14668.75 | H50: 45422 | I50: Agênciamento de serviços de desenvovimento de software | J50: Total nota fiscal: R$ 44006,26. Rateio: 33,33 % | K50: TRUE | L50: TRUE
B51: Notify | C51: Design System | D51: Mout´s Soluçõesem Tecnologia da Informação Ltda. | E51: 5.056.849/0001-08 | F51: 3317 | G51: 14668.75 | H51: 45422 | I51: Agênciamento de serviços de desenvovimento de software | J51: Total nota fiscal: R$ 44006,26. Rateio: 33,33 % | K51: TRUE | L51: TRUE
B52: Notify | C52: Templates de gráficos | D52: Amazon AWS Serviços Brasil Ltda | E52: 23.412.247/0001-10 | F52: 3125620_V8RXCCLU | G52: 10010.61 | H52: 45414 | I52: Custo da infraestrutura em nuvem | J52: Total nota fiscal: R$ 20021,22. Rateio: 50 % | K52: TRUE | L52: TRUE
B53: Notify | C53: Configuração Gateway para o IRIS V3 | D53: Amazon AWS Serviços Brasil Ltda | E53: 23.412.247/0001-10 | F53: 3125620_V8RXCCLU | G53: 10010.61 | H53: 45414 | I53: Custo da infraestrutura em nuvem | J53: Total nota fiscal: R$ 20021,22. Rateio: 50 % | K53: TRUE | L53: TRUE
B54: Notify | C54: Configuração Gateway para o IRIS V3 | D54: Materialize Serviços Digitais Ltda | E54: 34.269.716/0001-00 | F54: 781 | G54: 32040 | H54: 45414 | I54: Agênciamento de serviços de desenvovimento de software | J54: Total nota fiscal: R$ 32040. Rateio: 100 % | K54: TRUE | L54: TRUE
B55: Notify | C55: Configuração Gateway para o IRIS V3 | D55: Mout´s Soluçõesem Tecnologia da Informação Ltda. | E55: 5.056.849/0001-08 | F55: 3357 | G55: 5067.9 | H55: 45446 | I55: Agênciamento de serviços de desenvovimento de software | J55: Total nota fiscal: R$ 10135,8. Rateio: 50 % | K55: TRUE | L55: TRUE
B56: Notify | C56: Design System | D56: Mout´s Soluçõesem Tecnologia da Informação Ltda. | E56: 5.056.849/0001-08 | F56: 3357 | G56: 5067.9 | H56: 45446 | I56: Agênciamento de serviços de desenvovimento de software | J56: Total nota fiscal: R$ 10135,8. Rateio: 50 % | K56: TRUE | L56: TRUE
B57: Notify | C57: Configuração Gateway para o IRIS V3 | D57: Mout´s Soluçõesem Tecnologia da Informação Ltda. | E57: 5.056.849/0001-08 | F57: 3370 | G57: 15210 | H57: 45450 | I57: Agênciamento de serviços de desenvovimento de software | J57: Total nota fiscal: R$ 30420. Rateio: 50 % | K57: TRUE | L57: TRUE
B58: Notify | C58: Design System | D58: Mout´s Soluçõesem Tecnologia da Informação Ltda. | E58: 5.056.849/0001-08 | F58: 3370 | G58: 15210 | H58: 45450 | I58: Agênciamento de serviços de desenvovimento de software | J58: Total nota fiscal: R$ 30420. Rateio: 50 % | K58: TRUE | L58: TRUE
B59: Notify | C59: Configuração Gateway para o IRIS V3 | D59: Amazon AWS Serviços Brasil Ltda | E59: 23.412.247/0001-10 | F59: 3196905_5AZYVJH6 | G59: 21043.05 | H59: 45414 | I59: Custo da infraestrutura em nuvem | J59: Total nota fiscal: R$ 21043,05. Rateio: 100 % | K59: TRUE | L59: TRUE
B60: Notify | C60: Configuração Gateway para o IRIS V3 | D60: Mout´s Soluçõesem Tecnologia da Informação Ltda. | E60: 5.056.849/0001-08 | F60: 3417 | G60: 13950 | H60: 45478 | I60: Agênciamento de serviços de desenvovimento de software | J60: Total nota fiscal: R$ 27900. Rateio: 50 % | K60: TRUE | L60: TRUE
B61: Notify | C61: Gerenciamento interno | D61: Mout´s Soluçõesem Tecnologia da Informação Ltda. | E61: 5.056.849/0001-08 | F61: 3417 | G61: 13950 | H61: 45478 | I61: Agênciamento de serviços de desenvovimento de software | J61: Total nota fiscal: R$ 27900. Rateio: 50 % | K61: TRUE | L61: TRUE
B62: Notify | C62: Configuração Gateway para o IRIS V3 | D62: Amazon AWS Serviços Brasil Ltda | E62: 23.412.247/0001-10 | F62: 3286189_BGKZLLHT | G62: 21293.57 | H62: 45475 | I62: Custo da infraestrutura em nuvem | J62: Total nota fiscal: R$ 21293,57. Rateio: 100 % | K62: TRUE | L62: TRUE
B63: Notify | C63: Configuração Gateway para o IRIS V3 | D63: Materialize Serviços Digitais Ltda | E63: 34.269.716/0001-00 | F63: 817 | G63: 32040 | H63: 45512 | I63: Agênciamento de serviços de desenvovimento de software | J63: Total nota fiscal: R$ 32040. Rateio: 100 % | K63: TRUE | L63: TRUE
B64: Notify | C64: Configuração Gateway para o IRIS V3 | D64: Mout´s Soluçõesem Tecnologia da Informação Ltda. | E64: 5.056.849/0001-08 | F64: 3518 | G64: 16605 | H64: 45519 | I64: Agênciamento de serviços de desenvovimento de software | J64: Total nota fiscal: R$ 33210. Rateio: 50 % | K64: TRUE | L64: TRUE
B65: Notify | C65: Gerenciamento interno | D65: Mout´s Soluçõesem Tecnologia da Informação Ltda. | E65: 5.056.849/0001-08 | F65: 3518 | G65: 16605 | H65: 45519 | I65: Agênciamento de serviços de desenvovimento de software | J65: Total nota fiscal: R$ 33210. Rateio: 50 % | K65: TRUE | L65: TRUE
B66: Notify | C66: Configuração Gateway para o IRIS V3 | D66: Amazon AWS Serviços Brasil Ltda | E66: 23.412.247/0001-10 | F66: 3385593_HEEGDXLC | G66: 19166.67 | H66: 45506 | I66: Custo da infraestrutura em nuvem | J66: Total nota fiscal: R$ 19166,67. Rateio: 100 % | K66: TRUE | L66: TRUE
B67: Notify | C67: Configuração Gateway para o IRIS V3 | D67: Materialize Serviços Digitais Ltda | E67: 34.269.716/0001-00 | F67: 825 | G67: 32040 | H67: 45538 | I67: Agênciamento de serviços de desenvovimento de software | J67: Total nota fiscal: R$ 32040. Rateio: 100 % | K67: TRUE | L67: TRUE
B68: Notify | C68: Configuração Gateway para o IRIS V3 | D68: Mout´s Soluçõesem Tecnologia da Informação Ltda. | E68: 5.056.849/0001-08 | F68: 3584 | G68: 15345 | H68: 45546 | I68: Agênciamento de serviços de desenvovimento de software | J68: Total nota fiscal: R$ 30690. Rateio: 50 % | K68: TRUE | L68: TRUE
B69: Notify | C69: Gerenciamento interno | D69: Mout´s Soluçõesem Tecnologia da Informação Ltda. | E69: 5.056.849/0001-08 | F69: 3584 | G69: 15345 | H69: 45546 | I69: Agênciamento de serviços de desenvovimento de software | J69: Total nota fiscal: R$ 30690. Rateio: 50 % | K69: TRUE | L69: TRUE
B70: Notify | C70: Configuração Gateway para o IRIS V3 | D70: Amazon AWS Serviços Brasil Ltda | E70: 23.412.247/0001-10 | F70: 3488856_KVCXJ5V5 | G70: 17677.81 | H70: 45537 | I70: Custo da infraestrutura em nuvem | J70: Total nota fiscal: R$ 17677,81. Rateio: 100 % | K70: TRUE | L70: TRUE
B71: Notify | C71: Gerenciamento interno | D71: Materialize Serviços Digitais Ltda | E71: 34.269.716/0001-00 | F71: 832 | G71: 17216.12 | H71: 45567 | I71: Agênciamento de serviços de desenvovimento de software | J71: Total nota fiscal: R$ 17216,12. Rateio: 100 % | K71: TRUE | L71: TRUE
B72: Notify | C72: Gateway para IRIS V3 Essentials | D72: Mout´s Soluçõesem Tecnologia da Informação Ltda. | E72: 5.056.849/0001-08 | F72: 3748 | G72: 15668.26 | H72: 45602 | I72: Agênciamento de serviços de desenvovimento de software | J72: Total nota fiscal: R$ 31336,51. Rateio: 50 % | K72: TRUE | L72: TRUE
B73: Notify | C73: Gerenciamento interno | D73: Mout´s Soluçõesem Tecnologia da Informação Ltda. | E73: 5.056.849/0001-08 | F73: 3748 | G73: 15668.26 | H73: 45602 | I73: Agênciamento de serviços de desenvovimento de software | J73: Total nota fiscal: R$ 31336,51. Rateio: 50 % | K73: TRUE | L73: TRUE
B74: Notify | C74: Gateway para IRIS V3 Essentials | D74: Amazon AWS Serviços Brasil Ltda | E74: 23.412.247/0001-10 | F74: 3584324_1DMEVBAE | G74: 17216.12 | H74: 45566 | I74: Custo da infraestrutura em nuvem | J74: Total nota fiscal: R$ 17216,12. Rateio: 100 % | K74: TRUE | L74: TRUE
B75: Notify | C75: Configuração Gateway para o IRIS V3 | D75: Materialize Serviços Digitais Ltda | E75: 34.269.716/0001-00 | F75: 202400000000880 | G75: 32040 | H75: 45603 | I75: Agênciamento de serviços de desenvovimento de software | J75: Total nota fiscal: R$ 32040. Rateio: 100 % | K75: TRUE | L75: TRUE
B76: Notify | C76: Gateway para IRIS V3 Essentials | D76: Mout´s Soluçõesem Tecnologia da Informação Ltda. | E76: 5.056.849/0001-08 | F76: 3665 | G76: 17235 | H76: 45573 | I76: Agênciamento de serviços de desenvovimento de software | J76: Total nota fiscal: R$ 34470. Rateio: 50 % | K76: TRUE | L76: TRUE
B77: Notify | C77: Gerenciamento interno | D77: Mout´s Soluçõesem Tecnologia da Informação Ltda. | E77: 5.056.849/0001-08 | F77: 3665 | G77: 17235 | H77: 45573 | I77: Agênciamento de serviços de desenvovimento de software | J77: Total nota fiscal: R$ 34470. Rateio: 50 % | K77: TRUE | L77: TRUE
B78: Notify | C78: Configuração Gateway para o IRIS V3 | D78: Amazon AWS Serviços Brasil Ltda | E78: 23.412.247/0001-10 | F78: 3689410_LLXIYFEF | G78: 18479.53 | H78: 45597 | I78: Custo da infraestrutura em nuvem | J78: Total nota fiscal: R$ 18479,53. Rateio: 100 % | K78: TRUE | L78: TRUE
B79: Notify | C79: Configuração Gateway para o IRIS V3 | D79: Materialize Serviços Digitais Ltda | E79: 34.269.716/0001-00 | F79: 202400000000901 | G79: 32040 | H79: 45629 | I79: Agênciamento de serviços de desenvovimento de software | J79: Total nota fiscal: R$ 32040. Rateio: 100 % | K79: TRUE | L79: TRUE
B80: Notify | C80: Configuração Gateway para o IRIS V3 | D80: Mout´s Soluçõesem Tecnologia da Informação Ltda. | E80: 5.056.849/0001-08 | F80: 3841 | G80: 15480 | H80: 45631 | I80: Agênciamento de serviços de desenvovimento de software | J80: Total nota fiscal: R$ 30960. Rateio: 50 % | K80: TRUE | L80: TRUE
B81: Notify | C81: Gerenciamento interno | D81: Mout´s Soluçõesem Tecnologia da Informação Ltda. | E81: 5.056.849/0001-08 | F81: 3841 | G81: 15480 | H81: 45631 | I81: Agênciamento de serviços de desenvovimento de software | J81: Total nota fiscal: R$ 30960. Rateio: 50 % | K81: TRUE | L81: TRUE
B82: Notify | C82: Configuração Gateway para o IRIS V3 | D82: Amazon AWS Serviços Brasil Ltda | E82: 23.412.247/0001-10 | F82: 3790213_FDP4MRWP | G82: 22299.43 | H82: 45627 | I82: Custo da infraestrutura em nuvem | J82: Total nota fiscal: R$ 22299,43. Rateio: 100 % | K82: TRUE | L82: TRUE
K83: FALSE
B84: P&D_2 | C84: Melhorias do MasterCream MINI / Outros tamanhos e geometrias de dentes das ferramentas, outros materiais / Facas de pré-corte | G84: 1250 | H84: 45343 | I84: Material para teste de laboratorio | J84: Testes | K84: FALSE | L84: FALSE
B85: P&D_2 | C85: Melhorias do MasterCream MINI / Outros tamanhos e geometrias de dentes das ferramentas, outros materiais / Facas de pré-corte | G85: 349.84 | H85: 45343 | I85: Horas de laboratorio | J85: Testes | K85: FALSE | L85: FALSE
B86: P&D_2 | C86: Adequação conforme design higienico | G86: 17.1 | H86: 45343 | I86: Materia prima de fabricação mecanica | J86: Testes | K86: FALSE | L86: FALSE
B87: P&D_2 | C87: Adequação conforme design higienico | G87: 154.08 | H87: 45343 | I87: Usinagem interna | J87: Testes | K87: FALSE | L87: FALSE
B88: P&D_2 | C88: Adequação conforme design higienico | G88: 240 | H88: 45343 | I88: Usinagem interna | J88: Testes | K88: FALSE | L88: FALSE
B89: P&D_3 | C89: Adequação conforme design higienico | D89: IFM ELECTRONIC LTDA | E89: 02.263.430/0001-21 | G89: 1329.23 | H89: 45459 | I89: compra de PT-100 higienico | J89: Adequar conexoes de sensores de temperatura conforme design higienico | K89: TRUE | L89: TRUE
B90: P&D_3 | C90: Limpeza com água | G90: 8330.56 | H90: 45414 | I90: Material para teste de laboratorio | J90: Testes | K90: FALSE | L90: TRUE
B91: P&D_3 | C91: Limpeza com água | G91: 142.68 | H91: 45386 | I91: Peças complementares de equipamento | J91: Testes | K91: FALSE | L91: TRUE
B92: P&D_3 | C92: Limpeza com água | D92: LABOR FOOD LABORATORIO DE ANALISES | E92: 41.077.883/0001-15 | G92: 12711.1 | H92: 45448 | I92: Analise de alergenicos | J92: Analise de resultados dos testes | K92: TRUE | L92: TRUE
B93: P&D_3 | C93: Limpeza com água | D93: LABOR FOOD LABORATORIO DE ANALISES | E93: 41.077.883/0001-15 | G93: 3000 | H93: 45432 | I93: Analise de alergenicos | J93: Analise de resultados dos testes | K93: TRUE | L93: TRUE
B94: P&D_3 | C94: Limpeza com água | D94: LABORATORIO ALAC LTDA | E94: 94.088.952/0001-52 | G94: 2510.6 | H94: 45402 | I94: Analise de alergenicos | J94: Analise de resultados dos testes | K94: TRUE | L94: TRUE
B95: P&D_3 | C95: Limpeza com água | D95: LABORATORIO ALAC LTDA | E95: 94.088.952/0001-52 | G95: 2189.6 | H95: 45371 | I95: Analise de alergenicos | J95: Analise de resultados dos testes | K95: TRUE | L95: TRUE
B96: P&D_3 | C96: Adequação conforme design higienico | D96: SJV SERVICOS INDUSTRIAIS LTDA | E96: 39.724.206/0001-08 | G96: 361.01 | H96: 45459 | I96: Servico de soldagem | J96: Adaptar conexao MC10 conforme design higienico | K96: TRUE | L96: TRUE
B97: P&D_3 | C97: Adequação conforme design higienico | D97: JGW MECANICA INDUSTRIAL LTDA | E97: 07.564.023/0001-78 | G97: 1900 | H97: 45387 | I97: Servico de polimento de tubulação | J97: Redução da rugosidade da tubulação para melhor limpeza | K97: TRUE | L97: TRUE
B98: P&D_3 | C98: Limpeza com água | D98: LABOR FOOD LABORATORIO DE ANALISES | E98: 41.077.883/0001-15 | G98: 58.4 | H98: 45342 | I98: Analise de alergenicos | J98: Analise de resultados dos testes | K98: FALSE | L98: TRUE
B99: P&D_3 | C99: Teste 3.14 | D99: LABORATORIO ALAC LTDA | E99: 94.088.952/0001-52 | F99: NFS 115436 | G99: 2737 | H99: 45572 | I99: Analise de alergenicos | J99: Analise de resultados dos testes | K99: TRUE | L99: TRUE
B100: P&D_3 | C100: Teste 3.15 | D100: LABORATORIO ALAC LTDA | E100: 94.088.952/0001-52 | F100: NFS 63465 | G100: 25 | H100: 45589 | I100: Analise de alergenicos | J100: Analise de resultados dos testes | K100: TRUE | L100: TRUE
B101: P&D_3 | C101: Teste 3.15 | D101: LABOR FOOD LABORATORIO DE ANALISES | E101: 41.077.883/0001-15 | F101: NFS 10975 | G101: 80 | H101: 45600 | I101: Análise de diferença de cor em chocolate branco | J101: Análise de diferença de cor | K101: TRUE | L101: TRUE
B102: P&D_3 | C102: Teste 3.15 | D102: LABORATORIO ALAC LTDA | E102: 94.088.952/0001-52 | F102: NFS 116603 | G102: 2054.94 | H102: 45609 | I102: Analise de alergenicos | J102: Analise de resultados dos testes | K102: TRUE | L102: TRUE
B103: P&D_3 | C103: Teste 3.15 | D103: LABORATORIO ALAC LTDA | E103: 94.088.952/0001-52 | F103: NFS 116646 | G103: 547.4 | H103: 45610 | I103: Analise de alergenicos | J103: Analise de resultados dos testes | K103: TRUE | L103: TRUE
B104: P&D_3 | C104: Teste 3.15 | D104: LABOR FOOD LABORATORIO DE ANALISES | E104: 41.077.883/0001-15 | F104: NFS 11082 | G104: 240 | H104: 45618 | I104: Análise de diferença de cor em chocolate branco | J104: Análise de diferença de cor | K104: TRUE | L104: TRUE
...

Sheet Tabela dinâmica 2

Sheet IRIS
B2: Netzsch Moagem
B3: Pesquisa, Desenvolvimento & Inovação
B4: Formulário de PD&I - Ano 2024 | J4: Incentivado pela Lei do Bem | M4: TRUE
B5: - preencher somente os campos sombreados (cinza) e - adicionar cronograma no formato de imagem ao fim do formulário - preencher um deste para cada projeto de PD&I | J5: Objetiva tornar-se um Ativo | M5: FALSE
J6: Objetiva gerar patente/registro | M6: FALSE
B8: Dossiê do projeto
B9: Dados gerais para identificação e validação do projeto de PD&I
B11: Nome do projeto | E11: IRIS -> IRIS V3
J12: Pesquisa básica | M12: 📑
B13: Classificação do projeto | E13: Desenvolvimento experimental | J13: Pesquisa aplicada | M13: 📑
J14: Desenvolvimento experimental | M14: 📑
B15: Objetivos do projeto | E15: Desenvolver uma série de funcionalidades inovadoras para o software de automação de equipamento de moagem a úmido, que permitam maior precisão e eficiência no processo de moagem, reduzindo o consumo de energia e aumentando a produtividade. O projeto visa implementar algoritmos avançados de controle de processos e análise preditiva para otimizar as operações de moagem em tempo real.
J16: Inovação tecnológica de produto | M16: 📑
B17: Tipo de inovação | E17: Inovação tecnológica de produto | J17: Inovação tecnológica de processo | M17: 📑
J18: Inovação tecnológica de serviços | M18: 📑
B19: Elemento inovador | E19: O software incorporará algoritmos de aprendizado de máquina para adaptar automaticamente os parâmetros de moagem com base em variações de matéria-prima e condições de operação. Essa abordagem inovadora permite uma resposta dinâmica do sistema, introduzindo um nível de automação e inteligência artificial que atualmente não é utilizado nesta indústria em nossa região. | J19: - Não podem ser consideradas as inovações organizacionais, comerciais e de marketing
J20: Empresa ou segmento regional | M20: 📑
B21: Nível de inovação | E21: Empresa ou segmento regional | J21: Inovador para o Brasil | M21: 📑
J22: Inovador para o Mundo | M22: 📑
B23: Risco tecnológico | E23: "Processo aprimorado de moagem no modo passada; Processo aprimorado de moagem no modo circulação; Registro avançado de dados de processo Portabilidade para funcionamento com CLP da Rockwell; Gerenciamento de dados remanecentes; Portabilidade para funcionamento com CLP da Rockwell; Implementação de sistema automático de gerenciamento de garantia; Portabilidade para funcionamento com CLP da Rockwell; IRIS V3 Epsilon InView - Desenvolvimento; IRIS V3 for Confectionary - Prototipação; IRIS V3 Epsilon InView - Desenvolvimento; IRIS V3 for Confectionary - Prototipação; IRIS V3 Epsilon InView - Recontrole; IRIS V3 for Confectionary - Prototipação"
B25: Metodologias | E25: Classificação e Análise de Feedback de Clientes: Utilização de técnicas de análise de dados para classificar e priorizar as sugestões e necessidades dos clientes em termos de funcionalidades de software. Desenvolvimento e Validação de Protótipos: Protótipos serão desenvolvidos usando métodos ágeis para iterar rapidamente com base no feedback do usuário. Implementação de Funcionalidades: Desenvolvimento de novas funcionalidades utilizando programação orientada a objetos e práticas de desenvolvimento de software seguro. Testes em Ambiente Controlado e Validação com Usuários: Testes rigorosos em ambientes simulados e em condições reais de operação para garantir a funcionalidade e segurança. Lançamento de Funcionalidades: Implementação gradual das novas funcionalidades para todos os usuários, com monitoramento contínuo de performance e coleta de feedback para futuras melhorias.
B27: Equipe | E27: Nome Completo | F27: Cargo/Função | G27: Qualificação | H27: !
E28: Ivo Ersching | F28: Desenvolvedor | G28: Graduação | L28: Técnico | M28: 📑
E29: Filipe Harbs | F29: Desenvolvedor | G29: Técnico | L29: Graduação
E30: Gabriel Oliveira | F30: Designer | G30: Graduação | L30: Pós-graduação
E31: Gabriel Alves Ferraz | F31: Desenvolvedor | G31: Graduação | L31: Mestrado
E32: Johann Ribeiro | F32: Desenvolvedor | G32: Técnico | L32: Doutorado
E33: Guilherme Jacques | F33: Desenvolvedor | G33: Graduação
E34: Rafael Augusto Barbieri Lobato | F34: Desenvolvedor | G34: Graduação
E35: Italo Ebel | F35: Desenvolvedor | G35: Graduação
E36: Alexandre Baseggio | F36: Desenvolvedor | G36: Pós-graduação
E37: Marcos Tribess | F37: Desenvolvedor | G37: Graduação
E38: Gabriel Oliveira
E39: Arthur Muniz
E40: Italo Ebel
E41: Bruno katzjarowksi
E42: Cleiton Capristano
B43: Cronograma | E43: Gabriel Possamai
B44: [anexar imagem - preferencialmente Gantt] | E44: Paulo Odwazny
E45: Cristiano Schroeder
E46: Gabriel Oliveira
E47: Arthur Muniz
E48: Italo Ebel
E49: Bruno katzjarowksi
E50: Cleiton Capristano
E51: Gabriel Possamai
E52: Paulo Odwazny
E53: Cristiano Schroeder
E54: Gabriel Oliveira
E55: Arthur Muniz
E56: Bruno katzjarowksi
... E76: Alberto Reuters

Sheet IRIS MILESTONES
B2: NETZSCH
B3: Pesquisa, Desenvolvimento & Inovação
B4: Formulário de PD&I - Ano 2024
B5: - preencher somente os campos sombreados (cinza)
B8: Dossiê do projeto | E8: Um objetivo a ser concluído durante esta etapa. Podemos ter vários em cada etapa. | G8: Uma data estimada que atualizará após etapa concluída
B9: Etapas e Milestones
B11: Projeto | C11: Etapa | D11: Principais atividades | E11: Milestones | F11: Data inicial | G11: Data conclusão | H11: Observações do gestor
B12: IRIS | C12: Processo aprimorado de moagem no modo passada | D12: Processo guiado de moagem no modo passada, com fluxos de ação para auxiliar o operador. Possibilidade de cálculo de energia específica por passada de foram automáticas pelo sistema. Cálculo baseado no total da solução ou na concentração do princípio ativo. | E12: Conclusão e validação da etapa | F12: 45294 | G12: 45322
B13: IRIS | C13: Processo aprimorado de moagem no modo circulação | D13: Processo guiado de moagem em modo de circulação, com fluxos de ação para auxiliar o operador. Possibilidade adicional de operação por taxa de produção, energia específica ou cálculo de ciclos. Cálculo da energia específica baseada no total da solução ou na concentração do princípio ativo. | E13: Conclusão e validação da etapa | F13: 45323 | G13: 45351
B14: IRIS | C14: Comunicação criptografada entre os elementos de controle e operação | D14: Registro, coleta e armazenamento de todas as etapas operacionais e ações realzidas pelo operador durante o processo de moagem | E14: Conclusão e validação da etapa | F14: 45324 | G14: 45345
B15: IRIS | C15: Registro avançado de dados de processo | D15: Registro, coleta e armazenamento de todas as etapas operacionais e ações realzidas pelo operador durante o processo de moagem | E15: Conclusão e validação da etapa | F15: 45352 | G15: 45380
B16: IRIS | C16: Portabilidade para funcionamento com CLP da Rockwell | D16: Reprogramação de todos as funcionalidaes desenvolvidas no CLP (Controlador Lógico Programável) da Siemens para o fabricante Rockwell. Estudo dos requerimentos, avaliação das capacidades e desenvolvimento | E16: Conclusão e validação da etapa | F16: 45383 | G16: 45504
B17: IRIS | C17: Gerenciamento de dados remanecentes | D17: Automatização no registro de dados para garantir a integridade dos dados de processo | E17: Conclusão e validação da etapa | F17: 45383 | G17: 45412
B18: IRIS | C18: Implementação de sistema automático de gerenciamento de garantia; | D18: Gerenciamento em tempo real da garantia do equipamento. Previsão levando em consideração relação comercial do faturamento, e instalação do equipamento no cliente | E18: Conclusão e validação da etapa | F18: 45413 | G18: 45443
B19: IRIS | C19: IRIS V3 Epsilon InView - Desenvolvimento | D19: Desenvolviemnto de software de automação com a platafaorma IRIS V3 | E19: Conclusão e validação da etapa | F19: 45474 | G19: 45534
B20: IRIS | C20: IRIS V3 Epsilon InView - Recontrole | D20: Validação da etapa de desenvolvimento com o recontrole de Epsilon presente no laboratório da empresa | E20: Conclusão e validação da etapa | F20: 45537 | G20: 45562
B21: IRIS | C21: IRIS V3 for Confectionary - Prototipação | D21: Pesquisa, documentação, criação de mockup (protótipo) e validação com clientes internos e externos | E21: Conclusão e validação da etapa | F21: 45474 | G21: 45562
B22: IRIS | C22: IRIS V3 BeadMill Essential | D22: Upgrade da automação da linha de entrada do moinho a umido, equipamento operado por botões, permitindo a coleta de dados por meio de um dispositivo IoT para posterior análise de processo no Notify. O processo consiste nas etapas de pesquisa, documentação e validação. | E22: Conclusão e validação da etapa | F22: 45568 | G22: 45716
B23: IRIS | C23: IRIS V3 for Confectionary - Desenvolvimento | D23: Desenvolvimento da base do software de automação com a plataforma IRIS V3 após a fase de prototipação | E23: Conclusão e validação da etapa | F23: 45566 | G23: 45656
... B26: IRIS | C26: IRIS V3 BeadMill Inview - Advance Training video | D26: Desenvolvimento de treinaemnto especializado com videos sobdemanda de cada um das funcionalidades do IRIS V3 BeadMill InvVew utilizadas por técnicos de After-Sales | E26: Conclusão e validação da etapa | F26: 45580 | G26: 45716

Sheet IRIS TIMESHEET
B2: NETZSCH
B3: Pesquisa, Desenvolvimento & Inovação
B4: Formulário de PD&I - Ano 2024
B5: - preencher somente os campos sombreados (cinza)
I6: Treinamento
I7: Pesquisa
B8: Dossiê do projeto | I8: Desenvolvimento
B9: Atividades de Pesquisa, Desenvolvimento e Inovação | I9: Gestão e outros
H10: =SUBTOTAL(9,H12:H149) -> 5890.29
B11: RowID | C11: Projeto | D11: Etapa | E11: Colaborador | F11: CPF | G11: Data | H11: Tempo (h) | I11: Classificação | J11: Descrição da atividade e observações
C12: IRIS | D12: Processo aprimorado de moagem no modo passada | E12: Gabriel Alves Ferraz | G12: 45313 | H12: 76.9 | I12: Desenvolvimento | J12: Desenvolvimento IHM
C13: IRIS | D13: Processo aprimorado de moagem no modo passada | E13: Gabriel Oliveira | G13: 45294 | H13: 166.5 | I13: Desenvolvimento | J13: Design UX/UI
C14: IRIS | D14: Processo aprimorado de moagem no modo passada | E14: Guilherme Jacques | G14: 45320 | H14: 4.5 | I14: Desenvolvimento | J14: Desenvolvimento PLC
C15: IRIS | D15: Processo aprimorado de moagem no modo passada | E15: Filipe Harbs | G15: 45299 | H15: 186.75 | I15: Desenvolvimento | J15: Desenvolvimento IHM
C16: IRIS | D16: Processo aprimorado de moagem no modo passada | E16: Italo Ebel | G16: 45295 | H16: 43 | I16: Desenvolvimento | J16: Documentação
C17: IRIS | D17: Processo aprimorado de moagem no modo passada | E17: Ivo Ersching | G17: 45299 | H17: 140 | I17: Desenvolvimento | J17: Desenvolvimento PLC
C18: IRIS | D18: Processo aprimorado de moagem no modo passada | E18: Johann Ribeiro | G18: 45299 | H18: 43.5 | I18: Desenvolvimento | J18: Documentação
C19: IRIS | D19: Processo aprimorado de moagem no modo passada | E19: Rafael Augusto Barbieri Lobato | G19: 45313 | H19: 2.8 | I19: Desenvolvimento | J19: Desenvolvimento PLC
C20: IRIS | D20: Processo aprimorado de moagem no modo circulação | E20: Alexandre Baseggio | G20: 45344 | H20: 6.75 | I20: Desenvolvimento | J20: Desenvolvimento PLC
C21: IRIS | D21: Processo aprimorado de moagem no modo circulação | E21: Gabriel Alves Ferraz | G21: 45323 | H21: 71.8 | I21: Desenvolvimento | J21: Desenvolvimento IHM
C22: IRIS | D22: Processo aprimorado de moagem no modo circulação | E22: Gabriel Oliveira | G22: 45323 | H22: 189.92 | I22: Desenvolvimento | J22: Design UX/UI
C23: IRIS | D23: Processo aprimorado de moagem no modo circulação | E23: Guilherme Jacques | G23: 45327 | H23: 115.65 | I23: Desenvolvimento | J23: Desenvolvimento PLC
... C149: IRIS | D149: IRIS V3 BeadMill Inview - Advance Training video | E149: Johann Ribeiro | G149: 45628 | H149: 30 | I149: Desenvolvimento | J149: Gravação de videos

Sheet IRIS TERCEIROS
B2: NETZSCH
B3: Pesquisa, Desenvolvimento & Inovação
B4: Formulário de PD&I - Ano 2024
B5: - preencher somente os campos sombreados (cinza)
B8: Dossiê do projeto
B9: Investimentos com terceiros | F9: Recebido via e-mail pela senhora Edilaine
B11: Projeto | C11: Etapa | D11: Fornecedor | E11: CNPJ | F11: Nota fiscal | G11: Valor | H11: Data | I11: Descrição da Atividade | J11: Objetivo do gasto e eventual info de rateio | K11: Gasto incentiv.
B12: IRIS | C12: Processo aprimorado de moagem no modo passada | D12: KMCC Equipamentos Elétricos Ltda | E12: 07.389.050/0001-51 | F12: 2288 | G12: 10353.48 | H12: 45307 | I12: Desenvolvimento IHM | J12: Pedido 2304662. Total do pedido: R$ 10.451,00. Percentual no projeto: 99% | K12: TRUE
B13: IRIS | C13: Processo aprimorado de moagem no modo circulação | D13: KMCC Equipamentos Elétricos Ltda | E13: 07.389.050/0001-51 | F13: 2268 | G13: 18491 | H13: 45323 | I13: Desenvolvimento IHM | J13: Pedido 2302666. Total do pedido: R$ 18.491,00. Percentual no projeto: 100 % | K13: TRUE
B14: IRIS | C14: Registro avançado de dados de processo | D14: KMCC Equipamentos Elétricos Ltda | E14: 07.389.050/0001-51 | F14: 2287 | G14: 16965.07 | H14: 45352 | I14: Desenvolvimento IHM | J14: Pedido 2304623. Total do pedido: R$ 17.467,00. Percentual no projeto: 97 % | K14: TRUE
B15: IRIS | C15: Portabilidade para funcionamento com CLP da Rockwell | D15: KMCC Equipamentos Elétricos Ltda | E15: 07.389.050/0001-51 | F15: NFS 2292 | G15: 275 | H15: 45383 | I15: Desenvolvimento IHM | K15: TRUE
B16: IRIS | C16: Gerenciamento de dados remanecentes | D16: KMCC Equipamentos Elétricos Ltda | E16: 07.389.050/0001-51 | F16: NFS 2292 | G16: 14235 | H16: 45383 | I16: Desenvolvimento IHM | K16: TRUE
B17: IRIS | C17: Portabilidade para funcionamento com CLP da Rockwell | D17: KMCC Equipamentos Elétricos Ltda | E17: 07.389.050/0001-51 | F17: NFS 2310 | G17: 4508 | H17: 45413 | I17: Desenvolvimento IHM | K17: TRUE
B18: IRIS | C18: Implementação de sistema automático de gerenciamento de garantia | D18: KMCC Equipamentos Elétricos Ltda | E18: 07.389.050/0001-51 | F18: NFS 2310 | G18: 6595 | H18: 45413 | I18: Desenvolvimento IHM | K18: TRUE
B19: IRIS | C19: Portabilidade para funcionamento com CLP da Rockwell | D19: KMCC Equipamentos Elétricos Ltda | E19: 07.389.050/0001-51 | F19: NFS 2311 | G19: 10940 | H19: 45444 | I19: Desenvolvimento IHM | K19: TRUE
B20: IRIS | C20: IRIS V3 Epsilon InView - Desenvolvimento | D20: KMCC Equipamentos Elétricos Ltda | E20: 07.389.050/0001-51 | F20: NFS 21013 | G20: 1180 | H20: 45474 | I20: Desenvolvimento IHM | J20: Percentual no projeto: 7,6 % | K20: TRUE
B21: IRIS | C21: IRIS V3 for Confectionary - Prototipação | D21: KMCC Equipamentos Elétricos Ltda | E21: 07.389.050/0001-51 | F21: NFS 21013 | G21: 1607 | H21: 45474 | I21: Documentação | J21: Percentual no projeto: 10,4 % | K21: TRUE
B22: IRIS | C22: IRIS V3 Epsilon InView - Desenvolvimento | D22: KMCC Equipamentos Elétricos Ltda | E22: 07.389.050/0001-51 | F22: Requisição de pedido: 4401020 | G22: 2623 | H22: 45505 | I22: Desenvolvimento IHM | J22: Percentual no projeto: 16,8 % | K22: TRUE
B23: IRIS | C23: IRIS V3 for Confectionary - Prototipação | D23: KMCC Equipamentos Elétricos Ltda | E23: 07.389.050/0001-51 | F23: Requisição de pedido: 4401020 | G23: 2357 | H23: 45505 | I23: Documentação | J23: Percentual no projeto: 15,1 % | K23: TRUE
B24: IRIS | C24: IRIS V3 Epsilon InView - Recontrole | D24: KMCC Equipamentos Elétricos Ltda | E24: 07.389.050/0001-51 | F24: Pedido: 2316035 | G24: 2332 | H24: 45536 | I24: Desenvolvimento IHM | J24: Percentual no projeto: 13,4 % | K24: TRUE
B25: IRIS | C25: IRIS V3 for Confectionary - Prototipação | D25: KMCC Equipamentos Elétricos Ltda | E25: 07.389.050/0001-51 | F25: Pedido: 2316035 | G25: 5935 | H25: 45536 | I25: Documentação | J25: Percentual no projeto: 34 % | K25: TRUE

Sheet NOTIFY
B2: Netzsch Moagem
B3: Pesquisa, Desenvolvimento & Inovação
B4: Formulário de PD&I - Ano 2024 | J4: Incentivado pela Lei do Bem | M4: TRUE
B5: - preencher somente os campos sombreados (cinza) e - adicionar cronograma no formato de imagem ao fim do formulário - preencher um deste para cada projeto de PD&I | J5: Objetiva tornar-se um Ativo | M5: FALSE
J6: Objetiva gerar patente/registro | M6: FALSE
B8: Dossiê do projeto
B9: Dados gerais para identificação e validação do projeto de PD&I
B11: Nome do projeto | E11: Notify - Novas funcionalidades
J12: Pesquisa básica | M12: 📑
B13: Classificação do projeto | E13: Desenvolvimento experimental | J13: Pesquisa aplicada | M13: 📑
J14: Desenvolvimento experimental | M14: 📑
B15: Objetivos do projeto | E15: Desenvolver novas funcionalidades no software Notify para aprimorar a análise de dados operacionais das máquinas e enriquecer a experiência do usuário. As funcionalidades pretendem tornar o software uma ferramenta mais intuitiva e capaz de oferecer insights operacionais detalhados através de uma interface de usuário otimizada e funcionalidades avançadas de relatório.
J16: Inovação tecnológica de produto | M16: 📑
B17: Tipo de inovação | E17: Inovação tecnológica de serviços | J17: Inovação tecnológica de processo | M17: 📑
J18: Inovação tecnológica de serviços | M18: 📑
B19: Elemento inovador | E19: Gerenciamento de Licenças: Introdução de um sistema sofisticado para gerenciar licenças de software que facilita a expansão de uso sem complicações. Duplicação de Máquinas Existentes: Permitir aos usuários duplicar configurações de máquinas existentes para novas instalações, economizando tempo e reduzindo erros. Relatório de Lotes: Desenvolvimento de uma funcionalidade para relatórios detalhados de lotes de produção que pode ser personalizado conforme as necessidades operacionais. Exportação de Dados para o Excel: Facilitar a exportação de dados operacionais para Excel para análises mais profundas. Adequação e Configuração do Gateway para o IRIS V3: Adaptar o software para integrar com a nova versão do sistema IRIS, permitindo uma comunicação mais eficiente e segura. Templates de Gráficos e Design System dos Produtos Digitais: Desenvolver templates para gráficos e um design system unificado que melhore a consistência visual e a usabilidade em todos os produtos digitais da empresa. | J19: - Não podem ser consideradas as inovações organizacionais, comerciais e de marketing
J20: Empresa ou segmento regional | M20: 📑
B21: Nível de inovação | E21: Empresa ou segmento regional | J21: Inovador para o Brasil | M21: 📑
J22: Inovador para o Mundo | M22: 📑
B23: Risco tecnológico | E23: O desenvolvimento das funcionalidades envolve riscos tecnológicos relacionados à integração com sistemas existentes, adaptação às novas versões de softwares de base e garantia de que as novas funcionalidades operem conforme o esperado em diferentes ambientes tecnológicos. Os riscos incluem a possibilidade de falhas técnicas durante a integração e a necessidade de ajustes significativos após os testes iniciais.
B25: Metodologias | E25: Classificação de Feedbacks: Análise detalhada dos feedbacks dos clientes para priorizar o desenvolvimento conforme as necessidades mais críticas. Criação e Validação de Protótipos: Prototipagem rápida e iterativa com a participação ativa dos usuários para garantir que as novas funcionalidades atendam às expectativas e requisitos operacionais. Desenvolvimento das Funcionalidades: Utilização de metodologias ágeis para o desenvolvimento de software, permitindo flexibilidade e adaptação durante o ciclo de desenvolvimento. Validação em Ambiente de Teste: Testes rigorosos em ambientes controlados para garantir a funcionalidade e robustez antes da implementação final. Liberação das Funcionalidades: Implantação gradual das funcionalidades para todos os usuários, acompanhada de suporte técnico proativo para resolver qualquer questão emergente.
B27: Equipe | E27: Nome Completo | F27: Cargo/Função | G27: Qualificação | H27: !
E28: Bruno katzjarowksi | F28: Desenvolvedor | L28: Técnico | M28: 📑
E29: Gabriel Possamai | F29: Desenvolvedor | L29: Graduação
E30: Cristiano Schroeder | F30: Desenvolvedor | L30: Pós-graduação
E31: Arthur Muniz | F31: Desenvolvedor | L31: Mestrado
E32: Cleiton Capristano | F32: Desenvolvedor | G32: Graduação | L32: Doutorado
E33: Gabriel Alves Ferraz | F33: Desenvolvedor | G33: Graduação
E34: Alberto Reuters | F34: Gerente de Desenvolvimento e Automação | G34: Mestrado
E35: Eduardo Flohr | F35: Supervisor de Automação | G35: Pós-graduação
E36: Paulo Odwazny | F36: Supervisor de Desenvolvimento | G36: Graduação
E37: Johann Ribeiro | F37: Desenvolvedor
E38: Gabriel Oliveira | F38: Designer | G38: Graduação
E39: Italo Ebel | F39: Desenvolvedor
E40: Jivago Rusch
B41: Cronograma
B42: [anexar imagem - preferencialmente Gantt]

Sheet NOTIFY TIMESHEET
B2: NETZSCH
B3: Pesquisa, Desenvolvimento & Inovação
B4: Formulário de PD&I - Ano 2024
B5: - preencher somente os campos sombreados (cinza)
I6: Treinamento
I7: Pesquisa
B8: Dossiê do projeto | I8: Desenvolvimento
B9: Atividades de Pesquisa, Desenvolvimento e Inovação | I9: Gestão e outros
H10: =sum(H12:H103) -> 11100
B11: RowID | C11: Projeto | D11: Etapa | E11: Colaborador | F11: CPF | G11: Data | H11: Tempo (h) | I11: Classificação | J11: Descrição da atividade e observações
C12: Notify | D12: Relatório de lotes | E12: Gabriel Oliveira | F12: 085.943.039-12 | G12: 45292 | H12: 20 | I12: Desenvolvimento | J12: Desenvolvimento dos designs (UI/UX)
C13: Notify | D13: Configuração Gateway para o IRIS V3 | E13: Arthur Muniz | F13: 037.196.611-64 | G13: 45292 | H13: 191 | I13: Desenvolvimento | J13: Desenvolvimento Beckend
C14: Notify | D14: Exportar dados para o Excel | E14: Italo Ebel | F14: 534.546.398-08 | G14: 45292 | H14: 4 | I14: Desenvolvimento | J14: Testes
C15: Notify | D15: Adequação do Gateway para o IRIS V3 | E15: Bruno katzjarowksi | F15: 080.850.859-84 | G15: 45292 | H15: 198 | I15: Desenvolvimento | J15: Desenvolvimento Beckend
C16: Notify | D16: Templates de gráficos | E16: Cleiton Capristano | F16: 068.504.079-88 | G16: 45292 | H16: 122 | I16: Desenvolvimento | J16: Desenvolvimento Fronend
C17: Notify | D17: Configuração Gateway para o IRIS V3 | E17: Gabriel Possamai | F17: 085.815.809-47 | G17: 45292 | H17: 120 | I17: Pesquisa | J17: Especificação da funcionalidade
C18: Notify | D18: Configuração Gateway para o IRIS V3 | E18: Paulo Odwazny | F18: 035.705.119-01 | G18: 45292 | H18: 5 | I18: Pesquisa | J18: Especificação da funcionalidade
C19: Notify | D19: Templates de gráficos | E19: Cristiano Schroeder | F19: 080.335.889-00 | G19: 45292 | H19: 168 | I19: Desenvolvimento | J19: Testes
C20: Notify | D20: Relatório de lotes | E20: Gabriel Oliveira | F20: 085.943.039-12 | G20: 45323 | H20: 17 | I20: Desenvolvimento | J20: Desenvolvimento dos designs (UI/UX)
C21: Notify | D21: Configuração Gateway para o IRIS V3 | E21: Arthur Muniz | F21: 037.196.611-64 | G21: 45323 | H21: 89 | I21: Desenvolvimento | J21: Desenvolvimento Beckend
C22: Notify | D22: Templates de gráficos | E22: Italo Ebel | F22: 534.546.398-08 | G22: 45323 | H22: 36 | I22: Desenvolvimento | J22: Testes
C23: Notify | D23: Adequação do Gateway para o IRIS V3 | E23: Bruno katzjarowksi | F23: 080.850.859-84 | G23: 45323 | H23: 193 | I23: Desenvolvimento | J23: Desenvolvimento Beckend
... C103: Notify | D103: Adequação do Gateway para o IRIS V3 | E103: Italo Ebel | F103: 534.546.398-08 | G103: 45627 | H103: 154 | I103: Desenvolvimento | J103: Testes

Sheet NOTIFY MILESTONES
B2: NETZSCH
B3: Pesquisa, Desenvolvimento & Inovação
B4: Formulário de PD&I - Ano 2024
B5: - preencher somente os campos sombreados (cinza)
B8: Dossiê do projeto | E8: Um objetivo a ser concluído durante esta etapa. Podemos ter vários em cada etapa. | G8: Uma data estimada que atualizará após etapa concluída
B9: Etapas e Milestones
B11: Projeto | C11: Etapa | D11: Principais atividades | E11: Milestones | F11: Data inicial | G11: Data conclusão | H11: Observações do gestor
B12: Notify | C12: Relatório de lotes | D12: Relatório dos lotes produzidos pelas máquinas NETZSCH | E12: Documentação para apresentação ao Board | F12: 45108 | G12: 45350
B13: Notify | C13: Adequação do Gateway para o IRIS V3 | D13: Gateway para envio dos dados de máquina para os servidores do Notify | E13: Lançamento da funcionalidade | F13: 45170 | G13: 45412
B14: Notify | C14: Templates de gráficos | D14: Modelo de gráfico para comparação de sensores | E14: Lançamento da funcionalidade | F14: 45200 | G14: 45443
B15: Notify | C15: Configuração Gateway para o IRIS V3 | D15: Configuração do gateway de envio de dados da máquina para os servidores do Notify pelo aplicativo Manager Tool, disponível para os técnicos da NETZSCH | E15: Lançamento da funcionalidade | F15: 45292 | G15: 45473
B16: Notify | C16: Design System | D16: Conjunto de padrões e componentes que define a linguagem visual e funcional de um produto digital, promovendo consistência, eficiência e colaboração entre equipes de design e desenvolvimento. | E16: Documentação para apresentação ao Board | F16: 45292 | G16: 45473
B17: Notify | C17: Troca de infraestrutura | D17: Migração dos dados do banco de dados Timescale para o Timescale Cloud, com o objetivo de possibilitar a compressão de dados menos acessados e, assim, reduzir os custos de armazenamento. | E17: Conclusão e validação da etapa | F17: 45505 | G17: 45657
B18: Notify | C18: Gerenciamento interno | D18: Desenvolvimento de atualização de gateways, tabela para verificar licenças expiradas e biblioteca de componentes para acelerar o desenvolvimento | E18: Lançamento da funcionalidade | F18: 45474 | G18: 45657
B19: Notify | C19: Gateway para IRIS V3 Essentials | D19: Gateway para envio dos dados de máquina, equipadas com o sistema de controle IRIS V3 Essenstials, para os servidores do Notify | E19: Lançamento da funcionalidade | F19: 45536 | G19: 45688
B20: Notify | C20: Gateway para IRIS V3 Inside | D20: Gateway para envio dos dados de máquina, equipadas com o sistema de controle IRIS V3 Inside, para os servidores do Notify | E20: Lançamento da funcionalidade | F20: 45689 | G20: 45838

Sheet NOTIFY TERCEIROS
B2: NETZSCH
B3: Pesquisa, Desenvolvimento & Inovação
B4: Formulário de PD&I - Ano 2024
B5: - preencher somente os campos sombreados (cinza)
B8: Dossiê do projeto
B9: Investimentos com terceiros
B11: Projeto | C11: Etapa | D11: Fornecedor | E11: CNPJ | F11: Nota fiscal | G11: Valor | H11: Data | I11: Descrição da Atividade | J11: Objetivo do gasto e eventual info de rateio | K11: Gasto incentiv.
B12: Notify | C12: Relatório de lotes | D12: Materialize Serviços Digitais Ltda | E12: 34.269.716/0001-00 | F12: 650 | G12: 32040 | H12: 45293 | I12: Agenciamento de serviços de desenvovimento de software | J12: Total nota fiscal: R$ 32040. Rateio: 100 % | K12: TRUE
B13: Notify | C13: Templates de gráficos | D13: Mout´s Soluçõesem Tecnologia da Informação Ltda. | E13: 5.056.849/0001-08 | F13: 3169 | G13: 19849.28 | H13: 45308 | I13: Agenciamento de serviços de desenvovimento de software | J13: Total nota fiscal: R$ 39698,55. Rateio: 50 % | K13: TRUE
B14: Notify | C14: Relatório de lotes | D14: Mout´s Soluçõesem Tecnologia da Informação Ltda. | E14: 5.056.849/0001-08 | F14: 3169 | G14: 19849.28 | H14: 45308 | I14: Agenciamento de serviços de desenvovimento de software | J14: Total nota fiscal: R$ 39698,55. Rateio: 50 % | K14: TRUE
B15: Notify | C15: Templates de gráficos | D15: Amazon AWS Serviços Brasil Ltda | E15: 23.412.247/0001-10 | F15: 2709240_ECNZ6XB8 | G15: 5412.76 | H15: 45293 | I15: Custo da infraestrutura em nuvem | J15: Total nota fiscal: R$ 10825,52. Rateio: 50 % | K15: TRUE
B16: Notify | C16: Relatório de lotes | D16: Amazon AWS Serviços Brasil Ltda | E16: 23.412.247/0001-10 | F16: 2709240_ECNZ6XB8 | G16: 5412.76 | H16: 45293 | I16: Custo da infraestrutura em nuvem | J16: Total nota fiscal: R$ 10825,52. Rateio: 50 % | K16: TRUE
B17: Notify | C17: Templates de gráficos | D17: Materialize Serviços Digitais Ltda | E17: 34.269.716/0001-00 | F17: 684 | G17: 32040 | H17: 45323 | I17: Agenciamento de serviços de desenvovimento de software | J17: Total nota fiscal: R$ 32040. Rateio: 100 % | K17: TRUE
B18: Notify | C18: Templates de gráficos | D18: Mout´s Soluçõesem Tecnologia da Informação Ltda. | E18: 5.056.849/0001-08 | F18: 3188 | G18: 22059.44 | H18: 45328 | I18: Agenciamento de serviços de desenvovimento de software | J18: Total nota fiscal: R$ 44118,88. Rateio: 50 % | K18: TRUE
B19: Notify | C19: Relatório de lotes | D19: Mout´s Soluçõesem Tecnologia da Informação Ltda. | E19: 5.056.849/0001-08 | F19: 3188 | G19: 22059.44 | H19: 45328 | I19: Agenciamento de serviços de desenvovimento de software | J19: Total nota fiscal: R$ 44118,88. Rateio: 50 % | K19: TRUE
B20: Notify | C20: Templates de gráficos | D20: Amazon AWS Serviços Brasil Ltda | E20: 23.412.247/0001-10 | F20: 2845975_9ZHR17CA | G20: 5496.54 | H20: 45324 | I20: Custo da infraestrutura em nuvem | J20: Total nota fiscal: R$ 10993,07. Rateio: 50 % | K20: TRUE
B21: Notify | C21: Relatório de lotes | D21: Amazon AWS Serviços Brasil Ltda | E21: 23.412.247/0001-10 | F21: 2845975_9ZHR17CA | G21: 5496.54 | H21: 45324 | I21: Custo da infraestrutura em nuvem | J21: Total nota fiscal: R$ 10993,07. Rateio: 50 % | K21: TRUE
B22: Notify | C22: Templates de gráficos | D22: Materialize Serviços Digitais Ltda | E22: 34.269.716/0001-00 | F22: 710 | G22: 32040 | H22: 45355 | I22: Agenciamento de serviços de desenvovimento de software | J22: Total nota fiscal: R$ 32040. Rateio: 100 % | K22: TRUE
B23: Notify | C23: Templates de gráficos | D23: Mout´s Soluçõesem Tecnologia da Informação Ltda. | E23: 5.056.849/0001-08 | F23: 3225 | G23: 16057.73 | H23: 45359 | I23: Agenciamento de serviços de desenvovimento de software | J23: Total nota fiscal: R$ 48173,2. Rateio: 33,33 % | K23: TRUE
B24: Notify | C24: Configuração Gateway para o IRIS V3 | D24: Mout´s Soluçõesem Tecnologia da Informação Ltda. | E24: 5.056.849/0001-08 | F24: 3228 | G24: 16057.73 | H24: 45359 | I24: Agenciamento de serviços de desenvovimento de software | J24: Total nota fiscal: R$ 48173,2. Rateio: 33,33 % | K24: TRUE
B25: Notify | C25: Design System | D25: Mout´s Soluçõesem Tecnologia da Informação Ltda. | E25: 5.056.849/0001-08 | F25: 3228 | G25: 16057.73 | H25: 45359 | I25: Agenciamento de serviços de desenvovimento de software | J25: Total nota fiscal: R$ 48173,2. Rateio: 33,33 % | K25: TRUE
B26: Notify | C26: Templates de gráficos | D26: Amazon AWS Serviços Brasil Ltda | E26: 23.412.247/0001-10 | F26: 2901379_BRL69BTP | G26: 5486.78 | H26: 45353 | I26: Custo da infraestrutura em nuvem | J26: Total nota fiscal: R$ 10973,56. Rateio: 50 % | K26: TRUE
B27: Notify | C27: Configuração Gateway para o IRIS V3 | D27: Amazon AWS Serviços Brasil Ltda | E27: 23.412.247/0001-10 | F27: 2901379_BRL69BTP | G27: 5486.78 | H27: 45353 | I27: Custo da infraestrutura em nuvem | J27: Total nota fiscal: R$ 10973,56. Rateio: 50 % | K27: TRUE
B28: Notify | C28: Templates de gráficos | D28: Materialize Serviços Digitais Ltda | E28: 34.269.716/0001-00 | F28: 729 | G28: 32040 | H28: 45383 | I28: Agênciamento de serviços de desenvovimento de software | J28: Total nota fiscal: R$ 32040. Rateio: 100 % | K28: TRUE
B29: Notify | C29: Templates de gráficos | D29: Mout´s Soluçõesem Tecnologia da Informação Ltda. | E29: 5.056.849/0001-08 | F29: 3266 | G29: 14884.61 | H29: 45386 | I29: Agênciamento de serviços de desenvovimento de software | J29: Total nota fiscal: R$ 44653,83. Rateio: 33,33 % | K29: TRUE
B30: Notify | C30: Configuração Gateway para o IRIS V3 | D30: Mout´s Soluçõesem Tecnologia da Informação Ltda. | E30: 5.056.849/0001-08 | F30: 3266 | G30: 14884.61 | H30: 45386 | I30: Agênciamento de serviços de desenvovimento de software | J30: Total nota fiscal: R$ 44653,83. Rateio: 33,33 % | K30: TRUE
B31: Notify | C31: Design System | D31: Mout´s Soluçõesem Tecnologia da Informação Ltda. | E31: 5.056.849/0001-08 | F31: 3266 | G31: 14884.61 | H31: 45386 | I31: Agênciamento de serviços de desenvovimento de software | J31: Total nota fiscal: R$ 44653,83. Rateio: 33,33 % | K31: TRUE
B32: Notify | C32: Templates de gráficos | D32: Amazon AWS Serviços Brasil Ltda | E32: 23.412.247/0001-10 | F32: 2992055_YIQTWU6S | G32: 6465.15 | H32: 45384 | I32: Custo da infraestrutura em nuvem | J32: Total nota fiscal: R$ 12930,29. Rateio: 50 % | K32: TRUE
B33: Notify | C33: Configuração Gateway para o IRIS V3 | D33: Amazon AWS Serviços Brasil Ltda | E33: 23.412.247/0001-10 | F33: 2992055_YIQTWU6S | G33: 6465.15 | H33: 45384 | I33: Custo da infraestrutura em nuvem | J33: Total nota fiscal: R$ 12930,29. Rateio: 50 % | K33: TRUE
B34: Notify | C34: Templates de gráficos | D34: Materialize Serviços Digitais Ltda | E34: 34.269.716/0001-00 | F34: 757 | G34: 32040 | H34: 45414 | I34: Agênciamento de serviços de desenvovimento de software | J34: Total nota fiscal: R$ 32040. Rateio: 100 % | K34: TRUE
B35: Notify | C35: Templates de gráficos | D35: Mout´s Soluçõesem Tecnologia da Informação Ltda. | E35: 5.056.849/0001-08 | F35: 3317 | G35: 14668.75 | H35: 45422 | I35: Agênciamento de serviços de desenvovimento de software | J35: Total nota fiscal: R$ 44006,26. Rateio: 33,33 % | K35: TRUE
B36: Notify | C36: Configuração Gateway para o IRIS V3 | D36: Mout´s Soluçõesem Tecnologia da Informação Ltda. | E36: 5.056.849/0001-08 | F36: 3317 | G36: 14668.75 | H36: 45422 | I36: Agênciamento de serviços de desenvovimento de software | J36: Total nota fiscal: R$ 44006,26. Rateio: 33,33 % | K36: TRUE
B37: Notify | C37: Design System | D37: Mout´s Soluçõesem Tecnologia da Informação Ltda. | E37: 5.056.849/0001-08 | F37: 3317 | G37: 14668.75 | H37: 45422 | I37: Agênciamento de serviços de desenvovimento de software | J37: Total nota fiscal: R$ 44006,26. Rateio: 33,33 % | K37: TRUE
B38: Notify | C38: Templates de gráficos | D38: Amazon AWS Serviços Brasil Ltda | E38: 23.412.247/0001-10 | F38: 3125620_V8RXCCLU | G38: 10010.61 | H38: 45414 | I38: Custo da infraestrutura em nuvem | J38: Total nota fiscal: R$ 20021,22. Rateio: 50 % | K38: TRUE
B39: Notify | C39: Configuração Gateway para o IRIS V3 | D39: Amazon AWS Serviços Brasil Ltda | E39: 23.412.247/0001-10 | F39: 3125620_V8RXCCLU | G39: 10010.61 | H39: 45414 | I39: Custo da infraestrutura em nuvem | J39: Total nota fiscal: R$ 20021,22. Rateio: 50 % | K39: TRUE
B40: Notify | C40: Configuração Gateway para o IRIS V3 | D40: Materialize Serviços Digitais Ltda | E40: 34.269.716/0001-00 | F40: 781 | G40: 32040 | H40: 45414 | I40: Agênciamento de serviços de desenvovimento de software | J40: Total nota fiscal: R$ 32040. Rateio: 100 % | K40: TRUE
B41: Notify | C41: Configuração Gateway para o IRIS V3 | D41: Mout´s Soluçõesem Tecnologia da Informação Ltda. | E41: 5.056.849/0001-08 | F41: 3357 | G41: 5067.9 | H41: 45446 | I41: Agênciamento de serviços de desenvovimento de software | J41: Total nota fiscal: R$ 10135,8. Rateio: 50 % | K41: TRUE
B42: Notify | C42: Design System | D42: Mout´s Soluçõesem Tecnologia da Informação Ltda. | E42: 5.056.849/0001-08 | F42: 3357 | G42: 5067.9 | H42: 45446 | I42: Agênciamento de serviços de desenvovimento de software | J42: Total nota fiscal: R$ 10135,8. Rateio: 50 % | K42: TRUE
B43: Notify | C43: Configuração Gateway para o IRIS V3 | D43: Mout´s Soluçõesem Tecnologia da Informação Ltda. | E43: 5.056.849/0001-08 | F43: 3370 | G43: 15210 | H43: 45450 | I43: Agênciamento de serviços de desenvovimento de software | J43: Total nota fiscal: R$ 30420. Rateio: 50 % | K43: TRUE
B44: Notify | C44: Design System | D44: Mout´s Soluçõesem Tecnologia da Informação Ltda. | E44: 5.056.849/0001-08 | F44: 3370 | G44: 15210 | H44: 45450 | I44: Agênciamento de serviços de desenvovimento de software | J44: Total nota fiscal: R$ 30420. Rateio: 50 % | K44: TRUE
B45: Notify | C45: Configuração Gateway para o IRIS V3 | D45: Amazon AWS Serviços Brasil Ltda | E45: 23.412.247/0001-10 | F45: 3196905_5AZYVJH6 | G45: 21043.05 | H45: 45414 | I45: Custo da infraestrutura em nuvem | J45: Total nota fiscal: R$ 21043,05. Rateio: 100 % | K45: TRUE
B46: Notify | C46: Configuração Gateway para o IRIS V3 | D46: Mout´s Soluçõesem Tecnologia da Informação Ltda. | E46: 5.056.849/0001-08 | F46: 3417 | G46: 13950 | H46: 45478 | I46: Agênciamento de serviços de desenvovimento de software | J46: Total nota fiscal: R$ 27900. Rateio: 50 % | K46: TRUE
B47: Notify | C47: Gerenciamento interno | D47: Mout´s Soluçõesem Tecnologia da Informação Ltda. | E47: 5.056.849/0001-08 | F47: 3417 | G47: 13950 | H47: 45478 | I47: Agênciamento de serviços de desenvovimento de software | J47: Total nota fiscal: R$ 27900. Rateio: 50 % | K47: TRUE
B48: Notify | C48: Configuração Gateway para o IRIS V3 | D48: Amazon AWS Serviços Brasil Ltda | E48: 23.412.247/0001-10 | F48: 3286189_BGKZLLHT | G48: 21293.57 | H48: 45475 | I48: Custo da infraestrutura em nuvem | J48: Total nota fiscal: R$ 21293,57. Rateio: 100 % | K48: TRUE
B49: Notify | C49: Configuração Gateway para o IRIS V3 | D49: Materialize Serviços Digitais Ltda | E49: 34.269.716/0001-00 | F49: 817 | G49: 32040 | H49: 45512 | I49: Agênciamento de serviços de desenvovimento de software | J49: Total nota fiscal: R$ 32040. Rateio: 100 % | K49: TRUE
B50: Notify | C50: Configuração Gateway para o IRIS V3 | D50: Mout´s Soluçõesem Tecnologia da Informação Ltda. | E50: 5.056.849/0001-08 | F50: 3518 | G50: 16605 | H50: 45519 | I50: Agênciamento de serviços de desenvovimento de software | J50: Total nota fiscal: R$ 33210. Rateio: 50 % | K50: TRUE
B51: Notify | C51: Gerenciamento interno | D51: Mout´s Soluçõesem Tecnologia da Informação Ltda. | E51: 5.056.849/0001-08 | F51: 3518 | G51: 16605 | H51: 45519 | I51: Agênciamento de serviços de desenvovimento de software | J51: Total nota fiscal: R$ 33210. Rateio: 50 % | K51: TRUE
B52: Notify | C52: Configuração Gateway para o IRIS V3 | D52: Amazon AWS Serviços Brasil Ltda | E52: 23.412.247/0001-10 | F52: 3385593_HEEGDXLC | G52: 19166.67 | H52: 45506 | I52: Custo da infraestrutura em nuvem | J52: Total nota fiscal: R$ 19166,67. Rateio: 100 % | K52: TRUE
B53: Notify | C53: Configuração Gateway para o IRIS V3 | D53: Materialize Serviços Digitais Ltda | E53: 34.269.716/0001-00 | F53: 825 | G53: 32040 | H53: 45538 | I53: Agênciamento de serviços de desenvovimento de software | J53: Total nota fiscal: R$ 32040. Rateio: 100 % | K53: TRUE
B54: Notify | C54: Configuração Gateway para o IRIS V3 | D54: Mout´s Soluçõesem Tecnologia da Informação Ltda. | E54: 5.056.849/0001-08 | F54: 3584 | G54: 15345 | H54: 45546 | I54: Agênciamento de serviços de desenvovimento de software | J54: Total nota fiscal: R$ 30690. Rateio: 50 % | K54: TRUE
B55: Notify | C55: Gerenciamento interno | D55: Mout´s Soluçõesem Tecnologia da Informação Ltda. | E55: 5.056.849/0001-08 | F55: 3584 | G55: 15345 | H55: 45546 | I55: Agênciamento de serviços de desenvovimento de software | J55: Total nota fiscal: R$ 30690. Rateio: 50 % | K55: TRUE
B56: Notify | C56: Configuração Gateway para o IRIS V3 | D56: Amazon AWS Serviços Brasil Ltda | E56: 23.412.247/0001-10 | F56: 3488856_KVCXJ5V5 | G56: 17677.81 | H56: 45537 | I56: Custo da infraestrutura em nuvem | J56: Total nota fiscal: R$ 17677,81. Rateio: 100 % | K56: TRUE
B57: Notify | C57: Gerenciamento interno | D57: Materialize Serviços Digitais Ltda | E57: 34.269.716/0001-00 | F57: 832 | G57: 17216.12 | H57: 45567 | I57: Agênciamento de serviços de desenvovimento de software | J57: Total nota fiscal: R$ 17216,12. Rateio: 100 % | K57: TRUE
B58: Notify | C58: Gateway para IRIS V3 Essentials | D58: Mout´s Soluçõesem Tecnologia da Informação Ltda. | E58: 5.056.849/0001-08 | F58: 3748 | G58: 15668.26 | H58: 45602 | I58: Agênciamento de serviços de desenvovimento de software | J58: Total nota fiscal: R$ 31336,51. Rateio: 50 % | K58: TRUE
B59: Notify | C59: Gerenciamento interno | D59: Mout´s Soluçõesem Tecnologia da Informação Ltda. | E59: 5.056.849/0001-08 | F59: 3748 | G59: 15668.26 | H59: 45602 | I59: Agênciamento de serviços de desenvovimento de software | J59: Total nota fiscal: R$ 31336,51. Rateio: 50 % | K59: TRUE
B60: Notify | C60: Gateway para IRIS V3 Essentials | D60: Amazon AWS Serviços Brasil Ltda | E60: 23.412.247/0001-10 | F60: 3584324_1DMEVBAE | G60: 17216.12 | H60: 45566 | I60: Custo da infraestrutura em nuvem | J60: Total nota fiscal: R$ 17216,12. Rateio: 100 % | K60: TRUE
B61: Notify | C61: Configuração Gateway para o IRIS V3 | D61: Materialize Serviços Digitais Ltda | E61: 34.269.716/0001-00 | F61: 202400000000880 | G61: 32040 | H61: 45603 | I61: Agênciamento de serviços de desenvovimento de software | J61: Total nota fiscal: R$ 32040. Rateio: 100 % | K61: TRUE
B62: Notify | C62: Gateway para IRIS V3 Essentials | D62: Mout´s Soluçõesem Tecnologia da Informação Ltda. | E62: 5.056.849/0001-08 | F62: 3665 | G62: 17235 | H62: 45573 | I62: Agênciamento de serviços de desenvovimento de software | J62: Total nota fiscal: R$ 34470. Rateio: 50 % | K62: TRUE
B63: Notify | C63: Gerenciamento interno | D63: Mout´s Soluçõesem Tecnologia da Informação Ltda. | E63: 5.056.849/0001-08 | F63: 3665 | G63: 17235 | H63: 45573 | I63: Agênciamento de serviços de desenvovimento de software | J63: Total nota fiscal: R$ 34470. Rateio: 50 % | K63: TRUE
B64: Notify | C64: Configuração Gateway para o IRIS V3 | D64: Amazon AWS Serviços Brasil Ltda | E64: 23.412.247/0001-10 | F64: 3689410_LLXIYFEF | G64: 18479.53 | H64: 45597 | I64: Custo da infraestrutura em nuvem | J64: Total nota fiscal: R$ 18479,53. Rateio: 100 % | K64: TRUE
B65: Notify | C65: Configuração Gateway para o IRIS V3 | D65: Materialize Serviços Digitais Ltda | E65: 34.269.716/0001-00 | F65: 202400000000901 | G65: 32040 | H65: 45629 | I65: Agênciamento de serviços de desenvovimento de software | J65: Total nota fiscal: R$ 32040. Rateio: 100 % | K65: TRUE
B66: Notify | C66: Configuração Gateway para o IRIS V3 | D66: Mout´s Soluçõesem Tecnologia da Informação Ltda. | E66: 5.056.849/0001-08 | F66: 3841 | G66: 15480 | H66: 45631 | I66: Agênciamento de serviços de desenvovimento de software | J66: Total nota fiscal: R$ 30960. Rateio: 50 % | K66: TRUE
B67: Notify | C67: Gerenciamento interno | D67: Mout´s Soluçõesem Tecnologia da Informação Ltda. | E67: 5.056.849/0001-08 | F67: 3841 | G67: 15480 | H67: 45631 | I67: Agênciamento de serviços de desenvovimento de software | J67: Total nota fiscal: R$ 30960. Rateio: 50 % | K67: TRUE
B68: Notify | C68: Configuração Gateway para o IRIS V3 | D68: Amazon AWS Serviços Brasil Ltda | E68: 23.412.247/0001-10 | F68: 3790213_FDP4MRWP | G68: 22299.43 | H68: 45627 | I68: Custo da infraestrutura em nuvem | J68: Total nota fiscal: R$ 22299,43. Rateio: 100 % | K68: TRUE

Sheet P&D_1
B2: Netzsch Moagem
B3: Pesquisa, Desenvolvimento & Inovação
B4: Formulário de PD&I - Ano 2024 | J4: Incentivado pela Lei do Bem | M4: FALSE
B5: - preencher somente os campos sombreados (cinza) e - adicionar cronograma no formato de imagem ao fim do formulário - preencher um deste para cada projeto de PD&I | J5: Objetiva tornar-se um Ativo | M5: FALSE
J6: Objetiva gerar patente/registro | M6: FALSE
B8: Dossiê do projeto
B9: Dados gerais para identificação e validação do projeto de PD&I
E10: ChocoFlow
B11: Nome do projeto | E11: Projeto 1 - Otimização da viscosidade do chocolate ao leite
J12: Pesquisa básica | M12: 📑
B13: Classificação do projeto | E13: Desenvolvimento experimental | J13: Pesquisa aplicada | M13: 📑
J14: Desenvolvimento experimental | M14: 📑
B15: Objetivos do projeto | E15: A partir do processo de fabricação da massa de chocolate desenvolvido pela Netzsch, reduzir a viscosidade e ponto de fluidez de um chocolate ao leite europeu sem adição de PGPR . O valor maximo de viscosidade deve ser 2,3Pas, valor do ponto de fluidez deve estar entre 10 a 20Pa e granulometria de 18 a 22µm
J16: Inovação tecnológica de produto | M16: 📑
B17: Tipo de inovação | E17: Inovação tecnológica de processo | J17: Inovação tecnológica de processo | M17: 📑
J18: Inovação tecnológica de serviços | M18: 📑
B19: Elemento inovador | E19: Processo de cristalização da lactose antes da etapa de conchagem a seco para liberação da gordura do leite que possibilita a redução da quantidade de manteiga de cacau (ingrediente de alto valor agregado) melhoria na reologia e sabor caracteristico de leite dos chocolates europeus. Inclusão da maquina Netzsch MasterCream Inline com ferramentas lisas após o processo de moagem para reduzir a viscosidade sem aumento consideravel no ponto de fluidez. Retenção de manteiga do processo para adição após o processo de moagem que possibilita a melhoria consideravel na reologia. | J19: - Não podem ser consideradas as inovações organizacionais, comerciais e de marketing
J20: Empresa ou segmento regional | M20: 📑
B21: Nível de inovação | E21: Inovador para o Mundo | J21: Inovador para o Brasil | M21: 📑
J22: Inovador para o Mundo | M22: 📑
B23: Risco tecnológico | E23: Não identificado
B25: Metodologias | E25: Realização de testes de fabricação de massa de chocolate ao leite no laboratório de food da Netzsch moagem em Pomerode. Coletar dados de reologia, umidade, granulometria e capacidade do processo. A partir dos dados coletados, ajustar parâmetros como potência, tamanho de esferas, quantidade de esferas, emulsificantes, tamanho de dente da ferramenta de pre moagem, temperatura, tempo de conchagem/cristalização da lactose, quantidade de água, quantidade de manteiga retida. Realizar ajuste de parâmetros para teste seguinte e coletar dados. Depois de realizar um teste com resultados efetivos, realizar teste de repetição e passar os parâmetros para a NFT para ser realizado na Alemanha.
B27: Equipe | E27: Nome Completo | F27: Cargo/Função | G27: Qualificação | H27: !
E28: Theron Wolfgang Harbs | F28: Consultor | G28: Graduação | H28: TRUE | L28: Técnico | M28: 📑
E29: Jivago Rusch | F29: Projetista Industrial | G29: Pós-graduação | H29: TRUE | L29: Graduação
H30: FALSE | L30: Pós-graduação
H31: FALSE | L31: Mestrado
H32: FALSE | L32: Doutorado
H33: FALSE
H34: FALSE
B36: Cronograma
B37: [anexar imagem - preferencialmente Gantt em pdf]

Sheet P&D_1 MILESTONES
B2: NETZSCH
B3: Pesquisa, Desenvolvimento & Inovação
B4: Formulário de PD&I - Ano 2024
B5: - preencher somente os campos sombreados (cinza)
B8: Dossiê do projeto | E8: Um objetivo a ser concluído durante esta etapa. Podemos ter vários em cada etapa. | G8: Uma data estimada que atualizará após etapa concluída
B9: Etapas e Milestones
B11: Projeto | C11: Etapa | D11: Principais atividades | E11: Milestones | F11: Data inicial | G11: Data conclusão | H11: Observações do gestor
B12: P&D_1 | C12: Adaptação para produto do mercado da NEM | D12: Replicar teste 9, receita similar mas sem lactose, utilizar PGPR, granulometria mais alta | E12: Produzir um produto que atenda o mercado do Brasil e America latina | F12: 45323 | G12: 45474

Sheet P&D_1 TIMESHEET
B2: NETZSCH
B3: Pesquisa, Desenvolvimento & Inovação
B4: Formulário de PD&I - Ano 2024
B5: - preencher somente os campos sombreados (cinza)
I6: Treinamento
I7: Pesquisa
B8: Dossiê do projeto | I8: Desenvolvimento
B9: Atividades de Pesquisa, Desenvolvimento e Inovação | I9: Gestão e outros
B11: RowID | C11: Projeto | D11: Etapa | E11: Colaborador | F11: CPF | G11: Data | H11: Tempo (h) | I11: Classificação | J11: Descrição da atividade e observações

Sheet P&D_1 TERCEIROS
B2: NETZSCH
B3: Pesquisa, Desenvolvimento & Inovação
B4: Formulário de PD&I - Ano 2024
B5: - preencher somente os campos sombreados (cinza)
B8: Dossiê do projeto
B9: Investimentos com terceiros
B11: Projeto | C11: Etapa | D11: Fornecedor | E11: CNPJ | F11: Nota fiscal | G11: Valor | H11: Data | I11: Descrição da Atividade | J11: Objetivo do gasto e eventual info de rateio | K11: Gasto incentiv.
K12: FALSE

Sheet P&D_2
A1: FALSE
B2: Netzsch Moagem
B3: Pesquisa, Desenvolvimento & Inovação
B4: Formulário de PD&I - Ano 2024 | J4: Incentivado pela Lei do Bem | M4: FALSE
B5: - preencher somente os campos sombreados (cinza) e - adicionar cronograma no formato de imagem ao fim do formulário - preencher um deste para cada projeto de PD&I | J5: Objetiva tornar-se um Ativo | M5: FALSE
J6: Objetiva gerar patente/registro | M6: FALSE
B8: Dossiê do projeto
B9: Dados gerais para identificação e validação do projeto de PD&I
E10: MasterCream Maximizer
B11: Nome do projeto | E11: Projeto 2 - Expansão das Aplicações do Equipamento MasterCream
J12: Pesquisa básica | M12: 📑
B13: Classificação do projeto | E13: Desenvolvimento experimental | J13: Pesquisa aplicada | M13: 📑
J14: Desenvolvimento experimental | M14: 📑
B15: Objetivos do projeto | E15: Desenvolver outros tamanhos e geometrias de dentes/estator, alvo: suspensão com alguns pedaços ou granulado como produto final. Melhorias no funil/tubo de alimentação e no eixo helicoidal, como feito no Mini MasterCream para produtos difíceis de alimentar. Desenvolver facas de pré-corte para produtos como amêndoas que são difíceis de moer, especialmente quando têm umidade de até 4%, como aplicado na Lübecker para MasterCream 20. Desenvolver altura ajustável de estator cônico para produtos em pedaços grandes. Melhorar a construção de acordo com o projeto higiênico para facilitar o trabalho com possível sistema CIP. Em conjunto com o projeto 1, desenvolver ferramentas com rotor/estator liso para reduzir a viscosidade após a moagem
J16: Inovação tecnológica de produto | M16: 📑
B17: Tipo de inovação | E17: Inovação tecnológica de produto | J17: Inovação tecnológica de processo | M17: 📑
J18: Inovação tecnológica de serviços | M18: 📑
B19: Elemento inovador | E19: Limpeza do sistema de moagem, conchagem e seus perifericos como tubulação, tanques de processo, bombas etc. aplicado a fabricação de chocolate e coberturas, com intuito de atingir um grau de limpeza que possibilite a troca de produto entre um lote e outro, por exemplo, a troca de um chocolate meio amargo para um chocolate branco ou um produto não vegano para um produto vegano. | J19: - Não podem ser consideradas as inovações organizacionais, comerciais e de marketing
J20: Empresa ou segmento regional | M20: 📑
B21: Nível de inovação | E21: Inovador para o Mundo | J21: Inovador para o Brasil | M21: 📑
J22: Inovador para o Mundo | M22: 📑
B23: Risco tecnológico | E23: Não identificado
B25: Metodologias | E25: 1 - Dentes maiores: a partir de 5 mm em anéis cilíndricos, incluindo estator cônico 2 - Avaliar um melhor esvaziamento do produto moído, menos por tubulação e mais por gravidade – queda livre 3 - Adicionar (como opcional) o rotor helicoidal central para melhor alimentação do funil, sem formação de ponte 4 - Acompanhe os resultados da configuração resistente ao desgaste – revestimentos ou materiais 5 - Adicionar (como opcional) a ferramenta de pré-corte grosso da faca, como feito no cliente Lübecker na Alemanha 6 - Adicionar a possibilidade de aumentar a distância entre o rotor cônico e o estator, até cerca de 10 mm, sem alterar a posição relativa dos anéis estáticos 7 - Verifique o design higiênico, materiais resistentes à corrosão e vedações 8 - Criar um banco de dados MasterCream com informações de vazão, potência, rotação, tamanho de partícula, etc. 9 - Melhoria MasterCream MINI. 10 - Rotor/estator cego para melhoria da viscosidade após o moinho
B27: Equipe | E27: Nome Completo | F27: Cargo/Função | G27: Qualificação | H27: !
E28: Alexandre Baseggio | F28: Consultor | G28: Graduação | L28: Técnico | M28: 📑
E29: Gabriel Alves Ferraz | F29: Projetista Industrial | G29: Pós-graduação | L29: Graduação
E30: Gabriel Oliveira | L30: Pós-graduação
E31: Guilherme Jacques | L31: Mestrado
E32: Italo Ebel | L32: Doutorado
E33: Ivo Ersching
E34: Johann Ribeiro
E35: Rafael Augusto Barbieri Lobato
E36: William Buttenberg
B41: Cronograma
B42: [anexar imagem - preferencialmente Gantt em pdf]

Sheet P&D_2 MILESTONES
B2: NETZSCH
B3: Pesquisa, Desenvolvimento & Inovação
B4: Formulário de PD&I - Ano 2024
B5: - preencher somente os campos sombreados (cinza)
B8: Dossiê do projeto | E8: Um objetivo a ser concluído durante esta etapa. Podemos ter vários em cada etapa. | G8: Uma data estimada que atualizará após etapa concluída
B9: Etapas e Milestones
B11: Projeto | C11: Etapa | D11: Principais atividades | E11: Milestones | F11: Data inicial | G11: Data conclusão | H11: Observações do gestor
B12: P&D_2 | C12: Outros tamanhos e geometrias de dentes das ferramentas, outros materiais | D12: Desenvolver ferramentas com dentes de 5mm para pastas com granulados; desenvolver ferramentas com materiais resistentes ao desgaste; redução da area de moagem do MCIL40, redução da capacidade de bombeamento do MCIL40 | E12: Produzir pastas com granulados de amendoim, alho, pimenta etc. Testar ferramentas de WC ZrO2 com açai e mostarda | F12: 45203 | G12: 45566
B13: P&D_2 | C13: Melhorias do MasterCream MINI | D13: Desenvolver novo rotor de moagem, acionamento com mais potencia, dispositivo para diferentes tamanhos de entrada de produto, tubo de imersão, valvula para limitação da area de descarga | E13: Possibilitar a operação continua com o funil afogado | F13: 45139 | G13: 45505
B14: P&D_2 | C14: Facas de pré-corte | D14: Desenvolver facas de pré-corte na entrada do MasterCream | E14: Cortar o produto com alto teor de umidade e possibilitar que o rotor superior faça a pré quebra | F14: 45198 | G14: 45564
B15: P&D_2 | C15: Altura ajustavel do estator conico | D15: Desenvolver dispositivo para ajuste da altura do estator conico | E15: Testar dispositivo com produtos dificies de moer | F15: 45444 | G15: 45627
B16: P&D_2 | C16: Eixo helicoidal para alimentação | D16: Desenvolver eixo helicoidal similar ao do MC-MINI para MC10, 20, 40 | E16: Otimizar alimentação vertical | F16: 45444 | G16: 45627
B17: P&D_2 | C17: Adequação conforme design higienico | D17: Desenvolver carcaça, conexão de entrada, conexão de saída, funil, vedações e ferramentas conforme design higienico | E17: Diminuir a quantidade de acumolo residual | F17: 45444 | G17: 45627
B18: P&D_2 | C18: Criar banco de dados de processo com informações de vazão, potencia, rotação e tamanho de particula para MasterCream | D18: Desenvolver planilha de scale up para os diferentes tamanhos de maquina para comparar os dados de processo | E18: Coletar os dados de processo do MCIL40 que está operando em cliene | F18: 45198 | G18: 45564
B19: P&D_2 | C19: Rotor liso para redução da viscosidade após a moagem | D19: Desenvolver ferramentas para MasterCream lisas | E19: Montar após o moinho e testar para verificar possivel redução da viscosidade | F19: 45167 | G19: 45533

Sheet P&D_2 TERCEIROS
B2: NETZSCH
B3: Pesquisa, Desenvolvimento & Inovação
B4: Formulário de PD&I - Ano 2024
B5: - preencher somente os campos sombreados (cinza)
B8: Dossiê do projeto
B9: Investimentos com terceiros
B11: Projeto | C11: Etapa | D11: Fornecedor | E11: CNPJ | F11: Nota fiscal | G11: Valor | H11: Data | I11: Descrição da Atividade | J11: Objetivo do gasto e eventual info de rateio | K11: Gasto incentiv.
B12: P&D_2 | C12: Melhorias do MasterCream MINI / Outros tamanhos e geometrias de dentes das ferramentas, outros materiais / Facas de pré-corte | G12: 1250 | H12: 45343 | I12: Material para teste de laboratorio | J12: Testes | K12: FALSE
B13: P&D_2 | C13: Melhorias do MasterCream MINI / Outros tamanhos e geometrias de dentes das ferramentas, outros materiais / Facas de pré-corte | G13: 349.84 | H13: 45343 | I13: Horas de laboratorio | J13: Testes | K13: FALSE
B14: P&D_2 | C14: Adequação conforme design higienico | G14: 17.1 | H14: 45343 | I14: Materia prima de fabricação mecanica | J14: Testes | K14: FALSE
B15: P&D_2 | C15: Adequação conforme design higienico | G15: 154.08 | H15: 45343 | I15: Usinagem interna | J15: Testes | K15: FALSE
B16: P&D_2 | C16: Adequação conforme design higienico | G16: 240 | H16: 45343 | I16: Usinagem interna | J16: Testes | K16: FALSE

Sheet P&D_2 TIMESHEET
B2: NETZSCH
B3: Pesquisa, Desenvolvimento & Inovação
B4: Formulário de PD&I - Ano 2024
B5: - preencher somente os campos sombreados (cinza)
I6: Treinamento
I7: Pesquisa
B8: Dossiê do projeto | I8: Desenvolvimento
B9: Atividades de Pesquisa, Desenvolvimento e Inovação | I9: Gestão e outros
B11: RowID | C11: Projeto | D11: Etapa | E11: Colaborador | F11: CPF | G11: Data | H11: Tempo (h) | I11: Classificação | J11: Descrição da atividade e observações
C12: P&D_2 | D12: Outros tamanhos e geometrias de dentes das ferramentas, outros materiais | E12: Jivago Rusch | G12: 45314 | H12: 16 | I12: Desenvolvimento | J12: Teste com ferramentas de 5mm com amendoim
C13: P&D_2 | D13: Ferramentas resistente ao desgaste | E13: Jivago Rusch | G13: 45338 | H13: 8 | I13: Desenvolvimento | J13: Modelamento de ferramenta com novo design progressivo para maior resistencia ao desgaste
C14: P&D_2 | D14: Melhorias do MasterCream MINI | E14: Jivago Rusch | G14: 45343 | H14: 40 | I14: Desenvolvimento | J14: Testes com novas ferramentas
C15: P&D_2 | D15: Rotor liso para redução da viscosidade após a moagem | E15: Jivago Rusch | G15: 45436 | H15: 40 | I15: Desenvolvimento | J15: Testes com rotor liso para redução da viscosidade do chocolate
C16: P&D_2 | D16: Adequação conforme design higienico | E16: Jivago Rusch | G16: 45468 | H16: 40 | I16: Desenvolvimento | J16: Desenho em corte do MC10 e MCIL10 com melhorias proposta conforme design higienico
C17: P&D_2 | D17: Adequações do MC10 conforme norma americana NFS ANSI 8 | E17: Jivago Rusch | G17: 45558 | H17: 40 | I17: Desenvolvimento | J17: Desenvolvimento do projeto do equipamento MC10 atendendo requisitos da norma do mercado de alimentos americana NFS ANSI 8 para certificar o equipamento e facilitar processos de limpeza CIP e garantir a segurança alimentar

Sheet P&D_3
B2: Netzsch Moagem
B3: Pesquisa, Desenvolvimento & Inovação
B4: Formulário de PD&I - Ano 2024 | J4: Incentivado pela Lei do Bem | M4: FALSE
B5: - preencher somente os campos sombreados (cinza) e - adicionar cronograma no formato de imagem ao fim do formulário - preencher um deste para cada projeto de PD&I | J5: Objetiva tornar-se um Ativo | M5: FALSE
J6: Objetiva gerar patente/registro | M6: FALSE
B8: Dossiê do projeto
B9: Dados gerais para identificação e validação do projeto de PD&I
B11: Nome do projeto | E11: Projeto 3 - Desenvolvimento de Processo de Limpeza CIP e SIP para linhas Food
J12: Pesquisa básica | M12: 📑
B13: Classificação do projeto | E13: Desenvolvimento experimental | J13: Pesquisa aplicada | M13: 📑
J14: Desenvolvimento experimental | M14: 📑
B15: Objetivos do projeto | E15: A NETZSCH é pioneira em CIP à base de óleo para máquinas de produção de confeitaria como Conch, Mixer, Bead Mill, em grande parte devido ao conceito de processo fechado O recurso CIP, bem como a configuração rápida com menor consumo de meios de limpeza, exigem design higiênico (HD) para que todos os componentes em contato com o produto sejam eficientes As diretrizes EHEDG (European Hygienic Engineering & Design Group), HACCP (Hazard Analysis Critical Control Point) e GMP (Good Manufacturing Practice), bem como a própria experiência, fornecem muitas recomendações valiosas para HD. Embora exista um conceito básico, ele ainda não foi aplicado a toda a linha de produção, consequentemente. Algumas ferramentas ainda não estão totalmente otimizadas, como os cabeçotes de limpeza, que permanecem dentro da máquina durante o processo, representando peças estáticas que acumulam resíduos e por isso necessitam de esforços extras para serem totalmente limpas. Outros equipamentos, como o Bead Mill MasterRefiner, possuem um conceito para HD que ainda precisa ser validado e posteriormente implementado pela Engenharia apoiada pela Equipe de P&D.
J16: Inovação tecnológica de produto | M16: 📑
B17: Tipo de inovação | E17: Inovação tecnológica de processo | J17: Inovação tecnológica de processo | M17: 📑
J18: Inovação tecnológica de serviços | M18: 📑
B19: Elemento inovador | E19: Limpeza do sistema de moagem, conchagem e seus perifericos como tubulação, tanques de processo, bombas etc. aplicado a fabricação de chocolate e coberturas, com intuito de atingir um grau de limpeza que possibilite a troca de produto entre um lote e outro, por exemplo, a troca de um chocolate meio amargo para um chocolate branco ou um produto não vegano para um produto vegano. | J19: - Não podem ser consideradas as inovações organizacionais, comerciais e de marketing
J20: Empresa ou segmento regional | M20: 📑
B21: Nível de inovação | E21: Inovador para o Mundo | J21: Inovador para o Brasil | M21: 📑
J22: Inovador para o Mundo | M22: 📑
B23: Risco tecnológico | E23: Não identificado
B25: Metodologias | E25: 1 - Especificar preliminarmente as etapas do sistema CIP para a planta Rumba/Salsa 300 do laboratório NEM. 2 - Configurar um sistema CIP preliminar para testar os cabeçotes de limpeza no MAC300 e coletar dados como vazão, temperatura, pressão e tempo. 3 - Verificar a quantidade de resíduo restante na concha e verificar os pontos mais críticos. 4 - Melhorar a construção de equipamentos, tubulações, válvulas, pontos de amostragem e conexões respeitando as diretrizes de projeto higiênico. 5 - Com a ajuda do engenheiro de alimentos, realizar análises microbiológicas para determinar o grau de limpeza alcançado. 6 - Especificar o grau de limpeza aceitável conforme normas para cada tipo de aplicação, por exemplo, trocando o produto de chocolate ao leite por chocolate branco ou produto não vegano para vegano. 7 - Desenvolver o sistema definitivo, descrevendo as etapas de cada aplicação e projeto de automação
B27: Equipe | E27: Nome Completo | F27: Cargo/Função | G27: Qualificação | H27: !
E28: Theron Wolfgang Harbs | F28: Consultor | G28: Graduação | L28: Técnico | M28: 📑
E29: Jivago Rusch | F29: Projetista Industrial | G29: Pós-graduação | L29: Graduação
E30: Fernando Leal | F30: Bolsista | G30: Doutorado | L30: Pós-graduação
L31: Mestrado
L32: Doutorado
B37: Cronograma
B38: [anexar imagem - preferencialmente Gantt em pdf]

Sheet P&D_3 MILESTONES
B2: NETZSCH
B3: Pesquisa, Desenvolvimento & Inovação
B4: Formulário de PD&I - Ano 2024
B5: - preencher somente os campos sombreados (cinza)
B8: Dossiê do projeto | E8: Um objetivo a ser concluído durante esta etapa. Podemos ter vários em cada etapa. | G8: Uma data estimada que atualizará após etapa concluída
B9: Etapas e Milestones
B11: Projeto | C11: Etapa | D11: Principais atividades | E11: Milestones | F11: Data inicial | G11: Data conclusão | H11: Observações do gestor
B12: P&D_3 | C12: MasterRefiner 30 Hygienic design | D12: Desenvolver peças para adequar o MR30 do laboratorio conforme design higienico | E12: Realizar teste de limpeza | F12: 45024 | G12: 45351
B13: P&D_3 | C13: Sistema de limpeza com água | D13: Desenvolver fluxo de limpeza para Rumba/Salsa 300 | E13: Testar cabeçotes Hydroclaw | F13: 45148 | G13: 45383
B14: P&D_3 | C14: Sistema de esvaziamento com ar comprimido | D14: Desenvolver sistema de pressurização para Moinho, tubulação e sistema de pre moagem | E14: Testar esvaziamento no moinho | F14: 45383 | G14: 45444
B15: P&D_3 | C15: Sistema de secagem com ar quente | D15: Adequar sistema de ar quente existente na concha para secagem do sistema completo | E15: Testar secagem do sistema | F15: 45383 | G15: 45444
B16: P&D_3 | C16: Sistema de secagem com vácuo | D16: Adequar sistema de vacuo existente no lab para secagem do sistema completo | E16: Testar secagem com vacuo no sistema | F16: 45383 | G16: 45444
B17: P&D_3 | C17: Adequação do laboratorio Rumba 300 para CIP/Design higienico | D17: Projetar tanques de processo, tubulação, bombas e valvulas conforme design higienico | E17: Realizar teste de CIP completo | F17: 45170 | G17: 45536
B18: P&D_3 | C18: Caracterização de nivel de residuos remanescentes | D18: Pesquisar normas/legislação brasileira, europeia e americana. Desenvolver metodo de analise de residuos | E18: Classificar grau de limpeza requerido para troca de produto | F18: 45268 | G18: 45536

Sheet P&D_3 TIMESHEET
B2: NETZSCH
B3: Pesquisa, Desenvolvimento & Inovação
B4: Formulário de PD&I - Ano 2024
B5: - preencher somente os campos sombreados (cinza)
I6: Treinamento
I7: Pesquisa
B8: Dossiê do projeto | I8: Desenvolvimento
B9: Atividades de Pesquisa, Desenvolvimento e Inovação | I9: Gestão e outros
B11: RowID | C11: Projeto | D11: Etapa | E11: Colaborador | F11: CPF | G11: Data | H11: Tempo (h) | I11: Classificação | J11: Descrição da atividade e observações
C12: P&D_3 | D12: Testes de limpeza e e secagem com linha Rumba sem tanques | E12: Jivago Rusch | G12: 45321 | H12: 8 | I12: Desenvolvimento | J12: Teste 3.5 - Chocolate ao leite
D13: Testes de limpeza e e secagem com linha Rumba sem tanques | E13: Fernando Leal | G13: 45321 | H13: 8 | I13: Desenvolvimento | J13: Teste 3.5 - Chocolate ao leite
C14: P&D_3 | D14: Testes de limpeza e e secagem com linha Rumba sem tanques | E14: Jivago Rusch | G14: 45334 | H14: 8 | I14: Desenvolvimento | J14: Teste 3.6 - Chocolate ao leite
D15: Testes de limpeza e e secagem com linha Rumba sem tanques | E15: Fernando Leal | G15: 45334 | H15: 8 | I15: Desenvolvimento | J15: Teste 3.6 - Chocolate ao leite
C16: P&D_3 | D16: Testes de limpeza e e secagem com linha Rumba sem tanques | E16: Jivago Rusch | G16: 45379 | H16: 8 | I16: Desenvolvimento | J16: Teste 3.7 - Compound
D17: Testes de limpeza e e secagem com linha Rumba sem tanques | E17: Fernando Leal | G17: 45379 | H17: 8 | I17: Desenvolvimento | J17: Teste 3.7 - Compound
C18: P&D_3 | D18: Testes de limpeza e e secagem com linha Rumba sem tanques | E18: Jivago Rusch | G18: 45391 | H18: 8 | I18: Desenvolvimento | J18: Teste 3.8 - Chocolate amargo
D19: Testes de limpeza e e secagem com linha Rumba sem tanques | E19: Fernando Leal | G19: 45391 | H19: 8 | I19: Desenvolvimento | J19: Teste 3.8 - Chocolate amargo
C20: P&D_3 | D20: Testes de limpeza e e secagem com linha Rumba sem tanques | E20: Jivago Rusch | G20: 45394 | H20: 8 | I20: Desenvolvimento | J20: Teste 3.9 - Chocolate ao leite - Cristalização da lactose
D21: Testes de limpeza e e secagem com linha Rumba sem tanques | E21: Fernando Leal | G21: 45394 | H21: 8 | I21: Desenvolvimento | J21: Teste 3.9 - Chocolate ao leite - Cristalização da lactose
C22: P&D_3 | D22: Testes de limpeza e e secagem com linha Rumba sem tanques | E22: Jivago Rusch | G22: 45411 | H22: 8 | I22: Desenvolvimento | J22: Teste 3.10 - Chocolate ao leite - Cristalização da lactose
D23: Testes de limpeza e e secagem com linha Rumba sem tanques | E23: Fernando Leal | G23: 45411 | H23: 8 | I23: Desenvolvimento | J23: Teste 3.10 - Chocolate ao leite - Cristalização da lactose
C24: P&D_3 | D24: Testes de limpeza e e secagem com linha Rumba sem tanques | E24: Jivago Rusch | G24: 45447 | H24: 8 | I24: Desenvolvimento | J24: Teste 3.11 - Chocolate branco
C25: P&D_3 | D25: Testes de limpeza e e secagem com linha Rumba sem tanques | E25: Jivago Rusch | G25: 45447 | H25: 8 | I25: Pesquisa | J25: Teste 3.11 - Chocolate branco
C26: P&D_3 | D26: Testes de limpeza e e secagem com linha Rumba sem tanques | E26: Fernando Leal | G26: 45447 | H26: 8 | I26: Pesquisa | J26: Teste 3.11 - Chocolate branco
C27: P&D_3 | D27: Testes de limpeza e e secagem com linha Rumba sem tanques | E27: Jivago Rusch | G27: 45489 | H27: 8 | I27: Pesquisa | J27: Teste 3.12 - Recheio com amendoim. Realizada analise de alergenicos para amendoim. Foi identificada a presença de alergenicos na tubulação, porem a analise não quantifica. Necessario desenvolver uma analise que quantifique em ppm.
C28: P&D_3 | D28: Testes de limpeza e e secagem com linha Rumba sem tanques | E28: Fernando Leal | G28: 45489 | H28: 8 | I28: Pesquisa | J28: Teste 3.12 - Recheio com amendoim. Realizada analise de alergenicos para amendoim. Foi identificada a presença de alergenicos na tubulação, porem a analise não quantifica. Necessario desenvolver uma analise que quantifique em ppm.
C30: P&D_3 | D30: Testes de limpeza e e secagem com linha Rumba sem tanques | E30: Jivago Rusch | G30: 45558 | H30: 8 | I30: Pesquisa | J30: Teste 3.14 - Recheio com amendoim 2%, realizada a limpeza e analise de alergenicos de amendoim, resultados abaixo de 2ppm.
C31: P&D_3 | D31: Testes de limpeza e e secagem com linha Rumba sem tanques | E31: Fernando Leal | G31: 45558 | H31: 8 | I31: Pesquisa | J31: Teste 3.14 - Recheio com amendoim 2%, realizada a limpeza e analise de alergenicos de amendoim, resultados abaixo de 2ppm.

Sheet P&D_3 TERCEIROS
B2: NETZSCH
B3: Pesquisa, Desenvolvimento & Inovação
B4: Formulário de PD&I - Ano 2024
B5: - preencher somente os campos sombreados (cinza)
B8: Dossiê do projeto
B9: Investimentos com terceiros
B11: Projeto | C11: Etapa | D11: Fornecedor | E11: CNPJ | F11: Nota fiscal | G11: Valor | H11: Data | I11: Descrição da Atividade | J11: Objetivo do gasto e eventual info de rateio | K11: Gasto incentiv.
B12: P&D_3 | C12: Adequação conforme design higienico | D12: IFM ELECTRONIC LTDA | E12: 02.263.430/0001-21 | G12: 1329.23 | H12: 45459 | I12: compra de PT-100 higienico | J12: Adequar conexoes de sensores de temperatura conforme design higienico | K12: TRUE
B13: P&D_3 | C13: Limpeza com água | G13: 8330.56 | H13: 45414 | I13: Material para teste de laboratorio | J13: Testes | K13: FALSE
B14: P&D_3 | C14: Limpeza com água | G14: 142.68 | H14: 45386 | I14: Peças complementares de equipamento | J14: Testes | K14: FALSE
B15: P&D_3 | C15: Limpeza com água | D15: LABOR FOOD LABORATORIO DE ANALISES | E15: 41.077.883/0001-15 | G15: 12711.1 | H15: 45448 | I15: Analise de alergenicos | J15: Analise de resultados dos testes | K15: TRUE
B16: P&D_3 | C16: Limpeza com água | D16: LABOR FOOD LABORATORIO DE ANALISES | E16: 41.077.883/0001-15 | G16: 3000 | H16: 45432 | I16: Analise de alergenicos | J16: Analise de resultados dos testes | K16: TRUE
B17: P&D_3 | C17: Limpeza com água | D17: LABORATORIO ALAC LTDA | E17: 94.088.952/0001-52 | G17: 2510.6 | H17: 45402 | I17: Analise de alergenicos | J17: Analise de resultados dos testes | K17: TRUE
B18: P&D_3 | C18: Limpeza com água | D18: LABORATORIO ALAC LTDA | E18: 94.088.952/0001-52 | G18: 2189.6 | H18: 45371 | I18: Analise de alergenicos | J18: Analise de resultados dos testes | K18: TRUE
B19: P&D_3 | C19: Adequação conforme design higienico | D19: SJV SERVICOS INDUSTRIAIS LTDA | E19: 39.724.206/0001-08 | G19: 361.01 | H19: 45459 | I19: Servico de soldagem | J19: Adaptar conexao MC10 conforme design higienico | K19: TRUE
B20: P&D_3 | C20: Adequação conforme design higienico | D20: JGW MECANICA INDUSTRIAL LTDA | E20: 07.564.023/0001-78 | G20: 1900 | H20: 45387 | I20: Servico de polimento de tubulação | J20: Redução da rugosidade da tubulação para melhor limpeza | K20: TRUE
B21: P&D_3 | C21: Limpeza com água | D21: LABOR FOOD LABORATORIO DE ANALISES | E21: 41.077.883/0001-15 | G21: 58.4 | H21: 45342 | I21: Analise de alergenicos | J21: Analise de resultados dos testes | K21: FALSE
B22: P&D_3 | C22: Teste 3.14 | D22: LABORATORIO ALAC LTDA | E22: 94.088.952/0001-52 | F22: NFS 115436 | G22: 2737 | H22: 45572 | I22: Analise de alergenicos | J22: Analise de resultados dos testes | K22: TRUE
B23: P&D_3 | C23: Teste 3.15 | D23: LABORATORIO ALAC LTDA | E23: 94.088.952/0001-52 | F23: NFS 63465 | G23: 25 | H23: 45589 | I23: Analise de alergenicos | J23: Analise de resultados dos testes | K23: TRUE
B24: P&D_3 | C24: Teste 3.15 | D24: LABOR FOOD LABORATORIO DE ANALISES | E24: 41.077.883/0001-15 | F24: NFS 10975 | G24: 80 | H24: 45600 | I24: Análise de diferença de cor em chocolate branco | J24: Análise de diferença de cor | K24: TRUE
B25: P&D_3 | C25: Teste 3.15 | D25: LABORATORIO ALAC LTDA | E25: 94.088.952/0001-52 | F25: NFS 116603 | G25: 2054.94 | H25: 45609 | I25: Analise de alergenicos | J25: Analise de resultados dos testes | K25: TRUE
B26: P&D_3 | C26: Teste 3.15 | D26: LABORATORIO ALAC LTDA | E26: 94.088.952/0001-52 | F26: NFS 116646 | G26: 547.4 | H26: 45610 | I26: Analise de alergenicos | J26: Analise de resultados dos testes | K26: TRUE
B27: P&D_3 | C27: Teste 3.15 | D27: LABOR FOOD LABORATORIO DE ANALISES | E27: 41.077.883/0001-15 | F27: NFS 11082 | G27: 240 | H27: 45618 | I27: Análise de diferença de cor em chocolate branco | J27: Análise de diferença de cor | K27: TRUE
B28: P&D_3 | C28: Teste 3.16 | D28: LABORATORIO ALAC LTDA | E28: 94.088.952/0001-52 | F28: NFS 63991 | G28: 50 | H28: 45622 | I28: Analise de alergenicos | J28: Analise de resultados dos testes | K28: TRUE
B29: P&D_3 | C29: Teste 3.18 | D29: LABORATORIO ALAC LTDA | E29: 94.088.952/0001-52 | F29: NFS 117178 | G29: 2054.94 | H29: 45630 | I29: Analise de alergenicos | J29: Analise de resultados dos testes | K29: TRUE
B30: P&D_3 | C30: Teste 3.18 | D30: LABORATORIO ALAC LTDA | E30: 94.088.952/0001-52 | F30: NFS 117319 | G30: 3298.2 | H30: 45636 | I30: Analise de alergenicos em produto final | J30: Verificação de residual de alergênicos em chocolate | K30: TRUE

Sheet # CPRBINSS
B1: Empregados | C1: Cont. Inviduais | D1: INSS empresa | E1: % Patronal | F1: % Patronal efetivo | G1: Faturamento 2,5%
