Workbook

Sheet Resumo
B1: PRODIET NUTRIÇÃO
B2: INOVAÇÃO TECNOLÓGICA 2013
B3: Resumo de investimentos
C6: Natureza | D6: 1 TRIM | E6: 2 TRIM | F6: 3 TRIM | G6: 4 TRIM | H6: TOTAL
C7: Material | D7: =SUMIFS(Investimentos!$P$6:$P$100,Investimentos!$L$6:$L$100,Resumo!D$6,Investimentos!$I$6:$I$100,Resumo!$C7) -> 770 | E7: =SUMIFS(Investimentos!$P$6:$P$100,Investimentos!$L$6:$L$100,Resumo!E$6,Investimentos!$I$6:$I$100,Resumo!$C7) -> 9355.14 | F7: =SUMIFS(Investimentos!$P$6:$P$100,Investimentos!$L$6:$L$100,Resumo!F$6,Investimentos!$I$6:$I$100,Resumo!$C7) -> 2985.55 | G7: =SUMIFS(Investimentos!$P$6:$P$100,Investimentos!$L$6:$L$100,Resumo!G$6,Investimentos!$I$6:$I$100,Resumo!$C7) -> 1711.48 | H7: =SUM(D7:G7) -> 14822.17
C8: RH (Parcial inovação) | D8: =SUMIFS(Investimentos!$P$6:$P$100,Investimentos!$L$6:$L$100,Resumo!D$6,Investimentos!$I$6:$I$100,Resumo!$C8) -> 116.46973 | E8: =SUMIFS(Investimentos!$P$6:$P$100,Investimentos!$L$6:$L$100,Resumo!E$6,Investimentos!$I$6:$I$100,Resumo!$C8) -> 77.935973 | F8: =SUMIFS(Investimentos!$P$6:$P$100,Investimentos!$L$6:$L$100,Resumo!F$6,Investimentos!$I$6:$I$100,Resumo!$C8) -> 1585.104 | G8: =SUMIFS(Investimentos!$P$6:$P$100,Investimentos!$L$6:$L$100,Resumo!G$6,Investimentos!$I$6:$I$100,Resumo!$C8) -> 128.85048 | H8: =SUM(D8:G8) -> 1908.3602
C9: RH (Exclusivo inovação) | D9: =SUMIFS('Salário e Custo Hora'!$E$20:$P$20,'Salário e Custo Hora'!$E$18:$P$18,Resumo!D6) -> 14449.653 | E9: =SUMIFS('Salário e Custo Hora'!$E$20:$P$20,'Salário e Custo Hora'!$E$18:$P$18,Resumo!E6) -> 14449.653 | F9: =SUMIFS('Salário e Custo Hora'!$E$20:$P$20,'Salário e Custo Hora'!$E$18:$P$18,Resumo!F6) -> 15605.633 | G9: =SUMIFS('Salário e Custo Hora'!$E$20:$P$20,'Salário e Custo Hora'!$E$18:$P$18,Resumo!G6) -> 15605.633 | H9: =SUM(D9:G9) -> 60110.573
C10: Terceiros | D10: =SUMIFS(Investimentos!$P$6:$P$100,Investimentos!$L$6:$L$100,Resumo!D$6,Investimentos!$I$6:$I$100,Resumo!$C10)+SUMIFS(Terceiros!$H$6:$H$24,Terceiros!$E$6:$E$24,Resumo!D6) -> 21361.446 | E10: =SUMIFS(Investimentos!$P$6:$P$100,Investimentos!$L$6:$L$100,Resumo!E$6,Investimentos!$I$6:$I$100,Resumo!$C10)+SUMIFS(Terceiros!$H$6:$H$24,Terceiros!$E$6:$E$24,Resumo!E6) -> 23662.446 | F10: =SUMIFS(Investimentos!$P$6:$P$100,Investimentos!$L$6:$L$100,Resumo!F$6,Investimentos!$I$6:$I$100,Resumo!$C10)+SUMIFS(Terceiros!$H$6:$H$24,Terceiros!$E$6:$E$24,Resumo!F6) -> 30064.706 | G10: =SUMIFS(Investimentos!$P$6:$P$100,Investimentos!$L$6:$L$100,Resumo!G$6,Investimentos!$I$6:$I$100,Resumo!$C10)+SUMIFS(Terceiros!$H$6:$H$24,Terceiros!$E$6:$E$24,Resumo!G6) -> 32570.748 | H10: =SUM(D10:G10) -> 107659.35
C11: Total | D11: =SUM(D7:D10) -> 36697.569 | E11: =SUM(E7:E10) -> 47545.175 | F11: =SUM(F7:F10) -> 50240.993 | G11: =SUM(G7:G10) -> 50016.712 | H11: =SUM(D11:G11) -> 184500.45
C12: Percentual Exclusão | D12: 0.6 | E12: 0.6 | F12: 0.6 | G12: 0.6 | H12: 0.6
C13: Benefício Máximo | D13: =D11*D12 -> 22018.541 | E13: =E11*E12 -> 28527.105 | F13: =F11*F12 -> 30144.596 | G13: =G11*G12 -> 30010.027 | H13: =SUM(D13:G13) -> 110700.27
H14: =SUM(D14:G14) -> 0
C15: Exclusão Base de Cálculo | D15: =D27 -> -22018.541 | E15: =E27 -> -28527.105 | F15: =F27 -> -30144.596 | G15: =G27 -> 0 | H15: =SUM(D15:G15) -> -80690.242
C16: IRPJ e CSLL antes Inovação | D16: 76208.98 | E16: 81372.76 | F16: 67785.78 | G16: 0 | H16: =SUM(D16:G16) -> 225367.52 | I16: (a)
C17: IRPJ e CSLL com inovação | D17: 71061.04 | E17: 74703.12 | F17: 60737.97 | G17: =G36 -> 0 | H17: =SUM(D17:G17) -> 206502.13 | I17: (b)
C18: Benefício Líquido | D18: =D16-D17 -> 5147.94 | E18: =E16-E17 -> 6669.64 | F18: =F16-F17 -> 7047.81 | G18: =G16-G17 -> 0 | H18: =SUM(D18:G18) -> 18865.39
C19: Honorário McBenner (10%) | D19: =10%*D18 -> 514.794 | E19: =10%*E18 -> 666.964 | F19: =10%*F18 -> 704.781 | G19: =10%*G18 -> 0 | H19: =SUM(D19:G19) -> 1886.539
A21: (b) | B21: Detalhamento da Apuração com exclusão de inovação
C23: Lucro do Período | D23: 380951.9 | E23: 558509.81 | F23: 666480.89 | G23: -166565.98
C24: (+) Total das Adições | D24: 23073.44 | E24: 416065.06 | F24: 614826.51 | G24: 695465.73
C25: (-) Total das Exclusões antes da inovação | D25: -52404.397 | E25: -600867.59 | F25: -965713.83 | G25: -835761.48
C26: (=) Lucro Real antes da Exclusão da Inovação | D26: =SUM(D23:D25) -> 351620.94 | E26: =SUM(E23:E25) -> 373707.28 | F26: =SUM(F23:F25) -> 315593.57 | G26: =SUM(G23:G25) -> -306861.73
C27: (-) Exclusão da Inovação | D27: =-IF(D26>0,MIN(D13,D26),0) -> -22018.541 | E27: =-IF(E26>0,MIN(E13,E26),0) -> -28527.105 | F27: =-IF(F26>0,MIN(F13,F26),0) -> -30144.596 | G27: =IF(G26>0,MIN(G13,G26),0) -> 0
C28: (=) Lucro antes da compensção do prejuízo | D28: =IF(D26>0,D26+D27,0) -> 329602.4 | E28: =IF(E26>0,E26+E27,0) -> 345180.17 | F28: =IF(F26>0,F26+F27,0) -> 285448.97 | G28: =IF(G26>0,G26-G27,0) -> 0
C29: (-) Compensação de Prejuízo | D29: =-D28*30% -> -98880.721 | E29: =-E28*30% -> -103554.05 | F29: =-F28*30% -> -85634.692 | G29: =-G28*30% -> 0
C30: (=) Base de cálculo do IRPJ | D30: =SUM(D28:D29) -> 230721.68 | E30: =SUM(E28:E29) -> 241626.12 | F30: =SUM(F28:F29) -> 199814.28 | G30: =G28-G29 -> 0
C31: IRPJ (15%) | D31: =D30*15% -> 34608.252 | E31: =E30*15% -> 36243.918 | F31: =F30*15% -> 29972.142 | G31: =G30*15% -> 0
C32: Adicional IR (10%) | D32: =IF(D30>60000,(D30-60000)*10%,0) -> 17072.168 | E32: =IF(E30>60000,(E30-60000)*10%,0) -> 18162.612 | F32: =IF(F30>60000,(F30-60000)*10%,0) -> 13981.428 | G32: =IF(G30>60000,(G30-60000)*10%,0) -> 0
C33: (-) PAT | D33: =-D31*4% -> -1384.3301 | E33: =-E31*4% -> -1449.7567 | F33: =-F31*4% -> -1198.8857 | G33: =-G32*4% -> 0
C34: Total de IRPJ a pagar | D34: =SUM(D31:D33) -> 50296.09 | E34: =SUM(E31:E33) -> 52956.774 | F34: =SUM(F31:F33) -> 42754.684 | G34: =SUM(G31:G33) -> 0
C35: CSLL (9%) | D35: =D30*9% -> 20764.951 | E35: =E30*9% -> 21746.351 | F35: =F30*9% -> 17983.285 | G35: =G30*9% -> 0
C36: (=) Total de IRPJ/CSLL a pagar | D36: =SUM(D34:D35) -> 71061.042 | E36: =SUM(E34:E35) -> 74703.125 | F36: =SUM(F34:F35) -> 60737.97 | G36: =SUM(G34:G35) -> 0
A39: (a) | B39: Detalhamento da Apuração sem exclusão de inovação
C41: Lucro do Período | D41: 380951.9 | E41: 558509.81 | F41: 666480.89 | G41: -166565.98
C42: (+) Total das Adições | D42: 23073.44 | E42: 416065.06 | F42: 614826.51 | G42: 695465.73
C43: (-) Total das Exclusões antes da inovação | D43: -52404.397 | E43: -600867.59 | F43: -965713.83 | G43: -835761.48
C44: (=) Lucro Real antes da Exclusão da Inovação | D44: =SUM(D41:D43) -> 351620.94 | E44: =SUM(E41:E43) -> 373707.28 | F44: =SUM(F41:F43) -> 315593.57 | G44: =SUM(G41:G43) -> -306861.73
C45: (-) Exclusão da Inovação | D45: 0 | E45: 0 | F45: 0 | G45: =IF(G44>0,MIN(G31,G44),0) -> 0
C46: (=) Lucro antes da compensção do prejuízo | D46: =IF(D44>0,D44+D45,0) -> 351620.94 | E46: =IF(E44>0,E44+E45,0) -> 373707.28 | F46: =IF(F44>0,F44+F45,0) -> 315593.57 | G46: =IF(G44>0,G44-G45,0) -> 0
C47: (-) Compensação de Prejuízo | D47: =-D46*30% -> -105486.28 | E47: =-E46*30% -> -112112.18 | F47: =-F46*30% -> -94678.07 | G47: =-G46*30% -> 0
C48: (=) Base de cálculo do IRPJ | D48: =SUM(D46:D47) -> 246134.66 | E48: =SUM(E46:E47) -> 261595.1 | F48: =SUM(F46:F47) -> 220915.5 | G48: =G46-G47 -> 0
C49: IRPJ (15%) | D49: =D48*15% -> 36920.199 | E49: =E48*15% -> 39239.264 | F49: =F48*15% -> 33137.325 | G49: =G48*15% -> 0
C50: Adicional IR (10%) | D50: =IF(D48>60000,(D48-60000)*10%,0) -> 18613.466 | E50: =IF(E48>60000,(E48-60000)*10%,0) -> 20159.51 | F50: =IF(F48>60000,(F48-60000)*10%,0) -> 16091.55 | G50: =IF(G48>60000,(G48-60000)*10%,0) -> 0
C51: (-) PAT | D51: =-D49*4% -> -1476.808 | E51: =-E49*4% -> -1569.5706 | F51: =-F49*4% -> -1325.493 | G51: =-G50*4% -> 0
C52: Total de IRPJ a pagar | D52: =SUM(D49:D51) -> 54056.857 | E52: =SUM(E49:E51) -> 57829.203 | F52: =SUM(F49:F51) -> 47903.381 | G52: =SUM(G49:G51) -> 0
C53: CSLL (9%) | D53: =D48*9% -> 22152.119 | E53: =E48*9% -> 23543.559 | F53: =F48*9% -> 19882.395 | G53: =G48*9% -> 0
C54: (=) Total de IRPJ/CSLL a pagar | D54: =SUM(D52:D53) -> 76208.977 | E54: =SUM(E52:E53) -> 81372.762 | F54: =SUM(F52:F53) -> 67785.776 | G54: =SUM(G52:G53) -> 0

Sheet Investimentos
C1: PRODIET NUTRIÇÃO
C2: INOVAÇÃO TECNOLÓGICA 2013
C3: Investimentos
P4: =SUBTOTAL(9,P6:P100) -> 38182.3 | Q4: S
B5: Documento | C5: PROJETO | D5: SUB PROJETO | E5: PRODUTO | F5: RECURSO | G5: ESCOLARIDADE | H5: ATIVIDADE | I5: NATUREZA | J5: DATA | K5: Mês | L5: Trimestre | M5: MEDIDA | N5: QTD | O5: UNITÁRIO | P5: TOTAL
B6: 4 | C6: Melhoria de produto | D6: Embalagem | F6: Prodiet | H6: Compra de produto concorrente para análise: NUTRISON SOYA 800 gr | I6: Material | J6: 41419 | K6: =MONTH(J6) -> 5 | L6: =IF(K6<=3,"1 TRIM",IF(K6<=6,"2 TRIM",IF(K6<=9,"3 TRIM","4 TRIM"))) -> 2 TRIM | M6: Unidade | N6: 1 | O6: 52.29 | P6: =N6*O6 -> 52.29
B7: 4 | C7: Melhoria de produto | D7: Embalagem | F7: Prodiet | H7: Compra de produto concorrente para análise: NUTREN 1 O 400gr | I7: Material | J7: 41419 | K7: =MONTH(J7) -> 5 | L7: =IF(K7<=3,"1 TRIM",IF(K7<=6,"2 TRIM",IF(K7<=9,"3 TRIM","4 TRIM"))) -> 2 TRIM | M7: Unidade | N7: 1 | O7: 48.15 | P7: =IF(C7="",0,O7*N7) -> 48.15
B8: 3 | C8: Melhoria de produto | D8: Embalagem | F8: Prodiet | H8: Compra de produto concorrente para análise: NUTRISON SOYA 800 gr | I8: Material | J8: 41402 | K8: =MONTH(J8) -> 5 | L8: =IF(K8<=3,"1 TRIM",IF(K8<=6,"2 TRIM",IF(K8<=9,"3 TRIM","4 TRIM"))) -> 2 TRIM | M8: Unidade | N8: 1 | O8: 52.29 | P8: =N8*O8 -> 52.29
B9: 3 | C9: Melhoria de produto | D9: Embalagem | F9: Prodiet | H9: Compra de produto concorrente para análise: NUTRI ENTERAL SOYA 800gr | I9: Material | J9: 41402 | K9: =MONTH(J9) -> 5 | L9: =IF(K9<=3,"1 TRIM",IF(K9<=6,"2 TRIM",IF(K9<=9,"3 TRIM","4 TRIM"))) -> 2 TRIM | M9: Unidade | N9: 1 | O9: 65 | P9: =IF(C9="",0,O9*N9) -> 65
B10: 3 | C10: Melhoria de produto | D10: Embalagem | F10: Prodiet | H10: Compra de produto concorrente para análise: NUTREN 1 O 400gr | I10: Material | J10: 41402 | K10: =MONTH(J10) -> 5 | L10: =IF(K10<=3,"1 TRIM",IF(K10<=6,"2 TRIM",IF(K10<=9,"3 TRIM","4 TRIM"))) -> 2 TRIM | M10: Unidade | N10: 1 | O10: 48.15 | P10: =IF(C10="",0,O10*N10) -> 48.15
B11: 5 | C11: Melhoria de produto | D11: Embalagem | F11: Prodiet | H11: Compra de livro no Instituto de Tecnologia de Alimentos para estudo | I11: Material | J11: 41513 | K11: =MONTH(J11) -> 8 | L11: =IF(K11<=3,"1 TRIM",IF(K11<=6,"2 TRIM",IF(K11<=9,"3 TRIM","4 TRIM"))) -> 3 TRIM | M11: Unidade | N11: 1 | O11: 120 | P11: =IF(C11="",0,O11*N11) -> 120
B12: 84 | C12: Novo Copack | D12: Produto Líquido | E12: Petit Max | F12: Larissa Suellen da Silva | G12: =VLOOKUP(F12,'Salário e Custo Hora'!$B$48:$C$52,2,FALSE) -> Graduado | H12: Teste de administração por sonda do produto | I12: RH (Parcial inovação) | J12: 41309 | K12: =MONTH(J12) -> 2 | L12: =IF(K12<=3,"1 TRIM",IF(K12<=6,"2 TRIM",IF(K12<=9,"3 TRIM","4 TRIM"))) -> 1 TRIM | M12: Hora | N12: =5/60 -> 0.083333333 | O12: =IF(ISNA(VLOOKUP($F12,'Salário e Custo Hora'!$B$28:$P$32,3+Investimentos!$K12,FALSE)),0,VLOOKUP($F12,'Salário e Custo Hora'!$B$28:$P$32,3+Investimentos!$K12,FALSE)) -> 16.838996 | P12: =IF(C12="",0,O12*N12) -> 1.4032497
B13: 84 | C13: Melhoria de produto | E13: Trophic Bio | F13: Larissa Suellen da Silva | G13: =VLOOKUP(F13,'Salário e Custo Hora'!$B$48:$C$52,2,FALSE) -> Graduado | H13: Teste de administração por sonda do produto | I13: RH (Parcial inovação) | J13: 41309 | K13: =MONTH(J13) -> 2 | L13: =IF(K13<=3,"1 TRIM",IF(K13<=6,"2 TRIM",IF(K13<=9,"3 TRIM","4 TRIM"))) -> 1 TRIM | M13: Hora | N13: =5/60 -> 0.083333333 | O13: =IF(ISNA(VLOOKUP($F13,'Salário e Custo Hora'!$B$28:$P$32,3+Investimentos!$K13,FALSE)),0,VLOOKUP($F13,'Salário e Custo Hora'!$B$28:$P$32,3+Investimentos!$K13,FALSE)) -> 16.838996 | P13: =IF(C13="",0,O13*N13) -> 1.4032497
B14: 84 | C14: Novo Copack | D14: Produto Líquido | E14: Trophic Basic - Castrolanda | F14: Larissa Suellen da Silva | G14: =VLOOKUP(F14,'Salário e Custo Hora'!$B$48:$C$52,2,FALSE) -> Graduado | H14: Teste de administração por sonda do produto | I14: RH (Parcial inovação) | J14: 41323 | K14: =MONTH(J14) -> 2 | L14: =IF(K14<=3,"1 TRIM",IF(K14<=6,"2 TRIM",IF(K14<=9,"3 TRIM","4 TRIM"))) -> 1 TRIM | M14: Hora | N14: 3 | O14: =IF(ISNA(VLOOKUP($F14,'Salário e Custo Hora'!$B$28:$P$32,3+Investimentos!$K14,FALSE)),0,VLOOKUP($F14,'Salário e Custo Hora'!$B$28:$P$32,3+Investimentos!$K14,FALSE)) -> 16.838996 | P14: =IF(C14="",0,O14*N14) -> 50.516989
B15: 84 | C15: Melhoria de produto | E15: Trophic Basic - PIS | F15: Larissa Suellen da Silva | G15: =VLOOKUP(F15,'Salário e Custo Hora'!$B$48:$C$52,2,FALSE) -> Graduado | H15: Teste de administração por sonda do produto | I15: RH (Parcial inovação) | J15: 41325 | K15: =MONTH(J15) -> 2 | L15: =IF(K15<=3,"1 TRIM",IF(K15<=6,"2 TRIM",IF(K15<=9,"3 TRIM","4 TRIM"))) -> 1 TRIM | M15: Hora | N15: =40/60 -> 0.66666667 | O15: =IF(ISNA(VLOOKUP($F15,'Salário e Custo Hora'!$B$28:$P$32,3+Investimentos!$K15,FALSE)),0,VLOOKUP($F15,'Salário e Custo Hora'!$B$28:$P$32,3+Investimentos!$K15,FALSE)) -> 16.838996 | P15: =IF(C15="",0,O15*N15) -> 11.225998
B16: 84 | C16: Novo Copack | D16: Produto Líquido | E16: Trophic Basic - Castrolanda | F16: Larissa Suellen da Silva | G16: =VLOOKUP(F16,'Salário e Custo Hora'!$B$48:$C$52,2,FALSE) -> Graduado | H16: Controle em Shelf Life | I16: RH (Parcial inovação) | J16: 41332 | K16: =MONTH(J16) -> 2 | L16: =IF(K16<=3,"1 TRIM",IF(K16<=6,"2 TRIM",IF(K16<=9,"3 TRIM","4 TRIM"))) -> 1 TRIM | M16: Hora | N16: =75/60 -> 1.25 | O16: =IF(ISNA(VLOOKUP($F16,'Salário e Custo Hora'!$B$28:$P$32,3+Investimentos!$K16,FALSE)),0,VLOOKUP($F16,'Salário e Custo Hora'!$B$28:$P$32,3+Investimentos!$K16,FALSE)) -> 16.838996 | P16: =IF(C16="",0,O16*N16) -> 21.048746
B17: 84 | C17: Melhoria de produto | E17: Trophic Soya | F17: Larissa Suellen da Silva | G17: =VLOOKUP(F17,'Salário e Custo Hora'!$B$48:$C$52,2,FALSE) -> Graduado | H17: Controle em Shelf Life | I17: RH (Parcial inovação) | J17: 41360 | K17: =MONTH(J17) -> 3 | L17: =IF(K17<=3,"1 TRIM",IF(K17<=6,"2 TRIM",IF(K17<=9,"3 TRIM","4 TRIM"))) -> 1 TRIM | M17: Hora | N17: =65/60 -> 1.0833333 | O17: =IF(ISNA(VLOOKUP($F17,'Salário e Custo Hora'!$B$28:$P$32,3+Investimentos!$K17,FALSE)),0,VLOOKUP($F17,'Salário e Custo Hora'!$B$28:$P$32,3+Investimentos!$K17,FALSE)) -> 16.838996 | P17: =IF(C17="",0,O17*N17) -> 18.242246
B18: 84 | C18: Melhoria de produto | E18: Trophic Basic - Caseinato Ca CC902i | F18: Larissa Suellen da Silva | G18: =VLOOKUP(F18,'Salário e Custo Hora'!$B$48:$C$52,2,FALSE) -> Graduado | H18: Teste de administração por sonda do produto | I18: RH (Parcial inovação) | J18: 41339 | K18: =MONTH(J18) -> 3 | L18: =IF(K18<=3,"1 TRIM",IF(K18<=6,"2 TRIM",IF(K18<=9,"3 TRIM","4 TRIM"))) -> 1 TRIM | M18: Hora | N18: =40/60 -> 0.66666667 | O18: =IF(ISNA(VLOOKUP($F18,'Salário e Custo Hora'!$B$28:$P$32,3+Investimentos!$K18,FALSE)),0,VLOOKUP($F18,'Salário e Custo Hora'!$B$28:$P$32,3+Investimentos!$K18,FALSE)) -> 16.838996 | P18: =IF(C18="",0,O18*N18) -> 11.225998
B19: 84 | C19: Melhoria de produto | E19: Trophic Fiber - Fibrim 1270 | F19: Larissa Suellen da Silva | G19: =VLOOKUP(F19,'Salário e Custo Hora'!$B$48:$C$52,2,FALSE) -> Graduado | H19: Controle em Shelf Life | I19: RH (Parcial inovação) | J19: 41360 | K19: =MONTH(J19) -> 3 | L19: =IF(K19<=3,"1 TRIM",IF(K19<=6,"2 TRIM",IF(K19<=9,"3 TRIM","4 TRIM"))) -> 1 TRIM | M19: Hora | N19: =5/60 -> 0.083333333 | O19: =IF(ISNA(VLOOKUP($F19,'Salário e Custo Hora'!$B$28:$P$32,3+Investimentos!$K19,FALSE)),0,VLOOKUP($F19,'Salário e Custo Hora'!$B$28:$P$32,3+Investimentos!$K19,FALSE)) -> 16.838996 | P19: =IF(C19="",0,O19*N19) -> 1.4032497
B20: 84 | C20: Novo Copack | D20: Produto Líquido | E20: Trophic Basic-Castrolanda | F20: Larissa Suellen da Silva | G20: =VLOOKUP(F20,'Salário e Custo Hora'!$B$48:$C$52,2,FALSE) -> Graduado | H20: Controle em Shelf Life | I20: RH (Parcial inovação) | J20: 41419 | K20: =MONTH(J20) -> 5 | L20: =IF(K20<=3,"1 TRIM",IF(K20<=6,"2 TRIM",IF(K20<=9,"3 TRIM","4 TRIM"))) -> 2 TRIM | M20: Hora | N20: =15/60 -> 0.25 | O20: =IF(ISNA(VLOOKUP($F20,'Salário e Custo Hora'!$B$28:$P$32,3+Investimentos!$K20,FALSE)),0,VLOOKUP($F20,'Salário e Custo Hora'!$B$28:$P$32,3+Investimentos!$K20,FALSE)) -> 16.037139 | P20: =IF(C20="",0,O20*N20) -> 4.0092849
B21: 84 | C21: Melhoria de produto | E21: Trophic Soya | F21: Larissa Suellen da Silva | G21: =VLOOKUP(F21,'Salário e Custo Hora'!$B$48:$C$52,2,FALSE) -> Graduado | H21: Controle em Shelf Life | I21: RH (Parcial inovação) | J21: 41452 | K21: =MONTH(J21) -> 6 | L21: =IF(K21<=3,"1 TRIM",IF(K21<=6,"2 TRIM",IF(K21<=9,"3 TRIM","4 TRIM"))) -> 2 TRIM | M21: Hora | N21: =15/60 -> 0.25 | O21: =IF(ISNA(VLOOKUP($F21,'Salário e Custo Hora'!$B$28:$P$32,3+Investimentos!$K21,FALSE)),0,VLOOKUP($F21,'Salário e Custo Hora'!$B$28:$P$32,3+Investimentos!$K21,FALSE)) -> 16.838996 | P21: =IF(C21="",0,O21*N21) -> 4.2097491
B22: 84 | C22: Melhoria de produto | E22: Trophic Fiber - Fibrim 1270 | F22: Larissa Suellen da Silva | G22: =VLOOKUP(F22,'Salário e Custo Hora'!$B$48:$C$52,2,FALSE) -> Graduado | H22: Controle em Shelf Life | I22: RH (Parcial inovação) | J22: 41452 | K22: =MONTH(J22) -> 6 | L22: =IF(K22<=3,"1 TRIM",IF(K22<=6,"2 TRIM",IF(K22<=9,"3 TRIM","4 TRIM"))) -> 2 TRIM | M22: Hora | N22: =5/60 -> 0.083333333 | O22: =IF(ISNA(VLOOKUP($F22,'Salário e Custo Hora'!$B$28:$P$32,3+Investimentos!$K22,FALSE)),0,VLOOKUP($F22,'Salário e Custo Hora'!$B$28:$P$32,3+Investimentos!$K22,FALSE)) -> 16.838996 | P22: =IF(C22="",0,O22*N22) -> 1.4032497
B23: 84 | C23: Melhoria de produto | D23: Estabilidade | E23: Trophic Basic | F23: Larissa Suellen da Silva | G23: =VLOOKUP(F23,'Salário e Custo Hora'!$B$48:$C$52,2,FALSE) -> Graduado | H23: Teste de estabilidade | I23: RH (Parcial inovação) | J23: 41465 | K23: =MONTH(J23) -> 7 | L23: =IF(K23<=3,"1 TRIM",IF(K23<=6,"2 TRIM",IF(K23<=9,"3 TRIM","4 TRIM"))) -> 3 TRIM | M23: Hora | N23: 3 | O23: =IF(ISNA(VLOOKUP($F23,'Salário e Custo Hora'!$B$28:$P$32,3+Investimentos!$K23,FALSE)),0,VLOOKUP($F23,'Salário e Custo Hora'!$B$28:$P$32,3+Investimentos!$K23,FALSE)) -> 14.642606 | P23: =IF(C23="",0,O23*N23) -> 43.927817
B24: 84 | C24: Melhoria de produto | D24: Estabilidade | E24: Trophic EP | F24: Larissa Suellen da Silva | G24: =VLOOKUP(F24,'Salário e Custo Hora'!$B$48:$C$52,2,FALSE) -> Graduado | H24: Teste de estabilidade | I24: RH (Parcial inovação) | J24: 41465 | K24: =MONTH(J24) -> 7 | L24: =IF(K24<=3,"1 TRIM",IF(K24<=6,"2 TRIM",IF(K24<=9,"3 TRIM","4 TRIM"))) -> 3 TRIM | M24: Hora | N24: 3 | O24: =IF(ISNA(VLOOKUP($F24,'Salário e Custo Hora'!$B$28:$P$32,3+Investimentos!$K24,FALSE)),0,VLOOKUP($F24,'Salário e Custo Hora'!$B$28:$P$32,3+Investimentos!$K24,FALSE)) -> 14.642606 | P24: =IF(C24="",0,O24*N24) -> 43.927817
B25: 84 | C25: Melhoria de produto | D25: Estabilidade | E25: Trophic Fiber | F25: Larissa Suellen da Silva | G25: =VLOOKUP(F25,'Salário e Custo Hora'!$B$48:$C$52,2,FALSE) -> Graduado | H25: Teste de estabilidade | I25: RH (Parcial inovação) | J25: 41465 | K25: =MONTH(J25) -> 7 | L25: =IF(K25<=3,"1 TRIM",IF(K25<=6,"2 TRIM",IF(K25<=9,"3 TRIM","4 TRIM"))) -> 3 TRIM | M25: Hora | N25: 3 | O25: =IF(ISNA(VLOOKUP($F25,'Salário e Custo Hora'!$B$28:$P$32,3+Investimentos!$K25,FALSE)),0,VLOOKUP($F25,'Salário e Custo Hora'!$B$28:$P$32,3+Investimentos!$K25,FALSE)) -> 14.642606 | P25: =IF(C25="",0,O25*N25) -> 43.927817
B26: 84 | C26: Melhoria de produto | D26: Embalagem | F26: Larissa Suellen da Silva | G26: =VLOOKUP(F26,'Salário e Custo Hora'!$B$48:$C$52,2,FALSE) -> Graduado | H26: Teste de embalagem - Pote PET | I26: RH (Parcial inovação) | J26: 41478 | K26: =MONTH(J26) -> 7 | L26: =IF(K26<=3,"1 TRIM",IF(K26<=6,"2 TRIM",IF(K26<=9,"3 TRIM","4 TRIM"))) -> 3 TRIM | M26: Hora | N26: =45/60 -> 0.75 | O26: =IF(ISNA(VLOOKUP($F26,'Salário e Custo Hora'!$B$28:$P$32,3+Investimentos!$K26,FALSE)),0,VLOOKUP($F26,'Salário e Custo Hora'!$B$28:$P$32,3+Investimentos!$K26,FALSE)) -> 14.642606 | P26: =IF(C26="",0,O26*N26) -> 10.981954
B27: 84 | C27: Melhoria de produto | D27: Estabilidade | E27: Energyzip BG | F27: Larissa Suellen da Silva | G27: =VLOOKUP(F27,'Salário e Custo Hora'!$B$48:$C$52,2,FALSE) -> Graduado | H27: Estabilidade de pH | I27: RH (Parcial inovação) | J27: 41499 | K27: =MONTH(J27) -> 8 | L27: =IF(K27<=3,"1 TRIM",IF(K27<=6,"2 TRIM",IF(K27<=9,"3 TRIM","4 TRIM"))) -> 3 TRIM | M27: Hora | N27: 1 | O27: =IF(ISNA(VLOOKUP($F27,'Salário e Custo Hora'!$B$28:$P$32,3+Investimentos!$K27,FALSE)),0,VLOOKUP($F27,'Salário e Custo Hora'!$B$28:$P$32,3+Investimentos!$K27,FALSE)) -> 15.308179 | P27: =IF(C27="",0,O27*N27) -> 15.308179
B28: 84 | C28: Melhoria de produto | D28: Estabilidade | E28: Renalmax | F28: Larissa Suellen da Silva | G28: =VLOOKUP(F28,'Salário e Custo Hora'!$B$48:$C$52,2,FALSE) -> Graduado | H28: Estabilidade de pH | I28: RH (Parcial inovação) | J28: 41499 | K28: =MONTH(J28) -> 8 | L28: =IF(K28<=3,"1 TRIM",IF(K28<=6,"2 TRIM",IF(K28<=9,"3 TRIM","4 TRIM"))) -> 3 TRIM | M28: Hora | N28: 1 | O28: =IF(ISNA(VLOOKUP($F28,'Salário e Custo Hora'!$B$28:$P$32,3+Investimentos!$K28,FALSE)),0,VLOOKUP($F28,'Salário e Custo Hora'!$B$28:$P$32,3+Investimentos!$K28,FALSE)) -> 15.308179 | P28: =IF(C28="",0,O28*N28) -> 15.308179
B29: 84 | C29: Melhoria de produto | D29: Estabilidade | E29: Trophic 1.5 | F29: Larissa Suellen da Silva | G29: =VLOOKUP(F29,'Salário e Custo Hora'!$B$48:$C$52,2,FALSE) -> Graduado | H29: Estabilidade de pH | I29: RH (Parcial inovação) | J29: 41499 | K29: =MONTH(J29) -> 8 | L29: =IF(K29<=3,"1 TRIM",IF(K29<=6,"2 TRIM",IF(K29<=9,"3 TRIM","4 TRIM"))) -> 3 TRIM | M29: Hora | N29: 1 | O29: =IF(ISNA(VLOOKUP($F29,'Salário e Custo Hora'!$B$28:$P$32,3+Investimentos!$K29,FALSE)),0,VLOOKUP($F29,'Salário e Custo Hora'!$B$28:$P$32,3+Investimentos!$K29,FALSE)) -> 15.308179 | P29: =IF(C29="",0,O29*N29) -> 15.308179
B30: 84 | C30: Melhoria de produto | D30: Estabilidade | E30: Energyzip BG | F30: Larissa Suellen da Silva | G30: =VLOOKUP(F30,'Salário e Custo Hora'!$B$48:$C$52,2,FALSE) -> Graduado | H30: Controle em Shelf Life | I30: RH (Parcial inovação) | J30: 41514 | K30: =MONTH(J30) -> 8 | L30: =IF(K30<=3,"1 TRIM",IF(K30<=6,"2 TRIM",IF(K30<=9,"3 TRIM","4 TRIM"))) -> 3 TRIM | M30: Hora | N30: =20/60 -> 0.33333333 | O30: =IF(ISNA(VLOOKUP($F30,'Salário e Custo Hora'!$B$28:$P$32,3+Investimentos!$K30,FALSE)),0,VLOOKUP($F30,'Salário e Custo Hora'!$B$28:$P$32,3+Investimentos!$K30,FALSE)) -> 15.308179 | P30: =IF(C30="",0,O30*N30) -> 5.1027262
B31: 84 | C31: Melhoria de produto | D31: Estabilidade | E31: Renalmax | F31: Larissa Suellen da Silva | G31: =VLOOKUP(F31,'Salário e Custo Hora'!$B$48:$C$52,2,FALSE) -> Graduado | H31: Controle em Shelf Life | I31: RH (Parcial inovação) | J31: 41514 | K31: =MONTH(J31) -> 8 | L31: =IF(K31<=3,"1 TRIM",IF(K31<=6,"2 TRIM",IF(K31<=9,"3 TRIM","4 TRIM"))) -> 3 TRIM | M31: Hora | N31: =20/60 -> 0.33333333 | O31: =IF(ISNA(VLOOKUP($F31,'Salário e Custo Hora'!$B$28:$P$32,3+Investimentos!$K31,FALSE)),0,VLOOKUP($F31,'Salário e Custo Hora'!$B$28:$P$32,3+Investimentos!$K31,FALSE)) -> 15.308179 | P31: =IF(C31="",0,O31*N31) -> 5.1027262
B32: 84 | C32: Melhoria de produto | D32: Estabilidade | E32: Trophic 1.5 | F32: Larissa Suellen da Silva | G32: =VLOOKUP(F32,'Salário e Custo Hora'!$B$48:$C$52,2,FALSE) -> Graduado | H32: Controle em Shelf Life | I32: RH (Parcial inovação) | J32: 41514 | K32: =MONTH(J32) -> 8 | L32: =IF(K32<=3,"1 TRIM",IF(K32<=6,"2 TRIM",IF(K32<=9,"3 TRIM","4 TRIM"))) -> 3 TRIM | M32: Hora | N32: =20/60 -> 0.33333333 | O32: =IF(ISNA(VLOOKUP($F32,'Salário e Custo Hora'!$B$28:$P$32,3+Investimentos!$K32,FALSE)),0,VLOOKUP($F32,'Salário e Custo Hora'!$B$28:$P$32,3+Investimentos!$K32,FALSE)) -> 15.308179 | P32: =IF(C32="",0,O32*N32) -> 5.1027262
B33: 84 | C33: Novo Copack | D33: Produto Líquido | E33: Trophic Basic-Castrolanda | F33: Larissa Suellen da Silva | G33: =VLOOKUP(F33,'Salário e Custo Hora'!$B$48:$C$52,2,FALSE) -> Graduado | H33: Controle em Shelf Life | I33: RH (Parcial inovação) | J33: 41514 | K33: =MONTH(J33) -> 8 | L33: =IF(K33<=3,"1 TRIM",IF(K33<=6,"2 TRIM",IF(K33<=9,"3 TRIM","4 TRIM"))) -> 3 TRIM | M33: Hora | N33: =15/60 -> 0.25 | O33: =IF(ISNA(VLOOKUP($F33,'Salário e Custo Hora'!$B$28:$P$32,3+Investimentos!$K33,FALSE)),0,VLOOKUP($F33,'Salário e Custo Hora'!$B$28:$P$32,3+Investimentos!$K33,FALSE)) -> 15.308179 | P33: =IF(C33="",0,O33*N33) -> 3.8270446
B34: 84 | C34: Melhoria de produto | E34: Trophic Soya | F34: Larissa Suellen da Silva | G34: =VLOOKUP(F34,'Salário e Custo Hora'!$B$48:$C$52,2,FALSE) -> Graduado | H34: Controle em Shelf Life | I34: RH (Parcial inovação) | J34: 41547 | K34: =MONTH(J34) -> 9 | L34: =IF(K34<=3,"1 TRIM",IF(K34<=6,"2 TRIM",IF(K34<=9,"3 TRIM","4 TRIM"))) -> 3 TRIM | M34: Hora | N34: =15/60 -> 0.25 | O34: =IF(ISNA(VLOOKUP($F34,'Salário e Custo Hora'!$B$28:$P$32,3+Investimentos!$K34,FALSE)),0,VLOOKUP($F34,'Salário e Custo Hora'!$B$28:$P$32,3+Investimentos!$K34,FALSE)) -> 16.037139 | P34: =IF(C34="",0,O34*N34) -> 4.0092849
B35: 84 | C35: Melhoria de produto | E35: Energyzip BG | F35: Larissa Suellen da Silva | G35: =VLOOKUP(F35,'Salário e Custo Hora'!$B$48:$C$52,2,FALSE) -> Graduado | H35: Controle em Shelf Life | I35: RH (Parcial inovação) | J35: 41541 | K35: =MONTH(J35) -> 9 | L35: =IF(K35<=3,"1 TRIM",IF(K35<=6,"2 TRIM",IF(K35<=9,"3 TRIM","4 TRIM"))) -> 3 TRIM | M35: Hora | N35: =5/60 -> 0.083333333 | O35: =IF(ISNA(VLOOKUP($F35,'Salário e Custo Hora'!$B$28:$P$32,3+Investimentos!$K35,FALSE)),0,VLOOKUP($F35,'Salário e Custo Hora'!$B$28:$P$32,3+Investimentos!$K35,FALSE)) -> 16.037139 | P35: =IF(C35="",0,O35*N35) -> 1.3364283
B36: 84 | C36: Melhoria de produto | E36: Renalmax | F36: Larissa Suellen da Silva | G36: =VLOOKUP(F36,'Salário e Custo Hora'!$B$48:$C$52,2,FALSE) -> Graduado | H36: Controle em Shelf Life | I36: RH (Parcial inovação) | J36: 41541 | K36: =MONTH(J36) -> 9 | L36: =IF(K36<=3,"1 TRIM",IF(K36<=6,"2 TRIM",IF(K36<=9,"3 TRIM","4 TRIM"))) -> 3 TRIM | M36: Hora | N36: =5/60 -> 0.083333333 | O36: =IF(ISNA(VLOOKUP($F36,'Salário e Custo Hora'!$B$28:$P$32,3+Investimentos!$K36,FALSE)),0,VLOOKUP($F36,'Salário e Custo Hora'!$B$28:$P$32,3+Investimentos!$K36,FALSE)) -> 16.037139 | P36: =IF(C36="",0,O36*N36) -> 1.3364283
B37: 84 | C37: Melhoria de produto | E37: Trophic 1.5 | F37: Larissa Suellen da Silva | G37: =VLOOKUP(F37,'Salário e Custo Hora'!$B$48:$C$52,2,FALSE) -> Graduado | H37: Controle em Shelf Life | I37: RH (Parcial inovação) | J37: 41541 | K37: =MONTH(J37) -> 9 | L37: =IF(K37<=3,"1 TRIM",IF(K37<=6,"2 TRIM",IF(K37<=9,"3 TRIM","4 TRIM"))) -> 3 TRIM | M37: Hora | N37: =5/60 -> 0.083333333 | O37: =IF(ISNA(VLOOKUP($F37,'Salário e Custo Hora'!$B$28:$P$32,3+Investimentos!$K37,FALSE)),0,VLOOKUP($F37,'Salário e Custo Hora'!$B$28:$P$32,3+Investimentos!$K37,FALSE)) -> 16.037139 | P37: =IF(C37="",0,O37*N37) -> 1.3364283
B38: 84 | C38: Melhoria de produto | E38: Trophic Fiber - Fibrim 1270 | F38: Larissa Suellen da Silva | G38: =VLOOKUP(F38,'Salário e Custo Hora'!$B$48:$C$52,2,FALSE) -> Graduado | H38: Controle em Shelf Life | I38: RH (Parcial inovação) | J38: 41541 | K38: =MONTH(J38) -> 9 | L38: =IF(K38<=3,"1 TRIM",IF(K38<=6,"2 TRIM",IF(K38<=9,"3 TRIM","4 TRIM"))) -> 3 TRIM | M38: Hora | N38: =5/60 -> 0.083333333 | O38: =IF(ISNA(VLOOKUP($F38,'Salário e Custo Hora'!$B$28:$P$32,3+Investimentos!$K38,FALSE)),0,VLOOKUP($F38,'Salário e Custo Hora'!$B$28:$P$32,3+Investimentos!$K38,FALSE)) -> 16.037139 | P38: =IF(C38="",0,O38*N38) -> 1.3364283
B39: Detalhamento da Apuração sem exclusão de inovação | C39: Novas matérias prima | D39: Macronutrientes | E39: Trophic 1.5 - 58G18 | F39: Larissa Suellen da Silva | G39: =VLOOKUP(F39,'Salário e Custo Hora'!$B$48:$C$52,2,FALSE) -> Graduado | H39: Controle em Shelf Life | I39: RH (Parcial inovação) | J39: 41604 | K39: =MONTH(J39) -> 11 | L39: =IF(K39<=3,"1 TRIM",IF(K39<=6,"2 TRIM",IF(K39<=9,"3 TRIM","4 TRIM"))) -> 4 TRIM | M39: Hora | N39: 0.33 | O39: =IF(ISNA(VLOOKUP($F39,'Salário e Custo Hora'!$B$28:$P$32,3+Investimentos!$K39,FALSE)),0,VLOOKUP($F39,'Salário e Custo Hora'!$B$28:$P$32,3+Investimentos!$K39,FALSE)) -> 16.838996 | P39: =IF(C39="",0,O39*N39) -> 5.5568688
B40: 84 | C40: Novas matérias prima | D40: Macronutrientes | E40: Trophic 1.5 - 58M20 | F40: Larissa Suellen da Silva | G40: =VLOOKUP(F40,'Salário e Custo Hora'!$B$48:$C$52,2,FALSE) -> Graduado | H40: Controle em Shelf Life | I40: RH (Parcial inovação) | J40: 41604 | K40: =MONTH(J40) -> 11 | L40: =IF(K40<=3,"1 TRIM",IF(K40<=6,"2 TRIM",IF(K40<=9,"3 TRIM","4 TRIM"))) -> 4 TRIM | M40: Hora | N40: =20/60 -> 0.33333333 | O40: =IF(ISNA(VLOOKUP($F40,'Salário e Custo Hora'!$B$28:$P$32,3+Investimentos!$K40,FALSE)),0,VLOOKUP($F40,'Salário e Custo Hora'!$B$28:$P$32,3+Investimentos!$K40,FALSE)) -> 16.838996 | P40: =IF(C40="",0,O40*N40) -> 5.6129988
B41: 84 | C41: Novos produtos | D41: Shelf Life | E41: Energyzip 1.0 - 879 (Novo projeto - Erica inserir) | F41: Larissa Suellen da Silva | G41: =VLOOKUP(F41,'Salário e Custo Hora'!$B$48:$C$52,2,FALSE) -> Graduado | H41: Controle em Shelf Life | I41: RH (Parcial inovação) | J41: 41604 | K41: =MONTH(J41) -> 11 | L41: =IF(K41<=3,"1 TRIM",IF(K41<=6,"2 TRIM",IF(K41<=9,"3 TRIM","4 TRIM"))) -> 4 TRIM | M41: Hora | N41: =20/60 -> 0.33333333 | O41: =IF(ISNA(VLOOKUP($F41,'Salário e Custo Hora'!$B$28:$P$32,3+Investimentos!$K41,FALSE)),0,VLOOKUP($F41,'Salário e Custo Hora'!$B$28:$P$32,3+Investimentos!$K41,FALSE)) -> 16.838996 | P41: =IF(C41="",0,O41*N41) -> 5.6129988
B42: 84 | C42: Melhoria de produto | E42: Energyzip Morango | F42: Larissa Suellen da Silva | G42: =VLOOKUP(F42,'Salário e Custo Hora'!$B$48:$C$52,2,FALSE) -> Graduado | H42: Controle em Shelf Life | I42: RH (Parcial inovação) | J42: 41604 | K42: =MONTH(J42) -> 11 | L42: =IF(K42<=3,"1 TRIM",IF(K42<=6,"2 TRIM",IF(K42<=9,"3 TRIM","4 TRIM"))) -> 4 TRIM | M42: Hora | N42: =5/60 -> 0.083333333 | O42: =IF(ISNA(VLOOKUP($F42,'Salário e Custo Hora'!$B$28:$P$32,3+Investimentos!$K42,FALSE)),0,VLOOKUP($F42,'Salário e Custo Hora'!$B$28:$P$32,3+Investimentos!$K42,FALSE)) -> 16.838996 | P42: =IF(C42="",0,O42*N42) -> 1.4032497
B43: 84 | C43: Melhoria de produto | E43: Energyzip Fiber Chocolate | F43: Larissa Suellen da Silva | G43: =VLOOKUP(F43,'Salário e Custo Hora'!$B$48:$C$52,2,FALSE) -> Graduado | H43: Controle em Shelf Life | I43: RH (Parcial inovação) | J43: 41604 | K43: =MONTH(J43) -> 11 | L43: =IF(K43<=3,"1 TRIM",IF(K43<=6,"2 TRIM",IF(K43<=9,"3 TRIM","4 TRIM"))) -> 4 TRIM | M43: Hora | N43: =15/60 -> 0.25 | O43: =IF(ISNA(VLOOKUP($F43,'Salário e Custo Hora'!$B$28:$P$32,3+Investimentos!$K43,FALSE)),0,VLOOKUP($F43,'Salário e Custo Hora'!$B$28:$P$32,3+Investimentos!$K43,FALSE)) -> 16.838996 | P43: =IF(C43="",0,O43*N43) -> 4.2097491
B44: 84 | C44: Melhoria de produto | E44: Trophic Fiber | F44: Larissa Suellen da Silva | G44: =VLOOKUP(F44,'Salário e Custo Hora'!$B$48:$C$52,2,FALSE) -> Graduado | H44: Controle em Shelf Life | I44: RH (Parcial inovação) | J44: 41604 | K44: =MONTH(J44) -> 11 | L44: =IF(K44<=3,"1 TRIM",IF(K44<=6,"2 TRIM",IF(K44<=9,"3 TRIM","4 TRIM"))) -> 4 TRIM | M44: Hora | N44: =10/60 -> 0.16666667 | O44: =IF(ISNA(VLOOKUP($F44,'Salário e Custo Hora'!$B$28:$P$32,3+Investimentos!$K44,FALSE)),0,VLOOKUP($F44,'Salário e Custo Hora'!$B$28:$P$32,3+Investimentos!$K44,FALSE)) -> 16.838996 | P44: =IF(C44="",0,O44*N44) -> 2.8064994
B45: 84 | C45: Novo Copack | D45: Produto Líquido | E45: Trophic Basic - Castrolanda | F45: Larissa Suellen da Silva | G45: =VLOOKUP(F45,'Salário e Custo Hora'!$B$48:$C$52,2,FALSE) -> Graduado | H45: Controle em Shelf Life | I45: RH (Parcial inovação) | J45: 41604 | K45: =MONTH(J45) -> 11 | L45: =IF(K45<=3,"1 TRIM",IF(K45<=6,"2 TRIM",IF(K45<=9,"3 TRIM","4 TRIM"))) -> 4 TRIM | M45: Hora | N45: =10/60 -> 0.16666667 | O45: =IF(ISNA(VLOOKUP($F45,'Salário e Custo Hora'!$B$28:$P$32,3+Investimentos!$K45,FALSE)),0,VLOOKUP($F45,'Salário e Custo Hora'!$B$28:$P$32,3+Investimentos!$K45,FALSE)) -> 16.838996 | P45: =IF(C45="",0,O45*N45) -> 2.8064994
B46: 82 | C46: Novos produtos | E46: Obesidade Bariatrica | F46: Felipe Camargo Chavita | G46: =VLOOKUP(F46,'Salário e Custo Hora'!$B$48:$C$52,2,FALSE) -> Graduado | I46: RH (Parcial inovação) | J46: 41577 | K46: =MONTH(J46) -> 10 | L46: =IF(K46<=3,"1 TRIM",IF(K46<=6,"2 TRIM",IF(K46<=9,"3 TRIM","4 TRIM"))) -> 4 TRIM | M46: Hora | N46: =40/60 -> 0.66666667 | O46: =IF(ISNA(VLOOKUP($F46,'Salário e Custo Hora'!$B$28:$P$32,3+Investimentos!$K46,FALSE)),0,VLOOKUP($F46,'Salário e Custo Hora'!$B$28:$P$32,3+Investimentos!$K46,FALSE)) -> 10.592342 | P46: =IF(C46="",0,O46*N46) -> 7.0615612
B47: 82 | C47: Novos produtos | E47: Suplemento em pó | F47: Felipe Camargo Chavita | G47: =VLOOKUP(F47,'Salário e Custo Hora'!$B$48:$C$52,2,FALSE) -> Graduado | I47: RH (Parcial inovação) | J47: 41577 | K47: =MONTH(J47) -> 10 | L47: =IF(K47<=3,"1 TRIM",IF(K47<=6,"2 TRIM",IF(K47<=9,"3 TRIM","4 TRIM"))) -> 4 TRIM | M47: Hora | N47: =40/60 -> 0.66666667 | O47: =IF(ISNA(VLOOKUP($F47,'Salário e Custo Hora'!$B$28:$P$32,3+Investimentos!$K47,FALSE)),0,VLOOKUP($F47,'Salário e Custo Hora'!$B$28:$P$32,3+Investimentos!$K47,FALSE)) -> 10.592342 | P47: =IF(C47="",0,O47*N47) -> 7.0615612
B48: 12/83 | C48: Melhoria de produto | D48: Estabilidade | E48: KOH - Energyzip BG | F48: Luciana Dutra | G48: =VLOOKUP(F48,'Salário e Custo Hora'!$B$48:$C$52,2,FALSE) -> Pós-Graduado | H48: Teste piloto - ITAL | I48: RH (Parcial inovação) | J48: 41513 | K48: =MONTH(J48) -> 8 | L48: =IF(K48<=3,"1 TRIM",IF(K48<=6,"2 TRIM",IF(K48<=9,"3 TRIM","4 TRIM"))) -> 3 TRIM | M48: Hora | N48: 3.5 | O48: =IF(ISNA(VLOOKUP($F48,'Salário e Custo Hora'!$B$28:$P$32,3+Investimentos!$K48,FALSE)),0,VLOOKUP($F48,'Salário e Custo Hora'!$B$28:$P$32,3+Investimentos!$K48,FALSE)) -> 45.54246 | P48: =IF(C48="",0,O48*N48) -> 159.39861
B49: 18/83 | C49: Melhoria de produto | D49: Estabilidade | E49: KOH - Renalmax | F49: Luciana Dutra | G49: =VLOOKUP(F49,'Salário e Custo Hora'!$B$48:$C$52,2,FALSE) -> Pós-Graduado | H49: Teste piloto - ITAL - Produção | I49: RH (Parcial inovação) | J49: 41513 | K49: =MONTH(J49) -> 8 | L49: =IF(K49<=3,"1 TRIM",IF(K49<=6,"2 TRIM",IF(K49<=9,"3 TRIM","4 TRIM"))) -> 3 TRIM | M49: Hora | N49: 3.5 | O49: =IF(ISNA(VLOOKUP($F49,'Salário e Custo Hora'!$B$28:$P$32,3+Investimentos!$K49,FALSE)),0,VLOOKUP($F49,'Salário e Custo Hora'!$B$28:$P$32,3+Investimentos!$K49,FALSE)) -> 45.54246 | P49: =IF(C49="",0,O49*N49) -> 159.39861
B50: 83 | C50: Novas matérias prima | D50: Micronutrientes | F50: Luciana Dutra | G50: =VLOOKUP(F50,'Salário e Custo Hora'!$B$48:$C$52,2,FALSE) -> Pós-Graduado | H50: Reunião MCassab | I50: RH (Parcial inovação) | J50: 41501 | K50: =MONTH(J50) -> 8 | L50: =IF(K50<=3,"1 TRIM",IF(K50<=6,"2 TRIM",IF(K50<=9,"3 TRIM","4 TRIM"))) -> 3 TRIM | M50: Hora | N50: 2 | O50: =IF(ISNA(VLOOKUP($F50,'Salário e Custo Hora'!$B$28:$P$32,3+Investimentos!$K50,FALSE)),0,VLOOKUP($F50,'Salário e Custo Hora'!$B$28:$P$32,3+Investimentos!$K50,FALSE)) -> 45.54246 | P50: =IF(C50="",0,O50*N50) -> 91.084919
B51: 19/83 | C51: Melhoria de produto | D51: Estabilidade | E51: KOH - Trophic 1.5 | F51: Luciana Dutra | G51: =VLOOKUP(F51,'Salário e Custo Hora'!$B$48:$C$52,2,FALSE) -> Pós-Graduado | H51: Teste piloto - ITAL | I51: RH (Parcial inovação) | J51: 41513 | K51: =MONTH(J51) -> 8 | L51: =IF(K51<=3,"1 TRIM",IF(K51<=6,"2 TRIM",IF(K51<=9,"3 TRIM","4 TRIM"))) -> 3 TRIM | M51: Hora | N51: 3.5 | O51: =IF(ISNA(VLOOKUP($F51,'Salário e Custo Hora'!$B$28:$P$32,3+Investimentos!$K51,FALSE)),0,VLOOKUP($F51,'Salário e Custo Hora'!$B$28:$P$32,3+Investimentos!$K51,FALSE)) -> 45.54246 | P51: =IF(C51="",0,O51*N51) -> 159.39861
B52: 83 | C52: Novas matérias prima | D52: Micronutrientes | F52: Luciana Dutra | G52: =VLOOKUP(F52,'Salário e Custo Hora'!$B$48:$C$52,2,FALSE) -> Pós-Graduado | H52: Reunião MCassab | I52: RH (Parcial inovação) | J52: 41460 | K52: =MONTH(J52) -> 7 | L52: =IF(K52<=3,"1 TRIM",IF(K52<=6,"2 TRIM",IF(K52<=9,"3 TRIM","4 TRIM"))) -> 3 TRIM | M52: Hora | N52: 3 | O52: =IF(ISNA(VLOOKUP($F52,'Salário e Custo Hora'!$B$28:$P$32,3+Investimentos!$K52,FALSE)),0,VLOOKUP($F52,'Salário e Custo Hora'!$B$28:$P$32,3+Investimentos!$K52,FALSE)) -> 43.562353 | P52: =IF(C52="",0,O52*N52) -> 130.68706
B53: 83 | C53: Novas matérias prima | D53: Micronutrientes | F53: Luciana Dutra | G53: =VLOOKUP(F53,'Salário e Custo Hora'!$B$48:$C$52,2,FALSE) -> Pós-Graduado | H53: reunião DSM | I53: RH (Parcial inovação) | J53: 41474 | K53: =MONTH(J53) -> 7 | L53: =IF(K53<=3,"1 TRIM",IF(K53<=6,"2 TRIM",IF(K53<=9,"3 TRIM","4 TRIM"))) -> 3 TRIM | M53: Hora | N53: 1 | O53: =IF(ISNA(VLOOKUP($F53,'Salário e Custo Hora'!$B$28:$P$32,3+Investimentos!$K53,FALSE)),0,VLOOKUP($F53,'Salário e Custo Hora'!$B$28:$P$32,3+Investimentos!$K53,FALSE)) -> 43.562353 | P53: =IF(C53="",0,O53*N53) -> 43.562353
B54: 10 | C54: Melhoria de produto | D54: Estabilidade | E54: Diversos | F54: Prodiet | H54: Material para teste - Hidróxido de Potássio | I54: Material | J54: 41512 | K54: =MONTH(J54) -> 8 | L54: =IF(K54<=3,"1 TRIM",IF(K54<=6,"2 TRIM",IF(K54<=9,"3 TRIM","4 TRIM"))) -> 3 TRIM | M54: Hora | N54: 1 | O54: 98.98 | P54: =IF(C54="",0,O54*N54) -> 98.98
B55: 11 | C55: Melhoria de produto | D55: Estabilidade | E55: Diversos | F55: Tetra Pak | H55: Serviços de Assessoria ou Consultoria - NF 6243 | I55: Terceiros | J55: 41536 | K55: =MONTH(J55) -> 9 | L55: =IF(K55<=3,"1 TRIM",IF(K55<=6,"2 TRIM",IF(K55<=9,"3 TRIM","4 TRIM"))) -> 3 TRIM | M55: Unidade | N55: 1 | O55: 8163.26 | P55: =IF(C55="",0,O55*N55) -> 8163.26
B56: 23 | C56: Melhoria de produto | D56: Estabilidade | E56: Diversos | F56: Érica Serra | H56: Passagem aerea para acompanhamento de andamento de projeto e teste do produto | I56: Material | J56: 41513 | K56: =MONTH(J56) -> 8 | L56: =IF(K56<=3,"1 TRIM",IF(K56<=6,"2 TRIM",IF(K56<=9,"3 TRIM","4 TRIM"))) -> 3 TRIM | M56: Trecho | N56: 1 | O56: 304.5 | P56: =N56*O56 -> 304.5
B57: 26 | C57: Melhoria de produto | D57: Estabilidade | E57: Nitrogênio | F57: Labor Três Laboratórios e Consultoria Técnica Ltda | H57: Análise de amostra - CA 12370 a 12372 - NF 17.181 | I57: Terceiros | J57: 41374 | K57: =MONTH(J57) -> 4 | L57: =IF(K57<=3,"1 TRIM",IF(K57<=6,"2 TRIM",IF(K57<=9,"3 TRIM","4 TRIM"))) -> 2 TRIM | M57: Serviço | N57: 1 | O57: 497 | P57: =N57*O57 -> 497
B58: 30 | C58: Melhoria de produto | D58: Sensorial | E58: Trophic Infant | F58: Prodiet | H58: Compra de produto concorrente para teste sensorial | I58: Material | J58: 41567 | K58: =MONTH(J58) -> 10 | L58: =IF(K58<=3,"1 TRIM",IF(K58<=6,"2 TRIM",IF(K58<=9,"3 TRIM","4 TRIM"))) -> 4 TRIM | M58: Unidade | N58: 1 | O58: 59.45 | P58: =IF(C58="",0,O58*N58) -> 59.45
B59: 31 | C59: Melhoria de produto | D59: Piloto | E59: Energyzip 1.0 | F59: Prodiet | H59: Compra de produto concorrente para teste de bancada - Óleo de Canola | I59: Material | J59: 41567 | K59: =MONTH(J59) -> 10 | L59: =IF(K59<=3,"1 TRIM",IF(K59<=6,"2 TRIM",IF(K59<=9,"3 TRIM","4 TRIM"))) -> 4 TRIM | M59: Unidade | N59: 1 | O59: 5.86 | P59: =IF(C59="",0,O59*N59) -> 5.86
B60: 29 | C60: Melhoria de produto | D60: Sensorial | E60: Trophic Infant | F60: Prodiet | H60: Utilização do Laboratório da PUC-PR para teste do produto | I60: Material | J60: 41554 | K60: =MONTH(J60) -> 10 | L60: =IF(K60<=3,"1 TRIM",IF(K60<=6,"2 TRIM",IF(K60<=9,"3 TRIM","4 TRIM"))) -> 4 TRIM | M60: Hora | N60: =1/3 -> 0.33333333 | O60: 145.75 | P60: =IF(C60="",0,O60*N60) -> 48.583333
B61: 35 | C61: Melhoria de produto | D61: Sensorial | E61: Trophic Infant | F61: Érica Serra | H61: Passagem rodoviária de Ida e Volta de Cutitiba-Jaraguá do Sul para participação no Curso Análise sensorial | I61: Material | J61: 41437 | K61: =MONTH(J61) -> 6 | L61: =IF(K61<=3,"1 TRIM",IF(K61<=6,"2 TRIM",IF(K61<=9,"3 TRIM","4 TRIM"))) -> 2 TRIM | M61: Trecho | N61: 2 | O61: =(29.75+28.25)/2 -> 29 | P61: =IF(C61="",0,O61*N61) -> 58
B62: 126 | C62: Novas matérias prima | D62: Macronutrientes | E62: Carboidrato - Globe 18 | F62: Labor Três Laboratórios e Consultoria Técnica Ltda | H62: Análise de amostras - NF 18.858 | I62: Terceiros | J62: 41604 | K62: =MONTH(J62) -> 11 | L62: =IF(K62<=3,"1 TRIM",IF(K62<=6,"2 TRIM",IF(K62<=9,"3 TRIM","4 TRIM"))) -> 4 TRIM | M62: Hora | N62: =1/3 -> 0.33333333 | O62: 1570 | P62: =N62*O62 -> 523.33333
B63: 41 | C63: Novas matérias prima | D63: Macronutrientes | E63: Carboidrato - Globe 18 | F63: Prodiet | H63: Análise Laboratorial | I63: Material | J63: 41554 | K63: =MONTH(J63) -> 10 | L63: =IF(K63<=3,"1 TRIM",IF(K63<=6,"2 TRIM",IF(K63<=9,"3 TRIM","4 TRIM"))) -> 4 TRIM | M63: Hora | N63: =1/3 -> 0.33333333 | O63: 145.75 | P63: =IF(C63="",0,O63*N63) -> 48.583333
B64: 126 | C64: Novas matérias prima | D64: Macronutrientes | E64: Carboidrato - Maltogill | F64: Labor Três Laboratórios e Consultoria Técnica Ltda | H64: Análise de amostras - NF 18.858 | I64: Terceiros | J64: 41590 | K64: =MONTH(J64) -> 11 | L64: =IF(K64<=3,"1 TRIM",IF(K64<=6,"2 TRIM",IF(K64<=9,"3 TRIM","4 TRIM"))) -> 4 TRIM | M64: Amostra | N64: =1/3 -> 0.33333333 | O64: 1570 | P64: =N64*O64 -> 523.33333
B65: 37 | C65: Novas matérias prima | D65: Macronutrientes | E65: Carboidrato - Maltogill | F65: Prodiet | H65: Teste de bancada em laboratório na PUC/PR | I65: Material | J65: 41554 | K65: =MONTH(J65) -> 10 | L65: =IF(K65<=3,"1 TRIM",IF(K65<=6,"2 TRIM",IF(K65<=9,"3 TRIM","4 TRIM"))) -> 4 TRIM | M65: Hora | N65: =1/3 -> 0.33333333 | O65: 145.75 | P65: =IF(C65="",0,O65*N65) -> 48.583333
B66: 47 | C66: Novas matérias prima | D66: Macronutrientes | E66: Gordura | F66: BIOAGRI Análises de Alimentos Ltda | H66: Análise de amostra nº 214765 - NF 22.222 | I66: Terceiros | J66: 41579 | K66: =MONTH(J66) -> 11 | L66: =IF(K66<=3,"1 TRIM",IF(K66<=6,"2 TRIM",IF(K66<=9,"3 TRIM","4 TRIM"))) -> 4 TRIM | M66: Análise | N66: 1 | O66: 444.25 | P66: =IF(C66="",0,O66*N66) -> 444.25
B67: 46 | C67: Novas matérias prima | D67: Macronutrientes | E67: Gordura | F67: Labor Três Laboratórios e Consultoria Técnica Ltda | H67: Análise de amostra - 28846.1/2013-0 NF 18.398 | I67: Terceiros | J67: 41537 | K67: =MONTH(J67) -> 9 | L67: =IF(K67<=3,"1 TRIM",IF(K67<=6,"2 TRIM",IF(K67<=9,"3 TRIM","4 TRIM"))) -> 3 TRIM | M67: Análise | N67: 1 | O67: 270 | P67: =IF(C67="",0,O67*N67) -> 270
B68: 48 | C68: Novas matérias prima | D68: Macronutrientes | E68: Gordura | F68: Prodiet | H68: Teste de bancada em laboratório na PUC/PR - Recibo 1197 | I68: Material | J68: 41486 | K68: =MONTH(J68) -> 7 | L68: =IF(K68<=3,"1 TRIM",IF(K68<=6,"2 TRIM",IF(K68<=9,"3 TRIM","4 TRIM"))) -> 3 TRIM | M68: Análise | N68: =1/3 -> 0.33333333 | O68: 157.5 | P68: =IF(C68="",0,O68*N68) -> 52.5
B69: 51 | C69: Novas matérias prima | D69: Macronutrientes | E69: Proteína - Caseinato de Calcio | F69: Prodiet | H69: Teste de bancada em laboratório na PUC/PR - Recibo 953 | I69: Material | J69: 41312 | K69: =MONTH(J69) -> 2 | L69: =IF(K69<=3,"1 TRIM",IF(K69<=6,"2 TRIM",IF(K69<=9,"3 TRIM","4 TRIM"))) -> 1 TRIM | M69: Análise | N69: 1 | O69: 385 | P69: =IF(C69="",0,O69*N69) -> 385
B70: 50 | C70: Novas matérias prima | D70: Macronutrientes | E70: Proteína - Caseinato de Calcio | F70: Prodiet | H70: Teste de bancada em laboratório na PUC/PR - Recibo 1197 | I70: Material | J70: 41486 | K70: =MONTH(J70) -> 7 | L70: =IF(K70<=3,"1 TRIM",IF(K70<=6,"2 TRIM",IF(K70<=9,"3 TRIM","4 TRIM"))) -> 3 TRIM | M70: Análise | N70: =1/3 -> 0.33333333 | O70: 157.5 | P70: =IF(C70="",0,O70*N70) -> 52.5
B71: 52 | C71: Novas matérias prima | D71: Macronutrientes | E71: Proteína - Isolada de Soja | F71: Prodiet | H71: Teste de bancada em laboratório na PUC/PR - Recibo 1197 | I71: Material | J71: 41486 | K71: =MONTH(J71) -> 7 | L71: =IF(K71<=3,"1 TRIM",IF(K71<=6,"2 TRIM",IF(K71<=9,"3 TRIM","4 TRIM"))) -> 3 TRIM | M71: Análise | N71: =1/3 -> 0.33333333 | O71: 157.5 | P71: =IF(C71="",0,O71*N71) -> 52.5
B72: 53 | C72: Novas matérias prima | D72: Macronutrientes | E72: Proteína - Isolada de Soja | F72: Prodiet | H72: Teste de bancada em laboratório na PUC/PR - Recibo 953 | I72: Material | J72: 41295 | K72: =MONTH(J72) -> 1 | L72: =IF(K72<=3,"1 TRIM",IF(K72<=6,"2 TRIM",IF(K72<=9,"3 TRIM","4 TRIM"))) -> 1 TRIM | M72: Análise | N72: 1 | O72: 385 | P72: =IF(C72="",0,O72*N72) -> 385
B73: 49 | C73: Novas matérias prima | D73: Micronutrintes | E73: Minerais - Nutrix | F73: Labor Três Laboratórios e Consultoria Técnica Ltda | H73: Análise de amostra - 10483.1/2013-0 NF 17.008 | I73: Terceiros | J73: 41367 | K73: =MONTH(J73) -> 4 | L73: =IF(K73<=3,"1 TRIM",IF(K73<=6,"2 TRIM",IF(K73<=9,"3 TRIM","4 TRIM"))) -> 2 TRIM | M73: Análise | N73: 0.5 | O73: 759 | P73: =IF(C73="",0,O73*N73) -> 379.5
B74: 54 | C74: Novas matérias prima | D74: Micronutrintes | E74: Vitaminas - Cassab | F74: Labor Três Laboratórios e Consultoria Técnica Ltda | H74: Análise de característica - 18114.1 - NF 17.630 | I74: Terceiros | J74: 41439 | K74: =MONTH(J74) -> 6 | L74: =IF(K74<=3,"1 TRIM",IF(K74<=6,"2 TRIM",IF(K74<=9,"3 TRIM","4 TRIM"))) -> 2 TRIM | M74: Análise | N74: 1 | O74: 1045 | P74: =IF(C74="",0,O74*N74) -> 1045
B75: 55 | C75: Novo Copack | D75: Produto Líquido | E75: Castrolanda | F75: Luciana Dutra | H75: Estadia no Hotel Slavieiro - 2 diárias - Para acompanhamento do desenvolvimento do projeto | I75: Material | J75: 41465 | K75: =MONTH(J75) -> 7 | L75: =IF(K75<=3,"1 TRIM",IF(K75<=6,"2 TRIM",IF(K75<=9,"3 TRIM","4 TRIM"))) -> 3 TRIM | M75: Diária | N75: 208 | O75: 2 | P75: =N75*O75 -> 416
B76: 122 | C76: Novo Copack | D76: Produto Líquido | E76: Castrolanda | F76: Labor Três Laboratórios e Consultoria Técnica Ltda | H76: Análise de característica CA 21301 - NF 17.896 | I76: Terceiros | J76: 41470 | K76: =MONTH(J76) -> 7 | L76: =IF(K76<=3,"1 TRIM",IF(K76<=6,"2 TRIM",IF(K76<=9,"3 TRIM","4 TRIM"))) -> 3 TRIM | M76: Análise | N76: 1 | O76: 270 | P76: =N76*O76 -> 270
B77: 57 | C77: Novo Copack | D77: Produto Líquido | E77: Castrolanda | F77: Luciana Dutra | H77: Passagem aérea SPO-CWB - Para acompanhamento do desenvolvimento do projeto | I77: Material | J77: 41465 | K77: =MONTH(J77) -> 7 | L77: =IF(K77<=3,"1 TRIM",IF(K77<=6,"2 TRIM",IF(K77<=9,"3 TRIM","4 TRIM"))) -> 3 TRIM | M77: Trecho | N77: 1 | O77: 507.57 | P77: =N77*O77 -> 507.57
B78: 119 | C78: Novo Copack | D78: Produto Líquido | E78: Castrolanda | F78: Vera Moura | H78: Passagem aérea para acompanhamento de teste 2 de piloto | I78: Material | J78: 41456 | K78: =MONTH(J78) -> 7 | L78: =IF(K78<=3,"1 TRIM",IF(K78<=6,"2 TRIM",IF(K78<=9,"3 TRIM","4 TRIM"))) -> 3 TRIM | M78: Trecho | N78: 1 | O78: 656.5 | P78: =N78*O78 -> 656.5
B79: 117 | C79: Novo Copack | D79: Produto Líquido | E79: Castrolanda | F79: Luciana Dutra | H79: Transfer em carro executivo entre Curitiba e Castro - Luciana Dutra e Vera Moura | I79: Material | J79: 41466 | K79: =MONTH(J79) -> 7 | L79: =IF(K79<=3,"1 TRIM",IF(K79<=6,"2 TRIM",IF(K79<=9,"3 TRIM","4 TRIM"))) -> 3 TRIM | M79: Trecho | N79: 1 | O79: =690*1.05 -> 724.5 | P79: =N79*O79 -> 724.5
B80: 111 | C80: Novos produtos | D80: Piloto | E80: Energyzip 1.0 | F80: Tetra Pak | H80: Serviços de Assessoria ou Consultoria no teste piloto - NF 6772 | I80: Terceiros | J80: 41597 | K80: =MONTH(J80) -> 11 | L80: =IF(K80<=3,"1 TRIM",IF(K80<=6,"2 TRIM",IF(K80<=9,"3 TRIM","4 TRIM"))) -> 4 TRIM | M80: Análise | N80: 1 | O80: 8163.26 | P80: =IF(C80="",0,O80*N80) -> 8163.26
B81: 112 | C81: Novos produtos | D81: Shelf Life | E81: Energyzip 1.0 | F81: Labor Três Laboratórios e Consultoria Técnica Ltda | H81: Análise de característica - NF 18.858 | I81: Terceiros | J81: 41590 | K81: =MONTH(J81) -> 11 | L81: =IF(K81<=3,"1 TRIM",IF(K81<=6,"2 TRIM",IF(K81<=9,"3 TRIM","4 TRIM"))) -> 4 TRIM | M81: Análise | N81: =1/3 -> 0.33333333 | O81: 1570 | P81: =IF(C81="",0,O81*N81) -> 523.33333
B82: 62 | C82: Novos produtos | E82: Obesidade Bariatrica | F82: Érica Serra | H82: Inscrição no Congresso Brasileiro de Obesidade | I82: Material | J82: 41424 | K82: =MONTH(J82) -> 5 | L82: =IF(K82<=3,"1 TRIM",IF(K82<=6,"2 TRIM",IF(K82<=9,"3 TRIM","4 TRIM"))) -> 2 TRIM | M82: Curso | N82: 1 | O82: 380 | P82: =IF(C82="",0,O82*N82) -> 380
B83: 63 | C83: Novos produtos | E83: Obesidade Bariatrica | F83: Prodiet | H83: Material para estudo - Compra de livro no Congresso Brasileiro de Obesidade | I83: Material | J83: 41425 | K83: =MONTH(J83) -> 5 | L83: =IF(K83<=3,"1 TRIM",IF(K83<=6,"2 TRIM",IF(K83<=9,"3 TRIM","4 TRIM"))) -> 2 TRIM | M83: Unidade | N83: 1 | O83: 88 | P83: =IF(C83="",0,O83*N83) -> 88
B84: 98 | C84: Novos produtos | D84: Congresso - ILSI | E84: Suplemento em pó | F84: Érica Serra | H84: Congresso ILSI - Inscrição para participação em workshop sobre Propriedades funcionais dos alimentos | I84: Material | J84: 41605 | K84: =MONTH(J84) -> 11 | L84: =IF(K84<=3,"1 TRIM",IF(K84<=6,"2 TRIM",IF(K84<=9,"3 TRIM","4 TRIM"))) -> 4 TRIM | M84: Unidade | N84: 1 | O84: 500 | P84: =N84*O84 -> 500
B85: 104 | C85: Novos produtos | D85: Congresso - SBNPE | E85: Suplemento em pó | F85: Érica Serra | H85: Inscrição no Congresso Brasileiro de Nutrição Parenteral e Enteral - SBNPE | I85: Material | J85: 41412 | K85: =MONTH(J85) -> 5 | L85: =IF(K85<=3,"1 TRIM",IF(K85<=6,"2 TRIM",IF(K85<=9,"3 TRIM","4 TRIM"))) -> 2 TRIM | M85: Unidade | N85: 1 | O85: 400 | P85: =N85*O85 -> 400
B86: 107 | C86: Novos produtos | D86: Congresso - SBNPE | E86: Suplemento em pó | F86: Érica Serra | H86: Translado até o curso - Passagem aérea da GOL | I86: Material | J86: 41612 | K86: =MONTH(J86) -> 12 | L86: =IF(K86<=3,"1 TRIM",IF(K86<=6,"2 TRIM",IF(K86<=9,"3 TRIM","4 TRIM"))) -> 4 TRIM | M86: Trecho | N86: 1 | O86: 963.92 | P86: =N86*O86 -> 963.92
B87: 106 | C87: Novos produtos | D87: Congresso - SBNPE | E87: Suplemento em pó | F87: Érica Serra | H87: Tranlado de ônibus entre aeroporto de congonhas e guarulhos | I87: Material | J87: 41607 | K87: =MONTH(J87) -> 11 | L87: =IF(K87<=3,"1 TRIM",IF(K87<=6,"2 TRIM",IF(K87<=9,"3 TRIM","4 TRIM"))) -> 4 TRIM | M87: Trecho | N87: 1 | O87: 36.5 | P87: =N87*O87 -> 36.5
B88: 71 | C88: Novos produtos | D88: Piloto | E88: Trophic Soya | F88: Tetra Pak | H88: Serviços de Assessoria ou Consultoria no teste piloto - NF 5230 | I88: Material | J88: 41416 | K88: =MONTH(J88) -> 5 | L88: =IF(K88<=3,"1 TRIM",IF(K88<=6,"2 TRIM",IF(K88<=9,"3 TRIM","4 TRIM"))) -> 2 TRIM | M88: Diversos | N88: 1 | O88: 8163.26 | P88: =IF(C88="",0,O88*N88) -> 8163.26
B89: 110 | C89: Novos produtos | D89: Shelf Life | E89: Trophic Soya | F89: Labor Três Laboratórios e Consultoria Técnica Ltda | H89: Análise de característica para teste de validade de produto - NF 17.008 | I89: Terceiros | J89: 41367 | K89: =MONTH(J89) -> 4 | L89: =IF(K89<=3,"1 TRIM",IF(K89<=6,"2 TRIM",IF(K89<=9,"3 TRIM","4 TRIM"))) -> 2 TRIM | M89: Análise | N89: 0.5 | O89: 759 | P89: =IF(C89="",0,O89*N89) -> 379.5
B90: 114 | C90: Novo Copack | D90: Produto Líquido | E90: Castrolanda | F90: Labor Três Laboratórios e Consultoria Técnica Ltda | H90: Análise de características - NF 19.223 | I90: Terceiros | J90: 41635 | K90: =MONTH(J90) -> 12 | L90: =IF(K90<=3,"1 TRIM",IF(K90<=6,"2 TRIM",IF(K90<=9,"3 TRIM","4 TRIM"))) -> 4 TRIM | M90: Análise | N90: 1 | O90: 270 | P90: =N90*O90 -> 270
B91: 82 | C91: Novas matérias prima | D91: Macronutrientes | E91: Trophic 1.5 | F91: Felipe Camargo Chavita | G91: =VLOOKUP(F91,'Salário e Custo Hora'!$B$48:$C$52,2,FALSE) -> Graduado | I91: RH (Parcial inovação) | J91: 41604 | K91: =MONTH(J91) -> 11 | L91: =IF(K91<=3,"1 TRIM",IF(K91<=6,"2 TRIM",IF(K91<=9,"3 TRIM","4 TRIM"))) -> 4 TRIM | M91: Hora | N91: =20/60 -> 0.33333333 | O91: =IF(ISNA(VLOOKUP($F91,'Salário e Custo Hora'!$B$28:$P$32,3+Investimentos!$K91,FALSE)),0,VLOOKUP($F91,'Salário e Custo Hora'!$B$28:$P$32,3+Investimentos!$K91,FALSE)) -> 12.181193 | P91: =IF(C91="",0,O91*N91) -> 4.0603977
B92: 82 | C92: Novas matérias prima | D92: Macronutrientes | E92: Trophic 1.5 | F92: Felipe Camargo Chavita | G92: =VLOOKUP(F92,'Salário e Custo Hora'!$B$48:$C$52,2,FALSE) -> Graduado | I92: RH (Parcial inovação) | J92: 41604 | K92: =MONTH(J92) -> 11 | L92: =IF(K92<=3,"1 TRIM",IF(K92<=6,"2 TRIM",IF(K92<=9,"3 TRIM","4 TRIM"))) -> 4 TRIM | M92: Hora | N92: =20/60 -> 0.33333333 | O92: =IF(ISNA(VLOOKUP($F92,'Salário e Custo Hora'!$B$28:$P$32,3+Investimentos!$K92,FALSE)),0,VLOOKUP($F92,'Salário e Custo Hora'!$B$28:$P$32,3+Investimentos!$K92,FALSE)) -> 12.181193 | P92: =IF(C92="",0,O92*N92) -> 4.0603977
B93: 82 | C93: Melhoria de produto | D93: Estabilidade | E93: Fórmula | F93: Felipe Camargo Chavita | G93: =VLOOKUP(F93,'Salário e Custo Hora'!$B$48:$C$52,2,FALSE) -> Graduado | H93: Teste de estabilidade | I93: RH (Parcial inovação) | J93: 41605 | K93: =MONTH(J93) -> 11 | L93: =IF(K93<=3,"1 TRIM",IF(K93<=6,"2 TRIM",IF(K93<=9,"3 TRIM","4 TRIM"))) -> 4 TRIM | M93: Hora | N93: =30/60 -> 0.5 | O93: =IF(ISNA(VLOOKUP($F93,'Salário e Custo Hora'!$B$28:$P$32,3+Investimentos!$K93,FALSE)),0,VLOOKUP($F93,'Salário e Custo Hora'!$B$28:$P$32,3+Investimentos!$K93,FALSE)) -> 12.181193 | P93: =IF(C93="",0,O93*N93) -> 6.0905965
B94: 82 | C94: Novas matérias prima | D94: Micronutrientes | F94: Felipe Camargo Chavita | G94: =VLOOKUP(F94,'Salário e Custo Hora'!$B$48:$C$52,2,FALSE) -> Graduado | H94: Pesagem e teste de componetes mix 8789 | I94: RH (Parcial inovação) | J94: 41617 | K94: =MONTH(J94) -> 12 | L94: =IF(K94<=3,"1 TRIM",IF(K94<=6,"2 TRIM",IF(K94<=9,"3 TRIM","4 TRIM"))) -> 4 TRIM | M94: Hora | N94: =190/60 -> 3.1666667 | O94: =IF(ISNA(VLOOKUP($F94,'Salário e Custo Hora'!$B$28:$P$32,3+Investimentos!$K94,FALSE)),0,VLOOKUP($F94,'Salário e Custo Hora'!$B$28:$P$32,3+Investimentos!$K94,FALSE)) -> 11.601136 | P94: =IF(C94="",0,O94*N94) -> 36.736931
B95: 82 | C95: Novas matérias prima | D95: Micronutrientes | F95: Felipe Camargo Chavita | G95: =VLOOKUP(F95,'Salário e Custo Hora'!$B$48:$C$52,2,FALSE) -> Graduado | H95: Pesagem e teste de componetes mix 8789 | I95: RH (Parcial inovação) | J95: 41618 | K95: =MONTH(J95) -> 12 | L95: =IF(K95<=3,"1 TRIM",IF(K95<=6,"2 TRIM",IF(K95<=9,"3 TRIM","4 TRIM"))) -> 4 TRIM | M95: Hora | N95: =50/60 -> 0.83333333 | O95: =IF(ISNA(VLOOKUP($F95,'Salário e Custo Hora'!$B$28:$P$32,3+Investimentos!$K95,FALSE)),0,VLOOKUP($F95,'Salário e Custo Hora'!$B$28:$P$32,3+Investimentos!$K95,FALSE)) -> 11.601136 | P95: =IF(C95="",0,O95*N95) -> 9.6676135
B96: 82 | C96: Novo Copack | D96: Produto Líquido | E96: Castrolanda | F96: Felipe Camargo Chavita | G96: =VLOOKUP(F96,'Salário e Custo Hora'!$B$48:$C$52,2,FALSE) -> Graduado | H96: Pesagem e teste de componetes mix 8789 | I96: RH (Parcial inovação) | J96: 41624 | K96: =MONTH(J96) -> 12 | L96: =IF(K96<=3,"1 TRIM",IF(K96<=6,"2 TRIM",IF(K96<=9,"3 TRIM","4 TRIM"))) -> 4 TRIM | M96: Hora | N96: =90/60 -> 1.5 | O96: =IF(ISNA(VLOOKUP($F96,'Salário e Custo Hora'!$B$28:$P$32,3+Investimentos!$K96,FALSE)),0,VLOOKUP($F96,'Salário e Custo Hora'!$B$28:$P$32,3+Investimentos!$K96,FALSE)) -> 11.601136 | P96: =IF(C96="",0,O96*N96) -> 17.401704
B97: 82 | C97: Novos produtos | D97: Piloto | E97: Trophic Soya | F97: Felipe Camargo Chavita | G97: =VLOOKUP(F97,'Salário e Custo Hora'!$B$48:$C$52,2,FALSE) -> Graduado | H97: Controle em Shelf Life | I97: RH (Parcial inovação) | J97: 41631 | K97: =MONTH(J97) -> 12 | L97: =IF(K97<=3,"1 TRIM",IF(K97<=6,"2 TRIM",IF(K97<=9,"3 TRIM","4 TRIM"))) -> 4 TRIM | M97: Hora | N97: =45/60 -> 0.75 | O97: =IF(ISNA(VLOOKUP($F97,'Salário e Custo Hora'!$B$28:$P$32,3+Investimentos!$K97,FALSE)),0,VLOOKUP($F97,'Salário e Custo Hora'!$B$28:$P$32,3+Investimentos!$K97,FALSE)) -> 11.601136 | P97: =IF(C97="",0,O97*N97) -> 8.7008522
B98: 83 | C98: Novas matérias prima | D98: Micronutrientes | F98: Luciana Dutra | G98: =VLOOKUP(F98,'Salário e Custo Hora'!$B$48:$C$52,2,FALSE) -> Pós-Graduado | H98: Reunião MCassab | I98: RH (Parcial inovação) | J98: 41372 | K98: =MONTH(J98) -> 4 | L98: =IF(K98<=3,"1 TRIM",IF(K98<=6,"2 TRIM",IF(K98<=9,"3 TRIM","4 TRIM"))) -> 2 TRIM | M98: Hora | N98: =90/60 -> 1.5 | O98: =IF(ISNA(VLOOKUP($F98,'Salário e Custo Hora'!$B$28:$P$32,3+Investimentos!$K98,FALSE)),0,VLOOKUP($F98,'Salário e Custo Hora'!$B$28:$P$32,3+Investimentos!$K98,FALSE)) -> 45.54246 | P98: =IF(C98="",0,O98*N98) -> 68.31369
B99: 21/83 | C99: Melhoria de produto | D99: Estabilidade | E99: Trophic Fiber | F99: Luciana Dutra | G99: =VLOOKUP(F99,'Salário e Custo Hora'!$B$48:$C$52,2,FALSE) -> Pós-Graduado | H99: Teste KOH | I99: RH (Parcial inovação) | J99: 41479 | K99: =MONTH(J99) -> 7 | L99: =IF(K99<=3,"1 TRIM",IF(K99<=6,"2 TRIM",IF(K99<=9,"3 TRIM","4 TRIM"))) -> 3 TRIM | M99: Hora | N99: 6 | O99: =IF(ISNA(VLOOKUP($F99,'Salário e Custo Hora'!$B$28:$P$32,3+Investimentos!$K99,FALSE)),0,VLOOKUP($F99,'Salário e Custo Hora'!$B$28:$P$32,3+Investimentos!$K99,FALSE)) -> 43.562353 | P99: =N99*O99 -> 261.37412
B100: 22/83 | C100: Melhoria de produto | D100: Estabilidade | E100: Trophic EP | F100: Luciana Dutra | G100: =VLOOKUP(F100,'Salário e Custo Hora'!$B$48:$C$52,2,FALSE) -> Pós-Graduado | H100: Teste KOH | I100: RH (Parcial inovação) | J100: 41484 | K100: =MONTH(J100) -> 7 | L100: =IF(K100<=3,"1 TRIM",IF(K100<=6,"2 TRIM",IF(K100<=9,"3 TRIM","4 TRIM"))) -> 3 TRIM | M100: Hora | N100: =8+20/60 -> 8.3333333 | O100: =IF(ISNA(VLOOKUP($F100,'Salário e Custo Hora'!$B$28:$P$32,3+Investimentos!$K100,FALSE)),0,VLOOKUP($F100,'Salário e Custo Hora'!$B$28:$P$32,3+Investimentos!$K100,FALSE)) -> 43.562353 | P100: =IF(C100="",0,O100*N100) -> 363.01961
...

Sheet Terceiros
B1: PRODIET NUTRIÇÃO
B2: INOVAÇÃO TECNOLÓGICA 2013
B3: Terceiros envolvidos em inovação
B5: Terceiro | C5: CNPJ | D5: Mês | E5: Trimestre | F5: Valor NF (R$) | G5: Proporção Inovação | H5: Valor Inovação | I5: Quem? | J5: Projeto
A6: (a) (b) (c) | B6: Nutrimento Gestão de Dados Empresariais Ltda. | C6: 03.150.501/0001-42 | D6: 41275 | E6: =IF(MONTH(D6)<=3,"1 TRIM",IF(MONTH(D6)<=6,"2 TRIM",IF(MONTH(D6)<=9,"3 TRIM","4TRIM"))) -> 1 TRIM | F6: 23734.94 | G6: 0.3 | H6: =F6*G6 -> 7120.482 | I6: Ana Celes | J6: Todos
B7: Nutrimento Gestão de Dados Empresariais Ltda. | C7: 03.150.501/0001-42 | D7: 41306 | E7: =IF(MONTH(D7)<=3,"1 TRIM",IF(MONTH(D7)<=6,"2 TRIM",IF(MONTH(D7)<=9,"3 TRIM","4TRIM"))) -> 1 TRIM | F7: 23734.94 | G7: 0.3 | H7: =F7*G7 -> 7120.482 | I7: Ana Celes | J7: Todos
B8: Nutrimento Gestão de Dados Empresariais Ltda. | C8: 03.150.501/0001-42 | D8: 41334 | E8: =IF(MONTH(D8)<=3,"1 TRIM",IF(MONTH(D8)<=6,"2 TRIM",IF(MONTH(D8)<=9,"3 TRIM","4TRIM"))) -> 1 TRIM | F8: 23734.94 | G8: 0.3 | H8: =F8*G8 -> 7120.482 | I8: Ana Celes | J8: Todos
B9: Nutrimento Gestão de Dados Empresariais Ltda. | C9: 03.150.501/0001-42 | D9: 41365 | E9: =IF(MONTH(D9)<=3,"1 TRIM",IF(MONTH(D9)<=6,"2 TRIM",IF(MONTH(D9)<=9,"3 TRIM","4TRIM"))) -> 2 TRIM | F9: 23734.94 | G9: 0.3 | H9: =F9*G9 -> 7120.482 | I9: Ana Celes | J9: Todos
B10: Nutrimento Gestão de Dados Empresariais Ltda. | C10: 03.150.501/0001-42 | D10: 41395 | E10: =IF(MONTH(D10)<=3,"1 TRIM",IF(MONTH(D10)<=6,"2 TRIM",IF(MONTH(D10)<=9,"3 TRIM","4TRIM"))) -> 2 TRIM | F10: 23734.94 | G10: 0.3 | H10: =F10*G10 -> 7120.482 | I10: Ana Celes | J10: Todos
B11: Nutrimento Gestão de Dados Empresariais Ltda. | C11: 03.150.501/0001-42 | D11: 41426 | E11: =IF(MONTH(D11)<=3,"1 TRIM",IF(MONTH(D11)<=6,"2 TRIM",IF(MONTH(D11)<=9,"3 TRIM","4TRIM"))) -> 2 TRIM | F11: 23734.94 | G11: 0.3 | H11: =F11*G11 -> 7120.482 | I11: Ana Celes | J11: Todos
B12: Nutrimento Gestão de Dados Empresariais Ltda. | C12: 03.150.501/0001-42 | D12: 41456 | E12: =IF(MONTH(D12)<=3,"1 TRIM",IF(MONTH(D12)<=6,"2 TRIM",IF(MONTH(D12)<=9,"3 TRIM","4TRIM"))) -> 3 TRIM | F12: 23734.94 | G12: 0.3 | H12: =F12*G12 -> 7120.482 | I12: Ana Celes | J12: Todos
B13: Nutrimento Gestão de Dados Empresariais Ltda. | C13: 03.150.501/0001-42 | D13: 41487 | E13: =IF(MONTH(D13)<=3,"1 TRIM",IF(MONTH(D13)<=6,"2 TRIM",IF(MONTH(D13)<=9,"3 TRIM","4TRIM"))) -> 3 TRIM | F13: 23734.94 | G13: 0.3 | H13: =F13*G13 -> 7120.482 | I13: Ana Celes | J13: Todos
B14: Nutrimento Gestão de Dados Empresariais Ltda. | C14: 03.150.501/0001-42 | D14: 41518 | E14: =IF(MONTH(D14)<=3,"1 TRIM",IF(MONTH(D14)<=6,"2 TRIM",IF(MONTH(D14)<=9,"3 TRIM","4TRIM"))) -> 3 TRIM | F14: 23734.94 | G14: 0.3 | H14: =F14*G14 -> 7120.482 | I14: Ana Celes | J14: Todos
B15: Nutrimento Gestão de Dados Empresariais Ltda. | C15: 03.150.501/0001-42 | D15: 41548 | E15: =IF(MONTH(D15)<=3,"1 TRIM",IF(MONTH(D15)<=6,"2 TRIM",IF(MONTH(D15)<=9,"3 TRIM","4 TRIM"))) -> 4 TRIM | F15: 23734.94 | G15: 0.3 | H15: =F15*G15 -> 7120.482 | I15: Ana Celes | J15: Todos
B16: Nutrimento Gestão de Dados Empresariais Ltda. | C16: 03.150.501/0001-42 | D16: 41579 | E16: =IF(MONTH(D16)<=3,"1 TRIM",IF(MONTH(D16)<=6,"2 TRIM",IF(MONTH(D16)<=9,"3 TRIM","4 TRIM"))) -> 4 TRIM | F16: =F15/2 -> 11867.47 | G16: 0.3 | H16: =F16*G16 -> 3560.241 | I16: Ana Celes | J16: Todos
B17: Nutrimento Gestão de Dados Empresariais Ltda. | C17: 03.150.501/0001-42 | D17: 41609 | E17: =IF(MONTH(D17)<=3,"1 TRIM",IF(MONTH(D17)<=6,"2 TRIM",IF(MONTH(D17)<=9,"3 TRIM","4 TRIM"))) -> 4 TRIM | F17: =F16 -> 11867.47 | G17: 0.3 | H17: =F17*G17 -> 3560.241 | I17: Ana Celes | J17: Todos
B18: Nutrimento Gestão de Dados Empresariais Ltda. | C18: 03.150.501/0001-42 | D18: 41609 | E18: =IF(MONTH(D18)<=3,"1 TRIM",IF(MONTH(D18)<=6,"2 TRIM",IF(MONTH(D18)<=9,"3 TRIM","4 TRIM"))) -> 4 TRIM | F18: 23734.94 | G18: 0.3 | H18: =F18*G18 -> 7120.482 | I18: Ana Celes | J18: Todos
B19: VLL Moura Serviços de Apoio Administrativo | C19: 18.390.865/0001-77 | D19: 41574 | E19: =IF(MONTH(D19)<=3,"1 TRIM",IF(MONTH(D19)<=6,"2 TRIM",IF(MONTH(D19)<=9,"3 TRIM","4 TRIM"))) -> 4 TRIM | F19: 0 | G19: 0 | H19: =F19*G19 -> 0 | I19: Vera Moura
B20: VLL Moura Serviços de Apoio Administrativo | C20: 18.390.865/0001-77 | D20: 41624 | E20: =IF(MONTH(D20)<=3,"1 TRIM",IF(MONTH(D20)<=6,"2 TRIM",IF(MONTH(D20)<=9,"3 TRIM","4 TRIM"))) -> 4 TRIM | F20: 0 | G20: 0 | H20: =F20*G20 -> 0 | I20: Vera Moura
B21: L Dutra Serviços ME | C21: 18.337.175/0001-54 | D21: 41554 | E21: =IF(MONTH(D21)<=3,"1 TRIM",IF(MONTH(D21)<=6,"2 TRIM",IF(MONTH(D21)<=9,"3 TRIM","4 TRIM"))) -> 4 TRIM | F21: 4200 | G21: 0 | H21: =F21*G21 -> 0 | I21: Luciana Dutra
B22: L Dutra Serviços ME | C22: 18.337.175/0001-54 | D22: 41577 | E22: =IF(MONTH(D22)<=3,"1 TRIM",IF(MONTH(D22)<=6,"2 TRIM",IF(MONTH(D22)<=9,"3 TRIM","4 TRIM"))) -> 4 TRIM | F22: 8400 | G22: 0 | H22: =F22*G22 -> 0 | I22: Luciana Dutra
B23: L Dutra Serviços ME | C23: 18.337.175/0001-54 | D23: 41606 | E23: =IF(MONTH(D23)<=3,"1 TRIM",IF(MONTH(D23)<=6,"2 TRIM",IF(MONTH(D23)<=9,"3 TRIM","4 TRIM"))) -> 4 TRIM | F23: 8400 | G23: =3/('Dias Úteis'!G17*8.48) -> 0.017688679 | H23: =F23*G23 -> 148.58491 | I23: Luciana Dutra | J23: Todos. Mas lançar em um só pois o valor é muito baixo
B24: L Dutra Serviços ME | C24: 18.337.175/0001-54 | D24: 41626 | E24: =IF(MONTH(D24)<=3,"1 TRIM",IF(MONTH(D24)<=6,"2 TRIM",IF(MONTH(D24)<=9,"3 TRIM","4 TRIM"))) -> 4 TRIM | F24: 11200 | G24: =9.75/('Dias Úteis'!G18*8.48) -> 0.054750674 | H24: =F24*G24 -> 613.20755 | I24: Luciana Dutra | J24: Melhoria de produto
B25: TOTAL | H25: =SUM(H6:H24) -> 86207.576
B29: Horas apontadas do Terceiro L Dutra Serviços ME
A30: Documento | B30: PROJETO | C30: RECURSO | D30: ATIVIDADE | E30: NATUREZA | F30: DATA | G30: Trimestre | H30: Horas apontadas | J30: SUB PROJETO | K30: PRODUTO
A31: 1/83 | B31: Melhoria de Produto | Estabilidade | C31: L Dutra Serviços ME | D31: Análise ML | E31: Terceiro | F31: 41620 | G31: 4 TRIM | H31: 1.5 | J31: Fórmula | K31: Diamax
A32: 2/83 | B32: Melhoria de Produto | Estabilidade | C32: L Dutra Serviços ME | D32: Identificar na amostra do Trophic Fiber qual matéria-prima pode estar causando instabilidade | E32: Terceiro | F32: 41620 | G32: 4 TRIM | H32: 1.5 | J32: Fórmula | K32: Trophic Fiber
A33: 83 | B33: Todos | C33: L Dutra Serviços ME | D33: Teste ITAL | E33: Terceiro | F33: 41584 | G33: 4 TRIM | H33: 9.75 | J33: Sem projeto | K33: Sem projeto
B37: PROJETO | C37: Propoção Terceiros | D37: Nutrimento Gestão de Dados Empresariais Ltda. | E37: L Dutra Serviços ME | F37: Total
B38: Melhoria de produto | C38: 0.2 | D38: =SUMIFS($H$6:$H$24,$B$6:$B$24,$D$37)*C38 -> 17089.157 | E38: =H24 -> 613.20755 | F38: =SUM(D38:E38) -> 17702.364
B39: Novo Copack | C39: 0.1 | D39: =SUMIFS($H$6:$H$24,$B$6:$B$24,$D$37)*C39 -> 8544.5784 | E39: 0 | F39: =SUM(D39:E39) -> 8544.5784
B40: Novos produtos | C40: 0.4 | D40: =SUMIFS($H$6:$H$24,$B$6:$B$24,$D$37)*C40 -> 34178.314 | E40: =H23 -> 148.58491 | F40: =SUM(D40:E40) -> 34326.899
B41: Novas matérias prima | C41: 0.3 | D41: =SUMIFS($H$6:$H$24,$B$6:$B$24,$D$37)*C41 -> 25633.735 | E41: 0 | F41: =SUM(D41:E41) -> 25633.735
C42: =SUM(C38:C41) -> 1 | D42: =SUM(D38:D41) -> 85445.784 | E42: =SUM(E38:E41) -> 761.79245 | F42: =SUM(F38:F41) -> 86207.576
A53: (a) | B53: Esse percentual foi decidido pela Ana Celes (Nutrimento). A informação veio por e-mail do Álvaro (doc 92)
A54: (b) | B54: Cartão CNPJ - Doc 90
A55: (c) | B55: Detalhamento da Apuração sem exclusão de inovação

Sheet Terceiros-Resumo
B2: Terceiro | C2: Descrição | D2: Total
B3: Tetra Pak | C3: Consultoria para adaptação da embalagem tetrapak a certos produtos da empresa. São feitos diversos testes, com a assistência do terceiro, como teste de validade e rodar lote pilote. Ele acompanha e ajuda a ajustar as variáveis que envolvem o produto em si e o processo produtivo à nova embalagem. | D3: =SUMIFS(Investimentos!$P$6:$P$100,Investimentos!$F$6:$F$100,'Terceiros-Resumo'!B3,Investimentos!$I$6:$I$100,"Terceiros") -> 16326.52
B4: Labor Três Laboratórios e Consultoria Técnica Ltda | C4: Faz testes laboratorias específicos solicitados pela Prodiet. São testes de análise de caracterísca de componente específico do produto e análise de validade do produto | D4: =SUMIFS(Investimentos!$P$6:$P$100,Investimentos!$F$6:$F$100,'Terceiros-Resumo'!B4,Investimentos!$I$6:$I$100,"Terceiros") -> 4681
B5: BIOAGRI Análises de Alimentos Ltda | C5: Faz análise laboratorial de amostras de produtos para verificar estabilidade de componentes e características finais | D5: =SUMIFS(Investimentos!$P$6:$P$100,Investimentos!$F$6:$F$100,'Terceiros-Resumo'!B5,Investimentos!$I$6:$I$100,"Terceiros") -> 444.25
B6: Nutrimento Gestão de Dados Empresariais Ltda. | C6: Analisa os testes dos produtos e dá assistência na parametrização do produto e dos novos testes a serem feitos. Faz acompanhamento técnico de todos os projetos de pesquisa e desenvolvimento. | D6: =SUMIFS(Terceiros!$H$6:$H$24,Terceiros!$B$6:$B$24,'Terceiros-Resumo'!B6) -> 85445.784
B7: L Dutra Serviços ME | C7: Acompanha e faz teste nos produtos para validação de lote pilote, teste de validade do produto, teste de caracterísca e teste de de administração do produto final., visto que são pordutos de alimentação hospitalar, oral e domiciliar pós-internação | D7: =SUMIFS(Terceiros!$H$6:$H$24,Terceiros!$B$6:$B$24,'Terceiros-Resumo'!B7) -> 761.79245
D8: =SUM(D3:D7) -> 107659.35
B12: Projeto | C12: Terceiro | D12: Valor
B13: Melhoria de produto | C13: Tetra Pak | D13: =SUMIFS(Investimentos!$P$6:$P$100,Investimentos!$C$6:$C$100,'Terceiros-Resumo'!B13,Investimentos!$I$6:$I$100,"Terceiros",Investimentos!$F$6:$F$100,'Terceiros-Resumo'!C13) -> 8163.26 | E13: 61.528.030/0001-60
B14: Novo Copack | C14: Tetra Pak | D14: =SUMIFS(Investimentos!$P$6:$P$100,Investimentos!$C$6:$C$100,'Terceiros-Resumo'!B14,Investimentos!$I$6:$I$100,"Terceiros",Investimentos!$F$6:$F$100,'Terceiros-Resumo'!C14) -> 0
B15: Macronutrientes | C15: Tetra Pak | D15: =SUMIFS(Investimentos!$P$6:$P$100,Investimentos!$C$6:$C$100,'Terceiros-Resumo'!B15,Investimentos!$I$6:$I$100,"Terceiros",Investimentos!$F$6:$F$100,'Terceiros-Resumo'!C15) -> 0
B16: Novos produtos | C16: Tetra Pak | D16: =SUMIFS(Investimentos!$P$6:$P$100,Investimentos!$C$6:$C$100,'Terceiros-Resumo'!B16,Investimentos!$I$6:$I$100,"Terceiros",Investimentos!$F$6:$F$100,'Terceiros-Resumo'!C16) -> 8163.26
B17: Micronutrientes | C17: Tetra Pak | D17: =SUMIFS(Investimentos!$P$6:$P$100,Investimentos!$C$6:$C$100,'Terceiros-Resumo'!B17,Investimentos!$I$6:$I$100,"Terceiros",Investimentos!$F$6:$F$100,'Terceiros-Resumo'!C17) -> 0
B18: Novas matérias prima | C18: Tetra Pak | D18: =SUMIFS(Investimentos!$P$6:$P$100,Investimentos!$C$6:$C$100,'Terceiros-Resumo'!B18,Investimentos!$I$6:$I$100,"Terceiros",Investimentos!$F$6:$F$100,'Terceiros-Resumo'!C18) -> 0
B19: Melhoria de produto | C19: Labor Três Laboratórios e Consultoria Técnica Ltda | D19: =SUMIFS(Investimentos!$P$6:$P$100,Investimentos!$C$6:$C$100,'Terceiros-Resumo'!B19,Investimentos!$I$6:$I$100,"Terceiros",Investimentos!$F$6:$F$100,'Terceiros-Resumo'!C19) -> 497 | E19: 02.021.076/0001-29
B20: Novo Copack | C20: Labor Três Laboratórios e Consultoria Técnica Ltda | D20: =SUMIFS(Investimentos!$P$6:$P$100,Investimentos!$C$6:$C$100,'Terceiros-Resumo'!B20,Investimentos!$I$6:$I$100,"Terceiros",Investimentos!$F$6:$F$100,'Terceiros-Resumo'!C20) -> 540
B21: Macronutrientes | C21: Labor Três Laboratórios e Consultoria Técnica Ltda | D21: =SUMIFS(Investimentos!$P$6:$P$100,Investimentos!$C$6:$C$100,'Terceiros-Resumo'!B21,Investimentos!$I$6:$I$100,"Terceiros",Investimentos!$F$6:$F$100,'Terceiros-Resumo'!C21) -> 0
B22: Novos produtos | C22: Labor Três Laboratórios e Consultoria Técnica Ltda | D22: =SUMIFS(Investimentos!$P$6:$P$100,Investimentos!$C$6:$C$100,'Terceiros-Resumo'!B22,Investimentos!$I$6:$I$100,"Terceiros",Investimentos!$F$6:$F$100,'Terceiros-Resumo'!C22) -> 902.83333
B23: Micronutrientes | C23: Labor Três Laboratórios e Consultoria Técnica Ltda | D23: =SUMIFS(Investimentos!$P$6:$P$100,Investimentos!$C$6:$C$100,'Terceiros-Resumo'!B23,Investimentos!$I$6:$I$100,"Terceiros",Investimentos!$F$6:$F$100,'Terceiros-Resumo'!C23) -> 0
B24: Novas matérias prima | C24: Labor Três Laboratórios e Consultoria Técnica Ltda | D24: =SUMIFS(Investimentos!$P$6:$P$100,Investimentos!$C$6:$C$100,'Terceiros-Resumo'!B24,Investimentos!$I$6:$I$100,"Terceiros",Investimentos!$F$6:$F$100,'Terceiros-Resumo'!C24) -> 2741.1667
B25: Melhoria de produto | C25: BIOAGRI Análises de Alimentos Ltda | D25: =SUMIFS(Investimentos!$P$6:$P$100,Investimentos!$C$6:$C$100,'Terceiros-Resumo'!B25,Investimentos!$I$6:$I$100,"Terceiros",Investimentos!$F$6:$F$100,'Terceiros-Resumo'!C25) -> 0 | E25: 00.000.410/0001-32
B26: Novo Copack | C26: BIOAGRI Análises de Alimentos Ltda | D26: =SUMIFS(Investimentos!$P$6:$P$100,Investimentos!$C$6:$C$100,'Terceiros-Resumo'!B26,Investimentos!$I$6:$I$100,"Terceiros",Investimentos!$F$6:$F$100,'Terceiros-Resumo'!C26) -> 0
B27: Macronutrientes | C27: BIOAGRI Análises de Alimentos Ltda | D27: =SUMIFS(Investimentos!$P$6:$P$100,Investimentos!$C$6:$C$100,'Terceiros-Resumo'!B27,Investimentos!$I$6:$I$100,"Terceiros",Investimentos!$F$6:$F$100,'Terceiros-Resumo'!C27) -> 0
B28: Novos produtos | C28: BIOAGRI Análises de Alimentos Ltda | D28: =SUMIFS(Investimentos!$P$6:$P$100,Investimentos!$C$6:$C$100,'Terceiros-Resumo'!B28,Investimentos!$I$6:$I$100,"Terceiros",Investimentos!$F$6:$F$100,'Terceiros-Resumo'!C28) -> 0
B29: Micronutrientes | C29: BIOAGRI Análises de Alimentos Ltda | D29: =SUMIFS(Investimentos!$P$6:$P$100,Investimentos!$C$6:$C$100,'Terceiros-Resumo'!B29,Investimentos!$I$6:$I$100,"Terceiros",Investimentos!$F$6:$F$100,'Terceiros-Resumo'!C29) -> 0
B30: Novas matérias prima | C30: BIOAGRI Análises de Alimentos Ltda | D30: =SUMIFS(Investimentos!$P$6:$P$100,Investimentos!$C$6:$C$100,'Terceiros-Resumo'!B30,Investimentos!$I$6:$I$100,"Terceiros",Investimentos!$F$6:$F$100,'Terceiros-Resumo'!C30) -> 444.25
B31: Melhoria de produto | C31: Nutrimento Gestão de Dados Empresariais Ltda. | D31: =Terceiros!D38 -> 17089.157
B32: Novo Copack | C32: Nutrimento Gestão de Dados Empresariais Ltda. | D32: =Terceiros!D39 -> 8544.5784
B33: Macronutrientes | C33: Nutrimento Gestão de Dados Empresariais Ltda. | D33: =Terceiros!#REF! -> #REF!
B34: Novos produtos | C34: Nutrimento Gestão de Dados Empresariais Ltda. | D34: =Terceiros!D40 -> 34178.314
B35: Micronutrientes | C35: Nutrimento Gestão de Dados Empresariais Ltda. | D35: =Terceiros!#REF! -> #REF!
B36: Novas matérias prima | C36: Nutrimento Gestão de Dados Empresariais Ltda. | D36: =Terceiros!D41 -> 25633.735
B37: Melhoria de produto | C37: L Dutra Serviços ME | D37: =Terceiros!E38 -> 613.20755
B38: Novo Copack | C38: L Dutra Serviços ME | D38: =Terceiros!E39 -> 0
B39: Macronutrientes | C39: L Dutra Serviços ME | D39: =Terceiros!#REF! -> #REF!
B40: Novos produtos | C40: L Dutra Serviços ME | D40: =Terceiros!E40 -> 148.58491
B41: Micronutrientes | C41: L Dutra Serviços ME | D41: =Terceiros!#REF! -> #REF!
B42: Novas matérias prima | C42: L Dutra Serviços ME | D42: =Terceiros!E41 -> 0
D43: =SUM(D13:D42) -> #REF!

Sheet Salário e Custo Hora
B1: PRODIET NUTRIÇÃO LTDA.
B2: INOVAÇÃO TECNOLÓGICA 2013
B3: Salário bruto e Custo Hora
B5: Encargos sobre folha
B6: INSS | D6: FGTS | E6: Férias | F6: 13º | G6: Total
B7: 0.2333 | D7: 0.08 | E7: =((1/12)+(1/12/3))*(1+$D$7+$B$7) -> 0.14592222 | F7: =(1/12)*(1+$D$7+$B$7) -> 0.10944167 | G7: =SUM(B7:F7) -> 0.56866389
B9: Salário Bruto
B10: Nome | C10: Apelido | D10: Dedicação | E10: 41275 | F10: 41306 | G10: 41334 | H10: 41365 | I10: 41395 | J10: 41426 | K10: 41456 | L10: 41487 | M10: 41518 | N10: 41548 | O10: 41579 | P10: 41609 | Q10: Total Ano
A11: (a) | B11: Erica Ferreira Serra | C11: Érica Serra | D11: Exclusiva | E11: 3070.48 | F11: 3070.48 | G11: =F11 -> 3070.48 | H11: =G11 -> 3070.48 | I11: =H11 -> 3070.48 | J11: =I11 -> 3070.48 | K11: 3316.12 | L11: 3316.12 | M11: 3316.12 | N11: 3316.12 | O11: 3316.12 | P11: 3316.12 | Q11: =SUM(E11:P11) -> 38319.6
B12: Felipe Camargo Chavita | C12: Felipe Chavita | D12: Parcial | K12: 1317 | L12: 1317 | M12: 1317 | N12: 1317 | O12: 1317 | P12: 1317 | Q12: =SUM(E12:P12) -> 7902
B13: Larissa Suellen da Silva | C13: Larissa | D13: Parcial | E13: 1820.59 | F13: =E13 -> 1820.59 | G13: 1820.59 | H13: 1820.59 | I13: 1820.59 | J13: 1820.59 | K13: 1820.59 | L13: 1820.59 | M13: 1820.59 | N13: 1820.59 | O13: 1820.59 | P13: 2093 | Q13: =SUM(E13:P13) -> 22119.49
A14: (b) | B14: Luciana Dutra | C14: Luciana Dutra | D14: Parcial | E14: 5416.33 | F14: =E14 -> 5416.33 | G14: =F14 -> 5416.33 | H14: =G14 -> 5416.33 | I14: =H14 -> 5416.33 | J14: =I14 -> 5416.33 | K14: =J14 -> 5416.33 | L14: 5416.33 | M14: 0 | N14: 0 | O14: 0 | P14: 0 | Q14: =SUM(E14:P14) -> 43330.64
A15: (c) | B15: Vera Lucia Leite Moura | C15: Vera Moura | D15: Parcial | E15: 5194.74 | F15: =E15 -> 5194.74 | G15: =F15 -> 5194.74 | H15: =G15 -> 5194.74 | I15: =H15 -> 5194.74 | J15: =I15 -> 5194.74 | K15: =J15 -> 5194.74 | L15: =K15 -> 5194.74 | M15: 0 | N15: 0 | O15: 0 | P15: 0 | Q15: =SUM(E15:P15) -> 41557.92
B18: Salário Bruto com encargos | E18: 1 TRIM | F18: 1 TRIM | G18: 1 TRIM | H18: 2 TRIM | I18: 2 TRIM | J18: 2 TRIM | K18: 3 TRIM | L18: 3 TRIM | M18: 3 TRIM | N18: 4 TRIM | O18: 4 TRIM | P18: 4 TRIM
B19: Nome | C19: Apelido | D19: Dedicação | E19: 41275 | F19: 41306 | G19: 41334 | H19: 41365 | I19: 41395 | J19: 41426 | K19: 41456 | L19: 41487 | M19: 41518 | N19: 41548 | O19: 41579 | P19: 41609 | Q19: Total Ano
B20: Erica Ferreira Serra | C20: Érica Serra | D20: Exclusiva | E20: =E11*(1+$G$7) -> 4816.5511 | F20: =F11*(1+$G$7) -> 4816.5511 | G20: =G11*(1+$G$7) -> 4816.5511 | H20: =H11*(1+$G$7) -> 4816.5511 | I20: =I11*(1+$G$7) -> 4816.5511 | J20: =J11*(1+$G$7) -> 4816.5511 | K20: =K11*(1+$G$7) -> 5201.8777 | L20: =L11*(1+$G$7) -> 5201.8777 | ... P20: =P11*(1+$G$7) -> 5201.8777 | Q20: =SUM(E20:P20) -> 60110.573
B21: Felipe Camargo Chavita | C21: Felipe Chavita | D21: Parcial | E21: =E12*(1+$G$7) -> 0 | F21: =F12*(1+$G$7) -> 0 | G21: =G12*(1+$G$7) -> 0 | H21: =H12*(1+$G$7) -> 0 | I21: =I12*(1+$G$7) -> 0 | J21: =J12*(1+$G$7) -> 0 | K21: =K12*(1+$G$7) -> 2065.9303 | L21: =L12*(1+$G$7) -> 2065.9303 | ... P21: =P12*(1+$G$7) -> 2065.9303 | Q21: =SUM(E21:P21) -> 12395.582
B22: Larissa Suellen da Silva | C22: Larissa | D22: Parcial | E22: =E13*(1+$G$7) -> 2855.8938 | F22: =F13*(1+$G$7) -> 2855.8938 | G22: =G13*(1+$G$7) -> 2855.8938 | H22: =H13*(1+$G$7) -> 2855.8938 | I22: =I13*(1+$G$7) -> 2855.8938 | J22: =J13*(1+$G$7) -> 2855.8938 | K22: =K13*(1+$G$7) -> 2855.8938 | L22: =L13*(1+$G$7) -> 2855.8938 | ... P22: =P13*(1+$G$7) -> 3283.2135 | Q22: =SUM(E22:P22) -> 34698.045
B23: Luciana Dutra | C23: Luciana Dutra | D23: Parcial | E23: =E14*(1+$G$7) -> 8496.4013 | F23: =F14*(1+$G$7) -> 8496.4013 | G23: =G14*(1+$G$7) -> 8496.4013 | H23: =H14*(1+$G$7) -> 8496.4013 | I23: =I14*(1+$G$7) -> 8496.4013 | J23: =J14*(1+$G$7) -> 8496.4013 | K23: =K14*(1+$G$7) -> 8496.4013 | L23: =L14*(1+$G$7) -> 8496.4013 | ... P23: =P14*(1+$G$7) -> 0 | Q23: =SUM(E23:P23) -> 67971.21 | R23: Obs: É terceiro a partir de set/13
B24: Vera Lucia Leite Moura | C24: Vera Moura | D24: Parcial | E24: =E15*(1+$G$7) -> 8148.8011 | F24: =F15*(1+$G$7) -> 8148.8011 | G24: =G15*(1+$G$7) -> 8148.8011 | H24: =H15*(1+$G$7) -> 8148.8011 | I24: =I15*(1+$G$7) -> 8148.8011 | J24: =J15*(1+$G$7) -> 8148.8011 | K24: =K15*(1+$G$7) -> 8148.8011 | L24: =L15*(1+$G$7) -> 8148.8011 | ... P24: =P15*(1+$G$7) -> 0 | Q24: =SUM(E24:P24) -> 65190.408 | R24: Obs: É terceiro a partir de set/13
B26: Custo Hora com encargos
B27: Nome | C27: Apelido | D27: Dedicação | E27: 41275 | F27: 41306 | G27: 41334 | H27: 41365 | I27: 41395 | J27: 41426 | K27: 41456 | L27: 41487 | M27: 41518 | N27: 41548 | O27: 41579 | P27: 41609
B28: Erica Ferreira Serra | C28: =C11 -> Érica Serra | D28: Exclusiva | E28: =E20/E$36 -> 25.817705 | F28: =F20/F$36 -> 28.399476 | G28: =G20/G$36 -> 28.399476 | H28: =H20/H$36 -> 25.817705 | I28: =I20/I$36 -> 27.04712 | J28: =J20/J$36 -> 28.399476 | K28: =K20/K$36 -> 26.670825 | L28: =L20/L$36 -> 27.883135 | ... P28: =P20/P$36 -> 29.210903
B29: Felipe Camargo Chavita | C29: =C12 -> Felipe Chavita | D29: Parcial | E29: =E21/E$36 -> 0 | F29: =F21/F$36 -> 0 | G29: =G21/G$36 -> 0 | H29: =H21/H$36 -> 0 | I29: =I21/I$36 -> 0 | J29: =J21/J$36 -> 0 | K29: =K21/K$36 -> 10.592342 | L29: =L21/L$36 -> 11.073812 | ... P29: =P21/P$36 -> 11.601136
B30: Larissa Suellen da Silva | C30: =C13 -> Larissa | D30: Parcial | E30: =E22/E$36 -> 15.308179 | F30: =F22/F$36 -> 16.838996 | G30: =G22/G$36 -> 16.838996 | H30: =H22/H$36 -> 15.308179 | I30: =I22/I$36 -> 16.037139 | J30: =J22/J$36 -> 16.838996 | K30: =K22/K$36 -> 14.642606 | L30: =L22/L$36 -> 15.308179 | ... P30: =P22/P$36 -> 18.436734
B31: Luciana Dutra | C31: =C14 -> Luciana Dutra | D31: Parcial | E31: =E23/E$36 -> 45.54246 | F31: =F23/F$36 -> 50.096706 | G31: =G23/G$36 -> 50.096706 | H31: =H23/H$36 -> 45.54246 | I31: =I23/I$36 -> 47.711148 | J31: =J23/J$36 -> 50.096706 | K31: =K23/K$36 -> 43.562353 | L31: =L23/L$36 -> 45.54246 | ... P31: =P23/P$36 -> 0
B32: Vera Lucia Leite Moura | C32: =C15 -> Vera Moura | D32: Parcial | E32: =E24/E$36 -> 43.679251 | F32: =F24/F$36 -> 48.047176 | G32: =G24/G$36 -> 48.047176 | H32: =H24/H$36 -> 43.679251 | I32: =I24/I$36 -> 45.759215 | J32: =J24/J$36 -> 48.047176 | K32: =K24/K$36 -> 41.780153 | L32: =L24/L$36 -> 43.679251 | ... P32: =P24/P$36 -> 0
B34: Horas Úteis - CWB | E34: 41275 | F34: 41306 | G34: 41334 | H34: 41365 | I34: 41395 | J34: 41426 | K34: 41456 | L34: 41487 | M34: 41518 | N34: 41548 | O34: 41579 | P34: 41609
B35: Dias Úteis | E35: =VLOOKUP(E34,'Dias Úteis'!$E$7:$G$18,3,FALSE) -> 22 | F35: =VLOOKUP(F34,'Dias Úteis'!$E$7:$G$18,3,FALSE) -> 20 | G35: =VLOOKUP(G34,'Dias Úteis'!$E$7:$G$18,3,FALSE) -> 20 | H35: =VLOOKUP(H34,'Dias Úteis'!$E$7:$G$18,3,FALSE) -> 22 | I35: =VLOOKUP(I34,'Dias Úteis'!$E$7:$G$18,3,FALSE) -> 21 | J35: =VLOOKUP(J34,'Dias Úteis'!$E$7:$G$18,3,FALSE) -> 20 | K35: =VLOOKUP(K34,'Dias Úteis'!$E$7:$G$18,3,FALSE) -> 23 | L35: =VLOOKUP(L34,'Dias Úteis'!$E$7:$G$18,3,FALSE) -> 22 | ... P35: =VLOOKUP(P34,'Dias Úteis'!$E$7:$G$18,3,FALSE) -> 21
A36: (d) | B36: Horas Úteis | E36: =8.48*E35 -> 186.56 | F36: =8.48*F35 -> 169.6 | G36: =8.48*G35 -> 169.6 | H36: =8.48*H35 -> 186.56 | I36: =8.48*I35 -> 178.08 | J36: =8.48*J35 -> 169.6 | K36: =8.48*K35 -> 195.04 | L36: =8.48*L35 -> 186.56 | ... P36: =8.48*P35 -> 178.08
B39: Detalhamento da Apuração sem exclusão de inovação
A41: (a) | B41: A Érica Serra tem o cargo de Analista de P&D. Foi nos enviado descrição de cargo (doc 93)
A42: (b) | B42: A Luciana Dutra passou a ser PJ (LDUTRA) em setembro/2013. As notas fiscais foram enviadas pela PRODIET (doc 91)
A43: (c) | B43: A Vera Moura passou a ser PJ (VLL Moura Serviços de Apoio Administrativo ).
A44: (d) | B44: Confimado com Alexandre Velozo, via fone, que os funcionários trabalham 44 horas semanais.
B48: Felipe Camargo Chavita | C48: Graduado
B49: Larissa Suellen da Silva | C49: Graduado
B50: Erica Ferreira Serra | C50: Pós-Graduado
B51: Vera Lucia Leite Moura | C51: Graduado
B52: Luciana Dutra | C52: Pós-Graduado

Sheet Projetos
A1: PRODIET NUTRIÇÃO
A2: INOVAÇÃO TECNOLÓGICA 2013
A3: Projetos
D4: (a) | H4: (b) | I4: (c)
B5: Projeto | C5: Descrição | D5: RH (parcial inovação) | E5: Propoção Érica | F5: RH (exclusivo) | G5: Total RH | H5: Material | I5: Terceiros | J5: Total
B6: Melhoria de produto | C6: Foram feitas melhorias significativas em diversos produtos da empresa. As melhorias estão voltadas para aumentar a fluidez para sonda (administração por sonda); estabilidade de pH; embalagem; e melhoria sensorial (sabores e aromas, por exemplo) . Para uma gama de produtos foi testado trocar componente da fórmula atual, o que levou a uma série de testes de estabilidade do novo componente na fórmula, característica final do produto e teste de administração do produto. No desenvolvimento de embalagens devem ser analisados e testados diversos fatores por se tratarem de produtos alimentícios e hospitalares, como: conservação do produto, enviolabilidade, manuseio seguro, reações de oxidação, contaminação microbiolágica, entre outros. Foram realizados testes de validade do produto na nova embalagem; produção de lote piloto; testes microbiológicos e análise da característica final do produto. A aplicação de novos ensaios em ingredientes, os ajustes de processos através de teste de interação de ingredientes, assim como as interferências de processos (mistura-hidratação, homogeneização, esterilização, textura) e análises (físico-química, microbiológica, administração e sensorial) foram analisados sob a ótica dos processos industriais e regulatórios aos quais cada produto é submetido. Algumas das linhas de produtos alteradas: Trophic, Energyzip, Renalmax. | D6: =SUMIFS(Investimentos!$P$6:$P$100,Investimentos!$I$6:$I$100,D$5,Investimentos!$C$6:$C$100,Projetos!$B6) -> 1379.5665 | E6: 0.2 | F6: =E6*Resumo!$H$9 -> 12022.115 | G6: =D6+F6 -> 13401.681 | H6: =SUMIFS(Investimentos!$P$6:$P$100,Investimentos!$I$6:$I$100,H$5,Investimentos!$C$6:$C$100,Projetos!$B6) -> 961.25333 | I6: =SUMIFS(Investimentos!$P$6:$P$100,Investimentos!$I$6:$I$100,I$5,Investimentos!$C$6:$C$100,Projetos!$B6)+SUMIFS(Terceiros!$F$38:$F$41,Terceiros!$B$38:$B$41,Projetos!B6) -> 26362.624 | J6: =SUM(G6:I6) -> 40725.559
B7: Novo Copack | C7: Desenvolvimento de produto junto aos parceiros de produção.... | D7: =SUMIFS(Investimentos!$P$6:$P$100,Investimentos!$I$6:$I$100,D$5,Investimentos!$C$6:$C$100,Projetos!$B7) -> 101.01352 | E7: 0.1 | F7: =E7*Resumo!$H$9 -> 6011.0573 | G7: =D7+F7 -> 6112.0708 | H7: =SUMIFS(Investimentos!$P$6:$P$100,Investimentos!$I$6:$I$100,H$5,Investimentos!$C$6:$C$100,Projetos!$B7) -> 2304.57 | I7: =SUMIFS(Investimentos!$P$6:$P$100,Investimentos!$I$6:$I$100,I$5,Investimentos!$C$6:$C$100,Projetos!$B7)+SUMIFS(Terceiros!$F$38:$F$41,Terceiros!$B$38:$B$41,Projetos!B7) -> 9084.5784 | J7: =SUM(G7:I7) -> 17501.219
B8: Novos produtos | C8: Estudo, pesquisa e desenvolvimento de novos produtos para agregar a gama de produtos da empresa. A equipe desenvolveu quatro produtos durante o ano de 2013: Obesidade Bariátrica, Suplemento em pó, Energyzip 1.0, Trophic Soya. O produto Obesidade Bariátrica é um suplemento para auxiliar na dieta de pessoas com obesidade mórbida no pré e no pós-operatório e é completamente novo para a empresa e ainda está em fase de testes da fórmula. O Suplemento em pó ainda está em fase de testes da formulação. É um produto que deve ter os nutrientes necessários a uma dieta de (...) e deve ser facilmente misturado a meio líquido e tornar-se homogêneo, sem decantar. O Energezyp 1.0 e o Trophic Soya já estão em fases de teste piloto e de validade de produto. Caso os produtos apresentem testes negativos, eles voltam para alteração de fórmula e novas análises de componentes em laboratório. | D8: =SUMIFS(Investimentos!$P$6:$P$100,Investimentos!$I$6:$I$100,D$5,Investimentos!$C$6:$C$100,Projetos!$B8) -> 28.436973 | E8: 0.4 | F8: =E8*Resumo!$H$9 -> 24044.229 | G8: =D8+F8 -> 24072.666 | H8: =SUMIFS(Investimentos!$P$6:$P$100,Investimentos!$I$6:$I$100,H$5,Investimentos!$C$6:$C$100,Projetos!$B8) -> 10531.68 | I8: =SUMIFS(Investimentos!$P$6:$P$100,Investimentos!$I$6:$I$100,I$5,Investimentos!$C$6:$C$100,Projetos!$B8)+SUMIFS(Terceiros!$F$38:$F$41,Terceiros!$B$38:$B$41,Projetos!B8) -> 43392.992 | J8: =SUM(G8:I8) -> 77997.338
B9: Novas matérias prima | C9: Pesquisa de novos insumos para substituição dos existentes ou para inclusão de nova matéria-prima a produtos existentes, aumentando ou alterando nutrientes da formulação do produto. Diversos testes são necessários na troca ou inclusão de nova matéria-prima. Não é uma simples troca de fornecedor. São feitos análises em laboratório para testar como a nova matéria-prima se adapta a formulação e se não traz algum ponto negativo em relação à antiga formulação. Após análises em laboratório, é rodado teste piloto para teste de validade, composição final, sensorial e de administração do produto. Foram testatos os seguintes nutrientes no ano de 2013 em produtos diversos: Carboidrato Globe 18, Carboidrato Maltogill, Gordura, Proteína Caseinato de Cálcio, Proteína Isolada de Soja, Minerais Nutrix, Vitaminas. | D9: =SUMIFS(Investimentos!$P$6:$P$100,Investimentos!$I$6:$I$100,D$5,Investimentos!$C$6:$C$100,Projetos!$B9) -> 399.34323 | E9: 0.3 | F9: =E9*Resumo!$H$9 -> 18033.172 | G9: =D9+F9 -> 18432.515 | H9: =SUMIFS(Investimentos!$P$6:$P$100,Investimentos!$I$6:$I$100,H$5,Investimentos!$C$6:$C$100,Projetos!$B9) -> 1024.6667 | I9: =SUMIFS(Investimentos!$P$6:$P$100,Investimentos!$I$6:$I$100,I$5,Investimentos!$C$6:$C$100,Projetos!$B9)+SUMIFS(Terceiros!$F$38:$F$41,Terceiros!$B$38:$B$41,Projetos!B9) -> 28819.152 | J9: =SUM(G9:I9) -> 48276.334
D10: =SUM(D6:D9) -> 1908.3602 | E10: =SUM(E6:E9) -> 1 | F10: =SUM(F6:F9) -> 60110.573 | G10: =SUM(G6:G9) -> 62018.933 | H10: =SUM(H6:H9) -> 14822.17 | I10: =SUM(I6:I9) -> 107659.35 | J10: =SUM(G10:I10) -> 184500.45
B14: (a) | C14: Soma de "RH (Parcial inovação)" da coluna "Natureza" da planilha Investimentos e Soma do Total da Érica multiplicado por uma proporção inventada por mim (e que nça foi pro cliente, pode trocar a vontade)
B15: (b) | C15: Soma de "Material" da coluna "Natureza" da planilha Investimentos
B16: (c) | C16: Soma de "Terceiros" da coluna "Natureza" da planilha Investimentos + Soma dos valores da planilha de Terceiros

Sheet Dias Úteis
B5: FERIADOS EM CURITIBA | E5: Total de Dias úteis por mês
B6: Data | C6: Feriado | E6: Dt. Inicial | F6: Dt. Final | G6: Dias úteis
B7: 41362 | C7: Sexta-feira da Paixão | E7: 41275 | F7: 41305 | G7: =NETWORKDAYS(E7,F7,$B$7:$B$17) -> 22
B8: 41424 | C8: Corpus Christi | E8: 41306 | F8: 41333 | G8: =NETWORKDAYS(E8,F8,$B$7:$B$17) -> 20
B9: 41525 | C9: Nossa Senhora da Luz dos Pinhais | E9: 41334 | F9: 41364 | G9: =NETWORKDAYS(E9,F9,$B$7:$B$17) -> 20
B10: 41275 | C10: Confraternização Universal | E10: 41365 | F10: 41394 | G10: =NETWORKDAYS(E10,F10,$B$7:$B$17) -> 22
B11: 41385 | C11: Tiradentes | E11: 41395 | F11: 41425 | G11: =NETWORKDAYS(E11,F11,$B$7:$B$17) -> 21
B12: 41395 | C12: Dia do Trabalho | E12: 41426 | F12: 41455 | G12: =NETWORKDAYS(E12,F12,$B$7:$B$17) -> 20
B13: 41524 | C13: Independência do Brasil | E13: 41456 | F13: 41486 | G13: =NETWORKDAYS(E13,F13,$B$7:$B$17) -> 23
B14: 41559 | C14: Nossa Senhora Aparecida | E14: 41487 | F14: 41517 | G14: =NETWORKDAYS(E14,F14,$B$7:$B$17) -> 22
B15: 41580 | C15: Finados | E15: 41518 | F15: 41547 | G15: =NETWORKDAYS(E15,F15,$B$7:$B$17) -> 21
B16: 41593 | C16: Proclamação da República | E16: 41548 | F16: 41578 | G16: =NETWORKDAYS(E16,F16,$B$7:$B$17) -> 23
B17: 41633 | C17: Natal | E17: 41579 | F17: 41608 | G17: =NETWORKDAYS(E17,F17,$B$7:$B$17) -> 20
E18: 41609 | F18: 41639 | G18: =NETWORKDAYS(E18,F18,$B$7:$B$17) -> 21
B39: Detalhamento da Apuração sem exclusão de inovação

Sheet Valores desclassificados
A1: PRODIET NUTRIÇÃO
A2: INOVAÇÃO TECNOLÓGICA 2013
A3: Valores retirados do cálculo por falta de comprovação
N5: =SUM(N7:N46) -> 4665.0815
A6: DOC | B6: PROJETO | C6: SUB PROJETO | D6: PRODUTO | E6: RECURSO | F6: ATIVIDADE | G6: NATUREZA | H6: DATA | I6: Mês | J6: Trimestre | K6: MEDIDA | L6: QTD | M6: UNITÁRIO | N6: TOTAL | O6: OBS
A7: 65 | B7: Novos produtos | C7: Piloto | D7: Energyzip 1.0 | E7: Erica Serra | F7: Translado - Avião - Teste piloto UHT ida | G7: Material | H7: 41584 | I7: 11 | J7: 4 TRIM | K7: Trecho | L7: 1 | M7: 0 | N7: =M7*L7 -> 0 | O7: Só tem cartão de embargue. Não tem comporvante de pagamento com valor da passagem
A8: 65 | B8: Novos produtos | C8: Piloto | D8: Energyzip 1.0 | E8: Erica Serra | F8: Translado - Avião - Teste piloto UHT volta | G8: Material | H8: 41584 | I8: 11 | J8: 4 TRIM | K8: Trecho | L8: 1 | M8: 0 | N8: =M8*L8 -> 0 | O8: Só tem cartão de embargue. Não tem comporvante de pagamento com valor da passagem
A9: 99 | B9: Novos produtos | C9: Congresso - ILSI | D9: Suplemento em pó | E9: TAM | F9: Translado até o curso | G9: Material | H9: 41606 | I9: 11 | J9: 4 TRIM | K9: Trecho | L9: 1 | M9: 0 | N9: =M9*L9 -> 0 | O9: Só tem cartão de embargue. Não tem comporvante de pagamento com valor da passagem
A10: 103 | B10: Novos produtos | C10: Congresso - ILSI | D10: Suplemento em pó | E10: Taxi | F10: Translado até o curso | G10: Material | H10: 41606 | I10: 11 | J10: 4 TRIM | K10: Trecho | L10: 4 | M10: 38.333333 | N10: =M10*L10 -> 153.33333 | O10: Documento com 4 vouchers, mas são todos de empresa de taxi de curitiba incluindo o com o embarque em congonhas. Desclassifiquei a despesa
A11: 71 | B11: Novos produtos | C11: Piloto | D11: Trophic Soya | E11: Érica Serra | F11: Paassagem aérea de ida Curitiba-Campinas - Teste Piloto de produto no ITAL – Instituto de Tecnologia de Alimentos. Campinas-SP. (AZUL) | G11: Material | H11: 41359 | I11: 3 | J11: 1 TRIM | K11: Trecho | L11: 1 | M11: 0 | N11: =M11*L11 -> 0 | O11: Só tem cartão de embargue. Não tem comporvante de pagamento com valor da passagem
A12: 71 | B12: Novos produtos | C12: Piloto | D12: Trophic Soya | E12: Érica Serra | F12: Paassagem aérea de volta Curitiba-Campinas - Teste Piloto de produto no ITAL – Instituto de Tecnologia de Alimentos. Campinas-SP.(AZUL) | G12: Material | H12: 41359 | I12: 3 | J12: 1 TRIM | K12: Trecho | L12: 1 | M12: 0 | N12: =M12*L12 -> 0 | O12: Só tem cartão de embargue. Não tem comporvante de pagamento com valor da passagem
B13: Novos produtos | C13: Piloto | D13: Trophic Soya | E13: Insumos | F13: Lote piloto | G13: Material | H13: 41359 | I13: 3 | J13: 1 TRIM | K13: Diversos | L13: 0 | M13: 0 | N13: =M13*L13 -> 0 | O13: Não sei nem pq foi listado
B14: Novos produtos | C14: Piloto | D14: Energyzip 1.0 | E14: Érica Serra | F14: Acompanhamento de desenvolvimento | G14: RH (Parcial inovação) | H14: 41584 | I14: 11 | J14: 4 TRIM | K14: Lanche | L14: 1 | M14: 27.808134 | N14: =M14*L14 -> 27.808134 | O14: Não sei nem pq foi listado
A15: 113 | B15: Novo Copack | C15: Produto Líquido | D15: Castrolanda | E15: Vera Moura | F15: Estadia Slaviero Suites | G15: Material | H15: 41626 | I15: 12 | J15: 4 TRIM | K15: Diária | L15: 2 | M15: 208 | N15: =M15*L15 -> 416 | O15: A Vera foi desconsiderada para o Cálculo por ser apoio administrativo
B16: Novo Copack | C16: Produto Líquido | D16: Castrolanda | E16: Larissa | F16: Shelf Life | G16: RH (Parcial inovação) | H16: 41466 | I16: 7 | J16: 3 TRIM | K16: Hora | M16: 13.275654 | N16: =M16*L16 -> 0 | O16: Não sei nem pq foi listado
B17: Novo Copack | C17: Produto Líquido | D17: Castrolanda | E17: Oleo de Canôla | F17: Material para teste | G17: Material | H17: 41456 | I17: 7 | J17: 3 TRIM | K17: Unidade | L17: 40 | M17: 4.69 | N17: =M17*L17 -> 187.6 | O17: Não sei nem pq foi listado
B18: Novo Copack | C18: Produto Líquido | D18: Castrolanda | E18: Oleo de milho | F18: Material para teste | G18: Material | H18: 41456 | I18: 7 | J18: 3 TRIM | K18: Unidade | L18: 100 | M18: 5.39 | N18: =M18*L18 -> 539 | O18: Não sei nem pq foi listado
B19: Novo Copack | C19: Produto Líquido | D19: Castrolanda | E19: Estadia | F19: Acompanhar teste 3 | G19: Material | H19: 41627 | I19: 12 | J19: 4 TRIM | K19: Diária | L19: 2 | M19: 208 | N19: =M19*L19 -> 416 | O19: Não sei nem pq foi listado
B20: Novo Copack | C20: Produto Líquido | D20: Castrolanda | E20: Translado | F20: Acompanhar teste 3 (ida) | G20: Material | H20: 41626 | I20: 12 | J20: 4 TRIM | K20: Trecho | L20: 1 | M20: 353.96 | N20: =M20*L20 -> 353.96 | O20: Não sei nem pq foi listado
B21: Novo Copack | C21: Produto Líquido | D21: Castrolanda | E21: Translado | F21: Acompanhar teste 3 (volta) | G21: Material | H21: 41627 | I21: 12 | J21: 4 TRIM | K21: Trecho | L21: 1 | M21: 353.96 | N21: =M21*L21 -> 353.96 | O21: Não sei nem pq foi listado
B22: Novo Copack | C22: Produto Líquido | D22: Castrolanda | E22: Translado | F22: Acompanhar teste | G22: Material | H22: 41627 | I22: 12 | J22: 4 TRIM | K22: Trecho | L22: 1 | M22: 724.5 | N22: =M22*L22 -> 724.5 | O22: Não sei nem pq foi listado
A23: 113 | B23: Novo Copack | C23: Produto Líquido | D23: Castrolanda | E23: Vera Moura | F23: Aluguel carro | G23: Material | H23: 41627 | I23: 12 | J23: 4 TRIM | K23: Trecho | L23: 1 | M23: 724.5 | N23: =M23*L23 -> 724.5 | O23: A Vera foi desconsiderada para o Cálculo por ser apoio administrativo
A24: 113 | B24: Novo Copack | C24: Produto Líquido | D24: Castrolanda | E24: Vera Moura | F24: Passagem aérea | G24: Material | H24: 41627 | I24: 12 | J24: 4 TRIM | K24: Trecho | L24: 1 | M24: 707.92 | N24: =M24*L24 -> 707.92 | O24: A Vera foi desconsiderada para o Cálculo por ser apoio administrativo
A25: 118 | B25: Novo Copack | C25: Produto Líquido | D25: Castrolanda | E25: Luciana Dutra | F25: Alimentação | G25: Material | H25: 41465 | I25: 7 | J25: 3 TRIM | K25: Diversos | L25: 1 | M25: 60.5 | N25: =M25*L25 -> 60.5 | O25: Desconsiderado valor com alimentação
A26: 56 | B26: Novo Copack | C26: Produto Líquido | D26: Castrolanda | E26: Ana Celes | F26: Passagem aérea ida e volta de Rio de Janeiro-Curitiba pela Azul | G26: Material | H26: 41330 | I26: 2 | J26: 1 TRIM | K26: Trecho | L26: 1 | M26: 742.94 | N26: 0 | O26: Não tem lançamento de horas na plan de controle ou relatório que comprove que a viagem foi ligada a projeto de inovação
A27: 58 | B27: Novo Copack | C27: Produto Líquido | D27: Castrolanda | E27: Luciana Dutra | F27: Passagem aérea ida e volta SPO-CWB pela Gol - Acompanhar desenvolvimento | G27: Material | H27: 41330 | I27: 2 | J27: 1 TRIM | K27: Trecho | L27: 1 | M27: 1101.94 | N27: 0 | O27: Não tem lançamento de horas na plan de controle ou relatório que comprove que a viagem foi ligada a projeto de inovação
B28: Estabilidade | C28: Fórmula | D28: Diamax | E28: Fundação de Apoio a Univerdade de São Paulo FUSP | F28: Identificar na amostra do Trophic Fiber e do Diamax qual matéria-prima pode estar causando instabilidade | G28: Terceiros | H28: 41661 | I28: 2014 | K28: Hora | L28: 1 | M28: 500 | N28: 0 | O28: Despesa de 2014
A29: 6 | B29: Melhoria de produto | C29: Embalagem | D29: Emplas | E29: Luciana Dutra | F29: Análise de embalagens - O fornecedor trouxe uma nova embalagem para teste com o objetivo de diminuir o head space e possibilidade de aplicação e retenção de nitrogênio | G29: RH (Parcial inovação) | H29: 41486 | I29: 7 | J29: 3 TRIM | K29: Hora | L29: 0 | M29: 39.495616 | N29: 0 | O29: Não tem lançamento de horas na plan de controle
A30: 86 | E30: Vera Moura | F30: Acompanhamento de desenvolvimento, testes de envase, matéria prima e textura. | G30: RH (Parcial inovação) | H30: 41466 | I30: 7 | J30: 3 TRIM | K30: Hora | L30: 8.5 | M30: 0 | N30: 0 | O30: Lançamento incompleto na plan de controle
A31: 86 | E31: VLL Moura Serviços de Apoio Administrativo | F31: Acompanhamento de desenvolvimento, testes de envase, matéria prima e textura. | G31: Terceiros | H31: 41627 | I31: 12 | J31: 4 TRIM | K31: Hora | L31: 8 | M31: 0 | N31: 0 | O31: Terceiro não considerado
A32: 85 | D32: Suplementos em pó | E32: Lucas Torteli | G32: RH (Parcial inovação) | H32: 41577 | I32: 10 | J32: 4 TRIM | K32: Hora | L32: 0.66666667 | M32: 0 | N32: 0 | O32: Lançamento incompleto na plan de controle
A33: 85 | D33: Obesidade Bariátrica | E33: Lucas Torteli | G33: RH (Parcial inovação) | H33: 41577 | I33: 10 | J33: 4 TRIM | K33: Hora | L33: 0.66666667 | M33: 0 | N33: 0 | O33: Lançamento incompleto na plan de controle
A34: 85 | E34: Lucas Torteli | F34: Pesagem das 3OPs do teste Ital | G34: RH (Parcial inovação) | H34: 41582 | I34: 11 | J34: 4 TRIM | K34: Hora | L34: 3 | M34: 0 | N34: 0 | O34: Lançamento incompleto na plan de controle
A35: 82 | E35: Felipe Chavita | F35: Teste Ittal - Pesagem dos produtos | G35: RH (Parcial inovação) | H35: 41582 | I35: 11 | J35: 4 TRIM | K35: Hora | L35: 3 | M35: 11.044025 | N35: 0 | O35: Lançamento incompleto na plan de controle
A36: 83 | E36: Luciana Dutra | F36: Teste ITAL | G36: RH (Parcial inovação) | H36: 41359 | I36: 3 | J36: 1 TRIM | K36: Hora | L36: 10 | M36: 45.419958 | N36: 0 | O36: Lançamento incompleto na plan de controle
F37: Vera Moura | G37: Teste piloto | H37: RH (Parcial inovação) | I37: 41485 | J37: 7 | K37: 3 TRIM | L37: Hora | M37: 2.0052778 | N37: 0 | O37: Não tem lançamento de horas
F38: Vera Moura | G38: Teste piloto - 3 | H38: RH (Parcial inovação) | I38: 41485 | J38: 7 | K38: 3 TRIM | L38: Hora | M38: 0 | N38: 0 | O38: Não tem lançamento de horas
A39: 84 | B39: Detalhamento da Apuração sem exclusão de inovação | C39: Micronutrintes | D39: Minerais - Nutrix | E39: Larissa | F39: Shelf Life | G39: RH (Parcial inovação) | H39: 41359 | I39: 3 | J39: 1 TRIM | K39: Hora | L39: 1.08 | M39: 15.267002 | N39: 0 | O39: Não tem lançamento de horas
A40: 83 | B40: Melhoria de produto | C40: Estabilidade | D40: Nitrogênio | E40: Luciana Dutra | F40: Teste de inserção de nitrogênio - O objetivo do teste foi validar processo de inserção de N2 em embalagens que armazenam produtos em pó nos produtos Prodiet no atual processo industrial da New Millen | G40: RH (Parcial inovação) | H40: 41376 | I40: 4 | J40: 2 TRIM | K40: Hora | L40: 1.5 | M40: 41.290871 | N40: 0 | O40: Não tem lançamento de horas
A41: 83 | B41: Melhoria de produto | C41: Estabilidade | D41: KOH - Trophic Basic | E41: Luciana Dutra | F41: Shelf Life | G41: RH (Parcial inovação) | H41: 41466 | I41: 7 | J41: 3 TRIM | K41: Hora | L41: 0.61666667 | M41: 39.495616 | N41: 0 | O41: Não tem lançamento de horas
A42: 83 | B42: Melhoria de produto | C42: Estabilidade | D42: KOH - Trophic Basic | E42: Luciana Dutra | F42: Teste KOH | G42: RH (Parcial inovação) | H42: 41480 | I42: 7 | J42: 3 TRIM | K42: Hora | L42: 0 | M42: 39.495616 | N42: 0 | O42: Não tem lançamento de horas
A43: 18 | B43: Melhoria de produto | C43: Estabilidade | D43: KOH - Renalmax | E43: Luciana Dutra | F43: Teste piloto - ITAL - Teste de administração do produto | G43: RH (Parcial inovação) | H43: 41521 | I43: 9 | J43: 3 TRIM | K43: Hora | L43: 0.75 | M43: 0 | N43: 0 | O43: Não tem lançamento de horas
A44: 19 | B44: Melhoria de produto | C44: Estabilidade | D44: KOH - Trophic 1.5 | E44: Luciana Dutra | F44: Teste de administração do produto | G44: RH (Parcial inovação) | H44: 41521 | I44: 9 | J44: 3 TRIM | K44: Hora | L44: 0.63333333 | M44: 0 | N44: 0 | O44: Não tem lançamento de horas
A45: 6 | B45: Melhoria de produto | C45: Embalagem | D45: Emplas | E45: Felipe Chavita | F45: Teste de verificação da troca de embalagem no processo industrial da New Millen e da diminuição de head space. O objetivo não foi atingido. Para dar continuidade à pesquisa de melhoria de embalagem, é preciso adequação no selo de indução ao processo New Millen e diminuição da capacidade volumétrica. | G45: RH (Parcial inovação) | H45: 41501 | I45: 8 | J45: 3 TRIM | K45: Hora | L45: 2 | M45: 10.040023 | N45: 0 | O45: Não tem lançamento de horas
A46: 6 | B46: Melhoria de produto | C46: Embalagem | D46: Emplas | E46: Larissa | F46: Teste de verificação da troca de embalagem no processo industrial da New Millen e da diminuição de head space. O objetivo não foi atingido. Para dar continuidade à pesquisa de melhoria de embalagem, é preciso adequação no selo de indução ao processo New Millen e diminuição da capacidade volumétrica. | G46: RH (Parcial inovação) | H46: 41501 | I46: 8 | J46: 3 TRIM | K46: Hora | M46: 13.879093 | N46: 0 | O46: Não tem lançamento de horas
A47: 13 | B47: Melhoria de produto | C47: Estabilidade | D47: KOH - Protocolo PF | E47: Prodiet | F47: Controle de produtos químicos - Pagamento de taxa da Polícia Federal | G47: Material | H47: 41575 | I47: 10 | J47: 4 TRIM | K47: Unidade | L47: 1 | M47: 1000 | O47: Não tem lançamento de horas. A Prodiet não respondeu para que serviu essa despesa
A48: 14 | B48: Melhoria de produto | C48: Estabilidade | D48: KOH - Protocolo PF | E48: Prodiet | F48: Controle de produtos químicos - Pagamento de taxa da Polícia Federal | G48: Material | H48: 41575 | I48: 10 | J48: 4 TRIM | K48: Unidade | L48: 1 | M48: 500 | O48: Não tem lançamento de horas. A Prodiet não respondeu para que serviu essa despesa
A49: 18 | B49: Melhoria de produto | C49: Estabilidade | D49: KOH - Protocolo PF | E49: Thaís Dallagrana | F49: Refeição na data da viagem | G49: Material | H49: 41577 | I49: 10 | J49: 4 TRIM | K49: Unidade | L49: 1 | M49: 14.6 | O49: Não tem lançamento de horas. A Prodiet não respondeu para que serviu essa despesa
A50: 17 | B50: Melhoria de produto | C50: Estabilidade | D50: KOH - Protocolo PF | E50: Thaís Dallagrana | F50: Estadia no Hotel Bourbon - 3 diárias - Para acompanhamento do desenvolvimento do projeto | G50: Material | H50: 41576 | I50: 10 | J50: 4 TRIM | K50: Diária | L50: 3 | M50: 375 | O50: Não tem lançamento de horas. A Prodiet não respondeu para que serviu essa despesa
A51: 16 | B51: Melhoria de produto | C51: Estabilidade | D51: KOH - Protocolo PF | E51: Thaís Dallagrana | F51: Passagem de avião CWB - CGH ida em 29/10 e volta em 01/11 | G51: Material | H51: 41576 | I51: 10 | J51: 4 TRIM | K51: Unidade | L51: 1 | M51: 571.64 | O51: Não tem lançamento de horas. A Prodiet não respondeu para que serviu essa despesa
A52: 15 | B52: Melhoria de produto | C52: Estabilidade | D52: KOH - Protocolo PF | E52: Thaís Dallagrana | F52: Translado do aeroporto para a empresa | G52: Material | H52: 41576 | I52: 10 | J52: 4 TRIM | K52: Unidade | L52: 1 | M52: 120 | O52: Não tem lançamento de horas. A Prodiet não respondeu para que serviu essa despesa
A53: 28 | B53: Melhoria de produto | C53: Sensorial | D53: Trophic Infant | E53: Erica e Thais | F53: Passagem aérea para Thais Dallagrana e Erica Serra - Ida em 10/09 e volta em 13/09 - CWB-CGH | G53: Material | H53: 41522 | I53: 9 | J53: 3 TRIM | K53: Trecho | L53: 1 | M53: 1685.88 | N53: 0 | O53: Não tem lançamento de horas. A Prodiet não respondeu para que serviu essa despesa
B54: Estabilidade | C54: Fórmula | D54: Diversos | E54: FEPA | F54: Análises diversas | G54: Terceiros | H54: 41605 | I54: 11 | J54: 4 TRIM | K54: Unidade | L54: 1 | M54: 15.76 | N54: 0 | O54: Não encontrei documento com despesa
A55: 27 | B55: Melhoria de produto | C55: Sensorial | D55: Trophic Infant | E55: Ibis Budgte | F55: Estadia para acompanhamento de desenvolvimento | G55: Material | H55: 41527 | I55: 9 | J55: 3 TRIM | K55: Diária | L55: 3 | M55: 185 | N55: 0 | O55: Só tem o comprovante de reserva, não tem a nota com quanto foi realmente cobrado
B56: Melhoria de produto | C56: Sensorial | D56: Trophic Infant | E56: Érica Serra | F56: Cursos análise sensorial realizado por Duas Rodas Industrial Ltda | G56: Material | H56: 41439 | I56: 6 | J56: 2 TRIM | K56: Curso | L56: 1 | M56: 0 | N56: 0 | O56: Não tem comprovante de pagamento de inscrição no curso
A57: 82 | B57: Melhoria de produto | D57: Energyzip Morango | E57: Felipe Chavita | F57: Shelf Life | G57: RH (Parcial inovação) | H57: 41604 | I57: 11 | J57: 4 TRIM | K57: Hora | L57: 0.083333333 | M57: 11.044025 | N57: 0.92033543 | O57: Não tem nome do projeto principal na plan de controle
A58: 82 | B58: Melhoria de produto | D58: Energyzip Fiber Chocolate | E58: Felipe Chavita | F58: Shelf Life | G58: RH (Parcial inovação) | H58: 41604 | I58: 11 | J58: 4 TRIM | K58: Hora | L58: 0.25 | M58: 11.044025 | N58: 2.7610063 | O58: Não tem nome do projeto principal na plan de controle
A59: 82 | B59: Melhoria de produto | D59: Trophic Fiber | E59: Felipe Chavita | F59: Shelf Life | G59: RH (Parcial inovação) | H59: 41604 | I59: 11 | J59: 4 TRIM | K59: Hora | L59: 0.16666667 | M59: 11.044025 | N59: 1.8406709 | O59: Não tem nome do projeto principal na plan de controle
A60: 82 | B60: Melhoria de produto | D60: Trophic Basic - Castrolanda | E60: Felipe Chavita | F60: Shelf Life | G60: RH (Parcial inovação) | H60: 41604 | I60: 11 | J60: 4 TRIM | K60: Hora | L60: 0.16666667 | M60: 11.044025 | N60: 1.8406709 | O60: Não tem nome do projeto principal na plan de controle
A61: 82 | B61: Melhoria de produto | D61: Energyzip 1.0 - 879 | E61: Felipe Chavita | G61: RH (Parcial inovação) | H61: 41604 | I61: 11 | J61: 4 TRIM | K61: Hora | L61: 0.33333333 | M61: 11.044025 | N61: 3.6813417 | O61: Não tem nome do projeto principal na plan de controle
A62: 83 | B62: Aditivos | E62: Luciana Dutra | F62: Medir residual de %O2 | G62: RH (Parcial inovação) | H62: 41416 | I62: 5 | J62: 2 TRIM | K62: Hora | L62: 1.5 | M62: 43.257103 | N62: 64.885654

Sheet Quadro de pessoal
A1: PRODIET NUTRIÇÃO
A2: INOVAÇÃO TECNOLÓGICA 2013
A3: Quadro de pessoal
D6: Recursos Humanos
C7: Título | D7: Nº de Pessoas com Dedicação Parcial | E7: Valor Gasto | F7: Nº de Pessoas com Dedicação Exclusiva | G7: Valor Gasto | H7: Total Valor Gasto
C8: Doutores | H8: =SUM(E8,G8) -> 0
C9: Mestres | H9: =SUM(E9,G9) -> 0
C10: Pós-Graduados | D10: 1 | E10: 1538.1141 | F10: 1 | G10: 60110.573 | H10: =SUM(E10,G10) -> 61648.687
C11: Graduados | D11: 2 | E11: 481.51579 | H11: =SUM(E11,G11) -> 481.51579
C12: Tecnólogo | H12: =SUM(E12,G12) -> 0
C13: Técnico de nível médio | H13: =SUM(E13,G13) -> 0
C14: Total | D14: =SUM(D8:D13) -> 3 | E14: =SUM(E8:E13) -> 2019.6299 | F14: =SUM(F8:F13) -> 1 | G14: =SUM(G8:G13) -> 60110.573 | H14: =SUM(E14,G14) -> 62130.203
C15: Valor despendido com funcionários de apoio técnico
C16: VALOR TOTAL DESPENDIDO EM RH | H16: =SUM(H14:H15) -> 62130.203

Sheet Plan2
