Workbook

Sheet RESUMO
A2: Resumo dos investimentos
A3: BENEFÍCIO FISCAL DE PD&I 2020
G4: 2019-088 PRODIET
A5: PRODIET NUTRIÇÃO CLINICA LTDA | E5: CNPJ 08.183.359/0001-53 | G5: =TODAY() -> 46168
A6: Rua General Potiguara, 1428, Lotes 20 e 21, Novo Mundo - PR - SUL - CURITIBA - CEP 81.050-500 - fone: (41) 3342-2825
A8: Natureza | B8: Totalizadores | C8: ( i ) Origem dos dados
A9: Material | B9: =D48 -> 5084.71 | C9: (a1) Material consumido - planilha Investimentos
A10: Terceiros | B10: =E48 -> 372736.95 | C10: (a2) Serviços contratados - planilha Investimentos
A11: RH (Parcial inovação) | B11: =Pessoal!T32 -> 300723.97 | C11: (b) Dispêndio com funcionários de dedicação parcial - planilha Timesheet
A12: RH (Exclusivo inovação) | B12: =Pessoal!T33 -> 0 | C12: (c) Custo total dos funcionários com dedicação exclusiva - planilha Salários
A13: Total | B13: =SUM(B9:B12) -> 678545.63
A14: Percentual Exclusão | B14: 0.6 | D14: 60% | E14: +10% | F14: +20% | G14: +20%
A15: Exclusão da Base de cálculo do IRPJ e CSLL | B15: =B13*B14 -> 407127.38 | D15: Benefício padrão | E15: Incremento <5% de pesquisadores exclusivos | F15: Incremento >5% de pesquisadores exclusivos | G15: Dispendios com registro de patente
A17: Economia Estimada [34%] | B17: =B15*34% -> 138423.31
A18: Comissão McBenner | B18: =B17*0.1 -> 13842.331
A20: Observações:
A21: 1. Os dispêndios devem ser registrados na contabilidade em conta específica
A22: 2. O benefício deve ser aproveitado na ECF do respectivo ano/competência
A23: 3. O formulário do MCTIC (governo) deve ser enviado até fim de setembro/2021
A24: 4. Os projetos estão descritos em arquivo a parte a ser anexado no FORM PD&I
A25: 5. Alguns benefícios previstos na Lei do Bem não foram utilizados:
A26: --- 5.1. Depreciação acelerada
A27: --- 5.2. Redução de IPI na aquisição de equipamento para PD&I
A30: Equipe de PD&I
A31: Quadro de resumo | B31: Dedicação Parcial | E31: Dedicação Exclusiva
B32: Qtd | C32: Valor gasto | D32: Horas | E32: Qtd | F32: Valor gasto | G32: Horas
A33: Técnico | B33: =IFERROR(__xludf.DUMMYFUNCTION("COUNTA(IFERROR(FILTER(Pessoal!$E$6:$E$26,Pessoal!$E$6:$E$26 = $A33,Pessoal!$U$6:$U$26 = ""Parcial"",Pessoal!$U$37:$U$57 = TRUE),))"),0.0) -> 0 | C33: =IFERROR(__xludf.DUMMYFUNCTION("SUM(IFERROR(FILTER(Pessoal!$T$37:$T$57,Pessoal!$E$37:$E$57 = $A33,Pessoal!$D$37:$D$57 = ""Parcial""),0))"),0.0) -> 0 | D33: =IFERROR(__xludf.DUMMYFUNCTION("SUM(IFERROR(FILTER(Pessoal!$S$6:$S$26,Pessoal!$E$6:$E$26 = $A33,Pessoal!$U$6:$U$26 = ""Parcial""),0))*24"),0.0) -> 0 | E33: =IFERROR(__xludf.DUMMYFUNCTION("COUNTA(IFERROR(FILTER(Pessoal!$E$6:$E$26,Pessoal!$E$6:$E$26 = $A33,Pessoal!$U$6:$U$26 = ""Exclusivo"",Pessoal!$U$37:$U$57 = TRUE),))"),0.0) -> 0 | F33: =IFERROR(__xludf.DUMMYFUNCTION("SUM(IFERROR(FILTER(Pessoal!$T$37:$T$57,Pessoal!$E$37:$E$57 = $A33,Pessoal!$D$37:$D$57 = ""Exclusivo""),0))"),0.0) -> 0 | G33: =IFERROR(__xludf.DUMMYFUNCTION("SUM(IFERROR(FILTER(Pessoal!$S$6:$S$26,Pessoal!$E$6:$E$26 = $A33,Pessoal!$U$6:$U$26 = ""Exclusivo""),0))*24"),0.0) -> 0
A34: Tecnologo | B34: =IFERROR(__xludf.DUMMYFUNCTION("COUNTA(IFERROR(FILTER(Pessoal!$E$6:$E$26,Pessoal!$E$6:$E$26 = $A34,Pessoal!$U$6:$U$26 = ""Parcial"",Pessoal!$U$37:$U$57 = TRUE),))"),0.0) -> 0 | C34: =IFERROR(__xludf.DUMMYFUNCTION("SUM(IFERROR(FILTER(Pessoal!$T$37:$T$57,Pessoal!$E$37:$E$57 = $A34,Pessoal!$D$37:$D$57 = ""Parcial""),0))"),0.0) -> 0 | D34: =IFERROR(__xludf.DUMMYFUNCTION("SUM(IFERROR(FILTER(Pessoal!$S$6:$S$26,Pessoal!$E$6:$E$26 = $A34,Pessoal!$U$6:$U$26 = ""Parcial""),0))*24"),0.0) -> 0 | E34: =IFERROR(__xludf.DUMMYFUNCTION("COUNTA(IFERROR(FILTER(Pessoal!$E$6:$E$26,Pessoal!$E$6:$E$26 = $A34,Pessoal!$U$6:$U$26 = ""Exclusivo"",Pessoal!$U$37:$U$57 = TRUE),))"),0.0) -> 0 | F34: =IFERROR(__xludf.DUMMYFUNCTION("SUM(IFERROR(FILTER(Pessoal!$T$37:$T$57,Pessoal!$E$37:$E$57 = $A34,Pessoal!$D$37:$D$57 = ""Exclusivo""),0))"),0.0) -> 0 | G34: =IFERROR(__xludf.DUMMYFUNCTION("SUM(IFERROR(FILTER(Pessoal!$S$6:$S$26,Pessoal!$E$6:$E$26 = $A34,Pessoal!$U$6:$U$26 = ""Exclusivo""),0))*24"),0.0) -> 0
A35: Superior Completo | B35: =IFERROR(__xludf.DUMMYFUNCTION("COUNTA(IFERROR(FILTER(Pessoal!$E$6:$E$26,Pessoal!$E$6:$E$26 = $A35,Pessoal!$U$6:$U$26 = ""Parcial"",Pessoal!$U$37:$U$57 = TRUE),))"),3.0) -> 3 | C35: =IFERROR(__xludf.DUMMYFUNCTION("SUM(IFERROR(FILTER(Pessoal!$T$37:$T$57,Pessoal!$E$37:$E$57 = $A35,Pessoal!$D$37:$D$57 = ""Parcial""),0))"),82186.17763465601) -> 82186.178 | D35: =IFERROR(__xludf.DUMMYFUNCTION("SUM(IFERROR(FILTER(Pessoal!$S$6:$S$26,Pessoal!$E$6:$E$26 = $A35,Pessoal!$U$6:$U$26 = ""Parcial""),0))*24"),2533.283333333333) -> 2533.2833 | E35: =IFERROR(__xludf.DUMMYFUNCTION("COUNTA(IFERROR(FILTER(Pessoal!$E$6:$E$26,Pessoal!$E$6:$E$26 = $A35,Pessoal!$U$6:$U$26 = ""Exclusivo"",Pessoal!$U$37:$U$57 = TRUE),))"),0.0) -> 0 | F35: =IFERROR(__xludf.DUMMYFUNCTION("SUM(IFERROR(FILTER(Pessoal!$T$37:$T$57,Pessoal!$E$37:$E$57 = $A35,Pessoal!$D$37:$D$57 = ""Exclusivo""),0))"),0.0) -> 0 | G35: =IFERROR(__xludf.DUMMYFUNCTION("SUM(IFERROR(FILTER(Pessoal!$S$6:$S$26,Pessoal!$E$6:$E$26 = $A35,Pessoal!$U$6:$U$26 = ""Exclusivo""),0))*24"),0.0) -> 0
A36: Pós graduado | B36: =IFERROR(__xludf.DUMMYFUNCTION("COUNTA(IFERROR(FILTER(Pessoal!$E$6:$E$26,Pessoal!$E$6:$E$26 = $A36,Pessoal!$U$6:$U$26 = ""Parcial"",Pessoal!$U$37:$U$57 = TRUE),))"),6.0) -> 6 | C36: =IFERROR(__xludf.DUMMYFUNCTION("SUM(IFERROR(FILTER(Pessoal!$T$37:$T$57,Pessoal!$E$37:$E$57 = $A36,Pessoal!$D$37:$D$57 = ""Parcial""),0))"),66486.16777574933) -> 66486.168 | D36: =IFERROR(__xludf.DUMMYFUNCTION("SUM(IFERROR(FILTER(Pessoal!$S$6:$S$26,Pessoal!$E$6:$E$26 = $A36,Pessoal!$U$6:$U$26 = ""Parcial""),0))*24"),528.3833333333332) -> 528.38333 | E36: =IFERROR(__xludf.DUMMYFUNCTION("COUNTA(IFERROR(FILTER(Pessoal!$E$6:$E$26,Pessoal!$E$6:$E$26 = $A36,Pessoal!$U$6:$U$26 = ""Exclusivo"",Pessoal!$U$37:$U$57 = TRUE),))"),0.0) -> 0 | F36: =IFERROR(__xludf.DUMMYFUNCTION("SUM(IFERROR(FILTER(Pessoal!$T$37:$T$57,Pessoal!$E$37:$E$57 = $A36,Pessoal!$D$37:$D$57 = ""Exclusivo""),0))"),0.0) -> 0 | G36: =IFERROR(__xludf.DUMMYFUNCTION("SUM(IFERROR(FILTER(Pessoal!$S$6:$S$26,Pessoal!$E$6:$E$26 = $A36,Pessoal!$U$6:$U$26 = ""Exclusivo""),0))*24"),0.0) -> 0
A37: Mestrado | B37: =IFERROR(__xludf.DUMMYFUNCTION("COUNTA(IFERROR(FILTER(Pessoal!$E$6:$E$26,Pessoal!$E$6:$E$26 = $A37,Pessoal!$U$6:$U$26 = ""Parcial"",Pessoal!$U$37:$U$57 = TRUE),))"),2.0) -> 2 | C37: =IFERROR(__xludf.DUMMYFUNCTION("SUM(IFERROR(FILTER(Pessoal!$T$37:$T$57,Pessoal!$E$37:$E$57 = $A37,Pessoal!$D$37:$D$57 = ""Parcial""),0))"),152051.6233288585) -> 152051.62 | D37: =IFERROR(__xludf.DUMMYFUNCTION("SUM(IFERROR(FILTER(Pessoal!$S$6:$S$26,Pessoal!$E$6:$E$26 = $A37,Pessoal!$U$6:$U$26 = ""Parcial""),0))*24"),2312.1166666666672) -> 2312.1167 | E37: =IFERROR(__xludf.DUMMYFUNCTION("COUNTA(IFERROR(FILTER(Pessoal!$E$6:$E$26,Pessoal!$E$6:$E$26 = $A37,Pessoal!$U$6:$U$26 = ""Exclusivo"",Pessoal!$U$37:$U$57 = TRUE),))"),0.0) -> 0 | F37: =IFERROR(__xludf.DUMMYFUNCTION("SUM(IFERROR(FILTER(Pessoal!$T$37:$T$57,Pessoal!$E$37:$E$57 = $A37,Pessoal!$D$37:$D$57 = ""Exclusivo""),0))"),0.0) -> 0 | G37: =IFERROR(__xludf.DUMMYFUNCTION("SUM(IFERROR(FILTER(Pessoal!$S$6:$S$26,Pessoal!$E$6:$E$26 = $A37,Pessoal!$U$6:$U$26 = ""Exclusivo""),0))*24"),0.0) -> 0
A38: Doutorado | B38: =IFERROR(__xludf.DUMMYFUNCTION("COUNTA(IFERROR(FILTER(Pessoal!$E$6:$E$26,Pessoal!$E$6:$E$26 = $A38,Pessoal!$U$6:$U$26 = ""Parcial"",Pessoal!$U$37:$U$57 = TRUE),))"),0.0) -> 0 | C38: =IFERROR(__xludf.DUMMYFUNCTION("SUM(IFERROR(FILTER(Pessoal!$T$37:$T$57,Pessoal!$E$37:$E$57 = $A38,Pessoal!$D$37:$D$57 = ""Parcial""),0))"),0.0) -> 0 | D38: =IFERROR(__xludf.DUMMYFUNCTION("SUM(IFERROR(FILTER(Pessoal!$S$6:$S$26,Pessoal!$E$6:$E$26 = $A38,Pessoal!$U$6:$U$26 = ""Parcial""),0))*24"),0.0) -> 0 | E38: =IFERROR(__xludf.DUMMYFUNCTION("COUNTA(IFERROR(FILTER(Pessoal!$E$6:$E$26,Pessoal!$E$6:$E$26 = $A38,Pessoal!$U$6:$U$26 = ""Exclusivo"",Pessoal!$U$37:$U$57 = TRUE),))"),0.0) -> 0 | F38: =IFERROR(__xludf.DUMMYFUNCTION("SUM(IFERROR(FILTER(Pessoal!$T$37:$T$57,Pessoal!$E$37:$E$57 = $A38,Pessoal!$D$37:$D$57 = ""Exclusivo""),0))"),0.0) -> 0 | G38: =IFERROR(__xludf.DUMMYFUNCTION("SUM(IFERROR(FILTER(Pessoal!$S$6:$S$26,Pessoal!$E$6:$E$26 = $A38,Pessoal!$U$6:$U$26 = ""Exclusivo""),0))*24"),0.0) -> 0
B39: =SUM(B33:B38) -> 11 | C39: =SUM(C33:C38) -> 300723.97 | D39: =SUM(D33:D38) -> 5373.7833 | E39: =SUM(E33:E38) -> 0 | F39: =SUM(F33:F38) -> 0 | G39: =SUM(G33:G38) -> 0
A41: Valores por projeto de PD&I
A42: Projetos | B42: Identificação | D42: Vlr materiais | E42: Vlr terceiros | F42: Vlr Rh parcial | G42: Vlr exclusivos
A43: Novos Produtos | B43: NP | D43: =IFERROR(__xludf.DUMMYFUNCTION("SUM(FILTER(Investimentos!$O:$O,Investimentos!$N:$N = ""Material"",Investimentos!$L:$L = TRUE))"),1511.75) -> 1511.75 | E43: =IFERROR(__xludf.DUMMYFUNCTION("SUM(FILTER(Investimentos!$O:$O,Investimentos!$N:$N = ""Serviço"",Investimentos!$L:$L = TRUE))"),274463.99) -> 274463.99 | F43: =$B$11*(E43/$E$48) -> 221437.4 | G43: =$B$12*(E43/$E$48) -> 0
A44: Novas Matérias-primas | B44: Nmp | D44: =IFERROR(__xludf.DUMMYFUNCTION("SUM(FILTER(Investimentos!$P:$P,Investimentos!$N:$N = ""Material"",Investimentos!$L:$L = TRUE,Investimentos!$W:$W = TRUE))"),0.0) -> 0 | E44: =IFERROR(__xludf.DUMMYFUNCTION("SUM(FILTER(Investimentos!$P:$P,Investimentos!$N:$N = ""Serviço"",Investimentos!$L:$L = TRUE))"),0.0) -> 0 | F44: =$B$11*(E44/$E$48) -> 0 | G44: =$B$12*(E44/$E$48) -> 0
A45: Melhoria de Produto | B45: Mprod | D45: =IFERROR(__xludf.DUMMYFUNCTION("SUM(FILTER(Investimentos!$Q:$Q,Investimentos!$N:$N = ""Material"",Investimentos!$L:$L = TRUE()))"),362.9) -> 362.9 | E45: =IFERROR(__xludf.DUMMYFUNCTION("SUM(FILTER(Investimentos!$Q:$Q,Investimentos!$N:$N = ""Serviço"",Investimentos!$L:$L = TRUE))"),84741.82000000002) -> 84741.82 | F45: =$B$11*(E45/$E$48) -> 68369.654 | G45: =$B$12*(E45/$E$48) -> 0
A46: Melhoria de Processos | B46: Mproc | D46: =IFERROR(__xludf.DUMMYFUNCTION("SUM(FILTER(Investimentos!$R:$R,Investimentos!$N:$N = ""Material"",Investimentos!$L:$L = TRUE))"),3210.06) -> 3210.06 | E46: =IFERROR(__xludf.DUMMYFUNCTION("SUM(FILTER(Investimentos!$R:$R,Investimentos!$N:$N = ""Serviço"",Investimentos!$L:$L = TRUE))"),13531.140000000001) -> 13531.14 | F46: =$B$11*(E46/$E$48) -> 10916.916 | G46: =$B$12*(E46/$E$48) -> 0
A47: Segurança Alimentar | B47: SgAlim | D47: =IFERROR(__xludf.DUMMYFUNCTION("SUM(FILTER(Investimentos!$S:$S,Investimentos!$N:$N = ""Material"",Investimentos!$L:$L = TRUE,Investimentos!$W:$W = TRUE))"),0.0) -> 0 | E47: =IFERROR(__xludf.DUMMYFUNCTION("SUM(FILTER(Investimentos!$S:$S,Investimentos!$N:$N = ""Serviço"",Investimentos!$L:$L = TRUE,Investimentos!$W:$W <> FALSE))"),0.0) -> 0 | F47: =$B$11*(E47/$E$48) -> 0 | G47: =$B$12*(E47/$E$48) -> 0
A48: Subtotais | D48: =SUM(D43:D47) -> 5084.71 | E48: =SUM(E43:E47) -> 372736.95 | F48: =SUM(F43:F47) -> 300723.97 | G48: =SUM(G43:G47) -> 0

Sheet Projetos
A2: Projetos
A3: BENEFÍCIO FISCAL DE PD&I 2019
A5: Projeto | B5: Agrupamento | C5: Categoria do projeto | D5: Elemento tecnologicamente novo ou inovador | E5: Barreira ou desafio tecnológico a superar | F5: Metodologia empregada | G5: Data início | H5: Data de término (estimada) | I5: Descrição | J5: Attachments | K5: Timesheet | L5: Lei do Bem
A6: {=SORT(UNIQUE({Timesheet!C7:C42;PrjAdd!A2:A10}),1,true)} -> Bemmax Sabor Neutro | L6: TRUE
A7: CarboCH | L7: TRUE
A8: Centro de Inovação | L8: FALSE
A9: Cicatrização | L9: TRUE
A10: Congresso ESPEN | L10: TRUE
A11: Congresso Ganepão | L11: TRUE
A12: Congressos | L12: TRUE
A13: Diamax IG | L13: TRUE
A14: Dieta artesanal | L14: TRUE
A15: EE - 2020 | L15: TRUE
A16: Energyzip 1.0 | L16: TRUE
A17: Energyzip baunilha | L17: TRUE
A18: Energyzip Chocolate | L18: TRUE
... A42: Vulcano (pote jumbo e sachês a vácuo) | L42: FALSE

Sheet PrjAdd
A1: Concorrente
A2: Energyzip baunilha
A3: Trophic Basic pó
A4: Energyzip morango
A5: Energyzip 1.0
A6: Energyzip Chocolate
A7: Energyzip Fiber
A8: HDmax 1.5
A9: ProteinPT
A10: CarboCH

Sheet Timesheet
A2: Timesheet
A3: BENEFÍCIO FISCAL DE PD&I 2019 | I3: Parcial | J3: =J5-J4 -> 312686.56
I4: Exclusivo | J4: =IFERROR(__xludf.DUMMYFUNCTION("SUMIF($B$7:$B3492,FILTER(Pessoal!$A$10:$A$26,Pessoal!$U$10:$U$26 = ""Exclusivo"",MATCH(Pessoal!$A$10:$A$26,FILTER(Pessoal!$A$37:$A$57,Pessoal!$U$37:$U$57 = TRUE),0)),$J$7:$J3492)"),0.0) -> 0
I5: TOTAL | J5: =SUM(J7:J3492) -> 312686.56
A6: Cod | B6: Pessoa | C6: Projeto | D6: Descrição | E6: Start | F6: Tempo aplicado | G6: Atividade incentivada | H6: Attachments | I6: Valor (R$) | J6: Custo | K6: checkprojetos
A7: 1 | B7: Ademir Mararangoni | C7: Immax - etapa final da Pesquisa Clínica | D7: Coordenar pesagem e produção | E7: 43846 | F7: 0.041666667 | G7: TRUE | H7: =IF(VLOOKUP(C7,Projetos!A:L,12,false)=TRUE,TRUE,FALSE) -> TRUE | I7: {=VLOOKUP(B7:B3492,Pessoal!$A$36:$R$57,MONTH(E7:E3492)+6,false)} -> 63.065873 | J7: =IFERROR(IF(AND(G7=TRUE,YEAR(E7)<2021),F7,"")*(I7*24),0) -> 63.065873 | K7: {=VLOOKUP(C7:C3492,Projetos!A6:L3492,12,false)} -> TRUE
A8: 2 | B8: Ademir Mararangoni | C8: InstanTH NEO | D8: Coordenar separação, emissão de NF e envio dos materiais para produção | E8: 43840 | F8: 0.083333333 | G8: TRUE | H8: =IF(VLOOKUP(C8,Projetos!A:L,12,false)=TRUE,TRUE,FALSE) -> TRUE | I8: 63.065873 | J8: =IFERROR(IF(AND(G8=TRUE,YEAR(E8)<2021),F8,"")*(I8*24),0) -> 126.13175 | K8: TRUE
A9: 3 | B9: Ademir Mararangoni | C9: InstanTH CLEAR (espessante) | D9: Adequação da linha de produção para o envase (Novo Twister, Envasadora, Esteira tampadora Plock off) | E9: 43850 | F9: 0.40625 | G9: TRUE | H9: =IF(VLOOKUP(C9,Projetos!A:L,12,false)=TRUE,TRUE,FALSE) -> TRUE | I9: 63.065873 | J9: =IFERROR(IF(AND(G9=TRUE,YEAR(E9)<2021),F9,"")*(I9*24),0) -> 614.89226 | K9: TRUE
A10: 4 | B10: Ademir Mararangoni | C10: Inovação industrial - misturas secas | D10: Implementação do projeto balança onde integraliza a pesagem do fracionamento com o estrutura do sistema para minimizar erros | E10: 43843 | F10: 0.40625 | G10: FALSE | H10: =IF(VLOOKUP(C10,Projetos!A:L,12,false)=TRUE,TRUE,FALSE) -> FALSE | I10: 63.065873 | J10: =IFERROR(IF(AND(G10=TRUE,YEAR(E10)<2021),F10,"")*(I10*24),0) -> 0 | K10: FALSE
A11: 5 | B11: Ademir Mararangoni | C11: Inovação industrial - misturas secas | D11: Teste de n² com enertizado da Brasilata | E11: 43845 | F11: 0.23958333 | G11: FALSE | H11: =IF(VLOOKUP(C11,Projetos!A:L,12,false)=TRUE,TRUE,FALSE) -> FALSE | I11: 63.065873 | J11: =IFERROR(IF(AND(G11=TRUE,YEAR(E11)<2021),F11,"")*(I11*24),0) -> 0 | K11: FALSE
A12: 6 | B12: Ademir Mararangoni | C12: InstanTH CLEAR (espessante) | D12: Primeira produção do Instant clear | E12: 43872 | F12: 0.083333333 | G12: TRUE | H12: =IF(VLOOKUP(C12,Projetos!A:L,12,false)=TRUE,TRUE,FALSE) -> TRUE | I12: 60.199242 | J12: =IFERROR(IF(AND(G12=TRUE,YEAR(E12)<2021),F12,"")*(I12*24),0) -> 120.39848 | K12: TRUE
A13: 7 | B13: Ademir Mararangoni | C13: InstanTH NEO | D13: Apontamento, triangulazação de NF | E13: 43888 | F13: 0.083333333 | G13: FALSE | H13: =IF(VLOOKUP(C13,Projetos!A:L,12,false)=TRUE,TRUE,FALSE) -> TRUE | I13: 60.199242 | J13: =IFERROR(IF(AND(G13=TRUE,YEAR(E13)<2021),F13,"")*(I13*24),0) -> 0 | K13: TRUE
A14: 8 | B14: Ademir Mararangoni | C14: Bemmax Sabor Neutro | D14: Teste de envase -peso alcançado 350g | E14: 43879 | F14: 0.10416667 | G14: TRUE | H14: =IF(VLOOKUP(C14,Projetos!A:L,12,false)=TRUE,TRUE,FALSE) -> TRUE | I14: 60.199242 | J14: =IFERROR(IF(AND(G14=TRUE,YEAR(E14)<2021),F14,"")*(I14*24),0) -> 150.49811 | K14: TRUE
A15: 9 | B15: Ademir Mararangoni | C15: Retort (Sistema Fechado) | D15: Separação de MP fisico e sistema para pesagem de teste | E15: 43876 | F15: 0.083333333 | G15: FALSE | H15: =IF(VLOOKUP(C15,Projetos!A:L,12,false)=TRUE,TRUE,FALSE) -> TRUE | I15: 60.199242 | J15: =IFERROR(IF(AND(G15=TRUE,YEAR(E15)<2021),F15,"")*(I15*24),0) -> 0 | K15: TRUE
A16: 10 | B16: Ademir Mararangoni | C16: HDmax 2.0 | D16: Separação de MP fisico e sistema para pesagem de teste | E16: 43874 | F16: 0.083333333 | G16: TRUE | H16: =IF(VLOOKUP(C16,Projetos!A:L,12,false)=TRUE,TRUE,FALSE) -> TRUE | I16: 60.199242 | J16: =IFERROR(IF(AND(G16=TRUE,YEAR(E16)<2021),F16,"")*(I16*24),0) -> 120.39848 | K16: TRUE
A17: 11 | B17: Ademir Mararangoni | C17: Inovação industrial - misturas secas | D17: Validação com comercial e manutenção pra aquisição de strechadeira automática | E17: 43886 | F17: 0.083333333 | G17: FALSE | H17: =IF(VLOOKUP(C17,Projetos!A:L,12,false)=TRUE,TRUE,FALSE) -> FALSE | I17: 60.199242 | J17: =IFERROR(IF(AND(G17=TRUE,YEAR(E17)<2021),F17,"")*(I17*24),0) -> 0 | K17: FALSE
A18: 12 | B18: Ademir Mararangoni | C18: Inovação industrial - misturas secas | D18: Alinhamento do projeto balança onde integraliza a pesagem do fracionamento com o estrutura do sistema para minimizar erros | E18: 43865 | F18: 0.041666667 | G18: FALSE | H18: =IF(VLOOKUP(C18,Projetos!A:L,12,false)=TRUE,TRUE,FALSE) -> FALSE | I18: 60.199242 | J18: =IFERROR(IF(AND(G18=TRUE,YEAR(E18)<2021),F18,"")*(I18*24),0) -> 0 | K18: FALSE
A19: 13 | B19: Ademir Mararangoni | C19: Inovação industrial - misturas secas | D19: Alinhamento do projeto balança onde integraliza a pesagem do fracionamento com o estrutura do sistema para minimizar erros | E19: 43875 | F19: 0.083333333 | G19: FALSE | H19: =IF(VLOOKUP(C19,Projetos!A:L,12,false)=TRUE,TRUE,FALSE) -> FALSE | I19: 60.199242 | J19: =IFERROR(IF(AND(G19=TRUE,YEAR(E19)<2021),F19,"")*(I19*24),0) -> 0 | K19: FALSE
... A856: 850 | B856: Ana Paula Celes | C856: InstanTH NEO | D856: Discussão de linhas de pesquisa clinica | E856: 43844 | F856: 0.020833333 | G856: TRUE | H856: =IF(VLOOKUP(C856,Projetos!A:L,12,false)=TRUE,TRUE,FALSE) -> TRUE | I856: 169.03747 | J856: =IFERROR(IF(AND(G856=TRUE,YEAR(E856)<2021),F856,"")*(I856*24),0) -> 84.518733 | K856: TRUE
A857: 851 | B857: Ana Paula Celes | C857: InstanTH NEO | D857: Discussão de linhas de pesquisa clinica | F857: 0 | G857: FALSE | H857: =IF(VLOOKUP(C857,Projetos!A:L,12,false)=TRUE,TRUE,FALSE) -> TRUE | I857: 169.03747 | J857: =IFERROR(IF(AND(G857=TRUE,YEAR(E857)<2021),F857,"")*(I857*24),0) -> 0 | K857: TRUE
A858: 852 | B858: Ana Paula Celes | C858: Retort (Sistema Fechado) | D858: Planejamento das embalagens | E858: 43837 | F858: 0.0625 | G858: FALSE | H858: =IF(VLOOKUP(C858,Projetos!A:L,12,false)=TRUE,TRUE,FALSE) -> TRUE | I858: 169.03747 | J858: =IFERROR(IF(AND(G858=TRUE,YEAR(E858)<2021),F858,"")*(I858*24),0) -> 0 | K858: TRUE
A859: 853 | B859: Ana Paula Celes | C859: Retort (Sistema Fechado) | D859: Direcionamento global de todo sitema de tratamento termico | E859: 43838 | F859: 0.083333333 | G859: FALSE | H859: =IF(VLOOKUP(C859,Projetos!A:L,12,false)=TRUE,TRUE,FALSE) -> TRUE | I859: 169.03747 | J859: =IFERROR(IF(AND(G859=TRUE,YEAR(E859)<2021),F859,"")*(I859*24),0) -> 0 | K859: TRUE
A860: 854 | B860: Ana Paula Celes | C860: Retort (Sistema Fechado) | D860: Diretrizes e cmposição micronutrientes das fórmulas | E860: 43858 | F860: 0.041666667 | G860: FALSE | H860: =IF(VLOOKUP(C860,Projetos!A:L,12,false)=TRUE,TRUE,FALSE) -> TRUE | I860: 169.03747 | J860: =IFERROR(IF(AND(G860=TRUE,YEAR(E860)<2021),F860,"")*(I860*24),0) -> 0 | K860: TRUE
A861: 855 | B861: Ana Paula Celes | C861: Sarcopenia | D861: Definição do conceito de inovação e nutrientes da formula | E861: 43837 | F861: 0.041666667 | G861: TRUE | H861: =IF(VLOOKUP(C861,Projetos!A:L,12,false)=TRUE,TRUE,FALSE) -> TRUE | I861: 169.03747 | J861: =IFERROR(IF(AND(G861=TRUE,YEAR(E861)<2021),F861,"")*(I861*24),0) -> 169.03747 | K861: TRUE
A862: 856 | B862: Ana Paula Celes | C862: InstanTH NEO | D862: Análise e discussão da comunicção de inovação ao mercado | E862: 43873 | F862: 0.041666667 | G862: TRUE | H862: =IF(VLOOKUP(C862,Projetos!A:L,12,false)=TRUE,TRUE,FALSE) -> TRUE | I862: 161.35394 | J862: =IFERROR(IF(AND(G862=TRUE,YEAR(E862)<2021),F862,"")*(I862*24),0) -> 161.35394 | K862: TRUE
A863: 857 | B863: Ana Paula Celes | C863: Retort (Sistema Fechado) | D863: Planejamento para teste piloto | E863: 43866 | F863: 0.041666667 | G863: TRUE | H863: =IF(VLOOKUP(C863,Projetos!A:L,12,false)=TRUE,TRUE,FALSE) -> TRUE | I863: 161.35394 | J863: =IFERROR(IF(AND(G863=TRUE,YEAR(E863)<2021),F863,"")*(I863*24),0) -> 161.35394 | K863: TRUE
A864: 858 | B864: Ana Paula Celes | C864: Retort (Sistema Fechado) | D864: Atualizações do projeto | E864: 43871 | F864: 0.0625 | G864: FALSE | H864: =IF(VLOOKUP(C864,Projetos!A:L,12,false)=TRUE,TRUE,FALSE) -> TRUE | I864: 161.35394 | J864: =IFERROR(IF(AND(G864=TRUE,YEAR(E864)<2021),F864,"")*(I864*24),0) -> 0 | K864: TRUE
A865: 859 | B865: Ana Paula Celes | C865: Retort (Sistema Fechado) | D865: Discussão de linhas de pesquisa clinica | E865: 43872 | F865: 0.041666667 | G865: TRUE | H865: =IF(VLOOKUP(C865,Projetos!A:L,12,false)=TRUE,TRUE,FALSE) -> TRUE | I865: 161.35394 | J865: =IFERROR(IF(AND(G865=TRUE,YEAR(E865)<2021),F865,"")*(I865*24),0) -> 161.35394 | K865: TRUE
A866: 860 | B866: Ana Paula Celes | C866: Retort (Sistema Fechado) | D866: Fechamento de diretrizes do teste piloto | E866: 43873 | F866: 0.020833333 | G866: TRUE | H866: =IF(VLOOKUP(C866,Projetos!A:L,12,false)=TRUE,TRUE,FALSE) -> TRUE | I866: 161.35394 | J866: =IFERROR(IF(AND(G866=TRUE,YEAR(E866)<2021),F866,"")*(I866*24),0) -> 80.676972 | K866: TRUE
A867: 861 | B867: Ana Paula Celes | C867: Retort (Sistema Fechado) | D867: Execução de tetes em planta piloto | E867: 43878 | F867: 0.41666667 | G867: TRUE | H867: =IF(VLOOKUP(C867,Projetos!A:L,12,false)=TRUE,TRUE,FALSE) -> TRUE | I867: 161.35394 | J867: =IFERROR(IF(AND(G867=TRUE,YEAR(E867)<2021),F867,"")*(I867*24),0) -> 1613.5394 | K867: TRUE
A868: 862 | B868: Ana Paula Celes | C868: Retort (Sistema Fechado) | D868: Execução de tetes em planta piloto | E868: 43879 | F868: 0.41666667 | G868: TRUE | H868: =IF(VLOOKUP(C868,Projetos!A:L,12,false)=TRUE,TRUE,FALSE) -> TRUE | I868: 161.35394 | J868: =IFERROR(IF(AND(G868=TRUE,YEAR(E868)<2021),F868,"")*(I868*24),0) -> 1613.5394 | K868: TRUE
A869: 863 | B869: Ana Paula Celes | C869: Retort (Sistema Fechado) | D869: Monitoramento dos resultados de testes FQ | E869: 43889 | F869: 0.041666667 | G869: TRUE | H869: =IF(VLOOKUP(C869,Projetos!A:L,12,false)=TRUE,TRUE,FALSE) -> TRUE | I869: 161.35394 | J869: =IFERROR(IF(AND(G869=TRUE,YEAR(E869)<2021),F869,"")*(I869*24),0) -> 161.35394 | K869: TRUE
... A1058: 1052 | B1058: Ana Paula Celes | C1058: Vulcano (pote jumbo e sachês a vácuo) | D1058: Definições de ações do projeto Jumbo e sache vacuo | E1058: 44194 | F1058: 0.083333333 | G1058: FALSE | H1058: =IF(VLOOKUP(C1058,Projetos!A:L,12,false)=TRUE,TRUE,FALSE) -> FALSE | I1058: 169.03747 | J1058: =IFERROR(IF(AND(G1058=TRUE,YEAR(E1058)<2021),F1058,"")*(I1058*24),0) -> 0 | K1058: FALSE
A1059: 1053 | B1059: Ana Paula Celes | C1059: Centro de Inovação | D1059: Análise de atividades de P&D | F1059: 0.0625 | G1059: FALSE | H1059: =IF(VLOOKUP(C1059,Projetos!A:L,12,false)=TRUE,TRUE,FALSE) -> FALSE | I1059: 169.03747 | J1059: =IFERROR(IF(AND(G1059=TRUE,YEAR(E1059)<2021),F1059,"")*(I1059*24),0) -> 0 | K1059: FALSE
A1060: 1054 | B1060: Ana Claudia Zanini | C1060: Sarcopenia | D1060: Desenvolvimento de protocolo de pesquisa clinica | E1060: 43895 | F1060: 0.1875 | G1060: TRUE | H1060: =IF(VLOOKUP(C1060,Projetos!A:L,12,false)=TRUE,TRUE,FALSE) -> TRUE | I1060: 29.312396 | J1060: =IFERROR(IF(AND(G1060=TRUE,YEAR(E1060)<2021),F1060,"")*(I1060*24),0) -> 131.90578 | K1060: TRUE
A1061: 1055 | B1061: Ana Claudia Zanini | C1061: Sarcopenia | D1061: Desenvolvimento de protocolo de pesquisa clinica | E1061: 43896 | F1061: 0.16666667 | G1061: TRUE | H1061: =IF(VLOOKUP(C1061,Projetos!A:L,12,false)=TRUE,TRUE,FALSE) -> TRUE | I1061: 29.312396 | J1061: =IFERROR(IF(AND(G1061=TRUE,YEAR(E1061)<2021),F1061,"")*(I1061*24),0) -> 117.24959 | K1061: TRUE
A1062: 1056 | B1062: Ana Claudia Zanini | C1062: Sarcopenia | D1062: Desenvolvimento de protocolo de pesquisa clinica | E1062: 43901 | F1062: 0.1875 | G1062: TRUE | H1062: =IF(VLOOKUP(C1062,Projetos!A:L,12,false)=TRUE,TRUE,FALSE) -> TRUE | I1062: 29.312396 | J1062: =IFERROR(IF(AND(G1062=TRUE,YEAR(E1062)<2021),F1062,"")*(I1062*24),0) -> 131.90578 | K1062: TRUE
A1063: 1057 | B1063: Ana Claudia Zanini | C1063: Sarcopenia | D1063: Desenvolvimento de protocolo de pesquisa clinica | E1063: 43903 | F1063: 0.10416667 | G1063: TRUE | H1063: =IF(VLOOKUP(C1063,Projetos!A:L,12,false)=TRUE,TRUE,FALSE) -> TRUE | I1063: 29.312396 | J1063: =IFERROR(IF(AND(G1063=TRUE,YEAR(E1063)<2021),F1063,"")*(I1063*24),0) -> 73.280991 | K1063: TRUE
A1064: 1058 | B1064: Ana Claudia Zanini | C1064: Sarcopenia | D1064: Desenvolvimento de protocolo de pesquisa clinica | E1064: 43903 | F1064: 0.083333333 | G1064: TRUE | H1064: =IF(VLOOKUP(C1064,Projetos!A:L,12,false)=TRUE,TRUE,FALSE) -> TRUE | I1064: 29.312396 | J1064: =IFERROR(IF(AND(G1064=TRUE,YEAR(E1064)<2021),F1064,"")*(I1064*24),0) -> 58.624793 | K1064: TRUE
A1065: 1059 | B1065: Ana Claudia Zanini | C1065: InstanTH NEO | D1065: Pesquisa sobre profissionais para estudo de caso | E1065: 43907 | F1065: 0.041666667 | G1065: TRUE | H1065: =IF(VLOOKUP(C1065,Projetos!A:L,12,false)=TRUE,TRUE,FALSE) -> TRUE | I1065: 29.312396 | J1065: =IFERROR(IF(AND(G1065=TRUE,YEAR(E1065)<2021),F1065,"")*(I1065*24),0) -> 29.312396 | K1065: TRUE
A1066: 1060 | B1066: Ana Claudia Zanini | C1066: InstanTH NEO | D1066: Pesquisa sobre profissionais para estudo de caso | E1066: 43908 | F1066: 0.041666667 | G1066: TRUE | H1066: =IF(VLOOKUP(C1066,Projetos!A:L,12,false)=TRUE,TRUE,FALSE) -> TRUE | I1066: 29.312396 | J1066: =IFERROR(IF(AND(G1066=TRUE,YEAR(E1066)<2021),F1066,"")*(I1066*24),0) -> 29.312396 | K1066: TRUE
A1067: 1061 | B1067: Ana Claudia Zanini | C1067: InstanTH NEO | D1067: Pesquisa sobre profissionais para estudo de caso | E1067: 43916 | F1067: 0.041666667 | G1067: TRUE | H1067: =IF(VLOOKUP(C1067,Projetos!A:L,12,false)=TRUE,TRUE,FALSE) -> TRUE | I1067: 29.312396 | J1067: =IFERROR(IF(AND(G1067=TRUE,YEAR(E1067)<2021),F1067,"")*(I1067*24),0) -> 29.312396 | K1067: TRUE
A1068: 1062 | B1068: Ana Claudia Zanini | C1068: InstanTH NEO | D1068: Pesquisa sobre profissionais para estudo de caso | E1068: 43917 | F1068: 0.03125 | G1068: TRUE | H1068: =IF(VLOOKUP(C1068,Projetos!A:L,12,false)=TRUE,TRUE,FALSE) -> TRUE | I1068: 29.312396 | J1068: =IFERROR(IF(AND(G1068=TRUE,YEAR(E1068)<2021),F1068,"")*(I1068*24),0) -> 21.984297 | K1068: TRUE
A1069: 1063 | B1069: Ana Claudia Zanini | C1069: Novos Produtos Turquia | D1069: Pesquisa e desenvolvimento de novas fórmulas | E1069: 43910 | F1069: 0.1875 | G1069: TRUE | H1069: =IF(VLOOKUP(C1069,Projetos!A:L,12,false)=TRUE,TRUE,FALSE) -> TRUE | I1069: 29.312396 | J1069: =IFERROR(IF(AND(G1069=TRUE,YEAR(E1069)<2021),F1069,"")*(I1069*24),0) -> 131.90578 | K1069: TRUE
A1070: 1064 | B1070: Ana Claudia Zanini | C1070: Novos Produtos Turquia | D1070: Pesquisa e desenvolvimento de novas fórmulas | E1070: 43914 | F1070: 0.20833333 | G1070: TRUE | H1070: =IF(VLOOKUP(C1070,Projetos!A:L,12,false)=TRUE,TRUE,FALSE) -> TRUE | I1070: 29.312396 | J1070: =IFERROR(IF(AND(G1070=TRUE,YEAR(E1070)<2021),F1070,"")*(I1070*24),0) -> 146.56198 | K1070: TRUE
A1071: 1065 | B1071: Ana Claudia Zanini | C1071: Novos Produtos Turquia | D1071: Pesquisa e desenvolvimento de novas fórmulas | E1071: 43916 | F1071: 0.125 | G1071: TRUE | H1071: =IF(VLOOKUP(C1071,Projetos!A:L,12,false)=TRUE,TRUE,FALSE) -> TRUE | I1071: 29.312396 | J1071: =IFERROR(IF(AND(G1071=TRUE,YEAR(E1071)<2021),F1071,"")*(I1071*24),0) -> 87.937189 | K1071: TRUE
... A3492: 3486 | B3492: Hellin dos Santos | C3492: Trophic Soya 1.5 Fiber | D3492: Pesquisa Básica PIS | E3492: 44175 | F3492: 0.0625 | G3492: TRUE | H3492: =IF(VLOOKUP(C3492,Projetos!A:L,12,false)=TRUE,TRUE,FALSE) -> TRUE | I3492: 108.543 | J3492: =IFERROR(IF(AND(G3492=TRUE,YEAR(E3492)<2021),F3492,"")*(I3492*24),0) -> 162.81451 | K3492: TRUE

Sheet Cópia de Timesheet
A2: Timesheet
A3: BENEFÍCIO FISCAL DE PD&I 2019 | I3: Parcial | J3: =J5-J4 -> 312686.56
I4: Exclusivo | J4: =IFERROR(__xludf.DUMMYFUNCTION("SUMIF($B$7:$B3492,FILTER(Pessoal!$A$10:$A$26,Pessoal!$U$10:$U$26 = ""Exclusivo"",MATCH(Pessoal!$A$10:$A$26,FILTER(Pessoal!$A$37:$A$57,Pessoal!$U$37:$U$57 = TRUE),0)),$J$7:$J3492)"),0.0) -> 0
I5: TOTAL | J5: =SUM(J7:J3492) -> 312686.56
A6: Cod | B6: Pessoa | C6: Projeto | D6: Descrição | E6: Start | F6: Tempo aplicado | G6: Atividade incentivada | H6: Attachments | I6: Valor (R$) | J6: Custo | K6: checkprojetos
A7: 1 | B7: Ademir Mararangoni | C7: Immax - etapa final da Pesquisa Clínica | D7: Coordenar pesagem e produção | E7: 43846 | F7: 0.041666667 | G7: TRUE | H7: =IF(VLOOKUP(C7,Projetos!A:L,12,false)=TRUE,TRUE,FALSE) -> TRUE | I7: {=VLOOKUP(B7:B3492,Pessoal!$A$36:$R$57,MONTH(E7:E3492)+6,false)} -> 63.065873 | J7: =IFERROR(IF(AND(G7=TRUE,YEAR(E7)<2021),F7,"")*(I7*24),0) -> 63.065873 | K7: {=VLOOKUP(C7:C3492,Projetos!A6:L3492,12,false)} -> TRUE
A8: 2 | B8: Ademir Mararangoni | C8: InstanTH NEO | D8: Coordenar separação, emissão de NF e envio dos materiais para produção | E8: 43840 | F8: 0.083333333 | G8: TRUE | H8: =IF(VLOOKUP(C8,Projetos!A:L,12,false)=TRUE,TRUE,FALSE) -> TRUE | I8: 63.065873 | J8: =IFERROR(IF(AND(G8=TRUE,YEAR(E8)<2021),F8,"")*(I8*24),0) -> 126.13175 | K8: TRUE
A9: 3 | B9: Ademir Mararangoni | C9: InstanTH CLEAR (espessante) | D9: Adequação da linha de produção para o envase (Novo Twister, Envasadora, Esteira tampadora Plock off) | E9: 43850 | F9: 0.40625 | G9: TRUE | H9: =IF(VLOOKUP(C9,Projetos!A:L,12,false)=TRUE,TRUE,FALSE) -> TRUE | I9: 63.065873 | J9: =IFERROR(IF(AND(G9=TRUE,YEAR(E9)<2021),F9,"")*(I9*24),0) -> 614.89226 | K9: TRUE
A10: 4 | B10: Ademir Mararangoni | C10: Inovação industrial - misturas secas | D10: Implementação do projeto balança onde integraliza a pesagem do fracionamento com o estrutura do sistema para minimizar erros | E10: 43843 | F10: 0.40625 | G10: FALSE | H10: =IF(VLOOKUP(C10,Projetos!A:L,12,false)=TRUE,TRUE,FALSE) -> FALSE | I10: 63.065873 | J10: =IFERROR(IF(AND(G10=TRUE,YEAR(E10)<2021),F10,"")*(I10*24),0) -> 0 | K10: FALSE
A11: 5 | B11: Ademir Mararangoni | C11: Inovação industrial - misturas secas | D11: Teste de n² com enertizado da Brasilata | E11: 43845 | F11: 0.23958333 | G11: FALSE | H11: =IF(VLOOKUP(C11,Projetos!A:L,12,false)=TRUE,TRUE,FALSE) -> FALSE | I11: 63.065873 | J11: =IFERROR(IF(AND(G11=TRUE,YEAR(E11)<2021),F11,"")*(I11*24),0) -> 0 | K11: FALSE
A12: 6 | B12: Ademir Mararangoni | C12: InstanTH CLEAR (espessante) | D12: Primeira produção do Instant clear | E12: 43872 | F12: 0.083333333 | G12: TRUE | H12: =IF(VLOOKUP(C12,Projetos!A:L,12,false)=TRUE,TRUE,FALSE) -> TRUE | I12: 60.199242 | J12: =IFERROR(IF(AND(G12=TRUE,YEAR(E12)<2021),F12,"")*(I12*24),0) -> 120.39848 | K12: TRUE
A13: 7 | B13: Ademir Mararangoni | C13: InstanTH NEO | D13: Apontamento, triangulazação de NF | E13: 43888 | F13: 0.083333333 | G13: FALSE | H13: =IF(VLOOKUP(C13,Projetos!A:L,12,false)=TRUE,TRUE,FALSE) -> TRUE | I13: 60.199242 | J13: =IFERROR(IF(AND(G13=TRUE,YEAR(E13)<2021),F13,"")*(I13*24),0) -> 0 | K13: TRUE
A14: 8 | B14: Ademir Mararangoni | C14: Bemmax Sabor Neutro | D14: Teste de envase -peso alcançado 350g | E14: 43879 | F14: 0.10416667 | G14: TRUE | H14: =IF(VLOOKUP(C14,Projetos!A:L,12,false)=TRUE,TRUE,FALSE) -> TRUE | I14: 60.199242 | J14: =IFERROR(IF(AND(G14=TRUE,YEAR(E14)<2021),F14,"")*(I14*24),0) -> 150.49811 | K14: TRUE
A15: 9 | B15: Ademir Mararangoni | C15: Retort (Sistema Fechado) | D15: Separação de MP fisico e sistema para pesagem de teste | E15: 43876 | F15: 0.083333333 | G15: FALSE | H15: =IF(VLOOKUP(C15,Projetos!A:L,12,false)=TRUE,TRUE,FALSE) -> TRUE | I15: 60.199242 | J15: =IFERROR(IF(AND(G15=TRUE,YEAR(E15)<2021),F15,"")*(I15*24),0) -> 0 | K15: TRUE
A16: 10 | B16: Ademir Mararangoni | C16: HDmax 2.0 | D16: Separação de MP fisico e sistema para pesagem de teste | E16: 43874 | F16: 0.083333333 | G16: TRUE | H16: =IF(VLOOKUP(C16,Projetos!A:L,12,false)=TRUE,TRUE,FALSE) -> TRUE | I16: 60.199242 | J16: =IFERROR(IF(AND(G16=TRUE,YEAR(E16)<2021),F16,"")*(I16*24),0) -> 120.39848 | K16: TRUE
A17: 11 | B17: Ademir Mararangoni | C17: Inovação industrial - misturas secas | D17: Validação com comercial e manutenção pra aquisição de strechadeira automática | E17: 43886 | F17: 0.083333333 | G17: FALSE | H17: =IF(VLOOKUP(C17,Projetos!A:L,12,false)=TRUE,TRUE,FALSE) -> FALSE | I17: 60.199242 | J17: =IFERROR(IF(AND(G17=TRUE,YEAR(E17)<2021),F17,"")*(I17*24),0) -> 0 | K17: FALSE
A18: 12 | B18: Ademir Mararangoni | C18: Inovação industrial - misturas secas | D18: Alinhamento do projeto balança onde integraliza a pesagem do fracionamento com o estrutura do sistema para minimizar erros | E18: 43865 | F18: 0.041666667 | G18: FALSE | H18: =IF(VLOOKUP(C18,Projetos!A:L,12,false)=TRUE,TRUE,FALSE) -> FALSE | I18: 60.199242 | J18: =IFERROR(IF(AND(G18=TRUE,YEAR(E18)<2021),F18,"")*(I18*24),0) -> 0 | K18: FALSE
A19: 13 | B19: Ademir Mararangoni | C19: Inovação industrial - misturas secas | D19: Alinhamento do projeto balança onde integraliza a pesagem do fracionamento com o estrutura do sistema para minimizar erros | E19: 43875 | F19: 0.083333333 | G19: FALSE | H19: =IF(VLOOKUP(C19,Projetos!A:L,12,false)=TRUE,TRUE,FALSE) -> FALSE | I19: 60.199242 | J19: =IFERROR(IF(AND(G19=TRUE,YEAR(E19)<2021),F19,"")*(I19*24),0) -> 0 | K19: FALSE
... A856: 850 | B856: Ana Paula Celes | C856: InstanTH NEO | D856: Discussão de linhas de pesquisa clinica | E856: 43844 | F856: 0.020833333 | G856: TRUE | H856: =IF(VLOOKUP(C856,Projetos!A:L,12,false)=TRUE,TRUE,FALSE) -> TRUE | I856: 169.03747 | J856: =IFERROR(IF(AND(G856=TRUE,YEAR(E856)<2021),F856,"")*(I856*24),0) -> 84.518733 | K856: TRUE
A857: 851 | B857: Ana Paula Celes | C857: InstanTH NEO | D857: Discussão de linhas de pesquisa clinica | F857: 0 | G857: FALSE | H857: =IF(VLOOKUP(C857,Projetos!A:L,12,false)=TRUE,TRUE,FALSE) -> TRUE | I857: 169.03747 | J857: =IFERROR(IF(AND(G857=TRUE,YEAR(E857)<2021),F857,"")*(I857*24),0) -> 0 | K857: TRUE
A858: 852 | B858: Ana Paula Celes | C858: Retort (Sistema Fechado) | D858: Planejamento das embalagens | E858: 43837 | F858: 0.0625 | G858: FALSE | H858: =IF(VLOOKUP(C858,Projetos!A:L,12,false)=TRUE,TRUE,FALSE) -> TRUE | I858: 169.03747 | J858: =IFERROR(IF(AND(G858=TRUE,YEAR(E858)<2021),F858,"")*(I858*24),0) -> 0 | K858: TRUE
A859: 853 | B859: Ana Paula Celes | C859: Retort (Sistema Fechado) | D859: Direcionamento global de todo sitema de tratamento termico | E859: 43838 | F859: 0.083333333 | G859: FALSE | H859: =IF(VLOOKUP(C859,Projetos!A:L,12,false)=TRUE,TRUE,FALSE) -> TRUE | I859: 169.03747 | J859: =IFERROR(IF(AND(G859=TRUE,YEAR(E859)<2021),F859,"")*(I859*24),0) -> 0 | K859: TRUE
A860: 854 | B860: Ana Paula Celes | C860: Retort (Sistema Fechado) | D860: Diretrizes e cmposição micronutrientes das fórmulas | E860: 43858 | F860: 0.041666667 | G860: FALSE | H860: =IF(VLOOKUP(C860,Projetos!A:L,12,false)=TRUE,TRUE,FALSE) -> TRUE | I860: 169.03747 | J860: =IFERROR(IF(AND(G860=TRUE,YEAR(E860)<2021),F860,"")*(I860*24),0) -> 0 | K860: TRUE
A861: 855 | B861: Ana Paula Celes | C861: Sarcopenia | D861: Definição do conceito de inovação e nutrientes da formula | E861: 43837 | F861: 0.041666667 | G861: TRUE | H861: =IF(VLOOKUP(C861,Projetos!A:L,12,false)=TRUE,TRUE,FALSE) -> TRUE | I861: 169.03747 | J861: =IFERROR(IF(AND(G861=TRUE,YEAR(E861)<2021),F861,"")*(I861*24),0) -> 169.03747 | K861: TRUE
A862: 856 | B862: Ana Paula Celes | C862: InstanTH NEO | D862: Análise e discussão da comunicção de inovação ao mercado | E862: 43873 | F862: 0.041666667 | G862: TRUE | H862: =IF(VLOOKUP(C862,Projetos!A:L,12,false)=TRUE,TRUE,FALSE) -> TRUE | I862: 161.35394 | J862: =IFERROR(IF(AND(G862=TRUE,YEAR(E862)<2021),F862,"")*(I862*24),0) -> 161.35394 | K862: TRUE
A863: 857 | B863: Ana Paula Celes | C863: Retort (Sistema Fechado) | D863: Planejamento para teste piloto | E863: 43866 | F863: 0.041666667 | G863: TRUE | H863: =IF(VLOOKUP(C863,Projetos!A:L,12,false)=TRUE,TRUE,FALSE) -> TRUE | I863: 161.35394 | J863: =IFERROR(IF(AND(G863=TRUE,YEAR(E863)<2021),F863,"")*(I863*24),0) -> 161.35394 | K863: TRUE
A864: 858 | B864: Ana Paula Celes | C864: Retort (Sistema Fechado) | D864: Atualizações do projeto | E864: 43871 | F864: 0.0625 | G864: FALSE | H864: =IF(VLOOKUP(C864,Projetos!A:L,12,false)=TRUE,TRUE,FALSE) -> TRUE | I864: 161.35394 | J864: =IFERROR(IF(AND(G864=TRUE,YEAR(E864)<2021),F864,"")*(I864*24),0) -> 0 | K864: TRUE
A865: 859 | B865: Ana Paula Celes | C865: Retort (Sistema Fechado) | D865: Discussão de linhas de pesquisa clinica | E865: 43872 | F865: 0.041666667 | G865: TRUE | H865: =IF(VLOOKUP(C865,Projetos!A:L,12,false)=TRUE,TRUE,FALSE) -> TRUE | I865: 161.35394 | J865: =IFERROR(IF(AND(G865=TRUE,YEAR(E865)<2021),F865,"")*(I865*24),0) -> 161.35394 | K865: TRUE
A866: 860 | B866: Ana Paula Celes | C866: Retort (Sistema Fechado) | D866: Fechamento de diretrizes do teste piloto | E866: 43873 | F866: 0.020833333 | G866: TRUE | H866: =IF(VLOOKUP(C866,Projetos!A:L,12,false)=TRUE,TRUE,FALSE) -> TRUE | I866: 161.35394 | J866: =IFERROR(IF(AND(G866=TRUE,YEAR(E866)<2021),F866,"")*(I866*24),0) -> 80.676972 | K866: TRUE
A867: 861 | B867: Ana Paula Celes | C867: Retort (Sistema Fechado) | D867: Execução de tetes em planta piloto | E867: 43878 | F867: 0.41666667 | G867: TRUE | H867: =IF(VLOOKUP(C867,Projetos!A:L,12,false)=TRUE,TRUE,FALSE) -> TRUE | I867: 161.35394 | J867: =IFERROR(IF(AND(G867=TRUE,YEAR(E867)<2021),F867,"")*(I867*24),0) -> 1613.5394 | K867: TRUE
A868: 862 | B868: Ana Paula Celes | C868: Retort (Sistema Fechado) | D868: Execução de tetes em planta piloto | E868: 43879 | F868: 0.41666667 | G868: TRUE | H868: =IF(VLOOKUP(C868,Projetos!A:L,12,false)=TRUE,TRUE,FALSE) -> TRUE | I868: 161.35394 | J868: =IFERROR(IF(AND(G868=TRUE,YEAR(E868)<2021),F868,"")*(I868*24),0) -> 1613.5394 | K868: TRUE
A869: 863 | B869: Ana Paula Celes | C869: Retort (Sistema Fechado) | D869: Monitoramento dos resultados de testes FQ | E869: 43889 | F869: 0.041666667 | G869: TRUE | H869: =IF(VLOOKUP(C869,Projetos!A:L,12,false)=TRUE,TRUE,FALSE) -> TRUE | I869: 161.35394 | J869: =IFERROR(IF(AND(G869=TRUE,YEAR(E869)<2021),F869,"")*(I869*24),0) -> 161.35394 | K869: TRUE
... A1058: 1052 | B1058: Ana Paula Celes | C1058: Vulcano (pote jumbo e sachês a vácuo) | D1058: Definições de ações do projeto Jumbo e sache vacuo | E1058: 44194 | F1058: 0.083333333 | G1058: FALSE | H1058: =IF(VLOOKUP(C1058,Projetos!A:L,12,false)=TRUE,TRUE,FALSE) -> FALSE | I1058: 169.03747 | J1058: =IFERROR(IF(AND(G1058=TRUE,YEAR(E1058)<2021),F1058,"")*(I1058*24),0) -> 0 | K1058: FALSE
A1059: 1053 | B1059: Ana Paula Celes | C1059: Centro de Inovação | D1059: Análise de atividades de P&D | F1059: 0.0625 | G1059: FALSE | H1059: =IF(VLOOKUP(C1059,Projetos!A:L,12,false)=TRUE,TRUE,FALSE) -> FALSE | I1059: 169.03747 | J1059: =IFERROR(IF(AND(G1059=TRUE,YEAR(E1059)<2021),F1059,"")*(I1059*24),0) -> 0 | K1059: FALSE
A1060: 1054 | B1060: Ana Claudia Zanini | C1060: Sarcopenia | D1060: Desenvolvimento de protocolo de pesquisa clinica | E1060: 43895 | F1060: 0.1875 | G1060: TRUE | H1060: =IF(VLOOKUP(C1060,Projetos!A:L,12,false)=TRUE,TRUE,FALSE) -> TRUE | I1060: 29.312396 | J1060: =IFERROR(IF(AND(G1060=TRUE,YEAR(E1060)<2021),F1060,"")*(I1060*24),0) -> 131.90578 | K1060: TRUE
A1061: 1055 | B1061: Ana Claudia Zanini | C1061: Sarcopenia | D1061: Desenvolvimento de protocolo de pesquisa clinica | E1061: 43896 | F1061: 0.16666667 | G1061: TRUE | H1061: =IF(VLOOKUP(C1061,Projetos!A:L,12,false)=TRUE,TRUE,FALSE) -> TRUE | I1061: 29.312396 | J1061: =IFERROR(IF(AND(G1061=TRUE,YEAR(E1061)<2021),F1061,"")*(I1061*24),0) -> 117.24959 | K1061: TRUE
A1062: 1056 | B1062: Ana Claudia Zanini | C1062: Sarcopenia | D1062: Desenvolvimento de protocolo de pesquisa clinica | E1062: 43901 | F1062: 0.1875 | G1062: TRUE | H1062: =IF(VLOOKUP(C1062,Projetos!A:L,12,false)=TRUE,TRUE,FALSE) -> TRUE | I1062: 29.312396 | J1062: =IFERROR(IF(AND(G1062=TRUE,YEAR(E1062)<2021),F1062,"")*(I1062*24),0) -> 131.90578 | K1062: TRUE
A1063: 1057 | B1063: Ana Claudia Zanini | C1063: Sarcopenia | D1063: Desenvolvimento de protocolo de pesquisa clinica | E1063: 43903 | F1063: 0.10416667 | G1063: TRUE | H1063: =IF(VLOOKUP(C1063,Projetos!A:L,12,false)=TRUE,TRUE,FALSE) -> TRUE | I1063: 29.312396 | J1063: =IFERROR(IF(AND(G1063=TRUE,YEAR(E1063)<2021),F1063,"")*(I1063*24),0) -> 73.280991 | K1063: TRUE
A1064: 1058 | B1064: Ana Claudia Zanini | C1064: Sarcopenia | D1064: Desenvolvimento de protocolo de pesquisa clinica | E1064: 43903 | F1064: 0.083333333 | G1064: TRUE | H1064: =IF(VLOOKUP(C1064,Projetos!A:L,12,false)=TRUE,TRUE,FALSE) -> TRUE | I1064: 29.312396 | J1064: =IFERROR(IF(AND(G1064=TRUE,YEAR(E1064)<2021),F1064,"")*(I1064*24),0) -> 58.624793 | K1064: TRUE
A1065: 1059 | B1065: Ana Claudia Zanini | C1065: InstanTH NEO | D1065: Pesquisa sobre profissionais para estudo de caso | E1065: 43907 | F1065: 0.041666667 | G1065: TRUE | H1065: =IF(VLOOKUP(C1065,Projetos!A:L,12,false)=TRUE,TRUE,FALSE) -> TRUE | I1065: 29.312396 | J1065: =IFERROR(IF(AND(G1065=TRUE,YEAR(E1065)<2021),F1065,"")*(I1065*24),0) -> 29.312396 | K1065: TRUE
A1066: 1060 | B1066: Ana Claudia Zanini | C1066: InstanTH NEO | D1066: Pesquisa sobre profissionais para estudo de caso | E1066: 43908 | F1066: 0.041666667 | G1066: TRUE | H1066: =IF(VLOOKUP(C1066,Projetos!A:L,12,false)=TRUE,TRUE,FALSE) -> TRUE | I1066: 29.312396 | J1066: =IFERROR(IF(AND(G1066=TRUE,YEAR(E1066)<2021),F1066,"")*(I1066*24),0) -> 29.312396 | K1066: TRUE
A1067: 1061 | B1067: Ana Claudia Zanini | C1067: InstanTH NEO | D1067: Pesquisa sobre profissionais para estudo de caso | E1067: 43916 | F1067: 0.041666667 | G1067: TRUE | H1067: =IF(VLOOKUP(C1067,Projetos!A:L,12,false)=TRUE,TRUE,FALSE) -> TRUE | I1067: 29.312396 | J1067: =IFERROR(IF(AND(G1067=TRUE,YEAR(E1067)<2021),F1067,"")*(I1067*24),0) -> 29.312396 | K1067: TRUE
A1068: 1062 | B1068: Ana Claudia Zanini | C1068: InstanTH NEO | D1068: Pesquisa sobre profissionais para estudo de caso | E1068: 43917 | F1068: 0.03125 | G1068: TRUE | H1068: =IF(VLOOKUP(C1068,Projetos!A:L,12,false)=TRUE,TRUE,FALSE) -> TRUE | I1068: 29.312396 | J1068: =IFERROR(IF(AND(G1068=TRUE,YEAR(E1068)<2021),F1068,"")*(I1068*24),0) -> 21.984297 | K1068: TRUE
A1069: 1063 | B1069: Ana Claudia Zanini | C1069: Novos Produtos Turquia | D1069: Pesquisa e desenvolvimento de novas fórmulas | E1069: 43910 | F1069: 0.1875 | G1069: TRUE | H1069: =IF(VLOOKUP(C1069,Projetos!A:L,12,false)=TRUE,TRUE,FALSE) -> TRUE | I1069: 29.312396 | J1069: =IFERROR(IF(AND(G1069=TRUE,YEAR(E1069)<2021),F1069,"")*(I1069*24),0) -> 131.90578 | K1069: TRUE
A1070: 1064 | B1070: Ana Claudia Zanini | C1070: Novos Produtos Turquia | D1070: Pesquisa e desenvolvimento de novas fórmulas | E1070: 43914 | F1070: 0.20833333 | G1070: TRUE | H1070: =IF(VLOOKUP(C1070,Projetos!A:L,12,false)=TRUE,TRUE,FALSE) -> TRUE | I1070: 29.312396 | J1070: =IFERROR(IF(AND(G1070=TRUE,YEAR(E1070)<2021),F1070,"")*(I1070*24),0) -> 146.56198 | K1070: TRUE
A1071: 1065 | B1071: Ana Claudia Zanini | C1071: Novos Produtos Turquia | D1071: Pesquisa e desenvolvimento de novas fórmulas | E1071: 43916 | F1071: 0.125 | G1071: TRUE | H1071: =IF(VLOOKUP(C1071,Projetos!A:L,12,false)=TRUE,TRUE,FALSE) -> TRUE | I1071: 29.312396 | J1071: =IFERROR(IF(AND(G1071=TRUE,YEAR(E1071)<2021),F1071,"")*(I1071*24),0) -> 87.937189 | K1071: TRUE
... A3492: 3486 | B3492: Hellin dos Santos | C3492: Trophic Soya 1.5 Fiber | D3492: Pesquisa Básica PIS | E3492: 44175 | F3492: 0.0625 | G3492: TRUE | H3492: =IF(VLOOKUP(C3492,Projetos!A:L,12,false)=TRUE,TRUE,FALSE) -> TRUE | I3492: 108.543 | J3492: =IFERROR(IF(AND(G3492=TRUE,YEAR(E3492)<2021),F3492,"")*(I3492*24),0) -> 162.81451 | K3492: TRUE

Sheet Pessoal
A2: Pessoal
A4: Salario bruto | G4: planilha RH | H4: planilha RH | I4: planilha RH | J4: planilha RH | K4: planilha RH | L4: planilha RH | M4: planilha RH | N4: planilha RH | O4: planilha RH | P4: planilha RH | Q4: RH atualizou online | R4: RH atualizou online | S4: =(T4/12)*24 -> 171.33333 | T4: =(SUM(G35:R35)*8)/24 -> 85.666667
A5: Nome Completo | B5: CPF | C5: notas | D5: Cargo/função | E5: Formação | F5: Attachments | G5: Salário 01 | H5: Salário 02 | I5: Salário 03 | J5: Salário 04 | K5: Salário 05 | L5: Salário 06 | M5: Salário 07 | N5: Salário 08 | O5: Salário 09 | P5: Salário 10 | Q5: Salário 11 | R5: Salário 12 | S5: PD&I time | T5: PD&I (%) | U5: Classificação | V5: Pesquisador
A6: Ademir Mararangoni | B6: 018.764.779-89 | D6: Coord. PCP | E6: Superior Completo | G6: 7255.64 | H6: 7255.64 | I6: 7255.64 | J6: 7255.64 | K6: 7255.64 | L6: 7255.64 | M6: 7255.64 | N6: 7255.64 | O6: 7618.42 | P6: 7618.42 | Q6: 7743.36 | R6: =Q6 -> 7743.36 | S6: =IFERROR(__xludf.DUMMYFUNCTION("IFERROR(if(V6=true, SUM(FILTER(Timesheet!$F:$F,Timesheet!G:G = TRUE,Timesheet!B:B = A6,Timesheet!E:E < DATE(2021,1,1))),0),0)"),0.0) -> 0 | T6: =S6/$T$4 -> 0 | U6: =IF(T6<80%,"Parcial","Exclusivo") -> Parcial | V6: FALSE
A7: Ana Claudia Zanini | B7: 076.046.519-33 | D7: Analista Científico | E7: Mestrado | I7: 3372.35 | J7: 3372.35 | K7: 3372.35 | L7: 3372.35 | M7: 3372.35 | N7: 3372.35 | O7: 3372.35 | P7: 3372.35 | Q7: 3599.04 | R7: =Q7 -> 3599.04 | S7: =IFERROR(__xludf.DUMMYFUNCTION("IFERROR(if(V7=true, SUM(FILTER(Timesheet!$F:$F,Timesheet!G:G = TRUE,Timesheet!B:B = A7,Timesheet!E:E < DATE(2021,1,1))),0),0)"),38.302083333333314) -> 38.302083 | T7: =S7/$T$4 -> 0.44710603 | U7: =IF(T7<80%,"Parcial","Exclusivo") -> Parcial | V7: TRUE
A8: Ana Paula Celes | B8: 759.837.297-72 | D8: Diretora Técnica | E8: Pós graduado | F8: PJ | G8: 30393.85 | H8: 30393.85 | I8: 30393.85 | J8: 30393.85 | K8: 30393.85 | L8: 30393.85 | M8: 30393.85 | N8: 30393.85 | O8: 30393.85 | P8: 30393.85 | Q8: =P8 -> 30393.85 | R8: =Q8 -> 30393.85 | S8: =IFERROR(__xludf.DUMMYFUNCTION("IFERROR(if(V8=true, SUM(FILTER(Timesheet!$F:$F,Timesheet!G:G = TRUE,Timesheet!B:B = A8,Timesheet!E:E < DATE(2021,1,1))),0),0)"),5.503472222222221) -> 5.5034722 | T8: =S8/$T$4 -> 0.064242866 | U8: =IF(T8<80%,"Parcial","Exclusivo") -> Parcial | V8: TRUE
A9: Arianna Schreiber | B9: 066.466.799-67 | D9: Gerente Mkt | E9: Pós graduado | G9: 7869.54 | H9: 7869.54 | I9: 7869.54 | J9: 7869.54 | K9: 7869.54 | L9: 7869.54 | M9: 7869.54 | N9: 7869.54 | O9: 8735.19 | P9: 8735.19 | Q9: 8878.45 | R9: =Q9 -> 8878.45 | S9: =IFERROR(__xludf.DUMMYFUNCTION("IFERROR(if(V9=true, SUM(FILTER(Timesheet!$F:$F,Timesheet!G:G = TRUE,Timesheet!B:B = A9,Timesheet!E:E < DATE(2021,1,1))),0),0)"),1.2500000000000002) -> 1.25 | T9: =S9/$T$4 -> 0.01459144 | U9: =IF(T9<80%,"Parcial","Exclusivo") -> Parcial | V9: TRUE
A10: Camila Mendes Pereira | B10: 083.832.289-10 | D10: Assistente de P&D | E10: Superior Completo | G10: 2493.03 | H10: 2493.03 | I10: 2493.03 | J10: 2493.03 | K10: 2493.03 | L10: 2493.03 | M10: 2493.03 | N10: 2493.03 | O10: 2771.24 | P10: 2771.24 | Q10: 2816.69 | R10: =Q10 -> 2816.69 | S10: =IFERROR(__xludf.DUMMYFUNCTION("IFERROR(if(V10=true, SUM(FILTER(Timesheet!$F:$F,Timesheet!G:G = TRUE,Timesheet!B:B = A10,Timesheet!E:E < DATE(2021,1,1))),0),0)"),30.124305555555548) -> 30.124306 | T10: =S10/$T$4 -> 0.35164559 | U10: =IF(T10<80%,"Parcial","Exclusivo") -> Parcial | V10: TRUE
A11: Denise Barros Ferreira | B11: 796.047.576-87 | D11: Coord. CQ | E11: Superior Completo | G11: 5010.94 | H11: 5010.94 | I11: 5010.94 | J11: 5010.94 | K11: 5010.94 | L11: 5010.94 | M11: 5010.94 | N11: 5010.94 | O11: 5010.94 | P11: 5010.94 | Q11: 5093.12 | R11: =Q11 -> 5093.12 | S11: =IFERROR(__xludf.DUMMYFUNCTION("IFERROR(if(V11=true, SUM(FILTER(Timesheet!$F:$F,Timesheet!G:G = TRUE,Timesheet!B:B = A11,Timesheet!E:E < DATE(2021,1,1))),0),0)"),0.0) -> 0 | T11: =S11/$T$4 -> 0 | U11: =IF(T11<80%,"Parcial","Exclusivo") -> Parcial | V11: FALSE
A12: Emanuela Adam Bechlin Picheki | B12: 065.358.929-80 | D12: Compradora | E12: Pós graduado | G12: 6215.73 | H12: 6215.73 | I12: 6215.73 | J12: 6215.73 | K12: 6215.73 | L12: 6215.73 | M12: 6215.73 | N12: 6215.73 | O12: 6215.73 | P12: 6215.73 | Q12: 6949.43 | R12: =Q12 -> 6949.43 | S12: =IFERROR(__xludf.DUMMYFUNCTION("IFERROR(if(V12=true, SUM(FILTER(Timesheet!$F:$F,Timesheet!G:G = TRUE,Timesheet!B:B = A12,Timesheet!E:E < DATE(2021,1,1))),0),0)"),3.3541666666666647) -> 3.3541667 | T12: =S12/$T$4 -> 0.039153697 | U12: =IF(T12<80%,"Parcial","Exclusivo") -> Parcial | V12: TRUE
A13: Fabiano Ribeiro da Silva | B13: 023.493.009-86 | D13: Coord. Manutenção | E13: Pós graduado | G13: 5566.87 | H13: 5566.87 | I13: 5566.87 | J13: 5566.87 | K13: 5566.87 | L13: 5566.87 | M13: 5566.87 | N13: 5566.87 | O13: 6012.22 | P13: 6012.22 | Q13: 6110.82 | R13: =Q13 -> 6110.82 | S13: =IFERROR(__xludf.DUMMYFUNCTION("IFERROR(if(V13=true, SUM(FILTER(Timesheet!$F:$F,Timesheet!G:G = TRUE,Timesheet!B:B = A13,Timesheet!E:E < DATE(2021,1,1))),0),0)"),0.0) -> 0 | T13: =S13/$T$4 -> 0 | U13: =IF(T13<80%,"Parcial","Exclusivo") -> Parcial | V13: FALSE
A14: Flavia Firmano Coelho | B14: 029.717.539-48 | D14: Analista AR | E14: Pós graduado | G14: 4650.77 | H14: 4765.42 | I14: 4765.42 | J14: 4765.42 | K14: 4765.42 | L14: 4765.42 | M14: 4765.42 | N14: 4765.42 | O14: 4765.42 | S14: =IFERROR(__xludf.DUMMYFUNCTION("IFERROR(if(V14=true, SUM(FILTER(Timesheet!$F:$F,Timesheet!G:G = TRUE,Timesheet!B:B = A14,Timesheet!E:E < DATE(2021,1,1))),0),0)"),0.0) -> 0 | T14: =S14/$T$4 -> 0 | U14: =IF(T14<80%,"Parcial","Exclusivo") -> Parcial | V14: FALSE
A15: Gabriela Faria de Oliveira | B15: 087.823.469-17 | D15: Analista Científico | E15: Superior Completo | G15: 3372.35 | H15: 3372.35 | I15: 3372.35 | J15: 3372.35 | K15: 3372.35 | L15: 3372.35 | M15: 3372.35 | N15: 3372.35 | O15: 3713 | P15: 3713 | Q15: 3773.89 | R15: =Q15 -> 3773.89 | S15: =IFERROR(__xludf.DUMMYFUNCTION("IFERROR(if(V15=true, SUM(FILTER(Timesheet!$F:$F,Timesheet!G:G = TRUE,Timesheet!B:B = A15,Timesheet!E:E < DATE(2021,1,1))),0),0)"),19.577083333333338) -> 19.577083 | T15: =S15/$T$4 -> 0.22852626 | U15: =IF(T15<80%,"Parcial","Exclusivo") -> Parcial | V15: TRUE
A16: Hellin dos Santos | B16: 058.544.839-63 | D16: Gerente Cientifico | E16: Mestrado | G16: 10111.64 | H16: 10111.64 | I16: 10111.64 | J16: 10111.64 | K16: 10111.64 | L16: 10111.64 | M16: 10111.64 | N16: 10111.64 | O16: 12286.23 | P16: 12286.23 | Q16: 12487.72 | R16: =Q16 -> 12487.72 | S16: =IFERROR(__xludf.DUMMYFUNCTION("IFERROR(if(V16=true, SUM(FILTER(Timesheet!$F:$F,Timesheet!G:G = TRUE,Timesheet!B:B = A16,Timesheet!E:E < DATE(2021,1,1))),0),0)"),58.036111111111154) -> 58.036111 | T16: =S16/$T$4 -> 0.67746433 | U16: =IF(T16<80%,"Parcial","Exclusivo") -> Parcial | V16: TRUE
A17: Kézia Rithássia Piccoli | B17: 077.680.169-47 | D17: Analista de GQ | E17: Pós graduado | G17: 3708.73 | H17: 3708.73 | I17: 3708.73 | J17: 3708.73 | K17: 3708.73 | L17: 3708.73 | M17: 3708.73 | N17: 3708.73 | O17: 4005.43 | P17: 4005.43 | Q17: 4071.12 | R17: =Q17 -> 4071.12 | S17: =IFERROR(__xludf.DUMMYFUNCTION("IFERROR(if(V17=true, SUM(FILTER(Timesheet!$F:$F,Timesheet!G:G = TRUE,Timesheet!B:B = A17,Timesheet!E:E < DATE(2021,1,1))),0),0)"),0.0) -> 0 | T17: =S17/$T$4 -> 0 | U17: =IF(T17<80%,"Parcial","Exclusivo") -> Parcial | V17: FALSE
A18: Lizianne Shmeil | B18: 052.485.199-93 | D18: Analista P&D | E18: Superior Completo | G18: 4332.79 | H18: 4332.79 | I18: 4332.79 | J18: 4332.79 | K18: 4332.79 | L18: 4332.79 | M18: 4332.79 | N18: 4332.79 | O18: 4914.94 | P18: 4914.94 | Q18: 4995.55 | R18: =Q18 -> 4995.55 | S18: =IFERROR(__xludf.DUMMYFUNCTION("IFERROR(if(V18=true, SUM(FILTER(Timesheet!$F:$F,Timesheet!G:G = TRUE,Timesheet!B:B = A18,Timesheet!E:E < DATE(2021,1,1))),0),0)"),55.85208333333332) -> 55.852083 | T18: =S18/$T$4 -> 0.65196984 | U18: =IF(T18<80%,"Parcial","Exclusivo") -> Parcial | V18: TRUE
A19: Luciana Dutra | B19: 186.586.978-35 | D19: Gerente Técnica | E19: Pós graduado | G19: 17326.88 | H19: 17326.88 | I19: 17326.88 | J19: 17326.88 | K19: 17326.88 | L19: 17326.88 | M19: 17326.88 | N19: 17326.88 | O19: 17326.88 | P19: 17326.88 | Q19: 17611.04 | R19: =Q19 -> 17611.04 | S19: =IFERROR(__xludf.DUMMYFUNCTION("IFERROR(if(V19=true, SUM(FILTER(Timesheet!$F:$F,Timesheet!G:G = TRUE,Timesheet!B:B = A19,Timesheet!E:E < DATE(2021,1,1))),0),0)"),10.304166666666664) -> 10.304167 | T19: =S19/$T$4 -> 0.1202821 | U19: =IF(T19<80%,"Parcial","Exclusivo") -> Parcial | V19: TRUE
A20: Lucimari Reway dos Santos | B20: 022.396.139-63 | C20: Técnico em Alimentos | D20: Analista CQ | E20: Técnico | G20: 2493.04 | H20: 2493.04 | I20: 2493.04 | J20: 2493.04 | K20: 2493.04 | L20: 2493.04 | M20: 2493.04 | N20: 2493.04 | O20: 3034.9 | P20: 3034.9 | Q20: 3084.67 | R20: =Q20 -> 3084.67 | S20: =IFERROR(__xludf.DUMMYFUNCTION("IFERROR(if(V20=true, SUM(FILTER(Timesheet!$F:$F,Timesheet!G:G = TRUE,Timesheet!B:B = A20,Timesheet!E:E < DATE(2021,1,1))),0),0)"),0.0) -> 0 | T20: =S20/$T$4 -> 0 | U20: =IF(T20<80%,"Parcial","Exclusivo") -> Parcial | V20: FALSE
A21: Marcella Malucelli Baltazar | B21: 098.146.729-63 | D21: Superv. produção | E21: Superior Completo | G21: 3708.73 | H21: 3708.73 | I21: 3708.73 | J21: 3708.73 | K21: 3708.73 | L21: 3708.73 | M21: 3708.73 | N21: 3708.73 | O21: 3708.73 | P21: 3708.73 | Q21: 3769.55 | R21: =Q21 -> 3769.55 | S21: =IFERROR(__xludf.DUMMYFUNCTION("IFERROR(if(V21=true, SUM(FILTER(Timesheet!$F:$F,Timesheet!G:G = TRUE,Timesheet!B:B = A21,Timesheet!E:E < DATE(2021,1,1))),0),0)"),0.0) -> 0 | T21: =S21/$T$4 -> 0 | U21: =IF(T21<80%,"Parcial","Exclusivo") -> Parcial | V21: FALSE
A22: Marianne Stigar | B22: 066.424.199-95 | D22: Coord. GQ | E22: Pós graduado | G22: 4640.42 | H22: 5010.94 | I22: 5010.94 | J22: 5010.94 | K22: 5010.94 | L22: 5010.94 | M22: 5010.94 | N22: 5010.94 | O22: 5010.94 | P22: 5010.94 | Q22: 5093.12 | R22: =Q22 -> 5093.12 | S22: =IFERROR(__xludf.DUMMYFUNCTION("IFERROR(if(V22=true, SUM(FILTER(Timesheet!$F:$F,Timesheet!G:G = TRUE,Timesheet!B:B = A22,Timesheet!E:E < DATE(2021,1,1))),0),0)"),0.125) -> 0.125 | T22: =S22/$T$4 -> 0.001459144 | U22: =IF(T22<80%,"Parcial","Exclusivo") -> Parcial | V22: TRUE
A23: Naíssa Previde Bernardo | B23: 215.916.758-47 | D23: Especisalista EEE | E23: Mestrado | P23: 9000 | Q23: =P23 -> 9000 | S23: =IFERROR(__xludf.DUMMYFUNCTION("IFERROR(if(V23=true, SUM(FILTER(Timesheet!$F:$F,Timesheet!G:G = TRUE,Timesheet!B:B = A23,Timesheet!E:E < DATE(2021,1,1))),0),0)"),0.0) -> 0 | T23: =S23/$T$4 -> 0 | U23: =IF(T23<80%,"Parcial","Exclusivo") -> Parcial | V23: FALSE
A24: Tahuany Leite | B24: 086.481.459-37 | D24: Analista MKT | E24: Pós graduado | G24: 3899.08 | H24: 3899.08 | I24: 3899.08 | J24: 3899.08 | K24: 3899.08 | L24: 3899.08 | M24: 3899.08 | N24: 3899.08 | O24: 3899.08 | P24: 3899.08 | Q24: 3963.02 | R24: =Q24 -> 3963.02 | S24: =IFERROR(__xludf.DUMMYFUNCTION("IFERROR(if(V24=true, SUM(FILTER(Timesheet!$F:$F,Timesheet!G:G = TRUE,Timesheet!B:B = A24,Timesheet!E:E < DATE(2021,1,1))),0),0)"),1.4791666666666665) -> 1.4791667 | T24: =S24/$T$4 -> 0.017266537 | U24: =IF(T24<80%,"Parcial","Exclusivo") -> Parcial | V24: TRUE
A25: Tais Carlotto | B25: 034.226.309-96 | D25: Coord. AR | E25: Superior Completo | G25: 5566.87 | H25: 6123.88 | I25: 6123.88 | J25: 6123.88 | K25: 6123.88 | L25: 6123.88 | M25: 6123.88 | N25: 6123.88 | O25: 6123.88 | P25: 6123.88 | Q25: 6224.31 | R25: =Q25 -> 6224.31 | S25: =IFERROR(__xludf.DUMMYFUNCTION("IFERROR(if(V25=true, SUM(FILTER(Timesheet!$F:$F,Timesheet!G:G = TRUE,Timesheet!B:B = A25,Timesheet!E:E < DATE(2021,1,1))),0),0)"),0.0) -> 0 | T25: =S25/$T$4 -> 0 | U25: =IF(T25<80%,"Parcial","Exclusivo") -> Parcial | V25: FALSE
S26: =IFERROR(__xludf.DUMMYFUNCTION("IFERROR(if(V26=true, SUM(FILTER(Timesheet!$F:$F,Timesheet!G:G = TRUE,Timesheet!B:B = A26,Timesheet!E:E < DATE(2021,1,1))),0),0)"),0.0) -> 0 | T26: =S26/$T$4 -> 0 | U26: =IF(T26<80%,"Parcial","Exclusivo") -> Parcial | V26: FALSE
A29: Cálculo do custo/hora
A31: Encargos sobre folha | H31: INSS | I31: Patronal | J31: 0.2
A32: INSS | B32: FGTS | C32: Férias | D32: 13º | E32: Total | I32: Terceiros | J32: 0.058 | T32: =IFERROR(__xludf.DUMMYFUNCTION("sum(FILTER(T37:T56,match(A37:A56,FILTER(A6:A25,U6:U25 = ""Parcial""))))"),300723.96873926383) -> 300723.97
A33: =sum(J31:J33) -> 0.273 | B33: 0.08 | C33: =((1+(1/3))+A33+B33)/12 -> 0.14052778 | D33: =(1+A33+B33)/12 -> 0.11275 | E33: =sum(A33:D33) -> 0.60627778 | I33: RAT | J33: 0.015 | T33: =IFERROR(__xludf.DUMMYFUNCTION("IFERROR(sum(FILTER(T37:T56,match(A37:A56,FILTER(A6:A25,U6:U25 = ""Exclusivo"")))),0)"),0.0) -> 0
G35: =NETWORKDAYS(DATE(2020,(LEFT(G$36,2)+0),1),DATE(2020,(LEFT(G$36,2)+0)+1,0),$A$62:$A$74) -> 21 | H35: =NETWORKDAYS(DATE(2020,(LEFT(H$36,2)+0),1),DATE(2020,(LEFT(H$36,2)+0)+1,0),$A$62:$A$74) -> 22 | I35: =NETWORKDAYS(DATE(2020,(LEFT(I$36,2)+0),1),DATE(2020,(LEFT(I$36,2)+0)+1,0),$A$62:$A$74) -> 21 | J35: =NETWORKDAYS(DATE(2020,(LEFT(J$36,2)+0),1),DATE(2020,(LEFT(J$36,2)+0)+1,0),$A$62:$A$74) -> 22 | K35: =NETWORKDAYS(DATE(2020,(LEFT(K$36,2)+0),1),DATE(2020,(LEFT(K$36,2)+0)+1,0),$A$62:$A$74) -> 21 | L35: =NETWORKDAYS(DATE(2020,(LEFT(L$36,2)+0),1),DATE(2020,(LEFT(L$36,2)+0)+1,0),$A$62:$A$74) -> 22 | M35: =NETWORKDAYS(DATE(2020,(LEFT(M$36,2)+0),1),DATE(2020,(LEFT(M$36,2)+0)+1,0),$A$62:$A$74) -> 21 | N35: =NETWORKDAYS(DATE(2020,(LEFT(N$36,2)+0),1),DATE(2020,(LEFT(N$36,2)+0)+1,0),$A$62:$A$74) -> 21 | ... R35: =NETWORKDAYS(DATE(2020,(LEFT(R$36,2)+0),1),DATE(2020,(LEFT(R$36,2)+0)+1,0),$A$62:$A$74) -> 21 | S35: =sum(S37:S56) -> 312686.56 | T35: =sum(T37:T56) -> 300723.97 | U35: =T35-S35 -> -11962.592
A36: Nome Completo | D36: {=U5:U26} -> Classificação | E36: {=E5:E26} -> Formação | F36: Custo / Hora | G36: 43861 | H36: 43890 | I36: 43921 | J36: 43951 | K36: 43982 | L36: 44012 | M36: 44043 | N36: 44074 | O36: 44104 | P36: 44135 | Q36: 44165 | R36: 44196 | S36: PD&I R$ | T36: Aprovado R$ | U36: Pesquisador
A37: {=unique(A6:A26)} -> Ademir Mararangoni | D37: Parcial | E37: Superior Completo | G37: =vlookup($A37,$A$6:$R$26,month(G$36)+6)*(1+$E$33)/(G$35*8.8) -> 63.065873 | H37: =vlookup($A37,$A$6:$R$26,month(H$36)+6)*(1+$E$33)/(H$35*8.8) -> 60.199242 | I37: =vlookup($A37,$A$6:$R$26,month(I$36)+6)*(1+$E$33)/(I$35*8.8) -> 63.065873 | J37: =vlookup($A37,$A$6:$R$26,month(J$36)+6)*(1+$E$33)/(J$35*8.8) -> 60.199242 | K37: =vlookup($A37,$A$6:$R$26,month(K$36)+6)*(1+$E$33)/(K$35*8.8) -> 63.065873 | L37: =vlookup($A37,$A$6:$R$26,month(L$36)+6)*(1+$E$33)/(L$35*8.8) -> 60.199242 | M37: =vlookup($A37,$A$6:$R$26,month(M$36)+6)*(1+$E$33)/(M$35*8.8) -> 63.065873 | N37: =vlookup($A37,$A$6:$R$26,month(N$36)+6)*(1+$E$33)/(N$35*8.8) -> 63.065873 | ... R37: =vlookup($A37,$A$6:$R$26,month(R$36)+6)*(1+$E$33)/(R$35*8.8) -> 67.305125 | S37: =SUMIF(Timesheet!B:B,A37,Timesheet!J:J) -> 4540.3755 | T37: =SUMIF(U37,TRUE,S37) -> 0 | U37: FALSE
A38: Ana Claudia Zanini | D38: Parcial | E38: Mestrado | G38: =vlookup($A38,$A$6:$R$26,month(G$36)+6)*(1+$E$33)/(G$35*8.8) -> 0 | H38: =vlookup($A38,$A$6:$R$26,month(H$36)+6)*(1+$E$33)/(H$35*8.8) -> 0 | I38: =vlookup($A38,$A$6:$R$26,month(I$36)+6)*(1+$E$33)/(I$35*8.8) -> 29.312396 | J38: =vlookup($A38,$A$6:$R$26,month(J$36)+6)*(1+$E$33)/(J$35*8.8) -> 27.980015 | K38: =vlookup($A38,$A$6:$R$26,month(K$36)+6)*(1+$E$33)/(K$35*8.8) -> 29.312396 | L38: =vlookup($A38,$A$6:$R$26,month(L$36)+6)*(1+$E$33)/(L$35*8.8) -> 27.980015 | M38: =vlookup($A38,$A$6:$R$26,month(M$36)+6)*(1+$E$33)/(M$35*8.8) -> 29.312396 | N38: =vlookup($A38,$A$6:$R$26,month(N$36)+6)*(1+$E$33)/(N$35*8.8) -> 29.312396 | ... R38: =vlookup($A38,$A$6:$R$26,month(R$36)+6)*(1+$E$33)/(R$35*8.8) -> 31.282781 | S38: =SUMIF(Timesheet!B:B,A38,Timesheet!J:J) -> 26660.389 | T38: =SUMIF(U38,TRUE,S38) -> 26660.389 | U38: TRUE
A39: Ana Paula Celes | D39: Parcial | E39: Pós graduado | G39: =G8*(((1/3)*1/12)+1)/(G35*(44/5)) -> 169.03747 | H39: =H8*(((1/3)*1/12)+1)/(H35*(44/5)) -> 161.35394 | I39: =I8*(((1/3)*1/12)+1)/(I35*(44/5)) -> 169.03747 | J39: =J8*(((1/3)*1/12)+1)/(J35*(44/5)) -> 161.35394 | K39: =K8*(((1/3)*1/12)+1)/(K35*(44/5)) -> 169.03747 | L39: =L8*(((1/3)*1/12)+1)/(L35*(44/5)) -> 161.35394 | M39: =M8*(((1/3)*1/12)+1)/(M35*(44/5)) -> 169.03747 | N39: =N8*(((1/3)*1/12)+1)/(N35*(44/5)) -> 169.03747 | ... R39: =R8*(((1/3)*1/12)+1)/(R35*(44/5)) -> 169.03747 | S39: =SUMIF(Timesheet!B:B,A39,Timesheet!J:J) -> 21958.223 | T39: =SUMIF(U39,TRUE,S39) -> 21958.223 | U39: TRUE
A40: Arianna Schreiber | D40: Parcial | E40: Pós graduado | G40: =vlookup($A40,$A$6:$R$26,month(G$36)+6)*(1+$E$33)/(G$35*8.8) -> 68.401879 | H40: =vlookup($A40,$A$6:$R$26,month(H$36)+6)*(1+$E$33)/(H$35*8.8) -> 65.292703 | I40: =vlookup($A40,$A$6:$R$26,month(I$36)+6)*(1+$E$33)/(I$35*8.8) -> 68.401879 | J40: =vlookup($A40,$A$6:$R$26,month(J$36)+6)*(1+$E$33)/(J$35*8.8) -> 65.292703 | K40: =vlookup($A40,$A$6:$R$26,month(K$36)+6)*(1+$E$33)/(K$35*8.8) -> 68.401879 | L40: =vlookup($A40,$A$6:$R$26,month(L$36)+6)*(1+$E$33)/(L$35*8.8) -> 65.292703 | M40: =vlookup($A40,$A$6:$R$26,month(M$36)+6)*(1+$E$33)/(M$35*8.8) -> 68.401879 | N40: =vlookup($A40,$A$6:$R$26,month(N$36)+6)*(1+$E$33)/(N$35*8.8) -> 68.401879 | ... R40: =vlookup($A40,$A$6:$R$26,month(R$36)+6)*(1+$E$33)/(R$35*8.8) -> 77.171304 | S40: =SUMIF(Timesheet!B:B,A40,Timesheet!J:J) -> 2106.8997 | T40: =SUMIF(U40,TRUE,S40) -> 2106.8997 | U40: TRUE
A41: Camila Mendes Pereira | D41: Parcial | E41: Superior Completo | G41: =vlookup($A41,$A$6:$R$26,month(G$36)+6)*(1+$E$33)/(G$35*8.8) -> 21.669365 | H41: =vlookup($A41,$A$6:$R$26,month(H$36)+6)*(1+$E$33)/(H$35*8.8) -> 20.684394 | I41: =vlookup($A41,$A$6:$R$26,month(I$36)+6)*(1+$E$33)/(I$35*8.8) -> 21.669365 | J41: =vlookup($A41,$A$6:$R$26,month(J$36)+6)*(1+$E$33)/(J$35*8.8) -> 20.684394 | K41: =vlookup($A41,$A$6:$R$26,month(K$36)+6)*(1+$E$33)/(K$35*8.8) -> 21.669365 | L41: =vlookup($A41,$A$6:$R$26,month(L$36)+6)*(1+$E$33)/(L$35*8.8) -> 20.684394 | M41: =vlookup($A41,$A$6:$R$26,month(M$36)+6)*(1+$E$33)/(M$35*8.8) -> 21.669365 | N41: =vlookup($A41,$A$6:$R$26,month(N$36)+6)*(1+$E$33)/(N$35*8.8) -> 21.669365 | ... R41: =vlookup($A41,$A$6:$R$26,month(R$36)+6)*(1+$E$33)/(R$35*8.8) -> 24.482611 | S41: =SUMIF(Timesheet!B:B,A41,Timesheet!J:J) -> 16066.77 | T41: =SUMIF(U41,TRUE,S41) -> 16066.77 | U41: TRUE
A42: Denise Barros Ferreira | D42: Parcial | E42: Superior Completo | G42: =vlookup($A42,$A$6:$R$26,month(G$36)+6)*(1+$E$33)/(G$35*8.8) -> 43.554987 | H42: =vlookup($A42,$A$6:$R$26,month(H$36)+6)*(1+$E$33)/(H$35*8.8) -> 41.575215 | I42: =vlookup($A42,$A$6:$R$26,month(I$36)+6)*(1+$E$33)/(I$35*8.8) -> 43.554987 | J42: =vlookup($A42,$A$6:$R$26,month(J$36)+6)*(1+$E$33)/(J$35*8.8) -> 41.575215 | K42: =vlookup($A42,$A$6:$R$26,month(K$36)+6)*(1+$E$33)/(K$35*8.8) -> 43.554987 | L42: =vlookup($A42,$A$6:$R$26,month(L$36)+6)*(1+$E$33)/(L$35*8.8) -> 41.575215 | M42: =vlookup($A42,$A$6:$R$26,month(M$36)+6)*(1+$E$33)/(M$35*8.8) -> 43.554987 | N42: =vlookup($A42,$A$6:$R$26,month(N$36)+6)*(1+$E$33)/(N$35*8.8) -> 43.554987 | ... R42: =vlookup($A42,$A$6:$R$26,month(R$36)+6)*(1+$E$33)/(R$35*8.8) -> 44.269294 | S42: =SUMIF(Timesheet!B:B,A42,Timesheet!J:J) -> 1032.825 | T42: =SUMIF(U42,TRUE,S42) -> 0 | U42: FALSE
A43: Emanuela Adam Bechlin Picheki | D43: Parcial | E43: Pós graduado | G43: =vlookup($A43,$A$6:$R$26,month(G$36)+6)*(1+$E$33)/(G$35*8.8) -> 54.026997 | H43: =vlookup($A43,$A$6:$R$26,month(H$36)+6)*(1+$E$33)/(H$35*8.8) -> 51.571224 | I43: =vlookup($A43,$A$6:$R$26,month(I$36)+6)*(1+$E$33)/(I$35*8.8) -> 54.026997 | J43: =vlookup($A43,$A$6:$R$26,month(J$36)+6)*(1+$E$33)/(J$35*8.8) -> 51.571224 | K43: =vlookup($A43,$A$6:$R$26,month(K$36)+6)*(1+$E$33)/(K$35*8.8) -> 54.026997 | L43: =vlookup($A43,$A$6:$R$26,month(L$36)+6)*(1+$E$33)/(L$35*8.8) -> 51.571224 | M43: =vlookup($A43,$A$6:$R$26,month(M$36)+6)*(1+$E$33)/(M$35*8.8) -> 54.026997 | N43: =vlookup($A43,$A$6:$R$26,month(N$36)+6)*(1+$E$33)/(N$35*8.8) -> 54.026997 | ... R43: =vlookup($A43,$A$6:$R$26,month(R$36)+6)*(1+$E$33)/(R$35*8.8) -> 60.404302 | S43: =SUMIF(Timesheet!B:B,A43,Timesheet!J:J) -> 4335.8203 | T43: =SUMIF(U43,TRUE,S43) -> 4335.8203 | U43: TRUE
A44: Fabiano Ribeiro da Silva | D44: Parcial | E44: Pós graduado | G44: =vlookup($A44,$A$6:$R$26,month(G$36)+6)*(1+$E$33)/(G$35*8.8) -> 48.387119 | H44: =vlookup($A44,$A$6:$R$26,month(H$36)+6)*(1+$E$33)/(H$35*8.8) -> 46.187704 | I44: =vlookup($A44,$A$6:$R$26,month(I$36)+6)*(1+$E$33)/(I$35*8.8) -> 48.387119 | J44: =vlookup($A44,$A$6:$R$26,month(J$36)+6)*(1+$E$33)/(J$35*8.8) -> 46.187704 | K44: =vlookup($A44,$A$6:$R$26,month(K$36)+6)*(1+$E$33)/(K$35*8.8) -> 48.387119 | L44: =vlookup($A44,$A$6:$R$26,month(L$36)+6)*(1+$E$33)/(L$35*8.8) -> 46.187704 | M44: =vlookup($A44,$A$6:$R$26,month(M$36)+6)*(1+$E$33)/(M$35*8.8) -> 48.387119 | N44: =vlookup($A44,$A$6:$R$26,month(N$36)+6)*(1+$E$33)/(N$35*8.8) -> 48.387119 | ... R44: =vlookup($A44,$A$6:$R$26,month(R$36)+6)*(1+$E$33)/(R$35*8.8) -> 53.115121 | S44: =SUMIF(Timesheet!B:B,A44,Timesheet!J:J) -> 2223.1351 | T44: =SUMIF(U44,TRUE,S44) -> 0 | U44: FALSE
A45: Flavia Firmano Coelho | D45: Parcial | E45: Pós graduado | G45: =vlookup($A45,$A$6:$R$26,month(G$36)+6)*(1+$E$33)/(G$35*8.8) -> 40.424397 | H45: =vlookup($A45,$A$6:$R$26,month(H$36)+6)*(1+$E$33)/(H$35*8.8) -> 39.538162 | I45: =vlookup($A45,$A$6:$R$26,month(I$36)+6)*(1+$E$33)/(I$35*8.8) -> 41.420932 | J45: =vlookup($A45,$A$6:$R$26,month(J$36)+6)*(1+$E$33)/(J$35*8.8) -> 39.538162 | K45: =vlookup($A45,$A$6:$R$26,month(K$36)+6)*(1+$E$33)/(K$35*8.8) -> 41.420932 | L45: =vlookup($A45,$A$6:$R$26,month(L$36)+6)*(1+$E$33)/(L$35*8.8) -> 39.538162 | M45: =vlookup($A45,$A$6:$R$26,month(M$36)+6)*(1+$E$33)/(M$35*8.8) -> 41.420932 | N45: =vlookup($A45,$A$6:$R$26,month(N$36)+6)*(1+$E$33)/(N$35*8.8) -> 41.420932 | ... R45: =vlookup($A45,$A$6:$R$26,month(R$36)+6)*(1+$E$33)/(R$35*8.8) -> 0 | S45: =SUMIF(Timesheet!B:B,A45,Timesheet!J:J) -> 0 | T45: =SUMIF(U45,TRUE,S45) -> 0 | U45: FALSE
A46: Gabriela Faria de Oliveira | D46: Parcial | E46: Superior Completo | G46: =vlookup($A46,$A$6:$R$26,month(G$36)+6)*(1+$E$33)/(G$35*8.8) -> 29.312396 | H46: =vlookup($A46,$A$6:$R$26,month(H$36)+6)*(1+$E$33)/(H$35*8.8) -> 27.980015 | I46: =vlookup($A46,$A$6:$R$26,month(I$36)+6)*(1+$E$33)/(I$35*8.8) -> 29.312396 | J46: =vlookup($A46,$A$6:$R$26,month(J$36)+6)*(1+$E$33)/(J$35*8.8) -> 27.980015 | K46: =vlookup($A46,$A$6:$R$26,month(K$36)+6)*(1+$E$33)/(K$35*8.8) -> 29.312396 | L46: =vlookup($A46,$A$6:$R$26,month(L$36)+6)*(1+$E$33)/(L$35*8.8) -> 27.980015 | M46: =vlookup($A46,$A$6:$R$26,month(M$36)+6)*(1+$E$33)/(M$35*8.8) -> 29.312396 | N46: =vlookup($A46,$A$6:$R$26,month(N$36)+6)*(1+$E$33)/(N$35*8.8) -> 29.312396 | ... R46: =vlookup($A46,$A$6:$R$26,month(R$36)+6)*(1+$E$33)/(R$35*8.8) -> 32.802574 | S46: =SUMIF(Timesheet!B:B,A46,Timesheet!J:J) -> 13911.697 | T46: =SUMIF(U46,TRUE,S46) -> 13911.697 | U46: TRUE
A47: Hellin dos Santos | D47: Parcial | E47: Mestrado | G47: =vlookup($A47,$A$6:$R$26,month(G$36)+6)*(1+$E$33)/(G$35*8.8) -> 87.890166 | H47: =vlookup($A47,$A$6:$R$26,month(H$36)+6)*(1+$E$33)/(H$35*8.8) -> 83.895158 | I47: =vlookup($A47,$A$6:$R$26,month(I$36)+6)*(1+$E$33)/(I$35*8.8) -> 87.890166 | J47: =vlookup($A47,$A$6:$R$26,month(J$36)+6)*(1+$E$33)/(J$35*8.8) -> 83.895158 | K47: =vlookup($A47,$A$6:$R$26,month(K$36)+6)*(1+$E$33)/(K$35*8.8) -> 87.890166 | L47: =vlookup($A47,$A$6:$R$26,month(L$36)+6)*(1+$E$33)/(L$35*8.8) -> 83.895158 | M47: =vlookup($A47,$A$6:$R$26,month(M$36)+6)*(1+$E$33)/(M$35*8.8) -> 87.890166 | N47: =vlookup($A47,$A$6:$R$26,month(N$36)+6)*(1+$E$33)/(N$35*8.8) -> 87.890166 | ... R47: =vlookup($A47,$A$6:$R$26,month(R$36)+6)*(1+$E$33)/(R$35*8.8) -> 108.543 | S47: =SUMIF(Timesheet!B:B,A47,Timesheet!J:J) -> 125391.23 | T47: =SUMIF(U47,TRUE,S47) -> 125391.23 | U47: TRUE
A48: Kézia Rithássia Piccoli | D48: Parcial | E48: Pós graduado | G48: =vlookup($A48,$A$6:$R$26,month(G$36)+6)*(1+$E$33)/(G$35*8.8) -> 32.236204 | H48: =vlookup($A48,$A$6:$R$26,month(H$36)+6)*(1+$E$33)/(H$35*8.8) -> 30.770922 | I48: =vlookup($A48,$A$6:$R$26,month(I$36)+6)*(1+$E$33)/(I$35*8.8) -> 32.236204 | J48: =vlookup($A48,$A$6:$R$26,month(J$36)+6)*(1+$E$33)/(J$35*8.8) -> 30.770922 | K48: =vlookup($A48,$A$6:$R$26,month(K$36)+6)*(1+$E$33)/(K$35*8.8) -> 32.236204 | L48: =vlookup($A48,$A$6:$R$26,month(L$36)+6)*(1+$E$33)/(L$35*8.8) -> 30.770922 | M48: =vlookup($A48,$A$6:$R$26,month(M$36)+6)*(1+$E$33)/(M$35*8.8) -> 32.236204 | N48: =vlookup($A48,$A$6:$R$26,month(N$36)+6)*(1+$E$33)/(N$35*8.8) -> 32.236204 | ... R48: =vlookup($A48,$A$6:$R$26,month(R$36)+6)*(1+$E$33)/(R$35*8.8) -> 35.386091 | S48: =SUMIF(Timesheet!B:B,A48,Timesheet!J:J) -> 2075.4498 | T48: =SUMIF(U48,TRUE,S48) -> 0 | U48: FALSE
A49: Lizianne Shmeil | D49: Parcial | E49: Superior Completo | G49: =vlookup($A49,$A$6:$R$26,month(G$36)+6)*(1+$E$33)/(G$35*8.8) -> 37.660521 | H49: =vlookup($A49,$A$6:$R$26,month(H$36)+6)*(1+$E$33)/(H$35*8.8) -> 35.948679 | I49: =vlookup($A49,$A$6:$R$26,month(I$36)+6)*(1+$E$33)/(I$35*8.8) -> 37.660521 | J49: =vlookup($A49,$A$6:$R$26,month(J$36)+6)*(1+$E$33)/(J$35*8.8) -> 35.948679 | K49: =vlookup($A49,$A$6:$R$26,month(K$36)+6)*(1+$E$33)/(K$35*8.8) -> 37.660521 | L49: =vlookup($A49,$A$6:$R$26,month(L$36)+6)*(1+$E$33)/(L$35*8.8) -> 35.948679 | M49: =vlookup($A49,$A$6:$R$26,month(M$36)+6)*(1+$E$33)/(M$35*8.8) -> 37.660521 | N49: =vlookup($A49,$A$6:$R$26,month(N$36)+6)*(1+$E$33)/(N$35*8.8) -> 37.660521 | ... R49: =vlookup($A49,$A$6:$R$26,month(R$36)+6)*(1+$E$33)/(R$35*8.8) -> 43.421217 | S49: =SUMIF(Timesheet!B:B,A49,Timesheet!J:J) -> 52207.711 | T49: =SUMIF(U49,TRUE,S49) -> 52207.711 | U49: TRUE
A50: Luciana Dutra | D50: Parcial | E50: Pós graduado | G50: =vlookup($A50,$A$6:$R$26,month(G$36)+6)*(1+$E$33)/(G$35*8.8) -> 150.60488 | H50: =vlookup($A50,$A$6:$R$26,month(H$36)+6)*(1+$E$33)/(H$35*8.8) -> 143.75921 | I50: =vlookup($A50,$A$6:$R$26,month(I$36)+6)*(1+$E$33)/(I$35*8.8) -> 150.60488 | J50: =vlookup($A50,$A$6:$R$26,month(J$36)+6)*(1+$E$33)/(J$35*8.8) -> 143.75921 | K50: =vlookup($A50,$A$6:$R$26,month(K$36)+6)*(1+$E$33)/(K$35*8.8) -> 150.60488 | L50: =vlookup($A50,$A$6:$R$26,month(L$36)+6)*(1+$E$33)/(L$35*8.8) -> 143.75921 | M50: =vlookup($A50,$A$6:$R$26,month(M$36)+6)*(1+$E$33)/(M$35*8.8) -> 150.60488 | N50: =vlookup($A50,$A$6:$R$26,month(N$36)+6)*(1+$E$33)/(N$35*8.8) -> 150.60488 | ... R50: =vlookup($A50,$A$6:$R$26,month(R$36)+6)*(1+$E$33)/(R$35*8.8) -> 153.0748 | S50: =SUMIF(Timesheet!B:B,A50,Timesheet!J:J) -> 36776.014 | T50: =SUMIF(U50,TRUE,S50) -> 36776.014 | U50: TRUE
A51: Lucimari Reway dos Santos | D51: Parcial | E51: Técnico | G51: =vlookup($A51,$A$6:$R$26,month(G$36)+6)*(1+$E$33)/(G$35*8.8) -> 21.669452 | H51: =vlookup($A51,$A$6:$R$26,month(H$36)+6)*(1+$E$33)/(H$35*8.8) -> 20.684477 | I51: =vlookup($A51,$A$6:$R$26,month(I$36)+6)*(1+$E$33)/(I$35*8.8) -> 21.669452 | J51: =vlookup($A51,$A$6:$R$26,month(J$36)+6)*(1+$E$33)/(J$35*8.8) -> 20.684477 | K51: =vlookup($A51,$A$6:$R$26,month(K$36)+6)*(1+$E$33)/(K$35*8.8) -> 21.669452 | L51: =vlookup($A51,$A$6:$R$26,month(L$36)+6)*(1+$E$33)/(L$35*8.8) -> 20.684477 | M51: =vlookup($A51,$A$6:$R$26,month(M$36)+6)*(1+$E$33)/(M$35*8.8) -> 21.669452 | N51: =vlookup($A51,$A$6:$R$26,month(N$36)+6)*(1+$E$33)/(N$35*8.8) -> 21.669452 | ... R51: =vlookup($A51,$A$6:$R$26,month(R$36)+6)*(1+$E$33)/(R$35*8.8) -> 26.811888 | S51: =SUMIF(Timesheet!B:B,A51,Timesheet!J:J) -> 0 | T51: =SUMIF(U51,TRUE,S51) -> 0 | U51: FALSE
... A56: Tais Carlotto | D56: Parcial | E56: Superior Completo | G56: =vlookup($A56,$A$6:$R$26,month(G$36)+6)*(1+$E$33)/(G$35*8.8) -> 48.387119 | H56: =vlookup($A56,$A$6:$R$26,month(H$36)+6)*(1+$E$33)/(H$35*8.8) -> 50.809155 | I56: =vlookup($A56,$A$6:$R$26,month(I$36)+6)*(1+$E$33)/(I$35*8.8) -> 53.228638 | J56: =vlookup($A56,$A$6:$R$26,month(J$36)+6)*(1+$E$33)/(J$35*8.8) -> 50.809155 | K56: =vlookup($A56,$A$6:$R$26,month(K$36)+6)*(1+$E$33)/(K$35*8.8) -> 53.228638 | L56: =vlookup($A56,$A$6:$R$26,month(L$36)+6)*(1+$E$33)/(L$35*8.8) -> 50.809155 | M56: =vlookup($A56,$A$6:$R$26,month(M$36)+6)*(1+$E$33)/(M$35*8.8) -> 53.228638 | N56: =vlookup($A56,$A$6:$R$26,month(N$36)+6)*(1+$E$33)/(N$35*8.8) -> 53.228638 | ... R56: =vlookup($A56,$A$6:$R$26,month(R$36)+6)*(1+$E$33)/(R$35*8.8) -> 54.101574 | S56: =SUMIF(Timesheet!B:B,A56,Timesheet!J:J) -> 0 | T56: =SUMIF(U56,TRUE,S56) -> 0 | U56: FALSE
D57: Parcial | S57: =SUMIF(Timesheet!B:B,A57,Timesheet!J:J) -> 0 | T57: =SUMIF(U57,TRUE,S57) -> 0 | U57: FALSE
A60: Feriados
A62: 43831 | B62: quarta-feira | C62: Confraternização Universal
A63: 43885 | B63: segunda-feira | C63: Carnaval
A64: 43886 | B64: terça-feira | C64: Carnaval
A65: 43931 | B65: sexta-feira | C65: Paixão de Cristo
A66: 43942 | B66: terça-feira | C66: Tiradentes
A67: 43952 | B67: sexta-feira | C67: Dia do Trabalho
A68: 43993 | B68: quinta-feira | C68: Corpus Christi
A69: 44081 | B69: segunda-feira | C69: Independência do Brasil
A70: 44116 | B70: segunda-feira | C70: Nossa Sr.a Aparecida - Padroeira do Brasil
A71: 44137 | B71: segunda-feira | C71: Finados
A72: 44189 | B72: quinta-feira | C72: Vespera de natal
A73: 44190 | B73: sexta-feira | C73: Natal
A74: 44196 | B74: quinta-feira | C74: Véspera de ano novo

Sheet #Form
B1: MATERIAIS | C1: =IFERROR(__xludf.DUMMYFUNCTION("SUM(FILTER(Investimentos!J:J,Investimentos!L:L = TRUE,Investimentos!N:N = ""Material""))"),5084.709999999999) -> 5084.71 | D1: =C1+C2 -> 377821.66
B2: SERVIÇOS | C2: =SUM(C4:C32) -> 372736.95
B4: =IFERROR(__xludf.DUMMYFUNCTION("UNIQUE(FILTER(Investimentos!C:C,Investimentos!L:L = TRUE,Investimentos!N:N = ""Serviço""))"),"ALLPARK EMPREENDIMENTOS PARTICIPACOES SERVICOS S.A") -> ALLPARK EMPREENDIMENTOS PARTICIPACOES SERVICOS S.A | C4: =SUMIF(Investimentos!C:C,B4,Investimentos!J:J) -> 19
B5: =IFERROR(__xludf.DUMMYFUNCTION("""COMPUTED_VALUE"""),"Anderson Mendonça Lima") -> Anderson Mendonça Lima | C5: =SUMIF(Investimentos!C:C,B5,Investimentos!J:J) -> 6000
B6: =IFERROR(__xludf.DUMMYFUNCTION("""COMPUTED_VALUE"""),"B2W VIAGENS E TURISMO LTDA - Submarino viagens") -> B2W VIAGENS E TURISMO LTDA - Submarino viagens | C6: =SUMIF(Investimentos!C:C,B6,Investimentos!J:J) -> 610.74
B7: =IFERROR(__xludf.DUMMYFUNCTION("""COMPUTED_VALUE"""),"Bendito Gosto Eventos Ltda") -> Bendito Gosto Eventos Ltda | C7: =SUMIF(Investimentos!C:C,B7,Investimentos!J:J) -> 560
B8: =IFERROR(__xludf.DUMMYFUNCTION("""COMPUTED_VALUE"""),"Braseq Brasileira de Equipamentos Ltda") -> Braseq Brasileira de Equipamentos Ltda | C8: =SUMIF(Investimentos!C:C,B8,Investimentos!J:J) -> 3600
B9: =IFERROR(__xludf.DUMMYFUNCTION("""COMPUTED_VALUE"""),"BRAZILSUL Serviços Administrativos Ltda") -> BRAZILSUL Serviços Administrativos Ltda | C9: =SUMIF(Investimentos!C:C,B9,Investimentos!J:J) -> 16970
B10: =IFERROR(__xludf.DUMMYFUNCTION("""COMPUTED_VALUE"""),"DECOLAR. COM LTDA - Decolar.com") -> DECOLAR. COM LTDA - Decolar.com | C10: =SUMIF(Investimentos!C:C,B10,Investimentos!J:J) -> 742.13 | F10: 3.1 | G10: RECEITAS | H10: 1.0745953e+08
B11: =IFERROR(__xludf.DUMMYFUNCTION("""COMPUTED_VALUE"""),"DHL") -> DHL | C11: =SUMIF(Investimentos!C:C,B11,Investimentos!J:J) -> 1522.08 | F11: 3.2 | G11: DEDUCOES DA RECEITA | H11: -16941528
B12: =IFERROR(__xludf.DUMMYFUNCTION("""COMPUTED_VALUE"""),"DPR Turismo Ltda.") -> DPR Turismo Ltda. | C12: =SUMIF(Investimentos!C:C,B12,Investimentos!J:J) -> 22.9
B13: =IFERROR(__xludf.DUMMYFUNCTION("""COMPUTED_VALUE"""),"Elsevier Editora Ltda") -> Elsevier Editora Ltda | C13: =SUMIF(Investimentos!C:C,B13,Investimentos!J:J) -> 25200 | F13: RECEITA LIQUIDA | H13: =H10+H11 -> 90518001
B14: =IFERROR(__xludf.DUMMYFUNCTION("""COMPUTED_VALUE"""),"FUNDAÇÃO ARTHUR BERNARDES") -> FUNDAÇÃO ARTHUR BERNARDES | C14: =SUMIF(Investimentos!C:C,B14,Investimentos!J:J) -> 20576
B15: =IFERROR(__xludf.DUMMYFUNCTION("""COMPUTED_VALUE"""),"Fundação de Apoio à Pesquisa e ao Desenvolvimento - FAPED") -> Fundação de Apoio à Pesquisa e ao Desenvolvimento - FAPED | C15: =SUMIF(Investimentos!C:C,B15,Investimentos!J:J) -> 4000
B16: =IFERROR(__xludf.DUMMYFUNCTION("""COMPUTED_VALUE"""),"Fundação de Apoio à Universidade de São Paulo") -> Fundação de Apoio à Universidade de São Paulo | C16: =SUMIF(Investimentos!C:C,B16,Investimentos!J:J) -> 678
B17: =IFERROR(__xludf.DUMMYFUNCTION("""COMPUTED_VALUE"""),"Fundação de desenv. da pesquisa do agronegócio - FUNDEPAG") -> Fundação de desenv. da pesquisa do agronegócio - FUNDEPAG | C17: =SUMIF(Investimentos!C:C,B17,Investimentos!J:J) -> 23903
B18: =IFERROR(__xludf.DUMMYFUNCTION("""COMPUTED_VALUE"""),"FUNDAÇÃO EDUCACIONAL CIÊNCIA E DESENVOLVIMENTO FECD") -> FUNDAÇÃO EDUCACIONAL CIÊNCIA E DESENVOLVIMENTO FECD | C18: =SUMIF(Investimentos!C:C,B18,Investimentos!J:J) -> 66285.43
B19: =IFERROR(__xludf.DUMMYFUNCTION("""COMPUTED_VALUE"""),"Grupo HU Viagens e Turismo S.A. - Hurb") -> Grupo HU Viagens e Turismo S.A. - Hurb | C19: =SUMIF(Investimentos!C:C,B19,Investimentos!J:J) -> 630.81
B20: =IFERROR(__xludf.DUMMYFUNCTION("""COMPUTED_VALUE"""),"Instituto Cristina Martins Educação e Pesquisa em Nutrição Ltda") -> Instituto Cristina Martins Educação e Pesquisa em Nutrição Ltda | C20: =SUMIF(Investimentos!C:C,B20,Investimentos!J:J) -> 3000
B21: =IFERROR(__xludf.DUMMYFUNCTION("""COMPUTED_VALUE"""),"J&J Serviços de Entregas Ltda - ME") -> J&J Serviços de Entregas Ltda - ME | C21: =SUMIF(Investimentos!C:C,B21,Investimentos!J:J) -> 3027.57
B22: =IFERROR(__xludf.DUMMYFUNCTION("""COMPUTED_VALUE"""),"KONTIK FRANSTUR VIAGENS E TURISMO LTDA") -> KONTIK FRANSTUR VIAGENS E TURISMO LTDA | C22: =SUMIF(Investimentos!C:C,B22,Investimentos!J:J) -> 551.26
B23: =IFERROR(__xludf.DUMMYFUNCTION("""COMPUTED_VALUE"""),"Labor Três Laboratórios e Consultoria Técnica Ltda") -> Labor Três Laboratórios e Consultoria Técnica Ltda | C23: =SUMIF(Investimentos!C:C,B23,Investimentos!J:J) -> 914
B24: =IFERROR(__xludf.DUMMYFUNCTION("""COMPUTED_VALUE"""),"Laboratório ALAC Ltda") -> Laboratório ALAC Ltda | C24: =SUMIF(Investimentos!C:C,B24,Investimentos!J:J) -> 159391.43
B25: =IFERROR(__xludf.DUMMYFUNCTION("""COMPUTED_VALUE"""),"LOCALIZA RENT A CAR S/A") -> LOCALIZA RENT A CAR S/A | C25: =SUMIF(Investimentos!C:C,B25,Investimentos!J:J) -> 315.84
B26: =IFERROR(__xludf.DUMMYFUNCTION("""COMPUTED_VALUE"""),"MM Turismo & Viagens Ltda - Max Milhas") -> MM Turismo & Viagens Ltda - Max Milhas | C26: =SUMIF(Investimentos!C:C,B26,Investimentos!J:J) -> 427.15
B27: =IFERROR(__xludf.DUMMYFUNCTION("""COMPUTED_VALUE"""),"Tetra Pak Ltda") -> Tetra Pak Ltda | C27: =SUMIF(Investimentos!C:C,B27,Investimentos!J:J) -> 27988.34
B28: =IFERROR(__xludf.DUMMYFUNCTION("""COMPUTED_VALUE"""),"Transmazili Transporte de Cargas e Logística Ltda") -> Transmazili Transporte de Cargas e Logística Ltda | C28: =SUMIF(Investimentos!C:C,B28,Investimentos!J:J) -> 5450
B29: =IFERROR(__xludf.DUMMYFUNCTION("""COMPUTED_VALUE"""),"TUV SUD SFDK Laboratório de Análise de Produtos Eireli") -> TUV SUD SFDK Laboratório de Análise de Produtos Eireli | C29: =SUMIF(Investimentos!C:C,B29,Investimentos!J:J) -> 330.16
B30: =IFERROR(__xludf.DUMMYFUNCTION("""COMPUTED_VALUE"""),"VIP CAR VEICULOS LTDA - VIPCars.com") -> VIP CAR VEICULOS LTDA - VIPCars.com | C30: =SUMIF(Investimentos!C:C,B30,Investimentos!J:J) -> 21.11

Sheet Investimentos
A2: Investimentos
O3: =SUMIF($L$6:$L200,TRUE,O6:O200) -> 275975.74 | P3: =SUMIF($L$6:$L200,TRUE,P6:P200) -> 0 | Q3: =SUMIF($L$6:$L200,TRUE,Q6:Q200) -> 85104.72 | R3: =SUMIF($L$6:$L200,TRUE,R6:R200) -> 16741.2 | S3: =SUMIF($L$6:$L200,TRUE,S6:S200) -> 0
J4: =SUM(J8:J200) -> 377821.66 | O4: =SUM(O6:O200) -> 379871.33 | P4: =SUM(P6:P200) -> 0 | Q4: =SUM(Q6:Q200) -> 93654.53 | R4: =SUM(R6:R200) -> 26064.44 | S4: =SUM(S6:S200) -> 0
A5: Cod | C5: Fornecedor | D5: CNPJ | E5: Descrição | F5: NF/ND | G5: Centro de custo | H5: Conta contábil | I5: Valor original | J5: R$ Incentivavel | K5: Data | L5: Inovação? | M5: Attachments | N5: Tipo | O5: Novos Produtos | P5: Novas matérias-primas | Q5: Melhoria de Produto | R5: Melhoria de Processo | S5: Segurança Alimentar | T5: Tipo2 | U5: Projeto | V5: Projeto | W5: Proj incentivado?
A6: 21 | C6: Aéreo congresso ASPEN | D6: NA | E6: Aéreo para o congresso da ASPEN | F6: Recibo - NA | I6: 2677.62 | J6: =IF(L6=TRUE,I6,"") | K6: 43874 | L6: FALSE | N6: Serviço | O6: 2677.62 | P6: - | Q6: - | R6: - | S6: - | T6: Serviço de terceiros | U6: InstanTH NEO/ Novos produtos | V6: InstanTH NEO/ Novos produtos | W6: {=VLOOKUP(U6:U200,Projetos!A:L,12,false)} -> #N/A
A7: 2 | C7: Fundação de Apoio à Pesquisa a ao Desenvolvimento - FAPED | D7: 00.849.774/0001-91 | E7: Parcela de aluguel de planta Embrapa/RJ | F7: NF - 23642 | I7: 4000 | J7: =IF(L7=TRUE,I7,"") | K7: 43808 | L7: FALSE | N7: Serviço | O7: 4000 | P7: - | Q7: - | R7: - | S7: - | T7: Serviço de terceiros | U7: Retort (Sistema Fechado) | W7: TRUE
A8: 50 | C8: ALLPARK EMPREENDIMENTOS PARTICIPACOES SERVICOS S.A | D8: 60.537.263/0001-66 | E8: Estacionamento - trabalho externo junto a fornecedor | F8: Recibo - NA | I8: 19 | J8: =IF(L8=TRUE,SUM(O8:S8),"") -> 19 | K8: 43881 | L8: TRUE | N8: Serviço | O8: 19 | P8: - | Q8: - | R8: - | S8: - | T8: Serviço próprios | U8: Diamax IG | W8: TRUE
A9: 140 | C9: Anderson Mendonça Lima | D9: 35.964.728/0001-18 | E9: Consultoria EE | F9: NF - 4 | I9: 3000 | J9: =IF(L9=TRUE,SUM(O9:S9),"") -> 3000 | K9: 44070 | L9: TRUE | N9: Serviço | O9: - | P9: - | Q9: 3000 | R9: - | S9: - | T9: Serviço de terceiros | U9: Energyzip morango | W9: TRUE
A10: 180 | C10: Anderson Mendonça Lima | D10: 35.964.728/0001-18 | E10: Consultoria EE | F10: NF - 5 | I10: 3000 | J10: =IF(L10=TRUE,SUM(O10:S10),"") -> 3000 | K10: 44125 | L10: TRUE | N10: Serviço | O10: - | P10: - | Q10: 3000 | R10: - | S10: - | T10: Serviço de terceiros | U10: Produtos em pó e líquidos | V10: Produtos em pó e líquidos | W10: #N/A
A11: 66 | C11: Andrei Publicações Médicas Farmacêuticas Técnicas Ltda | D11: 62.958.491/0001-35 | E11: Publicação de material de comunicação | F11: NF - 61411 | I11: 780 | J11: =IF(L11=TRUE,I11,"") | K11: 43928 | L11: FALSE | N11: Serviço | O11: 97.5 | P11: - | Q11: - | R11: - | S11: - | T11: Serviço de terceiros | U11: Bemmax Sabor Neutro, Instanth NEO, InstanTH CLEAR (espessante) | V11: Bemmax Sabor Neutro, Instant NEO, Instanth Clear | W11: #N/A
A12: 78 | C12: Andrei Publicações Médicas Farmacêuticas Técnicas Ltda | D12: 62.958.491/0001-35 | E12: Publicação de material de comunicação | F12: NF - 61734 | I12: 780 | J12: =IF(L12=TRUE,I12,"") | K12: 43957 | L12: FALSE | N12: Serviço | O12: 97.5 | P12: - | Q12: - | R12: - | S12: - | T12: Serviço de terceiros | U12: Bemmax Sabor Neutro, Instanth NEO, InstanTH CLEAR (espessante) | V12: Bemmax Sabor Neutro, Instant NEO, Instanth Clear | W12: #N/A
A13: 105 | C13: Andrei Publicações Médicas Farmacêuticas Técnicas Ltda | D13: 62.958.491/0001-35 | E13: Publicação de material de comunicação | F13: NF - 062593 | I13: 780 | J13: =IF(L13=TRUE,I13,"") | K13: 44020 | L13: FALSE | N13: Serviço | O13: 97.6 | P13: - | Q13: - | R13: - | S13: - | T13: Serviço de terceiros | U13: Bemmax Sabor Neutro, Instanth NEO, InstanTH CLEAR (espessante) | V13: Bemmax Sabor Neutro, Instant NEO, Instanth Clear | W13: #N/A
A14: 122 | C14: Andrei Publicações Médicas Farmacêuticas Técnicas Ltda | D14: 62.958.491/0001-35 | E14: Publicação de material de comunicação | F14: NF - 063092 | I14: 780 | J14: =IF(L14=TRUE,I14,"") | K14: 44050 | L14: FALSE | N14: Serviço | O14: 97.5 | P14: - | Q14: - | R14: - | S14: - | T14: Serviço de terceiros | U14: Bemmax Sabor Neutro, Instanth NEO, InstanTH CLEAR (espessante) | V14: Bemmax Sabor Neutro, Instant NEO, Instanth Clear | W14: #N/A
A15: 152 | C15: Andrei Publicações Médicas Farmacêuticas Técnicas Ltda | D15: 62.958.491/0001-35 | E15: Publicação de material de comunicação | F15: NF - 063550 | I15: 780 | J15: =IF(L15=TRUE,I15,"") | K15: 44089 | L15: FALSE | N15: Serviço | O15: 97.5 | P15: - | Q15: - | R15: - | S15: - | T15: Serviço de terceiros | U15: Bemmax Sabor Neutro, Instanth NEO, InstanTH CLEAR (espessante) | V15: Bemmax Sabor Neutro, Instant NEO, Instanth Clear | W15: #N/A
A16: 11 | C16: Studio MAD Creative Design Ltda - ME | D16: 11.115.312/0001-67 | E16: Serviços de marketing | F16: NF - 1061 | I16: 7255.16 | J16: =IF(L16=TRUE,I16,"") | K16: 43838 | L16: FALSE | N16: Serviço | O16: 500 | P16: - | Q16: - | R16: - | S16: - | T16: Serviço de terceiros | U16: InstanTH CLEAR (espessante) | V16: Instanth CLEAR | W16: TRUE
A17: 15 | C17: B2W VIAGENS E TURISMO LTDA - Submarino viagens | D17: 06.179.342/0001-05 | E17: Aéreo teste Tetra Pak (Monte Mor/SP) - fev 2020 | F17: Recibos - NA | I17: 610.74 | J17: =IF(L17=TRUE,SUM(O17:S17),"") -> 610.74 | K17: 43864 | L17: TRUE | N17: Serviço | O17: 610.74 | P17: - | Q17: - | R17: - | S17: - | T17: Serviço de terceiros | U17: HDmax 2.0 | W17: TRUE
A18: 43 | C18: Bendito Gosto Eventos Ltda | D18: 17.194.307/0001-73 | E18: Coffee break evento InstanTH NEO | F18: NF - 2062 | I18: 560 | J18: =IF(L18=TRUE,SUM(O18:S18),"") -> 560 | K18: 43895 | L18: TRUE | N18: Serviço | O18: 560 | P18: - | Q18: - | R18: - | S18: - | T18: Serviço de terceiros | U18: InstanTH NEO | W18: TRUE
A19: 3 | C19: Braseq Brasileira de Equipamentos Ltda | D19: 57.017.774/0001-42 | E19: Treinamento viscosímetro | F19: NF - 201900000012738 | I19: 3600 | J19: =IF(L19=TRUE,SUM(O19:S19),"") -> 3600 | K19: 43825 | L19: TRUE | N19: Serviço | O19: 2880 | P19: - | Q19: 720 | R19: - | S19: - | T19: Serviço de terceiros | U19: Produtos líquidos - todos os projetos | V19: Produtos líquidos - todos os projetos | W19: #N/A
A20: 18 | C20: BRAZILSUL Serviços Administrativos Ltda | D20: 11.456.079/0001-86 | E20: Elaboração da minuta para depósito e acompanhamento do pedido de patente | F20: NF - 1892 | I20: 7100 | J20: =IF(L20=TRUE,SUM(O20:S20),"") -> 7100 | K20: 43846 | L20: TRUE | N20: Serviço | O20: 7100 | P20: - | Q20: - | R20: - | S20: - | T20: Serviço de terceiros | U20: InstanTH NEO | W20: TRUE
A21: 118 | C21: BRAZILSUL Serviços Administrativos Ltda | D21: 11.456.079/0001-86 | E21: Prestação de serviço - patente | F21: NF - 2273 | I21: 2770 | J21: =IF(L21=TRUE,SUM(O21:S21),"") -> 2770 | K21: 44046 | L21: TRUE | N21: Serviço | O21: 2770 | P21: - | Q21: - | R21: - | S21: - | T21: Serviço de terceiros | U21: InstanTH NEO | W21: TRUE
A22: 167 | C22: BRAZILSUL Serviços Administrativos Ltda | D22: 11.456.079/0001-86 | E22: Prestação de serviço - patente | F22: NF - 1892 | I22: 7100 | J22: =IF(L22=TRUE,SUM(O22:S22),"") -> 7100 | K22: 43846 | L22: TRUE | N22: Serviço | O22: 7100 | P22: - | Q22: - | R22: - | S22: - | T22: Serviço de terceiros | U22: InstanTH NEO | W22: TRUE
A23: 14 | C23: DECOLAR. COM LTDA - Decolar.com | D23: 03.563.689/0001-50 | E23: Hospedagem - Ana Paula - teste Embrapa/RJ - fev 2020 | F23: Recibos - NA | I23: 297.57 | J23: =IF(L23=TRUE,SUM(O23:S23),"") -> 297.57 | K23: 43866 | L23: TRUE | N23: Serviço | O23: 297.57 | P23: - | Q23: - | R23: - | S23: - | T23: Serviço de terceiros | U23: Retort (Sistema Fechado) | W23: TRUE
A24: 16 | C24: DECOLAR. COM LTDA - Decolar.com | D24: 03.563.689/0001-50 | E24: Hospedagem - teste Tetra Pak (Monte Mor/SP) - fev 2020 | F24: Recibos - NA | I24: 444.56 | J24: =IF(L24=TRUE,SUM(O24:S24),"") -> 444.56 | K24: 43864 | L24: TRUE | N24: Serviço | O24: 444.56 | P24: - | Q24: - | R24: - | S24: - | T24: Serviço de terceiros | U24: HDmax 2.0 | W24: TRUE
A25: 20 | C25: despesas de locomoção (uber) e refeições | D25: NA | E25: despesas de locomoção (uber) e refeições | F25: Recibos - NA | I25: 334.51 | J25: =IF(L25=TRUE,I25,"") | K25: 43859 | L25: FALSE | N25: Serviço | O25: 334.51 | P25: - | Q25: - | R25: - | S25: - | T25: Serviço de terceiros | U25: InstanTH NEO | W25: TRUE
A26: 136 | C26: DHL | D26: 02.836.056/0001-06 | E26: Importação de amostras de embalagens para teste piloto | F26: Invoice - 2940252066 | I26: 1522.08 | J26: =IF(L26=TRUE,SUM(O26:S26),"") -> 1522.08 | K26: 44054 | L26: TRUE | N26: Serviço | O26: 1522.08 | P26: - | Q26: - | R26: - | S26: - | T26: Serviço de terceiros | U26: Retort (Sistema Fechado) | W26: TRUE
A27: 22 | C27: Prodiet Nutrição Clínica Ltda | D27: 08.183.359/0001-53 | E27: MP para TB | F27: NF - 9072 | I27: 102.3 | J27: =IF(L27=TRUE,I27,"") | K27: 43873 | L27: FALSE | M27: Prodiet não lançou em conta contábil específica e nem no centro de custo de inovação. Valor foi contabilizado nos custos e a empresa não irá remover, | N27: Material | O27: 102.3 | P27: - | Q27: - | R27: - | S27: - | T27: Serviço próprios | U27: Bemmax Sabor Neutro | W27: TRUE
A28: 23 | C28: Prodiet Nutrição Clínica Ltda | D28: 08.183.359/0001-53 | E28: MP para TP | F28: NF - 9066 | I28: 269.95 | J28: =IF(L28=TRUE,I28,"") | K28: 43873 | L28: FALSE | M28: Prodiet não lançou em conta contábil específica e nem no centro de custo de inovação. Valor foi contabilizado nos custos e a empresa não irá remover, | N28: Material | O28: 269.95 | P28: - | Q28: - | R28: - | S28: - | T28: Serviço próprios | U28: Retort (Sistema Fechado) | W28: TRUE
A29: 24 | C29: Rafael Silva de Oliveira - Comunicação - EPP | D29: 17.927.780/0001-12 | E29: Publicações mkt | F29: NF - 685 | I29: 6100 | J29: =IF(L29=TRUE,I29,"") | K29: 43872 | L29: FALSE | N29: Serviço | O29: 2500 | P29: - | Q29: - | R29: - | S29: - | T29: Serviço de terceiros | U29: InstanTH NEO | W29: TRUE
A30: 185 | C30: DPR Turismo Ltda. | D30: 73.506.453/0001-68 | E30: Fee da agencia Flytour pela operação de locação de carro - teste Embrapa/RJ | F30: NF - 45652 | I30: 22.9 | J30: =IF(L30=TRUE,SUM(O30:S30),"") -> 22.9 | K30: 44139 | L30: TRUE | N30: Serviço | O30: 22.9 | P30: - | Q30: - | R30: - | S30: - | T30: Serviço de terceiros | U30: Retort (Sistema Fechado) | W30: TRUE
A31: 41 | C31: Elsevier Editora Ltda | D31: 42.546.531/0001-24 | E31: Compra de pacote de 200 artigos científicos | F31: Invoice - NA | I31: 25200 | J31: =IF(L31=TRUE,SUM(O31:S31),"") -> 25200 | K31: 43866 | L31: TRUE | N31: Serviço | O31: 25200 | P31: - | Q31: - | R31: - | S31: - | T31: Serviço de terceiros | U31: Novos produtos | V31: Novos produtos | W31: #N/A
A32: 54 | C32: FUNDAÇÃO ARTHUR BERNARDES | D32: 20.320.503/0001-51 | E32: Aluguel Embrapa/RJ - 1a/4 parcela | F32: NF - 202000000000425 | I32: 5144 | J32: =IF(L32=TRUE,SUM(O32:S32),"") -> 5144 | K32: 43917 | L32: TRUE | N32: Serviço | O32: 5144 | P32: - | Q32: - | R32: - | S32: - | T32: Serviço de terceiros | U32: Retort (Sistema Fechado) | W32: TRUE
A33: 67 | C33: FUNDAÇÃO ARTHUR BERNARDES | D33: 20.320.503/0001-51 | E33: Aluguel Embrapa/RJ - 2a/4 parcela | F33: NF - 202000000000524 | I33: 5144 | J33: =IF(L33=TRUE,SUM(O33:S33),"") -> 5144 | K33: 43948 | L33: TRUE | N33: Serviço | O33: 5144 | P33: - | Q33: - | R33: - | S33: - | T33: Serviço de terceiros | U33: Retort (Sistema Fechado) | W33: TRUE
A34: 86 | C34: FUNDAÇÃO ARTHUR BERNARDES | D34: 20.320.503/0001-51 | E34: Aluguel Embrapa/RJ - 3a/4 parcela | F34: NF - 202000000000660 | I34: 5144 | J34: =IF(L34=TRUE,SUM(O34:S34),"") -> 5144 | K34: 43991 | L34: TRUE | N34: Serviço | O34: 5144 | P34: - | Q34: - | R34: - | S34: - | T34: Serviço de terceiros | U34: Retort (Sistema Fechado) | W34: TRUE
A35: 30 | C35: Nex Coworking | D35: 19.012.195/0001-18 | E35: Locação auditório - 1a parcela | F35: Recibo - NA | I35: 1000 | J35: =IF(L35=TRUE,I35,"") | K35: 43888 | L35: FALSE | N35: Serviço | O35: 500 | P35: - | Q35: - | R35: - | S35: - | T35: Serviço de terceiros | U35: InstanTH NEO | W35: TRUE
A36: 31 | C36: Nex Coworking | D36: 19.012.195/0001-18 | E36: Locação auditório - 2a parcela | F36: Recibo - NA | I36: 1000 | J36: =IF(L36=TRUE,I36,"") | K36: 43888 | L36: FALSE | N36: Serviço | O36: 500 | P36: - | Q36: - | R36: - | S36: - | T36: Serviço de terceiros | U36: InstanTH NEO | W36: TRUE
A37: 32 | C37: Aguzzoli & Aguzzoli Ltda - ME | D37: 17.196.802/0001-11 | E37: Apresentação de palestra - mkt | F37: NF - 2020/3 | I37: 3710 | J37: =IF(L37=TRUE,I37,"") | K37: 43888 | L37: FALSE | N37: Serviço | O37: 3710 | P37: - | Q37: - | R37: - | S37: - | T37: Serviço de terceiros | U37: InstanTH NEO | W37: TRUE
A38: 33 | C38: Área 51 Polo Cultural Ltda | D38: 22.992.736/0001-26 | E38: Locação de sala | F38: Recibo - NA | I38: 450 | J38: =IF(L38=TRUE,I38,"") | K38: 43881 | L38: FALSE | N38: Serviço | O38: 450 | P38: - | Q38: - | R38: - | S38: - | T38: Serviço de terceiros | U38: InstanTH NEO | W38: TRUE
A39: 34 | C39: Zupper | D39: 73.431.686/0010-30 | E39: Aéreo Rio para acompanhar palestra - mkt | F39: Recibo - NA | I39: 291.98 | J39: =IF(L39=TRUE,I39,"") | K39: 43882 | L39: FALSE | N39: Serviço | O39: 291.98 | P39: - | Q39: - | R39: - | S39: - | T39: Serviço de terceiros | U39: InstanTH NEO | W39: TRUE
A40: 106 | C40: FUNDAÇÃO ARTHUR BERNARDES | D40: 20.320.503/0001-51 | E40: Aluguel Embrapa/RJ - 4a/4 parcela | F40: NF - 202000000000830 | I40: 5144 | J40: =IF(L40=TRUE,SUM(O40:S40),"") -> 5144 | K40: 44032 | L40: TRUE | N40: Serviço | O40: 5144 | P40: - | Q40: - | R40: - | S40: - | T40: Serviço de terceiros | U40: Retort (Sistema Fechado) | W40: TRUE
A41: 1 | C41: Fundação de Apoio à Pesquisa e ao Desenvolvimento - FAPED | D41: 00.849.774/0001-91 | E41: Aluguel de planta - Embrapa/RJ (6a parcela) | F41: NF - 23708 | I41: 4000 | J41: =IF(L41=TRUE,SUM(O41:S41),"") -> 4000 | K41: 43837 | L41: TRUE | N41: Serviço | O41: 4000 | P41: - | Q41: - | R41: - | S41: - | T41: Serviço de terceiros | U41: Retort (Sistema Fechado) | W41: TRUE
A42: 48 | C42: Fundação de Apoio à Universidade de São Paulo | D42: 68.314.830/0001-27 | E42: Análise de DP | F42: NF - 44694 | I42: 678 | J42: =IF(L42=TRUE,SUM(O42:S42),"") -> 678 | K42: 43903 | L42: TRUE | N42: Serviço | O42: 678 | P42: - | Q42: - | R42: - | S42: - | T42: Serviço de terceiros | U42: Retort (Sistema Fechado) | W42: TRUE
A43: 25 | C43: Fundação de desenv. da pesquisa do agronegócio - FUNDEPAG | D43: 50.276.237/0001-78 | E43: Análise de perfil lipídico | F43: NF - 115781 | I43: 2001 | J43: =IF(L43=TRUE,SUM(O43:S43),"") -> 2001 | K43: 43868 | L43: TRUE | N43: Serviço | O43: - | P43: - | Q43: 2001 | R43: - | S43: - | T43: Serviço de terceiros | U43: Produtos líquidos | V43: Produtos líquidos | W43: #N/A
A44: 6 | C44: Fundação de desenv. da pesquisa do agronegócio - FUNDEPAG | D44: 50.276.237/0001-78 | E44: Análise de perfil lipídico | F44: NF - 115288 | I44: 612 | J44: =IF(L44=TRUE,SUM(O44:S44),"") -> 612 | K44: 43846 | L44: TRUE | N44: Serviço | O44: 612 | P44: - | Q44: - | R44: - | S44: - | T44: Serviço de terceiros | U44: Trophic Soya 1.5 Fiber | V44: Trophic Soya 1.5 | W44: TRUE
A45: 8 | C45: Fundação de desenv. da pesquisa do agronegócio - FUNDEPAG | D45: 50.276.237/0001-78 | E45: Análise de perfil lipídico | F45: NF - 115287 | I45: 612 | J45: =IF(L45=TRUE,SUM(O45:S45),"") -> 612 | K45: 43846 | L45: TRUE | N45: Serviço | O45: 612 | P45: - | Q45: - | R45: - | S45: - | T45: Serviço de terceiros | U45: Trophic Soya 1.5 Fiber | V45: Trophic Soya 1.5 | W45: TRUE
A46: 9 | C46: Fundação de desenv. da pesquisa do agronegócio - FUNDEPAG | D46: 50.276.237/0001-78 | E46: Análise de perfil lipídico | F46: NF - 115195 | I46: 1224 | J46: =IF(L46=TRUE,SUM(O46:S46),"") -> 1224 | K46: 43840 | L46: TRUE | N46: Serviço | O46: 1224 | P46: - | Q46: - | R46: - | S46: - | T46: Serviço de terceiros | U46: Energyzip Fiber | W46: TRUE
A47: 42 | C47: Luiz Volpato Arquitetura S/S | D47: 08.921.374/0001-51 | E47: Estudos e projetos arquitetônicos | F47: NF - 488 | I47: 5887.5 | J47: =IF(L47=TRUE,I47,"") | K47: 43896 | L47: FALSE | N47: Serviço | O47: 5887.5 | P47: - | Q47: - | R47: - | S47: - | T47: Serviço de terceiros | U47: Centro de Inovação | W47: FALSE
A48: 10 | C48: Fundação de desenv. da pesquisa do agronegócio - FUNDEPAG | D48: 50.276.237/0001-78 | E48: Análise de perfil lipídico | F48: NF - 115054 | I48: 1224 | J48: =IF(L48=TRUE,SUM(O48:S48),"") -> 1224 | K48: 43837 | L48: TRUE | N48: Serviço | O48: 1224 | P48: - | Q48: - | R48: - | S48: - | T48: Serviço de terceiros | U48: Energyzip Fiber | W48: TRUE
A49: 44 | C49: Rafael Silva de Oliveira - Comunicação - EPP | D49: 17.927.780/0001-12 | E49: Publicações mkt | F49: NF - 700 | I49: 87.03 | J49: =IF(L49=TRUE,I49,"") | K49: 43896 | L49: FALSE | N49: Serviço | O49: 87.03 | P49: - | Q49: - | R49: - | S49: - | T49: Serviço de terceiros | U49: InstanTH NEO e InstanTH CLEAR (espessante) | V49: InstanTH NEO e Instanth Clear | W49: #N/A
A50: 45 | C50: Rafael Silva de Oliveira - Comunicação - EPP | D50: 17.927.780/0001-12 | E50: Publicações mkt | F50: NF - 699 | I50: 6100 | J50: =IF(L50=TRUE,I50,"") | K50: 43896 | L50: FALSE | N50: Serviço | O50: 5000 | P50: - | Q50: - | R50: - | S50: - | T50: Serviço de terceiros | U50: InstanTH NEO e InstanTH CLEAR (espessante) | V50: InstanTH NEO e Instanth Clear | W50: #N/A
A51: 46 | C51: Studio Madcreative Design Ltda - ME | D51: 11.115.312/0001-67 | E51: Serviços de marketing | F51: NF - 1104 | I51: 12591.75 | J51: =IF(L51=TRUE,I51,"") | K51: 43893 | L51: FALSE | N51: Serviço | O51: 4000 | P51: - | Q51: - | R51: - | S51: - | T51: Serviço de terceiros | U51: InstanTH NEO e InstanTH CLEAR (espessante) | V51: InstanTH NEO e Instanth Clear | W51: #N/A
A52: 47 | C52: WJ Packaging Solutions Corp | D52: NA | E52: Logística de Comex para entrada de embalagens | F52: NF - 9171 | I52: 720.88 | J52: =IF(L52=TRUE,I52,"") | K52: 43892 | L52: FALSE | M52: Prodiet não lançou em conta contábil específica e nem no centro de custo de inovação. Valor foi contabilizado nos custos e a empresa não irá remover, | N52: Material | O52: 720.88 | P52: - | Q52: - | R52: - | S52: - | T52: Serviço próprios | U52: Retort (Sistema Fechado) | W52: TRUE
A53: 28 | C53: Fundação de desenv. da pesquisa do agronegócio - FUNDEPAG | D53: 50.276.237/0001-78 | E53: Análise de perfil lipídico - morango | F53: NF - 116066 | I53: 667 | J53: =IF(L53=TRUE,SUM(O53:S53),"") -> 667 | K53: 43878 | L53: TRUE | N53: Serviço | O53: 667 | P53: - | Q53: - | R53: - | S53: - | T53: Serviço de terceiros | U53: Energyzip Fiber | W53: TRUE
A54: 107 | C54: Fundação de desenv. da pesquisa do agronegócio - FUNDEPAG | D54: 50.276.237/0001-78 | E54: Análise de perfil lipídico | F54: NF - 00119004 | I54: 667 | J54: =IF(L54=TRUE,SUM(O54:S54),"") -> 667 | K54: 44029 | L54: TRUE | N54: Serviço | O54: - | P54: - | Q54: 667 | R54: - | S54: - | T54: Serviço de terceiros | U54: Energyzip morango | W54: TRUE
A55: 126 | C55: Fundação de desenv. da pesquisa do agronegócio - FUNDEPAG | D55: 50.276.237/0001-78 | E55: Análise de perfil lipídico | F55: NF - 00119451 | I55: 667 | J55: =IF(L55=TRUE,SUM(O55:S55),"") -> 667 | K55: 44053 | L55: TRUE | N55: Serviço | O55: - | P55: - | Q55: 667 | R55: - | S55: - | T55: Serviço de terceiros | U55: Energyzip 1.0 | W55: TRUE
A56: 129 | C56: Fundação de desenv. da pesquisa do agronegócio - FUNDEPAG | D56: 50.276.237/0001-78 | E56: Análise de perfil lipídico | F56: NF - 00119409 | I56: 667 | J56: =IF(L56=TRUE,SUM(O56:S56),"") -> 667 | K56: 44050 | L56: TRUE | N56: Serviço | O56: - | P56: - | Q56: 667 | R56: - | S56: - | T56: Serviço de terceiros | U56: Energyzip Baunilha | V56: Energyzip Baunilha | W56: TRUE
A57: 131 | C57: Fundação de desenv. da pesquisa do agronegócio - FUNDEPAG | D57: 50.276.237/0001-78 | E57: Análise de perfil lipídico | F57: NF - 00119563 | I57: 667 | J57: =IF(L57=TRUE,SUM(O57:S57),"") -> 667 | K57: 44056 | L57: TRUE | N57: Serviço | O57: - | P57: - | Q57: 667 | R57: - | S57: - | T57: Serviço de terceiros | U57: Energyzip morango | W57: TRUE
A58: 49 | C58: Fundação de desenv. da pesquisa do agronegócio - FUNDEPAG | D58: 50.276.237/0001-78 | E58: Análise de perfil lipídico | F58: NF - 116840 | I58: 2668 | J58: =IF(L58=TRUE,SUM(O58:S58),"") -> 2668 | K58: 43909 | L58: TRUE | N58: Serviço | O58: 2668 | P58: - | Q58: - | R58: - | S58: - | T58: Serviço de terceiros | U58: Retort (Sistema Fechado) | W58: TRUE
A59: 160 | C59: Fundação de desenv. da pesquisa do agronegócio - FUNDEPAG | D59: 50.276.237/0001-78 | E59: Análise de perfil lipídico | F59: NF - 00120989 | I59: 667 | J59: =IF(L59=TRUE,SUM(O59:S59),"") -> 667 | K59: 44111 | L59: TRUE | N59: Serviço | O59: 667 | P59: - | Q59: - | R59: - | S59: - | T59: Serviço de terceiros | U59: InstanTH NEO | W59: TRUE
A60: 163 | C60: Fundação de desenv. da pesquisa do agronegócio - FUNDEPAG | D60: 50.276.237/0001-78 | E60: Análise de perfil lipídico | F60: NF - 00121162 | I60: 1334 | J60: =IF(L60=TRUE,SUM(O60:S60),"") -> 1334 | K60: 44118 | L60: TRUE | N60: Serviço | O60: 1334 | P60: - | Q60: - | R60: - | S60: - | T60: Serviço de terceiros | U60: HDmax 2.0 | W60: TRUE
A61: 178 | C61: Fundação de desenv. da pesquisa do agronegócio - FUNDEPAG | D61: 50.276.237/0001-78 | E61: Análise de perfil lipídico | F61: NF - 00121346 | I61: 667 | J61: =IF(L61=TRUE,SUM(O61:S61),"") -> 667 | K61: 44124 | L61: TRUE | N61: Serviço | O61: - | P61: - | Q61: - | R61: 667 | S61: - | T61: Serviço de terceiros | U61: Immax - etapa final da Pesquisa Clínica | V61: Immax | W61: TRUE
A62: 181 | C62: Fundação de desenv. da pesquisa do agronegócio - FUNDEPAG | D62: 50.276.237/0001-78 | E62: Análise de perfil lipídico | F62: NF - 00121300 | I62: 2001 | J62: =IF(L62=TRUE,SUM(O62:S62),"") -> 1334 | K62: 44123 | L62: TRUE | N62: Serviço | O62: 1334 | P62: - | Q62: - | R62: - | S62: - | T62: Serviço de terceiros | U62: Immax - etapa final da Pesquisa Clínica | W62: TRUE
A63: 192 | C63: Fundação de desenv. da pesquisa do agronegócio - FUNDEPAG | D63: 50.276.237/0001-78 | E63: Análise de perfil lipídico | F63: NF - 00121781 | I63: 667 | J63: =IF(L63=TRUE,SUM(O63:S63),"") -> 667 | K63: 44144 | L63: TRUE | N63: Serviço | O63: - | P63: - | Q63: 667 | R63: - | S63: - | T63: Serviço de terceiros | U63: Energyzip baunilha | V63: Energyzip baunilha | W63: TRUE
A64: 65 | C64: Fundação de desenv. da pesquisa do agronegócio - FUNDEPAG | D64: 50.276.237/0001-78 | E64: Análise de perfil lipídico (correção do laudo) | F64: NF - 117224 | I64: 138 | J64: =IF(L64=TRUE,SUM(O64:S64),"") -> 138 | K64: 43927 | L64: TRUE | N64: Serviço | O64: 138 | P64: - | Q64: - | R64: - | S64: - | T64: Serviço de terceiros | U64: Retort (Sistema Fechado) | W64: TRUE
A65: 59 | C65: Transmazili Transporte de Cargas e Logística Ltda | D65: 14.574.799/0001-34 | E65: Retorno de produtos-teste da Embrapa/RJ | F65: NF - 11861 | I65: 1200 | J65: =IF(L65=TRUE,I65,"") | K65: 43893 | L65: FALSE | N65: Serviço | O65: 1200 | P65: - | Q65: - | R65: - | S65: - | T65: Serviço de terceiros | U65: Retort (Sistema Fechado) | W65: TRUE
A66: 62 | C66: Fundação de desenv. da pesquisa do agronegócio - FUNDEPAG | D66: 50.276.237/0001-78 | E66: Análise de perfil lipídico | F66: NF - 117007 | I66: 1334 | J66: =IF(L66=TRUE,SUM(O66:S66),"") -> 1334 | K66: 43922 | L66: TRUE | N66: Serviço | O66: 1334 | P66: - | Q66: - | R66: - | S66: - | T66: Serviço de terceiros | U66: Bemmax Sabor Neutro, Instanth NEO | V66: Bemmax Sabor Neutro, Instant NEO | W66: #N/A
A67: 83 | C67: Fundação de desenv. da pesquisa do agronegócio - FUNDEPAG | D67: 50.276.237/0001-78 | E67: Curso Ital - Embalagens plásticas | F67: NF - 00118015 | I67: 750 | J67: =IF(L67=TRUE,SUM(O67:S67),"") -> 750 | K67: 43984 | L67: TRUE | N67: Serviço | O67: 750 | P67: - | Q67: - | R67: - | S67: - | T67: Serviço de terceiros | U67: Produtos pó | V67: Produtos pó | W67: #N/A
A68: 87 | C68: Fundação de desenv. da pesquisa do agronegócio - FUNDEPAG | D68: 50.276.237/0001-78 | E68: Análise de perfil lipídico | F68: NF - 00118106 | I68: 667 | J68: =IF(L68=TRUE,SUM(O68:S68),"") -> 667 | K68: 43990 | L68: TRUE | N68: Serviço | O68: - | P68: - | Q68: 667 | R68: - | S68: - | T68: Serviço de terceiros | U68: Trophic EP | V68: Trophic EP | W68: #N/A
A69: 63 | C69: Studio Madcreative Design Ltda - ME | D69: 11.115.312/0001-67 | E69: Serviços de marketing | F69: NF - 1113 | I69: 12591.75 | J69: =IF(L69=TRUE,I69,"") | K69: 43922 | L69: FALSE | N69: Serviço | O69: 5000 | P69: - | Q69: - | R69: - | S69: - | T69: Serviço de terceiros | U69: InstanTH CLEAR (espessante), InstanTH NEO e Bemmax Sabor Neutro | V69: Instanth Clear, InstanTH NEO e Bemmax Sabor Neutro | W69: #N/A
A70: 97 | C70: Fundação de desenv. da pesquisa do agronegócio - FUNDEPAG | D70: 50.276.237/0001-78 | E70: Análise de perfil lipídico | F70: NF - 00110671 | I70: 667 | J70: =IF(L70=TRUE,SUM(O70:S70),"") -> 667 | K70: 44014 | L70: TRUE | N70: Serviço | O70: - | P70: - | Q70: 667 | R70: - | S70: - | T70: Serviço de terceiros | U70: Trophic EP | V70: Trophic EP | W70: #N/A
A71: 134 | C71: Fundação de desenv. da pesquisa do agronegócio - FUNDEPAG | D71: 50.276.237/0001-78 | E71: Análise de perfil lipídico | F71: NF - 00119738 | I71: 2668 | J71: =IF(L71=TRUE,SUM(O71:S71),"") -> 2668 | K71: 44061 | L71: TRUE | N71: Serviço | O71: - | P71: - | Q71: 2668 | R71: - | S71: - | T71: Serviço de terceiros | U71: Trophic Basic L, Trophic Fiber L, Trophic 1.5, Energyzip Chocolate | V71: Trophic Basic L, Trophic Fiber L, Trophic 1.5, Energyzip Chocolate | W71: #N/A
A72: 137 | C72: Fundação de desenv. da pesquisa do agronegócio - FUNDEPAG | D72: 50.276.237/0001-78 | E72: Análise de perfil lipídico | F72: NF - 00119798 | I72: 1334 | J72: =IF(L72=TRUE,SUM(O72:S72),"") -> 1334 | K72: 44063 | L72: TRUE | N72: Serviço | O72: 667 | P72: - | Q72: 667 | R72: - | S72: - | T72: Serviço de terceiros | U72: HDmax e Instanth NEO | V72: HDmax e Instant Neo | W72: #N/A
A73: 53 | C73: FUNDAÇÃO EDUCACIONAL CIÊNCIA E DESENVOLVIMENTO FECD | D73: 03.078.688/0001-10 | E73: Segunda eatapa pesquisa InstanTH NEO UFRJ | F73: NF - 5382 | I73: 66285.43 | J73: =IF(L73=TRUE,SUM(O73:S73),"") -> 66285.43 | K73: 43892 | L73: TRUE | N73: Serviço | O73: 66285.43 | P73: - | Q73: - | R73: - | S73: - | T73: Serviço de terceiros | U73: InstanTH NEO | W73: TRUE
A74: 13 | C74: Grupo HU Viagens e Turismo S.A. - Hurb | D74: 12.954.744/0001-24 | E74: Hospedagem - Lizianne - teste Embrapa/RJ - fev 2020 | F74: Recibos - NA | I74: 630.81 | J74: =IF(L74=TRUE,SUM(O74:S74),"") -> 630.81 | K74: 43866 | L74: TRUE | N74: Serviço | O74: 630.81 | P74: - | Q74: - | R74: - | S74: - | T74: Serviço de terceiros | U74: Retort (Sistema Fechado) | W74: TRUE
A75: 116 | C75: Instituto Cristina Martins Educação e Pesquisa em Nutrição Ltda | D75: 33.253.322/0001-00 | E75: Serviço técnico - pesquisa básica sobre nutrientes essecnciais na diálise | F75: NF - 75 | I75: 3000 | J75: =IF(L75=TRUE,SUM(O75:S75),"") -> 3000 | K75: 44028 | L75: TRUE | N75: Serviço | O75: - | P75: - | Q75: 3000 | R75: - | S75: - | T75: Serviço de terceiros | U75: Hdmax | V75: Hdmax | W75: #N/A
A76: 26 | C76: J&J Serviços de Entregas Ltda - ME | D76: 20.618.029/0001-49 | E76: Envio de amostra para análise | F76: NF - 37473 | I76: 141.6 | J76: =IF(L76=TRUE,SUM(O76:S76),"") -> 90.4 | K76: 43872 | L76: TRUE | N76: Serviço | O76: - | P76: - | Q76: 90.4 | R76: - | S76: - | T76: Serviço de terceiros | U76: Produtos líquidos | V76: Produtos líquidos | W76: #N/A
A77: 71 | C77: Labor Três Laboratórios e Consultoria Técnica Ltda | D77: 02.021.076/0001-29 | E77: Análise de Bacillus cereus | F77: NF - 38979 | I77: 74 | J77: =IF(L77=TRUE,I77,"") | K77: 43943 | L77: FALSE | N77: Serviço | O77: 74 | P77: - | Q77: - | R77: - | S77: - | T77: Serviço de terceiros | U77: Bemmax Sabor Neutro | W77: TRUE
A78: 39 | C78: J&J Serviços de Entregas Ltda - ME | D78: 20.618.029/0001-49 | E78: Envio de amostra para análise | F78: NF - 38035 | I78: 105.55 | J78: =IF(L78=TRUE,SUM(O78:S78),"") -> 105.55 | K78: 43893 | L78: TRUE | N78: Serviço | O78: 105.55 | P78: - | Q78: - | R78: - | S78: - | T78: Serviço de terceiros | U78: Retort (Sistema Fechado) | W78: TRUE
A79: 5 | C79: J&J Serviços de Entregas Ltda - ME | D79: 20.618.029/0001-49 | E79: Envio de amostra para análise | F79: NF - 36715 | I79: 120.9 | J79: =IF(L79=TRUE,SUM(O79:S79),"") -> 120.9 | K79: 43851 | L79: TRUE | N79: Serviço | O79: 120.9 | P79: - | Q79: - | R79: - | S79: - | T79: Serviço de terceiros | U79: Energyzip Fiber | W79: TRUE
A80: 74 | C80: J&J Serviços de Entregas Ltda - ME | D80: 20.618.029/0001-49 | E80: Envio de amostra para análise | F80: NF - 39816 | I80: 112.3 | J80: =IF(L80=TRUE,SUM(O80:S80),"") -> 36.45 | K80: 43963 | L80: TRUE | N80: Serviço | O80: 36.45 | P80: - | Q80: - | R80: - | S80: - | T80: Serviço de terceiros | U80: Bemmax Sabor Neutro | W80: TRUE
A81: 94 | C81: J&J Serviços de Entregas Ltda - ME | D81: 20.618.029/0001-49 | E81: Envio de amostra para análise | F81: NF - 40951 | I81: 348.3 | J81: =IF(L81=TRUE,SUM(O81:S81),"") -> 51 | K81: 44004 | L81: TRUE | N81: Serviço | O81: - | P81: - | Q81: 51 | R81: - | S81: - | T81: Serviço de terceiros | U81: Energyzip morango | W81: TRUE
A82: 95 | C82: J&J Serviços de Entregas Ltda - ME | D82: 20.618.029/0001-49 | E82: Envio de amostra para análise | F82: NF - 41285 | I82: 182.65 | J82: =IF(L82=TRUE,SUM(O82:S82),"") -> 122.6 | K82: 44013 | L82: TRUE | N82: Serviço | O82: 122.6 | P82: - | Q82: - | R82: - | S82: - | T82: Serviço de terceiros | U82: HDmax 2.0 | W82: TRUE
A83: 132 | C83: J&J Serviços de Entregas Ltda - ME | D83: 20.618.029/0001-49 | E83: Envio de amostra para análise | F83: NF - 42626 | I83: 109.35 | J83: =IF(L83=TRUE,SUM(O83:S83),"") -> 36.45 | K83: 44055 | L83: TRUE | N83: Serviço | O83: - | P83: - | Q83: 36.45 | R83: - | S83: - | T83: Serviço de terceiros | U83: Immax - etapa final da Pesquisa Clínica | V83: Immax | W83: TRUE
A84: 79 | C84: J&J Serviços de Entregas Ltda - ME | D84: 20.618.029/0001-49 | E84: Envio de amostra para análise | F84: NF - 40051 | I84: 289.08 | J84: =IF(L84=TRUE,SUM(O84:S84),"") -> 213.23 | K84: 43972 | L84: TRUE | N84: Serviço | O84: - | P84: - | Q84: 213.23 | R84: - | S84: - | T84: Serviço de terceiros | U84: Immax - etapa final da Pesquisa Clínica, ProteinPT e CarboCH | V84: Immax, ProteinPT e CarboCH | W84: #N/A
A85: 84 | C85: J&J Serviços de Entregas Ltda - ME | D85: 20.618.029/0001-49 | E85: Envio de amostra para análise | F85: NF - 40386 | I85: 316.09 | J85: =IF(L85=TRUE,SUM(O85:S85),"") -> 130.74 | K85: 43984 | L85: TRUE | N85: Serviço | O85: 65.37 | P85: - | Q85: 65.37 | R85: - | S85: - | T85: Serviço de terceiros | U85: Retort (Sistema Fechado) e Energyzip morango | V85: Retort (Sistema Fechado) e Energyzip morango | W85: #N/A
A86: 80 | C86: AD Literam Tradutores Associados Eireli | D86: 04.498.297/0001-18 | E86: Tradução de material publicitário | F86: NF - 445 | I86: 100 | J86: =IF(L86=TRUE,I86,"") | K86: 43977 | L86: FALSE | N86: Serviço | O86: 100 | P86: - | Q86: - | R86: - | S86: - | T86: Serviço de terceiros | U86: InstanTH NEO | W86: TRUE
A87: 148 | C87: J&J Serviços de Entregas Ltda - ME | D87: 20.618.029/0001-49 | E87: Envio de amostra para análise | F87: NF - 43919 | I87: 793.74 | J87: =IF(L87=TRUE,SUM(O87:S87),"") -> 153.84 | K87: 44092 | L87: TRUE | N87: Serviço | O87: 153.84 | P87: - | Q87: - | R87: - | S87: - | T87: Serviço de terceiros | U87: InstanTH NEO | W87: TRUE
A88: 92 | C88: J&J Serviços de Entregas Ltda - ME | D88: 20.618.029/0001-49 | E88: Envio de amostra para análise | F88: NF - 40716 | I88: 451.14 | J88: =IF(L88=TRUE,SUM(O88:S88),"") -> 282.79 | K88: 43994 | L88: TRUE | N88: Serviço | O88: - | P88: - | Q88: 282.79 | R88: - | S88: - | T88: Serviço de terceiros | U88: Trophic EP e HDmax | V88: Trophic EP e HDmax | W88: #N/A
A89: 182 | C89: J&J Serviços de Entregas Ltda - ME | D89: 20.618.029/0001-49 | E89: Envio de amostra para análise | F89: NF - 44878 | I89: 853.15 | J89: =IF(L89=TRUE,SUM(O89:S89),"") -> 87.25 | K89: 44123 | L89: TRUE | N89: Serviço | O89: - | P89: - | Q89: 87.25 | R89: - | S89: - | T89: Serviço de terceiros | U89: Energyzip baunilha | V89: Energyzip baunilha | W89: TRUE
A90: 103 | C90: J&J Serviços de Entregas Ltda - ME | D90: 20.618.029/0001-49 | E90: Envio de amostra para análise | F90: NF - 41668 | I90: 643.78 | J90: =IF(L90=TRUE,SUM(O90:S90),"") -> 406.43 | K90: 44025 | L90: TRUE | N90: Serviço | O90: - | P90: - | Q90: 406.43 | R90: - | S90: - | T90: Serviço de terceiros | U90: Energyzip baunilha, Energyzip 1.0 | V90: Energyzip baunilha, Energyzip 1.0 | W90: #N/A
A91: 108 | C91: J&J Serviços de Entregas Ltda - ME | D91: 20.618.029/0001-49 | E91: Envio de amostra para análise | F91: NF - 41951 | I91: 487.98 | J91: =IF(L91=TRUE,SUM(O91:S91),"") -> 379.69 | K91: 44033 | L91: TRUE | N91: Serviço | O91: - | P91: - | Q91: 379.69 | R91: - | S91: - | T91: Serviço de terceiros | U91: Trophic Basic, Trophic Fiber, Trophic 1.5 e Energyzip Chocolate | V91: Trophic Basic, Trophic Fiber, Trophic 1.5 e Energyzip Chocolate | W91: #N/A
A92: 115 | C92: J&J Serviços de Entregas Ltda - ME | D92: 20.618.029/0001-49 | E92: Envio de amostra para análise | F92: NF - 42110 | I92: 454.58 | J92: =IF(L92=TRUE,SUM(O92:S92),"") -> 358.08 | K92: 44044 | L92: TRUE | N92: Serviço | O92: 179.04 | P92: - | Q92: 179.04 | R92: - | S92: - | T92: Serviço de terceiros | U92: Bemmax Sabor Neutro, InstanTH NEO, HDmax e Energyzip Morango | V92: Bemmax Sabor Neutro, InstanTH NEO, HDmax e Energyzip Morango | W92: #N/A
A93: 141 | C93: J&J Serviços de Entregas Ltda - ME | D93: 20.618.029/0001-49 | E93: Envio de amostra para análise | F93: NF - 43372 | I93: 221.54 | J93: =IF(L93=TRUE,SUM(O93:S93),"") -> 96.3 | K93: 44076 | L93: TRUE | N93: Serviço | O93: 48.15 | P93: - | Q93: 48.15 | R93: - | S93: - | T93: Serviço de terceiros | U93: Retort (Sistema Fechado) e Immax - etapa final da Pesquisa Clínica | V93: Retort (Sistema Fechado) e Immax | W93: #N/A
A94: 88 | C94: Fundação de desenv. da pesquisa do agronegócio - FUNDEPAG | D94: 50.276.237/0001-78 | E94: Curso Ital - Embalagens plásticas | F94: NF - 00118237 | I94: 750 | J94: =IF(L94=TRUE,I94,"") | K94: 43992 | L94: FALSE | N94: Serviço | O94: - | P94: - | Q94: 750 | R94: - | S94: - | T94: Serviço de terceiros | U94: Produtos pó | V94: Produtos pó | W94: #N/A
A95: 89 | C95: ANKofis Consulting Ltd | D95: NA | E95: Consultoria produtos Turquia | F95: NF - ANK-192020 | I95: 9406.25 | J95: =IF(L95=TRUE,I95,"") | K95: 43993 | L95: FALSE | N95: Serviço | O95: 4703.13 | P95: - | Q95: 4703.13 | R95: - | S95: - | T95: Serviço de terceiros | U95: Produtos líquidos | V95: Produtos líquidos | W95: #N/A
A96: 90 | C96: Andrei Publicações Médicas Farmacêuticas Técnicas Ltda | D96: 62.958.491/0001-35 | E96: Publicação de material de comunicação | F96: NF - 062231 | I96: 780 | J96: =IF(L96=TRUE,I96,"") | K96: 43994 | L96: FALSE | N96: Serviço | O96: 97.5 | P96: - | Q96: - | R96: - | S96: - | T96: Serviço de terceiros | U96: Bemmax Sabor Neutro, Instanth NEO, InstanTH CLEAR (espessante) | V96: Bemmax Sabor Neutro, Instant NEO, Instanth Clear | W96: #N/A
A97: 91 | C97: Rafael Silva de Oliveira - Comunicação - EPP | D97: 17.927.780/0001-12 | E97: Desenvolvimento de peças e materiais de publicação | F97: NF - 716 | I97: 10669.5 | J97: =IF(L97=TRUE,I97,"") | K97: 43997 | L97: FALSE | N97: Serviço | O97: 5000 | P97: - | Q97: - | R97: - | S97: - | T97: Serviço de terceiros | U97: Bemmax Sabor Neutro, Instanth NEO | V97: Bemmax Sabor Neutro, Instant NEO | W97: #N/A
A98: 156 | C98: J&J Serviços de Entregas Ltda - ME | D98: 20.618.029/0001-49 | E98: Envio de amostra para análise | F98: NF - 44455 | I98: 881.42 | J98: =IF(L98=TRUE,SUM(O98:S98),"") -> 355.87 | K98: 44109 | L98: TRUE | N98: Serviço | O98: 355.87 | P98: - | Q98: - | R98: - | S98: - | T98: Serviço de terceiros | U98: InstanTH NEO, Trophioc Soya 1.5, HDmax 2.0 | V98: InstanTH NEO, Trophioc Soya 1.5, HDmax 2.0 | W98: #N/A
A99: 55 | C99: KONTIK FRANSTUR VIAGENS E TURISMO LTDA | D99: 73.431.686/0010-30 | E99: aéreo POA - evento InstanTH NEO | F99: Recibo - NA | I99: 153.56 | J99: =IF(L99=TRUE,SUM(O99:S99),"") -> 153.56 | K99: 43893 | L99: TRUE | N99: Serviço | O99: 153.56 | P99: - | Q99: - | R99: - | S99: - | T99: Serviço de terceiros | U99: InstanTH NEO | W99: TRUE
A100: 19 | C100: KONTIK FRANSTUR VIAGENS E TURISMO LTDA | D100: 73.431.686/0010-30 | E100: aéreo Rio - para acompanhar a pesquisa pré-clínica InstanTH NEO | F100: Recibos - NA | I100: 397.7 | J100: =IF(L100=TRUE,SUM(O100:S100),"") -> 397.7 | K100: 43859 | L100: TRUE | N100: Serviço | O100: 397.7 | P100: - | Q100: - | R100: - | S100: - | T100: Serviço de terceiros | U100: InstanTH NEO | W100: TRUE
A101: 37 | C101: Labor Três Laboratórios e Consultoria Técnica Ltda | D101: 02.021.076/0001-29 | E101: Análise de Esterilidade Comercial - NN, CG, HN | F101: NF - 38598 | I101: 825 | J101: =IF(L101=TRUE,SUM(O101:S101),"") -> 825 | K101: 43893 | L101: TRUE | N101: Serviço | O101: 825 | P101: - | Q101: - | R101: - | S101: - | T101: Serviço de terceiros | U101: Retort (Sistema Fechado) | W101: TRUE
...
