Workbook

Sheet RESUMO
A2: Resumo dos investimentos
A3: BENEFÍCIO FISCAL DE PD&I 2021
G4: 2019-088 PRODIET
A5: PRODIET NUTRIÇÃO CLINICA LTDA | E5: CNPJ 08.183.359/0001-53 | G5: =TODAY() -> 46168
A6: Rua General Potiguara, 1428, Lotes 20 e 21, Novo Mundo - PR - SUL - CURITIBA - CEP 81.050-500 - fone: (41) 3342-2825
A8: Natureza | B8: Totalizadores | C8: ( i ) Origem dos dados
A9: Material | B9: =D54 -> 0 | C9: (a1) Material consumido - planilha Investimentos
A10: Terceiros | B10: =E54 -> 503579.72 | C10: (a2) Serviços contratados - planilha Investimentos
A11: RH (Parcial inovação) | B11: =Pessoal!T24 -> 356413.4 | C11: (b) Dispêndio com funcionários de dedicação parcial - planilha Timesheet
A12: RH (Exclusivo inovação) | B12: =Pessoal!T25 -> 0 | C12: (c) Custo total dos funcionários com dedicação exclusiva - planilha Salários
A13: Total 1 | B13: =sum(B9:B12) -> 859993.12
A14: Percentual Exclusão | B14: 0.6 | D14: 60% | E14: +10% | F14: +20% | G14: +20%
A15: Exclusão da Base de cálculo do IRPJ e CSLL | B15: =B13*B14 -> 515995.87 | D15: Benefício padrão | E15: Incremento <5% de pesquisadores exclusivos | F15: Incremento >5% de pesquisadores exclusivos | G15: Dispendios com registro de patente
A17: Patente (Gastos "InstanTH Neo") | B17: =IFERROR(__xludf.DUMMYFUNCTION("importrange(""1yvA7oQIjfgmieoV6G0WRoHhQ2zeDLsO5Kom90H_sfJU"",""Resumo geral!J16"")"),333294.53749999974) -> 333294.54
A18: Percentual Exclusão | B18: 0.2
A19: Exclusão da Base de cálculo do IRPJ e CSLL | B19: =B17*B18 -> 66658.908
A21: Total exclusão | B21: =sum(B15,B19) -> 582654.78
A23: Economia Estimada [34%] | B23: =B21*34% -> 198102.63
A24: Comissão McBenner | B24: =B23*0.1 -> 19810.263
A26: Observações:
A27: 1. Os dispêndios devem ser registrados na contabilidade em conta específica
A28: 2. O benefício deve ser aproveitado na ECF do respectivo ano/competência
A29: 3. O formulário do MCTIC (governo) deve ser enviado até fim de setembro/2021
A30: 4. Os projetos estão descritos em arquivo a parte a ser anexado no FORM PD&I
A31: 5. Alguns benefícios previstos na Lei do Bem não foram utilizados:
A32: --- 5.1. Depreciação acelerada
A33: --- 5.2. Redução de IPI na aquisição de equipamento para PD&I
A36: Equipe de PD&I
A37: Quadro de resumo | B37: Dedicação Parcial | E37: Dedicação Exclusiva
B38: Qtd | C38: Valor gasto | D38: Horas | E38: Qtd | F38: Valor gasto | G38: Horas
A39: Técnico | B39: =IFERROR(__xludf.DUMMYFUNCTION("COUNTA(IFERROR(FILTER(Pessoal!$E$6:$E$18,Pessoal!$E$6:$E$18 = $A39,Pessoal!$U$6:$U$18 = ""Parcial"",Pessoal!$U$29:$U$41 = TRUE),))"),0.0) -> 0 | C39: =IFERROR(__xludf.DUMMYFUNCTION("SUM(IFERROR(FILTER(Pessoal!$T$29:$T$41,Pessoal!$E$29:$E$41 = $A39,Pessoal!$D$29:$D$41 = ""Parcial""),0))"),0.0) -> 0 | D39: =IFERROR(__xludf.DUMMYFUNCTION("SUM(IFERROR(FILTER(Pessoal!$S$6:$S$18,Pessoal!$E$6:$E$18 = $A39,Pessoal!$U$6:$U$18 = ""Parcial""),0))*24"),0.0) -> 0 | E39: =IFERROR(__xludf.DUMMYFUNCTION("COUNTA(IFERROR(FILTER(Pessoal!$E$6:$E$18,Pessoal!$E$6:$E$18 = $A39,Pessoal!$U$6:$U$18 = ""Exclusivo"",Pessoal!$U$29:$U$40 = TRUE),))"),0.0) -> 0 | F39: =IFERROR(__xludf.DUMMYFUNCTION("SUM(IFERROR(FILTER(Pessoal!$T$29:$T$40,Pessoal!$E$29:$E$40 = $A39,Pessoal!$D$29:$D$40 = ""Exclusivo""),0))"),0.0) -> 0 | G39: =IFERROR(__xludf.DUMMYFUNCTION("SUM(IFERROR(FILTER(Pessoal!$S$6:$S$18,Pessoal!$E$6:$E$18 = $A39,Pessoal!$U$6:$U$18 = ""Exclusivo""),0))*24"),0.0) -> 0
A40: Tecnologo | B40: =IFERROR(__xludf.DUMMYFUNCTION("COUNTA(IFERROR(FILTER(Pessoal!$E$6:$E$18,Pessoal!$E$6:$E$18 = $A40,Pessoal!$U$6:$U$18 = ""Parcial"",Pessoal!$U$29:$U$41 = TRUE),))"),0.0) -> 0 | C40: =IFERROR(__xludf.DUMMYFUNCTION("SUM(IFERROR(FILTER(Pessoal!$T$29:$T$41,Pessoal!$E$29:$E$41 = $A40,Pessoal!$D$29:$D$41 = ""Parcial""),0))"),0.0) -> 0 | D40: =IFERROR(__xludf.DUMMYFUNCTION("SUM(IFERROR(FILTER(Pessoal!$S$6:$S$18,Pessoal!$E$6:$E$18 = $A40,Pessoal!$U$6:$U$18 = ""Parcial""),0))*24"),0.0) -> 0 | E40: =IFERROR(__xludf.DUMMYFUNCTION("COUNTA(IFERROR(FILTER(Pessoal!$E$6:$E$18,Pessoal!$E$6:$E$18 = $A40,Pessoal!$U$6:$U$18 = ""Exclusivo"",Pessoal!$U$29:$U$40 = TRUE),))"),0.0) -> 0 | F40: =IFERROR(__xludf.DUMMYFUNCTION("SUM(IFERROR(FILTER(Pessoal!$T$29:$T$40,Pessoal!$E$29:$E$40 = $A40,Pessoal!$D$29:$D$40 = ""Exclusivo""),0))"),0.0) -> 0 | G40: =IFERROR(__xludf.DUMMYFUNCTION("SUM(IFERROR(FILTER(Pessoal!$S$6:$S$18,Pessoal!$E$6:$E$18 = $A40,Pessoal!$U$6:$U$18 = ""Exclusivo""),0))*24"),0.0) -> 0
A41: Superior Completo | B41: =IFERROR(__xludf.DUMMYFUNCTION("COUNTA(IFERROR(FILTER(Pessoal!$E$6:$E$18,Pessoal!$E$6:$E$18 = $A41,Pessoal!$U$6:$U$18 = ""Parcial"",Pessoal!$U$29:$U$41 = TRUE),))"),3.0) -> 3 | C41: =IFERROR(__xludf.DUMMYFUNCTION("SUM(IFERROR(FILTER(Pessoal!$T$29:$T$41,Pessoal!$E$29:$E$41 = $A41,Pessoal!$D$29:$D$41 = ""Parcial""),0))"),120218.49720611384) -> 120218.5 | D41: =IFERROR(__xludf.DUMMYFUNCTION("SUM(IFERROR(FILTER(Pessoal!$S$6:$S$18,Pessoal!$E$6:$E$18 = $A41,Pessoal!$U$6:$U$18 = ""Parcial""),0))*24"),2782.1666666666647) -> 2782.1667 | E41: =IFERROR(__xludf.DUMMYFUNCTION("COUNTA(IFERROR(FILTER(Pessoal!$E$6:$E$18,Pessoal!$E$6:$E$18 = $A41,Pessoal!$U$6:$U$18 = ""Exclusivo"",Pessoal!$U$29:$U$40 = TRUE),))"),0.0) -> 0 | F41: =IFERROR(__xludf.DUMMYFUNCTION("SUM(IFERROR(FILTER(Pessoal!$T$29:$T$40,Pessoal!$E$29:$E$40 = $A41,Pessoal!$D$29:$D$40 = ""Exclusivo""),0))"),0.0) -> 0 | G41: =IFERROR(__xludf.DUMMYFUNCTION("SUM(IFERROR(FILTER(Pessoal!$S$6:$S$18,Pessoal!$E$6:$E$18 = $A41,Pessoal!$U$6:$U$18 = ""Exclusivo""),0))*24"),0.0) -> 0
A42: Pós graduado | B42: =IFERROR(__xludf.DUMMYFUNCTION("COUNTA(IFERROR(FILTER(Pessoal!$E$6:$E$18,Pessoal!$E$6:$E$18 = $A42,Pessoal!$U$6:$U$18 = ""Parcial"",Pessoal!$U$29:$U$41 = TRUE),))"),8.0) -> 8 | C42: =IFERROR(__xludf.DUMMYFUNCTION("SUM(IFERROR(FILTER(Pessoal!$T$29:$T$41,Pessoal!$E$29:$E$41 = $A42,Pessoal!$D$29:$D$41 = ""Parcial""),0))"),197945.15917924847) -> 197945.16 | D42: =IFERROR(__xludf.DUMMYFUNCTION("SUM(IFERROR(FILTER(Pessoal!$S$6:$S$18,Pessoal!$E$6:$E$18 = $A42,Pessoal!$U$6:$U$18 = ""Parcial""),0))*24"),3332.116666666666) -> 3332.1167 | E42: =IFERROR(__xludf.DUMMYFUNCTION("COUNTA(IFERROR(FILTER(Pessoal!$E$6:$E$18,Pessoal!$E$6:$E$18 = $A42,Pessoal!$U$6:$U$18 = ""Exclusivo"",Pessoal!$U$29:$U$40 = TRUE),))"),0.0) -> 0 | F42: =IFERROR(__xludf.DUMMYFUNCTION("SUM(IFERROR(FILTER(Pessoal!$T$29:$T$40,Pessoal!$E$29:$E$40 = $A42,Pessoal!$D$29:$D$40 = ""Exclusivo""),0))"),0.0) -> 0 | G42: =IFERROR(__xludf.DUMMYFUNCTION("SUM(IFERROR(FILTER(Pessoal!$S$6:$S$18,Pessoal!$E$6:$E$18 = $A42,Pessoal!$U$6:$U$18 = ""Exclusivo""),0))*24"),0.0) -> 0
A43: Mestrado | B43: =IFERROR(__xludf.DUMMYFUNCTION("COUNTA(IFERROR(FILTER(Pessoal!$E$6:$E$18,Pessoal!$E$6:$E$18 = $A43,Pessoal!$U$6:$U$18 = ""Parcial"",Pessoal!$U$29:$U$41 = TRUE),))"),2.0) -> 2 | C43: =IFERROR(__xludf.DUMMYFUNCTION("SUM(IFERROR(FILTER(Pessoal!$T$29:$T$41,Pessoal!$E$29:$E$41 = $A43,Pessoal!$D$29:$D$41 = ""Parcial""),0))"),38249.74538828467) -> 38249.745 | D43: =IFERROR(__xludf.DUMMYFUNCTION("SUM(IFERROR(FILTER(Pessoal!$S$6:$S$18,Pessoal!$E$6:$E$18 = $A43,Pessoal!$U$6:$U$18 = ""Parcial""),0))*24"),1153.499999999999) -> 1153.5 | E43: =IFERROR(__xludf.DUMMYFUNCTION("COUNTA(IFERROR(FILTER(Pessoal!$E$6:$E$18,Pessoal!$E$6:$E$18 = $A43,Pessoal!$U$6:$U$18 = ""Exclusivo"",Pessoal!$U$29:$U$40 = TRUE),))"),0.0) -> 0 | F43: =IFERROR(__xludf.DUMMYFUNCTION("SUM(IFERROR(FILTER(Pessoal!$T$29:$T$40,Pessoal!$E$29:$E$40 = $A43,Pessoal!$D$29:$D$40 = ""Exclusivo""),0))"),0.0) -> 0 | G43: =IFERROR(__xludf.DUMMYFUNCTION("SUM(IFERROR(FILTER(Pessoal!$S$6:$S$18,Pessoal!$E$6:$E$18 = $A43,Pessoal!$U$6:$U$18 = ""Exclusivo""),0))*24"),0.0) -> 0
A44: Doutorado | B44: =IFERROR(__xludf.DUMMYFUNCTION("COUNTA(IFERROR(FILTER(Pessoal!$E$6:$E$18,Pessoal!$E$6:$E$18 = $A44,Pessoal!$U$6:$U$18 = ""Parcial"",Pessoal!$U$29:$U$41 = TRUE),))"),0.0) -> 0 | C44: =IFERROR(__xludf.DUMMYFUNCTION("SUM(IFERROR(FILTER(Pessoal!$T$29:$T$41,Pessoal!$E$29:$E$41 = $A44,Pessoal!$D$29:$D$41 = ""Parcial""),0))"),0.0) -> 0 | D44: =IFERROR(__xludf.DUMMYFUNCTION("SUM(IFERROR(FILTER(Pessoal!$S$6:$S$18,Pessoal!$E$6:$E$18 = $A44,Pessoal!$U$6:$U$18 = ""Parcial""),0))*24"),0.0) -> 0 | E44: =IFERROR(__xludf.DUMMYFUNCTION("COUNTA(IFERROR(FILTER(Pessoal!$E$6:$E$18,Pessoal!$E$6:$E$18 = $A44,Pessoal!$U$6:$U$18 = ""Exclusivo"",Pessoal!$U$29:$U$40 = TRUE),))"),0.0) -> 0 | F44: =IFERROR(__xludf.DUMMYFUNCTION("SUM(IFERROR(FILTER(Pessoal!$T$29:$T$40,Pessoal!$E$29:$E$40 = $A44,Pessoal!$D$29:$D$40 = ""Exclusivo""),0))"),0.0) -> 0 | G44: =IFERROR(__xludf.DUMMYFUNCTION("SUM(IFERROR(FILTER(Pessoal!$S$6:$S$18,Pessoal!$E$6:$E$18 = $A44,Pessoal!$U$6:$U$18 = ""Exclusivo""),0))*24"),0.0) -> 0
B45: =SUM(B39:B44) -> 13 | C45: =SUM(C39:C44) -> 356413.4 | D45: =SUM(D39:D44) -> 7267.7833 | E45: =SUM(E39:E44) -> 0 | F45: =SUM(F39:F44) -> 0 | G45: =SUM(G39:G44) -> 0
A47: Valores por projeto de PD&I
A48: Projetos | B48: Identificação | D48: Vlr materiais | E48: Vlr terceiros | F48: Vlr Rh parcial | G48: Vlr exclusivos
A49: Novos Produtos | B49: NP | D49: =IFERROR(__xludf.DUMMYFUNCTION("iferror(SUM(FILTER(Investimentos!$M:$M,Investimentos!$L:$L = ""Material"",Investimentos!$J:$J = TRUE)),0)"),0.0) -> 0 | E49: =IFERROR(__xludf.DUMMYFUNCTION("SUM(FILTER(Investimentos!$M:$M,Investimentos!$L:$L = ""Serviço"",Investimentos!$J:$J = TRUE,Investimentos!$U:$U = TRUE))"),239212.73000000004) -> 239212.73 | F49: =$B$11*(E49/$E$54) -> 169305.12 | G49: =$B$12*(E49/$E$54) -> 0
A50: Novas Matérias-primas | B50: Nmp | D50: =IFERROR(__xludf.DUMMYFUNCTION("iferror(SUM(FILTER(Investimentos!$N:$N,Investimentos!$L:$L = ""Material"",Investimentos!$J:$J = TRUE,Investimentos!$U:$U = TRUE)),0)"),0.0) -> 0 | E50: =IFERROR(__xludf.DUMMYFUNCTION("SUM(FILTER(Investimentos!$N:$N,Investimentos!$L:$L = ""Serviço"",Investimentos!$J:$J = TRUE,Investimentos!$U:$U = TRUE))"),0.0) -> 0 | F50: =$B$11*(E50/$E$54) -> 0 | G50: =$B$12*(E50/$E$54) -> 0
A51: Melhoria de Produto | B51: Mprod | D51: =IFERROR(__xludf.DUMMYFUNCTION("iferror(SUM(FILTER(Investimentos!$O:$O,Investimentos!$L:$L = ""Material"",Investimentos!$J:$J = TRUE())),0)"),0.0) -> 0 | E51: =IFERROR(__xludf.DUMMYFUNCTION("SUM(FILTER(Investimentos!$O:$O,Investimentos!$L:$L = ""Serviço"",Investimentos!$J:$J = TRUE,Investimentos!$U:$U = TRUE))"),243517.54999999993) -> 243517.55 | F51: =$B$11*(E51/$E$54) -> 172351.89 | G51: =$B$12*(E51/$E$54) -> 0
A52: Melhoria de Processos | B52: Mproc | D52: =IFERROR(__xludf.DUMMYFUNCTION("iferror(SUM(FILTER(Investimentos!$P:$P,Investimentos!$L:$L = ""Material"",Investimentos!$J:$J = TRUE)),0)"),0.0) -> 0 | E52: =IFERROR(__xludf.DUMMYFUNCTION("SUM(FILTER(Investimentos!$P:$P,Investimentos!$L:$L = ""Serviço"",Investimentos!$J:$J = TRUE,Investimentos!$U:$U = TRUE))"),20849.44) -> 20849.44 | F52: =$B$11*(E52/$E$54) -> 14756.392 | G52: =$B$12*(E52/$E$54) -> 0
A53: Segurança Alimentar | B53: SgAlim | D53: =IFERROR(__xludf.DUMMYFUNCTION("iferror(SUM(FILTER(Investimentos!$Q:$Q,Investimentos!$L:$L = ""Material"",Investimentos!$J:$J = TRUE,Investimentos!$U:$U = TRUE)),0)"),0.0) -> 0 | E53: =IFERROR(__xludf.DUMMYFUNCTION("SUM(FILTER(Investimentos!$Q:$Q,Investimentos!$L:$L = ""Serviço"",Investimentos!$J:$J = TRUE,Investimentos!$U:$U = TRUE))"),0.0) -> 0 | F53: =$B$11*(E53/$E$54) -> 0 | G53: =$B$12*(E53/$E$54) -> 0
A54: Subtotais | D54: =SUM(D49:D53) -> 0 | E54: =SUM(E49:E53) -> 503579.72 | F54: =SUM(F49:F53) -> 356413.4 | G54: =SUM(G49:G53) -> 0

Sheet Projetos
A2: Projetos
A3: BENEFÍCIO FISCAL DE PD&I 2021
A5: Projeto | B5: Agrupamento | C5: Categoria do projeto | D5: Elemento tecnologicamente novo ou inovador | E5: Barreira ou desafio tecnológico a superar | F5: Metodologia empregada | G5: Data início | H5: Data de término (estimada) | I5: Descrição | J5: Attachments | K5: Timesheet | L5: Lei do Bem
A6: {=SORT(UNIQUE({Timesheet!C7:C56;PrjAdd!A2:A10}),1,true)} -> Bemmax sabor neutro | L6: TRUE
A7: CarboCH | L7: TRUE
A8: Centro de Inovação / Novos laboratórios | L8: FALSE
A9: Cicatrização | L9: TRUE
A10: Congresso ESPEN | L10: TRUE
A11: Congresso Ganepão | L11: TRUE
A12: Diamax IG | L12: TRUE
A13: Diamax pó | K13: Novo | L13: TRUE
A14: Dieta artesanal | L14: TRUE
A15: EE - 2020 | L15: TRUE
A16: Energyzip 1.0 | L16: TRUE
A17: Energyzip baunilha | K17: Novo | L17: TRUE
A18: Energyzip Chocolate | L18: TRUE
A19: Energyzip Fiber | L19: TRUE
A20: Energyzip morango | L20: TRUE
A21: Energyzip pó | L21: TRUE
A22: EnergyZIP Protein | K22: Novo | L22: TRUE
A23: Energyzip Sênior | L23: TRUE
A24: Estabilidade misturas secas | L24: TRUE
A25: HDmax - pesquisa | K25: Novo | L25: TRUE
A26: HDmax 1.5 | L26: TRUE
A27: HDmax 2.0 | L27: TRUE
A28: Immax - etapa final da Pesquisa Clínica | L28: TRUE
A29: Inovação industrial - misturas secas | L29: TRUE
A30: InstanTH CLEAR (espessante) | L30: TRUE
A31: InstanTH Neo | L31: TRUE
A32: Jumbo UHT | K32: Novo | L32: TRUE
A33: Licenciamento | K33: Novo | L33: FALSE
A34: Linha Soya pó | K34: Novo | L34: FALSE
A35: Marca própria - Enterfiber Prebiotic | K35: Novo | L35: FALSE
A36: Novos produtos Turquia | L36: TRUE
A37: Pasta de Amendoim - RUTF | K37: Novo | L37: TRUE
A38: Peptimax - pesquisa | K38: Novo | L38: TRUE
A39: ProteinPT | L39: TRUE
A40: Retort (Sistema Fechado) | L40: TRUE
A41: Sachê | L41: TRUE
A42: Sarcopenia | L42: TRUE
A43: Software P&D | L43: FALSE
A44: Suplemento hiperproteico líquido | L44: TRUE
A45: Trophic 1.5 250mL - Edge | L45: TRUE
A46: Trophic Basic Enteral | K46: Novo | L46: TRUE
A47: Trophic Basic pó | L47: TRUE
A48: Trophic Dose Única | K48: Novo | L48: TRUE
A49: Trophic Dose Única 250mL - Edge | K49: Novo | L49: TRUE
A50: Trophic Junior Líquido 1.0 (ARB) | K50: Novo | L50: TRUE
A51: Trophic Junior Líquido 1.0 e 1.5 (ARB) | K51: Novo | L51: TRUE
A52: Trophic Junior Powder (China) | L52: TRUE
A53: Trophic Soya 1.5 Fiber | L53: TRUE
A54: Trophic Soya pó | K54: Novo | L54: FALSE
A55: Vulcano (pote jumbo e Sachês a vácuo) | L55: FALSE
L56: FALSE

Sheet Timesheet
A2: Timesheet
A3: BENEFÍCIO FISCAL DE PD&I 2021 | M3: Parcial | N3: =N5-N4 -> 356413.4
M4: Exclusivo | N4: =IFERROR(__xludf.DUMMYFUNCTION("SUMIF($B$7:$B4641,FILTER(Pessoal!$A$9:$A$18,Pessoal!$U$9:$U$18 = ""Exclusivo"",MATCH(Pessoal!$A$9:$A$18,FILTER(Pessoal!$A$29:$A$40,Pessoal!$U$29:$U$40 = TRUE),0)),$N$7:$N4641)"),0.0) -> 0
M5: TOTAL | N5: =SUM(N7:N4641) -> 356413.4
A6: Cod | B6: Pessoa | C6: Projeto | E6: Descrição | F6: Start | G6: End | H6: Tempo aplicado | I6: Data | J6: Atividade incentivada | L6: Attachments | M6: Valor (R$) | N6: Custo | O6: checkprojetos
B7: Ana Claudia Zanini | C7: Trophic Soya 1.5 Fiber | D7: =vlookup(C7,'Classificação p pessoal'!F:G,2,false) -> NP | E7: Pesquisa basica para Produção de material cientifico | F7: 0.5625 | G7: 0.75 | H7: 0.1875 | I7: 44200 | J7: TRUE | L7: =IF(VLOOKUP(C7,Projetos!A:L,12,false)=TRUE,TRUE,FALSE) -> TRUE | M7: {=VLOOKUP(B7:B4641,Pessoal!$A$28:$R$40,MONTH(F7:F4641)+6,false)} -> 33.159727 | N7: =IFERROR(IF(AND(J7=TRUE,O7=TRUE,YEAR(F7)<2021),H7,"")*(M7*24),0) -> 149.21877 | O7: {=VLOOKUP(C7:C4641,Projetos!A6:L4641,12,false)} -> TRUE
B8: Ana Claudia Zanini | C8: Trophic Soya 1.5 Fiber | D8: =vlookup(C8,'Classificação p pessoal'!F:G,2,false) -> NP | E8: Pesquisa basica para Produção de material cientifico | F8: 0.34375 | G8: 0.51041667 | H8: 0.16666667 | I8: 44201 | J8: TRUE | L8: =IF(VLOOKUP(C8,Projetos!A:L,12,false)=TRUE,TRUE,FALSE) -> TRUE | M8: 33.159727 | N8: =IFERROR(IF(AND(J8=TRUE,O8=TRUE,YEAR(F8)<2021),H8,"")*(M8*24),0) -> 132.63891 | O8: TRUE
B9: Ana Claudia Zanini | C9: Suplemento hiperproteico líquido | D9: =vlookup(C9,'Classificação p pessoal'!F:G,2,false) -> NP | E9: Pesquisa e desenvolvimento de nova fórmula | F9: 0.5625 | G9: 0.75 | H9: 0.1875 | I9: 44201 | J9: TRUE | L9: =IF(VLOOKUP(C9,Projetos!A:L,12,false)=TRUE,TRUE,FALSE) -> TRUE | M9: 33.159727 | N9: =IFERROR(IF(AND(J9=TRUE,O9=TRUE,YEAR(F9)<2021),H9,"")*(M9*24),0) -> 149.21877 | O9: TRUE
B10: Ana Claudia Zanini | C10: Trophic Soya 1.5 Fiber | D10: =vlookup(C10,'Classificação p pessoal'!F:G,2,false) -> NP | E10: Pesquisa basica para Produção de material cientifico | F10: 0.35416667 | G10: 0.5625 | H10: 0.20833333 | I10: 44202 | J10: TRUE | L10: =IF(VLOOKUP(C10,Projetos!A:L,12,false)=TRUE,TRUE,FALSE) -> TRUE | M10: 33.159727 | N10: =IFERROR(IF(AND(J10=TRUE,O10=TRUE,YEAR(F10)<2021),H10,"")*(M10*24),0) -> 165.79864 | O10: TRUE
B11: Ana Claudia Zanini | C11: Suplemento hiperproteico líquido | D11: =vlookup(C11,'Classificação p pessoal'!F:G,2,false) -> NP | E11: Pesquisa e desenvolvimento de nova fórmula | F11: 0.625 | G11: 0.75 | H11: 0.125 | I11: 44202 | J11: TRUE | L11: =IF(VLOOKUP(C11,Projetos!A:L,12,false)=TRUE,TRUE,FALSE) -> TRUE | M11: 33.159727 | N11: =IFERROR(IF(AND(J11=TRUE,O11=TRUE,YEAR(F11)<2021),H11,"")*(M11*24),0) -> 99.479182 | O11: TRUE
B12: Ana Claudia Zanini | C12: Trophic Soya 1.5 Fiber | D12: =vlookup(C12,'Classificação p pessoal'!F:G,2,false) -> NP | E12: Pesquisa basica para Produção de material cientifico | F12: 0.35416667 | G12: 0.45833333 | H12: 0.10416667 | I12: 44203 | J12: TRUE | L12: =IF(VLOOKUP(C12,Projetos!A:L,12,false)=TRUE,TRUE,FALSE) -> TRUE | M12: 33.159727 | N12: =IFERROR(IF(AND(J12=TRUE,O12=TRUE,YEAR(F12)<2021),H12,"")*(M12*24),0) -> 82.899318 | O12: TRUE
B13: Ana Claudia Zanini | C13: Suplemento hiperproteico líquido | D13: =vlookup(C13,'Classificação p pessoal'!F:G,2,false) -> NP | E13: Pesquisa e desenvolvimento de nova fórmula | F13: 0.5625 | G13: 0.75 | H13: 0.1875 | I13: 44203 | J13: TRUE | L13: =IF(VLOOKUP(C13,Projetos!A:L,12,false)=TRUE,TRUE,FALSE) -> TRUE | M13: 33.159727 | N13: =IFERROR(IF(AND(J13=TRUE,O13=TRUE,YEAR(F13)<2021),H13,"")*(M13*24),0) -> 149.21877 | O13: TRUE
B14: Ana Claudia Zanini | C14: Trophic Soya 1.5 Fiber | D14: =vlookup(C14,'Classificação p pessoal'!F:G,2,false) -> NP | E14: Pesquisa basica para Produção de material cientifico | F14: 0.35416667 | G14: 0.5625 | H14: 0.20833333 | I14: 44204 | J14: TRUE | L14: =IF(VLOOKUP(C14,Projetos!A:L,12,false)=TRUE,TRUE,FALSE) -> TRUE | M14: 33.159727 | N14: =IFERROR(IF(AND(J14=TRUE,O14=TRUE,YEAR(F14)<2021),H14,"")*(M14*24),0) -> 165.79864 | O14: TRUE
B15: Ana Claudia Zanini | C15: Trophic Soya 1.5 Fiber | D15: =vlookup(C15,'Classificação p pessoal'!F:G,2,false) -> NP | E15: Pesquisa basica para Produção de material cientifico | F15: 0.35416667 | G15: 0.54166667 | H15: 0.1875 | I15: 44207 | J15: TRUE | L15: =IF(VLOOKUP(C15,Projetos!A:L,12,false)=TRUE,TRUE,FALSE) -> TRUE | M15: 33.159727 | N15: =IFERROR(IF(AND(J15=TRUE,O15=TRUE,YEAR(F15)<2021),H15,"")*(M15*24),0) -> 149.21877 | O15: TRUE
B16: Ana Claudia Zanini | C16: InstanTH Neo | E16: Desenvolvimento de comunicação da fórmula do produto | F16: 0.72916667 | G16: 0.75 | H16: 0.020833333 | I16: 44208 | J16: FALSE | K16: Não entra | L16: =IF(VLOOKUP(C16,Projetos!A:L,12,false)=TRUE,TRUE,FALSE) -> TRUE | M16: 33.159727 | N16: =IFERROR(IF(AND(J16=TRUE,O16=TRUE,YEAR(F16)<2021),H16,"")*(M16*24),0) -> 0 | O16: TRUE
B17: Ana Claudia Zanini | C17: Trophic Soya 1.5 Fiber | D17: =vlookup(C17,'Classificação p pessoal'!F:G,2,false) -> NP | E17: Pesquisa basica para Produção de material cientifico | F17: 0.5625 | G17: 0.70833333 | H17: 0.14583333 | I17: 44208 | J17: TRUE | L17: =IF(VLOOKUP(C17,Projetos!A:L,12,false)=TRUE,TRUE,FALSE) -> TRUE | M17: 33.159727 | N17: =IFERROR(IF(AND(J17=TRUE,O17=TRUE,YEAR(F17)<2021),H17,"")*(M17*24),0) -> 116.05905 | O17: TRUE
B18: Ana Claudia Zanini | C18: InstanTH Neo | E18: Desenvolvimento de comunicação da fórmula do produto | F18: 0.41666667 | G18: 0.45833333 | H18: 0.041666667 | I18: 44209 | J18: FALSE | K18: Não entra | L18: =IF(VLOOKUP(C18,Projetos!A:L,12,false)=TRUE,TRUE,FALSE) -> TRUE | M18: 33.159727 | N18: =IFERROR(IF(AND(J18=TRUE,O18=TRUE,YEAR(F18)<2021),H18,"")*(M18*24),0) -> 0 | O18: TRUE
B19: Ana Claudia Zanini | C19: Trophic Soya 1.5 Fiber | D19: =vlookup(C19,'Classificação p pessoal'!F:G,2,false) -> NP | E19: Pesquisa basica para Produção de material cientifico | F19: 0.5625 | G19: 0.75 | H19: 0.1875 | I19: 44209 | J19: TRUE | L19: =IF(VLOOKUP(C19,Projetos!A:L,12,false)=TRUE,TRUE,FALSE) -> TRUE | M19: 33.159727 | N19: =IFERROR(IF(AND(J19=TRUE,O19=TRUE,YEAR(F19)<2021),H19,"")*(M19*24),0) -> 149.21877 | O19: TRUE
B20: Ana Claudia Zanini | C20: Suplemento hiperproteico líquido | D20: =vlookup(C20,'Classificação p pessoal'!F:G,2,false) -> NP | E20: Pesquisa e desenvolvimento de nova fórmula | F20: 0.35416667 | G20: 0.52083333 | H20: 0.16666667 | I20: 44210 | J20: TRUE | L20: =IF(VLOOKUP(C20,Projetos!A:L,12,false)=TRUE,TRUE,FALSE) -> TRUE | M20: 33.159727 | N20: =IFERROR(IF(AND(J20=TRUE,O20=TRUE,YEAR(F20)<2021),H20,"")*(M20*24),0) -> 132.63891 | O20: TRUE
B21: Ana Claudia Zanini | C21: Trophic Soya 1.5 Fiber | D21: =vlookup(C21,'Classificação p pessoal'!F:G,2,false) -> NP | E21: Pesquisa basica para Produção de material cientifico | F21: 0.58333333 | G21: 0.75 | H21: 0.16666667 | I21: 44210 | J21: TRUE | L21: =IF(VLOOKUP(C21,Projetos!A:L,12,false)=TRUE,TRUE,FALSE) -> TRUE | M21: 33.159727 | N21: =IFERROR(IF(AND(J21=TRUE,O21=TRUE,YEAR(F21)<2021),H21,"")*(M21*24),0) -> 132.63891 | O21: TRUE
B22: Ana Claudia Zanini | C22: Trophic Soya 1.5 Fiber | D22: =vlookup(C22,'Classificação p pessoal'!F:G,2,false) -> NP | E22: Pesquisa basica para Produção de material cientifico | F22: 0.35416667 | G22: 0.4375 | H22: 0.083333333 | I22: 44211 | J22: TRUE | L22: =IF(VLOOKUP(C22,Projetos!A:L,12,false)=TRUE,TRUE,FALSE) -> TRUE | M22: 33.159727 | N22: =IFERROR(IF(AND(J22=TRUE,O22=TRUE,YEAR(F22)<2021),H22,"")*(M22*24),0) -> 66.319455 | O22: TRUE
B23: Ana Claudia Zanini | C23: Trophic Junior Líquido 1.0 (ARB) | D23: =vlookup(C23,'Classificação p pessoal'!F:G,2,false) -> NP | E23: Pesquisa e desenvolvimento de nova fórmula | F23: 0.54166667 | G23: 0.75 | H23: 0.20833333 | I23: 44214 | J23: TRUE | L23: =IF(VLOOKUP(C23,Projetos!A:L,12,false)=TRUE,TRUE,FALSE) -> TRUE | M23: 33.159727 | N23: =IFERROR(IF(AND(J23=TRUE,O23=TRUE,YEAR(F23)<2021),H23,"")*(M23*24),0) -> 165.79864 | O23: TRUE
B24: Ana Claudia Zanini | C24: Suplemento hiperproteico líquido | D24: =vlookup(C24,'Classificação p pessoal'!F:G,2,false) -> NP | E24: Pesquisa e desenvolvimento de nova fórmula | F24: 0.35416667 | G24: 0.5625 | H24: 0.20833333 | I24: 44215 | J24: TRUE | L24: =IF(VLOOKUP(C24,Projetos!A:L,12,false)=TRUE,TRUE,FALSE) -> TRUE | M24: 33.159727 | N24: =IFERROR(IF(AND(J24=TRUE,O24=TRUE,YEAR(F24)<2021),H24,"")*(M24*24),0) -> 165.79864 | O24: TRUE
B25: Ana Claudia Zanini | C25: Suplemento hiperproteico líquido | D25: =vlookup(C25,'Classificação p pessoal'!F:G,2,false) -> NP | E25: Pesquisa e desenvolvimento de nova fórmula | F25: 0.35416667 | G25: 0.54166667 | H25: 0.1875 | I25: 44216 | J25: TRUE | L25: =IF(VLOOKUP(C25,Projetos!A:L,12,false)=TRUE,TRUE,FALSE) -> TRUE | M25: 33.159727 | N25: =IFERROR(IF(AND(J25=TRUE,O25=TRUE,YEAR(F25)<2021),H25,"")*(M25*24),0) -> 149.21877 | O25: TRUE
B26: Ana Claudia Zanini | C26: Diamax IG | E26: Desenvolvimento de comunicação da fórmula do produto | F26: 0.5625 | G26: 0.75 | H26: 0.1875 | I26: 44217 | J26: FALSE | K26: Não entra | L26: =IF(VLOOKUP(C26,Projetos!A:L,12,false)=TRUE,TRUE,FALSE) -> TRUE | M26: 33.159727 | N26: =IFERROR(IF(AND(J26=TRUE,O26=TRUE,YEAR(F26)<2021),H26,"")*(M26*24),0) -> 0 | O26: TRUE
B27: Ana Claudia Zanini | C27: Diamax IG | E27: Desenvolvimento de comunicação da fórmula do produto | F27: 0.52083333 | G27: 0.75 | H27: 0.22916667 | I27: 44218 | J27: FALSE | K27: Não entra | L27: =IF(VLOOKUP(C27,Projetos!A:L,12,false)=TRUE,TRUE,FALSE) -> TRUE | M27: 33.159727 | N27: =IFERROR(IF(AND(J27=TRUE,O27=TRUE,YEAR(F27)<2021),H27,"")*(M27*24),0) -> 0 | O27: TRUE
B28: Ana Claudia Zanini | C28: Diamax IG | E28: Desenvolvimento de comunicação da fórmula do produto | F28: 0.34375 | G28: 0.54166667 | H28: 0.19791667 | I28: 44221 | J28: FALSE | K28: Não entra | L28: =IF(VLOOKUP(C28,Projetos!A:L,12,false)=TRUE,TRUE,FALSE) -> TRUE | M28: 33.159727 | N28: =IFERROR(IF(AND(J28=TRUE,O28=TRUE,YEAR(F28)<2021),H28,"")*(M28*24),0) -> 0 | O28: TRUE
B29: Ana Claudia Zanini | C29: Suplemento hiperproteico líquido | D29: =vlookup(C29,'Classificação p pessoal'!F:G,2,false) -> NP | E29: Pesquisa e desenvolvimento de nova fórmula | F29: 0.58333333 | G29: 0.75 | H29: 0.16666667 | I29: 44221 | J29: TRUE | L29: =IF(VLOOKUP(C29,Projetos!A:L,12,false)=TRUE,TRUE,FALSE) -> TRUE | M29: 33.159727 | N29: =IFERROR(IF(AND(J29=TRUE,O29=TRUE,YEAR(F29)<2021),H29,"")*(M29*24),0) -> 132.63891 | O29: TRUE
B30: Ana Claudia Zanini | C30: Suplemento hiperproteico líquido | D30: =vlookup(C30,'Classificação p pessoal'!F:G,2,false) -> NP | E30: Pesquisa e desenvolvimento de nova fórmula | F30: 0.34375 | G30: 0.54166667 | H30: 0.19791667 | I30: 44222 | J30: TRUE | L30: =IF(VLOOKUP(C30,Projetos!A:L,12,false)=TRUE,TRUE,FALSE) -> TRUE | M30: 33.159727 | N30: =IFERROR(IF(AND(J30=TRUE,O30=TRUE,YEAR(F30)<2021),H30,"")*(M30*24),0) -> 157.5087 | O30: TRUE
B31: Ana Claudia Zanini | C31: Diamax IG | E31: Desenvolvimento de comunicação da fórmula do produto | F31: 0.58333333 | G31: 0.75 | H31: 0.16666667 | I31: 44222 | J31: FALSE | K31: Não entra | L31: =IF(VLOOKUP(C31,Projetos!A:L,12,false)=TRUE,TRUE,FALSE) -> TRUE | M31: 33.159727 | N31: =IFERROR(IF(AND(J31=TRUE,O31=TRUE,YEAR(F31)<2021),H31,"")*(M31*24),0) -> 0 | O31: TRUE
B32: Ana Claudia Zanini | C32: Suplemento hiperproteico líquido | D32: =vlookup(C32,'Classificação p pessoal'!F:G,2,false) -> NP | E32: Pesquisa e desenvolvimento de nova fórmula | F32: 0.34375 | G32: 0.54166667 | H32: 0.19791667 | I32: 44223 | J32: TRUE | L32: =IF(VLOOKUP(C32,Projetos!A:L,12,false)=TRUE,TRUE,FALSE) -> TRUE | M32: 33.159727 | N32: =IFERROR(IF(AND(J32=TRUE,O32=TRUE,YEAR(F32)<2021),H32,"")*(M32*24),0) -> 157.5087 | O32: TRUE
B33: Ana Claudia Zanini | C33: Suplemento hiperproteico líquido | D33: =vlookup(C33,'Classificação p pessoal'!F:G,2,false) -> NP | E33: Pesquisa e desenvolvimento de nova fórmula | F33: 0.34375 | G33: 0.54166667 | H33: 0.19791667 | I33: 44224 | J33: TRUE | L33: =IF(VLOOKUP(C33,Projetos!A:L,12,false)=TRUE,TRUE,FALSE) -> TRUE | M33: 33.159727 | N33: =IFERROR(IF(AND(J33=TRUE,O33=TRUE,YEAR(F33)<2021),H33,"")*(M33*24),0) -> 157.5087 | O33: TRUE
B34: Ana Claudia Zanini | C34: Suplemento hiperproteico líquido | D34: =vlookup(C34,'Classificação p pessoal'!F:G,2,false) -> NP | E34: Pesquisa e desenvolvimento de nova fórmula | F34: 0.34375 | G34: 0.41666667 | H34: 0.072916667 | I34: 44225 | J34: TRUE | L34: =IF(VLOOKUP(C34,Projetos!A:L,12,false)=TRUE,TRUE,FALSE) -> TRUE | M34: 33.159727 | N34: =IFERROR(IF(AND(J34=TRUE,O34=TRUE,YEAR(F34)<2021),H34,"")*(M34*24),0) -> 58.029523 | O34: TRUE
B35: Ana Claudia Zanini | C35: Trophic Soya 1.5 Fiber | D35: =vlookup(C35,'Classificação p pessoal'!F:G,2,false) -> NP | E35: Pesquisa basica para Produção de material cientifico | F35: 0.5 | G35: 0.70833333 | H35: 0.20833333 | I35: 44225 | J35: TRUE | L35: =IF(VLOOKUP(C35,Projetos!A:L,12,false)=TRUE,TRUE,FALSE) -> TRUE | M35: 33.159727 | N35: =IFERROR(IF(AND(J35=TRUE,O35=TRUE,YEAR(F35)<2021),H35,"")*(M35*24),0) -> 165.79864 | O35: TRUE
B36: Ana Claudia Zanini | C36: Trophic Soya 1.5 Fiber | D36: =vlookup(C36,'Classificação p pessoal'!F:G,2,false) -> NP | E36: Pesquisa basica para Produção de material cientifico | F36: 0.35416667 | G36: 0.52083333 | H36: 0.16666667 | I36: 44228 | J36: TRUE | L36: =IF(VLOOKUP(C36,Projetos!A:L,12,false)=TRUE,TRUE,FALSE) -> TRUE | M36: 33.159727 | N36: =IFERROR(IF(AND(J36=TRUE,O36=TRUE,YEAR(F36)<2021),H36,"")*(M36*24),0) -> 132.63891 | O36: TRUE
B37: Ana Claudia Zanini | C37: Trophic Junior Líquido 1.0 (ARB) | D37: =vlookup(C37,'Classificação p pessoal'!F:G,2,false) -> NP | E37: Pesquisa e desenvolvimento de nova fórmula | F37: 0.625 | G37: 0.75 | H37: 0.125 | I37: 44228 | J37: TRUE | L37: =IF(VLOOKUP(C37,Projetos!A:L,12,false)=TRUE,TRUE,FALSE) -> TRUE | M37: 33.159727 | N37: =IFERROR(IF(AND(J37=TRUE,O37=TRUE,YEAR(F37)<2021),H37,"")*(M37*24),0) -> 99.479182 | O37: TRUE
B38: Ana Claudia Zanini | C38: Trophic Junior Líquido 1.0 (ARB) | D38: =vlookup(C38,'Classificação p pessoal'!F:G,2,false) -> NP | E38: Pesquisa e desenvolvimento de nova fórmula | F38: 0.34375 | G38: 0.55208333 | H38: 0.20833333 | I38: 44229 | J38: TRUE | L38: =IF(VLOOKUP(C38,Projetos!A:L,12,false)=TRUE,TRUE,FALSE) -> TRUE | M38: 33.159727 | N38: =IFERROR(IF(AND(J38=TRUE,O38=TRUE,YEAR(F38)<2021),H38,"")*(M38*24),0) -> 165.79864 | O38: TRUE
B39: Ana Claudia Zanini | C39: Trophic Junior Líquido 1.0 (ARB) | D39: =vlookup(C39,'Classificação p pessoal'!F:G,2,false) -> NP | E39: Pesquisa e desenvolvimento de nova fórmula | F39: 0.34375 | G39: 0.46875 | H39: 0.125 | I39: 44230 | J39: TRUE | L39: =IF(VLOOKUP(C39,Projetos!A:L,12,false)=TRUE,TRUE,FALSE) -> TRUE | M39: 33.159727 | N39: =IFERROR(IF(AND(J39=TRUE,O39=TRUE,YEAR(F39)<2021),H39,"")*(M39*24),0) -> 99.479182 | O39: TRUE
B40: Ana Claudia Zanini | C40: Trophic Soya 1.5 Fiber | D40: =vlookup(C40,'Classificação p pessoal'!F:G,2,false) -> NP | E40: Pesquisa basica para Produção de material cientifico | F40: 0.625 | G40: 0.75 | H40: 0.125 | I40: 44230 | J40: TRUE | L40: =IF(VLOOKUP(C40,Projetos!A:L,12,false)=TRUE,TRUE,FALSE) -> TRUE | M40: 33.159727 | N40: =IFERROR(IF(AND(J40=TRUE,O40=TRUE,YEAR(F40)<2021),H40,"")*(M40*24),0) -> 99.479182 | O40: TRUE
B41: Ana Claudia Zanini | C41: Trophic Soya 1.5 Fiber | D41: =vlookup(C41,'Classificação p pessoal'!F:G,2,false) -> NP | E41: Pesquisa basica para Produção de material cientifico | F41: 0.34375 | G41: 0.46875 | H41: 0.125 | I41: 44231 | J41: TRUE | L41: =IF(VLOOKUP(C41,Projetos!A:L,12,false)=TRUE,TRUE,FALSE) -> TRUE | M41: 33.159727 | N41: =IFERROR(IF(AND(J41=TRUE,O41=TRUE,YEAR(F41)<2021),H41,"")*(M41*24),0) -> 99.479182 | O41: TRUE
B42: Ana Claudia Zanini | C42: Trophic Junior Líquido 1.0 (ARB) | D42: =vlookup(C42,'Classificação p pessoal'!F:G,2,false) -> NP | E42: Pesquisa e desenvolvimento de nova fórmula | F42: 0.58333333 | G42: 0.75 | H42: 0.16666667 | I42: 44231 | J42: TRUE | L42: =IF(VLOOKUP(C42,Projetos!A:L,12,false)=TRUE,TRUE,FALSE) -> TRUE | M42: 33.159727 | N42: =IFERROR(IF(AND(J42=TRUE,O42=TRUE,YEAR(F42)<2021),H42,"")*(M42*24),0) -> 132.63891 | O42: TRUE
B43: Ana Claudia Zanini | C43: Trophic Junior Líquido 1.0 (ARB) | D43: =vlookup(C43,'Classificação p pessoal'!F:G,2,false) -> NP | E43: Pesquisa e desenvolvimento de nova fórmula | F43: 0.35416667 | G43: 0.54166667 | H43: 0.1875 | I43: 44232 | J43: TRUE | L43: =IF(VLOOKUP(C43,Projetos!A:L,12,false)=TRUE,TRUE,FALSE) -> TRUE | M43: 33.159727 | N43: =IFERROR(IF(AND(J43=TRUE,O43=TRUE,YEAR(F43)<2021),H43,"")*(M43*24),0) -> 149.21877 | O43: TRUE
... B127: Ana Claudia Zanini | C127: Sachê | D127: =vlookup(C127,'Classificação p pessoal'!F:G,2,false) -> MProduto | E127: Pesquisa basica para Produção de material cientifico | F127: 0.45833333 | G127: 0.58333333 | H127: 0.125 | I127: 44323 | J127: TRUE | L127: =IF(VLOOKUP(C127,Projetos!A:L,12,false)=TRUE,TRUE,FALSE) -> TRUE | M127: 33.159727 | N127: =IFERROR(IF(AND(J127=TRUE,O127=TRUE,YEAR(F127)<2021),H127,"")*(M127*24),0) -> 99.479182 | O127: TRUE
B128: Ana Claudia Zanini | C128: Bemmax sabor neutro | E128: Produção de material cientifico | F128: 0.375 | G128: 0.45833333 | H128: 0.083333333 | I128: 44326 | J128: FALSE | K128: Não entra | L128: =IF(VLOOKUP(C128,Projetos!A:L,12,false)=TRUE,TRUE,FALSE) -> TRUE | M128: 33.159727 | N128: =IFERROR(IF(AND(J128=TRUE,O128=TRUE,YEAR(F128)<2021),H128,"")*(M128*24),0) -> 0 | O128: TRUE
B129: Ana Claudia Zanini | C129: Retort (Sistema Fechado) | D129: =vlookup(C129,'Classificação p pessoal'!F:G,2,false) -> NP | E129: Análise de composição de novo produto | F129: 0.41666667 | G129: 0.45833333 | H129: 0.041666667 | I129: 44327 | J129: TRUE | L129: =IF(VLOOKUP(C129,Projetos!A:L,12,false)=TRUE,TRUE,FALSE) -> TRUE | M129: 33.159727 | N129: =IFERROR(IF(AND(J129=TRUE,O129=TRUE,YEAR(F129)<2021),H129,"")*(M129*24),0) -> 33.159727 | O129: TRUE
B130: Ana Claudia Zanini | C130: Diamax IG | D130: =vlookup(C130,'Classificação p pessoal'!F:G,2,false) -> MProduto | E130: Pesquisa basica para Produção de material cientifico | F130: 0.58333333 | G130: 0.75 | H130: 0.16666667 | I130: 44327 | J130: TRUE | L130: =IF(VLOOKUP(C130,Projetos!A:L,12,false)=TRUE,TRUE,FALSE) -> TRUE | M130: 33.159727 | N130: =IFERROR(IF(AND(J130=TRUE,O130=TRUE,YEAR(F130)<2021),H130,"")*(M130*24),0) -> 132.63891 | O130: TRUE
B131: Ana Claudia Zanini | C131: Diamax IG | D131: =vlookup(C131,'Classificação p pessoal'!F:G,2,false) -> MProduto | E131: Pesquisa basica para Produção de material cientifico | F131: 0.34375 | G131: 0.55208333 | H131: 0.20833333 | I131: 44328 | J131: TRUE | L131: =IF(VLOOKUP(C131,Projetos!A:L,12,false)=TRUE,TRUE,FALSE) -> TRUE | M131: 33.159727 | N131: =IFERROR(IF(AND(J131=TRUE,O131=TRUE,YEAR(F131)<2021),H131,"")*(M131*24),0) -> 165.79864 | O131: TRUE
B132: Ana Claudia Zanini | C132: Bemmax sabor neutro | E132: Produção de material cientifico | F132: 0.625 | G132: 0.66666667 | H132: 0.041666667 | I132: 44328 | J132: FALSE | K132: Não entra | L132: =IF(VLOOKUP(C132,Projetos!A:L,12,false)=TRUE,TRUE,FALSE) -> TRUE | M132: 33.159727 | N132: =IFERROR(IF(AND(J132=TRUE,O132=TRUE,YEAR(F132)<2021),H132,"")*(M132*24),0) -> 0 | O132: TRUE
B133: Ana Claudia Zanini | C133: Diamax IG | D133: =vlookup(C133,'Classificação p pessoal'!F:G,2,false) -> MProduto | E133: Pesquisa basica para Produção de material cientifico | F133: 0.54166667 | G133: 0.75 | H133: 0.20833333 | I133: 44329 | J133: TRUE | L133: =IF(VLOOKUP(C133,Projetos!A:L,12,false)=TRUE,TRUE,FALSE) -> TRUE | M133: 33.159727 | N133: =IFERROR(IF(AND(J133=TRUE,O133=TRUE,YEAR(F133)<2021),H133,"")*(M133*24),0) -> 165.79864 | O133: TRUE
B134: Ana Claudia Zanini | C134: Suplemento hiperproteico líquido | D134: =vlookup(C134,'Classificação p pessoal'!F:G,2,false) -> NP | E134: Pesquisa e desenvolvimento de nova fórmula | F134: 0.45833333 | G134: 0.5 | H134: 0.041666667 | I134: 44329 | J134: TRUE | L134: =IF(VLOOKUP(C134,Projetos!A:L,12,false)=TRUE,TRUE,FALSE) -> TRUE | M134: 33.159727 | N134: =IFERROR(IF(AND(J134=TRUE,O134=TRUE,YEAR(F134)<2021),H134,"")*(M134*24),0) -> 33.159727 | O134: TRUE
B135: Ana Claudia Zanini | C135: Diamax IG | D135: =vlookup(C135,'Classificação p pessoal'!F:G,2,false) -> MProduto | E135: Pesquisa e desenvolvimento de nova fórmula | F135: 0.35416667 | G135: 0.54166667 | H135: 0.1875 | I135: 44330 | J135: TRUE | L135: =IF(VLOOKUP(C135,Projetos!A:L,12,false)=TRUE,TRUE,FALSE) -> TRUE | M135: 33.159727 | N135: =IFERROR(IF(AND(J135=TRUE,O135=TRUE,YEAR(F135)<2021),H135,"")*(M135*24),0) -> 149.21877 | O135: TRUE
B136: Ana Claudia Zanini | C136: Retort (Sistema Fechado) | D136: =vlookup(C136,'Classificação p pessoal'!F:G,2,false) -> NP | E136: Análise de composição de novo produto | F136: 0.58333333 | G136: 0.625 | H136: 0.041666667 | I136: 44330 | J136: TRUE | L136: =IF(VLOOKUP(C136,Projetos!A:L,12,false)=TRUE,TRUE,FALSE) -> TRUE | M136: 33.159727 | N136: =IFERROR(IF(AND(J136=TRUE,O136=TRUE,YEAR(F136)<2021),H136,"")*(M136*24),0) -> 33.159727 | O136: TRUE
B137: Ana Claudia Zanini | C137: Bemmax sabor neutro | E137: Produção de material cientifico | F137: 0.625 | G137: 0.66666667 | H137: 0.041666667 | I137: 44330 | J137: FALSE | K137: Não entra | L137: =IF(VLOOKUP(C137,Projetos!A:L,12,false)=TRUE,TRUE,FALSE) -> TRUE | M137: 33.159727 | N137: =IFERROR(IF(AND(J137=TRUE,O137=TRUE,YEAR(F137)<2021),H137,"")*(M137*24),0) -> 0 | O137: TRUE
B138: Ana Claudia Zanini | C138: Diamax IG | D138: =vlookup(C138,'Classificação p pessoal'!F:G,2,false) -> MProduto | E138: Pesquisa basica para Produção de material cientifico | F138: 0.35416667 | G138: 0.54166667 | H138: 0.1875 | I138: 44333 | J138: TRUE | L138: =IF(VLOOKUP(C138,Projetos!A:L,12,false)=TRUE,TRUE,FALSE) -> TRUE | M138: 33.159727 | N138: =IFERROR(IF(AND(J138=TRUE,O138=TRUE,YEAR(F138)<2021),H138,"")*(M138*24),0) -> 149.21877 | O138: TRUE
B139: Ana Claudia Zanini | C139: Diamax IG | D139: =vlookup(C139,'Classificação p pessoal'!F:G,2,false) -> MProduto | E139: Pesquisa basica para Produção de material cientifico | F139: 0.41666667 | G139: 0.54166667 | H139: 0.125 | I139: 44334 | J139: TRUE | L139: =IF(VLOOKUP(C139,Projetos!A:L,12,false)=TRUE,TRUE,FALSE) -> TRUE | M139: 33.159727 | N139: =IFERROR(IF(AND(J139=TRUE,O139=TRUE,YEAR(F139)<2021),H139,"")*(M139*24),0) -> 99.479182 | O139: TRUE
B140: Ana Claudia Zanini | C140: Retort (Sistema Fechado) | D140: =vlookup(C140,'Classificação p pessoal'!F:G,2,false) -> NP | E140: Pesquisa e desenvolvimento de nova fórmula | F140: 0.625 | G140: 0.75 | H140: 0.125 | I140: 44334 | J140: TRUE | L140: =IF(VLOOKUP(C140,Projetos!A:L,12,false)=TRUE,TRUE,FALSE) -> TRUE | M140: 33.159727 | N140: =IFERROR(IF(AND(J140=TRUE,O140=TRUE,YEAR(F140)<2021),H140,"")*(M140*24),0) -> 99.479182 | O140: TRUE
B141: Ana Claudia Zanini | C141: Bemmax sabor neutro | E141: Produção de material cientifico | F141: 0.58333333 | G141: 0.625 | H141: 0.041666667 | I141: 44334 | J141: FALSE | K141: Não entra | L141: =IF(VLOOKUP(C141,Projetos!A:L,12,false)=TRUE,TRUE,FALSE) -> TRUE | M141: 33.159727 | N141: =IFERROR(IF(AND(J141=TRUE,O141=TRUE,YEAR(F141)<2021),H141,"")*(M141*24),0) -> 0 | O141: TRUE
B142: Ana Claudia Zanini | C142: Bemmax sabor neutro | E142: Produção de material cientifico | F142: 0.625 | G142: 0.66666667 | H142: 0.041666667 | I142: 44335 | J142: FALSE | K142: Não entra | L142: =IF(VLOOKUP(C142,Projetos!A:L,12,false)=TRUE,TRUE,FALSE) -> TRUE | M142: 33.159727 | N142: =IFERROR(IF(AND(J142=TRUE,O142=TRUE,YEAR(F142)<2021),H142,"")*(M142*24),0) -> 0 | O142: TRUE
B143: Ana Claudia Zanini | C143: Retort (Sistema Fechado) | D143: =vlookup(C143,'Classificação p pessoal'!F:G,2,false) -> NP | E143: Pesquisa e desenvolvimento de nova fórmula | F143: 0.35416667 | G143: 0.54166667 | H143: 0.1875 | I143: 44336 | J143: TRUE | L143: =IF(VLOOKUP(C143,Projetos!A:L,12,false)=TRUE,TRUE,FALSE) -> TRUE | M143: 33.159727 | N143: =IFERROR(IF(AND(J143=TRUE,O143=TRUE,YEAR(F143)<2021),H143,"")*(M143*24),0) -> 149.21877 | O143: TRUE
B144: Ana Claudia Zanini | C144: Diamax IG | D144: =vlookup(C144,'Classificação p pessoal'!F:G,2,false) -> MProduto | E144: Pesquisa basica para Produção de material cientifico | F144: 0.47916667 | G144: 0.54166667 | H144: 0.0625 | I144: 44337 | J144: TRUE | L144: =IF(VLOOKUP(C144,Projetos!A:L,12,false)=TRUE,TRUE,FALSE) -> TRUE | M144: 33.159727 | N144: =IFERROR(IF(AND(J144=TRUE,O144=TRUE,YEAR(F144)<2021),H144,"")*(M144*24),0) -> 49.739591 | O144: TRUE
B145: Ana Claudia Zanini | C145: Retort (Sistema Fechado) | D145: =vlookup(C145,'Classificação p pessoal'!F:G,2,false) -> NP | E145: Pesquisa e desenvolvimento de nova fórmula | F145: 0.625 | G145: 0.75 | H145: 0.125 | I145: 44337 | J145: TRUE | L145: =IF(VLOOKUP(C145,Projetos!A:L,12,false)=TRUE,TRUE,FALSE) -> TRUE | M145: 33.159727 | N145: =IFERROR(IF(AND(J145=TRUE,O145=TRUE,YEAR(F145)<2021),H145,"")*(M145*24),0) -> 99.479182 | O145: TRUE
B146: Ana Claudia Zanini | C146: Diamax IG | D146: =vlookup(C146,'Classificação p pessoal'!F:G,2,false) -> MProduto | E146: Pesquisa basica para Produção de material cientifico | F146: 0.58333333 | G146: 0.75 | H146: 0.16666667 | I146: 44340 | J146: TRUE | L146: =IF(VLOOKUP(C146,Projetos!A:L,12,false)=TRUE,TRUE,FALSE) -> TRUE | M146: 33.159727 | N146: =IFERROR(IF(AND(J146=TRUE,O146=TRUE,YEAR(F146)<2021),H146,"")*(M146*24),0) -> 132.63891 | O146: TRUE
B147: Ana Claudia Zanini | C147: Diamax IG | D147: =vlookup(C147,'Classificação p pessoal'!F:G,2,false) -> MProduto | E147: Pesquisa basica para Produção de material cientifico | F147: 0.58333333 | G147: 0.66666667 | H147: 0.083333333 | I147: 44341 | J147: TRUE | L147: =IF(VLOOKUP(C147,Projetos!A:L,12,false)=TRUE,TRUE,FALSE) -> TRUE | M147: 33.159727 | N147: =IFERROR(IF(AND(J147=TRUE,O147=TRUE,YEAR(F147)<2021),H147,"")*(M147*24),0) -> 66.319455 | O147: TRUE
B148: Ana Claudia Zanini | C148: Suplemento hiperproteico líquido | D148: =vlookup(C148,'Classificação p pessoal'!F:G,2,false) -> NP | E148: Pesquisa e desenvolvimento de nova fórmula | F148: 0.66666667 | G148: 0.75 | H148: 0.083333333 | I148: 44341 | J148: TRUE | L148: =IF(VLOOKUP(C148,Projetos!A:L,12,false)=TRUE,TRUE,FALSE) -> TRUE | M148: 33.159727 | N148: =IFERROR(IF(AND(J148=TRUE,O148=TRUE,YEAR(F148)<2021),H148,"")*(M148*24),0) -> 66.319455 | O148: TRUE
B149: Ana Claudia Zanini | C149: Suplemento hiperproteico líquido | D149: =vlookup(C149,'Classificação p pessoal'!F:G,2,false) -> NP | E149: Pesquisa e desenvolvimento de nova fórmula | F149: 0.66666667 | G149: 0.75 | H149: 0.083333333 | I149: 44342 | J149: TRUE | L149: =IF(VLOOKUP(C149,Projetos!A:L,12,false)=TRUE,TRUE,FALSE) -> TRUE | M149: 33.159727 | N149: =IFERROR(IF(AND(J149=TRUE,O149=TRUE,YEAR(F149)<2021),H149,"")*(M149*24),0) -> 66.319455 | O149: TRUE
B150: Ana Claudia Zanini | C150: Suplemento hiperproteico líquido | D150: =vlookup(C150,'Classificação p pessoal'!F:G,2,false) -> NP | E150: Pesquisa e desenvolvimento de nova fórmula | F150: 0.58333333 | G150: 0.66666667 | H150: 0.083333333 | I150: 44343 | J150: TRUE | L150: =IF(VLOOKUP(C150,Projetos!A:L,12,false)=TRUE,TRUE,FALSE) -> TRUE | M150: 33.159727 | N150: =IFERROR(IF(AND(J150=TRUE,O150=TRUE,YEAR(F150)<2021),H150,"")*(M150*24),0) -> 66.319455 | O150: TRUE
B151: Ana Claudia Zanini | C151: Trophic 1.5 250mL - Edge | D151: =vlookup(C151,'Classificação p pessoal'!F:G,2,false) -> NP | E151: Desenvolvimento de equipo SAMTRONIC - Teste | F151: 0.58333333 | G151: 0.75 | H151: 0.16666667 | I151: 44343 | J151: TRUE | L151: =IF(VLOOKUP(C151,Projetos!A:L,12,false)=TRUE,TRUE,FALSE) -> TRUE | M151: 33.159727 | N151: =IFERROR(IF(AND(J151=TRUE,O151=TRUE,YEAR(F151)<2021),H151,"")*(M151*24),0) -> 132.63891 | O151: TRUE
B152: Ana Claudia Zanini | C152: Trophic 1.5 250mL - Edge | D152: =vlookup(C152,'Classificação p pessoal'!F:G,2,false) -> NP | E152: Desenvolvimento de equipo SAMTRONIC - Teste | F152: 0.34375 | G152: 0.38541667 | H152: 0.041666667 | I152: 44344 | J152: TRUE | L152: =IF(VLOOKUP(C152,Projetos!A:L,12,false)=TRUE,TRUE,FALSE) -> TRUE | M152: 33.159727 | N152: =IFERROR(IF(AND(J152=TRUE,O152=TRUE,YEAR(F152)<2021),H152,"")*(M152*24),0) -> 33.159727 | O152: TRUE
B153: Ana Claudia Zanini | C153: Diamax IG | D153: =vlookup(C153,'Classificação p pessoal'!F:G,2,false) -> MProduto | E153: Pesquisa basica para Produção de material cientifico | F153: 0.34375 | G153: 0.54166667 | H153: 0.19791667 | I153: 44347 | J153: TRUE | L153: =IF(VLOOKUP(C153,Projetos!A:L,12,false)=TRUE,TRUE,FALSE) -> TRUE | M153: 33.159727 | N153: =IFERROR(IF(AND(J153=TRUE,O153=TRUE,YEAR(F153)<2021),H153,"")*(M153*24),0) -> 157.5087 | O153: TRUE
B154: Ana Claudia Zanini | C154: Retort (Sistema Fechado) | D154: =vlookup(C154,'Classificação p pessoal'!F:G,2,false) -> NP | E154: Pesquisa e desenvolvimento de nova fórmula | F154: 0.35416667 | G154: 0.52083333 | H154: 0.16666667 | I154: 44348 | J154: TRUE | L154: =IF(VLOOKUP(C154,Projetos!A:L,12,false)=TRUE,TRUE,FALSE) -> TRUE | M154: 33.159727 | N154: =IFERROR(IF(AND(J154=TRUE,O154=TRUE,YEAR(F154)<2021),H154,"")*(M154*24),0) -> 132.63891 | O154: TRUE
... B240: Ana Claudia Zanini | C240: Diamax pó | D240: =vlookup(C240,'Classificação p pessoal'!F:G,2,false) -> NP | E240: Desenvolvimento de novo produto | F240: 0.58333333 | G240: 0.66666667 | H240: 0.083333333 | I240: 44467 | J240: TRUE | L240: =IF(VLOOKUP(C240,Projetos!A:L,12,false)=TRUE,TRUE,FALSE) -> TRUE | M240: 33.159727 | N240: =IFERROR(IF(AND(J240=TRUE,O240=TRUE,YEAR(F240)<2021),H240,"")*(M240*24),0) -> 66.319455 | O240: TRUE
B241: Ana Claudia Zanini | C241: Diamax IG | E241: Pesquisa basica para elaboração de material cientifico | F241: 0.54166667 | G241: 0.75 | H241: 0.20833333 | I241: 44468 | J241: FALSE | K241: Não entra | L241: =IF(VLOOKUP(C241,Projetos!A:L,12,false)=TRUE,TRUE,FALSE) -> TRUE | M241: 33.159727 | N241: =IFERROR(IF(AND(J241=TRUE,O241=TRUE,YEAR(F241)<2021),H241,"")*(M241*24),0) -> 0 | O241: TRUE
B242: Ana Claudia Zanini | C242: Congresso ESPEN | D242: =vlookup(C242,'Classificação p pessoal'!F:G,2,false) -> NP | E242: Pesquisa Básica pós Congresso ESPEN(projeto novos produtos e novas pesquisas) | F242: 0.75 | G242: 0.83333333 | H242: 0.083333333 | I242: 44468 | J242: TRUE | L242: =IF(VLOOKUP(C242,Projetos!A:L,12,false)=TRUE,TRUE,FALSE) -> TRUE | M242: 33.159727 | N242: =IFERROR(IF(AND(J242=TRUE,O242=TRUE,YEAR(F242)<2021),H242,"")*(M242*24),0) -> 66.319455 | O242: TRUE
B243: Ana Claudia Zanini | C243: Diamax pó | D243: =vlookup(C243,'Classificação p pessoal'!F:G,2,false) -> NP | E243: Desenvolvimento de novo produto | F243: 0.54166667 | G243: 0.75 | H243: 0.20833333 | I243: 44469 | J243: TRUE | L243: =IF(VLOOKUP(C243,Projetos!A:L,12,false)=TRUE,TRUE,FALSE) -> TRUE | M243: 33.159727 | N243: =IFERROR(IF(AND(J243=TRUE,O243=TRUE,YEAR(F243)<2021),H243,"")*(M243*24),0) -> 165.79864 | O243: TRUE
B244: Ana Claudia Zanini | C244: Retort (Sistema Fechado) | D244: =vlookup(C244,'Classificação p pessoal'!F:G,2,false) -> NP | E244: Pesquisa e desenvolvimento de nova fórmula | F244: 0.58333333 | G244: 0.66666667 | H244: 0.083333333 | I244: 44470 | J244: TRUE | L244: =IF(VLOOKUP(C244,Projetos!A:L,12,false)=TRUE,TRUE,FALSE) -> TRUE | M244: 33.159727 | N244: =IFERROR(IF(AND(J244=TRUE,O244=TRUE,YEAR(F244)<2021),H244,"")*(M244*24),0) -> 66.319455 | O244: TRUE
B245: Ana Claudia Zanini | C245: Congresso ESPEN | D245: =vlookup(C245,'Classificação p pessoal'!F:G,2,false) -> NP | E245: Pesquisa Básica pós Congresso ESPEN(projeto novos produtos e novas pesquisas) | F245: 0.35416667 | G245: 0.52083333 | H245: 0.16666667 | I245: 44473 | J245: TRUE | L245: =IF(VLOOKUP(C245,Projetos!A:L,12,false)=TRUE,TRUE,FALSE) -> TRUE | M245: 33.159727 | N245: =IFERROR(IF(AND(J245=TRUE,O245=TRUE,YEAR(F245)<2021),H245,"")*(M245*24),0) -> 132.63891 | O245: TRUE
B246: Ana Claudia Zanini | C246: Retort (Sistema Fechado) | D246: =vlookup(C246,'Classificação p pessoal'!F:G,2,false) -> NP | E246: Pesquisa e desenvolvimento de nova fórmula | F246: 0.66666667 | G246: 0.75 | H246: 0.083333333 | I246: 44473 | J246: TRUE | L246: =IF(VLOOKUP(C246,Projetos!A:L,12,false)=TRUE,TRUE,FALSE) -> TRUE | M246: 33.159727 | N246: =IFERROR(IF(AND(J246=TRUE,O246=TRUE,YEAR(F246)<2021),H246,"")*(M246*24),0) -> 66.319455 | O246: TRUE
B247: Ana Claudia Zanini | C247: Congresso ESPEN | D247: =vlookup(C247,'Classificação p pessoal'!F:G,2,false) -> NP | E247: Pesquisa Básica pós Congresso ESPEN(projeto novos produtos e novas pesquisas) | F247: 0.35416667 | G247: 0.5 | H247: 0.14583333 | I247: 44474 | J247: TRUE | L247: =IF(VLOOKUP(C247,Projetos!A:L,12,false)=TRUE,TRUE,FALSE) -> TRUE | M247: 33.159727 | N247: =IFERROR(IF(AND(J247=TRUE,O247=TRUE,YEAR(F247)<2021),H247,"")*(M247*24),0) -> 116.05905 | O247: TRUE
B248: Ana Claudia Zanini | C248: Retort (Sistema Fechado) | D248: =vlookup(C248,'Classificação p pessoal'!F:G,2,false) -> NP | E248: Pesquisa e desenvolvimento de nova fórmula | F248: 0.5625 | G248: 0.6875 | H248: 0.125 | I248: 44474 | J248: TRUE | L248: =IF(VLOOKUP(C248,Projetos!A:L,12,false)=TRUE,TRUE,FALSE) -> TRUE | M248: 33.159727 | N248: =IFERROR(IF(AND(J248=TRUE,O248=TRUE,YEAR(F248)<2021),H248,"")*(M248*24),0) -> 99.479182 | O248: TRUE
B249: Ana Claudia Zanini | C249: Retort (Sistema Fechado) | D249: =vlookup(C249,'Classificação p pessoal'!F:G,2,false) -> NP | E249: Pesquisa e desenvolvimento de nova fórmula | F249: 0.35416667 | G249: 0.4375 | H249: 0.083333333 | I249: 44475 | J249: TRUE | L249: =IF(VLOOKUP(C249,Projetos!A:L,12,false)=TRUE,TRUE,FALSE) -> TRUE | M249: 33.159727 | N249: =IFERROR(IF(AND(J249=TRUE,O249=TRUE,YEAR(F249)<2021),H249,"")*(M249*24),0) -> 66.319455 | O249: TRUE
B250: Ana Claudia Zanini | C250: Trophic Junior Líquido 1.0 (ARB) | D250: =vlookup(C250,'Classificação p pessoal'!F:G,2,false) -> NP | E250: Pesquisa e desenvolvimento de nova fórmula | F250: 0.45833333 | G250: 0.54166667 | H250: 0.083333333 | I250: 44475 | J250: TRUE | L250: =IF(VLOOKUP(C250,Projetos!A:L,12,false)=TRUE,TRUE,FALSE) -> TRUE | M250: 33.159727 | N250: =IFERROR(IF(AND(J250=TRUE,O250=TRUE,YEAR(F250)<2021),H250,"")*(M250*24),0) -> 66.319455 | O250: TRUE
B251: Ana Claudia Zanini | C251: Diamax pó | D251: =vlookup(C251,'Classificação p pessoal'!F:G,2,false) -> NP | E251: Pesquisa e desenvolvimento de nova fórmula | F251: 0.58333333 | G251: 0.75 | H251: 0.16666667 | I251: 44475 | J251: TRUE | L251: =IF(VLOOKUP(C251,Projetos!A:L,12,false)=TRUE,TRUE,FALSE) -> TRUE | M251: 33.159727 | N251: =IFERROR(IF(AND(J251=TRUE,O251=TRUE,YEAR(F251)<2021),H251,"")*(M251*24),0) -> 132.63891 | O251: TRUE
B252: Ana Claudia Zanini | C252: Retort (Sistema Fechado) | D252: =vlookup(C252,'Classificação p pessoal'!F:G,2,false) -> NP | E252: Pesquisa e desenvolvimento de nova fórmula | F252: 0.35416667 | G252: 0.52083333 | H252: 0.16666667 | I252: 44476 | J252: TRUE | L252: =IF(VLOOKUP(C252,Projetos!A:L,12,false)=TRUE,TRUE,FALSE) -> TRUE | M252: 33.159727 | N252: =IFERROR(IF(AND(J252=TRUE,O252=TRUE,YEAR(F252)<2021),H252,"")*(M252*24),0) -> 132.63891 | O252: TRUE
B253: Ana Claudia Zanini | C253: Diamax pó | D253: =vlookup(C253,'Classificação p pessoal'!F:G,2,false) -> NP | E253: Pesquisa e desenvolvimento de nova fórmula | F253: 0.35416667 | G253: 0.47916667 | H253: 0.125 | I253: 44482 | J253: TRUE | L253: =IF(VLOOKUP(C253,Projetos!A:L,12,false)=TRUE,TRUE,FALSE) -> TRUE | M253: 33.159727 | N253: =IFERROR(IF(AND(J253=TRUE,O253=TRUE,YEAR(F253)<2021),H253,"")*(M253*24),0) -> 99.479182 | O253: TRUE
... B255: Ana Claudia Zanini | C255: Congresso ESPEN | D255: =vlookup(C255,'Classificação p pessoal'!F:G,2,false) -> NP | E255: Pesquisa Básica pós Congresso ESPEN(projeto novos produtos e novas pesquisas) | F255: 0.35416667 | G255: 0.41666667 | H255: 0.0625 | I255: 44483 | J255: TRUE | L255: =IF(VLOOKUP(C255,Projetos!A:L,12,false)=TRUE,TRUE,FALSE) -> TRUE | M255: 33.159727 | N255: =IFERROR(IF(AND(J255=TRUE,O255=TRUE,YEAR(F255)<2021),H255,"")*(M255*24),0) -> 49.739591 | O255: TRUE
B256: Ana Claudia Zanini | C256: Diamax IG | E256: Pesquisa basica para elaboração de material cientifico | F256: 0.54166667 | G256: 0.66666667 | H256: 0.125 | I256: 44483 | J256: FALSE | K256: Não entra | L256: =IF(VLOOKUP(C256,Projetos!A:L,12,false)=TRUE,TRUE,FALSE) -> TRUE | M256: 33.159727 | N256: =IFERROR(IF(AND(J256=TRUE,O256=TRUE,YEAR(F256)<2021),H256,"")*(M256*24),0) -> 0 | O256: TRUE
B257: Ana Claudia Zanini | C257: Diamax pó | D257: =vlookup(C257,'Classificação p pessoal'!F:G,2,false) -> NP | E257: Pesquisa e desenvolvimento de nova fórmula | F257: 0.54166667 | G257: 0.66666667 | H257: 0.125 | I257: 44484 | J257: TRUE | L257: =IF(VLOOKUP(C257,Projetos!A:L,12,false)=TRUE,TRUE,FALSE) -> TRUE | M257: 33.159727 | N257: =IFERROR(IF(AND(J257=TRUE,O257=TRUE,YEAR(F257)<2021),H257,"")*(M257*24),0) -> 99.479182 | O257: TRUE
B258: Ana Claudia Zanini | C258: Diamax IG | E258: Pesquisa basica para elaboração de material cientifico | F258: 0.66666667 | G258: 0.75 | H258: 0.083333333 | I258: 44484 | J258: FALSE | K258: Não entra | L258: =IF(VLOOKUP(C258,Projetos!A:L,12,false)=TRUE,TRUE,FALSE) -> TRUE | M258: 33.159727 | N258: =IFERROR(IF(AND(J258=TRUE,O258=TRUE,YEAR(F258)<2021),H258,"")*(M258*24),0) -> 0 | O258: TRUE
B259: Ana Claudia Zanini | C259: Retort (Sistema Fechado) | D259: =vlookup(C259,'Classificação p pessoal'!F:G,2,false) -> NP | E259: Pesquisa e desenvolvimento de nova fórmula | F259: 0.35416667 | G259: 0.54166667 | H259: 0.1875 | I259: 44509 | J259: TRUE | L259: =IF(VLOOKUP(C259,Projetos!A:L,12,false)=TRUE,TRUE,FALSE) -> TRUE | M259: 33.159727 | N259: =IFERROR(IF(AND(J259=TRUE,O259=TRUE,YEAR(F259)<2021),H259,"")*(M259*24),0) -> 149.21877 | O259: TRUE
B260: Ana Claudia Zanini | C260: Retort (Sistema Fechado) | D260: =vlookup(C260,'Classificação p pessoal'!F:G,2,false) -> NP | E260: Pesquisa e desenvolvimento de nova fórmula | F260: 0.35416667 | G260: 0.54166667 | H260: 0.1875 | I260: 44510 | J260: TRUE | L260: =IF(VLOOKUP(C260,Projetos!A:L,12,false)=TRUE,TRUE,FALSE) -> TRUE | M260: 33.159727 | N260: =IFERROR(IF(AND(J260=TRUE,O260=TRUE,YEAR(F260)<2021),H260,"")*(M260*24),0) -> 149.21877 | O260: TRUE
B261: Ana Claudia Zanini | C261: Retort (Sistema Fechado) | D261: =vlookup(C261,'Classificação p pessoal'!F:G,2,false) -> NP | E261: Pesquisa e desenvolvimento de nova fórmula | F261: 0.35416667 | G261: 0.54166667 | H261: 0.1875 | I261: 44511 | J261: TRUE | L261: =IF(VLOOKUP(C261,Projetos!A:L,12,false)=TRUE,TRUE,FALSE) -> TRUE | M261: 33.159727 | N261: =IFERROR(IF(AND(J261=TRUE,O261=TRUE,YEAR(F261)<2021),H261,"")*(M261*24),0) -> 149.21877 | O261: TRUE
B262: Ana Claudia Zanini | C262: Retort (Sistema Fechado) | D262: =vlookup(C262,'Classificação p pessoal'!F:G,2,false) -> NP | E262: Pesquisa e desenvolvimento de nova fórmula | F262: 0.35416667 | G262: 0.54166667 | H262: 0.1875 | I262: 44512 | J262: TRUE | L262: =IF(VLOOKUP(C262,Projetos!A:L,12,false)=TRUE,TRUE,FALSE) -> TRUE | M262: 33.159727 | N262: =IFERROR(IF(AND(J262=TRUE,O262=TRUE,YEAR(F262)<2021),H262,"")*(M262*24),0) -> 149.21877 | O262: TRUE
B263: Ana Claudia Zanini | C263: Retort (Sistema Fechado) | D263: =vlookup(C263,'Classificação p pessoal'!F:G,2,false) -> NP | E263: Pesquisa e desenvolvimento de nova fórmula | F263: 0.375 | G263: 0.54166667 | H263: 0.16666667 | I263: 44517 | J263: TRUE | L263: =IF(VLOOKUP(C263,Projetos!A:L,12,false)=TRUE,TRUE,FALSE) -> TRUE | M263: 33.159727 | N263: =IFERROR(IF(AND(J263=TRUE,O263=TRUE,YEAR(F263)<2021),H263,"")*(M263*24),0) -> 132.63891 | O263: TRUE
B264: Ana Claudia Zanini | C264: Retort (Sistema Fechado) | D264: =vlookup(C264,'Classificação p pessoal'!F:G,2,false) -> NP | E264: Pesquisa e desenvolvimento de nova fórmula | F264: 0.58333333 | G264: 0.75 | H264: 0.16666667 | I264: 44525 | J264: TRUE | L264: =IF(VLOOKUP(C264,Projetos!A:L,12,false)=TRUE,TRUE,FALSE) -> TRUE | M264: 33.159727 | N264: =IFERROR(IF(AND(J264=TRUE,O264=TRUE,YEAR(F264)<2021),H264,"")*(M264*24),0) -> 132.63891 | O264: TRUE
B265: Ana Claudia Zanini | C265: Diamax pó | D265: =vlookup(C265,'Classificação p pessoal'!F:G,2,false) -> NP | E265: Pesquisa e desenvolvimento de nova fórmula | F265: 0.58333333 | G265: 0.75 | H265: 0.16666667 | I265: 44526 | J265: TRUE | L265: =IF(VLOOKUP(C265,Projetos!A:L,12,false)=TRUE,TRUE,FALSE) -> TRUE | M265: 33.159727 | N265: =IFERROR(IF(AND(J265=TRUE,O265=TRUE,YEAR(F265)<2021),H265,"")*(M265*24),0) -> 132.63891 | O265: TRUE
B266: Ana Claudia Zanini | C266: Retort (Sistema Fechado) | D266: =vlookup(C266,'Classificação p pessoal'!F:G,2,false) -> NP | E266: Pesquisa e desenvolvimento de nova fórmula | F266: 0.58333333 | G266: 0.66666667 | H266: 0.083333333 | I266: 44529 | J266: TRUE | L266: =IF(VLOOKUP(C266,Projetos!A:L,12,false)=TRUE,TRUE,FALSE) -> TRUE | M266: 33.159727 | N266: =IFERROR(IF(AND(J266=TRUE,O266=TRUE,YEAR(F266)<2021),H266,"")*(M266*24),0) -> 66.319455 | O266: TRUE
B267: Ana Claudia Zanini | C267: Diamax pó | D267: =vlookup(C267,'Classificação p pessoal'!F:G,2,false) -> NP | E267: Pesquisa e desenvolvimento de nova fórmula | F267: 0.625 | G267: 0.75 | H267: 0.125 | I267: 44530 | J267: TRUE | L267: =IF(VLOOKUP(C267,Projetos!A:L,12,false)=TRUE,TRUE,FALSE) -> TRUE | M267: 33.159727 | N267: =IFERROR(IF(AND(J267=TRUE,O267=TRUE,YEAR(F267)<2021),H267,"")*(M267*24),0) -> 99.479182 | O267: TRUE
B268: Ana Claudia Zanini | C268: Diamax pó | D268: =vlookup(C268,'Classificação p pessoal'!F:G,2,false) -> NP | E268: Pesquisa e desenvolvimento de nova fórmula | F268: 0.375 | G268: 0.5 | H268: 0.125 | I268: 44537 | J268: TRUE | L268: =IF(VLOOKUP(C268,Projetos!A:L,12,false)=TRUE,TRUE,FALSE) -> TRUE | M268: 33.159727 | N268: =IFERROR(IF(AND(J268=TRUE,O268=TRUE,YEAR(F268)<2021),H268,"")*(M268*24),0) -> 99.479182 | O268: TRUE
B269: Ana Claudia Zanini | C269: Diamax pó | D269: =vlookup(C269,'Classificação p pessoal'!F:G,2,false) -> NP | E269: Pesquisa e desenvolvimento de nova fórmula | F269: 0.66666667 | G269: 0.75 | H269: 0.083333333 | I269: 44546 | J269: TRUE | L269: =IF(VLOOKUP(C269,Projetos!A:L,12,false)=TRUE,TRUE,FALSE) -> TRUE | M269: 33.159727 | N269: =IFERROR(IF(AND(J269=TRUE,O269=TRUE,YEAR(F269)<2021),H269,"")*(M269*24),0) -> 66.319455 | O269: TRUE
B270: Ana Claudia Zanini | C270: Diamax pó | D270: =vlookup(C270,'Classificação p pessoal'!F:G,2,false) -> NP | E270: Pesquisa e desenvolvimento de nova fórmula | F270: 0.58333333 | G270: 0.66666667 | H270: 0.083333333 | I270: 44551 | J270: TRUE | L270: =IF(VLOOKUP(C270,Projetos!A:L,12,false)=TRUE,TRUE,FALSE) -> TRUE | M270: 33.159727 | N270: =IFERROR(IF(AND(J270=TRUE,O270=TRUE,YEAR(F270)<2021),H270,"")*(M270*24),0) -> 66.319455 | O270: TRUE
...

Sheet Cópia de Timesheet
A2: Timesheet | N2: =SUMPRODUCT(H16:H4641,M16:M4597) -> #VALUE!
A3: BENEFÍCIO FISCAL DE PD&I 2021 | M3: Parcial | N3: =N5-N4 -> 356413.4
M4: Exclusivo | N4: =IFERROR(__xludf.DUMMYFUNCTION("SUMIF($B$7:$B4641,FILTER(Pessoal!$A$9:$A$18,Pessoal!$U$9:$U$18 = ""Exclusivo"",MATCH(Pessoal!$A$9:$A$18,FILTER(Pessoal!$A$29:$A$40,Pessoal!$U$29:$U$40 = TRUE),0)),$N$7:$N4641)"),0.0) -> 0
M5: TOTAL | N5: =SUM(N7:N4641) -> 356413.4
A6: Cod | B6: Pessoa | C6: Projeto | E6: Descrição | F6: Start | G6: End | H6: Tempo aplicado | I6: Data | J6: Atividade incentivada | L6: Attachments | M6: Valor (R$) | N6: Custo | O6: checkprojetos
B7: Ana Claudia Zanini | C7: Trophic Soya 1.5 Fiber | D7: =vlookup(C7,'Classificação p pessoal'!F:G,2,false) -> NP | E7: Pesquisa basica para Produção de material cientifico | F7: 0.5625 | G7: 0.75 | H7: 0.1875 | I7: 44200 | J7: TRUE | L7: =IF(VLOOKUP(C7,Projetos!A:L,12,false)=TRUE,TRUE,FALSE) -> TRUE | M7: {=VLOOKUP(B7:B4641,Pessoal!$A$28:$R$40,MONTH(F7:F4641)+6,false)} -> 33.159727 | N7: =IFERROR(IF(AND(J7=TRUE,O7=TRUE,YEAR(F7)<2021),H7,"")*(M7*24),0) -> 149.21877 | O7: {=VLOOKUP(C7:C4641,Projetos!A6:L4641,12,false)} -> TRUE
B8: Ana Claudia Zanini | C8: Trophic Soya 1.5 Fiber | D8: =vlookup(C8,'Classificação p pessoal'!F:G,2,false) -> NP | E8: Pesquisa basica para Produção de material cientifico | F8: 0.34375 | G8: 0.51041667 | H8: 0.16666667 | I8: 44201 | J8: TRUE | L8: =IF(VLOOKUP(C8,Projetos!A:L,12,false)=TRUE,TRUE,FALSE) -> TRUE | M8: 33.159727 | N8: =IFERROR(IF(AND(J8=TRUE,O8=TRUE,YEAR(F8)<2021),H8,"")*(M8*24),0) -> 132.63891 | O8: TRUE
B9: Ana Claudia Zanini | C9: Suplemento hiperproteico líquido | D9: =vlookup(C9,'Classificação p pessoal'!F:G,2,false) -> NP | E9: Pesquisa e desenvolvimento de nova fórmula | F9: 0.5625 | G9: 0.75 | H9: 0.1875 | I9: 44201 | J9: TRUE | L9: =IF(VLOOKUP(C9,Projetos!A:L,12,false)=TRUE,TRUE,FALSE) -> TRUE | M9: 33.159727 | N9: =IFERROR(IF(AND(J9=TRUE,O9=TRUE,YEAR(F9)<2021),H9,"")*(M9*24),0) -> 149.21877 | O9: TRUE
B10: Ana Claudia Zanini | C10: Trophic Soya 1.5 Fiber | D10: =vlookup(C10,'Classificação p pessoal'!F:G,2,false) -> NP | E10: Pesquisa basica para Produção de material cientifico | F10: 0.35416667 | G10: 0.5625 | H10: 0.20833333 | I10: 44202 | J10: TRUE | L10: =IF(VLOOKUP(C10,Projetos!A:L,12,false)=TRUE,TRUE,FALSE) -> TRUE | M10: 33.159727 | N10: =IFERROR(IF(AND(J10=TRUE,O10=TRUE,YEAR(F10)<2021),H10,"")*(M10*24),0) -> 165.79864 | O10: TRUE
B11: Ana Claudia Zanini | C11: Suplemento hiperproteico líquido | D11: =vlookup(C11,'Classificação p pessoal'!F:G,2,false) -> NP | E11: Pesquisa e desenvolvimento de nova fórmula | F11: 0.625 | G11: 0.75 | H11: 0.125 | I11: 44202 | J11: TRUE | L11: =IF(VLOOKUP(C11,Projetos!A:L,12,false)=TRUE,TRUE,FALSE) -> TRUE | M11: 33.159727 | N11: =IFERROR(IF(AND(J11=TRUE,O11=TRUE,YEAR(F11)<2021),H11,"")*(M11*24),0) -> 99.479182 | O11: TRUE
B12: Ana Claudia Zanini | C12: Trophic Soya 1.5 Fiber | D12: =vlookup(C12,'Classificação p pessoal'!F:G,2,false) -> NP | E12: Pesquisa basica para Produção de material cientifico | F12: 0.35416667 | G12: 0.45833333 | H12: 0.10416667 | I12: 44203 | J12: TRUE | L12: =IF(VLOOKUP(C12,Projetos!A:L,12,false)=TRUE,TRUE,FALSE) -> TRUE | M12: 33.159727 | N12: =IFERROR(IF(AND(J12=TRUE,O12=TRUE,YEAR(F12)<2021),H12,"")*(M12*24),0) -> 82.899318 | O12: TRUE
B13: Ana Claudia Zanini | C13: Suplemento hiperproteico líquido | D13: =vlookup(C13,'Classificação p pessoal'!F:G,2,false) -> NP | E13: Pesquisa e desenvolvimento de nova fórmula | F13: 0.5625 | G13: 0.75 | H13: 0.1875 | I13: 44203 | J13: TRUE | L13: =IF(VLOOKUP(C13,Projetos!A:L,12,false)=TRUE,TRUE,FALSE) -> TRUE | M13: 33.159727 | N13: =IFERROR(IF(AND(J13=TRUE,O13=TRUE,YEAR(F13)<2021),H13,"")*(M13*24),0) -> 149.21877 | O13: TRUE
B14: Ana Claudia Zanini | C14: Trophic Soya 1.5 Fiber | D14: =vlookup(C14,'Classificação p pessoal'!F:G,2,false) -> NP | E14: Pesquisa basica para Produção de material cientifico | F14: 0.35416667 | G14: 0.5625 | H14: 0.20833333 | I14: 44204 | J14: TRUE | L14: =IF(VLOOKUP(C14,Projetos!A:L,12,false)=TRUE,TRUE,FALSE) -> TRUE | M14: 33.159727 | N14: =IFERROR(IF(AND(J14=TRUE,O14=TRUE,YEAR(F14)<2021),H14,"")*(M14*24),0) -> 165.79864 | O14: TRUE
B15: Ana Claudia Zanini | C15: Trophic Soya 1.5 Fiber | D15: =vlookup(C15,'Classificação p pessoal'!F:G,2,false) -> NP | E15: Pesquisa basica para Produção de material cientifico | F15: 0.35416667 | G15: 0.54166667 | H15: 0.1875 | I15: 44207 | J15: TRUE | L15: =IF(VLOOKUP(C15,Projetos!A:L,12,false)=TRUE,TRUE,FALSE) -> TRUE | M15: 33.159727 | N15: =IFERROR(IF(AND(J15=TRUE,O15=TRUE,YEAR(F15)<2021),H15,"")*(M15*24),0) -> 149.21877 | O15: TRUE
B16: Ana Claudia Zanini | C16: InstanTH Neo | E16: Desenvolvimento de comunicação da fórmula do produto | F16: 0.72916667 | G16: 0.75 | H16: 0.020833333 | I16: 44208 | J16: FALSE | K16: Não entra | L16: =IF(VLOOKUP(C16,Projetos!A:L,12,false)=TRUE,TRUE,FALSE) -> TRUE | M16: 33.159727 | N16: =IFERROR(IF(AND(J16=TRUE,O16=TRUE,YEAR(F16)<2021),H16,"")*(M16*24),0) -> 0 | O16: TRUE
B17: Ana Claudia Zanini | C17: Trophic Soya 1.5 Fiber | D17: =vlookup(C17,'Classificação p pessoal'!F:G,2,false) -> NP | E17: Pesquisa basica para Produção de material cientifico | F17: 0.5625 | G17: 0.70833333 | H17: 0.14583333 | I17: 44208 | J17: TRUE | L17: =IF(VLOOKUP(C17,Projetos!A:L,12,false)=TRUE,TRUE,FALSE) -> TRUE | M17: 33.159727 | N17: =IFERROR(IF(AND(J17=TRUE,O17=TRUE,YEAR(F17)<2021),H17,"")*(M17*24),0) -> 116.05905 | O17: TRUE
B18: Ana Claudia Zanini | C18: InstanTH Neo | E18: Desenvolvimento de comunicação da fórmula do produto | F18: 0.41666667 | G18: 0.45833333 | H18: 0.041666667 | I18: 44209 | J18: FALSE | K18: Não entra | L18: =IF(VLOOKUP(C18,Projetos!A:L,12,false)=TRUE,TRUE,FALSE) -> TRUE | M18: 33.159727 | N18: =IFERROR(IF(AND(J18=TRUE,O18=TRUE,YEAR(F18)<2021),H18,"")*(M18*24),0) -> 0 | O18: TRUE
B19: Ana Claudia Zanini | C19: Trophic Soya 1.5 Fiber | D19: =vlookup(C19,'Classificação p pessoal'!F:G,2,false) -> NP | E19: Pesquisa basica para Produção de material cientifico | F19: 0.5625 | G19: 0.75 | H19: 0.1875 | I19: 44209 | J19: TRUE | L19: =IF(VLOOKUP(C19,Projetos!A:L,12,false)=TRUE,TRUE,FALSE) -> TRUE | M19: 33.159727 | N19: =IFERROR(IF(AND(J19=TRUE,O19=TRUE,YEAR(F19)<2021),H19,"")*(M19*24),0) -> 149.21877 | O19: TRUE
B20: Ana Claudia Zanini | C20: Suplemento hiperproteico líquido | D20: =vlookup(C20,'Classificação p pessoal'!F:G,2,false) -> NP | E20: Pesquisa e desenvolvimento de nova fórmula | F20: 0.35416667 | G20: 0.52083333 | H20: 0.16666667 | I20: 44210 | J20: TRUE | L20: =IF(VLOOKUP(C20,Projetos!A:L,12,false)=TRUE,TRUE,FALSE) -> TRUE | M20: 33.159727 | N20: =IFERROR(IF(AND(J20=TRUE,O20=TRUE,YEAR(F20)<2021),H20,"")*(M20*24),0) -> 132.63891 | O20: TRUE
B21: Ana Claudia Zanini | C21: Trophic Soya 1.5 Fiber | D21: =vlookup(C21,'Classificação p pessoal'!F:G,2,false) -> NP | E21: Pesquisa basica para Produção de material cientifico | F21: 0.58333333 | G21: 0.75 | H21: 0.16666667 | I21: 44210 | J21: TRUE | L21: =IF(VLOOKUP(C21,Projetos!A:L,12,false)=TRUE,TRUE,FALSE) -> TRUE | M21: 33.159727 | N21: =IFERROR(IF(AND(J21=TRUE,O21=TRUE,YEAR(F21)<2021),H21,"")*(M21*24),0) -> 132.63891 | O21: TRUE
B22: Ana Claudia Zanini | C22: Trophic Soya 1.5 Fiber | D22: =vlookup(C22,'Classificação p pessoal'!F:G,2,false) -> NP | E22: Pesquisa basica para Produção de material cientifico | F22: 0.35416667 | G22: 0.4375 | H22: 0.083333333 | I22: 44211 | J22: TRUE | L22: =IF(VLOOKUP(C22,Projetos!A:L,12,false)=TRUE,TRUE,FALSE) -> TRUE | M22: 33.159727 | N22: =IFERROR(IF(AND(J22=TRUE,O22=TRUE,YEAR(F22)<2021),H22,"")*(M22*24),0) -> 66.319455 | O22: TRUE
B23: Ana Claudia Zanini | C23: Trophic Junior Líquido 1.0 (ARB) | D23: =vlookup(C23,'Classificação p pessoal'!F:G,2,false) -> NP | E23: Pesquisa e desenvolvimento de nova fórmula | F23: 0.54166667 | G23: 0.75 | H23: 0.20833333 | I23: 44214 | J23: TRUE | L23: =IF(VLOOKUP(C23,Projetos!A:L,12,false)=TRUE,TRUE,FALSE) -> TRUE | M23: 33.159727 | N23: =IFERROR(IF(AND(J23=TRUE,O23=TRUE,YEAR(F23)<2021),H23,"")*(M23*24),0) -> 165.79864 | O23: TRUE
B24: Ana Claudia Zanini | C24: Suplemento hiperproteico líquido | D24: =vlookup(C24,'Classificação p pessoal'!F:G,2,false) -> NP | E24: Pesquisa e desenvolvimento de nova fórmula | F24: 0.35416667 | G24: 0.5625 | H24: 0.20833333 | I24: 44215 | J24: TRUE | L24: =IF(VLOOKUP(C24,Projetos!A:L,12,false)=TRUE,TRUE,FALSE) -> TRUE | M24: 33.159727 | N24: =IFERROR(IF(AND(J24=TRUE,O24=TRUE,YEAR(F24)<2021),H24,"")*(M24*24),0) -> 165.79864 | O24: TRUE
B25: Ana Claudia Zanini | C25: Suplemento hiperproteico líquido | D25: =vlookup(C25,'Classificação p pessoal'!F:G,2,false) -> NP | E25: Pesquisa e desenvolvimento de nova fórmula | F25: 0.35416667 | G25: 0.54166667 | H25: 0.1875 | I25: 44216 | J25: TRUE | L25: =IF(VLOOKUP(C25,Projetos!A:L,12,false)=TRUE,TRUE,FALSE) -> TRUE | M25: 33.159727 | N25: =IFERROR(IF(AND(J25=TRUE,O25=TRUE,YEAR(F25)<2021),H25,"")*(M25*24),0) -> 149.21877 | O25: TRUE
B26: Ana Claudia Zanini | C26: Diamax IG | E26: Desenvolvimento de comunicação da fórmula do produto | F26: 0.5625 | G26: 0.75 | H26: 0.1875 | I26: 44217 | J26: FALSE | K26: Não entra | L26: =IF(VLOOKUP(C26,Projetos!A:L,12,false)=TRUE,TRUE,FALSE) -> TRUE | M26: 33.159727 | N26: =IFERROR(IF(AND(J26=TRUE,O26=TRUE,YEAR(F26)<2021),H26,"")*(M26*24),0) -> 0 | O26: TRUE
B27: Ana Claudia Zanini | C27: Diamax IG | E27: Desenvolvimento de comunicação da fórmula do produto | F27: 0.52083333 | G27: 0.75 | H27: 0.22916667 | I27: 44218 | J27: FALSE | K27: Não entra | L27: =IF(VLOOKUP(C27,Projetos!A:L,12,false)=TRUE,TRUE,FALSE) -> TRUE | M27: 33.159727 | N27: =IFERROR(IF(AND(J27=TRUE,O27=TRUE,YEAR(F27)<2021),H27,"")*(M27*24),0) -> 0 | O27: TRUE
B28: Ana Claudia Zanini | C28: Diamax IG | E28: Desenvolvimento de comunicação da fórmula do produto | F28: 0.34375 | G28: 0.54166667 | H28: 0.19791667 | I28: 44221 | J28: FALSE | K28: Não entra | L28: =IF(VLOOKUP(C28,Projetos!A:L,12,false)=TRUE,TRUE,FALSE) -> TRUE | M28: 33.159727 | N28: =IFERROR(IF(AND(J28=TRUE,O28=TRUE,YEAR(F28)<2021),H28,"")*(M28*24),0) -> 0 | O28: TRUE
B29: Ana Claudia Zanini | C29: Suplemento hiperproteico líquido | D29: =vlookup(C29,'Classificação p pessoal'!F:G,2,false) -> NP | E29: Pesquisa e desenvolvimento de nova fórmula | F29: 0.58333333 | G29: 0.75 | H29: 0.16666667 | I29: 44221 | J29: TRUE | L29: =IF(VLOOKUP(C29,Projetos!A:L,12,false)=TRUE,TRUE,FALSE) -> TRUE | M29: 33.159727 | N29: =IFERROR(IF(AND(J29=TRUE,O29=TRUE,YEAR(F29)<2021),H29,"")*(M29*24),0) -> 132.63891 | O29: TRUE
B30: Ana Claudia Zanini | C30: Suplemento hiperproteico líquido | D30: =vlookup(C30,'Classificação p pessoal'!F:G,2,false) -> NP | E30: Pesquisa e desenvolvimento de nova fórmula | F30: 0.34375 | G30: 0.54166667 | H30: 0.19791667 | I30: 44222 | J30: TRUE | L30: =IF(VLOOKUP(C30,Projetos!A:L,12,false)=TRUE,TRUE,FALSE) -> TRUE | M30: 33.159727 | N30: =IFERROR(IF(AND(J30=TRUE,O30=TRUE,YEAR(F30)<2021),H30,"")*(M30*24),0) -> 157.5087 | O30: TRUE
B31: Ana Claudia Zanini | C31: Diamax IG | E31: Desenvolvimento de comunicação da fórmula do produto | F31: 0.58333333 | G31: 0.75 | H31: 0.16666667 | I31: 44222 | J31: FALSE | K31: Não entra | L31: =IF(VLOOKUP(C31,Projetos!A:L,12,false)=TRUE,TRUE,FALSE) -> TRUE | M31: 33.159727 | N31: =IFERROR(IF(AND(J31=TRUE,O31=TRUE,YEAR(F31)<2021),H31,"")*(M31*24),0) -> 0 | O31: TRUE
B32: Ana Claudia Zanini | C32: Suplemento hiperproteico líquido | D32: =vlookup(C32,'Classificação p pessoal'!F:G,2,false) -> NP | E32: Pesquisa e desenvolvimento de nova fórmula | F32: 0.34375 | G32: 0.54166667 | H32: 0.19791667 | I32: 44223 | J32: TRUE | L32: =IF(VLOOKUP(C32,Projetos!A:L,12,false)=TRUE,TRUE,FALSE) -> TRUE | M32: 33.159727 | N32: =IFERROR(IF(AND(J32=TRUE,O32=TRUE,YEAR(F32)<2021),H32,"")*(M32*24),0) -> 157.5087 | O32: TRUE
B33: Ana Claudia Zanini | C33: Suplemento hiperproteico líquido | D33: =vlookup(C33,'Classificação p pessoal'!F:G,2,false) -> NP | E33: Pesquisa e desenvolvimento de nova fórmula | F33: 0.34375 | G33: 0.54166667 | H33: 0.19791667 | I33: 44224 | J33: TRUE | L33: =IF(VLOOKUP(C33,Projetos!A:L,12,false)=TRUE,TRUE,FALSE) -> TRUE | M33: 33.159727 | N33: =IFERROR(IF(AND(J33=TRUE,O33=TRUE,YEAR(F33)<2021),H33,"")*(M33*24),0) -> 157.5087 | O33: TRUE
B34: Ana Claudia Zanini | C34: Suplemento hiperproteico líquido | D34: =vlookup(C34,'Classificação p pessoal'!F:G,2,false) -> NP | E34: Pesquisa e desenvolvimento de nova fórmula | F34: 0.34375 | G34: 0.41666667 | H34: 0.072916667 | I34: 44225 | J34: TRUE | L34: =IF(VLOOKUP(C34,Projetos!A:L,12,false)=TRUE,TRUE,FALSE) -> TRUE | M34: 33.159727 | N34: =IFERROR(IF(AND(J34=TRUE,O34=TRUE,YEAR(F34)<2021),H34,"")*(M34*24),0) -> 58.029523 | O34: TRUE
B35: Ana Claudia Zanini | C35: Trophic Soya 1.5 Fiber | D35: =vlookup(C35,'Classificação p pessoal'!F:G,2,false) -> NP | E35: Pesquisa basica para Produção de material cientifico | F35: 0.5 | G35: 0.70833333 | H35: 0.20833333 | I35: 44225 | J35: TRUE | L35: =IF(VLOOKUP(C35,Projetos!A:L,12,false)=TRUE,TRUE,FALSE) -> TRUE | M35: 33.159727 | N35: =IFERROR(IF(AND(J35=TRUE,O35=TRUE,YEAR(F35)<2021),H35,"")*(M35*24),0) -> 165.79864 | O35: TRUE
B36: Ana Claudia Zanini | C36: Trophic Soya 1.5 Fiber | D36: =vlookup(C36,'Classificação p pessoal'!F:G,2,false) -> NP | E36: Pesquisa basica para Produção de material cientifico | F36: 0.35416667 | G36: 0.52083333 | H36: 0.16666667 | I36: 44228 | J36: TRUE | L36: =IF(VLOOKUP(C36,Projetos!A:L,12,false)=TRUE,TRUE,FALSE) -> TRUE | M36: 33.159727 | N36: =IFERROR(IF(AND(J36=TRUE,O36=TRUE,YEAR(F36)<2021),H36,"")*(M36*24),0) -> 132.63891 | O36: TRUE
B37: Ana Claudia Zanini | C37: Trophic Junior Líquido 1.0 (ARB) | D37: =vlookup(C37,'Classificação p pessoal'!F:G,2,false) -> NP | E37: Pesquisa e desenvolvimento de nova fórmula | F37: 0.625 | G37: 0.75 | H37: 0.125 | I37: 44228 | J37: TRUE | L37: =IF(VLOOKUP(C37,Projetos!A:L,12,false)=TRUE,TRUE,FALSE) -> TRUE | M37: 33.159727 | N37: =IFERROR(IF(AND(J37=TRUE,O37=TRUE,YEAR(F37)<2021),H37,"")*(M37*24),0) -> 99.479182 | O37: TRUE
B38: Ana Claudia Zanini | C38: Trophic Junior Líquido 1.0 (ARB) | D38: =vlookup(C38,'Classificação p pessoal'!F:G,2,false) -> NP | E38: Pesquisa e desenvolvimento de nova fórmula | F38: 0.34375 | G38: 0.55208333 | H38: 0.20833333 | I38: 44229 | J38: TRUE | L38: =IF(VLOOKUP(C38,Projetos!A:L,12,false)=TRUE,TRUE,FALSE) -> TRUE | M38: 33.159727 | N38: =IFERROR(IF(AND(J38=TRUE,O38=TRUE,YEAR(F38)<2021),H38,"")*(M38*24),0) -> 165.79864 | O38: TRUE
B39: Ana Claudia Zanini | C39: Trophic Junior Líquido 1.0 (ARB) | D39: =vlookup(C39,'Classificação p pessoal'!F:G,2,false) -> NP | E39: Pesquisa e desenvolvimento de nova fórmula | F39: 0.34375 | G39: 0.46875 | H39: 0.125 | I39: 44230 | J39: TRUE | L39: =IF(VLOOKUP(C39,Projetos!A:L,12,false)=TRUE,TRUE,FALSE) -> TRUE | M39: 33.159727 | N39: =IFERROR(IF(AND(J39=TRUE,O39=TRUE,YEAR(F39)<2021),H39,"")*(M39*24),0) -> 99.479182 | O39: TRUE
B40: Ana Claudia Zanini | C40: Trophic Soya 1.5 Fiber | D40: =vlookup(C40,'Classificação p pessoal'!F:G,2,false) -> NP | E40: Pesquisa basica para Produção de material cientifico | F40: 0.625 | G40: 0.75 | H40: 0.125 | I40: 44230 | J40: TRUE | L40: =IF(VLOOKUP(C40,Projetos!A:L,12,false)=TRUE,TRUE,FALSE) -> TRUE | M40: 33.159727 | N40: =IFERROR(IF(AND(J40=TRUE,O40=TRUE,YEAR(F40)<2021),H40,"")*(M40*24),0) -> 99.479182 | O40: TRUE
B41: Ana Claudia Zanini | C41: Trophic Soya 1.5 Fiber | D41: =vlookup(C41,'Classificação p pessoal'!F:G,2,false) -> NP | E41: Pesquisa basica para Produção de material cientifico | F41: 0.34375 | G41: 0.46875 | H41: 0.125 | I41: 44231 | J41: TRUE | L41: =IF(VLOOKUP(C41,Projetos!A:L,12,false)=TRUE,TRUE,FALSE) -> TRUE | M41: 33.159727 | N41: =IFERROR(IF(AND(J41=TRUE,O41=TRUE,YEAR(F41)<2021),H41,"")*(M41*24),0) -> 99.479182 | O41: TRUE
B42: Ana Claudia Zanini | C42: Trophic Junior Líquido 1.0 (ARB) | D42: =vlookup(C42,'Classificação p pessoal'!F:G,2,false) -> NP | E42: Pesquisa e desenvolvimento de nova fórmula | F42: 0.58333333 | G42: 0.75 | H42: 0.16666667 | I42: 44231 | J42: TRUE | L42: =IF(VLOOKUP(C42,Projetos!A:L,12,false)=TRUE,TRUE,FALSE) -> TRUE | M42: 33.159727 | N42: =IFERROR(IF(AND(J42=TRUE,O42=TRUE,YEAR(F42)<2021),H42,"")*(M42*24),0) -> 132.63891 | O42: TRUE
B43: Ana Claudia Zanini | C43: Trophic Junior Líquido 1.0 (ARB) | D43: =vlookup(C43,'Classificação p pessoal'!F:G,2,false) -> NP | E43: Pesquisa e desenvolvimento de nova fórmula | F43: 0.35416667 | G43: 0.54166667 | H43: 0.1875 | I43: 44232 | J43: TRUE | L43: =IF(VLOOKUP(C43,Projetos!A:L,12,false)=TRUE,TRUE,FALSE) -> TRUE | M43: 33.159727 | N43: =IFERROR(IF(AND(J43=TRUE,O43=TRUE,YEAR(F43)<2021),H43,"")*(M43*24),0) -> 149.21877 | O43: TRUE
... B127: Ana Claudia Zanini | C127: Sachê | D127: =vlookup(C127,'Classificação p pessoal'!F:G,2,false) -> MProduto | E127: Pesquisa basica para Produção de material cientifico | F127: 0.45833333 | G127: 0.58333333 | H127: 0.125 | I127: 44323 | J127: TRUE | L127: =IF(VLOOKUP(C127,Projetos!A:L,12,false)=TRUE,TRUE,FALSE) -> TRUE | M127: 33.159727 | N127: =IFERROR(IF(AND(J127=TRUE,O127=TRUE,YEAR(F127)<2021),H127,"")*(M127*24),0) -> 99.479182 | O127: TRUE
B128: Ana Claudia Zanini | C128: Bemmax sabor neutro | E128: Produção de material cientifico | F128: 0.375 | G128: 0.45833333 | H128: 0.083333333 | I128: 44326 | J128: FALSE | K128: Não entra | L128: =IF(VLOOKUP(C128,Projetos!A:L,12,false)=TRUE,TRUE,FALSE) -> TRUE | M128: 33.159727 | N128: =IFERROR(IF(AND(J128=TRUE,O128=TRUE,YEAR(F128)<2021),H128,"")*(M128*24),0) -> 0 | O128: TRUE
B129: Ana Claudia Zanini | C129: Retort (Sistema Fechado) | D129: =vlookup(C129,'Classificação p pessoal'!F:G,2,false) -> NP | E129: Análise de composição de novo produto | F129: 0.41666667 | G129: 0.45833333 | H129: 0.041666667 | I129: 44327 | J129: TRUE | L129: =IF(VLOOKUP(C129,Projetos!A:L,12,false)=TRUE,TRUE,FALSE) -> TRUE | M129: 33.159727 | N129: =IFERROR(IF(AND(J129=TRUE,O129=TRUE,YEAR(F129)<2021),H129,"")*(M129*24),0) -> 33.159727 | O129: TRUE
B130: Ana Claudia Zanini | C130: Diamax IG | D130: =vlookup(C130,'Classificação p pessoal'!F:G,2,false) -> MProduto | E130: Pesquisa basica para Produção de material cientifico | F130: 0.58333333 | G130: 0.75 | H130: 0.16666667 | I130: 44327 | J130: TRUE | L130: =IF(VLOOKUP(C130,Projetos!A:L,12,false)=TRUE,TRUE,FALSE) -> TRUE | M130: 33.159727 | N130: =IFERROR(IF(AND(J130=TRUE,O130=TRUE,YEAR(F130)<2021),H130,"")*(M130*24),0) -> 132.63891 | O130: TRUE
B131: Ana Claudia Zanini | C131: Diamax IG | D131: =vlookup(C131,'Classificação p pessoal'!F:G,2,false) -> MProduto | E131: Pesquisa basica para Produção de material cientifico | F131: 0.34375 | G131: 0.55208333 | H131: 0.20833333 | I131: 44328 | J131: TRUE | L131: =IF(VLOOKUP(C131,Projetos!A:L,12,false)=TRUE,TRUE,FALSE) -> TRUE | M131: 33.159727 | N131: =IFERROR(IF(AND(J131=TRUE,O131=TRUE,YEAR(F131)<2021),H131,"")*(M131*24),0) -> 165.79864 | O131: TRUE
B132: Ana Claudia Zanini | C132: Bemmax sabor neutro | E132: Produção de material cientifico | F132: 0.625 | G132: 0.66666667 | H132: 0.041666667 | I132: 44328 | J132: FALSE | K132: Não entra | L132: =IF(VLOOKUP(C132,Projetos!A:L,12,false)=TRUE,TRUE,FALSE) -> TRUE | M132: 33.159727 | N132: =IFERROR(IF(AND(J132=TRUE,O132=TRUE,YEAR(F132)<2021),H132,"")*(M132*24),0) -> 0 | O132: TRUE
B133: Ana Claudia Zanini | C133: Diamax IG | D133: =vlookup(C133,'Classificação p pessoal'!F:G,2,false) -> MProduto | E133: Pesquisa basica para Produção de material cientifico | F133: 0.54166667 | G133: 0.75 | H133: 0.20833333 | I133: 44329 | J133: TRUE | L133: =IF(VLOOKUP(C133,Projetos!A:L,12,false)=TRUE,TRUE,FALSE) -> TRUE | M133: 33.159727 | N133: =IFERROR(IF(AND(J133=TRUE,O133=TRUE,YEAR(F133)<2021),H133,"")*(M133*24),0) -> 165.79864 | O133: TRUE
B134: Ana Claudia Zanini | C134: Suplemento hiperproteico líquido | D134: =vlookup(C134,'Classificação p pessoal'!F:G,2,false) -> NP | E134: Pesquisa e desenvolvimento de nova fórmula | F134: 0.45833333 | G134: 0.5 | H134: 0.041666667 | I134: 44329 | J134: TRUE | L134: =IF(VLOOKUP(C134,Projetos!A:L,12,false)=TRUE,TRUE,FALSE) -> TRUE | M134: 33.159727 | N134: =IFERROR(IF(AND(J134=TRUE,O134=TRUE,YEAR(F134)<2021),H134,"")*(M134*24),0) -> 33.159727 | O134: TRUE
B135: Ana Claudia Zanini | C135: Diamax IG | D135: =vlookup(C135,'Classificação p pessoal'!F:G,2,false) -> MProduto | E135: Pesquisa e desenvolvimento de nova fórmula | F135: 0.35416667 | G135: 0.54166667 | H135: 0.1875 | I135: 44330 | J135: TRUE | L135: =IF(VLOOKUP(C135,Projetos!A:L,12,false)=TRUE,TRUE,FALSE) -> TRUE | M135: 33.159727 | N135: =IFERROR(IF(AND(J135=TRUE,O135=TRUE,YEAR(F135)<2021),H135,"")*(M135*24),0) -> 149.21877 | O135: TRUE
B136: Ana Claudia Zanini | C136: Retort (Sistema Fechado) | D136: =vlookup(C136,'Classificação p pessoal'!F:G,2,false) -> NP | E136: Análise de composição de novo produto | F136: 0.58333333 | G136: 0.625 | H136: 0.041666667 | I136: 44330 | J136: TRUE | L136: =IF(VLOOKUP(C136,Projetos!A:L,12,false)=TRUE,TRUE,FALSE) -> TRUE | M136: 33.159727 | N136: =IFERROR(IF(AND(J136=TRUE,O136=TRUE,YEAR(F136)<2021),H136,"")*(M136*24),0) -> 33.159727 | O136: TRUE
B137: Ana Claudia Zanini | C137: Bemmax sabor neutro | E137: Produção de material cientifico | F137: 0.625 | G137: 0.66666667 | H137: 0.041666667 | I137: 44330 | J137: FALSE | K137: Não entra | L137: =IF(VLOOKUP(C137,Projetos!A:L,12,false)=TRUE,TRUE,FALSE) -> TRUE | M137: 33.159727 | N137: =IFERROR(IF(AND(J137=TRUE,O137=TRUE,YEAR(F137)<2021),H137,"")*(M137*24),0) -> 0 | O137: TRUE
B138: Ana Claudia Zanini | C138: Diamax IG | D138: =vlookup(C138,'Classificação p pessoal'!F:G,2,false) -> MProduto | E138: Pesquisa basica para Produção de material cientifico | F138: 0.35416667 | G138: 0.54166667 | H138: 0.1875 | I138: 44333 | J138: TRUE | L138: =IF(VLOOKUP(C138,Projetos!A:L,12,false)=TRUE,TRUE,FALSE) -> TRUE | M138: 33.159727 | N138: =IFERROR(IF(AND(J138=TRUE,O138=TRUE,YEAR(F138)<2021),H138,"")*(M138*24),0) -> 149.21877 | O138: TRUE
B139: Ana Claudia Zanini | C139: Diamax IG | D139: =vlookup(C139,'Classificação p pessoal'!F:G,2,false) -> MProduto | E139: Pesquisa basica para Produção de material cientifico | F139: 0.41666667 | G139: 0.54166667 | H139: 0.125 | I139: 44334 | J139: TRUE | L139: =IF(VLOOKUP(C139,Projetos!A:L,12,false)=TRUE,TRUE,FALSE) -> TRUE | M139: 33.159727 | N139: =IFERROR(IF(AND(J139=TRUE,O139=TRUE,YEAR(F139)<2021),H139,"")*(M139*24),0) -> 99.479182 | O139: TRUE
B140: Ana Claudia Zanini | C140: Retort (Sistema Fechado) | D140: =vlookup(C140,'Classificação p pessoal'!F:G,2,false) -> NP | E140: Pesquisa e desenvolvimento de nova fórmula | F140: 0.625 | G140: 0.75 | H140: 0.125 | I140: 44334 | J140: TRUE | L140: =IF(VLOOKUP(C140,Projetos!A:L,12,false)=TRUE,TRUE,FALSE) -> TRUE | M140: 33.159727 | N140: =IFERROR(IF(AND(J140=TRUE,O140=TRUE,YEAR(F140)<2021),H140,"")*(M140*24),0) -> 99.479182 | O140: TRUE
B141: Ana Claudia Zanini | C141: Bemmax sabor neutro | E141: Produção de material cientifico | F141: 0.58333333 | G141: 0.625 | H141: 0.041666667 | I141: 44334 | J141: FALSE | K141: Não entra | L141: =IF(VLOOKUP(C141,Projetos!A:L,12,false)=TRUE,TRUE,FALSE) -> TRUE | M141: 33.159727 | N141: =IFERROR(IF(AND(J141=TRUE,O141=TRUE,YEAR(F141)<2021),H141,"")*(M141*24),0) -> 0 | O141: TRUE
B142: Ana Claudia Zanini | C142: Bemmax sabor neutro | E142: Produção de material cientifico | F142: 0.625 | G142: 0.66666667 | H142: 0.041666667 | I142: 44335 | J142: FALSE | K142: Não entra | L142: =IF(VLOOKUP(C142,Projetos!A:L,12,false)=TRUE,TRUE,FALSE) -> TRUE | M142: 33.159727 | N142: =IFERROR(IF(AND(J142=TRUE,O142=TRUE,YEAR(F142)<2021),H142,"")*(M142*24),0) -> 0 | O142: TRUE
B143: Ana Claudia Zanini | C143: Retort (Sistema Fechado) | D143: =vlookup(C143,'Classificação p pessoal'!F:G,2,false) -> NP | E143: Pesquisa e desenvolvimento de nova fórmula | F143: 0.35416667 | G143: 0.54166667 | H143: 0.1875 | I143: 44336 | J143: TRUE | L143: =IF(VLOOKUP(C143,Projetos!A:L,12,false)=TRUE,TRUE,FALSE) -> TRUE | M143: 33.159727 | N143: =IFERROR(IF(AND(J143=TRUE,O143=TRUE,YEAR(F143)<2021),H143,"")*(M143*24),0) -> 149.21877 | O143: TRUE
B144: Ana Claudia Zanini | C144: Diamax IG | D144: =vlookup(C144,'Classificação p pessoal'!F:G,2,false) -> MProduto | E144: Pesquisa basica para Produção de material cientifico | F144: 0.47916667 | G144: 0.54166667 | H144: 0.0625 | I144: 44337 | J144: TRUE | L144: =IF(VLOOKUP(C144,Projetos!A:L,12,false)=TRUE,TRUE,FALSE) -> TRUE | M144: 33.159727 | N144: =IFERROR(IF(AND(J144=TRUE,O144=TRUE,YEAR(F144)<2021),H144,"")*(M144*24),0) -> 49.739591 | O144: TRUE
B145: Ana Claudia Zanini | C145: Retort (Sistema Fechado) | D145: =vlookup(C145,'Classificação p pessoal'!F:G,2,false) -> NP | E145: Pesquisa e desenvolvimento de nova fórmula | F145: 0.625 | G145: 0.75 | H145: 0.125 | I145: 44337 | J145: TRUE | L145: =IF(VLOOKUP(C145,Projetos!A:L,12,false)=TRUE,TRUE,FALSE) -> TRUE | M145: 33.159727 | N145: =IFERROR(IF(AND(J145=TRUE,O145=TRUE,YEAR(F145)<2021),H145,"")*(M145*24),0) -> 99.479182 | O145: TRUE
B146: Ana Claudia Zanini | C146: Diamax IG | D146: =vlookup(C146,'Classificação p pessoal'!F:G,2,false) -> MProduto | E146: Pesquisa basica para Produção de material cientifico | F146: 0.58333333 | G146: 0.75 | H146: 0.16666667 | I146: 44340 | J146: TRUE | L146: =IF(VLOOKUP(C146,Projetos!A:L,12,false)=TRUE,TRUE,FALSE) -> TRUE | M146: 33.159727 | N146: =IFERROR(IF(AND(J146=TRUE,O146=TRUE,YEAR(F146)<2021),H146,"")*(M146*24),0) -> 132.63891 | O146: TRUE
B147: Ana Claudia Zanini | C147: Diamax IG | D147: =vlookup(C147,'Classificação p pessoal'!F:G,2,false) -> MProduto | E147: Pesquisa basica para Produção de material cientifico | F147: 0.58333333 | G147: 0.66666667 | H147: 0.083333333 | I147: 44341 | J147: TRUE | L147: =IF(VLOOKUP(C147,Projetos!A:L,12,false)=TRUE,TRUE,FALSE) -> TRUE | M147: 33.159727 | N147: =IFERROR(IF(AND(J147=TRUE,O147=TRUE,YEAR(F147)<2021),H147,"")*(M147*24),0) -> 66.319455 | O147: TRUE
B148: Ana Claudia Zanini | C148: Suplemento hiperproteico líquido | D148: =vlookup(C148,'Classificação p pessoal'!F:G,2,false) -> NP | E148: Pesquisa e desenvolvimento de nova fórmula | F148: 0.66666667 | G148: 0.75 | H148: 0.083333333 | I148: 44341 | J148: TRUE | L148: =IF(VLOOKUP(C148,Projetos!A:L,12,false)=TRUE,TRUE,FALSE) -> TRUE | M148: 33.159727 | N148: =IFERROR(IF(AND(J148=TRUE,O148=TRUE,YEAR(F148)<2021),H148,"")*(M148*24),0) -> 66.319455 | O148: TRUE
B149: Ana Claudia Zanini | C149: Suplemento hiperproteico líquido | D149: =vlookup(C149,'Classificação p pessoal'!F:G,2,false) -> NP | E149: Pesquisa e desenvolvimento de nova fórmula | F149: 0.66666667 | G149: 0.75 | H149: 0.083333333 | I149: 44342 | J149: TRUE | L149: =IF(VLOOKUP(C149,Projetos!A:L,12,false)=TRUE,TRUE,FALSE) -> TRUE | M149: 33.159727 | N149: =IFERROR(IF(AND(J149=TRUE,O149=TRUE,YEAR(F149)<2021),H149,"")*(M149*24),0) -> 66.319455 | O149: TRUE
B150: Ana Claudia Zanini | C150: Suplemento hiperproteico líquido | D150: =vlookup(C150,'Classificação p pessoal'!F:G,2,false) -> NP | E150: Pesquisa e desenvolvimento de nova fórmula | F150: 0.58333333 | G150: 0.66666667 | H150: 0.083333333 | I150: 44343 | J150: TRUE | L150: =IF(VLOOKUP(C150,Projetos!A:L,12,false)=TRUE,TRUE,FALSE) -> TRUE | M150: 33.159727 | N150: =IFERROR(IF(AND(J150=TRUE,O150=TRUE,YEAR(F150)<2021),H150,"")*(M150*24),0) -> 66.319455 | O150: TRUE
B151: Ana Claudia Zanini | C151: Trophic 1.5 250mL - Edge | D151: =vlookup(C151,'Classificação p pessoal'!F:G,2,false) -> NP | E151: Desenvolvimento de equipo SAMTRONIC - Teste | F151: 0.58333333 | G151: 0.75 | H151: 0.16666667 | I151: 44343 | J151: TRUE | L151: =IF(VLOOKUP(C151,Projetos!A:L,12,false)=TRUE,TRUE,FALSE) -> TRUE | M151: 33.159727 | N151: =IFERROR(IF(AND(J151=TRUE,O151=TRUE,YEAR(F151)<2021),H151,"")*(M151*24),0) -> 132.63891 | O151: TRUE
B152: Ana Claudia Zanini | C152: Trophic 1.5 250mL - Edge | D152: =vlookup(C152,'Classificação p pessoal'!F:G,2,false) -> NP | E152: Desenvolvimento de equipo SAMTRONIC - Teste | F152: 0.34375 | G152: 0.38541667 | H152: 0.041666667 | I152: 44344 | J152: TRUE | L152: =IF(VLOOKUP(C152,Projetos!A:L,12,false)=TRUE,TRUE,FALSE) -> TRUE | M152: 33.159727 | N152: =IFERROR(IF(AND(J152=TRUE,O152=TRUE,YEAR(F152)<2021),H152,"")*(M152*24),0) -> 33.159727 | O152: TRUE
B153: Ana Claudia Zanini | C153: Diamax IG | D153: =vlookup(C153,'Classificação p pessoal'!F:G,2,false) -> MProduto | E153: Pesquisa basica para Produção de material cientifico | F153: 0.34375 | G153: 0.54166667 | H153: 0.19791667 | I153: 44347 | J153: TRUE | L153: =IF(VLOOKUP(C153,Projetos!A:L,12,false)=TRUE,TRUE,FALSE) -> TRUE | M153: 33.159727 | N153: =IFERROR(IF(AND(J153=TRUE,O153=TRUE,YEAR(F153)<2021),H153,"")*(M153*24),0) -> 157.5087 | O153: TRUE
B154: Ana Claudia Zanini | C154: Retort (Sistema Fechado) | D154: =vlookup(C154,'Classificação p pessoal'!F:G,2,false) -> NP | E154: Pesquisa e desenvolvimento de nova fórmula | F154: 0.35416667 | G154: 0.52083333 | H154: 0.16666667 | I154: 44348 | J154: TRUE | L154: =IF(VLOOKUP(C154,Projetos!A:L,12,false)=TRUE,TRUE,FALSE) -> TRUE | M154: 33.159727 | N154: =IFERROR(IF(AND(J154=TRUE,O154=TRUE,YEAR(F154)<2021),H154,"")*(M154*24),0) -> 132.63891 | O154: TRUE
... B240: Ana Claudia Zanini | C240: Diamax pó | D240: =vlookup(C240,'Classificação p pessoal'!F:G,2,false) -> NP | E240: Desenvolvimento de novo produto | F240: 0.58333333 | G240: 0.66666667 | H240: 0.083333333 | I240: 44467 | J240: TRUE | L240: =IF(VLOOKUP(C240,Projetos!A:L,12,false)=TRUE,TRUE,FALSE) -> TRUE | M240: 33.159727 | N240: =IFERROR(IF(AND(J240=TRUE,O240=TRUE,YEAR(F240)<2021),H240,"")*(M240*24),0) -> 66.319455 | O240: TRUE
B241: Ana Claudia Zanini | C241: Diamax IG | E241: Pesquisa basica para elaboração de material cientifico | F241: 0.54166667 | G241: 0.75 | H241: 0.20833333 | I241: 44468 | J241: FALSE | K241: Não entra | L241: =IF(VLOOKUP(C241,Projetos!A:L,12,false)=TRUE,TRUE,FALSE) -> TRUE | M241: 33.159727 | N241: =IFERROR(IF(AND(J241=TRUE,O241=TRUE,YEAR(F241)<2021),H241,"")*(M241*24),0) -> 0 | O241: TRUE
B242: Ana Claudia Zanini | C242: Congresso ESPEN | D242: =vlookup(C242,'Classificação p pessoal'!F:G,2,false) -> NP | E242: Pesquisa Básica pós Congresso ESPEN(projeto novos produtos e novas pesquisas) | F242: 0.75 | G242: 0.83333333 | H242: 0.083333333 | I242: 44468 | J242: TRUE | L242: =IF(VLOOKUP(C242,Projetos!A:L,12,false)=TRUE,TRUE,FALSE) -> TRUE | M242: 33.159727 | N242: =IFERROR(IF(AND(J242=TRUE,O242=TRUE,YEAR(F242)<2021),H242,"")*(M242*24),0) -> 66.319455 | O242: TRUE
B243: Ana Claudia Zanini | C243: Diamax pó | D243: =vlookup(C243,'Classificação p pessoal'!F:G,2,false) -> NP | E243: Desenvolvimento de novo produto | F243: 0.54166667 | G243: 0.75 | H243: 0.20833333 | I243: 44469 | J243: TRUE | L243: =IF(VLOOKUP(C243,Projetos!A:L,12,false)=TRUE,TRUE,FALSE) -> TRUE | M243: 33.159727 | N243: =IFERROR(IF(AND(J243=TRUE,O243=TRUE,YEAR(F243)<2021),H243,"")*(M243*24),0) -> 165.79864 | O243: TRUE
B244: Ana Claudia Zanini | C244: Retort (Sistema Fechado) | D244: =vlookup(C244,'Classificação p pessoal'!F:G,2,false) -> NP | E244: Pesquisa e desenvolvimento de nova fórmula | F244: 0.58333333 | G244: 0.66666667 | H244: 0.083333333 | I244: 44470 | J244: TRUE | L244: =IF(VLOOKUP(C244,Projetos!A:L,12,false)=TRUE,TRUE,FALSE) -> TRUE | M244: 33.159727 | N244: =IFERROR(IF(AND(J244=TRUE,O244=TRUE,YEAR(F244)<2021),H244,"")*(M244*24),0) -> 66.319455 | O244: TRUE
B245: Ana Claudia Zanini | C245: Congresso ESPEN | D245: =vlookup(C245,'Classificação p pessoal'!F:G,2,false) -> NP | E245: Pesquisa Básica pós Congresso ESPEN(projeto novos produtos e novas pesquisas) | F245: 0.35416667 | G245: 0.52083333 | H245: 0.16666667 | I245: 44473 | J245: TRUE | L245: =IF(VLOOKUP(C245,Projetos!A:L,12,false)=TRUE,TRUE,FALSE) -> TRUE | M245: 33.159727 | N245: =IFERROR(IF(AND(J245=TRUE,O245=TRUE,YEAR(F245)<2021),H245,"")*(M245*24),0) -> 132.63891 | O245: TRUE
B246: Ana Claudia Zanini | C246: Retort (Sistema Fechado) | D246: =vlookup(C246,'Classificação p pessoal'!F:G,2,false) -> NP | E246: Pesquisa e desenvolvimento de nova fórmula | F246: 0.66666667 | G246: 0.75 | H246: 0.083333333 | I246: 44473 | J246: TRUE | L246: =IF(VLOOKUP(C246,Projetos!A:L,12,false)=TRUE,TRUE,FALSE) -> TRUE | M246: 33.159727 | N246: =IFERROR(IF(AND(J246=TRUE,O246=TRUE,YEAR(F246)<2021),H246,"")*(M246*24),0) -> 66.319455 | O246: TRUE
B247: Ana Claudia Zanini | C247: Congresso ESPEN | D247: =vlookup(C247,'Classificação p pessoal'!F:G,2,false) -> NP | E247: Pesquisa Básica pós Congresso ESPEN(projeto novos produtos e novas pesquisas) | F247: 0.35416667 | G247: 0.5 | H247: 0.14583333 | I247: 44474 | J247: TRUE | L247: =IF(VLOOKUP(C247,Projetos!A:L,12,false)=TRUE,TRUE,FALSE) -> TRUE | M247: 33.159727 | N247: =IFERROR(IF(AND(J247=TRUE,O247=TRUE,YEAR(F247)<2021),H247,"")*(M247*24),0) -> 116.05905 | O247: TRUE
B248: Ana Claudia Zanini | C248: Retort (Sistema Fechado) | D248: =vlookup(C248,'Classificação p pessoal'!F:G,2,false) -> NP | E248: Pesquisa e desenvolvimento de nova fórmula | F248: 0.5625 | G248: 0.6875 | H248: 0.125 | I248: 44474 | J248: TRUE | L248: =IF(VLOOKUP(C248,Projetos!A:L,12,false)=TRUE,TRUE,FALSE) -> TRUE | M248: 33.159727 | N248: =IFERROR(IF(AND(J248=TRUE,O248=TRUE,YEAR(F248)<2021),H248,"")*(M248*24),0) -> 99.479182 | O248: TRUE
B249: Ana Claudia Zanini | C249: Retort (Sistema Fechado) | D249: =vlookup(C249,'Classificação p pessoal'!F:G,2,false) -> NP | E249: Pesquisa e desenvolvimento de nova fórmula | F249: 0.35416667 | G249: 0.4375 | H249: 0.083333333 | I249: 44475 | J249: TRUE | L249: =IF(VLOOKUP(C249,Projetos!A:L,12,false)=TRUE,TRUE,FALSE) -> TRUE | M249: 33.159727 | N249: =IFERROR(IF(AND(J249=TRUE,O249=TRUE,YEAR(F249)<2021),H249,"")*(M249*24),0) -> 66.319455 | O249: TRUE
B250: Ana Claudia Zanini | C250: Trophic Junior Líquido 1.0 (ARB) | D250: =vlookup(C250,'Classificação p pessoal'!F:G,2,false) -> NP | E250: Pesquisa e desenvolvimento de nova fórmula | F250: 0.45833333 | G250: 0.54166667 | H250: 0.083333333 | I250: 44475 | J250: TRUE | L250: =IF(VLOOKUP(C250,Projetos!A:L,12,false)=TRUE,TRUE,FALSE) -> TRUE | M250: 33.159727 | N250: =IFERROR(IF(AND(J250=TRUE,O250=TRUE,YEAR(F250)<2021),H250,"")*(M250*24),0) -> 66.319455 | O250: TRUE
B251: Ana Claudia Zanini | C251: Diamax pó | D251: =vlookup(C251,'Classificação p pessoal'!F:G,2,false) -> NP | E251: Pesquisa e desenvolvimento de nova fórmula | F251: 0.58333333 | G251: 0.75 | H251: 0.16666667 | I251: 44475 | J251: TRUE | L251: =IF(VLOOKUP(C251,Projetos!A:L,12,false)=TRUE,TRUE,FALSE) -> TRUE | M251: 33.159727 | N251: =IFERROR(IF(AND(J251=TRUE,O251=TRUE,YEAR(F251)<2021),H251,"")*(M251*24),0) -> 132.63891 | O251: TRUE
B252: Ana Claudia Zanini | C252: Retort (Sistema Fechado) | D252: =vlookup(C252,'Classificação p pessoal'!F:G,2,false) -> NP | E252: Pesquisa e desenvolvimento de nova fórmula | F252: 0.35416667 | G252: 0.52083333 | H252: 0.16666667 | I252: 44476 | J252: TRUE | L252: =IF(VLOOKUP(C252,Projetos!A:L,12,false)=TRUE,TRUE,FALSE) -> TRUE | M252: 33.159727 | N252: =IFERROR(IF(AND(J252=TRUE,O252=TRUE,YEAR(F252)<2021),H252,"")*(M252*24),0) -> 132.63891 | O252: TRUE
B253: Ana Claudia Zanini | C253: Diamax pó | D253: =vlookup(C253,'Classificação p pessoal'!F:G,2,false) -> NP | E253: Pesquisa e desenvolvimento de nova fórmula | F253: 0.35416667 | G253: 0.47916667 | H253: 0.125 | I253: 44482 | J253: TRUE | L253: =IF(VLOOKUP(C253,Projetos!A:L,12,false)=TRUE,TRUE,FALSE) -> TRUE | M253: 33.159727 | N253: =IFERROR(IF(AND(J253=TRUE,O253=TRUE,YEAR(F253)<2021),H253,"")*(M253*24),0) -> 99.479182 | O253: TRUE
... B255: Ana Claudia Zanini | C255: Congresso ESPEN | D255: =vlookup(C255,'Classificação p pessoal'!F:G,2,false) -> NP | E255: Pesquisa Básica pós Congresso ESPEN(projeto novos produtos e novas pesquisas) | F255: 0.35416667 | G255: 0.41666667 | H255: 0.0625 | I255: 44483 | J255: TRUE | L255: =IF(VLOOKUP(C255,Projetos!A:L,12,false)=TRUE,TRUE,FALSE) -> TRUE | M255: 33.159727 | N255: =IFERROR(IF(AND(J255=TRUE,O255=TRUE,YEAR(F255)<2021),H255,"")*(M255*24),0) -> 49.739591 | O255: TRUE
B256: Ana Claudia Zanini | C256: Diamax IG | E256: Pesquisa basica para elaboração de material cientifico | F256: 0.54166667 | G256: 0.66666667 | H256: 0.125 | I256: 44483 | J256: FALSE | K256: Não entra | L256: =IF(VLOOKUP(C256,Projetos!A:L,12,false)=TRUE,TRUE,FALSE) -> TRUE | M256: 33.159727 | N256: =IFERROR(IF(AND(J256=TRUE,O256=TRUE,YEAR(F256)<2021),H256,"")*(M256*24),0) -> 0 | O256: TRUE
B257: Ana Claudia Zanini | C257: Diamax pó | D257: =vlookup(C257,'Classificação p pessoal'!F:G,2,false) -> NP | E257: Pesquisa e desenvolvimento de nova fórmula | F257: 0.54166667 | G257: 0.66666667 | H257: 0.125 | I257: 44484 | J257: TRUE | L257: =IF(VLOOKUP(C257,Projetos!A:L,12,false)=TRUE,TRUE,FALSE) -> TRUE | M257: 33.159727 | N257: =IFERROR(IF(AND(J257=TRUE,O257=TRUE,YEAR(F257)<2021),H257,"")*(M257*24),0) -> 99.479182 | O257: TRUE
B258: Ana Claudia Zanini | C258: Diamax IG | E258: Pesquisa basica para elaboração de material cientifico | F258: 0.66666667 | G258: 0.75 | H258: 0.083333333 | I258: 44484 | J258: FALSE | K258: Não entra | L258: =IF(VLOOKUP(C258,Projetos!A:L,12,false)=TRUE,TRUE,FALSE) -> TRUE | M258: 33.159727 | N258: =IFERROR(IF(AND(J258=TRUE,O258=TRUE,YEAR(F258)<2021),H258,"")*(M258*24),0) -> 0 | O258: TRUE
B259: Ana Claudia Zanini | C259: Retort (Sistema Fechado) | D259: =vlookup(C259,'Classificação p pessoal'!F:G,2,false) -> NP | E259: Pesquisa e desenvolvimento de nova fórmula | F259: 0.35416667 | G259: 0.54166667 | H259: 0.1875 | I259: 44509 | J259: TRUE | L259: =IF(VLOOKUP(C259,Projetos!A:L,12,false)=TRUE,TRUE,FALSE) -> TRUE | M259: 33.159727 | N259: =IFERROR(IF(AND(J259=TRUE,O259=TRUE,YEAR(F259)<2021),H259,"")*(M259*24),0) -> 149.21877 | O259: TRUE
B260: Ana Claudia Zanini | C260: Retort (Sistema Fechado) | D260: =vlookup(C260,'Classificação p pessoal'!F:G,2,false) -> NP | E260: Pesquisa e desenvolvimento de nova fórmula | F260: 0.35416667 | G260: 0.54166667 | H260: 0.1875 | I260: 44510 | J260: TRUE | L260: =IF(VLOOKUP(C260,Projetos!A:L,12,false)=TRUE,TRUE,FALSE) -> TRUE | M260: 33.159727 | N260: =IFERROR(IF(AND(J260=TRUE,O260=TRUE,YEAR(F260)<2021),H260,"")*(M260*24),0) -> 149.21877 | O260: TRUE
B261: Ana Claudia Zanini | C261: Retort (Sistema Fechado) | D261: =vlookup(C261,'Classificação p pessoal'!F:G,2,false) -> NP | E261: Pesquisa e desenvolvimento de nova fórmula | F261: 0.35416667 | G261: 0.54166667 | H261: 0.1875 | I261: 44511 | J261: TRUE | L261: =IF(VLOOKUP(C261,Projetos!A:L,12,false)=TRUE,TRUE,FALSE) -> TRUE | M261: 33.159727 | N261: =IFERROR(IF(AND(J261=TRUE,O261=TRUE,YEAR(F261)<2021),H261,"")*(M261*24),0) -> 149.21877 | O261: TRUE
B262: Ana Claudia Zanini | C262: Retort (Sistema Fechado) | D262: =vlookup(C262,'Classificação p pessoal'!F:G,2,false) -> NP | E262: Pesquisa e desenvolvimento de nova fórmula | F262: 0.35416667 | G262: 0.54166667 | H262: 0.1875 | I262: 44512 | J262: TRUE | L262: =IF(VLOOKUP(C262,Projetos!A:L,12,false)=TRUE,TRUE,FALSE) -> TRUE | M262: 33.159727 | N262: =IFERROR(IF(AND(J262=TRUE,O262=TRUE,YEAR(F262)<2021),H262,"")*(M262*24),0) -> 149.21877 | O262: TRUE
B263: Ana Claudia Zanini | C263: Retort (Sistema Fechado) | D263: =vlookup(C263,'Classificação p pessoal'!F:G,2,false) -> NP | E263: Pesquisa e desenvolvimento de nova fórmula | F263: 0.375 | G263: 0.54166667 | H263: 0.16666667 | I263: 44517 | J263: TRUE | L263: =IF(VLOOKUP(C263,Projetos!A:L,12,false)=TRUE,TRUE,FALSE) -> TRUE | M263: 33.159727 | N263: =IFERROR(IF(AND(J263=TRUE,O263=TRUE,YEAR(F263)<2021),H263,"")*(M263*24),0) -> 132.63891 | O263: TRUE
B264: Ana Claudia Zanini | C264: Retort (Sistema Fechado) | D264: =vlookup(C264,'Classificação p pessoal'!F:G,2,false) -> NP | E264: Pesquisa e desenvolvimento de nova fórmula | F264: 0.58333333 | G264: 0.75 | H264: 0.16666667 | I264: 44525 | J264: TRUE | L264: =IF(VLOOKUP(C264,Projetos!A:L,12,false)=TRUE,TRUE,FALSE) -> TRUE | M264: 33.159727 | N264: =IFERROR(IF(AND(J264=TRUE,O264=TRUE,YEAR(F264)<2021),H264,"")*(M264*24),0) -> 132.63891 | O264: TRUE
B265: Ana Claudia Zanini | C265: Diamax pó | D265: =vlookup(C265,'Classificação p pessoal'!F:G,2,false) -> NP | E265: Pesquisa e desenvolvimento de nova fórmula | F265: 0.58333333 | G265: 0.75 | H265: 0.16666667 | I265: 44526 | J265: TRUE | L265: =IF(VLOOKUP(C265,Projetos!A:L,12,false)=TRUE,TRUE,FALSE) -> TRUE | M265: 33.159727 | N265: =IFERROR(IF(AND(J265=TRUE,O265=TRUE,YEAR(F265)<2021),H265,"")*(M265*24),0) -> 132.63891 | O265: TRUE
B266: Ana Claudia Zanini | C266: Retort (Sistema Fechado) | D266: =vlookup(C266,'Classificação p pessoal'!F:G,2,false) -> NP | E266: Pesquisa e desenvolvimento de nova fórmula | F266: 0.58333333 | G266: 0.66666667 | H266: 0.083333333 | I266: 44529 | J266: TRUE | L266: =IF(VLOOKUP(C266,Projetos!A:L,12,false)=TRUE,TRUE,FALSE) -> TRUE | M266: 33.159727 | N266: =IFERROR(IF(AND(J266=TRUE,O266=TRUE,YEAR(F266)<2021),H266,"")*(M266*24),0) -> 66.319455 | O266: TRUE
B267: Ana Claudia Zanini | C267: Diamax pó | D267: =vlookup(C267,'Classificação p pessoal'!F:G,2,false) -> NP | E267: Pesquisa e desenvolvimento de nova fórmula | F267: 0.625 | G267: 0.75 | H267: 0.125 | I267: 44530 | J267: TRUE | L267: =IF(VLOOKUP(C267,Projetos!A:L,12,false)=TRUE,TRUE,FALSE) -> TRUE | M267: 33.159727 | N267: =IFERROR(IF(AND(J267=TRUE,O267=TRUE,YEAR(F267)<2021),H267,"")*(M267*24),0) -> 99.479182 | O267: TRUE
B268: Ana Claudia Zanini | C268: Diamax pó | D268: =vlookup(C268,'Classificação p pessoal'!F:G,2,false) -> NP | E268: Pesquisa e desenvolvimento de nova fórmula | F268: 0.375 | G268: 0.5 | H268: 0.125 | I268: 44537 | J268: TRUE | L268: =IF(VLOOKUP(C268,Projetos!A:L,12,false)=TRUE,TRUE,FALSE) -> TRUE | M268: 33.159727 | N268: =IFERROR(IF(AND(J268=TRUE,O268=TRUE,YEAR(F268)<2021),H268,"")*(M268*24),0) -> 99.479182 | O268: TRUE
B269: Ana Claudia Zanini | C269: Diamax pó | D269: =vlookup(C269,'Classificação p pessoal'!F:G,2,false) -> NP | E269: Pesquisa e desenvolvimento de nova fórmula | F269: 0.66666667 | G269: 0.75 | H269: 0.083333333 | I269: 44546 | J269: TRUE | L269: =IF(VLOOKUP(C269,Projetos!A:L,12,false)=TRUE,TRUE,FALSE) -> TRUE | M269: 33.159727 | N269: =IFERROR(IF(AND(J269=TRUE,O269=TRUE,YEAR(F269)<2021),H269,"")*(M269*24),0) -> 66.319455 | O269: TRUE
B270: Ana Claudia Zanini | C270: Diamax pó | D270: =vlookup(C270,'Classificação p pessoal'!F:G,2,false) -> NP | E270: Pesquisa e desenvolvimento de nova fórmula | F270: 0.58333333 | G270: 0.66666667 | H270: 0.083333333 | I270: 44551 | J270: TRUE | L270: =IF(VLOOKUP(C270,Projetos!A:L,12,false)=TRUE,TRUE,FALSE) -> TRUE | M270: 33.159727 | N270: =IFERROR(IF(AND(J270=TRUE,O270=TRUE,YEAR(F270)<2021),H270,"")*(M270*24),0) -> 66.319455 | O270: TRUE
...

Sheet Pessoal
A2: Pessoal
A4: Salario bruto | G4: planilha RH | H4: planilha RH | I4: planilha RH | J4: planilha RH | K4: planilha RH | L4: planilha RH | M4: planilha RH | N4: planilha RH | O4: planilha RH | P4: planilha RH | Q4: RH atualizou online | R4: RH atualizou online | S4: =(T4/12)*24 -> 170 | T4: =(SUM(G27:R27)*8)/24 -> 85
A5: Nome Completo | B5: CPF | C5: notas | D5: Cargo/função | E5: Formação | F5: Attachments | G5: Salário 01 | H5: Salário 02 | I5: Salário 03 | J5: Salário 04 | K5: Salário 05 | L5: Salário 06 | M5: Salário 07 | N5: Salário 08 | O5: Salário 09 | P5: Salário 10 | Q5: Salário 11 | R5: Salário 12 | S5: PD&I time | T5: PD&I (%) | U5: Classificação | V5: Pesquisador
A6: Ana Claudia Zanini | B6: 076.046.519-33 | D6: Analista Científico | E6: Mestrado | G6: 3599.04 | H6: 3599.04 | I6: 3599.04 | J6: 3599.04 | K6: 3814.98 | L6: 3814.98 | M6: 3814.98 | N6: 3814.98 | O6: 3814.98 | P6: 3814.98 | Q6: 3814.98 | R6: 3814.98 | S6: =IFERROR(__xludf.DUMMYFUNCTION("IFERROR(if(V6=true, SUM(FILTER(Timesheet!$H:$H,Timesheet!J:J = TRUE,Timesheet!O:O = TRUE,Timesheet!B:B = A6,Timesheet!F:F < DATE(2022,1,1))),0),0)"),48.062499999999964) -> 48.0625 | T6: =S6/$T$4 -> 0.56544118 | U6: =IF(T6<80%,"Parcial","Exclusivo") -> Parcial | V6: TRUE
A7: Ana Paula Celes | B7: 759.837.297-72 | D7: Diretora Técnica | E7: Pós graduado | F7: PJ | G7: 31767.65 | H7: 31767.65 | I7: 316767.65 | J7: 31767.65 | K7: 31767.65 | L7: 31767.65 | M7: 31767.65 | N7: 31767.65 | O7: 31767.65 | P7: 31767.65 | Q7: 31767.65 | R7: 31767.65 | S7: =IFERROR(__xludf.DUMMYFUNCTION("IFERROR(if(V7=true, SUM(FILTER(Timesheet!$H:$H,Timesheet!J:J = TRUE,Timesheet!O:O = TRUE,Timesheet!B:B = A7,Timesheet!F:F < DATE(2022,1,1))),0),0)"),0.0) -> 0 | T7: =S7/$T$4 -> 0 | U7: =IF(T7<80%,"Parcial","Exclusivo") -> Parcial | V7: TRUE
A8: Arianna Schreiber | B8: 066.466.799-67 | D8: Gerente Mkt | E8: Pós graduado | G8: 8878.45 | H8: 8878.45 | I8: 8878.45 | J8: 10095 | K8: 10700.7 | L8: 10700.7 | M8: 10700.7 | N8: 10700.7 | O8: 10700.7 | P8: 10700.7 | Q8: 10700.7 | R8: 10700.7 | S8: =IFERROR(__xludf.DUMMYFUNCTION("IFERROR(if(V8=true, SUM(FILTER(Timesheet!$H:$H,Timesheet!J:J = TRUE,Timesheet!O:O = TRUE,Timesheet!B:B = A8,Timesheet!F:F < DATE(2022,1,1))),0),0)"),1.2916666666666667) -> 1.2916667 | T8: =S8/$T$4 -> 0.015196078 | U8: =IF(T8<80%,"Parcial","Exclusivo") -> Parcial | V8: TRUE
A9: Camila Mendes Pereira | B9: 083.832.289-10 | D9: Assistente de P&D | E9: Superior Completo | G9: 2816.69 | H9: 2816.69 | I9: 2816.69 | J9: 3367.8 | K9: 3569.87 | L9: 3569.87 | M9: 3568.87 | N9: 3569.87 | O9: 3569.87 | P9: 3569.87 | Q9: 3569.87 | R9: 3569.87 | S9: =IFERROR(__xludf.DUMMYFUNCTION("IFERROR(if(V9=true, SUM(FILTER(Timesheet!$H:$H,Timesheet!J:J = TRUE,Timesheet!O:O = TRUE,Timesheet!B:B = A9,Timesheet!F:F < DATE(2022,1,1))),0),0)"),27.11111111111111) -> 27.111111 | T9: =S9/$T$4 -> 0.31895425 | U9: =IF(T9<80%,"Parcial","Exclusivo") -> Parcial | V9: TRUE
A10: Gabriela Faria de Oliveira | B10: 087.823.469-17 | D10: Analista Científico | E10: Superior Completo | G10: 3773.89 | H10: 3773.89 | I10: 3773.89 | J10: 3773.89 | K10: 4000.32 | L10: 4000.32 | M10: 4000.32 | N10: 4000.32 | O10: 4000.32 | P10: 4000.32 | Q10: 4000.32 | R10: 4000.32 | S10: =IFERROR(__xludf.DUMMYFUNCTION("IFERROR(if(V10=true, SUM(FILTER(Timesheet!$H:$H,Timesheet!J:J = TRUE,Timesheet!O:O = TRUE,Timesheet!B:B = A10,Timesheet!F:F < DATE(2022,1,1))),0),0)"),27.85416666666664) -> 27.854167 | T10: =S10/$T$4 -> 0.32769608 | U10: =IF(T10<80%,"Parcial","Exclusivo") -> Parcial | V10: TRUE
A11: Hellin dos Santos | B11: 058.544.839-63 | D11: Gerente Cientifico | E11: Mestrado | G11: 12487.72 | H11: 12487.72 | I11: 12487.72 | J11: 12487.72 | K11: 13236.98 | L11: 13236.98 | M11: 13236.98 | N11: 13236.98 | O11: 14358.3 | P11: 14358.3 | Q11: 14358.3 | R11: 14358.3 | S11: =IFERROR(__xludf.DUMMYFUNCTION("IFERROR(if(V11=true, SUM(FILTER(Timesheet!$H:$H,Timesheet!J:J = TRUE,Timesheet!O:O = TRUE,Timesheet!B:B = A11,Timesheet!F:F < DATE(2022,1,1))),0),0)"),0.0) -> 0 | T11: =S11/$T$4 -> 0 | U11: =IF(T11<80%,"Parcial","Exclusivo") -> Parcial | V11: TRUE
A12: Juliana Lamas Roberto | B12: 317.875.738-42 | D12: Especialista em Estudos de Estabilidade | E12: Pós graduado | G12: 8000 | H12: 8000 | I12: 8000 | J12: 8000 | K12: 8480 | L12: 8480 | M12: 8480 | N12: 8480 | O12: 8480 | P12: 8480 | Q12: 8480 | R12: 8480 | S12: =IFERROR(__xludf.DUMMYFUNCTION("IFERROR(if(V12=true, SUM(FILTER(Timesheet!$H:$H,Timesheet!J:J = TRUE,Timesheet!O:O = TRUE,Timesheet!B:B = A12,Timesheet!F:F < DATE(2022,1,1))),0),0)"),64.8902777777778) -> 64.890278 | T12: =S12/$T$4 -> 0.76341503 | U12: =IF(T12<80%,"Parcial","Exclusivo") -> Parcial | V12: TRUE
A13: Kézia Rithássia Piccoli | B13: 077.680.169-47 | D13: Analista de GQ | E13: Pós graduado | G13: 4071.12 | H13: 4071.12 | I13: 4071.12 | J13: 4071.12 | K13: 4315.39 | L13: 4315.39 | M13: 4315.39 | N13: 4315.39 | O13: 4315.39 | P13: 4315.39 | Q13: 4315.39 | R13: 4315.39 | S13: =IFERROR(__xludf.DUMMYFUNCTION("IFERROR(if(V13=true, SUM(FILTER(Timesheet!$H:$H,Timesheet!J:J = TRUE,Timesheet!O:O = TRUE,Timesheet!B:B = A13,Timesheet!F:F < DATE(2022,1,1))),0),0)"),30.357638888888886) -> 30.357639 | T13: =S13/$T$4 -> 0.35714869 | U13: =IF(T13<80%,"Parcial","Exclusivo") -> Parcial | V13: TRUE
A14: Lizianne Shmeil | B14: 052.485.199-93 | D14: Analista P&D | E14: Superior Completo | G14: 4995.55 | H14: 4995.55 | I14: 4995.55 | J14: 4995.55 | K14: 5295.28 | L14: 5295.28 | M14: 5295.28 | N14: 5295.28 | O14: 6038.25 | P14: 6038.25 | Q14: 6038.25 | R14: 6038.25 | S14: =IFERROR(__xludf.DUMMYFUNCTION("IFERROR(if(V14=true, SUM(FILTER(Timesheet!$H:$H,Timesheet!J:J = TRUE,Timesheet!O:O = TRUE,Timesheet!B:B = A14,Timesheet!F:F < DATE(2022,1,1))),0),0)"),60.95833333333327) -> 60.958333 | T14: =S14/$T$4 -> 0.71715686 | U14: =IF(T14<80%,"Parcial","Exclusivo") -> Parcial | V14: TRUE
A15: Luciana Dutra | B15: 186.586.978-35 | D15: Gerente Técnica | E15: Pós graduado | G15: 17611.04 | H15: 17611.04 | I15: 17611.04 | J15: 17611.04 | K15: 17611.04 | L15: 17611.04 | M15: 18667.7 | N15: 18667.7 | O15: 18667.7 | P15: 18668 | Q15: 18668 | R15: 18668 | S15: =IFERROR(__xludf.DUMMYFUNCTION("IFERROR(if(V15=true, SUM(FILTER(Timesheet!$H:$H,Timesheet!J:J = TRUE,Timesheet!O:O = TRUE,Timesheet!B:B = A15,Timesheet!F:F < DATE(2022,1,1))),0),0)"),0.0) -> 0 | T15: =S15/$T$4 -> 0 | U15: =IF(T15<80%,"Parcial","Exclusivo") -> Parcial | V15: TRUE
A16: Márcio Henrique Nogueira | B16: 088.869.216-16 | D16: Analista de P&D | E16: Pós graduado | G16: 5500 | H16: 5500 | I16: 5500 | J16: 5500 | K16: 6000 | L16: 6000 | M16: 6000 | N16: 6000 | O16: 6000 | P16: 6000 | Q16: 6000 | R16: 6000 | S16: =IFERROR(__xludf.DUMMYFUNCTION("IFERROR(if(V16=true, SUM(FILTER(Timesheet!$H:$H,Timesheet!J:J = TRUE,Timesheet!O:O = TRUE,Timesheet!B:B = A16,Timesheet!F:F < DATE(2022,1,1))),0),0)"),42.29861111111107) -> 42.298611 | T16: =S16/$T$4 -> 0.49763072 | U16: =IF(T16<80%,"Parcial","Exclusivo") -> Parcial | V16: TRUE
A17: Marianne Stigar | B17: 066.424.199-95 | D17: Coord. GQ | E17: Pós graduado | G17: 5093.12 | H17: 5093.12 | I17: 5093.12 | J17: 5093.12 | K17: 5398.71 | L17: 5398.71 | M17: 5978 | N17: 5978 | O17: 5978 | P17: 5978 | Q17: 5978 | R17: 5978 | S17: =IFERROR(__xludf.DUMMYFUNCTION("IFERROR(if(V17=true, SUM(FILTER(Timesheet!$H:$H,Timesheet!J:J = TRUE,Timesheet!O:O = TRUE,Timesheet!B:B = A17,Timesheet!F:F < DATE(2022,1,1))),0),0)"),0.0) -> 0 | T17: =S17/$T$4 -> 0 | U17: =IF(T17<80%,"Parcial","Exclusivo") -> Parcial | V17: TRUE
A18: Tahuany Leite | B18: 086.481.459-37 | D18: Analista MKT | E18: Pós graduado | G18: 3963.02 | H18: 3963.02 | I18: 3963.02 | J18: 3963.02 | K18: 3963.02 | L18: 3963.02 | M18: 4200.8 | N18: 4200.8 | O18: 4200.8 | P18: 4454.72 | Q18: 4454.72 | R18: 4454.72 | S18: =IFERROR(__xludf.DUMMYFUNCTION("IFERROR(if(V18=true, SUM(FILTER(Timesheet!$H:$H,Timesheet!J:J = TRUE,Timesheet!O:O = TRUE,Timesheet!B:B = A18,Timesheet!F:F < DATE(2022,1,1))),0),0)"),0.0) -> 0 | T18: =S18/$T$4 -> 0 | U18: =IF(T18<80%,"Parcial","Exclusivo") -> Parcial | V18: TRUE
A21: Cálculo do custo/hora
A23: Encargos sobre folha | H23: INSS | I23: Patronal | J23: 0.2
A24: INSS | B24: FGTS | C24: Férias | D24: 13º | E24: Total | I24: Terceiros | J24: 0.058 | T24: =IFERROR(__xludf.DUMMYFUNCTION("sum(FILTER(T29:T39,match(A29:A39,FILTER(A6:A18,U6:U18 = ""Parcial""))))"),356413.40177364694) -> 356413.4
A25: =sum(J23:J25) -> 0.273 | B25: 0.08 | C25: =((1+(1/3))+A25+B25)/12 -> 0.14052778 | D25: =(1+A25+B25)/12 -> 0.11275 | E25: =sum(A25:D25) -> 0.60627778 | I25: RAT | J25: 0.015 | T25: =IFERROR(__xludf.DUMMYFUNCTION("IFERROR(sum(FILTER(T29:T39,match(A29:A39,FILTER(A6:A18,U6:U18 = ""Exclusivo"")))),0)"),0.0) -> 0
G27: =NETWORKDAYS(DATE(2021,(LEFT(G$28,2)+0),1),DATE(2021,(LEFT(G$28,2)+0)+1,0),$A$45:$A$53) -> 21 | H27: =NETWORKDAYS(DATE(2021,(LEFT(H$28,2)+0),1),DATE(2021,(LEFT(H$28,2)+0)+1,0),$A$45:$A$53) -> 20 | I27: =NETWORKDAYS(DATE(2021,(LEFT(I$28,2)+0),1),DATE(2021,(LEFT(I$28,2)+0)+1,0),$A$45:$A$53) -> 21 | J27: =NETWORKDAYS(DATE(2021,(LEFT(J$28,2)+0),1),DATE(2021,(LEFT(J$28,2)+0)+1,0),$A$45:$A$53) -> 22 | K27: =NETWORKDAYS(DATE(2021,(LEFT(K$28,2)+0),1),DATE(2021,(LEFT(K$28,2)+0)+1,0),$A$45:$A$53) -> 21 | L27: =NETWORKDAYS(DATE(2021,(LEFT(L$28,2)+0),1),DATE(2021,(LEFT(L$28,2)+0)+1,0),$A$45:$A$53) -> 22 | M27: =NETWORKDAYS(DATE(2021,(LEFT(M$28,2)+0),1),DATE(2021,(LEFT(M$28,2)+0)+1,0),$A$45:$A$53) -> 21 | N27: =NETWORKDAYS(DATE(2021,(LEFT(N$28,2)+0),1),DATE(2021,(LEFT(N$28,2)+0)+1,0),$A$45:$A$53) -> 21 | ... R27: =NETWORKDAYS(DATE(2021,(LEFT(R$28,2)+0),1),DATE(2021,(LEFT(R$28,2)+0)+1,0),$A$45:$A$53) -> 21 | S27: =sum(S29:S39) -> 356413.4 | T27: =sum(T29:T39) -> 356413.4 | U27: =T27-S27 -> 0
A28: Nome Completo | D28: {=U5:U18} -> Classificação | E28: {=E5:E18} -> Formação | F28: Custo / Hora | G28: 44227 | H28: 44255 | I28: 44286 | J28: 44316 | K28: 44347 | L28: 44377 | M28: 44408 | N28: 44439 | O28: 44469 | P28: 44500 | Q28: 44530 | R28: 44561 | S28: PD&I R$ | T28: Aprovado R$ | U28: Pesquisador
A29: {=unique(A6:A18)} -> Ana Claudia Zanini | D29: Parcial | E29: Mestrado | G29: =vlookup($A29,$A$6:$R$18,month(G$28)+6)*(1+$E$25)/(G$27*8.8) -> 31.282781 | H29: =vlookup($A29,$A$6:$R$18,month(H$28)+6)*(1+$E$25)/(H$27*8.8) -> 32.84692 | I29: =vlookup($A29,$A$6:$R$18,month(I$28)+6)*(1+$E$25)/(I$27*8.8) -> 31.282781 | J29: =vlookup($A29,$A$6:$R$18,month(J$28)+6)*(1+$E$25)/(J$27*8.8) -> 29.860837 | K29: =vlookup($A29,$A$6:$R$18,month(K$28)+6)*(1+$E$25)/(K$27*8.8) -> 33.159727 | L29: =vlookup($A29,$A$6:$R$18,month(L$28)+6)*(1+$E$25)/(L$27*8.8) -> 31.652467 | M29: =vlookup($A29,$A$6:$R$18,month(M$28)+6)*(1+$E$25)/(M$27*8.8) -> 33.159727 | N29: =vlookup($A29,$A$6:$R$18,month(N$28)+6)*(1+$E$25)/(N$27*8.8) -> 33.159727 | ... R29: =vlookup($A29,$A$6:$R$18,month(R$28)+6)*(1+$E$25)/(R$27*8.8) -> 33.159727 | S29: =SUMIF(Timesheet!B:B,A29,Timesheet!N:N) -> 38249.745 | T29: =SUMIF(U29,TRUE,S29) -> 38249.745 | U29: TRUE
A30: Ana Paula Celes | D30: Parcial | E30: Pós graduado | G30: =G7*(((1/3)*1/12)+1)/(G27*(44/5)) -> 176.67795 | H30: =H7*(((1/3)*1/12)+1)/(H27*(44/5)) -> 185.51184 | I30: =I7*(((1/3)*1/12)+1)/(I27*(44/5)) -> 1761.7248 | J30: =J7*(((1/3)*1/12)+1)/(J27*(44/5)) -> 168.64713 | K30: =K7*(((1/3)*1/12)+1)/(K27*(44/5)) -> 176.67795 | L30: =L7*(((1/3)*1/12)+1)/(L27*(44/5)) -> 168.64713 | M30: =M7*(((1/3)*1/12)+1)/(M27*(44/5)) -> 176.67795 | N30: =N7*(((1/3)*1/12)+1)/(N27*(44/5)) -> 176.67795 | ... R30: =R7*(((1/3)*1/12)+1)/(R27*(44/5)) -> 176.67795 | S30: =SUMIF(Timesheet!B:B,A30,Timesheet!N:N) -> 0 | T30: =SUMIF(U30,TRUE,S30) -> 0 | U30: TRUE
A31: Arianna Schreiber | D31: Parcial | E31: Pós graduado | G31: =vlookup($A31,$A$6:$R$18,month(G$28)+6)*(1+$E$25)/(G$27*8.8) -> 77.171304 | H31: =vlookup($A31,$A$6:$R$18,month(H$28)+6)*(1+$E$25)/(H$27*8.8) -> 81.029869 | I31: =vlookup($A31,$A$6:$R$18,month(I$28)+6)*(1+$E$25)/(I$27*8.8) -> 77.171304 | J31: =vlookup($A31,$A$6:$R$18,month(J$28)+6)*(1+$E$25)/(J$27*8.8) -> 83.757098 | K31: =vlookup($A31,$A$6:$R$18,month(K$28)+6)*(1+$E$25)/(K$27*8.8) -> 93.010263 | L31: =vlookup($A31,$A$6:$R$18,month(L$28)+6)*(1+$E$25)/(L$27*8.8) -> 88.782524 | M31: =vlookup($A31,$A$6:$R$18,month(M$28)+6)*(1+$E$25)/(M$27*8.8) -> 93.010263 | N31: =vlookup($A31,$A$6:$R$18,month(N$28)+6)*(1+$E$25)/(N$27*8.8) -> 93.010263 | ... R31: =vlookup($A31,$A$6:$R$18,month(R$28)+6)*(1+$E$25)/(R$27*8.8) -> 93.010263 | S31: =SUMIF(Timesheet!B:B,A31,Timesheet!N:N) -> 2883.3182 | T31: =SUMIF(U31,TRUE,S31) -> 2883.3182 | U31: TRUE
A32: Camila Mendes Pereira | D32: Parcial | E32: Superior Completo | G32: =vlookup($A32,$A$6:$R$18,month(G$28)+6)*(1+$E$25)/(G$27*8.8) -> 24.482611 | H32: =vlookup($A32,$A$6:$R$18,month(H$28)+6)*(1+$E$25)/(H$27*8.8) -> 25.706742 | I32: =vlookup($A32,$A$6:$R$18,month(I$28)+6)*(1+$E$25)/(I$27*8.8) -> 24.482611 | J32: =vlookup($A32,$A$6:$R$18,month(J$28)+6)*(1+$E$25)/(J$27*8.8) -> 27.942264 | K32: =vlookup($A32,$A$6:$R$18,month(K$28)+6)*(1+$E$25)/(K$27*8.8) -> 31.029236 | L32: =vlookup($A32,$A$6:$R$18,month(L$28)+6)*(1+$E$25)/(L$27*8.8) -> 29.618816 | M32: =vlookup($A32,$A$6:$R$18,month(M$28)+6)*(1+$E$25)/(M$27*8.8) -> 31.020544 | N32: =vlookup($A32,$A$6:$R$18,month(N$28)+6)*(1+$E$25)/(N$27*8.8) -> 31.029236 | ... R32: =vlookup($A32,$A$6:$R$18,month(R$28)+6)*(1+$E$25)/(R$27*8.8) -> 31.029236 | S32: =SUMIF(Timesheet!B:B,A32,Timesheet!N:N) -> 20189.69 | T32: =SUMIF(U32,TRUE,S32) -> 20189.69 | U32: TRUE
A33: Gabriela Faria de Oliveira | D33: Parcial | E33: Superior Completo | G33: =vlookup($A33,$A$6:$R$18,month(G$28)+6)*(1+$E$25)/(G$27*8.8) -> 32.802574 | H33: =vlookup($A33,$A$6:$R$18,month(H$28)+6)*(1+$E$25)/(H$27*8.8) -> 34.442703 | I33: =vlookup($A33,$A$6:$R$18,month(I$28)+6)*(1+$E$25)/(I$27*8.8) -> 32.802574 | J33: =vlookup($A33,$A$6:$R$18,month(J$28)+6)*(1+$E$25)/(J$27*8.8) -> 31.311548 | K33: =vlookup($A33,$A$6:$R$18,month(K$28)+6)*(1+$E$25)/(K$27*8.8) -> 34.770699 | L33: =vlookup($A33,$A$6:$R$18,month(L$28)+6)*(1+$E$25)/(L$27*8.8) -> 33.190212 | M33: =vlookup($A33,$A$6:$R$18,month(M$28)+6)*(1+$E$25)/(M$27*8.8) -> 34.770699 | N33: =vlookup($A33,$A$6:$R$18,month(N$28)+6)*(1+$E$25)/(N$27*8.8) -> 34.770699 | ... R33: =vlookup($A33,$A$6:$R$18,month(R$28)+6)*(1+$E$25)/(R$27*8.8) -> 34.770699 | S33: =SUMIF(Timesheet!B:B,A33,Timesheet!N:N) -> 23244.212 | T33: =SUMIF(U33,TRUE,S33) -> 23244.212 | U33: TRUE
A34: Hellin dos Santos | D34: Parcial | E34: Mestrado | G34: =vlookup($A34,$A$6:$R$18,month(G$28)+6)*(1+$E$25)/(G$27*8.8) -> 108.543 | H34: =vlookup($A34,$A$6:$R$18,month(H$28)+6)*(1+$E$25)/(H$27*8.8) -> 113.97015 | I34: =vlookup($A34,$A$6:$R$18,month(I$28)+6)*(1+$E$25)/(I$27*8.8) -> 108.543 | J34: =vlookup($A34,$A$6:$R$18,month(J$28)+6)*(1+$E$25)/(J$27*8.8) -> 103.60923 | K34: =vlookup($A34,$A$6:$R$18,month(K$28)+6)*(1+$E$25)/(K$27*8.8) -> 115.05556 | L34: =vlookup($A34,$A$6:$R$18,month(L$28)+6)*(1+$E$25)/(L$27*8.8) -> 109.82576 | M34: =vlookup($A34,$A$6:$R$18,month(M$28)+6)*(1+$E$25)/(M$27*8.8) -> 115.05556 | N34: =vlookup($A34,$A$6:$R$18,month(N$28)+6)*(1+$E$25)/(N$27*8.8) -> 115.05556 | ... R34: =vlookup($A34,$A$6:$R$18,month(R$28)+6)*(1+$E$25)/(R$27*8.8) -> 124.80205 | S34: =SUMIF(Timesheet!B:B,A34,Timesheet!N:N) -> 0 | T34: =SUMIF(U34,TRUE,S34) -> 0 | U34: TRUE
A35: Juliana Lamas Roberto | D35: Parcial | E35: Pós graduado | G35: =vlookup($A35,$A$6:$R$18,month(G$28)+6)*(1+$E$25)/(G$27*8.8) -> 69.535835 | H35: =vlookup($A35,$A$6:$R$18,month(H$28)+6)*(1+$E$25)/(H$27*8.8) -> 73.012626 | I35: =vlookup($A35,$A$6:$R$18,month(I$28)+6)*(1+$E$25)/(I$27*8.8) -> 69.535835 | J35: =vlookup($A35,$A$6:$R$18,month(J$28)+6)*(1+$E$25)/(J$27*8.8) -> 66.375115 | K35: =vlookup($A35,$A$6:$R$18,month(K$28)+6)*(1+$E$25)/(K$27*8.8) -> 73.707985 | L35: =vlookup($A35,$A$6:$R$18,month(L$28)+6)*(1+$E$25)/(L$27*8.8) -> 70.357622 | M35: =vlookup($A35,$A$6:$R$18,month(M$28)+6)*(1+$E$25)/(M$27*8.8) -> 73.707985 | N35: =vlookup($A35,$A$6:$R$18,month(N$28)+6)*(1+$E$25)/(N$27*8.8) -> 73.707985 | ... R35: =vlookup($A35,$A$6:$R$18,month(R$28)+6)*(1+$E$25)/(R$27*8.8) -> 73.707985 | S35: =SUMIF(Timesheet!B:B,A35,Timesheet!N:N) -> 114790.36 | T35: =SUMIF(U35,TRUE,S35) -> 114790.36 | U35: TRUE
A36: Kézia Rithássia Piccoli | D36: Parcial | E36: Pós graduado | G36: =vlookup($A36,$A$6:$R$18,month(G$28)+6)*(1+$E$25)/(G$27*8.8) -> 35.386091 | H36: =vlookup($A36,$A$6:$R$18,month(H$28)+6)*(1+$E$25)/(H$27*8.8) -> 37.155395 | I36: =vlookup($A36,$A$6:$R$18,month(I$28)+6)*(1+$E$25)/(I$27*8.8) -> 35.386091 | J36: =vlookup($A36,$A$6:$R$18,month(J$28)+6)*(1+$E$25)/(J$27*8.8) -> 33.777632 | K36: =vlookup($A36,$A$6:$R$18,month(K$28)+6)*(1+$E$25)/(K$27*8.8) -> 37.509281 | L36: =vlookup($A36,$A$6:$R$18,month(L$28)+6)*(1+$E$25)/(L$27*8.8) -> 35.804313 | M36: =vlookup($A36,$A$6:$R$18,month(M$28)+6)*(1+$E$25)/(M$27*8.8) -> 37.509281 | N36: =vlookup($A36,$A$6:$R$18,month(N$28)+6)*(1+$E$25)/(N$27*8.8) -> 37.509281 | ... R36: =vlookup($A36,$A$6:$R$18,month(R$28)+6)*(1+$E$25)/(R$27*8.8) -> 37.509281 | S36: =SUMIF(Timesheet!B:B,A36,Timesheet!N:N) -> 27328.637 | T36: =SUMIF(U36,TRUE,S36) -> 27328.637 | U36: TRUE
A37: Lizianne Shmeil | D37: Parcial | E37: Superior Completo | G37: =vlookup($A37,$A$6:$R$18,month(G$28)+6)*(1+$E$25)/(G$27*8.8) -> 43.421217 | H37: =vlookup($A37,$A$6:$R$18,month(H$28)+6)*(1+$E$25)/(H$27*8.8) -> 45.592278 | I37: =vlookup($A37,$A$6:$R$18,month(I$28)+6)*(1+$E$25)/(I$27*8.8) -> 43.421217 | J37: =vlookup($A37,$A$6:$R$18,month(J$28)+6)*(1+$E$25)/(J$27*8.8) -> 41.447526 | K37: =vlookup($A37,$A$6:$R$18,month(K$28)+6)*(1+$E$25)/(K$27*8.8) -> 46.026464 | L37: =vlookup($A37,$A$6:$R$18,month(L$28)+6)*(1+$E$25)/(L$27*8.8) -> 43.934352 | M37: =vlookup($A37,$A$6:$R$18,month(M$28)+6)*(1+$E$25)/(M$27*8.8) -> 46.026464 | N37: =vlookup($A37,$A$6:$R$18,month(N$28)+6)*(1+$E$25)/(N$27*8.8) -> 46.026464 | ... R37: =vlookup($A37,$A$6:$R$18,month(R$28)+6)*(1+$E$25)/(R$27*8.8) -> 52.484344 | S37: =SUMIF(Timesheet!B:B,A37,Timesheet!N:N) -> 76784.595 | T37: =SUMIF(U37,TRUE,S37) -> 76784.595 | U37: TRUE
A38: Luciana Dutra | D38: Parcial | E38: Pós graduado | G38: =vlookup($A38,$A$6:$R$18,month(G$28)+6)*(1+$E$25)/(G$27*8.8) -> 153.0748 | H38: =vlookup($A38,$A$6:$R$18,month(H$28)+6)*(1+$E$25)/(H$27*8.8) -> 160.72854 | I38: =vlookup($A38,$A$6:$R$18,month(I$28)+6)*(1+$E$25)/(I$27*8.8) -> 153.0748 | J38: =vlookup($A38,$A$6:$R$18,month(J$28)+6)*(1+$E$25)/(J$27*8.8) -> 146.11685 | K38: =vlookup($A38,$A$6:$R$18,month(K$28)+6)*(1+$E$25)/(K$27*8.8) -> 153.0748 | L38: =vlookup($A38,$A$6:$R$18,month(L$28)+6)*(1+$E$25)/(L$27*8.8) -> 146.11685 | M38: =vlookup($A38,$A$6:$R$18,month(M$28)+6)*(1+$E$25)/(M$27*8.8) -> 162.25926 | N38: =vlookup($A38,$A$6:$R$18,month(N$28)+6)*(1+$E$25)/(N$27*8.8) -> 162.25926 | ... R38: =vlookup($A38,$A$6:$R$18,month(R$28)+6)*(1+$E$25)/(R$27*8.8) -> 162.26187 | S38: =SUMIF(Timesheet!B:B,A38,Timesheet!N:N) -> 0 | T38: =SUMIF(U38,TRUE,S38) -> 0 | U38: TRUE
A39: Márcio Henrique Nogueira | D39: Parcial | E39: Pós graduado | G39: =vlookup($A39,$A$6:$R$18,month(G$28)+6)*(1+$E$25)/(G$27*8.8) -> 47.805886 | H39: =vlookup($A39,$A$6:$R$18,month(H$28)+6)*(1+$E$25)/(H$27*8.8) -> 50.196181 | I39: =vlookup($A39,$A$6:$R$18,month(I$28)+6)*(1+$E$25)/(I$27*8.8) -> 47.805886 | J39: =vlookup($A39,$A$6:$R$18,month(J$28)+6)*(1+$E$25)/(J$27*8.8) -> 45.632891 | K39: =vlookup($A39,$A$6:$R$18,month(K$28)+6)*(1+$E$25)/(K$27*8.8) -> 52.151876 | L39: =vlookup($A39,$A$6:$R$18,month(L$28)+6)*(1+$E$25)/(L$27*8.8) -> 49.781336 | M39: =vlookup($A39,$A$6:$R$18,month(M$28)+6)*(1+$E$25)/(M$27*8.8) -> 52.151876 | N39: =vlookup($A39,$A$6:$R$18,month(N$28)+6)*(1+$E$25)/(N$27*8.8) -> 52.151876 | ... R39: =vlookup($A39,$A$6:$R$18,month(R$28)+6)*(1+$E$25)/(R$27*8.8) -> 52.151876 | S39: =SUMIF(Timesheet!B:B,A39,Timesheet!N:N) -> 52942.846 | T39: =SUMIF(U39,TRUE,S39) -> 52942.846 | U39: TRUE
A40: Marianne Stigar | D40: Parcial | E40: Pós graduado | G40: =vlookup($A40,$A$6:$R$18,month(G$28)+6)*(1+$E$25)/(G$27*8.8) -> 44.269294 | H40: =vlookup($A40,$A$6:$R$18,month(H$28)+6)*(1+$E$25)/(H$27*8.8) -> 46.482758 | I40: =vlookup($A40,$A$6:$R$18,month(I$28)+6)*(1+$E$25)/(I$27*8.8) -> 44.269294 | J40: =vlookup($A40,$A$6:$R$18,month(J$28)+6)*(1+$E$25)/(J$27*8.8) -> 42.257053 | K40: =vlookup($A40,$A$6:$R$18,month(K$28)+6)*(1+$E$25)/(K$27*8.8) -> 46.925476 | L40: =vlookup($A40,$A$6:$R$18,month(L$28)+6)*(1+$E$25)/(L$27*8.8) -> 44.792499 | M40: =vlookup($A40,$A$6:$R$18,month(M$28)+6)*(1+$E$25)/(M$27*8.8) -> 51.960652 | N40: =vlookup($A40,$A$6:$R$18,month(N$28)+6)*(1+$E$25)/(N$27*8.8) -> 51.960652 | ... R40: =vlookup($A40,$A$6:$R$18,month(R$28)+6)*(1+$E$25)/(R$27*8.8) -> 51.960652 | S40: =SUMIF(Timesheet!B:B,A40,Timesheet!N:N) -> 0 | T40: =SUMIF(U40,TRUE,S40) -> 0 | U40: TRUE
A41: Tahuany Leite | D41: Parcial | E41: Pós graduado | G41: =vlookup($A41,$A$6:$R$18,month(G$28)+6)*(1+$E$25)/(G$27*8.8) -> 34.446488 | H41: =vlookup($A41,$A$6:$R$18,month(H$28)+6)*(1+$E$25)/(H$27*8.8) -> 36.168812 | I41: =vlookup($A41,$A$6:$R$18,month(I$28)+6)*(1+$E$25)/(I$27*8.8) -> 34.446488 | J41: =vlookup($A41,$A$6:$R$18,month(J$28)+6)*(1+$E$25)/(J$27*8.8) -> 32.880738 | K41: =vlookup($A41,$A$6:$R$18,month(K$28)+6)*(1+$E$25)/(K$27*8.8) -> 34.446488 | L41: =vlookup($A41,$A$6:$R$18,month(L$28)+6)*(1+$E$25)/(L$27*8.8) -> 32.880738 | M41: =vlookup($A41,$A$6:$R$18,month(M$28)+6)*(1+$E$25)/(M$27*8.8) -> 36.513267 | N41: =vlookup($A41,$A$6:$R$18,month(N$28)+6)*(1+$E$25)/(N$27*8.8) -> 36.513267 | ... R41: =vlookup($A41,$A$6:$R$18,month(R$28)+6)*(1+$E$25)/(R$27*8.8) -> 38.720334 | S41: =SUMIF(Timesheet!B:B,A41,Timesheet!N:N) -> 0 | T41: =SUMIF(U41,TRUE,S41) -> 0 | U41: TRUE
A43: Feriados
A45: 44197 | B45: sexta-feira | C45: Confraternização Universal
A46: 44288 | B46: sexta-feira | C46: Paixão de Cristo
A47: 44307 | B47: quarta-feira | C47: Tiradentes
A48: 44350 | B48: quinta-feira | C48: Corpus Christi
A49: 44446 | B49: terça-feira | C49: Independência do Brasil
A50: 44447 | B50: quarta-feira | C50: Aniversário de Curitiba
A51: 44481 | B51: terça-feira | C51: Nossa Sr.a Aparecida - Padroeira do Brasil
A52: 44502 | B52: terça-feira | C52: Finados
A53: 44515 | B53: segunda-feira | C53: Proclamação da República

Sheet #Form
B1: MATERIAIS | E1: =IFERROR(__xludf.DUMMYFUNCTION("iferror(SUM(FILTER(Investimentos!H:H,Investimentos!J:J = TRUE,Investimentos!L:L = ""Material"")),0)"),0.0) -> 0 | F1: =E1+E2 -> 740679.72
B2: SERVIÇOS | E2: =SUM(E6:E33) -> 740679.72
F4: Projeto 1 | G4: Projeto 2 | H4: Projeto 3
B5: Empresa | C5: Código FORMS | D5: CNPJ | E5: Valor | F5: Novos Produtos | G5: Melhoria de Produto | H5: Melhoria de Processo | J5: Descrição
B6: Fundação de Apoio à Universidade de São Paulo | C6: 3.1.15.1.2 | D6: 68.314.830/0001-27 | E6: 1872 | F6: =IFERROR(__xludf.DUMMYFUNCTION("sum(filter(Investimentos!$M:$M,Investimentos!$C:$C=$B6,Investimentos!$J:$J=TRUE))"),5550.04) -> 5550.04 | G6: =IFERROR(__xludf.DUMMYFUNCTION("sum(filter(Investimentos!$O:$O,Investimentos!$C:$C=$B6,Investimentos!$J:$J=TRUE))"),574.8) -> 574.8 | H6: =IFERROR(__xludf.DUMMYFUNCTION("sum(filter(Investimentos!$P:$P,Investimentos!$C:$C=$B6,Investimentos!$J:$J=TRUE))"),0.0) -> 0 | J6: Análise de Distribuição de Partículas
B7: Embrapa/CTAA | C7: 3.1.15.1.2 | D7: 68.314.830/0001-27 | E7: 2216.5 | F7: =IFERROR(__xludf.DUMMYFUNCTION("sum(filter(Investimentos!$M:$M,Investimentos!$C:$C=$B7,Investimentos!$J:$J=TRUE))"),"#N/A") -> #N/A | G7: =IFERROR(__xludf.DUMMYFUNCTION("sum(filter(Investimentos!$O:$O,Investimentos!$C:$C=$B7,Investimentos!$J:$J=TRUE))"),"#N/A") -> #N/A | H7: =IFERROR(__xludf.DUMMYFUNCTION("sum(filter(Investimentos!$P:$P,Investimentos!$C:$C=$B7,Investimentos!$J:$J=TRUE))"),"#N/A") -> #N/A | J7: Análise de Distribuição de Partículas
B8: Luciana Dutra | C8: 3.1.15.2.4 | D8: 186.586.978-35 | E8: 2087.64 | F8: =IFERROR(__xludf.DUMMYFUNCTION("sum(filter(Investimentos!$M:$M,Investimentos!$C:$C=$B8,Investimentos!$J:$J=TRUE))"),"#N/A") -> #N/A | G8: =IFERROR(__xludf.DUMMYFUNCTION("sum(filter(Investimentos!$O:$O,Investimentos!$C:$C=$B8,Investimentos!$J:$J=TRUE))"),"#N/A") -> #N/A | H8: =IFERROR(__xludf.DUMMYFUNCTION("sum(filter(Investimentos!$P:$P,Investimentos!$C:$C=$B8,Investimentos!$J:$J=TRUE))"),"#N/A") -> #N/A | J8: Despesas relacionadas aos testes realizados na Tetra Pak (Monte Mor/SP) e Embrapa/RJ
B9: Lizianne Shmeil | C9: 3.1.15.2.4 | D9: 052.485.199-93 | E9: 2478.73 | F9: =IFERROR(__xludf.DUMMYFUNCTION("sum(filter(Investimentos!$M:$M,Investimentos!$C:$C=$B9,Investimentos!$J:$J=TRUE))"),"#N/A") -> #N/A | G9: =IFERROR(__xludf.DUMMYFUNCTION("sum(filter(Investimentos!$O:$O,Investimentos!$C:$C=$B9,Investimentos!$J:$J=TRUE))"),"#N/A") -> #N/A | H9: =IFERROR(__xludf.DUMMYFUNCTION("sum(filter(Investimentos!$P:$P,Investimentos!$C:$C=$B9,Investimentos!$J:$J=TRUE))"),"#N/A") -> #N/A | J9: Despesas relacionadas aos testes realizados na Tetra Pak (Monte Mor/SP) e Embrapa/RJ
B10: Márcio Nogueira | C10: 3.1.15.2.4 | D10: 088.869.216-16 | E10: 2353.94 | F10: =IFERROR(__xludf.DUMMYFUNCTION("sum(filter(Investimentos!$M:$M,Investimentos!$C:$C=$B10,Investimentos!$J:$J=TRUE))"),5503.77) -> 5503.77 | G10: =IFERROR(__xludf.DUMMYFUNCTION("sum(filter(Investimentos!$O:$O,Investimentos!$C:$C=$B10,Investimentos!$J:$J=TRUE))"),0.0) -> 0 | H10: =IFERROR(__xludf.DUMMYFUNCTION("sum(filter(Investimentos!$P:$P,Investimentos!$C:$C=$B10,Investimentos!$J:$J=TRUE))"),0.0) -> 0 | J10: Despesas relacionadas aos testes realizados na Tetra Pak (Monte Mor/SP) e Embrapa/RJ
B11: CASA OMEGA NUTRIÇÃO LTDA | C11: 3.1.15.2.6 | D11: 32.749.234/0001-22 | E11: 69.5 | F11: =IFERROR(__xludf.DUMMYFUNCTION("sum(filter(Investimentos!$M:$M,Investimentos!$C:$C=$B11,Investimentos!$J:$J=TRUE))"),"#N/A") -> #N/A | G11: =IFERROR(__xludf.DUMMYFUNCTION("sum(filter(Investimentos!$O:$O,Investimentos!$C:$C=$B11,Investimentos!$J:$J=TRUE))"),"#N/A") -> #N/A | H11: =IFERROR(__xludf.DUMMYFUNCTION("sum(filter(Investimentos!$P:$P,Investimentos!$C:$C=$B11,Investimentos!$J:$J=TRUE))"),"#N/A") -> #N/A | J11: Insumos para análises de produtos de concorrentes
B12: RAIADROGASIL S/A | C12: 3.1.15.2.6 | D12: 61.585.865/1660-41 | E12: 124.99 | F12: =IFERROR(__xludf.DUMMYFUNCTION("sum(filter(Investimentos!$M:$M,Investimentos!$C:$C=$B12,Investimentos!$J:$J=TRUE))"),"#N/A") -> #N/A | G12: =IFERROR(__xludf.DUMMYFUNCTION("sum(filter(Investimentos!$O:$O,Investimentos!$C:$C=$B12,Investimentos!$J:$J=TRUE))"),"#N/A") -> #N/A | H12: =IFERROR(__xludf.DUMMYFUNCTION("sum(filter(Investimentos!$P:$P,Investimentos!$C:$C=$B12,Investimentos!$J:$J=TRUE))"),"#N/A") -> #N/A | J12: Insumos para análises de produtos de concorrentes
B13: Nutrihealth Comercio de Produtos Alimenticios | C13: 3.1.15.2.6 | D13: 14.942.128/0001-89 | E13: 107.84 | F13: =IFERROR(__xludf.DUMMYFUNCTION("sum(filter(Investimentos!$M:$M,Investimentos!$C:$C=$B13,Investimentos!$J:$J=TRUE))"),"#N/A") -> #N/A | G13: =IFERROR(__xludf.DUMMYFUNCTION("sum(filter(Investimentos!$O:$O,Investimentos!$C:$C=$B13,Investimentos!$J:$J=TRUE))"),"#N/A") -> #N/A | H13: =IFERROR(__xludf.DUMMYFUNCTION("sum(filter(Investimentos!$P:$P,Investimentos!$C:$C=$B13,Investimentos!$J:$J=TRUE))"),"#N/A") -> #N/A | J13: Insumos para análises de produtos de concorrentes
B14: NP Analytical Laboratories | C14: 3.1.15.2.6 | D14: NA | E14: 6734.39 | F14: =IFERROR(__xludf.DUMMYFUNCTION("sum(filter(Investimentos!$M:$M,Investimentos!$C:$C=$B14,Investimentos!$J:$J=TRUE))"),"#N/A") -> #N/A | G14: =IFERROR(__xludf.DUMMYFUNCTION("sum(filter(Investimentos!$O:$O,Investimentos!$C:$C=$B14,Investimentos!$J:$J=TRUE))"),"#N/A") -> #N/A | H14: =IFERROR(__xludf.DUMMYFUNCTION("sum(filter(Investimentos!$P:$P,Investimentos!$C:$C=$B14,Investimentos!$J:$J=TRUE))"),"#N/A") -> #N/A | J14: Insumos para análise de aminoácidos
B15: Laboratório ALAC Ltda | C15: 3.1.16.2.5 | D15: 94.088.952/0001-52 | E15: 63139.61 | F15: =IFERROR(__xludf.DUMMYFUNCTION("sum(filter(Investimentos!$M:$M,Investimentos!$C:$C=$B15,Investimentos!$J:$J=TRUE))"),"#N/A") -> #N/A | G15: =IFERROR(__xludf.DUMMYFUNCTION("sum(filter(Investimentos!$O:$O,Investimentos!$C:$C=$B15,Investimentos!$J:$J=TRUE))"),"#N/A") -> #N/A | H15: =IFERROR(__xludf.DUMMYFUNCTION("sum(filter(Investimentos!$P:$P,Investimentos!$C:$C=$B15,Investimentos!$J:$J=TRUE))"),"#N/A") -> #N/A | J15: Análises de Estudo de estabilidade; Análises de Matéria Prima para novo produto (ex. validar nova maltodextrina, validar novo WPI, macronutriente); Análises para validar o tempo de mistura; e Validação de mistura com Bin menor (50L)
B16: Fundação de desenv. da pesquisa do agronegócio - FUNDEPAG | C16: 3.1.16.2.5 | D16: 50.276.237/0001-78 | E16: 56470 | F16: =IFERROR(__xludf.DUMMYFUNCTION("sum(filter(Investimentos!$M:$M,Investimentos!$C:$C=$B16,Investimentos!$J:$J=TRUE))"),63386.72) -> 63386.72 | G16: =IFERROR(__xludf.DUMMYFUNCTION("sum(filter(Investimentos!$O:$O,Investimentos!$C:$C=$B16,Investimentos!$J:$J=TRUE))"),61345.920000000006) -> 61345.92 | H16: =IFERROR(__xludf.DUMMYFUNCTION("sum(filter(Investimentos!$P:$P,Investimentos!$C:$C=$B16,Investimentos!$J:$J=TRUE))"),1334.96) -> 1334.96 | J16: Reanálise de perfil lipídico; Análise de TPVA e TPO2 bobina Suprema; Análise de validação de mistura
B17: Eurofins do Brasil Análise de Alimentos Ltda. | C17: 3.1.16.2.5 | D17: 04.329.668/0001-38 | E17: 449589.36 | F17: =IFERROR(__xludf.DUMMYFUNCTION("sum(filter(Investimentos!$M:$M,Investimentos!$C:$C=$B17,Investimentos!$J:$J=TRUE))"),33116.19) -> 33116.19 | G17: =IFERROR(__xludf.DUMMYFUNCTION("sum(filter(Investimentos!$O:$O,Investimentos!$C:$C=$B17,Investimentos!$J:$J=TRUE))"),45915.32) -> 45915.32 | H17: =IFERROR(__xludf.DUMMYFUNCTION("sum(filter(Investimentos!$P:$P,Investimentos!$C:$C=$B17,Investimentos!$J:$J=TRUE))"),2461.3399999999997) -> 2461.34 | J17: Análises de Estudo de Estabilidade; Análise de aminograma; Investigação de sódio nos produtos; Covalidações metodologicas das análises; Validações de novas Matérias Primas; Investigação de Estabilidade das fórmulas de concorrentes; Análise para investigação de vitaminas sensíveis ao pH
B18: Fundação Arthur Bernardes | C18: 3.1.16.2.5 | D18: 20.320.503/0001-51 | E18: 50733.5 | F18: =IFERROR(__xludf.DUMMYFUNCTION("sum(filter(Investimentos!$M:$M,Investimentos!$C:$C=$B18,Investimentos!$J:$J=TRUE))"),2677.92) -> 2677.92 | G18: =IFERROR(__xludf.DUMMYFUNCTION("sum(filter(Investimentos!$O:$O,Investimentos!$C:$C=$B18,Investimentos!$J:$J=TRUE))"),5888.85) -> 5888.85 | H18: =IFERROR(__xludf.DUMMYFUNCTION("sum(filter(Investimentos!$P:$P,Investimentos!$C:$C=$B18,Investimentos!$J:$J=TRUE))"),2023.14) -> 2023.14 | J18: Valores pagos por Apoio técnico no contrato EMBRAPA/FUNARBE
B19: Anderson Mendonça Lima | C19: 3.1.16.2.5 | D19: 35.964.728/0001 18 | E19: 3200 | F19: =IFERROR(__xludf.DUMMYFUNCTION("sum(filter(Investimentos!$M:$M,Investimentos!$C:$C=$B19,Investimentos!$J:$J=TRUE))"),"#N/A") -> #N/A | G19: =IFERROR(__xludf.DUMMYFUNCTION("sum(filter(Investimentos!$O:$O,Investimentos!$C:$C=$B19,Investimentos!$J:$J=TRUE))"),"#N/A") -> #N/A | H19: =IFERROR(__xludf.DUMMYFUNCTION("sum(filter(Investimentos!$P:$P,Investimentos!$C:$C=$B19,Investimentos!$J:$J=TRUE))"),"#N/A") -> #N/A | J19: Consultoria em Estudos de Estabilidade e Validação de métodos analíticos
B20: PZL Indústria Eletrônica Ltda. | C20: 3.1.16.2.5 | D20: 76.785.302/0001-84 | E20: 240 | F20: =IFERROR(__xludf.DUMMYFUNCTION("sum(filter(Investimentos!$M:$M,Investimentos!$C:$C=$B20,Investimentos!$J:$J=TRUE))"),"#N/A") -> #N/A | G20: =IFERROR(__xludf.DUMMYFUNCTION("sum(filter(Investimentos!$O:$O,Investimentos!$C:$C=$B20,Investimentos!$J:$J=TRUE))"),"#N/A") -> #N/A | H20: =IFERROR(__xludf.DUMMYFUNCTION("sum(filter(Investimentos!$P:$P,Investimentos!$C:$C=$B20,Investimentos!$J:$J=TRUE))"),"#N/A") -> #N/A | J20: Solução de calibração do osmômetro
B21: Tuv Sud SFDK Laboratório de Análise de Produtos Eireli | C21: 3.1.16.2.5 | D21: 55.953.079/0001-67 | E21: 373.02 | F21: =IFERROR(__xludf.DUMMYFUNCTION("sum(filter(Investimentos!$M:$M,Investimentos!$C:$C=$B21,Investimentos!$J:$J=TRUE))"),"#N/A") -> #N/A | G21: =IFERROR(__xludf.DUMMYFUNCTION("sum(filter(Investimentos!$O:$O,Investimentos!$C:$C=$B21,Investimentos!$J:$J=TRUE))"),"#N/A") -> #N/A | H21: =IFERROR(__xludf.DUMMYFUNCTION("sum(filter(Investimentos!$P:$P,Investimentos!$C:$C=$B21,Investimentos!$J:$J=TRUE))"),"#N/A") -> #N/A | J21: Análise microbiológica
B22: D + L CONSULTORIA E TREINAMENTO DE ALIMENTOS LTDA | C22: 3.1.16.2.5 | D22: 26.522.083/0001-72 | E22: 173.5 | F22: =IFERROR(__xludf.DUMMYFUNCTION("sum(filter(Investimentos!$M:$M,Investimentos!$C:$C=$B22,Investimentos!$J:$J=TRUE))"),"#N/A") -> #N/A | G22: =IFERROR(__xludf.DUMMYFUNCTION("sum(filter(Investimentos!$O:$O,Investimentos!$C:$C=$B22,Investimentos!$J:$J=TRUE))"),"#N/A") -> #N/A | H22: =IFERROR(__xludf.DUMMYFUNCTION("sum(filter(Investimentos!$P:$P,Investimentos!$C:$C=$B22,Investimentos!$J:$J=TRUE))"),"#N/A") -> #N/A | J22: Evento Horizonte 21- inovação em ingredientes
B23: DMED consultoria científica e Treinamento profissional ltda | C23: 3.1.16.2.5 | D23: 24.466.324/0001-88 | E23: 94 | F23: =IFERROR(__xludf.DUMMYFUNCTION("sum(filter(Investimentos!$M:$M,Investimentos!$C:$C=$B23,Investimentos!$J:$J=TRUE))"),"#N/A") -> #N/A | G23: =IFERROR(__xludf.DUMMYFUNCTION("sum(filter(Investimentos!$O:$O,Investimentos!$C:$C=$B23,Investimentos!$J:$J=TRUE))"),"#N/A") -> #N/A | H23: =IFERROR(__xludf.DUMMYFUNCTION("sum(filter(Investimentos!$P:$P,Investimentos!$C:$C=$B23,Investimentos!$J:$J=TRUE))"),"#N/A") -> #N/A | J23: Inscrição em congresso
B24: Tetra Pak Ltda. | C24: 3.1.16.2.5 | D24: 61.528.030/0001-60 | E24: 69970.85 | F24: =IFERROR(__xludf.DUMMYFUNCTION("sum(filter(Investimentos!$M:$M,Investimentos!$C:$C=$B24,Investimentos!$J:$J=TRUE))"),"#N/A") -> #N/A | G24: =IFERROR(__xludf.DUMMYFUNCTION("sum(filter(Investimentos!$O:$O,Investimentos!$C:$C=$B24,Investimentos!$J:$J=TRUE))"),"#N/A") -> #N/A | H24: =IFERROR(__xludf.DUMMYFUNCTION("sum(filter(Investimentos!$P:$P,Investimentos!$C:$C=$B24,Investimentos!$J:$J=TRUE))"),"#N/A") -> #N/A | J24: Aluguel de planta para Teste de NP
B25: Atlantica Hotels International do Brasil Ltda. | C25: 3.1.16.2.5 | D25: 02.223.996/0004-66 | E25: 406.04 | F25: =IFERROR(__xludf.DUMMYFUNCTION("sum(filter(Investimentos!$M:$M,Investimentos!$C:$C=$B25,Investimentos!$J:$J=TRUE))"),"#N/A") -> #N/A | G25: =IFERROR(__xludf.DUMMYFUNCTION("sum(filter(Investimentos!$O:$O,Investimentos!$C:$C=$B25,Investimentos!$J:$J=TRUE))"),"#N/A") -> #N/A | H25: =IFERROR(__xludf.DUMMYFUNCTION("sum(filter(Investimentos!$P:$P,Investimentos!$C:$C=$B25,Investimentos!$J:$J=TRUE))"),"#N/A") -> #N/A | J25: Hospedagem e estacionamento - Teste Tetra Pak (Monte Mor/SP)
B26: Labor Três Laboratórios e Consultoria Técnica Ltda. | C26: 3.1.16.2.5 | D26: 02.021.076/0001-29 | E26: 1980 | F26: =IFERROR(__xludf.DUMMYFUNCTION("sum(filter(Investimentos!$M:$M,Investimentos!$C:$C=$B26,Investimentos!$J:$J=TRUE))"),295.95) -> 295.95 | G26: =IFERROR(__xludf.DUMMYFUNCTION("sum(filter(Investimentos!$O:$O,Investimentos!$C:$C=$B26,Investimentos!$J:$J=TRUE))"),2779.8599999999997) -> 2779.86 | H26: =IFERROR(__xludf.DUMMYFUNCTION("sum(filter(Investimentos!$P:$P,Investimentos!$C:$C=$B26,Investimentos!$J:$J=TRUE))"),0.0) -> 0 | J26: Análises de Estudos de Estabilidade
B27: Dr Aguilar Nascimento | C27: 3.1.16.2.5 | D27: 08.608.841/0001-98 | E27: 2300 | F27: =IFERROR(__xludf.DUMMYFUNCTION("sum(filter(Investimentos!$M:$M,Investimentos!$C:$C=$B27,Investimentos!$J:$J=TRUE))"),"#N/A") -> #N/A | G27: =IFERROR(__xludf.DUMMYFUNCTION("sum(filter(Investimentos!$O:$O,Investimentos!$C:$C=$B27,Investimentos!$J:$J=TRUE))"),"#N/A") -> #N/A | H27: =IFERROR(__xludf.DUMMYFUNCTION("sum(filter(Investimentos!$P:$P,Investimentos!$C:$C=$B27,Investimentos!$J:$J=TRUE))"),"#N/A") -> #N/A | J27: Palestra Polspen
B28: Nutrimens assessoria e consultoria | C28: 3.1.16.2.5 | D28: 08.218.651/0001-64 | E28: 1800 | F28: =IFERROR(__xludf.DUMMYFUNCTION("sum(filter(Investimentos!$M:$M,Investimentos!$C:$C=$B28,Investimentos!$J:$J=TRUE))"),"#N/A") -> #N/A | G28: =IFERROR(__xludf.DUMMYFUNCTION("sum(filter(Investimentos!$O:$O,Investimentos!$C:$C=$B28,Investimentos!$J:$J=TRUE))"),"#N/A") -> #N/A | H28: =IFERROR(__xludf.DUMMYFUNCTION("sum(filter(Investimentos!$P:$P,Investimentos!$C:$C=$B28,Investimentos!$J:$J=TRUE))"),"#N/A") -> #N/A | J28: Consultoria fórmula Diamax IG
B29: BRAZILSUL Serviços Administrativos Ltda | C29: 3.1.16.2.5 | D29: 11.456.079/0001-86 | E29: 6525 | F29: =IFERROR(__xludf.DUMMYFUNCTION("sum(filter(Investimentos!$M:$M,Investimentos!$C:$C=$B29,Investimentos!$J:$J=TRUE))"),"#N/A") -> #N/A | G29: =IFERROR(__xludf.DUMMYFUNCTION("sum(filter(Investimentos!$O:$O,Investimentos!$C:$C=$B29,Investimentos!$J:$J=TRUE))"),"#N/A") -> #N/A | H29: =IFERROR(__xludf.DUMMYFUNCTION("sum(filter(Investimentos!$P:$P,Investimentos!$C:$C=$B29,Investimentos!$J:$J=TRUE))"),"#N/A") -> #N/A | J29: Elaboração da minuta para depósito e acompanhamento do pedido de patente do Instanth Neo
B30: DPR Turismo Ltda EPP "Em recuperação judicial" | C30: 3.1.16.2.5 | D30: 73.506.453/0001-68 | E30: 4389.31 | F30: =IFERROR(__xludf.DUMMYFUNCTION("sum(filter(Investimentos!$M:$M,Investimentos!$C:$C=$B30,Investimentos!$J:$J=TRUE))"),"#N/A") -> #N/A | G30: =IFERROR(__xludf.DUMMYFUNCTION("sum(filter(Investimentos!$O:$O,Investimentos!$C:$C=$B30,Investimentos!$J:$J=TRUE))"),"#N/A") -> #N/A | H30: =IFERROR(__xludf.DUMMYFUNCTION("sum(filter(Investimentos!$P:$P,Investimentos!$C:$C=$B30,Investimentos!$J:$J=TRUE))"),"#N/A") -> #N/A | J30: Despesas de viagens para a Embrapa/RJ e SEMCO/SP para realização de testes de maior complexidade
B31: RNC Médicos intensivistas | C31: 3.1.16.2.5 | D31: 26.528.525/0001-98 | E31: 5000 | F31: =IFERROR(__xludf.DUMMYFUNCTION("sum(filter(Investimentos!$M:$M,Investimentos!$C:$C=$B31,Investimentos!$J:$J=TRUE))"),"#N/A") -> #N/A | G31: =IFERROR(__xludf.DUMMYFUNCTION("sum(filter(Investimentos!$O:$O,Investimentos!$C:$C=$B31,Investimentos!$J:$J=TRUE))"),"#N/A") -> #N/A | H31: =IFERROR(__xludf.DUMMYFUNCTION("sum(filter(Investimentos!$P:$P,Investimentos!$C:$C=$B31,Investimentos!$J:$J=TRUE))"),"#N/A") -> #N/A | J31: Consultoria sobre formulação
B32: Empresa Brasileira de Pesquisa Agropecuária | C32: 3.1.16.2.5 | D32: 00.348.003/0011-92 | E32: 2250 | F32: =IFERROR(__xludf.DUMMYFUNCTION("sum(filter(Investimentos!$M:$M,Investimentos!$C:$C=$B32,Investimentos!$J:$J=TRUE))"),"#N/A") -> #N/A | G32: =IFERROR(__xludf.DUMMYFUNCTION("sum(filter(Investimentos!$O:$O,Investimentos!$C:$C=$B32,Investimentos!$J:$J=TRUE))"),"#N/A") -> #N/A | H32: =IFERROR(__xludf.DUMMYFUNCTION("sum(filter(Investimentos!$P:$P,Investimentos!$C:$C=$B32,Investimentos!$J:$J=TRUE))"),"#N/A") -> #N/A | J32: Análise de Distribuição de Partículas
B33: SEMCO TECNOLOGIA EM PROCESSOS LTDA. | C33: 3.1.16.2.5 | D33: 15.108.353/0002-68 | E33: 4000 | F33: =IFERROR(__xludf.DUMMYFUNCTION("sum(filter(Investimentos!$M:$M,Investimentos!$C:$C=$B33,Investimentos!$J:$J=TRUE))"),"#N/A") -> #N/A | G33: =IFERROR(__xludf.DUMMYFUNCTION("sum(filter(Investimentos!$O:$O,Investimentos!$C:$C=$B33,Investimentos!$J:$J=TRUE))"),"#N/A") -> #N/A | H33: =IFERROR(__xludf.DUMMYFUNCTION("sum(filter(Investimentos!$P:$P,Investimentos!$C:$C=$B33,Investimentos!$J:$J=TRUE))"),"#N/A") -> #N/A | J33: Teste HSM
B36: Recursos Humanos | F36: Projeto 1 | H36: Projeto 2 | J36: Projeto 3
B37: {='Classificação p pessoal'!J1:S17} | F37: NP | H37: MProduto | J37: MProcesso
B38: Dedicação | C38: Pessoa | D38: CPF | E38: Formação | F38: Valor | G38: Horas | H38: Valor | I38: Horas | J38: Valor | K38: Horas
B39: Parcial | C39: Ana Claudia Zanini | D39: 076.046.519-33 | E39: Mestrado | F39: 21238.805 | G39: 640.5 | H39: 17010.94 | I39: 513 | K39: 0
B40: Parcial | C40: Arianna Schreiber | D40: 066.466.799-67 | E40: Pós graduado | F40: 2697.2976 | G40: 29 | H40: 186.02053 | I40: 2 | K40: 0
B41: Parcial | C41: Camila Mendes Pereira | D41: 083.832.289-10 | E41: Superior Completo | F41: 15699.682 | G41: 505.96418 | H41: 1208.6659 | I41: 38.952486 | J41: 3281.3417 | K41: 105.75
B42: Parcial | C42: Lizianne Shmeil | D42: 052.485.199-93 | E42: Superior Completo | F42: 67615.094 | G42: 1288.2907 | H42: 8802.1107 | I42: 167.70926 | J42: 367.39041 | K42: 7
B43: Parcial | C43: Márcio Henrique Nogueira | D43: 088.869.216-16 | E43: Pós graduado | F43: 44211.464 | G43: 847.74445 | H43: 7714.4209 | I43: 147.92221 | J43: 1016.9616 | K43: 19.5
B44: Parcial | C44: Kézia Rithássia Piccoli | D44: 077.680.169-47 | E44: Pós graduado | F44: 8235.1357 | G44: 219.54928 | H44: 18205.781 | I44: 485.36738 | J44: 887.71964 | K44: 23.666667
B45: Parcial | C45: Juliana Lamas Roberto | D45: 317.875.738-42 | E45: Pós graduado | F45: 97214.163 | G45: 1318.9095 | H45: 15794.919 | I45: 214.29047 | J45: 1781.2763 | K45: 24.166667
B46: Parcial | C46: Gabriela Faria de Oliveira | D46: 087.823.469-17 | E46: Superior Completo | F46: 23237.233 | G46: 668.29928 | H46: 6.9790539 | I46: 0.20071653 | K46: 0
F47: 280148.88 | G47: 5518.2575 | H47: 68929.837 | I47: 1569.4425 | J47: 7334.6897 | K47: 180.08333
J49: Valor total | K49: 356413.4
J50: Total horas | K50: 7267.7833
J52: Valor que deveria ter | K52: 356413.4
J53: Horas que deveria ter | K53: 7267.7833
D57: 3.1 | E57: RECEITAS | F57: 131443338
D58: 3.2 | E58: DEDUCOES DA RECEITA | F58: -24537510
D60: RECEITA LIQUIDA | F60: =F57+F58 -> 1.0690583e+08

Sheet Classificação p pessoal
B1: Novos produtos | C1: Melhoria de produtos | D1: Melhoria de processos | F1: Projetos no HD | G1: Classificação | H1: Valor total | N1: NP | P1: MProduto | R1: MProcesso
B2: Trophic Junior | C2: Trophic Dose Única | D2: Estabilidade de misturas secas | F2: Trophic Soya 1.5 Fiber | G2: NP | H2: =IFERROR(__xludf.DUMMYFUNCTION("sum(filter(Timesheet!$N:$N,Timesheet!$C:$C=$F2))"),16988.953893813134) -> 16988.954 | J2: Dedicação | K2: Pessoa | L2: CPF | M2: Formação | N2: Valor | O2: Horas | P2: Valor | Q2: Horas | R2: Valor | S2: Horas
B3: Energyzip Junior | C3: Sachê a vácuo | D3: Sacheteira | F3: Suplemento hiperproteico líquido | G3: NP | H3: =IFERROR(__xludf.DUMMYFUNCTION("sum(filter(Timesheet!$N:$N,Timesheet!$C:$C=$F3))"),5659.8717437449895) -> 5659.8717 | J3: =vlookup(K3,Pessoal!$A$6:$U$18,21) -> Parcial | K3: Ana Claudia Zanini | L3: =vlookup(K3,Pessoal!$A$6:$B$18,2,false) -> 076.046.519-33 | M3: =vlookup(K3,Pessoal!$A$6:$E$18,5,false) -> Mestrado | N3: =IFERROR(__xludf.DUMMYFUNCTION("iferror(sum(filter(Timesheet!$N:$N,Timesheet!$D:$D=""NP"",Timesheet!$J:$J=TRUE,Timesheet!$B:$B=$K3)))+N21"),21238.805306628758) -> 21238.805 | O3: =IFERROR(__xludf.DUMMYFUNCTION("(iferror(sum(filter(Timesheet!$H:$H,Timesheet!$D:$D=""NP"",Timesheet!$J:$J=TRUE,Timesheet!$B:$B=$K3)))*24)+O21"),640.4999999999998) -> 640.5 | P3: =IFERROR(__xludf.DUMMYFUNCTION("iferror(sum(filter(Timesheet!$N:$N,Timesheet!$D:$D=""MProduto"",Timesheet!$J:$J=TRUE,Timesheet!$B:$B=$K3)))+P21"),17010.940081655823) -> 17010.94 | Q3: =IFERROR(__xludf.DUMMYFUNCTION("(IFERROR(SUM(filter(Timesheet!$H:$H,Timesheet!$D:$D=""MProduto"",Timesheet!$J:$J=TRUE,Timesheet!$B:$B=$K3)))*24)+Q21"),512.9999999999998) -> 513 | R3: =IFERROR(__xludf.DUMMYFUNCTION("iferror(sum(filter(Timesheet!$N:$N,Timesheet!$D:$D=""MProcesso"",Timesheet!$J:$J=TRUE,Timesheet!$B:$B=$K3)))"),"") | S3: =IFERROR(__xludf.DUMMYFUNCTION("iferror(sum(filter(Timesheet!$H:$H,Timesheet!$D:$D=""MProcesso"",Timesheet!$J:$J=TRUE,Timesheet!$B:$B=$K3)))*24"),0.0) -> 0
B4: Trophic Soya 1.5 Fiber | C4: DiamaxIG | F4: InstanTH Neo | G4: NP | H4: =IFERROR(__xludf.DUMMYFUNCTION("sum(filter(Timesheet!$N:$N,Timesheet!$C:$C=$F4))"),15829.923570509913) -> 15829.924 | J4: =vlookup(K4,Pessoal!$A$6:$U$18,21) -> Parcial | K4: Arianna Schreiber | L4: =vlookup(K4,Pessoal!$A$6:$B$18,2,false) -> 066.466.799-67 | M4: =vlookup(K4,Pessoal!$A$6:$E$18,5,false) -> Pós graduado | N4: =IFERROR(__xludf.DUMMYFUNCTION("iferror(sum(filter(Timesheet!$N:$N,Timesheet!$D:$D=""NP"",Timesheet!$J:$J=TRUE,Timesheet!$B:$B=$K4)))+N22"),2697.297629238817) -> 2697.2976 | O4: =IFERROR(__xludf.DUMMYFUNCTION("(iferror(sum(filter(Timesheet!$H:$H,Timesheet!$D:$D=""NP"",Timesheet!$J:$J=TRUE,Timesheet!$B:$B=$K4)))*24)+O22"),29.0) -> 29 | P4: =IFERROR(__xludf.DUMMYFUNCTION("iferror(sum(filter(Timesheet!$N:$N,Timesheet!$D:$D=""MProduto"",Timesheet!$J:$J=TRUE,Timesheet!$B:$B=$K4)))+P22"),186.02052615440113) -> 186.02053 | Q4: =IFERROR(__xludf.DUMMYFUNCTION("(IFERROR(SUM(filter(Timesheet!$H:$H,Timesheet!$D:$D=""MProduto"",Timesheet!$J:$J=TRUE,Timesheet!$B:$B=$K4)))*24)+Q22"),2.0) -> 2 | R4: =IFERROR(__xludf.DUMMYFUNCTION("iferror(sum(filter(Timesheet!$N:$N,Timesheet!$D:$D=""MProcesso"",Timesheet!$J:$J=TRUE,Timesheet!$B:$B=$K4)))"),"") | S4: =IFERROR(__xludf.DUMMYFUNCTION("iferror(sum(filter(Timesheet!$H:$H,Timesheet!$D:$D=""MProcesso"",Timesheet!$J:$J=TRUE,Timesheet!$B:$B=$K4)))*24"),0.0) -> 0
B5: EnergyZIP Protein | F5: Trophic Junior Líquido 1.0 (ARB) | G5: NP | H5: =IFERROR(__xludf.DUMMYFUNCTION("sum(filter(Timesheet!$N:$N,Timesheet!$C:$C=$F5))"),4876.61226626533) -> 4876.6123 | J5: =vlookup(K5,Pessoal!$A$6:$U$18,21) -> Parcial | K5: Camila Mendes Pereira | L5: =vlookup(K5,Pessoal!$A$6:$B$18,2,false) -> 083.832.289-10 | M5: =vlookup(K5,Pessoal!$A$6:$E$18,5,false) -> Superior Completo | N5: =IFERROR(__xludf.DUMMYFUNCTION("iferror(sum(filter(Timesheet!$N:$N,Timesheet!$D:$D=""NP"",Timesheet!$J:$J=TRUE,Timesheet!$B:$B=$K5)))+N23"),15699.682084337666) -> 15699.682 | O5: =IFERROR(__xludf.DUMMYFUNCTION("(iferror(sum(filter(Timesheet!$H:$H,Timesheet!$D:$D=""NP"",Timesheet!$J:$J=TRUE,Timesheet!$B:$B=$K5)))*24)+O23"),505.9641810377379) -> 505.96418 | P5: =IFERROR(__xludf.DUMMYFUNCTION("iferror(sum(filter(Timesheet!$N:$N,Timesheet!$D:$D=""MProduto"",Timesheet!$J:$J=TRUE,Timesheet!$B:$B=$K5)))+P23"),1208.6658773248391) -> 1208.6659 | Q5: =IFERROR(__xludf.DUMMYFUNCTION("(IFERROR(SUM(filter(Timesheet!$H:$H,Timesheet!$D:$D=""MProduto"",Timesheet!$J:$J=TRUE,Timesheet!$B:$B=$K5)))*24)+Q23"),38.95248562892923) -> 38.952486 | R5: =IFERROR(__xludf.DUMMYFUNCTION("iferror(sum(filter(Timesheet!$N:$N,Timesheet!$D:$D=""MProcesso"",Timesheet!$J:$J=TRUE,Timesheet!$B:$B=$K5)))"),3281.3417286052495) -> 3281.3417 | S5: =IFERROR(__xludf.DUMMYFUNCTION("iferror(sum(filter(Timesheet!$H:$H,Timesheet!$D:$D=""MProcesso"",Timesheet!$J:$J=TRUE,Timesheet!$B:$B=$K5)))*24"),105.75000000000004) -> 105.75
B6: Energyzip / Diamax novos sabores | F6: Diamax IG | G6: MProduto | H6: =IFERROR(__xludf.DUMMYFUNCTION("sum(filter(Timesheet!$N:$N,Timesheet!$C:$C=$F6))"),16906.927945758165) -> 16906.928 | J6: =vlookup(K6,Pessoal!$A$6:$U$18,21) -> Parcial | K6: Lizianne Shmeil | L6: =vlookup(K6,Pessoal!$A$6:$B$18,2,false) -> 052.485.199-93 | M6: =vlookup(K6,Pessoal!$A$6:$E$18,5,false) -> Superior Completo | N6: =IFERROR(__xludf.DUMMYFUNCTION("iferror(sum(filter(Timesheet!$N:$N,Timesheet!$D:$D=""NP"",Timesheet!$J:$J=TRUE,Timesheet!$B:$B=$K6)))+N24"),67615.09433009496) -> 67615.094 | O6: =IFERROR(__xludf.DUMMYFUNCTION("(iferror(sum(filter(Timesheet!$H:$H,Timesheet!$D:$D=""NP"",Timesheet!$J:$J=TRUE,Timesheet!$B:$B=$K6)))*24)+O24"),1288.2907365178487) -> 1288.2907 | P6: =IFERROR(__xludf.DUMMYFUNCTION("iferror(sum(filter(Timesheet!$N:$N,Timesheet!$D:$D=""MProduto"",Timesheet!$J:$J=TRUE,Timesheet!$B:$B=$K6)))+P24"),8802.110695157711) -> 8802.1107 | Q6: =IFERROR(__xludf.DUMMYFUNCTION("(IFERROR(SUM(filter(Timesheet!$H:$H,Timesheet!$D:$D=""MProduto"",Timesheet!$J:$J=TRUE,Timesheet!$B:$B=$K6)))*24)+Q24"),167.70926348215093) -> 167.70926 | R6: =IFERROR(__xludf.DUMMYFUNCTION("iferror(sum(filter(Timesheet!$N:$N,Timesheet!$D:$D=""MProcesso"",Timesheet!$J:$J=TRUE,Timesheet!$B:$B=$K6)))"),367.3904087752526) -> 367.39041 | S6: =IFERROR(__xludf.DUMMYFUNCTION("iferror(sum(filter(Timesheet!$H:$H,Timesheet!$D:$D=""MProcesso"",Timesheet!$J:$J=TRUE,Timesheet!$B:$B=$K6)))*24"),7.0) -> 7
B7: Sistema Fechado | F7: Sachê | G7: MProduto | H7: =IFERROR(__xludf.DUMMYFUNCTION("sum(filter(Timesheet!$N:$N,Timesheet!$C:$C=$F7))"),20900.759744359275) -> 20900.76 | J7: =vlookup(K7,Pessoal!$A$6:$U$18,21) -> Parcial | K7: Márcio Henrique Nogueira | L7: =vlookup(K7,Pessoal!$A$6:$B$18,2,false) -> 088.869.216-16 | M7: =vlookup(K7,Pessoal!$A$6:$E$18,5,false) -> Pós graduado | N7: =IFERROR(__xludf.DUMMYFUNCTION("iferror(sum(filter(Timesheet!$N:$N,Timesheet!$D:$D=""NP"",Timesheet!$J:$J=TRUE,Timesheet!$B:$B=$K7)))+N25"),44211.46352954651) -> 44211.464 | O7: =IFERROR(__xludf.DUMMYFUNCTION("(iferror(sum(filter(Timesheet!$H:$H,Timesheet!$D:$D=""NP"",Timesheet!$J:$J=TRUE,Timesheet!$B:$B=$K7)))*24)+O25"),847.7444533870771) -> 847.74445 | P7: =IFERROR(__xludf.DUMMYFUNCTION("iferror(sum(filter(Timesheet!$N:$N,Timesheet!$D:$D=""MProduto"",Timesheet!$J:$J=TRUE,Timesheet!$B:$B=$K7)))+P25"),7714.420910088008) -> 7714.4209 | Q7: =IFERROR(__xludf.DUMMYFUNCTION("(IFERROR(SUM(filter(Timesheet!$H:$H,Timesheet!$D:$D=""MProduto"",Timesheet!$J:$J=TRUE,Timesheet!$B:$B=$K7)))*24)+Q25"),147.92221327959004) -> 147.92221 | R7: =IFERROR(__xludf.DUMMYFUNCTION("iferror(sum(filter(Timesheet!$N:$N,Timesheet!$D:$D=""MProcesso"",Timesheet!$J:$J=TRUE,Timesheet!$B:$B=$K7)))"),1016.9615800865798) -> 1016.9616 | S7: =IFERROR(__xludf.DUMMYFUNCTION("iferror(sum(filter(Timesheet!$H:$H,Timesheet!$D:$D=""MProcesso"",Timesheet!$J:$J=TRUE,Timesheet!$B:$B=$K7)))*24"),19.500000000000004) -> 19.5
B8: Energyzip Sênior | F8: Retort (Sistema Fechado) | G8: NP | H8: =IFERROR(__xludf.DUMMYFUNCTION("sum(filter(Timesheet!$N:$N,Timesheet!$C:$C=$F8))"),71600.39919750144) -> 71600.399 | J8: =vlookup(K8,Pessoal!$A$6:$U$18,21) -> Parcial | K8: Kézia Rithássia Piccoli | L8: =vlookup(K8,Pessoal!$A$6:$B$18,2,false) -> 077.680.169-47 | M8: =vlookup(K8,Pessoal!$A$6:$E$18,5,false) -> Pós graduado | N8: =IFERROR(__xludf.DUMMYFUNCTION("iferror(sum(filter(Timesheet!$N:$N,Timesheet!$D:$D=""NP"",Timesheet!$J:$J=TRUE,Timesheet!$B:$B=$K8)))+N26"),8235.135684727024) -> 8235.1357 | O8: =IFERROR(__xludf.DUMMYFUNCTION("(iferror(sum(filter(Timesheet!$H:$H,Timesheet!$D:$D=""NP"",Timesheet!$J:$J=TRUE,Timesheet!$B:$B=$K8)))*24)+O26"),219.54928347264257) -> 219.54928 | P8: =IFERROR(__xludf.DUMMYFUNCTION("iferror(sum(filter(Timesheet!$N:$N,Timesheet!$D:$D=""MProduto"",Timesheet!$J:$J=TRUE,Timesheet!$B:$B=$K8)))+P26"),18205.781382300647) -> 18205.781 | Q8: =IFERROR(__xludf.DUMMYFUNCTION("(IFERROR(SUM(filter(Timesheet!$H:$H,Timesheet!$D:$D=""MProduto"",Timesheet!$J:$J=TRUE,Timesheet!$B:$B=$K8)))*24)+Q26"),485.3673831940241) -> 485.36738 | R8: =IFERROR(__xludf.DUMMYFUNCTION("iferror(sum(filter(Timesheet!$N:$N,Timesheet!$D:$D=""MProcesso"",Timesheet!$J:$J=TRUE,Timesheet!$B:$B=$K8)))"),887.7196414512185) -> 887.71964 | S8: =IFERROR(__xludf.DUMMYFUNCTION("iferror(sum(filter(Timesheet!$H:$H,Timesheet!$D:$D=""MProcesso"",Timesheet!$J:$J=TRUE,Timesheet!$B:$B=$K8)))*24"),23.66666666666667) -> 23.666667
B9: Energyzip pó | F9: Bemmax sabor neutro | G9: MProduto | H9: =IFERROR(__xludf.DUMMYFUNCTION("sum(filter(Timesheet!$N:$N,Timesheet!$C:$C=$F9))"),1608.9957669535129) -> 1608.9958 | J9: =vlookup(K9,Pessoal!$A$6:$U$18,21) -> Parcial | K9: Juliana Lamas Roberto | L9: =vlookup(K9,Pessoal!$A$6:$B$18,2,false) -> 317.875.738-42 | M9: =vlookup(K9,Pessoal!$A$6:$E$18,5,false) -> Pós graduado | N9: =IFERROR(__xludf.DUMMYFUNCTION("iferror(sum(filter(Timesheet!$N:$N,Timesheet!$D:$D=""NP"",Timesheet!$J:$J=TRUE,Timesheet!$B:$B=$K9)))+N27"),97214.16345810794) -> 97214.163 | O9: =IFERROR(__xludf.DUMMYFUNCTION("(iferror(sum(filter(Timesheet!$H:$H,Timesheet!$D:$D=""NP"",Timesheet!$J:$J=TRUE,Timesheet!$B:$B=$K9)))*24)+O27"),1318.909531648988) -> 1318.9095 | P9: =IFERROR(__xludf.DUMMYFUNCTION("iferror(sum(filter(Timesheet!$N:$N,Timesheet!$D:$D=""MProduto"",Timesheet!$J:$J=TRUE,Timesheet!$B:$B=$K9)))+P27"),15794.918542854268) -> 15794.919 | Q9: =IFERROR(__xludf.DUMMYFUNCTION("(IFERROR(SUM(filter(Timesheet!$H:$H,Timesheet!$D:$D=""MProduto"",Timesheet!$J:$J=TRUE,Timesheet!$B:$B=$K9)))*24)+Q27"),214.2904683510124) -> 214.29047 | R9: =IFERROR(__xludf.DUMMYFUNCTION("iferror(sum(filter(Timesheet!$N:$N,Timesheet!$D:$D=""MProcesso"",Timesheet!$J:$J=TRUE,Timesheet!$B:$B=$K9)))"),1781.2762946929613) -> 1781.2763 | S9: =IFERROR(__xludf.DUMMYFUNCTION("iferror(sum(filter(Timesheet!$H:$H,Timesheet!$D:$D=""MProcesso"",Timesheet!$J:$J=TRUE,Timesheet!$B:$B=$K9)))*24"),24.16666666666667) -> 24.166667
B10: Linha Soya pó | F10: Trophic 1.5 250mL - Edge | G10: NP | H10: =IFERROR(__xludf.DUMMYFUNCTION("sum(filter(Timesheet!$N:$N,Timesheet!$C:$C=$F10))"),5109.1659773215815) -> 5109.166 | J10: =vlookup(K10,Pessoal!$A$6:$U$18,21) -> Parcial | K10: Gabriela Faria de Oliveira | L10: =vlookup(K10,Pessoal!$A$6:$B$18,2,false) -> 087.823.469-17 | M10: =vlookup(K10,Pessoal!$A$6:$E$18,5,false) -> Superior Completo | N10: =IFERROR(__xludf.DUMMYFUNCTION("iferror(sum(filter(Timesheet!$N:$N,Timesheet!$D:$D=""NP"",Timesheet!$J:$J=TRUE,Timesheet!$B:$B=$K10)))+N28"),23237.233027921084) -> 23237.233 | O10: =IFERROR(__xludf.DUMMYFUNCTION("(iferror(sum(filter(Timesheet!$H:$H,Timesheet!$D:$D=""NP"",Timesheet!$J:$J=TRUE,Timesheet!$B:$B=$K10)))*24)+O28"),668.2992834726421) -> 668.29928 | P10: =IFERROR(__xludf.DUMMYFUNCTION("iferror(sum(filter(Timesheet!$N:$N,Timesheet!$D:$D=""MProduto"",Timesheet!$J:$J=TRUE,Timesheet!$B:$B=$K10)))+P28"),6.979053897114981) -> 6.9790539 | Q10: =IFERROR(__xludf.DUMMYFUNCTION("(IFERROR(SUM(filter(Timesheet!$H:$H,Timesheet!$D:$D=""MProduto"",Timesheet!$J:$J=TRUE,Timesheet!$B:$B=$K10)))*24)+Q28"),0.20071652735739562) -> 0.20071653 | R10: =IFERROR(__xludf.DUMMYFUNCTION("iferror(sum(filter(Timesheet!$N:$N,Timesheet!$D:$D=""MProcesso"",Timesheet!$J:$J=TRUE,Timesheet!$B:$B=$K10)))"),"") | S10: =IFERROR(__xludf.DUMMYFUNCTION("iferror(sum(filter(Timesheet!$H:$H,Timesheet!$D:$D=""MProcesso"",Timesheet!$J:$J=TRUE,Timesheet!$B:$B=$K10)))*24"),0.0) -> 0
B11: Instanth Neo | F11: Diamax pó | G11: NP | H11: =IFERROR(__xludf.DUMMYFUNCTION("sum(filter(Timesheet!$N:$N,Timesheet!$C:$C=$F11))"),1990.952708943602) -> 1990.9527 | N11: =sum(N3:N10) -> 280148.88 | O11: =sum(O3:O10) -> 5518.2575 | P11: =sum(P3:P10) -> 68929.837 | Q11: =sum(Q3:Q10) -> 1569.4425 | R11: =sum(R3:R10) -> 7334.6897 | S11: =sum(S3:S10) -> 180.08333
B12: Diamax pó | F12: Congresso Ganepão | G12: MProduto | H12: =IFERROR(__xludf.DUMMYFUNCTION("sum(filter(Timesheet!$N:$N,Timesheet!$C:$C=$F12))"),3349.1324527236643) -> 3349.1325
B13: Dieta artesanal | F13: InstanTH CLEAR (espessante) | G13: NP | H13: =IFERROR(__xludf.DUMMYFUNCTION("sum(filter(Timesheet!$N:$N,Timesheet!$C:$C=$F13))"),13353.31288410496) -> 13353.313 | R13: Valor total | S13: =sum(N11,P11,R11) -> 356413.4
B14: Instanth Clear | F14: Energyzip Sênior | G14: NP | H14: =IFERROR(__xludf.DUMMYFUNCTION("sum(filter(Timesheet!$N:$N,Timesheet!$C:$C=$F14))"),7527.4481659156045) -> 7527.4482 | R14: Total horas | S14: =sum(O11,Q11,S11) -> 7267.7833
F15: EE - 2020 | H15: =IFERROR(__xludf.DUMMYFUNCTION("sum(filter(Timesheet!$N:$N,Timesheet!$C:$C=$F15))"),119218.19869362672) -> 119218.2 | I15: Doc. 2020
F16: Dieta artesanal | G16: NP | H16: =IFERROR(__xludf.DUMMYFUNCTION("sum(filter(Timesheet!$N:$N,Timesheet!$C:$C=$F16))"),2685.9614846237673) -> 2685.9615 | R16: Valor que deveria ter | S16: 356413.4
F17: Estabilidade misturas secas | G17: NP | H17: =IFERROR(__xludf.DUMMYFUNCTION("sum(filter(Timesheet!$N:$N,Timesheet!$C:$C=$F17))"),4860.454564830097) -> 4860.4546 | R17: Horas que deveria ter | S17: 7267.7833
F18: Inovação industrial - misturas secas | G18: MProcesso | H18: =IFERROR(__xludf.DUMMYFUNCTION("sum(filter(Timesheet!$N:$N,Timesheet!$C:$C=$F18))"),7334.6896536112645) -> 7334.6897 | N18: NP | P18: MProduto
F19: Sarcopenia | G19: NP | H19: =IFERROR(__xludf.DUMMYFUNCTION("sum(filter(Timesheet!$N:$N,Timesheet!$C:$C=$F19))"),1476.7422313244047) -> 1476.7422 | I19: Doc. 2020 | J19: Tie:in - rateio de aproveitamento dos estudos de estabilidade | N19: Valor | O19: Horas | P19: Valor | Q19: Horas
F20: Novos produtos Turquia | G20: NP | H20: =IFERROR(__xludf.DUMMYFUNCTION("sum(filter(Timesheet!$N:$N,Timesheet!$C:$C=$F20))"),12611.989736858935) -> 12611.99 | J20: Dedicação | K20: Pessoa | L20: CPF | M20: Formação | N20: =IFERROR(__xludf.DUMMYFUNCTION("iferror(sum(filter(Timesheet!$N:$N,Timesheet!$D:$D=""NP"",Timesheet!$J:$J=TRUE,Timesheet!$B:$B=$K20)))"),"") | P20: =IFERROR(__xludf.DUMMYFUNCTION("iferror(sum(filter(Timesheet!$N:$N,Timesheet!$D:$D=""MProduto"",Timesheet!$J:$J=TRUE,Timesheet!$B:$B=$K20)))"),"") | R20: valor total | S20: horas totais
F21: EnergyZIP Protein | G21: NP | H21: =IFERROR(__xludf.DUMMYFUNCTION("sum(filter(Timesheet!$N:$N,Timesheet!$C:$C=$F21))"),224.68757842412217) -> 224.68758 | J21: =vlookup(K21,Pessoal!$A$6:$U$18,21) -> Parcial | K21: Ana Claudia Zanini | L21: =vlookup(K21,Pessoal!$A$6:$B$18,2,false) -> 076.046.519-33 | M21: =vlookup(K21,Pessoal!$A$6:$E$18,5,false) -> Mestrado | N21: =$R21*(N$31/($N$31+$P$31)) -> 0 | O21: =$S21*(N$31/($N$31+$P$31)) -> 0 | P21: =$R21*(P$31/($N$31+$P$31)) -> 0 | Q21: =$S21*(P$31/($N$31+$P$31)) -> 0 | R21: =IFERROR(__xludf.DUMMYFUNCTION("iferror(sum(filter(Timesheet!$N:$N,Timesheet!$C:$C=""EE - 2020"",Timesheet!$J:$J=TRUE,Timesheet!$B:$B=$K21)))"),"") | S21: =IFERROR(__xludf.DUMMYFUNCTION("IFERROR(SUM(filter(Timesheet!$H:$H,Timesheet!$C:$C=""EE - 2020"",Timesheet!$J:$J=TRUE,Timesheet!$B:$B=$K21)))*24"),0.0) -> 0
F22: Energyzip pó | G22: NP | H22: =IFERROR(__xludf.DUMMYFUNCTION("sum(filter(Timesheet!$N:$N,Timesheet!$C:$C=$F22))"),3112.6664600468957) -> 3112.6665 | J22: =vlookup(K22,Pessoal!$A$6:$U$18,21) -> Parcial | K22: Arianna Schreiber | L22: =vlookup(K22,Pessoal!$A$6:$B$18,2,false) -> 066.466.799-67 | M22: =vlookup(K22,Pessoal!$A$6:$E$18,5,false) -> Pós graduado | N22: =$R22*(N$31/($N$31+$P$31)) -> 0 | O22: =$S22*(N$31/($N$31+$P$31)) -> 0 | P22: =$R22*(P$31/($N$31+$P$31)) -> 0 | Q22: =$S22*(P$31/($N$31+$P$31)) -> 0 | R22: =IFERROR(__xludf.DUMMYFUNCTION("iferror(sum(filter(Timesheet!$N:$N,Timesheet!$C:$C=""EE - 2020"",Timesheet!$J:$J=TRUE,Timesheet!$B:$B=$K22)))"),"") | S22: =IFERROR(__xludf.DUMMYFUNCTION("IFERROR(SUM(filter(Timesheet!$H:$H,Timesheet!$C:$C=""EE - 2020"",Timesheet!$J:$J=TRUE,Timesheet!$B:$B=$K22)))*24"),0.0) -> 0
F23: Cicatrização | G23: NP | H23: =IFERROR(__xludf.DUMMYFUNCTION("sum(filter(Timesheet!$N:$N,Timesheet!$C:$C=$F23))"),8234.753434032284) -> 8234.7534 | J23: =vlookup(K23,Pessoal!$A$6:$U$18,21) -> Parcial | K23: Camila Mendes Pereira | L23: =vlookup(K23,Pessoal!$A$6:$B$18,2,false) -> 083.832.289-10 | M23: =vlookup(K23,Pessoal!$A$6:$E$18,5,false) -> Superior Completo | N23: =$R23*(N$31/($N$31+$P$31)) -> 1816.6847 | O23: =$S23*(N$31/($N$31+$P$31)) -> 58.547514 | P23: =$R23*(P$31/($N$31+$P$31)) -> 456.2069 | Q23: =$S23*(P$31/($N$31+$P$31)) -> 14.702486 | R23: =IFERROR(__xludf.DUMMYFUNCTION("iferror(sum(filter(Timesheet!$N:$N,Timesheet!$C:$C=""EE - 2020"",Timesheet!$J:$J=TRUE,Timesheet!$B:$B=$K23)))"),2272.8915519653383) -> 2272.8916 | S23: =IFERROR(__xludf.DUMMYFUNCTION("IFERROR(SUM(filter(Timesheet!$H:$H,Timesheet!$C:$C=""EE - 2020"",Timesheet!$J:$J=TRUE,Timesheet!$B:$B=$K23)))*24"),73.25000000000001) -> 73.25
F24: Trophic Dose Única 250mL - Edge | G24: NP | H24: =IFERROR(__xludf.DUMMYFUNCTION("sum(filter(Timesheet!$N:$N,Timesheet!$C:$C=$F24))"),69.5413974025974) -> 69.541397 | J24: =vlookup(K24,Pessoal!$A$6:$U$18,21) -> Parcial | K24: Lizianne Shmeil | L24: =vlookup(K24,Pessoal!$A$6:$B$18,2,false) -> 052.485.199-93 | M24: =vlookup(K24,Pessoal!$A$6:$E$18,5,false) -> Superior Completo | N24: =$R24*(N$31/($N$31+$P$31)) -> 15178.861 | O24: =$S24*(N$31/($N$31+$P$31)) -> 289.2074 | P24: =$R24*(P$31/($N$31+$P$31)) -> 3811.7243 | Q24: =$S24*(P$31/($N$31+$P$31)) -> 72.62593 | R24: =IFERROR(__xludf.DUMMYFUNCTION("iferror(sum(filter(Timesheet!$N:$N,Timesheet!$C:$C=""EE - 2020"",Timesheet!$J:$J=TRUE,Timesheet!$B:$B=$K24)))"),18990.585177406498) -> 18990.585 | S24: =IFERROR(__xludf.DUMMYFUNCTION("IFERROR(SUM(filter(Timesheet!$H:$H,Timesheet!$C:$C=""EE - 2020"",Timesheet!$J:$J=TRUE,Timesheet!$B:$B=$K24)))*24"),361.8333333333332) -> 361.83333
F25: HDmax - pesquisa | G25: NP | H25: =IFERROR(__xludf.DUMMYFUNCTION("sum(filter(Timesheet!$N:$N,Timesheet!$C:$C=$F25))"),382.4776857142856) -> 382.47769 | I25: Doc. 2020 | J25: =vlookup(K25,Pessoal!$A$6:$U$18,21) -> Parcial | K25: Márcio Henrique Nogueira | L25: =vlookup(K25,Pessoal!$A$6:$B$18,2,false) -> 088.869.216-16 | M25: =vlookup(K25,Pessoal!$A$6:$E$18,5,false) -> Pós graduado | N25: =$R25*(N$31/($N$31+$P$31)) -> 16805.653 | O25: =$S25*(N$31/($N$31+$P$31)) -> 322.24445 | P25: =$R25*(P$31/($N$31+$P$31)) -> 4220.2452 | Q25: =$S25*(P$31/($N$31+$P$31)) -> 80.922213 | R25: =IFERROR(__xludf.DUMMYFUNCTION("iferror(sum(filter(Timesheet!$N:$N,Timesheet!$C:$C=""EE - 2020"",Timesheet!$J:$J=TRUE,Timesheet!$B:$B=$K25)))"),21025.897967773013) -> 21025.898 | S25: =IFERROR(__xludf.DUMMYFUNCTION("IFERROR(SUM(filter(Timesheet!$H:$H,Timesheet!$C:$C=""EE - 2020"",Timesheet!$J:$J=TRUE,Timesheet!$B:$B=$K25)))*24"),403.16666666666686) -> 403.16667
F26: Peptimax - pesquisa | G26: NP | H26: =IFERROR(__xludf.DUMMYFUNCTION("sum(filter(Timesheet!$N:$N,Timesheet!$C:$C=$F26))"),799.7260701298701) -> 799.72607 | J26: =vlookup(K26,Pessoal!$A$6:$U$18,21) -> Parcial | K26: Kézia Rithássia Piccoli | L26: =vlookup(K26,Pessoal!$A$6:$B$18,2,false) -> 077.680.169-47 | M26: =vlookup(K26,Pessoal!$A$6:$E$18,5,false) -> Pós graduado | N26: =$R26*(N$31/($N$31+$P$31)) -> 29.980548 | O26: =$S26*(N$31/($N$31+$P$31)) -> 0.79928347 | P26: =$R26*(P$31/($N$31+$P$31)) -> 7.5287326 | Q26: =$S26*(P$31/($N$31+$P$31)) -> 0.20071653 | R26: =IFERROR(__xludf.DUMMYFUNCTION("iferror(sum(filter(Timesheet!$N:$N,Timesheet!$C:$C=""EE - 2020"",Timesheet!$J:$J=TRUE,Timesheet!$B:$B=$K26)))"),37.50928062469937) -> 37.509281 | S26: =IFERROR(__xludf.DUMMYFUNCTION("IFERROR(SUM(filter(Timesheet!$H:$H,Timesheet!$C:$C=""EE - 2020"",Timesheet!$J:$J=TRUE,Timesheet!$B:$B=$K26)))*24"),1.0) -> 1
F27: HDmax 2.0 | G27: NP | H27: =IFERROR(__xludf.DUMMYFUNCTION("sum(filter(Timesheet!$N:$N,Timesheet!$C:$C=$F27))"),503.93814435275374) -> 503.93814 | I27: Doc. 2020 | J27: =vlookup(K27,Pessoal!$A$6:$U$18,21) -> Parcial | K27: Juliana Lamas Roberto | L27: =vlookup(K27,Pessoal!$A$6:$B$18,2,false) -> 317.875.738-42 | M27: =vlookup(K27,Pessoal!$A$6:$E$18,5,false) -> Pós graduado | N27: =$R27*(N$31/($N$31+$P$31)) -> 61430.165 | O27: =$S27*(N$31/($N$31+$P$31)) -> 833.4262 | P27: =$R27*(P$31/($N$31+$P$31)) -> 15426.379 | Q27: =$S27*(P$31/($N$31+$P$31)) -> 209.29047 | R27: =IFERROR(__xludf.DUMMYFUNCTION("iferror(sum(filter(Timesheet!$N:$N,Timesheet!$C:$C=""EE - 2020"",Timesheet!$J:$J=TRUE,Timesheet!$B:$B=$K27)))"),76856.54401715586) -> 76856.544 | S27: =IFERROR(__xludf.DUMMYFUNCTION("IFERROR(SUM(filter(Timesheet!$H:$H,Timesheet!$C:$C=""EE - 2020"",Timesheet!$J:$J=TRUE,Timesheet!$B:$B=$K27)))*24"),1042.716666666667) -> 1042.7167
F28: Pasta de Amendoim - RUTF | G28: NP | H28: =IFERROR(__xludf.DUMMYFUNCTION("sum(filter(Timesheet!$N:$N,Timesheet!$C:$C=$F28))"),1797.161249060546) -> 1797.1612 | J28: =vlookup(K28,Pessoal!$A$6:$U$18,21) -> Parcial | K28: Gabriela Faria de Oliveira | L28: =vlookup(K28,Pessoal!$A$6:$B$18,2,false) -> 087.823.469-17 | M28: =vlookup(K28,Pessoal!$A$6:$E$18,5,false) -> Superior Completo | N28: =$R28*(N$31/($N$31+$P$31)) -> 27.791645 | O28: =$S28*(N$31/($N$31+$P$31)) -> 0.79928347 | P28: =$R28*(P$31/($N$31+$P$31)) -> 6.9790539 | Q28: =$S28*(P$31/($N$31+$P$31)) -> 0.20071653 | R28: =IFERROR(__xludf.DUMMYFUNCTION("iferror(sum(filter(Timesheet!$N:$N,Timesheet!$C:$C=""EE - 2020"",Timesheet!$J:$J=TRUE,Timesheet!$B:$B=$K28)))"),34.7706987012987) -> 34.770699 | S28: =IFERROR(__xludf.DUMMYFUNCTION("IFERROR(SUM(filter(Timesheet!$H:$H,Timesheet!$C:$C=""EE - 2020"",Timesheet!$J:$J=TRUE,Timesheet!$B:$B=$K28)))*24"),1.0) -> 1
F29: Immax - etapa final da Pesquisa Clínica | G29: NP | H29: =IFERROR(__xludf.DUMMYFUNCTION("sum(filter(Timesheet!$N:$N,Timesheet!$C:$C=$F29))"),783.9153162923882) -> 783.91532 | I29: Doc. 2020 | N29: =sum(N20:N28) -> 95289.136 | O29: =sum(O20:O28) -> 1505.0241 | P29: =sum(P20:P28) -> 23929.063 | Q29: =sum(Q20:Q28) -> 377.94253
F30: Trophic Dose Única | G30: MProduto | H30: =IFERROR(__xludf.DUMMYFUNCTION("sum(filter(Timesheet!$N:$N,Timesheet!$C:$C=$F30))"),2234.9583200494526) -> 2234.9583
F31: Trophic Basic Enteral | G31: NP | H31: =IFERROR(__xludf.DUMMYFUNCTION("sum(filter(Timesheet!$N:$N,Timesheet!$C:$C=$F31))"),2079.875286257666) -> 2079.8753 | M31: Valores e horas sem o EE - 2020 | N31: 179199.87 | O31: 3880.2333 | P31: 45000.774 | Q31: 1191.5
F32: Jumbo UHT | G32: NP | H32: =IFERROR(__xludf.DUMMYFUNCTION("sum(filter(Timesheet!$N:$N,Timesheet!$C:$C=$F32))"),419.87475288600285) -> 419.87475
F33: Trophic Junior Líquido 1.0 e 1.5 (ARB) | G33: NP | H33: =IFERROR(__xludf.DUMMYFUNCTION("sum(filter(Timesheet!$N:$N,Timesheet!$C:$C=$F33))"),131.2108602768759) -> 131.21086
F34: Trophic Junior Powder (China) | G34: NP | H34: =IFERROR(__xludf.DUMMYFUNCTION("sum(filter(Timesheet!$N:$N,Timesheet!$C:$C=$F34))"),156.4556277056277) -> 156.45563
F35: Congresso ESPEN | G35: NP | H35: =IFERROR(__xludf.DUMMYFUNCTION("sum(filter(Timesheet!$N:$N,Timesheet!$C:$C=$F35))"),1591.666908225108) -> 1591.6669
H36: =sum(H2:H35) -> 356413.4

Sheet Investimentos
A2: Investimentos | R2: 740679.72
M3: =SUMIFS(M7:M137,$J$7:$J137,TRUE,$U$7:$U137,TRUE) -> 239212.73 | N3: =SUMIFS(N7:N137,$J$7:$J137,TRUE,$U$7:$U137,TRUE) -> 0 | O3: =SUMIFS(O7:O137,$J$7:$J137,TRUE,$U$7:$U137,TRUE) -> 243517.55 | P3: =SUMIFS(P7:P137,$J$7:$J137,TRUE,$U$7:$U137,TRUE) -> 20849.44 | Q3: =SUMIFS(Q7:Q137,$J$7:$J137,TRUE,$U$7:$U137,TRUE) -> 0 | R3: =SUM(M3:Q3) -> 503579.72
G4: =SUM(G6:G137) -> 739470.82 | H4: =SUM(H6:H137) -> 608065.64 | M4: =SUM(M7:M137) -> 239674.48 | N4: =SUM(N7:N137) -> 0 | O4: =SUM(O7:O137) -> 243517.55 | P4: =SUM(P7:P137) -> 20849.44 | Q4: =SUM(Q7:Q137) -> 0 | R4: =R2-R3 -> 237100
A5: Cod | C5: Fornecedor | D5: CNPJ | E5: Descrição | F5: NF/ND | G5: Valor original | H5: R$ Incentivavel | I5: Data | J5: Inovação? | K5: Attachments | L5: Tipo | M5: Novos Produtos | N5: Novas matérias-primas | O5: Melhoria de Produto | P5: Melhoria de Processo | Q5: Segurança Alimentar | R5: Tipo 2 | S5: Projeto | T5: Projeto | U5: Proj incentivado?
A6: 1º Semestre | U6: FALSE
A7: 1 | C7: J&J Serviços de Entregas Ltda - ME | D7: 20.618.029/0001-49 | E7: Envio de amostra para análise | F7: 47078 | G7: 193.01 | H7: 193.01 | I7: 44200 | J7: TRUE | L7: Serviço | M7: - | N7: - | O7: 241.44 | P7: 74.6 | R7: Serviço de terceiros | S7: Immax, Trophic EP, Trophic Basic, Trophic Fiber | T7: InstanTH NEO/ Novos produtos | U7: TRUE
A8: 2 | C8: Eurofins do Brasil Análise de Alimentos Ltda. | D8: 04.329.668/0001-38 | E8: Análise de macronutrientes | F8: 68453 | G8: 2010.8 | H8: 2010.8 | I8: 44201 | J8: TRUE | L8: Serviço | M8: 131.88 | N8: - | O8: 1115.74 | P8: - | R8: Serviço de terceiros | S8: Trophic Basic, Trophic Fiber, Energyzip Sênior | U8: TRUE
A9: 3 | C9: ASPEN - American Society for Parenteral and Enteral Society | E9: Inscrição em Congresso | F9: 123287 | G9: 3208.5 | H9: 3208.5 | I9: 44203 | J9: TRUE | L9: Serviço | M9: 823 | N9: - | O9: 823 | P9: - | R9: Serviço de terceiros | S9: Bemmax e Immax | U9: TRUE
A10: 4 | C10: Fundação de desenv. da pesquisa do agronegócio - FUNDEPAG | D10: 50.276.237/0001-78 | E10: Análise de perfil lipídico (T0) | F10: 123266 | G10: 6170 | H10: 6170 | I10: 44203 | J10: TRUE | L10: Serviço | M10: 667 | N10: - | O10: 667 | P10: - | R10: Serviço de terceiros | S10: Bemmax e Immax | U10: TRUE
A11: 5 | C11: Fundação de desenv. da pesquisa do agronegócio - FUNDEPAG | D11: 50.276.237/0001-78 | E11: Análise de perfil lipídico (T0) | F11: 3434319092 | G11: 1234 | H11: 1234 | I11: 44200 | J11: TRUE | K11: Não entra | L11: Serviço | M11: 1911.51 | N11: - | O11: - | P11: - | R11: Serviço de terceiros | S11: Retort | T11: Produtos em pó e líquidos | U11: TRUE
A12: 6 | C12: Eurofins do Brasil Análise de Alimentos Ltda. | D12: 04.329.668/0001-38 | E12: Análise de macro e micronutrientes | F12: 68933 | G12: 13299.57 | H12: 13299.57 | I12: 44211 | J12: TRUE | L12: Serviço | M12: - | N12: - | O12: 259.14 | P12: - | R12: Serviço de terceiros | S12: Energyzip baunilha | T12: Bemmax Sabor Neutro, Instant NEO, Instanth Clear | U12: TRUE
A13: 7 | C13: Fundação Arthur Bernardes | D13: 20.320.503/0001-51 | E13: 1a/2 parcela contrato Embrapa FUNARBE de R$11.600,00 (contrato 052/21) | F13: 47650 | G13: 5800 | H13: 5800 | I13: 44215 | J13: TRUE | L13: Serviço | M13: - | N13: - | O13: 196.95 | P13: - | R13: Serviço de terceiros | S13: Energyzip baunilha, Energyzip 1.0, Energyzip chocolate, Trophic Fiber líq e Trophic Basic líq | T13: Bemmax Sabor Neutro, Instant NEO, Instanth Clear | U13: TRUE
A14: 8 | C14: Eurofins do Brasil Análise de Alimentos Ltda. | D14: 04.329.668/0001-38 | E14: Análise T0 das 5 dietas retort | F14: 154760 | G14: 43159 | H14: 43159 | I14: 44215 | J14: TRUE | L14: Serviço | M14: - | N14: - | O14: 246.8 | P14: - | R14: Serviço de terceiros | S14: Trophic EP | T14: Bemmax Sabor Neutro, Instant NEO, Instanth Clear | U14: TRUE
A15: 9 | C15: Fundação Arthur Bernardes | D15: 20.320.503/0001-51 | E15: 2a/2 parcela contrato Embrapa FUNARBE de R$11.600,00 (contrato 052/21) | F15: 68740 | G15: 5800 | H15: 5800 | I15: 44208 | J15: TRUE | L15: Serviço | M15: 395.64 | N15: - | O15: 1982.9 | P15: - | R15: Serviço de terceiros | S15: Trophic Basic pó, Trophic Fiber pó e Energyzip Sênior | T15: Bemmax Sabor Neutro, Instant NEO, Instanth Clear | U15: TRUE
A16: 10 | C16: JF Inox - Metais e Serviços Eireli | E16: Confecção de bandejas para autoclave Embrapa | F16: 123478 | G16: 1440 | H16: 1440 | I16: 44215 | J16: TRUE | L16: Serviço | M16: - | N16: - | O16: 2001 | P16: - | R16: Serviço de terceiros | S16: Trophic Basic pó e Trophic Fiber pó | T16: Bemmax Sabor Neutro, Instant NEO, Instanth Clear | U16: TRUE
A17: 11 | C17: Márcio Nogueira | D17: 088.869.216-16 | E17: Gastos com viagem para TP Castrolanda (Castro/PR) | F17: CGHR003524800 | G17: 682.2 | H17: 682.2 | I17: 44211 | J17: TRUE | L17: Serviço | M17: 359.77 | N17: - | O17: - | P17: - | R17: Serviço de terceiros | S17: Isosource Soya, Fresubin Soya Fibre, Retort NN | T17: Instanth CLEAR | U17: TRUE
A18: 12 | C18: LSD SERVIÇOS DE TRADUÇÃO LTDA | E18: Tradução de artigo cientifico | F18: CWBIR01614171 | G18: 906 | H18: 906 | I18: 44211 | J18: TRUE | K18: Não entra | L18: Serviço | M18: 1603.03 | N18: - | O18: - | P18: - | R18: Serviço de terceiros | S18: Retort | U18: TRUE
A19: 13 | C19: Camila Mendes Pereira | E19: Compra de concorrentes para TB | F19: 69328 | G19: 233.8 | H19: 233.8 | I19: 44221 | J19: TRUE | L19: Serviço | M19: - | N19: - | O19: 829.08 | P19: - | R19: Serviço de terceiros | S19: Energyzip baunilha | U19: TRUE
A20: 14 | C20: Márcio Nogueira | D20: 088.869.216-16 | E20: Gastos com viagem para TP Castrolanda (Castro/PR) | F20: 202100000000122 | G20: 448 | H20: 448 | I20: 44222 | J20: TRUE | L20: Serviço | M20: 5144 | N20: - | O20: - | P20: - | R20: Serviço de terceiros | S20: Retort | T20: Produtos líquidos - todos os projetos | U20: TRUE
A21: 15 | C21: Localiza rent a car AS | E21: Aluguel de veículo para teste com Perfilmaq (General Carneiro/PR) | F21: 8 | G21: 312.93 | H21: 312.93 | I21: 44227 | J21: TRUE | L21: Serviço | M21: - | N21: - | O21: 3200 | P21: - | R21: Serviço de terceiros | S21: Todos os produtos (pó e líquido) | U21: TRUE | V21: GERAL
A22: 16 | C22: J&J Serviços de Entregas Ltda - ME | D22: 20.618.029/0001-49 | E22: Envio de amostra para análise | F22: 1423 | G22: 79.1 | H22: 79.1 | I22: 44228 | J22: TRUE | K22: Não entra | L22: Serviço | M22: 4500 | N22: - | O22: - | P22: - | R22: Serviço de terceiros | S22: Trophic Basic pó, Trophic Fiber pó, Trophic 1.5 250mL, Sachês (Carboch, Proteinpt Whey e Enterfiber Prebiotic) | U22: TRUE
A23: 17 | C23: Eurofins do Brasil Análise de Alimentos Ltda. | D23: 04.329.668/0001-38 | E23: Envio para análises EE | F23: 48081 | G23: 195.54 | H23: 195.54 | I23: 44230 | J23: TRUE | L23: Serviço | M23: 54.76 | N23: - | O23: 140.69 | P23: - | R23: Serviço de terceiros | S23: Instanth Neo, Energyzip Chocolate, Energyzip Morango e Trophic Fiber | U23: TRUE
A24: 18 | C24: Fundação de desenv. da pesquisa do agronegócio - FUNDEPAG | D24: 50.276.237/0001-78 | E24: Curso Embalagem Celulósicas - CETEA | F24: 104700 | G24: 550 | H24: 550 | I24: 44223 | J24: TRUE | L24: Serviço | M24: 6734.39 | N24: - | O24: - | P24: - | R24: Serviço de terceiros | S24: Concorrentes e NN | U24: TRUE | V24: GERAL
A25: 19 | C25: Eurofins do Brasil Análise de Alimentos Ltda. | D25: 04.329.668/0001-38 | E25: Análise T0 | F25: 65055 | G25: 12979.17 | H25: 12979.17 | I25: 44207 | J25: TRUE | K25: Não entra | L25: Serviço | M25: 97.5 | N25: - | O25: - | P25: - | R25: Serviço de terceiros | S25: Instanth, Instanth Clear e Bemmax Sabor Neutro | U25: TRUE
A26: 20 | C26: Fundação de desenv. da pesquisa do agronegócio - FUNDEPAG | D26: 50.276.237/0001-78 | E26: Análise de perfil lipídico (t0) | F26: 123727 | G26: 1405 | H26: 1405 | I26: 44232 | J26: TRUE | L26: Serviço | M26: 2196.86 | N26: - | O26: - | P26: - | R26: Serviço de terceiros | S26: Instanth Neo | U26: TRUE
A27: 21 | C27: Cell e Target Eventos e Cursos Ltda | E27: Inscrição no Ganepão | F27: 155988 | G27: 397 | H27: 397 | I27: 44235 | J27: TRUE | L27: Serviço | M27: - | N27: - | O27: 991.2 | P27: - | R27: Serviço de terceiros | S27: Trophic EP | U27: TRUE
A28: 22 | C28: Eurofins do Brasil Análise de Alimentos Ltda. | D28: 04.329.668/0001-38 | E28: Análise T4 | F28: 65405 | G28: 10878.21 | H28: 10878.21 | I28: 44235 | J28: TRUE | K28: Não entra | L28: Serviço | M28: 97.5 | N28: - | O28: - | P28: - | R28: Serviço de terceiros | S28: Instanth, Instanth Clear e Bemmax Sabor Neutro | U28: TRUE
A29: 23 | C29: Eurofins do Brasil Análise de Alimentos Ltda. | D29: 04.329.668/0001-38 | E29: Análise T0 (aumento SL) | F29: 69962 | G29: 12982.29 | H29: 12982.29 | I29: 44236 | J29: TRUE | L29: Serviço | M29: - | N29: - | O29: - | P29: 2255.64 | R29: Serviço de terceiros | S29: Produtos em pó | U29: TRUE | V29: GERAL
A30: 24 | C30: Azul Linhas Aereas Brasileiras S.A | E30: Aéreo teste Embrapa/RJ - Juliana | F30: 156512 | G30: 774.38 | H30: 774.38 | I30: 44243 | J30: TRUE | L30: Serviço | M30: - | N30: - | O30: 6829.6 | P30: - | R30: Serviço de terceiros | S30: Trophic 1.5, Trophic Basic, Trophic Fiber, Energyzip 1.0 | U30: TRUE
A31: 25 | C31: Azul Linhas Aereas Brasileiras S.A | E31: Aéreo teste Embrapa/RJ - Lizianne | F31: 156456 | G31: 724.21 | H31: 724.21 | I31: 44242 | J31: TRUE | L31: Serviço | M31: - | N31: - | O31: 233.1 | P31: - | R31: Serviço de terceiros | S31: Energyzip Chocolate | U31: TRUE
A32: 26 | C32: Restaurante Canaa | E32: Alimentação teste Latco (Cruzeiro do Oeste/PR) - Lizianne | F32: 202100000000207 | G32: 28 | H32: 28 | I32: 44237 | J32: TRUE | L32: Serviço | M32: 5144 | N32: - | O32: - | P32: - | R32: Serviço de terceiros | S32: Retort | T32: Novos produtos | U32: TRUE
A33: 27 | C33: Cocamar Postos de Combustíveis Ltda | E33: Combustível para carro alugado - teste Lacto (Cruzeiro do Oeste/PR) | F33: 21318 | G33: 149.03 | H33: 149.03 | I33: 44236 | J33: TRUE | L33: Serviço | M33: 120 | N33: - | O33: 120 | P33: - | R33: Serviço de terceiros | S33: Todos os produtos (pó e líquido) | U33: TRUE | V33: GERAL
A34: 28 | C34: FLP PIZZARIA EIRELI | E34: Alimentação teste Latco (Cruzeiro do Oeste/PR) - Lizianne | F34: 123927 | G34: 58.97 | H34: 58.97 | I34: 44239 | J34: TRUE | L34: Serviço | M34: - | N34: - | O34: 3505 | P34: - | R34: Serviço de terceiros | S34: Trophic 1.5, Trophic Basic, Trophic Fiber, Energyzip 1.0, Energyzip chocolate | U34: TRUE
A35: 29 | C35: DPR Turismo Ltda | E35: Aéreo teste Latco (Cruzeiro do Oeste/PR) - Marianne | F35: 123937 | G35: 804.63 | H35: 804.63 | I35: 44239 | J35: TRUE | L35: Serviço | M35: - | N35: - | O35: 701 | P35: - | R35: Serviço de terceiros | S35: Energyzip morango | U35: TRUE
A36: 30 | C36: DPR Turismo Ltda | E36: Aéreo teste Latco (Cruzeiro do Oeste/PR) - Fabiano | F36: 156661 | G36: 804.63 | H36: 804.63 | I36: 44244 | J36: TRUE | L36: Serviço | M36: - | N36: - | O36: 5957.54 | P36: - | R36: Serviço de terceiros | S36: Energyzip morango | U36: TRUE
A37: 31 | C37: Eurofins do Brasil Análise de Alimentos Ltda. | D37: 04.329.668/0001-38 | E37: Análise T12 (Soya e EP), T18 (Peptimax) | F37: 48524 | G37: 55054.02 | H37: 55054.02 | I37: 44244 | J37: TRUE | L37: Serviço | M37: 104.45 | N37: - | O37: - | P37: - | R37: Serviço de terceiros | S37: Instanth Neo | U37: TRUE
A38: 32 | C38: Studio Madcreative Design Ltda - ME | D38: 11.115.312/0001-67 | E38: Desenvolvimento de embalagens | F38: 156764 | G38: 7200 | H38: 7200 | I38: 44245 | J38: TRUE | L38: Serviço | M38: - | N38: - | O38: 16224.02 | P38: - | R38: Serviço de terceiros | S38: Trophic EP, Energyzip morango, Energyzip chocolate | U38: TRUE
A39: 33 | C39: Fundação de desenv. da pesquisa do agronegócio - FUNDEPAG | D39: 50.276.237/0001-78 | E39: Análise de perfil lipídico - T6A (HH, HN e NHcF), T0 (Trophic Soya 1.5) | F39: 156878 | G39: 5000 | H39: 5000 | I39: 44246 | J39: TRUE | L39: Serviço | M39: - | N39: - | O39: 546 | P39: - | R39: Serviço de terceiros | S39: Energyzip morango | U39: TRUE
A40: 34 | C40: Eurofins do Brasil Análise de Alimentos Ltda. | D40: 04.329.668/0001-38 | E40: Análise de T6LD e T6A de vit, min e macronutrientes (HH, HN e NHcF) | F40: 124111 | G40: 36223.97 | H40: 36223.97 | I40: 44245 | J40: TRUE | L40: Serviço | M40: - | N40: - | O40: 3335 | P40: - | R40: Serviço de terceiros | S40: Immax e Bemmax | U40: TRUE
A41: 35 | C41: J&J Serviços de Entregas Ltda - ME | D41: 20.618.029/0001-49 | E41: Envio de amostra para análise | F41: 157010 | G41: 285.66 | H41: 285.66 | I41: 44249 | J41: TRUE | L41: Serviço | M41: - | N41: - | O41: 246.8 | P41: - | R41: Serviço de terceiros | S41: Energyzip Chocolate | U41: TRUE
A42: 36 | C42: Everton Claudi Graeff | E42: RDV teste Embrapa/RJ | F42: 157030 | G42: 711.88 | H42: 711.88 | I42: 44249 | J42: TRUE | L42: Serviço | M42: - | N42: - | O42: 32225.2 | P42: - | R42: Serviço de terceiros | S42: Trophic 1.5, Trophic Basic, Trophic Fiber, Energyzip 1.0 | U42: TRUE
A43: 37 | C43: Eurofins do Brasil Análise de Alimentos Ltda. | D43: 04.329.668/0001-38 | E43: Análise T0 de vitaminas, minerais e macronutrientes | F43: 157187 | G43: 12554.79 | H43: 12554.79 | I43: 44251 | J43: TRUE | L43: Serviço | M43: - | N43: - | O43: 2753.7 | P43: - | R43: Serviço de terceiros | S43: Trophic 1.5, Trophic Basic, Trophic Fiber | U43: TRUE
A44: 38 | C44: Eurofins do Brasil Análise de Alimentos Ltda. | D44: 04.329.668/0001-38 | E44: Análise T0 de vitaminas, minerais e macronutrientes | F44: 157251 | G44: 13961.66 | H44: 0 | I44: 44252 | J44: TRUE | L44: Serviço | M44: - | N44: - | O44: 7715.68 | P44: - | R44: Serviço de terceiros | S44: Trophic 1.5, Trophic Basic, Trophic Fiber, Energyzip 1.0, Energyzip chocolate, Energyzip morango | T44: Produtos líquidos | U44: TRUE
A45: 39 | C45: Studio Madcreative Design Ltda - ME | D45: 11.115.312/0001-67 | E45: Desenvolvimento de embalagens | F45: 157225 | G45: 7200 | H45: 7200 | I45: 44252 | J45: TRUE | L45: Serviço | M45: - | N45: - | O45: 3007.9 | P45: - | R45: Serviço de terceiros | S45: Energyzip morango, Energyzip chocolate | T45: Trophic Soya 1.5 | U45: TRUE
A46: 40 | C46: Studio Madcreative Design Ltda - ME | D46: 11.115.312/0001-67 | E46: Desenvolvimento de embalagens | F46: 157400 | G46: 7200 | H46: 7200 | I46: 44256 | J46: TRUE | L46: Serviço | M46: - | N46: - | O46: 5958.8 | P46: - | R46: Serviço de terceiros | S46: Trophic 1.5, Trophic Basic, Trophic Fiber, Energyzip 1.0 | T46: Trophic Soya 1.5 | U46: TRUE
A47: 41 | C47: MCI Suisse SA, Rue du Pré-Bouvier 9, 1242 Satigny, Switzerland - ESPEN | E47: Inscrição em congresso ESPEN | F47: 70804 | G47: 2888.5 | H47: 2888.5 | I47: 44256 | J47: TRUE | L47: Serviço | M47: - | N47: - | O47: - | P47: 9465.46 | R47: Serviço de terceiros | S47: Instanth Neo | U47: TRUE
A48: 42 | C48: Gol Linhas aéreas | E48: Aéreo CWB - SP - CWB | F48: 71194 | G48: 471.8 | H48: 471.8 | I48: 44263 | J48: TRUE | L48: Serviço | M48: - | N48: - | O48: 229.63 | P48: 4434.24 | R48: Serviço de terceiros | S48: Produtos pó, Immax, ProteinPT Whey | U48: TRUE
A49: 43 | C49: Ibis | E49: Ibis Viena (1 diária) | F49: 157844 | G49: 341.66 | H49: 341.66 | I49: 44260 | J49: TRUE | L49: Serviço | M49: - | N49: - | O49: 105 | P49: - | R49: Serviço de terceiros | S49: Energyzip chocolate | U49: TRUE
A50: 44 | C50: Fundação de desenv. da pesquisa do agronegócio - FUNDEPAG | D50: 50.276.237/0001-78 | E50: Análise de perfil lipídico - T0 | F50: 70999 | G50: 1405 | H50: 1405 | I50: 44258 | J50: TRUE | L50: Serviço | M50: =829.08+259.14 -> 1088.22 | N50: - | O50: 527.73 | P50: - | R50: Serviço de terceiros | S50: Instanth Neo, Trophic Soya 1.5, Sustenlac Baunilha | T50: InstanTH NEO e Instanth Clear | U50: TRUE
A51: 45 | C51: Labor Três Laboratórios e Consultoria Técnica Ltda. | D51: 02.021.076/0001-29 | E51: Análises de Esterilidade comercial - T0 | F51: 65774 | G51: 762.3 | H51: 762.3 | I51: 44263 | J51: TRUE | K51: Não entra | L51: Serviço | M51: 200 | N51: - | O51: - | P51: - | R51: Serviço de terceiros | S51: Instanth, Instanth Clear e Bemmax Sabor Neutro | T51: InstanTH NEO e Instanth Clear | U51: TRUE
A52: 46 | C52: J&J Serviços de Entregas Ltda - ME | D52: 20.618.029/0001-49 | E52: Envio de amostra para análise | F52: 48845 | G52: 147.5 | H52: 147.5 | I52: 44257 | J52: TRUE | L52: Serviço | M52: 60.35 | N52: - | O52: - | P52: 227.55 | R52: Serviço de terceiros | S52: Immax e Retort | T52: InstanTH NEO e Instanth Clear | U52: TRUE
A53: 47 | C53: Fundação de Apoio à Universidade de São Paulo | E53: Análise de DP - HN, HH e HNcF | F53: 202100000000342 | G53: 777 | H53: 777 | I53: 44265 | J53: TRUE | L53: Serviço | M53: 5144 | N53: - | O53: - | P53: - | R53: Serviço de terceiros | S53: Retort | U53: TRUE
A54: 48 | C54: Juliana Lamas Roberto | E54: RDV teste Embrapa/RJ | F54: 107973 | G54: 388.27 | H54: 388.27 | I54: 44271 | J54: TRUE | L54: Serviço | M54: 373.02 | N54: - | O54: - | P54: - | R54: Serviço de terceiros | S54: Instanth Neo | U54: TRUE
A55: 49 | C55: Lizianne Angelica Shmeil | E55: RDV teste Embrapa/RJ | F55: 49307 | G55: 1970.56 | H55: 1970.56 | I55: 44273 | J55: TRUE | L55: Serviço | M55: 64.75 | N55: - | O55: - | P55: - | R55: Serviço de terceiros | S55: Produtos líquidos | U55: FALSE
A56: 50 | C56: Fundação Arthur Bernardes | D56: 20.320.503/0001-51 | E56: 1a/3 parcela contrato Embrapa FUNARBE de R$30.000,00 (contrato 007/22) | F56: 71636 | G56: 10000 | H56: 10000 | I56: 44273 | J56: TRUE | L56: Serviço | M56: 2023.14 | N56: - | O56: - | P56: 2023.14 | R56: Serviço de terceiros | S56: Immax, Trophic Basic, Trophic Fiber | U56: TRUE
A57: 51 | C57: DPR Turismo Ltda | E57: Hospedagem teste Embrapa/RJ - Lizianne e Juliana) + Aluguel de carro teste Embrapa/RJ | F57: 3762 | G57: 1336.84 | H57: 1336.84 | I57: 44271 | J57: TRUE | L57: Serviço | M57: 173.5 | N57: - | O57: - | P57: - | R57: Serviço de terceiros | S57: Dieta complemento artesanal | T57: Energyzip Baunilha | U57: TRUE
A58: 52 | C58: J&J Serviços de Entregas Ltda - ME | D58: 20.618.029/0001-49 | E58: Envio de amostra para análise | F58: 124960 | G58: 100.33 | H58: 0 | I58: 44274 | J58: TRUE | L58: Serviço | M58: 701 | N58: - | O58: - | P58: - | R58: Serviço de terceiros | S58: Instanth Neo | U58: TRUE
A59: 53 | C59: Fundação de desenv. da pesquisa do agronegócio - FUNDEPAG | D59: 50.276.237/0001-78 | E59: Análise de perfil lipídico - T18 | F59: 159096 | G59: 797 | H59: 0 | I59: 44277 | J59: TRUE | L59: Serviço | M59: - | N59: - | O59: 3798.48 | P59: - | R59: Serviço de terceiros | S59: Trophic 1.5, Trophic Basic, Trophic Fiber, Energyzip 1.0 | U59: TRUE
A60: 54 | C60: Fundação de apoio à Pesquisa | E60: Apoio à pesquisa clinica | F60: 125083 | G60: 8856 | H60: 8856 | I60: 44280 | J60: TRUE | L60: Serviço | M60: - | N60: - | O60: - | P60: 701 | R60: Serviço de terceiros | S60: Immax lata recravada | U60: TRUE
A61: 55 | C61: Fundação Arthur Bernardes | D61: 20.320.503/0001-51 | E61: 2a/3 parcela contrato Embrapa FUNARBE de R$30.000,00 (contrato 007/22) | F61: 71755 | G61: 10000 | H61: 10000 | I61: 44277 | J61: TRUE | L61: Serviço | M61: 259.14 | N61: - | O61: - | P61: - | R61: Serviço de terceiros | S61: Trophic Fiber pó | U61: TRUE
A62: 56 | C62: DHL Express (Brazil) Ltda | E62: Recebimento de amostra de pouch (Alemanha) | F62: 1 | G62: 482.11 | H62: 482.11 | I62: 44283 | J62: TRUE | K62: Não entra | L62: Serviço | M62: 5000 | N62: - | O62: - | P62: - | R62: Serviço de terceiros | S62: Trophic dose única 250mL | T62: Immax | U62: TRUE
A63: 57 | C63: Eurofins do Brasil Análise de Alimentos Ltda. | D63: 04.329.668/0001-38 | E63: Análise de vitaminas B1, C e A (HH antes do processo de esterilização) | F63: 125080 | G63: 2066.62 | H63: 2066.62 | I63: 44280 | J63: TRUE | L63: Serviço | M63: 701 | N63: - | O63: - | P63: - | R63: Serviço de terceiros | S63: Instanth Neo | U63: TRUE
A64: 58 | C64: Eurofins do Brasil Análise de Alimentos Ltda. | D64: 04.329.668/0001-38 | E64: Análise de vitaminas, minerais e macronutrientes para T0 (HH, HN e HNcF) | F64: 159589 | G64: 41570.82 | H64: 41570.82 | I64: 44285 | J64: TRUE | L64: Serviço | M64: - | N64: - | O64: 1003.91 | P64: - | R64: Serviço de terceiros | S64: Trophic EP | T64: Energyzip baunilha | U64: TRUE
A65: 59 | C65: Eurofins do Brasil Análise de Alimentos Ltda. | D65: 04.329.668/0001-38 | E65: Análise de vitaminas, minerais e macronutrientes para T18 | F65: 159663 | G65: 14438.49 | H65: 0 | I65: 44287 | J65: TRUE | L65: Serviço | M65: - | N65: - | O65: 4456.64 | P65: - | R65: Serviço de terceiros | S65: Trophic 1.5, Trophic Basic, Trophic Fiber, Energyzip 1.0 | U65: TRUE
A66: 60 | C66: J&J Serviços de Entregas Ltda - ME | D66: 20.618.029/0001-49 | E66: Envio de amostra para análise - NHcF T9LD | F66: 1526 | G66: 58.36 | H66: 58.36 | I66: 44287 | J66: TRUE | K66: Não entra | L66: Serviço | M66: 3000 | N66: - | O66: - | P66: - | R66: Serviço de terceiros | S66: Sachês e Diamax IG | U66: TRUE
A67: 61 | C67: Fundação de desenv. da pesquisa do agronegócio - FUNDEPAG | D67: 50.276.237/0001-78 | E67: Análise de perfil lipídico - T0 (HH, HN e HNcF) | F67: 202100000000508 | G67: 4215 | H67: 4215 | I67: 44295 | J67: TRUE | L67: Serviço | M67: 5144 | N67: - | O67: - | P67: - | R67: Serviço de terceiros | S67: Retort | T67: Bemmax Sabor Neutro, Instant NEO | U67: TRUE
A68: 62 | C68: Studio Madcreative Design Ltda - ME | D68: 11.115.312/0001-67 | E68: Desenvolvimento de rotulagem | F68: 405124 | G68: 7200 | H68: 7200 | I68: 44294 | J68: TRUE | L68: Serviço | M68: 1402 | N68: - | O68: - | P68: - | R68: Serviço de terceiros | S68: Trophic 1.5 e Trophic EP | T68: Produtos pó | U68: TRUE
A69: 63 | C69: Eurofins do Brasil Análise de Alimentos Ltda. | D69: 04.329.668/0001-38 | E69: Análise de vitaminas, minerais e macronutrientes para T12 | F69: 72407 | G69: 14865.99 | H69: 0 | I69: 44295 | J69: TRUE | L69: Serviço | M69: 259.14 | N69: - | O69: 4273.68 | P69: - | R69: Serviço de terceiros | S69: Produtos concorrentes e Trophic Basic pó lata | T69: Trophic EP | U69: TRUE
A70: 64 | C70: Fundação de desenv. da pesquisa do agronegócio - FUNDEPAG | D70: 50.276.237/0001-78 | E70: Análise de perfil lipídico - T18 | F70: 72239 | G70: 730 | H70: 0 | I70: 44291 | J70: TRUE | L70: Serviço | M70: - | N70: - | O70: 5427.24 | P70: - | R70: Serviço de terceiros | S70: Produto concorrente | T70: Instanth Clear, InstanTH NEO e Bemmax Sabor Neutro | U70: TRUE | V70: GERAL
A71: 65 | C71: Labor Três Laboratórios e Consultoria Técnica Ltda. | D71: 02.021.076/0001-29 | E71: Análise de microbiologia - T18 | F71: 160216 | G71: 260 | H71: 0 | I71: 44293 | J71: TRUE | L71: Serviço | M71: - | N71: - | O71: 2683.91 | P71: - | R71: Serviço de terceiros | S71: Peptimax | T71: Trophic EP | U71: TRUE
A72: 66 | C72: Fundação de apoio à Pesquisa | E72: Apoio à pesquisa clinica | F72: 160034 | G72: 8856 | H72: 8856 | I72: 44291 | J72: TRUE | L72: Serviço | M72: - | N72: - | O72: 9848.1 | P72: - | R72: Serviço de terceiros | S72: Peptimax | T72: Trophic Basic L, Trophic Fiber L, Trophic 1.5, Energyzip Chocolate | U72: TRUE
A73: 67 | C73: ZAY SERVIÇOS DE ANÁLISES QUÍMICAS LTDA | E73: Serviço terceirizado de condução de estudo de estabilidade | F73: 2021/24 | G73: 2158.55 | H73: 2158.55 | I73: 44293 | J73: TRUE | K73: Não entra | L73: Serviço | M73: 1840 | N73: - | O73: - | P73: - | R73: Serviço de terceiros | S73: Diamax IG | T73: HDmax e Instant Neo | U73: TRUE
A74: 68 | C74: Tetra Pak Ltda | E74: Aluguel de planta para teste piloto | F74: 49705 | G74: 27988.34 | H74: 27988.34 | I74: 44291 | J74: TRUE | L74: Serviço | M74: - | N74: - | O74: - | P74: 127.15 | R74: Serviço de terceiros | S74: Immax lata recravada | U74: TRUE
A75: 69 | C75: Eurofins do Brasil Análise de Alimentos Ltda. | D75: 04.329.668/0001-38 | E75: Análise de macronutrientes para T18 | F75: 72542 | G75: 222.12 | H75: 0 | I75: 44298 | J75: TRUE | L75: Serviço | M75: - | N75: - | O75: 16281.72 | P75: - | R75: Serviço de terceiros | S75: Produtos concorrentes | U75: TRUE | V75: GERAL
A76: 70 | C76: Fundação de desenv. da pesquisa do agronegócio - FUNDEPAG | D76: 50.276.237/0001-78 | E76: Análise de perfil lipídico - T9 NHcF | F76: 125637 | G76: 730 | H76: 730 | I76: 44300 | J76: TRUE | L76: Serviço | M76: 1402 | N76: - | O76: - | P76: - | R76: Serviço de terceiros | S76: Retort | T76: Hdmax | U76: TRUE
A77: 71 | C77: J&J Serviços de Entregas Ltda - ME | D77: 20.618.029/0001-49 | E77: Envio de amostra para análise | F77: 211060 | G77: 42 | H77: 0 | I77: 44305 | J77: TRUE | L77: Serviço | M77: 18140.73 | N77: - | O77: - | P77: - | R77: Serviço de terceiros | S77: Instanth Neo | T77: Produtos líquidos | U77: TRUE
A78: 72 | C78: J&J Serviços de Entregas Ltda - ME | D78: 20.618.029/0001-49 | E78: Envio de amostra para análise | F78: 160945 | G78: 133 | H78: 133 | I78: 44302 | J78: TRUE | L78: Serviço | M78: - | N78: - | O78: 3486.9 | P78: - | R78: Serviço de terceiros | S78: Peptimax | U78: TRUE
A79: 73 | C79: ZAY SERVIÇOS DE ANÁLISES QUÍMICAS LTDA | E79: Aluguel de espaço em câmara climática, para estudo acelerado das dietas retort HH, HN e HNcF V04 e V05 | F79: 50184 | G79: 3000 | H79: 3000 | I79: 44305 | J79: TRUE | L79: Serviço | M79: 202.8 | N79: - | O79: 126.35 | P79: - | R79: Serviço de terceiros | S79: HDMaX 2.0, Energyzip Sênior, Trophic Fiber, Trophic EP e Trophic Soya | U79: TRUE
A80: 74 | C80: Fundação Arthur Bernardes | D80: 20.320.503/0001-51 | E80: 3a/3 parcela contrato Embrapa FUNARBE de R$30.000,00 (contrato 007/22) | F80: 72991 | G80: 10000 | H80: 10000 | I80: 44306 | J80: TRUE | L80: Serviço | M80: - | N80: - | O80: 3709 | P80: - | R80: Serviço de terceiros | S80: Produtos concorrentes | U80: TRUE | V80: GERAL
A81: 75 | C81: Eurofins do Brasil Análise de Alimentos Ltda. | D81: 04.329.668/0001-38 | E81: Análise de macronutrientes, Vitamina E, B1, B2, B5, Biotina, Selênio, Molibdênio e Cromo (T9LD NHcF) | F81: 27 | G81: 6539.76 | H81: 6539.76 | I81: 44296 | J81: TRUE | K81: Não entra | L81: Serviço | M81: - | N81: - | O81: 624.33 | P81: - | R81: Serviço de terceiros | S81: Bemmax | U81: TRUE
A82: 76 | C82: J&J Serviços de Entregas Ltda - ME | D82: 20.618.029/0001-49 | E82: Envio de amostra para análise | F82: 4997 | G82: 62.7 | H82: 0 | I82: 44314 | J82: TRUE | K82: Não entra | L82: Serviço | M82: 397 | N82: - | O82: - | P82: - | R82: Serviço de terceiros | U82: FALSE
A83: 77 | C83: Fundação de apoio à Pesquisa | E83: Apoio à pesquisa clinica | F83: 1123 | G83: 1476 | H83: 1476 | I83: 44314 | J83: TRUE | L83: Serviço | M83: 37.6 | N83: - | O83: 56.4 | P83: - | R83: Serviço de terceiros | S83: CarboCH e Cicatrização | U83: TRUE
A84: 78 | C84: Eurofins do Brasil Análise de Alimentos Ltda. | D84: 04.329.668/0001-38 | E84: Análise de Vitaminas e Minerais, para T9LD do retort NHcF e Vitaminas, Minerais e Macronutrientes para T0 do Energyzip 25% | F84: 2022 | G84: 21374.52 | H84: 21374.52 | I84: 44315 | J84: TRUE | L84: Serviço | M84: - | N84: - | O84: 69.5 | P84: - | R84: Serviço de terceiros | S84: Instanth Clear | T84: Immax | U84: TRUE
A85: 79 | C85: Eurofins do Brasil Análise de Alimentos Ltda. | D85: 04.329.668/0001-38 | E85: Análise de macronutrientes para T12 | F85: 55545 | G85: 2105.82 | H85: 0 | I85: 44315 | J85: TRUE | L85: Serviço | M85: - | N85: - | O85: 124.99 | P85: - | R85: Serviço de terceiros | S85: Instanth Clear | T85: Immax, ProteinPT e CarboCH | U85: TRUE
A86: 80 | C86: DPR Turismo Ltda | E86: Hospedagem teste Embrapa/RJ - Everton | F86: 7389 | G86: 778.9 | H86: 778.9 | I86: 44315 | J86: TRUE | L86: Serviço | M86: - | N86: - | O86: 107.84 | P86: - | R86: Serviço de terceiros | S86: Instanth Clear | T86: Retort (Sistema Fechado) e Energyzip morango | U86: TRUE
A87: 81 | C87: DPR Turismo Ltda | E87: Hospedagem teste Embrapa/RJ - Lizianne e Luciana | F87: 19394 | G87: 1053.8 | H87: 1053.8 | I87: 44314 | J87: TRUE | L87: Serviço | M87: 27988.34 | N87: - | O87: - | P87: - | R87: Serviço de terceiros | S87: Trophic Junior 1.0 e 1.5 | U87: TRUE
A88: 82 | C88: J&J Serviços de Entregas Ltda - ME | D88: 20.618.029/0001-49 | E88: Envio de amostra para análise | F88: NA | G88: 340.85 | H88: 227.23 | I88: 44308 | J88: TRUE | L88: Serviço | M88: 349.4 | N88: - | O88: - | P88: - | R88: Serviço próprio | S88: Trophic Junior 1.0 e 1.5 | U88: TRUE
A89: 83 | C89: Fundação de desenv. da pesquisa do agronegócio - FUNDEPAG | D89: 50.276.237/0001-78 | E89: Análise de perfil lipídico - T0 (acompanhamento) | F89: 73091 | G89: 1405 | H89: 0 | I89: 44309 | J89: TRUE | L89: Serviço | M89: 393.44 | N89: - | O89: 393.44 | P89: - | R89: Serviço de terceiros | S89: Bemmax sabor neutro e Immax | T89: Trophic EP e HDmax | U89: TRUE
A90: 84 | C90: Eurofins do Brasil Análise de Alimentos Ltda. | D90: 04.329.668/0001-38 | E90: Análise de novas MP's | F90: 161940 | G90: 5651.1 | H90: 2825.55 | I90: 44319 | J90: TRUE | L90: Serviço | M90: 406.8 | N90: - | O90: - | P90: - | R90: Serviço de terceiros | S90: Concorrentes espessante | T90: Energyzip baunilha | U90: TRUE | V90: GERAL
A91: 85 | C91: Tetra Pak Ltda | E91: Aluguel de planta para teste piloto | F91: NA | G91: 27988.34 | H91: 27988.34 | I91: 44308 | J91: TRUE | L91: Serviço | M91: 442.92 | N91: - | O91: - | P91: - | R91: Serviço próprio | S91: Retort | T91: Energyzip baunilha, Energyzip 1.0 | U91: TRUE
A92: 86 | C92: Localiza Rent a Car S/A | E92: Aluguel de carro teste Embrapa/RJ (set 2022) | F92: NA | G92: 290.15 | H92: 290.15 | I92: 44308 | J92: TRUE | L92: Serviço | M92: 699.92 | N92: - | O92: - | P92: - | R92: Serviço próprio | S92: Retort | T92: Trophic Basic, Trophic Fiber, Trophic 1.5 e Energyzip Chocolate | U92: TRUE
A93: 87 | C93: Fundação de Apoio à Universidade de São Paulo | E93: Análise de DP - UTI, Diamax RTH e Trophic Soya RTH | F93: 160588 | G93: 777 | H93: 777 | I93: 44309 | J93: TRUE | L93: Serviço | M93: 406.04 | N93: - | O93: - | P93: - | R93: Serviço de terceiros | S93: Trophic Junior 1.0 e 1.5 | T93: Bemmax Sabor Neutro, InstanTH NEO, HDmax e Energyzip Morango | U93: TRUE
A94: 88 | C94: Eurofins do Brasil Análise de Alimentos Ltda. | D94: 04.329.668/0001-38 | E94: Análise de vitaminas e minerais - T18 | F94: NA | G94: 12554.79 | H94: 0 | I94: 44308 | J94: TRUE | L94: Serviço | M94: 84.8 | N94: - | O94: - | P94: - | R94: Serviço próprio | S94: Trophic Junior 1.0 e 1.5 | T94: Retort (Sistema Fechado) e Immax | U94: TRUE
A95: 89 | C95: Eurofins do Brasil Análise de Alimentos Ltda. | D95: 04.329.668/0001-38 | E95: Análise de vitaminas e minerais - T0 | F95: NA | G95: 15112.74 | H95: 15112.74 | I95: 44315 | J95: TRUE | L95: Serviço | M95: 50.24 | N95: - | O95: - | P95: - | R95: Serviço próprio | S95: Retort | T95: Produtos pó | U95: TRUE
A96: 90 | C96: J&J Serviços de Entregas Ltda - ME | D96: 20.618.029/0001-49 | E96: Envio de amostra para análise | F96: NA | G96: 62.7 | H96: 62.7 | I96: 44308 | J96: TRUE | L96: Serviço | M96: 56.13 | N96: - | O96: - | P96: - | R96: Serviço próprio | S96: Trophic Junior 1.0 e 1.5 | T96: Produtos líquidos | U96: TRUE
A97: 91 | C97: ZAY SERVIÇOS DE ANÁLISES QUÍMICAS LTDA | E97: Aluguel de espaço em câmara climática, para estudo acelerado das dietas retort HH, HN e HNcF V04 e V05 | F97: NA | G97: 3100 | H97: 3100 | I97: 44309 | J97: TRUE | L97: Serviço | M97: 52.05 | N97: - | O97: - | P97: - | R97: Serviço próprio | S97: Trophic Junior 1.0 e 1.5 | T97: Bemmax Sabor Neutro, Instant NEO, Instanth Clear | U97: TRUE
A98: 92 | C98: Spectral Service AG | E98: Análise de fosfolipídios - T12 | F98: NA | G98: 1528.67 | H98: 0 | I98: 44312 | J98: TRUE | L98: Serviço | M98: 156.24 | N98: - | O98: - | P98: - | R98: Serviço próprio | S98: Retort | T98: Bemmax Sabor Neutro, Instant NEO | U98: TRUE
A99: 93 | C99: Eurofins do Brasil Análise de Alimentos Ltda. | D99: 04.329.668/0001-38 | E99: Análise de vitaminas e minerais (Immax - T24) e vitaminas, minerais, macronutrientes e perfil de açúcar (Diamax IN - T0) | F99: 162105 | G99: 22654.17 | H99: 11327.09 | I99: 44321 | J99: TRUE | L99: Serviço | M99: 2010.8 | N99: - | O99: - | P99: - | R99: Serviço de terceiros | S99: Eneryzip Force + (Sênior) | T99: InstanTH NEO, Trophioc Soya 1.5, HDmax 2.0 | U99: TRUE
A100: 94 | C100: Labor Três Laboratórios e Consultoria Técnica Ltda. | D100: 02.021.076/0001-29 | E100: Análise de microbiologia - T0 (Diamax RTH, Trophic Soya RTH, UTI) | F100: 50685 | G100: 762.3 | H100: 762.3 | I100: 44321 | J100: TRUE | L100: Serviço | M100: 95.95 | N100: - | O100: 95.95 | P100: - | R100: Serviço de terceiros | S100: Bemmax sabor neutro e Immax | U100: TRUE
A101: 95 | C101: Eurofins do Brasil Análise de Alimentos Ltda. | D101: 04.329.668/0001-38 | E101: Análise de vitaminas, minerais e macronutrientes (Trophic Fiber pó - T18LD / Instanth Neo - T12) | F101: 42195 | G101: 37134.85 | H101: 18567.43 | I101: 44321 | J101: TRUE | L101: Serviço | M101: 45 | N101: - | O101: 135 | P101: - | R101: Serviço de terceiros | S101: Bemmax sabor neutro, Enterfiber e Immax | U101: TRUE
...

Sheet Página18
B3: J&J Serviços de Entregas Ltda - ME | C3: 20.618.029/0001-49
B4: Eurofins do Brasil Análise de Alimentos Ltda. | C4: 04.329.668/0001-38
B5: ASPEN - American Society for Parenteral and Enteral Society
B6: Fundação de desenv. da pesquisa do agronegócio - FUNDEPAG | C6: 50.276.237/0001-78
B7: Fundação de desenv. da pesquisa do agronegócio - FUNDEPAG | C7: 50.276.237/0001-78
B8: Eurofins do Brasil Análise de Alimentos Ltda. | C8: 04.329.668/0001-38
B9: Fundação Arthur Bernardes | C9: 20.320.503/0001-51
B10: Eurofins do Brasil Análise de Alimentos Ltda. | C10: 04.329.668/0001-38
B11: Fundação Arthur Bernardes | C11: 20.320.503/0001-51
B12: JF Inox - Metais e Serviços Eireli
B13: Márcio Nogueira | C13: 088.869.216-16
B14: LSD SERVIÇOS DE TRADUÇÃO LTDA
B15: Camila Mendes Pereira
B16: Márcio Nogueira | C16: 088.869.216-16
B17: Localiza rent a car AS
B18: J&J Serviços de Entregas Ltda - ME | C18: 20.618.029/0001-49
B19: Eurofins do Brasil Análise de Alimentos Ltda. | C19: 04.329.668/0001-38
B20: Fundação de desenv. da pesquisa do agronegócio - FUNDEPAG | C20: 50.276.237/0001-78
B21: Eurofins do Brasil Análise de Alimentos Ltda. | C21: 04.329.668/0001-38
B22: Fundação de desenv. da pesquisa do agronegócio - FUNDEPAG | C22: 50.276.237/0001-78
B23: Cell e Target Eventos e Cursos Ltda
B24: Eurofins do Brasil Análise de Alimentos Ltda. | C24: 04.329.668/0001-38
B25: Eurofins do Brasil Análise de Alimentos Ltda. | C25: 04.329.668/0001-38
B26: Azul Linhas Aereas Brasileiras S.A
B27: Azul Linhas Aereas Brasileiras S.A
B28: Restaurante Canaa
B29: Cocamar Postos de Combustíveis Ltda
B30: FLP PIZZARIA EIRELI
B31: DPR Turismo Ltda
B32: DPR Turismo Ltda
B33: Eurofins do Brasil Análise de Alimentos Ltda. | C33: 04.329.668/0001-38
B34: Studio Madcreative Design Ltda - ME | C34: 11.115.312/0001-67
B35: Fundação de desenv. da pesquisa do agronegócio - FUNDEPAG | C35: 50.276.237/0001-78
B36: Eurofins do Brasil Análise de Alimentos Ltda. | C36: 04.329.668/0001-38
B37: J&J Serviços de Entregas Ltda - ME | C37: 20.618.029/0001-49
B38: Everton Claudi Graeff
B39: Eurofins do Brasil Análise de Alimentos Ltda. | C39: 04.329.668/0001-38
B40: Eurofins do Brasil Análise de Alimentos Ltda. | C40: 04.329.668/0001-38
B41: Studio Madcreative Design Ltda - ME | C41: 11.115.312/0001-67
B42: Studio Madcreative Design Ltda - ME | C42: 11.115.312/0001-67
B43: MCI Suisse SA, Rue du Pré-Bouvier 9, 1242 Satigny, Switzerland - ESPEN
B44: Gol Linhas aéreas
B45: Ibis
B46: Fundação de desenv. da pesquisa do agronegócio - FUNDEPAG | C46: 50.276.237/0001-78
B47: Labor Três Laboratórios e Consultoria Técnica Ltda. | C47: 02.021.076/0001-29
B48: J&J Serviços de Entregas Ltda - ME | C48: 20.618.029/0001-49
B49: Fundação de Apoio à Universidade de São Paulo
B50: Juliana Lamas Roberto
B51: Lizianne Angelica Shmeil
B52: Fundação Arthur Bernardes | C52: 20.320.503/0001-51
B53: DPR Turismo Ltda
B54: J&J Serviços de Entregas Ltda - ME | C54: 20.618.029/0001-49
B55: Fundação de desenv. da pesquisa do agronegócio - FUNDEPAG | C55: 50.276.237/0001-78
B56: Fundação de apoio à Pesquisa
B57: Fundação Arthur Bernardes | C57: 20.320.503/0001-51
B58: DHL Express (Brazil) Ltda
B59: Eurofins do Brasil Análise de Alimentos Ltda. | C59: 04.329.668/0001-38
B60: Eurofins do Brasil Análise de Alimentos Ltda. | C60: 04.329.668/0001-38
B61: Eurofins do Brasil Análise de Alimentos Ltda. | C61: 04.329.668/0001-38
B62: J&J Serviços de Entregas Ltda - ME | C62: 20.618.029/0001-49
B63: Fundação de desenv. da pesquisa do agronegócio - FUNDEPAG | C63: 50.276.237/0001-78
B64: Studio Madcreative Design Ltda - ME | C64: 11.115.312/0001-67
B65: Eurofins do Brasil Análise de Alimentos Ltda. | C65: 04.329.668/0001-38
