Workbook

Sheet RESUMO
A2: Resumo dos investimentos
A3: BENEFÍCIO FISCAL DE PD&I 2023
G4: 2019-088 PRODIET
A5: PRODIET NUTRIÇÃO CLINICA LTDA | E5: CNPJ 08.183.359/0001-53 | G5: =TODAY() -> 46168
A6: Rua General Potiguara, 1428, Lotes 20 e 21, Novo Mundo - PR - SUL - CURITIBA - CEP 81.050-500 - fone: (41) 3342-2825
A8: Natureza | B8: 1º Trimestre | C8: 2º Trimestre | D8: 3º Trimestre | E8: 4º Trimestre | G8: TOTAL
A9: Material | B9: - | C9: - | D9: - | E9: - | G9: =sum(B9:E9) -> 0
A10: Terceiros | B10: =IFERROR(__xludf.DUMMYFUNCTION("iferror(sum(filter(TERCEIROS!$L12:$L66,month(TERCEIROS!$H12:$H66)>=1,month(TERCEIROS!$H12:$H66)<=3)),0)"),105659.93000000001) -> 105659.93 | C10: =IFERROR(__xludf.DUMMYFUNCTION("iferror(sum(filter(TERCEIROS!$L12:$L66,month(TERCEIROS!$H12:$H66)>=4,month(TERCEIROS!$H12:$H66)<=6)),0)"),89153.48) -> 89153.48 | D10: =IFERROR(__xludf.DUMMYFUNCTION("iferror(sum(filter(TERCEIROS!$L12:$L66,month(TERCEIROS!$H12:$H66)>=7,month(TERCEIROS!$H12:$H66)<=9)),0)"),109284.745) -> 109284.74 | E10: =IFERROR(__xludf.DUMMYFUNCTION("iferror(sum(filter(TERCEIROS!$L12:$L66,month(TERCEIROS!$H12:$H66)>=10,month(TERCEIROS!$H12:$H66)<=12)),0)"),62550.06) -> 62550.06 | G10: =sum(B10:E10) -> 366648.22
A11: RH (Parcial inovação) | B11: =IFERROR(__xludf.DUMMYFUNCTION("iferror(sum(filter(TIMESHEET!$N$12:$N66,TIMESHEET!$Q$12:$Q66=""Parcial"",month(TIMESHEET!$F$12:$F66)>=1,month(TIMESHEET!$F$12:$F66)<=3)),0)"),55379.129999999925) -> 55379.13 | C11: =IFERROR(__xludf.DUMMYFUNCTION("iferror(sum(filter(TIMESHEET!$N$12:$N66,TIMESHEET!$Q$12:$Q66=""Parcial"",month(TIMESHEET!$F$12:$F66)>=4,month(TIMESHEET!$F$12:$F66)<=6)),0)"),62396.73584798719) -> 62396.736 | D11: =IFERROR(__xludf.DUMMYFUNCTION("iferror(sum(filter(TIMESHEET!$N$12:$N66,TIMESHEET!$Q$12:$Q66=""Parcial"",month(TIMESHEET!$F$12:$F66)>=7,month(TIMESHEET!$F$12:$F66)<=9)),0)"),36288.97724144722) -> 36288.977 | E11: =IFERROR(__xludf.DUMMYFUNCTION("iferror(sum(filter(TIMESHEET!$N$12:$N66,TIMESHEET!$Q$12:$Q66=""Parcial"",month(TIMESHEET!$F$12:$F66)>=10,month(TIMESHEET!$F$12:$F66)<=12)),0)"),52844.009887970664) -> 52844.01 | G11: =sum(B11:E11) -> 206908.85
A12: RH (Exclusivo inovação) | B12: =IFERROR(__xludf.DUMMYFUNCTION("iferror(sum(filter(TIMESHEET!$N$12:$N66,TIMESHEET!$Q$12:$Q66=""Exclusivo"",month(TIMESHEET!$F$12:$F66)>=1,month(TIMESHEET!$F$12:$F66)<=3)),0)"),0.0) -> 0 | C12: =IFERROR(__xludf.DUMMYFUNCTION("iferror(sum(filter(TIMESHEET!$N$12:$N66,TIMESHEET!$Q$12:$Q66=""Exclusivo"",month(TIMESHEET!$F$12:$F66)>=4,month(TIMESHEET!$F$12:$F66)<=6)),0)"),0.0) -> 0 | D12: =IFERROR(__xludf.DUMMYFUNCTION("iferror(sum(filter(TIMESHEET!$N$12:$N66,TIMESHEET!$Q$12:$Q66=""Exclusivo"",month(TIMESHEET!$F$12:$F66)>=7,month(TIMESHEET!$F$12:$F66)<=9)),0)"),0.0) -> 0 | E12: =IFERROR(__xludf.DUMMYFUNCTION("iferror(sum(filter(TIMESHEET!$N$12:$N66,TIMESHEET!$Q$12:$Q66=""Exclusivo"",month(TIMESHEET!$F$12:$F66)>=10,month(TIMESHEET!$F$12:$F66)<=12)),0)"),0.0) -> 0 | G12: =sum(B12:E12) -> 0
A13: Total 1 | B13: =sum(B10:B12) -> 161039.06 | C13: =sum(C10:C12) -> 151550.22 | D13: =sum(D10:D12) -> 145573.72 | E13: =sum(E10:E12) -> 115394.07 | G13: =sum(B13:E13) -> 573557.07
A14: Percentual Exclusão | B14: 0.6 | C14: 0.6 | D14: 0.6 | E14: 0.6 | G14: 0.6
A15: Exclusão da Base de cálculo do IRPJ e CSLL | B15: =B13*B14 -> 96623.436 | C15: =C13*C14 -> 90930.13 | D15: =D13*D14 -> 87344.233 | E15: =E13*E14 -> 69236.442 | G15: =sum(B15:E15) -> 344134.24
A17: Economia Estimada [34%] | B17: =B15*34% -> 32851.968 | C17: =C15*34% -> 30916.244 | D17: =D15*34% -> 29697.039 | E17: =E15*34% -> 23540.39 | G17: =sum(B17:E17) -> 117005.64
A18: Comissão McBenner | B18: =B17*0.1 -> 3285.1968 | C18: =C17*0.1 -> 3091.6244 | D18: =D17*0.1 -> 2969.7039 | E18: =E17*0.1 -> 2354.039 | G18: =sum(B18:E18) -> 11700.564
A20: Observações:
A21: 1. Os dispêndios devem ser registrados na contabilidade em conta específica
A22: 2. O benefício deve ser aproveitado na ECF do respectivo ano/competência
A23: 3. O formulário do MCTIC (governo) deve ser enviado até fim de Julho/2024
A24: 4. Os projetos estão descritos em arquivo a parte a ser anexado no FORM PD&I
A25: 5. Alguns benefícios previstos na Lei do Bem não foram utilizados:
A26: --- 5.1. Depreciação acelerada
A27: --- 5.2. Redução de IPI na aquisição de equipamento para PD&I
A28: 5. Alguns benefícios previstos na Lei do Bem não foram utilizados:
A30: Equipe de PD&I
A31: Quadro de resumo | B31: Dedicação Parcial | E31: Dedicação Exclusiva
B32: Qtd | C32: Valor gasto | D32: Horas | E32: Qtd | F32: Valor gasto | G32: Horas
A33: Técnico | B33: =IFERROR(__xludf.DUMMYFUNCTION("COUNTA(IFERROR(FILTER(PESSOAL!$F$13:$F$23,PESSOAL!$F$13:$F$23 = $A33,PESSOAL!$V$13:$V$23 = ""Parcial"",PESSOAL!$W$13:$W$23 = TRUE),))"),0.0) -> 0 | C33: =IFERROR(__xludf.DUMMYFUNCTION("SUM(IFERROR(FILTER(PESSOAL!$U$35:$U$45,PESSOAL!$F$35:$F$45 = $A33,PESSOAL!$E$35:$E$45 = ""Parcial""),0))"),0.0) -> 0 | D33: =IFERROR(__xludf.DUMMYFUNCTION("SUM(IFERROR(FILTER(PESSOAL!$T$13:$T$23,PESSOAL!$F$13:$F$23 = $A33,PESSOAL!$V$13:$V$23 = ""Parcial""),0))*24"),0.0) -> 0 | E33: =IFERROR(__xludf.DUMMYFUNCTION("COUNTA(IFERROR(FILTER(PESSOAL!$E$6:$E$19,PESSOAL!$E$6:$E$19 = $A33,PESSOAL!$U$6:$U$19 = ""Exclusivo"",PESSOAL!$U$28:$U$39 = TRUE),))"),0.0) -> 0 | F33: =IFERROR(__xludf.DUMMYFUNCTION("SUM(IFERROR(FILTER(PESSOAL!$U$35:$U$44,PESSOAL!$F$35:$F$44 = $A33,PESSOAL!$E$35:$E$44 = ""Exclusivo);0))"")))"),0.0) -> 0 | G33: =IFERROR(__xludf.DUMMYFUNCTION("SUM(IFERROR(FILTER(PESSOAL!$T$13:$T$23,PESSOAL!$F$13:$F$23 = $A33,PESSOAL!$V$13:$V$23 = ""Exclusivo""),0))*24"),0.0) -> 0
A34: Tecnologo | B34: =IFERROR(__xludf.DUMMYFUNCTION("COUNTA(IFERROR(FILTER(PESSOAL!$F$13:$F$23,PESSOAL!$F$13:$F$23 = $A34,PESSOAL!$V$13:$V$23 = ""Parcial"",PESSOAL!$W$13:$W$23 = TRUE),))"),0.0) -> 0 | C34: =IFERROR(__xludf.DUMMYFUNCTION("SUM(IFERROR(FILTER(PESSOAL!$U$35:$U$45,PESSOAL!$F$35:$F$45 = $A34,PESSOAL!$E$35:$E$45 = ""Parcial""),0))"),0.0) -> 0 | D34: =IFERROR(__xludf.DUMMYFUNCTION("SUM(IFERROR(FILTER(PESSOAL!$T$13:$T$23,PESSOAL!$F$13:$F$23 = $A34,PESSOAL!$V$13:$V$23 = ""Parcial""),0))*24"),0.0) -> 0 | E34: =IFERROR(__xludf.DUMMYFUNCTION("COUNTA(IFERROR(FILTER(PESSOAL!$E$6:$E$19,PESSOAL!$E$6:$E$19 = $A34,PESSOAL!$U$6:$U$19 = ""Exclusivo"",PESSOAL!$U$28:$U$39 = TRUE),))"),0.0) -> 0 | F34: =IFERROR(__xludf.DUMMYFUNCTION("SUM(IFERROR(FILTER(PESSOAL!$U$35:$U$44,PESSOAL!$F$35:$F$44 = $A34,PESSOAL!$E$35:$E$44 = ""Exclusivo);0))"")))"),0.0) -> 0 | G34: =IFERROR(__xludf.DUMMYFUNCTION("SUM(IFERROR(FILTER(PESSOAL!$T$13:$T$23,PESSOAL!$F$13:$F$23 = $A34,PESSOAL!$V$13:$V$23 = ""Exclusivo""),0))*24"),0.0) -> 0
A35: Superior Completo | B35: =IFERROR(__xludf.DUMMYFUNCTION("COUNTA(IFERROR(FILTER(PESSOAL!$F$13:$F$23,PESSOAL!$F$13:$F$23 = $A35,PESSOAL!$V$13:$V$23 = ""Parcial"",PESSOAL!$W$13:$W$23 = TRUE),))"),4.0) -> 4 | C35: =IFERROR(__xludf.DUMMYFUNCTION("SUM(IFERROR(FILTER(PESSOAL!$U$35:$U$45,PESSOAL!$F$35:$F$45 = $A35,PESSOAL!$E$35:$E$45 = ""Parcial""),0))"),75955.78293522184) -> 75955.783 | D35: =IFERROR(__xludf.DUMMYFUNCTION("SUM(IFERROR(FILTER(PESSOAL!$T$13:$T$23,PESSOAL!$F$13:$F$23 = $A35,PESSOAL!$V$13:$V$23 = ""Parcial""),0))*24"),1302.5666666666668) -> 1302.5667 | E35: =IFERROR(__xludf.DUMMYFUNCTION("COUNTA(IFERROR(FILTER(PESSOAL!$E$6:$E$19,PESSOAL!$E$6:$E$19 = $A35,PESSOAL!$U$6:$U$19 = ""Exclusivo"",PESSOAL!$U$28:$U$39 = TRUE),))"),0.0) -> 0 | F35: =IFERROR(__xludf.DUMMYFUNCTION("SUM(IFERROR(FILTER(PESSOAL!$U$35:$U$44,PESSOAL!$F$35:$F$44 = $A35,PESSOAL!$E$35:$E$44 = ""Exclusivo);0))"")))"),0.0) -> 0 | G35: =IFERROR(__xludf.DUMMYFUNCTION("SUM(IFERROR(FILTER(PESSOAL!$T$13:$T$23,PESSOAL!$F$13:$F$23 = $A35,PESSOAL!$V$13:$V$23 = ""Exclusivo""),0))*24"),0.0) -> 0
A36: Pós graduado | B36: =IFERROR(__xludf.DUMMYFUNCTION("COUNTA(IFERROR(FILTER(PESSOAL!$F$13:$F$23,PESSOAL!$F$13:$F$23 = $A36,PESSOAL!$V$13:$V$23 = ""Parcial"",PESSOAL!$W$13:$W$23 = TRUE),))"),3.0) -> 3 | C36: =IFERROR(__xludf.DUMMYFUNCTION("SUM(IFERROR(FILTER(PESSOAL!$U$35:$U$45,PESSOAL!$F$35:$F$45 = $A36,PESSOAL!$E$35:$E$45 = ""Parcial""),0))"),23118.883308544828) -> 23118.883 | D36: =IFERROR(__xludf.DUMMYFUNCTION("SUM(IFERROR(FILTER(PESSOAL!$T$13:$T$23,PESSOAL!$F$13:$F$23 = $A36,PESSOAL!$V$13:$V$23 = ""Parcial""),0))*24"),271.74999999999994) -> 271.75 | E36: =IFERROR(__xludf.DUMMYFUNCTION("COUNTA(IFERROR(FILTER(PESSOAL!$E$6:$E$19,PESSOAL!$E$6:$E$19 = $A36,PESSOAL!$U$6:$U$19 = ""Exclusivo"",PESSOAL!$U$28:$U$39 = TRUE),))"),0.0) -> 0 | F36: =IFERROR(__xludf.DUMMYFUNCTION("SUM(IFERROR(FILTER(PESSOAL!$U$35:$U$44,PESSOAL!$F$35:$F$44 = $A36,PESSOAL!$E$35:$E$44 = ""Exclusivo);0))"")))"),0.0) -> 0 | G36: =IFERROR(__xludf.DUMMYFUNCTION("SUM(IFERROR(FILTER(PESSOAL!$T$13:$T$23,PESSOAL!$F$13:$F$23 = $A36,PESSOAL!$V$13:$V$23 = ""Exclusivo""),0))*24"),0.0) -> 0
A37: Mestrado | B37: =IFERROR(__xludf.DUMMYFUNCTION("COUNTA(IFERROR(FILTER(PESSOAL!$F$13:$F$23,PESSOAL!$F$13:$F$23 = $A37,PESSOAL!$V$13:$V$23 = ""Parcial"",PESSOAL!$W$13:$W$23 = TRUE),))"),4.0) -> 4 | C37: =IFERROR(__xludf.DUMMYFUNCTION("SUM(IFERROR(FILTER(PESSOAL!$U$35:$U$45,PESSOAL!$F$35:$F$45 = $A37,PESSOAL!$E$35:$E$45 = ""Parcial""),0))"),100109.26978075242) -> 100109.27 | D37: =IFERROR(__xludf.DUMMYFUNCTION("SUM(IFERROR(FILTER(PESSOAL!$T$13:$T$23,PESSOAL!$F$13:$F$23 = $A37,PESSOAL!$V$13:$V$23 = ""Parcial""),0))*24"),1500.050000000001) -> 1500.05 | E37: =IFERROR(__xludf.DUMMYFUNCTION("COUNTA(IFERROR(FILTER(PESSOAL!$E$6:$E$19,PESSOAL!$E$6:$E$19 = $A37,PESSOAL!$U$6:$U$19 = ""Exclusivo"",PESSOAL!$U$28:$U$39 = TRUE),))"),0.0) -> 0 | F37: =IFERROR(__xludf.DUMMYFUNCTION("SUM(IFERROR(FILTER(PESSOAL!$U$35:$U$44,PESSOAL!$F$35:$F$44 = $A37,PESSOAL!$E$35:$E$44 = ""Exclusivo);0))"")))"),0.0) -> 0 | G37: =IFERROR(__xludf.DUMMYFUNCTION("SUM(IFERROR(FILTER(PESSOAL!$T$13:$T$23,PESSOAL!$F$13:$F$23 = $A37,PESSOAL!$V$13:$V$23 = ""Exclusivo""),0))*24"),0.0) -> 0
A38: Doutorado | B38: =IFERROR(__xludf.DUMMYFUNCTION("COUNTA(IFERROR(FILTER(PESSOAL!$F$13:$F$23,PESSOAL!$F$13:$F$23 = $A38,PESSOAL!$V$13:$V$23 = ""Parcial"",PESSOAL!$W$13:$W$23 = TRUE),))"),0.0) -> 0 | C38: =IFERROR(__xludf.DUMMYFUNCTION("SUM(IFERROR(FILTER(PESSOAL!$U$35:$U$45,PESSOAL!$F$35:$F$45 = $A38,PESSOAL!$E$35:$E$45 = ""Parcial""),0))"),0.0) -> 0 | D38: =IFERROR(__xludf.DUMMYFUNCTION("SUM(IFERROR(FILTER(PESSOAL!$T$13:$T$23,PESSOAL!$F$13:$F$23 = $A38,PESSOAL!$V$13:$V$23 = ""Parcial""),0))*24"),0.0) -> 0 | E38: =IFERROR(__xludf.DUMMYFUNCTION("COUNTA(IFERROR(FILTER(PESSOAL!$E$6:$E$19,PESSOAL!$E$6:$E$19 = $A38,PESSOAL!$U$6:$U$19 = ""Exclusivo"",PESSOAL!$U$28:$U$39 = TRUE),))"),0.0) -> 0 | F38: =IFERROR(__xludf.DUMMYFUNCTION("SUM(IFERROR(FILTER(PESSOAL!$U$35:$U$44,PESSOAL!$F$35:$F$44 = $A38,PESSOAL!$E$35:$E$44 = ""Exclusivo);0))"")))"),0.0) -> 0 | G38: =IFERROR(__xludf.DUMMYFUNCTION("SUM(IFERROR(FILTER(PESSOAL!$T$13:$T$23,PESSOAL!$F$13:$F$23 = $A38,PESSOAL!$V$13:$V$23 = ""Exclusivo""),0))*24"),0.0) -> 0
B39: =SUM(B33:B38) -> 11 | C39: =SUM(C33:C38) -> 199183.94 | D39: =SUM(D33:D38) -> 3074.3667 | E39: =SUM(E33:E38) -> 0 | F39: =SUM(F33:F38) -> 0 | G39: =SUM(G33:G38) -> 0
A41: Valores por projeto de PD&I
B42: =sum(D42:G42) -> 573557.07 | D42: =sum(D44:D66) -> 0 | E42: =sum(E44:E66) -> 366648.22 | F42: =sum(F44:F66) -> 206908.85 | G42: =sum(G44:G66) -> 0
A43: Projetos | B43: TOTAL | D43: Vlr materiais | E43: Vlr terceiros | F43: Vlr Rh parcial | G43: Vlr exclusivos
A44: {='BD Projetos'!A2:A24} -> INOV00001 | B44: =sum(D44:G44) -> 285941.65 | D44: - | E44: {=iferror(XLOOKUP(A44:A66,transpose(TERCEIROS!$P$11:$AW$11),transpose(TERCEIROS!$P$10:$AW$10),0,0),"")} -> 196831.42 | F44: =IFERROR(__xludf.DUMMYFUNCTION("ArrayFormula(IFERROR(SUM(filter(TIMESHEET!$N$12:$N66,TIMESHEET!$C$12:$C66=A44,TIMESHEET!$Q$12:$Q66=""Parcial"")),""-""))"),89110.22431248204) -> 89110.224 | G44: =IFERROR(__xludf.DUMMYFUNCTION("iferror(sum(filter(TIMESHEET!$N12:$N66,TIMESHEET!$C12:$C66=A44,TIMESHEET!$Q12:$Q66=""Exclusivo"")),""-"")"),"-") -> -
A45: INOV00004 | B45: =sum(D45:G45) -> 10095.228 | D45: - | E45: 0 | F45: =IFERROR(__xludf.DUMMYFUNCTION("ArrayFormula(IFERROR(SUM(filter(TIMESHEET!$N$12:$N66,TIMESHEET!$C$12:$C66=A45,TIMESHEET!$Q$12:$Q66=""Parcial"")),""-""))"),10095.227904826466) -> 10095.228 | G45: =IFERROR(__xludf.DUMMYFUNCTION("iferror(sum(filter(TIMESHEET!$N13:$N66,TIMESHEET!$C13:$C66=A45,TIMESHEET!$Q13:$Q66=""Exclusivo"")),""-"")"),"-") -> -
A46: INOV00006 | B46: =sum(D46:G46) -> 9719.4221 | D46: - | E46: 0 | F46: =IFERROR(__xludf.DUMMYFUNCTION("ArrayFormula(IFERROR(SUM(filter(TIMESHEET!$N$12:$N66,TIMESHEET!$C$12:$C66=A46,TIMESHEET!$Q$12:$Q66=""Parcial"")),""-""))"),9719.422113103337) -> 9719.4221 | G46: =IFERROR(__xludf.DUMMYFUNCTION("iferror(sum(filter(TIMESHEET!$N14:$N66,TIMESHEET!$C14:$C66=A46,TIMESHEET!$Q14:$Q66=""Exclusivo"")),""-"")"),"-") -> -
A47: INOV00010 | B47: =sum(D47:G47) -> 24629.085 | D47: - | E47: 18843.485 | F47: =IFERROR(__xludf.DUMMYFUNCTION("ArrayFormula(IFERROR(SUM(filter(TIMESHEET!$N$12:$N66,TIMESHEET!$C$12:$C66=A47,TIMESHEET!$Q$12:$Q66=""Parcial"")),""-""))"),5785.599652159814) -> 5785.5997 | G47: =IFERROR(__xludf.DUMMYFUNCTION("iferror(sum(filter(TIMESHEET!$N15:$N66,TIMESHEET!$C15:$C66=A47,TIMESHEET!$Q15:$Q66=""Exclusivo"")),""-"")"),"-") -> -
A48: INOV00013 | B48: =sum(D48:G48) -> 20708.518 | D48: - | E48: 14802.65 | F48: =IFERROR(__xludf.DUMMYFUNCTION("ArrayFormula(IFERROR(SUM(filter(TIMESHEET!$N$12:$N66,TIMESHEET!$C$12:$C66=A48,TIMESHEET!$Q$12:$Q66=""Parcial"")),""-""))"),5905.867513413776) -> 5905.8675 | G48: =IFERROR(__xludf.DUMMYFUNCTION("iferror(sum(filter(TIMESHEET!$N16:$N66,TIMESHEET!$C16:$C66=A48,TIMESHEET!$Q16:$Q66=""Exclusivo"")),""-"")"),"-") -> -
A49: INOV00014 | B49: =sum(D49:G49) -> 8569.4245 | D49: - | E49: 1914.23 | F49: =IFERROR(__xludf.DUMMYFUNCTION("ArrayFormula(IFERROR(SUM(filter(TIMESHEET!$N$12:$N66,TIMESHEET!$C$12:$C66=A49,TIMESHEET!$Q$12:$Q66=""Parcial"")),""-""))"),6655.194498857989) -> 6655.1945 | G49: =IFERROR(__xludf.DUMMYFUNCTION("iferror(sum(filter(TIMESHEET!$N17:$N66,TIMESHEET!$C17:$C66=A49,TIMESHEET!$Q17:$Q66=""Exclusivo"")),""-"")"),"-") -> -
A50: INOV00016 | B50: =sum(D50:G50) -> 102180.92 | D50: - | E50: 84801.625 | F50: =IFERROR(__xludf.DUMMYFUNCTION("ArrayFormula(IFERROR(SUM(filter(TIMESHEET!$N$12:$N66,TIMESHEET!$C$12:$C66=A50,TIMESHEET!$Q$12:$Q66=""Parcial"")),""-""))"),17379.29916204822) -> 17379.299 | G50: =IFERROR(__xludf.DUMMYFUNCTION("iferror(sum(filter(TIMESHEET!$N18:$N66,TIMESHEET!$C18:$C66=A50,TIMESHEET!$Q18:$Q66=""Exclusivo"")),""-"")"),"-") -> -
A51: INOV00017 | B51: =sum(D51:G51) -> 17865.333 | D51: - | E51: 7379.13 | F51: =IFERROR(__xludf.DUMMYFUNCTION("ArrayFormula(IFERROR(SUM(filter(TIMESHEET!$N$12:$N66,TIMESHEET!$C$12:$C66=A51,TIMESHEET!$Q$12:$Q66=""Parcial"")),""-""))"),10486.202977498835) -> 10486.203 | G51: =IFERROR(__xludf.DUMMYFUNCTION("iferror(sum(filter(TIMESHEET!$N19:$N66,TIMESHEET!$C19:$C66=A51,TIMESHEET!$Q19:$Q66=""Exclusivo"")),""-"")"),"-") -> -
A52: INOV00021 | B52: =sum(D52:G52) -> 9305.6428 | D52: - | E52: 817.13 | F52: =IFERROR(__xludf.DUMMYFUNCTION("ArrayFormula(IFERROR(SUM(filter(TIMESHEET!$N$12:$N66,TIMESHEET!$C$12:$C66=A52,TIMESHEET!$Q$12:$Q66=""Parcial"")),""-""))"),8488.512827566217) -> 8488.5128 | G52: =IFERROR(__xludf.DUMMYFUNCTION("iferror(sum(filter(TIMESHEET!$N20:$N66,TIMESHEET!$C20:$C66=A52,TIMESHEET!$Q20:$Q66=""Exclusivo"")),""-"")"),"-") -> -
A53: INOV00022 | B53: =sum(D53:G53) -> 10509.036 | D53: - | E53: 730 | F53: =IFERROR(__xludf.DUMMYFUNCTION("ArrayFormula(IFERROR(SUM(filter(TIMESHEET!$N$12:$N66,TIMESHEET!$C$12:$C66=A53,TIMESHEET!$Q$12:$Q66=""Parcial"")),""-""))"),9779.036140085675) -> 9779.0361 | G53: =IFERROR(__xludf.DUMMYFUNCTION("iferror(sum(filter(TIMESHEET!$N21:$N66,TIMESHEET!$C21:$C66=A53,TIMESHEET!$Q21:$Q66=""Exclusivo"")),""-"")"),"-") -> -
A54: INOV00023 | B54: =sum(D54:G54) -> 12172.535 | D54: - | E54: 7380 | F54: =IFERROR(__xludf.DUMMYFUNCTION("ArrayFormula(IFERROR(SUM(filter(TIMESHEET!$N$12:$N66,TIMESHEET!$C$12:$C66=A54,TIMESHEET!$Q$12:$Q66=""Parcial"")),""-""))"),4792.534743366326) -> 4792.5347 | G54: =IFERROR(__xludf.DUMMYFUNCTION("iferror(sum(filter(TIMESHEET!$N22:$N66,TIMESHEET!$C22:$C66=A54,TIMESHEET!$Q22:$Q66=""Exclusivo"")),""-"")"),"-") -> -
A55: INOV00024 | B55: =sum(D55:G55) -> 9051.3444 | D55: - | E55: 1523 | F55: =IFERROR(__xludf.DUMMYFUNCTION("ArrayFormula(IFERROR(SUM(filter(TIMESHEET!$N$12:$N66,TIMESHEET!$C$12:$C66=A55,TIMESHEET!$Q$12:$Q66=""Parcial"")),""-""))"),7528.344366824644) -> 7528.3444 | G55: =IFERROR(__xludf.DUMMYFUNCTION("iferror(sum(filter(TIMESHEET!$N23:$N66,TIMESHEET!$C23:$C66=A55,TIMESHEET!$Q23:$Q66=""Exclusivo"")),""-"")"),"-") -> -
A56: INOV00027 | B56: =sum(D56:G56) -> 548.50303 | D56: - | E56: 0 | F56: =IFERROR(__xludf.DUMMYFUNCTION("ArrayFormula(IFERROR(SUM(filter(TIMESHEET!$N$12:$N66,TIMESHEET!$C$12:$C66=A56,TIMESHEET!$Q$12:$Q66=""Parcial"")),""-""))"),548.5030345170454) -> 548.50303 | G56: =IFERROR(__xludf.DUMMYFUNCTION("iferror(sum(filter(TIMESHEET!$N24:$N66,TIMESHEET!$C24:$C66=A56,TIMESHEET!$Q24:$Q66=""Exclusivo"")),""-"")"),"-") -> -
A57: INOV00031 | B57: =sum(D57:G57) -> 18931.795 | D57: - | E57: 17286.16 | F57: =IFERROR(__xludf.DUMMYFUNCTION("ArrayFormula(IFERROR(SUM(filter(TIMESHEET!$N$12:$N66,TIMESHEET!$C$12:$C66=A57,TIMESHEET!$Q$12:$Q66=""Parcial"")),""-""))"),1645.635184076597) -> 1645.6352 | G57: =IFERROR(__xludf.DUMMYFUNCTION("iferror(sum(filter(TIMESHEET!$N25:$N66,TIMESHEET!$C25:$C66=A57,TIMESHEET!$Q25:$Q66=""Exclusivo"")),""-"")"),"-") -> -
A58: INOV00034 | B58: =sum(D58:G58) -> 1922.5291 | D58: - | E58: 0 | F58: =IFERROR(__xludf.DUMMYFUNCTION("ArrayFormula(IFERROR(SUM(filter(TIMESHEET!$N$12:$N66,TIMESHEET!$C$12:$C66=A58,TIMESHEET!$Q$12:$Q66=""Parcial"")),""-""))"),1922.5291148184226) -> 1922.5291 | G58: =IFERROR(__xludf.DUMMYFUNCTION("iferror(sum(filter(TIMESHEET!$N26:$N66,TIMESHEET!$C26:$C66=A58,TIMESHEET!$Q26:$Q66=""Exclusivo"")),""-"")"),"-") -> -
A59: INOV00035 | B59: =sum(D59:G59) -> 0 | D59: - | E59: 0 | F59: =IFERROR(__xludf.DUMMYFUNCTION("ArrayFormula(IFERROR(SUM(filter(TIMESHEET!$N$12:$N66,TIMESHEET!$C$12:$C66=A59,TIMESHEET!$Q$12:$Q66=""Parcial"")),""-""))"),0.0) -> 0 | G59: =IFERROR(__xludf.DUMMYFUNCTION("iferror(sum(filter(TIMESHEET!$N27:$N66,TIMESHEET!$C27:$C66=A59,TIMESHEET!$Q27:$Q66=""Exclusivo"")),""-"")"),"-") -> -
A60: INOV00036 | B60: =sum(D60:G60) -> 0 | D60: - | E60: 0 | F60: =IFERROR(__xludf.DUMMYFUNCTION("ArrayFormula(IFERROR(SUM(filter(TIMESHEET!$N$12:$N66,TIMESHEET!$C$12:$C66=A60,TIMESHEET!$Q$12:$Q66=""Parcial"")),""-""))"),0.0) -> 0 | G60: =IFERROR(__xludf.DUMMYFUNCTION("iferror(sum(filter(TIMESHEET!$N28:$N66,TIMESHEET!$C28:$C66=A60,TIMESHEET!$Q28:$Q66=""Exclusivo"")),""-"")"),"-") -> -
A61: INOV00037 | B61: =sum(D61:G61) -> 3081.6776 | D61: - | E61: 0 | F61: =IFERROR(__xludf.DUMMYFUNCTION("ArrayFormula(IFERROR(SUM(filter(TIMESHEET!$N$12:$N66,TIMESHEET!$C$12:$C66=A61,TIMESHEET!$Q$12:$Q66=""Parcial"")),""-""))"),3081.6776084919898) -> 3081.6776 | G61: =IFERROR(__xludf.DUMMYFUNCTION("iferror(sum(filter(TIMESHEET!$N29:$N66,TIMESHEET!$C29:$C66=A61,TIMESHEET!$Q29:$Q66=""Exclusivo"")),""-"")"),"-") -> -
A62: INOV00038 | B62: =sum(D62:G62) -> 937.96539 | D62: - | E62: 0 | F62: =IFERROR(__xludf.DUMMYFUNCTION("ArrayFormula(IFERROR(SUM(filter(TIMESHEET!$N$12:$N66,TIMESHEET!$C$12:$C66=A62,TIMESHEET!$Q$12:$Q66=""Parcial"")),""-""))"),937.9653948991403) -> 937.96539 | G62: =IFERROR(__xludf.DUMMYFUNCTION("iferror(sum(filter(TIMESHEET!$N30:$N66,TIMESHEET!$C30:$C66=A62,TIMESHEET!$Q30:$Q66=""Exclusivo"")),""-"")"),"-") -> -
A63: INOV00039 | B63: =sum(D63:G63) -> 14687.996 | D63: - | E63: 13018 | F63: =IFERROR(__xludf.DUMMYFUNCTION("ArrayFormula(IFERROR(SUM(filter(TIMESHEET!$N$12:$N66,TIMESHEET!$C$12:$C66=A63,TIMESHEET!$Q$12:$Q66=""Parcial"")),""-""))"),1669.996482306097) -> 1669.9965 | G63: =IFERROR(__xludf.DUMMYFUNCTION("iferror(sum(filter(TIMESHEET!$N31:$N66,TIMESHEET!$C31:$C66=A63,TIMESHEET!$Q31:$Q66=""Exclusivo"")),""-"")"),"-") -> -
A64: INOV00040 | B64: =sum(D64:G64) -> 0 | D64: - | E64: 0 | F64: =IFERROR(__xludf.DUMMYFUNCTION("ArrayFormula(IFERROR(SUM(filter(TIMESHEET!$N$12:$N66,TIMESHEET!$C$12:$C66=A64,TIMESHEET!$Q$12:$Q66=""Parcial"")),""-""))"),0.0) -> 0 | G64: =IFERROR(__xludf.DUMMYFUNCTION("iferror(sum(filter(TIMESHEET!$N32:$N66,TIMESHEET!$C32:$C66=A64,TIMESHEET!$Q32:$Q66=""Exclusivo"")),""-"")"),"-") -> -
A65: INOV00041 | B65: =sum(D65:G65) -> 12698.46 | D65: - | E65: 1321.38 | F65: =IFERROR(__xludf.DUMMYFUNCTION("ArrayFormula(IFERROR(SUM(filter(TIMESHEET!$N$12:$N66,TIMESHEET!$C$12:$C66=A65,TIMESHEET!$Q$12:$Q66=""Parcial"")),""-""))"),11377.079946062458) -> 11377.08 | G65: =IFERROR(__xludf.DUMMYFUNCTION("iferror(sum(filter(TIMESHEET!$N33:$N66,TIMESHEET!$C33:$C66=A65,TIMESHEET!$Q33:$Q66=""Exclusivo"")),""-"")"),"-") -> -
A66: INOV00046 | B66: =sum(D66:G66) -> 0 | D66: - | E66: 0 | F66: =IFERROR(__xludf.DUMMYFUNCTION("ArrayFormula(IFERROR(SUM(filter(TIMESHEET!$N$12:$N66,TIMESHEET!$C$12:$C66=A66,TIMESHEET!$Q$12:$Q66=""Parcial"")),""-""))"),0.0) -> 0 | G66: =IFERROR(__xludf.DUMMYFUNCTION("iferror(sum(filter(TIMESHEET!$N34:$N66,TIMESHEET!$C34:$C66=A66,TIMESHEET!$Q34:$Q66=""Exclusivo"")),""-"")"),"-") -> -

Sheet INOV0001
B2: PRODIET
B3: Pesquisa, Desenvolvimento & Inovação
B4: Formulário de PD&I - Ano 2023 | J4: Incentivado pela Lei do Bem | M4: TRUE
B5: - preencher somente os campos sombreados (cinza) e - adicionar cronograma no formato de imagem ao fim do formulário - preencher um deste para cada projeto de PD&I | J5: Objetiva tornar-se um Ativo | M5: FALSE
J6: Objetiva gerar patente/registro | M6: FALSE
B8: Dossiê do projeto
B9: Dados gerais para identificação e validação do projeto de PD&I
B11: Nome do projeto | E11: INOV000001 (2018 - RETORT)
J12: Pesquisa básica | M12: 📑
B13: Classificação do projeto | E13: Desenvolvimento experimental | J13: Pesquisa aplicada | M13: 📑
J14: Desenvolvimento experimental | M14: 📑
B15: Objetivos do projeto | E15: A Prodiet tem como objetivo desenvolver e lançar uma nova linha de produtos de Nutrição Enteral, focada em atender a 50% do mercado que atualmente não é contemplado pelos produtos em pó e líquidos UHT da empresa. Esta nova linha utilizará a tecnologia de tratamento térmico em autoclave para criar produtos inovadores que garantam maior qualidade e segurança alimentar. Especificamente, a linha incluirá produtos de nutrição enteral formulados para atender condições clínicas diversas, como fórmulas para pacientes com necessidades calóricas elevadas, fórmulas para intolerâncias alimentares e fórmulas para suporte nutricional de longo prazo. A empresa identificou essa demanda específica através de estudos de mercado detalhados, incluindo análises de concorrência, feedback de profissionais de saúde e dados de vendas regionais. A atual linha de produtos não atende a esta demanda devido à falta de tecnologia adequada para produzir fórmulas mais específicas e de maior estabilidade.
J16: Inovação tecnológica de produto | M16: 📑
B17: Tipo de inovação | E17: Inovação tecnológica de processo | J17: Inovação tecnológica de processo | M17: 📑
J18: Inovação tecnológica de serviços | M18: 📑
B19: Elemento inovador | E19: A introdução da tecnologia de tratamento térmico em autoclave representa uma inovação significativa para a Prodiet, que atualmente utiliza apenas processos UHT. A escolha da tecnologia de autoclave foi motivada pela necessidade de melhorar a qualidade e a segurança dos produtos de nutrição enteral, reduzindo riscos de contaminação e aumentando a vida útil sem a necessidade de aditivos químicos. Comparada aos métodos UHT, a tecnologia de autoclave proporciona um tratamento térmico mais homogêneo e controlado, resultando em produtos de maior qualidade e estabilidade. Além disso, permite a criação de uma variedade maior de produtos, atendendo a necessidades específicas do mercado. A adoção desta tecnologia requer a construção de uma nova área fabril, com mudanças significativas nos fluxos de trabalho e equipamentos. A Prodiet planeja integrar novos processos e treinar funcionários para operar com a tecnologia de autoclave. A empresa também planeja proteger essa inovação através de patentes e outros mecanismos de propriedade intelectual, garantindo que os avanços tecnológicos desenvolvidos sejam devidamente reconhecidos e protegidos. | J19: - Não podem ser consideradas as inovações organizacionais, comerciais e de marketing
J20: Empresa ou segmento regional | M20: 📑
B21: Nível de inovação | E21: Empresa ou segmento regional | J21: Inovador para o Brasil | M21: 📑
J22: Inovador para o Mundo | M22: 📑
B23: Risco tecnológico | E23: O principal desafio do projeto será implantar uma nova área fabril do zero, compreendendo totalmente a tecnologia de autoclave e assegurando a estabilidade e esterilidade comercial dos produtos. Será necessário desenvolver novas embalagens compatíveis com o processo e encontrar um copacker adequado para otimizar o tempo de lançamento dos produtos. A empresa planeja superar esses desafios através de uma abordagem multifásica, que inclui a contratação de consultorias especializadas, desenvolvimento de protótipos em plantas piloto, e estreita colaboração com fornecedores de equipamentos e embalagens.
B25: Metodologias | E25: A Prodiet está realizando diversos estudos e consultorias para adquirir o conhecimento necessário sobre a tecnologia de autoclave. Estes estudos incluem a contratação de consultorias para formulações e desenvolvimento de produtos, a pesquisa de locais para testes em planta piloto, o contato com fornecedores de embalagens e prestadores de serviços, além de estudos detalhados sobre a nova tecnologia, abrangendo produto, processo, equipamentos e embalagens. Estes estudos estão sendo financiados através de fundos próprios e incentivos fiscais da Lei do Bem, geridos por uma equipe dedicada que inclui departamentos de Pesquisa Científica, Assuntos Regulatórios, Qualidade, Manutenção e Produção. As várias áreas da empresa estão colaborando de forma integrada, com reuniões regulares e troca de informações para garantir que todos os aspectos do projeto sejam devidamente considerados e implementados.
B27: Equipe | E27: Nome Completo | F27: Cargo/Função | G27: Qualificação | H27: !
E28: Lizianne Angelica Shmeil | F28: Analista de P&D | G28: Pós-graduação | L28: Técnico | M28: 📑
E29: Ana Paula Celes | F29: Diretora Técnica | G29: Pós-graduação | L29: Graduação
E30: Luciana Dutra | F30: Gerente Técnica | G30: Pós-graduação | L30: Pós-graduação
L31: Mestrado
L32: Doutorado
B35: Cronograma
B36: [anexar imagem - preferencialmente Gantt]

Sheet INOV0004
B2: PRODIET
B3: Pesquisa, Desenvolvimento & Inovação
B4: Formulário de PD&I - Ano 2023 | J4: Incentivado pela Lei do Bem | M4: TRUE
B5: - preencher somente os campos sombreados (cinza) e - adicionar cronograma no formato de imagem ao fim do formulário - preencher um deste para cada projeto de PD&I | J5: Objetiva tornar-se um Ativo | M5: FALSE
J6: Objetiva gerar patente/registro | M6: FALSE
B8: Dossiê do projeto
B9: Dados gerais para identificação e validação do projeto de PD&I
B11: Nome do projeto | E11: INOV000004 (2019 - CICATRIZAÇÃO)
J12: Pesquisa básica | M12: 📑
B13: Classificação do projeto | E13: Desenvolvimento experimental | J13: Pesquisa aplicada | M13: 📑
J14: Desenvolvimento experimental | M14: 📑
B15: Objetivos do projeto | E15: A Prodiet está desenvolvendo um produto voltado para cicatrização, adequado tanto para uso em pós-operatórios quanto para a prevenção e tratamento de lesões por pressão. Para alcançar a eficácia no tratamento de lesões, estão sendo realizados diversos estudos científicos e clínicos. Esses estudos incluem a análise de mecanismos de cicatrização, testes de eficácia em diferentes tipos de lesões e avaliações de segurança. Além disso, foram incorporados novos processos de formulação e testes para assegurar a estabilidade e a eficácia dos ingredientes ativos na cicatrização.
J16: Inovação tecnológica de produto | M16: 📑
B17: Tipo de inovação | E17: Inovação tecnológica de produto | J17: Inovação tecnológica de processo | M17: 📑
J18: Inovação tecnológica de serviços | M18: 📑
B19: Elemento inovador | E19: A fórmula para cicatrização desenvolvida pela Prodiet oferece uma combinação inovadora de nutrientes que não é encontrada em produtos similares no mercado. Enquanto a maioria dos produtos recomendados em ambientes hospitalares são líquidos, a Prodiet desenvolveu uma versão em pó, com o objetivo de oferecer um melhor custo-benefício aos pacientes. Esta fórmula em pó difere significativamente dos produtos líquidos tradicionais ao proporcionar maior flexibilidade na dosagem e uma melhor estabilidade dos nutrientes durante o armazenamento. A principal diferença na cicatrização entre o produto em forma líquida e em pó reside na bioavaliação dos nutrientes, onde a versão em pó tem demonstrado uma liberação mais controlada e eficiente dos componentes ativos. | J19: - Não podem ser consideradas as inovações organizacionais, comerciais e de marketing
J20: Empresa ou segmento regional | M20: 📑
B21: Nível de inovação | E21: Empresa ou segmento regional | J21: Inovador para o Brasil | M21: 📑
J22: Inovador para o Mundo | M22: 📑
B23: Risco tecnológico | E23: O desenvolvimento do produto apresenta desafios tecnológicos significativos, especialmente no que se refere ao sensorial agradável e à combinação de nutrientes de alto residual, como aminoácidos isolados e colágeno hidrolisado. Os principais aminoácidos isolados presentes no produto que causam desafios sensoriais incluem aqueles com sabores intensos e persistentes. Para lidar com esses desafios, a empresa está realizando pesquisas sensoriais e testes de sabor, além de explorar tecnologias de encapsulamento para mascarar sabores indesejados. No que diz respeito ao colágeno hidrolisado, a empresa está garantindo sua estabilidade durante o processamento térmico através de métodos específicos de produção, como a microencapsulação, que protege os nutrientes durante o processo UHT (Ultra High Temperature). Para minimizar os efeitos sensoriais indesejados dos ingredientes com alto residual de sabor ou aroma, estão sendo exploradas diversas estratégias, incluindo a utilização de flavorizantes naturais e a modificação do perfil de liberação dos nutrientes. O processo UHT é adaptado para acomodar ingredientes sensíveis, garantindo a integridade nutricional do produto através de ajustes precisos de temperatura e tempo de processamento. Estão sendo conduzidas pesquisas e testes específicos para avaliar a estabilidade dos ingredientes durante o processamento térmico, utilizando critérios rigorosos para determinar a estabilidade dos componentes, como a retenção de atividade biológica e a ausência de degradação significativa. O desenvolvimento do produto envolveu a colaboração com especialistas externos e consultores, que contribuíram com conhecimentos avançados e técnicas inovadoras para superar os desafios tecnológicos específicos.
B25: Metodologias | E25: A metodologia adotada pela Prodiet para o desenvolvimento da fórmula envolve intensiva pesquisa e contatos com profissionais do setor. A empresa busca compreender o comportamento das matérias-primas selecionadas através de estudos existentes e de novos testes em parceria com fornecedores. Para definir um produto que apresenta sensorial agradável, a Prodiet realiza avaliações sensoriais detalhadas, incluindo testes de sabor, textura e aceitação por parte de grupos de consumidores. Os indicadores utilizados para determinar se o produto é sensorialmente agradável incluem escalas de aceitação sensorial, testes de preferência e análises quantitativas de atributos sensoriais específicos, assegurando que o produto final atenda aos altos padrões de qualidade e aceitação do mercado.
B27: Equipe | E27: Nome Completo | F27: Cargo/Função | G27: Qualificação | H27: !
E28: Gabriela Faria de Oliveira | F28: Analista Científico | G28: Pós-graduação | L28: Técnico | M28: 📑
E29: Rafael Parreira Lorini | F29: Analista de P&D | L29: Graduação
E30: Ana Paula Celes | F30: Diretora Técnica | G30: Pós-graduação | L30: Pós-graduação
E31: Luciana Dutra | F31: Gerente Técnica | G31: Pós-graduação | L31: Mestrado
E32: Hellin dos Santos | F32: Gerente Científico | G32: Mestrado | L32: Doutorado
B35: Cronograma
B36: [anexar imagem - preferencialmente Gantt]

Sheet INOV0006
B2: PRODIET
B3: Pesquisa, Desenvolvimento & Inovação
B4: Formulário de PD&I - Ano 2023 | J4: Incentivado pela Lei do Bem | M4: TRUE
B5: - preencher somente os campos sombreados (cinza) e - adicionar cronograma no formato de imagem ao fim do formulário - preencher um deste para cada projeto de PD&I | J5: Objetiva tornar-se um Ativo | M5: FALSE
J6: Objetiva gerar patente/registro | M6: FALSE
B8: Dossiê do projeto
B9: Dados gerais para identificação e validação do projeto de PD&I
B11: Nome do projeto | E11: INOV000006 (2019 - ARTESANAL)
J12: Pesquisa básica | M12: 📑
B13: Classificação do projeto | E13: Desenvolvimento experimental | J13: Pesquisa aplicada | M13: 📑
J14: Desenvolvimento experimental | M14: 📑
B15: Objetivos do projeto | E15: A Prodiet está desenvolvendo um produto inovador no mercado brasileiro, com o objetivo de complementar a dieta enteral artesanal, oferecendo uma ótima relação custo/benefício. Este produto é único, pois não há similares disponíveis no mercado atualmente. Ele visa preencher uma lacuna significativa no mercado de nutrição enteral, proporcionando uma solução nutritiva e acessível para pacientes que dependem de dietas artesanais.
J16: Inovação tecnológica de produto | M16: 📑
B17: Tipo de inovação | E17: Inovação tecnológica de produto | J17: Inovação tecnológica de processo | M17: 📑
J18: Inovação tecnológica de serviços | M18: 📑
B19: Elemento inovador | E19: A fórmula desenvolvida pela Prodiet é totalmente inovadora, incorporando alimentos que atendem a uma demanda específica ainda não contemplada no mercado brasileiro. Esta formulação oferece propriedades exclusivas que a tornam valiosa para os consumidores, como a utilização de alimentos liofilizados que mantêm o valor nutricional dos ingredientes in natura. A demanda específica foi identificada através de estudos de mercado detalhados, pesquisas com consumidores e análises de tendências de saúde, que indicaram uma necessidade crescente por soluções de nutrição enteral artesanal com melhor qualidade e custo-benefício. | J19: - Não podem ser consideradas as inovações organizacionais, comerciais e de marketing
J20: Empresa ou segmento regional | M20: 📑
B21: Nível de inovação | E21: Inovador para o Brasil | J21: Inovador para o Brasil | M21: 📑
J22: Inovador para o Mundo | M22: 📑
B23: Risco tecnológico | E23: Os desafios tecnológicos associados a este projeto incluem a utilização de novas matérias-primas, como alimentos liofilizados, que apresentam uma composição nutricional variável, dificultando a seleção de ingredientes que atendam ao perfil nutricional desejado. Além disso, desenvolver um produto que seja nutricionalmente adequado para o público que utiliza nutrição enteral artesanal, com um perfil sensorial neutro e solubilidade adequada, representa uma barreira significativa. Para abordar esses desafios, a empresa está adotando estratégias específicas, como a análise rigorosa de lotes de matérias-primas para garantir consistência nutricional e o uso de técnicas avançadas de formulação para melhorar a solubilidade e o perfil sensorial do produto. Medidas estão sendo tomadas para garantir que a fórmula seja segura para consumo em nutrição enteral, incluindo testes rigorosos de segurança e qualidade. A viabilidade técnica da formulação proposta é um foco constante, com esforços contínuos para superar desafios significativos através de inovação e colaboração com especialistas do setor.
B25: Metodologias | E25: A metodologia adotada pela Prodiet inclui um estudo detalhado dos principais nutrientes deficientes na dieta artesanal oferecida a indivíduos que utilizam nutrição enteral artesanal. Análises da composição de produtos com ingredientes in natura e análises sensoriais foram conduzidas para entender melhor os desafios e necessidades. O estudo de novas matérias-primas foi liderado pelos departamentos Científico e de Pesquisa e Desenvolvimento (P&D). Os primeiros testes de bancada não foram satisfatórios devido à presença de grânulos e sabor residual desagradável. No momento, o P&D está realizando novos estudos de matérias-primas em parceria com fornecedores para melhorar a formulação.
B27: Equipe | E27: Nome Completo | F27: Cargo/Função | G27: Qualificação | H27: !
E28: Gabriela Faria de Oliveira | F28: Analista Científico | G28: Pós-graduação | L28: Técnico | M28: 📑
E29: Camila Mendes Pereira | F29: Analista de P&D | G29: Graduação | L29: Graduação
E30: Luciana Dutra | F30: Gerente Técnica | G30: Pós-graduação | L30: Pós-graduação
E31: Hellin dos Santos | F31: Gerente Científico | G31: Mestrado | L31: Mestrado
E32: Ana Paula Celes | F32: Diretora Técnica | G32: Pós-graduação | L32: Doutorado
B35: Cronograma
B36: [anexar imagem - preferencialmente Gantt]

Sheet INOV00010
B2: PRODIET
B3: Pesquisa, Desenvolvimento & Inovação
B4: Formulário de PD&I - Ano 2023 | J4: Incentivado pela Lei do Bem | M4: TRUE
B5: - preencher somente os campos sombreados (cinza) e - adicionar cronograma no formato de imagem ao fim do formulário - preencher um deste para cada projeto de PD&I | J5: Objetiva tornar-se um Ativo | M5: FALSE
J6: Objetiva gerar patente/registro | M6: FALSE
B8: Dossiê do projeto
B9: Dados gerais para identificação e validação do projeto de PD&I
B11: Nome do projeto | E11: INOV000010 (2021 - DIAMAX PÓ)
J12: Pesquisa básica | M12: 📑
B13: Classificação do projeto | E13: Desenvolvimento experimental | J13: Pesquisa aplicada | M13: 📑
J14: Desenvolvimento experimental | M14: 📑
B15: Objetivos do projeto | E15: A Prodiet está desenvolvendo um produto competitivo ao Glucerna* para venda no varejo, categorizado como suplemento para permitir agilidade no lançamento. O produto será focado tanto para diabéticos quanto para a população geral, sendo desenvolvido na forma de pó para facilitar o consumo e a armazenagem. Este produto visa preencher uma lacuna no mercado, oferecendo uma opção acessível e eficaz para o controle glicêmico com alto teor de proteína, alinhado com a linha Diamax já existente no portfólio da empresa.
J16: Inovação tecnológica de produto | M16: 📑
B17: Tipo de inovação | E17: Inovação tecnológica de produto | J17: Inovação tecnológica de processo | M17: 📑
J18: Inovação tecnológica de serviços | M18: 📑
B19: Elemento inovador | E19: O elemento inovador deste produto é a sua formulação específica para controle glicêmico, com aumento do teor proteico, destinado ao mercado varejista. O aumento de proteína no produto contribui para o controle da glicemia ao promover uma liberação mais lenta de glicose no sangue, melhorando a resposta glicêmica pós-prandial. Os benefícios associados a um maior teor de proteína incluem a manutenção da massa muscular, maior saciedade e melhor controle do peso, aspectos essenciais para a gestão da diabetes e saúde geral. | J19: - Não podem ser consideradas as inovações organizacionais, comerciais e de marketing
J20: Empresa ou segmento regional | M20: 📑
B21: Nível de inovação | E21: Empresa ou segmento regional | J21: Inovador para o Brasil | M21: 📑
J22: Inovador para o Mundo | M22: 📑
B23: Risco tecnológico | E23: Os desafios tecnológicos envolvem a construção de um produto com preço de venda competitivo, mantendo a qualidade sensorial que não limite seu consumo. As principais limitações incluem sabor, preço e oferta no mercado. O sensorial final do consumidor será avaliado com foco na efetividade do produto, preço e acessibilidade. Estudos estão sendo realizados para mensurar a aceitação do público-alvo, utilizando pesquisas de mercado e testes de produto. O projeto aborda o desafio de construir um produto com preço de venda competitivo em relação ao Glucerna* e outros concorrentes através de estratégias de otimização de custos na produção e escolha de ingredientes. Para o desenvolvimento de aromas e sabores, a empresa está colaborando com fornecedores especializados para criar perfis sensoriais que sejam agradáveis e aceitos pelo público-alvo.
B25: Metodologias | E25: A metodologia para o desenvolvimento do produto inclui a elaboração de um target de micronutrientes único para suplementos, considerando as necessidades específicas de indivíduos diabéticos, desnutridos e principais deficiências nutricionais encontradas na população. O aumento da proporção de proteína vegetal na formulação visa a redução de custo sem comprometer a qualidade nutricional. As necessidades de diabéticos e desnutridos são priorizadas de forma balanceada, garantindo que o produto atenda ambas as populações de forma eficaz. A parte inovadora de aumentar a proteína vegetal reside na escolha de fontes vegetais de alta qualidade que são mais sustentáveis e economicamente viáveis. Os micronutrientes específicos considerados no target incluem cromo, magnésio, vitaminas do complexo B e antioxidantes, todos críticos para a gestão da diabetes e melhoria do estado nutricional. A empresa planeja aumentar a proporção de proteína vegetal na formulação utilizando fontes como soja, ervilha e arroz, que são conhecidas por seus perfis nutricionais completos. O desenvolvimento de novos aromas em parceria com fornecedores envolve testes rigorosos de palatabilidade e estabilidade, garantindo que os sabores resultantes sejam agradáveis e aceitos pelo consumidor final.
B27: Equipe | E27: Nome Completo | F27: Cargo/Função | G27: Qualificação | H27: !
E28: Ana Claudia Zanini | F28: Analista cientifico | G28: Mestrado | L28: Técnico | M28: 📑
E29: Camila Mendes Pereira | F29: Analista de P&D | G29: Graduação | L29: Graduação
E30: Juliana Lamas Roberto | F30: Especialista de Estudo de Estabilidade | G30: Mestrado | L30: Pós-graduação
E31: Luciana Dutra | F31: Gerente Técnica | G31: Pós-graduação | L31: Mestrado
E32: Hellin dos Santos | F32: Gerente Cientifico | G32: Mestrado | L32: Doutorado
E33: Ana Paula Celes | F33: Diretora Técnica | G33: Pós-graduação
B35: Cronograma
B36: [anexar imagem - preferencialmente Gantt]

Sheet INOV00013
B2: PRODIET
B3: Pesquisa, Desenvolvimento & Inovação
B4: Formulário de PD&I - Ano 2023 | J4: Incentivado pela Lei do Bem | M4: TRUE
B5: - preencher somente os campos sombreados (cinza) e - adicionar cronograma no formato de imagem ao fim do formulário - preencher um deste para cada projeto de PD&I | J5: Objetiva tornar-se um Ativo | M5: FALSE
J6: Objetiva gerar patente/registro | M6: FALSE
B8: Dossiê do projeto
B9: Dados gerais para identificação e validação do projeto de PD&I
B11: Nome do projeto | E11: INOV000013 (2021 - SACHÊ A VÁCUO)
J12: Pesquisa básica | M12: 📑
B13: Classificação do projeto | E13: Desenvolvimento experimental | J13: Pesquisa aplicada | M13: 📑
J14: Desenvolvimento experimental | M14: 📑
B15: Objetivos do projeto | E15: A Prodiet está aplicando o uso do vácuo no envase dos produtos em pó do seu portfólio atual, com o objetivo de estudar se a embalagem mantém o vácuo ao longo do shelf-life, bem como auxiliar a manter as características nutricionais e sensoriais dos produtos, em comparação às embalagens atuais, como potes e latas. Este projeto busca explorar uma abordagem inovadora na conservação de produtos de nutrição enteral, garantindo qualidade superior durante todo o período de validade.
J16: Inovação tecnológica de produto | M16: 📑
B17: Tipo de inovação | E17: Inovação tecnológica de processo | J17: Inovação tecnológica de processo | M17: 📑
J18: Inovação tecnológica de serviços | M18: 📑
B19: Elemento inovador | E19: Atualmente, os produtos em pó são fabricados em embalagens plásticas rígidas (potes), latas de alumínio e embalagens plásticas flexíveis (sachês). A utilização de embalagens a vácuo para nutrição enteral não é uma prática comum no mercado nacional. As principais diferenças ou vantagens esperadas entre as embalagens a vácuo propostas e as embalagens atuais incluem uma melhor preservação das características nutricionais e sensoriais dos produtos, uma maior proteção contra a umidade e oxidação, e uma potencial extensão do shelf-life dos produtos. Existem dados de referência que fundamentam essa comparação, demonstrando os benefícios do vácuo em outras indústrias alimentícias, o que justifica a implementação dessa tecnologia na nutrição enteral. | J19: - Não podem ser consideradas as inovações organizacionais, comerciais e de marketing
J20: Empresa ou segmento regional | M20: 📑
B21: Nível de inovação | E21: Inovador para o Brasil | J21: Inovador para o Brasil | M21: 📑
J22: Inovador para o Mundo | M22: 📑
B23: Risco tecnológico | E23: O principal desafio é entender como o mercado nacional reagirá ao novo tipo de embalagem para nutrição enteral. Além disso, é necessário considerar a limitação fabril, o investimento em novos equipamentos e em uma nova linha de processo, bem como manter um preço de venda competitivo. A reação do mercado será avaliada através de pesquisas de mercado, grupos focais e outros métodos para medir a aceitação do cliente. O investimento em novos equipamentos e linhas de processo inclui a aquisição de máquinas de envase a vácuo e a implementação de uma linha de produção dedicada. O plano de implementação envolve fases de testes e validação para garantir a eficiência e eficácia do processo. A colaboração com fornecedores e parceiros será fundamental para superar os desafios tecnológicos e de produção, garantindo que a cadeia de suprimentos esteja alinhada com os padrões de qualidade e eficiência exigidos. Um estudo de viabilidade econômica foi realizado, levando em consideração os investimentos necessários e o potencial retorno sobre o investimento (ROI), monitorando indicadores financeiros críticos para garantir a sustentabilidade do projeto.
B25: Metodologias | E25: A metodologia envolve a busca de fornecedores de embalagens que suportem o vácuo e de fornecedores de equipamentos com a tecnologia adequada para o envase e selagem dos produtos a vácuo. Um piloto industrial será realizado em parceria com um fornecedor. Os critérios específicos para a seleção dos fornecedores incluem considerações técnicas, qualidade, custo e capacidade de produção. O processo de avaliação de fornecedores garante que eles atendam aos padrões de qualidade necessários, assegurando que a implementação da nova tecnologia seja bem-sucedida e beneficie os consumidores finais.
B27: Equipe | E27: Nome Completo | F27: Cargo/Função | G27: Qualificação | H27: !
E28: Lizianne Shmeil | F28: Analista de P&D | G28: Pós-graduação | L28: Técnico | M28: 📑
L29: Graduação
L30: Pós-graduação
L31: Mestrado
L32: Doutorado
B35: Cronograma
B36: [anexar imagem - preferencialmente Gantt]

Sheet INOV00014
B2: PRODIET
B3: Pesquisa, Desenvolvimento & Inovação
B4: Formulário de PD&I - Ano 2023 | J4: Incentivado pela Lei do Bem | M4: TRUE
B5: - preencher somente os campos sombreados (cinza) e - adicionar cronograma no formato de imagem ao fim do formulário - preencher um deste para cada projeto de PD&I | J5: Objetiva tornar-se um Ativo | M5: FALSE
J6: Objetiva gerar patente/registro | M6: FALSE
B8: Dossiê do projeto
B9: Dados gerais para identificação e validação do projeto de PD&I
B11: Nome do projeto | E11: INOV000014 (2021 - ENERGYZIP 25%)
J12: Pesquisa básica | M12: 📑
B13: Classificação do projeto | E13: Desenvolvimento experimental | J13: Pesquisa aplicada | M13: 📑
J14: Desenvolvimento experimental | M14: 📑
B15: Objetivos do projeto | E15: A Prodiet tem como objetivo desenvolver um suplemento hipercalórico e hiperproteico líquido, visando permitir maior abertura no mercado público e privado. Atualmente, a empresa não possui este tipo de produto em seu portfólio, e existe uma demanda crescente por suplementos hiperproteicos no mercado. Este projeto também acompanhará o lançamento da linha de sistema fechado, oferecendo um mix de vendas para hospitais e sendo competitivo para processos públicos e para o mercado internacional. Para entender melhor o projeto, são necessárias informações específicas, como o público-alvo detalhado e os requisitos técnicos e regulatórios a serem atendidos. No mercado internacional, a demanda por suplementos hipercalóricos e hiperproteicos líquidos é impulsionada por um aumento na conscientização sobre saúde e nutrição, a necessidade de produtos de fácil administração em ambientes clínicos, e o crescimento da população idosa que requer suplementação proteica. Estudos de mercado internacionais indicam uma tendência crescente de consumidores buscando produtos que atendam a essas necessidades nutricionais específicas.
J16: Inovação tecnológica de produto | M16: 📑
B17: Tipo de inovação | E17: Inovação tecnológica de produto | J17: Inovação tecnológica de processo | M17: 📑
J18: Inovação tecnológica de serviços | M18: 📑
B19: Elemento inovador | E19: A inovação desse produto está no aumento do teor de proteína em comparação com os produtos de linha atuais. Isso possibilitará um ganho de mercado, tanto em relação à competição com outros suplementos quanto para fórmulas enterais que necessitam de um aporte proteico mais expressivo. O aumento de proteína será implementado em produtos específicos destinados a pacientes com maiores necessidades proteicas. O aumento no teor de proteína será alcançado através da adição de fontes proteicas de alta qualidade, como proteínas isoladas de soro de leite ou proteína vegetal concentrada, garantindo que o suplemento mantenha sua qualidade nutricional. | J19: - Não podem ser consideradas as inovações organizacionais, comerciais e de marketing
J20: Empresa ou segmento regional | M20: 📑
B21: Nível de inovação | E21: Empresa ou segmento regional | J21: Inovador para o Brasil | M21: 📑
J22: Inovador para o Mundo | M22: 📑
B23: Risco tecnológico | E23: O principal desafio no desenvolvimento dessa fórmula está na estabilização proteica/estrutural, pois o aumento do teor de proteína resulta em maior viscosidade, o que pode dificultar a administração das fórmulas enterais. A alta viscosidade pode afetar a administração, tornando o produto mais difícil de passar através de sondas e equipamentos de alimentação enteral. Na linha de produção, a viscosidade alta pode causar problemas de fluxo e preenchimento, exigindo ajustes nos equipamentos de envase. Para abordar esses desafios, a empresa está utilizando tecnologias de processamento que permitem a redução da viscosidade, como a hidrólise parcial das proteínas, e aditivos que estabilizam a fórmula. Além da viscosidade, estão sendo consideradas outras características sensoriais e de formulação, como sabor, cor e estabilidade ao longo do shelf-life, para garantir uma administração eficaz do produto.
B25: Metodologias | E25: A metodologia para este projeto inclui o desenvolvimento e testes piloto de uma fórmula com maior teor de proteínas. O objetivo é aumentar o teor de proteínas sem comprometer a liquidez do produto, garantindo que ele seja fácil de administrar. A quantidade de aumento de proteína desejada está sendo determinada com base em estudos de necessidades nutricionais dos pacientes alvo. Os indicadores de sucesso do projeto incluem a aceitação sensorial do produto, a estabilidade nutricional ao longo do shelf-life e a viabilidade de produção em larga escala. Os testes piloto estão sendo conduzidos com parâmetros rigorosos, como a solubilidade das proteínas, a viscosidade da fórmula e a estabilidade em diferentes condições de armazenamento.
B27: Equipe | E27: Nome Completo | F27: Cargo/Função | G27: Qualificação | H27: !
E28: Ana Claudia Zanini | F28: Analista Cientifico | G28: Mestrado | L28: Técnico | M28: 📑
E29: Márcio Henrique Nogueira | F29: Analista de P&D | G29: Doutorado | L29: Graduação
E30: Juliana Lamas Roberto | F30: Especialista de Estudo de Estabilidade | G30: Mestrado | L30: Pós-graduação
E31: Hellin dos Santos | F31: Gerente cientifico | G31: Mestrado | L31: Mestrado
E32: Ana Paula Celes | F32: Diretora Técnica | G32: Pós-graduação | L32: Doutorado
E33: Rafael Parreira Lorini | F33: Analista de P&D | G33: Pós-graduação
B35: Cronograma
B36: [anexar imagem - preferencialmente Gantt]

Sheet INOV00016
B2: PRODIET
B3: Pesquisa, Desenvolvimento & Inovação
B4: Formulário de PD&I - Ano 2023 | J4: Incentivado pela Lei do Bem | M4: TRUE
B5: - preencher somente os campos sombreados (cinza) e - adicionar cronograma no formato de imagem ao fim do formulário - preencher um deste para cada projeto de PD&I | J5: Objetiva tornar-se um Ativo | M5: FALSE
J6: Objetiva gerar patente/registro | M6: FALSE
B8: Dossiê do projeto
B9: Dados gerais para identificação e validação do projeto de PD&I
B11: Nome do projeto | E11: INOV000016 (2018 - LINHA TROPHIC SOYA LÍQUIDO)
J12: Pesquisa básica | M12: 📑
B13: Classificação do projeto | E13: Desenvolvimento experimental | J13: Pesquisa aplicada | M13: 📑
J14: Desenvolvimento experimental | M14: 📑
B15: Objetivos do projeto | E15: A Prodiet está expandindo o portfólio da linha 100% Soja com o desenvolvimento de um novo produto de alto perfil proteico e adição de fibras, destinado a consumidores com alergias alimentares às proteínas do leite. O objetivo é oferecer um suplemento nutricional robusto que atenda às necessidades específicas desse público-alvo. Os valores-alvo para o perfil proteico e de fibras são determinados com base em diretrizes nutricionais e necessidades do mercado. Especificamente, o novo produto deve fornecer aproximadamente 1,5 kcal/mL de energia, com um teor de proteína adequado para suportar a saúde muscular e uma quantidade significativa de fibras para promover a saúde digestiva. Esses valores foram estabelecidos após análise de literatura científica, recomendações de especialistas em nutrição e feedback de consumidores.
J16: Inovação tecnológica de produto | M16: 📑
B17: Tipo de inovação | E17: Inovação tecnológica de produto | J17: Inovação tecnológica de processo | M17: 📑
J18: Inovação tecnológica de serviços | M18: 📑
B19: Elemento inovador | E19: O elemento inovador do projeto reside na criação de um produto de alto teor proteico e adição de fibras, sem incluir proteínas de leite. Para alcançar essa formulação, a empresa está considerando o uso de proteínas vegetais, como proteína isolada de soja e ervilha, que oferecem um perfil aminoacídico completo e alta biodisponibilidade. Além disso, estão sendo incorporadas fibras solúveis e insolúveis, como inulina e fibra de chicória, para melhorar a saúde digestiva. Pesquisas e estudos de mercado justificam a escolha desse perfil nutricional, destacando a crescente demanda por produtos livres de alérgenos e ricos em nutrientes. Para abordar o desafio de criar um produto saboroso, a empresa está investindo em testes sensoriais e desenvolvimento de sabores agradáveis, colaborando com especialistas em aromas e palatabilidade. | J19: - Não podem ser consideradas as inovações organizacionais, comerciais e de marketing
J20: Empresa ou segmento regional | M20: 📑
B21: Nível de inovação | E21: Inovador para o Brasil | J21: Inovador para o Brasil | M21: 📑
J22: Inovador para o Mundo | M22: 📑
B23: Risco tecnológico | E23: O principal desafio tecnológico é a estabilização da fórmula, especialmente devido ao aumento do teor de proteína e fibras, que pode resultar em alta viscosidade, dificultando a administração do produto. Para estabilizar a fórmula, estão sendo consideradas abordagens específicas, como a utilização de agentes estabilizantes naturais e a otimização do processo de mistura. Estudos de formulação estão em andamento para encontrar o equilíbrio ideal entre proteína, fibras e viscosidade. Tecnologias de produção avançadas, como homogeneização de alta pressão, estão sendo avaliadas para lidar com a alta viscosidade. A empresa pode precisar investir em equipamentos especiais para garantir a consistência do produto. Para otimizar o processo de fabricação, a Prodiet está implementando protocolos rigorosos de controle de qualidade e consistência de lotes. Além disso, colaborações com pesquisadores acadêmicos e consultores estão sendo exploradas para obter insights adicionais sobre a estabilização do produto e superar os desafios tecnológicos.
B25: Metodologias | E25: A metodologia para este projeto inclui a realização de testes pilotos UHT e a avaliação de estudos de estabilidade da fórmula para garantir que o produto atinja os parâmetros necessários para a comercialização. Os principais objetivos dos testes pilotos UHT são a esterilização e a preservação da estabilidade nutricional e sensorial do produto. A capacidade de produção dos testes pilotos será comparada à escala de produção comercial para assegurar a viabilidade do processo. Estudos de estabilidade serão conduzidos em condições controladas de armazenamento, simulando temperaturas e umidades típicas para avaliar a durabilidade do produto ao longo do tempo. Testes acelerados de estabilidade estão planejados para prever o comportamento do produto em longo prazo, permitindo ajustes na formulação antes da produção em larga escala.
B27: Equipe | E27: Nome Completo | F27: Cargo/Função | G27: Qualificação | H27: !
E28: Rafael Lorini | F28: Analista de P&D | G28: Graduação | L28: Técnico | M28: 📑
E29: Luciana Dutra | F29: Gerente Técnica | G29: Pós-graduação | L29: Graduação
L30: Pós-graduação
L31: Mestrado
L32: Doutorado
B35: Cronograma
B36: [anexar imagem - preferencialmente Gantt]

Sheet INOV00017
B2: PRODIET
B3: Pesquisa, Desenvolvimento & Inovação
B4: Formulário de PD&I - Ano 2023 | J4: Incentivado pela Lei do Bem | M4: TRUE
B5: - preencher somente os campos sombreados (cinza) e - adicionar cronograma no formato de imagem ao fim do formulário - preencher um deste para cada projeto de PD&I | J5: Objetiva tornar-se um Ativo | M5: FALSE
J6: Objetiva gerar patente/registro | M6: FALSE
B8: Dossiê do projeto
B9: Dados gerais para identificação e validação do projeto de PD&I
B11: Nome do projeto | E11: INOV000017 (2020 - LINHA TROPHIC SOYA PÓ)
J12: Pesquisa básica | M12: 📑
B13: Classificação do projeto | E13: Desenvolvimento experimental | J13: Pesquisa aplicada | M13: 📑
J14: Desenvolvimento experimental | M14: 📑
B15: Objetivos do projeto | E15: A Prodiet tem como objetivo expandir a linha guarda-chuva Soya, desenvolvendo produtos em pó para nutrição enteral e oral voltados para o público adulto, com foco em editais de licitação. Este produto será inovador e específico para atender aos requisitos dos editais de licitação. Além de atender aos editais governamentais, o foco também incluirá a venda para o público geral. A demanda específica nos editais de licitação para produtos em pó de nutrição enteral e oral inclui critérios essenciais como composição nutricional adequada, custo competitivo e capacidade de atender grandes volumes. Esses critérios são determinados pelas necessidades de pacientes em ambientes hospitalares e programas de saúde pública.
J16: Inovação tecnológica de produto | M16: 📑
B17: Tipo de inovação | E17: Inovação tecnológica de produto | J17: Inovação tecnológica de processo | M17: 📑
J18: Inovação tecnológica de serviços | M18: 📑
B19: Elemento inovador | E19: O elemento inovador deste projeto é o desenvolvimento de uma linha de produtos em pó com 80% de proteínas de origem vegetal (soja) e apenas 20% de proteína animal, diferindo dos produtos líquidos existentes na linha Soya. Esta composição inovadora oferece vantagens significativas em termos de sustentabilidade e adequação a dietas específicas. A linha Soya existente será expandida para incluir produtos líquidos e em pó, mantendo duas sub-linhas distintas. O aumento da proporção de proteína de soja em relação à proteína animal se alinha à estratégia da Prodiet de oferecer produtos nutricionais mais sustentáveis e acessíveis, respondendo à crescente demanda por produtos vegetais. Os benefícios específicos desta composição incluem uma menor pegada ambiental, melhor aceitação por consumidores com restrições alimentares, e uma fonte de proteína completa e balanceada. | J19: - Não podem ser consideradas as inovações organizacionais, comerciais e de marketing
J20: Empresa ou segmento regional | M20: 📑
B21: Nível de inovação | E21: Empresa ou segmento regional | J21: Inovador para o Brasil | M21: 📑
J22: Inovador para o Mundo | M22: 📑
B23: Risco tecnológico | E23: O principal desafio tecnológico reside na estabilização do sabor e palatabilidade dos produtos, devido ao sabor residual da proteína de soja. A empresa está desenvolvendo estratégias para melhorar o sabor e a palatabilidade, como a aplicação de aromas que mascaram o sabor da proteína de soja e tornam o produto agradável tanto para administração enteral quanto oral. Para manter um custo competitivo, especialmente devido à presença de óleos em pó, estão sendo exploradas alternativas mais econômicas, como a utilização de óleo líquido e tecnologias de spray dryer para misturar proteínas, carboidratos e óleos. Estas estratégias buscam reduzir o custo sem comprometer a qualidade nutricional e sensorial do produto.
B25: Metodologias | E25: As metodologias adotadas incluem a busca por alternativas às gorduras em pó, como óleos líquidos de menor custo e maior solubilidade. A mistura de proteínas, carboidratos e óleo líquido por meio do processo de spray dryer está sendo testada para melhorar a solubilidade, aspecto e sabor do produto. Os testes de adsorção de óleo líquido através da maltodextrina de tapioca visam avaliar a solubilidade e a estabilidade do óleo na formulação. Estes testes estão sendo realizados em bancada, com resultados preliminares indicando uma boa estabilidade e solubilidade. O critério-chave para avaliar essas alternativas inclui o custo, solubilidade, estabilidade e aceitação sensorial do produto final. O prazo estimado para a conclusão dos testes e a determinação da melhor alternativa para as gorduras é de alguns meses, dependendo dos resultados dos testes em andamento. Caso as alternativas testadas não atinjam os resultados desejados, o plano de ação inclui a reavaliação das formulações e o ajuste das proporções dos ingredientes, bem como a busca por novos fornecedores e tecnologias que possam oferecer soluções mais adequadas. Esta abordagem garante que a Prodiet continue a desenvolver produtos que atendam aos altos padrões de qualidade, custo e aceitação no mercado.
B27: Equipe | E27: Nome Completo | F27: Cargo/Função | G27: Qualificação | H27: !
E28: Camila Mendes Pereira | F28: Aanalista de P&D | G28: Graduação | L28: Técnico | M28: 📑
E29: Luciana Dutra | F29: Gerente Técnica | G29: Pós-graduação | L29: Graduação
E30: Ana Paula Celes | F30: Diretora Técnica | G30: Pós-graduação | L30: Pós-graduação
L31: Mestrado
L32: Doutorado
B35: Cronograma
B36: [anexar imagem - preferencialmente Gantt]

Sheet INOV00021
B2: PRODIET
B3: Pesquisa, Desenvolvimento & Inovação
B4: Formulário de PD&I - Ano 2023 | J4: Incentivado pela Lei do Bem | M4: TRUE
B5: - preencher somente os campos sombreados (cinza) e - adicionar cronograma no formato de imagem ao fim do formulário - preencher um deste para cada projeto de PD&I | J5: Objetiva tornar-se um Ativo | M5: FALSE
J6: Objetiva gerar patente/registro | M6: FALSE
B8: Dossiê do projeto
B9: Dados gerais para identificação e validação do projeto de PD&I
B11: Nome do projeto | E11: INOV000021 (2022 - SOBREMESA)
J12: Pesquisa básica | M12: 📑
B13: Classificação do projeto | E13: Desenvolvimento experimental | J13: Pesquisa aplicada | M13: 📑
J14: Desenvolvimento experimental | M14: 📑
B15: Objetivos do projeto | E15: O projeto visa desenvolver uma nova forma de consumir os nutrientes 3+ do Immax, especificamente através de um sorvete nutritivo. A razão para criar essa nova forma de consumo é oferecer uma alternativa agradável e inovadora para a ingestão desses nutrientes, especialmente para pacientes que podem ter dificuldade em consumir suplementos tradicionais. Ao transformar os nutrientes em um sorvete, o objetivo é aumentar a adesão ao tratamento e proporcionar uma experiência de consumo mais agradável.
J16: Inovação tecnológica de produto | M16: 📑
B17: Tipo de inovação | E17: Inovação tecnológica de produto | J17: Inovação tecnológica de processo | M17: 📑
J18: Inovação tecnológica de serviços | M18: 📑
B19: Elemento inovador | E19: A inovação do projeto está na incorporação dos nutrientes do Immax em um sorvete. Esta abordagem não apenas replica os nutrientes existentes no Immax, mas também pode adicionar novos nutrientes, dependendo das necessidades nutricionais identificadas. A conclusão de que o sorvete seria a forma ótima para consumir os nutrientes 3+ do Immax foi baseada em estudos de aceitação sensorial e em pesquisas que indicam uma preferência por formas de consumo mais palatáveis e agradáveis. O sorvete pode incorporar os nutrientes do Immax através de técnicas de microencapsulação e estabilização, garantindo que nutrientes como proteínas, vitaminas, minerais e fibras estejam presentes no produto final. Os benefícios de oferecer esses nutrientes por meio de um sorvete incluem uma maior aceitação pelo público, facilidade de consumo, e potencial para uma melhor absorção dos nutrientes devido à sua forma palatável. | J19: - Não podem ser consideradas as inovações organizacionais, comerciais e de marketing
J20: Empresa ou segmento regional | M20: 📑
B21: Nível de inovação | E21: Inovador para o Brasil | J21: Inovador para o Brasil | M21: 📑
J22: Inovador para o Mundo | M22: 📑
B23: Risco tecnológico | E23: Um dos principais riscos tecnológicos é a não aceitação do mercado. Pesquisas de mercado preliminares indicam que existe um interesse crescente por produtos alimentícios que combinam prazer e saúde, mas ainda há incertezas quanto à aceitação específica de um sorvete nutricional. Para lidar com esse risco, a empresa planeja realizar testes de mercado e estratégias de marketing focadas em demonstrar os benefícios do produto, além de campanhas de educação nutricional. Medidas estão sendo tomadas para garantir que o sorvete mantenha a eficácia nutricional dos nutrientes do Immax durante todo o processo de fabricação e armazenamento, incluindo o uso de tecnologias de preservação e estabilização de nutrientes.
B25: Metodologias | E25: A metodologia envolve o desenvolvimento de uma sobremesa que possa ser acrescida dos nutrientes Pro 3+ do Immax, proporcionando aos pacientes uma forma alternativa e agradável de consumir esses ingredientes. A implementação dos nutrientes no sorvete será feita através de processos como microencapsulação, que protege os nutrientes durante a fabricação e armazenamento, garantindo sua estabilidade e biodisponibilidade. O mercado alvo inclui tanto o público geral quanto pacientes em tratamento nutricional, especialmente aqueles que necessitam de suplementação mas preferem formas de consumo mais agradáveis. O processo de desenvolvimento da sobremesa envolve várias etapas, incluindo pesquisa e desenvolvimento de formulações, testes sensoriais, e avaliações de estabilidade e segurança alimentar. A empresa pretende garantir a dosagem precisa dos nutrientes em cada porção de sorvete através de um rigoroso controle de qualidade durante a produção. Além disso, há planos para avaliar a aceitação do paciente em relação a essa nova forma de consumo através de estudos clínicos e feedback de consumidores. A empresa também está explorando outras formas criativas de oferecer os nutrientes do Immax, como barras nutricionais e bebidas fortificadas, para atender a diferentes preferências e necessidades dos pacientes.
B27: Equipe | E27: Nome Completo | F27: Cargo/Função | G27: Qualificação | H27: !
E28: Luciana Dutra | F28: Gerente P&D e AR | G28: Pós-graduação | L28: Técnico | M28: 📑
E29: Tahuany Caetano | F29: Analista MKT | G29: Pós-graduação | L29: Graduação
E30: Camila Pereira | F30: Anlaista P&D pleno | G30: Graduação | L30: Pós-graduação
E31: Lizianne Shmeil | F31: Anlaista P&D sênior | G31: Pós-graduação | L31: Mestrado
L32: Doutorado
B35: Cronograma
B36: [anexar imagem - preferencialmente Gantt]

Sheet INOV00022
B2: PRODIET
B3: Pesquisa, Desenvolvimento & Inovação
B4: Formulário de PD&I - Ano 2023 | J4: Incentivado pela Lei do Bem | M4: TRUE
B5: - preencher somente os campos sombreados (cinza) e - adicionar cronograma no formato de imagem ao fim do formulário - preencher um deste para cada projeto de PD&I | J5: Objetiva tornar-se um Ativo | M5: FALSE
J6: Objetiva gerar patente/registro | M6: FALSE
B8: Dossiê do projeto
B9: Dados gerais para identificação e validação do projeto de PD&I
B11: Nome do projeto | E11: INOV000022 (2021 - PESQUISA CLÍNICA - INSTANTH NEO)
J12: Pesquisa básica | M12: 📑
B13: Classificação do projeto | E13: Pesquisa aplicada | J13: Pesquisa aplicada | M13: 📑
J14: Desenvolvimento experimental | M14: 📑
B15: Objetivos do projeto | E15: Este projeto tem como objetivo determinar se o uso de Instanth Neo por 6 meses em pacientes acima dos 60 anos, com diagnóstico de Comprometimento Cognitivo Leve (CCL) por Doença de Alzheimer (DA), é capaz de interferir no desempenho cognitivo, medido por testes neuropsicológicos. A motivação específica para conduzir este estudo é baseada em evidências preliminares que sugerem que certos nutrientes podem ter um efeito positivo na função cognitiva em pacientes com CCL por DA. Estudos anteriores indicaram que ácidos graxos de cadeia média, como o ácido cáprico e caprílico, juntamente com fosfatidilserina, DHA, vitaminas e minerais, podem oferecer benefícios neuroprotetores. O desenho do estudo será um ensaio clínico randomizado controlado por placebo, com um grupo de controle que não receberá o suplemento. Os pacientes serão recrutados e selecionados com base em critérios de inclusão específicos, como idade acima de 60 anos, diagnóstico confirmado de CCL por DA, e critérios de exclusão, como outras condições neurológicas graves. Os testes neuropsicológicos específicos que serão usados para avaliar o desempenho cognitivo incluem a Mini-Mental State Examination (MMSE), Teste de Fluência Verbal, e a Escala de Avaliação de Demência de Alzheimer (ADAS-Cog). Critérios claros serão estabelecidos para determinar a melhoria ou deterioração no desempenho cognitivo, baseados em mudanças estatisticamente significativas nas pontuações dos testes ao longo do período de estudo.
J16: Inovação tecnológica de produto | M16: 📑
B17: Tipo de inovação | E17: Inovação tecnológica de produto | J17: Inovação tecnológica de processo | M17: 📑
J18: Inovação tecnológica de serviços | M18: 📑
B19: Elemento inovador | E19: O Instanth Neo é um suplemento alimentar com uma combinação patenteada de nutrientes: ácido cáprico, caprílico, fosfatidilserina, DHA, e vitaminas e minerais. Esta combinação foi patenteada com o objetivo de suplementação na doença de Alzheimer, com base em pesquisas que indicam que esses nutrientes podem influenciar positivamente a função cognitiva. O mecanismo de ação proposto sugere que os ácidos graxos de cadeia média podem fornecer uma fonte alternativa de energia para o cérebro, enquanto o DHA e a fosfatidilserina contribuem para a integridade das membranas neuronais e sinápticas. Os protocolos de pesquisa clínica seguidos para avaliar a eficácia do suplemento incluem diretrizes rigorosas de ensaios clínicos, como a randomização, controle por placebo, e duplo-cego. Além da pesquisa em pacientes com DA, há planos para explorar outros usos potenciais para o suplemento, como em pacientes com diferentes tipos de declínio cognitivo e em populações que buscam melhorar a função cognitiva geral. | J19: - Não podem ser consideradas as inovações organizacionais, comerciais e de marketing
J20: Empresa ou segmento regional | M20: 📑
B21: Nível de inovação | E21: Inovador para o Mundo | J21: Inovador para o Brasil | M21: 📑
J22: Inovador para o Mundo | M22: 📑
B23: Risco tecnológico | E23: A produção do Instanth Neo apresenta desafios tecnológicos, como a necessidade de envase com nitrogênio para evitar a oxidação da formulação, devido à alta especificidade da composição (90% lipídios). Este processo está sendo implementado por meio de parceria com terceiros especializados em envase com nitrogênio. As especificações técnicas para o envase incluem a manutenção de um ambiente inerte e a monitorização constante da qualidade do nitrogênio utilizado, garantindo a ausência de oxidação dos ingredientes. Com relação às pesquisas, o principal desafio é o atraso causado pela pandemia, que impactou significativamente o cronograma da pesquisa clínica prevista para iniciar em 2021. O protocolo do estudo é robusto e inclui critérios rigorosos de inclusão/exclusão, monitorização contínua dos participantes e análise estatística detalhada dos dados coletados. Parcerias dentro da universidade, como com a UNIFESP, estão sendo estabelecidas para garantir que o desenho do estudo seja satisfatório, aproveitando a expertise acadêmica e a infraestrutura disponível.
B25: Metodologias | E25: A parceria com a UNIFESP visa avaliar a eficácia do produto AZ2021 no desfecho cognitivo de pacientes com Comprometimento Cognitivo Leve por provável Doença de Alzheimer, através de um estudo randomizado duplo-cego controlado por placebo. A UNIFESP foi escolhida como parceira devido à sua reputação e expertise em pesquisas neuropsicológicas e clínicas. Esta colaboração beneficia o estudo ao proporcionar acesso a recursos acadêmicos, expertise clínica e uma base de pacientes adequada. Os objetivos específicos da parceria incluem a realização do estudo com rigor científico e a obtenção de dados robustos sobre a eficácia do AZ2021. O desenho do estudo incluirá dois grupos de participantes, um recebendo o AZ2021 e o outro recebendo placebo, com alocação randomizada para garantir a imparcialidade dos resultados. O tamanho da amostra planejado para o estudo será baseado em cálculos de poder estatístico para detectar diferenças significativas entre os grupos. Os critérios de inclusão e exclusão serão rigorosamente aplicados para selecionar participantes adequados. A composição do produto AZ2021 incluirá os nutrientes patenteados do Instanth Neo, formulados para administração oral, enquanto o placebo será composto de ingredientes inertes que imitam a aparência e o sabor do AZ2021. Os testes de aceitação do paciente serão realizados para avaliar a palatabilidade e a adesão ao tratamento, garantindo que a nova forma de consumo seja bem recebida pelos pacientes.
B27: Equipe | E27: Nome Completo | F27: Cargo/Função | G27: Qualificação | H27: !
E28: Hellin dos Santos | F28: Gerente cientifico | G28: Mestrado | L28: Técnico | M28: 📑
E29: Ana Paula Celes | F29: Diretora Técnica | G29: Pós-graduação | L29: Graduação
L30: Pós-graduação
L31: Mestrado
L32: Doutorado
B35: Cronograma

Sheet INOV00023
B2: PRODIET
B3: Pesquisa, Desenvolvimento & Inovação
B4: Formulário de PD&I - Ano 2023 | J4: Incentivado pela Lei do Bem | M4: TRUE
B5: - preencher somente os campos sombreados (cinza) e - adicionar cronograma no formato de imagem ao fim do formulário - preencher um deste para cada projeto de PD&I | J5: Objetiva tornar-se um Ativo | M5: FALSE
J6: Objetiva gerar patente/registro | M6: FALSE
B8: Dossiê do projeto
B9: Dados gerais para identificação e validação do projeto de PD&I
B11: Nome do projeto | E11: INOV000023 (2021 - PESQUISA CLÍNICA - DIAMAX IG)
J12: Pesquisa básica | M12: 📑
B13: Classificação do projeto | E13: Pesquisa aplicada | J13: Pesquisa aplicada | M13: 📑
J14: Desenvolvimento experimental | M14: 📑
B15: Objetivos do projeto | E15: Este projeto visa comprovar os benefícios e a segurança do uso do produto DiamaxIG em pacientes com Diabetes Mellitus tipo 2 e apresentar os resultados encontrados em forma de abstracts em congressos e artigos científicos. A inovação neste contexto reside na geração de novas evidências científicas que demonstrem a eficácia e segurança do DiamaxIG, contribuindo para a literatura acadêmica e influenciando práticas clínicas. Os principais benefícios esperados incluem a redução da variabilidade glicêmica e a melhoria do controle glicêmico em pacientes com Diabetes Mellitus tipo 2. Além de apresentar os resultados em congressos e artigos científicos, o projeto tem como objetivo secundário informar e educar profissionais de saúde sobre as vantagens do uso do DiamaxIG, promovendo sua adoção clínica.
J16: Inovação tecnológica de produto | M16: 📑
B17: Tipo de inovação | E17: Inovação tecnológica de produto | J17: Inovação tecnológica de processo | M17: 📑
J18: Inovação tecnológica de serviços | M18: 📑
B19: Elemento inovador | E19: O uso de uma fórmula especializada como o DiamaxIG para controle glicêmico pode reduzir a variabilidade glicêmica, o que é crucial para melhorar a saúde de pessoas com diabetes. O DiamaxIG foi desenvolvido com nutrientes específicos que modulam a resposta glicêmica, contribuindo para uma liberação mais lenta e constante de glicose no sangue. Os mecanismos envolvidos incluem a presença de fibras solúveis e proteínas de alta qualidade que retardam a absorção de carboidratos e promovem uma liberação gradual de glicose. As principais diferenças entre o DiamaxIG e outros produtos ou tratamentos disponíveis são a formulação única que combina nutrientes específicos para um melhor controle glicêmico e a capacidade de reduzir picos e quedas bruscas de glicose. | J19: - Não podem ser consideradas as inovações organizacionais, comerciais e de marketing
J20: Empresa ou segmento regional | M20: 📑
B21: Nível de inovação | E21: Empresa ou segmento regional | J21: Inovador para o Brasil | M21: 📑
J22: Inovador para o Mundo | M22: 📑
B23: Risco tecnológico | E23: Um dos principais riscos tecnológicos é a possibilidade de a pesquisa não apresentar resultados satisfatórios em termos de redução da variabilidade glicêmica em indivíduos com diabetes mellitus tipo 2. Para mitigar este risco, a empresa planeja conduzir um estudo piloto preliminar para ajustar a metodologia e garantir a robustez do protocolo de pesquisa. Além disso, serão utilizados critérios e indicadores rigorosos para determinar o sucesso ou insucesso da pesquisa, como a redução estatisticamente significativa na variabilidade glicêmica medida por sensores contínuos de glicose.
B25: Metodologias | E25: Para controlar possíveis vieses de pesquisa, será seguido um protocolo bem estabelecido. A variabilidade glicêmica será avaliada utilizando sensores de monitoramento contínuo de glicose, que são atualmente o método mais avançado de quantificação. Os indivíduos adequados para essa pesquisa serão pacientes com Diabetes Mellitus tipo 2, selecionados com base em critérios de inclusão específicos, como idade, duração do diabetes e controle glicêmico basal. A duração da pesquisa será de 6 meses, permitindo uma avaliação abrangente dos efeitos do DiamaxIG. A pesquisa também abordará a segurança de uso do DiamaxIG, monitorando possíveis efeitos colaterais e eventos adversos. Isso garantirá que o produto não apenas seja eficaz, mas também seguro para uso a longo prazo em pacientes com diabetes. Especificações Adicionais Justificação para escolher a UNIFESP como parceira: A UNIFESP foi escolhida devido à sua reputação em pesquisa clínica e expertise em estudos neuropsicológicos e de diabetes. Objetivos específicos da parceria: Realizar um estudo rigoroso que forneça dados robustos sobre a eficácia do DiamaxIG. Tamanho da amostra planejado: Determinado com base em cálculos de poder estatístico para detectar diferenças significativas entre grupos.
B27: Equipe | E27: Nome Completo | F27: Cargo/Função | G27: Qualificação | H27: !
E28: Ana Claudia Zanini | F28: Analista Científico | G28: Mestrado | L28: Técnico | M28: 📑
E29: Hellin dos Santos | F29: Gerente Científico | G29: Mestrado | L29: Graduação
E30: Ana Paula Celes | F30: Diretora Técnica | G30: Pós-graduação | L30: Pós-graduação
L31: Mestrado
L32: Doutorado
B35: Cronograma
B36: [anexar imagem - preferencialmente Gantt]

Sheet INOV00024
B2: PRODIET
B3: Pesquisa, Desenvolvimento & Inovação
B4: Formulário de PD&I - Ano 2023 | J4: Incentivado pela Lei do Bem | M4: TRUE
B5: - preencher somente os campos sombreados (cinza) e - adicionar cronograma no formato de imagem ao fim do formulário - preencher um deste para cada projeto de PD&I | J5: Objetiva tornar-se um Ativo | M5: FALSE
J6: Objetiva gerar patente/registro | M6: FALSE
B8: Dossiê do projeto
B9: Dados gerais para identificação e validação do projeto de PD&I
B11: Nome do projeto | E11: INOV000024 (2021 - ESTUDO DE CASO)
J12: Pesquisa básica | M12: 📑
B13: Classificação do projeto | E13: Pesquisa básica | J13: Pesquisa aplicada | M13: 📑
J14: Desenvolvimento experimental | M14: 📑
B15: Objetivos do projeto | E15: A realização de estudos de caso (EC) permite à empresa comprovar os benefícios e a segurança de uso dos produtos, aumentar a participação na comunidade científica pela parceria com profissionais e apresentar os resultados em forma de abstracts em congressos e/ou artigos científicos. Além da participação na comunidade científica, a empresa espera obter benefícios específicos como a promoção de seus produtos, a validação científica das formulações, o aumento da confiança dos profissionais de saúde e dos consumidores, e a expansão do mercado. Esses estudos também visam fortalecer a reputação da empresa como líder em inovação e pesquisa na área de nutrição enteral.
J16: Inovação tecnológica de produto | M16: 📑
B17: Tipo de inovação | E17: Inovação tecnológica de serviços | J17: Inovação tecnológica de processo | M17: 📑
J18: Inovação tecnológica de serviços | M18: 📑
B19: Elemento inovador | E19: Os estudos de caso oferecem uma alternativa mais econômica em comparação com outros tipos de pesquisa clínica, como ensaios clínicos randomizados, que são mais complexos e caros. As economias de custo associadas incluem menores despesas com recrutamento de participantes, monitoramento, e infraestrutura de pesquisa. Além disso, os estudos de caso podem ser realizados com maior agilidade, permitindo a obtenção de resultados preliminares de forma mais rápida, o que é vantajoso para a tomada de decisões e ajustes nas estratégias de produto. | J19: - Não podem ser consideradas as inovações organizacionais, comerciais e de marketing
J20: Empresa ou segmento regional | M20: 📑
B21: Nível de inovação | E21: Empresa ou segmento regional | J21: Inovador para o Brasil | M21: 📑
J22: Inovador para o Mundo | M22: 📑
B23: Risco tecnológico | E23: O principal risco dos estudos de caso prospectivos é a possibilidade de não obter o resultado esperado na conduta clínica, devido à menor capacidade de controle de vieses e à possibilidade de os estudos não serem aceitos para publicação ou apresentação devido ao menor peso científico. Para mitigar esses riscos, a empresa pretende implementar medidas específicas para minimizar vieses, como a padronização de protocolos de estudo e a utilização de critérios rigorosos de seleção de casos. Além disso, estratégias para aumentar a credibilidade dos estudos incluem a colaboração com reconhecidos profissionais de saúde e pesquisadores, a publicação em periódicos de alto impacto, e a apresentação em conferências de renome.
B25: Metodologias | E25: A publicação de um relato de caso envolve a escrita de um caso clínico e a evolução sobre o uso de determinado produto do portfólio, conforme o interesse manifestado pelo profissional que acompanha o caso e a empresa. Os estudos de caso podem ser realizados de forma prospectiva, através da doação de produtos a profissionais, ou de maneira retrospectiva, por levantamento de dados de um caso já finalizado. Seleção de Casos Clínicos: Os casos clínicos são selecionados com base em critérios de relevância clínica, potencial impacto dos resultados e interesse científico. A escolha dos casos é feita em colaboração com profissionais de saúde que identificam pacientes adequados e relatam casos com potencial para gerar dados significativos. Vantagens e Desvantagens: Prospectivos: Permitem o controle e monitoramento do caso desde o início, mas podem ser mais sujeitos a vieses devido à falta de randomização e controles rigorosos. Retrospectivos: Baseiam-se em dados já coletados, o que pode reduzir custos e tempo, mas limitam a capacidade de controle sobre a qualidade dos dados e a uniformidade dos registros. Consentimento Informado: O consentimento informado dos pacientes é obtido de acordo com protocolos éticos rigorosos. Isso envolve a explicação detalhada do estudo, dos potenciais riscos e benefícios, e a garantia de que a participação é voluntária. Os pacientes assinam um termo de consentimento que é revisado e aprovado por um comitê de ética em pesquisa. Divulgação dos Resultados: Além de congressos e artigos científicos, os resultados dos estudos de caso serão divulgados através de ações de marketing e comunicação com a comunidade médica, incluindo webinars, newsletters, e materiais educativos. Esses esforços visam ampliar o alcance dos resultados e aumentar a adoção dos produtos. Cronograma: O cronograma para a realização dos estudos de caso inclui a identificação e seleção de casos, a execução dos estudos prospectivos e/ou retrospectivos, a análise dos dados, e a preparação dos manuscritos para publicação e apresentações. Prazos específicos serão definidos para cada fase do projeto, com o objetivo de apresentar os primeiros resultados em congressos relevantes e submeter artigos para revisão por pares dentro de 12 a 18 meses.
B27: Equipe | E27: Nome Completo | F27: Cargo/Função | G27: Qualificação | H27: !
E28: Ana Claudia Zanini | F28: Analista Cientifico | G28: Mestrado | L28: Técnico | M28: 📑
E29: Gabriela Faria de Oliveria | F29: Analista Cientifico | G29: Pós-graduação | L29: Graduação
E30: Hellin dos Santos | F30: Gerente Cientifico | G30: Mestrado | L30: Pós-graduação
L31: Mestrado
L32: Doutorado
B35: Cronograma
B36: [anexar imagem - preferencialmente Gantt]

Sheet INOV00027
B2: PRODIET
B3: Pesquisa, Desenvolvimento & Inovação
B4: Formulário de PD&I - Ano 2023 | J4: Incentivado pela Lei do Bem | M4: TRUE
B5: - preencher somente os campos sombreados (cinza) e - adicionar cronograma no formato de imagem ao fim do formulário - preencher um deste para cada projeto de PD&I | J5: Objetiva tornar-se um Ativo | M5: FALSE
J6: Objetiva gerar patente/registro | M6: FALSE
B8: Dossiê do projeto
B9: Dados gerais para identificação e validação do projeto de PD&I
B11: Nome do projeto | E11: INOV000027 (2022 - PROJETO PESQUISA BÁSICA)
J12: Pesquisa básica | M12: 📑
B13: Classificação do projeto | E13: Pesquisa básica | J13: Pesquisa aplicada | M13: 📑
J14: Desenvolvimento experimental | M14: 📑
B15: Objetivos do projeto | E15: A realização de pesquisas clínicas permite à empresa comprovar os benefícios e a segurança de uso dos produtos, aumentar a participação na comunidade científica através de parcerias com universidades, e apresentar os resultados em forma de abstracts em congressos e/ou artigos científicos. Além da participação na comunidade científica, a empresa espera obter benefícios específicos como a validação científica de seus produtos, aumento da credibilidade e confiança dos consumidores, potencial para melhorar a formulação de produtos existentes, e identificar novas oportunidades de mercado. Estas pesquisas também podem levar ao desenvolvimento de novas tecnologias e intervenções nutricionais, além de fortalecer as parcerias acadêmicas e de pesquisa.
J16: Inovação tecnológica de produto | M16: 📑
B17: Tipo de inovação | E17: Inovação tecnológica de serviços | J17: Inovação tecnológica de processo | M17: 📑
J18: Inovação tecnológica de serviços | M18: 📑
B19: Elemento inovador | E19: A participação em congressos e o entendimento dos conteúdos e pesquisas recentes sobre intervenções nutricionais permitem à empresa avaliar possibilidades de desenvolvimento de novos produtos, embasando a inovação. Congressos científicos são uma fonte rica de novas ideias e tendências emergentes na área de nutrição e saúde. Por exemplo, inovações como a formulação de produtos específicos para controle glicêmico, desenvolvimento de suplementos com melhor perfil nutricional para idosos, e a criação de alimentos funcionais que atendem a necessidades dietéticas especiais surgiram da inspiração obtida em congressos. Essas interações permitem à empresa estar na vanguarda da pesquisa nutricional e aplicar as últimas descobertas em seus produtos. | J19: - Não podem ser consideradas as inovações organizacionais, comerciais e de marketing
J20: Empresa ou segmento regional | M20: 📑
B21: Nível de inovação | E21: Empresa ou segmento regional | J21: Inovador para o Brasil | M21: 📑
J22: Inovador para o Mundo | M22: 📑
B23: Risco tecnológico | E23: A diversidade de temas em congressos nacionais e internacionais pode ser uma barreira, dificultando o alinhamento dos conteúdos com as inovações desejadas. A participação em congressos com pesquisas específicas é crucial para contribuir para a inovação e melhoria contínua dos produtos da Prodiet. A empresa lida com essa diversidade através de uma análise criteriosa dos programas dos congressos e pela seleção de eventos que mais se alinham com seus objetivos de pesquisa e inovação. Selecionar congressos relevantes é feito com base no impacto potencial dos temas discutidos e na presença de líderes de opinião e pesquisadores de renome na área de interesse da empresa.
B25: Metodologias | E25: A empresa planeja e entende as palestras, estudos e conteúdos compartilhados em congressos como uma estratégia para obter acesso a pesquisas relevantes. A programação prévia das pesquisas para congressos nacionais e internacionais, levando em conta as datas limites para submissão, é uma abordagem estratégica. A empresa garante que os resultados das pesquisas estejam disponíveis a tempo de serem apresentados, planejando cronogramas de pesquisa que considerem todas as etapas desde a concepção até a análise dos dados e redação dos abstracts. Programação Prévia de Pesquisas: A programação prévia envolve a definição de objetivos claros de pesquisa, a alocação de recursos adequados, e o estabelecimento de cronogramas detalhados que permitam a conclusão das pesquisas a tempo. Os critérios para a seleção de pesquisas a serem submetidas incluem a relevância científica, o alinhamento com as áreas estratégicas da empresa, e a probabilidade de aceitação pelos congressos. O processo de submissão é gerenciado através de um sistema de rastreamento de prazos, preparação de documentos e revisão por pares dentro da equipe de pesquisa para garantir a qualidade das submissões. Critérios para Seleção de Pesquisas: Relevância e originalidade científica Impacto potencial na área de nutrição e saúde Alinhamento com os objetivos estratégicos da empresa Qualidade e robustez metodológica Potencial para gerar dados publicáveis em revistas de alto impacto Processo de Submissão: O processo de submissão é rigorosamente gerenciado, começando com a identificação de congressos relevantes e a leitura cuidadosa dos requisitos de submissão. Os pesquisadores preparam abstracts e apresentações de acordo com as diretrizes do congresso, seguidos por revisões internas para garantir clareza e precisão. As submissões são acompanhadas até a aceitação final e preparação para a apresentação no evento. Avaliação de Conteúdos em Congressos: A empresa mantém uma equipe dedicada para revisar os programas dos congressos e selecionar as palestras e sessões mais relevantes. Participantes designados relatam as descobertas e insights obtidos, que são discutidos em reuniões de equipe para identificar oportunidades de aplicação prática. Benefícios da Participação em Congressos: Atualização sobre as últimas tendências e avanços científicos Networking com pesquisadores e profissionais da área Identificação de oportunidades de colaboração Inspiração para novas linhas de pesquisa e desenvolvimento de produtos
B27: Equipe | E27: Nome Completo | F27: Cargo/Função | G27: Qualificação | H27: !
E28: Gabriela Faria de Oliveira | F28: Analista Científico | G28: Pós-graduação | L28: Técnico | M28: 📑
E29: Ana Cláudia Zanini | F29: Analista Científico | G29: Mestrado | L29: Graduação
E30: Hellin dos Santos | F30: Gerente Científico | G30: Mestrado | L30: Pós-graduação
E31: Ana Paula M Celes | F31: Diretora Técnica | G31: Pós-graduação | L31: Mestrado
L32: Doutorado
B35: Cronograma
B36: [anexar imagem - preferencialmente Gantt]

Sheet INOV00031
B2: PRODIET
B3: Pesquisa, Desenvolvimento & Inovação
B4: Formulário de PD&I - Ano 2023 | J4: Incentivado pela Lei do Bem | M4: TRUE
B5: - preencher somente os campos sombreados (cinza) e - adicionar cronograma no formato de imagem ao fim do formulário - preencher um deste para cada projeto de PD&I | J5: Objetiva tornar-se um Ativo | M5: FALSE
J6: Objetiva gerar patente/registro | M6: FALSE
B8: Dossiê do projeto
B9: Dados gerais para identificação e validação do projeto de PD&I
B11: Nome do projeto | E11: INOV000031 (2021 - ENERGYZIP SÊNIOR) | O11: Comentário
J12: Pesquisa básica | M12: 📑
B13: Classificação do projeto | E13: Desenvolvimento experimental | J13: Pesquisa aplicada | M13: 📑
J14: Desenvolvimento experimental | M14: 📑
B15: Objetivos do projeto | E15: O objetivo do projeto é desenvolver um produto competitivo para venda em processos de licitação, além de criar um produto específico para idosos, que é o foco dos recentes lançamentos dos produtos Prodiet. Este novo produto, denominado Energyzip Sênior, será implementado tanto no mercado público quanto privado, com ênfase em licitações governamentais e em estabelecimentos de saúde que atendem a população idosa. a) O produto será implementado no mercado de nutrição clínica, com foco em instituições de saúde, lares para idosos, e programas governamentais de suporte nutricional. b) Exemplos de produtos lançados recentemente pelo Prodiet incluem a linha Diamax para controle glicêmico e a linha 100% Soja para consumidores com alergias alimentares. c) O Energyzip Sênior atenderá às necessidades específicas dos pacientes idosos, oferecendo uma fórmula equilibrada com nutrientes essenciais para a saúde óssea, muscular, e cognitiva, além de ser fácil de digerir e absorver, diferenciando-se dos outros produtos Prodiet por ser totalmente voltado para as exigências nutricionais dos idosos. | O15: Comentário
J16: Inovação tecnológica de produto | M16: 📑
B17: Tipo de inovação | E17: Inovação tecnológica de produto | J17: Inovação tecnológica de processo | M17: 📑
J18: Inovação tecnológica de serviços | M18: 📑
B19: Elemento inovador | E19: O Energyzip Sênior é um produto desenvolvido exclusivamente para pacientes idosos, expandindo o público-alvo dos produtos Prodiet. Nenhum outro produto do portfólio atual é dedicado especificamente para este público. a) A inovação inclui tanto a criação de novos produtos específicos para idosos quanto a modificação de produtos existentes para melhor atender às necessidades desta faixa etária. b) Produtos para idosos se diferenciam dos produtos para jovens e adultos por terem uma formulação adaptada às necessidades nutricionais dos idosos, como maior teor de proteínas de fácil digestão, vitaminas e minerais essenciais para a saúde óssea e muscular, e a inclusão de nutrientes que auxiliam na saúde cognitiva. c) Os principais benefícios que tornam o Energyzip Sênior exclusivo para o público idoso incluem uma formulação rica em proteínas de alta qualidade, baixa em lactose, fortificada com vitaminas e minerais essenciais para idosos, e de fácil digestão, garantindo melhor absorção dos nutrientes. | J19: - Não podem ser consideradas as inovações organizacionais, comerciais e de marketing | O19: Comentário
J20: Empresa ou segmento regional | M20: 📑
B21: Nível de inovação | E21: Empresa ou segmento regional | J21: Inovador para o Brasil | M21: 📑
J22: Inovador para o Mundo | M22: 📑
B23: Risco tecnológico | E23: Um dos principais desafios tecnológicos é desenvolver uma fórmula isenta de lactose e com custo viável para produção em larga escala. a) Dados mostram que uma significativa porcentagem de idosos apresenta intolerância à lactose, necessitando de produtos específicos que não contenham este componente. b) O plano inclui a produção de variantes do Energyzip Sênior, tanto isentas de lactose quanto com lactose, para atender diferentes necessidades e preferências do mercado. c) A empresa planeja garantir que a nova fórmula do Energyzip Sênior seja isenta de lactose e mantenha um custo viável através da utilização de ingredientes alternativos de menor custo e processos de produção eficientes, como a substituição do leite integral zero lactose por leite integral com lactose para variantes específicas. d) Estratégias para otimizar o custo sem comprometer a qualidade incluem a reformulação do mix de vitaminas e minerais, a substituição de ingredientes de maior custo, e a negociação com fornecedores para obter melhores preços. | O23: Comentário
B25: Metodologias | E25: A metodologia inclui a revisão da informação nutricional para reformulação do mix de vitaminas e minerais, com a retirada de componentes de maior custo como o cloreto de cálcio, e a alteração de ingredientes para versões mais econômicas. a) Dados mostram que as necessidades nutricionais mais importantes para idosos incluem proteínas de alta qualidade, vitamina D, cálcio, vitamina B12, e fibras para manter a saúde óssea, muscular e cognitiva. b) Estudos e feedback de clientes indicam que a retirada de fontes de maior custo pode ter um impacto positivo para o cliente, mantendo a eficácia nutricional enquanto reduz o custo final do produto. Cronograma: Primeiros 3 meses: Seleção de ingredientes, desenvolvimento de fórmula inicial e testes de estabilidade. 4 a 6 meses: Realização de testes sensoriais e ajustes de fórmula com base no feedback. 6 a 9 meses: Produção piloto e validação da cadeia de fornecimento. 9 a 12 meses: Preparação de documentação para submissão a congressos e publicação de resultados iniciais. Divulgação dos Resultados: Além de congressos e artigos científicos, os resultados dos estudos de caso serão divulgados através de campanhas de marketing direcionadas, webinars educativos, e comunicações com a comunidade médica, para maximizar a visibilidade e adoção do Energyzip Sênior. | O25: Comentário
B27: Equipe | E27: Nome Completo | F27: Cargo/Função | G27: Qualificação | H27: !
E28: Camila Mendes Pereira | F28: Analista de P&D | G28: Graduação | L28: Técnico | M28: 📑
E29: Gabriela Faria de Oliveira | F29: Analista Científico | G29: Pós-graduação | L29: Graduação
E30: Luciana Dutra | F30: Gerente Técnica | G30: Pós-graduação | L30: Pós-graduação
E31: Juliana Lamas Roberto | F31: Especialista de Estudo de Estabilidade | G31: Mestrado | L31: Mestrado
E32: Hellin dos Santos | F32: Gerente Científico | G32: Mestrado | L32: Doutorado
E33: Ana Paula Celes | F33: Diretora Técnica | G33: Pós-graduação
B35: Cronograma
B36: [anexar imagem - preferencialmente Gantt]

Sheet INOV00034
B2: PRODIET
B3: Pesquisa, Desenvolvimento & Inovação
B4: Formulário de PD&I - Ano 2023 | J4: Incentivado pela Lei do Bem | M4: TRUE
B5: - preencher somente os campos sombreados (cinza) e - adicionar cronograma no formato de imagem ao fim do formulário - preencher um deste para cada projeto de PD&I | J5: Objetiva tornar-se um Ativo | M5: FALSE
J6: Objetiva gerar patente/registro | M6: FALSE
B8: Dossiê do projeto
B9: Dados gerais para identificação e validação do projeto de PD&I
B11: Nome do projeto | E11: INOV000034 (2023 - PESQUISA CLÍNICA - CARBOCH)
J12: Pesquisa básica | M12: 📑
B13: Classificação do projeto | E13: Pesquisa aplicada | J13: Pesquisa aplicada | M13: 📑
J14: Desenvolvimento experimental | M14: 📑
B15: Objetivos do projeto | E15: Avaliar o impacto do uso do suplemento de carboidrato em sachê na abreviação do jejum pré-operatório sobre desfechos clínicos e biomarcadores em pacientes submetidos a cirurgias eletivas ASA I e II. A justificativa para esta avaliação está baseada em evidências científicas e clínicas que indicam que a abreviação do jejum pré-operatório pode melhorar o bem-estar dos pacientes, reduzir complicações pós-operatórias e melhorar a recuperação. Estudos anteriores sugerem que a manutenção de um estado nutricional adequado até poucas horas antes da cirurgia pode reduzir a resposta inflamatória, melhorar a função imunológica e preservar a massa muscular.
J16: Inovação tecnológica de produto | M16: 📑
B17: Tipo de inovação | E17: Inovação tecnológica de produto | J17: Inovação tecnológica de processo | M17: 📑
J18: Inovação tecnológica de serviços | M18: 📑
B19: Elemento inovador | E19: A aplicação clínica de um suplemento produzido pela indústria brasileira visa avaliar o efeito da abreviação do tempo de jejum pré-operatório na satisfação, bem-estar e evolução clínica dos pacientes submetidos a procedimentos cirúrgicos eletivos. Além disso, busca-se reduzir sintomas desagradáveis relacionados ao jejum, como fome e sede. a) O suplemento produzido pela indústria brasileira se diferencia de outras abordagens por ser especificamente formulado para uso pré-operatório, contendo uma combinação ideal de carboidratos de fácil digestão que fornecem energia rápida sem sobrecarregar o sistema digestivo. A formulação pode ser mais adequada e economicamente viável em comparação com produtos importados ou generalistas. b) Os benefícios esperados do suplemento incluem maior satisfação e bem-estar dos pacientes, redução dos sintomas de fome e sede, e potencial melhora na evolução clínica, como menor tempo de recuperação e redução de complicações pós-operatórias. c) Reduzir sintomas desagradáveis relacionados ao jejum, como fome e sede, é crucial para o conforto e bem-estar dos pacientes, podendo também contribuir para uma melhor adesão às instruções pré-operatórias e reduzir a ansiedade | J19: - Não podem ser consideradas as inovações organizacionais, comerciais e de marketing
J20: Empresa ou segmento regional | M20: 📑
B21: Nível de inovação | E21: Inovador para o Brasil | J21: Inovador para o Brasil | M21: 📑
J22: Inovador para o Mundo | M22: 📑
B23: Risco tecnológico | E23: Os efeitos sobre a glicemia de pacientes submetidos a cirurgias eletivas são um risco potencial que deve ser monitorado cuidadosamente. a) Os riscos potenciais incluem hiperglicemia ou hipoglicemia perioperatória, que podem complicar a gestão clínica dos pacientes e aumentar o risco de complicações cirúrgicas. b) Esses riscos serão monitorados através de medições regulares da glicemia antes, durante e após a administração do suplemento e a cirurgia. O estudo incluirá protocolos rigorosos de monitoramento glicêmico e planos de ação para responder a quaisquer alterações significativas nos níveis de glicose.
B25: Metodologias | E25: A metodologia envolve colaboração com anestesiologistas e pesquisadores parceiros, doação do produto investigacional, subvenção parcial para biomarcadores e consultoria técnica para elaboração do projeto de pesquisa. a) O anestesiologista/pesquisador parceiro desempenha um papel crucial na condução do estudo, sendo responsável pela administração do suplemento, monitoramento dos pacientes e coleta de dados. Esta colaboração é fundamental para assegurar que o estudo seja conduzido de acordo com os padrões clínicos e éticos. b) A subvenção parcial para biomarcadores será utilizada para medir indicadores relevantes como níveis de glicose, marcadores inflamatórios (por exemplo, proteína C-reativa), e indicadores de estresse metabólico e imunológico. Esses biomarcadores são essenciais para avaliar o impacto fisiológico do suplemento e correlacionar com os desfechos clínicos. c) A empresa planeja avaliar o impacto do estudo na prática clínica através de uma análise abrangente dos resultados obtidos, incluindo dados clínicos e feedback dos pacientes. A intenção é publicar os resultados em revistas científicas e apresentar em congressos para disseminar os achados e influenciar as práticas clínicas em cirurgias eletivas.
B27: Equipe | E27: Nome Completo | F27: Cargo/Função | G27: Qualificação | H27: !
E28: Vaneisse C L Monteiro | F28: Analista Científico | G28: Doutorado | L28: Técnico | M28: 📑
E29: Gabriela Faria de Oliveira | F29: Analista Científico | G29: Pós-graduação | L29: Graduação
E30: Hellin dos Santos | F30: Gerente Científico | G30: Mestrado | L30: Pós-graduação
E31: Ana Paula M Celes | F31: Diretora Técnica | G31: Pós-graduação | L31: Mestrado
L32: Doutorado
B35: Cronograma
B36: [anexar imagem - preferencialmente Gantt]

Sheet INOV00035
B2: PRODIET
B3: Pesquisa, Desenvolvimento & Inovação
B4: Formulário de PD&I - Ano 2023 | J4: Incentivado pela Lei do Bem | M4: TRUE
B5: - preencher somente os campos sombreados (cinza) e - adicionar cronograma no formato de imagem ao fim do formulário - preencher um deste para cada projeto de PD&I | J5: Objetiva tornar-se um Ativo | M5: FALSE
J6: Objetiva gerar patente/registro | M6: FALSE
B8: Dossiê do projeto
B9: Dados gerais para identificação e validação do projeto de PD&I
B11: Nome do projeto | E11: INOV000035 (2023 - PESQUISA CLÍNICA - CICATRIZAÇÃO)
J12: Pesquisa básica | M12: 📑
B13: Classificação do projeto | E13: Pesquisa aplicada | J13: Pesquisa aplicada | M13: 📑
J14: Desenvolvimento experimental | M14: 📑
B15: Objetivos do projeto | E15: Avaliar o impacto do uso do suplemento em pó para cicatrização no tempo de cicatrização e evolução da ferida. A motivação por trás desta avaliação é baseada em evidências que sugerem que uma nutrição adequada pode acelerar o processo de cicatrização, melhorar a qualidade da cicatrização e reduzir o risco de complicações. O suplemento foi formulado para fornecer nutrientes essenciais que suportam os processos biológicos envolvidos na cicatrização de feridas.
J16: Inovação tecnológica de produto | M16: 📑
B17: Tipo de inovação | E17: Inovação tecnológica de produto | J17: Inovação tecnológica de processo | M17: 📑
J18: Inovação tecnológica de serviços | M18: 📑
B19: Elemento inovador | E19: A combinação de peptídeos de colágeno, arginina, micronutrientes chave para cicatrização e isomaltulose para controle glicêmico é inovadora e se diferencia de outros produtos disponíveis para cicatrização. a) Esta combinação se diferencia por oferecer um perfil nutricional completo e balanceado que não apenas suporta a síntese de colágeno e outros componentes da matriz extracelular, mas também fornece energia de liberação lenta para controle glicêmico, essencial para pacientes com diabetes ou outras condições que afetam a cicatrização. Produtos concorrentes podem não fornecer uma combinação tão específica e sinérgica de nutrientes. b) Os benefícios esperados incluem uma cicatrização mais rápida e eficiente, melhoria na qualidade da cicatriz, redução de inflamação e infecção, e controle melhorado dos níveis de glicose, o que é crucial para pacientes com condições crônicas como diabetes. | J19: - Não podem ser consideradas as inovações organizacionais, comerciais e de marketing
J20: Empresa ou segmento regional | M20: 📑
B21: Nível de inovação | E21: Inovador para o Mundo | J21: Inovador para o Brasil | M21: 📑
J22: Inovador para o Mundo | M22: 📑
B23: Risco tecnológico | E23: Um risco tecnológico significativo é a possibilidade de o suplemento não alcançar os resultados clínicos esperados, como a redução significativa no tempo de cicatrização ou melhorias notáveis na evolução da ferida. a) O resultado esperado na conduta clínica inclui uma redução no tempo de cicatrização e uma melhoria na qualidade da cicatrização, como menos infecção, menos inflamação e melhor formação de tecido. Este risco está sendo gerenciado através de um protocolo rigoroso de estudo clínico que inclui critérios de inclusão e exclusão bem definidos, monitoramento contínuo dos pacientes e análise detalhada dos dados coletados para garantir a robustez dos resultados.
B25: Metodologias | E25: O projeto inclui a doação do produto investigacional, consultoria técnica, e análise de biomarcadores e escalas clínicas para avaliar o impacto do suplemento na cicatrização. a) O processo de doação do produto investigacional aos pacientes participantes será gerido através de uma colaboração com centros de saúde e hospitais. Pacientes elegíveis serão identificados e recrutados para o estudo, e o suplemento será fornecido gratuitamente durante o período do estudo. A administração do suplemento será monitorada por profissionais de saúde para garantir adesão e segurança. b) Os biomarcadores que serão utilizados para avaliar o impacto do suplemento incluem níveis de proteínas inflamatórias (como CRP), marcadores de formação de colágeno, e glicemia. As escalas clínicas incluem o PUSH Tool (Pressure Ulcer Scale for Healing) para avaliar a evolução da ferida, e escalas de dor e qualidade de vida para monitorar o bem-estar dos pacientes. Estas medições serão realizadas em intervalos regulares durante o estudo para acompanhar a progressão da cicatrização e a eficácia do suplemento.
B27: Equipe | E27: Nome Completo | F27: Cargo/Função | G27: Qualificação | H27: !
E28: Gabriela Faria de Oliveria | F28: Analista Cientifico | G28: Pós-graduação | L28: Técnico | M28: 📑
E29: Hellin dos Santos | F29: Gerente Cientifico | G29: Mestrado | L29: Graduação
E30: Vaneisse C L Monteiro | F30: Analista Cientifico | G30: Doutorado | L30: Pós-graduação
L31: Mestrado
L32: Doutorado
B35: Cronograma
B36: [anexar imagem - preferencialmente Gantt]

Sheet INOV00036
B2: PRODIET
B3: Pesquisa, Desenvolvimento & Inovação
B4: Formulário de PD&I - Ano 2023 | J4: Incentivado pela Lei do Bem | M4: TRUE
B5: - preencher somente os campos sombreados (cinza) e - adicionar cronograma no formato de imagem ao fim do formulário - preencher um deste para cada projeto de PD&I | J5: Objetiva tornar-se um Ativo | M5: FALSE
J6: Objetiva gerar patente/registro | M6: FALSE
B8: Dossiê do projeto
B9: Dados gerais para identificação e validação do projeto de PD&I
B11: Nome do projeto | E11: INOV000036 (2023 - PESQUISA APLICADA - ARTESANAL)
J12: Pesquisa básica | M12: 📑
B13: Classificação do projeto | E13: Pesquisa aplicada | J13: Pesquisa aplicada | M13: 📑
J14: Desenvolvimento experimental | M14: 📑
B15: Objetivos do projeto | E15: Avaliar a composição físico-química de dietas enterais artesanais com e sem o uso de suplementação específica, por meio de análises laboratoriais. A motivação por trás dessa avaliação é garantir que as dietas enterais artesanais ofereçam um perfil nutricional adequado e seguro para os pacientes, comparável ao das dietas industrializadas. Os objetivos clínicos e de pesquisa incluem determinar a qualidade nutricional das dietas, identificar possíveis deficiências ou excessos de nutrientes e avaliar a segurança alimentar. Este estudo busca proporcionar dados que possam melhorar a formulação das dietas artesanais e garantir que elas atendam às necessidades nutricionais dos pacientes.
J16: Inovação tecnológica de produto | M16: 📑
B17: Tipo de inovação | E17: Inovação tecnológica de produto | J17: Inovação tecnológica de processo | M17: 📑
J18: Inovação tecnológica de serviços | M18: 📑
B19: Elemento inovador | E19: A utilização de elementos presentes em dietas artesanais com oferta de micronutrientes e segurança é o foco inovador deste projeto. a) A oferta de micronutrientes e a segurança alimentar são abordadas como elementos inovadores através da incorporação de suplementos específicos que garantem a presença de todos os nutrientes essenciais nas quantidades recomendadas. O valor agregado pela inclusão desses elementos nas dietas artesanais reside na melhoria da qualidade nutricional, garantindo que os pacientes recebam uma dieta balanceada que suporte sua recuperação e bem-estar. Além disso, a segurança alimentar é aumentada pela padronização e controle da composição das dietas, reduzindo o risco de contaminações e desequilíbrios nutricionais. | J19: - Não podem ser consideradas as inovações organizacionais, comerciais e de marketing
J20: Empresa ou segmento regional | M20: 📑
B21: Nível de inovação | E21: Inovador para o Brasil | J21: Inovador para o Brasil | M21: 📑
J22: Inovador para o Mundo | M22: 📑
B23: Risco tecnológico | E23: Um risco potencial é a possibilidade de não observar diferenças significativas na composição físico-química de dietas enterais artesanais com e sem o uso de suplementação específica. a) Para gerenciar esse risco, o estudo será desenhado com um tamanho de amostra adequado e análise estatística rigorosa para detectar pequenas diferenças na composição. Serão considerados cenários alternativos, como a avaliação de outros desfechos clínicos ou a reavaliação da composição das dietas e dos suplementos utilizados, caso os resultados não sejam significativos. b) Se os resultados não forem significativos, o estudo poderá explorar outras variáveis, como a palatabilidade, a aceitação pelos pacientes e a relação custo-benefício, para fornecer recomendações práticas sobre o uso de suplementos em dietas artesanais.
B25: Metodologias | E25: A análise química das dietas incluirá calorias, proteínas, carboidratos, gorduras, fibras, ferro, cobre, cromo, ácido fólico, ácido pantotênico e colina. a) As análises laboratoriais específicas serão realizadas utilizando técnicas como cromatografia líquida de alta eficiência (HPLC), espectrometria de absorção atômica (AAS) e análise de composição proximal. Estas análises serão conduzidas seguindo protocolos padronizados e critérios de referência estabelecidos por diretrizes nutricionais internacionais. b) A amostragem das dietas enterais artesanais será realizada de forma sistemática, coletando amostras representativas de diferentes preparações e locais de produção. Isso garantirá que as amostras reflitam a variabilidade das dietas consumidas pelos pacientes. c) Os padrões ou referências utilizados para determinar a composição nutricional ideal das dietas enterais artesanais incluirão diretrizes da Organização Mundial da Saúde (OMS), Dietary Reference Intakes (DRIs) e outras regulamentações específicas para nutrição enteral. Estas diretrizes fornecem as recomendações sobre os níveis adequados de nutrientes para diferentes grupos populacionais. d) A relação entre os resultados da análise físico-química e os desfechos clínicos dos pacientes será estabelecida através da comparação dos dados nutricionais com indicadores de saúde dos pacientes, como tempo de cicatrização, recuperação pós-operatória, e indicadores de estado nutricional (IMC, níveis séricos de nutrientes). Os resultados serão interpretados em um contexto clínico para fornecer recomendações práticas sobre a formulação e suplementação de dietas enterais artesanais.
B27: Equipe | E27: Nome Completo | F27: Cargo/Função | G27: Qualificação | H27: !
E28: Gabriela Faria de Oliveria | F28: Analista Cientifico | G28: Pós-graduação | L28: Técnico | M28: 📑
E29: Hellin dos Santos | F29: Gerente Cientifico | G29: Mestrado | L29: Graduação
E30: Vaneisse C L Monteiro | F30: Analista Cientifico | G30: Doutorado | L30: Pós-graduação
L31: Mestrado
L32: Doutorado
B35: Cronograma
B36: [anexar imagem - preferencialmente Gantt]

Sheet INOV00037
B2: PRODIET
B3: Pesquisa, Desenvolvimento & Inovação
B4: Formulário de PD&I - Ano 2023 | J4: Incentivado pela Lei do Bem | M4: TRUE
B5: - preencher somente os campos sombreados (cinza) e - adicionar cronograma no formato de imagem ao fim do formulário - preencher um deste para cada projeto de PD&I | J5: Objetiva tornar-se um Ativo | M5: FALSE
J6: Objetiva gerar patente/registro | M6: FALSE
B8: Dossiê do projeto
B9: Dados gerais para identificação e validação do projeto de PD&I
B11: Nome do projeto | E11: INOV000037 (2023 - PESQUISA CLÍNICA - IMMAX)
J12: Pesquisa básica | M12: 📑
B13: Classificação do projeto | E13: Pesquisa aplicada | J13: Pesquisa aplicada | M13: 📑
J14: Desenvolvimento experimental | M14: 📑
B15: Objetivos do projeto | E15: O objetivo do projeto é comprovar os benefícios e a segurança do uso do produto Immax em uma amostra de indivíduos com câncer colorretal e apresentar os resultados em forma de abstracts em congressos e artigos científicos. Além da comprovação da segurança, o projeto espera demonstrar benefícios específicos como a redução da perda de massa muscular, melhora na qualidade de vida, aumento da massa muscular, melhora do estado nutricional geral e potencial melhora na resposta ao tratamento oncológico.
J16: Inovação tecnológica de produto | M16: 📑
B17: Tipo de inovação | E17: Inovação tecnológica de produto | J17: Inovação tecnológica de processo | M17: 📑
J18: Inovação tecnológica de serviços | M18: 📑
B19: Elemento inovador | E19: O uso de uma fórmula especializada para pacientes oncológicos, como o Immax, pode reduzir a perda de massa muscular e/ou estimular o aumento da massa muscular, o que é crucial devido ao grande impacto na saúde e qualidade de vida das pessoas com câncer. a) A fórmula especializada se diferencia de outras abordagens ou produtos por conter uma combinação otimizada de nutrientes essenciais especificamente formulados para atender às necessidades nutricionais de pacientes oncológicos. Isso pode incluir proteínas de alta qualidade, aminoácidos essenciais, ácidos graxos ômega-3, vitaminas, minerais e compostos bioativos que auxiliam na manutenção e ganho de massa muscular. b) Os benefícios potenciais dessa fórmula incluem a preservação da massa muscular, melhora da força física e funcionalidade, redução da inflamação e catabolismo, melhoria da qualidade de vida, e possivelmente uma melhor resposta aos tratamentos oncológicos devido ao melhor estado nutricional. | J19: - Não podem ser consideradas as inovações organizacionais, comerciais e de marketing
J20: Empresa ou segmento regional | M20: 📑
B21: Nível de inovação | E21: Empresa ou segmento regional | J21: Inovador para o Brasil | M21: 📑
J22: Inovador para o Mundo | M22: 📑
B23: Risco tecnológico | E23: O principal risco é a pesquisa não apresentar resultados satisfatórios em termos de redução da perda de massa muscular ou aumento da massa muscular em indivíduos com câncer colorretal. a) Esse risco está sendo gerenciado através de um desenho de estudo robusto, que inclui um tamanho de amostra adequado, critérios rigorosos de inclusão e exclusão, e o uso de métodos precisos de avaliação de massa muscular. Em caso de resultados negativos, cenários alternativos incluem a reavaliação da dose ou composição do suplemento, ou a consideração de subgrupos específicos de pacientes que possam se beneficiar mais claramente do produto.
B25: Metodologias | E25: Para controlar possíveis vieses de pesquisa, o projeto segue um protocolo bem estabelecido. A massa muscular será avaliada por meio de densitometria óssea (DXA), que é um dos melhores métodos de quantificação sem exposição à radiação excessiva. a) Para garantir a validade dos resultados e controlar possíveis vieses, medidas incluem a randomização dos participantes, duplo-cego (onde aplicável), e controle por placebo. Além disso, serão utilizadas técnicas padronizadas para coleta de dados e análise estatística rigorosa para minimizar a influência de fatores externos e vieses de seleção. b) A estratégia de amostragem envolve o recrutamento de pacientes com diagnóstico confirmado de câncer colorretal que estejam em tratamento ativo ou em fase de recuperação pós-tratamento. O tamanho da amostra foi determinado com base em cálculos de poder estatístico para garantir que o estudo tenha força suficiente para detectar diferenças significativas nos desfechos de interesse, como a mudança na massa muscular.
B27: Equipe | E27: Nome Completo | F27: Cargo/Função | G27: Qualificação | H27: !
E28: Ana Claudia Zanini | F28: Analista Científico | G28: Mestrado | L28: Técnico | M28: 📑
E29: Hellin dos Santos | F29: Gerente Científico | G29: Mestrado | L29: Graduação
E30: Ana Paula Celes | F30: Diretora Técnica | G30: Pós-graduação | L30: Pós-graduação
L31: Mestrado
L32: Doutorado
B35: Cronograma
B36: [anexar imagem - preferencialmente Gantt]

Sheet INOV00038
B2: PRODIET
B3: Pesquisa, Desenvolvimento & Inovação
B4: Formulário de PD&I - Ano 2023 | J4: Incentivado pela Lei do Bem | M4: TRUE
B5: - preencher somente os campos sombreados (cinza) e - adicionar cronograma no formato de imagem ao fim do formulário - preencher um deste para cada projeto de PD&I | J5: Objetiva tornar-se um Ativo | M5: FALSE
J6: Objetiva gerar patente/registro | M6: FALSE
B8: Dossiê do projeto
B9: Dados gerais para identificação e validação do projeto de PD&I
B11: Nome do projeto | E11: INOV000038 (2023 - PESQUISA CLÍNICA - PEPTIMAX)
J12: Pesquisa básica | M12: 📑
B13: Classificação do projeto | E13: Pesquisa aplicada | J13: Pesquisa aplicada | M13: 📑
J14: Desenvolvimento experimental | M14: 📑
B15: Objetivos do projeto | E15: Avaliar o impacto do uso da fórmula oligomérica Peptimax em pacientes com sintomas disabsortivos, após utilização de fórmulas poliméricas e oligoméricas em sistema fechado. A motivação por trás dessa avaliação é entender como a fórmula Peptimax pode melhorar a absorção de nutrientes e aliviar sintomas em pacientes que não responderam adequadamente a outras fórmulas. Esses pacientes muitas vezes apresentam necessidades clínicas não atendidas, como má absorção de nutrientes, perda de peso, e desnutrição, que podem comprometer sua recuperação e qualidade de vida.
J16: Inovação tecnológica de produto | M16: 📑
B17: Tipo de inovação | E17: Inovação tecnológica de produto | J17: Inovação tecnológica de processo | M17: 📑
J18: Inovação tecnológica de serviços | M18: 📑
B19: Elemento inovador | E19: O uso da fórmula Peptimax em pacientes refratários a outros tratamentos é inovador porque oferece uma alternativa especializada para uma população de pacientes que não obtiveram benefícios de outras abordagens nutricionais. a) A fórmula Peptimax se diferencia de abordagens anteriores por ser oligomérica, o que significa que seus nutrientes estão em formas parcialmente digeridas, facilitando a absorção em pacientes com comprometimento da capacidade digestiva e absortiva. As expectativas em relação a essa população de pacientes incluem melhora na absorção de nutrientes, estabilização do peso, redução dos sintomas disabsortivos e uma melhora geral no estado nutricional e na qualidade de vida. | J19: - Não podem ser consideradas as inovações organizacionais, comerciais e de marketing
J20: Empresa ou segmento regional | M20: 📑
B21: Nível de inovação | E21: Inovador para o Brasil | J21: Inovador para o Brasil | M21: 📑
J22: Inovador para o Mundo | M22: 📑
B23: Risco tecnológico | E23: O principal risco dos estudos de caso prospectivos é a possibilidade de não obter o resultado esperado na conduta clínica, devido à variabilidade individual dos pacientes e à natureza menos controlada desses estudos. a) O risco de não obter o resultado esperado está sendo gerenciado através de uma cuidadosa seleção dos pacientes, utilização de protocolos padronizados e monitoramento rigoroso durante o estudo. Além disso, serão implementadas análises estatísticas apropriadas para identificar qualquer tendência ou benefício mesmo que os resultados não sejam estatisticamente significativos. b) Se os resultados não forem satisfatórios, estratégias alternativas incluem a reavaliação dos critérios de inclusão dos pacientes, ajustes na formulação do Peptimax, ou o desenvolvimento de subgrupos específicos de pacientes que possam se beneficiar mais do produto.
B25: Metodologias | E25: O estudo será conduzido como uma série de casos clínicos prospectivos, com doação de produtos Peptimax aos pacientes participantes. a) A série de casos clínicos prospectivos será conduzida através da identificação e recrutamento de pacientes com sintomas disabsortivos que não responderam adequadamente a fórmulas poliméricas e oligoméricas padrão. Os critérios de seleção incluirão diagnósticos de má absorção, histórico de uso de outras fórmulas sem sucesso, e a capacidade de dar consentimento informado. Os pacientes serão monitorados de perto para avaliar a resposta à fórmula Peptimax, incluindo parâmetros como absorção de nutrientes, ganho de peso, e melhora dos sintomas disabsortivos. b) O processo de doação dos produtos Peptimax aos pacientes participantes envolverá parcerias com centros de saúde e hospitais. A empresa fornecerá a fórmula gratuitamente durante o período do estudo, garantindo que todos os participantes tenham acesso ao suplemento necessário. A administração do Peptimax será supervisionada por profissionais de saúde, que também serão responsáveis pela coleta de dados e monitoramento do progresso dos pacientes.
B27: Equipe | E27: Nome Completo | F27: Cargo/Função | G27: Qualificação | H27: !
E28: Hellin dos Santos | F28: Gerente Cientifico | G28: Mestrado | L28: Técnico | M28: 📑
E29: Vaneisse C L Monteiro | F29: Analista Científico | G29: Doutorado | L29: Graduação
L30: Pós-graduação
L31: Mestrado
L32: Doutorado
B35: Cronograma
B36: [anexar imagem - preferencialmente Gantt]

Sheet INOV00039
B2: PRODIET
B3: Pesquisa, Desenvolvimento & Inovação
B4: Formulário de PD&I - Ano 2023 | J4: Incentivado pela Lei do Bem | M4: TRUE
B5: - preencher somente os campos sombreados (cinza) e - adicionar cronograma no formato de imagem ao fim do formulário - preencher um deste para cada projeto de PD&I | J5: Objetiva tornar-se um Ativo | M5: FALSE
J6: Objetiva gerar patente/registro | M6: FALSE
B8: Dossiê do projeto
B9: Dados gerais para identificação e validação do projeto de PD&I
B11: Nome do projeto | E11: INOV000039 (2023 - PESQUISA ÍNDICE GLICÊMICO - DIAMAX IN / SF UTI)
J12: Pesquisa básica | M12: 📑
B13: Classificação do projeto | E13: Pesquisa aplicada | J13: Pesquisa aplicada | M13: 📑
J14: Desenvolvimento experimental | M14: 📑
B15: Objetivos do projeto | E15: Determinar o índice glicêmico de duas fórmulas especializadas. Além de comprovar o baixo índice glicêmico, o projeto espera demonstrar benefícios específicos em relação às fórmulas especializadas para pacientes com diabetes mellitus e hiperglicemia por estresse, como melhor controle glicêmico, redução de picos de glicose pós-prandiais e melhora na gestão geral da condição diabética.
J16: Inovação tecnológica de produto | M16: 📑
B17: Tipo de inovação | E17: Inovação tecnológica de produto | J17: Inovação tecnológica de processo | M17: 📑
J18: Inovação tecnológica de serviços | M18: 📑
B19: Elemento inovador | E19: Fórmulas especializadas com baixo índice glicêmico apresentam benefícios significativos para pacientes com diabetes mellitus e hiperglicemia por estresse. A comprovação do baixo índice glicêmico dessas fórmulas embasaria a prescrição para esses grupos populacionais. a) A prescrição dessas fórmulas pode ser para produtos do Prodiet destinados a hospitais e clínicas, assim como para farmácias, onde poderiam ser adquiridos por consumidores finais com orientação médica. b) A prescrição de fórmulas especializadas com baixo índice glicêmico se diferencia de outras abordagens ou produtos usados no tratamento de diabetes e hiperglicemia por estresse por oferecer um controle mais preciso e sustentado dos níveis de glicose no sangue, minimizando picos e quedas bruscas, e reduzindo o risco de complicações associadas ao diabetes. c) O uso de fórmulas com baixo índice glicêmico pode impactar positivamente a saúde dos pacientes ao proporcionar um controle glicêmico mais estável, reduzindo a necessidade de intervenções médicas adicionais, melhorando a qualidade de vida, e potencialmente diminuindo o risco de complicações a longo prazo, como doenças cardiovasculares e neuropatias. | J19: - Não podem ser consideradas as inovações organizacionais, comerciais e de marketing
J20: Empresa ou segmento regional | M20: 📑
B21: Nível de inovação | E21: Empresa ou segmento regional | J21: Inovador para o Brasil | M21: 📑
J22: Inovador para o Mundo | M22: 📑
B23: Risco tecnológico | E23: O principal risco é que as fórmulas não apresentem resultados satisfatórios de baixo índice glicêmico. a) Este risco está sendo gerenciado através de um desenho de estudo rigoroso que inclui a seleção cuidadosa dos participantes, o uso de métodos padronizados e validados para a determinação do índice glicêmico, e a realização de testes preliminares para ajustar a formulação das fórmulas antes da avaliação final.
B25: Metodologias | E25: Para controlar possíveis vieses de pesquisa, o projeto seguirá um protocolo bem estabelecido. A determinação do índice glicêmico será realizada em um centro de referência no Brasil para este tipo de pesquisa, seguindo os protocolos recomendados na literatura científica. a) O projeto planeja controlar possíveis vieses de pesquisa na determinação do índice glicêmico através da randomização dos participantes, cegamento dos avaliadores, e uso de métodos analíticos padronizados e validados. b) Para garantir a validade dos resultados, serão implementadas medidas como a seleção de um tamanho de amostra adequado, a utilização de controles apropriados, e a repetição dos testes para confirmar a consistência dos resultados. c) O centro de referência no Brasil para esse tipo de pesquisa é o Centro de Pesquisa em Alimentos (FoRC), reconhecido por sua expertise na avaliação do índice glicêmico. d) Os protocolos específicos que serão seguidos para a determinação do índice glicêmico incluem a ingestão das fórmulas pelos participantes em jejum, a medição dos níveis de glicose no sangue em intervalos específicos após a ingestão, e a comparação dos resultados com um alimento de referência, geralmente glicose pura ou pão branco. Os dados serão analisados para calcular o índice glicêmico com base na área sob a curva glicêmica.
B27: Equipe | E27: Nome Completo | F27: Cargo/Função | G27: Qualificação | H27: !
E28: Ana Claudia Zanini | F28: Analista Científico | G28: Mestrado | L28: Técnico | M28: 📑
E29: Hellin dos Santos | F29: Gerente Científico | G29: Mestrado | L29: Graduação
E30: Ana Paula Celes | F30: Diretora Técnica | G30: Pós-graduação | L30: Pós-graduação
L31: Mestrado
L32: Doutorado
B35: Cronograma
B36: [anexar imagem - preferencialmente Gantt]

Sheet INOV00040
B2: PRODIET
B3: Pesquisa, Desenvolvimento & Inovação
B4: Formulário de PD&I - Ano 2023 | J4: Incentivado pela Lei do Bem | M4: FALSE
B5: - preencher somente os campos sombreados (cinza) e - adicionar cronograma no formato de imagem ao fim do formulário - preencher um deste para cada projeto de PD&I | J5: Objetiva tornar-se um Ativo | M5: FALSE
J6: Objetiva gerar patente/registro | M6: FALSE
B8: Dossiê do projeto
B9: Dados gerais para identificação e validação do projeto de PD&I
B11: Nome do projeto | E11: INOV000040 (2023 – SUSTENLAC)
J12: Pesquisa básica | M12: 📑
B13: Classificação do projeto | E13: Desenvolvimento experimental | J13: Pesquisa aplicada | M13: 📑
J14: Desenvolvimento experimental | M14: 📑
B15: Objetivos do projeto | E15: Sustenlac Protein: Desenvolver um produto com 25% proteína do leite, palatável, para cliente marca própria. Sustenlac Suplemeto Alimentar: alterar categoria do produto de pó para preparo para suplemento alimentar
J16: Inovação tecnológica de produto | M16: 📑
B17: Tipo de inovação | E17: Inovação tecnológica de produto | J17: Inovação tecnológica de processo | M17: 📑
J18: Inovação tecnológica de serviços | M18: 📑
B19: Elemento inovador | E19: Sustenlac Protein: Produto palatável com 25% de proteína do leite, com registro MAPA e diversidade de sabores, incluindo opção neutra. Sustenlac Suplemento Alimentar: avançar com o produto no mercado de varejo, com melhora das caracteristicas sensoriais principalmente sabor chocolate. | J19: - Não podem ser consideradas as inovações organizacionais, comerciais e de marketing
J20: Empresa ou segmento regional | M20: 📑
B21: Nível de inovação | E21: Empresa ou segmento regional | J21: Inovador para o Brasil | M21: 📑
J22: Inovador para o Mundo | M22: 📑
B23: Risco tecnológico | E23: Sustenlac Protein: O maior desafio para este produto será a obtenção de licença MAPA e prospecção/aceitação do cliente Sustenlac Suplemento Alimentar: maior desafio será melhorar o perfil sensorial do sabor chocolate para melhor aceitação no varejo
B25: Metodologias | E25: Sustenlac Protein: Levantamento de volume de demanda de varejistas de Marca Própria. Processo de avaliação da fábrica e centro de distribuição para obtenção da licença MAPA Sustenlac Suplemento Alimentar: desenvolver a fórmula de acordo com os limites para Suplementos Alimentar, avaliar em escala laboratorial e executar teste piloto para composição da informação nutricional.
B27: Equipe | E27: Nome Completo | F27: Cargo/Função | G27: Qualificação | H27: !
E28: Camila Mendes Pereira | F28: Analista de Pesquisa e Desenvolvimento | G28: Graduação | L28: Técnico | M28: 📑
E29: Joyce Camargo | F29: Analista de AR | L29: Graduação
E30: Junia Carla de Oliveira Maia | F30: Coordenadora de AR | L30: Pós-graduação
L31: Mestrado
L32: Doutorado
B35: Cronograma
B36: [anexar imagem - preferencialmente Gantt]

Sheet INOV00041
B2: PRODIET
B3: Pesquisa, Desenvolvimento & Inovação
B4: Formulário de PD&I - Ano 2023 | J4: Incentivado pela Lei do Bem | M4: TRUE
B5: - preencher somente os campos sombreados (cinza) e - adicionar cronograma no formato de imagem ao fim do formulário - preencher um deste para cada projeto de PD&I | J5: Objetiva tornar-se um Ativo | M5: FALSE
J6: Objetiva gerar patente/registro | M6: FALSE
B8: Dossiê do projeto
B9: Dados gerais para identificação e validação do projeto de PD&I
B11: Nome do projeto | E11: INOV000041 (2023 - PROTEÍNA LÍQUIDA)
J12: Pesquisa básica | M12: 📑
B13: Classificação do projeto | E13: Desenvolvimento experimental | J13: Pesquisa aplicada | M13: 📑
J14: Desenvolvimento experimental | M14: 📑
B15: Objetivos do projeto | E15: Desenvolver um módulo de proteína líquido para produção própria, utilizando o processo retort, que forneça o mínimo de aminoácidos conforme a RDC 21/2015, com menor volume, para uso em hospitais. a) A necessidade específica no mercado de Nutrição Enteral que este módulo de proteína líquido busca atender é a demanda por suplementos proteicos eficientes e de baixo volume que possam ser facilmente administrados a pacientes hospitalizados. Este produto é especialmente importante para pacientes que necessitam de uma suplementação proteica concentrada devido a estados catabólicos aumentados, como aqueles em recuperação pós-cirúrgica, com feridas crônicas, ou que estão desnutridos.
J16: Inovação tecnológica de produto | M16: 📑
B17: Tipo de inovação | E17: Inovação tecnológica de produto | J17: Inovação tecnológica de processo | M17: 📑
J18: Inovação tecnológica de serviços | M18: 📑
B19: Elemento inovador | E19: O desenvolvimento de um módulo líquido próprio, inovador para o mercado brasileiro, na categoria de Nutrição Enteral, se destaca por sua formulação concentrada e eficiente, adequada às necessidades específicas de pacientes hospitalizados. a) Este módulo líquido próprio se diferencia dos produtos disponíveis no mercado brasileiro de Nutrição Enteral pela sua capacidade de fornecer uma alta concentração de proteínas e aminoácidos essenciais em um volume reduzido. A inovação também reside no uso do processo retort para garantir a estabilidade e segurança do produto, além de atender às exigências regulatórias da RDC 21/2015, oferecendo uma alternativa prática e eficiente para a administração de proteínas em ambientes hospitalares. | J19: - Não podem ser consideradas as inovações organizacionais, comerciais e de marketing
J20: Empresa ou segmento regional | M20: 📑
B21: Nível de inovação | E21: Inovador para o Brasil | J21: Inovador para o Brasil | M21: 📑
J22: Inovador para o Mundo | M22: 📑
B23: Risco tecnológico | E23: O principal risco tecnológico associado ao desenvolvimento do módulo de proteína líquido para Nutrição Enteral é a possibilidade de não alcançar a estabilidade e integridade nutricional esperada após o tratamento térmico em autoclave. Especificamente, há riscos de desnaturação das proteínas, separação de fases na emulsão, perda de aminoácidos essenciais, contaminação microbiana e comprometimento da palatabilidade e aceitação do produto pelos pacientes. Para gerenciar esses riscos, o projeto envolve uma cuidadosa seleção de ingredientes e a otimização de parâmetros de processamento. A utilização de estabilizantes e emulsificantes adequados, a realização de testes de estabilidade física e química e o monitoramento contínuo dos níveis de aminoácidos são medidas cruciais para garantir a qualidade do produto. Controles rigorosos de qualidade e segurança, juntamente com testes sensoriais, asseguram que o produto final seja palatável e aceitável.
B25: Metodologias | E25: O projeto envolve o estudo da estabilidade de emulsões de proteínas, para criar uma combinação que atenda ao perfil de aminoácidos conforme o briefing do departamento científico. As formulações serão aplicadas com tratamento térmico em autoclave. a) O estudo da estabilidade de emulsões de proteínas está sendo conduzido através de uma série de etapas experimentais que incluem a seleção de diferentes fontes proteicas, a otimização das proporções de emulsificantes e estabilizantes, e a realização de testes de estabilidade física e química das emulsões. Estes testes incluem a avaliação da separação de fases, viscosidade, e integridade proteica ao longo do tempo e sob diferentes condições de armazenamento. b) O projeto está garantindo que o perfil de aminoácidos do módulo de proteína líquido atenda às regulamentações da RDC 21/2015 através de análises detalhadas da composição de aminoácidos de cada fórmula desenvolvida. Essas análises são realizadas utilizando métodos de cromatografia líquida de alta eficiência (HPLC) e outras técnicas de quantificação de aminoácidos. Além disso, o desenvolvimento do produto é guiado por um briefing científico que especifica os requisitos mínimos para cada aminoácido essencial, conforme estipulado pela RDC 21/2015. c) As etapas específicas do processo de tratamento térmico em autoclave incluem: Preparação da Formulação: Mistura dos ingredientes de acordo com a formulação otimizada, incluindo proteínas, emulsificantes, estabilizantes e água. Homogeneização: A emulsão é homogeneizada para garantir uma distribuição uniforme das partículas e melhorar a estabilidade. Envasamento: A emulsão homogeneizada é envasada em embalagens adequadas que suportam o tratamento térmico. Selagem: As embalagens são seladas hermeticamente para evitar contaminação. Tratamento Térmico em Autoclave: As embalagens seladas são submetidas ao processo de retort, onde são expostas a temperaturas elevadas (geralmente entre 110-121°C) sob pressão por um tempo específico. Este processo é controlado rigorosamente para garantir a esterilização do produto sem comprometer a integridade nutricional. Resfriamento: Após o tratamento térmico, as embalagens são resfriadas rapidamente para evitar a degradação térmica adicional. Armazenamento e Testes de Estabilidade: Os produtos finalizados são armazenados em condições controladas e submetidos a testes de estabilidade para garantir a sua integridade ao longo do shelf-life.
B27: Equipe | E27: Nome Completo | F27: Cargo/Função | G27: Qualificação | H27: !
E28: Ana Claudia Zanini | F28: Analista Científico | G28: Mestrado | L28: Técnico | M28: 📑
E29: Lizianne Shmeil | F29: Analista de P&D | G29: Pós-graduação | L29: Graduação
E30: Hellin dos Santos | F30: Gerente Científico | G30: Mestrado | L30: Pós-graduação
E31: Ana Paula Celes | F31: Diretora Técnica | G31: Pós-graduação | L31: Mestrado
E32: Luciana Dutra | F32: Gerente Técnica | G32: Pós-graduação | L32: Doutorado
B35: Cronograma
B36: [anexar imagem - preferencialmente Gantt]

Sheet INOV00046
B2: PRODIET
B3: Pesquisa, Desenvolvimento & Inovação
B4: Formulário de PD&I - Ano 2023 | J4: Incentivado pela Lei do Bem | M4: TRUE
B5: - preencher somente os campos sombreados (cinza) e - adicionar cronograma no formato de imagem ao fim do formulário - preencher um deste para cada projeto de PD&I | J5: Objetiva tornar-se um Ativo | M5: FALSE
J6: Objetiva gerar patente/registro | M6: FALSE
B8: Dossiê do projeto
B9: Dados gerais para identificação e validação do projeto de PD&I
B11: Nome do projeto | E11: INOV000046 (PEPTIMAX IBD)
J12: Pesquisa básica | M12: 📑
B13: Classificação do projeto | E13: Pesquisa básica | J13: Pesquisa aplicada | M13: 📑
J14: Desenvolvimento experimental | M14: 📑
B15: Objetivos do projeto | E15: Este projeto tem como objetivo desenvolver um suplemento nutricional inovador para pacientes com doenças inflamatórias intestinais, como a doença de Crohn. A formulação do produto combinará TGF beta 2, uma proteína hidrolisada do soro do leite e glutamina. Esta combinação visa oferecer uma abordagem terapêutica direcionada, proporcionando benefícios nutricionais significativos e controle da inflamação intestinal. A escolha desses componentes baseia-se em evidências científicas que demonstram a eficácia do TGF beta 2 na regulação imunológica e no suporte à saúde intestinal, bem como os benefícios da glutamina como fonte de energia para enterócitos.
J16: Inovação tecnológica de produto | M16: 📑
B17: Tipo de inovação | E17: Inovação tecnológica de produto | J17: Inovação tecnológica de processo | M17: 📑
J18: Inovação tecnológica de serviços | M18: 📑
B19: Elemento inovador | E19: A inovação reside na integração do TGF beta 2 na formulação do suplemento, junto com a proteína hidrolisada do soro do leite e a glutamina. Esta combinação específica não está presente em produtos atuais no mercado e é projetada para fornecer um suporte nutricional mais eficaz para pacientes com doenças inflamatórias intestinais. O TGF beta 2 foi escolhido devido à sua capacidade comprovada de controlar a inflamação intestinal e melhorar os padrões nutricionais e inflamatórios em pacientes. A glutamina é incluída por seu papel crítico na manutenção da saúde intestinal, enquanto a proteína hidrolisada do soro do leite é conhecida por sua rápida absorção e suporte nutricional. | J19: - Não podem ser consideradas as inovações organizacionais, comerciais e de marketing
J20: Empresa ou segmento regional | M20: 📑
B21: Nível de inovação | E21: Empresa ou segmento regional | J21: Inovador para o Brasil | M21: 📑
J22: Inovador para o Mundo | M22: 📑
B23: Risco tecnológico | E23: O principal desafio tecnológico é desenvolver um produto que mantenha a integridade e a atividade biológica do TGF beta 2, juntamente com a garantia de um perfil sensorial aceitável, apesar da presença de ingredientes funcionais com sabores e texturas desafiadores. Isso inclui o desenvolvimento de estratégias de formulação e processos de produção que garantam a estabilidade do TGF beta 2 e dos outros componentes bioativos, mantendo ao mesmo tempo a palatabilidade e a aceitabilidade do produto para os consumidores.
B25: Metodologias | E25: Pesquisa e Desenvolvimento (P&D) Intensivo: A fase inicial envolverá uma pesquisa aprofundada sobre as propriedades bioquímicas e terapêuticas do TGF beta 2 e sua interação com outros componentes da formulação. Isso incluirá análises literárias e colaborações com instituições acadêmicas para explorar os mecanismos subjacentes ao efeito do TGF beta 2 em condições inflamatórias intestinais. Desenvolvimento de Formulação e Testes Analíticos: Esta fase se concentrará na formulação do produto e no desenvolvimento de métodos analíticos para quantificar a concentração e a atividade do TGF beta 2. Métodos como cromatografia líquida de alta eficiência (HPLC) e ensaios de ligação, como ELISA, serão empregados para garantir a qualidade e consistência do ingrediente ativo. Otimização de Sabor e Textura: Dada a importância da aceitação do consumidor, serão conduzidos testes sensoriais extensivos para ajustar o sabor, odor e textura do produto. A colaboração com especialistas em sabores e aromas será crucial para desenvolver uma formulação que mascare quaisquer sabores desagradáveis inerentes aos ingredientes bioativos, sem comprometer sua eficácia. Desenvolvimento de Processos de Fabricação: A seleção e otimização de processos de fabricação que preservem a estabilidade dos componentes bioativos serão cruciais. Métodos como microencapsulação ou tecnologias de preservação a frio podem ser explorados para proteger o TGF beta 2 durante o processamento e armazenamento. Ensaios Clínicos e Estudos de Mercado: Antes do lançamento comercial, serão realizados ensaios clínicos rigorosos para validar a eficácia e segurança do produto. Paralelamente, estudos de mercado serão conduzidos para avaliar a aceitação do consumidor e refinar a formulação com base nas preferências dos usuários finais. Monitoramento Contínuo e Melhoria do Produto: Após o lançamento, o feedback dos consumidores será monitorado de perto, e ajustes contínuos na formulação e no processo de fabricação serão realizados com base nos dados coletados para garantir a satisfação do cliente e a eficácia do produto.
B27: Equipe | E27: Nome Completo | F27: Cargo/Função | G27: Qualificação | H27: !
E28: Gabriela Faria de Oliveira | F28: Analista Científico | G28: Pós-graduação | L28: Técnico | M28: 📑
E29: Camila Mendes Pereira | F29: Analista de P&D | G29: Graduação | L29: Graduação
E30: Ana Paula Celes | F30: Diretora Técnica | G30: Pós-graduação | L30: Pós-graduação
E31: Luciana Dutra | F31: Gerente Head de P&D e AR | G31: Pós-graduação | L31: Mestrado
E32: Hellin dos Santos | F32: Gerente Científico | G32: Mestrado | L32: Doutorado
E33: Juliana Lamas Roberto | F33: Especialista de Estudo de Estabilidade | G33: Mestrado
B35: Cronograma
B36: [anexar imagem - preferencialmente Gantt]

Sheet BD Projetos
B1: Incentivado pela Lei do Bem | C1: Objetiva tornar-se um Ativo | D1: Objetiva gerar patente/registro
A2: INOV00001 | B2: TRUE | C2: FALSE | D2: FALSE
A3: INOV00004 | B3: TRUE | C3: FALSE | D3: FALSE
A4: INOV00006 | B4: TRUE | C4: FALSE | D4: FALSE
A5: INOV00010 | B5: TRUE | C5: FALSE | D5: FALSE
A6: INOV00013 | B6: TRUE | C6: FALSE | D6: FALSE
A7: INOV00014 | B7: TRUE | C7: FALSE | D7: FALSE
A8: INOV00016 | B8: TRUE | C8: FALSE | D8: FALSE
A9: INOV00017 | B9: TRUE | C9: FALSE | D9: FALSE
A10: INOV00021 | B10: TRUE | C10: FALSE | D10: FALSE
A11: INOV00022 | B11: TRUE | C11: FALSE | D11: FALSE
A12: INOV00023 | B12: TRUE | C12: FALSE | D12: FALSE
A13: INOV00024 | B13: TRUE | C13: FALSE | D13: FALSE
... A24: INOV00046 | B24: FALSE | C24: FALSE | D24: FALSE

Sheet PROJETO
B2: PRODIET
B3: Pesquisa, Desenvolvimento & Inovação
B4: Formulário de PD&I - Ano 2023 | J4: Incentivado pela Lei do Bem | M4: FALSE
B5: - preencher somente os campos sombreados (cinza) e - adicionar cronograma no formato de imagem ao fim do formulário - preencher um deste para cada projeto de PD&I | J5: Objetiva tornar-se um Ativo | M5: FALSE
J6: Objetiva gerar patente/registro | M6: FALSE
B8: Dossiêdoprojeto
B9: DadosgeraisparaidentificaçãoevalidaçãodoprojetodePD&I
B11: Nome do projeto | E11: Nome completo do projeto de PD&I
J12: Pesquisa básica | M12: 📑
B13: Classificação do projeto | E13: Desenvolvimento experimental | J13: Pesquisa aplicada | M13: 📑
J14: Desenvolvimento experimental | M14: 📑
B15: Objetivos do projeto | E15: Contar qual/quais a(s) EXPECTATIVA(S) da empresa caso o projeto obtenha sucesso
J16: Inovação tecnológica de produto | M16: 📑
B17: Tipo de inovação | E17: Inovação tecnológica de serviços | J17: Inovação tecnológica de processo | M17: 📑
J18: Inovação tecnológica de serviços | M18: 📑
B19: Elemento inovador | E19: Contar O QUE faz o resultado desse projeto ser tecnologicamente novo ou inovador | J19: - Não podem ser consideradas as inovações organizacionais, comerciais e de marketing
J20: Empresa ou segmento regional | M20: 📑
B21: Nível de inovação | E21: Empresa ou segmento regional | J21: Inovador para o Brasil | M21: 📑
J22: Inovador para o Mundo | M22: 📑
B23: Risco tecnológico | E23: Descrever qual é o RISCO ou a BARREIRA tecnológica que impossibilitava a empresa de alcançar o objetivo, antes da realização deste projeto
B25: Metodologias | E25: Descrever quais serão as ESTRATÉGIAS sistematizadas para conseguir superar a barreira tecnológica e alcançar os objetivos. Não basta citar quais são as metodologias, mas deve-se explicar como cada uma delas se relaciona com as etapas do projeto.
B27: Equipe | E27: NomeCompleto | F27: Cargo|Função | G27: Qualificação | H27: !
E28: Lizianne Angelica Shmeil | F28: Analista de P&D | G28: Pós-graduação | H28: FALSE | L28: Técnico | M28: 📑
E29: Ana Paula Celes | F29: Diretora Técnica | G29: Pós-graduação | H29: FALSE | L29: Graduação
E30: Luciana Dutra | F30: Gerente Técnica | G30: Pós-graduação | H30: FALSE | L30: Pós-graduação
E31: Gabriela Faria de Oliveira | F31: Analista Científico | G31: Pós-graduação | H31: FALSE | L31: Mestrado
E32: Rafael Parreira Lorini | F32: Analista de P&D | G32: Graduação | H32: FALSE | L32: Doutorado
E33: Hellin dos Santos | F33: Gerente Científico | G33: Mestrado | H33: FALSE
E34: Camila Mendes Pereira | F34: Analista de P&D | G34: Graduação | H34: FALSE
E35: Ana Claudia Zanini | F35: Analista cientifico | G35: Mestrado | H35: FALSE
E36: Juliana Lamas Roberto | F36: Especialista de Estudo de Estabilidade | G36: Mestrado | H36: FALSE
E37: Márcio Henrique Nogueira | F37: Analista de P&D | G37: Doutorado | H37: FALSE
E38: Tahuany Caetano | F38: Analista MKT | G38: Pós-graduação | H38: FALSE
E39: Arianna Schreiber | F39: MARKETING
E40: Mihaela Theer Moura | F40: MARKETING
E41: Tahuany Leite | F41: MARKETING
E42: Vaneisse Cristina Lima Monteiro
E43: Ana Paula Biz
E44: Raissa Bellotti
E45: Alyne Alves Nunes Oliveira
B47: Cronograma
B48: [anexarimagem-preferencialmenteGantt]

Sheet PESSOAL
B2: PRODIET
B3: Pesquisa ,Desenvolvimento & Inovação
B4: Formulário de PD&I - Ano2023
B5: -preencher somente os campos sombreados (cinza)
B8: Dossiê do projeto
B9: Cálculo de custo - Pessoal
B11: Salário bruto | T11: =(U11/12)*24 -> 181.86667 | U11: =(SUM(H33:S33)*8.8)/24 -> 90.933333
B12: Nome Completo | C12: CPF | D12: notas | E12: Cargo/função | F12: Formação | G12: Attachments | H12: Salário 01 | I12: Salário 02 | J12: Salário 03 | K12: Salário 04 | L12: Salário 05 | M12: Salário 06 | N12: Salário 07 | O12: Salário 08 | P12: Salário 09 | Q12: Salário 10 | R12: Salário 11 | S12: Salário 12 | T12: PD&I time | U12: PD&I (%) | V12: Classificação | W12: Pesquisador
B13: Ana Claudia Zanini | C13: 076.046.519-33 | D13: CLT | E13: Analista Científico | F13: Mestrado | H13: 5343.94 | I13: 5343.94 | J13: 5343.94 | K13: 5343.94 | L13: 5584.42 | M13: 5584.42 | N13: 5743.25 | O13: 5743.25 | P13: 5743.25 | Q13: 6143.46 | R13: 6143.46 | S13: 6143.46 | T13: =IFERROR(__xludf.DUMMYFUNCTION("IFERROR(if(W13=true, SUM(FILTER(TIMESHEET!$G:$G,TIMESHEET!O:O = TRUE,TIMESHEET!P:P = TRUE,TIMESHEET!E:E = B13,TIMESHEET!F:F < DATE(2024,1,1))),0),0)"),29.781250000000032) -> 29.78125 | U13: =T13/$U$11 -> 0.32750641 | V13: =IF(U13<80%,"Parcial","Exclusivo") -> Parcial | W13: TRUE
B14: Ana Paula Biz | C14: 071.847.899-11 | D14: CLT | E14: ANALISTA DE P&D PLENO | F14: Mestrado | H14: 0 | I14: 0 | J14: 0 | K14: 0 | L14: 4594.31 | M14: 4594.31 | N14: 4594.31 | O14: 4594.31 | P14: 4594.31 | Q14: 4594.31 | R14: 4594.31 | S14: 4594.31 | T14: =IFERROR(__xludf.DUMMYFUNCTION("IFERROR(if(W14=true, SUM(FILTER(TIMESHEET!$G:$G,TIMESHEET!O:O = TRUE,TIMESHEET!P:P = TRUE,TIMESHEET!E:E = B14,TIMESHEET!F:F < DATE(2024,1,1))),0),0)"),3.1319444444444455) -> 3.1319444 | U14: =T14/$U$11 -> 0.034442204 | V14: =IF(U14<80%,"Parcial","Exclusivo") -> Parcial | W14: TRUE
B15: Ana Paula Celes | C15: 759.837.297-72 | D15: PJ | E15: Diretora Técnica | F15: Pós Graduado | H15: 36129.83 | I15: 36129.83 | J15: 36129.83 | K15: 36129.83 | L15: 36129.83 | M15: 37755.67 | N15: 37755.67 | O15: 37755.67 | P15: 37755.67 | Q15: 37755.67 | R15: 37755.67 | S15: 37755.67 | T15: =IFERROR(__xludf.DUMMYFUNCTION("IFERROR(if(W15=true, SUM(FILTER(TIMESHEET!$G:$G,TIMESHEET!O:O = TRUE,TIMESHEET!P:P = TRUE,TIMESHEET!E:E = B15,TIMESHEET!F:F < DATE(2024,1,1))),0),0)"),1.1354166666666667) -> 1.1354167 | U15: =T15/$U$11 -> 0.012486254 | V15: =IF(U15<80%,"Parcial","Exclusivo") -> Parcial | W15: TRUE
B16: Camila Mendes Pereira | C16: 83.832.289-10 | D16: CLT | E16: Analista de P&D | F16: Superior Completo | H16: 4757.63 | I16: 4757.63 | J16: 4757.63 | K16: 4757.63 | L16: 4971.72 | M16: 5318.49 | N16: 5469.76 | O16: 5469.76 | P16: 5469.76 | Q16: 5469.76 | R16: 5469.76 | S16: 5469.76 | T16: =IFERROR(__xludf.DUMMYFUNCTION("IFERROR(if(W16=true, SUM(FILTER(TIMESHEET!$G:$G,TIMESHEET!O:O = TRUE,TIMESHEET!P:P = TRUE,TIMESHEET!E:E = B16,TIMESHEET!F:F < DATE(2024,1,1))),0),0)"),7.510416666666668) -> 7.5104167 | U16: =T16/$U$11 -> 0.082592559 | V16: =IF(U16<80%,"Parcial","Exclusivo") -> Parcial | W16: TRUE
B17: Gabriela Faria de Oliveira | C17: 087.823.469-17 | D17: CLT | E17: Analista Científico | F17: Pós Graduado | H17: 5343.94 | I17: 5343.94 | J17: 5343.94 | K17: 5343.94 | L17: 5584.42 | M17: 5584.42 | N17: 5743.25 | O17: 5743.25 | P17: 5743.25 | Q17: 5743.25 | R17: 5743.25 | S17: 5743.25 | T17: =IFERROR(__xludf.DUMMYFUNCTION("IFERROR(if(W17=true, SUM(FILTER(TIMESHEET!$G:$G,TIMESHEET!O:O = TRUE,TIMESHEET!P:P = TRUE,TIMESHEET!E:E = B17,TIMESHEET!F:F < DATE(2024,1,1))),0),0)"),8.249999999999998) -> 8.25 | U17: =T17/$U$11 -> 0.090725806 | V17: =IF(U17<80%,"Parcial","Exclusivo") -> Parcial | W17: TRUE
B18: Hellin dos Santos | C18: 058.544.839-63 | D18: CLT | E18: Gerente Científico | F18: Mestrado | H18: 16734.6 | I18: 16734.6 | J18: 16734.6 | K18: 16734.6 | L18: 17487.66 | M18: 17487.66 | N18: 17985.04 | O18: 17985.04 | P18: 17985.04 | Q18: 17985.04 | R18: 17985.04 | S18: 17985.04 | T18: =IFERROR(__xludf.DUMMYFUNCTION("IFERROR(if(W18=true, SUM(FILTER(TIMESHEET!$G:$G,TIMESHEET!O:O = TRUE,TIMESHEET!P:P = TRUE,TIMESHEET!E:E = B18,TIMESHEET!F:F < DATE(2024,1,1))),0),0)"),6.437500000000004) -> 6.4375 | U18: =T18/$U$11 -> 0.070793622 | V18: =IF(U18<80%,"Parcial","Exclusivo") -> Parcial | W18: TRUE
B19: Juliana Lamas Roberto | C19: 317.875.738-42 | D19: CLT | E19: Especialista em EE | F19: Mestrado | H19: 9883.44 | I19: 9883.44 | J19: 9883.44 | K19: 9883.44 | L19: 10328.19 | M19: 10915.04 | N19: 11225.48 | O19: 11225.48 | P19: 11225.48 | Q19: 11225.48 | R19: 11225.48 | S19: 11225.48 | T19: =IFERROR(__xludf.DUMMYFUNCTION("IFERROR(if(W19=true, SUM(FILTER(TIMESHEET!$G:$G,TIMESHEET!O:O = TRUE,TIMESHEET!P:P = TRUE,TIMESHEET!E:E = B19,TIMESHEET!F:F < DATE(2024,1,1))),0),0)"),23.151388888888892) -> 23.151389 | U19: =T19/$U$11 -> 0.25459739 | V19: =IF(U19<80%,"Parcial","Exclusivo") -> Parcial | W19: TRUE
B20: Lizianne Angelica Shmeil | C20: 052.485.199-93 | D20: CLT | E20: Analista de P&D | F20: Superior Completo | H20: 7037.58 | I20: 7037.58 | J20: 7037.58 | K20: 7037.58 | L20: 7354.27 | M20: 7354.27 | N20: 7563.44 | O20: 7563.44 | P20: 7563.44 | Q20: 7563.44 | R20: 7563.44 | S20: 7563.44 | T20: =IFERROR(__xludf.DUMMYFUNCTION("IFERROR(if(W20=true, SUM(FILTER(TIMESHEET!$G:$G,TIMESHEET!O:O = TRUE,TIMESHEET!P:P = TRUE,TIMESHEET!E:E = B20,TIMESHEET!F:F < DATE(2024,1,1))),0),0)"),39.485416666666666) -> 39.485417 | U20: =T20/$U$11 -> 0.43422379 | V20: =IF(U20<80%,"Parcial","Exclusivo") -> Parcial | W20: TRUE
B21: Luciana Dutra | C21: 186.586.978-35 | D21: CLT | E21: Head de P&D e AR | F21: Pós Graduado | H21: 21522 | I21: 21522 | J21: 21522 | K21: 21522 | L21: 22940.49 | M21: 22940.49 | N21: 23130.16 | O21: 23130.16 | P21: 23130.16 | Q21: 23130.16 | R21: 23130.16 | S21: 23130.16 | T21: =IFERROR(__xludf.DUMMYFUNCTION("IFERROR(if(W21=true, SUM(FILTER(TIMESHEET!$G:$G,TIMESHEET!O:O = TRUE,TIMESHEET!P:P = TRUE,TIMESHEET!E:E = B21,TIMESHEET!F:F < DATE(2024,1,1))),0),0)"),1.9375000000000007) -> 1.9375 | U21: =T21/$U$11 -> 0.021306818 | V21: =IF(U21<80%,"Parcial","Exclusivo") -> Parcial | W21: TRUE
B22: Rafael Parreira Lorini | C22: 024.486.920-09 | D22: CLT | E22: Analista de P&D | F22: Superior Completo | H22: 3962.54 | I22: 3962.54 | J22: 3962.54 | K22: 3962.54 | L22: 4140.85 | M22: 5318.49 | N22: 5318.49 | O22: 5318.49 | P22: 5318.49 | Q22: 5318.49 | R22: 5318.49 | S22: 5318.49 | T22: =IFERROR(__xludf.DUMMYFUNCTION("IFERROR(if(W22=true, SUM(FILTER(TIMESHEET!$G:$G,TIMESHEET!O:O = TRUE,TIMESHEET!P:P = TRUE,TIMESHEET!E:E = B22,TIMESHEET!F:F < DATE(2024,1,1))),0),0)"),2.447916666666667) -> 2.4479167 | U22: =T22/$U$11 -> 0.026919905 | V22: =IF(U22<80%,"Parcial","Exclusivo") -> Parcial | W22: TRUE
B23: Vaneisse Cristina Lima Monteiro | D23: CLT | F23: Superior Completo | H23: 4616.29 | I23: 4616.29 | J23: 4616.29 | K23: 4616.29 | L23: 4824.02 | M23: 0 | N23: 0 | O23: 0 | P23: 0 | Q23: 0 | R23: 0 | S23: 0 | T23: =IFERROR(__xludf.DUMMYFUNCTION("IFERROR(if(W23=true, SUM(FILTER(TIMESHEET!$G:$G,TIMESHEET!O:O = TRUE,TIMESHEET!P:P = TRUE,TIMESHEET!E:E = B23,TIMESHEET!F:F < DATE(2024,1,1))),0),0)"),4.829861111111112) -> 4.8298611 | U23: =T23/$U$11 -> 0.053114308 | V23: =IF(U23<80%,"Parcial","Exclusivo") -> Parcial | W23: TRUE
B24: Alyne Alves Nunes Oliveira | C24: 129.307.117-01 | D24: CLT | E24: Especialista de P&D | F24: Doutorado | H24: 0 | I24: 0 | J24: 0 | K24: 0 | L24: 0 | M24: 0 | N24: 0 | O24: 0 | P24: 0 | Q24: 7234.78 | R24: 7234.78 | S24: 7234.78 | T24: =IFERROR(__xludf.DUMMYFUNCTION("IFERROR(if(W24=true, SUM(FILTER(TIMESHEET!$G:$G,TIMESHEET!O:O = TRUE,TIMESHEET!P:P = TRUE,TIMESHEET!E:E = B24,TIMESHEET!F:F < DATE(2024,1,1))),0),0)"),2.15625) -> 2.15625 | U24: =T24/$U$11 -> 0.023712427 | V24: =IF(U24<80%,"Parcial","Exclusivo") -> Parcial | W24: TRUE
B25: Raissa Bellotti | C25: 430.604.838-17 | D25: CLT | E25: Analista Científico | F25: Pós Graduada | H25: 0 | I25: 0 | J25: 0 | K25: 0 | L25: 0 | M25: 0 | N25: 0 | O25: 0 | P25: 0 | Q25: 4780.42 | R25: 4780.42 | S25: 4780.42 | T25: =IFERROR(__xludf.DUMMYFUNCTION("IFERROR(if(W25=true, SUM(FILTER(TIMESHEET!$G:$G,TIMESHEET!O:O = TRUE,TIMESHEET!P:P = TRUE,TIMESHEET!E:E = B25,TIMESHEET!F:F < DATE(2024,1,1))),0),0)"),4.298611111111112) -> 4.2986111 | U25: =T25/$U$11 -> 0.047272116 | V25: =IF(U25<80%,"Parcial","Exclusivo") -> Parcial | W25: TRUE
B27: Cálculo do custo/hora
B29: Encargos sobre folha | I29: INSS | J29: Patronal | K29: 0.2
B30: INSS | C30: FGTS | D30: Férias | E30: 13º | F30: Total | J30: Terceiros | K30: 0.058
B31: =SUM(K29:K31) -> 0.273 | C31: 0.08 | D31: =((1+(1/3))*(1+B31+C31)/12) -> 0.15033333 | E31: =(1+B31+C31)/12 -> 0.11275 | F31: =SUM(B31:E31) -> 0.61608333 | J31: RAT | K31: 0.015
H33: =NETWORKDAYS(DATE(right(H34,4),mid(H34,4,2),1),DATE(right(H34,4),mid(H34,4,2)+1,0),$B$50:$B$61) -> 22 | I33: =NETWORKDAYS(DATE(right(I34,4),mid(I34,4,2),1),DATE(right(I34,4),mid(I34,4,2)+1,0),$B$50:$B$61) -> 17 | J33: =NETWORKDAYS(DATE(right(J34,4),mid(J34,4,2),1),DATE(right(J34,4),mid(J34,4,2)+1,0),$B$50:$B$61) -> 23 | K33: =NETWORKDAYS(DATE(right(K34,4),mid(K34,4,2),1),DATE(right(K34,4),mid(K34,4,2)+1,0),$B$50:$B$61) -> 18 | L33: =NETWORKDAYS(DATE(right(L34,4),mid(L34,4,2),1),DATE(right(L34,4),mid(L34,4,2)+1,0),$B$50:$B$61) -> 22 | M33: =NETWORKDAYS(DATE(right(M34,4),mid(M34,4,2),1),DATE(right(M34,4),mid(M34,4,2)+1,0),$B$50:$B$61) -> 21 | N33: =NETWORKDAYS(DATE(right(N34,4),mid(N34,4,2),1),DATE(right(N34,4),mid(N34,4,2)+1,0),$B$50:$B$61) -> 21 | O33: =NETWORKDAYS(DATE(right(O34,4),mid(O34,4,2),1),DATE(right(O34,4),mid(O34,4,2)+1,0),$B$50:$B$61) -> 23 | ... S33: =NETWORKDAYS(DATE(right(S34,4),mid(S34,4,2),1),DATE(right(S34,4),mid(S34,4,2)+1,0),$B$50:$B$61) -> 21 | T33: =SUM(T35:T49) -> 206908.85 | U33: =SUM(U35:U49) -> 206908.85 | V33: =U33-T33 -> 0
B34: Nome Completo | E34: Classificação | F34: Formação | H34: 44957 | I34: 44985 | J34: 45016 | K34: 45046 | L34: 45077 | M34: 45107 | N34: 45138 | O34: 45169 | P34: 45199 | Q34: 45230 | R34: 45260 | S34: 45291 | T34: PD&I R$ | U34: Aprovado R$ | V34: Pesquisador
B35: {=unique(B13:B25)} -> Ana Claudia Zanini | E35: {=V13:V25} -> Parcial | F35: {=F13:F25} -> Mestrado | H35: =vlookup($B35,$B$13:$S$23,month(H$34)+6,0)*(1+$F$31)/(H$33*8.8) -> 44.608742 | I35: =vlookup($B35,$B$13:$S$23,month(I$34)+6,0)*(1+$F$31)/(I$33*8.8) -> 57.72896 | J35: =vlookup($B35,$B$13:$S$23,month(J$34)+6,0)*(1+$F$31)/(J$33*8.8) -> 42.669231 | K35: =vlookup($B35,$B$13:$S$23,month(K$34)+6,0)*(1+$F$31)/(K$33*8.8) -> 54.521795 | L35: =vlookup($B35,$B$13:$S$23,month(L$34)+6,0)*(1+$F$31)/(L$33*8.8) -> 46.616157 | M35: =vlookup($B35,$B$13:$S$23,month(M$34)+6,0)*(1+$F$31)/(M$33*8.8) -> 48.835974 | N35: =vlookup($B35,$B$13:$S$23,month(N$34)+6,0)*(1+$F$31)/(N$33*8.8) -> 50.224949 | O35: =vlookup($B35,$B$13:$S$23,month(O$34)+6,0)*(1+$F$31)/(O$33*8.8) -> 45.857562 | ... S35: =vlookup($B35,$B$13:$S$23,month(S$34)+6,0)*(1+$F$31)/(S$33*8.8) -> 53.724801 | T35: =SUMIF(TIMESHEET!E:E,B35,TIMESHEET!N:N) -> 27768.622 | U35: =SUMIF(V35,TRUE,T35) -> 27768.622 | V35: TRUE
B36: Ana Paula Biz | E36: Parcial | F36: Mestrado | H36: =vlookup($B36,$B$13:$S$23,month(H$34)+6,0)*(1+$F$31)/(H$33*8.8) -> 0 | I36: =vlookup($B36,$B$13:$S$23,month(I$34)+6,0)*(1+$F$31)/(I$33*8.8) -> 0 | J36: =vlookup($B36,$B$13:$S$23,month(J$34)+6,0)*(1+$F$31)/(J$33*8.8) -> 0 | K36: =vlookup($B36,$B$13:$S$23,month(K$34)+6,0)*(1+$F$31)/(K$33*8.8) -> 0 | L36: =vlookup($B36,$B$13:$S$23,month(L$34)+6,0)*(1+$F$31)/(L$33*8.8) -> 38.351177 | M36: =vlookup($B36,$B$13:$S$23,month(M$34)+6,0)*(1+$F$31)/(M$33*8.8) -> 40.177423 | N36: =vlookup($B36,$B$13:$S$23,month(N$34)+6,0)*(1+$F$31)/(N$33*8.8) -> 40.177423 | O36: =vlookup($B36,$B$13:$S$23,month(O$34)+6,0)*(1+$F$31)/(O$33*8.8) -> 36.683734 | ... S36: =vlookup($B36,$B$13:$S$23,month(S$34)+6,0)*(1+$F$31)/(S$33*8.8) -> 40.177423 | T36: =SUMIF(TIMESHEET!E:E,B36,TIMESHEET!N:N) -> 3015.7033 | U36: =SUMIF(V36,TRUE,T36) -> 3015.7033 | V36: TRUE
B37: Ana Paula Celes | E37: Parcial | F37: Pós Graduado | H37: =vlookup($B37,$B$13:$S$23,month(H$34)+6,0)*(1+$F$31)/(H$33*8.8) -> 301.59512 | I37: =vlookup($B37,$B$13:$S$23,month(I$34)+6,0)*(1+$F$31)/(I$33*8.8) -> 390.29957 | J37: =vlookup($B37,$B$13:$S$23,month(J$34)+6,0)*(1+$F$31)/(J$33*8.8) -> 288.48229 | K37: =vlookup($B37,$B$13:$S$23,month(K$34)+6,0)*(1+$F$31)/(K$33*8.8) -> 368.61626 | L37: =vlookup($B37,$B$13:$S$23,month(L$34)+6,0)*(1+$F$31)/(L$33*8.8) -> 301.59512 | M37: =vlookup($B37,$B$13:$S$23,month(M$34)+6,0)*(1+$F$31)/(M$33*8.8) -> 330.17483 | N37: =vlookup($B37,$B$13:$S$23,month(N$34)+6,0)/(N$33*8.8) -> 204.30557 | O37: =vlookup($B37,$B$13:$S$23,month(O$34)+6,0)/(O$33*8.8) -> 186.53987 | P37: =vlookup($B37,$B$13:$S$23,month(P$34)+6,0)/(P$33*8.8) -> 225.81142 | Q37: =vlookup($B37,$B$13:$S$23,month(Q$34)+6,0)/(Q$33*8.8) -> 204.30557 | R37: =vlookup($B37,$B$13:$S$23,month(R$34)+6,0)/(R$33*8.8) -> 214.52085 | S37: =vlookup($B37,$B$13:$S$23,month(S$34)+6,0)/(S$33*8.8) -> 204.30557 | T37: =SUMIF(TIMESHEET!E:E,B37,TIMESHEET!N:N) -> 6544.8412 | U37: =SUMIF(V37,TRUE,T37) -> 6544.8412 | V37: TRUE
B38: Camila Mendes Pereira | E38: Parcial | F38: Superior Completo | H38: =vlookup($B38,$B$13:$S$23,month(H$34)+6,0)*(1+$F$31)/(H$33*8.8) -> 39.714497 | I38: =vlookup($B38,$B$13:$S$23,month(I$34)+6,0)*(1+$F$31)/(I$33*8.8) -> 51.395231 | J38: =vlookup($B38,$B$13:$S$23,month(J$34)+6,0)*(1+$F$31)/(J$33*8.8) -> 37.987779 | K38: =vlookup($B38,$B$13:$S$23,month(K$34)+6,0)*(1+$F$31)/(K$33*8.8) -> 48.53994 | L38: =vlookup($B38,$B$13:$S$23,month(L$34)+6,0)*(1+$F$31)/(L$33*8.8) -> 41.501621 | M38: =vlookup($B38,$B$13:$S$23,month(M$34)+6,0)*(1+$F$31)/(M$33*8.8) -> 46.510406 | N38: =vlookup($B38,$B$13:$S$23,month(N$34)+6,0)*(1+$F$31)/(N$33*8.8) -> 47.833268 | O38: =vlookup($B38,$B$13:$S$23,month(O$34)+6,0)*(1+$F$31)/(O$33*8.8) -> 43.673854 | ... S38: =vlookup($B38,$B$13:$S$23,month(S$34)+6,0)*(1+$F$31)/(S$33*8.8) -> 47.833268 | T38: =SUMIF(TIMESHEET!E:E,B38,TIMESHEET!N:N) -> 8272.4843 | U38: =SUMIF(V38,TRUE,T38) -> 8272.4843 | V38: TRUE
B39: Gabriela Faria de Oliveira | E39: Parcial | F39: Pós Graduado | H39: =vlookup($B39,$B$13:$S$23,month(H$34)+6,0)*(1+$F$31)/(H$33*8.8) -> 44.608742 | I39: =vlookup($B39,$B$13:$S$23,month(I$34)+6,0)*(1+$F$31)/(I$33*8.8) -> 57.72896 | J39: =vlookup($B39,$B$13:$S$23,month(J$34)+6,0)*(1+$F$31)/(J$33*8.8) -> 42.669231 | K39: =vlookup($B39,$B$13:$S$23,month(K$34)+6,0)*(1+$F$31)/(K$33*8.8) -> 54.521795 | L39: =vlookup($B39,$B$13:$S$23,month(L$34)+6,0)*(1+$F$31)/(L$33*8.8) -> 46.616157 | M39: =vlookup($B39,$B$13:$S$23,month(M$34)+6,0)*(1+$F$31)/(M$33*8.8) -> 48.835974 | N39: =vlookup($B39,$B$13:$S$23,month(N$34)+6,0)*(1+$F$31)/(N$33*8.8) -> 50.224949 | O39: =vlookup($B39,$B$13:$S$23,month(O$34)+6,0)*(1+$F$31)/(O$33*8.8) -> 45.857562 | ... S39: =vlookup($B39,$B$13:$S$23,month(S$34)+6,0)*(1+$F$31)/(S$33*8.8) -> 50.224949 | T39: =SUMIF(TIMESHEET!E:E,B39,TIMESHEET!N:N) -> 7868.1234 | U39: =SUMIF(V39,TRUE,T39) -> 7868.1234 | V39: TRUE
B40: Hellin dos Santos | E40: Parcial | F40: Mestrado | H40: =vlookup($B40,$B$13:$S$23,month(H$34)+6,0)*(1+$F$31)/(H$33*8.8) -> 139.69271 | I40: =vlookup($B40,$B$13:$S$23,month(I$34)+6,0)*(1+$F$31)/(I$33*8.8) -> 180.7788 | J40: =vlookup($B40,$B$13:$S$23,month(J$34)+6,0)*(1+$F$31)/(J$33*8.8) -> 133.61911 | K40: =vlookup($B40,$B$13:$S$23,month(K$34)+6,0)*(1+$F$31)/(K$33*8.8) -> 170.73553 | L40: =vlookup($B40,$B$13:$S$23,month(L$34)+6,0)*(1+$F$31)/(L$33*8.8) -> 145.9789 | M40: =vlookup($B40,$B$13:$S$23,month(M$34)+6,0)*(1+$F$31)/(M$33*8.8) -> 152.93028 | N40: =vlookup($B40,$B$13:$S$23,month(N$34)+6,0)*(1+$F$31)/(N$33*8.8) -> 157.27989 | O40: =vlookup($B40,$B$13:$S$23,month(O$34)+6,0)*(1+$F$31)/(O$33*8.8) -> 143.60338 | ... S40: =vlookup($B40,$B$13:$S$23,month(S$34)+6,0)*(1+$F$31)/(S$33*8.8) -> 157.27989 | T40: =SUMIF(TIMESHEET!E:E,B40,TIMESHEET!N:N) -> 16555.425 | U40: =SUMIF(V40,TRUE,T40) -> 16555.425 | V40: TRUE
B41: Juliana Lamas Roberto | E41: Parcial | F41: Mestrado | H41: =vlookup($B41,$B$13:$S$23,month(H$34)+6,0)*(1+$F$31)/(H$33*8.8) -> 82.50239 | I41: =vlookup($B41,$B$13:$S$23,month(I$34)+6,0)*(1+$F$31)/(I$33*8.8) -> 106.7678 | J41: =vlookup($B41,$B$13:$S$23,month(J$34)+6,0)*(1+$F$31)/(J$33*8.8) -> 78.915329 | K41: =vlookup($B41,$B$13:$S$23,month(K$34)+6,0)*(1+$F$31)/(K$33*8.8) -> 100.83625 | L41: =vlookup($B41,$B$13:$S$23,month(L$34)+6,0)*(1+$F$31)/(L$33*8.8) -> 86.214957 | M41: =vlookup($B41,$B$13:$S$23,month(M$34)+6,0)*(1+$F$31)/(M$33*8.8) -> 95.452458 | N41: =vlookup($B41,$B$13:$S$23,month(N$34)+6,0)*(1+$F$31)/(N$33*8.8) -> 98.167268 | O41: =vlookup($B41,$B$13:$S$23,month(O$34)+6,0)*(1+$F$31)/(O$33*8.8) -> 89.630984 | ... S41: =vlookup($B41,$B$13:$S$23,month(S$34)+6,0)*(1+$F$31)/(S$33*8.8) -> 98.167268 | T41: =SUMIF(TIMESHEET!E:E,B41,TIMESHEET!N:N) -> 52769.52 | U41: =SUMIF(V41,TRUE,T41) -> 52769.52 | V41: TRUE
B42: Lizianne Angelica Shmeil | E42: Parcial | F42: Superior Completo | H42: =vlookup($B42,$B$13:$S$23,month(H$34)+6,0)*(1+$F$31)/(H$33*8.8) -> 58.746466 | I42: =vlookup($B42,$B$13:$S$23,month(I$34)+6,0)*(1+$F$31)/(I$33*8.8) -> 76.024838 | J42: =vlookup($B42,$B$13:$S$23,month(J$34)+6,0)*(1+$F$31)/(J$33*8.8) -> 56.192271 | K42: =vlookup($B42,$B$13:$S$23,month(K$34)+6,0)*(1+$F$31)/(K$33*8.8) -> 71.801236 | L42: =vlookup($B42,$B$13:$S$23,month(L$34)+6,0)*(1+$F$31)/(L$33*8.8) -> 61.390047 | M42: =vlookup($B42,$B$13:$S$23,month(M$34)+6,0)*(1+$F$31)/(M$33*8.8) -> 64.313383 | N42: =vlookup($B42,$B$13:$S$23,month(N$34)+6,0)*(1+$F$31)/(N$33*8.8) -> 66.142583 | O42: =vlookup($B42,$B$13:$S$23,month(O$34)+6,0)*(1+$F$31)/(O$33*8.8) -> 60.391054 | ... S42: =vlookup($B42,$B$13:$S$23,month(S$34)+6,0)*(1+$F$31)/(S$33*8.8) -> 66.142583 | T42: =SUMIF(TIMESHEET!E:E,B42,TIMESHEET!N:N) -> 61507.294 | U42: =SUMIF(V42,TRUE,T42) -> 61507.294 | V42: TRUE
B43: Luciana Dutra | E43: Parcial | F43: Pós Graduado | H43: =vlookup($B43,$B$13:$S$23,month(H$34)+6,0)*(1+$F$31)/(H$33*8.8) -> 179.65571 | I43: =vlookup($B43,$B$13:$S$23,month(I$34)+6,0)*(1+$F$31)/(I$33*8.8) -> 232.49562 | J43: =vlookup($B43,$B$13:$S$23,month(J$34)+6,0)*(1+$F$31)/(J$33*8.8) -> 171.84459 | K43: =vlookup($B43,$B$13:$S$23,month(K$34)+6,0)*(1+$F$31)/(K$33*8.8) -> 219.5792 | L43: =vlookup($B43,$B$13:$S$23,month(L$34)+6,0)*(1+$F$31)/(L$33*8.8) -> 191.49661 | M43: =vlookup($B43,$B$13:$S$23,month(M$34)+6,0)*(1+$F$31)/(M$33*8.8) -> 200.6155 | N43: =vlookup($B43,$B$13:$S$23,month(N$34)+6,0)*(1+$F$31)/(N$33*8.8) -> 202.27417 | O43: =vlookup($B43,$B$13:$S$23,month(O$34)+6,0)*(1+$F$31)/(O$33*8.8) -> 184.68511 | ... S43: =vlookup($B43,$B$13:$S$23,month(S$34)+6,0)*(1+$F$31)/(S$33*8.8) -> 202.27417 | T43: =SUMIF(TIMESHEET!E:E,B43,TIMESHEET!N:N) -> 8705.9187 | U43: =SUMIF(V43,TRUE,T43) -> 8705.9187 | V43: TRUE
B44: Rafael Parreira Lorini | E44: Parcial | F44: Superior Completo | H44: =vlookup($B44,$B$13:$S$25,month(H$34)+6,0)*(1+$F$31)/(H$33*8.8) -> 33.077453 | I44: =vlookup($B44,$B$13:$S$23,month(I$34)+6,0)*(1+$F$31)/(I$33*8.8) -> 42.806115 | J44: =vlookup($B44,$B$13:$S$23,month(J$34)+6,0)*(1+$F$31)/(J$33*8.8) -> 31.639303 | K44: =vlookup($B44,$B$13:$S$23,month(K$34)+6,0)*(1+$F$31)/(K$33*8.8) -> 40.427998 | L44: =vlookup($B44,$B$13:$S$23,month(L$34)+6,0)*(1+$F$31)/(L$33*8.8) -> 34.565902 | M44: =vlookup($B44,$B$13:$S$23,month(M$34)+6,0)*(1+$F$31)/(M$33*8.8) -> 46.510406 | N44: =vlookup($B44,$B$13:$S$23,month(N$34)+6,0)*(1+$F$31)/(N$33*8.8) -> 46.510406 | O44: =vlookup($B44,$B$13:$S$23,month(O$34)+6,0)*(1+$F$31)/(O$33*8.8) -> 42.466023 | P44: =vlookup($B44,$B$13:$S$23,month(P$34)+6,0)*(1+$F$31)/(P$33*8.8) -> 51.406238 | ... S44: =vlookup($B44,$B$13:$S$23,month(S$34)+6,0)*(1+$F$31)/(S$33*8.8) -> 46.510406 | T44: =SUMIF(TIMESHEET!E:E,B44,TIMESHEET!N:N) -> 2090.04 | U44: =SUMIF(V44,TRUE,T44) -> 2090.04 | V44: TRUE
B45: Vaneisse Cristina Lima Monteiro | E45: Parcial | F45: Superior Completo | H45: =vlookup($B45,$B$13:$S$23,month(H$34)+6,0)*(1+$F$31)/(H$33*8.8) -> 38.534656 | I45: =vlookup($B45,$B$13:$S$23,month(I$34)+6,0)*(1+$F$31)/(I$33*8.8) -> 49.868378 | J45: =vlookup($B45,$B$13:$S$23,month(J$34)+6,0)*(1+$F$31)/(J$33*8.8) -> 36.859236 | K45: =vlookup($B45,$B$13:$S$23,month(K$34)+6,0)*(1+$F$31)/(K$33*8.8) -> 47.097912 | L45: =vlookup($B45,$B$13:$S$23,month(L$34)+6,0)*(1+$F$31)/(L$33*8.8) -> 40.26869 | M45: =vlookup($B45,$B$13:$S$23,month(M$34)+6,0)*(1+$F$31)/(M$33*8.8) -> 0 | N45: =vlookup($B45,$B$13:$S$23,month(N$34)+6,0)*(1+$F$31)/(N$33*8.8) -> 0 | O45: =vlookup($B45,$B$13:$S$23,month(O$34)+6,0)*(1+$F$31)/(O$33*8.8) -> 0 | ... S45: =vlookup($B45,$B$13:$S$23,month(S$34)+6,0)*(1+$F$31)/(S$33*8.8) -> 0 | T45: =SUMIF(TIMESHEET!E:E,B45,TIMESHEET!N:N) -> 4085.9646 | U45: =SUMIF(V45,TRUE,T45) -> 4085.9646 | V45: TRUE
B46: Alyne Alves Nunes Oliveira | E46: Parcial | F46: Doutorado | H46: =vlookup($B46,$B$13:$S$25,month(H$34)+6,0)*(1+$F$31)/(H$33*8.8) -> 0 | I46: =vlookup($B46,$B$13:$S$25,month(I$34)+6,0)*(1+$F$31)/(I$33*8.8) -> 0 | J46: =vlookup($B46,$B$13:$S$25,month(J$34)+6,0)*(1+$F$31)/(J$33*8.8) -> 0 | K46: =vlookup($B46,$B$13:$S$25,month(K$34)+6,0)*(1+$F$31)/(K$33*8.8) -> 0 | L46: =vlookup($B46,$B$13:$S$25,month(L$34)+6,0)*(1+$F$31)/(L$33*8.8) -> 0 | M46: =vlookup($B46,$B$13:$S$25,month(M$34)+6,0)*(1+$F$31)/(M$33*8.8) -> 0 | N46: =vlookup($B46,$B$13:$S$25,month(N$34)+6,0)*(1+$F$31)/(N$33*8.8) -> 0 | O46: =vlookup($B46,$B$13:$S$25,month(O$34)+6,0)*(1+$F$31)/(O$33*8.8) -> 0 | ... S46: =vlookup($B46,$B$13:$S$25,month(S$34)+6,0)*(1+$F$31)/(S$33*8.8) -> 63.268438 | T46: =SUMIF(TIMESHEET!E:E,B46,TIMESHEET!N:N) -> 3326.3381 | U46: =SUMIF(V46,TRUE,T46) -> 3326.3381 | V46: TRUE
B47: Raissa Bellotti | E47: Parcial | F47: Pós Graduada | H47: =vlookup($B47,$B$13:$S$25,month(H$34)+6,0)*(1+$F$31)/(H$33*8.8) -> 0 | I47: =vlookup($B47,$B$13:$S$25,month(I$34)+6,0)*(1+$F$31)/(I$33*8.8) -> 0 | J47: =vlookup($B47,$B$13:$S$25,month(J$34)+6,0)*(1+$F$31)/(J$33*8.8) -> 0 | K47: =vlookup($B47,$B$13:$S$25,month(K$34)+6,0)*(1+$F$31)/(K$33*8.8) -> 0 | L47: =vlookup($B47,$B$13:$S$25,month(L$34)+6,0)*(1+$F$31)/(L$33*8.8) -> 0 | M47: =vlookup($B47,$B$13:$S$25,month(M$34)+6,0)*(1+$F$31)/(M$33*8.8) -> 0 | N47: =vlookup($B47,$B$13:$S$25,month(N$34)+6,0)*(1+$F$31)/(N$33*8.8) -> 0 | O47: =vlookup($B47,$B$13:$S$25,month(O$34)+6,0)*(1+$F$31)/(O$33*8.8) -> 0 | ... S47: =vlookup($B47,$B$13:$S$25,month(S$34)+6,0)*(1+$F$31)/(S$33*8.8) -> 41.804963 | T47: =SUMIF(TIMESHEET!E:E,B47,TIMESHEET!N:N) -> 4398.5788 | U47: =SUMIF(V47,TRUE,T47) -> 4398.5788 | V47: TRUE
B49: Feriados
B50: 44977 | E50: Carnaval
B51: 44978 | E51: Carnaval
B52: 44979 | E52: Quarta de cinzas
B53: 45023 | E53: Paixão de Cristo
B54: 45037 | E54: Tiradentes
B55: 45047 | E55: Dia do Trabalho
B56: 45085 | E56: Corpus Christi
B57: 45176 | E57: Independência do Brasil
B58: 45177 | E58: Padroeira Curitiba
B59: 45211 | E59: Nossa Senhora - Padroeira do Brasil
B60: 45232 | E60: Finados
B61: 45245 | E61: Proclamação da Republica
B62: 45285 | E62: Natal

Sheet CHECKLIST
B2: PRODIET
B3: Pesquisa ,Desenvolvimento & Inovação
B4: Formulário de PD&I - Ano2023
B5: -preencher somente os campos sombreados (cinza)
B8: Dossiê do projeto
B9: Checklist - outras informações
B11: Área | C11: Item | D11: Descrição | E11: Status | F11: Comentáriocliente | G11: ComentárioMcBenner
B12: RH | C12: Info.funcionários | D12: Listacom:Nome|CPF|Cargo|Qualificação | E12: Parcial | F12: FALTA OS CPFs
B13: RH | C13: Salários | D13: Listacomossaláriosmensaisdosfuncionáriosenvolvidos | E13: Pendente
B14: RH | C14: Feriados | D14: Listacomosferiadosadotadosduranteoanopelaempresa | E14: Pendente
B15: RH | C15: Qtddefuncionários | D15: Informaçãodonúmerototaldefuncionárioscomvínculoempregatício | E15: Pendente
B16: RH | C16: PerfilPrevidenciário | D16: InformaçãoquantoaopçãoINSS|CPRBenocasodetributaçãomista,informarpercentuaismêsamês | E16: Pendente
B17: Contabilidade | C17: Receitalíquida | D17: Valordareceitalíquidanoanobase | E17: Pendente
B18: Contabilidade | C18: Lucro|Prejuízofiscal | D18: InformaçãoqueseráenviadanaECFnoLALUR:valordolucrofiscalprejuízofiscalnoanobase | E18: Pendente
B19: Contabilidade | C19: RAT|FAP | D19: RATeFAPparacálculodoRATajustado | E19: Pendente
B20: Contabilidade | C20: ContabilizaçãoDespesa | D20: RazãocontábilcomacontabilizaçãodetodososinvestimentosemPD&I | E20: Pendente
B21: Desenvolvimento | C21: Evidências | D21: Fotos,esquemas,análisesdocumentaisqueprovemqueo(s)projeto(s)realmenteexiste(m) | E21: Pendente

Sheet Página10
A1: Projeto | B1: Código Protheus | C1: Status
A2: 2018 - Retort | B2: INOV00001 | C2: Vigente
A3: 2019 - Sarcopenia | B3: INOV00003 | C3: Stand-by | F3: Alyne Alves Nunes Oliveira
A4: 2019 - Cicatrização | B4: INOV00004 | C4: Vigente | F4: Ana Claudia Zanini
A5: 2019 - Artesanal | B5: INOV00006 | C5: Vigente | F5: Ana Paula Biz
A6: 2021 - Diamax pó | B6: INOV00010 | C6: Vigente | F6: Ana Paula Celes
A7: 2021 - Marca própria | B7: INOV00012 | C7: Vigente | F7: Camila Mendes Pereira
A8: 2021 - Sachê a vácuo | B8: INOV00013 | C8: Vigente | F8: Gabriela Faria de Oliveira
A9: 2021 - Energyzip 25% | B9: INOV00014 | C9: Vigente | F9: Hellin dos Santos
A10: 2018 - Linha Trophic Soya Líquido | B10: INOV00016 | C10: Vigente | F10: Juliana Lamas Roberto
A11: 2020 - Linha Trophic Soya Pó | B11: INOV00017 | C11: Vigente | F11: Lizianne Angelica Shmeil
A12: 2018 - Trophic Júnior 1.5 Líq | B12: INOV00018 | C12: Stand-by | F12: Luciana Dutra
A13: 2021 - Energyzip Pó | B13: INOV00019 | C13: Stand-by | F13: Rafael Parreira Lorini
A14: 2022 - Peptimax Júnior | B14: INOV00020 | C14: Vigente | F14: Raissa Bellotti
A15: 2022 - Sobremesa | B15: INOV00021 | C15: Vigente | F15: Vaneisse Cristina Lima Monteiro
A16: 2021 - Pesquisa Clínica - Instanth Neo | B16: INOV00022 | C16: Vigente
A17: 2021 - Pesquisa Clínica - Diamax IG | B17: INOV00023 | C17: Vigente
A18: 2021 - Estudo de Caso | B18: INOV00024 | C18: Vigente
A19: 2022 - Tetra Pak SF | B19: INOV00025 | C19: Vigente
A20: 2022 - Projeto Hydra | B20: INOV00026 | C20: Vigente
A21: 2022 - Projeto Pesquisa Básica | B21: INOV00027 | C21: Vigente
A22: 2021 - Pesquisa Aplicada - Resultados P&D | B22: INOV00028 | C22: Vigente
A23: 2021 - Pesquisa Clínica - Hdmax | B23: INOV00029 | C23: Vigente
A24: 2021 - Trophic Dose Única | B24: INOV00030 | C24: Vigente
A25: 2021 - Energyzip Sênior | B25: INOV00031 | C25: Vigente
A26: 2022 - Spray dryer | B26: INOV00032 | C26: Vigente
A27: 2022 - NADA-KSA | B27: INOV00033 | C27: Vigente
... A40: 2023 - PEPTIMAX IBD | B40: INOV00046 | C40: Vigente
A42: 2023 - MIXME MS+PIRAMAL

Sheet TIMESHEET
B2: PRODIET
B3: Pesquisa ,Desenvolvimento & Inovação
B4: Formulário de PD&I - Ano2023
B5: -preencher somente os campos sombreados (cinza)
H6: Treinamento
H7: Pesquisa | I7: → Estudo, pesquisa, prospecção, contato com fornecedor, etc.
B8: Dossiê do projeto | H8: Desenvolvimento | I8: → Análise, Teste, Formulação, etc.
B9: Atividades de Pesquisa, Desenvolvimento e Inovação | H9: Gestão e outros | I9: → Contagem, reunião diretoria, controles financeiros, etc.
N10: =subtotal(9,N12:N1903) -> 548.50303
B11: RowID | C11: Projeto 1 | D11: Etapa | E11: Colaborador | F11: Data | G11: Tempo(h) | H11: Classificação PRODIET | I11: Classificação MCBENNER | K11: Descrição da atividade e observações | L11: Revisão McBenner | M11: Projeto | N11: Custo | O11: Atividade incentiv. | P11: Projeto incentiv.
C12: INOV00001 | D12: =vlookup(M12,'Página10'!A:B,2,false) -> INOV00001 | E12: Ana Paula Celes | F12: 44932 | G12: 0.0625 | H12: Gestão e outros | I12: Desenvolvimento | J12: =I12=H12 -> FALSE | K12: Alinhamento de atividades para testes latco(bags, cestos, tubulações) | M12: 2018 - Retort | N12: 0 | O12: =if(OR(H12="Treinamento",H12="Pesquisa",H12="Desenvolvimento"),TRUE,FALSE) -> FALSE | P12: {=iferror(vlookup($C$12:$C1903,'BD Projetos'!$A:$B,2,false),FALSE)} -> TRUE | Q12: {=vlookup($E$12:$E1903,PESSOAL!B$35:$E$47,4,false)} -> Parcial
C13: INOV00001 | D13: =vlookup(M13,'Página10'!A:B,2,false) -> INOV00001 | E13: Ana Paula Celes | F13: 44932 | G13: 0.041666667 | H13: Desenvolvimento | I13: Desenvolvimento | J13: =I13=H13 -> TRUE | K13: Análise tecnica dos estudos finais de estabilidade | M13: 2018 - Retort | N13: 299.77 | O13: =if(OR(H13="Treinamento",H13="Pesquisa",H13="Desenvolvimento"),TRUE,FALSE) -> TRUE | P13: TRUE | Q13: Parcial
C14: INOV00012 | D14: =vlookup(M14,'Página10'!A:B,2,false) -> INOV00012 | E14: Ana Paula Celes | F14: 44935 | G14: 0.041666667 | H14: Desenvolvimento | I14: Desenvolvimento | J14: =I14=H14 -> TRUE | K14: Construção de processos para Marca Própria | M14: 2021 - Marca própria | N14: 0 | O14: =if(OR(H14="Treinamento",H14="Pesquisa",H14="Desenvolvimento"),TRUE,FALSE) -> TRUE | P14: FALSE | Q14: Parcial
C15: INOV00001 | D15: =vlookup(M15,'Página10'!A:B,2,false) -> INOV00001 | E15: Ana Paula Celes | F15: 44939 | G15: 0.041666667 | H15: Pesquisa | I15: Pesquisa | J15: =I15=H15 -> TRUE | K15: Estudo de plantas pilotos | M15: 2018 - Retort | N15: 299.77 | O15: =if(OR(H15="Treinamento",H15="Pesquisa",H15="Desenvolvimento"),TRUE,FALSE) -> TRUE | P15: TRUE | Q15: Parcial
C16: INOV00001 | D16: =vlookup(M16,'Página10'!A:B,2,false) -> INOV00001 | E16: Ana Paula Celes | F16: 44942 | G16: 0.020833333 | H16: Desenvolvimento | I16: Desenvolvimento | J16: =I16=H16 -> TRUE | K16: Composição de respaldo para NHcF | M16: 2018 - Retort | N16: 149.88 | O16: =if(OR(H16="Treinamento",H16="Pesquisa",H16="Desenvolvimento"),TRUE,FALSE) -> TRUE | P16: TRUE | Q16: Parcial
C17: INOV00001 | D17: =vlookup(M17,'Página10'!A:B,2,false) -> INOV00001 | E17: Ana Paula Celes | F17: 44943 | G17: 0.020833333 | H17: Gestão e outros | I17: Gestão e outros | J17: =I17=H17 -> TRUE | K17: Análises do EE final e aminograma | M17: 2018 - Retort | N17: 0 | O17: =if(OR(H17="Treinamento",H17="Pesquisa",H17="Desenvolvimento"),TRUE,FALSE) -> FALSE | P17: TRUE | Q17: Parcial
C18: INOV00020 | D18: =vlookup(M18,'Página10'!A:B,2,false) -> INOV00020 | E18: Ana Paula Celes | F18: 44951 | G18: 0.083333333 | H18: Desenvolvimento | I18: Desenvolvimento | J18: =I18=H18 -> TRUE | K18: Estudo e análise do briefing | M18: 2022 - Peptimax Júnior | N18: 0 | O18: =if(OR(H18="Treinamento",H18="Pesquisa",H18="Desenvolvimento"),TRUE,FALSE) -> TRUE | P18: FALSE | Q18: Parcial
C19: INOV00004 | D19: =vlookup(M19,'Página10'!A:B,2,false) -> INOV00004 | E19: Ana Paula Celes | F19: 44951 | G19: 0.03125 | H19: Desenvolvimento | I19: Desenvolvimento | J19: =I19=H19 -> TRUE | K19: Degustação para definição das caracteristicas sensorial | M19: 2019 - Cicatrização | N19: 224.82 | O19: =if(OR(H19="Treinamento",H19="Pesquisa",H19="Desenvolvimento"),TRUE,FALSE) -> TRUE | P19: TRUE | Q19: Parcial
C20: INOV00023 | D20: =vlookup(M20,'Página10'!A:B,2,false) -> INOV00023 | E20: Ana Paula Celes | F20: 44959 | G20: 0.041666667 | H20: Pesquisa | I20: Pesquisa | J20: =I20=H20 -> TRUE | K20: discussão de protocolo UFRN | M20: 2021 - Pesquisa Clínica - Diamax IG | N20: 387.93 | O20: =if(OR(H20="Treinamento",H20="Pesquisa",H20="Desenvolvimento"),TRUE,FALSE) -> TRUE | P20: TRUE | Q20: Parcial
C21: INOV00001 | D21: =vlookup(M21,'Página10'!A:B,2,false) -> INOV00001 | E21: Ana Paula Celes | F21: 44960 | G21: 0.020833333 | H21: Pesquisa | I21: Pesquisa | J21: =I21=H21 -> TRUE | K21: fechamento do tema NHcF | M21: 2018 - Retort | N21: 193.97 | O21: =if(OR(H21="Treinamento",H21="Pesquisa",H21="Desenvolvimento"),TRUE,FALSE) -> TRUE | P21: TRUE | Q21: Parcial
C22: INOV00025 | D22: =vlookup(M22,'Página10'!A:B,2,false) -> INOV00025 | E22: Ana Paula Celes | F22: 44963 | G22: 0.020833333 | H22: Desenvolvimento | I22: Desenvolvimento | J22: =I22=H22 -> TRUE | K22: Conhecendo possibilidades de bicos | M22: 2022 - Tetra Pak SF | N22: 0 | O22: =if(OR(H22="Treinamento",H22="Pesquisa",H22="Desenvolvimento"),TRUE,FALSE) -> TRUE | P22: FALSE | Q22: Parcial
C23: INOV00010 | D23: =vlookup(M23,'Página10'!A:B,2,false) -> INOV00010 | E23: Ana Paula Celes | F23: 44963 | G23: 0.041666667 | H23: Desenvolvimento | I23: Desenvolvimento | J23: =I23=H23 -> TRUE | K23: Definindo IN e porção | M23: 2021 - Diamax pó | N23: 387.93 | O23: =if(OR(H23="Treinamento",H23="Pesquisa",H23="Desenvolvimento"),TRUE,FALSE) -> TRUE | P23: TRUE | Q23: Parcial
C24: INOV00001 | D24: =vlookup(M24,'Página10'!A:B,2,false) -> INOV00001 | E24: Ana Paula Celes | F24: 44991 | G24: 0.041666667 | H24: Desenvolvimento | I24: Desenvolvimento | J24: =I24=H24 -> TRUE | K24: Definição dos testes na Embrapa | M24: 2018 - Retort | N24: 286.73 | O24: =if(OR(H24="Treinamento",H24="Pesquisa",H24="Desenvolvimento"),TRUE,FALSE) -> TRUE | P24: TRUE | Q24: Parcial
... C697: INOV00041 | D697: =vlookup(M697,'Página10'!A:B,2,false) -> INOV00041 | E697: Ana Paula Celes | F697: 45020 | G697: 0.041666667 | H697: Pesquisa | I697: Pesquisa | J697: =I697=H697 -> TRUE | K697: Alinhamento de atividades para primeira compra | M697: 2023 - PROTEÍNA LÍQUIDA | N697: 0 | O697: =if(OR(H697="Treinamento",H697="Pesquisa",H697="Desenvolvimento"),TRUE,FALSE) -> TRUE | P697: TRUE | Q697: Parcial
C698: INOV00025 | D698: =vlookup(M698,'Página10'!A:B,2,false) -> INOV00025 | E698: Ana Paula Celes | F698: 45020 | G698: 0.020833333 | H698: Desenvolvimento | I698: Desenvolvimento | J698: =I698=H698 -> TRUE | K698: Alinhamento semanal | M698: 2022 - Tetra Pak SF | N698: =if(and(O698=TRUE,P698=TRUE), VLOOKUP($E698,PESSOAL!$B$35:$S$45,MONTH($F698)+6,false)*G698*24,0) -> 0 | O698: =if(OR(H698="Treinamento",H698="Pesquisa",H698="Desenvolvimento"),TRUE,FALSE) -> TRUE | P698: FALSE | Q698: Parcial
C699: INOV00024 | D699: =vlookup(M699,'Página10'!A:B,2,false) -> INOV00024 | E699: Ana Paula Celes | F699: 45020 | G699: 0.020833333 | H699: Pesquisa | I699: Pesquisa | J699: =I699=H699 -> TRUE | K699: Alinhamentos de parceria | M699: 2021 - Estudo de Caso | N699: =if(and(O699=TRUE,P699=TRUE), VLOOKUP($E699,PESSOAL!$B$35:$S$45,MONTH($F699)+6,false)*G699*24,0) -> 184.30813 | O699: =if(OR(H699="Treinamento",H699="Pesquisa",H699="Desenvolvimento"),TRUE,FALSE) -> TRUE | P699: TRUE | Q699: Parcial
C700: INOV00001 | D700: =vlookup(M700,'Página10'!A:B,2,false) -> INOV00001 | E700: Ana Paula Celes | F700: 45027 | G700: 0.020833333 | H700: Desenvolvimento | I700: Desenvolvimento | J700: =I700=H700 -> TRUE | K700: Definição de Marca para produto | M700: 2018 - Retort | N700: =if(and(O700=TRUE,P700=TRUE), VLOOKUP($E700,PESSOAL!$B$35:$S$45,MONTH($F700)+6,false)*G700*24,0) -> 184.30813 | O700: =if(OR(H700="Treinamento",H700="Pesquisa",H700="Desenvolvimento"),TRUE,FALSE) -> TRUE | P700: TRUE | Q700: Parcial
C701: INOV00004 | D701: =vlookup(M701,'Página10'!A:B,2,false) -> INOV00004 | E701: Ana Paula Celes | F701: 45030 | G701: 0.041666667 | H701: Desenvolvimento | I701: Desenvolvimento | J701: =I701=H701 -> TRUE | K701: Alinhamento dos dados de BC | M701: 2019 - Cicatrização | N701: =if(and(O701=TRUE,P701=TRUE), VLOOKUP($E701,PESSOAL!$B$35:$S$45,MONTH($F701)+6,false)*G701*24,0) -> 368.61626 | O701: =if(OR(H701="Treinamento",H701="Pesquisa",H701="Desenvolvimento"),TRUE,FALSE) -> TRUE | P701: TRUE | Q701: Parcial
C702: INOV00020 | D702: =vlookup(M702,'Página10'!A:B,2,false) -> INOV00020 | E702: Ana Paula Celes | F702: 45030 | G702: 0.020833333 | H702: Desenvolvimento | I702: Desenvolvimento | J702: =I702=H702 -> TRUE | K702: Alinhamento modulo whey criança | M702: 2022 - Peptimax Júnior | N702: =if(and(O702=TRUE,P702=TRUE), VLOOKUP($E702,PESSOAL!$B$35:$S$45,MONTH($F702)+6,false)*G702*24,0) -> 0 | O702: =if(OR(H702="Treinamento",H702="Pesquisa",H702="Desenvolvimento"),TRUE,FALSE) -> TRUE | P702: FALSE | Q702: Parcial
C703: INOV00019 | D703: =vlookup(M703,'Página10'!A:B,2,false) -> INOV00019 | E703: Ana Paula Celes | F703: 45030 | G703: 0.020833333 | H703: Desenvolvimento | I703: Desenvolvimento | J703: =I703=H703 -> TRUE | K703: Alinhamento dos dados de BC | M703: 2021 - Energyzip Pó | N703: =if(and(O703=TRUE,P703=TRUE), VLOOKUP($E703,PESSOAL!$B$35:$S$45,MONTH($F703)+6,false)*G703*24,0) -> 0 | O703: =if(OR(H703="Treinamento",H703="Pesquisa",H703="Desenvolvimento"),TRUE,FALSE) -> TRUE | P703: FALSE | Q703: Parcial
C704: INOV00021 | D704: =vlookup(M704,'Página10'!A:B,2,false) -> INOV00021 | E704: Ana Paula Celes | F704: 45041 | G704: 0.020833333 | H704: Desenvolvimento | I704: Desenvolvimento | J704: =I704=H704 -> TRUE | K704: Alinhamento final de produto | M704: 2022 - Sobremesa | N704: =if(and(O704=TRUE,P704=TRUE), VLOOKUP($E704,PESSOAL!$B$35:$S$45,MONTH($F704)+6,false)*G704*24,0) -> 184.30813 | O704: =if(OR(H704="Treinamento",H704="Pesquisa",H704="Desenvolvimento"),TRUE,FALSE) -> TRUE | P704: TRUE | Q704: Parcial
C705: INOV00001 | D705: =vlookup(M705,'Página10'!A:B,2,false) -> INOV00001 | E705: Ana Paula Celes | F705: 45042 | G705: 0.0625 | H705: Gestão e outros | I705: Gestão e outros | J705: =I705=H705 -> TRUE | K705: Definindo as linhas de embalagens e layout | M705: 2018 - Retort | N705: =if(and(O705=TRUE,P705=TRUE), VLOOKUP($E705,PESSOAL!$B$35:$S$45,MONTH($F705)+6,false)*G705*24,0) -> 0 | O705: =if(OR(H705="Treinamento",H705="Pesquisa",H705="Desenvolvimento"),TRUE,FALSE) -> FALSE | P705: TRUE | Q705: Parcial
C706: INOV00041 | D706: =vlookup(M706,'Página10'!A:B,2,false) -> INOV00041 | E706: Ana Paula Celes | F706: 45044 | G706: 0.0625 | H706: Desenvolvimento | I706: Desenvolvimento | J706: =I706=H706 -> TRUE | K706: Round cientifico | M706: 2023 - PROTEÍNA LÍQUIDA | N706: 0 | O706: =if(OR(H706="Treinamento",H706="Pesquisa",H706="Desenvolvimento"),TRUE,FALSE) -> TRUE | P706: TRUE | Q706: Parcial
C707: INOV00021 | D707: =vlookup(M707,'Página10'!A:B,2,false) -> INOV00021 | E707: Ana Paula Celes | F707: 45044 | G707: 0.020833333 | H707: Desenvolvimento | I707: Desenvolvimento | J707: =I707=H707 -> TRUE | K707: Alinhamento de custo | M707: 2022 - Sobremesa | N707: =if(and(O707=TRUE,P707=TRUE), VLOOKUP($E707,PESSOAL!$B$35:$S$45,MONTH($F707)+6,false)*G707*24,0) -> 184.30813 | O707: =if(OR(H707="Treinamento",H707="Pesquisa",H707="Desenvolvimento"),TRUE,FALSE) -> TRUE | P707: TRUE | Q707: Parcial
C708: INOV00037 | D708: =vlookup(M708,'Página10'!A:B,2,false) -> INOV00037 | E708: Ana Paula Celes | F708: 45051 | G708: 0.020833333 | H708: Pesquisa | I708: Pesquisa | J708: =I708=H708 -> TRUE | K708: Direcionais da pesquisa | M708: 2023 - PESQUISA CLÍNICA - IMMAX | N708: =if(and(O708=TRUE,P708=TRUE), VLOOKUP($E708,PESSOAL!$B$35:$S$45,MONTH($F708)+6,false)*G708*24,0) -> 150.79756 | O708: =if(OR(H708="Treinamento",H708="Pesquisa",H708="Desenvolvimento"),TRUE,FALSE) -> TRUE | P708: TRUE | Q708: Parcial
C709: INOV00021 | D709: =vlookup(M709,'Página10'!A:B,2,false) -> INOV00021 | E709: Ana Paula Celes | F709: 45058 | G709: 0.041666667 | H709: Desenvolvimento | I709: Desenvolvimento | J709: =I709=H709 -> TRUE | K709: Avaliação de BC | M709: 2022 - Sobremesa | N709: =if(and(O709=TRUE,P709=TRUE), VLOOKUP($E709,PESSOAL!$B$35:$S$45,MONTH($F709)+6,false)*G709*24,0) -> 301.59512 | O709: =if(OR(H709="Treinamento",H709="Pesquisa",H709="Desenvolvimento"),TRUE,FALSE) -> TRUE | P709: TRUE | Q709: Parcial
C710: INOV00004 | D710: =vlookup(M710,'Página10'!A:B,2,false) -> INOV00004 | E710: Ana Paula Celes | F710: 45061 | G710: 0.041666667 | H710: Gestão e outros | I710: Gestão e outros | J710: =I710=H710 -> TRUE | K710: Apresentação do BC | M710: 2019 - Cicatrização | N710: =if(and(O710=TRUE,P710=TRUE), VLOOKUP($E710,PESSOAL!$B$35:$S$45,MONTH($F710)+6,false)*G710*24,0) -> 0 | O710: =if(OR(H710="Treinamento",H710="Pesquisa",H710="Desenvolvimento"),TRUE,FALSE) -> FALSE | P710: TRUE | Q710: Parcial
C711: INOV00041 | D711: =vlookup(M711,'Página10'!A:B,2,false) -> INOV00041 | E711: Ana Paula Celes | F711: 45061 | G711: 0.041666667 | H711: Desenvolvimento | I711: Desenvolvimento | J711: =I711=H711 -> TRUE | K711: Apresentação e alinhamento do produto | M711: 2023 - PROTEÍNA LÍQUIDA | N711: 0 | O711: =if(OR(H711="Treinamento",H711="Pesquisa",H711="Desenvolvimento"),TRUE,FALSE) -> TRUE | P711: TRUE | Q711: Parcial
C712: INOV00020 | D712: =vlookup(M712,'Página10'!A:B,2,false) -> INOV00020 | E712: Ana Paula Celes | F712: 45064 | G712: 0.041666667 | H712: Desenvolvimento | I712: Desenvolvimento | J712: =I712=H712 -> TRUE | K712: Apresentação e alinhamento do produto | M712: 2022 - Peptimax Júnior | N712: =if(and(O712=TRUE,P712=TRUE), VLOOKUP($E712,PESSOAL!$B$35:$S$45,MONTH($F712)+6,false)*G712*24,0) -> 0 | O712: =if(OR(H712="Treinamento",H712="Pesquisa",H712="Desenvolvimento"),TRUE,FALSE) -> TRUE | P712: FALSE | Q712: Parcial
C713: INOV00041 | D713: =vlookup(M713,'Página10'!A:B,2,false) -> INOV00041 | E713: Ana Paula Celes | F713: 45065 | G713: 0.041666667 | H713: Desenvolvimento | I713: Desenvolvimento | J713: =I713=H713 -> TRUE | K713: Apresentação e alinhamento do produto | M713: 2023 - PROTEÍNA LÍQUIDA | N713: 0 | O713: =if(OR(H713="Treinamento",H713="Pesquisa",H713="Desenvolvimento"),TRUE,FALSE) -> TRUE | P713: TRUE | Q713: Parcial
C714: INOV00041 | D714: =vlookup(M714,'Página10'!A:B,2,false) -> INOV00041 | E714: Ana Paula Celes | F714: 45077 | G714: 0.041666667 | H714: Desenvolvimento | I714: Desenvolvimento | J714: =I714=H714 -> TRUE | K714: Apresentação e alinhamento do produto | M714: 2023 - PROTEÍNA LÍQUIDA | N714: 0 | O714: =if(OR(H714="Treinamento",H714="Pesquisa",H714="Desenvolvimento"),TRUE,FALSE) -> TRUE | P714: TRUE | Q714: Parcial
C715: INOV00006 | D715: =vlookup(M715,'Página10'!A:B,2,false) -> INOV00006 | E715: Ana Paula Celes | F715: 45079 | G715: 0.041666667 | H715: Desenvolvimento | I715: Desenvolvimento | J715: =I715=H715 -> TRUE | K715: Reestudo de ingredientes | M715: 2019 - Artesanal | N715: =if(and(O715=TRUE,P715=TRUE), VLOOKUP($E715,PESSOAL!$B$35:$S$45,MONTH($F715)+6,false)*G715*24,0) -> 330.17483 | O715: =if(OR(H715="Treinamento",H715="Pesquisa",H715="Desenvolvimento"),TRUE,FALSE) -> TRUE | P715: TRUE | Q715: Parcial
C716: INOV00001 | D716: =vlookup(M716,'Página10'!A:B,2,false) -> INOV00001 | E716: Ana Paula Celes | F716: 45052 | G716: 0.020833333 | H716: Desenvolvimento | I716: Desenvolvimento | J716: =I716=H716 -> TRUE | K716: Alinhamentos para teste industrial | M716: 2018 - Retort | N716: =if(and(O716=TRUE,P716=TRUE), VLOOKUP($E716,PESSOAL!$B$35:$S$45,MONTH($F716)+6,false)*G716*24,0) -> 150.79756 | O716: =if(OR(H716="Treinamento",H716="Pesquisa",H716="Desenvolvimento"),TRUE,FALSE) -> TRUE | P716: TRUE | Q716: Parcial
C717: INOV00022 | D717: =vlookup(M717,'Página10'!A:B,2,false) -> INOV00022 | E717: Ana Paula Celes | F717: 45099 | G717: 0.020833333 | H717: Pesquisa | I717: Pesquisa | J717: =I717=H717 -> TRUE | K717: Alinhamento para pesquisa/serie de casos | M717: 2021 - Pesquisa Clínica - Instanth Neo | N717: =if(and(O717=TRUE,P717=TRUE), VLOOKUP($E717,PESSOAL!$B$35:$S$45,MONTH($F717)+6,false)*G717*24,0) -> 165.08742 | O717: =if(OR(H717="Treinamento",H717="Pesquisa",H717="Desenvolvimento"),TRUE,FALSE) -> TRUE | P717: TRUE | Q717: Parcial
C718: INOV00017 | D718: =vlookup(M718,'Página10'!A:B,2,false) -> INOV00017 | E718: Ana Paula Celes | F718: 45104 | G718: 0.041666667 | H718: Desenvolvimento | I718: Desenvolvimento | J718: =I718=H718 -> TRUE | K718: Análise sensorial | M718: 2020 - Linha Trophic Soya Pó | N718: =if(and(O718=TRUE,P718=TRUE), VLOOKUP($E718,PESSOAL!$B$35:$S$45,MONTH($F718)+6,false)*G718*24,0) -> 330.17483 | O718: =if(OR(H718="Treinamento",H718="Pesquisa",H718="Desenvolvimento"),TRUE,FALSE) -> TRUE | P718: TRUE | Q718: Parcial
C719: INOV00022 | D719: =vlookup(M719,'Página10'!A:B,2,false) -> INOV00022 | E719: Ana Claudia Zanini | F719: 45019 | G719: 0.0625 | H719: Pesquisa | I719: Pesquisa | J719: =I719=H719 -> TRUE | K719: Pesquisa básica - Revisão de literatura sobre de desfechos de estudos | M719: 2021 - Pesquisa Clínica - Instanth Neo | N719: =if(and(O719=TRUE,P719=TRUE), VLOOKUP($E719,PESSOAL!$B$35:$S$45,MONTH($F719)+6,false)*G719*24,0) -> 81.782693 | O719: =if(OR(H719="Treinamento",H719="Pesquisa",H719="Desenvolvimento"),TRUE,FALSE) -> TRUE | P719: TRUE | Q719: Parcial
C720: INOV00029 | D720: =vlookup(M720,'Página10'!A:B,2,false) -> INOV00029 | E720: Ana Claudia Zanini | F720: 45019 | G720: 0.083333333 | H720: Pesquisa | I720: Pesquisa | J720: =I720=H720 -> TRUE | K720: Pesquisa básica - Revisão de literatura sobre de desfechos de estudos | M720: 2021 - Pesquisa Clínica - Hdmax | N720: =if(and(O720=TRUE,P720=TRUE), VLOOKUP($E720,PESSOAL!$B$35:$S$45,MONTH($F720)+6,false)*G720*24,0) -> 0 | O720: =if(OR(H720="Treinamento",H720="Pesquisa",H720="Desenvolvimento"),TRUE,FALSE) -> TRUE | P720: FALSE | Q720: Parcial
C721: INOV00041 | D721: =vlookup(M721,'Página10'!A:B,2,false) -> INOV00041 | E721: Ana Claudia Zanini | F721: 45020 | G721: 0.125 | H721: Pesquisa | I721: Pesquisa | J721: =I721=H721 -> TRUE | K721: Pesquisa básica para desenvolvimento de novo produto | M721: 2023 - PROTEÍNA LÍQUIDA | N721: 0 | O721: =if(OR(H721="Treinamento",H721="Pesquisa",H721="Desenvolvimento"),TRUE,FALSE) -> TRUE | P721: TRUE | Q721: Parcial
C722: INOV00024 | D722: =vlookup(M722,'Página10'!A:B,2,false) -> INOV00024 | E722: Ana Claudia Zanini | F722: 45020 | G722: 0.041666667 | H722: Pesquisa | I722: Pesquisa | J722: =I722=H722 -> TRUE | K722: Pesquisa Clínica - Revisão de literatura sobre ferramentas de avaliação de desfechos clínicos | M722: 2021 - Estudo de Caso | N722: =if(and(O722=TRUE,P722=TRUE), VLOOKUP($E722,PESSOAL!$B$35:$S$45,MONTH($F722)+6,false)*G722*24,0) -> 54.521795 | O722: =if(OR(H722="Treinamento",H722="Pesquisa",H722="Desenvolvimento"),TRUE,FALSE) -> TRUE | P722: TRUE | Q722: Parcial
C723: INOV00024 | D723: =vlookup(M723,'Página10'!A:B,2,false) -> INOV00024 | E723: Ana Claudia Zanini | F723: 45021 | G723: 0.041666667 | H723: Pesquisa | I723: Pesquisa | J723: =I723=H723 -> TRUE | K723: Pesquisa básica para desenvolvimento de protocolo de relato de caso | M723: 2021 - Estudo de Caso | N723: =if(and(O723=TRUE,P723=TRUE), VLOOKUP($E723,PESSOAL!$B$35:$S$45,MONTH($F723)+6,false)*G723*24,0) -> 54.521795 | O723: =if(OR(H723="Treinamento",H723="Pesquisa",H723="Desenvolvimento"),TRUE,FALSE) -> TRUE | P723: TRUE | Q723: Parcial
C724: INOV00029 | D724: =vlookup(M724,'Página10'!A:B,2,false) -> INOV00029 | E724: Ana Claudia Zanini | F724: 45021 | G724: 0.083333333 | H724: Pesquisa | I724: Pesquisa | J724: =I724=H724 -> TRUE | K724: Pesquisa básica para desenvolvimento de resumo cientifico para congresso | M724: 2021 - Pesquisa Clínica - Hdmax | N724: =if(and(O724=TRUE,P724=TRUE), VLOOKUP($E724,PESSOAL!$B$35:$S$45,MONTH($F724)+6,false)*G724*24,0) -> 0 | O724: =if(OR(H724="Treinamento",H724="Pesquisa",H724="Desenvolvimento"),TRUE,FALSE) -> TRUE | P724: FALSE | Q724: Parcial
C725: INOV00041 | D725: =vlookup(M725,'Página10'!A:B,2,false) -> INOV00041 | E725: Ana Claudia Zanini | F725: 45021 | G725: 0.083333333 | H725: Pesquisa | I725: Pesquisa | J725: =I725=H725 -> TRUE | K725: Pesquisa básica para desenvolvimento de novo produto | M725: 2023 - PROTEÍNA LÍQUIDA | N725: 0 | O725: =if(OR(H725="Treinamento",H725="Pesquisa",H725="Desenvolvimento"),TRUE,FALSE) -> TRUE | P725: TRUE | Q725: Parcial
C726: INOV00041 | D726: =vlookup(M726,'Página10'!A:B,2,false) -> INOV00041 | E726: Ana Claudia Zanini | F726: 45021 | G726: 0.083333333 | H726: Pesquisa | I726: Pesquisa | J726: =I726=H726 -> TRUE | K726: Pesquisa básica para desenvolvimento de novo produto | M726: 2023 - PROTEÍNA LÍQUIDA | N726: 0 | O726: =if(OR(H726="Treinamento",H726="Pesquisa",H726="Desenvolvimento"),TRUE,FALSE) -> TRUE | P726: TRUE | Q726: Parcial
C727: INOV00024 | D727: =vlookup(M727,'Página10'!A:B,2,false) -> INOV00024 | E727: Ana Claudia Zanini | F727: 45021 | G727: 0.041666667 | H727: Desenvolvimento | I727: Desenvolvimento | J727: =I727=H727 -> TRUE | K727: Prospecção de centro para realização de Relato de caso e definição de protocolo | M727: 2021 - Estudo de Caso | N727: =if(and(O727=TRUE,P727=TRUE), VLOOKUP($E727,PESSOAL!$B$35:$S$45,MONTH($F727)+6,false)*G727*24,0) -> 54.521795 | O727: =if(OR(H727="Treinamento",H727="Pesquisa",H727="Desenvolvimento"),TRUE,FALSE) -> TRUE | P727: TRUE | Q727: Parcial
C728: INOV00029 | D728: =vlookup(M728,'Página10'!A:B,2,false) -> INOV00029 | E728: Ana Claudia Zanini | F728: 45026 | G728: 0.125 | H728: Pesquisa | I728: Pesquisa | J728: =I728=H728 -> TRUE | K728: Pesquisa básica para desenvolvimento de resumo cientifico para congresso | M728: 2021 - Pesquisa Clínica - Hdmax | N728: =if(and(O728=TRUE,P728=TRUE), VLOOKUP($E728,PESSOAL!$B$35:$S$45,MONTH($F728)+6,false)*G728*24,0) -> 0 | O728: =if(OR(H728="Treinamento",H728="Pesquisa",H728="Desenvolvimento"),TRUE,FALSE) -> TRUE | P728: FALSE | Q728: Parcial
C729: INOV00029 | D729: =vlookup(M729,'Página10'!A:B,2,false) -> INOV00029 | E729: Ana Claudia Zanini | F729: 45027 | G729: 0.125 | H729: Pesquisa | I729: Pesquisa | J729: =I729=H729 -> TRUE | K729: Pesquisa básica para desenvolvimento de resumo cientifico para congresso | M729: 2021 - Pesquisa Clínica - Hdmax | N729: =if(and(O729=TRUE,P729=TRUE), VLOOKUP($E729,PESSOAL!$B$35:$S$45,MONTH($F729)+6,false)*G729*24,0) -> 0 | O729: =if(OR(H729="Treinamento",H729="Pesquisa",H729="Desenvolvimento"),TRUE,FALSE) -> TRUE | P729: FALSE | Q729: Parcial
C730: INOV00041 | D730: =vlookup(M730,'Página10'!A:B,2,false) -> INOV00041 | E730: Ana Claudia Zanini | F730: 45027 | G730: 0.125 | H730: Pesquisa | I730: Pesquisa | J730: =I730=H730 -> TRUE | K730: Pesquisa básica para desenvolvimento de novo produto | M730: 2023 - PROTEÍNA LÍQUIDA | N730: 0 | O730: =if(OR(H730="Treinamento",H730="Pesquisa",H730="Desenvolvimento"),TRUE,FALSE) -> TRUE | P730: TRUE | Q730: Parcial
C731: INOV00041 | D731: =vlookup(M731,'Página10'!A:B,2,false) -> INOV00041 | E731: Ana Claudia Zanini | F731: 45029 | G731: 0.16666667 | H731: Pesquisa | I731: Pesquisa | J731: =I731=H731 -> TRUE | K731: Pesquisa básica para desenvolvimento de novo produto | M731: 2023 - PROTEÍNA LÍQUIDA | N731: 0 | O731: =if(OR(H731="Treinamento",H731="Pesquisa",H731="Desenvolvimento"),TRUE,FALSE) -> TRUE | P731: TRUE | Q731: Parcial
C732: INOV00041 | D732: =vlookup(M732,'Página10'!A:B,2,false) -> INOV00041 | E732: Ana Claudia Zanini | F732: 45030 | G732: 0.125 | H732: Pesquisa | I732: Pesquisa | J732: =I732=H732 -> TRUE | K732: Pesquisa básica para desenvolvimento de novo produto | M732: 2023 - PROTEÍNA LÍQUIDA | N732: 0 | O732: =if(OR(H732="Treinamento",H732="Pesquisa",H732="Desenvolvimento"),TRUE,FALSE) -> TRUE | P732: TRUE | Q732: Parcial
C733: INOV00041 | D733: =vlookup(M733,'Página10'!A:B,2,false) -> INOV00041 | E733: Ana Claudia Zanini | F733: 45034 | G733: 0.083333333 | H733: Pesquisa | I733: Pesquisa | J733: =I733=H733 -> TRUE | K733: Pesquisa básica para desenvolvimento de protocolo de teste de produto | M733: 2023 - PROTEÍNA LÍQUIDA | N733: 0 | O733: =if(OR(H733="Treinamento",H733="Pesquisa",H733="Desenvolvimento"),TRUE,FALSE) -> TRUE | P733: TRUE | Q733: Parcial
