Workbook

Sheet Base Projetos
B1: Incentivado pela Lei do Bem | C1: Objetiva tornar-se um Ativo | D1: Objetiva gerar patente/registro
A2: INOV00001 | B2: TRUE | C2: FALSE | D2: FALSE
A3: INOV00004 | B3: TRUE | C3: FALSE | D3: FALSE
A4: INOV00006 | B4: TRUE | C4: FALSE | D4: FALSE
A5: INOV00010 | B5: TRUE | C5: FALSE | D5: FALSE
A6: INOV00013 | B6: TRUE | C6: FALSE | D6: FALSE
A7: INOV00014 | B7: TRUE | C7: FALSE | D7: FALSE
A8: INOV00016 | B8: TRUE | C8: FALSE | D8: FALSE
A9: INOV00017 | B9: TRUE | C9: FALSE | D9: FALSE
A10: INOV00020 | B10: FALSE | C10: FALSE | D10: FALSE
A11: INOV00022 | B11: TRUE | C11: FALSE | D11: FALSE
A12: INOV00023 | B12: TRUE | C12: FALSE | D12: FALSE
A13: INOV00024 | B13: TRUE | C13: FALSE | D13: FALSE
A14: INOV00025 | B14: TRUE | C14: FALSE | D14: FALSE | E14: New | F14: Tampa
A15: INOV00027 | B15: FALSE | C15: FALSE | D15: FALSE
A16: INOV00029 | B16: TRUE | C16: FALSE | D16: FALSE | E16: New | F16: (Pesquisa)
A17: INOV00032 | B17: TRUE | C17: FALSE | D17: FALSE | E17: New | F17: (Spray)
A18: INOV00035 | B18: TRUE | C18: FALSE | D18: FALSE
A19: INOV00036 | B19: TRUE | C19: FALSE | D19: FALSE
A20: INOV00037 | B20: TRUE | C20: FALSE | D20: FALSE
A21: INOV00038 | B21: TRUE | C21: FALSE | D21: FALSE
A22: INOV00039 | B22: TRUE | C22: FALSE | D22: FALSE
A23: INOV00041 | B23: TRUE | C23: FALSE | D23: FALSE
A24: INOV00046 | B24: FALSE | C24: FALSE | D24: FALSE | E24: Perguntar | F24: aguardando resposta
A25: INOV00047 | B25: FALSE | C25: FALSE | D25: FALSE | E25: iguais | F25: aguardando resposta
A26: INOV00048 | B26: FALSE | C26: FALSE | D26: FALSE | E26: iguais | F26: aguardando resposta
A27: INOV00049 | B27: FALSE | C27: FALSE | D27: FALSE | E27: Perguntar | F27: aguardando resposta
A28: INOV00050 | B28: FALSE | C28: FALSE | D28: FALSE | E28: Perguntar | F28: aguardando resposta
A29: INOV00051 | B29: FALSE | C29: FALSE | D29: FALSE | E29: Perguntar | F29: aguardando resposta
A30: INOV00052 | B30: FALSE | C30: FALSE | D30: FALSE | E30: Solicitar | F30: aguardando resposta

Sheet RESUMO
B2: Resumo dos investimentos
B3: BENEFÍCIO FISCAL DE PD&I 2024
B5: PRODIET NUTRIÇÃO CLINICA LTDA | F5: CNPJ 08.183.359/0001-53 | H5: 2019-088 PRODIET
B6: Rua General Potiguara, 1428, Lotes 20 e 21, Novo Mundo - PR - SUL - CURITIBA - CEP 81.050-500 - fone: (41) 3342-2825 | H6: =TODAY() -> 46168
B8: Natureza | C8: 1º Trimestre | D8: 2º Trimestre | E8: 3º Trimestre | F8: 4º Trimestre | H8: TOTAL
B9: Material | C9: - | D9: - | E9: - | F9: - | H9: =sum(C9:F9) -> 0
B10: Terceiros | C10: =IFERROR(__xludf.DUMMYFUNCTION("iferror(sum(filter(TERCEIROS!$M12:$M71,month(TERCEIROS!$I12:$I71)>=1,month(TERCEIROS!$I12:$I71)<=3)),0)"),36035.1) -> 36035.1 | D10: =IFERROR(__xludf.DUMMYFUNCTION("iferror(sum(filter(TERCEIROS!$M12:$M71,month(TERCEIROS!$I12:$I71)>=4,month(TERCEIROS!$I12:$I71)<=6)),0)"),162191.78) -> 162191.78 | E10: =IFERROR(__xludf.DUMMYFUNCTION("iferror(sum(filter(TERCEIROS!$M12:$M71,month(TERCEIROS!$I12:$I71)>=7,month(TERCEIROS!$I12:$I71)<=9)),0)"),132155.385) -> 132155.39 | F10: =IFERROR(__xludf.DUMMYFUNCTION("iferror(sum(filter(TERCEIROS!$M12:$M71,month(TERCEIROS!$I12:$I71)>=10,month(TERCEIROS!$I12:$I71)<=12)),0)"),32886.7) -> 32886.7 | H10: =sum(C10:F10) -> 363268.97
B11: RH (Parcial inovação) | C11: =IFERROR(__xludf.DUMMYFUNCTION("iferror(sum(filter(TIMESHEET!$N$12:$N71,TIMESHEET!$Q$12:$Q71=""Parcial"",month(TIMESHEET!$F$12:$F71)>=1,month(TIMESHEET!$F$12:$F71)<=3)),0)-0.06"),15366.9) -> 15366.9 | D11: =IFERROR(__xludf.DUMMYFUNCTION("iferror(sum(filter(TIMESHEET!$N$12:$N71,TIMESHEET!$Q$12:$Q71=""Parcial"",month(TIMESHEET!$F$12:$F71)>=4,month(TIMESHEET!$F$12:$F71)<=6)),0)"),37022.72820846256) -> 37022.728 | E11: =IFERROR(__xludf.DUMMYFUNCTION("iferror(sum(filter(TIMESHEET!$N$12:$N71,TIMESHEET!$Q$12:$Q71=""Parcial"",month(TIMESHEET!$F$12:$F71)>=7,month(TIMESHEET!$F$12:$F71)<=9)),0)"),34877.28698090117) -> 34877.287 | F11: =IFERROR(__xludf.DUMMYFUNCTION("iferror(sum(filter(TIMESHEET!$N$12:$N71,TIMESHEET!$Q$12:$Q71=""Parcial"",month(TIMESHEET!$F$12:$F71)>=10,month(TIMESHEET!$F$12:$F71)<=12)),0)"),12531.24418370417) -> 12531.244 | H11: =sum(C11:F11) -> 99798.159
B12: RH (Exclusivo inovação) | C12: =IFERROR(__xludf.DUMMYFUNCTION("iferror(sum(filter(TIMESHEET!$N$12:$N71,TIMESHEET!$Q$12:$Q71=""Exclusivo"",month(TIMESHEET!$F$12:$F71)>=1,month(TIMESHEET!$F$12:$F71)<=3)),0)"),0.0) -> 0 | D12: =IFERROR(__xludf.DUMMYFUNCTION("iferror(sum(filter(TIMESHEET!$N$12:$N71,TIMESHEET!$Q$12:$Q71=""Exclusivo"",month(TIMESHEET!$F$12:$F71)>=4,month(TIMESHEET!$F$12:$F71)<=6)),0)"),0.0) -> 0 | E12: =IFERROR(__xludf.DUMMYFUNCTION("iferror(sum(filter(TIMESHEET!$N$12:$N71,TIMESHEET!$Q$12:$Q71=""Exclusivo"",month(TIMESHEET!$F$12:$F71)>=7,month(TIMESHEET!$F$12:$F71)<=9)),0)"),0.0) -> 0 | F12: =IFERROR(__xludf.DUMMYFUNCTION("iferror(sum(filter(TIMESHEET!$N$12:$N71,TIMESHEET!$Q$12:$Q71=""Exclusivo"",month(TIMESHEET!$F$12:$F71)>=10,month(TIMESHEET!$F$12:$F71)<=12)),0)"),0.0) -> 0 | H12: =sum(C12:F12) -> 0
B13: Total 1 | C13: =sum(C10:C12) -> 51402 | D13: =sum(D10:D12) -> 199214.51 | E13: =sum(E10:E12) -> 167032.67 | F13: =sum(F10:F12) -> 45417.944 | H13: =sum(C13:F13) -> 463067.12
B14: Percentual Exclusão | C14: 0.6 | D14: 0.6 | E14: 0.6 | F14: 0.6 | H14: 0.6
B15: Exclusão da Base de cálculo do IRPJ e CSLL | C15: =C13*C14 -> 30841.2 | D15: =D13*D14 -> 119528.7 | E15: =E13*E14 -> 100219.6 | F15: =F13*F14 -> 27250.767 | H15: =sum(C15:F15) -> 277840.27
B17: Economia Estimada [34%] | C17: =C15*34% -> 10486.008 | D17: =D15*34% -> 40639.76 | E17: =E15*34% -> 34074.665 | F17: =F15*34% -> 9265.2606 | H17: =sum(C17:F17) -> 94465.693
B18: Comissão McBenner | C18: =C17*0.1 -> 1048.6008 | D18: =D17*0.1 -> 4063.976 | E18: =E17*0.1 -> 3407.4665 | F18: =F17*0.1 -> 926.52606 | H18: =sum(C18:F18) -> 9446.5693
B20: Observações:
B21: 1. Os dispêndios devem ser registrados na contabilidade em conta específica
B22: 2. O benefício deve ser aproveitado na ECF do respectivo ano/competência
B23: 3. O formulário do MCTIC (governo) deve ser enviado até fim de Julho/2025
B24: 4. Os projetos estão descritos em arquivo a parte a ser anexado no FORM PD&I
B25: 5. Alguns benefícios previstos na Lei do Bem não foram utilizados:
B26: --- 5.1. Depreciação acelerada
B27: --- 5.2. Redução de IPI na aquisição de equipamento para PD&I
B29: Equipe de PD&I
B30: Quadro de resumo | C30: Dedicação Parcial | F30: Dedicação Exclusiva
C31: Qtd | D31: Valor gasto | E31: Horas | F31: Qtd | G31: Valor gasto | H31: Horas
B32: Técnico | C32: =IFERROR(__xludf.DUMMYFUNCTION("COUNTA(IFERROR(FILTER(PESSOAL!$F$13:$F$23,PESSOAL!$F$13:$F$23 = $B32,PESSOAL!$V$13:$V$23 = ""Parcial"",PESSOAL!$W$13:$W$23 = TRUE),))"),0.0) -> 0 | D32: =IFERROR(__xludf.DUMMYFUNCTION("SUM(IFERROR(FILTER(PESSOAL!$U$35:$U$45,PESSOAL!$F$35:$F$45 = $B32,PESSOAL!$E$35:$E$45 = ""Parcial""),0))"),0.0) -> 0 | E32: =IFERROR(__xludf.DUMMYFUNCTION("SUM(IFERROR(FILTER(PESSOAL!$T$13:$T$23,PESSOAL!$F$13:$F$23 = $B32,PESSOAL!$V$13:$V$23 = ""Parcial""),0))*24"),0.0) -> 0 | F32: =IFERROR(__xludf.DUMMYFUNCTION("COUNTA(IFERROR(FILTER(PESSOAL!$E$6:$E$19,PESSOAL!$E$6:$E$19 = $B32,PESSOAL!$U$6:$U$19 = ""Exclusivo"",PESSOAL!$U$28:$U$39 = TRUE),))"),0.0) -> 0 | G32: =IFERROR(__xludf.DUMMYFUNCTION("SUM(IFERROR(FILTER(PESSOAL!$U$35:$U$44,PESSOAL!$F$35:$F$44 = $B32,PESSOAL!$E$35:$E$44 = ""Exclusivo);0))"")))"),0.0) -> 0 | H32: =IFERROR(__xludf.DUMMYFUNCTION("SUM(IFERROR(FILTER(PESSOAL!$T$13:$T$23,PESSOAL!$F$13:$F$23 = $B32,PESSOAL!$V$13:$V$23 = ""Exclusivo""),0))*24"),0.0) -> 0
B33: Tecnologo | C33: =IFERROR(__xludf.DUMMYFUNCTION("COUNTA(IFERROR(FILTER(PESSOAL!$F$13:$F$23,PESSOAL!$F$13:$F$23 = $B33,PESSOAL!$V$13:$V$23 = ""Parcial"",PESSOAL!$W$13:$W$23 = TRUE),))"),0.0) -> 0 | D33: =IFERROR(__xludf.DUMMYFUNCTION("SUM(IFERROR(FILTER(PESSOAL!$U$35:$U$45,PESSOAL!$F$35:$F$45 = $B33,PESSOAL!$E$35:$E$45 = ""Parcial""),0))"),0.0) -> 0 | E33: =IFERROR(__xludf.DUMMYFUNCTION("SUM(IFERROR(FILTER(PESSOAL!$T$13:$T$23,PESSOAL!$F$13:$F$23 = $B33,PESSOAL!$V$13:$V$23 = ""Parcial""),0))*24"),0.0) -> 0 | F33: =IFERROR(__xludf.DUMMYFUNCTION("COUNTA(IFERROR(FILTER(PESSOAL!$E$6:$E$19,PESSOAL!$E$6:$E$19 = $B33,PESSOAL!$U$6:$U$19 = ""Exclusivo"",PESSOAL!$U$28:$U$39 = TRUE),))"),0.0) -> 0 | G33: =IFERROR(__xludf.DUMMYFUNCTION("SUM(IFERROR(FILTER(PESSOAL!$U$35:$U$44,PESSOAL!$F$35:$F$44 = $B33,PESSOAL!$E$35:$E$44 = ""Exclusivo);0))"")))"),0.0) -> 0 | H33: =IFERROR(__xludf.DUMMYFUNCTION("SUM(IFERROR(FILTER(PESSOAL!$T$13:$T$23,PESSOAL!$F$13:$F$23 = $B33,PESSOAL!$V$13:$V$23 = ""Exclusivo""),0))*24"),0.0) -> 0
B34: Graduação | C34: =IFERROR(__xludf.DUMMYFUNCTION("COUNTA(IFERROR(FILTER(PESSOAL!$F$13:$F$23,PESSOAL!$F$13:$F$23 = $B34,PESSOAL!$V$13:$V$23 = ""Parcial"",PESSOAL!$W$13:$W$23 = TRUE),))"),2.0) -> 2 | D34: =IFERROR(__xludf.DUMMYFUNCTION("SUM(IFERROR(FILTER(PESSOAL!$U$35:$U$45,PESSOAL!$F$35:$F$45 = $B34,PESSOAL!$E$35:$E$45 = ""Parcial""),0))"),16980.383291514452) -> 16980.383 | E34: =IFERROR(__xludf.DUMMYFUNCTION("SUM(IFERROR(FILTER(PESSOAL!$T$13:$T$23,PESSOAL!$F$13:$F$23 = $B34,PESSOAL!$V$13:$V$23 = ""Parcial""),0))*24"),311.2500000000001) -> 311.25 | F34: =IFERROR(__xludf.DUMMYFUNCTION("COUNTA(IFERROR(FILTER(PESSOAL!$E$6:$E$19,PESSOAL!$E$6:$E$19 = $B34,PESSOAL!$U$6:$U$19 = ""Exclusivo"",PESSOAL!$U$28:$U$39 = TRUE),))"),0.0) -> 0 | G34: =IFERROR(__xludf.DUMMYFUNCTION("SUM(IFERROR(FILTER(PESSOAL!$U$35:$U$44,PESSOAL!$F$35:$F$44 = $B34,PESSOAL!$E$35:$E$44 = ""Exclusivo);0))"")))"),0.0) -> 0 | H34: =IFERROR(__xludf.DUMMYFUNCTION("SUM(IFERROR(FILTER(PESSOAL!$T$13:$T$23,PESSOAL!$F$13:$F$23 = $B34,PESSOAL!$V$13:$V$23 = ""Exclusivo""),0))*24"),0.0) -> 0
B35: Pós graduado | C35: =IFERROR(__xludf.DUMMYFUNCTION("COUNTA(IFERROR(FILTER(PESSOAL!$F$13:$F$23,PESSOAL!$F$13:$F$23 = $B35,PESSOAL!$V$13:$V$23 = ""Parcial"",PESSOAL!$W$13:$W$23 = TRUE),))"),3.0) -> 3 | D35: =IFERROR(__xludf.DUMMYFUNCTION("SUM(IFERROR(FILTER(PESSOAL!$U$35:$U$45,PESSOAL!$F$35:$F$45 = $B35,PESSOAL!$E$35:$E$45 = ""Parcial""),0))"),28795.85934765911) -> 28795.859 | E35: =IFERROR(__xludf.DUMMYFUNCTION("SUM(IFERROR(FILTER(PESSOAL!$T$13:$T$23,PESSOAL!$F$13:$F$23 = $B35,PESSOAL!$V$13:$V$23 = ""Parcial""),0))*24"),542.0) -> 542 | F35: =IFERROR(__xludf.DUMMYFUNCTION("COUNTA(IFERROR(FILTER(PESSOAL!$E$6:$E$19,PESSOAL!$E$6:$E$19 = $B35,PESSOAL!$U$6:$U$19 = ""Exclusivo"",PESSOAL!$U$28:$U$39 = TRUE),))"),0.0) -> 0 | G35: =IFERROR(__xludf.DUMMYFUNCTION("SUM(IFERROR(FILTER(PESSOAL!$U$35:$U$44,PESSOAL!$F$35:$F$44 = $B35,PESSOAL!$E$35:$E$44 = ""Exclusivo);0))"")))"),0.0) -> 0 | H35: =IFERROR(__xludf.DUMMYFUNCTION("SUM(IFERROR(FILTER(PESSOAL!$T$13:$T$23,PESSOAL!$F$13:$F$23 = $B35,PESSOAL!$V$13:$V$23 = ""Exclusivo""),0))*24"),0.0) -> 0
B36: Mestrado | C36: =IFERROR(__xludf.DUMMYFUNCTION("COUNTA(IFERROR(FILTER(PESSOAL!$F$13:$F$23,PESSOAL!$F$13:$F$23 = $B36,PESSOAL!$V$13:$V$23 = ""Parcial"",PESSOAL!$W$13:$W$23 = TRUE),))"),1.0) -> 1 | D36: =IFERROR(__xludf.DUMMYFUNCTION("SUM(IFERROR(FILTER(PESSOAL!$U$35:$U$45,PESSOAL!$F$35:$F$45 = $B36,PESSOAL!$E$35:$E$45 = ""Parcial""),0))"),23918.220024484064) -> 23918.22 | E36: =IFERROR(__xludf.DUMMYFUNCTION("SUM(IFERROR(FILTER(PESSOAL!$T$13:$T$23,PESSOAL!$F$13:$F$23 = $B36,PESSOAL!$V$13:$V$23 = ""Parcial""),0))*24"),258.84999999999997) -> 258.85 | F36: =IFERROR(__xludf.DUMMYFUNCTION("COUNTA(IFERROR(FILTER(PESSOAL!$E$6:$E$19,PESSOAL!$E$6:$E$19 = $B36,PESSOAL!$U$6:$U$19 = ""Exclusivo"",PESSOAL!$U$28:$U$39 = TRUE),))"),0.0) -> 0 | G36: =IFERROR(__xludf.DUMMYFUNCTION("SUM(IFERROR(FILTER(PESSOAL!$U$35:$U$44,PESSOAL!$F$35:$F$44 = $B36,PESSOAL!$E$35:$E$44 = ""Exclusivo);0))"")))"),0.0) -> 0 | H36: =IFERROR(__xludf.DUMMYFUNCTION("SUM(IFERROR(FILTER(PESSOAL!$T$13:$T$23,PESSOAL!$F$13:$F$23 = $B36,PESSOAL!$V$13:$V$23 = ""Exclusivo""),0))*24"),0.0) -> 0
B37: Doutorado | C37: =IFERROR(__xludf.DUMMYFUNCTION("COUNTA(IFERROR(FILTER(PESSOAL!$F$13:$F$23,PESSOAL!$F$13:$F$23 = $B37,PESSOAL!$V$13:$V$23 = ""Parcial"",PESSOAL!$W$13:$W$23 = TRUE),))"),2.0) -> 2 | D37: =IFERROR(__xludf.DUMMYFUNCTION("SUM(IFERROR(FILTER(PESSOAL!$U$35:$U$45,PESSOAL!$F$35:$F$45 = $B37,PESSOAL!$E$35:$E$45 = ""Parcial""),0))"),30103.75670941025) -> 30103.757 | E37: =IFERROR(__xludf.DUMMYFUNCTION("SUM(IFERROR(FILTER(PESSOAL!$T$13:$T$23,PESSOAL!$F$13:$F$23 = $B37,PESSOAL!$V$13:$V$23 = ""Parcial""),0))*24"),559.1) -> 559.1 | F37: =IFERROR(__xludf.DUMMYFUNCTION("COUNTA(IFERROR(FILTER(PESSOAL!$E$6:$E$19,PESSOAL!$E$6:$E$19 = $B37,PESSOAL!$U$6:$U$19 = ""Exclusivo"",PESSOAL!$U$28:$U$39 = TRUE),))"),0.0) -> 0 | G37: =IFERROR(__xludf.DUMMYFUNCTION("SUM(IFERROR(FILTER(PESSOAL!$U$35:$U$44,PESSOAL!$F$35:$F$44 = $B37,PESSOAL!$E$35:$E$44 = ""Exclusivo);0))"")))"),0.0) -> 0 | H37: =IFERROR(__xludf.DUMMYFUNCTION("SUM(IFERROR(FILTER(PESSOAL!$T$13:$T$23,PESSOAL!$F$13:$F$23 = $B37,PESSOAL!$V$13:$V$23 = ""Exclusivo""),0))*24"),0.0) -> 0
C38: =SUM(C32:C37) -> 8 | D38: =SUM(D32:D37) -> 99798.219 | E38: =SUM(E32:E37) -> 1671.2 | F38: =SUM(F32:F37) -> 0 | G38: =SUM(G32:G37) -> 0 | H38: =SUM(H32:H37) -> 0
B40: Valores por projeto de PD&I
B41: Projetos | C41: TOTAL | E41: Vlr materiais | F41: Vlr terceiros | G41: Vlr Rh parcial | H41: Vlr exclusivos
A42: 1 | B42: {='Base Projetos'!A2:A71} -> INOV00001 | C42: =sum(E42:H42) -> 162088.55 | E42: - | F42: {=IFERROR(XLOOKUP(B42:B70,TRANSPOSE(TERCEIROS!$Q$11:$AX$11),TRANSPOSE(TERCEIROS!$Q$10:$AX$10),0,0),"")} -> 112121.99 | G42: =IFERROR(__xludf.DUMMYFUNCTION("ArrayFormula(IFERROR(SUM(filter(TIMESHEET!$N$12:$N71,TIMESHEET!$C$12:$C71=B42,TIMESHEET!$Q$12:$Q71=""Parcial"")),""-""))"),49966.559431866524) -> 49966.559 | H42: =IFERROR(__xludf.DUMMYFUNCTION("iferror(sum(filter(TIMESHEET!$N12:$N71,TIMESHEET!$C12:$C71=B42,TIMESHEET!$Q12:$Q71=""Exclusivo"")),""-"")"),"-") -> -
A43: 2 | B43: INOV00004 | C43: =sum(E43:H43) -> 17072.115 | E43: - | F43: 5388.575 | G43: =IFERROR(__xludf.DUMMYFUNCTION("ArrayFormula(IFERROR(SUM(filter(TIMESHEET!$N$12:$N71,TIMESHEET!$C$12:$C71=B43,TIMESHEET!$Q$12:$Q71=""Parcial"")),""-""))"),11683.539797642836) -> 11683.54 | H43: =IFERROR(__xludf.DUMMYFUNCTION("iferror(sum(filter(TIMESHEET!$N13:$N71,TIMESHEET!$C13:$C71=B43,TIMESHEET!$Q13:$Q71=""Exclusivo"")),""-"")"),"-") -> -
A44: 3 | B44: INOV00006 | C44: =sum(E44:H44) -> 14246.671 | E44: - | F44: 5322.08 | G44: =IFERROR(__xludf.DUMMYFUNCTION("ArrayFormula(IFERROR(SUM(filter(TIMESHEET!$N$12:$N71,TIMESHEET!$C$12:$C71=B44,TIMESHEET!$Q$12:$Q71=""Parcial"")),""-""))"),8924.590649799264) -> 8924.5907 | H44: =IFERROR(__xludf.DUMMYFUNCTION("iferror(sum(filter(TIMESHEET!$N14:$N71,TIMESHEET!$C14:$C71=B44,TIMESHEET!$Q14:$Q71=""Exclusivo"")),""-"")"),"-") -> -
A45: 4 | B45: INOV00010 | C45: =sum(E45:H45) -> 12156.39 | E45: - | F45: 12156.39 | G45: =IFERROR(__xludf.DUMMYFUNCTION("ArrayFormula(IFERROR(SUM(filter(TIMESHEET!$N$12:$N71,TIMESHEET!$C$12:$C71=B45,TIMESHEET!$Q$12:$Q71=""Parcial"")),""-""))"),"-") -> - | H45: =IFERROR(__xludf.DUMMYFUNCTION("iferror(sum(filter(TIMESHEET!$N15:$N71,TIMESHEET!$C15:$C71=B45,TIMESHEET!$Q15:$Q71=""Exclusivo"")),""-"")"),"-") -> -
A46: 5 | B46: INOV00013 | C46: =sum(E46:H46) -> 32723.672 | E46: - | F46: 32488.45 | G46: =IFERROR(__xludf.DUMMYFUNCTION("ArrayFormula(IFERROR(SUM(filter(TIMESHEET!$N$12:$N71,TIMESHEET!$C$12:$C71=B46,TIMESHEET!$Q$12:$Q71=""Parcial"")),""-""))"),235.22225388463443) -> 235.22225 | H46: =IFERROR(__xludf.DUMMYFUNCTION("iferror(sum(filter(TIMESHEET!$N16:$N71,TIMESHEET!$C16:$C71=B46,TIMESHEET!$Q16:$Q71=""Exclusivo"")),""-"")"),"-") -> -
A47: 6 | B47: INOV00014 | C47: =sum(E47:H47) -> 53892.415 | E47: - | F47: 49956.91 | G47: =IFERROR(__xludf.DUMMYFUNCTION("ArrayFormula(IFERROR(SUM(filter(TIMESHEET!$N$12:$N71,TIMESHEET!$C$12:$C71=B47,TIMESHEET!$Q$12:$Q71=""Parcial"")),""-""))"),3935.5051161177626) -> 3935.5051 | H47: =IFERROR(__xludf.DUMMYFUNCTION("iferror(sum(filter(TIMESHEET!$N17:$N71,TIMESHEET!$C17:$C71=B47,TIMESHEET!$Q17:$Q71=""Exclusivo"")),""-"")"),"-") -> -
A48: 7 | B48: INOV00016 | C48: =sum(E48:H48) -> 96354.702 | E48: - | F48: 94173.6 | G48: =IFERROR(__xludf.DUMMYFUNCTION("ArrayFormula(IFERROR(SUM(filter(TIMESHEET!$N$12:$N71,TIMESHEET!$C$12:$C71=B48,TIMESHEET!$Q$12:$Q71=""Parcial"")),""-""))"),2181.1021259728986) -> 2181.1021 | H48: =IFERROR(__xludf.DUMMYFUNCTION("iferror(sum(filter(TIMESHEET!$N18:$N71,TIMESHEET!$C18:$C71=B48,TIMESHEET!$Q18:$Q71=""Exclusivo"")),""-"")"),"-") -> -
A49: 8 | B49: INOV00017 | C49: =sum(E49:H49) -> 45645.906 | E49: - | F49: 43160.965 | G49: =IFERROR(__xludf.DUMMYFUNCTION("ArrayFormula(IFERROR(SUM(filter(TIMESHEET!$N$12:$N71,TIMESHEET!$C$12:$C71=B49,TIMESHEET!$Q$12:$Q71=""Parcial"")),""-""))"),2484.940558661307) -> 2484.9406 | H49: =IFERROR(__xludf.DUMMYFUNCTION("iferror(sum(filter(TIMESHEET!$N19:$N71,TIMESHEET!$C19:$C71=B49,TIMESHEET!$Q19:$Q71=""Exclusivo"")),""-"")"),"-") -> -
B50: INOV00020 | C50: =sum(E50:H50) -> 0 | E50: - | F50: 0 | G50: =IFERROR(__xludf.DUMMYFUNCTION("ArrayFormula(IFERROR(SUM(filter(TIMESHEET!$N$12:$N71,TIMESHEET!$C$12:$C71=B50,TIMESHEET!$Q$12:$Q71=""Parcial"")),""-""))"),0.0) -> 0 | H50: =IFERROR(__xludf.DUMMYFUNCTION("iferror(sum(filter(TIMESHEET!$N20:$N71,TIMESHEET!$C20:$C71=B50,TIMESHEET!$Q20:$Q71=""Exclusivo"")),""-"")"),"-") -> -
A51: 9 | B51: INOV00022 | C51: =sum(E51:H51) -> 1356.9018 | E51: - | F51: 0 | G51: =IFERROR(__xludf.DUMMYFUNCTION("ArrayFormula(IFERROR(SUM(filter(TIMESHEET!$N$12:$N71,TIMESHEET!$C$12:$C71=B51,TIMESHEET!$Q$12:$Q71=""Parcial"")),""-""))"),1356.9018264918009) -> 1356.9018 | H51: =IFERROR(__xludf.DUMMYFUNCTION("iferror(sum(filter(TIMESHEET!$N21:$N71,TIMESHEET!$C21:$C71=B51,TIMESHEET!$Q21:$Q71=""Exclusivo"")),""-"")"),"-") -> -
A52: 10 | B52: INOV00023 | C52: =sum(E52:H52) -> 2006.1545 | E52: - | F52: 0 | G52: =IFERROR(__xludf.DUMMYFUNCTION("ArrayFormula(IFERROR(SUM(filter(TIMESHEET!$N$12:$N71,TIMESHEET!$C$12:$C71=B52,TIMESHEET!$Q$12:$Q71=""Parcial"")),""-""))"),2006.154504553748) -> 2006.1545 | H52: =IFERROR(__xludf.DUMMYFUNCTION("iferror(sum(filter(TIMESHEET!$N22:$N71,TIMESHEET!$C22:$C71=B52,TIMESHEET!$Q22:$Q71=""Exclusivo"")),""-"")"),"-") -> -
A53: 11 | B53: INOV00024 | C53: =sum(E53:H53) -> 6526.6148 | E53: - | F53: 0 | G53: =IFERROR(__xludf.DUMMYFUNCTION("ArrayFormula(IFERROR(SUM(filter(TIMESHEET!$N$12:$N71,TIMESHEET!$C$12:$C71=B53,TIMESHEET!$Q$12:$Q71=""Parcial"")),""-""))"),6526.614832819879) -> 6526.6148 | H53: =IFERROR(__xludf.DUMMYFUNCTION("iferror(sum(filter(TIMESHEET!$N23:$N71,TIMESHEET!$C23:$C71=B53,TIMESHEET!$Q23:$Q71=""Exclusivo"")),""-"")"),"-") -> -
B54: INOV00025 | C54: =sum(E54:H54) -> 0 | E54: - | F54: 0 | G54: =IFERROR(__xludf.DUMMYFUNCTION("ArrayFormula(IFERROR(SUM(filter(TIMESHEET!$N$12:$N71,TIMESHEET!$C$12:$C71=B54,TIMESHEET!$Q$12:$Q71=""Parcial"")),""-""))"),"-") -> - | H54: =IFERROR(__xludf.DUMMYFUNCTION("iferror(sum(filter(TIMESHEET!$N24:$N71,TIMESHEET!$C24:$C71=B54,TIMESHEET!$Q24:$Q71=""Exclusivo"")),""-"")"),"-") -> -
B55: INOV00027 | C55: =sum(E55:H55) -> 0 | E55: - | F55: 0 | G55: =IFERROR(__xludf.DUMMYFUNCTION("ArrayFormula(IFERROR(SUM(filter(TIMESHEET!$N$12:$N71,TIMESHEET!$C$12:$C71=B55,TIMESHEET!$Q$12:$Q71=""Parcial"")),""-""))"),"-") -> - | H55: =IFERROR(__xludf.DUMMYFUNCTION("iferror(sum(filter(TIMESHEET!$N25:$N71,TIMESHEET!$C25:$C71=B55,TIMESHEET!$Q25:$Q71=""Exclusivo"")),""-"")"),"-") -> -
A56: 12 | B56: INOV00029 | C56: =sum(E56:H56) -> 282.44 | E56: - | F56: 0 | G56: =IFERROR(__xludf.DUMMYFUNCTION("ArrayFormula(IFERROR(SUM(filter(TIMESHEET!$N$12:$N71,TIMESHEET!$C$12:$C71=B56,TIMESHEET!$Q$12:$Q71=""Parcial"")),""-""))"),282.44) -> 282.44 | H56: =IFERROR(__xludf.DUMMYFUNCTION("iferror(sum(filter(TIMESHEET!$N26:$N71,TIMESHEET!$C26:$C71=B56,TIMESHEET!$Q26:$Q71=""Exclusivo"")),""-"")"),"-") -> -
A57: 13 | B57: INOV00032 | C57: =sum(E57:H57) -> 147.7291 | E57: - | F57: 0 | G57: =IFERROR(__xludf.DUMMYFUNCTION("ArrayFormula(IFERROR(SUM(filter(TIMESHEET!$N$12:$N71,TIMESHEET!$C$12:$C71=B57,TIMESHEET!$Q$12:$Q71=""Parcial"")),""-""))"),147.72909913825757) -> 147.7291 | H57: =IFERROR(__xludf.DUMMYFUNCTION("iferror(sum(filter(TIMESHEET!$N27:$N71,TIMESHEET!$C27:$C71=B57,TIMESHEET!$Q27:$Q71=""Exclusivo"")),""-"")"),"-") -> -
A58: 14 | B58: INOV00035 | C58: =sum(E58:H58) -> 7918.5827 | E58: - | F58: 5000 | G58: =IFERROR(__xludf.DUMMYFUNCTION("ArrayFormula(IFERROR(SUM(filter(TIMESHEET!$N$12:$N71,TIMESHEET!$C$12:$C71=B58,TIMESHEET!$Q$12:$Q71=""Parcial"")),""-""))"),2918.5827180357737) -> 2918.5827 | H58: =IFERROR(__xludf.DUMMYFUNCTION("iferror(sum(filter(TIMESHEET!$N28:$N71,TIMESHEET!$C28:$C71=B58,TIMESHEET!$Q28:$Q71=""Exclusivo"")),""-"")"),"-") -> -
A59: 15 | B59: INOV00036 | C59: =sum(E59:H59) -> 534.0435 | E59: - | F59: 0 | G59: =IFERROR(__xludf.DUMMYFUNCTION("ArrayFormula(IFERROR(SUM(filter(TIMESHEET!$N$12:$N71,TIMESHEET!$C$12:$C71=B59,TIMESHEET!$Q$12:$Q71=""Parcial"")),""-""))"),534.0435024147728) -> 534.0435 | H59: =IFERROR(__xludf.DUMMYFUNCTION("iferror(sum(filter(TIMESHEET!$N29:$N71,TIMESHEET!$C29:$C71=B59,TIMESHEET!$Q29:$Q71=""Exclusivo"")),""-"")"),"-") -> -
A60: 16 | B60: INOV00037 | C60: =sum(E60:H60) -> 2021.6557 | E60: - | F60: 0 | G60: =IFERROR(__xludf.DUMMYFUNCTION("ArrayFormula(IFERROR(SUM(filter(TIMESHEET!$N$12:$N71,TIMESHEET!$C$12:$C71=B60,TIMESHEET!$Q$12:$Q71=""Parcial"")),""-""))"),2021.655722495236) -> 2021.6557 | H60: =IFERROR(__xludf.DUMMYFUNCTION("iferror(sum(filter(TIMESHEET!$N30:$N71,TIMESHEET!$C30:$C71=B60,TIMESHEET!$Q30:$Q71=""Exclusivo"")),""-"")"),"-") -> -
B61: INOV00038 | C61: =sum(E61:H61) -> 0 | E61: - | F61: 0 | G61: =IFERROR(__xludf.DUMMYFUNCTION("ArrayFormula(IFERROR(SUM(filter(TIMESHEET!$N$12:$N71,TIMESHEET!$C$12:$C71=B61,TIMESHEET!$Q$12:$Q71=""Parcial"")),""-""))"),"-") -> - | H61: =IFERROR(__xludf.DUMMYFUNCTION("iferror(sum(filter(TIMESHEET!$N31:$N71,TIMESHEET!$C31:$C71=B61,TIMESHEET!$Q31:$Q71=""Exclusivo"")),""-"")"),"-") -> -
A62: 17 | B62: INOV00039 | C62: =sum(E62:H62) -> 1603.1127 | E62: - | F62: 0 | G62: =IFERROR(__xludf.DUMMYFUNCTION("ArrayFormula(IFERROR(SUM(filter(TIMESHEET!$N$12:$N71,TIMESHEET!$C$12:$C71=B62,TIMESHEET!$Q$12:$Q71=""Parcial"")),""-""))"),1603.1126695295736) -> 1603.1127 | H62: =IFERROR(__xludf.DUMMYFUNCTION("iferror(sum(filter(TIMESHEET!$N32:$N71,TIMESHEET!$C32:$C71=B62,TIMESHEET!$Q32:$Q71=""Exclusivo"")),""-"")"),"-") -> -
A63: 18 | B63: INOV00041 | C63: =sum(E63:H63) -> 6489.5246 | E63: - | F63: 3500 | G63: =IFERROR(__xludf.DUMMYFUNCTION("ArrayFormula(IFERROR(SUM(filter(TIMESHEET!$N$12:$N71,TIMESHEET!$C$12:$C71=B63,TIMESHEET!$Q$12:$Q71=""Parcial"")),""-""))"),2989.524563643599) -> 2989.5246 | H63: =IFERROR(__xludf.DUMMYFUNCTION("iferror(sum(filter(TIMESHEET!$N33:$N71,TIMESHEET!$C33:$C71=B63,TIMESHEET!$Q33:$Q71=""Exclusivo"")),""-"")"),"-") -> -
B64: INOV00046 | C64: =sum(E64:H64) -> 0 | E64: - | F64: 0 | G64: =IFERROR(__xludf.DUMMYFUNCTION("ArrayFormula(IFERROR(SUM(filter(TIMESHEET!$N$12:$N71,TIMESHEET!$C$12:$C71=B64,TIMESHEET!$Q$12:$Q71=""Parcial"")),""-""))"),0.0) -> 0 | H64: =IFERROR(__xludf.DUMMYFUNCTION("iferror(sum(filter(TIMESHEET!$N34:$N71,TIMESHEET!$C34:$C71=B64,TIMESHEET!$Q34:$Q71=""Exclusivo"")),""-"")"),"-") -> -
B65: INOV00047 | C65: =sum(E65:H65) -> 0 | E65: - | F65: 0 | G65: =IFERROR(__xludf.DUMMYFUNCTION("ArrayFormula(IFERROR(SUM(filter(TIMESHEET!$N$12:$N71,TIMESHEET!$C$12:$C71=B65,TIMESHEET!$Q$12:$Q71=""Parcial"")),""-""))"),0.0) -> 0 | H65: =IFERROR(__xludf.DUMMYFUNCTION("iferror(sum(filter(TIMESHEET!$N35:$N71,TIMESHEET!$C35:$C71=B65,TIMESHEET!$Q35:$Q71=""Exclusivo"")),""-"")"),"-") -> -
B66: INOV00048 | C66: =sum(E66:H66) -> 0 | E66: - | F66: 0 | G66: =IFERROR(__xludf.DUMMYFUNCTION("ArrayFormula(IFERROR(SUM(filter(TIMESHEET!$N$12:$N71,TIMESHEET!$C$12:$C71=B66,TIMESHEET!$Q$12:$Q71=""Parcial"")),""-""))"),0.0) -> 0 | H66: =IFERROR(__xludf.DUMMYFUNCTION("iferror(sum(filter(TIMESHEET!$N36:$N71,TIMESHEET!$C36:$C71=B66,TIMESHEET!$Q36:$Q71=""Exclusivo"")),""-"")"),"-") -> -
B67: INOV00049 | C67: =sum(E67:H67) -> 0 | E67: - | F67: 0 | G67: =IFERROR(__xludf.DUMMYFUNCTION("ArrayFormula(IFERROR(SUM(filter(TIMESHEET!$N$12:$N71,TIMESHEET!$C$12:$C71=B67,TIMESHEET!$Q$12:$Q71=""Parcial"")),""-""))"),0.0) -> 0 | H67: =IFERROR(__xludf.DUMMYFUNCTION("iferror(sum(filter(TIMESHEET!$N37:$N71,TIMESHEET!$C37:$C71=B67,TIMESHEET!$Q37:$Q71=""Exclusivo"")),""-"")"),"-") -> -
B68: INOV00050 | C68: =sum(E68:H68) -> 0 | E68: - | F68: 0 | G68: =IFERROR(__xludf.DUMMYFUNCTION("ArrayFormula(IFERROR(SUM(filter(TIMESHEET!$N$12:$N71,TIMESHEET!$C$12:$C71=B68,TIMESHEET!$Q$12:$Q71=""Parcial"")),""-""))"),0.0) -> 0 | H68: =IFERROR(__xludf.DUMMYFUNCTION("iferror(sum(filter(TIMESHEET!$N38:$N71,TIMESHEET!$C38:$C71=B68,TIMESHEET!$Q38:$Q71=""Exclusivo"")),""-"")"),"-") -> -
B69: INOV00051 | C69: =sum(E69:H69) -> 0 | E69: - | F69: 0 | G69: =IFERROR(__xludf.DUMMYFUNCTION("ArrayFormula(IFERROR(SUM(filter(TIMESHEET!$N$12:$N71,TIMESHEET!$C$12:$C71=B69,TIMESHEET!$Q$12:$Q71=""Parcial"")),""-""))"),0.0) -> 0 | H69: =IFERROR(__xludf.DUMMYFUNCTION("iferror(sum(filter(TIMESHEET!$N39:$N71,TIMESHEET!$C39:$C71=B69,TIMESHEET!$Q39:$Q71=""Exclusivo"")),""-"")"),"-") -> -
B70: INOV00052 | C70: =sum(E70:H70) -> 0 | E70: - | F70: 0 | G70: =IFERROR(__xludf.DUMMYFUNCTION("ArrayFormula(IFERROR(SUM(filter(TIMESHEET!$N$12:$N71,TIMESHEET!$C$12:$C71=B70,TIMESHEET!$Q$12:$Q71=""Parcial"")),""-""))"),"-") -> - | H70: =IFERROR(__xludf.DUMMYFUNCTION("iferror(sum(filter(TIMESHEET!$N40:$N71,TIMESHEET!$C40:$C71=B70,TIMESHEET!$Q40:$Q71=""Exclusivo"")),""-"")"),"-") -> -
C71: =sum(E71:H71) -> 463067.18 | E71: =SUM(E42:E70) -> 0 | F71: =SUM(F42:F70) -> 363268.97 | G71: =SUM(G42:G70) -> 99798.219 | H71: =SUM(H42:H70) -> 0

Sheet PROJETO
B2: PRODIET
B3: Pesquisa, Desenvolvimento & Inovação
B4: Formulário de PD&I - Ano 2024 | J4: Incentivado pela Lei do Bem | M4: FALSE
B5: - preencher somente os campos sombreados (cinza) e - adicionar cronograma no formato de imagem ao fim do formulário - preencher um deste para cada projeto de PD&I | J5: Objetiva tornar-se um Ativo | M5: FALSE
J6: Objetiva gerar patente/registro | M6: FALSE
B8: Dossiêdoprojeto
B9: DadosgeraisparaidentificaçãoevalidaçãodoprojetodePD&I
B11: Nome do projeto
J12: Pesquisa básica | M12: 📑
B13: Classificação do projeto | J13: Pesquisa aplicada | M13: 📑
J14: Desenvolvimento experimental | M14: 📑
B15: Objetivos do projeto
J16: Inovação tecnológica de produto | M16: 📑
B17: Tipo de inovação | J17: Inovação tecnológica de processo | M17: 📑
J18: Inovação tecnológica de serviços | M18: 📑
B19: Elemento inovador | J19: - Não podem ser consideradas as inovações organizacionais, comerciais e de marketing
J20: Empresa ou segmento regional | M20: 📑
B21: Nível de inovação | J21: Inovador para o Brasil | M21: 📑
J22: Inovador para o Mundo | M22: 📑
B23: Risco tecnológico
B25: Metodologias
B27: Equipe | E27: NomeCompleto | F27: Cargo|Função | G27: Qualificação | H27: !
E28: Lizianne Angelica Shmeil | F28: Analista de P&D | G28: Pós-graduação | H28: FALSE | L28: Técnico | M28: 📑
E29: Ana Paula Celes | F29: Diretora Técnica | G29: Pós-graduação | H29: FALSE | L29: Graduação
E30: Luciana Dutra | F30: Gerente Técnica | G30: Pós-graduação | H30: FALSE | L30: Pós-graduação
E31: Gabriela Faria de Oliveira | F31: Analista Científico | G31: Pós-graduação | H31: FALSE | L31: Mestrado
E32: Rafael Parreira Lorini | F32: Analista de P&D | G32: Graduação | H32: FALSE | L32: Doutorado
E33: Hellin dos Santos | F33: Gerente Científico | G33: Mestrado | H33: FALSE
E34: Camila Mendes Pereira | F34: Analista de P&D | G34: Graduação | H34: FALSE
E35: Ana Claudia Zanini | F35: Analista cientifico | G35: Mestrado | H35: FALSE
E36: Juliana Lamas Roberto | F36: Especialista de Estudo de Estabilidade | G36: Mestrado | H36: FALSE
E37: Márcio Henrique Nogueira | F37: Analista de P&D | G37: Doutorado | H37: FALSE
E38: Tahuany Caetano | F38: Analista MKT | G38: Pós-graduação | H38: FALSE
E39: Arianna Schreiber | F39: MARKETING
E40: Mihaela Theer Moura | F40: MARKETING
E41: Tahuany Leite | F41: MARKETING
E42: Vaneisse Cristina Lima Monteiro
E43: Ana Paula Biz
E44: Raissa Bellotti
E45: Alyne Alves Nunes Oliveira
B47: Cronograma
B48: [anexarimagem-preferencialmenteGantt]

Sheet CHECKLIST
B2: PRODIET
B3: Pesquisa ,Desenvolvimento & Inovação
B4: Formulário de PD&I - Ano2024
B5: -preencher somente os campos sombreados (cinza)
B8: Dossiê do projeto
B9: Checklist - outras informações
B11: Área | C11: Item | D11: Descrição | E11: Status | F11: Comentáriocliente | G11: ComentárioMcBenner

Sheet PESSOAL
B2: PRODIET
B3: Pesquisa ,Desenvolvimento & Inovação
B4: Formulário de PD&I - Ano2024
B5: -preencher somente os campos sombreados (cinza)
B8: Dossiê do projeto
B9: Cálculo de custo - Pessoal
B11: Salário bruto | T11: =(U11/12)*24 -> 186.26667 | U11: =(SUM(H33:S33)*8.8)/24 -> 93.133333
B12: Nome Completo | C12: CPF | D12: notas | E12: Cargo/função | F12: Formação | G12: Attachments | H12: Salário 01 | I12: Salário 02 | J12: Salário 03 | K12: Salário 04 | L12: Salário 05 | M12: Salário 06 | N12: Salário 07 | O12: Salário 08 | P12: Salário 09 | Q12: Salário 10 | R12: Salário 11 | S12: Salário 12 | T12: PD&I time | U12: PD&I (%) | V12: Classificação | W12: Pesquisador
B13: {=SORT(UNIQUE(TIMESHEET!E12:E67))} -> Alyne Alves Nunes Oliveira | C13: 129.307.117-01 | E13: Especialista de P&D | F13: Doutorado | G13: CLT | H13: 7234.78 | I13: 7234.78 | J13: 7234.78 | K13: 7234.78 | L13: 7234.78 | M13: 7234.78 | N13: 7234.78 | O13: 7596.52 | P13: 7596.52 | Q13: 7596.52 | T13: =IFERROR(__xludf.DUMMYFUNCTION("IFERROR(IF(W13=TRUE, SUM(FILTER(TIMESHEET!$G:$G,TIMESHEET!O:O = TRUE,TIMESHEET!P:P = TRUE,TIMESHEET!E:E = B13,TIMESHEET!F:F < DATE(2025,1,1))),0),0)"),13.659722222222223) -> 13.659722 | U13: =T13/$U$11 -> 0.14666846 | V13: =IF(U13<80%,"Parcial","Exclusivo") -> Parcial | W13: TRUE
B14: Ana Claudia Zanini | C14: 076.046.519-33 | E14: Analista Científico SR | F14: Graduação | G14: CLT | H14: 6143.46 | I14: 6143.46 | J14: 6143.46 | K14: 6143.46 | L14: 6143.46 | M14: 6143.46 | N14: 6143.46 | O14: 7613.79 | P14: 7613.79 | Q14: 7613.79 | R14: 7613.79 | S14: 7613.79 | T14: =IFERROR(__xludf.DUMMYFUNCTION("IFERROR(IF(W14=TRUE, SUM(FILTER(TIMESHEET!$G:$G,TIMESHEET!O:O = TRUE,TIMESHEET!P:P = TRUE,TIMESHEET!E:E = B14,TIMESHEET!F:F < DATE(2025,1,1))),0),0)"),10.187500000000004) -> 10.1875 | U14: =T14/$U$11 -> 0.10938618 | V14: =IF(U14<80%,"Parcial","Exclusivo") -> Parcial | W14: TRUE
B15: Ana Paula Biz | C15: 071.847.899-11 | E15: Analista de P&D Pleno | F15: Doutorado | G15: CLT | H15: 4594.31 | I15: 4594.31 | J15: 4594.31 | K15: 4594.31 | L15: 4594.31 | M15: 4594.31 | N15: 4594.31 | O15: 4824.03 | P15: 4824.03 | Q15: 5481.24 | R15: 5481.24 | S15: 5481.24 | T15: =IFERROR(__xludf.DUMMYFUNCTION("IFERROR(IF(W15=TRUE, SUM(FILTER(TIMESHEET!$G:$G,TIMESHEET!O:O = TRUE,TIMESHEET!P:P = TRUE,TIMESHEET!E:E = B15,TIMESHEET!F:F < DATE(2025,1,1))),0),0)"),9.636111111111111) -> 9.6361111 | U15: =T15/$U$11 -> 0.10346576 | V15: =IF(U15<80%,"Parcial","Exclusivo") -> Parcial | W15: TRUE
B16: Ana Paula Celes | C16: 759.837.297-72 | E16: Diretora Técnica | F16: Pós Graduado | G16: PJ | H16: 37755.67 | I16: 37755.67 | J16: 37755.67 | K16: 37755.67 | L16: 37755.67 | M16: 37755.67 | N16: 37755.67 | O16: 37243.45 | P16: 37243.45 | Q16: 37243.45 | R16: 37243.45 | S16: 37243.45 | T16: =IFERROR(__xludf.DUMMYFUNCTION("IFERROR(IF(W16=TRUE, SUM(FILTER(TIMESHEET!$G:$G,TIMESHEET!O:O = TRUE,TIMESHEET!P:P = TRUE,TIMESHEET!E:E = B16,TIMESHEET!F:F < DATE(2025,1,1))),0),0)"),0.2604166666666667) -> 0.26041667 | U16: =T16/$U$11 -> 0.0027961704 | V16: =IF(U16<80%,"Parcial","Exclusivo") -> Parcial | W16: TRUE
B17: Camila Mendes Pereira | C17: 083.832.289-10 | E17: Analista de P&D Pleno | F17: Graduação | G17: CLT | H17: 5469.76 | I17: 5469.76 | J17: 5469.76 | K17: 5469.76 | L17: 5469.76 | M17: 5469.76 | N17: 5850.91 | O17: 6143.46 | P17: 6143.46 | Q17: 6143.46 | R17: 6143.46 | S17: 6143.46 | T17: =IFERROR(__xludf.DUMMYFUNCTION("IFERROR(IF(W17=TRUE, SUM(FILTER(TIMESHEET!$G:$G,TIMESHEET!O:O = TRUE,TIMESHEET!P:P = TRUE,TIMESHEET!E:E = B17,TIMESHEET!F:F < DATE(2025,1,1))),0),0)"),2.7812500000000004) -> 2.78125 | U17: =T17/$U$11 -> 0.0298631 | V17: =IF(U17<80%,"Parcial","Exclusivo") -> Parcial | W17: TRUE
B18: Gabriela Faria de Oliveira | C18: 087.823.469-17 | E18: Analista Científico SR | F18: Pós Graduado | G18: CLT | H18: 5743.25 | I18: 5743.25 | J18: 5743.25 | K18: 5743.25 | L18: 5743.25 | M18: 5743.25 | N18: 6143.46 | O18: 7234.78 | P18: 7234.78 | Q18: 7234.78 | R18: 7234.78 | S18: 7234.78 | T18: =IFERROR(__xludf.DUMMYFUNCTION("IFERROR(IF(W18=TRUE, SUM(FILTER(TIMESHEET!$G:$G,TIMESHEET!O:O = TRUE,TIMESHEET!P:P = TRUE,TIMESHEET!E:E = B18,TIMESHEET!F:F < DATE(2025,1,1))),0),0)"),17.208333333333336) -> 17.208333 | U18: =T18/$U$11 -> 0.18477094 | V18: =IF(U18<80%,"Parcial","Exclusivo") -> Parcial | W18: TRUE
B19: Juliana Lamas Roberto | C19: 317.875.738-42 | E19: Coordenadora de P&D | F19: Mestrado | G19: CLT | H19: 11225.48 | I19: 11225.48 | J19: 11225.48 | K19: 11225.48 | L19: 11225.48 | M19: 11225.48 | N19: 11225.48 | O19: 11786.75 | P19: 11786.75 | Q19: 11786.75 | R19: 11786.75 | S19: 11786.75 | T19: =IFERROR(__xludf.DUMMYFUNCTION("IFERROR(IF(W19=TRUE, SUM(FILTER(TIMESHEET!$G:$G,TIMESHEET!O:O = TRUE,TIMESHEET!P:P = TRUE,TIMESHEET!E:E = B19,TIMESHEET!F:F < DATE(2025,1,1))),0),0)"),10.785416666666665) -> 10.785417 | U19: =T19/$U$11 -> 0.11580619 | V19: =IF(U19<80%,"Parcial","Exclusivo") -> Parcial | W19: TRUE
B20: Raissa Bellotti | C20: 430.604.838-17 | E20: Analista Científico Jr | F20: Pós Graduado | G20: CLT | H20: 4780.42 | I20: 4780.42 | J20: 4780.42 | K20: 4780.42 | L20: 4780.42 | M20: 4780.42 | N20: 4780.42 | O20: 5481.24 | P20: 5481.24 | Q20: 5481.24 | R20: 5481.24 | S20: 5481.24 | T20: =IFERROR(__xludf.DUMMYFUNCTION("IFERROR(IF(W20=TRUE, SUM(FILTER(TIMESHEET!$G:$G,TIMESHEET!O:O = TRUE,TIMESHEET!P:P = TRUE,TIMESHEET!E:E = B20,TIMESHEET!F:F < DATE(2025,1,1))),0),0)"),5.114583333333334) -> 5.1145833 | U20: =T20/$U$11 -> 0.054916786 | V20: =IF(U20<80%,"Parcial","Exclusivo") -> Parcial | W20: TRUE
T21: =IFERROR(__xludf.DUMMYFUNCTION("IFERROR(IF(W21=TRUE, SUM(FILTER(TIMESHEET!$G:$G,TIMESHEET!O:O = TRUE,TIMESHEET!P:P = TRUE,TIMESHEET!E:E = B21,TIMESHEET!F:F < DATE(2025,1,1))),0),0)"),0.0) -> 0 | U21: =T21/$U$11 -> 0 | V21: =IF(U21<80%,"Parcial","Exclusivo") -> Parcial | W21: TRUE
T22: =IFERROR(__xludf.DUMMYFUNCTION("IFERROR(IF(W22=TRUE, SUM(FILTER(TIMESHEET!$G:$G,TIMESHEET!O:O = TRUE,TIMESHEET!P:P = TRUE,TIMESHEET!E:E = B22,TIMESHEET!F:F < DATE(2025,1,1))),0),0)"),0.0) -> 0 | U22: =T22/$U$11 -> 0 | V22: =IF(U22<80%,"Parcial","Exclusivo") -> Parcial | W22: TRUE
T23: =IFERROR(__xludf.DUMMYFUNCTION("IFERROR(IF(W23=TRUE, SUM(FILTER(TIMESHEET!$G:$G,TIMESHEET!O:O = TRUE,TIMESHEET!P:P = TRUE,TIMESHEET!E:E = B23,TIMESHEET!F:F < DATE(2025,1,1))),0),0)"),0.0) -> 0 | U23: =T23/$U$11 -> 0 | V23: =IF(U23<80%,"Parcial","Exclusivo") -> Parcial | W23: TRUE
T24: =IFERROR(__xludf.DUMMYFUNCTION("IFERROR(IF(W24=TRUE, SUM(FILTER(TIMESHEET!$G:$G,TIMESHEET!O:O = TRUE,TIMESHEET!P:P = TRUE,TIMESHEET!E:E = B24,TIMESHEET!F:F < DATE(2025,1,1))),0),0)"),0.0) -> 0 | U24: =T24/$U$11 -> 0 | V24: =IF(U24<80%,"Parcial","Exclusivo") -> Parcial | W24: TRUE
T25: =IFERROR(__xludf.DUMMYFUNCTION("IFERROR(IF(W25=TRUE, SUM(FILTER(TIMESHEET!$G:$G,TIMESHEET!O:O = TRUE,TIMESHEET!P:P = TRUE,TIMESHEET!E:E = B25,TIMESHEET!F:F < DATE(2025,1,1))),0),0)"),0.0) -> 0 | U25: =T25/$U$11 -> 0 | V25: =IF(U25<80%,"Parcial","Exclusivo") -> Parcial | W25: TRUE
B27: Cálculo do custo/hora
B29: Encargos sobre folha | I29: INSS | J29: Patronal | K29: 0.2
B30: INSS | C30: FGTS | D30: Férias | E30: 13º | F30: Total | J30: Terceiros | K30: 0.058
B31: =SUM(K29:K31) -> 0.273 | C31: 0.08 | D31: =((1+(1/3))*(1+B31+C31)/12) -> 0.15033333 | E31: =(1+B31+C31)/12 -> 0.11275 | F31: =SUM(B31:E31) -> 0.61608333 | J31: RAT | K31: 0.015
H33: =NETWORKDAYS(DATE(right(H34,4),mid(H34,4,2),1),DATE(right(H34,4),mid(H34,4,2)+1,0),$B$50:$B$61) -> 22 | I33: =NETWORKDAYS(DATE(right(I34,4),mid(I34,4,2),1),DATE(right(I34,4),mid(I34,4,2)+1,0),$B$50:$B$61) -> 19 | J33: =NETWORKDAYS(DATE(right(J34,4),mid(J34,4,2),1),DATE(right(J34,4),mid(J34,4,2)+1,0),$B$50:$B$61) -> 20 | K33: =NETWORKDAYS(DATE(right(K34,4),mid(K34,4,2),1),DATE(right(K34,4),mid(K34,4,2)+1,0),$B$50:$B$61) -> 22 | L33: =NETWORKDAYS(DATE(right(L34,4),mid(L34,4,2),1),DATE(right(L34,4),mid(L34,4,2)+1,0),$B$50:$B$61) -> 22 | M33: =NETWORKDAYS(DATE(right(M34,4),mid(M34,4,2),1),DATE(right(M34,4),mid(M34,4,2)+1,0),$B$50:$B$61) -> 20 | N33: =NETWORKDAYS(DATE(right(N34,4),mid(N34,4,2),1),DATE(right(N34,4),mid(N34,4,2)+1,0),$B$50:$B$61) -> 23 | O33: =NETWORKDAYS(DATE(right(O34,4),mid(O34,4,2),1),DATE(right(O34,4),mid(O34,4,2)+1,0),$B$50:$B$61) -> 22 | ... S33: =NETWORKDAYS(DATE(right(S34,4),mid(S34,4,2),1),DATE(right(S34,4),mid(S34,4,2)+1,0),$B$50:$B$61) -> 21 | T33: =SUM(T35:T49) -> 99798.219 | U33: =SUM(U35:U49) -> 99798.219 | V33: =U33-T33 -> 0
B34: Nome Completo | E34: Classificação | F34: Formação | H34: 45322 | I34: 45350 | J34: 45382 | K34: 45412 | L34: 45443 | M34: 45473 | N34: 45504 | O34: 45535 | P34: 45565 | Q34: 45596 | R34: 45626 | S34: 45657 | T34: PD&I R$ | U34: Aprovado R$ | V34: Pesquisador
B35: {=unique(B13:B25)} -> Alyne Alves Nunes Oliveira | E35: {=V13:V25} -> Parcial | F35: {=F13:F25} -> Doutorado | H35: =vlookup($B35,$B$13:$S$23,month(H$34)+6,0)*(1+$F$31)/(H$33*8.8) -> 60.3926 | I35: =vlookup($B35,$B$13:$S$23,month(I$34)+6,0)*(1+$F$31)/(I$33*8.8) -> 69.928274 | J35: =vlookup($B35,$B$13:$S$23,month(J$34)+6,0)*(1+$F$31)/(J$33*8.8) -> 66.43186 | K35: =vlookup($B35,$B$13:$S$23,month(K$34)+6,0)*(1+$F$31)/(K$33*8.8) -> 60.3926 | L35: =vlookup($B35,$B$13:$S$23,month(L$34)+6,0)*(1+$F$31)/(L$33*8.8) -> 60.3926 | M35: =vlookup($B35,$B$13:$S$23,month(M$34)+6,0)*(1+$F$31)/(M$33*8.8) -> 66.43186 | N35: =vlookup($B35,$B$13:$S$23,month(N$34)+6,0)*(1+$F$31)/(N$33*8.8) -> 57.766835 | O35: =vlookup($B35,$B$13:$S$23,month(O$34)+6,0)*(1+$F$31)/(O$33*8.8) -> 63.412238 | ... S35: =vlookup($B35,$B$13:$S$23,month(S$34)+6,0)*(1+$F$31)/(S$33*8.8) -> 0 | T35: =SUMIF(TIMESHEET!E:E,B35,TIMESHEET!N:N) -> 20331.727 | U35: =SUMIF(V35,TRUE,T35) -> 20331.727 | V35: TRUE
B36: Ana Claudia Zanini | E36: Parcial | F36: Graduação | H36: =vlookup($B36,$B$13:$S$23,month(H$34)+6,0)*(1+$F$31)/(H$33*8.8) -> 51.282765 | I36: =vlookup($B36,$B$13:$S$23,month(I$34)+6,0)*(1+$F$31)/(I$33*8.8) -> 59.380044 | J36: =vlookup($B36,$B$13:$S$23,month(J$34)+6,0)*(1+$F$31)/(J$33*8.8) -> 56.411042 | K36: =vlookup($B36,$B$13:$S$23,month(K$34)+6,0)*(1+$F$31)/(K$33*8.8) -> 51.282765 | L36: =vlookup($B36,$B$13:$S$23,month(L$34)+6,0)*(1+$F$31)/(L$33*8.8) -> 51.282765 | M36: =vlookup($B36,$B$13:$S$23,month(M$34)+6,0)*(1+$F$31)/(M$33*8.8) -> 56.411042 | N36: =vlookup($B36,$B$13:$S$23,month(N$34)+6,0)*(1+$F$31)/(N$33*8.8) -> 49.05308 | O36: =vlookup($B36,$B$13:$S$23,month(O$34)+6,0)*(1+$F$31)/(O$33*8.8) -> 63.5564 | ... S36: =vlookup($B36,$B$13:$S$23,month(S$34)+6,0)*(1+$F$31)/(S$33*8.8) -> 66.582896 | T36: =SUMIF(TIMESHEET!E:E,B36,TIMESHEET!N:N) -> 13740.744 | U36: =SUMIF(V36,TRUE,T36) -> 13740.744 | V36: TRUE
B37: Ana Paula Biz | E37: Parcial | F37: Doutorado | H37: =vlookup($B37,$B$13:$S$23,month(H$34)+6,0)*(1+$F$31)/(H$33*8.8) -> 38.351177 | I37: =vlookup($B37,$B$13:$S$23,month(I$34)+6,0)*(1+$F$31)/(I$33*8.8) -> 44.406626 | J37: =vlookup($B37,$B$13:$S$23,month(J$34)+6,0)*(1+$F$31)/(J$33*8.8) -> 42.186294 | K37: =vlookup($B37,$B$13:$S$23,month(K$34)+6,0)*(1+$F$31)/(K$33*8.8) -> 38.351177 | L37: =vlookup($B37,$B$13:$S$23,month(L$34)+6,0)*(1+$F$31)/(L$33*8.8) -> 38.351177 | M37: =vlookup($B37,$B$13:$S$23,month(M$34)+6,0)*(1+$F$31)/(M$33*8.8) -> 42.186294 | N37: =vlookup($B37,$B$13:$S$23,month(N$34)+6,0)*(1+$F$31)/(N$33*8.8) -> 36.683734 | O37: =vlookup($B37,$B$13:$S$23,month(O$34)+6,0)*(1+$F$31)/(O$33*8.8) -> 40.268773 | ... S37: =vlookup($B37,$B$13:$S$23,month(S$34)+6,0)*(1+$F$31)/(S$33*8.8) -> 47.933661 | T37: =SUMIF(TIMESHEET!E:E,B37,TIMESHEET!N:N) -> 9772.0299 | U37: =SUMIF(V37,TRUE,T37) -> 9772.0299 | V37: TRUE
B38: Ana Paula Celes | E38: Parcial | F38: Pós Graduado | G38: PJ | H38: =vlookup($B38,$B$13:$S$23,month(H$34)+6,0)/(H$33*8.8) -> 195.01896 | I38: =vlookup($B38,$B$13:$S$23,month(I$34)+6,0)/(I$33*8.8) -> 225.81142 | J38: =vlookup($B38,$B$13:$S$23,month(J$34)+6,0)/(J$33*8.8) -> 214.52085 | K38: =vlookup($B38,$B$13:$S$23,month(K$34)+6,0)/(K$33*8.8) -> 195.01896 | L38: =vlookup($B38,$B$13:$S$23,month(L$34)+6,0)/(L$33*8.8) -> 195.01896 | M38: =vlookup($B38,$B$13:$S$23,month(M$34)+6,0)/(M$33*8.8) -> 214.52085 | N38: =vlookup($B38,$B$13:$S$23,month(N$34)+6,0)/(N$33*8.8) -> 186.53987 | O38: =vlookup($B38,$B$13:$S$23,month(O$34)+6,0)/(O$33*8.8) -> 192.37319 | ... S38: =vlookup($B38,$B$13:$S$23,month(S$34)+6,0)/(S$33*8.8) -> 201.53382 | T38: =SUMIF(TIMESHEET!E:E,B38,TIMESHEET!N:N) -> 1843.959 | U38: =SUMIF(V38,TRUE,T38) -> 1843.959 | V38: TRUE
B39: Camila Mendes Pereira | E39: Parcial | F39: Graduação | H39: =vlookup($B39,$B$13:$S$23,month(H$34)+6,0)*(1+$F$31)/(H$33*8.8) -> 45.659029 | I39: =vlookup($B39,$B$13:$S$23,month(I$34)+6,0)*(1+$F$31)/(I$33*8.8) -> 52.868349 | J39: =vlookup($B39,$B$13:$S$23,month(J$34)+6,0)*(1+$F$31)/(J$33*8.8) -> 50.224932 | K39: =vlookup($B39,$B$13:$S$23,month(K$34)+6,0)*(1+$F$31)/(K$33*8.8) -> 45.659029 | L39: =vlookup($B39,$B$13:$S$23,month(L$34)+6,0)*(1+$F$31)/(L$33*8.8) -> 45.659029 | M39: =vlookup($B39,$B$13:$S$23,month(M$34)+6,0)*(1+$F$31)/(M$33*8.8) -> 50.224932 | N39: =vlookup($B39,$B$13:$S$23,month(N$34)+6,0)*(1+$F$31)/(N$33*8.8) -> 46.717184 | O39: =vlookup($B39,$B$13:$S$23,month(O$34)+6,0)*(1+$F$31)/(O$33*8.8) -> 51.282765 | ... S39: =vlookup($B39,$B$13:$S$23,month(S$34)+6,0)*(1+$F$31)/(S$33*8.8) -> 53.724801 | T39: =SUMIF(TIMESHEET!E:E,B39,TIMESHEET!N:N) -> 3239.6395 | U39: =SUMIF(V39,TRUE,T39) -> 3239.6395 | V39: TRUE
B40: Gabriela Faria de Oliveira | E40: Parcial | F40: Pós Graduado | H40: =vlookup($B40,$B$13:$S$23,month(H$34)+6,0)*(1+$F$31)/(H$33*8.8) -> 47.941997 | I40: =vlookup($B40,$B$13:$S$23,month(I$34)+6,0)*(1+$F$31)/(I$33*8.8) -> 55.511786 | J40: =vlookup($B40,$B$13:$S$23,month(J$34)+6,0)*(1+$F$31)/(J$33*8.8) -> 52.736197 | K40: =vlookup($B40,$B$13:$S$23,month(K$34)+6,0)*(1+$F$31)/(K$33*8.8) -> 47.941997 | L40: =vlookup($B40,$B$13:$S$23,month(L$34)+6,0)*(1+$F$31)/(L$33*8.8) -> 47.941997 | M40: =vlookup($B40,$B$13:$S$23,month(M$34)+6,0)*(1+$F$31)/(M$33*8.8) -> 52.736197 | N40: =vlookup($B40,$B$13:$S$23,month(N$34)+6,0)*(1+$F$31)/(N$33*8.8) -> 49.05308 | O40: =vlookup($B40,$B$13:$S$23,month(O$34)+6,0)*(1+$F$31)/(O$33*8.8) -> 60.3926 | ... S40: =vlookup($B40,$B$13:$S$23,month(S$34)+6,0)*(1+$F$31)/(S$33*8.8) -> 63.268438 | T40: =SUMIF(TIMESHEET!E:E,B40,TIMESHEET!N:N) -> 21526.287 | U40: =SUMIF(V40,TRUE,T40) -> 21526.287 | V40: TRUE
B41: Juliana Lamas Roberto | E41: Parcial | F41: Mestrado | H41: =vlookup($B41,$B$13:$S$23,month(H$34)+6,0)*(1+$F$31)/(H$33*8.8) -> 93.70512 | I41: =vlookup($B41,$B$13:$S$23,month(I$34)+6,0)*(1+$F$31)/(I$33*8.8) -> 108.50066 | J41: =vlookup($B41,$B$13:$S$23,month(J$34)+6,0)*(1+$F$31)/(J$33*8.8) -> 103.07563 | K41: =vlookup($B41,$B$13:$S$23,month(K$34)+6,0)*(1+$F$31)/(K$33*8.8) -> 93.70512 | L41: =vlookup($B41,$B$13:$S$23,month(L$34)+6,0)*(1+$F$31)/(L$33*8.8) -> 93.70512 | M41: =vlookup($B41,$B$13:$S$23,month(M$34)+6,0)*(1+$F$31)/(M$33*8.8) -> 103.07563 | N41: =vlookup($B41,$B$13:$S$23,month(N$34)+6,0)*(1+$F$31)/(N$33*8.8) -> 89.630984 | O41: =vlookup($B41,$B$13:$S$23,month(O$34)+6,0)*(1+$F$31)/(O$33*8.8) -> 98.390342 | ... S41: =vlookup($B41,$B$13:$S$23,month(S$34)+6,0)*(1+$F$31)/(S$33*8.8) -> 103.0756 | T41: =SUMIF(TIMESHEET!E:E,B41,TIMESHEET!N:N) -> 23918.22 | U41: =SUMIF(V41,TRUE,T41) -> 23918.22 | V41: TRUE
B42: Raissa Bellotti | E42: Parcial | F42: Pós Graduado | H42: =vlookup($B42,$B$13:$S$23,month(H$34)+6,0)*(1+$F$31)/(H$33*8.8) -> 39.904737 | I42: =vlookup($B42,$B$13:$S$23,month(I$34)+6,0)*(1+$F$31)/(I$33*8.8) -> 46.205485 | J42: =vlookup($B42,$B$13:$S$23,month(J$34)+6,0)*(1+$F$31)/(J$33*8.8) -> 43.895211 | K42: =vlookup($B42,$B$13:$S$23,month(K$34)+6,0)*(1+$F$31)/(K$33*8.8) -> 39.904737 | L42: =vlookup($B42,$B$13:$S$23,month(L$34)+6,0)*(1+$F$31)/(L$33*8.8) -> 39.904737 | M42: =vlookup($B42,$B$13:$S$23,month(M$34)+6,0)*(1+$F$31)/(M$33*8.8) -> 43.895211 | N42: =vlookup($B42,$B$13:$S$23,month(N$34)+6,0)*(1+$F$31)/(N$33*8.8) -> 38.169748 | O42: =vlookup($B42,$B$13:$S$23,month(O$34)+6,0)*(1+$F$31)/(O$33*8.8) -> 45.754859 | ... S42: =vlookup($B42,$B$13:$S$23,month(S$34)+6,0)*(1+$F$31)/(S$33*8.8) -> 47.933661 | T42: =SUMIF(TIMESHEET!E:E,B42,TIMESHEET!N:N) -> 5425.6135 | U42: =SUMIF(V42,TRUE,T42) -> 5425.6135 | V42: TRUE
E43: Parcial | H43: =vlookup($B43,$B$13:$S$23,month(H$34)+6,0)*(1+$F$31)/(H$33*8.8) -> #N/A | I43: =vlookup($B43,$B$13:$S$23,month(I$34)+6,0)*(1+$F$31)/(I$33*8.8) -> #N/A | J43: =vlookup($B43,$B$13:$S$23,month(J$34)+6,0)*(1+$F$31)/(J$33*8.8) -> #N/A | K43: =vlookup($B43,$B$13:$S$23,month(K$34)+6,0)*(1+$F$31)/(K$33*8.8) -> #N/A | L43: =vlookup($B43,$B$13:$S$23,month(L$34)+6,0)*(1+$F$31)/(L$33*8.8) -> #N/A | M43: =vlookup($B43,$B$13:$S$23,month(M$34)+6,0)*(1+$F$31)/(M$33*8.8) -> #N/A | N43: =vlookup($B43,$B$13:$S$23,month(N$34)+6,0)*(1+$F$31)/(N$33*8.8) -> #N/A | O43: =vlookup($B43,$B$13:$S$23,month(O$34)+6,0)*(1+$F$31)/(O$33*8.8) -> #N/A | ... S43: =vlookup($B43,$B$13:$S$23,month(S$34)+6,0)*(1+$F$31)/(S$33*8.8) -> #N/A | T43: =SUMIF(TIMESHEET!E:E,B43,TIMESHEET!N:N) -> 0 | U43: =SUMIF(V43,TRUE,T43) -> 0 | V43: TRUE
E44: Parcial | H44: =vlookup($B44,$B$13:$S$25,month(H$34)+6,0)*(1+$F$31)/(H$33*8.8) -> #N/A | I44: =vlookup($B44,$B$13:$S$23,month(I$34)+6,0)*(1+$F$31)/(I$33*8.8) -> #N/A | J44: =vlookup($B44,$B$13:$S$23,month(J$34)+6,0)*(1+$F$31)/(J$33*8.8) -> #N/A | K44: =vlookup($B44,$B$13:$S$23,month(K$34)+6,0)*(1+$F$31)/(K$33*8.8) -> #N/A | L44: =vlookup($B44,$B$13:$S$23,month(L$34)+6,0)*(1+$F$31)/(L$33*8.8) -> #N/A | M44: =vlookup($B44,$B$13:$S$23,month(M$34)+6,0)*(1+$F$31)/(M$33*8.8) -> #N/A | N44: =vlookup($B44,$B$13:$S$23,month(N$34)+6,0)*(1+$F$31)/(N$33*8.8) -> #N/A | O44: =vlookup($B44,$B$13:$S$23,month(O$34)+6,0)*(1+$F$31)/(O$33*8.8) -> #N/A | P44: =vlookup($B44,$B$13:$S$23,month(P$34)+6,0)*(1+$F$31)/(P$33*8.8) -> #N/A | ... S44: =vlookup($B44,$B$13:$S$23,month(S$34)+6,0)*(1+$F$31)/(S$33*8.8) -> #N/A | T44: =SUMIF(TIMESHEET!E:E,B44,TIMESHEET!N:N) -> 0 | U44: =SUMIF(V44,TRUE,T44) -> 0 | V44: TRUE
E45: Parcial | H45: =vlookup($B45,$B$13:$S$23,month(H$34)+6,0)*(1+$F$31)/(H$33*8.8) -> #N/A | I45: =vlookup($B45,$B$13:$S$23,month(I$34)+6,0)*(1+$F$31)/(I$33*8.8) -> #N/A | J45: =vlookup($B45,$B$13:$S$23,month(J$34)+6,0)*(1+$F$31)/(J$33*8.8) -> #N/A | K45: =vlookup($B45,$B$13:$S$23,month(K$34)+6,0)*(1+$F$31)/(K$33*8.8) -> #N/A | L45: =vlookup($B45,$B$13:$S$23,month(L$34)+6,0)*(1+$F$31)/(L$33*8.8) -> #N/A | M45: =vlookup($B45,$B$13:$S$23,month(M$34)+6,0)*(1+$F$31)/(M$33*8.8) -> #N/A | N45: =vlookup($B45,$B$13:$S$23,month(N$34)+6,0)*(1+$F$31)/(N$33*8.8) -> #N/A | O45: =vlookup($B45,$B$13:$S$23,month(O$34)+6,0)*(1+$F$31)/(O$33*8.8) -> #N/A | ... S45: =vlookup($B45,$B$13:$S$23,month(S$34)+6,0)*(1+$F$31)/(S$33*8.8) -> #N/A | T45: =SUMIF(TIMESHEET!E:E,B45,TIMESHEET!N:N) -> 0 | U45: =SUMIF(V45,TRUE,T45) -> 0 | V45: TRUE
E46: Parcial | H46: =vlookup($B46,$B$13:$S$25,month(H$34)+6,0)*(1+$F$31)/(H$33*8.8) -> #N/A | I46: =vlookup($B46,$B$13:$S$25,month(I$34)+6,0)*(1+$F$31)/(I$33*8.8) -> #N/A | J46: =vlookup($B46,$B$13:$S$25,month(J$34)+6,0)*(1+$F$31)/(J$33*8.8) -> #N/A | K46: =vlookup($B46,$B$13:$S$25,month(K$34)+6,0)*(1+$F$31)/(K$33*8.8) -> #N/A | L46: =vlookup($B46,$B$13:$S$25,month(L$34)+6,0)*(1+$F$31)/(L$33*8.8) -> #N/A | M46: =vlookup($B46,$B$13:$S$25,month(M$34)+6,0)*(1+$F$31)/(M$33*8.8) -> #N/A | N46: =vlookup($B46,$B$13:$S$25,month(N$34)+6,0)*(1+$F$31)/(N$33*8.8) -> #N/A | O46: =vlookup($B46,$B$13:$S$25,month(O$34)+6,0)*(1+$F$31)/(O$33*8.8) -> #N/A | ... S46: =vlookup($B46,$B$13:$S$25,month(S$34)+6,0)*(1+$F$31)/(S$33*8.8) -> #N/A | T46: =SUMIF(TIMESHEET!E:E,B46,TIMESHEET!N:N) -> 0 | U46: =SUMIF(V46,TRUE,T46) -> 0 | V46: TRUE
E47: Parcial | H47: =vlookup($B47,$B$13:$S$25,month(H$34)+6,0)*(1+$F$31)/(H$33*8.8) -> #N/A | I47: =vlookup($B47,$B$13:$S$25,month(I$34)+6,0)*(1+$F$31)/(I$33*8.8) -> #N/A | J47: =vlookup($B47,$B$13:$S$25,month(J$34)+6,0)*(1+$F$31)/(J$33*8.8) -> #N/A | K47: =vlookup($B47,$B$13:$S$25,month(K$34)+6,0)*(1+$F$31)/(K$33*8.8) -> #N/A | L47: =vlookup($B47,$B$13:$S$25,month(L$34)+6,0)*(1+$F$31)/(L$33*8.8) -> #N/A | M47: =vlookup($B47,$B$13:$S$25,month(M$34)+6,0)*(1+$F$31)/(M$33*8.8) -> #N/A | N47: =vlookup($B47,$B$13:$S$25,month(N$34)+6,0)*(1+$F$31)/(N$33*8.8) -> #N/A | O47: =vlookup($B47,$B$13:$S$25,month(O$34)+6,0)*(1+$F$31)/(O$33*8.8) -> #N/A | ... S47: =vlookup($B47,$B$13:$S$25,month(S$34)+6,0)*(1+$F$31)/(S$33*8.8) -> #N/A | T47: =SUMIF(TIMESHEET!E:E,B47,TIMESHEET!N:N) -> 0 | U47: =SUMIF(V47,TRUE,T47) -> 0 | V47: TRUE
B49: Feriados
B50: 45292 | C50: Ano Novo
B51: 45335 | C51: Carnaval
B52: 45336 | C52: 4ª feira de Cinzas (trabalhamos somente a partir das 13h)
B53: 45380 | C53: Sexta-feira Santa
B54: 45382 | C54: Páscoa
B55: 45442 | C55: Corpus Christi
B56: 45595 | C56: Feriado Municipal
B57: 45616 | C57: Consciência Negra
B58: 45651 | C58: Natal

Sheet TERCEIROS
B2: PRODIET
B3: Pesquisa ,Desenvolvimento & Inovação
B4: Formulário de PD&I - Ano2024
B5: -preencher somente os campos sombreados (cinza)
O7: Rateio
B8: Dossiê do projeto
B9: Investimentos com terceiros | H9: =SUBTOTAL(9,H24:H97) -> 459074.9 | K9: Diferença | Q9: {=XLOOKUP(Q11,'Base Projetos'!$A:$A,'Base Projetos'!$B:$B,FALSE)} -> TRUE | R9: {=XLOOKUP(R11,'Base Projetos'!$A:$A,'Base Projetos'!$B:$B,FALSE)} -> FALSE | S9: {=XLOOKUP(S11,'Base Projetos'!$A:$A,'Base Projetos'!$B:$B,FALSE)} -> TRUE | T9: {=XLOOKUP(T11,'Base Projetos'!$A:$A,'Base Projetos'!$B:$B,FALSE)} -> TRUE | U9: {=XLOOKUP(U11,'Base Projetos'!$A:$A,'Base Projetos'!$B:$B,FALSE)} -> TRUE | V9: {=XLOOKUP(V11,'Base Projetos'!$A:$A,'Base Projetos'!$B:$B,FALSE)} -> FALSE | W9: {=XLOOKUP(W11,'Base Projetos'!$A:$A,'Base Projetos'!$B:$B,FALSE)} -> TRUE | X9: {=XLOOKUP(X11,'Base Projetos'!$A:$A,'Base Projetos'!$B:$B,FALSE)} -> TRUE | ... BE9: {=XLOOKUP(BE11,'Base Projetos'!$A:$A,'Base Projetos'!$B:$B,FALSE)} -> FALSE
H10: =SUM(H12:H1135) -> 527033.36 | M10: =sum(M12:M1135) -> 363268.97 | O10: =sum(Q10:BE10) -> 363268.97 | Q10: =SUM(Q12:Q1135) -> 112121.99 | R10: =SUM(R12:R1135) -> 0 | S10: =SUM(S12:S1135) -> 5388.575 | T10: =SUM(T12:T1135) -> 5322.08 | U10: =SUM(U12:U1135) -> 12156.39 | V10: =SUM(V12:V1135) -> 0 | W10: =SUM(W12:W1135) -> 32488.45 | X10: =SUM(X12:X1135) -> 49956.91 | ... BE10: =SUM(BE12:BE1135) -> 0
B11: Projeto | C11: Etapa | D11: Fornecedor | F11: CNPJ | G11: Notafiscal | H11: Valor | I11: Data | J11: Descrição da Atividade | K11: Objetivo do gasto e eventual info de rateio | L11: Incentivado? | M11: Valor incentivado | O11: Conf. val. rateio | P11: Count | Q11: INOV00001 | R11: INOV00003 | S11: INOV00004 | T11: INOV00006 | U11: INOV00010 | V11: INOV00012 | W11: INOV00013 | X11: INOV00014 | Y11: INOV00015 | Z11: INOV00016 | AA11: INOV00017 | AB11: INOV00018 | AC11: INOV00019 | AD11: INOV00020 | AE11: INOV00021 | AF11: INOV00022 | AG11: INOV00023 | AH11: INOV00024 | AI11: INOV00025 | AJ11: INOV00026 | AK11: INOV00027 | AL11: INOV00028 | AM11: INOV00029 | AN11: INOV00030 | AO11: INOV00031 | AP11: INOV00032 | AQ11: INOV00034 | AR11: INOV00035 | AS11: INOV00036 | AT11: INOV00037 | AU11: INOV00038 | AV11: INOV00039 | AW11: INOV00040 | AX11: INOV00041 | AY11: INOV00046 | AZ11: INOV00047 | BA11: INOV00048 | BB11: INOV00049 | BC11: INOV00050 | BD11: INOV00051 | BE11: INOV00052
B12: INOV00013 | D12: Eurofins do Brasil Análise de Alimentos Ltda. | F12: 04.329.668/0001-38 | G12: 234790 | H12: 15029.59 | I12: 45302 | J12: Análise de vitaminas, minerais e macronutrientes. | L12: TRUE | M12: =SUM(Q12:BE12) -> 15029.59 | O12: =SUM(Q12:AP12)=H12 -> TRUE | P12: =IF(L12=FALSE,0,IF(LEN(B12)=0,0,IF(LEN(B12)=9,1,(LEN(B12)+1)/10))) -> 1 | Q12: =iferror(if(Q$9=FALSE,, if(if(search(Q$11,$B12,1)>0,1,0)=1,$H12/$P12,)),"") | R12: =iferror(if(R$9=FALSE,, if(if(search(R$11,$B12,1)>0,1,0)=1,$H12/$P12,)),"") | S12: =iferror(if(S$9=FALSE,, if(if(search(S$11,$B12,1)>0,1,0)=1,$H12/$P12,)),"") | T12: =iferror(if(T$9=FALSE,, if(if(search(T$11,$B12,1)>0,1,0)=1,$H12/$P12,)),"") | U12: =iferror(if(U$9=FALSE,, if(if(search(U$11,$B12,1)>0,1,0)=1,$H12/$P12,)),"") | V12: =iferror(if(V$9=FALSE,, if(if(search(V$11,$B12,1)>0,1,0)=1,$H12/$P12,)),"") | W12: =iferror(if(W$9=FALSE,, if(if(search(W$11,$B12,1)>0,1,0)=1,$H12/$P12,)),"") -> 15029.59 | X12: =iferror(if(X$9=FALSE,, if(if(search(X$11,$B12,1)>0,1,0)=1,$H12/$P12,)),"") | ... BE12: =iferror(if(BE$9=FALSE,, if(if(search(BE$11,$B12,1)>0,1,0)=1,$H12/$P12,)),"")
B13: INOV00006 | D13: Eurofins do Brasil Análise de Alimentos Ltda. | F13: 04.329.668/0001-38 | G13: 235095 | H13: 5322.08 | I13: 45307 | J13: Análise de vitaminas, minerais e macronutrientes. | L13: TRUE | M13: =SUM(Q13:BE13) -> 5322.08 | O13: =SUM(Q13:AP13)=H13 -> TRUE | P13: =IF(L13=FALSE,0,IF(LEN(B13)=0,0,IF(LEN(B13)=9,1,(LEN(B13)+1)/10))) -> 1 | Q13: =iferror(if(Q$9=FALSE,, if(if(search(Q$11,$B13,1)>0,1,0)=1,$H13/$P13,)),"") | R13: =iferror(if(R$9=FALSE,, if(if(search(R$11,$B13,1)>0,1,0)=1,$H13/$P13,)),"") | S13: =iferror(if(S$9=FALSE,, if(if(search(S$11,$B13,1)>0,1,0)=1,$H13/$P13,)),"") | T13: =iferror(if(T$9=FALSE,, if(if(search(T$11,$B13,1)>0,1,0)=1,$H13/$P13,)),"") -> 5322.08 | U13: =iferror(if(U$9=FALSE,, if(if(search(U$11,$B13,1)>0,1,0)=1,$H13/$P13,)),"") | V13: =iferror(if(V$9=FALSE,, if(if(search(V$11,$B13,1)>0,1,0)=1,$H13/$P13,)),"") | W13: =iferror(if(W$9=FALSE,, if(if(search(W$11,$B13,1)>0,1,0)=1,$H13/$P13,)),"") | X13: =iferror(if(X$9=FALSE,, if(if(search(X$11,$B13,1)>0,1,0)=1,$H13/$P13,)),"") | ... BE13: =iferror(if(BE$9=FALSE,, if(if(search(BE$11,$B13,1)>0,1,0)=1,$H13/$P13,)),"")
B14: INOV00013 | D14: Fundação de apoio à Pesquisa | F14: 50.276.237/0001-78 | G14: 149770 | H14: 2556 | I14: 45309 | J14: Análise de PL. | L14: TRUE | M14: =SUM(Q14:BE14) -> 2556 | O14: =SUM(Q14:AP14)=H14 -> TRUE | P14: =IF(L14=FALSE,0,IF(LEN(B14)=0,0,IF(LEN(B14)=9,1,(LEN(B14)+1)/10))) -> 1 | Q14: =iferror(if(Q$9=FALSE,, if(if(search(Q$11,$B14,1)>0,1,0)=1,$H14/$P14,)),"") | R14: =iferror(if(R$9=FALSE,, if(if(search(R$11,$B14,1)>0,1,0)=1,$H14/$P14,)),"") | S14: =iferror(if(S$9=FALSE,, if(if(search(S$11,$B14,1)>0,1,0)=1,$H14/$P14,)),"") | T14: =iferror(if(T$9=FALSE,, if(if(search(T$11,$B14,1)>0,1,0)=1,$H14/$P14,)),"") | U14: =iferror(if(U$9=FALSE,, if(if(search(U$11,$B14,1)>0,1,0)=1,$H14/$P14,)),"") | V14: =iferror(if(V$9=FALSE,, if(if(search(V$11,$B14,1)>0,1,0)=1,$H14/$P14,)),"") | W14: =iferror(if(W$9=FALSE,, if(if(search(W$11,$B14,1)>0,1,0)=1,$H14/$P14,)),"") -> 2556 | X14: =iferror(if(X$9=FALSE,, if(if(search(X$11,$B14,1)>0,1,0)=1,$H14/$P14,)),"") | ... BE14: =iferror(if(BE$9=FALSE,, if(if(search(BE$11,$B14,1)>0,1,0)=1,$H14/$P14,)),"")
B15: INOV00037 | D15: PRODIET NUTRICAO CLINICA LTDA | F15: 08.183.359/0003-15 | G15: 82609 | H15: 4821.12 | I15: 45322 | J15: Doação de Produto Immax para Pesquisa Clinica | L15: FALSE | M15: =SUM(Q15:BE15) -> 0 | O15: =SUM(Q15:AP15)=H15 -> FALSE | P15: =IF(L15=FALSE,0,IF(LEN(B15)=0,0,IF(LEN(B15)=9,1,(LEN(B15)+1)/10))) -> 0 | Q15: =iferror(if(Q$9=FALSE,, if(if(search(Q$11,$B15,1)>0,1,0)=1,$H15/$P15,)),"") | R15: =iferror(if(R$9=FALSE,, if(if(search(R$11,$B15,1)>0,1,0)=1,$H15/$P15,)),"") | S15: =iferror(if(S$9=FALSE,, if(if(search(S$11,$B15,1)>0,1,0)=1,$H15/$P15,)),"") | T15: =iferror(if(T$9=FALSE,, if(if(search(T$11,$B15,1)>0,1,0)=1,$H15/$P15,)),"") | U15: =iferror(if(U$9=FALSE,, if(if(search(U$11,$B15,1)>0,1,0)=1,$H15/$P15,)),"") | V15: =iferror(if(V$9=FALSE,, if(if(search(V$11,$B15,1)>0,1,0)=1,$H15/$P15,)),"") | W15: =iferror(if(W$9=FALSE,, if(if(search(W$11,$B15,1)>0,1,0)=1,$H15/$P15,)),"") | X15: =iferror(if(X$9=FALSE,, if(if(search(X$11,$B15,1)>0,1,0)=1,$H15/$P15,)),"") | ... BE15: =iferror(if(BE$9=FALSE,, if(if(search(BE$11,$B15,1)>0,1,0)=1,$H15/$P15,)),"")
B16: INOV00016 | D16: Eurofins do Brasil Análise de Alimentos Ltda. | F16: 04.329.668/0001-38 | G16: 235962 | H16: 971.04 | I16: 45323 | J16: Análise de Vitamina C. | L16: TRUE | M16: =SUM(Q16:BE16) -> 971.04 | O16: =SUM(Q16:AP16)=H16 -> TRUE | P16: =IF(L16=FALSE,0,IF(LEN(B16)=0,0,IF(LEN(B16)=9,1,(LEN(B16)+1)/10))) -> 1 | Q16: =iferror(if(Q$9=FALSE,, if(if(search(Q$11,$B16,1)>0,1,0)=1,$H16/$P16,)),"") | R16: =iferror(if(R$9=FALSE,, if(if(search(R$11,$B16,1)>0,1,0)=1,$H16/$P16,)),"") | S16: =iferror(if(S$9=FALSE,, if(if(search(S$11,$B16,1)>0,1,0)=1,$H16/$P16,)),"") | T16: =iferror(if(T$9=FALSE,, if(if(search(T$11,$B16,1)>0,1,0)=1,$H16/$P16,)),"") | U16: =iferror(if(U$9=FALSE,, if(if(search(U$11,$B16,1)>0,1,0)=1,$H16/$P16,)),"") | V16: =iferror(if(V$9=FALSE,, if(if(search(V$11,$B16,1)>0,1,0)=1,$H16/$P16,)),"") | W16: =iferror(if(W$9=FALSE,, if(if(search(W$11,$B16,1)>0,1,0)=1,$H16/$P16,)),"") | X16: =iferror(if(X$9=FALSE,, if(if(search(X$11,$B16,1)>0,1,0)=1,$H16/$P16,)),"") | ... BE16: =iferror(if(BE$9=FALSE,, if(if(search(BE$11,$B16,1)>0,1,0)=1,$H16/$P16,)),"")
B17: INOV00010 | D17: J&J Serviços de Entregas Ltda - ME | F17: 20.618.029/0001-49 | G17: 75457 | H17: 250.4 | I17: 45324 | J17: Envio para análise. | L17: TRUE | M17: =SUM(Q17:BE17) -> 250.4 | O17: =SUM(Q17:AP17)=H17 -> TRUE | P17: =IF(L17=FALSE,0,IF(LEN(B17)=0,0,IF(LEN(B17)=9,1,(LEN(B17)+1)/10))) -> 1 | Q17: =iferror(if(Q$9=FALSE,, if(if(search(Q$11,$B17,1)>0,1,0)=1,$H17/$P17,)),"") | R17: =iferror(if(R$9=FALSE,, if(if(search(R$11,$B17,1)>0,1,0)=1,$H17/$P17,)),"") | S17: =iferror(if(S$9=FALSE,, if(if(search(S$11,$B17,1)>0,1,0)=1,$H17/$P17,)),"") | T17: =iferror(if(T$9=FALSE,, if(if(search(T$11,$B17,1)>0,1,0)=1,$H17/$P17,)),"") | U17: =iferror(if(U$9=FALSE,, if(if(search(U$11,$B17,1)>0,1,0)=1,$H17/$P17,)),"") -> 250.4 | V17: =iferror(if(V$9=FALSE,, if(if(search(V$11,$B17,1)>0,1,0)=1,$H17/$P17,)),"") | W17: =iferror(if(W$9=FALSE,, if(if(search(W$11,$B17,1)>0,1,0)=1,$H17/$P17,)),"") | X17: =iferror(if(X$9=FALSE,, if(if(search(X$11,$B17,1)>0,1,0)=1,$H17/$P17,)),"") | ... BE17: =iferror(if(BE$9=FALSE,, if(if(search(BE$11,$B17,1)>0,1,0)=1,$H17/$P17,)),"")
B18: INOV00010 | D18: Eurofins do Brasil Análise de Alimentos Ltda. | F18: 04.329.668/0001-38 | G18: 237669 | H18: 10113.99 | I18: 45344 | J18: Análise de vitaminas, minerais e macronutrientes. | L18: TRUE | M18: =SUM(Q18:BE18) -> 10113.99 | O18: =SUM(Q18:AP18)=H18 -> TRUE | P18: =IF(L18=FALSE,0,IF(LEN(B18)=0,0,IF(LEN(B18)=9,1,(LEN(B18)+1)/10))) -> 1 | Q18: =iferror(if(Q$9=FALSE,, if(if(search(Q$11,$B18,1)>0,1,0)=1,$H18/$P18,)),"") | R18: =iferror(if(R$9=FALSE,, if(if(search(R$11,$B18,1)>0,1,0)=1,$H18/$P18,)),"") | S18: =iferror(if(S$9=FALSE,, if(if(search(S$11,$B18,1)>0,1,0)=1,$H18/$P18,)),"") | T18: =iferror(if(T$9=FALSE,, if(if(search(T$11,$B18,1)>0,1,0)=1,$H18/$P18,)),"") | U18: =iferror(if(U$9=FALSE,, if(if(search(U$11,$B18,1)>0,1,0)=1,$H18/$P18,)),"") -> 10113.99 | V18: =iferror(if(V$9=FALSE,, if(if(search(V$11,$B18,1)>0,1,0)=1,$H18/$P18,)),"") | W18: =iferror(if(W$9=FALSE,, if(if(search(W$11,$B18,1)>0,1,0)=1,$H18/$P18,)),"") | X18: =iferror(if(X$9=FALSE,, if(if(search(X$11,$B18,1)>0,1,0)=1,$H18/$P18,)),"") | ... BE18: =iferror(if(BE$9=FALSE,, if(if(search(BE$11,$B18,1)>0,1,0)=1,$H18/$P18,)),"")
B19: INOV00010 | D19: Fundação de Desenvolvimento da Pesquisa do Agronegocio | F19: 50.276.237/0001-78 | G19: 150563 | H19: 1792 | I19: 45352 | J19: Análise de PL. | L19: TRUE | M19: =SUM(Q19:BE19) -> 1792 | O19: =SUM(Q19:AP19)=H19 -> TRUE | P19: =IF(L19=FALSE,0,IF(LEN(B19)=0,0,IF(LEN(B19)=9,1,(LEN(B19)+1)/10))) -> 1 | Q19: =iferror(if(Q$9=FALSE,, if(if(search(Q$11,$B19,1)>0,1,0)=1,$H19/$P19,)),"") | R19: =iferror(if(R$9=FALSE,, if(if(search(R$11,$B19,1)>0,1,0)=1,$H19/$P19,)),"") | S19: =iferror(if(S$9=FALSE,, if(if(search(S$11,$B19,1)>0,1,0)=1,$H19/$P19,)),"") | T19: =iferror(if(T$9=FALSE,, if(if(search(T$11,$B19,1)>0,1,0)=1,$H19/$P19,)),"") | U19: =iferror(if(U$9=FALSE,, if(if(search(U$11,$B19,1)>0,1,0)=1,$H19/$P19,)),"") -> 1792 | V19: =iferror(if(V$9=FALSE,, if(if(search(V$11,$B19,1)>0,1,0)=1,$H19/$P19,)),"") | W19: =iferror(if(W$9=FALSE,, if(if(search(W$11,$B19,1)>0,1,0)=1,$H19/$P19,)),"") | X19: =iferror(if(X$9=FALSE,, if(if(search(X$11,$B19,1)>0,1,0)=1,$H19/$P19,)),"") | ... BE19: =iferror(if(BE$9=FALSE,, if(if(search(BE$11,$B19,1)>0,1,0)=1,$H19/$P19,)),"")
B20: INOV00023 | D20: RaiaDrogasil S/A | F20: 61.585.865/3103-47 | G20: 13955 | H20: 1205.5 | I20: 45352 | J20: Doação de sensores para Pesquisa Clínica | L20: FALSE | M20: =SUM(Q20:BE20) -> 0 | O20: =SUM(Q20:AP20)=H20 -> FALSE | P20: =IF(L20=FALSE,0,IF(LEN(B20)=0,0,IF(LEN(B20)=9,1,(LEN(B20)+1)/10))) -> 0 | Q20: =iferror(if(Q$9=FALSE,, if(if(search(Q$11,$B20,1)>0,1,0)=1,$H20/$P20,)),"") | R20: =iferror(if(R$9=FALSE,, if(if(search(R$11,$B20,1)>0,1,0)=1,$H20/$P20,)),"") | S20: =iferror(if(S$9=FALSE,, if(if(search(S$11,$B20,1)>0,1,0)=1,$H20/$P20,)),"") | T20: =iferror(if(T$9=FALSE,, if(if(search(T$11,$B20,1)>0,1,0)=1,$H20/$P20,)),"") | U20: =iferror(if(U$9=FALSE,, if(if(search(U$11,$B20,1)>0,1,0)=1,$H20/$P20,)),"") | V20: =iferror(if(V$9=FALSE,, if(if(search(V$11,$B20,1)>0,1,0)=1,$H20/$P20,)),"") | W20: =iferror(if(W$9=FALSE,, if(if(search(W$11,$B20,1)>0,1,0)=1,$H20/$P20,)),"") | X20: =iferror(if(X$9=FALSE,, if(if(search(X$11,$B20,1)>0,1,0)=1,$H20/$P20,)),"") | ... BE20: =iferror(if(BE$9=FALSE,, if(if(search(BE$11,$B20,1)>0,1,0)=1,$H20/$P20,)),"")
B21: INOV00023 | D21: RaiaDrogasil S/A | F21: 61.585.865/3103-47 | G21: 14277 | H21: 905.6 | I21: 45358 | J21: Doação de sensores para Pesquisa Clínica | L21: FALSE | M21: =SUM(Q21:BE21) -> 0 | O21: =SUM(Q21:AP21)=H21 -> FALSE | P21: =IF(L21=FALSE,0,IF(LEN(B21)=0,0,IF(LEN(B21)=9,1,(LEN(B21)+1)/10))) -> 0 | Q21: =iferror(if(Q$9=FALSE,, if(if(search(Q$11,$B21,1)>0,1,0)=1,$H21/$P21,)),"") | R21: =iferror(if(R$9=FALSE,, if(if(search(R$11,$B21,1)>0,1,0)=1,$H21/$P21,)),"") | S21: =iferror(if(S$9=FALSE,, if(if(search(S$11,$B21,1)>0,1,0)=1,$H21/$P21,)),"") | T21: =iferror(if(T$9=FALSE,, if(if(search(T$11,$B21,1)>0,1,0)=1,$H21/$P21,)),"") | U21: =iferror(if(U$9=FALSE,, if(if(search(U$11,$B21,1)>0,1,0)=1,$H21/$P21,)),"") | V21: =iferror(if(V$9=FALSE,, if(if(search(V$11,$B21,1)>0,1,0)=1,$H21/$P21,)),"") | W21: =iferror(if(W$9=FALSE,, if(if(search(W$11,$B21,1)>0,1,0)=1,$H21/$P21,)),"") | X21: =iferror(if(X$9=FALSE,, if(if(search(X$11,$B21,1)>0,1,0)=1,$H21/$P21,)),"") | ... BE21: =iferror(if(BE$9=FALSE,, if(if(search(BE$11,$B21,1)>0,1,0)=1,$H21/$P21,)),"")
B22: INOV00023 | D22: RaiaDrogasil S/A | F22: 61.585.865/3103-47 | G22: 14639 | H22: 305.8 | I22: 45364 | J22: Doação de sensores para Pesquisa Clínica | L22: FALSE | M22: =SUM(Q22:BE22) -> 0 | O22: =SUM(Q22:AP22)=H22 -> FALSE | P22: =IF(L22=FALSE,0,IF(LEN(B22)=0,0,IF(LEN(B22)=9,1,(LEN(B22)+1)/10))) -> 0 | Q22: =iferror(if(Q$9=FALSE,, if(if(search(Q$11,$B22,1)>0,1,0)=1,$H22/$P22,)),"") | R22: =iferror(if(R$9=FALSE,, if(if(search(R$11,$B22,1)>0,1,0)=1,$H22/$P22,)),"") | S22: =iferror(if(S$9=FALSE,, if(if(search(S$11,$B22,1)>0,1,0)=1,$H22/$P22,)),"") | T22: =iferror(if(T$9=FALSE,, if(if(search(T$11,$B22,1)>0,1,0)=1,$H22/$P22,)),"") | U22: =iferror(if(U$9=FALSE,, if(if(search(U$11,$B22,1)>0,1,0)=1,$H22/$P22,)),"") | V22: =iferror(if(V$9=FALSE,, if(if(search(V$11,$B22,1)>0,1,0)=1,$H22/$P22,)),"") | W22: =iferror(if(W$9=FALSE,, if(if(search(W$11,$B22,1)>0,1,0)=1,$H22/$P22,)),"") | X22: =iferror(if(X$9=FALSE,, if(if(search(X$11,$B22,1)>0,1,0)=1,$H22/$P22,)),"") | ... BE22: =iferror(if(BE$9=FALSE,, if(if(search(BE$11,$B22,1)>0,1,0)=1,$H22/$P22,)),"")
B23: INOV00001 | D23: J&J Serviços de Entregas Ltda - ME | F23: 20.618.029/0001-49 | G23: 76271 | H23: 541.28 | I23: 45371 | J23: Envio para análise. | L23: FALSE | M23: =SUM(Q23:BE23) -> 0 | O23: =SUM(Q23:AP23)=H23 -> FALSE | P23: =IF(L23=FALSE,0,IF(LEN(B23)=0,0,IF(LEN(B23)=9,1,(LEN(B23)+1)/10))) -> 0 | Q23: =iferror(if(Q$9=FALSE,, if(if(search(Q$11,$B23,1)>0,1,0)=1,$H23/$P23,)),"") | R23: =iferror(if(R$9=FALSE,, if(if(search(R$11,$B23,1)>0,1,0)=1,$H23/$P23,)),"") | S23: =iferror(if(S$9=FALSE,, if(if(search(S$11,$B23,1)>0,1,0)=1,$H23/$P23,)),"") | T23: =iferror(if(T$9=FALSE,, if(if(search(T$11,$B23,1)>0,1,0)=1,$H23/$P23,)),"") | U23: =iferror(if(U$9=FALSE,, if(if(search(U$11,$B23,1)>0,1,0)=1,$H23/$P23,)),"") | V23: =iferror(if(V$9=FALSE,, if(if(search(V$11,$B23,1)>0,1,0)=1,$H23/$P23,)),"") | W23: =iferror(if(W$9=FALSE,, if(if(search(W$11,$B23,1)>0,1,0)=1,$H23/$P23,)),"") | X23: =iferror(if(X$9=FALSE,, if(if(search(X$11,$B23,1)>0,1,0)=1,$H23/$P23,)),"") | ... BE23: =iferror(if(BE$9=FALSE,, if(if(search(BE$11,$B23,1)>0,1,0)=1,$H23/$P23,)),"")
... B36: INOV00016 | D36: J&J Serviços de Entregas Ltda - ME | F36: 20.618.029/0001-49 | G36: 77414 | H36: 67.6 | I36: 45429 | J36: Envio para análise. | L36: TRUE | M36: =SUM(Q36:BE36) -> 67.6 | O36: =SUM(Q36:AP36)=H36 -> TRUE | P36: =IF(L36=FALSE,0,IF(LEN(B36)=0,0,IF(LEN(B36)=9,1,(LEN(B36)+1)/10))) -> 1 | Q36: =iferror(if(Q$9=FALSE,, if(if(search(Q$11,$B36,1)>0,1,0)=1,$H36/$P36,)),"") | R36: =iferror(if(R$9=FALSE,, if(if(search(R$11,$B36,1)>0,1,0)=1,$H36/$P36,)),"") | S36: =iferror(if(S$9=FALSE,, if(if(search(S$11,$B36,1)>0,1,0)=1,$H36/$P36,)),"") | T36: =iferror(if(T$9=FALSE,, if(if(search(T$11,$B36,1)>0,1,0)=1,$H36/$P36,)),"") | U36: =iferror(if(U$9=FALSE,, if(if(search(U$11,$B36,1)>0,1,0)=1,$H36/$P36,)),"") | V36: =iferror(if(V$9=FALSE,, if(if(search(V$11,$B36,1)>0,1,0)=1,$H36/$P36,)),"") | W36: =iferror(if(W$9=FALSE,, if(if(search(W$11,$B36,1)>0,1,0)=1,$H36/$P36,)),"") | X36: =iferror(if(X$9=FALSE,, if(if(search(X$11,$B36,1)>0,1,0)=1,$H36/$P36,)),"") | ... BE36: =iferror(if(BE$9=FALSE,, if(if(search(BE$11,$B36,1)>0,1,0)=1,$H36/$P36,)),"")
B37: INOV00001 | D37: LATCO BEVERAGES IND. E COM. DE BEB. E ALIM. IMP. E EXP. LTDA. | F37: 01.046.213/0002-06 | G37: 003/2024 | H37: 2438.04 | I37: 45421 | J37: Aquisição de hidróxido de potássio | L37: TRUE | M37: =SUM(Q37:BE37) -> 2438.04 | O37: =SUM(Q37:AP37)=H37 -> TRUE | P37: =IF(L37=FALSE,0,IF(LEN(B37)=0,0,IF(LEN(B37)=9,1,(LEN(B37)+1)/10))) -> 1 | Q37: =iferror(if(Q$9=FALSE,, if(if(search(Q$11,$B37,1)>0,1,0)=1,$H37/$P37,)),"") -> 2438.04 | R37: =iferror(if(R$9=FALSE,, if(if(search(R$11,$B37,1)>0,1,0)=1,$H37/$P37,)),"") | S37: =iferror(if(S$9=FALSE,, if(if(search(S$11,$B37,1)>0,1,0)=1,$H37/$P37,)),"") | T37: =iferror(if(T$9=FALSE,, if(if(search(T$11,$B37,1)>0,1,0)=1,$H37/$P37,)),"") | U37: =iferror(if(U$9=FALSE,, if(if(search(U$11,$B37,1)>0,1,0)=1,$H37/$P37,)),"") | V37: =iferror(if(V$9=FALSE,, if(if(search(V$11,$B37,1)>0,1,0)=1,$H37/$P37,)),"") | W37: =iferror(if(W$9=FALSE,, if(if(search(W$11,$B37,1)>0,1,0)=1,$H37/$P37,)),"") | X37: =iferror(if(X$9=FALSE,, if(if(search(X$11,$B37,1)>0,1,0)=1,$H37/$P37,)),"") | ... BE37: =iferror(if(BE$9=FALSE,, if(if(search(BE$11,$B37,1)>0,1,0)=1,$H37/$P37,)),"")
B38: INOV00016 | D38: Eurofins do Brasil Análise de Alimentos Ltda. | F38: 04.329.668/0001-38 | G38: 244682 | H38: 26698.5 | I38: 45441 | J38: Análise de vitaminas, minerais. | L38: TRUE | M38: =SUM(Q38:BE38) -> 26698.5 | O38: =SUM(Q38:AP38)=H38 -> TRUE | P38: =IF(L38=FALSE,0,IF(LEN(B38)=0,0,IF(LEN(B38)=9,1,(LEN(B38)+1)/10))) -> 1 | Q38: =iferror(if(Q$9=FALSE,, if(if(search(Q$11,$B38,1)>0,1,0)=1,$H38/$P38,)),"") | R38: =iferror(if(R$9=FALSE,, if(if(search(R$11,$B38,1)>0,1,0)=1,$H38/$P38,)),"") | S38: =iferror(if(S$9=FALSE,, if(if(search(S$11,$B38,1)>0,1,0)=1,$H38/$P38,)),"") | T38: =iferror(if(T$9=FALSE,, if(if(search(T$11,$B38,1)>0,1,0)=1,$H38/$P38,)),"") | U38: =iferror(if(U$9=FALSE,, if(if(search(U$11,$B38,1)>0,1,0)=1,$H38/$P38,)),"") | V38: =iferror(if(V$9=FALSE,, if(if(search(V$11,$B38,1)>0,1,0)=1,$H38/$P38,)),"") | W38: =iferror(if(W$9=FALSE,, if(if(search(W$11,$B38,1)>0,1,0)=1,$H38/$P38,)),"") | X38: =iferror(if(X$9=FALSE,, if(if(search(X$11,$B38,1)>0,1,0)=1,$H38/$P38,)),"") | ... BE38: =iferror(if(BE$9=FALSE,, if(if(search(BE$11,$B38,1)>0,1,0)=1,$H38/$P38,)),"")
B39: INOV00023 | D39: RaiaDrogasil S/A | F39: 61.585.865/0300-69 | G39: 35068 | H39: 305.8 | I39: 45446 | J39: Doação de sensores para Pesquisa Clínica | L39: FALSE | M39: =SUM(Q39:BE39) -> 0 | O39: =SUM(Q39:AP39)=H39 -> FALSE | P39: =IF(L39=FALSE,0,IF(LEN(B39)=0,0,IF(LEN(B39)=9,1,(LEN(B39)+1)/10))) -> 0 | Q39: =iferror(if(Q$9=FALSE,, if(if(search(Q$11,$B39,1)>0,1,0)=1,$H39/$P39,)),"") | R39: =iferror(if(R$9=FALSE,, if(if(search(R$11,$B39,1)>0,1,0)=1,$H39/$P39,)),"") | S39: =iferror(if(S$9=FALSE,, if(if(search(S$11,$B39,1)>0,1,0)=1,$H39/$P39,)),"") | T39: =iferror(if(T$9=FALSE,, if(if(search(T$11,$B39,1)>0,1,0)=1,$H39/$P39,)),"") | U39: =iferror(if(U$9=FALSE,, if(if(search(U$11,$B39,1)>0,1,0)=1,$H39/$P39,)),"") | V39: =iferror(if(V$9=FALSE,, if(if(search(V$11,$B39,1)>0,1,0)=1,$H39/$P39,)),"") | W39: =iferror(if(W$9=FALSE,, if(if(search(W$11,$B39,1)>0,1,0)=1,$H39/$P39,)),"") | X39: =iferror(if(X$9=FALSE,, if(if(search(X$11,$B39,1)>0,1,0)=1,$H39/$P39,)),"") | ... BE39: =iferror(if(BE$9=FALSE,, if(if(search(BE$11,$B39,1)>0,1,0)=1,$H39/$P39,)),"")
B40: INOV00016 | D40: Laboratório ALAC | F40: 94.088.952/0001-52 | G40: 112105 | H40: 2386.43 | I40: 45448 | J40: Perfil de aminoácidos e proteína | L40: TRUE | M40: =SUM(Q40:BE40) -> 2386.43 | O40: =SUM(Q40:AP40)=H40 -> TRUE | P40: =IF(L40=FALSE,0,IF(LEN(B40)=0,0,IF(LEN(B40)=9,1,(LEN(B40)+1)/10))) -> 1 | Q40: =iferror(if(Q$9=FALSE,, if(if(search(Q$11,$B40,1)>0,1,0)=1,$H40/$P40,)),"") | R40: =iferror(if(R$9=FALSE,, if(if(search(R$11,$B40,1)>0,1,0)=1,$H40/$P40,)),"") | S40: =iferror(if(S$9=FALSE,, if(if(search(S$11,$B40,1)>0,1,0)=1,$H40/$P40,)),"") | T40: =iferror(if(T$9=FALSE,, if(if(search(T$11,$B40,1)>0,1,0)=1,$H40/$P40,)),"") | U40: =iferror(if(U$9=FALSE,, if(if(search(U$11,$B40,1)>0,1,0)=1,$H40/$P40,)),"") | V40: =iferror(if(V$9=FALSE,, if(if(search(V$11,$B40,1)>0,1,0)=1,$H40/$P40,)),"") | W40: =iferror(if(W$9=FALSE,, if(if(search(W$11,$B40,1)>0,1,0)=1,$H40/$P40,)),"") | X40: =iferror(if(X$9=FALSE,, if(if(search(X$11,$B40,1)>0,1,0)=1,$H40/$P40,)),"") | ... BE40: =iferror(if(BE$9=FALSE,, if(if(search(BE$11,$B40,1)>0,1,0)=1,$H40/$P40,)),"")
B41: INOV00013 | D41: Labor Três Laboratórios e Consultoria Técnica Ltda. | F41: 02.021.076/0001-29 | G41: 51219 | H41: 110 | I41: 45447 | J41: Bacillus cereus no pó e no produto diluído. | L41: TRUE | M41: =SUM(Q41:BE41) -> 110 | O41: =SUM(Q41:AP41)=H41 -> TRUE | P41: =IF(L41=FALSE,0,IF(LEN(B41)=0,0,IF(LEN(B41)=9,1,(LEN(B41)+1)/10))) -> 1 | Q41: =iferror(if(Q$9=FALSE,, if(if(search(Q$11,$B41,1)>0,1,0)=1,$H41/$P41,)),"") | R41: =iferror(if(R$9=FALSE,, if(if(search(R$11,$B41,1)>0,1,0)=1,$H41/$P41,)),"") | S41: =iferror(if(S$9=FALSE,, if(if(search(S$11,$B41,1)>0,1,0)=1,$H41/$P41,)),"") | T41: =iferror(if(T$9=FALSE,, if(if(search(T$11,$B41,1)>0,1,0)=1,$H41/$P41,)),"") | U41: =iferror(if(U$9=FALSE,, if(if(search(U$11,$B41,1)>0,1,0)=1,$H41/$P41,)),"") | V41: =iferror(if(V$9=FALSE,, if(if(search(V$11,$B41,1)>0,1,0)=1,$H41/$P41,)),"") | W41: =iferror(if(W$9=FALSE,, if(if(search(W$11,$B41,1)>0,1,0)=1,$H41/$P41,)),"") -> 110 | X41: =iferror(if(X$9=FALSE,, if(if(search(X$11,$B41,1)>0,1,0)=1,$H41/$P41,)),"") | ... BE41: =iferror(if(BE$9=FALSE,, if(if(search(BE$11,$B41,1)>0,1,0)=1,$H41/$P41,)),"")
B42: INOV00001 | D42: Fundação Arthur Bernardes | F42: 20.320.503/0001-51 | G42: 202400000001414 | H42: 8965.16 | I42: 45449 | J42: 03/03 parcela contrato Embrapa FUNARBE de R$26895,48 (Convênio 16369) | L42: TRUE | M42: =SUM(Q42:BE42) -> 8965.16 | O42: =SUM(Q42:AP42)=H42 -> TRUE | P42: =IF(L42=FALSE,0,IF(LEN(B42)=0,0,IF(LEN(B42)=9,1,(LEN(B42)+1)/10))) -> 1 | Q42: =iferror(if(Q$9=FALSE,, if(if(search(Q$11,$B42,1)>0,1,0)=1,$H42/$P42,)),"") -> 8965.16 | R42: =iferror(if(R$9=FALSE,, if(if(search(R$11,$B42,1)>0,1,0)=1,$H42/$P42,)),"") | S42: =iferror(if(S$9=FALSE,, if(if(search(S$11,$B42,1)>0,1,0)=1,$H42/$P42,)),"") | T42: =iferror(if(T$9=FALSE,, if(if(search(T$11,$B42,1)>0,1,0)=1,$H42/$P42,)),"") | U42: =iferror(if(U$9=FALSE,, if(if(search(U$11,$B42,1)>0,1,0)=1,$H42/$P42,)),"") | V42: =iferror(if(V$9=FALSE,, if(if(search(V$11,$B42,1)>0,1,0)=1,$H42/$P42,)),"") | W42: =iferror(if(W$9=FALSE,, if(if(search(W$11,$B42,1)>0,1,0)=1,$H42/$P42,)),"") | X42: =iferror(if(X$9=FALSE,, if(if(search(X$11,$B42,1)>0,1,0)=1,$H42/$P42,)),"") | ... BE42: =iferror(if(BE$9=FALSE,, if(if(search(BE$11,$B42,1)>0,1,0)=1,$H42/$P42,)),"")
B43: INOV00017 | D43: Laboratório ALAC | F43: 94.088.952/0001-52 | G43: 112616 | H43: 958.6 | I43: 45454 | J43: Reanálise de ácido fólico | L43: TRUE | M43: =SUM(Q43:BE43) -> 958.6 | O43: =SUM(Q43:AP43)=H43 -> TRUE | P43: =IF(L43=FALSE,0,IF(LEN(B43)=0,0,IF(LEN(B43)=9,1,(LEN(B43)+1)/10))) -> 1 | Q43: =iferror(if(Q$9=FALSE,, if(if(search(Q$11,$B43,1)>0,1,0)=1,$H43/$P43,)),"") | R43: =iferror(if(R$9=FALSE,, if(if(search(R$11,$B43,1)>0,1,0)=1,$H43/$P43,)),"") | S43: =iferror(if(S$9=FALSE,, if(if(search(S$11,$B43,1)>0,1,0)=1,$H43/$P43,)),"") | T43: =iferror(if(T$9=FALSE,, if(if(search(T$11,$B43,1)>0,1,0)=1,$H43/$P43,)),"") | U43: =iferror(if(U$9=FALSE,, if(if(search(U$11,$B43,1)>0,1,0)=1,$H43/$P43,)),"") | V43: =iferror(if(V$9=FALSE,, if(if(search(V$11,$B43,1)>0,1,0)=1,$H43/$P43,)),"") | W43: =iferror(if(W$9=FALSE,, if(if(search(W$11,$B43,1)>0,1,0)=1,$H43/$P43,)),"") | X43: =iferror(if(X$9=FALSE,, if(if(search(X$11,$B43,1)>0,1,0)=1,$H43/$P43,)),"") | ... BE43: =iferror(if(BE$9=FALSE,, if(if(search(BE$11,$B43,1)>0,1,0)=1,$H43/$P43,)),"")
B44: INOV00001 | D44: Labor Três Laboratórios e Consultoria Técnica Ltda. | F44: 02.021.076/0001-29 | G44: 51279 | H44: 560 | I44: 45455 | J44: Análise de esterilidade comercial. | L44: TRUE | M44: =SUM(Q44:BE44) -> 560 | O44: =SUM(Q44:AP44)=H44 -> TRUE | P44: =IF(L44=FALSE,0,IF(LEN(B44)=0,0,IF(LEN(B44)=9,1,(LEN(B44)+1)/10))) -> 1 | Q44: =iferror(if(Q$9=FALSE,, if(if(search(Q$11,$B44,1)>0,1,0)=1,$H44/$P44,)),"") -> 560 | R44: =iferror(if(R$9=FALSE,, if(if(search(R$11,$B44,1)>0,1,0)=1,$H44/$P44,)),"") | S44: =iferror(if(S$9=FALSE,, if(if(search(S$11,$B44,1)>0,1,0)=1,$H44/$P44,)),"") | T44: =iferror(if(T$9=FALSE,, if(if(search(T$11,$B44,1)>0,1,0)=1,$H44/$P44,)),"") | U44: =iferror(if(U$9=FALSE,, if(if(search(U$11,$B44,1)>0,1,0)=1,$H44/$P44,)),"") | V44: =iferror(if(V$9=FALSE,, if(if(search(V$11,$B44,1)>0,1,0)=1,$H44/$P44,)),"") | W44: =iferror(if(W$9=FALSE,, if(if(search(W$11,$B44,1)>0,1,0)=1,$H44/$P44,)),"") | X44: =iferror(if(X$9=FALSE,, if(if(search(X$11,$B44,1)>0,1,0)=1,$H44/$P44,)),"") | ... BE44: =iferror(if(BE$9=FALSE,, if(if(search(BE$11,$B44,1)>0,1,0)=1,$H44/$P44,)),"")
B45: INOV00035 | D45: Clínica Cicatripelli | F45: 25.128.189/0001-23 | G45: 1574 | H45: 5000 | I45: 45455 | J45: Relato de caso e participação em simpósio | L45: TRUE | M45: =SUM(Q45:BE45) -> 5000 | O45: =SUM(Q45:AP45)=H45 -> FALSE | P45: =IF(L45=FALSE,0,IF(LEN(B45)=0,0,IF(LEN(B45)=9,1,(LEN(B45)+1)/10))) -> 1 | Q45: =iferror(if(Q$9=FALSE,, if(if(search(Q$11,$B45,1)>0,1,0)=1,$H45/$P45,)),"") | R45: =iferror(if(R$9=FALSE,, if(if(search(R$11,$B45,1)>0,1,0)=1,$H45/$P45,)),"") | S45: =iferror(if(S$9=FALSE,, if(if(search(S$11,$B45,1)>0,1,0)=1,$H45/$P45,)),"") | T45: =iferror(if(T$9=FALSE,, if(if(search(T$11,$B45,1)>0,1,0)=1,$H45/$P45,)),"") | U45: =iferror(if(U$9=FALSE,, if(if(search(U$11,$B45,1)>0,1,0)=1,$H45/$P45,)),"") | V45: =iferror(if(V$9=FALSE,, if(if(search(V$11,$B45,1)>0,1,0)=1,$H45/$P45,)),"") | W45: =iferror(if(W$9=FALSE,, if(if(search(W$11,$B45,1)>0,1,0)=1,$H45/$P45,)),"") | X45: =iferror(if(X$9=FALSE,, if(if(search(X$11,$B45,1)>0,1,0)=1,$H45/$P45,)),"") | ... BE45: =iferror(if(BE$9=FALSE,, if(if(search(BE$11,$B45,1)>0,1,0)=1,$H45/$P45,)),"")
B46: INOV00016 | D46: Laboratório ALAC | F46: 94.088.952/0001-52 | G46: 112489 | H46: 17862.03 | I46: 45461 | J46: Análise de vitaminas, minerais e macronutrientes. | L46: TRUE | M46: =SUM(Q46:BE46) -> 17862.03 | O46: =SUM(Q46:AP46)=H46 -> TRUE | P46: =IF(L46=FALSE,0,IF(LEN(B46)=0,0,IF(LEN(B46)=9,1,(LEN(B46)+1)/10))) -> 1 | Q46: =iferror(if(Q$9=FALSE,, if(if(search(Q$11,$B46,1)>0,1,0)=1,$H46/$P46,)),"") | R46: =iferror(if(R$9=FALSE,, if(if(search(R$11,$B46,1)>0,1,0)=1,$H46/$P46,)),"") | S46: =iferror(if(S$9=FALSE,, if(if(search(S$11,$B46,1)>0,1,0)=1,$H46/$P46,)),"") | T46: =iferror(if(T$9=FALSE,, if(if(search(T$11,$B46,1)>0,1,0)=1,$H46/$P46,)),"") | U46: =iferror(if(U$9=FALSE,, if(if(search(U$11,$B46,1)>0,1,0)=1,$H46/$P46,)),"") | V46: =iferror(if(V$9=FALSE,, if(if(search(V$11,$B46,1)>0,1,0)=1,$H46/$P46,)),"") | W46: =iferror(if(W$9=FALSE,, if(if(search(W$11,$B46,1)>0,1,0)=1,$H46/$P46,)),"") | X46: =iferror(if(X$9=FALSE,, if(if(search(X$11,$B46,1)>0,1,0)=1,$H46/$P46,)),"") | ... BE46: =iferror(if(BE$9=FALSE,, if(if(search(BE$11,$B46,1)>0,1,0)=1,$H46/$P46,)),"")
B47: INOV00001|INOV00016 | D47: J&J Serviços de Entregas Ltda - ME | F47: 20.618.029/0001-49 | G47: 77974 | H47: 167.98 | I47: 45461 | J47: Envio para análise. | L47: TRUE | M47: =SUM(Q47:BE47) -> 167.98 | O47: =SUM(Q47:AP47)=H47 -> TRUE | P47: =IF(L47=FALSE,0,IF(LEN(B47)=0,0,IF(LEN(B47)=9,1,(LEN(B47)+1)/10))) -> 2 | Q47: =iferror(if(Q$9=FALSE,, if(if(search(Q$11,$B47,1)>0,1,0)=1,$H47/$P47,)),"") -> 83.99 | R47: =iferror(if(R$9=FALSE,, if(if(search(R$11,$B47,1)>0,1,0)=1,$H47/$P47,)),"") | S47: =iferror(if(S$9=FALSE,, if(if(search(S$11,$B47,1)>0,1,0)=1,$H47/$P47,)),"") | T47: =iferror(if(T$9=FALSE,, if(if(search(T$11,$B47,1)>0,1,0)=1,$H47/$P47,)),"") | U47: =iferror(if(U$9=FALSE,, if(if(search(U$11,$B47,1)>0,1,0)=1,$H47/$P47,)),"") | V47: =iferror(if(V$9=FALSE,, if(if(search(V$11,$B47,1)>0,1,0)=1,$H47/$P47,)),"") | W47: =iferror(if(W$9=FALSE,, if(if(search(W$11,$B47,1)>0,1,0)=1,$H47/$P47,)),"") | X47: =iferror(if(X$9=FALSE,, if(if(search(X$11,$B47,1)>0,1,0)=1,$H47/$P47,)),"") | ... BE47: =iferror(if(BE$9=FALSE,, if(if(search(BE$11,$B47,1)>0,1,0)=1,$H47/$P47,)),"")
B48: INOV00028 | D48: Tetra Pak Ltda | F48: 61.528.030/0001-60 | G48: 29664 | H48: 63043.15 | I48: 45467 | J48: Custo do aluguel da planta para teste piloto. | L48: TRUE | M48: =SUM(Q48:BE48) -> 0 | O48: =SUM(Q48:AP48)=H48 -> FALSE | P48: =IF(L48=FALSE,0,IF(LEN(B48)=0,0,IF(LEN(B48)=9,1,(LEN(B48)+1)/10))) -> 1 | Q48: =iferror(if(Q$9=FALSE,, if(if(search(Q$11,$B48,1)>0,1,0)=1,$H48/$P48,)),"") | R48: =iferror(if(R$9=FALSE,, if(if(search(R$11,$B48,1)>0,1,0)=1,$H48/$P48,)),"") | S48: =iferror(if(S$9=FALSE,, if(if(search(S$11,$B48,1)>0,1,0)=1,$H48/$P48,)),"") | T48: =iferror(if(T$9=FALSE,, if(if(search(T$11,$B48,1)>0,1,0)=1,$H48/$P48,)),"") | U48: =iferror(if(U$9=FALSE,, if(if(search(U$11,$B48,1)>0,1,0)=1,$H48/$P48,)),"") | V48: =iferror(if(V$9=FALSE,, if(if(search(V$11,$B48,1)>0,1,0)=1,$H48/$P48,)),"") | W48: =iferror(if(W$9=FALSE,, if(if(search(W$11,$B48,1)>0,1,0)=1,$H48/$P48,)),"") | X48: =iferror(if(X$9=FALSE,, if(if(search(X$11,$B48,1)>0,1,0)=1,$H48/$P48,)),"") | ... BE48: =iferror(if(BE$9=FALSE,, if(if(search(BE$11,$B48,1)>0,1,0)=1,$H48/$P48,)),"")
B49: INOV00028 | D49: Laboratório ALAC | F49: 94.088.952/0001-52 | G49: 112738 | H49: 40915.78 | I49: 45470 | J49: Análise de vitaminas, minerais e macronutrientes. | L49: TRUE | M49: =SUM(Q49:BE49) -> 0 | O49: =SUM(Q49:AP49)=H49 -> FALSE | P49: =IF(L49=FALSE,0,IF(LEN(B49)=0,0,IF(LEN(B49)=9,1,(LEN(B49)+1)/10))) -> 1 | Q49: =iferror(if(Q$9=FALSE,, if(if(search(Q$11,$B49,1)>0,1,0)=1,$H49/$P49,)),"") | R49: =iferror(if(R$9=FALSE,, if(if(search(R$11,$B49,1)>0,1,0)=1,$H49/$P49,)),"") | S49: =iferror(if(S$9=FALSE,, if(if(search(S$11,$B49,1)>0,1,0)=1,$H49/$P49,)),"") | T49: =iferror(if(T$9=FALSE,, if(if(search(T$11,$B49,1)>0,1,0)=1,$H49/$P49,)),"") | U49: =iferror(if(U$9=FALSE,, if(if(search(U$11,$B49,1)>0,1,0)=1,$H49/$P49,)),"") | V49: =iferror(if(V$9=FALSE,, if(if(search(V$11,$B49,1)>0,1,0)=1,$H49/$P49,)),"") | W49: =iferror(if(W$9=FALSE,, if(if(search(W$11,$B49,1)>0,1,0)=1,$H49/$P49,)),"") | X49: =iferror(if(X$9=FALSE,, if(if(search(X$11,$B49,1)>0,1,0)=1,$H49/$P49,)),"") | ... BE49: =iferror(if(BE$9=FALSE,, if(if(search(BE$11,$B49,1)>0,1,0)=1,$H49/$P49,)),"")
... B58: INOV00001 | D58: Labor Três Laboratórios e Consultoria Técnica Ltda. | F58: 02.021.076/0001-29 | G58: 51496 | H58: 280 | I58: 45481 | J58: Esterilidade comercial após TI Latco. | L58: TRUE | M58: =SUM(Q58:BE58) -> 280 | O58: =SUM(Q58:AP58)=H58 -> TRUE | P58: =IF(L58=FALSE,0,IF(LEN(B58)=0,0,IF(LEN(B58)=9,1,(LEN(B58)+1)/10))) -> 1 | Q58: =iferror(if(Q$9=FALSE,, if(if(search(Q$11,$B58,1)>0,1,0)=1,$H58/$P58,)),"") -> 280 | R58: =iferror(if(R$9=FALSE,, if(if(search(R$11,$B58,1)>0,1,0)=1,$H58/$P58,)),"") | S58: =iferror(if(S$9=FALSE,, if(if(search(S$11,$B58,1)>0,1,0)=1,$H58/$P58,)),"") | T58: =iferror(if(T$9=FALSE,, if(if(search(T$11,$B58,1)>0,1,0)=1,$H58/$P58,)),"") | U58: =iferror(if(U$9=FALSE,, if(if(search(U$11,$B58,1)>0,1,0)=1,$H58/$P58,)),"") | V58: =iferror(if(V$9=FALSE,, if(if(search(V$11,$B58,1)>0,1,0)=1,$H58/$P58,)),"") | W58: =iferror(if(W$9=FALSE,, if(if(search(W$11,$B58,1)>0,1,0)=1,$H58/$P58,)),"") | X58: =iferror(if(X$9=FALSE,, if(if(search(X$11,$B58,1)>0,1,0)=1,$H58/$P58,)),"") | ... BE58: =iferror(if(BE$9=FALSE,, if(if(search(BE$11,$B58,1)>0,1,0)=1,$H58/$P58,)),"")
B59: INOV00001 | D59: LATCO BEVERAGES IND. E COM. DE BEB. E ALIM. IMP. E EXP. LTDA. | F59: 01.046.213/0002-06 | G59: 007/2024 | H59: 28000 | I59: 45483 | J59: Aluguel da planta piloto para TI - LATCO. | L59: TRUE | M59: =SUM(Q59:BE59) -> 28000 | O59: =SUM(Q59:AP59)=H59 -> TRUE | P59: =IF(L59=FALSE,0,IF(LEN(B59)=0,0,IF(LEN(B59)=9,1,(LEN(B59)+1)/10))) -> 1 | Q59: =iferror(if(Q$9=FALSE,, if(if(search(Q$11,$B59,1)>0,1,0)=1,$H59/$P59,)),"") -> 28000 | R59: =iferror(if(R$9=FALSE,, if(if(search(R$11,$B59,1)>0,1,0)=1,$H59/$P59,)),"") | S59: =iferror(if(S$9=FALSE,, if(if(search(S$11,$B59,1)>0,1,0)=1,$H59/$P59,)),"") | T59: =iferror(if(T$9=FALSE,, if(if(search(T$11,$B59,1)>0,1,0)=1,$H59/$P59,)),"") | U59: =iferror(if(U$9=FALSE,, if(if(search(U$11,$B59,1)>0,1,0)=1,$H59/$P59,)),"") | V59: =iferror(if(V$9=FALSE,, if(if(search(V$11,$B59,1)>0,1,0)=1,$H59/$P59,)),"") | W59: =iferror(if(W$9=FALSE,, if(if(search(W$11,$B59,1)>0,1,0)=1,$H59/$P59,)),"") | X59: =iferror(if(X$9=FALSE,, if(if(search(X$11,$B59,1)>0,1,0)=1,$H59/$P59,)),"") | ... BE59: =iferror(if(BE$9=FALSE,, if(if(search(BE$11,$B59,1)>0,1,0)=1,$H59/$P59,)),"")
B60: INOV00016 | D60: Fundação de desenv. da pesquisa do agronegócio - FUNDEPAG | F60: 50.276.237/0001-78 | G60: 153781 | H60: 1792 | I60: 45483 | J60: Análise de perfil lipídico T0. | L60: TRUE | M60: =SUM(Q60:BE60) -> 1792 | O60: =SUM(Q60:AP60)=H60 -> TRUE | P60: =IF(L60=FALSE,0,IF(LEN(B60)=0,0,IF(LEN(B60)=9,1,(LEN(B60)+1)/10))) -> 1 | Q60: =iferror(if(Q$9=FALSE,, if(if(search(Q$11,$B60,1)>0,1,0)=1,$H60/$P60,)),"") | R60: =iferror(if(R$9=FALSE,, if(if(search(R$11,$B60,1)>0,1,0)=1,$H60/$P60,)),"") | S60: =iferror(if(S$9=FALSE,, if(if(search(S$11,$B60,1)>0,1,0)=1,$H60/$P60,)),"") | T60: =iferror(if(T$9=FALSE,, if(if(search(T$11,$B60,1)>0,1,0)=1,$H60/$P60,)),"") | U60: =iferror(if(U$9=FALSE,, if(if(search(U$11,$B60,1)>0,1,0)=1,$H60/$P60,)),"") | V60: =iferror(if(V$9=FALSE,, if(if(search(V$11,$B60,1)>0,1,0)=1,$H60/$P60,)),"") | W60: =iferror(if(W$9=FALSE,, if(if(search(W$11,$B60,1)>0,1,0)=1,$H60/$P60,)),"") | X60: =iferror(if(X$9=FALSE,, if(if(search(X$11,$B60,1)>0,1,0)=1,$H60/$P60,)),"") | ... BE60: =iferror(if(BE$9=FALSE,, if(if(search(BE$11,$B60,1)>0,1,0)=1,$H60/$P60,)),"")
B61: INOV00001 | D61: Fundação de Apoio à Universidade de São Paulo | F61: 68.314.830/0001-27 | G61: 63138 | H61: 297 | I61: 45483 | J61: Análise de distribuição de partículas no DiamaxIG RTH do TI da LATCO. | L61: TRUE | M61: =SUM(Q61:BE61) -> 297 | O61: =SUM(Q61:AP61)=H61 -> TRUE | P61: =IF(L61=FALSE,0,IF(LEN(B61)=0,0,IF(LEN(B61)=9,1,(LEN(B61)+1)/10))) -> 1 | Q61: =iferror(if(Q$9=FALSE,, if(if(search(Q$11,$B61,1)>0,1,0)=1,$H61/$P61,)),"") -> 297 | R61: =iferror(if(R$9=FALSE,, if(if(search(R$11,$B61,1)>0,1,0)=1,$H61/$P61,)),"") | S61: =iferror(if(S$9=FALSE,, if(if(search(S$11,$B61,1)>0,1,0)=1,$H61/$P61,)),"") | T61: =iferror(if(T$9=FALSE,, if(if(search(T$11,$B61,1)>0,1,0)=1,$H61/$P61,)),"") | U61: =iferror(if(U$9=FALSE,, if(if(search(U$11,$B61,1)>0,1,0)=1,$H61/$P61,)),"") | V61: =iferror(if(V$9=FALSE,, if(if(search(V$11,$B61,1)>0,1,0)=1,$H61/$P61,)),"") | W61: =iferror(if(W$9=FALSE,, if(if(search(W$11,$B61,1)>0,1,0)=1,$H61/$P61,)),"") | X61: =iferror(if(X$9=FALSE,, if(if(search(X$11,$B61,1)>0,1,0)=1,$H61/$P61,)),"") | ... BE61: =iferror(if(BE$9=FALSE,, if(if(search(BE$11,$B61,1)>0,1,0)=1,$H61/$P61,)),"")
B62: INOV00001 | D62: J&J Serviços de Entregas Ltda - ME | F62: 20.618.029/0001-49 | G62: 78563 | H62: 175 | I62: 45490 | J62: Envio para análise | L62: TRUE | M62: =SUM(Q62:BE62) -> 175 | O62: =SUM(Q62:AP62)=H62 -> TRUE | P62: =IF(L62=FALSE,0,IF(LEN(B62)=0,0,IF(LEN(B62)=9,1,(LEN(B62)+1)/10))) -> 1 | Q62: =iferror(if(Q$9=FALSE,, if(if(search(Q$11,$B62,1)>0,1,0)=1,$H62/$P62,)),"") -> 175 | R62: =iferror(if(R$9=FALSE,, if(if(search(R$11,$B62,1)>0,1,0)=1,$H62/$P62,)),"") | S62: =iferror(if(S$9=FALSE,, if(if(search(S$11,$B62,1)>0,1,0)=1,$H62/$P62,)),"") | T62: =iferror(if(T$9=FALSE,, if(if(search(T$11,$B62,1)>0,1,0)=1,$H62/$P62,)),"") | U62: =iferror(if(U$9=FALSE,, if(if(search(U$11,$B62,1)>0,1,0)=1,$H62/$P62,)),"") | V62: =iferror(if(V$9=FALSE,, if(if(search(V$11,$B62,1)>0,1,0)=1,$H62/$P62,)),"") | W62: =iferror(if(W$9=FALSE,, if(if(search(W$11,$B62,1)>0,1,0)=1,$H62/$P62,)),"") | X62: =iferror(if(X$9=FALSE,, if(if(search(X$11,$B62,1)>0,1,0)=1,$H62/$P62,)),"") | ... BE62: =iferror(if(BE$9=FALSE,, if(if(search(BE$11,$B62,1)>0,1,0)=1,$H62/$P62,)),"")
B63: INOV00023 | D63: RaiaDrogasil S/A | F63: 61.585.865/0300-69 | G63: 37700 | H63: 305.8 | I63: 45489 | J63: Doação de sensores para Pesquisa Clínica | L63: FALSE | M63: =SUM(Q63:BE63) -> 0 | O63: =SUM(Q63:AP63)=H63 -> FALSE | P63: =IF(L63=FALSE,0,IF(LEN(B63)=0,0,IF(LEN(B63)=9,1,(LEN(B63)+1)/10))) -> 0 | Q63: =iferror(if(Q$9=FALSE,, if(if(search(Q$11,$B63,1)>0,1,0)=1,$H63/$P63,)),"") | R63: =iferror(if(R$9=FALSE,, if(if(search(R$11,$B63,1)>0,1,0)=1,$H63/$P63,)),"") | S63: =iferror(if(S$9=FALSE,, if(if(search(S$11,$B63,1)>0,1,0)=1,$H63/$P63,)),"") | T63: =iferror(if(T$9=FALSE,, if(if(search(T$11,$B63,1)>0,1,0)=1,$H63/$P63,)),"") | U63: =iferror(if(U$9=FALSE,, if(if(search(U$11,$B63,1)>0,1,0)=1,$H63/$P63,)),"") | V63: =iferror(if(V$9=FALSE,, if(if(search(V$11,$B63,1)>0,1,0)=1,$H63/$P63,)),"") | W63: =iferror(if(W$9=FALSE,, if(if(search(W$11,$B63,1)>0,1,0)=1,$H63/$P63,)),"") | X63: =iferror(if(X$9=FALSE,, if(if(search(X$11,$B63,1)>0,1,0)=1,$H63/$P63,)),"") | ... BE63: =iferror(if(BE$9=FALSE,, if(if(search(BE$11,$B63,1)>0,1,0)=1,$H63/$P63,)),"")
B64: INOV00016 | D64: Fundação de desenv. da pesquisa do agronegócio - FUNDEPAG | F64: 50.276.237/0001-78 | G64: 154224 | H64: 3584 | I64: 45505 | J64: Análise de perfil lipídico T0. | L64: TRUE | M64: =SUM(Q64:BE64) -> 3584 | O64: =SUM(Q64:AP64)=H64 -> TRUE | P64: =IF(L64=FALSE,0,IF(LEN(B64)=0,0,IF(LEN(B64)=9,1,(LEN(B64)+1)/10))) -> 1 | Q64: =iferror(if(Q$9=FALSE,, if(if(search(Q$11,$B64,1)>0,1,0)=1,$H64/$P64,)),"") | R64: =iferror(if(R$9=FALSE,, if(if(search(R$11,$B64,1)>0,1,0)=1,$H64/$P64,)),"") | S64: =iferror(if(S$9=FALSE,, if(if(search(S$11,$B64,1)>0,1,0)=1,$H64/$P64,)),"") | T64: =iferror(if(T$9=FALSE,, if(if(search(T$11,$B64,1)>0,1,0)=1,$H64/$P64,)),"") | U64: =iferror(if(U$9=FALSE,, if(if(search(U$11,$B64,1)>0,1,0)=1,$H64/$P64,)),"") | V64: =iferror(if(V$9=FALSE,, if(if(search(V$11,$B64,1)>0,1,0)=1,$H64/$P64,)),"") | W64: =iferror(if(W$9=FALSE,, if(if(search(W$11,$B64,1)>0,1,0)=1,$H64/$P64,)),"") | X64: =iferror(if(X$9=FALSE,, if(if(search(X$11,$B64,1)>0,1,0)=1,$H64/$P64,)),"") | ... BE64: =iferror(if(BE$9=FALSE,, if(if(search(BE$11,$B64,1)>0,1,0)=1,$H64/$P64,)),"")
B65: INOV00028 | D65: Laboratório ALAC | F65: 94.088.952/0001-52 | G65: 114119 | H65: 5482.6 | I65: 45524 | J65: Análise de perfil de tocoferol para fechar T0 - Agrupamento. | L65: TRUE | M65: =SUM(Q65:BE65) -> 0 | O65: =SUM(Q65:AP65)=H65 -> FALSE | P65: =IF(L65=FALSE,0,IF(LEN(B65)=0,0,IF(LEN(B65)=9,1,(LEN(B65)+1)/10))) -> 1 | Q65: =iferror(if(Q$9=FALSE,, if(if(search(Q$11,$B65,1)>0,1,0)=1,$H65/$P65,)),"") | R65: =iferror(if(R$9=FALSE,, if(if(search(R$11,$B65,1)>0,1,0)=1,$H65/$P65,)),"") | S65: =iferror(if(S$9=FALSE,, if(if(search(S$11,$B65,1)>0,1,0)=1,$H65/$P65,)),"") | T65: =iferror(if(T$9=FALSE,, if(if(search(T$11,$B65,1)>0,1,0)=1,$H65/$P65,)),"") | U65: =iferror(if(U$9=FALSE,, if(if(search(U$11,$B65,1)>0,1,0)=1,$H65/$P65,)),"") | V65: =iferror(if(V$9=FALSE,, if(if(search(V$11,$B65,1)>0,1,0)=1,$H65/$P65,)),"") | W65: =iferror(if(W$9=FALSE,, if(if(search(W$11,$B65,1)>0,1,0)=1,$H65/$P65,)),"") | X65: =iferror(if(X$9=FALSE,, if(if(search(X$11,$B65,1)>0,1,0)=1,$H65/$P65,)),"") | ... BE65: =iferror(if(BE$9=FALSE,, if(if(search(BE$11,$B65,1)>0,1,0)=1,$H65/$P65,)),"")
B66: INOV00001|INOV00028 | D66: Laboratório ALAC | F66: 94.088.952/0001-52 | G66: 113984 | H66: 17058.89 | I66: 45517 | J66: Análise de macronutrientes, vitaminas e minerais do Retort NN (T0) e aminograma e proteína do Trophic Basic L. | L66: TRUE | M66: =SUM(Q66:BE66) -> 8529.445 | O66: =SUM(Q66:AP66)=H66 -> FALSE | P66: =IF(L66=FALSE,0,IF(LEN(B66)=0,0,IF(LEN(B66)=9,1,(LEN(B66)+1)/10))) -> 2 | Q66: =iferror(if(Q$9=FALSE,, if(if(search(Q$11,$B66,1)>0,1,0)=1,$H66/$P66,)),"") -> 8529.445 | R66: =iferror(if(R$9=FALSE,, if(if(search(R$11,$B66,1)>0,1,0)=1,$H66/$P66,)),"") | S66: =iferror(if(S$9=FALSE,, if(if(search(S$11,$B66,1)>0,1,0)=1,$H66/$P66,)),"") | T66: =iferror(if(T$9=FALSE,, if(if(search(T$11,$B66,1)>0,1,0)=1,$H66/$P66,)),"") | U66: =iferror(if(U$9=FALSE,, if(if(search(U$11,$B66,1)>0,1,0)=1,$H66/$P66,)),"") | V66: =iferror(if(V$9=FALSE,, if(if(search(V$11,$B66,1)>0,1,0)=1,$H66/$P66,)),"") | W66: =iferror(if(W$9=FALSE,, if(if(search(W$11,$B66,1)>0,1,0)=1,$H66/$P66,)),"") | X66: =iferror(if(X$9=FALSE,, if(if(search(X$11,$B66,1)>0,1,0)=1,$H66/$P66,)),"") | ... BE66: =iferror(if(BE$9=FALSE,, if(if(search(BE$11,$B66,1)>0,1,0)=1,$H66/$P66,)),"")
B67: INOV00001|INOV00028 | D67: Laboratório ALAC | F67: 94.088.952/0001-52 | G67: 113963 | H67: 9545.72 | I67: 45516 | J67: Análise de aminograma e proteína em T0. | L67: TRUE | M67: =SUM(Q67:BE67) -> 4772.86 | O67: =SUM(Q67:AP67)=H67 -> FALSE | P67: =IF(L67=FALSE,0,IF(LEN(B67)=0,0,IF(LEN(B67)=9,1,(LEN(B67)+1)/10))) -> 2 | Q67: =iferror(if(Q$9=FALSE,, if(if(search(Q$11,$B67,1)>0,1,0)=1,$H67/$P67,)),"") -> 4772.86 | R67: =iferror(if(R$9=FALSE,, if(if(search(R$11,$B67,1)>0,1,0)=1,$H67/$P67,)),"") | S67: =iferror(if(S$9=FALSE,, if(if(search(S$11,$B67,1)>0,1,0)=1,$H67/$P67,)),"") | T67: =iferror(if(T$9=FALSE,, if(if(search(T$11,$B67,1)>0,1,0)=1,$H67/$P67,)),"") | U67: =iferror(if(U$9=FALSE,, if(if(search(U$11,$B67,1)>0,1,0)=1,$H67/$P67,)),"") | V67: =iferror(if(V$9=FALSE,, if(if(search(V$11,$B67,1)>0,1,0)=1,$H67/$P67,)),"") | W67: =iferror(if(W$9=FALSE,, if(if(search(W$11,$B67,1)>0,1,0)=1,$H67/$P67,)),"") | X67: =iferror(if(X$9=FALSE,, if(if(search(X$11,$B67,1)>0,1,0)=1,$H67/$P67,)),"") | ... BE67: =iferror(if(BE$9=FALSE,, if(if(search(BE$11,$B67,1)>0,1,0)=1,$H67/$P67,)),"")
B68: INOV00040 | D68: Fundação de desenv. da pesquisa do agronegócio - FUNDEPAG | F68: 50.276.237/0001-78 | G68: 154601 | H68: 1792 | I68: 45511 | J68: Análise de perfil lipídico T12. | L68: TRUE | M68: =SUM(Q68:BE68) -> 0 | O68: =SUM(Q68:AP68)=H68 -> FALSE | P68: =IF(L68=FALSE,0,IF(LEN(B68)=0,0,IF(LEN(B68)=9,1,(LEN(B68)+1)/10))) -> 1 | Q68: =iferror(if(Q$9=FALSE,, if(if(search(Q$11,$B68,1)>0,1,0)=1,$H68/$P68,)),"") | R68: =iferror(if(R$9=FALSE,, if(if(search(R$11,$B68,1)>0,1,0)=1,$H68/$P68,)),"") | S68: =iferror(if(S$9=FALSE,, if(if(search(S$11,$B68,1)>0,1,0)=1,$H68/$P68,)),"") | T68: =iferror(if(T$9=FALSE,, if(if(search(T$11,$B68,1)>0,1,0)=1,$H68/$P68,)),"") | U68: =iferror(if(U$9=FALSE,, if(if(search(U$11,$B68,1)>0,1,0)=1,$H68/$P68,)),"") | V68: =iferror(if(V$9=FALSE,, if(if(search(V$11,$B68,1)>0,1,0)=1,$H68/$P68,)),"") | W68: =iferror(if(W$9=FALSE,, if(if(search(W$11,$B68,1)>0,1,0)=1,$H68/$P68,)),"") | X68: =iferror(if(X$9=FALSE,, if(if(search(X$11,$B68,1)>0,1,0)=1,$H68/$P68,)),"") | ... BE68: =iferror(if(BE$9=FALSE,, if(if(search(BE$11,$B68,1)>0,1,0)=1,$H68/$P68,)),"")
B69: INOV00028 | D69: Laboratório ALAC | F69: 94.088.952/0001-52 | G69: 114266 | H69: 7355.71 | I69: 45527 | J69: Análise de perfil de tocoferol para fechar T0 - Agrupamento, reanálise de cromo e ácido pantotênico. | L69: TRUE | M69: =SUM(Q69:BE69) -> 0 | O69: =SUM(Q69:AP69)=H69 -> FALSE | P69: =IF(L69=FALSE,0,IF(LEN(B69)=0,0,IF(LEN(B69)=9,1,(LEN(B69)+1)/10))) -> 1 | Q69: =iferror(if(Q$9=FALSE,, if(if(search(Q$11,$B69,1)>0,1,0)=1,$H69/$P69,)),"") | R69: =iferror(if(R$9=FALSE,, if(if(search(R$11,$B69,1)>0,1,0)=1,$H69/$P69,)),"") | S69: =iferror(if(S$9=FALSE,, if(if(search(S$11,$B69,1)>0,1,0)=1,$H69/$P69,)),"") | T69: =iferror(if(T$9=FALSE,, if(if(search(T$11,$B69,1)>0,1,0)=1,$H69/$P69,)),"") | U69: =iferror(if(U$9=FALSE,, if(if(search(U$11,$B69,1)>0,1,0)=1,$H69/$P69,)),"") | V69: =iferror(if(V$9=FALSE,, if(if(search(V$11,$B69,1)>0,1,0)=1,$H69/$P69,)),"") | W69: =iferror(if(W$9=FALSE,, if(if(search(W$11,$B69,1)>0,1,0)=1,$H69/$P69,)),"") | X69: =iferror(if(X$9=FALSE,, if(if(search(X$11,$B69,1)>0,1,0)=1,$H69/$P69,)),"") | ... BE69: =iferror(if(BE$9=FALSE,, if(if(search(BE$11,$B69,1)>0,1,0)=1,$H69/$P69,)),"")
B70: INOV00001 | D70: Laboratório ALAC | F70: 94.088.952/0001-52 | G70: 114009 | H70: 15092.26 | I70: 45527 | J70: Análise de macronutrientes, vitaminas e minerais T0. | L70: TRUE | M70: =SUM(Q70:BE70) -> 15092.26 | O70: =SUM(Q70:AP70)=H70 -> TRUE | P70: =IF(L70=FALSE,0,IF(LEN(B70)=0,0,IF(LEN(B70)=9,1,(LEN(B70)+1)/10))) -> 1 | Q70: =iferror(if(Q$9=FALSE,, if(if(search(Q$11,$B70,1)>0,1,0)=1,$H70/$P70,)),"") -> 15092.26 | R70: =iferror(if(R$9=FALSE,, if(if(search(R$11,$B70,1)>0,1,0)=1,$H70/$P70,)),"") | S70: =iferror(if(S$9=FALSE,, if(if(search(S$11,$B70,1)>0,1,0)=1,$H70/$P70,)),"") | T70: =iferror(if(T$9=FALSE,, if(if(search(T$11,$B70,1)>0,1,0)=1,$H70/$P70,)),"") | U70: =iferror(if(U$9=FALSE,, if(if(search(U$11,$B70,1)>0,1,0)=1,$H70/$P70,)),"") | V70: =iferror(if(V$9=FALSE,, if(if(search(V$11,$B70,1)>0,1,0)=1,$H70/$P70,)),"") | W70: =iferror(if(W$9=FALSE,, if(if(search(W$11,$B70,1)>0,1,0)=1,$H70/$P70,)),"") | X70: =iferror(if(X$9=FALSE,, if(if(search(X$11,$B70,1)>0,1,0)=1,$H70/$P70,)),"") | ... BE70: =iferror(if(BE$9=FALSE,, if(if(search(BE$11,$B70,1)>0,1,0)=1,$H70/$P70,)),"")
B71: INOV00001 | D71: Laboratório ALAC | F71: 94.088.952/0001-52 | G71: 114230 | H71: 3143.1 | I71: 45527 | J71: Análise de fibras e perfil de tocoferol para fechar T0. | L71: TRUE | M71: =SUM(Q71:BE71) -> 3143.1 | O71: =SUM(Q71:AP71)=H71 -> TRUE | P71: =IF(L71=FALSE,0,IF(LEN(B71)=0,0,IF(LEN(B71)=9,1,(LEN(B71)+1)/10))) -> 1 | Q71: =iferror(if(Q$9=FALSE,, if(if(search(Q$11,$B71,1)>0,1,0)=1,$H71/$P71,)),"") -> 3143.1 | R71: =iferror(if(R$9=FALSE,, if(if(search(R$11,$B71,1)>0,1,0)=1,$H71/$P71,)),"") | S71: =iferror(if(S$9=FALSE,, if(if(search(S$11,$B71,1)>0,1,0)=1,$H71/$P71,)),"") | T71: =iferror(if(T$9=FALSE,, if(if(search(T$11,$B71,1)>0,1,0)=1,$H71/$P71,)),"") | U71: =iferror(if(U$9=FALSE,, if(if(search(U$11,$B71,1)>0,1,0)=1,$H71/$P71,)),"") | V71: =iferror(if(V$9=FALSE,, if(if(search(V$11,$B71,1)>0,1,0)=1,$H71/$P71,)),"") | W71: =iferror(if(W$9=FALSE,, if(if(search(W$11,$B71,1)>0,1,0)=1,$H71/$P71,)),"") | X71: =iferror(if(X$9=FALSE,, if(if(search(X$11,$B71,1)>0,1,0)=1,$H71/$P71,)),"") | ... BE71: =iferror(if(BE$9=FALSE,, if(if(search(BE$11,$B71,1)>0,1,0)=1,$H71/$P71,)),"")
... B83: INOV00041 | D83: RNC MEDICOS INTENSIVISTAS LTDA | F83: 26.528.525/0001-98 | G83: 253 | H83: 3500 | I83: 45533 | J83: Consultoria para Pesquisa de aplicação ProteinPT Liquid | L83: TRUE | M83: =SUM(Q83:BE83) -> 3500 | O83: =SUM(Q83:AP83)=H83 -> FALSE | P83: =IF(L83=FALSE,0,IF(LEN(B83)=0,0,IF(LEN(B83)=9,1,(LEN(B83)+1)/10))) -> 1 | Q83: =iferror(if(Q$9=FALSE,, if(if(search(Q$11,$B83,1)>0,1,0)=1,$H83/$P83,)),"") | R83: =iferror(if(R$9=FALSE,, if(if(search(R$11,$B83,1)>0,1,0)=1,$H83/$P83,)),"") | S83: =iferror(if(S$9=FALSE,, if(if(search(S$11,$B83,1)>0,1,0)=1,$H83/$P83,)),"") | T83: =iferror(if(T$9=FALSE,, if(if(search(T$11,$B83,1)>0,1,0)=1,$H83/$P83,)),"") | U83: =iferror(if(U$9=FALSE,, if(if(search(U$11,$B83,1)>0,1,0)=1,$H83/$P83,)),"") | V83: =iferror(if(V$9=FALSE,, if(if(search(V$11,$B83,1)>0,1,0)=1,$H83/$P83,)),"") | W83: =iferror(if(W$9=FALSE,, if(if(search(W$11,$B83,1)>0,1,0)=1,$H83/$P83,)),"") | X83: =iferror(if(X$9=FALSE,, if(if(search(X$11,$B83,1)>0,1,0)=1,$H83/$P83,)),"") | ... BE83: =iferror(if(BE$9=FALSE,, if(if(search(BE$11,$B83,1)>0,1,0)=1,$H83/$P83,)),"")
B84: INOV00001 | D84: Laboratório ALAC | F84: 94.088.952/0001-52 | G84: 115298 | H84: 5615.66 | I84: 45567 | J84: Análise de vitaminas (após TI LATCO). | L84: TRUE | M84: =SUM(Q84:BE84) -> 5615.66 | O84: FALSE | P84: =IF(L84=FALSE,0,IF(LEN(B84)=0,0,IF(LEN(B84)=9,1,(LEN(B84)+1)/10))) -> 1 | Q84: =iferror(if(Q$9=FALSE,, if(if(search(Q$11,$B84,1)>0,1,0)=1,$H84/$P84,)),"") -> 5615.66 | R84: =iferror(if(R$9=FALSE,, if(if(search(R$11,$B84,1)>0,1,0)=1,$H84/$P84,)),"") | S84: =iferror(if(S$9=FALSE,, if(if(search(S$11,$B84,1)>0,1,0)=1,$H84/$P84,)),"") | T84: =iferror(if(T$9=FALSE,, if(if(search(T$11,$B84,1)>0,1,0)=1,$H84/$P84,)),"") | U84: =iferror(if(U$9=FALSE,, if(if(search(U$11,$B84,1)>0,1,0)=1,$H84/$P84,)),"") | V84: =iferror(if(V$9=FALSE,, if(if(search(V$11,$B84,1)>0,1,0)=1,$H84/$P84,)),"") | W84: =iferror(if(W$9=FALSE,, if(if(search(W$11,$B84,1)>0,1,0)=1,$H84/$P84,)),"") | X84: =iferror(if(X$9=FALSE,, if(if(search(X$11,$B84,1)>0,1,0)=1,$H84/$P84,)),"") | ... BE84: =iferror(if(BE$9=FALSE,, if(if(search(BE$11,$B84,1)>0,1,0)=1,$H84/$P84,)),"")
B85: INOV00016 | D85: J&J Serviços de Entregas Ltda - ME | F85: 20.618.029/0001-49 | G85: 79952 | H85: 0 | I85: 45568 | J85: Envio para análise de PL no ITAL. | L85: TRUE | M85: =SUM(Q85:BE85) -> 0 | O85: FALSE | P85: =IF(L85=FALSE,0,IF(LEN(B85)=0,0,IF(LEN(B85)=9,1,(LEN(B85)+1)/10))) -> 1 | Q85: =iferror(if(Q$9=FALSE,, if(if(search(Q$11,$B85,1)>0,1,0)=1,$H85/$P85,)),"") | R85: =iferror(if(R$9=FALSE,, if(if(search(R$11,$B85,1)>0,1,0)=1,$H85/$P85,)),"") | S85: =iferror(if(S$9=FALSE,, if(if(search(S$11,$B85,1)>0,1,0)=1,$H85/$P85,)),"") | T85: =iferror(if(T$9=FALSE,, if(if(search(T$11,$B85,1)>0,1,0)=1,$H85/$P85,)),"") | U85: =iferror(if(U$9=FALSE,, if(if(search(U$11,$B85,1)>0,1,0)=1,$H85/$P85,)),"") | V85: =iferror(if(V$9=FALSE,, if(if(search(V$11,$B85,1)>0,1,0)=1,$H85/$P85,)),"") | W85: =iferror(if(W$9=FALSE,, if(if(search(W$11,$B85,1)>0,1,0)=1,$H85/$P85,)),"") | X85: =iferror(if(X$9=FALSE,, if(if(search(X$11,$B85,1)>0,1,0)=1,$H85/$P85,)),"") | ... BE85: =iferror(if(BE$9=FALSE,, if(if(search(BE$11,$B85,1)>0,1,0)=1,$H85/$P85,)),"")
B86: INOV00001 | D86: Laboratório ALAC | F86: 94.088.952/0001-52 | G86: 115330 | H86: 2807.83 | I86: 45568 | J86: Análise de vitaminas (após TI LATCO). | L86: TRUE | M86: =SUM(Q86:BE86) -> 2807.83 | O86: =SUM(Q86:BE86)=H86 -> TRUE | P86: =IF(L86=FALSE,0,IF(LEN(B86)=0,0,IF(LEN(B86)=9,1,(LEN(B86)+1)/10))) -> 1 | Q86: =iferror(if(Q$9=FALSE,, if(if(search(Q$11,$B86,1)>0,1,0)=1,$H86/$P86,)),"") -> 2807.83 | R86: =iferror(if(R$9=FALSE,, if(if(search(R$11,$B86,1)>0,1,0)=1,$H86/$P86,)),"") | S86: =iferror(if(S$9=FALSE,, if(if(search(S$11,$B86,1)>0,1,0)=1,$H86/$P86,)),"") | T86: =iferror(if(T$9=FALSE,, if(if(search(T$11,$B86,1)>0,1,0)=1,$H86/$P86,)),"") | U86: =iferror(if(U$9=FALSE,, if(if(search(U$11,$B86,1)>0,1,0)=1,$H86/$P86,)),"") | V86: =iferror(if(V$9=FALSE,, if(if(search(V$11,$B86,1)>0,1,0)=1,$H86/$P86,)),"") | W86: =iferror(if(W$9=FALSE,, if(if(search(W$11,$B86,1)>0,1,0)=1,$H86/$P86,)),"") | X86: =iferror(if(X$9=FALSE,, if(if(search(X$11,$B86,1)>0,1,0)=1,$H86/$P86,)),"") | ... BE86: =iferror(if(BE$9=FALSE,, if(if(search(BE$11,$B86,1)>0,1,0)=1,$H86/$P86,)),"")
B87: INOV00016 | D87: Laboratório ALAC | F87: 94.088.952/0001-52 | G87: 115587 | H87: 62.19 | I87: 45579 | J87: Análise de gorduras | L87: TRUE | M87: =SUM(Q87:BE87) -> 62.19 | O87: =SUM(Q87:BE87)=H87 -> TRUE | P87: =IF(L87=FALSE,0,IF(LEN(B87)=0,0,IF(LEN(B87)=9,1,(LEN(B87)+1)/10))) -> 1 | Q87: =iferror(if(Q$9=FALSE,, if(if(search(Q$11,$B87,1)>0,1,0)=1,$H87/$P87,)),"") | R87: =iferror(if(R$9=FALSE,, if(if(search(R$11,$B87,1)>0,1,0)=1,$H87/$P87,)),"") | S87: =iferror(if(S$9=FALSE,, if(if(search(S$11,$B87,1)>0,1,0)=1,$H87/$P87,)),"") | T87: =iferror(if(T$9=FALSE,, if(if(search(T$11,$B87,1)>0,1,0)=1,$H87/$P87,)),"") | U87: =iferror(if(U$9=FALSE,, if(if(search(U$11,$B87,1)>0,1,0)=1,$H87/$P87,)),"") | V87: =iferror(if(V$9=FALSE,, if(if(search(V$11,$B87,1)>0,1,0)=1,$H87/$P87,)),"") | W87: =iferror(if(W$9=FALSE,, if(if(search(W$11,$B87,1)>0,1,0)=1,$H87/$P87,)),"") | X87: =iferror(if(X$9=FALSE,, if(if(search(X$11,$B87,1)>0,1,0)=1,$H87/$P87,)),"") | ... BE87: =iferror(if(BE$9=FALSE,, if(if(search(BE$11,$B87,1)>0,1,0)=1,$H87/$P87,)),"")
B88: INOV00040 | D88: Laboratório ALAC | F88: 94.088.952/0001-52 | G88: 115647 | H88: 152.01 | I88: 45580 | J88: Análise de selênio para fechar T12. | L88: FALSE | M88: =SUM(Q88:BE88) -> 0 | O88: =SUM(Q88:BE88)=H88 -> FALSE | P88: =IF(L88=FALSE,0,IF(LEN(B88)=0,0,IF(LEN(B88)=9,1,(LEN(B88)+1)/10))) -> 0 | Q88: =iferror(if(Q$9=FALSE,, if(if(search(Q$11,$B88,1)>0,1,0)=1,$H88/$P88,)),"") | R88: =iferror(if(R$9=FALSE,, if(if(search(R$11,$B88,1)>0,1,0)=1,$H88/$P88,)),"") | S88: =iferror(if(S$9=FALSE,, if(if(search(S$11,$B88,1)>0,1,0)=1,$H88/$P88,)),"") | T88: =iferror(if(T$9=FALSE,, if(if(search(T$11,$B88,1)>0,1,0)=1,$H88/$P88,)),"") | U88: =iferror(if(U$9=FALSE,, if(if(search(U$11,$B88,1)>0,1,0)=1,$H88/$P88,)),"") | V88: =iferror(if(V$9=FALSE,, if(if(search(V$11,$B88,1)>0,1,0)=1,$H88/$P88,)),"") | W88: =iferror(if(W$9=FALSE,, if(if(search(W$11,$B88,1)>0,1,0)=1,$H88/$P88,)),"") | X88: =iferror(if(X$9=FALSE,, if(if(search(X$11,$B88,1)>0,1,0)=1,$H88/$P88,)),"") | ... BE88: =iferror(if(BE$9=FALSE,, if(if(search(BE$11,$B88,1)>0,1,0)=1,$H88/$P88,)),"")
B89: INOV00016 | D89: Fundação de desenv. da pesquisa do agronegócio - FUNDEPAG | F89: 50.276.237/0001-78 | G89: 156448 | H89: 938 | I89: 45588 | J89: Análise de perfil lipídico. | L89: TRUE | M89: =SUM(Q89:BE89) -> 938 | O89: =SUM(Q89:BE89)=H89 -> TRUE | P89: =IF(L89=FALSE,0,IF(LEN(B89)=0,0,IF(LEN(B89)=9,1,(LEN(B89)+1)/10))) -> 1 | Q89: =iferror(if(Q$9=FALSE,, if(if(search(Q$11,$B89,1)>0,1,0)=1,$H89/$P89,)),"") | R89: =iferror(if(R$9=FALSE,, if(if(search(R$11,$B89,1)>0,1,0)=1,$H89/$P89,)),"") | S89: =iferror(if(S$9=FALSE,, if(if(search(S$11,$B89,1)>0,1,0)=1,$H89/$P89,)),"") | T89: =iferror(if(T$9=FALSE,, if(if(search(T$11,$B89,1)>0,1,0)=1,$H89/$P89,)),"") | U89: =iferror(if(U$9=FALSE,, if(if(search(U$11,$B89,1)>0,1,0)=1,$H89/$P89,)),"") | V89: =iferror(if(V$9=FALSE,, if(if(search(V$11,$B89,1)>0,1,0)=1,$H89/$P89,)),"") | W89: =iferror(if(W$9=FALSE,, if(if(search(W$11,$B89,1)>0,1,0)=1,$H89/$P89,)),"") | X89: =iferror(if(X$9=FALSE,, if(if(search(X$11,$B89,1)>0,1,0)=1,$H89/$P89,)),"") | ... BE89: =iferror(if(BE$9=FALSE,, if(if(search(BE$11,$B89,1)>0,1,0)=1,$H89/$P89,)),"")
B90: INOV00016 | D90: NP Analytical Laboratories | F90: NA | G90: 1-20240919-05236 | H90: 0 | I90: 45595 | J90: Análise de perfil de aminoácidos e proteína | L90: FALSE | M90: =SUM(Q90:BE90) -> 0 | O90: =SUM(Q90:BE90)=H90 -> TRUE | P90: =IF(L90=FALSE,0,IF(LEN(B90)=0,0,IF(LEN(B90)=9,1,(LEN(B90)+1)/10))) -> 0 | Q90: =iferror(if(Q$9=FALSE,, if(if(search(Q$11,$B90,1)>0,1,0)=1,$H90/$P90,)),"") | R90: =iferror(if(R$9=FALSE,, if(if(search(R$11,$B90,1)>0,1,0)=1,$H90/$P90,)),"") | S90: =iferror(if(S$9=FALSE,, if(if(search(S$11,$B90,1)>0,1,0)=1,$H90/$P90,)),"") | T90: =iferror(if(T$9=FALSE,, if(if(search(T$11,$B90,1)>0,1,0)=1,$H90/$P90,)),"") | U90: =iferror(if(U$9=FALSE,, if(if(search(U$11,$B90,1)>0,1,0)=1,$H90/$P90,)),"") | V90: =iferror(if(V$9=FALSE,, if(if(search(V$11,$B90,1)>0,1,0)=1,$H90/$P90,)),"") | W90: =iferror(if(W$9=FALSE,, if(if(search(W$11,$B90,1)>0,1,0)=1,$H90/$P90,)),"") | X90: =iferror(if(X$9=FALSE,, if(if(search(X$11,$B90,1)>0,1,0)=1,$H90/$P90,)),"") | ... BE90: =iferror(if(BE$9=FALSE,, if(if(search(BE$11,$B90,1)>0,1,0)=1,$H90/$P90,)),"")
B91: INOV00050 | D91: LSD serviços de tradução LTDA | F91: 43503492/0001-40 | G91: K2A1U10P | H91: 0 | I91: 45602 | J91: Tradução escrita artigo para ingles | L91: FALSE | M91: =SUM(Q91:BE91) -> 0 | O91: =SUM(Q91:BE91)=H91 -> TRUE | P91: =IF(L91=FALSE,0,IF(LEN(B91)=0,0,IF(LEN(B91)=9,1,(LEN(B91)+1)/10))) -> 0 | Q91: =iferror(if(Q$9=FALSE,, if(if(search(Q$11,$B91,1)>0,1,0)=1,$H91/$P91,)),"") | R91: =iferror(if(R$9=FALSE,, if(if(search(R$11,$B91,1)>0,1,0)=1,$H91/$P91,)),"") | S91: =iferror(if(S$9=FALSE,, if(if(search(S$11,$B91,1)>0,1,0)=1,$H91/$P91,)),"") | T91: =iferror(if(T$9=FALSE,, if(if(search(T$11,$B91,1)>0,1,0)=1,$H91/$P91,)),"") | U91: =iferror(if(U$9=FALSE,, if(if(search(U$11,$B91,1)>0,1,0)=1,$H91/$P91,)),"") | V91: =iferror(if(V$9=FALSE,, if(if(search(V$11,$B91,1)>0,1,0)=1,$H91/$P91,)),"") | W91: =iferror(if(W$9=FALSE,, if(if(search(W$11,$B91,1)>0,1,0)=1,$H91/$P91,)),"") | X91: =iferror(if(X$9=FALSE,, if(if(search(X$11,$B91,1)>0,1,0)=1,$H91/$P91,)),"") | ... BE91: =iferror(if(BE$9=FALSE,, if(if(search(BE$11,$B91,1)>0,1,0)=1,$H91/$P91,)),"")
B92: INOV00001 | D92: Laboratório ALAC | F92: 94.088.952/0001-52 | G92: 116546 | H92: 699.9 | I92: 45609 | J92: Análise de Vitamina A Retort NN - reanálise T0 | L92: TRUE | M92: =SUM(Q92:BE92) -> 699.9 | O92: =SUM(Q92:BE92)=H92 -> TRUE | P92: =IF(L92=FALSE,0,IF(LEN(B92)=0,0,IF(LEN(B92)=9,1,(LEN(B92)+1)/10))) -> 1 | Q92: =iferror(if(Q$9=FALSE,, if(if(search(Q$11,$B92,1)>0,1,0)=1,$H92/$P92,)),"") -> 699.9 | R92: =iferror(if(R$9=FALSE,, if(if(search(R$11,$B92,1)>0,1,0)=1,$H92/$P92,)),"") | S92: =iferror(if(S$9=FALSE,, if(if(search(S$11,$B92,1)>0,1,0)=1,$H92/$P92,)),"") | T92: =iferror(if(T$9=FALSE,, if(if(search(T$11,$B92,1)>0,1,0)=1,$H92/$P92,)),"") | U92: =iferror(if(U$9=FALSE,, if(if(search(U$11,$B92,1)>0,1,0)=1,$H92/$P92,)),"") | V92: =iferror(if(V$9=FALSE,, if(if(search(V$11,$B92,1)>0,1,0)=1,$H92/$P92,)),"") | W92: =iferror(if(W$9=FALSE,, if(if(search(W$11,$B92,1)>0,1,0)=1,$H92/$P92,)),"") | X92: =iferror(if(X$9=FALSE,, if(if(search(X$11,$B92,1)>0,1,0)=1,$H92/$P92,)),"") | ... BE92: =iferror(if(BE$9=FALSE,, if(if(search(BE$11,$B92,1)>0,1,0)=1,$H92/$P92,)),"")
B93: INOV00028 | D93: Laboratório ALAC | F93: 94.088.952/0001-52 | G93: 116380 | H93: 978.37 | I93: 45607 | J93: Análise de cromo e ácido pantotênico T3 | L93: FALSE | M93: =SUM(Q93:BE93) -> 0 | O93: =SUM(Q93:BE93)=H93 -> FALSE | P93: =IF(L93=FALSE,0,IF(LEN(B93)=0,0,IF(LEN(B93)=9,1,(LEN(B93)+1)/10))) -> 0 | Q93: =iferror(if(Q$9=FALSE,, if(if(search(Q$11,$B93,1)>0,1,0)=1,$H93/$P93,)),"") | R93: =iferror(if(R$9=FALSE,, if(if(search(R$11,$B93,1)>0,1,0)=1,$H93/$P93,)),"") | S93: =iferror(if(S$9=FALSE,, if(if(search(S$11,$B93,1)>0,1,0)=1,$H93/$P93,)),"") | T93: =iferror(if(T$9=FALSE,, if(if(search(T$11,$B93,1)>0,1,0)=1,$H93/$P93,)),"") | U93: =iferror(if(U$9=FALSE,, if(if(search(U$11,$B93,1)>0,1,0)=1,$H93/$P93,)),"") | V93: =iferror(if(V$9=FALSE,, if(if(search(V$11,$B93,1)>0,1,0)=1,$H93/$P93,)),"") | W93: =iferror(if(W$9=FALSE,, if(if(search(W$11,$B93,1)>0,1,0)=1,$H93/$P93,)),"") | X93: =iferror(if(X$9=FALSE,, if(if(search(X$11,$B93,1)>0,1,0)=1,$H93/$P93,)),"") | ... BE93: =iferror(if(BE$9=FALSE,, if(if(search(BE$11,$B93,1)>0,1,0)=1,$H93/$P93,)),"")
B94: INOV00001|INOV00014 | D94: J&J Serviços de Entregas Ltda - ME | F94: 20.618.029/0001-49 | G94: 775 | H94: 312.5 | I94: 45629 | J94: Envio para análise microbiológicas na Labor3 e para PL no ITAL - análises de T0. | L94: TRUE | M94: =SUM(Q94:BE94) -> 312.5 | O94: =SUM(Q94:BE94)=H94 -> TRUE | P94: =IF(L94=FALSE,0,IF(LEN(B94)=0,0,IF(LEN(B94)=9,1,(LEN(B94)+1)/10))) -> 2 | Q94: =iferror(if(Q$9=FALSE,, if(if(search(Q$11,$B94,1)>0,1,0)=1,$H94/$P94,)),"") -> 156.25 | R94: =iferror(if(R$9=FALSE,, if(if(search(R$11,$B94,1)>0,1,0)=1,$H94/$P94,)),"") | S94: =iferror(if(S$9=FALSE,, if(if(search(S$11,$B94,1)>0,1,0)=1,$H94/$P94,)),"") | T94: =iferror(if(T$9=FALSE,, if(if(search(T$11,$B94,1)>0,1,0)=1,$H94/$P94,)),"") | U94: =iferror(if(U$9=FALSE,, if(if(search(U$11,$B94,1)>0,1,0)=1,$H94/$P94,)),"") | V94: =iferror(if(V$9=FALSE,, if(if(search(V$11,$B94,1)>0,1,0)=1,$H94/$P94,)),"") | W94: =iferror(if(W$9=FALSE,, if(if(search(W$11,$B94,1)>0,1,0)=1,$H94/$P94,)),"") | X94: =iferror(if(X$9=FALSE,, if(if(search(X$11,$B94,1)>0,1,0)=1,$H94/$P94,)),"") -> 156.25 | ... BE94: =iferror(if(BE$9=FALSE,, if(if(search(BE$11,$B94,1)>0,1,0)=1,$H94/$P94,)),"")
B95: INOV00001 | D95: Laboratório ALAC | F95: 94.088.952/0001-52 | G95: 117105 | H95: 2078.14 | I95: 45629 | J95: Análise de minerais e vitamina A - T0 | L95: TRUE | M95: =SUM(Q95:BE95) -> 2078.14 | O95: =SUM(Q95:BE95)=H95 -> TRUE | P95: =IF(L95=FALSE,0,IF(LEN(B95)=0,0,IF(LEN(B95)=9,1,(LEN(B95)+1)/10))) -> 1 | Q95: =iferror(if(Q$9=FALSE,, if(if(search(Q$11,$B95,1)>0,1,0)=1,$H95/$P95,)),"") -> 2078.14 | R95: =iferror(if(R$9=FALSE,, if(if(search(R$11,$B95,1)>0,1,0)=1,$H95/$P95,)),"") | S95: =iferror(if(S$9=FALSE,, if(if(search(S$11,$B95,1)>0,1,0)=1,$H95/$P95,)),"") | T95: =iferror(if(T$9=FALSE,, if(if(search(T$11,$B95,1)>0,1,0)=1,$H95/$P95,)),"") | U95: =iferror(if(U$9=FALSE,, if(if(search(U$11,$B95,1)>0,1,0)=1,$H95/$P95,)),"") | V95: =iferror(if(V$9=FALSE,, if(if(search(V$11,$B95,1)>0,1,0)=1,$H95/$P95,)),"") | W95: =iferror(if(W$9=FALSE,, if(if(search(W$11,$B95,1)>0,1,0)=1,$H95/$P95,)),"") | X95: =iferror(if(X$9=FALSE,, if(if(search(X$11,$B95,1)>0,1,0)=1,$H95/$P95,)),"") | ... BE95: =iferror(if(BE$9=FALSE,, if(if(search(BE$11,$B95,1)>0,1,0)=1,$H95/$P95,)),"")
B96: INOV00001 | D96: Labor Três Laboratórios e Consultoria Técnica Ltda. | F96: 02.021.076/0001-29 | G96: 52890 | H96: 840 | I96: 45632 | J96: Esterilidade comercial após TI Latco. | L96: TRUE | M96: =SUM(Q96:BE96) -> 840 | O96: =SUM(Q96:BE96)=H96 -> TRUE | P96: =IF(L96=FALSE,0,IF(LEN(B96)=0,0,IF(LEN(B96)=9,1,(LEN(B96)+1)/10))) -> 1 | Q96: =iferror(if(Q$9=FALSE,, if(if(search(Q$11,$B96,1)>0,1,0)=1,$H96/$P96,)),"") -> 840 | R96: =iferror(if(R$9=FALSE,, if(if(search(R$11,$B96,1)>0,1,0)=1,$H96/$P96,)),"") | S96: =iferror(if(S$9=FALSE,, if(if(search(S$11,$B96,1)>0,1,0)=1,$H96/$P96,)),"") | T96: =iferror(if(T$9=FALSE,, if(if(search(T$11,$B96,1)>0,1,0)=1,$H96/$P96,)),"") | U96: =iferror(if(U$9=FALSE,, if(if(search(U$11,$B96,1)>0,1,0)=1,$H96/$P96,)),"") | V96: =iferror(if(V$9=FALSE,, if(if(search(V$11,$B96,1)>0,1,0)=1,$H96/$P96,)),"") | W96: =iferror(if(W$9=FALSE,, if(if(search(W$11,$B96,1)>0,1,0)=1,$H96/$P96,)),"") | X96: =iferror(if(X$9=FALSE,, if(if(search(X$11,$B96,1)>0,1,0)=1,$H96/$P96,)),"") | ... BE96: =iferror(if(BE$9=FALSE,, if(if(search(BE$11,$B96,1)>0,1,0)=1,$H96/$P96,)),"")
B97: INOV00001 | D97: Fundação de Apoio à Universidade de São Paulo | F97: 68.314.830/0001-27 | G97: 66649 | H97: 891 | I97: 45642 | J97: Análise de distribuição de partículas após TI LATCO | L97: TRUE | M97: =SUM(Q97:BE97) -> 891 | O97: =SUM(Q97:BE97)=H97 -> TRUE | P97: =IF(L97=FALSE,0,IF(LEN(B97)=0,0,IF(LEN(B97)=9,1,(LEN(B97)+1)/10))) -> 1 | Q97: =iferror(if(Q$9=FALSE,, if(if(search(Q$11,$B97,1)>0,1,0)=1,$H97/$P97,)),"") -> 891 | R97: =iferror(if(R$9=FALSE,, if(if(search(R$11,$B97,1)>0,1,0)=1,$H97/$P97,)),"") | S97: =iferror(if(S$9=FALSE,, if(if(search(S$11,$B97,1)>0,1,0)=1,$H97/$P97,)),"") | T97: =iferror(if(T$9=FALSE,, if(if(search(T$11,$B97,1)>0,1,0)=1,$H97/$P97,)),"") | U97: =iferror(if(U$9=FALSE,, if(if(search(U$11,$B97,1)>0,1,0)=1,$H97/$P97,)),"") | V97: =iferror(if(V$9=FALSE,, if(if(search(V$11,$B97,1)>0,1,0)=1,$H97/$P97,)),"") | W97: =iferror(if(W$9=FALSE,, if(if(search(W$11,$B97,1)>0,1,0)=1,$H97/$P97,)),"") | X97: =iferror(if(X$9=FALSE,, if(if(search(X$11,$B97,1)>0,1,0)=1,$H97/$P97,)),"") | ... BE97: =iferror(if(BE$9=FALSE,, if(if(search(BE$11,$B97,1)>0,1,0)=1,$H97/$P97,)),"")
B98: INOV00014 | D98: Laboratório ALAC | F98: 94.088.952/0001-52 | G98: 117769 | H98: 18641.48 | I98: 45652 | J98: Análises de vitaminas e minerais | L98: TRUE | M98: =SUM(Q98:BE98) -> 18641.48 | O98: =SUM(Q98:BE98)=H98 -> TRUE | P98: =IF(L98=FALSE,0,IF(LEN(B98)=0,0,IF(LEN(B98)=9,1,(LEN(B98)+1)/10))) -> 1 | Q98: =iferror(if(Q$9=FALSE,, if(if(search(Q$11,$B98,1)>0,1,0)=1,$H98/$P98,)),"") | R98: =iferror(if(R$9=FALSE,, if(if(search(R$11,$B98,1)>0,1,0)=1,$H98/$P98,)),"") | S98: =iferror(if(S$9=FALSE,, if(if(search(S$11,$B98,1)>0,1,0)=1,$H98/$P98,)),"") | T98: =iferror(if(T$9=FALSE,, if(if(search(T$11,$B98,1)>0,1,0)=1,$H98/$P98,)),"") | U98: =iferror(if(U$9=FALSE,, if(if(search(U$11,$B98,1)>0,1,0)=1,$H98/$P98,)),"") | V98: =iferror(if(V$9=FALSE,, if(if(search(V$11,$B98,1)>0,1,0)=1,$H98/$P98,)),"") | W98: =iferror(if(W$9=FALSE,, if(if(search(W$11,$B98,1)>0,1,0)=1,$H98/$P98,)),"") | X98: =iferror(if(X$9=FALSE,, if(if(search(X$11,$B98,1)>0,1,0)=1,$H98/$P98,)),"") -> 18641.48 | ... BE98: =iferror(if(BE$9=FALSE,, if(if(search(BE$11,$B98,1)>0,1,0)=1,$H98/$P98,)),"")
M99: =SUM(Q99:BE99) -> 0 | O99: =SUM(Q99:AP99)=H99 -> TRUE | P99: =IF(L99=FALSE,0,IF(LEN(B99)=0,0,IF(LEN(B99)=9,1,(LEN(B99)+1)/10))) -> 0 | Q99: =iferror(if(Q$9=FALSE,, if(if(search(Q$11,$B99,1)>0,1,0)=1,$H99/$P99,)),"") | R99: =iferror(if(R$9=FALSE,, if(if(search(R$11,$B99,1)>0,1,0)=1,$H99/$P99,)),"") | S99: =iferror(if(S$9=FALSE,, if(if(search(S$11,$B99,1)>0,1,0)=1,$H99/$P99,)),"") | T99: =iferror(if(T$9=FALSE,, if(if(search(T$11,$B99,1)>0,1,0)=1,$H99/$P99,)),"") | U99: =iferror(if(U$9=FALSE,, if(if(search(U$11,$B99,1)>0,1,0)=1,$H99/$P99,)),"") | V99: =iferror(if(V$9=FALSE,, if(if(search(V$11,$B99,1)>0,1,0)=1,$H99/$P99,)),"") | W99: =iferror(if(W$9=FALSE,, if(if(search(W$11,$B99,1)>0,1,0)=1,$H99/$P99,)),"") | X99: =iferror(if(X$9=FALSE,, if(if(search(X$11,$B99,1)>0,1,0)=1,$H99/$P99,)),"") | ... BE99: =iferror(if(BE$9=FALSE,, if(if(search(BE$11,$B99,1)>0,1,0)=1,$H99/$P99,)),"")
M100: =SUM(Q100:BE100) -> 0 | O100: =SUM(Q100:AP100)=H100 -> TRUE | P100: =IF(L100=FALSE,0,IF(LEN(B100)=0,0,IF(LEN(B100)=9,1,(LEN(B100)+1)/10))) -> 0 | Q100: =iferror(if(Q$9=FALSE,, if(if(search(Q$11,$B100,1)>0,1,0)=1,$H100/$P100,)),"") | R100: =iferror(if(R$9=FALSE,, if(if(search(R$11,$B100,1)>0,1,0)=1,$H100/$P100,)),"") | S100: =iferror(if(S$9=FALSE,, if(if(search(S$11,$B100,1)>0,1,0)=1,$H100/$P100,)),"") | T100: =iferror(if(T$9=FALSE,, if(if(search(T$11,$B100,1)>0,1,0)=1,$H100/$P100,)),"") | U100: =iferror(if(U$9=FALSE,, if(if(search(U$11,$B100,1)>0,1,0)=1,$H100/$P100,)),"") | V100: =iferror(if(V$9=FALSE,, if(if(search(V$11,$B100,1)>0,1,0)=1,$H100/$P100,)),"") | W100: =iferror(if(W$9=FALSE,, if(if(search(W$11,$B100,1)>0,1,0)=1,$H100/$P100,)),"") | X100: =iferror(if(X$9=FALSE,, if(if(search(X$11,$B100,1)>0,1,0)=1,$H100/$P100,)),"") | ... BE100: =iferror(if(BE$9=FALSE,, if(if(search(BE$11,$B100,1)>0,1,0)=1,$H100/$P100,)),"")
M101: =SUM(Q101:BE101) -> 0 | O101: =SUM(Q101:AP101)=H101 -> TRUE | P101: =IF(L101=FALSE,0,IF(LEN(B101)=0,0,IF(LEN(B101)=9,1,(LEN(B101)+1)/10))) -> 0 | Q101: =iferror(if(Q$9=FALSE,, if(if(search(Q$11,$B101,1)>0,1,0)=1,$H101/$P101,)),"") | R101: =iferror(if(R$9=FALSE,, if(if(search(R$11,$B101,1)>0,1,0)=1,$H101/$P101,)),"") | S101: =iferror(if(S$9=FALSE,, if(if(search(S$11,$B101,1)>0,1,0)=1,$H101/$P101,)),"") | T101: =iferror(if(T$9=FALSE,, if(if(search(T$11,$B101,1)>0,1,0)=1,$H101/$P101,)),"") | U101: =iferror(if(U$9=FALSE,, if(if(search(U$11,$B101,1)>0,1,0)=1,$H101/$P101,)),"") | V101: =iferror(if(V$9=FALSE,, if(if(search(V$11,$B101,1)>0,1,0)=1,$H101/$P101,)),"") | W101: =iferror(if(W$9=FALSE,, if(if(search(W$11,$B101,1)>0,1,0)=1,$H101/$P101,)),"") | X101: =iferror(if(X$9=FALSE,, if(if(search(X$11,$B101,1)>0,1,0)=1,$H101/$P101,)),"") | ... BE101: =iferror(if(BE$9=FALSE,, if(if(search(BE$11,$B101,1)>0,1,0)=1,$H101/$P101,)),"")
M102: =SUM(Q102:BE102) -> 0 | O102: =SUM(Q102:AP102)=H102 -> TRUE | P102: =IF(L102=FALSE,0,IF(LEN(B102)=0,0,IF(LEN(B102)=9,1,(LEN(B102)+1)/10))) -> 0 | Q102: =iferror(if(Q$9=FALSE,, if(if(search(Q$11,$B102,1)>0,1,0)=1,$H102/$P102,)),"") | R102: =iferror(if(R$9=FALSE,, if(if(search(R$11,$B102,1)>0,1,0)=1,$H102/$P102,)),"") | S102: =iferror(if(S$9=FALSE,, if(if(search(S$11,$B102,1)>0,1,0)=1,$H102/$P102,)),"") | T102: =iferror(if(T$9=FALSE,, if(if(search(T$11,$B102,1)>0,1,0)=1,$H102/$P102,)),"") | U102: =iferror(if(U$9=FALSE,, if(if(search(U$11,$B102,1)>0,1,0)=1,$H102/$P102,)),"") | V102: =iferror(if(V$9=FALSE,, if(if(search(V$11,$B102,1)>0,1,0)=1,$H102/$P102,)),"") | W102: =iferror(if(W$9=FALSE,, if(if(search(W$11,$B102,1)>0,1,0)=1,$H102/$P102,)),"") | X102: =iferror(if(X$9=FALSE,, if(if(search(X$11,$B102,1)>0,1,0)=1,$H102/$P102,)),"") | ... BE102: =iferror(if(BE$9=FALSE,, if(if(search(BE$11,$B102,1)>0,1,0)=1,$H102/$P102,)),"")
M103: =SUM(Q103:BE103) -> 0 | O103: =SUM(Q103:AP103)=H103 -> TRUE | P103: =IF(L103=FALSE,0,IF(LEN(B103)=0,0,IF(LEN(B103)=9,1,(LEN(B103)+1)/10))) -> 0 | Q103: =iferror(if(Q$9=FALSE,, if(if(search(Q$11,$B103,1)>0,1,0)=1,$H103/$P103,)),"") | R103: =iferror(if(R$9=FALSE,, if(if(search(R$11,$B103,1)>0,1,0)=1,$H103/$P103,)),"") | S103: =iferror(if(S$9=FALSE,, if(if(search(S$11,$B103,1)>0,1,0)=1,$H103/$P103,)),"") | T103: =iferror(if(T$9=FALSE,, if(if(search(T$11,$B103,1)>0,1,0)=1,$H103/$P103,)),"") | U103: =iferror(if(U$9=FALSE,, if(if(search(U$11,$B103,1)>0,1,0)=1,$H103/$P103,)),"") | V103: =iferror(if(V$9=FALSE,, if(if(search(V$11,$B103,1)>0,1,0)=1,$H103/$P103,)),"") | W103: =iferror(if(W$9=FALSE,, if(if(search(W$11,$B103,1)>0,1,0)=1,$H103/$P103,)),"") | X103: =iferror(if(X$9=FALSE,, if(if(search(X$11,$B103,1)>0,1,0)=1,$H103/$P103,)),"") | ... BE103: =iferror(if(BE$9=FALSE,, if(if(search(BE$11,$B103,1)>0,1,0)=1,$H103/$P103,)),"")
M104: =SUM(Q104:BE104) -> 0 | O104: =SUM(Q104:AP104)=H104 -> TRUE | P104: =IF(L104=FALSE,0,IF(LEN(B104)=0,0,IF(LEN(B104)=9,1,(LEN(B104)+1)/10))) -> 0 | Q104: =iferror(if(Q$9=FALSE,, if(if(search(Q$11,$B104,1)>0,1,0)=1,$H104/$P104,)),"") | R104: =iferror(if(R$9=FALSE,, if(if(search(R$11,$B104,1)>0,1,0)=1,$H104/$P104,)),"") | S104: =iferror(if(S$9=FALSE,, if(if(search(S$11,$B104,1)>0,1,0)=1,$H104/$P104,)),"") | T104: =iferror(if(T$9=FALSE,, if(if(search(T$11,$B104,1)>0,1,0)=1,$H104/$P104,)),"") | U104: =iferror(if(U$9=FALSE,, if(if(search(U$11,$B104,1)>0,1,0)=1,$H104/$P104,)),"") | V104: =iferror(if(V$9=FALSE,, if(if(search(V$11,$B104,1)>0,1,0)=1,$H104/$P104,)),"") | W104: =iferror(if(W$9=FALSE,, if(if(search(W$11,$B104,1)>0,1,0)=1,$H104/$P104,)),"") | X104: =iferror(if(X$9=FALSE,, if(if(search(X$11,$B104,1)>0,1,0)=1,$H104/$P104,)),"") | ... BE104: =iferror(if(BE$9=FALSE,, if(if(search(BE$11,$B104,1)>0,1,0)=1,$H104/$P104,)),"")
M105: =SUM(Q105:BE105) -> 0 | O105: =SUM(Q105:AP105)=H105 -> TRUE | P105: =IF(L105=FALSE,0,IF(LEN(B105)=0,0,IF(LEN(B105)=9,1,(LEN(B105)+1)/10))) -> 0 | Q105: =iferror(if(Q$9=FALSE,, if(if(search(Q$11,$B105,1)>0,1,0)=1,$H105/$P105,)),"") | R105: =iferror(if(R$9=FALSE,, if(if(search(R$11,$B105,1)>0,1,0)=1,$H105/$P105,)),"") | S105: =iferror(if(S$9=FALSE,, if(if(search(S$11,$B105,1)>0,1,0)=1,$H105/$P105,)),"") | T105: =iferror(if(T$9=FALSE,, if(if(search(T$11,$B105,1)>0,1,0)=1,$H105/$P105,)),"") | U105: =iferror(if(U$9=FALSE,, if(if(search(U$11,$B105,1)>0,1,0)=1,$H105/$P105,)),"") | V105: =iferror(if(V$9=FALSE,, if(if(search(V$11,$B105,1)>0,1,0)=1,$H105/$P105,)),"") | W105: =iferror(if(W$9=FALSE,, if(if(search(W$11,$B105,1)>0,1,0)=1,$H105/$P105,)),"") | X105: =iferror(if(X$9=FALSE,, if(if(search(X$11,$B105,1)>0,1,0)=1,$H105/$P105,)),"") | ... BE105: =iferror(if(BE$9=FALSE,, if(if(search(BE$11,$B105,1)>0,1,0)=1,$H105/$P105,)),"")
M106: =SUM(Q106:BE106) -> 0 | O106: =SUM(Q106:AP106)=H106 -> TRUE | P106: =IF(L106=FALSE,0,IF(LEN(B106)=0,0,IF(LEN(B106)=9,1,(LEN(B106)+1)/10))) -> 0 | Q106: =iferror(if(Q$9=FALSE,, if(if(search(Q$11,$B106,1)>0,1,0)=1,$H106/$P106,)),"") | R106: =iferror(if(R$9=FALSE,, if(if(search(R$11,$B106,1)>0,1,0)=1,$H106/$P106,)),"") | S106: =iferror(if(S$9=FALSE,, if(if(search(S$11,$B106,1)>0,1,0)=1,$H106/$P106,)),"") | T106: =iferror(if(T$9=FALSE,, if(if(search(T$11,$B106,1)>0,1,0)=1,$H106/$P106,)),"") | U106: =iferror(if(U$9=FALSE,, if(if(search(U$11,$B106,1)>0,1,0)=1,$H106/$P106,)),"") | V106: =iferror(if(V$9=FALSE,, if(if(search(V$11,$B106,1)>0,1,0)=1,$H106/$P106,)),"") | W106: =iferror(if(W$9=FALSE,, if(if(search(W$11,$B106,1)>0,1,0)=1,$H106/$P106,)),"") | X106: =iferror(if(X$9=FALSE,, if(if(search(X$11,$B106,1)>0,1,0)=1,$H106/$P106,)),"") | ... BE106: =iferror(if(BE$9=FALSE,, if(if(search(BE$11,$B106,1)>0,1,0)=1,$H106/$P106,)),"")
M107: =SUM(Q107:BE107) -> 0 | O107: =SUM(Q107:AP107)=H107 -> TRUE | P107: =IF(L107=FALSE,0,IF(LEN(B107)=0,0,IF(LEN(B107)=9,1,(LEN(B107)+1)/10))) -> 0 | Q107: =iferror(if(Q$9=FALSE,, if(if(search(Q$11,$B107,1)>0,1,0)=1,$H107/$P107,)),"") | R107: =iferror(if(R$9=FALSE,, if(if(search(R$11,$B107,1)>0,1,0)=1,$H107/$P107,)),"") | S107: =iferror(if(S$9=FALSE,, if(if(search(S$11,$B107,1)>0,1,0)=1,$H107/$P107,)),"") | T107: =iferror(if(T$9=FALSE,, if(if(search(T$11,$B107,1)>0,1,0)=1,$H107/$P107,)),"") | U107: =iferror(if(U$9=FALSE,, if(if(search(U$11,$B107,1)>0,1,0)=1,$H107/$P107,)),"") | V107: =iferror(if(V$9=FALSE,, if(if(search(V$11,$B107,1)>0,1,0)=1,$H107/$P107,)),"") | W107: =iferror(if(W$9=FALSE,, if(if(search(W$11,$B107,1)>0,1,0)=1,$H107/$P107,)),"") | X107: =iferror(if(X$9=FALSE,, if(if(search(X$11,$B107,1)>0,1,0)=1,$H107/$P107,)),"") | ... BE107: =iferror(if(BE$9=FALSE,, if(if(search(BE$11,$B107,1)>0,1,0)=1,$H107/$P107,)),"")
M108: =SUM(Q108:BE108) -> 0 | O108: =SUM(Q108:AP108)=H108 -> TRUE | P108: =IF(L108=FALSE,0,IF(LEN(B108)=0,0,IF(LEN(B108)=9,1,(LEN(B108)+1)/10))) -> 0 | Q108: =iferror(if(Q$9=FALSE,, if(if(search(Q$11,$B108,1)>0,1,0)=1,$H108/$P108,)),"") | R108: =iferror(if(R$9=FALSE,, if(if(search(R$11,$B108,1)>0,1,0)=1,$H108/$P108,)),"") | S108: =iferror(if(S$9=FALSE,, if(if(search(S$11,$B108,1)>0,1,0)=1,$H108/$P108,)),"") | T108: =iferror(if(T$9=FALSE,, if(if(search(T$11,$B108,1)>0,1,0)=1,$H108/$P108,)),"") | U108: =iferror(if(U$9=FALSE,, if(if(search(U$11,$B108,1)>0,1,0)=1,$H108/$P108,)),"") | V108: =iferror(if(V$9=FALSE,, if(if(search(V$11,$B108,1)>0,1,0)=1,$H108/$P108,)),"") | W108: =iferror(if(W$9=FALSE,, if(if(search(W$11,$B108,1)>0,1,0)=1,$H108/$P108,)),"") | X108: =iferror(if(X$9=FALSE,, if(if(search(X$11,$B108,1)>0,1,0)=1,$H108/$P108,)),"") | ... BE108: =iferror(if(BE$9=FALSE,, if(if(search(BE$11,$B108,1)>0,1,0)=1,$H108/$P108,)),"")
M109: =SUM(Q109:BE109) -> 0 | O109: =SUM(Q109:AP109)=H109 -> TRUE | P109: =IF(L109=FALSE,0,IF(LEN(B109)=0,0,IF(LEN(B109)=9,1,(LEN(B109)+1)/10))) -> 0 | Q109: =iferror(if(Q$9=FALSE,, if(if(search(Q$11,$B109,1)>0,1,0)=1,$H109/$P109,)),"") | R109: =iferror(if(R$9=FALSE,, if(if(search(R$11,$B109,1)>0,1,0)=1,$H109/$P109,)),"") | S109: =iferror(if(S$9=FALSE,, if(if(search(S$11,$B109,1)>0,1,0)=1,$H109/$P109,)),"") | T109: =iferror(if(T$9=FALSE,, if(if(search(T$11,$B109,1)>0,1,0)=1,$H109/$P109,)),"") | U109: =iferror(if(U$9=FALSE,, if(if(search(U$11,$B109,1)>0,1,0)=1,$H109/$P109,)),"") | V109: =iferror(if(V$9=FALSE,, if(if(search(V$11,$B109,1)>0,1,0)=1,$H109/$P109,)),"") | W109: =iferror(if(W$9=FALSE,, if(if(search(W$11,$B109,1)>0,1,0)=1,$H109/$P109,)),"") | X109: =iferror(if(X$9=FALSE,, if(if(search(X$11,$B109,1)>0,1,0)=1,$H109/$P109,)),"") | ... BE109: =iferror(if(BE$9=FALSE,, if(if(search(BE$11,$B109,1)>0,1,0)=1,$H109/$P109,)),"")
M110: =SUM(Q110:BE110) -> 0 | O110: =SUM(Q110:AP110)=H110 -> TRUE | P110: =IF(L110=FALSE,0,IF(LEN(B110)=0,0,IF(LEN(B110)=9,1,(LEN(B110)+1)/10))) -> 0 | Q110: =iferror(if(Q$9=FALSE,, if(if(search(Q$11,$B110,1)>0,1,0)=1,$H110/$P110,)),"") | R110: =iferror(if(R$9=FALSE,, if(if(search(R$11,$B110,1)>0,1,0)=1,$H110/$P110,)),"") | S110: =iferror(if(S$9=FALSE,, if(if(search(S$11,$B110,1)>0,1,0)=1,$H110/$P110,)),"") | T110: =iferror(if(T$9=FALSE,, if(if(search(T$11,$B110,1)>0,1,0)=1,$H110/$P110,)),"") | U110: =iferror(if(U$9=FALSE,, if(if(search(U$11,$B110,1)>0,1,0)=1,$H110/$P110,)),"") | V110: =iferror(if(V$9=FALSE,, if(if(search(V$11,$B110,1)>0,1,0)=1,$H110/$P110,)),"") | W110: =iferror(if(W$9=FALSE,, if(if(search(W$11,$B110,1)>0,1,0)=1,$H110/$P110,)),"") | X110: =iferror(if(X$9=FALSE,, if(if(search(X$11,$B110,1)>0,1,0)=1,$H110/$P110,)),"") | ... BE110: =iferror(if(BE$9=FALSE,, if(if(search(BE$11,$B110,1)>0,1,0)=1,$H110/$P110,)),"")
... M135: =SUM(Q135:BE135) -> 0 | O135: =SUM(Q135:AP135)=H135 -> TRUE | P135: =IF(L135=FALSE,0,IF(LEN(B135)=0,0,IF(LEN(B135)=9,1,(LEN(B135)+1)/10))) -> 0 | Q135: =iferror(if(Q$9=FALSE,, if(if(search(Q$11,$B135,1)>0,1,0)=1,$H135/$P135,)),"") | R135: =iferror(if(R$9=FALSE,, if(if(search(R$11,$B135,1)>0,1,0)=1,$H135/$P135,)),"") | S135: =iferror(if(S$9=FALSE,, if(if(search(S$11,$B135,1)>0,1,0)=1,$H135/$P135,)),"") | T135: =iferror(if(T$9=FALSE,, if(if(search(T$11,$B135,1)>0,1,0)=1,$H135/$P135,)),"") | U135: =iferror(if(U$9=FALSE,, if(if(search(U$11,$B135,1)>0,1,0)=1,$H135/$P135,)),"") | V135: =iferror(if(V$9=FALSE,, if(if(search(V$11,$B135,1)>0,1,0)=1,$H135/$P135,)),"") | W135: =iferror(if(W$9=FALSE,, if(if(search(W$11,$B135,1)>0,1,0)=1,$H135/$P135,)),"") | X135: =iferror(if(X$9=FALSE,, if(if(search(X$11,$B135,1)>0,1,0)=1,$H135/$P135,)),"") | ... BE135: =iferror(if(BE$9=FALSE,, if(if(search(BE$11,$B135,1)>0,1,0)=1,$H135/$P135,)),"")
O136: FALSE
O137: FALSE
O138: FALSE
O139: FALSE
O140: FALSE
O141: FALSE
O142: FALSE
O143: FALSE
O144: FALSE
O145: FALSE
O146: FALSE
O147: FALSE
... O1135: FALSE

Sheet TIMESHEET
B2: PRODIET
B3: Pesquisa ,Desenvolvimento & Inovação
B4: Formulário de PD&I - Ano2024
B5: -preencher somente os campos sombreados (cinza)
H6: Treinamento
H7: Pesquisa | I7: → Estudo, pesquisa, prospecção, contato com fornecedor, etc.
B8: Dossiê do projeto | H8: Desenvolvimento | I8: → Análise, Teste, Formulação, etc.
B9: Atividades de Pesquisa, Desenvolvimento e Inovação | H9: Gestão e outros | I9: → Contagem, reunião diretoria, controles financeiros, etc.
N10: =subtotal(9,N12:N1897) -> 2591.7327
B11: RowID | C11: Projeto | D11: Etapa | E11: Colaborador | F11: Data | G11: Tempo(h) | H11: Classificação PRODIET | I11: Classificação MCBENNER | K11: Descrição da atividade e observações | L11: Revisão McBenner | M11: Projeto | N11: Custo | O11: Atividade incentiv. | P11: Projeto incentiv.
C12: =VLOOKUP(M12,'#verificação horas por projeto'!A:B,2,FALSE) -> INOV00046 | D12: INOV00046 | E12: Ana Paula Biz | F12: 45293 | G12: 0.055555556 | H12: Pesquisa | I12: Pesquisa | K12: Pesquisa sobre metodologia de análise para quantificar o TGF beta 2 em produtos. | M12: 2023 - PEPTIMAX IBD | N12: 0 | O12: =if(OR(I12="Treinamento",I12="Pesquisa",I12="Desenvolvimento"),TRUE,FALSE) -> TRUE | P12: {=IFERROR(VLOOKUP($C$12:$C1897,'Base Projetos'!$A:$B,2,FALSE),FALSE)} -> FALSE | Q12: {=vlookup($E$12:$E1897,PESSOAL!B$35:$E$47,4,false)} -> Parcial
C13: =VLOOKUP(M13,'#verificação horas por projeto'!A:B,2,FALSE) -> INOV00044 | D13: INOV00044 | E13: Ana Paula Biz | F13: 45306 | G13: 0.11111111 | H13: Gestão e outros | I13: Gestão e outros | K13: Tradução, revisão e conferência do Estudo de Estabilidade. | M13: 2023 - MIXME MS+PIRAMAL | N13: 0 | O13: =if(OR(I13="Treinamento",I13="Pesquisa",I13="Desenvolvimento"),TRUE,FALSE) -> FALSE | P13: FALSE | Q13: Parcial
C14: =VLOOKUP(M14,'#verificação horas por projeto'!A:B,2,FALSE) -> INOV00013 | D14: INOV00013 | E14: Ana Paula Biz | F14: 45309 | G14: 0.010416667 | H14: Gestão e outros | I14: Gestão e outros | K14: Conferência de NF de análise do produto. | M14: 2021 - Sachê a vácuo | N14: 0 | O14: =if(OR(I14="Treinamento",I14="Pesquisa",I14="Desenvolvimento"),TRUE,FALSE) -> FALSE | P14: TRUE | Q14: Parcial
C15: =VLOOKUP(M15,'#verificação horas por projeto'!A:B,2,FALSE) -> INOV00006 | D15: INOV00006 | E15: Ana Paula Biz | F15: 45309 | G15: 0.0069444444 | H15: Gestão e outros | I15: Gestão e outros | K15: Conferência de NF de análise do produto. | M15: 2019 - Artesanal | N15: 0 | O15: =if(OR(I15="Treinamento",I15="Pesquisa",I15="Desenvolvimento"),TRUE,FALSE) -> FALSE | P15: TRUE | Q15: Parcial
C16: =VLOOKUP(M16,'#verificação horas por projeto'!A:B,2,FALSE) -> INOV00045 | D16: INOV00045 | E16: Ana Paula Biz | F16: 45330 | G16: 0.017361111 | H16: Gestão e outros | I16: Gestão e outros | K16: Reunião com potencial fornecedor sobre CoA e monografias. | M16: 2023 - PROJETOS PREMIX IN HOUSE | N16: 0 | O16: =if(OR(I16="Treinamento",I16="Pesquisa",I16="Desenvolvimento"),TRUE,FALSE) -> FALSE | P16: FALSE | Q16: Parcial
C17: =VLOOKUP(M17,'#verificação horas por projeto'!A:B,2,FALSE) -> INOV00031 | D17: INOV00031 | E17: Ana Paula Biz | F17: 45373 | G17: 0.125 | H17: Desenvolvimento | I17: Desenvolvimento | K17: Análise de dados e elaboração do relatório de EE. | M17: 2021 - Energyzip Sênior | N17: 0 | O17: =if(OR(I17="Treinamento",I17="Pesquisa",I17="Desenvolvimento"),TRUE,FALSE) -> TRUE | P17: FALSE | Q17: Parcial
C18: =VLOOKUP(M18,'#verificação horas por projeto'!A:B,2,FALSE) -> INOV00031 | D18: INOV00031 | E18: Ana Paula Biz | F18: 45376 | G18: 0.038194444 | H18: Desenvolvimento | I18: Desenvolvimento | K18: Revisão do relatório de EE. | M18: 2021 - Energyzip Sênior | N18: 0 | O18: =if(OR(I18="Treinamento",I18="Pesquisa",I18="Desenvolvimento"),TRUE,FALSE) -> TRUE | P18: FALSE | Q18: Parcial
C19: =VLOOKUP(M19,'#verificação horas por projeto'!A:B,2,FALSE) -> INOV00001 | D19: INOV00001 | E19: Ana Paula Biz | F19: 45373 | G19: 0.09375 | H19: Desenvolvimento | I19: Desenvolvimento | K19: Análise de dados e elaboração do relatório de EE. | M19: 2018 - Retort | N19: 80.89 | O19: =if(OR(I19="Treinamento",I19="Pesquisa",I19="Desenvolvimento"),TRUE,FALSE) -> TRUE | P19: TRUE | Q19: Parcial
C20: =VLOOKUP(M20,'#verificação horas por projeto'!A:B,2,FALSE) -> INOV00001 | D20: INOV00001 | E20: Ana Paula Biz | F20: 45376 | G20: 0.048611111 | H20: Desenvolvimento | I20: Desenvolvimento | K20: Revisão do relatório de EE. | M20: 2018 - Retort | N20: 41.94 | O20: =if(OR(I20="Treinamento",I20="Pesquisa",I20="Desenvolvimento"),TRUE,FALSE) -> TRUE | P20: TRUE | Q20: Parcial
C21: =VLOOKUP(M21,'#verificação horas por projeto'!A:B,2,FALSE) -> INOV00001 | D21: INOV00001 | E21: Ana Paula Biz | F21: 45357 | G21: 0.013888889 | H21: Gestão e outros | I21: Gestão e outros | K21: Apresentação dos dados do EE dos produtos DiamaxIG RTH e Trophic Soya RTH. | M21: 2018 - Retort | N21: 0 | O21: =if(OR(I21="Treinamento",I21="Pesquisa",I21="Desenvolvimento"),TRUE,FALSE) -> FALSE | P21: TRUE | Q21: Parcial
C22: =VLOOKUP(M22,'#verificação horas por projeto'!A:B,2,FALSE) -> INOV00017 | D22: INOV00017 | E22: Ana Paula Biz | F22: 45379 | G22: 0.052083333 | H22: Desenvolvimento | I22: Desenvolvimento | K22: Acompanhamento teste industrial. | M22: 2020 - Linha Trophic Soya Pó | N22: 44.94 | O22: =if(OR(I22="Treinamento",I22="Pesquisa",I22="Desenvolvimento"),TRUE,FALSE) -> TRUE | P22: TRUE | Q22: Parcial
C23: =VLOOKUP(M23,'#verificação horas por projeto'!A:B,2,FALSE) -> INOV00001 | D23: INOV00001 | E23: Ana Paula Celes | F23: 45299 | G23: 0.041666667 | H23: Desenvolvimento | I23: Desenvolvimento | K23: Alinhamento dos Conceitos de comunicação | M23: 2018 - Retort | N23: 195.02 | O23: =if(OR(I23="Treinamento",I23="Pesquisa",I23="Desenvolvimento"),TRUE,FALSE) -> TRUE | P23: TRUE | Q23: Parcial
C24: =VLOOKUP(M24,'#verificação horas por projeto'!A:B,2,FALSE) -> INOV00001 | D24: INOV00001 | E24: Ana Paula Celes | F24: 45302 | G24: 0.041666667 | H24: Gestão e outros | I24: Gestão e outros | K24: Diretrizes para compor informações com a nova envasadora | M24: 2018 - Retort | N24: 0 | O24: =if(OR(I24="Treinamento",I24="Pesquisa",I24="Desenvolvimento"),TRUE,FALSE) -> FALSE | P24: TRUE | Q24: Parcial
... C49: =VLOOKUP(M49,'#verificação horas por projeto'!A:B,2,FALSE) -> INOV00001 | D49: INOV00001 | E49: Alyne Alves Nunes Oliveira | F49: 45323 | G49: 0.020833333 | H49: Desenvolvimento | I49: Desenvolvimento | K49: Planejamento teste industrial Latco | M49: 2018 - Retort | N49: 29.8 | O49: =if(OR(I49="Treinamento",I49="Pesquisa",I49="Desenvolvimento"),TRUE,FALSE) -> TRUE | P49: TRUE | Q49: Parcial
C50: =VLOOKUP(M50,'#verificação horas por projeto'!A:B,2,FALSE) -> INOV00001 | D50: INOV00001 | E50: Alyne Alves Nunes Oliveira | F50: 45329 | G50: 0.020833333 | H50: Gestão e outros | I50: Gestão e outros | M50: 2018 - Retort | N50: 0 | O50: =if(OR(I50="Treinamento",I50="Pesquisa",I50="Desenvolvimento"),TRUE,FALSE) -> FALSE | P50: TRUE | Q50: Parcial
C51: =VLOOKUP(M51,'#verificação horas por projeto'!A:B,2,FALSE) -> INOV00001 | D51: INOV00001 | E51: Alyne Alves Nunes Oliveira | F51: 45341 | G51: 0.52083333 | H51: Gestão e outros | I51: Gestão e outros | K51: Deslocamento teste industrial Latco: Rio - Paraná | M51: 2018 - Retort | N51: 0 | O51: =if(OR(I51="Treinamento",I51="Pesquisa",I51="Desenvolvimento"),TRUE,FALSE) -> FALSE | P51: TRUE | Q51: Parcial
C52: =VLOOKUP(M52,'#verificação horas por projeto'!A:B,2,FALSE) -> INOV00001 | D52: INOV00001 | E52: Alyne Alves Nunes Oliveira | F52: 45348 | G52: 0.4375 | H52: Desenvolvimento | I52: Desenvolvimento | K52: Teste Industrial Latco - dieta HH | M52: 2018 - Retort | N52: 625.71 | O52: =if(OR(I52="Treinamento",I52="Pesquisa",I52="Desenvolvimento"),TRUE,FALSE) -> TRUE | P52: TRUE | Q52: Parcial
C53: =VLOOKUP(M53,'#verificação horas por projeto'!A:B,2,FALSE) -> INOV00001 | D53: INOV00001 | E53: Alyne Alves Nunes Oliveira | F53: 45349 | G53: 0.4375 | H53: Desenvolvimento | I53: Desenvolvimento | K53: Teste Industrial Latco - validação térmica autoclave | M53: 2018 - Retort | N53: 625.71 | O53: =if(OR(I53="Treinamento",I53="Pesquisa",I53="Desenvolvimento"),TRUE,FALSE) -> TRUE | P53: TRUE | Q53: Parcial
C54: =VLOOKUP(M54,'#verificação horas por projeto'!A:B,2,FALSE) -> INOV00001 | D54: INOV00001 | E54: Alyne Alves Nunes Oliveira | F54: 45350 | G54: 0.64583333 | H54: Desenvolvimento | I54: Desenvolvimento | K54: Teste Industrial Latco - validação térmica autoclave | M54: 2018 - Retort | N54: 923.67 | O54: =if(OR(I54="Treinamento",I54="Pesquisa",I54="Desenvolvimento"),TRUE,FALSE) -> TRUE | P54: TRUE | Q54: Parcial
C55: =VLOOKUP(M55,'#verificação horas por projeto'!A:B,2,FALSE) -> INOV00001 | D55: INOV00001 | E55: Alyne Alves Nunes Oliveira | F55: 45351 | G55: 0.33333333 | H55: Desenvolvimento | I55: Desenvolvimento | K55: Teste Industrial Latco - validação térmica autoclave | M55: 2018 - Retort | N55: 476.73 | O55: =if(OR(I55="Treinamento",I55="Pesquisa",I55="Desenvolvimento"),TRUE,FALSE) -> TRUE | P55: TRUE | Q55: Parcial
C56: =VLOOKUP(M56,'#verificação horas por projeto'!A:B,2,FALSE) -> INOV00001 | D56: INOV00001 | E56: Alyne Alves Nunes Oliveira | F56: 45352 | G56: 0.45833333 | H56: Gestão e outros | I56: Gestão e outros | K56: Deslocamento teste industrial Latco: Paraná - Rio | M56: 2018 - Retort | N56: 0 | O56: =if(OR(I56="Treinamento",I56="Pesquisa",I56="Desenvolvimento"),TRUE,FALSE) -> FALSE | P56: TRUE | Q56: Parcial
C57: =VLOOKUP(M57,'#verificação horas por projeto'!A:B,2,FALSE) -> INOV00001 | D57: INOV00001 | E57: Alyne Alves Nunes Oliveira | F57: 45356 | G57: 0.25 | H57: Desenvolvimento | I57: Desenvolvimento | K57: Relatório teste industrial Latco | M57: 2018 - Retort | N57: 339.67 | O57: =if(OR(I57="Treinamento",I57="Pesquisa",I57="Desenvolvimento"),TRUE,FALSE) -> TRUE | P57: TRUE | Q57: Parcial
C58: =VLOOKUP(M58,'#verificação horas por projeto'!A:B,2,FALSE) -> INOV00001 | D58: INOV00001 | E58: Alyne Alves Nunes Oliveira | F58: 45357 | G58: 0.041666667 | H58: Desenvolvimento | I58: Desenvolvimento | K58: Envio de amostra para análise externa | M58: 2018 - Retort | N58: 56.61 | O58: =if(OR(I58="Treinamento",I58="Pesquisa",I58="Desenvolvimento"),TRUE,FALSE) -> TRUE | P58: TRUE | Q58: Parcial
C59: =VLOOKUP(M59,'#verificação horas por projeto'!A:B,2,FALSE) -> INOV00001 | D59: INOV00001 | E59: Alyne Alves Nunes Oliveira | F59: 45357 | G59: 0.0625 | H59: Desenvolvimento | I59: Desenvolvimento | K59: Alinhamento teste industrial Latco - validação térmica | M59: 2018 - Retort | N59: 84.92 | O59: =if(OR(I59="Treinamento",I59="Pesquisa",I59="Desenvolvimento"),TRUE,FALSE) -> TRUE | P59: TRUE | Q59: Parcial
C60: =VLOOKUP(M60,'#verificação horas por projeto'!A:B,2,FALSE) -> INOV00006 | D60: INOV00006 | E60: Gabriela Faria de Oliveira | F60: 45293 | G60: 0.16666667 | H60: Desenvolvimento | I60: Desenvolvimento | K60: Desenvolvimento de novo produto - análise nutricional | M60: 2019 - Artesanal | N60: 163.42 | O60: =if(OR(I60="Treinamento",I60="Pesquisa",I60="Desenvolvimento"),TRUE,FALSE) -> TRUE | P60: TRUE | Q60: Parcial
C61: =VLOOKUP(M61,'#verificação horas por projeto'!A:B,2,FALSE) -> INOV00035 | D61: INOV00035 | E61: Gabriela Faria de Oliveira | F61: 45294 | G61: 0.083333333 | H61: Pesquisa | I61: Pesquisa | K61: Desenvolvimento de desenho de pesquisa clínica para novo produto | M61: 2023 - PESQUISA CLÍNICA - CICATRIZAÇÃO | N61: 81.71 | O61: =if(OR(I61="Treinamento",I61="Pesquisa",I61="Desenvolvimento"),TRUE,FALSE) -> TRUE | P61: TRUE | Q61: Parcial
C62: =VLOOKUP(M62,'#verificação horas por projeto'!A:B,2,FALSE) -> INOV00024 | D62: INOV00024 | E62: Gabriela Faria de Oliveira | F62: 45294 | G62: 0.041666667 | H62: Pesquisa | I62: Pesquisa | K62: Prospecção de novos estudos com produtos de portfólio | M62: 2021 - Estudo de Caso | N62: 40.86 | O62: =if(OR(I62="Treinamento",I62="Pesquisa",I62="Desenvolvimento"),TRUE,FALSE) -> TRUE | P62: TRUE | Q62: Parcial
... C121: =VLOOKUP(M121,'#verificação horas por projeto'!A:B,2,FALSE) -> INOV00024 | D121: INOV00024 | E121: Raissa Bellotti | F121: 45313 | G121: 0.041666667 | H121: Pesquisa | I121: Pesquisa | K121: Alinhamento de desenvolvimento de estudo de caso com profissionais | M121: 2021 - Estudo de Caso | N121: 34.01 | O121: =if(OR(I121="Treinamento",I121="Pesquisa",I121="Desenvolvimento"),TRUE,FALSE) -> TRUE | P121: TRUE | Q121: Parcial
C122: =VLOOKUP(M122,'#verificação horas por projeto'!A:B,2,FALSE) -> INOV00017 | D122: INOV00017 | E122: Ana Paula Biz | F122: 45383 | G122: 0.048611111 | H122: Desenvolvimento | I122: Desenvolvimento | K122: Acompanhamento teste industrial. | M122: 2020 - Linha Trophic Soya Pó | N122: =IF(AND(O122=TRUE,P122=TRUE), VLOOKUP($E122,PESSOAL!$B$35:$S$45,MONTH($F122)+6,FALSE)*G122*24,0) -> 44.74304 | O122: =if(OR(I122="Treinamento",I122="Pesquisa",I122="Desenvolvimento"),TRUE,FALSE) -> TRUE | P122: TRUE | Q122: Parcial
C123: =VLOOKUP(M123,'#verificação horas por projeto'!A:B,2,FALSE) -> INOV00017 | D123: INOV00017 | E123: Ana Paula Biz | F123: 45383 | G123: 0.069444444 | H123: Desenvolvimento | I123: Desenvolvimento | K123: Organização das amostras do teste industrial para início de EE. | M123: 2020 - Linha Trophic Soya Pó | N123: =IF(AND(O123=TRUE,P123=TRUE), VLOOKUP($E123,PESSOAL!$B$35:$S$45,MONTH($F123)+6,FALSE)*G123*24,0) -> 63.918628 | O123: =if(OR(I123="Treinamento",I123="Pesquisa",I123="Desenvolvimento"),TRUE,FALSE) -> TRUE | P123: TRUE | Q123: Parcial
C124: =VLOOKUP(M124,'#verificação horas por projeto'!A:B,2,FALSE) -> INOV00017 | D124: INOV00017 | E124: Ana Paula Biz | F124: 45383 | G124: 0.052083333 | H124: Desenvolvimento | I124: Desenvolvimento | K124: Organização das amostras do teste industrial para início de EE. | M124: 2020 - Linha Trophic Soya Pó | N124: =IF(AND(O124=TRUE,P124=TRUE), VLOOKUP($E124,PESSOAL!$B$35:$S$45,MONTH($F124)+6,FALSE)*G124*24,0) -> 47.938971 | O124: =if(OR(I124="Treinamento",I124="Pesquisa",I124="Desenvolvimento"),TRUE,FALSE) -> TRUE | P124: TRUE | Q124: Parcial
C125: =VLOOKUP(M125,'#verificação horas por projeto'!A:B,2,FALSE) -> INOV00017 | D125: INOV00017 | E125: Ana Paula Biz | F125: 45400 | G125: 0.020833333 | H125: Gestão e outros | I125: Gestão e outros | K125: Conferência de NF de análise de produto. | M125: 2020 - Linha Trophic Soya Pó | N125: =IF(AND(O125=TRUE,P125=TRUE), VLOOKUP($E125,PESSOAL!$B$35:$S$45,MONTH($F125)+6,FALSE)*G125*24,0) -> 0 | O125: =if(OR(I125="Treinamento",I125="Pesquisa",I125="Desenvolvimento"),TRUE,FALSE) -> FALSE | P125: TRUE | Q125: Parcial
C126: =VLOOKUP(M126,'#verificação horas por projeto'!A:B,2,FALSE) -> INOV00014 | D126: INOV00014 | E126: Ana Paula Biz | F126: 45419 | G126: 0.072916667 | H126: Desenvolvimento | I126: Desenvolvimento | K126: Avaliaçao de tendência da concentração dos premixes ao longo do estudo de estabilidade. | M126: 2021 - Energyzip 25% | N126: =IF(AND(O126=TRUE,P126=TRUE), VLOOKUP($E126,PESSOAL!$B$35:$S$45,MONTH($F126)+6,FALSE)*G126*24,0) -> 67.114559 | O126: =if(OR(I126="Treinamento",I126="Pesquisa",I126="Desenvolvimento"),TRUE,FALSE) -> TRUE | P126: TRUE | Q126: Parcial
C127: =VLOOKUP(M127,'#verificação horas por projeto'!A:B,2,FALSE) -> INOV00016 | D127: INOV00016 | E127: Ana Paula Biz | F127: 45443 | G127: 0.097222222 | H127: Desenvolvimento | I127: Desenvolvimento | K127: Análise dos resultados laboratoriais do produto em T0. | M127: 2018 - Linha Trophic Soya Líquido | N127: =IF(AND(O127=TRUE,P127=TRUE), VLOOKUP($E127,PESSOAL!$B$35:$S$45,MONTH($F127)+6,FALSE)*G127*24,0) -> 89.486079 | O127: =if(OR(I127="Treinamento",I127="Pesquisa",I127="Desenvolvimento"),TRUE,FALSE) -> TRUE | P127: TRUE | Q127: Parcial
C128: =VLOOKUP(M128,'#verificação horas por projeto'!A:B,2,FALSE) -> INOV00001 | D128: INOV00001 | E128: Ana Paula Biz | F128: 45443 | G128: 0.034722222 | H128: Desenvolvimento | I128: Desenvolvimento | K128: Análise de dados para responder exigência do HN. | M128: 2018 - Retort | N128: =IF(AND(O128=TRUE,P128=TRUE), VLOOKUP($E128,PESSOAL!$B$35:$S$45,MONTH($F128)+6,FALSE)*G128*24,0) -> 31.959314 | O128: =if(OR(I128="Treinamento",I128="Pesquisa",I128="Desenvolvimento"),TRUE,FALSE) -> TRUE | P128: TRUE | Q128: Parcial
C129: =VLOOKUP(M129,'#verificação horas por projeto'!A:B,2,FALSE) -> INOV00004 | D129: INOV00004 | E129: Ana Paula Biz | F129: 45421 | G129: 0.020833333 | H129: Desenvolvimento | I129: Desenvolvimento | K129: Determinação da IN do CorrectMax | M129: 2019 - Cicatrização | N129: =IF(AND(O129=TRUE,P129=TRUE), VLOOKUP($E129,PESSOAL!$B$35:$S$45,MONTH($F129)+6,FALSE)*G129*24,0) -> 19.175588 | O129: =if(OR(I129="Treinamento",I129="Pesquisa",I129="Desenvolvimento"),TRUE,FALSE) -> TRUE | P129: TRUE | Q129: Parcial
C130: =VLOOKUP(M130,'#verificação horas por projeto'!A:B,2,FALSE) -> INOV00046 | D130: INOV00046 | E130: Ana Paula Biz | F130: 45422 | G130: 0.03125 | H130: Pesquisa | I130: Pesquisa | K130: Determinação de métodos analíticos para quantificar TGF beta2. | M130: 2023 - PEPTIMAX IBD | N130: =IF(AND(O130=TRUE,P130=TRUE), VLOOKUP($E130,PESSOAL!$B$35:$S$45,MONTH($F130)+6,FALSE)*G130*24,0) -> 0 | O130: =if(OR(I130="Treinamento",I130="Pesquisa",I130="Desenvolvimento"),TRUE,FALSE) -> TRUE | P130: FALSE | Q130: Parcial
C131: =VLOOKUP(M131,'#verificação horas por projeto'!A:B,2,FALSE) -> INOV00001 | D131: INOV00001 | E131: Ana Paula Biz | F131: 45425 | G131: 0.020833333 | H131: Gestão e outros | I131: Gestão e outros | K131: Preparação e análise da exigência da HN para construção da resposta. | M131: 2018 - Retort | N131: =IF(AND(O131=TRUE,P131=TRUE), VLOOKUP($E131,PESSOAL!$B$35:$S$45,MONTH($F131)+6,FALSE)*G131*24,0) -> 0 | O131: =if(OR(I131="Treinamento",I131="Pesquisa",I131="Desenvolvimento"),TRUE,FALSE) -> FALSE | P131: TRUE | Q131: Parcial
C132: =VLOOKUP(M132,'#verificação horas por projeto'!A:B,2,FALSE) -> INOV00004 | D132: INOV00004 | E132: Ana Paula Biz | F132: 45427 | G132: 0.020833333 | H132: Desenvolvimento | I132: Desenvolvimento | K132: Determinação da IN do CorrectMax | M132: 2019 - Cicatrização | N132: =IF(AND(O132=TRUE,P132=TRUE), VLOOKUP($E132,PESSOAL!$B$35:$S$45,MONTH($F132)+6,FALSE)*G132*24,0) -> 19.175588 | O132: =if(OR(I132="Treinamento",I132="Pesquisa",I132="Desenvolvimento"),TRUE,FALSE) -> TRUE | P132: TRUE | Q132: Parcial
C133: =VLOOKUP(M133,'#verificação horas por projeto'!A:B,2,FALSE) -> INOV00001 | D133: INOV00001 | E133: Ana Paula Biz | F133: 45441 | G133: 0.0625 | H133: Desenvolvimento | I133: Desenvolvimento | K133: Avaliação física das embalagens e produto após TP. | M133: 2018 - Retort | N133: =IF(AND(O133=TRUE,P133=TRUE), VLOOKUP($E133,PESSOAL!$B$35:$S$45,MONTH($F133)+6,FALSE)*G133*24,0) -> 57.526765 | O133: =if(OR(I133="Treinamento",I133="Pesquisa",I133="Desenvolvimento"),TRUE,FALSE) -> TRUE | P133: TRUE | Q133: Parcial
... C390: =VLOOKUP(M390,'#verificação horas por projeto'!A:B,2,FALSE) -> INOV00048 | D390: INOV00048 | E390: Raissa Bellotti | F390: 45470 | G390: 0.125 | H390: Desenvolvimento | I390: Desenvolvimento | K390: Desenvolvimento de novo produto - pesquisa aprofundada recomendações nutricionais | M390: 2024 - TROPHIC JUNIOR LÍQUIDO | N390: =IF(AND(O390=TRUE,P390=TRUE), VLOOKUP($E390,PESSOAL!$B$35:$S$45,MONTH($F390)+6,FALSE)*G390*24,0) -> 0 | O390: =if(OR(I390="Treinamento",I390="Pesquisa",I390="Desenvolvimento"),TRUE,FALSE) -> TRUE | P390: FALSE | Q390: Parcial
C391: =VLOOKUP(M391,'#verificação horas por projeto'!A:B,2,FALSE) -> INOV00001 | D391: INOV00001 | E391: Ana Paula Biz | F391: 45558 | G391: 0.38541667 | H391: Gestão e outros | I391: Desenvolvimento | K391: Deslocamento para RJ - teste piloto EMBRAPA. | L391: Teste piloto EMBRAPA RJ | M391: 2018 - Retort | N391: =IF(AND(O391=TRUE,P391=TRUE), VLOOKUP($E391,PESSOAL!$B$35:$S$45,MONTH($F391)+6,FALSE)*G391*24,0) -> 390.22359 | O391: =if(OR(I391="Treinamento",I391="Pesquisa",I391="Desenvolvimento"),TRUE,FALSE) -> TRUE | P391: TRUE | Q391: Parcial
C392: =VLOOKUP(M392,'#verificação horas por projeto'!A:B,2,FALSE) -> INOV00001 | D392: INOV00001 | E392: Ana Paula Biz | F392: 45559 | G392: 0.29166667 | H392: Desenvolvimento | I392: Desenvolvimento | K392: Teste Piloto - EMBRAPA RJ | M392: 2018 - Retort | N392: =IF(AND(O392=TRUE,P392=TRUE), VLOOKUP($E392,PESSOAL!$B$35:$S$45,MONTH($F392)+6,FALSE)*G392*24,0) -> 295.30434 | O392: =if(OR(I392="Treinamento",I392="Pesquisa",I392="Desenvolvimento"),TRUE,FALSE) -> TRUE | P392: TRUE | Q392: Parcial
C393: =VLOOKUP(M393,'#verificação horas por projeto'!A:B,2,FALSE) -> INOV00001 | D393: INOV00001 | E393: Ana Paula Biz | F393: 45560 | G393: 0.29166667 | H393: Desenvolvimento | I393: Desenvolvimento | K393: Teste Piloto - EMBRAPA RJ | M393: 2018 - Retort | N393: =IF(AND(O393=TRUE,P393=TRUE), VLOOKUP($E393,PESSOAL!$B$35:$S$45,MONTH($F393)+6,FALSE)*G393*24,0) -> 295.30434 | O393: =if(OR(I393="Treinamento",I393="Pesquisa",I393="Desenvolvimento"),TRUE,FALSE) -> TRUE | P393: TRUE | Q393: Parcial
C394: =VLOOKUP(M394,'#verificação horas por projeto'!A:B,2,FALSE) -> INOV00001 | D394: INOV00001 | E394: Ana Paula Biz | F394: 45561 | G394: 0.23958333 | H394: Gestão e outros | I394: Desenvolvimento | K394: Deslocamento para Curitiba - após teste piloto EMBRAPA RJ. | L394: Teste piloto EMBRAPA RJ | M394: 2018 - Retort | N394: =IF(AND(O394=TRUE,P394=TRUE), VLOOKUP($E394,PESSOAL!$B$35:$S$45,MONTH($F394)+6,FALSE)*G394*24,0) -> 242.57142 | O394: =if(OR(I394="Treinamento",I394="Pesquisa",I394="Desenvolvimento"),TRUE,FALSE) -> TRUE | P394: TRUE | Q394: Parcial
C395: =VLOOKUP(M395,'#verificação horas por projeto'!A:B,2,FALSE) -> INOV00001 | D395: INOV00001 | E395: Ana Paula Biz | F395: 45548 | G395: 0.41666667 | H395: Desenvolvimento | I395: Desenvolvimento | K395: Double check das matérias-primas para o teste piloto - EMBRAPA RJ | M395: 2018 - Retort | N395: =IF(AND(O395=TRUE,P395=TRUE), VLOOKUP($E395,PESSOAL!$B$35:$S$45,MONTH($F395)+6,FALSE)*G395*24,0) -> 421.86334 | O395: =if(OR(I395="Treinamento",I395="Pesquisa",I395="Desenvolvimento"),TRUE,FALSE) -> TRUE | P395: TRUE | Q395: Parcial
C396: =VLOOKUP(M396,'#verificação horas por projeto'!A:B,2,FALSE) -> INOV00004 | D396: INOV00004 | E396: Ana Paula Biz | F396: 45565 | G396: 0.66666667 | H396: Pesquisa | I396: Pesquisa | K396: Análise de dados e construção de relatório de EE para o CorrectMax. | M396: 2019 - Cicatrização | N396: =IF(AND(O396=TRUE,P396=TRUE), VLOOKUP($E396,PESSOAL!$B$35:$S$45,MONTH($F396)+6,FALSE)*G396*24,0) -> 674.98134 | O396: =if(OR(I396="Treinamento",I396="Pesquisa",I396="Desenvolvimento"),TRUE,FALSE) -> TRUE | P396: TRUE | Q396: Parcial
C397: =VLOOKUP(M397,'#verificação horas por projeto'!A:B,2,FALSE) -> INOV00001 | D397: INOV00001 | E397: Ana Paula Biz | F397: 45561 | G397: 0.5625 | H397: Pesquisa | I397: Pesquisa | K397: Análise de dados e construção de relatório para inclusão de fabricante - Retort. | M397: 2018 - Retort | N397: =IF(AND(O397=TRUE,P397=TRUE), VLOOKUP($E397,PESSOAL!$B$35:$S$45,MONTH($F397)+6,FALSE)*G397*24,0) -> 569.51551 | O397: =if(OR(I397="Treinamento",I397="Pesquisa",I397="Desenvolvimento"),TRUE,FALSE) -> TRUE | P397: TRUE | Q397: Parcial
C398: =VLOOKUP(M398,'#verificação horas por projeto'!A:B,2,FALSE) -> INOV00001 | D398: INOV00001 | E398: Ana Paula Biz | F398: 45562 | G398: 0.375 | H398: Pesquisa | I398: Pesquisa | K398: Análise de dados e construção de relatório para inclusão de fabricante - Retort. | M398: 2018 - Retort | N398: =IF(AND(O398=TRUE,P398=TRUE), VLOOKUP($E398,PESSOAL!$B$35:$S$45,MONTH($F398)+6,FALSE)*G398*24,0) -> 379.677 | O398: =if(OR(I398="Treinamento",I398="Pesquisa",I398="Desenvolvimento"),TRUE,FALSE) -> TRUE | P398: TRUE | Q398: Parcial
C399: =VLOOKUP(M399,'#verificação horas por projeto'!A:B,2,FALSE) -> INOV00001 | D399: INOV00001 | E399: Ana Paula Biz | F399: 45565 | G399: 0.58333333 | H399: Pesquisa | I399: Pesquisa | K399: Análise de dados e construção de relatório para inclusão de fabricante - Retort. | M399: 2018 - Retort | N399: =IF(AND(O399=TRUE,P399=TRUE), VLOOKUP($E399,PESSOAL!$B$35:$S$45,MONTH($F399)+6,FALSE)*G399*24,0) -> 590.60867 | O399: =if(OR(I399="Treinamento",I399="Pesquisa",I399="Desenvolvimento"),TRUE,FALSE) -> TRUE | P399: TRUE | Q399: Parcial
C400: =VLOOKUP(M400,'#verificação horas por projeto'!A:B,2,FALSE) -> INOV00017 | D400: INOV00017 | E400: Ana Paula Biz | F400: 45477 | G400: 0.10416667 | H400: Desenvolvimento | I400: Desenvolvimento | K400: Análise de dados para definição da informação nutricional do PA. | M400: 2020 - Linha Trophic Soya Pó | N400: =IF(AND(O400=TRUE,P400=TRUE), VLOOKUP($E400,PESSOAL!$B$35:$S$45,MONTH($F400)+6,FALSE)*G400*24,0) -> 91.709336 | O400: =if(OR(I400="Treinamento",I400="Pesquisa",I400="Desenvolvimento"),TRUE,FALSE) -> TRUE | P400: TRUE | Q400: Parcial
C401: =VLOOKUP(M401,'#verificação horas por projeto'!A:B,2,FALSE) -> INOV00013 | D401: INOV00013 | E401: Ana Paula Biz | F401: 45475 | G401: 0.020833333 | H401: Desenvolvimento | I401: Desenvolvimento | K401: Análise dos resultados dos nutrientes para T24. | M401: 2021 - Sachê a vácuo | N401: =IF(AND(O401=TRUE,P401=TRUE), VLOOKUP($E401,PESSOAL!$B$35:$S$45,MONTH($F401)+6,FALSE)*G401*24,0) -> 18.341867 | O401: =if(OR(I401="Treinamento",I401="Pesquisa",I401="Desenvolvimento"),TRUE,FALSE) -> TRUE | P401: TRUE | Q401: Parcial
C402: =VLOOKUP(M402,'#verificação horas por projeto'!A:B,2,FALSE) -> INOV00017 | D402: INOV00017 | E402: Ana Paula Biz | F402: 45482 | G402: 0.027777778 | H402: Desenvolvimento | I402: Desenvolvimento | K402: Definição da IN do Trophic Soya Pó | M402: 2020 - Linha Trophic Soya Pó | N402: =IF(AND(O402=TRUE,P402=TRUE), VLOOKUP($E402,PESSOAL!$B$35:$S$45,MONTH($F402)+6,FALSE)*G402*24,0) -> 24.455823 | O402: =if(OR(I402="Treinamento",I402="Pesquisa",I402="Desenvolvimento"),TRUE,FALSE) -> TRUE | P402: TRUE | Q402: Parcial
C403: =VLOOKUP(M403,'#verificação horas por projeto'!A:B,2,FALSE) -> INOV00017 | D403: INOV00017 | E403: Ana Paula Biz | F403: 45483 | G403: 0.03125 | H403: Desenvolvimento | I403: Desenvolvimento | K403: Análise de dados de estudo de estabilidade para construção de informação nutricional. | M403: 2020 - Linha Trophic Soya Pó | N403: =IF(AND(O403=TRUE,P403=TRUE), VLOOKUP($E403,PESSOAL!$B$35:$S$45,MONTH($F403)+6,FALSE)*G403*24,0) -> 27.512801 | O403: =if(OR(I403="Treinamento",I403="Pesquisa",I403="Desenvolvimento"),TRUE,FALSE) -> TRUE | P403: TRUE | Q403: Parcial
C404: =VLOOKUP(M404,'#verificação horas por projeto'!A:B,2,FALSE) -> INOV00017 | D404: INOV00017 | E404: Ana Paula Biz | F404: 45483 | G404: 0.16666667 | H404: Desenvolvimento | I404: Desenvolvimento | K404: Análise de dados de estudo de estabilidade e elaboração de relatório de estudo de estabilidade. | M404: 2020 - Linha Trophic Soya Pó | N404: =IF(AND(O404=TRUE,P404=TRUE), VLOOKUP($E404,PESSOAL!$B$35:$S$45,MONTH($F404)+6,FALSE)*G404*24,0) -> 146.73494 | O404: =if(OR(I404="Treinamento",I404="Pesquisa",I404="Desenvolvimento"),TRUE,FALSE) -> TRUE | P404: TRUE | Q404: Parcial
C405: =VLOOKUP(M405,'#verificação horas por projeto'!A:B,2,FALSE) -> INOV00001 | D405: INOV00001 | E405: Ana Paula Biz | F405: 45484 | G405: 0.020833333 | H405: Pesquisa | I405: Pesquisa | K405: Avaliação de amostras sobre a qualidade e tipo de bico em pouch retort. | M405: 2018 - Retort | N405: =IF(AND(O405=TRUE,P405=TRUE), VLOOKUP($E405,PESSOAL!$B$35:$S$45,MONTH($F405)+6,FALSE)*G405*24,0) -> 18.341867 | O405: =if(OR(I405="Treinamento",I405="Pesquisa",I405="Desenvolvimento"),TRUE,FALSE) -> TRUE | P405: TRUE | Q405: Parcial
C406: =VLOOKUP(M406,'#verificação horas por projeto'!A:B,2,FALSE) -> INOV00001 | D406: INOV00001 | E406: Ana Paula Biz | F406: 45484 | G406: 0.125 | H406: Pesquisa | I406: Pesquisa | K406: Avaliação de amostras sobre a qualidade e tipo de bico em pouch retort. | M406: 2018 - Retort | N406: =IF(AND(O406=TRUE,P406=TRUE), VLOOKUP($E406,PESSOAL!$B$35:$S$45,MONTH($F406)+6,FALSE)*G406*24,0) -> 110.0512 | O406: =if(OR(I406="Treinamento",I406="Pesquisa",I406="Desenvolvimento"),TRUE,FALSE) -> TRUE | P406: TRUE | Q406: Parcial
... C435: =VLOOKUP(M435,'#verificação horas por projeto'!A:B,2,FALSE) -> INOV00001 | D435: INOV00001 | E435: Alyne Alves Nunes Oliveira | F435: 45518 | G435: 0.625 | H435: Desenvolvimento | I435: Desenvolvimento | K435: Alinhamento com a equipe teste Latco | M435: 2018 - Retort | N435: =IF(AND(O435=TRUE,P435=TRUE), VLOOKUP($E435,PESSOAL!$B$35:$S$45,MONTH($F435)+6,FALSE)*G435*24,0) -> 951.18358 | O435: =if(OR(I435="Treinamento",I435="Pesquisa",I435="Desenvolvimento"),TRUE,FALSE) -> TRUE | P435: TRUE | Q435: Parcial
C436: =VLOOKUP(M436,'#verificação horas por projeto'!A:B,2,FALSE) -> INOV00001 | D436: INOV00001 | E436: Alyne Alves Nunes Oliveira | F436: 45518 | G436: 0.6875 | H436: Gestão e outros | I436: Desenvolvimento | K436: Trâmites logísticos teste industrial Latco | L436: Teste industrial Latco | M436: 2018 - Retort | N436: =IF(AND(O436=TRUE,P436=TRUE), VLOOKUP($E436,PESSOAL!$B$35:$S$45,MONTH($F436)+6,FALSE)*G436*24,0) -> 1046.3019 | O436: =if(OR(I436="Treinamento",I436="Pesquisa",I436="Desenvolvimento"),TRUE,FALSE) -> TRUE | P436: TRUE | Q436: Parcial
C437: =VLOOKUP(M437,'#verificação horas por projeto'!A:B,2,FALSE) -> INOV00001 | D437: INOV00001 | E437: Alyne Alves Nunes Oliveira | F437: 45519 | G437: 0.625 | H437: Gestão e outros | I437: Gestão e outros | K437: Planejamento teste industrial Latco | M437: 2018 - Retort | N437: =IF(AND(O437=TRUE,P437=TRUE), VLOOKUP($E437,PESSOAL!$B$35:$S$45,MONTH($F437)+6,FALSE)*G437*24,0) -> 0 | O437: =if(OR(I437="Treinamento",I437="Pesquisa",I437="Desenvolvimento"),TRUE,FALSE) -> FALSE | P437: TRUE | Q437: Parcial
C438: =VLOOKUP(M438,'#verificação horas por projeto'!A:B,2,FALSE) -> INOV00001 | D438: INOV00001 | E438: Alyne Alves Nunes Oliveira | F438: 45520 | G438: 0.41666667 | H438: Desenvolvimento | I438: Desenvolvimento | K438: Ajuste de formulação dieta UTI - melhoria de viscosidade | M438: 2018 - Retort | N438: =IF(AND(O438=TRUE,P438=TRUE), VLOOKUP($E438,PESSOAL!$B$35:$S$45,MONTH($F438)+6,FALSE)*G438*24,0) -> 634.12238 | O438: =if(OR(I438="Treinamento",I438="Pesquisa",I438="Desenvolvimento"),TRUE,FALSE) -> TRUE | P438: TRUE | Q438: Parcial
C439: =VLOOKUP(M439,'#verificação horas por projeto'!A:B,2,FALSE) -> INOV00001 | D439: INOV00001 | E439: Alyne Alves Nunes Oliveira | F439: 45524 | G439: 0.70833333 | H439: Desenvolvimento | I439: Desenvolvimento | K439: Teste industrial Latco: dieta HH | M439: 2018 - Retort | N439: =IF(AND(O439=TRUE,P439=TRUE), VLOOKUP($E439,PESSOAL!$B$35:$S$45,MONTH($F439)+6,FALSE)*G439*24,0) -> 1078.0081 | O439: =if(OR(I439="Treinamento",I439="Pesquisa",I439="Desenvolvimento"),TRUE,FALSE) -> TRUE | P439: TRUE | Q439: Parcial
C440: =VLOOKUP(M440,'#verificação horas por projeto'!A:B,2,FALSE) -> INOV00001 | D440: INOV00001 | E440: Alyne Alves Nunes Oliveira | F440: 45525 | G440: 0.70833333 | H440: Desenvolvimento | I440: Desenvolvimento | K440: Teste industrial Latco: dieta HNcF | M440: 2018 - Retort | N440: =IF(AND(O440=TRUE,P440=TRUE), VLOOKUP($E440,PESSOAL!$B$35:$S$45,MONTH($F440)+6,FALSE)*G440*24,0) -> 1078.0081 | O440: =if(OR(I440="Treinamento",I440="Pesquisa",I440="Desenvolvimento"),TRUE,FALSE) -> TRUE | P440: TRUE | Q440: Parcial
C441: =VLOOKUP(M441,'#verificação horas por projeto'!A:B,2,FALSE) -> INOV00001 | D441: INOV00001 | E441: Alyne Alves Nunes Oliveira | F441: 45526 | G441: 0.70833333 | H441: Desenvolvimento | I441: Desenvolvimento | K441: Teste industrial Latco: dieta HNcF | M441: 2018 - Retort | N441: =IF(AND(O441=TRUE,P441=TRUE), VLOOKUP($E441,PESSOAL!$B$35:$S$45,MONTH($F441)+6,FALSE)*G441*24,0) -> 1078.0081 | O441: =if(OR(I441="Treinamento",I441="Pesquisa",I441="Desenvolvimento"),TRUE,FALSE) -> TRUE | P441: TRUE | Q441: Parcial
C442: =VLOOKUP(M442,'#verificação horas por projeto'!A:B,2,FALSE) -> INOV00001 | D442: INOV00001 | E442: Alyne Alves Nunes Oliveira | F442: 45559 | G442: 0.41666667 | H442: Desenvolvimento | I442: Desenvolvimento | K442: Teste piloto embrapa: HN e UTI | M442: 2018 - Retort | N442: =IF(AND(O442=TRUE,P442=TRUE), VLOOKUP($E442,PESSOAL!$B$35:$S$45,MONTH($F442)+6,FALSE)*G442*24,0) -> 664.31869 | O442: =if(OR(I442="Treinamento",I442="Pesquisa",I442="Desenvolvimento"),TRUE,FALSE) -> TRUE | P442: TRUE | Q442: Parcial
C443: =VLOOKUP(M443,'#verificação horas por projeto'!A:B,2,FALSE) -> INOV00001 | D443: INOV00001 | E443: Alyne Alves Nunes Oliveira | F443: 45559 | G443: 0.34375 | H443: Desenvolvimento | I443: Desenvolvimento | K443: Teste piloto embrapa: HN e UTI | M443: 2018 - Retort | N443: =IF(AND(O443=TRUE,P443=TRUE), VLOOKUP($E443,PESSOAL!$B$35:$S$45,MONTH($F443)+6,FALSE)*G443*24,0) -> 548.06292 | O443: =if(OR(I443="Treinamento",I443="Pesquisa",I443="Desenvolvimento"),TRUE,FALSE) -> TRUE | P443: TRUE | Q443: Parcial
C444: =VLOOKUP(M444,'#verificação horas por projeto'!A:B,2,FALSE) -> INOV00001 | D444: INOV00001 | E444: Alyne Alves Nunes Oliveira | F444: 45560 | G444: 0.072916667 | H444: Gestão e outros | I444: Desenvolvimento | K444: Trâmites logísticos teste piloto Embrapa | L444: Teste piloto Embrapa | M444: 2018 - Retort | N444: =IF(AND(O444=TRUE,P444=TRUE), VLOOKUP($E444,PESSOAL!$B$35:$S$45,MONTH($F444)+6,FALSE)*G444*24,0) -> 116.25577 | O444: =if(OR(I444="Treinamento",I444="Pesquisa",I444="Desenvolvimento"),TRUE,FALSE) -> TRUE | P444: TRUE | Q444: Parcial
C445: =VLOOKUP(M445,'#verificação horas por projeto'!A:B,2,FALSE) -> INOV00001 | D445: INOV00001 | E445: Alyne Alves Nunes Oliveira | F445: 45560 | G445: 0.083333333 | H445: Desenvolvimento | I445: Desenvolvimento | K445: Elaboração relatório teste piloto Embrapa | M445: 2018 - Retort | N445: =IF(AND(O445=TRUE,P445=TRUE), VLOOKUP($E445,PESSOAL!$B$35:$S$45,MONTH($F445)+6,FALSE)*G445*24,0) -> 132.86374 | O445: =if(OR(I445="Treinamento",I445="Pesquisa",I445="Desenvolvimento"),TRUE,FALSE) -> TRUE | P445: TRUE | Q445: Parcial
C446: =VLOOKUP(M446,'#verificação horas por projeto'!A:B,2,FALSE) -> INOV00001 | D446: INOV00001 | E446: Alyne Alves Nunes Oliveira | F446: 45565 | G446: 0.020833333 | H446: Desenvolvimento | I446: Desenvolvimento | K446: Avaliação dos resultados de T0 das vitaminas da dieta HNcF (Teste Industrial) | M446: 2018 - Retort | N446: =IF(AND(O446=TRUE,P446=TRUE), VLOOKUP($E446,PESSOAL!$B$35:$S$45,MONTH($F446)+6,FALSE)*G446*24,0) -> 33.215934 | O446: =if(OR(I446="Treinamento",I446="Pesquisa",I446="Desenvolvimento"),TRUE,FALSE) -> TRUE | P446: TRUE | Q446: Parcial
C447: =VLOOKUP(M447,'#verificação horas por projeto'!A:B,2,FALSE) -> INOV00041 | D447: INOV00041 | E447: Alyne Alves Nunes Oliveira | F447: 45552 | G447: 0.083333333 | H447: Pesquisa | I447: Pesquisa | K447: Estudo de novas MP + contato fornecedores | M447: 2023 - PROTEÍNA LÍQUIDA | N447: =IF(AND(O447=TRUE,P447=TRUE), VLOOKUP($E447,PESSOAL!$B$35:$S$45,MONTH($F447)+6,FALSE)*G447*24,0) -> 132.86374 | O447: =if(OR(I447="Treinamento",I447="Pesquisa",I447="Desenvolvimento"),TRUE,FALSE) -> TRUE | P447: TRUE | Q447: Parcial
C448: =VLOOKUP(M448,'#verificação horas por projeto'!A:B,2,FALSE) -> INOV00001 | D448: INOV00001 | E448: Alyne Alves Nunes Oliveira | F448: 45545 | G448: 0.041666667 | H448: Desenvolvimento | I448: Desenvolvimento | K448: Alinhamento teste piloto Embrapa | M448: 2018 - Retort | N448: =IF(AND(O448=TRUE,P448=TRUE), VLOOKUP($E448,PESSOAL!$B$35:$S$45,MONTH($F448)+6,FALSE)*G448*24,0) -> 66.431869 | O448: =if(OR(I448="Treinamento",I448="Pesquisa",I448="Desenvolvimento"),TRUE,FALSE) -> TRUE | P448: TRUE | Q448: Parcial
C449: =VLOOKUP(M449,'#verificação horas por projeto'!A:B,2,FALSE) -> INOV00001 | D449: INOV00001 | E449: Alyne Alves Nunes Oliveira | F449: 45538 | G449: 0.0625 | H449: Desenvolvimento | I449: Desenvolvimento | K449: Avaliação dos resultados de análise de distribuição de partículas das dietas HNcF e HH | M449: 2018 - Retort | N449: =IF(AND(O449=TRUE,P449=TRUE), VLOOKUP($E449,PESSOAL!$B$35:$S$45,MONTH($F449)+6,FALSE)*G449*24,0) -> 99.647803 | O449: =if(OR(I449="Treinamento",I449="Pesquisa",I449="Desenvolvimento"),TRUE,FALSE) -> TRUE | P449: TRUE | Q449: Parcial
C450: =VLOOKUP(M450,'#verificação horas por projeto'!A:B,2,FALSE) -> INOV00001 | D450: INOV00001 | E450: Alyne Alves Nunes Oliveira | F450: 45553 | G450: 0.020833333 | H450: Pesquisa | I450: Pesquisa | K450: Contato com fornecedor entendimento composição de proteína alternativa para o retort | M450: 2018 - Retort | N450: =IF(AND(O450=TRUE,P450=TRUE), VLOOKUP($E450,PESSOAL!$B$35:$S$45,MONTH($F450)+6,FALSE)*G450*24,0) -> 33.215934 | O450: =if(OR(I450="Treinamento",I450="Pesquisa",I450="Desenvolvimento"),TRUE,FALSE) -> TRUE | P450: TRUE | Q450: Parcial
C451: =VLOOKUP(M451,'#verificação horas por projeto'!A:B,2,FALSE) -> INOV00001 | D451: INOV00001 | E451: Alyne Alves Nunes Oliveira | F451: 45540 | G451: 0.083333333 | H451: Desenvolvimento | I451: Desenvolvimento | K451: Ajuste de formulação diet HN: estabilização da fórmula | M451: 2018 - Retort | N451: =IF(AND(O451=TRUE,P451=TRUE), VLOOKUP($E451,PESSOAL!$B$35:$S$45,MONTH($F451)+6,FALSE)*G451*24,0) -> 132.86374 | O451: =if(OR(I451="Treinamento",I451="Pesquisa",I451="Desenvolvimento"),TRUE,FALSE) -> TRUE | P451: TRUE | Q451: Parcial
C452: =VLOOKUP(M452,'#verificação horas por projeto'!A:B,2,FALSE) -> INOV00037 | D452: INOV00037 | E452: Ana Claudia Zanini | F452: 45474 | G452: 0.16666667 | H452: Pesquisa | I452: Pesquisa | K452: congresso Ganepão - atualizações paciente UTI, Oncologia, Pesquisa clínica e estudos de casos | M452: 2023 - PESQUISA CLÍNICA - IMMAX | N452: =IF(AND(O452=TRUE,P452=TRUE), VLOOKUP($E452,PESSOAL!$B$35:$S$45,MONTH($F452)+6,FALSE)*G452*24,0) -> 196.21232 | O452: =if(OR(I452="Treinamento",I452="Pesquisa",I452="Desenvolvimento"),TRUE,FALSE) -> TRUE | P452: TRUE | Q452: Parcial
C453: =VLOOKUP(M453,'#verificação horas por projeto'!A:B,2,FALSE) -> INOV00001 | D453: INOV00001 | E453: Ana Claudia Zanini | F453: 45475 | G453: 0.125 | H453: Pesquisa | I453: Pesquisa | K453: congresso Ganepão - atualizações paciente UTI, Oncologia, Pesquisa clínica e estudos de casos | M453: 2018 - Retort | N453: =IF(AND(O453=TRUE,P453=TRUE), VLOOKUP($E453,PESSOAL!$B$35:$S$45,MONTH($F453)+6,FALSE)*G453*24,0) -> 147.15924 | O453: =if(OR(I453="Treinamento",I453="Pesquisa",I453="Desenvolvimento"),TRUE,FALSE) -> TRUE | P453: TRUE | Q453: Parcial
C454: =VLOOKUP(M454,'#verificação horas por projeto'!A:B,2,FALSE) -> INOV00035 | D454: INOV00035 | E454: Ana Claudia Zanini | F454: 45476 | G454: 0.20833333 | H454: Pesquisa | I454: Pesquisa | K454: congresso Ganepão - atualizações paciente UTI, Oncologia, Pesquisa clínica e estudos de casos | M454: 2023 - PESQUISA CLÍNICA - CICATRIZAÇÃO | N454: =IF(AND(O454=TRUE,P454=TRUE), VLOOKUP($E454,PESSOAL!$B$35:$S$45,MONTH($F454)+6,FALSE)*G454*24,0) -> 245.2654 | O454: =if(OR(I454="Treinamento",I454="Pesquisa",I454="Desenvolvimento"),TRUE,FALSE) -> TRUE | P454: TRUE | Q454: Parcial
C455: =VLOOKUP(M455,'#verificação horas por projeto'!A:B,2,FALSE) -> INOV00041 | D455: INOV00041 | E455: Ana Claudia Zanini | F455: 45477 | G455: 0.125 | H455: Pesquisa | I455: Pesquisa | K455: congresso Ganepão - atualizações paciente UTI, Oncologia, Pesquisa clínica e estudos de casos | M455: 2023 - PROTEÍNA LÍQUIDA | N455: =IF(AND(O455=TRUE,P455=TRUE), VLOOKUP($E455,PESSOAL!$B$35:$S$45,MONTH($F455)+6,FALSE)*G455*24,0) -> 147.15924 | O455: =if(OR(I455="Treinamento",I455="Pesquisa",I455="Desenvolvimento"),TRUE,FALSE) -> TRUE | P455: TRUE | Q455: Parcial
C456: =VLOOKUP(M456,'#verificação horas por projeto'!A:B,2,FALSE) -> INOV00024 | D456: INOV00024 | E456: Ana Claudia Zanini | F456: 45478 | G456: 0.16666667 | H456: Pesquisa | I456: Pesquisa | K456: congresso Ganepão - atualizações paciente UTI, Oncologia, Pesquisa clínica e estudos de casos | M456: 2021 - Estudo de Caso | N456: =IF(AND(O456=TRUE,P456=TRUE), VLOOKUP($E456,PESSOAL!$B$35:$S$45,MONTH($F456)+6,FALSE)*G456*24,0) -> 196.21232 | O456: =if(OR(I456="Treinamento",I456="Pesquisa",I456="Desenvolvimento"),TRUE,FALSE) -> TRUE | P456: TRUE | Q456: Parcial
... C594: =VLOOKUP(M594,'#verificação horas por projeto'!A:B,2,FALSE) -> INOV00001 | D594: INOV00001 | E594: Raissa Bellotti | F594: 45512 | G594: 0.041666667 | H594: Pesquisa | I594: Pesquisa | K594: Prospecção de locais para pesquisa com novo produto Prodiet | M594: 2018 - Retort | N594: =IF(AND(O594=TRUE,P594=TRUE), VLOOKUP($E594,PESSOAL!$B$35:$S$45,MONTH($F594)+6,FALSE)*G594*24,0) -> 45.754859 | O594: =if(OR(I594="Treinamento",I594="Pesquisa",I594="Desenvolvimento"),TRUE,FALSE) -> TRUE | P594: TRUE | Q594: Parcial
C595: =VLOOKUP(M595,'#verificação horas por projeto'!A:B,2,FALSE) -> INOV00048 | D595: INOV00048 | E595: Raissa Bellotti | F595: 45512 | G595: 0.125 | H595: Desenvolvimento | I595: Desenvolvimento | K595: Desenvolvimento de novo produto - elaboração briefing | L595: Desenvolvimento de novo produto - briefing | M595: 2024 - TROPHIC JUNIOR LÍQUIDO | N595: =IF(AND(O595=TRUE,P595=TRUE), VLOOKUP($E595,PESSOAL!$B$35:$S$45,MONTH($F595)+6,FALSE)*G595*24,0) -> 0 | O595: =if(OR(I595="Treinamento",I595="Pesquisa",I595="Desenvolvimento"),TRUE,FALSE) -> TRUE | P595: FALSE | Q595: Parcial
C596: =VLOOKUP(M596,'#verificação horas por projeto'!A:B,2,FALSE) -> INOV00024 | D596: INOV00024 | E596: Raissa Bellotti | F596: 45513 | G596: 0.041666667 | H596: Pesquisa | I596: Pesquisa | K596: Alinhamento de desenvolvimento de pesquisa com profissionais - | M596: 2021 - Estudo de Caso | N596: =IF(AND(O596=TRUE,P596=TRUE), VLOOKUP($E596,PESSOAL!$B$35:$S$45,MONTH($F596)+6,FALSE)*G596*24,0) -> 45.754859 | O596: =if(OR(I596="Treinamento",I596="Pesquisa",I596="Desenvolvimento"),TRUE,FALSE) -> TRUE | P596: TRUE | Q596: Parcial
C597: =VLOOKUP(M597,'#verificação horas por projeto'!A:B,2,FALSE) -> INOV00024 | D597: INOV00024 | E597: Raissa Bellotti | F597: 45513 | G597: 0.041666667 | H597: Pesquisa | I597: Pesquisa | K597: Alinhamento de desenvolvimento de pesquisa com profissionais | M597: 2021 - Estudo de Caso | N597: =IF(AND(O597=TRUE,P597=TRUE), VLOOKUP($E597,PESSOAL!$B$35:$S$45,MONTH($F597)+6,FALSE)*G597*24,0) -> 45.754859 | O597: =if(OR(I597="Treinamento",I597="Pesquisa",I597="Desenvolvimento"),TRUE,FALSE) -> TRUE | P597: TRUE | Q597: Parcial
C598: =VLOOKUP(M598,'#verificação horas por projeto'!A:B,2,FALSE) -> #N/A | D598: INOV00051 | E598: Raissa Bellotti | F598: 45513 | G598: 0.041666667 | H598: Pesquisa | I598: Pesquisa | K598: Alinhamento de desenvolvimento de pesquisa com profissionais | M598: 2024 - PESQUISA DE APLICAÇÃO TROPHIC RTH | N598: =IF(AND(O598=TRUE,P598=TRUE), VLOOKUP($E598,PESSOAL!$B$35:$S$45,MONTH($F598)+6,FALSE)*G598*24,0) -> 0 | O598: =if(OR(I598="Treinamento",I598="Pesquisa",I598="Desenvolvimento"),TRUE,FALSE) -> TRUE | P598: FALSE | Q598: Parcial
C599: =VLOOKUP(M599,'#verificação horas por projeto'!A:B,2,FALSE) -> INOV00001 | D599: INOV00001 | E599: Raissa Bellotti | F599: 45518 | G599: 0.041666667 | H599: Pesquisa | I599: Pesquisa | K599: Prospecção de locais para pesquisa com novo produto Prodiet | M599: 2018 - Retort | N599: =IF(AND(O599=TRUE,P599=TRUE), VLOOKUP($E599,PESSOAL!$B$35:$S$45,MONTH($F599)+6,FALSE)*G599*24,0) -> 45.754859 | O599: =if(OR(I599="Treinamento",I599="Pesquisa",I599="Desenvolvimento"),TRUE,FALSE) -> TRUE | P599: TRUE | Q599: Parcial
C600: =VLOOKUP(M600,'#verificação horas por projeto'!A:B,2,FALSE) -> #N/A | D600: INOV00050 | E600: Raissa Bellotti | F600: 45518 | G600: 0.083333333 | H600: Pesquisa | I600: Pesquisa | K600: Revisão escrita artigo | M600: 2024 - PESQUISA DE APLICAÇÃO MICROBIOLOGIA | N600: =IF(AND(O600=TRUE,P600=TRUE), VLOOKUP($E600,PESSOAL!$B$35:$S$45,MONTH($F600)+6,FALSE)*G600*24,0) -> 0 | O600: =if(OR(I600="Treinamento",I600="Pesquisa",I600="Desenvolvimento"),TRUE,FALSE) -> TRUE | P600: FALSE | Q600: Parcial
C601: =VLOOKUP(M601,'#verificação horas por projeto'!A:B,2,FALSE) -> INOV00048 | D601: INOV00048 | E601: Raissa Bellotti | F601: 45523 | G601: 0.083333333 | H601: Desenvolvimento | I601: Desenvolvimento | K601: Desenvolvimento de novo produto - elaboração briefing | L601: Desenvolvimento de novo produto - briefing | M601: 2024 - TROPHIC JUNIOR LÍQUIDO | N601: =IF(AND(O601=TRUE,P601=TRUE), VLOOKUP($E601,PESSOAL!$B$35:$S$45,MONTH($F601)+6,FALSE)*G601*24,0) -> 0 | O601: =if(OR(I601="Treinamento",I601="Pesquisa",I601="Desenvolvimento"),TRUE,FALSE) -> TRUE | P601: FALSE | Q601: Parcial
C602: =VLOOKUP(M602,'#verificação horas por projeto'!A:B,2,FALSE) -> INOV00024 | D602: INOV00024 | E602: Raissa Bellotti | F602: 45524 | G602: 0.041666667 | H602: Pesquisa | I602: Pesquisa | K602: Alinhamento de desenvolvimento de pesquisa com profissionais | M602: 2021 - Estudo de Caso | N602: =IF(AND(O602=TRUE,P602=TRUE), VLOOKUP($E602,PESSOAL!$B$35:$S$45,MONTH($F602)+6,FALSE)*G602*24,0) -> 45.754859 | O602: =if(OR(I602="Treinamento",I602="Pesquisa",I602="Desenvolvimento"),TRUE,FALSE) -> TRUE | P602: TRUE | Q602: Parcial
C603: =VLOOKUP(M603,'#verificação horas por projeto'!A:B,2,FALSE) -> #N/A | D603: INOV00051 | E603: Raissa Bellotti | F603: 45525 | G603: 0.041666667 | H603: Pesquisa | I603: Pesquisa | K603: Alinhamento de desenvolvimento de pesquisa | M603: 2024 - PESQUISA DE APLICAÇÃO TROPHIC RTH | N603: =IF(AND(O603=TRUE,P603=TRUE), VLOOKUP($E603,PESSOAL!$B$35:$S$45,MONTH($F603)+6,FALSE)*G603*24,0) -> 0 | O603: =if(OR(I603="Treinamento",I603="Pesquisa",I603="Desenvolvimento"),TRUE,FALSE) -> TRUE | P603: FALSE | Q603: Parcial
C604: =VLOOKUP(M604,'#verificação horas por projeto'!A:B,2,FALSE) -> INOV00047 | D604: INOV00047 | E604: Raissa Bellotti | F604: 45526 | G604: 0.083333333 | H604: Desenvolvimento | I604: Desenvolvimento | K604: Desenvolvimento de novo produto - aprofundamento recomendações nutricionais | L604: Aprofundamento recomendações nutricionais | M604: 2024 - PEPTÍDICA JUNIOR LÍQUIDA | N604: =IF(AND(O604=TRUE,P604=TRUE), VLOOKUP($E604,PESSOAL!$B$35:$S$45,MONTH($F604)+6,FALSE)*G604*24,0) -> 0 | O604: =if(OR(I604="Treinamento",I604="Pesquisa",I604="Desenvolvimento"),TRUE,FALSE) -> TRUE | P604: FALSE | Q604: Parcial
...

Sheet Tabela dinâmica 2
F2: Ok
F3: Ok
F4: Ok
F6: Ok
F7: Ok
F8: Ok
F10: Ok
F11: Ok
F12: Ok
F14: Ok
F15: Ok
F16: Ok
... F42: Ok
F43: =20/24 -> 0.83333333 | G43: =F43-D43 -> -1
F44: =9/24 -> 0.375 | G44: =F44-D44 -> -2.0104167
F46: Ok
F47: Ok
F49: Ok
F51: =22/24 -> 0.91666667 | G51: =F51-D51 -> -1
F52: Ok
F54: Ok
F55: Ok
F57: Ok
F59: Ok
F61: Ok
F62: Ok
F63: Ok
F64: Ok
F65: Ok

Sheet MILESTONES
B2: PRODIET
B3: Pesquisa ,Desenvolvimento & Inovação
B4: Formulário de PD&I - Ano2024
B5: -preencher somente os campos sombreados (cinza)
B8: Dossiê do projeto | E8: Durante esta etapa, é importante definir um objetivo a ser alcançado. (i) É possível ter vários objetivos em cada etapa. (ii) É recomendável descrevê-la com o máximo de detalhes possível. | G8: Uma data estimada que atualizará após etapa concluída. Não utilizar: - Atual, em andamento ou qualquer outra observação; (i) precisamos de números (datas) que comprovem o andamento ou não projeto. (ii) utilizar a coluna Histórico para acrescentar informações dos motivos para tal data.
B9: Etapas e Milestones
B11: Projeto | C11: Etapa | D11: Principais atividades | E11: Milestones | F11: Data inicial | G11: Data conclusão | H11: Histórico e observações do gestor
B12: Spray dryer | C12: Pesquisa de Copacker | D12: Buscar parceiros que possam tercerizar a produção de um blend de Pt+Gord+Ch com a finalidade de reduzir custo de gordura em pó, e melhorar solubilidade da dieta. | E12: Parceiro demostrar interesse na parceria e disponibilidade para testes pilotos | F12: 44621 | G12: 44713
B13: Spray dryer | C13: Autorização da diretoria | D13: Apresentar objetivo do projeto para diretoria | E13: Ter autorização extra budget para seguir com o projeto ainda em 2022 | F13: 44621 | G13: 44652
B14: Spray dryer | C14: Realizar teste de bancada | D14: Realizar testes de bancada junto com o fornecedor | E14: Obter bons resultados nos testes de bancada | F14: 44652 | G14: 44774
B15: Spray dryer | C15: Realizar teste industrial | D15: Realizar testes industriais junto com o fornecedor | E15: Garantir no mínimo os bons resultados obtido em testes de bancada | F15: 45231 | G15: 44958
B16: Spray dryer | C16: Teste de bancada | D16: Aplicar o blend obtido no teste piloto nos produtos Trophic Fiber e Basic Enteral em escala laboratorial | E16: Obter umproduto final com pó fluido, boa dissolução, sem alteração sensorial e com melhora de passagem pelo equipo | F16: 44958 | G16: 45017
B17: Spray dryer | C17: Avaliação de custos | D17: Incluir todos os custos no Simulador | E17: Obter resultados favoráveis a redução de custos | F17: 44958 | G17: 45047 | H17: Custo de industrialização inviabilizou o projeto
B18: Spray dryer | C18: Business case | D18: Apresentar o projeto para Banca Business case | F18: Stand by
B19: Spray dryer | C19: Produção | D19: Aplicar o projeto em escala de produção | F19: Stand by
B20: Spray dryer | C20: Prospecção de novos parceiros | D20: Retomar a busca por parceiros, fornecedores, Universidades que tornem o projeto viável | E20: Desenvolver protocolo de pesquisa junto com Professor Alvaro/PUCPR | F20: 45139 | G20: Em andamento | H20: Em dez/23 foi apontado melhorias no contrato. Assinatura do contrato está em andamento, aguardando ajustes mencionados
B21: TETRA PAK SF | C21: Desenvolvimento da tampa | D21: Testes de bancada utilizando diferentes tampas conectadas à embalagem cartonada de 1L para verificar a possibilidade de administração | E21: Verificado que todas as tampas tiveram vazamento do produto e não foi possível realizar a administração | F21: 44593 | G21: 44593
B22: TETRA PAK SF | C22: Desenvolvimento da tampa | D22: Teste de bancada utilizando diferentes tampas e com selos de vedação, para evitar vazamento | E22: Modelo da tampa Biomédica/Nutrimed não apresentou vazamento com o selo da Gerladiscos de 2 mm | F22: 44682 | G22: 44682
B23: TETRA PAK SF | C23: Testes de Hanger | D23: Testes em laboratório com diferentes fornecedores de Hang Tabs para embalagem de 1L | E23: Avaliação de Hang-Tabs após testes. Aprovação de Hang-Tab da NeoBrasil | F23: 44805 | G23: 44805
B24: TETRA PAK SF | C24: Testes de Aplicação | D24: Testes de aplicação em linha industrial de tampas TetraPak, sem cutter, de diferentes fornecedores. Testes realizados na DAUS/GO | E24: 2 Fornecedores aprovados. 1 Fornecedor reprovado, por obstruir a canaleta de aplicação | F24: 44866 | G24: 44866
B25: TETRA PAK SF | C25: Testes de Aplicação | D25: Testes em laboratório de administração de produto utilizando tampas sem cutter, tampa impressa 3D e adaptador Biomédica com selo | E25: Tampa impressa e modelos de tampas sem cutter tiveram vazamentos (Esses modelos serão revistos). Adaptador Biomédica com selo de vedação administrou o produto sem vazamentos (Aprovado para próximas etapas). | F25: 44866 | G25: 44866
B26: TETRA PAK SF | C26: Testes de Hanger | D26: Testes em laboratório de administração de produto com Hang-Tab NeoBrasil, gravitacional e utilizando Bomba de Infusão | E26: Hang-Tab aprovado após testes de aplicação | F26: 44896 | G26: 44896
B27: TETRA PAK SF | C27: Bico/ventosa adaptadora | D27: Avaliação de viabilidade de aplicação de um bico diretamente a embalagem TetraPak sem tampa, para SF Verdadeiro | E27: Aguardando chegada de amostras | F27: 44927 | G27: em andamento
B28: TETRA PAK SF | C28: Aceitação comercial | D28: Avaliação de aceitabilidade técnica e comercial do adaptador Biomédica com selo em aplicação real (Ibranutro) | E28: Compra de insumos em quantidade para teste realizada. Aguardando montagem de adaptador + selo | F28: 44927 | G28: em andamento
B29: TETRA PAK SF | C29: Material de comunicação Científica | D29: Pesquisa científica para desenvolvimento do material de comunicação científico | E29: Enviado para MKT | F29: 45231 | G29: 45231
B30: PEPTIMAX JUNIOR | C30: Pesquisa Científica e desenvolvimento | D30: Levantamento de editais de licitação; concorrentes mercado | E30: Buscar materias de consulta em editais de licitação e concorrentes para desenvolvimento do Briefing | F30: 45465 | G30: 45495
B31: PEPTIMAX JUNIOR | D31: Levantamento de literatura/artigos/Guidelines | E31: Buscar materias de consulta em guidelines e diretrizes nacionais e internacionais para desenvolvimento do Briefing | F31: 45495 | G31: 45557
B32: PEPTIMAX JUNIOR | D32: Rounds Científicos | E32: Definição da formulação nutricional | F32: 45345 | G32: 45405
B33: PEPTIMAX JUNIOR | C33: Kick off | D33: Kick off com toda equipe técnica, comercial e marketing, para considerações no Briefing | E33: Fechamento do Briefing | F33: 45435 | G33: 45466
B34: PEPTIMAX JUNIOR | C34: Desenvolvimento da formulação | D34: Elaboração de formulações variadas para teste de bancada | E34: Seguindo o briefing do Científico foram formuladas algumas opções para seguir para TB | F34: 45108 | G34: Em andamento | H34: Permanece em andamento devido a avaliação de diferentes fornecedores de WPH
B35: PEPTIMAX JUNIOR | C35: Desenvolvimento da formulação | D35: Busca de WPH com baixo teor de lactose | E35: Contato com fornecedores para prospectar a nova MP | F35: 45139 | G35: Em andamento | H35: Em dez/23 a propscção e avaliação de fornecedores e MPs permanece em andmaneto, aguardando amostras para execução dos testes de bancada
B36: PEPTIMAX IBD | C36: Pesquisa científica e desenvolvimento | D36: Levantamento de descritivos de editais, levantamentos de referências sobre a composição nutricional, entendimento das MPs necessárias e de indicação de uso do produto | E36: Compreender as exigências de composição nutricional dos descritivos de licitações correlacionando com o desenho nutricional de acordo com estudos e recomendações | F36: 45231 | G36: 45261
B37: Proteína Líquida | C37: Pesquisa Científica e desenvolvimento | D37: Levantamento de literatura/artigos/Guidelines; concorrentes mercado | E37: Buscar materias de consulta em guidelines e diretrizes nacionais e internacionais, bm como concorrentes para desenvolvimento do Briefing | F37: 45314 | G37: 45435
B38: Proteína Líquida | C38: Pesquisa Científica e desenvolvimento | D38: Rounds Científicos | E38: Definir a formulação nutricional após discussões cientificas | F38: 45374 | G38: 45435
B39: Proteína Líquida | C39: Kick off | D39: Kick off com toda equipe técnica, comercial e marketing, para considerações no Briefing | E39: Elaborar briefing após considerações da area tecnica | F39: 45435 | G39: Em andamento
B40: Proteína Líquida | C40: Desenvolvimento da formulação | D40: Estudo sobre a estabilidade de emulsões proteicas | E40: Verificado que aminoácidos podem contribuir para a estabilidade da formulação | F40: 45078 | G40: 45139
B41: Proteína Líquida | C41: Desenvolvimento da formulação | D41: Elaboração de formulações variadas para teste de bancada | E41: Seguindo o briefing do Científico foram formuladas algumas opções para seguir para TB | F41: 45108 | G41: Em andamento
B42: Proteína Líquida | C42: Teste de bancada | D42: Testes de bancada utilizando a autoclave do Controle de Qualidade | E42: Os resultados apresentados permitiram ter uma boa noção de como seguir para TP | F42: 45139 | G42: 45139
B43: Proteína Líquida | C43: Teste piloto | D43: Testar as formulações escolhidas após TB, utilizando todos os equipamentos necessários para o processo industrial regular | E43: Formulações não desestabilzaram, porém, ficaram com alta viscosidade | F43: 45170 | G43: 45170
B44: Proteína Líquida | C44: Teste de bancada | D44: Uso da nova MP CanolaPro | E44: Dieta desestabilizou | F44: 45200 | G44: 45200
B45: Proteína Líquida | C45: Teste de bancada | D45: Uso da nova MP MiWhey | F45: 45261 | G45: NI
B46: PESQUISA ÍNDICE GLICÊMICO - DIAMAX IN / SF UTI | C46: Prospecção e definição de parceria | D46: Contato com pesquisadora para solicitação de orçamento | E46: Solicitar orçamento para realização de pesquisa clinica | F46: 44927 | G46: 2/28/2023
B47: PESQUISA ÍNDICE GLICÊMICO - DIAMAX IN / SF UTI | C47: Definição protocolo | D47: Definição de protocolo de pesquisa e discussão com pesquisadores | E47: Estabelecer e discutir o protocolo de pesquisa com os pesquisadores | F47: 44927 | G47: 2/28/2023
B48: PESQUISA ÍNDICE GLICÊMICO - DIAMAX IN / SF UTI | C48: Escrita do protocolo de pesquisa | D48: Levantamento de artigos científicos com produtos especializados para controle glicêmico para escrita da metodologia cientifica | E48: Realizar análise de metodologia de artigos cientificos; Escrever protocolo de pesquisa para sumissão ao CEP | F48: 44935 | G48: 10/20/2023
B49: PESQUISA ÍNDICE GLICÊMICO - DIAMAX IN / SF UTI | C49: Submissão e acompanhamento - CEP | D49: Submissão do projeto de pesquisa para avaliação do Comitê de Ética em Pesquisa (CEP) da universidade | E49: Acompanhar o processo de submissão do projeto de pesquisa ao CEP | F49: 10/25/2023 | G49: 11/30/2023
B50: PESQUISA CLÍNICA - IMMAX | C50: Prospecção e definição de parceria | D50: Análise de curriculum Lattes e contato com profissional após congresso da BRASPEN | E50: Buscar centros de referência em pesquisa com diabetes | F50: 44835 | G50: 44957
B51: PESQUISA CLÍNICA - IMMAX | C51: Definição protocolo | D51: Levantamento de artigos científicos com produtos especializados para oncologia e manutenção da massa muscular para analise de protocolo de pesquisa e discussão com pesquisadores | E51: Realizar análise de metodologia de artigos cientificos; Estabelecer e discutir o protocolo de pesquisa com os pesquisadores | F51: 44927 | G51: 45046
B52: PESQUISA CLÍNICA - IMMAX | C52: Submissão e acompanhamento - CEP | D52: Submissão do projeto de pesquisa para avaliação do Comitê de Ética em Pesquisa (CEP) da universidade | E52: Acompanhar o processo de submissão do projeto de pesquisa ao CEP | F52: 45039 | G52: 45138 | H52: Projeto submetido ao CEP em 28/04/23. Resposta as exigencias enviadas. Aprovação do CEP em Jul/23
B53: PESQUISA CLÍNICA - IMMAX | C53: Recrutamento e randomização | D53: Recrutamento de participantes elegíveis para a pesquisa clínica e randomização entre os grupos controle e intervenção | E53: Acompanhar processo de recrutamento e randomização dos participantes | F53: 45139 | G53: Em andamento
B54: PESQUISA CLÍNICA - IMMAX | C54: Coleta de dados | D54: Aplicação da interveção proposta nos participantes elegíveis | E54: Acompanhar a aplicação da intervenção | F54: 45139 | G54: Em andamento
B55: Pesquisa aplicada - ARTS | C55: Desenvolvimento de desenho de pesquisa | D55: Buscar em literatura referências para a elaboração de pesquisa de composição nutricional com novo produto artesanal | E55: Busca de referências; análise de receitas de dietas artesanais; análise de composição nutricional complementar; análise de interações de nutrientes para administração enteral | F55: 44958 | G55: Em andamento
B56: INOV000035 (2023 - PESQUISA CLÍNICA - CICATRIZAÇÃO) | C56: Prospeção | D56: Conversa com pesquisadores sobre possibilidade de parceria para pesquisa clínica e série de casos | E56: Acordo para parceria de Pesquisa | F56: 45587 | G56: 45466
B57: INOV000035 (2023 - PESQUISA CLÍNICA - CICATRIZAÇÃO) | C57: Levantamento para protocolo | D57: Fichamento de artigos científicos, pesquisa científica sobre o tema para definição de desfechos e metodologia | E57: Fichamento | F57: 45649 | G57: 45374
B58: INOV000035 (2023 - PESQUISA CLÍNICA - CICATRIZAÇÃO) | C58: Estatística | D58: Alinhamento com estatístico sobre número de amostra para pesquisa | E58: Viabilidade da pesquisa com Dante Pazzanese | F58: 45435 | G58: 45466 | H58: Projeto avaliado como inviável com este contato. Prospectando novos contatos
B59: PESQUISA CLÍNICA - HDMAX | C59: Prospecção e definição de parceria | D59: Contatar profissionais pesquisadores e compreender possibilidade de parceria | E59: Enviado e-mail para pesquisadora Vanessa e Adriano, pesquisadores na Universidade de Passo Fundo. Alinhado a possibilidade de pesquisa clínica mediante a doação de produto. Realizada doação de HDmax | F59: 43952 | G59: 43983
B60: PESQUISA CLÍNICA - HDMAX | C60: Definição de protocolo | D60: Compreender quais as possibilidade de protocolo de pesquisa - métodos mais eficientes e condizentes com a pesquisa | E60: Realizado reuniões com pesquisadores para compreender o desenho de pesquisa desejado e o protocolo de pesquisa a ser realizado. | F60: 43952 | G60: 43983
B61: PESQUISA CLÍNICA - HDMAX | C61: Submissão e acompanhamento ao CEP | D61: Submeter o projeto de pesquisa ao comitê de ética e pesquisa da insituição onde a pesquisa é realizada. | E61: Avaliado projeto de pesquisa e termo de consentimento livre e esclarecido que foram submetidos ao comitê. | F61: 44044 | G61: 44317
B62: PESQUISA CLÍNICA - HDMAX | C62: Coleta de dados | D62: Realizar a aplicação da intervenção proposta e avaliar pré e pós intervenção | E62: Realizada avaliação prévia a intervenção, aplicada a suplementação intradialítica durante 3 meses e realizada nova avaliação pós intervenção imediata e pós intervenção pós 6 meses. | F62: 44348 | G62: 44593
B63: PESQUISA CLÍNICA - HDMAX | C63: Análise de dados | D63: Analisar os dados obtidos pré e pós intervenção | E63: Análise em andamento - averiguado efeitos positivos da suplementação em estado nutricional e outros parâmetros como força muscular. | F63: 44621 | G63: 44743
B64: PESQUISA CLÍNICA - HDMAX | C64: Elaboração de artigo | D64: Desenvolver artigo para publicação em revista científica | E64: Escrita de artigo cientifico | F64: 45314 | G64: 45619
B65: PESQUISA CLÍNICA - HDMAX | C65: Elaboração de resumo cientifico | D65: Desenvolver resumo para apresentação em congresso científica | E65: Escrita de resumo para apresentação em congresso cientifico | F65: 45314 | G65: 45619
B66: ASPEN | C66: Participação em congresso | D66: Participação em congresso e apresentação de pesquisa | E66: Participação em congresso, apresentação de pesquisa, elaboração de relatório e apresentação para equipe com sugestões de aplicação do novo conhecimento adquirido, alinhando à novos produtos e à possibilidades de melhorias e inovação. | F66: 10/21 | G66: 05/22
B67: GANEPÃO | C67: Participação em congresso | D67: Participação em congresso e apresentação de pesquisa | E67: Participação em congresso, apresentação de pesquisa, elaboração de relatório e apresentação para equipe com sugestões de aplicação do novo conhecimento adquirido, alinhando à novos produtos e à possibilidades de melhorias e inovação. | F67: 03/22 | G67: 09/22
B68: ESPEN | C68: Participação em congresso | D68: Participação em congresso e apresentação de pesquisa | E68: Participação em congresso, apresentação de pesquisa, elaboração de relatório e apresentação para equipe com sugestões de aplicação do novo conhecimento adquirido, alinhando à novos produtos e à possibilidades de melhorias e inovação. | F68: 06/22 | G68: 11/22
B69: BRASPEN | C69: Participação em congresso | D69: Participação em congresso e apresentação de pesquisa | E69: Participação em congresso, apresentação de pesquisa, elaboração de relatório e apresentação para equipe com sugestões de aplicação do novo conhecimento adquirido, alinhando à novos produtos e à possibilidades de melhorias e inovação. | F69: 06/22 | G69: 12/22
B70: ASPEN | C70: Participação em congresso | D70: Participação em congresso e apresentação de pesquisa | E70: Participação em congresso, apresentação de pesquisa, elaboração de relatório e apresentação para equipe com sugestões de aplicação do novo conhecimento adquirido, alinhando à novos produtos e à possibilidades de melhorias e inovação. | F70: 10/22 | G70: 05/23
B71: GANEPÃO | C71: Participação em congresso | D71: Participação em congresso e apresentação de pesquisa | E71: Participação em congresso, apresentação de pesquisa, elaboração de relatório e apresentação para equipe com sugestões de aplicação do novo conhecimento adquirido, alinhando à novos produtos e à possibilidades de melhorias e inovação. | F71: 03/23 | G71: 08/23
B72: ESPEN | C72: Participação em congresso | D72: Participação em congresso e apresentação de pesquisa | E72: Participação em congresso, apresentação de pesquisa, elaboração de relatório e apresentação para equipe com sugestões de aplicação do novo conhecimento adquirido, alinhando à novos produtos e à possibilidades de melhorias e inovação. | F72: 06/23 | G72: 12/23
B73: BRASPEN | C73: Participação em congresso | D73: Participação em congresso e apresentação de pesquisa | E73: Participação em congresso, apresentação de pesquisa, elaboração de relatório e apresentação para equipe com sugestões de aplicação do novo conhecimento adquirido, alinhando à novos produtos e à possibilidades de melhorias e inovação. | F73: 06/23 | G73: 12/23
B74: ESTUDO DE CASO | C74: Prospecção e definição de parceria com profissionais da saúde | D74: Aplicação de Trophic EP para pacientes oncológicos | E74: Desenho de relato de caso prospetivo de pacientes que usam Trophic EP - definir pacientes para estudo e dados antropométricos e bioquímicos | F74: 45619 | G74: Em andamento
B75: ESTUDO DE CASO | C75: Submissão ao congresso GANEPÃO/23 | D75: Elaboração de resumo para submissão ao GANEPÃO/23 | E75: Organizar os dados coletados em pesquisa de aplicação interna realizada em 2021/2022 e elaborar resumo para congresso | F75: 44929 | G75: 3/14/2023 | H75: Tema livre sobre teor de sódio do Instanth Clear versus outras opções do mercado e correlação da quantidade de sódio consumida pelos pacientes
B76: ESTUDO DE CASO | C76: Apresentação do resumo em congresso Ganepão 2023 | D76: Apresentação do resumo elaborado no congresso da Ganepão 2023 com publicação nos anais de congressos | E76: Apresentar resumo em congresso | F76: 45236 | G76: 6/14/2023
B77: PESQUISA CLÍNICA - DIAMAX IG | C77: Prospecção e definição de parceria | D77: Análise de curriculum Lattes e contato com profissionais que realizem pesquisa clínica com diabetes | E77: Buscar centros de referência em pesquisa com diabetes | F77: 44287 | G77: 44682 | H77: Retorno e possível parceira com UFPA. 10/21: Parceria com UFPA não foi possível devido ao perfil dos alunos que ingressaram no mestrado. EC será executado na instituição. Retomada a busca por novas parcerias de pesquisa. Estebelecido parceria com a UFG.
B78: PESQUISA CLÍNICA - DIAMAX IG | C78: Definição protocolo | D78: Levantamento de artigos científicos com produtos especializados para controle glicêmico para analise de protocolo de pesquisa e discussão com pesquisadores | E78: Realizar análise de metodologia de artigos cientificos; Estabelecer e discutir o protocolo de pesquisa com os pesquisadores | F78: 44531 | G78: 44652
B79: PESQUISA CLÍNICA - DIAMAX IG | C79: Submissão e acompanhamento - CEP | D79: Submissão do projeto de pesquisa para avaliação do Comitê de Ética em Pesquisa (CEP) da universidade | E79: Acompanhar o processo de submissão do projeto de pesquisa ao CEP | F79: 44652 | G79: 44788 | H79: Projeto aprovado no CEP/UFG em 15/08/2022.
B80: PESQUISA CLÍNICA - DIAMAX IG | C80: Recrutamento | D80: Recrutamento de participantes elegíveis para a pesquisa clínica | E80: Acompanhar processo de recrutamento de participantes | F80: 44835 | G80: 45474 | H80: Em andamento
B81: PESQUISA CLÍNICA - DIAMAX IG | C81: Coleta de dados | D81: Aplicação da interveção proposta nos participantes elegíveis | E81: Acompanhar a aplicação da intervenção | F81: 44835 | G81: 45474 | H81: Em andamento
B82: PESQUISA CLÍNICA - DIAMAX IG | C82: Tabulação de dados | D82: Tabulação de dados coletados da pesquisa | E82: Acompanhar processo de tabulação de dados | F82: 44927 | G82: 45474 | H82: Em andamento
B83: PESQUISA CLÍNICA - DIAMAX IG | C83: Análise parcial de resultados | D83: Análise parcial dos dados coletados da pesquisa clinica e escreita de resumo cientifico para submissão em congresso nacional | E83: Analisar dados paciais da pesquisa e escrever resumo cientifico | F83: 44958 | G83: 45107
B84: Instanth Neo - Pesquisa Clínica UNIFESP | C84: Escrita protocolo | D84: Pesquisa básica para desenho da pesquisa | E84: submissão protocolo CEP | F84: 44197 | G84: 44469
B85: Instanth Neo - Pesquisa Clínica UNIFESP | C85: Submissão CEP | D85: Submissão e acompanhamento para pendências CEP | E85: aprovação CEP | F85: 44470 | G85: 44679 | H85: PROJETO REPROVADO
B86: Instanth Neo - Pesquisa Clínica UNIFESP | C86: Escrita protocolo | D86: Pesquisa básica para desenho e reescrita do protocolo de pesquisa com base nas pendências CEP | E86: Reescrever protocolo de pesquisa com foco em série de casos | F86: 44682 | G86: 45458 | H86: Exigências tornaram projeto inviável dentro do orçamento proposto. Alternativas foram evantadas e por enquanto o projeto está em stand by aguardando criação do ambulatório de CCL da UNIFESP. 05/23: Ambulatorio criado e reescrita do protocolo retomada. Aguardando avaliação dos pesquisadores para submissão do projeto ao CEP
B87: PEPTIMAX JUNIOR | C87: Pesquisa Científica e desenvolvimento | D87: Levantamento de editais de licitação; concorrentes mercado | E87: Buscar materias de consulta em editais de licitação e concorrentes para desenvolvimento do Briefing | F87: 45465 | G87: 45495
B88: PEPTIMAX JUNIOR | D88: Levantamento de literatura/artigos/Guidelines | E88: Buscar materias de consulta em guidelines e diretrizes nacionais e internacionais para desenvolvimento do Briefing | F88: 45495 | G88: 45557
B89: PEPTIMAX JUNIOR | D89: Rounds Científicos | E89: Definição da formulação nutricional | F89: 45345 | G89: 45405
B90: PEPTIMAX JUNIOR | C90: Kick off | D90: Kick off com toda equipe técnica, comercial e marketing, para considerações no Briefing | E90: Fechamento do Briefing | F90: 45435 | G90: 45466
B91: PEPTIMAX JUNIOR | C91: Desenvolvimento da formulação | D91: Elaboração de formulações variadas para teste de bancada | E91: Seguindo o briefing do Científico foram formuladas algumas opções para seguir para TB | F91: 45108 | G91: Em andamento
B92: PEPTIMAX JUNIOR | C92: Desenvolvimento da formulação | D92: Busca de WPH com baixo teor de lactose | E92: Contato com fornecedores para prospectar a nova MP | F92: 45139 | G92: Em andamento | H92: Em dez/23 a propscção e avaliação de fornecedores e MPs permanece em andmaneto, aguardando amostras para execução dos testes de bancada
B93: Linha Trophic Soya pó | C93: Desenvolvimento de Masterfile | D93: Elaborar o primeiro Masterfile (MF) teórico 100% Proteína Isolada da Soja (PIS) | E93: Desenvolver, a partir da composição do produto, o pré mix de vitaminas e minerais específico para a linha Soya pó | F93: 44256 | G93: 44256
B94: Linha Trophic Soya pó | C94: Desenvolvimento de aromas | D94: Solicitar aos fornecedores Duas Rodas e IFF opções de aromas | E94: Embora o objetivo principal do produto seja uso via tubo, o produto deve atingir sensorial palatável, por este motivo buscou-se opções de aromas que mascarem a PIS | F94: 44256 | G94: 44348
B95: Linha Trophic Soya pó | C95: Desenvolvimento de Masterfile | D95: Elaborar segunda versão do Masterfile teórico com 20% de proteína láctea e 80% PIS e realizar a degustação | E95: Encontrar melhor opção de mix proteico, de forma que o produto não contenha lactose e possua baixo custo. Análise sensorial em bancada foi realizado para definição da proteína láctea | F95: 44348 | G95: 44409
B96: Linha Trophic Soya pó | C96: Desenvolvimento pré mix micronutrientes | D96: Elaborar documento de desenvolvimento do pre mix com base na composição do produto, encaminhar ao fornecedor DSM para criação | E96: Receber toda a documentação relacionada ao novo pre mix desenvolvido, de forma que atenda ao solicitado e promova uma informação nutricional adequada e esperada ao produto, conforme target definido pelo Científico | F96: 44256 | G96: 44440 | H96: Pre mix criado com a descrição 11599A25 (vitaminas) e 11696A25 (minerais)
B97: Linha Trophic Soya pó | C97: Testes de bancada para avaliação da fórmula | D97: Realizar os testes de bancada com aplicação dos aromas, mix e todos os ingredientes | E97: Avaliar todos os critérios importantes para a fórmula: solubilidade, método de preparo, definição de aromas, aprovação sensorial e desta forma, definir a formulação final | F97: 44378 | G97: 44440
B98: Linha Trophic Soya pó | C98: Avaliação sensorial multidisciplicar | D98: Encaminhar amostras aos participantes da avaliação sensorial, dos setores de P&D, AR e Diretoria, e realizar um encontro online para degustação do produto final em conjunto | E98: Obter diferentes opiniões e comentários sobre melhorias da formulação para atingir a aprovação final | F98: 44470 | G98: 44470
B99: Linha Trophic Soya pó | C99: Ajuste de fórmula | D99: Teste de bancada para ajustes quanto estabilidade da fórmula com a possibilidade de retirada de lecitina de soja e melhoria de viscosidade com redução de goma xantana | E99: Obter dose adequada de lecitina de soja de maneira que a fórmula se mantenha estável. Reduzir a viscosidade da fórmula, principalmente quando preparado com liquidificador | F99: 44470 | G99: 44228
B100: Linha Trophic Soya pó | C100: Avaliação de custo | D100: Avaliar através do Simulador de custos de P&D, o custo do produto e alteranativas de redução de custo | E100: Obter custo viável e mais vantajoso (com diferença significativa) comercialmente em relação ao Trophic Basic e Trophic Fiber, ambos pó. | F100: 44470 | G100: 44621
B101: Linha Trophic Soya pó | C101: Publicação MF em Sharepoint | D101: Compartilhar o MF com os setores de Assusntos Regulatórios e Científico | E101: Avaliação final da composição e IN teórica pelos demais setores, quanto ao atendimento do briefing e legislação | F101: 44470 | G101: 44470
B102: Linha Trophic Soya pó | C102: Reformulação de mix | D102: Após teste industrial da fórmula líquida em que é compartilhado o mesmo mix, detectou-se a necessidade de reformular o mix de minerais para redução de pH | E102: Alterar a fonte de Magnésio por opção que promovo um pH mais ácido a formulação | F102: 44501 | G102: 44593 | H102: Em fevereiro de 2022, de modo a atender diretriz internas, foi otado por iniciar o desenvolvimento de pré-mixes que atendam vários produtos. Com isto, não foi seguido com o ajuste do pré-mix FS11696A25
B103: Linha Trophic Soya pó | C103: Reformulação de mix - padrão PIS | D103: Desenvolver novo pre mix de minerais dedicado para produtos com alto teor de PIS | E103: Receber toda a documentação relacionada ao novo pre mix desenvolvido, de forma que atenda ao solicitado e promova uma informação nutricional adequada e esperada ao produto, conforme target definido pelo Científico | F103: 44652 | G103: 44682
B104: Linha Trophic Soya pó | C104: Stand by | D104: O projeto está mantido em stand by | E104: Projeto permanecerá em stand by até que seja encontrada uma alternativa para redução de custo | F104: 44621 | G104: 44958
...

Sheet #verificação RH
A1: Total | B1: =sum(B3:B10) -> 15366.96 | C1: =sum(C3:C10) -> 37022.728 | D1: =sum(D3:D10) -> 34877.287 | E1: =sum(E3:E10) -> 12531.244 | F1: =sum(B1:E1) -> 99798.219
B2: 1º trimestre | C2: 2º trimestre | D2: 3º trimestre | E2: 4º trimestre | F2: Total
A3: Alyne Alves Nunes Oliveira | B3: =IFERROR(__xludf.DUMMYFUNCTION("iferror(sum(filter(TIMESHEET!$N:$N,month(TIMESHEET!$F:$F)>=1,month(TIMESHEET!$F:$F)<=3,TIMESHEET!$E:$E=$A3)),0)"),3857.3900000000003) -> 3857.39 | C3: =IFERROR(__xludf.DUMMYFUNCTION("iferror(sum(filter(TIMESHEET!$N:$N,month(TIMESHEET!$F:$F)>=4,month(TIMESHEET!$F:$F)<=6,TIMESHEET!$E:$E=$A3)),0)"),4738.302749096433) -> 4738.3027 | D3: =IFERROR(__xludf.DUMMYFUNCTION("iferror(sum(filter(TIMESHEET!$N:$N,month(TIMESHEET!$F:$F)>=7,month(TIMESHEET!$F:$F)<=9,TIMESHEET!$E:$E=$A3)),0)"),10732.006945744717) -> 10732.007 | E3: =IFERROR(__xludf.DUMMYFUNCTION("iferror(sum(filter(TIMESHEET!$N:$N,month(TIMESHEET!$F:$F)>=10,month(TIMESHEET!$F:$F)<=12,TIMESHEET!$E:$E=$A3)),0)"),1004.0271087436868) -> 1004.0271 | F3: =sum(B3:E3) -> 20331.727
