Workbook

Sheet Resumo
A1: Resumo de investimentos
A2: INOVAÇÃO TECNOLÓGICA 2016
A5: Natureza | B5: Total
A6: Material | B6: ='(a) Investimentos'!J4 -> 16180.07 | C6: (a1)
A7: Terceiros | B7: ='(a) Investimentos'!J5 -> 257166.12 | C7: (a2)
A8: RH (Parcial inovação) | B8: ='(b) Timesheet consolidado'!K7 -> 6980.2545 | C8: (b)
A9: RH (Exclusivo inovação) | B9: ='(c) Dedicação exclusiva'!Q13 -> 154995.32 | C9: (c)
A10: Total | B10: =SUM(B6:B9) -> 435321.76
A11: Percentual Exclusão | B11: 0.6
A12: Exclusão da Base de cálculo do IRPJ e CSLL | B12: =B10*B11 -> 261193.06
A14: Economia Estimada [34%] | B14: =B12*34% -> 88805.64
A16: (a1) Material consumido - detalhes na planilha Investimentos
A17: (a2) Serviços contratados + Ana Paula Celes e Luciana Dutra [dedicação parcial sem apontamento de horas] - detalhes na planilha Investimentos
A18: (b) Time Sheet [funcionários com dedicação parcial] - planilhas Timesheet consolidado
A19: (c) Custo total dos funcionários com dedicação exclusiva - planilha Dedicação Exclusiva

Sheet Distribuição
A1: Distribuição
A2: INOVAÇÃO TECNOLÓGICA 2016
A3: Distribuição entre os projetos dos gastos [para formulário do MCTI]
A6: R$ | B6: Novos produtos | C6: Novas matérias-primas | D6: Melhoria de produto | E6: Melhoria de produto | F6: Total
A7: RH Ded. | B7: =SUM('(c) Dedicação exclusiva'!$E$10:$P$12)*B15 -> 58223.604 | C7: =SUM('(c) Dedicação exclusiva'!$E$10:$P$12)*C15 -> 28806.105 | D7: =SUM('(c) Dedicação exclusiva'!$E$10:$P$12)*D15 -> 40236.433 | E7: =SUM('(c) Dedicação exclusiva'!$E$10:$P$12)*E15 -> 27729.178 | F7: =SUM(B7:E7) -> 154995.32
A8: RH Par. | B8: =SUM('(b) Timesheet consolidado'!$K$9:$K$71)*B15 -> 2622.1151 | C8: =SUM('(b) Timesheet consolidado'!$K$9:$K$71)*C15 -> 1297.2904 | D8: =SUM('(b) Timesheet consolidado'!$K$9:$K$71)*D15 -> 1812.0582 | E8: =SUM('(b) Timesheet consolidado'!$K$9:$K$71)*E15 -> 1248.7907 | F8: =SUM(B8:E8) -> 6980.2545
A9: Material | B9: =SUMIF('(a) Investimentos'!$I$8:$I$114,$A9,'(a) Investimentos'!W$8:W$114) -> 7378.48 | C9: =SUMIF('(a) Investimentos'!$I$8:$I$114,$A9,'(a) Investimentos'!X$8:X$114) -> 895.15 | D9: =SUMIF('(a) Investimentos'!$I$8:$I$114,$A9,'(a) Investimentos'!Y$8:Y$114) -> 2798.98 | E9: =SUMIF('(a) Investimentos'!$I$8:$I$114,$A9,'(a) Investimentos'!Z$8:Z$114) -> 0 | F9: =SUM(B9:E9) -> 11072.61
A10: PJ (terceiros) | B10: =SUMIFS('(a) Investimentos'!W8:W114,'(a) Investimentos'!$I$8:$I$114,"Terceiros") -> 83866.465 | C10: =SUMIFS('(a) Investimentos'!X8:X114,'(a) Investimentos'!$I$8:$I$114,"Terceiros") -> 43737.234 | D10: =SUMIFS('(a) Investimentos'!Y8:Y114,'(a) Investimentos'!$I$8:$I$114,"Terceiros") -> 59543.635 | E10: =SUMIFS('(a) Investimentos'!Z8:Z114,'(a) Investimentos'!$I$8:$I$114,"Terceiros") -> 42963.785 | F10: =SUM(B10:E10) -> 230111.12
A11: Distribuição ILSI (PJ) | B11: =SUMIFS('(a) Investimentos'!$N$8:$N$114,'(a) Investimentos'!$E$8:$E$114,"ILSI",'(a) Investimentos'!$I$8:$I$114,"Terceiros")*B15 -> 10163.143 | C11: =SUMIFS('(a) Investimentos'!$N$8:$N$114,'(a) Investimentos'!$E$8:$E$114,"ILSI",'(a) Investimentos'!$I$8:$I$114,"Terceiros")*C15 -> 5028.211 | D11: =SUMIFS('(a) Investimentos'!$N$8:$N$114,'(a) Investimentos'!$E$8:$E$114,"ILSI",'(a) Investimentos'!$I$8:$I$114,"Terceiros")*D15 -> 7023.4166 | E11: =SUMIFS('(a) Investimentos'!$N$8:$N$114,'(a) Investimentos'!$E$8:$E$114,"ILSI",'(a) Investimentos'!$I$8:$I$114,"Terceiros")*E15 -> 4840.2294 | F11: =SUM(B11:E11) -> 27055
A12: Distribuição ILSI (material) | B12: =SUMIFS('(a) Investimentos'!$N$8:$N$114,'(a) Investimentos'!$E$8:$E$114,"ILSI",'(a) Investimentos'!$I$8:$I$114,"Material")*B15 -> 1918.6045 | C12: =SUMIFS('(a) Investimentos'!$N$8:$N$114,'(a) Investimentos'!$E$8:$E$114,"ILSI",'(a) Investimentos'!$I$8:$I$114,"Material")*C15 -> 949.22886 | D12: =SUMIFS('(a) Investimentos'!$N$8:$N$114,'(a) Investimentos'!$E$8:$E$114,"ILSI",'(a) Investimentos'!$I$8:$I$114,"Material")*D15 -> 1325.885 | E12: =SUMIFS('(a) Investimentos'!$N$8:$N$114,'(a) Investimentos'!$E$8:$E$114,"ILSI",'(a) Investimentos'!$I$8:$I$114,"Material")*E15 -> 913.74157 | F12: =SUM(B12:E12) -> 5107.46
A13: Material (total) | B13: =B12+B9 -> 9297.0845 | C13: =C12+C9 -> 1844.3789 | D13: =D12+D9 -> 4124.865 | E13: =E12+E9 -> 913.74157 | F13: =SUM(B13:E13) -> 16180.07
A14: Total | B14: =SUM(B7:B12) -> 164172.41 | C14: =SUM(C7:C12) -> 80713.22 | D14: =SUM(D7:D12) -> 112740.41 | E14: =SUM(E7:E12) -> 77695.725 | F14: =SUM(B14:E14) -> 435321.76
A15: % (proporção) | B15: 0.37564749 | C15: 0.18585145 | D15: 0.25959773 | E15: 0.17890332 | F15: =SUM(B15:E15) -> 1
A16: Observação: a proporção foi calculada considerando o percentual de cada projeto nos gastos com PJ (terceiros).
B19: Novos produtos | C19: Novas matérias-primas | D19: Melhoria de produto | E19: Melhoria de produto | F19: Total (R$) | G19: Dedicação | H19: CPF | I19: Escolaridade | J19: Novos produtos | K19: Novas matérias-primas | L19: Melhoria de produto | M19: Melhoria de produto | N19: Total (Horas)
A20: Amid Tony Ibrahim | B20: =B$15*Salários!$Q$23 -> 17092.271 | C20: =C$15*Salários!$Q$23 -> 8456.3947 | D20: =D$15*Salários!$Q$23 -> 11811.911 | E20: =E$15*Salários!$Q$23 -> 8140.2491 | F20: =SUM(B20:E20) -> 45500.826 | G20: Exclusivo | H20: =VLOOKUP($A20,'Informações RH'!$A$2:$D$9,2,FALSE) -> 075.215.579-21 | I20: =VLOOKUP($A20,'Informações RH'!$A$2:$D$9,4,FALSE) -> Superior Completo | J20: ='Dias úteis'!$H$20*B$15 -> 839.64728 | K20: ='Dias úteis'!$H$20*C$15 -> 415.41517 | L20: ='Dias úteis'!$H$20*D$15 -> 580.25285 | M20: ='Dias úteis'!$H$20*E$15 -> 399.88471 | N20: =SUM(J20:M20) -> 2235.2
A21: Franciele Guedes | B21: =SUMIF('(b) Timesheet consolidado'!$A$9:$A$71,$A21,'(b) Timesheet consolidado'!$K$9:$K$71)*B$15 -> 520.81936 | C21: =SUMIF('(b) Timesheet consolidado'!$A$9:$A$71,$A21,'(b) Timesheet consolidado'!$K$9:$K$71)*C$15 -> 257.67518 | D21: =SUMIF('(b) Timesheet consolidado'!$A$9:$A$71,$A21,'(b) Timesheet consolidado'!$K$9:$K$71)*D$15 -> 359.92127 | E21: =SUMIF('(b) Timesheet consolidado'!$A$9:$A$71,$A21,'(b) Timesheet consolidado'!$K$9:$K$71)*E$15 -> 248.04189 | F21: =SUM(B21:E21) -> 1386.4577 | G21: Parcial | H21: =VLOOKUP($A21,'Informações RH'!$A$2:$D$9,2,FALSE) -> 065.423.719-07 | I21: =VLOOKUP($A21,'Informações RH'!$A$2:$D$9,4,FALSE) -> Superior Completo | J21: =SUMIF('(b) Timesheet consolidado'!$A$9:$A$71,$A21,'(b) Timesheet consolidado'!$G$9:$G$71)*B$15 -> 17.586563 | K21: =SUMIF('(b) Timesheet consolidado'!$A$9:$A$71,$A21,'(b) Timesheet consolidado'!$G$9:$G$71)*C$15 -> 8.7009455 | L21: =SUMIF('(b) Timesheet consolidado'!$A$9:$A$71,$A21,'(b) Timesheet consolidado'!$G$9:$G$71)*D$15 -> 12.1535 | M21: =SUMIF('(b) Timesheet consolidado'!$A$9:$A$71,$A21,'(b) Timesheet consolidado'!$G$9:$G$71)*E$15 -> 8.3756573 | N21: =SUM(J21:M21) -> 46.816667
A22: Hellin dos Santos | B22: =Salários!$Q$25*B$15 -> 33144.619 | C22: =Salários!$Q$25*C$15 -> 16398.287 | D22: =Salários!$Q$25*D$15 -> 22905.165 | E22: =Salários!$Q$25*E$15 -> 15785.231 | F22: =SUM(B22:E22) -> 88233.302 | G22: Exclusivo | H22: =VLOOKUP($A22,'Informações RH'!$A$2:$D$9,2,FALSE) -> 058.544.839-63 | I22: =VLOOKUP($A22,'Informações RH'!$A$2:$D$9,4,FALSE) -> Superior Completo | J22: ='Dias úteis'!$H$20*B$15 -> 839.64728 | K22: ='Dias úteis'!$H$20*C$15 -> 415.41517 | L22: ='Dias úteis'!$H$20*D$15 -> 580.25285 | M22: ='Dias úteis'!$H$20*E$15 -> 399.88471 | N22: =SUM(J22:M22) -> 2235.2
A23: Hozana Bueno | B23: =SUMIF('(b) Timesheet consolidado'!$A$9:$A$71,$A23,'(b) Timesheet consolidado'!$K$9:$K$71)*B$15 -> 170.9379 | C23: =SUMIF('(b) Timesheet consolidado'!$A$9:$A$71,$A23,'(b) Timesheet consolidado'!$K$9:$K$71)*C$15 -> 84.571461 | D23: =SUMIF('(b) Timesheet consolidado'!$A$9:$A$71,$A23,'(b) Timesheet consolidado'!$K$9:$K$71)*D$15 -> 118.12961 | E23: =SUMIF('(b) Timesheet consolidado'!$A$9:$A$71,$A23,'(b) Timesheet consolidado'!$K$9:$K$71)*E$15 -> 81.409725 | F23: =SUM(B23:E23) -> 455.0487 | G23: Parcial | H23: =VLOOKUP($A23,'Informações RH'!$A$2:$D$9,2,FALSE) -> 039.677.159-90 | I23: =VLOOKUP($A23,'Informações RH'!$A$2:$D$9,4,FALSE) -> Técnico | J23: =SUMIF('(b) Timesheet consolidado'!$A$9:$A$71,$A23,'(b) Timesheet consolidado'!$G$9:$G$71)*B$15 -> 9.0155398 | K23: =SUMIF('(b) Timesheet consolidado'!$A$9:$A$71,$A23,'(b) Timesheet consolidado'!$G$9:$G$71)*C$15 -> 4.4604349 | L23: =SUMIF('(b) Timesheet consolidado'!$A$9:$A$71,$A23,'(b) Timesheet consolidado'!$G$9:$G$71)*D$15 -> 6.2303455 | M23: =SUMIF('(b) Timesheet consolidado'!$A$9:$A$71,$A23,'(b) Timesheet consolidado'!$G$9:$G$71)*E$15 -> 4.2936798 | N23: =SUM(J23:M23) -> 24
A24: Jana Grenteski | B24: =B$15*Salários!$Q$27 -> 7986.7136 | C24: =C$15*Salários!$Q$27 -> 3951.4235 | D24: =D$15*Salários!$Q$27 -> 5519.3573 | E24: =E$15*Salários!$Q$27 -> 3803.698 | F24: =SUM(B24:E24) -> 21261.192 | G24: Exclusivo | H24: =VLOOKUP($A24,'Informações RH'!$A$2:$D$9,2,FALSE) -> 040.201.929-60 | I24: =VLOOKUP($A24,'Informações RH'!$A$2:$D$9,4,FALSE) -> Superior Completo / Doutorado em Andamento | J24: ='Dias úteis'!$H$20*B$15 -> 839.64728 | K24: ='Dias úteis'!$H$20*C$15 -> 415.41517 | L24: ='Dias úteis'!$H$20*D$15 -> 580.25285 | M24: ='Dias úteis'!$H$20*E$15 -> 399.88471 | N24: =SUM(J24:M24) -> 2235.2
A25: Lizianne Shmeil | B25: =SUMIF('(b) Timesheet consolidado'!$A$9:$A$71,$A25,'(b) Timesheet consolidado'!$K$9:$K$71)*B$15 -> 354.06264 | C25: =SUMIF('(b) Timesheet consolidado'!$A$9:$A$71,$A25,'(b) Timesheet consolidado'!$K$9:$K$71)*C$15 -> 175.17236 | D25: =SUMIF('(b) Timesheet consolidado'!$A$9:$A$71,$A25,'(b) Timesheet consolidado'!$K$9:$K$71)*D$15 -> 244.68114 | E25: =SUMIF('(b) Timesheet consolidado'!$A$9:$A$71,$A25,'(b) Timesheet consolidado'!$K$9:$K$71)*E$15 -> 168.62347 | F25: =SUM(B25:E25) -> 942.53961 | G25: Parcial | H25: =VLOOKUP($A25,'Informações RH'!$A$2:$D$9,2,FALSE) -> 052.485.199-93 | I25: =VLOOKUP($A25,'Informações RH'!$A$2:$D$9,4,FALSE) -> Pós graduada | J25: =SUMIF('(b) Timesheet consolidado'!$A$9:$A$71,$A25,'(b) Timesheet consolidado'!$G$9:$G$71)*B$15 -> 11.926808 | K25: =SUMIF('(b) Timesheet consolidado'!$A$9:$A$71,$A25,'(b) Timesheet consolidado'!$G$9:$G$71)*C$15 -> 5.9007836 | L25: =SUMIF('(b) Timesheet consolidado'!$A$9:$A$71,$A25,'(b) Timesheet consolidado'!$G$9:$G$71)*D$15 -> 8.2422279 | M25: =SUMIF('(b) Timesheet consolidado'!$A$9:$A$71,$A25,'(b) Timesheet consolidado'!$G$9:$G$71)*E$15 -> 5.6801806 | N25: =SUM(J25:M25) -> 31.75
A26: Marianne Stigar | B26: =SUMIF('(b) Timesheet consolidado'!$A$9:$A$71,$A26,'(b) Timesheet consolidado'!$K$9:$K$71)*B$15 -> 703.88126 | C26: =SUMIF('(b) Timesheet consolidado'!$A$9:$A$71,$A26,'(b) Timesheet consolidado'!$K$9:$K$71)*C$15 -> 348.24498 | D26: =SUMIF('(b) Timesheet consolidado'!$A$9:$A$71,$A26,'(b) Timesheet consolidado'!$K$9:$K$71)*D$15 -> 486.42938 | E26: =SUMIF('(b) Timesheet consolidado'!$A$9:$A$71,$A26,'(b) Timesheet consolidado'!$K$9:$K$71)*E$15 -> 335.22571 | F26: =SUM(B26:E26) -> 1873.7813 | G26: Parcial | H26: =VLOOKUP($A26,'Informações RH'!$A$2:$D$9,2,FALSE) -> 066.424.199-95 | I26: =VLOOKUP($A26,'Informações RH'!$A$2:$D$9,4,FALSE) -> Pós graduada | J26: =SUMIF('(b) Timesheet consolidado'!$A$9:$A$71,$A26,'(b) Timesheet consolidado'!$G$9:$G$71)*B$15 -> 21.004956 | K26: =SUMIF('(b) Timesheet consolidado'!$A$9:$A$71,$A26,'(b) Timesheet consolidado'!$G$9:$G$71)*C$15 -> 10.392194 | L26: =SUMIF('(b) Timesheet consolidado'!$A$9:$A$71,$A26,'(b) Timesheet consolidado'!$G$9:$G$71)*D$15 -> 14.51584 | M26: =SUMIF('(b) Timesheet consolidado'!$A$9:$A$71,$A26,'(b) Timesheet consolidado'!$G$9:$G$71)*E$15 -> 10.003678 | N26: =SUM(J26:M26) -> 55.916667
A27: Mauricio Ragadalli | B27: =SUMIF('(b) Timesheet consolidado'!$A$9:$A$71,$A27,'(b) Timesheet consolidado'!$K$9:$K$71)*B$15 -> 872.41395 | C27: =SUMIF('(b) Timesheet consolidado'!$A$9:$A$71,$A27,'(b) Timesheet consolidado'!$K$9:$K$71)*C$15 -> 431.62647 | D27: =SUMIF('(b) Timesheet consolidado'!$A$9:$A$71,$A27,'(b) Timesheet consolidado'!$K$9:$K$71)*D$15 -> 602.89682 | E27: =SUMIF('(b) Timesheet consolidado'!$A$9:$A$71,$A27,'(b) Timesheet consolidado'!$K$9:$K$71)*E$15 -> 415.48994 | F27: =SUM(B27:E27) -> 2322.4272 | G27: Parcial | H27: =VLOOKUP($A27,'Informações RH'!$A$2:$D$9,2,FALSE) -> 060.236.389-61 | I27: =VLOOKUP($A27,'Informações RH'!$A$2:$D$9,4,FALSE) -> Superior Completo | J27: =SUMIF('(b) Timesheet consolidado'!$A$9:$A$71,$A27,'(b) Timesheet consolidado'!$G$9:$G$71)*B$15 -> 19.314542 | K27: =SUMIF('(b) Timesheet consolidado'!$A$9:$A$71,$A27,'(b) Timesheet consolidado'!$G$9:$G$71)*C$15 -> 9.5558622 | L27: =SUMIF('(b) Timesheet consolidado'!$A$9:$A$71,$A27,'(b) Timesheet consolidado'!$G$9:$G$71)*D$15 -> 13.34765 | M27: =SUMIF('(b) Timesheet consolidado'!$A$9:$A$71,$A27,'(b) Timesheet consolidado'!$G$9:$G$71)*E$15 -> 9.1986126 | N27: =SUM(J27:M27) -> 51.416667
A28: Total | B28: =SUM(B20:B27) -> 60845.719 | C28: =SUM(C20:C27) -> 30103.396 | D28: =SUM(D20:D27) -> 42048.492 | E28: =SUM(E20:E27) -> 28977.969 | F28: =SUM(F20:F27) -> 161975.57 | J28: =SUM(J20:J27) -> 2597.7902 | K28: =SUM(K20:K27) -> 1285.2557 | L28: =SUM(L20:L27) -> 1795.2481 | M28: =SUM(M20:M27) -> 1237.2059 | N28: =SUM(N20:N27) -> 6915.5
D31: =SUBTOTAL(9,D33:D54) -> 83866.465 | E31: =SUBTOTAL(9,E33:E54) -> 43737.234 | F31: =SUBTOTAL(9,F33:F54) -> 59543.635 | G31: =SUBTOTAL(9,G33:G54) -> 42963.785 | H31: =SUBTOTAL(9,H33:H54) -> 27055 | I31: =SUM(D31:H31) -> 257166.12
A32: RECURSO | B32: CPF / CNPJ | C32: NATUREZA | D32: Novos Produtos | E32: Novas matérias-primas | F32: Melhoria de Produto | G32: Melhoria de Processo | H32: ILSI
A33: Bioagri Analises de alimentos Ltda | B33: 00.000.410/0001-32 | C33: Terceiros | D33: =SUMIFS('(a) Investimentos'!W$8:W$114,'(a) Investimentos'!$F$8:$F$114,$A33,'(a) Investimentos'!$G$8:$G$114,$B33,'(a) Investimentos'!$I$8:$I$114,$C33) -> 651.7 | E33: =SUMIFS('(a) Investimentos'!X$8:X$114,'(a) Investimentos'!$F$8:$F$114,$A33,'(a) Investimentos'!$G$8:$G$114,$B33,'(a) Investimentos'!$I$8:$I$114,$C33) -> 0 | F33: =SUMIFS('(a) Investimentos'!Y$8:Y$114,'(a) Investimentos'!$F$8:$F$114,$A33,'(a) Investimentos'!$G$8:$G$114,$B33,'(a) Investimentos'!$I$8:$I$114,$C33) -> 651.7 | G33: =SUMIFS('(a) Investimentos'!Z$8:Z$114,'(a) Investimentos'!$F$8:$F$114,$A33,'(a) Investimentos'!$G$8:$G$114,$B33,'(a) Investimentos'!$I$8:$I$114,$C33) -> 1303.4 | H33: =SUMIFS('(a) Investimentos'!AA$8:AA$114,'(a) Investimentos'!$F$8:$F$114,$A33,'(a) Investimentos'!$G$8:$G$114,$B33,'(a) Investimentos'!$I$8:$I$114,$C33) -> 0
A34: Oraculum Inteligência em Nutrição e Saúde Ltda - ME | B34: 21.213.714/0001-58 | C34: Terceiros | D34: =SUMIFS('(a) Investimentos'!W$8:W$114,'(a) Investimentos'!$F$8:$F$114,$A34,'(a) Investimentos'!$G$8:$G$114,$B34,'(a) Investimentos'!$I$8:$I$114,$C34) -> 12042 | E34: =SUMIFS('(a) Investimentos'!X$8:X$114,'(a) Investimentos'!$F$8:$F$114,$A34,'(a) Investimentos'!$G$8:$G$114,$B34,'(a) Investimentos'!$I$8:$I$114,$C34) -> 0 | F34: =SUMIFS('(a) Investimentos'!Y$8:Y$114,'(a) Investimentos'!$F$8:$F$114,$A34,'(a) Investimentos'!$G$8:$G$114,$B34,'(a) Investimentos'!$I$8:$I$114,$C34) -> 0 | G34: =SUMIFS('(a) Investimentos'!Z$8:Z$114,'(a) Investimentos'!$F$8:$F$114,$A34,'(a) Investimentos'!$G$8:$G$114,$B34,'(a) Investimentos'!$I$8:$I$114,$C34) -> 0 | H34: =SUMIFS('(a) Investimentos'!AA$8:AA$114,'(a) Investimentos'!$F$8:$F$114,$A34,'(a) Investimentos'!$G$8:$G$114,$B34,'(a) Investimentos'!$I$8:$I$114,$C34) -> 0
A35: Impressione Impressão Digital Ltda - ME | B35: 12.457.568/0001-15 | C35: Terceiros | D35: =SUMIFS('(a) Investimentos'!W$8:W$114,'(a) Investimentos'!$F$8:$F$114,$A35,'(a) Investimentos'!$G$8:$G$114,$B35,'(a) Investimentos'!$I$8:$I$114,$C35) -> 0 | E35: =SUMIFS('(a) Investimentos'!X$8:X$114,'(a) Investimentos'!$F$8:$F$114,$A35,'(a) Investimentos'!$G$8:$G$114,$B35,'(a) Investimentos'!$I$8:$I$114,$C35) -> 0 | F35: =SUMIFS('(a) Investimentos'!Y$8:Y$114,'(a) Investimentos'!$F$8:$F$114,$A35,'(a) Investimentos'!$G$8:$G$114,$B35,'(a) Investimentos'!$I$8:$I$114,$C35) -> 0 | G35: =SUMIFS('(a) Investimentos'!Z$8:Z$114,'(a) Investimentos'!$F$8:$F$114,$A35,'(a) Investimentos'!$G$8:$G$114,$B35,'(a) Investimentos'!$I$8:$I$114,$C35) -> 0 | H35: =SUMIFS('(a) Investimentos'!AA$8:AA$114,'(a) Investimentos'!$F$8:$F$114,$A35,'(a) Investimentos'!$G$8:$G$114,$B35,'(a) Investimentos'!$I$8:$I$114,$C35) -> 0
A36: Laboratório Alac Ltda | B36: 94.088.952/0001-52 | C36: Terceiros | D36: =SUMIFS('(a) Investimentos'!W$8:W$114,'(a) Investimentos'!$F$8:$F$114,$A36,'(a) Investimentos'!$G$8:$G$114,$B36,'(a) Investimentos'!$I$8:$I$114,$C36) -> 2425.256 | E36: =SUMIFS('(a) Investimentos'!X$8:X$114,'(a) Investimentos'!$F$8:$F$114,$A36,'(a) Investimentos'!$G$8:$G$114,$B36,'(a) Investimentos'!$I$8:$I$114,$C36) -> 3919.2255 | F36: =SUMIFS('(a) Investimentos'!Y$8:Y$114,'(a) Investimentos'!$F$8:$F$114,$A36,'(a) Investimentos'!$G$8:$G$114,$B36,'(a) Investimentos'!$I$8:$I$114,$C36) -> 8020.159 | G36: =SUMIFS('(a) Investimentos'!Z$8:Z$114,'(a) Investimentos'!$F$8:$F$114,$A36,'(a) Investimentos'!$G$8:$G$114,$B36,'(a) Investimentos'!$I$8:$I$114,$C36) -> 290 | H36: =SUMIFS('(a) Investimentos'!AA$8:AA$114,'(a) Investimentos'!$F$8:$F$114,$A36,'(a) Investimentos'!$G$8:$G$114,$B36,'(a) Investimentos'!$I$8:$I$114,$C36) -> 0
A37: Fundação de desenv. Da pesquisa do agronegócio - FUNDEPAG | B37: 50.276.237/0001-78 | C37: Terceiros | D37: =SUMIFS('(a) Investimentos'!W$8:W$114,'(a) Investimentos'!$F$8:$F$114,$A37,'(a) Investimentos'!$G$8:$G$114,$B37,'(a) Investimentos'!$I$8:$I$114,$C37) -> 5804.2 | E37: =SUMIFS('(a) Investimentos'!X$8:X$114,'(a) Investimentos'!$F$8:$F$114,$A37,'(a) Investimentos'!$G$8:$G$114,$B37,'(a) Investimentos'!$I$8:$I$114,$C37) -> 2364.7 | F37: =SUMIFS('(a) Investimentos'!Y$8:Y$114,'(a) Investimentos'!$F$8:$F$114,$A37,'(a) Investimentos'!$G$8:$G$114,$B37,'(a) Investimentos'!$I$8:$I$114,$C37) -> 12665.9 | G37: =SUMIFS('(a) Investimentos'!Z$8:Z$114,'(a) Investimentos'!$F$8:$F$114,$A37,'(a) Investimentos'!$G$8:$G$114,$B37,'(a) Investimentos'!$I$8:$I$114,$C37) -> 0 | H37: =SUMIFS('(a) Investimentos'!AA$8:AA$114,'(a) Investimentos'!$F$8:$F$114,$A37,'(a) Investimentos'!$G$8:$G$114,$B37,'(a) Investimentos'!$I$8:$I$114,$C37) -> 0
A38: Sandra Marcia da Silva de Souza - ME | B38: 13.807.270/0001-50 | C38: Terceiros | D38: =SUMIFS('(a) Investimentos'!W$8:W$114,'(a) Investimentos'!$F$8:$F$114,$A38,'(a) Investimentos'!$G$8:$G$114,$B38,'(a) Investimentos'!$I$8:$I$114,$C38) -> 0 | E38: =SUMIFS('(a) Investimentos'!X$8:X$114,'(a) Investimentos'!$F$8:$F$114,$A38,'(a) Investimentos'!$G$8:$G$114,$B38,'(a) Investimentos'!$I$8:$I$114,$C38) -> 0 | F38: =SUMIFS('(a) Investimentos'!Y$8:Y$114,'(a) Investimentos'!$F$8:$F$114,$A38,'(a) Investimentos'!$G$8:$G$114,$B38,'(a) Investimentos'!$I$8:$I$114,$C38) -> 0 | G38: =SUMIFS('(a) Investimentos'!Z$8:Z$114,'(a) Investimentos'!$F$8:$F$114,$A38,'(a) Investimentos'!$G$8:$G$114,$B38,'(a) Investimentos'!$I$8:$I$114,$C38) -> 0 | H38: =SUMIFS('(a) Investimentos'!AA$8:AA$114,'(a) Investimentos'!$F$8:$F$114,$A38,'(a) Investimentos'!$G$8:$G$114,$B38,'(a) Investimentos'!$I$8:$I$114,$C38) -> 0
A39: Clínica Médica Mourão Faccio S/S | B39: 04.404.467/0001-58 | C39: Terceiros | D39: =SUMIFS('(a) Investimentos'!W$8:W$114,'(a) Investimentos'!$F$8:$F$114,$A39,'(a) Investimentos'!$G$8:$G$114,$B39,'(a) Investimentos'!$I$8:$I$114,$C39) -> 24000 | E39: =SUMIFS('(a) Investimentos'!X$8:X$114,'(a) Investimentos'!$F$8:$F$114,$A39,'(a) Investimentos'!$G$8:$G$114,$B39,'(a) Investimentos'!$I$8:$I$114,$C39) -> 0 | F39: =SUMIFS('(a) Investimentos'!Y$8:Y$114,'(a) Investimentos'!$F$8:$F$114,$A39,'(a) Investimentos'!$G$8:$G$114,$B39,'(a) Investimentos'!$I$8:$I$114,$C39) -> 0 | G39: =SUMIFS('(a) Investimentos'!Z$8:Z$114,'(a) Investimentos'!$F$8:$F$114,$A39,'(a) Investimentos'!$G$8:$G$114,$B39,'(a) Investimentos'!$I$8:$I$114,$C39) -> 0 | H39: =SUMIFS('(a) Investimentos'!AA$8:AA$114,'(a) Investimentos'!$F$8:$F$114,$A39,'(a) Investimentos'!$G$8:$G$114,$B39,'(a) Investimentos'!$I$8:$I$114,$C39) -> 0
A40: Contabilista Papelaria e informática | B40: 77.765.840/0001-70 | C40: Terceiros | D40: =SUMIFS('(a) Investimentos'!W$8:W$114,'(a) Investimentos'!$F$8:$F$114,$A40,'(a) Investimentos'!$G$8:$G$114,$B40,'(a) Investimentos'!$I$8:$I$114,$C40) -> 0 | E40: =SUMIFS('(a) Investimentos'!X$8:X$114,'(a) Investimentos'!$F$8:$F$114,$A40,'(a) Investimentos'!$G$8:$G$114,$B40,'(a) Investimentos'!$I$8:$I$114,$C40) -> 0 | F40: =SUMIFS('(a) Investimentos'!Y$8:Y$114,'(a) Investimentos'!$F$8:$F$114,$A40,'(a) Investimentos'!$G$8:$G$114,$B40,'(a) Investimentos'!$I$8:$I$114,$C40) -> 0 | G40: =SUMIFS('(a) Investimentos'!Z$8:Z$114,'(a) Investimentos'!$F$8:$F$114,$A40,'(a) Investimentos'!$G$8:$G$114,$B40,'(a) Investimentos'!$I$8:$I$114,$C40) -> 0 | H40: =SUMIFS('(a) Investimentos'!AA$8:AA$114,'(a) Investimentos'!$F$8:$F$114,$A40,'(a) Investimentos'!$G$8:$G$114,$B40,'(a) Investimentos'!$I$8:$I$114,$C40) -> 0
A41: Medicalcom Hospitalares Eireli - ME | B41: 21.059.832/0001-53 | C41: Terceiros | D41: =SUMIFS('(a) Investimentos'!W$8:W$114,'(a) Investimentos'!$F$8:$F$114,$A41,'(a) Investimentos'!$G$8:$G$114,$B41,'(a) Investimentos'!$I$8:$I$114,$C41) -> 0 | E41: =SUMIFS('(a) Investimentos'!X$8:X$114,'(a) Investimentos'!$F$8:$F$114,$A41,'(a) Investimentos'!$G$8:$G$114,$B41,'(a) Investimentos'!$I$8:$I$114,$C41) -> 0 | F41: =SUMIFS('(a) Investimentos'!Y$8:Y$114,'(a) Investimentos'!$F$8:$F$114,$A41,'(a) Investimentos'!$G$8:$G$114,$B41,'(a) Investimentos'!$I$8:$I$114,$C41) -> 0 | G41: =SUMIFS('(a) Investimentos'!Z$8:Z$114,'(a) Investimentos'!$F$8:$F$114,$A41,'(a) Investimentos'!$G$8:$G$114,$B41,'(a) Investimentos'!$I$8:$I$114,$C41) -> 0 | H41: =SUMIFS('(a) Investimentos'!AA$8:AA$114,'(a) Investimentos'!$F$8:$F$114,$A41,'(a) Investimentos'!$G$8:$G$114,$B41,'(a) Investimentos'!$I$8:$I$114,$C41) -> 0
A42: Comercial Brey Ltda | B42: 02.608.645/0001-37 | C42: Terceiros | D42: =SUMIFS('(a) Investimentos'!W$8:W$114,'(a) Investimentos'!$F$8:$F$114,$A42,'(a) Investimentos'!$G$8:$G$114,$B42,'(a) Investimentos'!$I$8:$I$114,$C42) -> 0 | E42: =SUMIFS('(a) Investimentos'!X$8:X$114,'(a) Investimentos'!$F$8:$F$114,$A42,'(a) Investimentos'!$G$8:$G$114,$B42,'(a) Investimentos'!$I$8:$I$114,$C42) -> 0 | F42: =SUMIFS('(a) Investimentos'!Y$8:Y$114,'(a) Investimentos'!$F$8:$F$114,$A42,'(a) Investimentos'!$G$8:$G$114,$B42,'(a) Investimentos'!$I$8:$I$114,$C42) -> 0 | G42: =SUMIFS('(a) Investimentos'!Z$8:Z$114,'(a) Investimentos'!$F$8:$F$114,$A42,'(a) Investimentos'!$G$8:$G$114,$B42,'(a) Investimentos'!$I$8:$I$114,$C42) -> 0 | H42: =SUMIFS('(a) Investimentos'!AA$8:AA$114,'(a) Investimentos'!$F$8:$F$114,$A42,'(a) Investimentos'!$G$8:$G$114,$B42,'(a) Investimentos'!$I$8:$I$114,$C42) -> 0
A43: Valéria Paschoal Editora Produtos e Serviços Ltda EPP | B43: 06.635.677/0001-82 | C43: Terceiros | D43: =SUMIFS('(a) Investimentos'!W$8:W$114,'(a) Investimentos'!$F$8:$F$114,$A43,'(a) Investimentos'!$G$8:$G$114,$B43,'(a) Investimentos'!$I$8:$I$114,$C43) -> 0 | E43: =SUMIFS('(a) Investimentos'!X$8:X$114,'(a) Investimentos'!$F$8:$F$114,$A43,'(a) Investimentos'!$G$8:$G$114,$B43,'(a) Investimentos'!$I$8:$I$114,$C43) -> 0 | F43: =SUMIFS('(a) Investimentos'!Y$8:Y$114,'(a) Investimentos'!$F$8:$F$114,$A43,'(a) Investimentos'!$G$8:$G$114,$B43,'(a) Investimentos'!$I$8:$I$114,$C43) -> 0 | G43: =SUMIFS('(a) Investimentos'!Z$8:Z$114,'(a) Investimentos'!$F$8:$F$114,$A43,'(a) Investimentos'!$G$8:$G$114,$B43,'(a) Investimentos'!$I$8:$I$114,$C43) -> 0 | H43: =SUMIFS('(a) Investimentos'!AA$8:AA$114,'(a) Investimentos'!$F$8:$F$114,$A43,'(a) Investimentos'!$G$8:$G$114,$B43,'(a) Investimentos'!$I$8:$I$114,$C43) -> 0
A44: Nutrihealth Comercio de Produtos Alimentícios Eireli ME | B44: 14.492.128/0001-89 | C44: Terceiros | D44: =SUMIFS('(a) Investimentos'!W$8:W$114,'(a) Investimentos'!$F$8:$F$114,$A44,'(a) Investimentos'!$G$8:$G$114,$B44,'(a) Investimentos'!$I$8:$I$114,$C44) -> 0 | E44: =SUMIFS('(a) Investimentos'!X$8:X$114,'(a) Investimentos'!$F$8:$F$114,$A44,'(a) Investimentos'!$G$8:$G$114,$B44,'(a) Investimentos'!$I$8:$I$114,$C44) -> 0 | F44: =SUMIFS('(a) Investimentos'!Y$8:Y$114,'(a) Investimentos'!$F$8:$F$114,$A44,'(a) Investimentos'!$G$8:$G$114,$B44,'(a) Investimentos'!$I$8:$I$114,$C44) -> 0 | G44: =SUMIFS('(a) Investimentos'!Z$8:Z$114,'(a) Investimentos'!$F$8:$F$114,$A44,'(a) Investimentos'!$G$8:$G$114,$B44,'(a) Investimentos'!$I$8:$I$114,$C44) -> 0 | H44: =SUMIFS('(a) Investimentos'!AA$8:AA$114,'(a) Investimentos'!$F$8:$F$114,$A44,'(a) Investimentos'!$G$8:$G$114,$B44,'(a) Investimentos'!$I$8:$I$114,$C44) -> 0
... A54: L Dutra Serviços ME | B54: 18.337.175/0001-54 | C54: Terceiros | D54: =SUMIFS('(a) Investimentos'!W$8:W$114,'(a) Investimentos'!$F$8:$F$114,$A54,'(a) Investimentos'!$G$8:$G$114,$B54,'(a) Investimentos'!$I$8:$I$114,$C54) -> 27893.984 | E54: =SUMIFS('(a) Investimentos'!X$8:X$114,'(a) Investimentos'!$F$8:$F$114,$A54,'(a) Investimentos'!$G$8:$G$114,$B54,'(a) Investimentos'!$I$8:$I$114,$C54) -> 27893.984 | F54: =SUMIFS('(a) Investimentos'!Y$8:Y$114,'(a) Investimentos'!$F$8:$F$114,$A54,'(a) Investimentos'!$G$8:$G$114,$B54,'(a) Investimentos'!$I$8:$I$114,$C54) -> 27893.984 | G54: =SUMIFS('(a) Investimentos'!Z$8:Z$114,'(a) Investimentos'!$F$8:$F$114,$A54,'(a) Investimentos'!$G$8:$G$114,$B54,'(a) Investimentos'!$I$8:$I$114,$C54) -> 27893.984 | H54: =SUMIFS('(a) Investimentos'!AA$8:AA$114,'(a) Investimentos'!$F$8:$F$114,$A54,'(a) Investimentos'!$G$8:$G$114,$B54,'(a) Investimentos'!$I$8:$I$114,$C54) -> 0

Sheet (a) Investimentos
A1: PRODIET
A2: Anexo I - Investimentos - Materiais
A3: INOVAÇÃO TECNOLÓGICA 2016
I4: Material | J4: =SUMIF($I$8:$I$115,I4,$N$8:$N$115) -> 16180.07
I5: Terceiros | J5: =SUMIF($I$8:$I$115,I5,$N$8:$N$115) -> 257166.12
D6: =SUBTOTAL(9,D8:D114) -> 16180.07 | N6: =SUBTOTAL(9,N8:N114) -> 16180.07 | P6: Participação nos projetos | U6: =SUM(U8:U90)/COUNT(U8:U90) -> 1 | W6: Dispêndio (R$) por projeto
A7: Tipo de documento | B7: Documento | C7: DOCS | D7: Total NF | E7: PRODUTOS | F7: RECURSO | G7: CPF / CNPJ | H7: ATIVIDADE | I7: NATUREZA | J7: DATA | K7: Mês | L7: QTD | M7: UNITÁRIO | N7: TOTAL | P7: Novos Produtos | Q7: Novas matérias-primas | R7: Melhoria de Produto | S7: Melhoria de Processo | T7: ILSI | U7: Total | W7: Novos Produtos | X7: Novas matérias-primas | Y7: Melhoria de Produto | Z7: Melhoria de Processo | AA7: ILSI
A8: NF | B8: 34840 | C8: 1 | D8: 1303.4 | E8: Bemmax, Peptimax | F8: Bioagri Analises de alimentos Ltda | G8: 00.000.410/0001-32 | H8: Análise de ácidos graxos | I8: Terceiros | J8: 42500 | K8: 5 | L8: 1 | M8: 1303.4 | N8: =M8*L8 -> 1303.4 | P8: 0.5 | Q8: 0 | R8: 0 | S8: 0.5 | T8: 0 | U8: =SUM(P8:T8) -> 1 | W8: =$N8*P8 -> 651.7 | X8: =$N8*Q8 -> 0 | Y8: =$N8*R8 -> 0 | Z8: =$N8*S8 -> 651.7 | AA8: =$N8*T8 -> 0
A9: Bilhete e-ticket | B9: 577 0005868279 | C9: 2 | D9: 579.24 | E9: Immax | F9: Azul linhas aéreas | H9: Passagens Hellin IDA e VOLTA Ribeirão Preto | I9: Material | J9: 42641 | K9: 9 | L9: 1 | M9: 579.24 | N9: =M9*L9 -> 579.24 | P9: 1 | Q9: 0 | R9: 0 | S9: 0 | T9: 0 | U9: =SUM(P9:T9) -> 1 | W9: =$N9*P9 -> 579.24 | X9: =$N9*Q9 -> 0 | Y9: =$N9*R9 -> 0 | Z9: =$N9*S9 -> 0 | AA9: =$N9*T9 -> 0
A10: Cupons fiscais | C10: 2 | D10: 138.01 | E10: Immax | F10: Diversos | H10: Alimentação e táxi Hellin Ribeirão Preto | I10: Material | J10: 42641 | K10: 9 | L10: 1 | M10: 138.01 | N10: =M10*L10 -> 138.01 | P10: 1 | Q10: 0 | R10: 0 | S10: 0 | T10: 0 | U10: =SUM(P10:T10) -> 1 | W10: =$N10*P10 -> 138.01 | X10: =$N10*Q10 -> 0 | Y10: =$N10*R10 -> 0 | Z10: =$N10*S10 -> 0 | AA10: =$N10*T10 -> 0
A11: NF | B11: 98 | C11: 4 | D11: 12042 | E11: Immax | F11: Oraculum Inteligência em Nutrição e Saúde Ltda - ME | G11: 21.213.714/0001-58 | H11: Desenvolvimento de receitas Immax | I11: Terceiros | J11: 42628 | K11: 9 | L11: 1 | M11: 12042 | N11: =M11*L11 -> 12042 | P11: 1 | Q11: 0 | R11: 0 | S11: 0 | T11: 0 | U11: =SUM(P11:T11) -> 1 | W11: =$N11*P11 -> 12042 | X11: =$N11*Q11 -> 0 | Y11: =$N11*R11 -> 0 | Z11: =$N11*S11 -> 0 | AA11: =$N11*T11 -> 0
A12: NF | B12: 11849 | C12: 5 | D12: 877.5 | E12: Immax | F12: Impressione Impressão Digital Ltda - ME | G12: 12.457.568/0001-15 | H12: Immax | I12: Material | J12: 42529 | K12: 6 | L12: 1 | M12: 877.5 | N12: =M12*L12 -> 877.5 | P12: 1 | Q12: 0 | R12: 0 | S12: 0 | T12: 0 | U12: =SUM(P12:T12) -> 1 | W12: =$N12*P12 -> 877.5 | X12: =$N12*Q12 -> 0 | Y12: =$N12*R12 -> 0 | Z12: =$N12*S12 -> 0 | AA12: =$N12*T12 -> 0
A13: NF | B13: 9354 | C13: 6 | D13: 1230 | E13: Immax | F13: Laboratório Alac Ltda | G13: 94.088.952/0001-52 | H13: Análise de micronutrientes Immax | I13: Terceiros | J13: 42587 | K13: 8 | L13: 1 | M13: 1230 | N13: =M13*L13 -> 1230 | P13: 1 | Q13: 0 | R13: 0 | S13: 0 | T13: 0 | U13: =SUM(P13:T13) -> 1 | W13: =$N13*P13 -> 1230 | X13: =$N13*Q13 -> 0 | Y13: =$N13*R13 -> 0 | Z13: =$N13*S13 -> 0 | AA13: =$N13*T13 -> 0
A14: NF | B14: 81028 | C14: 7 | D14: 2401 | E14: Immax | F14: Fundação de desenv. Da pesquisa do agronegócio - FUNDEPAG | G14: 50.276.237/0001-78 | H14: Análises físico-químicas Immax | I14: Terceiros | J14: 42565 | K14: 7 | L14: 1 | M14: 2401 | N14: =M14*L14 -> 2401 | P14: 1 | Q14: 0 | R14: 0 | S14: 0 | T14: 0 | U14: =SUM(P14:T14) -> 1 | W14: =$N14*P14 -> 2401 | X14: =$N14*Q14 -> 0 | Y14: =$N14*R14 -> 0 | Z14: =$N14*S14 -> 0 | AA14: =$N14*T14 -> 0
A15: NF | B15: 81357 | C15: 8 | D15: 2401 | E15: Immax | F15: Fundação de desenv. Da pesquisa do agronegócio - FUNDEPAG | G15: 50.276.237/0001-78 | H15: Análises físico-químicas Immax | I15: Terceiros | J15: 42585 | K15: 8 | L15: 1 | M15: 2401 | N15: =M15*L15 -> 2401 | P15: 1 | Q15: 0 | R15: 0 | S15: 0 | T15: 0 | U15: =SUM(P15:T15) -> 1 | W15: =$N15*P15 -> 2401 | X15: =$N15*Q15 -> 0 | Y15: =$N15*R15 -> 0 | Z15: =$N15*S15 -> 0 | AA15: =$N15*T15 -> 0
A16: NF | B16: 38 | C16: 9 | D16: 1000 | E16: Immax | F16: Sandra Marcia da Silva de Souza - ME | G16: 13.807.270/0001-50 | H16: Immax | I16: Material | J16: 42611 | K16: 8 | L16: 1 | M16: 1000 | N16: =M16*L16 -> 1000 | P16: 1 | Q16: 0 | R16: 0 | S16: 0 | T16: 0 | U16: =SUM(P16:T16) -> 1 | W16: =$N16*P16 -> 1000 | X16: =$N16*Q16 -> 0 | Y16: =$N16*R16 -> 0 | Z16: =$N16*S16 -> 0 | AA16: =$N16*T16 -> 0
A17: NF | B17: 48 | C17: 10 | D17: 89 | E17: Immax | F17: Sandra Marcia da Silva de Souza - ME | G17: 13.807.270/0001-50 | H17: Immax | I17: Material | J17: 42654 | K17: 10 | L17: 1 | M17: 89 | N17: =M17*L17 -> 89 | P17: 1 | Q17: 0 | R17: 0 | S17: 0 | T17: 0 | U17: =SUM(P17:T17) -> 1 | W17: =$N17*P17 -> 89 | X17: =$N17*Q17 -> 0 | Y17: =$N17*R17 -> 0 | Z17: =$N17*S17 -> 0 | AA17: =$N17*T17 -> 0
A18: NF | B18: 80303 | C18: 11 | D18: 524 | E18: Immax | F18: Fundação de desenv. Da pesquisa do agronegócio - FUNDEPAG | G18: 50.276.237/0001-78 | H18: Análise de ácidos graxos Immax | I18: Terceiros | J18: 42541 | K18: 6 | L18: 1 | M18: 524 | N18: =M18*L18 -> 524 | P18: 1 | Q18: 0 | R18: 0 | S18: 0 | T18: 0 | U18: =SUM(P18:T18) -> 1 | W18: =$N18*P18 -> 524 | X18: =$N18*Q18 -> 0 | Y18: =$N18*R18 -> 0 | Z18: =$N18*S18 -> 0 | AA18: =$N18*T18 -> 0
A19: NF | B19: 423 | C19: 12 | D19: 24000 | E19: Immax | F19: Clínica Médica Mourão Faccio S/S | G19: 04.404.467/0001-58 | H19: 1ª parcela do contrato de prestação de serviço estudo clínico Immax | I19: Terceiros | J19: 42608 | K19: 8 | L19: 1 | M19: 24000 | N19: =M19*L19 -> 24000 | P19: 1 | Q19: 0 | R19: 0 | S19: 0 | T19: 0 | U19: =SUM(P19:T19) -> 1 | W19: =$N19*P19 -> 24000 | X19: =$N19*Q19 -> 0 | Y19: =$N19*R19 -> 0 | Z19: =$N19*S19 -> 0 | AA19: =$N19*T19 -> 0
A20: NF | B20: 776332 | C20: 13 | D20: 105.6 | E20: Immax | F20: Contabilista Papelaria e informática | G20: 77.765.840/0001-70 | H20: Materiais | I20: Material | J20: 42633 | K20: 9 | L20: 1 | M20: 105.6 | N20: =M20*L20 -> 105.6 | P20: 1 | Q20: 0 | R20: 0 | S20: 0 | T20: 0 | U20: =SUM(P20:T20) -> 1 | W20: =$N20*P20 -> 105.6 | X20: =$N20*Q20 -> 0 | Y20: =$N20*R20 -> 0 | Z20: =$N20*S20 -> 0 | AA20: =$N20*T20 -> 0
A21: NF | B21: 5270 | C21: 14 | D21: 1323.55 | E21: Immax | F21: Medicalcom Hospitalares Eireli - ME | G21: 21.059.832/0001-53 | H21: Balança de controle corporal - estudo clínico Immax | I21: Material | J21: 42520 | K21: 5 | L21: 1 | M21: 1323.55 | N21: =M21*L21 -> 1323.55 | P21: 1 | Q21: 0 | R21: 0 | S21: 0 | T21: 0 | U21: =SUM(P21:T21) -> 1 | W21: =$N21*P21 -> 1323.55 | X21: =$N21*Q21 -> 0 | Y21: =$N21*R21 -> 0 | Z21: =$N21*S21 -> 0 | AA21: =$N21*T21 -> 0
A22: NF | B22: 6739 | C22: 15 | D22: 240 | E22: Leites terapêuticos | F22: Comercial Brey Ltda | G22: 02.608.645/0001-37 | H22: Seladora de bancada - Leites terapêuticos | I22: Material | J22: 42675 | K22: 11 | L22: 1 | M22: 240 | N22: =M22*L22 -> 240 | P22: 1 | Q22: 0 | R22: 0 | S22: 0 | T22: 0 | U22: =SUM(P22:T22) -> 1 | W22: =$N22*P22 -> 240 | X22: =$N22*Q22 -> 0 | Y22: =$N22*R22 -> 0 | Z22: =$N22*S22 -> 0 | AA22: =$N22*T22 -> 0
... A24: NF | B24: 2162 | C24: 17 | D24: 127.68 | E24: Alzheimer, Bemmax, Immax | F24: Nutrihealth Comercio de Produtos Alimentícios Eireli ME | G24: 14.492.128/0001-89 | H24: Compra de produtos concorrentes | I24: Material | J24: 42706 | K24: 12 | L24: 1 | M24: 127.68 | N24: =M24*L24 -> 127.68 | P24: 1 | Q24: 0 | R24: 0 | S24: 0 | T24: 0 | U24: =SUM(P24:T24) -> 1 | W24: =$N24*P24 -> 127.68 | X24: =$N24*Q24 -> 0 | Y24: =$N24*R24 -> 0 | Z24: =$N24*S24 -> 0 | AA24: =$N24*T24 -> 0
A25: Invoice | B25: 422135 | C25: 18 | D25: 41.25 | E25: Trophic Junior | F25: Covance - The Development Service Company | H25: Densidade volumétrica Trophic Junior | I25: Material | J25: 42605 | K25: 8 | L25: 1 | M25: 41.25 | N25: =M25*L25 -> 41.25 | P25: 1 | Q25: 0 | R25: 0 | S25: 0 | T25: 0 | U25: =SUM(P25:T25) -> 1 | W25: =$N25*P25 -> 41.25 | X25: =$N25*Q25 -> 0 | Y25: =$N25*R25 -> 0 | Z25: =$N25*S25 -> 0 | AA25: =$N25*T25 -> 0
A26: Expresso | B26: Conhec. Aéreo 9692285061 | C26: 19 | D26: 436.44 | E26: Trophic Junior | H26: Envio de amostras de T. Junior para o exterior (Stern) | I26: Material | J26: 42576 | K26: 7 | L26: 1 | M26: 436.44 | N26: =M26*L26 -> 436.44 | P26: 1 | Q26: 0 | R26: 0 | S26: 0 | T26: 0 | U26: =SUM(P26:T26) -> 1 | W26: =$N26*P26 -> 436.44 | X26: =$N26*Q26 -> 0 | Y26: =$N26*R26 -> 0 | Z26: =$N26*S26 -> 0 | AA26: =$N26*T26 -> 0
A27: NF | B27: 5542 | C27: 20 | D27: 3220 | E27: Trophic Junior e mix 16006 | F27: Laboratório Alac Ltda | G27: 94.088.952/0001-52 | H27: Análise de micronutrentes T. Junior (mix 16006) | I27: Terceiros | J27: 42506 | K27: 5 | L27: 0.357195 | M27: 3220 | N27: =M27*L27 -> 1150.1679 | P27: 0.5 | Q27: 0.5 | R27: 0 | S27: 0 | T27: 0 | U27: =SUM(P27:T27) -> 1 | W27: =$N27*P27 -> 575.08395 | X27: =$N27*Q27 -> 575.08395 | Y27: =$N27*R27 -> 0 | Z27: =$N27*S27 -> 0 | AA27: =$N27*T27 -> 0
A28: Fatura | B28: AWB 6152 6505 2282 | C28: 21 | D28: 107.33 | E28: Mix de minerais 16006 | F28: FedEx | G28: 00.676.486/0001-82 | H28: Recebimento de amostra de mix 16006 | I28: Material | J28: 42432 | K28: 3 | L28: 1 | M28: 107.33 | N28: =M28*L28 -> 107.33 | P28: 0 | Q28: 1 | R28: 0 | S28: 0 | T28: 0 | U28: =SUM(P28:T28) -> 1 | W28: =$N28*P28 -> 0 | X28: =$N28*Q28 -> 107.33 | Y28: =$N28*R28 -> 0 | Z28: =$N28*S28 -> 0 | AA28: =$N28*T28 -> 0
A29: NF | B29: 2177 | C29: 22 | D29: 415.6 | E29: PHA Costantino | F29: A. Costantino & C. spa | H29: Recebimento de amostra de PHA Costantino | I29: Material | J29: 42719 | K29: 12 | L29: 1 | M29: 415.6 | N29: =M29*L29 -> 415.6 | P29: 0 | Q29: 1 | R29: 0 | S29: 0 | T29: 0 | U29: =SUM(P29:T29) -> 1 | W29: =$N29*P29 -> 0 | X29: =$N29*Q29 -> 415.6 | Y29: =$N29*R29 -> 0 | Z29: =$N29*S29 -> 0 | AA29: =$N29*T29 -> 0
A30: NF | B30: 27824 | C30: 23 | D30: 950 | E30: Vital Rice | F30: Labor Tres Laboratórios e Consultoria Técnica Ltda | G30: 02.021.076/0001-29 | H30: Análises físico-químicas e microbiológicas Vital Rice | I30: Terceiros | J30: 42647 | K30: 10 | L30: 1 | M30: 950 | N30: =M30*L30 -> 950 | P30: 1 | Q30: 0 | R30: 0 | S30: 0 | T30: 0 | U30: =SUM(P30:T30) -> 1 | W30: =$N30*P30 -> 950 | X30: =$N30*Q30 -> 0 | Y30: =$N30*R30 -> 0 | Z30: =$N30*S30 -> 0 | AA30: =$N30*T30 -> 0
A31: Cupom fiscal | B31: 71047 | C31: 24 | D31: 77.49 | E31: Vital Rice Complete | F31: Callfarma | G31: 08.011.373/0001-70 | H31: Compra de produtos concorrentes | I31: Material | J31: 42664 | K31: 10 | L31: 1 | M31: 77.49 | N31: =M31*L31 -> 77.49 | P31: 1 | Q31: 0 | R31: 0 | S31: 0 | T31: 0 | U31: =SUM(P31:T31) -> 1 | W31: =$N31*P31 -> 77.49 | X31: =$N31*Q31 -> 0 | Y31: =$N31*R31 -> 0 | Z31: =$N31*S31 -> 0 | AA31: =$N31*T31 -> 0
A32: Recibo | B32: 2358 | C32: 25 | D32: 574 | E32: Vital Rice Complete | F32: Associação Paranaense de Cultura - APC | G32: 76.659.820/0003-13 | H32: Teste de bancada na PUC-PR | I32: Terceiros | J32: 42398 | K32: 1 | L32: 1 | M32: 574 | N32: =M32*L32 -> 574 | P32: 1 | Q32: 0 | R32: 0 | S32: 0 | T32: 0 | U32: =SUM(P32:T32) -> 1 | W32: =$N32*P32 -> 574 | X32: =$N32*Q32 -> 0 | Y32: =$N32*R32 -> 0 | Z32: =$N32*S32 -> 0 | AA32: =$N32*T32 -> 0
A33: Recibo | B33: 2389 | C33: 26 | D33: 210 | E33: Vital Rice Complete | F33: Associação Paranaense de Cultura - APC | G33: 76.659.820/0003-13 | H33: Teste de bancada na PUC-PR | I33: Terceiros | J33: 42416 | K33: 2 | L33: 1 | M33: 210 | N33: =M33*L33 -> 210 | P33: 1 | Q33: 0 | R33: 0 | S33: 0 | T33: 0 | U33: =SUM(P33:T33) -> 1 | W33: =$N33*P33 -> 210 | X33: =$N33*Q33 -> 0 | Y33: =$N33*R33 -> 0 | Z33: =$N33*S33 -> 0 | AA33: =$N33*T33 -> 0
A34: NF | B34: 7567 | C34: 27 | D34: 450 | E34: Vital Rice Complete | F34: Laboratório Alac Ltda | G34: 94.088.952/0001-52 | H34: Teste de alergênicos lecitina de soja em pó | I34: Terceiros | J34: 42548 | K34: 6 | L34: 1 | M34: 450 | N34: =M34*L34 -> 450 | P34: 1 | Q34: 0 | R34: 0 | S34: 0 | T34: 0 | U34: =SUM(P34:T34) -> 1 | W34: =$N34*P34 -> 450 | X34: =$N34*Q34 -> 0 | Y34: =$N34*R34 -> 0 | Z34: =$N34*S34 -> 0 | AA34: =$N34*T34 -> 0
A35: Cupons fiscais | C35: 28 | D35: 315.63 | E35: Feira de nutrição enteral | H35: Gastos em Feira de Nutrição Enteral (Felanpe) para prospecção de novos projetos | I35: Material | J35: 42667 | K35: 10 | L35: 1 | M35: 315.63 | N35: =M35*L35 -> 315.63 | P35: 1 | Q35: 0 | R35: 0 | S35: 0 | T35: 0 | U35: =SUM(P35:T35) -> 1 | W35: =$N35*P35 -> 315.63 | X35: =$N35*Q35 -> 0 | Y35: =$N35*R35 -> 0 | Z35: =$N35*S35 -> 0 | AA35: =$N35*T35 -> 0
A36: NF | B36: 158262 | C36: 29 | D36: 25.18 | E36: Caseinato de cálcio Fonterra | F36: Castrolanda | G36: 76.108.349/0014-28 | H36: Envio de 24 amostras de T. Fiber para a Prodiet | I36: Material | J36: 42554 | K36: 7 | L36: 1 | M36: 25.18 | N36: =M36*L36 -> 25.18 | P36: 0 | Q36: 1 | R36: 0 | S36: 0 | T36: 0 | U36: =SUM(P36:T36) -> 1 | W36: =$N36*P36 -> 0 | X36: =$N36*Q36 -> 25.18 | Y36: =$N36*R36 -> 0 | Z36: =$N36*S36 -> 0 | AA36: =$N36*T36 -> 0
A37: NF | B37: 84232 | C37: 30 | D37: 956.4 | E37: Immax, L-leucina | F37: Fundação de desenv. Da pesquisa do agronegócio - FUNDEPAG | G37: 50.276.237/0001-78 | H37: Análises físico-químicas Immax | I37: Terceiros | J37: 42681 | K37: 11 | L37: 1 | M37: 956.4 | N37: =M37*L37 -> 956.4 | P37: 0.5 | Q37: 0.5 | R37: 0 | S37: 0 | T37: 0 | U37: =SUM(P37:T37) -> 1 | W37: =$N37*P37 -> 478.2 | X37: =$N37*Q37 -> 478.2 | Y37: =$N37*R37 -> 0 | Z37: =$N37*S37 -> 0 | AA37: =$N37*T37 -> 0
A38: NF | B38: 15516 | C38: 31 | D38: 1772.25 | E38: Mix 150243, PHA Friesl, T. Infant | F38: Laboratório Alac Ltda | G38: 94.088.952/0001-52 | H38: Análises vitaminas T. Infant nova fórmula; alergênico PHA | I38: Terceiros | J38: 42733 | K38: 12 | L38: 1 | M38: 1772.25 | N38: =M38*L38 -> 1772.25 | P38: 0 | Q38: 0.66666667 | R38: 0.33333333 | S38: 0 | T38: 0 | U38: =SUM(P38:T38) -> 1 | W38: =$N38*P38 -> 0 | X38: =$N38*Q38 -> 1181.5 | Y38: =$N38*R38 -> 590.75 | Z38: =$N38*S38 -> 0 | AA38: =$N38*T38 -> 0
A39: NF | B39: 27583 | C39: 32 | D39: 305 | E39: T. Infant, MPC Fonterra, Loremalt 2030M, Açúcar K, mix 150243 | F39: Labor Tres Laboratórios e Consultoria Técnica Ltda | G39: 02.021.076/0001-29 | H39: FQ T. Infant nova fórmula | I39: Terceiros | J39: 42615 | K39: 9 | L39: 1 | M39: 305 | N39: =M39*L39 -> 305 | P39: 0 | Q39: 0.8 | R39: 0.2 | S39: 0 | T39: 0 | U39: =SUM(P39:T39) -> 1 | W39: =$N39*P39 -> 0 | X39: =$N39*Q39 -> 244 | Y39: =$N39*R39 -> 61 | Z39: =$N39*S39 -> 0 | AA39: =$N39*T39 -> 0
A40: NF | B40: 13354 | C40: 33 | D40: 1344.25 | E40: T. EP e mix 152349 | F40: Laboratório Alac Ltda | G40: 94.088.952/0001-52 | H40: Analisa os testes dos produtos e dá assistência na parametrização do produto e dos novos testes a serem feitos. Faz acompanhamento técnico de todos os projetos de pesquisa e desenvolvimento. | I40: Terceiros | J40: 42683 | K40: 11 | L40: 1 | M40: 1344.25 | N40: =M40*L40 -> 1344.25 | P40: 0 | Q40: 0.5 | R40: 0.5 | S40: 0 | T40: 0 | U40: =SUM(P40:T40) -> 1 | W40: =$N40*P40 -> 0 | X40: =$N40*Q40 -> 672.125 | Y40: =$N40*R40 -> 672.125 | Z40: =$N40*S40 -> 0 | AA40: =$N40*T40 -> 0
A41: NF | B41: 8891 | C41: 34 | D41: 4254.3 | E41: Bio e Pept. (red. Na e P); T. Junior, mix 16006, mix 151160 | F41: Laboratório Alac Ltda | G41: 94.088.952/0001-52 | H41: Análises micronut. Bio, Pept., T. Fiber e T. Junior | I41: Terceiros | J41: 42578 | K41: 7 | L41: 1 | M41: 4254.3 | N41: =M41*L41 -> 4254.3 | P41: 0.04 | Q41: 0.08 | R41: 0.88 | S41: 0 | T41: 0 | U41: =SUM(P41:T41) -> 1 | W41: =$N41*P41 -> 170.172 | X41: =$N41*Q41 -> 340.344 | Y41: =$N41*R41 -> 3743.784 | Z41: =$N41*S41 -> 0 | AA41: =$N41*T41 -> 0
A42: NF | B42: 5003 | C42: 35 | D42: 2550.17 | E42: Mix 151160 | F42: Laboratório Alac Ltda | G42: 94.088.952/0001-52 | H42: Análise de minerais T.Fiber | I42: Terceiros | J42: 42496 | K42: 2 | L42: 0.451018 | M42: 2550.17 | N42: =M42*L42 -> 1150.1726 | P42: 0 | Q42: 1 | R42: 0 | S42: 0 | T42: 0 | U42: =SUM(P42:T42) -> 1 | W42: =$N42*P42 -> 0 | X42: =$N42*Q42 -> 1150.1726 | Y42: =$N42*R42 -> 0 | Z42: =$N42*S42 -> 0 | AA42: =$N42*T42 -> 0
A43: NF | B43: 28066 | C43: 36 | D43: 990 | E43: Trophic Junior, T. Basic pó | F43: Labor Tres Laboratórios e Consultoria Técnica Ltda | G43: 02.021.076/0001-29 | H43: Análise microbiologia T. Junior/T. Basic | I43: Terceiros | J43: 42677 | K43: 2 | L43: 0.42929 | M43: 990 | N43: =M43*L43 -> 424.9971 | P43: 0.33333333 | Q43: 0.33333333 | R43: 0 | S43: 0.33333333 | T43: 0 | U43: =SUM(P43:T43) -> 1 | W43: =$N43*P43 -> 141.6657 | X43: =$N43*Q43 -> 141.6657 | Y43: =$N43*R43 -> 0 | Z43: =$N43*S43 -> 141.6657 | AA43: =$N43*T43 -> 0
A44: Cupons fiscais e bilhete e-ticket | C44: 37 | D44: 347.04 | E44: Feira de ingredientes | H44: Participação em feira de ingredientes para prospecção de novas MP | I44: Material | J44: 42607 | K44: 8 | L44: 1 | M44: 347.04 | N44: =M44*L44 -> 347.04 | P44: 0 | Q44: 1 | R44: 0 | S44: 0 | T44: 0 | U44: =SUM(P44:T44) -> 1 | W44: =$N44*P44 -> 0 | X44: =$N44*Q44 -> 347.04 | Y44: =$N44*R44 -> 0 | Z44: =$N44*S44 -> 0 | AA44: =$N44*T44 -> 0
A45: NF | B45: 74225 | C45: 38 | D45: 281.93 | E45: Peptimax lata | F45: TUV SUD SFDK Laboratório de Análise de Produto LTDA | G45: 55.953.079/0001-67 | H45: Análise de shelf life primeira produção de Peptimax lata | I45: Terceiros | J45: 42662 | K45: 10 | L45: 1 | M45: 281.93 | N45: =M45*L45 -> 281.93 | P45: 0 | Q45: 0 | R45: 0 | S45: 1 | T45: 0 | U45: =SUM(P45:T45) -> 1 | W45: =$N45*P45 -> 0 | X45: =$N45*Q45 -> 0 | Y45: =$N45*R45 -> 0 | Z45: =$N45*S45 -> 281.93 | AA45: =$N45*T45 -> 0
A46: NF | B46: 69032 | C46: 39 | D46: 710.15 | E46: Energyzip 1.0 | F46: TUV SUD SFDK Laboratório de Análise de Produto LTDA | G46: 55.953.079/0001-67 | H46: Primeira produção de E 1.0 Castrolanda | I46: Terceiros | J46: 42404 | K46: 2 | L46: 1 | M46: 710.15 | N46: =M46*L46 -> 710.15 | P46: 0 | Q46: 0 | R46: 0 | S46: 1 | T46: 0 | U46: =SUM(P46:T46) -> 1 | W46: =$N46*P46 -> 0 | X46: =$N46*Q46 -> 0 | Y46: =$N46*R46 -> 0 | Z46: =$N46*S46 -> 710.15 | AA46: =$N46*T46 -> 0
A47: NF | B47: 7976 | C47: 40 | D47: 290 | E47: Energyzip 1.0 | F47: Laboratório Alac Ltda | G47: 94.088.952/0001-52 | H47: Shelf Life E 1.0 com maior tempo de retardo e menor temperatura de esterilização | I47: Terceiros | J47: 42557 | K47: 7 | L47: 1 | M47: 290 | N47: =M47*L47 -> 290 | P47: 0 | Q47: 0 | R47: 0 | S47: 1 | T47: 0 | U47: =SUM(P47:T47) -> 1 | W47: =$N47*P47 -> 0 | X47: =$N47*Q47 -> 0 | Y47: =$N47*R47 -> 0 | Z47: =$N47*S47 -> 290 | AA47: =$N47*T47 -> 0
A48: NF | B48: 15490 | C48: 41 | D48: 1330 | E48: T. Junior, T 1.5, Diamax, Peptimax, T. Basic líq, E. 10, T. Fiber | F48: Fundação de estudos e pesquisas aquáticas - FUNDESPA | G48: 61.379.657/0001-04 | H48: Análises de shelf life | I48: Terceiros | J48: 42495 | K48: 5 | L48: 1 | M48: 1330 | N48: =M48*L48 -> 1330 | P48: 0.14285714 | Q48: 0 | R48: 0 | S48: 0.85714286 | T48: 0 | U48: =SUM(P48:T48) -> 1 | W48: =$N48*P48 -> 190 | X48: =$N48*Q48 -> 0 | Y48: =$N48*R48 -> 0 | Z48: =$N48*S48 -> 1140 | AA48: =$N48*T48 -> 0
A49: NF | B49: 70623 | C49: 42 | D49: 1775.38 | E49: Diamax, E.10, T. Basic líq, T.15, T. Fiber | F49: TUV SUD SFDK Laboratório de Análise de Produto LTDA | G49: 55.953.079/0001-67 | H49: Análises de shelf life | I49: Terceiros | J49: 42480 | K49: 6 | L49: 1 | M49: 1775.38 | N49: =M49*L49 -> 1775.38 | P49: 0 | Q49: 0 | R49: 0 | S49: 1 | T49: 0 | U49: =SUM(P49:T49) -> 1 | W49: =$N49*P49 -> 0 | X49: =$N49*Q49 -> 0 | Y49: =$N49*R49 -> 0 | Z49: =$N49*S49 -> 1775.38 | AA49: =$N49*T49 -> 0
A50: NF | B50: 17048 | C50: 43 | D50: 760 | E50: T. Fiber, T 1.5, T EP, Peptimax | F50: Fundação de estudos e pesquisas aquáticas - FUNDESPA | G50: 61.379.657/0001-04 | H50: Análises distribuição de tamanho de partícula | I50: Terceiros | J50: 42702 | K50: 11 | L50: 1 | M50: 760 | N50: =M50*L50 -> 760 | P50: 0 | Q50: 0 | R50: 0.75 | S50: 0.25 | T50: 0 | U50: =SUM(P50:T50) -> 1 | W50: =$N50*P50 -> 0 | X50: =$N50*Q50 -> 0 | Y50: =$N50*R50 -> 570 | Z50: =$N50*S50 -> 190 | AA50: =$N50*T50 -> 0
A51: NF | B51: 16158 | C51: 44 | D51: 380 | E51: E. chocolate, T. Fiber (caseinato Ca) | F51: Fundação de estudos e pesquisas aquáticas - FUNDESPA | G51: 61.379.657/0001-04 | H51: Distribuição de partícula - E. chocolate e T Fiber com novo caseinato | I51: Terceiros | J51: 42593 | K51: 8 | L51: 1 | M51: 380 | N51: =M51*L51 -> 380 | P51: 0 | Q51: 0.5 | R51: 0.5 | S51: 0 | T51: 0 | U51: =SUM(P51:T51) -> 1 | W51: =$N51*P51 -> 0 | X51: =$N51*Q51 -> 190 | Y51: =$N51*R51 -> 190 | Z51: =$N51*S51 -> 0 | AA51: =$N51*T51 -> 0
A52: NF | B52: 38029 | C52: 45 | D52: 1303.4 | E52: Peptimax lata, T. Bio | F52: Bioagri Analises de alimentos Ltda | G52: 00.000.410/0001-32 | H52: Ácidos graxos T. Bio lecitinado e Peptimax lata | I52: Terceiros | J52: 04/11/2-16 | K52: 11 | L52: 1 | M52: 1303.4 | N52: =M52*L52 -> 1303.4 | P52: 0 | Q52: 0 | R52: 0.5 | S52: 0.5 | T52: 0 | U52: =SUM(P52:T52) -> 1 | W52: =$N52*P52 -> 0 | X52: =$N52*Q52 -> 0 | Y52: =$N52*R52 -> 651.7 | Z52: =$N52*S52 -> 651.7 | AA52: =$N52*T52 -> 0
A53: NF | B53: 84627 | C53: 46 | D53: 3773 | E53: Trophic EP (mix 152349) | F53: Fundação de desenv. Da pesquisa do agronegócio - FUNDEPAG | G53: 50.276.237/0001-78 | H53: Análise de vitaminas Trophic EP baixa viscosidade | I53: Terceiros | J53: 42697 | K53: 11 | L53: 1 | M53: 3773 | N53: =M53*L53 -> 3773 | P53: 0 | Q53: 0.5 | R53: 0.5 | S53: 0 | T53: 0 | U53: =SUM(P53:T53) -> 1 | W53: =$N53*P53 -> 0 | X53: =$N53*Q53 -> 1886.5 | Y53: =$N53*R53 -> 1886.5 | Z53: =$N53*S53 -> 0 | AA53: =$N53*T53 -> 0
A54: NF | B54: 70624 | C54: 47 | D54: 760.85 | E54: Trophic Infant e Peptimax | F54: TUV SUD SFDK Laboratório de Análise de Produto LTDA | G54: 55.953.079/0001-67 | H54: Análise microbiologia T Infant e Peptimax lata | I54: Terceiros | J54: 42480 | K54: 4 | L54: 1 | M54: 760.85 | N54: =M54*L54 -> 760.85 | P54: 0 | Q54: 0 | R54: 0.66666667 | S54: 0.33333333 | T54: 0 | U54: =SUM(P54:T54) -> 1 | W54: =$N54*P54 -> 0 | X54: =$N54*Q54 -> 0 | Y54: =$N54*R54 -> 507.23333 | Z54: =$N54*S54 -> 253.61667 | AA54: =$N54*T54 -> 0
A55: NF | B55: 81076 | C55: 48 | D55: 5127.7 | E55: Trophic Bio e Peptimax | F55: Fundação de desenv. Da pesquisa do agronegócio - FUNDEPAG | G55: 50.276.237/0001-78 | H55: Análise de micronutrientes para estudo de redução de Na e P | I55: Terceiros | J55: 42569 | K55: 7 | L55: 1 | M55: 5127.7 | N55: =M55*L55 -> 5127.7 | P55: 0 | Q55: 0 | R55: 1 | S55: 0 | T55: 0 | U55: =SUM(P55:T55) -> 1 | W55: =$N55*P55 -> 0 | X55: =$N55*Q55 -> 0 | Y55: =$N55*R55 -> 5127.7 | Z55: =$N55*S55 -> 0 | AA55: =$N55*T55 -> 0
A56: NF | B56: 80302 | C56: 49 | D56: 5127.7 | E56: Trophic Bio e Peptimax | F56: Fundação de desenv. Da pesquisa do agronegócio - FUNDEPAG | G56: 50.276.237/0001-78 | H56: Análise de micronutrientes para estudo de redução de Na e P | I56: Terceiros | J56: 42541 | K56: 6 | L56: 1 | M56: 5127.7 | N56: =M56*L56 -> 5127.7 | P56: 0 | Q56: 0 | R56: 1 | S56: 0 | T56: 0 | U56: =SUM(P56:T56) -> 1 | W56: =$N56*P56 -> 0 | X56: =$N56*Q56 -> 0 | Y56: =$N56*R56 -> 5127.7 | Z56: =$N56*S56 -> 0 | AA56: =$N56*T56 -> 0
A57: Invoice | B57: 411869 | C57: 50 | D57: 4198.47 | E57: T. Bio, Peptimax e Immax | F57: Covance - The Development Service Company | H57: Análise de micronutrientes - NP e redução de Na e P | I57: Material | J57: 42598 | K57: 8 | L57: 1 | M57: 4198.47 | N57: =M57*L57 -> 4198.47 | P57: 0.33333333 | Q57: 0 | R57: 0.66666667 | S57: 0 | T57: 0 | U57: =SUM(P57:T57) -> 1 | W57: =$N57*P57 -> 1399.49 | X57: =$N57*Q57 -> 0 | Y57: =$N57*R57 -> 2798.98 | Z57: =$N57*S57 -> 0 | AA57: =$N57*T57 -> 0
A58: NF | B58: 10844 | C58: 51 | D58: 436.5 | E58: Trophic Basic | F58: Laboratório Alac Ltda | G58: 94.088.952/0001-52 | H58: Análises de micronutrientes para estudo de redução Na e P | I58: Terceiros | J58: 42621 | K58: 9 | L58: 1 | M58: 436.5 | N58: =M58*L58 -> 436.5 | P58: 0 | Q58: 0 | R58: 1 | S58: 0 | T58: 0 | U58: =SUM(P58:T58) -> 1 | W58: =$N58*P58 -> 0 | X58: =$N58*Q58 -> 0 | Y58: =$N58*R58 -> 436.5 | Z58: =$N58*S58 -> 0 | AA58: =$N58*T58 -> 0
A59: NF | B59: 83455 | C59: 52 | D59: 524 | E59: Trophic Infant | F59: Fundação de desenv. Da pesquisa do agronegócio - FUNDEPAG | G59: 50.276.237/0001-78 | H59: Análises ácidos graxos T. Infant nova fórmula | I59: Terceiros | J59: 42653 | K59: 10 | L59: 1 | M59: 524 | N59: =M59*L59 -> 524 | P59: 0 | Q59: 0 | R59: 1 | S59: 0 | T59: 0 | U59: =SUM(P59:T59) -> 1 | W59: =$N59*P59 -> 0 | X59: =$N59*Q59 -> 0 | Y59: =$N59*R59 -> 524 | Z59: =$N59*S59 -> 0 | AA59: =$N59*T59 -> 0
A60: NF | B60: 12036 | C60: 53 | D60: 1217.75 | E60: Diamax | F60: Laboratório Alac Ltda | G60: 94.088.952/0001-52 | H60: Micronutrientes Diamax para estudo de extensão de validade | I60: Terceiros | J60: 42657 | K60: 10 | L60: 1 | M60: 1217.75 | N60: =M60*L60 -> 1217.75 | P60: 0 | Q60: 0 | R60: 1 | S60: 0 | T60: 0 | U60: =SUM(P60:T60) -> 1 | W60: =$N60*P60 -> 0 | X60: =$N60*Q60 -> 0 | Y60: =$N60*R60 -> 1217.75 | Z60: =$N60*S60 -> 0 | AA60: =$N60*T60 -> 0
A61: NF | B61: 12603 | C61: 54 | D61: 1359.25 | E61: Energyzip baunilha | F61: Laboratório Alac Ltda | G61: 94.088.952/0001-52 | H61: Micronutrientes E. baun para estudo de extensão de validade | I61: Terceiros | J61: 42664 | K61: 10 | L61: 1 | M61: 1359.25 | N61: =M61*L61 -> 1359.25 | P61: 0 | Q61: 0 | R61: 1 | S61: 0 | T61: 0 | U61: =SUM(P61:T61) -> 1 | W61: =$N61*P61 -> 0 | X61: =$N61*Q61 -> 0 | Y61: =$N61*R61 -> 1359.25 | Z61: =$N61*S61 -> 0 | AA61: =$N61*T61 -> 0
A62: Recibo | C62: 55 | D62: 2220 | E62: ILSI | F62: ILSI Brasil | G62: 65.086.001/0001-46 | H62: ILSI mensalidade julho | I62: Terceiros | J62: 42552 | K62: 7 | L62: 1 | M62: 2220 | N62: =M62*L62 -> 2220 | P62: 0 | Q62: 0 | R62: 0 | S62: 0 | T62: 1 | U62: =SUM(P62:T62) -> 1 | W62: =$N62*P62 -> 0 | X62: =$N62*Q62 -> 0 | Y62: =$N62*R62 -> 0 | Z62: =$N62*S62 -> 0 | AA62: =$N62*T62 -> 2220
A63: Recibo | C63: 56 | D63: 2220 | E63: ILSI | F63: ILSI Brasil | G63: 65.086.001/0001-46 | H63: ILSI mensalidade agosto | I63: Terceiros | J63: 42583 | K63: 8 | L63: 1 | M63: 2220 | N63: =M63*L63 -> 2220 | P63: 0 | Q63: 0 | R63: 0 | S63: 0 | T63: 1 | U63: =SUM(P63:T63) -> 1 | W63: =$N63*P63 -> 0 | X63: =$N63*Q63 -> 0 | Y63: =$N63*R63 -> 0 | Z63: =$N63*S63 -> 0 | AA63: =$N63*T63 -> 2220
A64: Recibo | C64: 57 | D64: 2220 | E64: ILSI | F64: ILSI Brasil | G64: 65.086.001/0001-46 | H64: ILSI mensalidade setembro | I64: Terceiros | J64: 42618 | K64: 9 | L64: 1 | M64: 2220 | N64: =M64*L64 -> 2220 | P64: 0 | Q64: 0 | R64: 0 | S64: 0 | T64: 1 | U64: =SUM(P64:T64) -> 1 | W64: =$N64*P64 -> 0 | X64: =$N64*Q64 -> 0 | Y64: =$N64*R64 -> 0 | Z64: =$N64*S64 -> 0 | AA64: =$N64*T64 -> 2220
A65: Recibo | C65: 58 | D65: 2220 | E65: ILSI | F65: ILSI Brasil | G65: 65.086.001/0001-46 | H65: ILSI mensalidade outubro | I65: Terceiros | J65: 42646 | K65: 10 | L65: 1 | M65: 2220 | N65: =M65*L65 -> 2220 | P65: 0 | Q65: 0 | R65: 0 | S65: 0 | T65: 1 | U65: =SUM(P65:T65) -> 1 | W65: =$N65*P65 -> 0 | X65: =$N65*Q65 -> 0 | Y65: =$N65*R65 -> 0 | Z65: =$N65*S65 -> 0 | AA65: =$N65*T65 -> 2220
A66: Recibo | C66: 59 | D66: 2220 | E66: ILSI | F66: ILSI Brasil | G66: 65.086.001/0001-46 | H66: ILSI mensalidade novembro | I66: Terceiros | J66: 42675 | K66: 11 | L66: 1 | M66: 2220 | N66: =M66*L66 -> 2220 | P66: 0 | Q66: 0 | R66: 0 | S66: 0 | T66: 1 | U66: =SUM(P66:T66) -> 1 | W66: =$N66*P66 -> 0 | X66: =$N66*Q66 -> 0 | Y66: =$N66*R66 -> 0 | Z66: =$N66*S66 -> 0 | AA66: =$N66*T66 -> 2220
A67: Recibo | C67: 60 | D67: 2220 | E67: ILSI | F67: ILSI Brasil | G67: 65.086.001/0001-46 | H67: ILSI mensalidade dezembro | I67: Terceiros | J67: 42705 | K67: 12 | L67: 1 | M67: 2220 | N67: =M67*L67 -> 2220 | P67: 0 | Q67: 0 | R67: 0 | S67: 0 | T67: 1 | U67: =SUM(P67:T67) -> 1 | W67: =$N67*P67 -> 0 | X67: =$N67*Q67 -> 0 | Y67: =$N67*R67 -> 0 | Z67: =$N67*S67 -> 0 | AA67: =$N67*T67 -> 2220
A68: Recibo | C68: 61 | D68: 40 | E68: ILSI | F68: ILSI Brasil | G68: 65.086.001/0001-46 | H68: ILSI aquisição de livros | I68: Terceiros | J68: 42627 | K68: 9 | L68: 1 | M68: 40 | N68: =M68*L68 -> 40 | P68: 0 | Q68: 0 | R68: 0 | S68: 0 | T68: 1 | U68: =SUM(P68:T68) -> 1 | W68: =$N68*P68 -> 0 | X68: =$N68*Q68 -> 0 | Y68: =$N68*R68 -> 0 | Z68: =$N68*S68 -> 0 | AA68: =$N68*T68 -> 40
A69: Recibo | C69: 62 | D69: 50 | E69: ILSI | F69: ILSI Brasil | G69: 65.086.001/0001-46 | H69: ILSI workshop | I69: Terceiros | J69: 42622 | K69: 9 | L69: 1 | M69: 50 | N69: =M69*L69 -> 50 | P69: 0 | Q69: 0 | R69: 0 | S69: 0 | T69: 1 | U69: =SUM(P69:T69) -> 1 | W69: =$N69*P69 -> 0 | X69: =$N69*Q69 -> 0 | Y69: =$N69*R69 -> 0 | Z69: =$N69*S69 -> 0 | AA69: =$N69*T69 -> 50
A70: Bilhete e-ticket | B70: 957 213526024/577 0005867190 | C70: 63 | D70: 350 | E70: ILSI | F70: LATAM e Azul Linhas Aéreas | H70: Passagens Hellin IDA e VOLTA workshop ILSI setembro | I70: Material | J70: 42626 | K70: 9 | L70: 1 | M70: 350 | N70: =M70*L70 -> 350 | P70: 0 | Q70: 0 | R70: 0 | S70: 0 | T70: 1 | U70: =SUM(P70:T70) -> 1 | W70: =$N70*P70 -> 0 | X70: =$N70*Q70 -> 0 | Y70: =$N70*R70 -> 0 | Z70: =$N70*S70 -> 0 | AA70: =$N70*T70 -> 350
A71: Recibo | C71: 64 | D71: 250 | E71: ILSI | F71: ILSI Brasil | G71: 65.086.001/0001-46 | H71: ILSI série de workshops | I71: Terceiros | J71: 42671 | K71: 10 | L71: 1 | M71: 250 | N71: =M71*L71 -> 250 | P71: 0 | Q71: 0 | R71: 0 | S71: 0 | T71: 1 | U71: =SUM(P71:T71) -> 1 | W71: =$N71*P71 -> 0 | X71: =$N71*Q71 -> 0 | Y71: =$N71*R71 -> 0 | Z71: =$N71*S71 -> 0 | AA71: =$N71*T71 -> 250
A72: Confirmação reserva | B72: 1167152312 | C72: 65 | D72: 290 | E72: ILSI | F72: Blue Tree Premium Paulista | H72: Reserva hotel Hellin - ILSI série de workshops | I72: Material | J72: 42681 | K72: 11 | L72: 1 | M72: 290 | N72: =M72*L72 -> 290 | P72: 0 | Q72: 0 | R72: 0 | S72: 0 | T72: 1 | U72: =SUM(P72:T72) -> 1 | W72: =$N72*P72 -> 0 | X72: =$N72*Q72 -> 0 | Y72: =$N72*R72 -> 0 | Z72: =$N72*S72 -> 0 | AA72: =$N72*T72 -> 290
A73: Bilhete e-ticket | B73: 247 2426021755/957 2137652929 | C73: 66 | D73: 396.12 | E73: ILSI | F73: Avianca e LATAM | H73: Passagens Hellin - ILSI série de workshops | I73: Material | J73: 42681 | K73: 11 | L73: 1 | M73: 396.12 | N73: =M73*L73 -> 396.12 | P73: 0 | Q73: 0 | R73: 0 | S73: 0 | T73: 1 | U73: =SUM(P73:T73) -> 1 | W73: =$N73*P73 -> 0 | X73: =$N73*Q73 -> 0 | Y73: =$N73*R73 -> 0 | Z73: =$N73*S73 -> 0 | AA73: =$N73*T73 -> 396.12
A74: Recibo | C74: 67 | D74: 50 | E74: ILSI | F74: ILSI Brasil | G74: 65.086.001/0001-46 | H74: ILSI workshop | I74: Terceiros | J74: 42423 | K74: 2 | L74: 1 | M74: 50 | N74: =M74*L74 -> 50 | P74: 0 | Q74: 0 | R74: 0 | S74: 0 | T74: 1 | U74: =SUM(P74:T74) -> 1 | W74: =$N74*P74 -> 0 | X74: =$N74*Q74 -> 0 | Y74: =$N74*R74 -> 0 | Z74: =$N74*S74 -> 0 | AA74: =$N74*T74 -> 50
A75: Bilhete e-ticket/Cupons fiscais | B75: 957 2124724203 | C75: 68 | D75: 773.78 | E75: ILSI | H75: Gastos Jana - workshop ILSI fevereiro | I75: Material | J75: 42425 | K75: 2 | L75: 1 | M75: 773.78 | N75: =M75*L75 -> 773.78 | P75: 0 | Q75: 0 | R75: 0 | S75: 0 | T75: 1 | U75: =SUM(P75:T75) -> 1 | W75: =$N75*P75 -> 0 | X75: =$N75*Q75 -> 0 | Y75: =$N75*R75 -> 0 | Z75: =$N75*S75 -> 0 | AA75: =$N75*T75 -> 773.78
A76: Bilhete e-ticket | B76: 957 2126179902 | C76: 69 | D76: 695.28 | E76: ILSI | F76: TAM | H76: Passagem workshop ILSI - Jana | I76: Material | J76: 42439 | K76: 3 | L76: 1 | M76: 695.28 | N76: =M76*L76 -> 695.28 | P76: 0 | Q76: 0 | R76: 0 | S76: 0 | T76: 1 | U76: =SUM(P76:T76) -> 1 | W76: =$N76*P76 -> 0 | X76: =$N76*Q76 -> 0 | Y76: =$N76*R76 -> 0 | Z76: =$N76*S76 -> 0 | AA76: =$N76*T76 -> 695.28
A77: Recibo | C77: 70 | D77: 25 | E77: ILSI | F77: ILSI Brasil | G77: 65.086.001/0001-46 | H77: ILSI workshop | I77: Terceiros | J77: 42437 | K77: 3 | L77: 1 | M77: 25 | N77: =M77*L77 -> 25 | P77: 0 | Q77: 0 | R77: 0 | S77: 0 | T77: 1 | U77: =SUM(P77:T77) -> 1 | W77: =$N77*P77 -> 0 | X77: =$N77*Q77 -> 0 | Y77: =$N77*R77 -> 0 | Z77: =$N77*S77 -> 0 | AA77: =$N77*T77 -> 25
A78: Cupons fiscais | C78: 71 | D78: 261.7 | E78: ILSI | H78: Gastos Jana - workshop ILSI março | I78: Material | J78: 42439 | K78: 3 | L78: 1 | M78: 261.7 | N78: =M78*L78 -> 261.7 | P78: 0 | Q78: 0 | R78: 0 | S78: 0 | T78: 1 | U78: =SUM(P78:T78) -> 1 | W78: =$N78*P78 -> 0 | X78: =$N78*Q78 -> 0 | Y78: =$N78*R78 -> 0 | Z78: =$N78*S78 -> 0 | AA78: =$N78*T78 -> 261.7
A79: Bilhete e-ticket | B79: 247 2425232331/127 0001897631 | C79: 72 | D79: 555.26 | E79: ILSI | F79: Aviana e GOL | H79: Gastos Hellin - reunião geral ILSI 14/10 | I79: Material | J79: 42657 | K79: 10 | L79: 1 | M79: 555.26 | N79: =M79*L79 -> 555.26 | P79: 0 | Q79: 0 | R79: 0 | S79: 0 | T79: 1 | U79: =SUM(P79:T79) -> 1 | W79: =$N79*P79 -> 0 | X79: =$N79*Q79 -> 0 | Y79: =$N79*R79 -> 0 | Z79: =$N79*S79 -> 0 | AA79: =$N79*T79 -> 555.26
A80: Recibo | C80: 73 | D80: 130.39 | E80: ILSI | H80: Gastos transporte Hellin - reunião geral ILSI 14/10 | I80: Material | J80: 42657 | K80: 10 | L80: 1 | M80: 130.39 | N80: =M80*L80 -> 130.39 | P80: 0 | Q80: 0 | R80: 0 | S80: 0 | T80: 1 | U80: =SUM(P80:T80) -> 1 | W80: =$N80*P80 -> 0 | X80: =$N80*Q80 -> 0 | Y80: =$N80*R80 -> 0 | Z80: =$N80*S80 -> 0 | AA80: =$N80*T80 -> 130.39
A81: Cupons fiscais | C81: 74 | D81: 165 | E81: ILSI | H81: Gastos Jana - reunião geral ILSI 14/10 | I81: Material | J81: 42480 | K81: 4 | L81: 1 | M81: 165 | N81: =M81*L81 -> 165 | P81: 0 | Q81: 0 | R81: 0 | S81: 0 | T81: 1 | U81: =SUM(P81:T81) -> 1 | W81: =$N81*P81 -> 0 | X81: =$N81*Q81 -> 0 | Y81: =$N81*R81 -> 0 | Z81: =$N81*S81 -> 0 | AA81: =$N81*T81 -> 165
A82: Bilhete e-ticket | B82: 957 212697498 | C82: 75 | D82: 359.94 | E82: ILSI | F82: TAM | H82: Passagem reunião geral ILSI - Jana | I82: Material | J82: 42480 | K82: 4 | L82: 1 | M82: 359.94 | N82: =M82*L82 -> 359.94 | P82: 0 | Q82: 0 | R82: 0 | S82: 0 | T82: 1 | U82: =SUM(P82:T82) -> 1 | W82: =$N82*P82 -> 0 | X82: =$N82*Q82 -> 0 | Y82: =$N82*R82 -> 0 | Z82: =$N82*S82 -> 0 | AA82: =$N82*T82 -> 359.94
A83: Bilhete e-ticket | B83: 577 0005846198/957 2133365958 | C83: 76 | D83: 411.26 | E83: ILSI | F83: Azul e LATAM | H83: Passagem reunião geral ILSI - Hellin | I83: Material | J83: 42605 | K83: 8 | L83: 1 | M83: 411.26 | N83: =M83*L83 -> 411.26 | P83: 0 | Q83: 0 | R83: 0 | S83: 0 | T83: 1 | U83: =SUM(P83:T83) -> 1 | W83: =$N83*P83 -> 0 | X83: =$N83*Q83 -> 0 | Y83: =$N83*R83 -> 0 | Z83: =$N83*S83 -> 0 | AA83: =$N83*T83 -> 411.26
A84: Bilhete e-ticket e recibos | B84: 127 0001931180 | C84: 77 | D84: 718.73 | E84: ILSI | H84: Gastos e passagem Hellin - reunião geral ILSI 29/11 | I84: Material | J84: 42703 | K84: 11 | L84: 1 | M84: 718.73 | N84: =M84*L84 -> 718.73 | P84: 0 | Q84: 0 | R84: 0 | S84: 0 | T84: 1 | U84: =SUM(P84:T84) -> 1 | W84: =$N84*P84 -> 0 | X84: =$N84*Q84 -> 0 | Y84: =$N84*R84 -> 0 | Z84: =$N84*S84 -> 0 | AA84: =$N84*T84 -> 718.73
A85: Recibo | C85: 78 | D85: 2220 | E85: ILSI | F85: ILSI Brasil | G85: 65.086.001/0001-46 | H85: ILSI mensalidade janeiro | I85: Terceiros | J85: 42380 | K85: 1 | L85: 1 | M85: 2220 | N85: =M85*L85 -> 2220 | P85: 0 | Q85: 0 | R85: 0 | S85: 0 | T85: 1 | U85: =SUM(P85:T85) -> 1 | W85: =$N85*P85 -> 0 | X85: =$N85*Q85 -> 0 | Y85: =$N85*R85 -> 0 | Z85: =$N85*S85 -> 0 | AA85: =$N85*T85 -> 2220
A86: Recibo | C86: 79 | D86: 2220 | E86: ILSI | F86: ILSI Brasil | G86: 65.086.001/0001-46 | H86: ILSI mensalidade fevereiro | I86: Terceiros | J86: 42401 | K86: 2 | L86: 1 | M86: 2220 | N86: =M86*L86 -> 2220 | P86: 0 | Q86: 0 | R86: 0 | S86: 0 | T86: 1 | U86: =SUM(P86:T86) -> 1 | W86: =$N86*P86 -> 0 | X86: =$N86*Q86 -> 0 | Y86: =$N86*R86 -> 0 | Z86: =$N86*S86 -> 0 | AA86: =$N86*T86 -> 2220
A87: Recibo | C87: 80 | D87: 2220 | E87: ILSI | F87: ILSI Brasil | G87: 65.086.001/0001-46 | H87: ILSI mensalidade março | I87: Terceiros | J87: 42430 | K87: 3 | L87: 1 | M87: 2220 | N87: =M87*L87 -> 2220 | P87: 0 | Q87: 0 | R87: 0 | S87: 0 | T87: 1 | U87: =SUM(P87:T87) -> 1 | W87: =$N87*P87 -> 0 | X87: =$N87*Q87 -> 0 | Y87: =$N87*R87 -> 0 | Z87: =$N87*S87 -> 0 | AA87: =$N87*T87 -> 2220
A88: Recibo | C88: 81 | D88: 2220 | E88: ILSI | F88: ILSI Brasil | G88: 65.086.001/0001-46 | H88: ILSI mensalidade abril | I88: Terceiros | J88: 42461 | K88: 4 | L88: 1 | M88: 2220 | N88: =M88*L88 -> 2220 | P88: 0 | Q88: 0 | R88: 0 | S88: 0 | T88: 1 | U88: =SUM(P88:T88) -> 1 | W88: =$N88*P88 -> 0 | X88: =$N88*Q88 -> 0 | Y88: =$N88*R88 -> 0 | Z88: =$N88*S88 -> 0 | AA88: =$N88*T88 -> 2220
A89: Recibo | C89: 82 | D89: 2220 | E89: ILSI | F89: ILSI Brasil | G89: 65.086.001/0001-46 | H89: ILSI mensalidade maio | I89: Terceiros | J89: 42492 | K89: 5 | L89: 1 | M89: 2220 | N89: =M89*L89 -> 2220 | P89: 0 | Q89: 0 | R89: 0 | S89: 0 | T89: 1 | U89: =SUM(P89:T89) -> 1 | W89: =$N89*P89 -> 0 | X89: =$N89*Q89 -> 0 | Y89: =$N89*R89 -> 0 | Z89: =$N89*S89 -> 0 | AA89: =$N89*T89 -> 2220
A90: Recibo | C90: 83 | D90: 2220 | E90: ILSI | F90: ILSI Brasil | G90: 65.086.001/0001-46 | H90: ILSI mensalidade junho | I90: Terceiros | J90: 42522 | K90: 6 | L90: 1 | M90: 2220 | N90: =M90*L90 -> 2220 | P90: 0 | Q90: 0 | R90: 0 | S90: 0 | T90: 1 | U90: =SUM(P90:T90) -> 1 | W90: =$N90*P90 -> 0 | X90: =$N90*Q90 -> 0 | Y90: =$N90*R90 -> 0 | Z90: =$N90*S90 -> 0 | AA90: =$N90*T90 -> 2220
A91: NF (Relatório contábil) | B91: 201600000000012 | C91: 84 | D91: 37210 | E91: Ana Paula Celes | F91: Nutrimento Gestão de Dados Empresariais Ltda. | G91: 03.150.501/0001-42 | H91: Analisa os testes dos produtos e dá assistência na parametrização do produto e dos novos testes a serem feitos. Faz acompanhamento técnico de todos os projetos de pesquisa e desenvolvimento. | I91: Terceiros | J91: 42397 | K91: 1 | L91: 0.1 | M91: 37210 | N91: =M91*L91 -> 3721 | P91: 0.25 | Q91: 0.25 | R91: 0.25 | S91: 0.25 | T91: 0 | U91: =SUM(P91:T91) -> 1 | W91: =$N91*P91 -> 930.25 | X91: =$N91*Q91 -> 930.25 | Y91: =$N91*R91 -> 930.25 | Z91: =$N91*S91 -> 930.25 | AA91: =$N91*T91 -> 0
A92: NF (Relatório contábil) | B92: 201600000000013 | C92: 85 | D92: 31227 | E92: Ana Paula Celes | F92: Nutrimento Gestão de Dados Empresariais Ltda. | G92: 03.150.501/0001-42 | H92: Analisa os testes dos produtos e dá assistência na parametrização do produto e dos novos testes a serem feitos. Faz acompanhamento técnico de todos os projetos de pesquisa e desenvolvimento. | I92: Terceiros | J92: 42425 | K92: 2 | L92: 0.1 | M92: 31227 | N92: =M92*L92 -> 3122.7 | P92: 0.25 | Q92: 0.25 | R92: 0.25 | S92: 0.25 | T92: 0 | U92: =SUM(P92:T92) -> 1 | W92: =$N92*P92 -> 780.675 | X92: =$N92*Q92 -> 780.675 | Y92: =$N92*R92 -> 780.675 | Z92: =$N92*S92 -> 780.675 | AA92: =$N92*T92 -> 0
A93: NF (Relatório contábil) | B93: 201600000000016 | C93: 86 | D93: 31226.69 | E93: Ana Paula Celes | F93: Nutrimento Gestão de Dados Empresariais Ltda. | G93: 03.150.501/0001-42 | H93: Analisa os testes dos produtos e dá assistência na parametrização do produto e dos novos testes a serem feitos. Faz acompanhamento técnico de todos os projetos de pesquisa e desenvolvimento. | I93: Terceiros | J93: 42458 | K93: 3 | L93: 0.1 | M93: 31226.69 | N93: =M93*L93 -> 3122.669 | P93: 0.25 | Q93: 0.25 | R93: 0.25 | S93: 0.25 | T93: 0 | U93: =SUM(P93:T93) -> 1 | W93: =$N93*P93 -> 780.66725 | X93: =$N93*Q93 -> 780.66725 | Y93: =$N93*R93 -> 780.66725 | Z93: =$N93*S93 -> 780.66725 | AA93: =$N93*T93 -> 0
A94: NF (Relatório contábil) | B94: 201600000000019 | C94: 87 | D94: 31226.69 | E94: Ana Paula Celes | F94: Nutrimento Gestão de Dados Empresariais Ltda. | G94: 03.150.501/0001-42 | H94: Analisa os testes dos produtos e dá assistência na parametrização do produto e dos novos testes a serem feitos. Faz acompanhamento técnico de todos os projetos de pesquisa e desenvolvimento. | I94: Terceiros | J94: 42488 | K94: 4 | L94: 0.1 | M94: 31226.69 | N94: =M94*L94 -> 3122.669 | P94: 0.25 | Q94: 0.25 | R94: 0.25 | S94: 0.25 | T94: 0 | U94: =SUM(P94:T94) -> 1 | W94: =$N94*P94 -> 780.66725 | X94: =$N94*Q94 -> 780.66725 | Y94: =$N94*R94 -> 780.66725 | Z94: =$N94*S94 -> 780.66725 | AA94: =$N94*T94 -> 0
A95: NF (Relatório contábil) | B95: 201600000000023 | C95: 88 | D95: 28557 | E95: Ana Paula Celes | F95: Nutrimento Gestão de Dados Empresariais Ltda. | G95: 03.150.501/0001-42 | H95: Analisa os testes dos produtos e dá assistência na parametrização do produto e dos novos testes a serem feitos. Faz acompanhamento técnico de todos os projetos de pesquisa e desenvolvimento. | I95: Terceiros | J95: 42517 | K95: 5 | L95: 0.1 | M95: 28557 | N95: =M95*L95 -> 2855.7 | P95: 0.25 | Q95: 0.25 | R95: 0.25 | S95: 0.25 | T95: 0 | U95: =SUM(P95:T95) -> 1 | W95: =$N95*P95 -> 713.925 | X95: =$N95*Q95 -> 713.925 | Y95: =$N95*R95 -> 713.925 | Z95: =$N95*S95 -> 713.925 | AA95: =$N95*T95 -> 0
A96: NF (Relatório contábil) | B96: 201600000000024 | C96: 89 | D96: 28557 | E96: Ana Paula Celes | F96: Nutrimento Gestão de Dados Empresariais Ltda. | G96: 03.150.501/0001-42 | H96: Analisa os testes dos produtos e dá assistência na parametrização do produto e dos novos testes a serem feitos. Faz acompanhamento técnico de todos os projetos de pesquisa e desenvolvimento. | I96: Terceiros | J96: 42550 | K96: 6 | L96: 0.1 | M96: 28557 | N96: =M96*L96 -> 2855.7 | P96: 0.25 | Q96: 0.25 | R96: 0.25 | S96: 0.25 | T96: 0 | U96: =SUM(P96:T96) -> 1 | W96: =$N96*P96 -> 713.925 | X96: =$N96*Q96 -> 713.925 | Y96: =$N96*R96 -> 713.925 | Z96: =$N96*S96 -> 713.925 | AA96: =$N96*T96 -> 0
A97: NF (Relatório contábil) | B97: 201600000000028 | C97: 90 | D97: 28557 | E97: Ana Paula Celes | F97: Nutrimento Gestão de Dados Empresariais Ltda. | G97: 03.150.501/0001-42 | H97: Analisa os testes dos produtos e dá assistência na parametrização do produto e dos novos testes a serem feitos. Faz acompanhamento técnico de todos os projetos de pesquisa e desenvolvimento. | I97: Terceiros | J97: 42579 | K97: 7 | L97: 0.1 | M97: 28557 | N97: =M97*L97 -> 2855.7 | P97: 0.25 | Q97: 0.25 | R97: 0.25 | S97: 0.25 | T97: 0 | U97: =SUM(P97:T97) -> 1 | W97: =$N97*P97 -> 713.925 | X97: =$N97*Q97 -> 713.925 | Y97: =$N97*R97 -> 713.925 | Z97: =$N97*S97 -> 713.925 | AA97: =$N97*T97 -> 0
A98: NF (Relatório contábil) | B98: 201600000000029 | C98: 91 | D98: 28557 | E98: Ana Paula Celes | F98: Nutrimento Gestão de Dados Empresariais Ltda. | G98: 03.150.501/0001-42 | H98: Analisa os testes dos produtos e dá assistência na parametrização do produto e dos novos testes a serem feitos. Faz acompanhamento técnico de todos os projetos de pesquisa e desenvolvimento. | I98: Terceiros | J98: 42611 | K98: 8 | L98: 0.1 | M98: 28557 | N98: =M98*L98 -> 2855.7 | P98: 0.25 | Q98: 0.25 | R98: 0.25 | S98: 0.25 | T98: 0 | U98: =SUM(P98:T98) -> 1 | W98: =$N98*P98 -> 713.925 | X98: =$N98*Q98 -> 713.925 | Y98: =$N98*R98 -> 713.925 | Z98: =$N98*S98 -> 713.925 | AA98: =$N98*T98 -> 0
A99: NF (Relatório contábil) | B99: 201600000000032 | C99: 92 | D99: 28557 | E99: Ana Paula Celes | F99: Nutrimento Gestão de Dados Empresariais Ltda. | G99: 03.150.501/0001-42 | H99: Analisa os testes dos produtos e dá assistência na parametrização do produto e dos novos testes a serem feitos. Faz acompanhamento técnico de todos os projetos de pesquisa e desenvolvimento. | I99: Terceiros | J99: 42642 | K99: 9 | L99: 0.1 | M99: 28557 | N99: =M99*L99 -> 2855.7 | P99: 0.25 | Q99: 0.25 | R99: 0.25 | S99: 0.25 | T99: 0 | U99: =SUM(P99:T99) -> 1 | W99: =$N99*P99 -> 713.925 | X99: =$N99*Q99 -> 713.925 | Y99: =$N99*R99 -> 713.925 | Z99: =$N99*S99 -> 713.925 | AA99: =$N99*T99 -> 0
A100: NF (Relatório contábil) | B100: 201600000000035 | C100: 93 | D100: 28557 | E100: Ana Paula Celes | F100: Nutrimento Gestão de Dados Empresariais Ltda. | G100: 03.150.501/0001-42 | H100: Analisa os testes dos produtos e dá assistência na parametrização do produto e dos novos testes a serem feitos. Faz acompanhamento técnico de todos os projetos de pesquisa e desenvolvimento. | I100: Terceiros | J100: 42674 | K100: 10 | L100: 0.1 | M100: 28557 | N100: =M100*L100 -> 2855.7 | P100: 0.25 | Q100: 0.25 | R100: 0.25 | S100: 0.25 | T100: 0 | U100: =SUM(P100:T100) -> 1 | W100: =$N100*P100 -> 713.925 | X100: =$N100*Q100 -> 713.925 | Y100: =$N100*R100 -> 713.925 | Z100: =$N100*S100 -> 713.925 | AA100: =$N100*T100 -> 0
A101: NF (Relatório contábil) | B101: 201600000000038 | C101: 94 | D101: 28557 | E101: Ana Paula Celes | F101: Nutrimento Gestão de Dados Empresariais Ltda. | G101: 03.150.501/0001-42 | H101: Analisa os testes dos produtos e dá assistência na parametrização do produto e dos novos testes a serem feitos. Faz acompanhamento técnico de todos os projetos de pesquisa e desenvolvimento. | I101: Terceiros | J101: 42703 | K101: 11 | L101: 0.1 | M101: 28557 | N101: =M101*L101 -> 2855.7 | P101: 0.25 | Q101: 0.25 | R101: 0.25 | S101: 0.25 | T101: 0 | U101: =SUM(P101:T101) -> 1 | W101: =$N101*P101 -> 713.925 | X101: =$N101*Q101 -> 713.925 | Y101: =$N101*R101 -> 713.925 | Z101: =$N101*S101 -> 713.925 | AA101: =$N101*T101 -> 0
...

Sheet (a) Investimentos (2)
A1: PRODIET
A2: Anexo II - Investimentos - Terceiros
A3: INOVAÇÃO TECNOLÓGICA 2016 | J3: Valores
I4: Material | J4: =SUMIF($I$8:$I$115,I4,$N$8:$N$115) -> 16180.07
I5: Terceiros | J5: =SUMIF($I$8:$I$115,I5,$N$8:$N$115) -> 257166.12
D6: =SUBTOTAL(9,D8:D114) -> 632430.95 | N6: =SUBTOTAL(9,N8:N114) -> 257166.12 | P6: Participação nos projetos | U6: =SUM(U8:U90)/COUNT(U8:U90) -> 1 | W6: Dispêndio (R$) por projeto
A7: Tipo | B7: Documento | C7: Controle DOCS | D7: Total NF | E7: PRODUTOS | F7: RECURSO | G7: CPF / CNPJ | H7: ATIVIDADE | I7: NATUREZA | J7: DATA | K7: Mês | L7: QTD | M7: UNITÁRIO | N7: TOTAL | P7: Novos Produtos | Q7: Novas matérias-primas | R7: Melhoria de Produto | S7: Melhoria de Processo | T7: ILSI | U7: Total | W7: Novos Produtos | X7: Novas matérias-primas | Y7: Melhoria de Produto | Z7: Melhoria de Processo | AA7: ILSI
A8: NF | B8: 34840 | C8: 1 | D8: 1303.4 | E8: Bemmax, Peptimax | F8: Bioagri Analises de alimentos Ltda | G8: 00.000.410/0001-32 | H8: Análise de ácidos graxos | I8: Terceiros | J8: 42500 | K8: 5 | L8: 1 | M8: 1303.4 | N8: =M8*L8 -> 1303.4 | P8: 0.5 | Q8: 0 | R8: 0 | S8: 0.5 | T8: 0 | U8: =SUM(P8:T8) -> 1 | W8: =$N8*P8 -> 651.7 | X8: =$N8*Q8 -> 0 | Y8: =$N8*R8 -> 0 | Z8: =$N8*S8 -> 651.7 | AA8: =$N8*T8 -> 0
A9: Bilhete e-ticket | B9: 577 0005868279 | C9: 2 | D9: 579.24 | E9: Immax | F9: Azul linhas aéreas | H9: Passagens Hellin IDA e VOLTA Ribeirão Preto | I9: Material | J9: 42641 | K9: 9 | L9: 1 | M9: 579.24 | N9: =M9*L9 -> 579.24 | P9: 1 | Q9: 0 | R9: 0 | S9: 0 | T9: 0 | U9: =SUM(P9:T9) -> 1 | W9: =$N9*P9 -> 579.24 | X9: =$N9*Q9 -> 0 | Y9: =$N9*R9 -> 0 | Z9: =$N9*S9 -> 0 | AA9: =$N9*T9 -> 0
A10: Cupons fiscais | C10: 2 | D10: 138.01 | E10: Immax | F10: Diversos | H10: Alimentação e táxi Hellin Ribeirão Preto | I10: Material | J10: 42641 | K10: 9 | L10: 1 | M10: 138.01 | N10: =M10*L10 -> 138.01 | P10: 1 | Q10: 0 | R10: 0 | S10: 0 | T10: 0 | U10: =SUM(P10:T10) -> 1 | W10: =$N10*P10 -> 138.01 | X10: =$N10*Q10 -> 0 | Y10: =$N10*R10 -> 0 | Z10: =$N10*S10 -> 0 | AA10: =$N10*T10 -> 0
A11: NF | B11: 98 | C11: 4 | D11: 12042 | E11: Immax | F11: Oraculum Inteligência em Nutrição e Saúde Ltda - ME | G11: 21.213.714/0001-58 | H11: Desenvolvimento de receitas Immax | I11: Terceiros | J11: 42628 | K11: 9 | L11: 1 | M11: 12042 | N11: =M11*L11 -> 12042 | P11: 1 | Q11: 0 | R11: 0 | S11: 0 | T11: 0 | U11: =SUM(P11:T11) -> 1 | W11: =$N11*P11 -> 12042 | X11: =$N11*Q11 -> 0 | Y11: =$N11*R11 -> 0 | Z11: =$N11*S11 -> 0 | AA11: =$N11*T11 -> 0
A12: NF | B12: 11849 | C12: 5 | D12: 877.5 | E12: Immax | F12: Impressione Impressão Digital Ltda - ME | G12: 12.457.568/0001-15 | H12: Immax | I12: Material | J12: 42529 | K12: 6 | L12: 1 | M12: 877.5 | N12: =M12*L12 -> 877.5 | P12: 1 | Q12: 0 | R12: 0 | S12: 0 | T12: 0 | U12: =SUM(P12:T12) -> 1 | W12: =$N12*P12 -> 877.5 | X12: =$N12*Q12 -> 0 | Y12: =$N12*R12 -> 0 | Z12: =$N12*S12 -> 0 | AA12: =$N12*T12 -> 0
A13: NF | B13: 9354 | C13: 6 | D13: 1230 | E13: Immax | F13: Laboratório Alac Ltda | G13: 94.088.952/0001-52 | H13: Análise de micronutrientes Immax | I13: Terceiros | J13: 42587 | K13: 8 | L13: 1 | M13: 1230 | N13: =M13*L13 -> 1230 | P13: 1 | Q13: 0 | R13: 0 | S13: 0 | T13: 0 | U13: =SUM(P13:T13) -> 1 | W13: =$N13*P13 -> 1230 | X13: =$N13*Q13 -> 0 | Y13: =$N13*R13 -> 0 | Z13: =$N13*S13 -> 0 | AA13: =$N13*T13 -> 0
A14: NF | B14: 81028 | C14: 7 | D14: 2401 | E14: Immax | F14: Fundação de desenv. Da pesquisa do agronegócio - FUNDEPAG | G14: 50.276.237/0001-78 | H14: Análises físico-químicas Immax | I14: Terceiros | J14: 42565 | K14: 7 | L14: 1 | M14: 2401 | N14: =M14*L14 -> 2401 | P14: 1 | Q14: 0 | R14: 0 | S14: 0 | T14: 0 | U14: =SUM(P14:T14) -> 1 | W14: =$N14*P14 -> 2401 | X14: =$N14*Q14 -> 0 | Y14: =$N14*R14 -> 0 | Z14: =$N14*S14 -> 0 | AA14: =$N14*T14 -> 0
A15: NF | B15: 81357 | C15: 8 | D15: 2401 | E15: Immax | F15: Fundação de desenv. Da pesquisa do agronegócio - FUNDEPAG | G15: 50.276.237/0001-78 | H15: Análises físico-químicas Immax | I15: Terceiros | J15: 42585 | K15: 8 | L15: 1 | M15: 2401 | N15: =M15*L15 -> 2401 | P15: 1 | Q15: 0 | R15: 0 | S15: 0 | T15: 0 | U15: =SUM(P15:T15) -> 1 | W15: =$N15*P15 -> 2401 | X15: =$N15*Q15 -> 0 | Y15: =$N15*R15 -> 0 | Z15: =$N15*S15 -> 0 | AA15: =$N15*T15 -> 0
A16: NF | B16: 38 | C16: 9 | D16: 1000 | E16: Immax | F16: Sandra Marcia da Silva de Souza - ME | G16: 13.807.270/0001-50 | H16: Immax | I16: Material | J16: 42611 | K16: 8 | L16: 1 | M16: 1000 | N16: =M16*L16 -> 1000 | P16: 1 | Q16: 0 | R16: 0 | S16: 0 | T16: 0 | U16: =SUM(P16:T16) -> 1 | W16: =$N16*P16 -> 1000 | X16: =$N16*Q16 -> 0 | Y16: =$N16*R16 -> 0 | Z16: =$N16*S16 -> 0 | AA16: =$N16*T16 -> 0
A17: NF | B17: 48 | C17: 10 | D17: 89 | E17: Immax | F17: Sandra Marcia da Silva de Souza - ME | G17: 13.807.270/0001-50 | H17: Immax | I17: Material | J17: 42654 | K17: 10 | L17: 1 | M17: 89 | N17: =M17*L17 -> 89 | P17: 1 | Q17: 0 | R17: 0 | S17: 0 | T17: 0 | U17: =SUM(P17:T17) -> 1 | W17: =$N17*P17 -> 89 | X17: =$N17*Q17 -> 0 | Y17: =$N17*R17 -> 0 | Z17: =$N17*S17 -> 0 | AA17: =$N17*T17 -> 0
A18: NF | B18: 80303 | C18: 11 | D18: 524 | E18: Immax | F18: Fundação de desenv. Da pesquisa do agronegócio - FUNDEPAG | G18: 50.276.237/0001-78 | H18: Análise de ácidos graxos Immax | I18: Terceiros | J18: 42541 | K18: 6 | L18: 1 | M18: 524 | N18: =M18*L18 -> 524 | P18: 1 | Q18: 0 | R18: 0 | S18: 0 | T18: 0 | U18: =SUM(P18:T18) -> 1 | W18: =$N18*P18 -> 524 | X18: =$N18*Q18 -> 0 | Y18: =$N18*R18 -> 0 | Z18: =$N18*S18 -> 0 | AA18: =$N18*T18 -> 0
A19: NF | B19: 423 | C19: 12 | D19: 24000 | E19: Immax | F19: Clínica Médica Mourão Faccio S/S | G19: 04.404.467/0001-58 | H19: 1ª parcela do contrato de prestação de serviço estudo clínico Immax | I19: Terceiros | J19: 42608 | K19: 8 | L19: 1 | M19: 24000 | N19: =M19*L19 -> 24000 | P19: 1 | Q19: 0 | R19: 0 | S19: 0 | T19: 0 | U19: =SUM(P19:T19) -> 1 | W19: =$N19*P19 -> 24000 | X19: =$N19*Q19 -> 0 | Y19: =$N19*R19 -> 0 | Z19: =$N19*S19 -> 0 | AA19: =$N19*T19 -> 0
A20: NF | B20: 776332 | C20: 13 | D20: 105.6 | E20: Immax | F20: Contabilista Papelaria e informática | G20: 77.765.840/0001-70 | H20: Materiais | I20: Material | J20: 42633 | K20: 9 | L20: 1 | M20: 105.6 | N20: =M20*L20 -> 105.6 | P20: 1 | Q20: 0 | R20: 0 | S20: 0 | T20: 0 | U20: =SUM(P20:T20) -> 1 | W20: =$N20*P20 -> 105.6 | X20: =$N20*Q20 -> 0 | Y20: =$N20*R20 -> 0 | Z20: =$N20*S20 -> 0 | AA20: =$N20*T20 -> 0
A21: NF | B21: 5270 | C21: 14 | D21: 1323.55 | E21: Immax | F21: Medicalcom Hospitalares Eireli - ME | G21: 21.059.832/0001-53 | H21: Balança de controle corporal - estudo clínico Immax | I21: Material | J21: 42520 | K21: 5 | L21: 1 | M21: 1323.55 | N21: =M21*L21 -> 1323.55 | P21: 1 | Q21: 0 | R21: 0 | S21: 0 | T21: 0 | U21: =SUM(P21:T21) -> 1 | W21: =$N21*P21 -> 1323.55 | X21: =$N21*Q21 -> 0 | Y21: =$N21*R21 -> 0 | Z21: =$N21*S21 -> 0 | AA21: =$N21*T21 -> 0
A22: NF | B22: 6739 | C22: 15 | D22: 240 | E22: Leites terapêuticos | F22: Comercial Brey Ltda | G22: 02.608.645/0001-37 | H22: Seladora de bancada - Leites terapêuticos | I22: Material | J22: 42675 | K22: 11 | L22: 1 | M22: 240 | N22: =M22*L22 -> 240 | P22: 1 | Q22: 0 | R22: 0 | S22: 0 | T22: 0 | U22: =SUM(P22:T22) -> 1 | W22: =$N22*P22 -> 240 | X22: =$N22*Q22 -> 0 | Y22: =$N22*R22 -> 0 | Z22: =$N22*S22 -> 0 | AA22: =$N22*T22 -> 0
... A24: NF | B24: 2162 | C24: 17 | D24: 127.68 | E24: Alzheimer, Bemmax, Immax | F24: Nutrihealth Comercio de Produtos Alimentícios Eireli ME | G24: 14.492.128/0001-89 | H24: Compra de produtos concorrentes | I24: Material | J24: 42706 | K24: 12 | L24: 1 | M24: 127.68 | N24: =M24*L24 -> 127.68 | P24: 1 | Q24: 0 | R24: 0 | S24: 0 | T24: 0 | U24: =SUM(P24:T24) -> 1 | W24: =$N24*P24 -> 127.68 | X24: =$N24*Q24 -> 0 | Y24: =$N24*R24 -> 0 | Z24: =$N24*S24 -> 0 | AA24: =$N24*T24 -> 0
A25: Invoice | B25: 422135 | C25: 18 | D25: 41.25 | E25: Trophic Junior | F25: Covance - The Development Service Company | H25: Densidade volumétrica Trophic Junior | I25: Material | J25: 42605 | K25: 8 | L25: 1 | M25: 41.25 | N25: =M25*L25 -> 41.25 | P25: 1 | Q25: 0 | R25: 0 | S25: 0 | T25: 0 | U25: =SUM(P25:T25) -> 1 | W25: =$N25*P25 -> 41.25 | X25: =$N25*Q25 -> 0 | Y25: =$N25*R25 -> 0 | Z25: =$N25*S25 -> 0 | AA25: =$N25*T25 -> 0
A26: Expresso | B26: Conhec. Aéreo 9692285061 | C26: 19 | D26: 436.44 | E26: Trophic Junior | H26: Envio de amostras de T. Junior para o exterior (Stern) | I26: Material | J26: 42576 | K26: 7 | L26: 1 | M26: 436.44 | N26: =M26*L26 -> 436.44 | P26: 1 | Q26: 0 | R26: 0 | S26: 0 | T26: 0 | U26: =SUM(P26:T26) -> 1 | W26: =$N26*P26 -> 436.44 | X26: =$N26*Q26 -> 0 | Y26: =$N26*R26 -> 0 | Z26: =$N26*S26 -> 0 | AA26: =$N26*T26 -> 0
A27: NF | B27: 5542 | C27: 20 | D27: 3220 | E27: Trophic Junior e mix 16006 | F27: Laboratório Alac Ltda | G27: 94.088.952/0001-52 | H27: Análise de micronutrentes T. Junior (mix 16006) | I27: Terceiros | J27: 42506 | K27: 5 | L27: 0.357195 | M27: 3220 | N27: =M27*L27 -> 1150.1679 | P27: 0.5 | Q27: 0.5 | R27: 0 | S27: 0 | T27: 0 | U27: =SUM(P27:T27) -> 1 | W27: =$N27*P27 -> 575.08395 | X27: =$N27*Q27 -> 575.08395 | Y27: =$N27*R27 -> 0 | Z27: =$N27*S27 -> 0 | AA27: =$N27*T27 -> 0
A28: Fatura | B28: AWB 6152 6505 2282 | C28: 21 | D28: 107.33 | E28: Mix de minerais 16006 | F28: FedEx | G28: 00.676.486/0001-82 | H28: Recebimento de amostra de mix 16006 | I28: Material | J28: 42432 | K28: 3 | L28: 1 | M28: 107.33 | N28: =M28*L28 -> 107.33 | P28: 0 | Q28: 1 | R28: 0 | S28: 0 | T28: 0 | U28: =SUM(P28:T28) -> 1 | W28: =$N28*P28 -> 0 | X28: =$N28*Q28 -> 107.33 | Y28: =$N28*R28 -> 0 | Z28: =$N28*S28 -> 0 | AA28: =$N28*T28 -> 0
A29: NF | B29: 2177 | C29: 22 | D29: 415.6 | E29: PHA Costantino | F29: A. Costantino & C. spa | H29: Recebimento de amostra de PHA Costantino | I29: Material | J29: 42719 | K29: 12 | L29: 1 | M29: 415.6 | N29: =M29*L29 -> 415.6 | P29: 0 | Q29: 1 | R29: 0 | S29: 0 | T29: 0 | U29: =SUM(P29:T29) -> 1 | W29: =$N29*P29 -> 0 | X29: =$N29*Q29 -> 415.6 | Y29: =$N29*R29 -> 0 | Z29: =$N29*S29 -> 0 | AA29: =$N29*T29 -> 0
A30: NF | B30: 27824 | C30: 23 | D30: 950 | E30: Vital Rice | F30: Labor Tres Laboratórios e Consultoria Técnica Ltda | G30: 02.021.076/0001-29 | H30: Análises físico-químicas e microbiológicas Vital Rice | I30: Terceiros | J30: 42647 | K30: 10 | L30: 1 | M30: 950 | N30: =M30*L30 -> 950 | P30: 1 | Q30: 0 | R30: 0 | S30: 0 | T30: 0 | U30: =SUM(P30:T30) -> 1 | W30: =$N30*P30 -> 950 | X30: =$N30*Q30 -> 0 | Y30: =$N30*R30 -> 0 | Z30: =$N30*S30 -> 0 | AA30: =$N30*T30 -> 0
A31: Cupom fiscal | B31: 71047 | C31: 24 | D31: 77.49 | E31: Vital Rice Complete | F31: Callfarma | G31: 08.011.373/0001-70 | H31: Compra de produtos concorrentes | I31: Material | J31: 42664 | K31: 10 | L31: 1 | M31: 77.49 | N31: =M31*L31 -> 77.49 | P31: 1 | Q31: 0 | R31: 0 | S31: 0 | T31: 0 | U31: =SUM(P31:T31) -> 1 | W31: =$N31*P31 -> 77.49 | X31: =$N31*Q31 -> 0 | Y31: =$N31*R31 -> 0 | Z31: =$N31*S31 -> 0 | AA31: =$N31*T31 -> 0
A32: Recibo | B32: 2358 | C32: 25 | D32: 574 | E32: Vital Rice Complete | F32: Associação Paranaense de Cultura - APC | G32: 76.659.820/0003-13 | H32: Teste de bancada na PUC-PR | I32: Terceiros | J32: 42398 | K32: 1 | L32: 1 | M32: 574 | N32: =M32*L32 -> 574 | P32: 1 | Q32: 0 | R32: 0 | S32: 0 | T32: 0 | U32: =SUM(P32:T32) -> 1 | W32: =$N32*P32 -> 574 | X32: =$N32*Q32 -> 0 | Y32: =$N32*R32 -> 0 | Z32: =$N32*S32 -> 0 | AA32: =$N32*T32 -> 0
A33: Recibo | B33: 2389 | C33: 26 | D33: 210 | E33: Vital Rice Complete | F33: Associação Paranaense de Cultura - APC | G33: 76.659.820/0003-13 | H33: Teste de bancada na PUC-PR | I33: Terceiros | J33: 42416 | K33: 2 | L33: 1 | M33: 210 | N33: =M33*L33 -> 210 | P33: 1 | Q33: 0 | R33: 0 | S33: 0 | T33: 0 | U33: =SUM(P33:T33) -> 1 | W33: =$N33*P33 -> 210 | X33: =$N33*Q33 -> 0 | Y33: =$N33*R33 -> 0 | Z33: =$N33*S33 -> 0 | AA33: =$N33*T33 -> 0
A34: NF | B34: 7567 | C34: 27 | D34: 450 | E34: Vital Rice Complete | F34: Laboratório Alac Ltda | G34: 94.088.952/0001-52 | H34: Teste de alergênicos lecitina de soja em pó | I34: Terceiros | J34: 42548 | K34: 6 | L34: 1 | M34: 450 | N34: =M34*L34 -> 450 | P34: 1 | Q34: 0 | R34: 0 | S34: 0 | T34: 0 | U34: =SUM(P34:T34) -> 1 | W34: =$N34*P34 -> 450 | X34: =$N34*Q34 -> 0 | Y34: =$N34*R34 -> 0 | Z34: =$N34*S34 -> 0 | AA34: =$N34*T34 -> 0
A35: Cupons fiscais | C35: 28 | D35: 315.63 | E35: Feira de nutrição enteral | H35: Gastos em Feira de Nutrição Enteral (Felanpe) para prospecção de novos projetos | I35: Material | J35: 42667 | K35: 10 | L35: 1 | M35: 315.63 | N35: =M35*L35 -> 315.63 | P35: 1 | Q35: 0 | R35: 0 | S35: 0 | T35: 0 | U35: =SUM(P35:T35) -> 1 | W35: =$N35*P35 -> 315.63 | X35: =$N35*Q35 -> 0 | Y35: =$N35*R35 -> 0 | Z35: =$N35*S35 -> 0 | AA35: =$N35*T35 -> 0
A36: NF | B36: 158262 | C36: 29 | D36: 25.18 | E36: Caseinato de cálcio Fonterra | F36: Castrolanda | G36: 76.108.349/0014-28 | H36: Envio de 24 amostras de T. Fiber para a Prodiet | I36: Material | J36: 42554 | K36: 7 | L36: 1 | M36: 25.18 | N36: =M36*L36 -> 25.18 | P36: 0 | Q36: 1 | R36: 0 | S36: 0 | T36: 0 | U36: =SUM(P36:T36) -> 1 | W36: =$N36*P36 -> 0 | X36: =$N36*Q36 -> 25.18 | Y36: =$N36*R36 -> 0 | Z36: =$N36*S36 -> 0 | AA36: =$N36*T36 -> 0
A37: NF | B37: 84232 | C37: 30 | D37: 956.4 | E37: Immax, L-leucina | F37: Fundação de desenv. Da pesquisa do agronegócio - FUNDEPAG | G37: 50.276.237/0001-78 | H37: Análises físico-químicas Immax | I37: Terceiros | J37: 42681 | K37: 11 | L37: 1 | M37: 956.4 | N37: =M37*L37 -> 956.4 | P37: 0.5 | Q37: 0.5 | R37: 0 | S37: 0 | T37: 0 | U37: =SUM(P37:T37) -> 1 | W37: =$N37*P37 -> 478.2 | X37: =$N37*Q37 -> 478.2 | Y37: =$N37*R37 -> 0 | Z37: =$N37*S37 -> 0 | AA37: =$N37*T37 -> 0
A38: NF | B38: 15516 | C38: 31 | D38: 1772.25 | E38: Mix 150243, PHA Friesl, T. Infant | F38: Laboratório Alac Ltda | G38: 94.088.952/0001-52 | H38: Análises vitaminas T. Infant nova fórmula; alergênico PHA | I38: Terceiros | J38: 42733 | K38: 12 | L38: 1 | M38: 1772.25 | N38: =M38*L38 -> 1772.25 | P38: 0 | Q38: 0.66666667 | R38: 0.33333333 | S38: 0 | T38: 0 | U38: =SUM(P38:T38) -> 1 | W38: =$N38*P38 -> 0 | X38: =$N38*Q38 -> 1181.5 | Y38: =$N38*R38 -> 590.75 | Z38: =$N38*S38 -> 0 | AA38: =$N38*T38 -> 0
A39: NF | B39: 27583 | C39: 32 | D39: 305 | E39: T. Infant, MPC Fonterra, Loremalt 2030M, Açúcar K, mix 150243 | F39: Labor Tres Laboratórios e Consultoria Técnica Ltda | G39: 02.021.076/0001-29 | H39: FQ T. Infant nova fórmula | I39: Terceiros | J39: 42615 | K39: 9 | L39: 1 | M39: 305 | N39: =M39*L39 -> 305 | P39: 0 | Q39: 0.8 | R39: 0.2 | S39: 0 | T39: 0 | U39: =SUM(P39:T39) -> 1 | W39: =$N39*P39 -> 0 | X39: =$N39*Q39 -> 244 | Y39: =$N39*R39 -> 61 | Z39: =$N39*S39 -> 0 | AA39: =$N39*T39 -> 0
A40: NF | B40: 13354 | C40: 33 | D40: 1344.25 | E40: T. EP e mix 152349 | F40: Laboratório Alac Ltda | G40: 94.088.952/0001-52 | H40: Analisa os testes dos produtos e dá assistência na parametrização do produto e dos novos testes a serem feitos. Faz acompanhamento técnico de todos os projetos de pesquisa e desenvolvimento. | I40: Terceiros | J40: 42683 | K40: 11 | L40: 1 | M40: 1344.25 | N40: =M40*L40 -> 1344.25 | P40: 0 | Q40: 0.5 | R40: 0.5 | S40: 0 | T40: 0 | U40: =SUM(P40:T40) -> 1 | W40: =$N40*P40 -> 0 | X40: =$N40*Q40 -> 672.125 | Y40: =$N40*R40 -> 672.125 | Z40: =$N40*S40 -> 0 | AA40: =$N40*T40 -> 0
A41: NF | B41: 8891 | C41: 34 | D41: 4254.3 | E41: Bio e Pept. (red. Na e P); T. Junior, mix 16006, mix 151160 | F41: Laboratório Alac Ltda | G41: 94.088.952/0001-52 | H41: Análises micronut. Bio, Pept., T. Fiber e T. Junior | I41: Terceiros | J41: 42578 | K41: 7 | L41: 1 | M41: 4254.3 | N41: =M41*L41 -> 4254.3 | P41: 0.04 | Q41: 0.08 | R41: 0.88 | S41: 0 | T41: 0 | U41: =SUM(P41:T41) -> 1 | W41: =$N41*P41 -> 170.172 | X41: =$N41*Q41 -> 340.344 | Y41: =$N41*R41 -> 3743.784 | Z41: =$N41*S41 -> 0 | AA41: =$N41*T41 -> 0
A42: NF | B42: 5003 | C42: 35 | D42: 2550.17 | E42: Mix 151160 | F42: Laboratório Alac Ltda | G42: 94.088.952/0001-52 | H42: Análise de minerais T.Fiber | I42: Terceiros | J42: 42496 | K42: 2 | L42: 0.451018 | M42: 2550.17 | N42: =M42*L42 -> 1150.1726 | P42: 0 | Q42: 1 | R42: 0 | S42: 0 | T42: 0 | U42: =SUM(P42:T42) -> 1 | W42: =$N42*P42 -> 0 | X42: =$N42*Q42 -> 1150.1726 | Y42: =$N42*R42 -> 0 | Z42: =$N42*S42 -> 0 | AA42: =$N42*T42 -> 0
A43: NF | B43: 28066 | C43: 36 | D43: 990 | E43: Trophic Junior, T. Basic pó | F43: Labor Tres Laboratórios e Consultoria Técnica Ltda | G43: 02.021.076/0001-29 | H43: Análise microbiologia T. Junior/T. Basic | I43: Terceiros | J43: 42677 | K43: 2 | L43: 0.42929 | M43: 990 | N43: =M43*L43 -> 424.9971 | P43: 0.33333333 | Q43: 0.33333333 | R43: 0 | S43: 0.33333333 | T43: 0 | U43: =SUM(P43:T43) -> 1 | W43: =$N43*P43 -> 141.6657 | X43: =$N43*Q43 -> 141.6657 | Y43: =$N43*R43 -> 0 | Z43: =$N43*S43 -> 141.6657 | AA43: =$N43*T43 -> 0
A44: Cupons fiscais e bilhete e-ticket | C44: 37 | D44: 347.04 | E44: Feira de ingredientes | H44: Participação em feira de ingredientes para prospecção de novas MP | I44: Material | J44: 42607 | K44: 8 | L44: 1 | M44: 347.04 | N44: =M44*L44 -> 347.04 | P44: 0 | Q44: 1 | R44: 0 | S44: 0 | T44: 0 | U44: =SUM(P44:T44) -> 1 | W44: =$N44*P44 -> 0 | X44: =$N44*Q44 -> 347.04 | Y44: =$N44*R44 -> 0 | Z44: =$N44*S44 -> 0 | AA44: =$N44*T44 -> 0
A45: NF | B45: 74225 | C45: 38 | D45: 281.93 | E45: Peptimax lata | F45: TUV SUD SFDK Laboratório de Análise de Produto LTDA | G45: 55.953.079/0001-67 | H45: Análise de shelf life primeira produção de Peptimax lata | I45: Terceiros | J45: 42662 | K45: 10 | L45: 1 | M45: 281.93 | N45: =M45*L45 -> 281.93 | P45: 0 | Q45: 0 | R45: 0 | S45: 1 | T45: 0 | U45: =SUM(P45:T45) -> 1 | W45: =$N45*P45 -> 0 | X45: =$N45*Q45 -> 0 | Y45: =$N45*R45 -> 0 | Z45: =$N45*S45 -> 281.93 | AA45: =$N45*T45 -> 0
A46: NF | B46: 69032 | C46: 39 | D46: 710.15 | E46: Energyzip 1.0 | F46: TUV SUD SFDK Laboratório de Análise de Produto LTDA | G46: 55.953.079/0001-67 | H46: Primeira produção de E 1.0 Castrolanda | I46: Terceiros | J46: 42404 | K46: 2 | L46: 1 | M46: 710.15 | N46: =M46*L46 -> 710.15 | P46: 0 | Q46: 0 | R46: 0 | S46: 1 | T46: 0 | U46: =SUM(P46:T46) -> 1 | W46: =$N46*P46 -> 0 | X46: =$N46*Q46 -> 0 | Y46: =$N46*R46 -> 0 | Z46: =$N46*S46 -> 710.15 | AA46: =$N46*T46 -> 0
A47: NF | B47: 7976 | C47: 40 | D47: 290 | E47: Energyzip 1.0 | F47: Laboratório Alac Ltda | G47: 94.088.952/0001-52 | H47: Shelf Life E 1.0 com maior tempo de retardo e menor temperatura de esterilização | I47: Terceiros | J47: 42557 | K47: 7 | L47: 1 | M47: 290 | N47: =M47*L47 -> 290 | P47: 0 | Q47: 0 | R47: 0 | S47: 1 | T47: 0 | U47: =SUM(P47:T47) -> 1 | W47: =$N47*P47 -> 0 | X47: =$N47*Q47 -> 0 | Y47: =$N47*R47 -> 0 | Z47: =$N47*S47 -> 290 | AA47: =$N47*T47 -> 0
A48: NF | B48: 15490 | C48: 41 | D48: 1330 | E48: T. Junior, T 1.5, Diamax, Peptimax, T. Basic líq, E. 10, T. Fiber | F48: Fundação de estudos e pesquisas aquáticas - FUNDESPA | G48: 61.379.657/0001-04 | H48: Análises de shelf life | I48: Terceiros | J48: 42495 | K48: 5 | L48: 1 | M48: 1330 | N48: =M48*L48 -> 1330 | P48: 0.14285714 | Q48: 0 | R48: 0 | S48: 0.85714286 | T48: 0 | U48: =SUM(P48:T48) -> 1 | W48: =$N48*P48 -> 190 | X48: =$N48*Q48 -> 0 | Y48: =$N48*R48 -> 0 | Z48: =$N48*S48 -> 1140 | AA48: =$N48*T48 -> 0
A49: NF | B49: 70623 | C49: 42 | D49: 1775.38 | E49: Diamax, E.10, T. Basic líq, T.15, T. Fiber | F49: TUV SUD SFDK Laboratório de Análise de Produto LTDA | G49: 55.953.079/0001-67 | H49: Análises de shelf life | I49: Terceiros | J49: 42480 | K49: 6 | L49: 1 | M49: 1775.38 | N49: =M49*L49 -> 1775.38 | P49: 0 | Q49: 0 | R49: 0 | S49: 1 | T49: 0 | U49: =SUM(P49:T49) -> 1 | W49: =$N49*P49 -> 0 | X49: =$N49*Q49 -> 0 | Y49: =$N49*R49 -> 0 | Z49: =$N49*S49 -> 1775.38 | AA49: =$N49*T49 -> 0
A50: NF | B50: 17048 | C50: 43 | D50: 760 | E50: T. Fiber, T 1.5, T EP, Peptimax | F50: Fundação de estudos e pesquisas aquáticas - FUNDESPA | G50: 61.379.657/0001-04 | H50: Análises distribuição de tamanho de partícula | I50: Terceiros | J50: 42702 | K50: 11 | L50: 1 | M50: 760 | N50: =M50*L50 -> 760 | P50: 0 | Q50: 0 | R50: 0.75 | S50: 0.25 | T50: 0 | U50: =SUM(P50:T50) -> 1 | W50: =$N50*P50 -> 0 | X50: =$N50*Q50 -> 0 | Y50: =$N50*R50 -> 570 | Z50: =$N50*S50 -> 190 | AA50: =$N50*T50 -> 0
A51: NF | B51: 16158 | C51: 44 | D51: 380 | E51: E. chocolate, T. Fiber (caseinato Ca) | F51: Fundação de estudos e pesquisas aquáticas - FUNDESPA | G51: 61.379.657/0001-04 | H51: Distribuição de partícula - E. chocolate e T Fiber com novo caseinato | I51: Terceiros | J51: 42593 | K51: 8 | L51: 1 | M51: 380 | N51: =M51*L51 -> 380 | P51: 0 | Q51: 0.5 | R51: 0.5 | S51: 0 | T51: 0 | U51: =SUM(P51:T51) -> 1 | W51: =$N51*P51 -> 0 | X51: =$N51*Q51 -> 190 | Y51: =$N51*R51 -> 190 | Z51: =$N51*S51 -> 0 | AA51: =$N51*T51 -> 0
A52: NF | B52: 38029 | C52: 45 | D52: 1303.4 | E52: Peptimax lata, T. Bio | F52: Bioagri Analises de alimentos Ltda | G52: 00.000.410/0001-32 | H52: Ácidos graxos T. Bio lecitinado e Peptimax lata | I52: Terceiros | J52: 04/11/2-16 | K52: 11 | L52: 1 | M52: 1303.4 | N52: =M52*L52 -> 1303.4 | P52: 0 | Q52: 0 | R52: 0.5 | S52: 0.5 | T52: 0 | U52: =SUM(P52:T52) -> 1 | W52: =$N52*P52 -> 0 | X52: =$N52*Q52 -> 0 | Y52: =$N52*R52 -> 651.7 | Z52: =$N52*S52 -> 651.7 | AA52: =$N52*T52 -> 0
A53: NF | B53: 84627 | C53: 46 | D53: 3773 | E53: Trophic EP (mix 152349) | F53: Fundação de desenv. Da pesquisa do agronegócio - FUNDEPAG | G53: 50.276.237/0001-78 | H53: Análise de vitaminas Trophic EP baixa viscosidade | I53: Terceiros | J53: 42697 | K53: 11 | L53: 1 | M53: 3773 | N53: =M53*L53 -> 3773 | P53: 0 | Q53: 0.5 | R53: 0.5 | S53: 0 | T53: 0 | U53: =SUM(P53:T53) -> 1 | W53: =$N53*P53 -> 0 | X53: =$N53*Q53 -> 1886.5 | Y53: =$N53*R53 -> 1886.5 | Z53: =$N53*S53 -> 0 | AA53: =$N53*T53 -> 0
A54: NF | B54: 70624 | C54: 47 | D54: 760.85 | E54: Trophic Infant e Peptimax | F54: TUV SUD SFDK Laboratório de Análise de Produto LTDA | G54: 55.953.079/0001-67 | H54: Análise microbiologia T Infant e Peptimax lata | I54: Terceiros | J54: 42480 | K54: 4 | L54: 1 | M54: 760.85 | N54: =M54*L54 -> 760.85 | P54: 0 | Q54: 0 | R54: 0.66666667 | S54: 0.33333333 | T54: 0 | U54: =SUM(P54:T54) -> 1 | W54: =$N54*P54 -> 0 | X54: =$N54*Q54 -> 0 | Y54: =$N54*R54 -> 507.23333 | Z54: =$N54*S54 -> 253.61667 | AA54: =$N54*T54 -> 0
A55: NF | B55: 81076 | C55: 48 | D55: 5127.7 | E55: Trophic Bio e Peptimax | F55: Fundação de desenv. Da pesquisa do agronegócio - FUNDEPAG | G55: 50.276.237/0001-78 | H55: Análise de micronutrientes para estudo de redução de Na e P | I55: Terceiros | J55: 42569 | K55: 7 | L55: 1 | M55: 5127.7 | N55: =M55*L55 -> 5127.7 | P55: 0 | Q55: 0 | R55: 1 | S55: 0 | T55: 0 | U55: =SUM(P55:T55) -> 1 | W55: =$N55*P55 -> 0 | X55: =$N55*Q55 -> 0 | Y55: =$N55*R55 -> 5127.7 | Z55: =$N55*S55 -> 0 | AA55: =$N55*T55 -> 0
A56: NF | B56: 80302 | C56: 49 | D56: 5127.7 | E56: Trophic Bio e Peptimax | F56: Fundação de desenv. Da pesquisa do agronegócio - FUNDEPAG | G56: 50.276.237/0001-78 | H56: Análise de micronutrientes para estudo de redução de Na e P | I56: Terceiros | J56: 42541 | K56: 6 | L56: 1 | M56: 5127.7 | N56: =M56*L56 -> 5127.7 | P56: 0 | Q56: 0 | R56: 1 | S56: 0 | T56: 0 | U56: =SUM(P56:T56) -> 1 | W56: =$N56*P56 -> 0 | X56: =$N56*Q56 -> 0 | Y56: =$N56*R56 -> 5127.7 | Z56: =$N56*S56 -> 0 | AA56: =$N56*T56 -> 0
A57: Invoice | B57: 411869 | C57: 50 | D57: 4198.47 | E57: T. Bio, Peptimax e Immax | F57: Covance - The Development Service Company | H57: Análise de micronutrientes - NP e redução de Na e P | I57: Material | J57: 42598 | K57: 8 | L57: 1 | M57: 4198.47 | N57: =M57*L57 -> 4198.47 | P57: 0.33333333 | Q57: 0 | R57: 0.66666667 | S57: 0 | T57: 0 | U57: =SUM(P57:T57) -> 1 | W57: =$N57*P57 -> 1399.49 | X57: =$N57*Q57 -> 0 | Y57: =$N57*R57 -> 2798.98 | Z57: =$N57*S57 -> 0 | AA57: =$N57*T57 -> 0
A58: NF | B58: 10844 | C58: 51 | D58: 436.5 | E58: Trophic Basic | F58: Laboratório Alac Ltda | G58: 94.088.952/0001-52 | H58: Análises de micronutrientes para estudo de redução Na e P | I58: Terceiros | J58: 42621 | K58: 9 | L58: 1 | M58: 436.5 | N58: =M58*L58 -> 436.5 | P58: 0 | Q58: 0 | R58: 1 | S58: 0 | T58: 0 | U58: =SUM(P58:T58) -> 1 | W58: =$N58*P58 -> 0 | X58: =$N58*Q58 -> 0 | Y58: =$N58*R58 -> 436.5 | Z58: =$N58*S58 -> 0 | AA58: =$N58*T58 -> 0
A59: NF | B59: 83455 | C59: 52 | D59: 524 | E59: Trophic Infant | F59: Fundação de desenv. Da pesquisa do agronegócio - FUNDEPAG | G59: 50.276.237/0001-78 | H59: Análises ácidos graxos T. Infant nova fórmula | I59: Terceiros | J59: 42653 | K59: 10 | L59: 1 | M59: 524 | N59: =M59*L59 -> 524 | P59: 0 | Q59: 0 | R59: 1 | S59: 0 | T59: 0 | U59: =SUM(P59:T59) -> 1 | W59: =$N59*P59 -> 0 | X59: =$N59*Q59 -> 0 | Y59: =$N59*R59 -> 524 | Z59: =$N59*S59 -> 0 | AA59: =$N59*T59 -> 0
A60: NF | B60: 12036 | C60: 53 | D60: 1217.75 | E60: Diamax | F60: Laboratório Alac Ltda | G60: 94.088.952/0001-52 | H60: Micronutrientes Diamax para estudo de extensão de validade | I60: Terceiros | J60: 42657 | K60: 10 | L60: 1 | M60: 1217.75 | N60: =M60*L60 -> 1217.75 | P60: 0 | Q60: 0 | R60: 1 | S60: 0 | T60: 0 | U60: =SUM(P60:T60) -> 1 | W60: =$N60*P60 -> 0 | X60: =$N60*Q60 -> 0 | Y60: =$N60*R60 -> 1217.75 | Z60: =$N60*S60 -> 0 | AA60: =$N60*T60 -> 0
A61: NF | B61: 12603 | C61: 54 | D61: 1359.25 | E61: Energyzip baunilha | F61: Laboratório Alac Ltda | G61: 94.088.952/0001-52 | H61: Micronutrientes E. baun para estudo de extensão de validade | I61: Terceiros | J61: 42664 | K61: 10 | L61: 1 | M61: 1359.25 | N61: =M61*L61 -> 1359.25 | P61: 0 | Q61: 0 | R61: 1 | S61: 0 | T61: 0 | U61: =SUM(P61:T61) -> 1 | W61: =$N61*P61 -> 0 | X61: =$N61*Q61 -> 0 | Y61: =$N61*R61 -> 1359.25 | Z61: =$N61*S61 -> 0 | AA61: =$N61*T61 -> 0
A62: Recibo | C62: 55 | D62: 2220 | E62: ILSI | F62: ILSI Brasil | G62: 65.086.001/0001-46 | H62: ILSI mensalidade julho | I62: Terceiros | J62: 42552 | K62: 7 | L62: 1 | M62: 2220 | N62: =M62*L62 -> 2220 | P62: 0 | Q62: 0 | R62: 0 | S62: 0 | T62: 1 | U62: =SUM(P62:T62) -> 1 | W62: =$N62*P62 -> 0 | X62: =$N62*Q62 -> 0 | Y62: =$N62*R62 -> 0 | Z62: =$N62*S62 -> 0 | AA62: =$N62*T62 -> 2220
A63: Recibo | C63: 56 | D63: 2220 | E63: ILSI | F63: ILSI Brasil | G63: 65.086.001/0001-46 | H63: ILSI mensalidade agosto | I63: Terceiros | J63: 42583 | K63: 8 | L63: 1 | M63: 2220 | N63: =M63*L63 -> 2220 | P63: 0 | Q63: 0 | R63: 0 | S63: 0 | T63: 1 | U63: =SUM(P63:T63) -> 1 | W63: =$N63*P63 -> 0 | X63: =$N63*Q63 -> 0 | Y63: =$N63*R63 -> 0 | Z63: =$N63*S63 -> 0 | AA63: =$N63*T63 -> 2220
A64: Recibo | C64: 57 | D64: 2220 | E64: ILSI | F64: ILSI Brasil | G64: 65.086.001/0001-46 | H64: ILSI mensalidade setembro | I64: Terceiros | J64: 42618 | K64: 9 | L64: 1 | M64: 2220 | N64: =M64*L64 -> 2220 | P64: 0 | Q64: 0 | R64: 0 | S64: 0 | T64: 1 | U64: =SUM(P64:T64) -> 1 | W64: =$N64*P64 -> 0 | X64: =$N64*Q64 -> 0 | Y64: =$N64*R64 -> 0 | Z64: =$N64*S64 -> 0 | AA64: =$N64*T64 -> 2220
A65: Recibo | C65: 58 | D65: 2220 | E65: ILSI | F65: ILSI Brasil | G65: 65.086.001/0001-46 | H65: ILSI mensalidade outubro | I65: Terceiros | J65: 42646 | K65: 10 | L65: 1 | M65: 2220 | N65: =M65*L65 -> 2220 | P65: 0 | Q65: 0 | R65: 0 | S65: 0 | T65: 1 | U65: =SUM(P65:T65) -> 1 | W65: =$N65*P65 -> 0 | X65: =$N65*Q65 -> 0 | Y65: =$N65*R65 -> 0 | Z65: =$N65*S65 -> 0 | AA65: =$N65*T65 -> 2220
A66: Recibo | C66: 59 | D66: 2220 | E66: ILSI | F66: ILSI Brasil | G66: 65.086.001/0001-46 | H66: ILSI mensalidade novembro | I66: Terceiros | J66: 42675 | K66: 11 | L66: 1 | M66: 2220 | N66: =M66*L66 -> 2220 | P66: 0 | Q66: 0 | R66: 0 | S66: 0 | T66: 1 | U66: =SUM(P66:T66) -> 1 | W66: =$N66*P66 -> 0 | X66: =$N66*Q66 -> 0 | Y66: =$N66*R66 -> 0 | Z66: =$N66*S66 -> 0 | AA66: =$N66*T66 -> 2220
A67: Recibo | C67: 60 | D67: 2220 | E67: ILSI | F67: ILSI Brasil | G67: 65.086.001/0001-46 | H67: ILSI mensalidade dezembro | I67: Terceiros | J67: 42705 | K67: 12 | L67: 1 | M67: 2220 | N67: =M67*L67 -> 2220 | P67: 0 | Q67: 0 | R67: 0 | S67: 0 | T67: 1 | U67: =SUM(P67:T67) -> 1 | W67: =$N67*P67 -> 0 | X67: =$N67*Q67 -> 0 | Y67: =$N67*R67 -> 0 | Z67: =$N67*S67 -> 0 | AA67: =$N67*T67 -> 2220
A68: Recibo | C68: 61 | D68: 40 | E68: ILSI | F68: ILSI Brasil | G68: 65.086.001/0001-46 | H68: ILSI aquisição de livros | I68: Terceiros | J68: 42627 | K68: 9 | L68: 1 | M68: 40 | N68: =M68*L68 -> 40 | P68: 0 | Q68: 0 | R68: 0 | S68: 0 | T68: 1 | U68: =SUM(P68:T68) -> 1 | W68: =$N68*P68 -> 0 | X68: =$N68*Q68 -> 0 | Y68: =$N68*R68 -> 0 | Z68: =$N68*S68 -> 0 | AA68: =$N68*T68 -> 40
A69: Recibo | C69: 62 | D69: 50 | E69: ILSI | F69: ILSI Brasil | G69: 65.086.001/0001-46 | H69: ILSI workshop | I69: Terceiros | J69: 42622 | K69: 9 | L69: 1 | M69: 50 | N69: =M69*L69 -> 50 | P69: 0 | Q69: 0 | R69: 0 | S69: 0 | T69: 1 | U69: =SUM(P69:T69) -> 1 | W69: =$N69*P69 -> 0 | X69: =$N69*Q69 -> 0 | Y69: =$N69*R69 -> 0 | Z69: =$N69*S69 -> 0 | AA69: =$N69*T69 -> 50
A70: Bilhete e-ticket | B70: 957 213526024/577 0005867190 | C70: 63 | D70: 350 | E70: ILSI | F70: LATAM e Azul Linhas Aéreas | H70: Passagens Hellin IDA e VOLTA workshop ILSI setembro | I70: Material | J70: 42626 | K70: 9 | L70: 1 | M70: 350 | N70: =M70*L70 -> 350 | P70: 0 | Q70: 0 | R70: 0 | S70: 0 | T70: 1 | U70: =SUM(P70:T70) -> 1 | W70: =$N70*P70 -> 0 | X70: =$N70*Q70 -> 0 | Y70: =$N70*R70 -> 0 | Z70: =$N70*S70 -> 0 | AA70: =$N70*T70 -> 350
A71: Recibo | C71: 64 | D71: 250 | E71: ILSI | F71: ILSI Brasil | G71: 65.086.001/0001-46 | H71: ILSI série de workshops | I71: Terceiros | J71: 42671 | K71: 10 | L71: 1 | M71: 250 | N71: =M71*L71 -> 250 | P71: 0 | Q71: 0 | R71: 0 | S71: 0 | T71: 1 | U71: =SUM(P71:T71) -> 1 | W71: =$N71*P71 -> 0 | X71: =$N71*Q71 -> 0 | Y71: =$N71*R71 -> 0 | Z71: =$N71*S71 -> 0 | AA71: =$N71*T71 -> 250
A72: Confirmação reserva | B72: 1167152312 | C72: 65 | D72: 290 | E72: ILSI | F72: Blue Tree Premium Paulista | H72: Reserva hotel Hellin - ILSI série de workshops | I72: Material | J72: 42681 | K72: 11 | L72: 1 | M72: 290 | N72: =M72*L72 -> 290 | P72: 0 | Q72: 0 | R72: 0 | S72: 0 | T72: 1 | U72: =SUM(P72:T72) -> 1 | W72: =$N72*P72 -> 0 | X72: =$N72*Q72 -> 0 | Y72: =$N72*R72 -> 0 | Z72: =$N72*S72 -> 0 | AA72: =$N72*T72 -> 290
A73: Bilhete e-ticket | B73: 247 2426021755/957 2137652929 | C73: 66 | D73: 396.12 | E73: ILSI | F73: Avianca e LATAM | H73: Passagens Hellin - ILSI série de workshops | I73: Material | J73: 42681 | K73: 11 | L73: 1 | M73: 396.12 | N73: =M73*L73 -> 396.12 | P73: 0 | Q73: 0 | R73: 0 | S73: 0 | T73: 1 | U73: =SUM(P73:T73) -> 1 | W73: =$N73*P73 -> 0 | X73: =$N73*Q73 -> 0 | Y73: =$N73*R73 -> 0 | Z73: =$N73*S73 -> 0 | AA73: =$N73*T73 -> 396.12
A74: Recibo | C74: 67 | D74: 50 | E74: ILSI | F74: ILSI Brasil | G74: 65.086.001/0001-46 | H74: ILSI workshop | I74: Terceiros | J74: 42423 | K74: 2 | L74: 1 | M74: 50 | N74: =M74*L74 -> 50 | P74: 0 | Q74: 0 | R74: 0 | S74: 0 | T74: 1 | U74: =SUM(P74:T74) -> 1 | W74: =$N74*P74 -> 0 | X74: =$N74*Q74 -> 0 | Y74: =$N74*R74 -> 0 | Z74: =$N74*S74 -> 0 | AA74: =$N74*T74 -> 50
A75: Bilhete e-ticket/Cupons fiscais | B75: 957 2124724203 | C75: 68 | D75: 773.78 | E75: ILSI | H75: Gastos Jana - workshop ILSI fevereiro | I75: Material | J75: 42425 | K75: 2 | L75: 1 | M75: 773.78 | N75: =M75*L75 -> 773.78 | P75: 0 | Q75: 0 | R75: 0 | S75: 0 | T75: 1 | U75: =SUM(P75:T75) -> 1 | W75: =$N75*P75 -> 0 | X75: =$N75*Q75 -> 0 | Y75: =$N75*R75 -> 0 | Z75: =$N75*S75 -> 0 | AA75: =$N75*T75 -> 773.78
A76: Bilhete e-ticket | B76: 957 2126179902 | C76: 69 | D76: 695.28 | E76: ILSI | F76: TAM | H76: Passagem workshop ILSI - Jana | I76: Material | J76: 42439 | K76: 3 | L76: 1 | M76: 695.28 | N76: =M76*L76 -> 695.28 | P76: 0 | Q76: 0 | R76: 0 | S76: 0 | T76: 1 | U76: =SUM(P76:T76) -> 1 | W76: =$N76*P76 -> 0 | X76: =$N76*Q76 -> 0 | Y76: =$N76*R76 -> 0 | Z76: =$N76*S76 -> 0 | AA76: =$N76*T76 -> 695.28
A77: Recibo | C77: 70 | D77: 25 | E77: ILSI | F77: ILSI Brasil | G77: 65.086.001/0001-46 | H77: ILSI workshop | I77: Terceiros | J77: 42437 | K77: 3 | L77: 1 | M77: 25 | N77: =M77*L77 -> 25 | P77: 0 | Q77: 0 | R77: 0 | S77: 0 | T77: 1 | U77: =SUM(P77:T77) -> 1 | W77: =$N77*P77 -> 0 | X77: =$N77*Q77 -> 0 | Y77: =$N77*R77 -> 0 | Z77: =$N77*S77 -> 0 | AA77: =$N77*T77 -> 25
A78: Cupons fiscais | C78: 71 | D78: 261.7 | E78: ILSI | H78: Gastos Jana - workshop ILSI março | I78: Material | J78: 42439 | K78: 3 | L78: 1 | M78: 261.7 | N78: =M78*L78 -> 261.7 | P78: 0 | Q78: 0 | R78: 0 | S78: 0 | T78: 1 | U78: =SUM(P78:T78) -> 1 | W78: =$N78*P78 -> 0 | X78: =$N78*Q78 -> 0 | Y78: =$N78*R78 -> 0 | Z78: =$N78*S78 -> 0 | AA78: =$N78*T78 -> 261.7
A79: Bilhete e-ticket | B79: 247 2425232331/127 0001897631 | C79: 72 | D79: 555.26 | E79: ILSI | F79: Aviana e GOL | H79: Gastos Hellin - reunião geral ILSI 14/10 | I79: Material | J79: 42657 | K79: 10 | L79: 1 | M79: 555.26 | N79: =M79*L79 -> 555.26 | P79: 0 | Q79: 0 | R79: 0 | S79: 0 | T79: 1 | U79: =SUM(P79:T79) -> 1 | W79: =$N79*P79 -> 0 | X79: =$N79*Q79 -> 0 | Y79: =$N79*R79 -> 0 | Z79: =$N79*S79 -> 0 | AA79: =$N79*T79 -> 555.26
A80: Recibo | C80: 73 | D80: 130.39 | E80: ILSI | H80: Gastos transporte Hellin - reunião geral ILSI 14/10 | I80: Material | J80: 42657 | K80: 10 | L80: 1 | M80: 130.39 | N80: =M80*L80 -> 130.39 | P80: 0 | Q80: 0 | R80: 0 | S80: 0 | T80: 1 | U80: =SUM(P80:T80) -> 1 | W80: =$N80*P80 -> 0 | X80: =$N80*Q80 -> 0 | Y80: =$N80*R80 -> 0 | Z80: =$N80*S80 -> 0 | AA80: =$N80*T80 -> 130.39
A81: Cupons fiscais | C81: 74 | D81: 165 | E81: ILSI | H81: Gastos Jana - reunião geral ILSI 14/10 | I81: Material | J81: 42480 | K81: 4 | L81: 1 | M81: 165 | N81: =M81*L81 -> 165 | P81: 0 | Q81: 0 | R81: 0 | S81: 0 | T81: 1 | U81: =SUM(P81:T81) -> 1 | W81: =$N81*P81 -> 0 | X81: =$N81*Q81 -> 0 | Y81: =$N81*R81 -> 0 | Z81: =$N81*S81 -> 0 | AA81: =$N81*T81 -> 165
A82: Bilhete e-ticket | B82: 957 212697498 | C82: 75 | D82: 359.94 | E82: ILSI | F82: TAM | H82: Passagem reunião geral ILSI - Jana | I82: Material | J82: 42480 | K82: 4 | L82: 1 | M82: 359.94 | N82: =M82*L82 -> 359.94 | P82: 0 | Q82: 0 | R82: 0 | S82: 0 | T82: 1 | U82: =SUM(P82:T82) -> 1 | W82: =$N82*P82 -> 0 | X82: =$N82*Q82 -> 0 | Y82: =$N82*R82 -> 0 | Z82: =$N82*S82 -> 0 | AA82: =$N82*T82 -> 359.94
A83: Bilhete e-ticket | B83: 577 0005846198/957 2133365958 | C83: 76 | D83: 411.26 | E83: ILSI | F83: Azul e LATAM | H83: Passagem reunião geral ILSI - Hellin | I83: Material | J83: 42605 | K83: 8 | L83: 1 | M83: 411.26 | N83: =M83*L83 -> 411.26 | P83: 0 | Q83: 0 | R83: 0 | S83: 0 | T83: 1 | U83: =SUM(P83:T83) -> 1 | W83: =$N83*P83 -> 0 | X83: =$N83*Q83 -> 0 | Y83: =$N83*R83 -> 0 | Z83: =$N83*S83 -> 0 | AA83: =$N83*T83 -> 411.26
A84: Bilhete e-ticket e recibos | B84: 127 0001931180 | C84: 77 | D84: 718.73 | E84: ILSI | H84: Gastos e passagem Hellin - reunião geral ILSI 29/11 | I84: Material | J84: 42703 | K84: 11 | L84: 1 | M84: 718.73 | N84: =M84*L84 -> 718.73 | P84: 0 | Q84: 0 | R84: 0 | S84: 0 | T84: 1 | U84: =SUM(P84:T84) -> 1 | W84: =$N84*P84 -> 0 | X84: =$N84*Q84 -> 0 | Y84: =$N84*R84 -> 0 | Z84: =$N84*S84 -> 0 | AA84: =$N84*T84 -> 718.73
A85: Recibo | C85: 78 | D85: 2220 | E85: ILSI | F85: ILSI Brasil | G85: 65.086.001/0001-46 | H85: ILSI mensalidade janeiro | I85: Terceiros | J85: 42380 | K85: 1 | L85: 1 | M85: 2220 | N85: =M85*L85 -> 2220 | P85: 0 | Q85: 0 | R85: 0 | S85: 0 | T85: 1 | U85: =SUM(P85:T85) -> 1 | W85: =$N85*P85 -> 0 | X85: =$N85*Q85 -> 0 | Y85: =$N85*R85 -> 0 | Z85: =$N85*S85 -> 0 | AA85: =$N85*T85 -> 2220
A86: Recibo | C86: 79 | D86: 2220 | E86: ILSI | F86: ILSI Brasil | G86: 65.086.001/0001-46 | H86: ILSI mensalidade fevereiro | I86: Terceiros | J86: 42401 | K86: 2 | L86: 1 | M86: 2220 | N86: =M86*L86 -> 2220 | P86: 0 | Q86: 0 | R86: 0 | S86: 0 | T86: 1 | U86: =SUM(P86:T86) -> 1 | W86: =$N86*P86 -> 0 | X86: =$N86*Q86 -> 0 | Y86: =$N86*R86 -> 0 | Z86: =$N86*S86 -> 0 | AA86: =$N86*T86 -> 2220
A87: Recibo | C87: 80 | D87: 2220 | E87: ILSI | F87: ILSI Brasil | G87: 65.086.001/0001-46 | H87: ILSI mensalidade março | I87: Terceiros | J87: 42430 | K87: 3 | L87: 1 | M87: 2220 | N87: =M87*L87 -> 2220 | P87: 0 | Q87: 0 | R87: 0 | S87: 0 | T87: 1 | U87: =SUM(P87:T87) -> 1 | W87: =$N87*P87 -> 0 | X87: =$N87*Q87 -> 0 | Y87: =$N87*R87 -> 0 | Z87: =$N87*S87 -> 0 | AA87: =$N87*T87 -> 2220
A88: Recibo | C88: 81 | D88: 2220 | E88: ILSI | F88: ILSI Brasil | G88: 65.086.001/0001-46 | H88: ILSI mensalidade abril | I88: Terceiros | J88: 42461 | K88: 4 | L88: 1 | M88: 2220 | N88: =M88*L88 -> 2220 | P88: 0 | Q88: 0 | R88: 0 | S88: 0 | T88: 1 | U88: =SUM(P88:T88) -> 1 | W88: =$N88*P88 -> 0 | X88: =$N88*Q88 -> 0 | Y88: =$N88*R88 -> 0 | Z88: =$N88*S88 -> 0 | AA88: =$N88*T88 -> 2220
A89: Recibo | C89: 82 | D89: 2220 | E89: ILSI | F89: ILSI Brasil | G89: 65.086.001/0001-46 | H89: ILSI mensalidade maio | I89: Terceiros | J89: 42492 | K89: 5 | L89: 1 | M89: 2220 | N89: =M89*L89 -> 2220 | P89: 0 | Q89: 0 | R89: 0 | S89: 0 | T89: 1 | U89: =SUM(P89:T89) -> 1 | W89: =$N89*P89 -> 0 | X89: =$N89*Q89 -> 0 | Y89: =$N89*R89 -> 0 | Z89: =$N89*S89 -> 0 | AA89: =$N89*T89 -> 2220
A90: Recibo | C90: 83 | D90: 2220 | E90: ILSI | F90: ILSI Brasil | G90: 65.086.001/0001-46 | H90: ILSI mensalidade junho | I90: Terceiros | J90: 42522 | K90: 6 | L90: 1 | M90: 2220 | N90: =M90*L90 -> 2220 | P90: 0 | Q90: 0 | R90: 0 | S90: 0 | T90: 1 | U90: =SUM(P90:T90) -> 1 | W90: =$N90*P90 -> 0 | X90: =$N90*Q90 -> 0 | Y90: =$N90*R90 -> 0 | Z90: =$N90*S90 -> 0 | AA90: =$N90*T90 -> 2220
A91: NF (Relatório contábil) | B91: 201600000000012 | C91: 84 | D91: 37210 | E91: Ana Paula Celes | F91: Nutrimento Gestão de Dados Empresariais Ltda. | G91: 03.150.501/0001-42 | H91: Analisa os testes dos produtos e dá assistência na parametrização do produto e dos novos testes a serem feitos. Faz acompanhamento técnico de todos os projetos de pesquisa e desenvolvimento. | I91: Terceiros | J91: 42397 | K91: 1 | L91: 0.1 | M91: 37210 | N91: =M91*L91 -> 3721 | P91: 0.25 | Q91: 0.25 | R91: 0.25 | S91: 0.25 | T91: 0 | U91: =SUM(P91:T91) -> 1 | W91: =$N91*P91 -> 930.25 | X91: =$N91*Q91 -> 930.25 | Y91: =$N91*R91 -> 930.25 | Z91: =$N91*S91 -> 930.25 | AA91: =$N91*T91 -> 0
A92: NF (Relatório contábil) | B92: 201600000000013 | C92: 85 | D92: 31227 | E92: Ana Paula Celes | F92: Nutrimento Gestão de Dados Empresariais Ltda. | G92: 03.150.501/0001-42 | H92: Analisa os testes dos produtos e dá assistência na parametrização do produto e dos novos testes a serem feitos. Faz acompanhamento técnico de todos os projetos de pesquisa e desenvolvimento. | I92: Terceiros | J92: 42425 | K92: 2 | L92: 0.1 | M92: 31227 | N92: =M92*L92 -> 3122.7 | P92: 0.25 | Q92: 0.25 | R92: 0.25 | S92: 0.25 | T92: 0 | U92: =SUM(P92:T92) -> 1 | W92: =$N92*P92 -> 780.675 | X92: =$N92*Q92 -> 780.675 | Y92: =$N92*R92 -> 780.675 | Z92: =$N92*S92 -> 780.675 | AA92: =$N92*T92 -> 0
A93: NF (Relatório contábil) | B93: 201600000000016 | C93: 86 | D93: 31226.69 | E93: Ana Paula Celes | F93: Nutrimento Gestão de Dados Empresariais Ltda. | G93: 03.150.501/0001-42 | H93: Analisa os testes dos produtos e dá assistência na parametrização do produto e dos novos testes a serem feitos. Faz acompanhamento técnico de todos os projetos de pesquisa e desenvolvimento. | I93: Terceiros | J93: 42458 | K93: 3 | L93: 0.1 | M93: 31226.69 | N93: =M93*L93 -> 3122.669 | P93: 0.25 | Q93: 0.25 | R93: 0.25 | S93: 0.25 | T93: 0 | U93: =SUM(P93:T93) -> 1 | W93: =$N93*P93 -> 780.66725 | X93: =$N93*Q93 -> 780.66725 | Y93: =$N93*R93 -> 780.66725 | Z93: =$N93*S93 -> 780.66725 | AA93: =$N93*T93 -> 0
A94: NF (Relatório contábil) | B94: 201600000000019 | C94: 87 | D94: 31226.69 | E94: Ana Paula Celes | F94: Nutrimento Gestão de Dados Empresariais Ltda. | G94: 03.150.501/0001-42 | H94: Analisa os testes dos produtos e dá assistência na parametrização do produto e dos novos testes a serem feitos. Faz acompanhamento técnico de todos os projetos de pesquisa e desenvolvimento. | I94: Terceiros | J94: 42488 | K94: 4 | L94: 0.1 | M94: 31226.69 | N94: =M94*L94 -> 3122.669 | P94: 0.25 | Q94: 0.25 | R94: 0.25 | S94: 0.25 | T94: 0 | U94: =SUM(P94:T94) -> 1 | W94: =$N94*P94 -> 780.66725 | X94: =$N94*Q94 -> 780.66725 | Y94: =$N94*R94 -> 780.66725 | Z94: =$N94*S94 -> 780.66725 | AA94: =$N94*T94 -> 0
A95: NF (Relatório contábil) | B95: 201600000000023 | C95: 88 | D95: 28557 | E95: Ana Paula Celes | F95: Nutrimento Gestão de Dados Empresariais Ltda. | G95: 03.150.501/0001-42 | H95: Analisa os testes dos produtos e dá assistência na parametrização do produto e dos novos testes a serem feitos. Faz acompanhamento técnico de todos os projetos de pesquisa e desenvolvimento. | I95: Terceiros | J95: 42517 | K95: 5 | L95: 0.1 | M95: 28557 | N95: =M95*L95 -> 2855.7 | P95: 0.25 | Q95: 0.25 | R95: 0.25 | S95: 0.25 | T95: 0 | U95: =SUM(P95:T95) -> 1 | W95: =$N95*P95 -> 713.925 | X95: =$N95*Q95 -> 713.925 | Y95: =$N95*R95 -> 713.925 | Z95: =$N95*S95 -> 713.925 | AA95: =$N95*T95 -> 0
A96: NF (Relatório contábil) | B96: 201600000000024 | C96: 89 | D96: 28557 | E96: Ana Paula Celes | F96: Nutrimento Gestão de Dados Empresariais Ltda. | G96: 03.150.501/0001-42 | H96: Analisa os testes dos produtos e dá assistência na parametrização do produto e dos novos testes a serem feitos. Faz acompanhamento técnico de todos os projetos de pesquisa e desenvolvimento. | I96: Terceiros | J96: 42550 | K96: 6 | L96: 0.1 | M96: 28557 | N96: =M96*L96 -> 2855.7 | P96: 0.25 | Q96: 0.25 | R96: 0.25 | S96: 0.25 | T96: 0 | U96: =SUM(P96:T96) -> 1 | W96: =$N96*P96 -> 713.925 | X96: =$N96*Q96 -> 713.925 | Y96: =$N96*R96 -> 713.925 | Z96: =$N96*S96 -> 713.925 | AA96: =$N96*T96 -> 0
A97: NF (Relatório contábil) | B97: 201600000000028 | C97: 90 | D97: 28557 | E97: Ana Paula Celes | F97: Nutrimento Gestão de Dados Empresariais Ltda. | G97: 03.150.501/0001-42 | H97: Analisa os testes dos produtos e dá assistência na parametrização do produto e dos novos testes a serem feitos. Faz acompanhamento técnico de todos os projetos de pesquisa e desenvolvimento. | I97: Terceiros | J97: 42579 | K97: 7 | L97: 0.1 | M97: 28557 | N97: =M97*L97 -> 2855.7 | P97: 0.25 | Q97: 0.25 | R97: 0.25 | S97: 0.25 | T97: 0 | U97: =SUM(P97:T97) -> 1 | W97: =$N97*P97 -> 713.925 | X97: =$N97*Q97 -> 713.925 | Y97: =$N97*R97 -> 713.925 | Z97: =$N97*S97 -> 713.925 | AA97: =$N97*T97 -> 0
A98: NF (Relatório contábil) | B98: 201600000000029 | C98: 91 | D98: 28557 | E98: Ana Paula Celes | F98: Nutrimento Gestão de Dados Empresariais Ltda. | G98: 03.150.501/0001-42 | H98: Analisa os testes dos produtos e dá assistência na parametrização do produto e dos novos testes a serem feitos. Faz acompanhamento técnico de todos os projetos de pesquisa e desenvolvimento. | I98: Terceiros | J98: 42611 | K98: 8 | L98: 0.1 | M98: 28557 | N98: =M98*L98 -> 2855.7 | P98: 0.25 | Q98: 0.25 | R98: 0.25 | S98: 0.25 | T98: 0 | U98: =SUM(P98:T98) -> 1 | W98: =$N98*P98 -> 713.925 | X98: =$N98*Q98 -> 713.925 | Y98: =$N98*R98 -> 713.925 | Z98: =$N98*S98 -> 713.925 | AA98: =$N98*T98 -> 0
A99: NF (Relatório contábil) | B99: 201600000000032 | C99: 92 | D99: 28557 | E99: Ana Paula Celes | F99: Nutrimento Gestão de Dados Empresariais Ltda. | G99: 03.150.501/0001-42 | H99: Analisa os testes dos produtos e dá assistência na parametrização do produto e dos novos testes a serem feitos. Faz acompanhamento técnico de todos os projetos de pesquisa e desenvolvimento. | I99: Terceiros | J99: 42642 | K99: 9 | L99: 0.1 | M99: 28557 | N99: =M99*L99 -> 2855.7 | P99: 0.25 | Q99: 0.25 | R99: 0.25 | S99: 0.25 | T99: 0 | U99: =SUM(P99:T99) -> 1 | W99: =$N99*P99 -> 713.925 | X99: =$N99*Q99 -> 713.925 | Y99: =$N99*R99 -> 713.925 | Z99: =$N99*S99 -> 713.925 | AA99: =$N99*T99 -> 0
A100: NF (Relatório contábil) | B100: 201600000000035 | C100: 93 | D100: 28557 | E100: Ana Paula Celes | F100: Nutrimento Gestão de Dados Empresariais Ltda. | G100: 03.150.501/0001-42 | H100: Analisa os testes dos produtos e dá assistência na parametrização do produto e dos novos testes a serem feitos. Faz acompanhamento técnico de todos os projetos de pesquisa e desenvolvimento. | I100: Terceiros | J100: 42674 | K100: 10 | L100: 0.1 | M100: 28557 | N100: =M100*L100 -> 2855.7 | P100: 0.25 | Q100: 0.25 | R100: 0.25 | S100: 0.25 | T100: 0 | U100: =SUM(P100:T100) -> 1 | W100: =$N100*P100 -> 713.925 | X100: =$N100*Q100 -> 713.925 | Y100: =$N100*R100 -> 713.925 | Z100: =$N100*S100 -> 713.925 | AA100: =$N100*T100 -> 0
A101: NF (Relatório contábil) | B101: 201600000000038 | C101: 94 | D101: 28557 | E101: Ana Paula Celes | F101: Nutrimento Gestão de Dados Empresariais Ltda. | G101: 03.150.501/0001-42 | H101: Analisa os testes dos produtos e dá assistência na parametrização do produto e dos novos testes a serem feitos. Faz acompanhamento técnico de todos os projetos de pesquisa e desenvolvimento. | I101: Terceiros | J101: 42703 | K101: 11 | L101: 0.1 | M101: 28557 | N101: =M101*L101 -> 2855.7 | P101: 0.25 | Q101: 0.25 | R101: 0.25 | S101: 0.25 | T101: 0 | U101: =SUM(P101:T101) -> 1 | W101: =$N101*P101 -> 713.925 | X101: =$N101*Q101 -> 713.925 | Y101: =$N101*R101 -> 713.925 | Z101: =$N101*S101 -> 713.925 | AA101: =$N101*T101 -> 0
...

Sheet (b) Timesheet consolidado
A1: PRODIET
A2: Anexo III - Timesheets consolidados
A3: INOVAÇÃO TECNOLÓGICA 2016
A4: Apontamento de horas [e cálculo do custo] do pessoal com dedicação parcial à inovação tecnológica
F7: =SUBTOTAL(9,F9:F71) -> 8.7458333 | G7: =SUBTOTAL(9,G9:G71) -> 209.9 | K7: =SUBTOTAL(9,K9:K71) -> 6980.2545
A8: Funcionário | B8: Projeto | C8: Data | D8: Início | E8: Fim | F8: Horas totais | G8: Horas totais [2] | H8: Descrição | I8: Mês | J8: Custo/Hora | K8: Custo Total
A9: Franciele Guedes | B9: Bemmax | C9: 42415 | D9: 0.34375 | E9: 0.75 | F9: =E9-D9 -> 0.40625 | G9: =F9*24 -> 9.75 | H9: Pesagem | I9: =MONTH(C9) -> 2 | J9: =VLOOKUP(A9,Salários!$A$35:$P$42,I9+4,FALSE) -> 31.118786 | K9: =J9*G9 -> 303.40817
A10: Franciele Guedes | B10: Bemmax | C10: 42416 | D10: 0.34375 | E10: 0.41666667 | F10: =E10-D10 -> 0.072916667 | G10: =F10*24 -> 1.75 | H10: Pesagem | I10: =MONTH(C10) -> 2 | J10: =VLOOKUP(A10,Salários!$A$35:$P$42,I10+4,FALSE) -> 31.118786 | K10: =J10*G10 -> 54.457876
A11: Franciele Guedes | B11: Bemmax | C11: 42436 | D11: 0.29861111 | E11: 0.70833333 | F11: =E11-D11 -> 0.40972222 | G11: =F11*24 -> 9.8333333 | H11: Produção | I11: =MONTH(C11) -> 3 | J11: =VLOOKUP(A11,Salários!$A$35:$P$42,I11+4,FALSE) -> 27.059814 | K11: =J11*G11 -> 266.08817
A12: Franciele Guedes | B12: Trophic Junior | C12: 42458 | D12: 0.47569444 | E12: 0.52083333 | F12: =E12-D12 -> 0.045138889 | G12: =F12*24 -> 1.0833333 | H12: Pesagem | I12: =MONTH(C12) -> 3 | J12: =VLOOKUP(A12,Salários!$A$35:$P$42,I12+4,FALSE) -> 27.059814 | K12: =J12*G12 -> 29.314799
A13: Franciele Guedes | B13: Trophic Basic - primeira produção Prodiet | C13: 42468 | D13: 0.34375 | E13: 0.75 | F13: =E13-D13 -> 0.40625 | G13: =F13*24 -> 9.75 | H13: Pesagem | I13: =MONTH(C13) -> 4 | J13: =VLOOKUP(A13,Salários!$A$35:$P$42,I13+4,FALSE) -> 31.118786 | K13: =J13*G13 -> 303.40817
A14: Franciele Guedes | B14: Trophic Basic - primeira produção Prodiet | C14: 42472 | D14: 0.35763889 | E14: 0.43055556 | F14: =E14-D14 -> 0.072916667 | G14: =F14*24 -> 1.75 | H14: Pesagem | I14: =MONTH(C14) -> 4 | J14: =VLOOKUP(A14,Salários!$A$35:$P$42,I14+4,FALSE) -> 31.118786 | K14: =J14*G14 -> 54.457876
A15: Franciele Guedes | B15: Trophic Basic - primeira produção Prodiet | C15: 42480 | D15: 0.65972222 | E15: 0.78125 | F15: =E15-D15 -> 0.12152778 | G15: =F15*24 -> 2.9166667 | H15: Produção | I15: =MONTH(C15) -> 4 | J15: =VLOOKUP(A15,Salários!$A$35:$P$42,I15+4,FALSE) -> 31.118786 | K15: =J15*G15 -> 90.763127
A16: Franciele Guedes | B16: Immax | C16: 42521 | D16: 0.58333333 | E16: 0.75 | F16: =E16-D16 -> 0.16666667 | G16: =F16*24 -> 4 | H16: Pesagem | I16: =MONTH(C16) -> 5 | J16: =VLOOKUP(A16,Salários!$A$35:$P$42,I16+4,FALSE) -> 28.289806 | K16: =J16*G16 -> 113.15922
A17: Franciele Guedes | B17: Immax | C17: 42522 | D17: 0.45138889 | E17: 0.5375 | F17: =E17-D17 -> 0.086111111 | G17: =F17*24 -> 2.0666667 | H17: Piloto pó | I17: =MONTH(C17) -> 6 | J17: =VLOOKUP(A17,Salários!$A$35:$P$42,I17+4,FALSE) -> 28.289806 | K17: =J17*G17 -> 58.465599
A18: Franciele Guedes | B18: Vital Rice | C18: 42550 | D18: 0.39930556 | E18: 0.49652778 | F18: =E18-D18 -> 0.097222222 | G18: =F18*24 -> 2.3333333 | H18: Pesagem | I18: =MONTH(C18) -> 6 | J18: =VLOOKUP(A18,Salários!$A$35:$P$42,I18+4,FALSE) -> 28.289806 | K18: =J18*G18 -> 66.009547
A19: Franciele Guedes | B19: Vital Rice | C19: 42559 | D19: 0.41666667 | E19: 0.45138889 | F19: =E19-D19 -> 0.034722222 | G19: =F19*24 -> 0.83333333 | H19: Pesagem | I19: =MONTH(C19) -> 7 | J19: =VLOOKUP(A19,Salários!$A$35:$P$42,I19+4,FALSE) -> 29.636939 | K19: =J19*G19 -> 24.69745
A20: Franciele Guedes | B20: Vital Rice | C20: 42573 | D20: 0.64583333 | E20: 0.67708333 | F20: =E20-D20 -> 0.03125 | G20: =F20*24 -> 0.75 | H20: Piloto pó | I20: =MONTH(C20) -> 7 | J20: =VLOOKUP(A20,Salários!$A$35:$P$42,I20+4,FALSE) -> 29.636939 | K20: =J20*G20 -> 22.227705
... A24: Hozana Bueno | B24: Trophic Infant pó - nova fórmula | C24: 43007 | D24: 0.39305556 | E24: 0.43472222 | F24: =E24-D24 -> 0.041666667 | G24: =F24*24 -> 1 | H24: Produção | I24: =MONTH(C24) -> 9 | J24: =VLOOKUP(A24,Salários!$A$35:$P$42,I24+4,FALSE) -> 20.054125 | K24: =J24*G24 -> 20.054125
A25: Hozana Bueno | B25: Controle em Shelf Life | C25: 43005 | D25: 0.5625 | E25: 0.75 | F25: =E25-D25 -> 0.1875 | G25: =F25*24 -> 4.5 | I25: =MONTH(C25) -> 9 | J25: =VLOOKUP(A25,Salários!$A$35:$P$42,I25+4,FALSE) -> 20.054125 | K25: =J25*G25 -> 90.243563
A26: Hozana Bueno | B26: Nova MP - mix 162562 Trophic Infant pó | C26: 43040 | D26: 0.48263889 | E26: 0.75 | F26: =E26-D26 -> 0.26736111 | G26: =F26*24 -> 6.4166667 | H26: Produção industrial | I26: =MONTH(C26) -> 11 | J26: =VLOOKUP(A26,Salários!$A$35:$P$42,I26+4,FALSE) -> 19.099167 | K26: =J26*G26 -> 122.55299
A27: Hozana Bueno | B27: Sustenlac | C27: 43070 | D27: 0.59027778 | E27: 0.6875 | F27: =E27-D27 -> 0.097222222 | G27: =F27*24 -> 2.3333333 | H27: Produção - morango | I27: =MONTH(C27) -> 12 | J27: =VLOOKUP(A27,Salários!$A$35:$P$42,I27+4,FALSE) -> 18.231023 | K27: =J27*G27 -> 42.539053
A28: Hozana Bueno | B28: Sustenlac | C28: 43074 | D28: 0.38888889 | E28: 0.47222222 | F28: =E28-D28 -> 0.083333333 | G28: =F28*24 -> 2 | H28: Produção - baunilha | I28: =MONTH(C28) -> 12 | J28: =VLOOKUP(A28,Salários!$A$35:$P$42,I28+4,FALSE) -> 18.231023 | K28: =J28*G28 -> 36.462045
A29: Hozana Bueno | B29: Sustenlac | C29: 43074 | D29: 0.49305556 | E29: 0.55208333 | F29: =E29-D29 -> 0.059027778 | G29: =F29*24 -> 1.4166667 | H29: Produção - chocolate | I29: =MONTH(C29) -> 12 | J29: =VLOOKUP(A29,Salários!$A$35:$P$42,I29+4,FALSE) -> 18.231023 | K29: =J29*G29 -> 25.827282
A30: Hozana Bueno | B30: Leites terapêuticos | C30: 43075 | D30: 0.58333333 | E30: 0.70833333 | F30: =E30-D30 -> 0.125 | G30: =F30*24 -> 3 | H30: Análises de laboratório | I30: =MONTH(C30) -> 12 | J30: =VLOOKUP(A30,Salários!$A$35:$P$42,I30+4,FALSE) -> 18.231023 | K30: =J30*G30 -> 54.693068
A31: Lizianne Shmeil | B31: Bemmax | C31: 42781 | D31: 0.34375 | E31: 0.75 | F31: =E31-D31 -> 0.40625 | G31: =F31*24 -> 9.75 | H31: Pesagem | I31: =MONTH(C31) -> 2 | J31: =VLOOKUP(A31,Salários!$A$35:$P$42,I31+4,FALSE) -> 30.200557 | K31: =J31*G31 -> 294.45543
A32: Lizianne Shmeil | B32: Bemmax | C32: 42782 | D32: 0.34375 | E32: 0.41666667 | F32: =E32-D32 -> 0.072916667 | G32: =F32*24 -> 1.75 | H32: Pesagem | I32: =MONTH(C32) -> 2 | J32: =VLOOKUP(A32,Salários!$A$35:$P$42,I32+4,FALSE) -> 30.200557 | K32: =J32*G32 -> 52.850975
A33: Lizianne Shmeil | B33: Trophic Junior | C33: 42823 | D33: 0.47569444 | E33: 0.52083333 | F33: =E33-D33 -> 0.045138889 | G33: =F33*24 -> 1.0833333 | H33: Pesagem | I33: =MONTH(C33) -> 3 | J33: =VLOOKUP(A33,Salários!$A$35:$P$42,I33+4,FALSE) -> 26.261354 | K33: =J33*G33 -> 28.4498
A34: Lizianne Shmeil | B34: Trophic Basic - primeira produção Prodiet | C34: 42833 | D34: 0.34375 | E34: 0.75 | F34: =E34-D34 -> 0.40625 | G34: =F34*24 -> 9.75 | H34: Pesagem | I34: =MONTH(C34) -> 4 | J34: =VLOOKUP(A34,Salários!$A$35:$P$42,I34+4,FALSE) -> 30.200557 | K34: =J34*G34 -> 294.45543
A35: Lizianne Shmeil | B35: Trophic Basic - primeira produção Prodiet | C35: 42837 | D35: 0.35763889 | E35: 0.43055556 | F35: =E35-D35 -> 0.072916667 | G35: =F35*24 -> 1.75 | H35: Pesagem | I35: =MONTH(C35) -> 4 | J35: =VLOOKUP(A35,Salários!$A$35:$P$42,I35+4,FALSE) -> 30.200557 | K35: =J35*G35 -> 52.850975
A36: Lizianne Shmeil | B36: Trophic Basic - primeira produção Prodiet | C36: 42845 | D36: 0.65972222 | E36: 0.78125 | F36: =E36-D36 -> 0.12152778 | G36: =F36*24 -> 2.9166667 | H36: Produção | I36: =MONTH(C36) -> 4 | J36: =VLOOKUP(A36,Salários!$A$35:$P$42,I36+4,FALSE) -> 30.200557 | K36: =J36*G36 -> 88.084959
A37: Lizianne Shmeil | B37: Immax | C37: 42886 | D37: 0.58333333 | E37: 0.75 | F37: =E37-D37 -> 0.16666667 | G37: =F37*24 -> 4 | H37: Pesagem | I37: =MONTH(C37) -> 5 | J37: =VLOOKUP(A37,Salários!$A$35:$P$42,I37+4,FALSE) -> 27.455052 | K37: =J37*G37 -> 109.82021
... A60: Marianne Stigar | B60: Trophic Infant pó - nova fórmula | C60: 43007 | D60: 0.39305556 | E60: 0.43472222 | F60: =E60-D60 -> 0.041666667 | G60: =F60*24 -> 1 | H60: Produção | I60: =MONTH(C60) -> 9 | J60: =VLOOKUP(A60,Salários!$A$35:$P$42,I60+4,FALSE) -> 34.93862 | K60: =J60*G60 -> 34.93862
A61: Marianne Stigar | B61: Controle em Shelf Life | C61: 43005 | D61: 0.5625 | E61: 0.75 | F61: =E61-D61 -> 0.1875 | G61: =F61*24 -> 4.5 | I61: =MONTH(C61) -> 9 | J61: =VLOOKUP(A61,Salários!$A$35:$P$42,I61+4,FALSE) -> 34.93862 | K61: =J61*G61 -> 157.22379
A62: Marianne Stigar | B62: Nova MP - mix 162562 Trophic Infant pó | C62: 43035 | D62: 0.38888889 | E62: 0.625 | F62: =E62-D62 -> 0.23611111 | G62: =F62*24 -> 5.6666667 | H62: Pesagem | I62: =MONTH(C62) -> 10 | J62: =VLOOKUP(A62,Salários!$A$35:$P$42,I62+4,FALSE) -> 34.93862 | K62: =J62*G62 -> 197.98551
A63: Marianne Stigar | B63: Nova MP - mix 162562 Trophic Infant pó | C63: 43036 | D63: 0.5625 | E63: 0.66666667 | F63: =E63-D63 -> 0.10416667 | G63: =F63*24 -> 2.5 | H63: Pesagem | I63: =MONTH(C63) -> 10 | J63: =VLOOKUP(A63,Salários!$A$35:$P$42,I63+4,FALSE) -> 34.93862 | K63: =J63*G63 -> 87.346549
A64: Marianne Stigar | B64: Nova MP - mix 162562 Trophic Infant pó | C64: 43040 | D64: 0.48263889 | E64: 0.75 | F64: =E64-D64 -> 0.26736111 | G64: =F64*24 -> 6.4166667 | H64: Produção industrial | I64: =MONTH(C64) -> 11 | J64: =VLOOKUP(A64,Salários!$A$35:$P$42,I64+4,FALSE) -> 33.274876 | K64: =J64*G64 -> 213.51379
A65: Marianne Stigar | B65: Leites terapêuticos | C65: 43068 | D65: 0.58333333 | E65: 0.70833333 | F65: =E65-D65 -> 0.125 | G65: =F65*24 -> 3 | H65: Pesagem | I65: =MONTH(C65) -> 11 | J65: =VLOOKUP(A65,Salários!$A$35:$P$42,I65+4,FALSE) -> 33.274876 | K65: =J65*G65 -> 99.824628
A66: Marianne Stigar | B66: Leites terapêuticos | C66: 43069 | D66: 0.70833333 | E66: 0.75 | F66: =E66-D66 -> 0.041666667 | G66: =F66*24 -> 1 | H66: Piloto experimental | I66: =MONTH(C66) -> 11 | J66: =VLOOKUP(A66,Salários!$A$35:$P$42,I66+4,FALSE) -> 33.274876 | K66: =J66*G66 -> 33.274876
A67: Marianne Stigar | B67: Sustenlac | C67: 43069 | D67: 0.34375 | E67: 0.75 | F67: =E67-D67 -> 0.40625 | G67: =F67*24 -> 9.75 | H67: Pesagem | I67: =MONTH(C67) -> 11 | J67: =VLOOKUP(A67,Salários!$A$35:$P$42,I67+4,FALSE) -> 33.274876 | K67: =J67*G67 -> 324.43004
A68: Marianne Stigar | B68: Leites terapêuticos | C68: 43070 | D68: 0.34375 | E68: 0.66666667 | F68: =E68-D68 -> 0.32291667 | G68: =F68*24 -> 7.75 | H68: Piloto experimental | I68: =MONTH(C68) -> 12 | J68: =VLOOKUP(A68,Salários!$A$35:$P$42,I68+4,FALSE) -> 31.762382 | K68: =J68*G68 -> 246.15846
A69: Marianne Stigar | B69: Sustenlac | C69: 43070 | D69: 0.59027778 | E69: 0.6875 | F69: =E69-D69 -> 0.097222222 | G69: =F69*24 -> 2.3333333 | H69: Produção - morango | I69: =MONTH(C69) -> 12 | J69: =VLOOKUP(A69,Salários!$A$35:$P$42,I69+4,FALSE) -> 31.762382 | K69: =J69*G69 -> 74.112224
A70: Marianne Stigar | B70: Sustenlac | C70: 43074 | D70: 0.38888889 | E70: 0.47222222 | F70: =E70-D70 -> 0.083333333 | G70: =F70*24 -> 2 | H70: Produção - baunilha | I70: =MONTH(C70) -> 12 | J70: =VLOOKUP(A70,Salários!$A$35:$P$42,I70+4,FALSE) -> 31.762382 | K70: =J70*G70 -> 63.524763
A71: Marianne Stigar | B71: Sustenlac | C71: 43074 | D71: 0.49305556 | E71: 0.55208333 | F71: =E71-D71 -> 0.059027778 | G71: =F71*24 -> 1.4166667 | H71: Produção - chocolate | I71: =MONTH(C71) -> 12 | J71: =VLOOKUP(A71,Salários!$A$35:$P$42,I71+4,FALSE) -> 31.762382 | K71: =J71*G71 -> 44.996707

Sheet (c) Dedicação exclusiva
A1: PRODIET
A2: ANEXO IV - Pessoal exclusivo
A3: INOVAÇÃO TECNOLÓGICA 2016
A4: Cálculo do custo do pessoal com dedicação exclusivo à inovação tecnológica
A8: SALÁRIO BRUTO [c/ encargos]
A9: Nome | B9: CPF | C9: Salário (R$) [dez] | D9: Dedicação | E9: Jan | F9: Fev | G9: Mar | H9: Abr | I9: Mai | J9: Jun | K9: Jul | L9: Ago | M9: Set | N9: Out | O9: Nov | P9: Dez | Q9: Total
A10: Amid Tony Ibrahim | B10: 075.215.579-21 | C10: 2668 | D10: Exclusiva | E10: 3219.238 | F10: 3576.3924 | G10: 3576.3924 | H10: 3576.3924 | I10: 3576.3924 | J10: 3576.3924 | K10: 3576.3924 | L10: 3576.3924 | M10: 4311.7103 | N10: 4311.7103 | O10: 4311.7103 | P10: 4311.7103 | Q10: =SUM(E10:P10) -> 45500.826
A11: Hellin dos Santos | B11: 058.544.839-63 | C11: 5148 | D11: Exclusiva | E11: 6398.0739 | F11: 6398.0739 | G11: 6398.0739 | H11: 6496.655 | I11: 6496.655 | J11: 7589.1273 | K11: 7589.1273 | L11: 7589.1273 | M11: 8319.597 | N11: 8319.597 | O11: 8319.597 | P11: 8319.597 | Q11: =SUM(E11:P11) -> 88233.302
A12: Jana Grenteski | B12: 040.201.929-60 | C12: 3289 | D12: Exclusiva | E12: 5315.2981 | F12: 5315.2981 | G12: 5315.2981 | H12: 5315.2981 | I12: 0 | J12: 0 | K12: 0 | L12: 0 | M12: 0 | N12: 0 | O12: 0 | P12: 0 | Q12: =SUM(E12:P12) -> 21261.192
E13: =SUM(E10:E12) -> 14932.61 | F13: =SUM(F10:F12) -> 15289.764 | G13: =SUM(G10:G12) -> 15289.764 | H13: =SUM(H10:H12) -> 15388.346 | I13: =SUM(I10:I12) -> 10073.047 | J13: =SUM(J10:J12) -> 11165.52 | K13: =SUM(K10:K12) -> 11165.52 | L13: =SUM(L10:L12) -> 11165.52 | ... Q13: =SUM(Q10:Q12) -> 154995.32

Sheet Salários
A1: PRODIET
A2: Anexo V - Salários
A3: INOVAÇÃO TECNOLÓGICA 2016
A5: Encargos sobre folha | H5: INSS | I5: Patronal | J5: 0.2
A6: INSS | B6: FGTS | D6: Férias | E6: 13º | F6: Total | I6: Terceiros | J6: 0.058
A7: 0.273 | B7: 0.08 | D7: 0.15033333 | E7: 0.11275 | F7: 0.61608333 | I7: RAT | J7: 0.015
A9: SALÁRIO BRUTO
A10: Nome | B10: CPF | C10: Salário (R$) [dez] | D10: Dedicação | E10: Jan | F10: Fev | G10: Mar | H10: Abr | I10: Mai | J10: Jun | K10: Jul | L10: Ago | M10: Set | N10: Out | O10: Nov | P10: Dez | Q10: Total
A11: Amid Tony Ibrahim | B11: 075.215.579-21 | C11: 2668 | D11: Exclusiva | E11: 1992 | F11: 2213 | G11: 2213 | H11: 2213 | I11: 2213 | J11: 2213 | K11: 2213 | L11: 2213 | M11: 2668 | N11: 2668 | O11: 2668 | P11: 2668 | Q11: =SUM(E11:P11) -> 28155
A12: Franciele Guedes | B12: 065.423.719-07 | C12: 3289 | D12: Parcial | E12: 3389 | F12: 3389 | G12: 3389 | H12: 3389 | I12: 3389 | J12: 3389 | K12: 3389 | L12: 3389 | M12: 3389 | N12: 0 | O12: 0 | P12: 0 | Q12: =SUM(E12:P12) -> 30501
A13: Hellin dos Santos | B13: 058.544.839-63 | C13: 5148 | D13: Exclusiva | E13: 3959 | F13: 3959 | G13: 3959 | H13: 4020 | I13: 4020 | J13: 4696 | K13: 4696 | L13: 4696 | M13: 5148 | N13: 5148 | O13: 5148 | P13: 5148 | Q13: =SUM(E13:P13) -> 54597
A14: Hozana Bueno | B14: 039.677.159-90 | C14: 2184 | D14: Parcial | E14: 0 | F14: 0 | G14: 0 | H14: 0 | I14: 0 | J14: 1992 | K14: 1992 | L14: 1992 | M14: 2184 | N14: 2184 | O14: 2184 | P14: 2184 | Q14: =SUM(E14:P14) -> 14712
A15: Jana Grenteski | B15: 040.201.929-60 | C15: 3289 | D15: Exclusiva | E15: 3289 | F15: 3289 | G15: 3289 | H15: 3289 | I15: 0 | J15: 0 | K15: 0 | L15: 0 | M15: 0 | N15: 0 | O15: 0 | P15: 0 | Q15: =SUM(E15:P15) -> 13156
A16: Lizianne Shmeil | B16: 052.485.199-93 | C16: 3289 | D16: Parcial | E16: 3289 | F16: 3289 | G16: 3289 | H16: 3289 | I16: 3289 | J16: 3289 | K16: 3289 | L16: 0 | M16: 0 | N16: 0 | O16: 0 | P16: 0 | Q16: =SUM(E16:P16) -> 23023
A17: Marianne Stigar | B17: 066.424.199-95 | C17: 3805 | D17: Parcial | E17: 0 | F17: 0 | G17: 0 | H17: 0 | I17: 0 | J17: 0 | K17: 3471 | L17: 3471 | M17: 3805 | N17: 3805 | O17: 3805 | P17: 3805 | Q17: =SUM(E17:P17) -> 22162
A18: Mauricio Ragadalli | B18: 060.236.389-61 | C18: 5148 | D18: Parcial | E18: 0 | F18: 0 | G18: 0 | H18: 0 | I18: 0 | J18: 0 | K18: 4696 | L18: 4696 | M18: 5148 | N18: 5148 | O18: 5148 | P18: 5148 | Q18: =SUM(E18:P18) -> 29984
E19: =SUM(E11:E18) -> 15918 | F19: =SUM(F11:F18) -> 16139 | G19: =SUM(G11:G18) -> 16139 | H19: =SUM(H11:H18) -> 16200 | I19: =SUM(I11:I18) -> 12911 | J19: =SUM(J11:J18) -> 15579 | K19: =SUM(K11:K18) -> 23746 | L19: =SUM(L11:L18) -> 20457 | ... Q19: =SUM(Q11:Q18) -> 216290
A21: SALÁRIO BRUTO [c/ encargos]
A22: Nome | B22: CPF | C22: Salário (R$) [dez] | D22: Dedicação | E22: Jan | F22: Fev | G22: Mar | H22: Abr | I22: Mai | J22: Jun | K22: Jul | L22: Ago | M22: Set | N22: Out | O22: Nov | P22: Dez | Q22: Total
A23: Amid Tony Ibrahim | B23: 075.215.579-21 | C23: 2668 | D23: Exclusiva | E23: =(1+$F$7)*E11 -> 3219.238 | F23: =(1+$F$7)*F11 -> 3576.3924 | G23: =(1+$F$7)*G11 -> 3576.3924 | H23: =(1+$F$7)*H11 -> 3576.3924 | I23: =(1+$F$7)*I11 -> 3576.3924 | J23: =(1+$F$7)*J11 -> 3576.3924 | K23: =(1+$F$7)*K11 -> 3576.3924 | L23: =(1+$F$7)*L11 -> 3576.3924 | ... P23: =(1+$F$7)*P11 -> 4311.7103 | Q23: =SUM(E23:P23) -> 45500.826
A24: Franciele Guedes | B24: 065.423.719-07 | C24: 3289 | D24: Parcial | E24: =(1+$F$7)*E12 -> 5476.9064 | F24: =(1+$F$7)*F12 -> 5476.9064 | G24: =(1+$F$7)*G12 -> 5476.9064 | H24: =(1+$F$7)*H12 -> 5476.9064 | I24: =(1+$F$7)*I12 -> 5476.9064 | J24: =(1+$F$7)*J12 -> 5476.9064 | K24: =(1+$F$7)*K12 -> 5476.9064 | L24: =(1+$F$7)*L12 -> 5476.9064 | ... P24: =(1+$F$7)*P12 -> 0 | Q24: =SUM(E24:P24) -> 49292.158
A25: Hellin dos Santos | B25: 058.544.839-63 | C25: 5148 | D25: Exclusiva | E25: =(1+$F$7)*E13 -> 6398.0739 | F25: =(1+$F$7)*F13 -> 6398.0739 | G25: =(1+$F$7)*G13 -> 6398.0739 | H25: =(1+$F$7)*H13 -> 6496.655 | I25: =(1+$F$7)*I13 -> 6496.655 | J25: =(1+$F$7)*J13 -> 7589.1273 | K25: =(1+$F$7)*K13 -> 7589.1273 | L25: =(1+$F$7)*L13 -> 7589.1273 | ... P25: =(1+$F$7)*P13 -> 8319.597 | Q25: =SUM(E25:P25) -> 88233.302
A26: Hozana Bueno | B26: 039.677.159-90 | C26: 2184 | D26: Parcial | E26: =(1+$F$7)*E14 -> 0 | F26: =(1+$F$7)*F14 -> 0 | G26: =(1+$F$7)*G14 -> 0 | H26: =(1+$F$7)*H14 -> 0 | I26: =(1+$F$7)*I14 -> 0 | J26: =(1+$F$7)*J14 -> 3219.238 | K26: =(1+$F$7)*K14 -> 3219.238 | L26: =(1+$F$7)*L14 -> 3219.238 | ... P26: =(1+$F$7)*P14 -> 3529.526 | Q26: =SUM(E26:P26) -> 23775.818
A27: Jana Grenteski | B27: 040.201.929-60 | C27: 3289 | D27: Exclusiva | E27: =(1+$F$7)*E15 -> 5315.2981 | F27: =(1+$F$7)*F15 -> 5315.2981 | G27: =(1+$F$7)*G15 -> 5315.2981 | H27: =(1+$F$7)*H15 -> 5315.2981 | I27: =(1+$F$7)*I15 -> 0 | J27: =(1+$F$7)*J15 -> 0 | K27: =(1+$F$7)*K15 -> 0 | L27: =(1+$F$7)*L15 -> 0 | ... P27: =(1+$F$7)*P15 -> 0 | Q27: =SUM(E27:P27) -> 21261.192
A28: Lizianne Shmeil | B28: 052.485.199-93 | C28: 3289 | D28: Parcial | E28: =(1+$F$7)*E16 -> 5315.2981 | F28: =(1+$F$7)*F16 -> 5315.2981 | G28: =(1+$F$7)*G16 -> 5315.2981 | H28: =(1+$F$7)*H16 -> 5315.2981 | I28: =(1+$F$7)*I16 -> 5315.2981 | J28: =(1+$F$7)*J16 -> 5315.2981 | K28: =(1+$F$7)*K16 -> 5315.2981 | L28: =(1+$F$7)*L16 -> 0 | ... P28: =(1+$F$7)*P16 -> 0 | Q28: =SUM(E28:P28) -> 37207.087
A29: Marianne Stigar | B29: 066.424.199-95 | C29: 3805 | D29: Parcial | E29: =(1+$F$7)*E17 -> 0 | F29: =(1+$F$7)*F17 -> 0 | G29: =(1+$F$7)*G17 -> 0 | H29: =(1+$F$7)*H17 -> 0 | I29: =(1+$F$7)*I17 -> 0 | J29: =(1+$F$7)*J17 -> 0 | K29: =(1+$F$7)*K17 -> 5609.4253 | L29: =(1+$F$7)*L17 -> 5609.4253 | ... P29: =(1+$F$7)*P17 -> 6149.1971 | Q29: =SUM(E29:P29) -> 35815.639
A30: Mauricio Ragadalli | B30: 060.236.389-61 | C30: 5148 | D30: Parcial | E30: =(1+$F$7)*E18 -> 0 | F30: =(1+$F$7)*F18 -> 0 | G30: =(1+$F$7)*G18 -> 0 | H30: =(1+$F$7)*H18 -> 0 | I30: =(1+$F$7)*I18 -> 0 | J30: =(1+$F$7)*J18 -> 0 | K30: =(1+$F$7)*K18 -> 7589.1273 | L30: =(1+$F$7)*L18 -> 7589.1273 | ... P30: =(1+$F$7)*P18 -> 8319.597 | Q30: =SUM(E30:P30) -> 48456.643
E31: =SUM(E23:E30) -> 25724.815 | F31: =SUM(F23:F30) -> 26081.969 | G31: =SUM(G23:G30) -> 26081.969 | H31: =SUM(H23:H30) -> 26180.55 | I31: =SUM(I23:I30) -> 20865.252 | J31: =SUM(J23:J30) -> 25176.962 | K31: =SUM(K23:K30) -> 38375.515 | L31: =SUM(L23:L30) -> 33060.217 | ... Q31: =SUM(Q23:Q30) -> 349542.66
A33: CUSTO/HORA [c/ encargos]
A34: Nome | B34: CPF | C34: Salário (R$) [dez] | D34: Dedicação | E34: Jan | F34: Fev | G34: Mar | H34: Abr | I34: Mai | J34: Jun | K34: Jul | L34: Ago | M34: Set | N34: Out | O34: Nov | P34: Dez
A35: Amid Tony Ibrahim | B35: 075.215.579-21 | C35: 2668 | D35: Exclusiva | E35: =E23/VLOOKUP(E$34,'Dias úteis'!$D$8:$H$19,5,FALSE) -> 18.291125 | F35: =F23/VLOOKUP(F$34,'Dias úteis'!$D$8:$H$19,5,FALSE) -> 20.320411 | G35: =G23/VLOOKUP(G$34,'Dias úteis'!$D$8:$H$19,5,FALSE) -> 17.669923 | H35: =H23/VLOOKUP(H$34,'Dias úteis'!$D$8:$H$19,5,FALSE) -> 20.320411 | I35: =I23/VLOOKUP(I$34,'Dias úteis'!$D$8:$H$19,5,FALSE) -> 18.473101 | J35: =J23/VLOOKUP(J$34,'Dias úteis'!$D$8:$H$19,5,FALSE) -> 18.473101 | K35: =K23/VLOOKUP(K$34,'Dias úteis'!$D$8:$H$19,5,FALSE) -> 19.352773 | L35: =L23/VLOOKUP(L$34,'Dias úteis'!$D$8:$H$19,5,FALSE) -> 17.669923 | ... P35: =P23/VLOOKUP(P$34,'Dias úteis'!$D$8:$H$19,5,FALSE) -> 22.271231
A36: Franciele Guedes | B36: 065.423.719-07 | C36: 3289 | D36: Parcial | E36: =E24/VLOOKUP(E$34,'Dias úteis'!$D$8:$H$19,5,FALSE) -> 31.118786 | F36: =F24/VLOOKUP(F$34,'Dias úteis'!$D$8:$H$19,5,FALSE) -> 31.118786 | G36: =G24/VLOOKUP(G$34,'Dias úteis'!$D$8:$H$19,5,FALSE) -> 27.059814 | H36: =H24/VLOOKUP(H$34,'Dias úteis'!$D$8:$H$19,5,FALSE) -> 31.118786 | I36: =I24/VLOOKUP(I$34,'Dias úteis'!$D$8:$H$19,5,FALSE) -> 28.289806 | J36: =J24/VLOOKUP(J$34,'Dias úteis'!$D$8:$H$19,5,FALSE) -> 28.289806 | K36: =K24/VLOOKUP(K$34,'Dias úteis'!$D$8:$H$19,5,FALSE) -> 29.636939 | L36: =L24/VLOOKUP(L$34,'Dias úteis'!$D$8:$H$19,5,FALSE) -> 27.059814 | ... P36: =P24/VLOOKUP(P$34,'Dias úteis'!$D$8:$H$19,5,FALSE) -> 0
A37: Hellin dos Santos | B37: 058.544.839-63 | C37: 5148 | D37: Exclusiva | E37: =E25/VLOOKUP(E$34,'Dias úteis'!$D$8:$H$19,5,FALSE) -> 36.352693 | F37: =F25/VLOOKUP(F$34,'Dias úteis'!$D$8:$H$19,5,FALSE) -> 36.352693 | G37: =G25/VLOOKUP(G$34,'Dias úteis'!$D$8:$H$19,5,FALSE) -> 31.611037 | H37: =H25/VLOOKUP(H$34,'Dias úteis'!$D$8:$H$19,5,FALSE) -> 36.912813 | I37: =I25/VLOOKUP(I$34,'Dias úteis'!$D$8:$H$19,5,FALSE) -> 33.557102 | J37: =J25/VLOOKUP(J$34,'Dias úteis'!$D$8:$H$19,5,FALSE) -> 39.200038 | K37: =K25/VLOOKUP(K$34,'Dias úteis'!$D$8:$H$19,5,FALSE) -> 41.066706 | L37: =L25/VLOOKUP(L$34,'Dias úteis'!$D$8:$H$19,5,FALSE) -> 37.495688 | ... P37: =P25/VLOOKUP(P$34,'Dias úteis'!$D$8:$H$19,5,FALSE) -> 42.973125
A38: Hozana Bueno | B38: 039.677.159-90 | C38: 2184 | D38: Parcial | E38: =E26/VLOOKUP(E$34,'Dias úteis'!$D$8:$H$19,5,FALSE) -> 0 | F38: =F26/VLOOKUP(F$34,'Dias úteis'!$D$8:$H$19,5,FALSE) -> 0 | G38: =G26/VLOOKUP(G$34,'Dias úteis'!$D$8:$H$19,5,FALSE) -> 0 | H38: =H26/VLOOKUP(H$34,'Dias úteis'!$D$8:$H$19,5,FALSE) -> 0 | I38: =I26/VLOOKUP(I$34,'Dias úteis'!$D$8:$H$19,5,FALSE) -> 0 | J38: =J26/VLOOKUP(J$34,'Dias úteis'!$D$8:$H$19,5,FALSE) -> 16.628295 | K38: =K26/VLOOKUP(K$34,'Dias úteis'!$D$8:$H$19,5,FALSE) -> 17.420119 | L38: =L26/VLOOKUP(L$34,'Dias úteis'!$D$8:$H$19,5,FALSE) -> 15.905326 | ... P38: =P26/VLOOKUP(P$34,'Dias úteis'!$D$8:$H$19,5,FALSE) -> 18.231023
A39: Jana Grenteski | B39: 040.201.929-60 | C39: 3289 | D39: Exclusiva | E39: =E27/VLOOKUP(E$34,'Dias úteis'!$D$8:$H$19,5,FALSE) -> 30.200557 | F39: =F27/VLOOKUP(F$34,'Dias úteis'!$D$8:$H$19,5,FALSE) -> 30.200557 | G39: =G27/VLOOKUP(G$34,'Dias úteis'!$D$8:$H$19,5,FALSE) -> 26.261354 | H39: =H27/VLOOKUP(H$34,'Dias úteis'!$D$8:$H$19,5,FALSE) -> 30.200557 | I39: =I27/VLOOKUP(I$34,'Dias úteis'!$D$8:$H$19,5,FALSE) -> 0 | J39: =J27/VLOOKUP(J$34,'Dias úteis'!$D$8:$H$19,5,FALSE) -> 0 | K39: =K27/VLOOKUP(K$34,'Dias úteis'!$D$8:$H$19,5,FALSE) -> 0 | L39: =L27/VLOOKUP(L$34,'Dias úteis'!$D$8:$H$19,5,FALSE) -> 0 | ... P39: =P27/VLOOKUP(P$34,'Dias úteis'!$D$8:$H$19,5,FALSE) -> 0
A40: Lizianne Shmeil | B40: 052.485.199-93 | C40: 3289 | D40: Parcial | E40: =E28/VLOOKUP(E$34,'Dias úteis'!$D$8:$H$19,5,FALSE) -> 30.200557 | F40: =F28/VLOOKUP(F$34,'Dias úteis'!$D$8:$H$19,5,FALSE) -> 30.200557 | G40: =G28/VLOOKUP(G$34,'Dias úteis'!$D$8:$H$19,5,FALSE) -> 26.261354 | H40: =H28/VLOOKUP(H$34,'Dias úteis'!$D$8:$H$19,5,FALSE) -> 30.200557 | I40: =I28/VLOOKUP(I$34,'Dias úteis'!$D$8:$H$19,5,FALSE) -> 27.455052 | J40: =J28/VLOOKUP(J$34,'Dias úteis'!$D$8:$H$19,5,FALSE) -> 27.455052 | K40: =K28/VLOOKUP(K$34,'Dias úteis'!$D$8:$H$19,5,FALSE) -> 28.762436 | L40: =L28/VLOOKUP(L$34,'Dias úteis'!$D$8:$H$19,5,FALSE) -> 0 | ... P40: =P28/VLOOKUP(P$34,'Dias úteis'!$D$8:$H$19,5,FALSE) -> 0
A41: Marianne Stigar | B41: 066.424.199-95 | C41: 3805 | D41: Parcial | E41: =E29/VLOOKUP(E$34,'Dias úteis'!$D$8:$H$19,5,FALSE) -> 0 | F41: =F29/VLOOKUP(F$34,'Dias úteis'!$D$8:$H$19,5,FALSE) -> 0 | G41: =G29/VLOOKUP(G$34,'Dias úteis'!$D$8:$H$19,5,FALSE) -> 0 | H41: =H29/VLOOKUP(H$34,'Dias úteis'!$D$8:$H$19,5,FALSE) -> 0 | I41: =I29/VLOOKUP(I$34,'Dias úteis'!$D$8:$H$19,5,FALSE) -> 0 | J41: =J29/VLOOKUP(J$34,'Dias úteis'!$D$8:$H$19,5,FALSE) -> 0 | K41: =K29/VLOOKUP(K$34,'Dias úteis'!$D$8:$H$19,5,FALSE) -> 30.354033 | L41: =L29/VLOOKUP(L$34,'Dias úteis'!$D$8:$H$19,5,FALSE) -> 27.714552 | ... P41: =P29/VLOOKUP(P$34,'Dias úteis'!$D$8:$H$19,5,FALSE) -> 31.762382
A42: Mauricio Ragadalli | B42: 060.236.389-61 | C42: 5148 | D42: Parcial | E42: =E30/VLOOKUP(E$34,'Dias úteis'!$D$8:$H$19,5,FALSE) -> 0 | F42: =F30/VLOOKUP(F$34,'Dias úteis'!$D$8:$H$19,5,FALSE) -> 0 | G42: =G30/VLOOKUP(G$34,'Dias úteis'!$D$8:$H$19,5,FALSE) -> 0 | H42: =H30/VLOOKUP(H$34,'Dias úteis'!$D$8:$H$19,5,FALSE) -> 0 | I42: =I30/VLOOKUP(I$34,'Dias úteis'!$D$8:$H$19,5,FALSE) -> 0 | J42: =J30/VLOOKUP(J$34,'Dias úteis'!$D$8:$H$19,5,FALSE) -> 0 | K42: =K30/VLOOKUP(K$34,'Dias úteis'!$D$8:$H$19,5,FALSE) -> 41.066706 | L42: =L30/VLOOKUP(L$34,'Dias úteis'!$D$8:$H$19,5,FALSE) -> 37.495688 | ... P42: =P30/VLOOKUP(P$34,'Dias úteis'!$D$8:$H$19,5,FALSE) -> 42.973125

Sheet Dias úteis
A1: PRODIET
A2: Anexo VI - Dias úteis
A3: INOVAÇÃO TECNOLÓGICA 2016
A6: Feriados em Curitiba | E6: Total de dias e horas úteis por mês
A7: Data | B7: Feriado | E7: Dt. Inicial | F7: Dt. Final | G7: Dias úteis | H7: Horas úteis
A8: 42370 | B8: Ano Novo | D8: Jan | E8: 42370 | F8: 42400 | G8: =NETWORKDAYS(E8,F8,$A$8:$A$19) -> 20 | H8: =44/5*G8 -> 176
A9: 42463 | B9: Páscoa | D9: Fev | E9: 42401 | F9: 42428 | G9: =NETWORKDAYS(E9,F9,$A$8:$A$19) -> 20 | H9: =44/5*G9 -> 176
A10: 42481 | B10: Tiradentes | D10: Mar | E10: 42430 | F10: 42460 | G10: =NETWORKDAYS(E10,F10,$A$8:$A$19) -> 23 | H10: =44/5*G10 -> 202.4
A11: 42491 | B11: Dia do Trabalho | D11: Abr | E11: 42461 | F11: 42490 | G11: =NETWORKDAYS(E11,F11,$A$8:$A$19) -> 20 | H11: =44/5*G11 -> 176
A12: 42525 | B12: Corpus Christi | D12: Mai | E12: 42491 | F12: 42521 | G12: =NETWORKDAYS(E12,F12,$A$8:$A$19) -> 22 | H12: =44/5*G12 -> 193.6
A13: 42620 | B13: Independência | D13: Jun | E13: 42522 | F13: 42551 | G13: =NETWORKDAYS(E13,F13,$A$8:$A$19) -> 22 | H13: =44/5*G13 -> 193.6
A14: 42621 | B14: Padroeira de Curitiba | D14: Jul | E14: 42552 | F14: 42582 | G14: =NETWORKDAYS(E14,F14,$A$8:$A$19) -> 21 | H14: =44/5*G14 -> 184.8
A15: 42655 | B15: N.S.Aparecida | D15: Ago | E15: 42583 | F15: 42613 | G15: =NETWORKDAYS(E15,F15,$A$8:$A$19) -> 23 | H15: =44/5*G15 -> 202.4
A16: 42676 | B16: Finados | D16: Set | E16: 42614 | F16: 42643 | G16: =NETWORKDAYS(E16,F16,$A$8:$A$19) -> 20 | H16: =44/5*G16 -> 176
A17: 42728 | B17: Natal | D17: Out | E17: 42644 | F17: 42674 | G17: =NETWORKDAYS(E17,F17,$A$8:$A$19) -> 20 | H17: =44/5*G17 -> 176
A18: 42729 | B18: Natal | D18: Nov | E18: 42675 | F18: 42704 | G18: =NETWORKDAYS(E18,F18,$A$8:$A$19) -> 21 | H18: =44/5*G18 -> 184.8
A19: 42735 | B19: Ano novo | D19: Dez | E19: 42705 | F19: 42735 | G19: =NETWORKDAYS(E19,F19,$A$8:$A$19) -> 22 | H19: =44/5*G19 -> 193.6
G20: =SUM(G8:G19) -> 254 | H20: =SUM(H8:H19) -> 2235.2

Sheet Salários (bruto)
A1: FUNCIONÁRIO | B1: AMID | C1: FRANCIELLE | D1: HELLIN | E1: HOZANA | F1: JANA | G1: LIZIANE | H1: MARIANNE | I1: MAURÍCIO | J1: ANA PAULA CELES | K1: LUCIANA DUTRA
A2: 42370 | B2: 1992 | C2: 3389 | D2: 3959 | E2: - | F2: 3289 | G2: 3289 | H2: - | I2: - | J2: 34520.71 | K2: 13766
A3: 42401 | B3: 2213 | C3: 3389 | D3: 3959 | E3: - | F3: 3289 | G3: 3289 | H3: - | I3: - | J3: 34520.71 | K3: 13766
A4: 42430 | B4: 2213 | C4: 3389 | D4: 3959 | E4: - | F4: 3289 | G4: 3289 | H4: - | I4: - | J4: 28557 | K4: 11960.11
A5: 42461 | B5: 2213 | C5: 3389 | D5: 4020 | E5: - | F5: 3289 | G5: 3289 | H5: - | I5: - | J5: 28557 | K5: 11960.11
A6: 42491 | B6: 2213 | C6: 3389 | D6: 4020 | E6: - | F6: - | G6: 3289 | H6: - | I6: - | J6: 28557 | K6: 11960.11
A7: 42522 | B7: 2213 | C7: 3389 | D7: 4696 | E7: 1992 | F7: - | G7: 3289 | H7: - | I7: - | J7: 28557 | K7: 11960.11
A8: 42552 | B8: 2213 | C8: 3389 | D8: 4696 | E8: 1992 | F8: - | G8: 3289 | H8: 3471 | I8: 4696 | J8: 28557 | K8: 11960.11
A9: 42583 | B9: 2213 | C9: 3389 | D9: 4696 | E9: 1992 | F9: - | G9: - | H9: 3471 | I9: 4696 | J9: 28557 | K9: 11960.11
A10: 42614 | B10: 2668 | C10: 3389 | D10: 5148 | E10: 2184 | F10: - | G10: - | H10: 3805 | I10: 5148 | J10: 28557 | K10: 11960.11
A11: 42644 | B11: 2668 | C11: - | D11: 5148 | E11: 2184 | F11: - | G11: - | H11: 3805 | I11: 5148 | J11: 28557 | K11: 11960.11
A12: 42675 | B12: 2668 | C12: - | D12: 5148 | E12: 2184 | F12: - | G12: - | H12: 3805 | I12: 5148 | J12: 28557 | K12: 11960.11
A13: 42705 | B13: 2668 | C13: - | D13: 5148 | E13: 2184 | F13: - | G13: - | H13: 3805 | I13: 5148 | J13: 28557 | K13: 11960.11

Sheet Informações RH
A1: Nome | B1: CPF | C1: Dedicação | D1: Escolaridade 2016 | E1: Curso
A2: Amid Tony Ibrahim | B2: 075.215.579-21 | C2: Exclusiva | D2: Superior Completo | E2: Eng. De Bioprocessos e Biotecnologia
A3: Franciele Guedes | B3: 065.423.719-07 | C3: Parcial | D3: Superior Completo | E3: Eng. De Produção
A4: Hellin dos Santos | B4: 058.544.839-63 | C4: Exclusiva | D4: Superior Completo | E4: Nutricionista
A5: Hozana Bueno | B5: 039.677.159-90 | C5: Parcial | D5: Técnico | E5: Técnico Qualidade
A6: Jana Grenteski | B6: 040.201.929-60 | C6: Exclusiva | D6: Superior Completo / Doutorado em Andamento | E6: Nutricionista
A7: Lizianne Shmeil | B7: 052.485.199-93 | C7: Parcial | D7: Pós graduada | E7: Graduada em Eng. Alimentos e Medicina Veterinária
A8: Marianne Stigar | B8: 066.424.199-95 | C8: Parcial | D8: Pós graduada | E8: Graduada em Processos Químicos e MBA em Eng. Produção e qualidade
A9: Mauricio Ragadalli | B9: 060.236.389-61 | C9: Parcial | D9: Superior Completo | E9: Eng produção

Sheet CNPJ NPs
A1: Associação Paranaense de Cultura - APC | B1: 76.659.820/0003-13 | C1: Teste de bancada na PUC-PR
A2: Bioagri Analises de alimentos Ltda | B2: 00.000.410/0001-32 | C2: Análise de ácidos graxos
A3: Callfarma | B3: 08.011.373/0001-70 | C3: Compra de produtos concorrentes
A4: Clínica Médica Mourão Faccio S/S | B4: 04.404.467/0001-58 | C4: 1ª parcela do contrato de prestação de serviço estudo clínico Immax
A5: Comercial Brey Ltda | B5: 02.608.645/0001-37 | C5: Seladora de bancada - Leites terapêuticos
A6: Contabilista Papelaria e informática | B6: 77.765.840/0001-70 | C6: Materiais
A7: Covance - The Development Service Company | C7: Densidade volumétrica Trophic Junior
A8: Fundação de desenv. Da pesquisa do agronegócio - FUNDEPAG | B8: 50.276.237/0001-78 | C8: Análises físico-químicas Immax
A9: Fundação de estudos e pesquisas aquáticas - FUNDESPA | B9: 61.379.657/0001-04 | C9: Análises de shelf life
A10: Impressione Impressão Digital Ltda - ME | B10: 12.457.568/0001-15 | C10: Impressão de material gráfico Immax
A11: Labor Tres Laboratórios e Consultoria Técnica Ltda | B11: 02.021.076/0001-29 | C11: Análises físico-químicas e microbiológicas Vital Rice
A12: Laboratório Alac Ltda | B12: 94.088.952/0001-52 | C12: Análise de micronutrientes Immax
A13: Medicalcom Hospitalares Eireli - ME | B13: 21.059.832/0001-53 | C13: Balança de controle corporal - estudo clínico Immax
A14: Nutrihealth Comercio de Produtos Alimentícios Eireli ME | B14: 14.492.128/0001-89 | C14: Compra de produtos concorrentes
A15: Oraculum Inteligência em Nutrição e Saúde Ltda - ME | B15: 21.213.714/0001-58 | C15: Desenvolvimento de receitas Immax
A16: Sandra Marcia da Silva de Souza - ME | B16: 13.807.270/0001-50 | C16: Impressões gráficas Immax
A17: Valéria Paschoal Editora Produtos e Serviços Ltda EPP | B17: 06.635.677/0001-82 | C17: Compra de livros nutrição enteral

Sheet Receita líquida
A1: Cálculo da Receita Líquida
A2: Fonte: Apuração IR e CSLL 2016_12 Balancete 31/12/2016 (1)
A4: 3.1.1.1 | B4: Receitas de vendas | C4: 47593237
A5: 3.1.1.2 | B5: Receitas financeiras | C5: 1187857.8
A6: 3.1.1.3 | B6: Outras receitas | C6: 87735.41
B7: Total | C7: =SUM(C4:C6) -> 48868830
A8: 3.2 | B8: Deduções da receita | C8: 9810120.2
B9: Receita líquida | C9: =C7-C8 -> 39058710
